Workbook

Sheet  MIs
A2: S.No | B2: NAme | C2: Lacation | D2: Card Number | E2: Card Number | F2: Category | G2: 1st Jan | I2: 2nd Jan | J2: 3rd Jan | K2: 4th Jan | L2: 5th Jan | M2: 6th Jan | N2: 7th Jan | O2: 8th Jan | P2: 9th Jan | Q2: 10th Jan | R2: 11th Jan | S2: 12th Jan | T2: 13th Jan | U2: 14th Jan | V2: 15th Jan | W2: 16th Jan | X2: 17th Jan | Y2: 18th Jan | Z2: 19th Jan | AA2: 20th Jan | AB2: 21st Jan | AC2: 22nd Jan | AD2: 23rd Jan | AE2: 24th Jan | AF2: 25th Jan | AG2: 26th Jan | AH2: 27th Jan | AI2: 28th Jan | AJ2: 29th Jan | AK2: 30th Jan | AL2: 31st Jan | AM2: Total
F3: Diesel
A4: 1 | B4: Rambabu | C4: HO(Two Wheeler) | D4: FC3450563999 | E4: Diesel | F4: 0 | G4: 0 | H4: 0 | I4: 0 | J4: 0 | K4: 0 | L4: 0 | M4: 0 | N4: 0 | O4: 0 | P4: 0 | Q4: 0 | R4: 0 | S4: 0 | T4: 0 | U4: 0 | V4: 0 | W4: 0 | X4: 5.22 | Y4: 0 | Z4: 0 | AA4: 0 | AB4: 0 | AC4: 0 | AD4: 60 | AE4: 0 | AF4: 0 | AG4: 0 | AH4: 4.56 | AI4: 0 | AJ4: 0 | AK4: 0 | AL4: 0 | AM4: =SUM(F4:AL4) -> 69.78
E5: Petrol | F5: 0 | G5: 4.69 | H5: 0 | I5: 0 | J5: 0 | K5: 0 | L5: 0 | M5: 0 | N5: 3.91 | O5: 0 | P5: 6.98 | Q5: 0 | R5: 0 | S5: 0 | T5: 0 | U5: 0 | V5: 0 | W5: 0 | X5: 0 | Y5: 0 | Z5: 0 | AB5: 0 | AC5: 0 | AD5: 0 | AE5: 0 | AF5: 0 | AG5: 0 | AH5: 0 | AI5: 0 | AJ5: 0 | AK5: 0 | AL5: 0 | AM5: =SUM(F5:AL5) -> 15.58
A6: 2 | B6: Hanumanth Rao | C6: HO | D6: FC3450676131 | E6: Diesel | F6: 0 | G6: 0 | H6: 0 | I6: 0 | J6: 0 | K6: 0 | L6: 0 | M6: 0 | N6: 0 | O6: 0 | P6: 0 | Q6: 0 | R6: 0 | S6: 0 | T6: 0 | U6: 0 | V6: 0 | W6: 0 | X6: 0 | Y6: 0 | Z6: 0 | AA6: 0 | AB6: 0 | AC6: 0 | AD6: 0 | AE6: 0 | AF6: 0 | AG6: 0 | AH6: 0 | AI6: 0 | AJ6: 0 | AK6: 0 | AL6: 0 | AM6: =SUM(F6:AL6) -> 0
E7: Petrol | F7: 0 | G7: 0 | H7: 0 | I7: 0 | J7: 0 | K7: 0 | L7: 0 | M7: 0 | N7: 0 | O7: 0 | P7: 0 | Q7: 0 | R7: 0 | S7: 0 | T7: 0 | U7: 0 | V7: 0 | W7: 0 | X7: 0 | Y7: 0 | Z7: 0 | AB7: 0 | AC7: 0 | AD7: 0 | AE7: 0 | AF7: 0 | AG7: 0 | AH7: 0 | AI7: 0 | AJ7: 0 | AK7: 0 | AL7: 0 | AM7: =SUM(F7:AL7) -> 0
A8: 3 | B8: Radhakrishna | C8: HO | D8: FC8000207658 | E8: Diesel | F8: 0 | G8: 0 | H8: 0 | I8: 0 | J8: 33.44 | K8: 0 | L8: 0 | M8: 0 | N8: 0 | O8: 0 | P8: 0 | Q8: 0 | R8: 35.53 | S8: 0 | T8: 0 | U8: 0 | V8: 0 | W8: 0 | X8: 0 | Y8: 0 | Z8: 0 | AA8: 0 | AB8: 33.44 | AC8: 0 | AD8: 0 | AE8: 0 | AF8: 0 | AG8: 0 | AH8: 0 | AI8: 0 | AJ8: 0 | AK8: 0 | AL8: 0 | AM8: =SUM(F8:AL8) -> 102.41
E9: Petrol | F9: 0 | G9: 0 | H9: 0 | I9: 0 | J9: 0 | K9: 0 | L9: 0 | M9: 0 | N9: 0 | O9: 0 | P9: 0 | Q9: 0 | R9: 0 | S9: 0 | T9: 0 | U9: 0 | V9: 0 | W9: 0 | X9: 0 | Y9: 0 | Z9: 0 | AB9: 0 | AC9: 0 | AD9: 0 | AE9: 0 | AF9: 0 | AG9: 0 | AH9: 0 | AI9: 0 | AJ9: 0 | AK9: 0 | AL9: 0 | AM9: =SUM(F9:AL9) -> 0
A10: 4 | B10: VIjay | C10: HO | D10: FC3450698859 | E10: Diesel | F10: 0 | G10: 0 | H10: 0 | I10: 0 | J10: 0 | K10: 0 | L10: 0 | M10: 0 | N10: 0 | O10: 0 | P10: 49.22 | Q10: 0 | R10: 0 | S10: 0 | T10: 0 | U10: 54.57 | V10: 0 | W10: 0 | X10: 0 | Y10: 0 | Z10: 0 | AA10: 0 | AB10: 0 | AC10: 0 | AD10: 49.8 | AE10: 0 | AF10: 0 | AG10: 0 | AH10: 0 | AI10: 0 | AJ10: 0 | AK10: 0 | AL10: 0 | AM10: =SUM(F10:AL10) -> 153.59
E11: Petrol | F11: 0 | G11: 0 | H11: 0 | I11: 0 | J11: 0 | K11: 0 | L11: 0 | M11: 0 | N11: 0 | O11: 0 | P11: 0 | Q11: 0 | R11: 0 | S11: 0 | T11: 0 | U11: 0 | V11: 0 | W11: 0 | X11: 0 | Y11: 0 | Z11: 0 | AB11: 0 | AC11: 0 | AD11: 0 | AE11: 0 | AF11: 0 | AG11: 0 | AH11: 0 | AI11: 0 | AJ11: 0 | AK11: 0 | AL11: 0 | AM11: =SUM(F11:AL11) -> 0
A12: 5 | B12: Client | C12: Hiriyur | D12: FC3450698864 | E12: Diesel | F12: 0 | G12: 0 | H12: 0 | I12: 0 | J12: 0 | K12: 0 | L12: 0 | M12: 0 | N12: 86.29 | O12: 0 | P12: 0 | Q12: 0 | R12: 0 | S12: 0 | T12: 0 | U12: 0 | V12: 0 | W12: 0 | X12: 0 | Y12: 0 | Z12: 0 | AA12: 0 | AB12: 0 | AC12: 0 | AD12: 145.61 | AE12: 0 | AF12: 0 | AG12: 0 | AH12: 0 | AI12: 0 | AJ12: 0 | AK12: 0 | AL12: 0 | AM12: =SUM(F12:AL12) -> 231.9
E13: Petrol | F13: 0 | G13: 0 | H13: 0 | I13: 0 | J13: 0 | K13: 0 | L13: 0 | M13: 0 | N13: 0 | O13: 0 | P13: 0 | Q13: 0 | R13: 0 | S13: 0 | T13: 0 | U13: 0 | V13: 0 | W13: 0 | X13: 0 | Y13: 0 | Z13: 0 | AB13: 0 | AC13: 0 | AD13: 0 | AE13: 0 | AF13: 0 | AG13: 0 | AH13: 0 | AI13: 0 | AJ13: 0 | AK13: 0 | AL13: 0 | AM13: =SUM(F13:AL13) -> 0
A14: 6 | B14: Client | C14: Hosadurga | D14: FC3450698865 | E14: Diesel | F14: 0 | G14: 0 | H14: 0 | I14: 0 | J14: 0 | K14: 0 | L14: 40 | M14: 40 | N14: 0 | O14: 36 | P14: 35 | Q14: 0 | R14: 0 | S14: 0 | T14: 0 | U14: 0 | V14: 0 | W14: 45 | X14: 45 | Y14: 43.53 | Z14: 40 | AA14: 43 | AB14: 0 | AC14: 40 | AD14: 0 | AE14: 40 | AF14: 0 | AG14: 0 | AH14: 0 | AI14: 0 | AJ14: 0 | AK14: 0 | AL14: 0 | AM14: =SUM(F14:AL14) -> 447.53
E15: Petrol | F15: 0 | G15: 0 | H15: 0 | I15: 0 | J15: 0 | K15: 0 | L15: 0 | M15: 0 | N15: 0 | O15: 0 | P15: 0 | Q15: 0 | R15: 0 | S15: 0 | T15: 0 | U15: 0 | V15: 0 | W15: 0 | X15: 0 | Y15: 0 | Z15: 0 | AB15: 0 | AC15: 0 | AD15: 0 | AE15: 0 | AF15: 0 | AG15: 0 | AH15: 0 | AI15: 0 | AJ15: 0 | AK15: 0 | AL15: 0 | AM15: =SUM(F15:AL15) -> 0
G18: Diesel Price

Sheet June-2026
A1: S.no | B1: Site Name | C1: Bunk Name | D1: Diesel(Liters) | E1: Diesel Amount | F1: Petrol(Liters) | G1: Petrol Amount | H1: Total Amount | I1: Opening Blance | J1: Amount Paid | K1: Closing Balances
A2: 1 | B2: Khammam-1 | C2: Divya laxmi ganapathi | D2: =+'Khammam-1'!E38 -> 66765.22 | E2: =+'Khammam-1'!G38 -> 6930229.8 | F2: =+'Khammam-1'!H38 -> 450 | G2: =+'Khammam-1'!J38 -> 52060.5 | H2: =E2+G2 -> 6982290.3 | I2: =+'Khammam-1'!K3 -> 2654498.9 | J2: =+'Khammam-1'!L38 -> 8021364 | K2: =H2+I2-J2 -> 1615425.2
A3: 2 | B3: Khammam-2 | C3: Jayasai union bunk | D3: =+'Khammam-2'!E38 -> 127541.88 | E3: =+'Khammam-2'!G38 -> 13241398 | F3: =+'Khammam-2'!H38 -> 450 | G3: =+'Khammam-2'!J38 -> 52074 | H3: =E3+G3 -> 13293472 | I3: =+'Khammam-2'!K3 -> 8720097.6 | J3: =+'Khammam-2'!L38 -> 12423326 | K3: =H3+I3-J3 -> 9590244
A4: 3 | B4: Khammam-3 | C4: JSASFuel Genie India Pvt.Ltd | D4: =+'Khammam-3'!E35 -> 0 | E4: =+'Khammam-3'!G35 -> 0 | F4: =+'Khammam-3'!H35 -> 0 | G4: =+'Khammam-3'!J35 -> 0 | H4: =E4+G4 -> 0 | I4: =+'Khammam-3'!M3 -> 1572600 | J4: =+'Khammam-3'!L35 -> 500000 | K4: =H4+I4-J4 -> 1072600
A5: 4 | B5: Khammam-Cash&Carry | C5: NA | D5: =+' Khammam&Cash'!E46 -> 8670.5217 | E5: =+' Khammam&Cash'!G46 -> 900000.15 | F5: =+' Khammam&Cash'!H46 -> 0 | G5: =+' Khammam&Cash'!J46 -> 0 | H5: =E5+G5 -> 900000.15 | I5: =+' Khammam&Cash'!M3 -> 0 | J5: =+' Khammam&Cash'!L46 -> 900000.15 | K5: =H5+I5-J5 -> 0
A6: 5 | B6: Jadcherla-1 | C6: JSASFuel Genie India Pvt.Ltd | D6: =+'Jadcherla-3'!E35 -> 0 | E6: =+'Jadcherla-3'!G35 -> 0 | F6: =+'Jadcherla-3'!H35 -> 0 | G6: =+'Jadcherla-3'!J35 -> 0 | H6: =E6+G6 -> 0 | I6: =+'Jadcherla-3'!M3 -> 1313281.7 | J6: =+'Jadcherla-3'!L35 -> 1313281 | K6: =H6+I6-J6 -> 0.7
A7: 6 | B7: Jadcherla-2 | C7: Shree Poornima F/S | D7: =+'Jadcherla-4'!E35 -> 2500 | E7: =+'Jadcherla-4'!G35 -> 261050 | F7: =+'Jadcherla-4'!H35 -> 80 | G7: =+'Jadcherla-4'!J35 -> 9306.4 | H7: =E7+G7 -> 270356.4 | I7: =+'Jadcherla-4'!M3 -> 15788.08 | J7: =+'Jadcherla-4'!L35 -> 279281 | K7: =H7+I7-J7 -> 6863.48
A8: 7 | B8: Jadcherla-3 | C8: Sai Baba Filling Station | D8: =+' Jadcherla'!E35 -> 0 | E8: =+' Jadcherla'!G35 -> 0 | F8: =+' Jadcherla'!H35 -> 0 | G8: =+' Jadcherla'!J35 -> 0 | H8: =E8+G8 -> 0 | I8: =+' Jadcherla'!M3 -> 171115.11 | J8: =+' Jadcherla'!L35 -> 171115.11 | K8: =H8+I8-J8 -> 0.00040000002
A9: 8 | B9: Sangareddy-2 | C9: Durga Bhavani F/S | D9: =+' Sangareddy-2'!E35 -> 3018.9 | E9: =+' Sangareddy-2'!G35 -> 315656.18 | F9: =+' Sangareddy-2'!H35 -> 109 | G9: =+' Sangareddy-2'!J35 -> 12702.86 | H9: =E9+G9 -> 328359.04 | I9: =+' Sangareddy-2'!M3 -> 108316.17 | J9: =+' Sangareddy-2'!L35 -> 308316 | K9: =H9+I9-J9 -> 128359.22 | M9: VASUDEO NIVRUTTI
A10: 9 | B10: Sangareddy-3 | C10: Shiva Parvathi Filling Station | D10: =+' Sangareddy-3'!E36 -> 13566 | E10: =+' Sangareddy-3'!G36 -> 1415612.1 | F10: =+' Sangareddy-3'!H36 -> 49 | G10: =+' Sangareddy-3'!J36 -> 5882.07 | H10: =E10+G10 -> 1421494.2 | I10: =+' Sangareddy-3'!M3 -> 986125.39 | J10: =+' Sangareddy-3'!L36 -> 2200000 | K10: =H10+I10-J10 -> 207619.56
A11: 10 | B11: NarayanaKhed | C11: Sai Shiva Filling Station | D11: =Narayankhed!E35 -> 2085.65 | E11: =+Narayankhed!G35 -> 225041.64 | F11: =+Narayankhed!H35 -> 0 | G11: =+Narayankhed!J35 -> 0 | H11: =E11+G11 -> 225041.64 | I11: =+Narayankhed!M3 -> 0 | J11: =+Narayankhed!L35 -> 225041.64 | K11: =H11+I11-J11 -> 0
A12: 11 | B12: Dindi | C12: Akarapu Balakistamma Fillling | D12: =+Dindi!E35 -> 0 | E12: =+Dindi!G35 -> 0 | F12: =+Dindi!H35 -> 0 | G12: =+Dindi!J35 -> 0 | H12: =E12+G12 -> 0 | I12: =+Dindi!M3 -> 0 | J12: =+Dindi!L35 -> 0 | K12: =H12+I12-J12 -> 0 | M12: =PROPER(M9) -> Vasudeo Nivrutti
A13: 12 | B13: Madanapalli | C13: NA | D13: =+'Madana palli'!E37 -> 0 | E13: =+'Madana palli'!G37 -> 0 | F13: =+'Madana palli'!H37 -> 18.84 | G13: =+'Madana palli'!J37 -> 2099.6078 | H13: =E13+G13 -> 2099.6078 | I13: =+'Madana palli'!M3 -> 0 | J13: =+'Madana palli'!L37 -> 2099.6078 | K13: =H13+I13-J13 -> 0
A14: 13 | B14: Kakinada | C14: NA | D14: =+Amalapuram!E246 -> 8824.401 | E14: =+Amalapuram!G246 -> 926569.75 | F14: =+Amalapuram!H246 -> 371.17 | G14: =+Amalapuram!J246 -> 43828.7 | H14: =E14+G14 -> 970398.45 | I14: =+Amalapuram!M3 -> 0 | J14: =+Amalapuram!L246 -> 970398.45 | K14: =H14+I14-J14 -> 0
A15: 14 | B15: YG Gudda-2 | C15: Pankaja HP Fuel Center | D15: =+'YG Gudda'!E39 -> 9000 | E15: =+'YG Gudda'!G39 -> 892260 | F15: =+'YG Gudda'!H39 -> 280 | G15: =+'YG Gudda'!J39 -> 31147.2 | H15: =E15+G15 -> 923407.2 | I15: =+'YG Gudda'!M3 -> 189118.96 | J15: =+'YG Gudda'!L39 -> 829742 | K15: =H15+I15-J15 -> 282784.16
A16: 15 | B16: YG Gudda-2 | C16: One stop | D16: =+' YG Gudda-2'!E39 -> 4000 | E16: =+' YG Gudda-2'!G39 -> 396080 | F16: =+' YG Gudda-2'!H39 -> 105 | G16: =+' YG Gudda-2'!J39 -> 11667.6 | H16: =E16+G16 -> 407747.6 | I16: =+' YG Gudda-2'!M3 -> 0 | J16: =+' YG Gudda-2'!L39 -> 200000 | K16: =H16+I16-J16 -> 207747.6
A17: 16 | B17: Hosadurga-2 | C17: Shree Veeraprathap Fuel | D17: =+'Hosadurga -2'!E35 -> 3000 | E17: =+'Hosadurga -2'!G35 -> 298410 | F17: =+'Hosadurga -2'!H35 -> 140 | G17: =+'Hosadurga -2'!J35 -> 15600.2 | H17: =+'Hosadurga -2'!K35 -> 314010.2 | I17: =+'Hosadurga -2'!K3 -> 148201.19 | J17: =+'Hosadurga -2'!L35 -> 347927 | K17: =H17+I17-J17 -> 114284.39
A18: 17 | B18: Malebennuru(KUWSDB) | C18: Sri Ramanjuneya Service Station | D18: =+'Malebenur(KUWSDB)'!E37 -> 5400 | E18: =+'Malebenur(KUWSDB)'!G37 -> 539028 | F18: =+'Malebenur(KUWSDB)'!H37 -> 220 | G18: =+'Malebenur(KUWSDB)'!J37 -> 24580.6 | H18: =E18+G18 -> 563608.6 | I18: =+'Malebenur(KUWSDB)'!K3 -> 95753.51 | J18: =+'Malebenur(KUWSDB)'!L37 -> 527000 | K18: =H18+I18-J18 -> 132362.11
A19: 18 | B19: kadur | C19: Vishal Service Station | D19: =+Kadur!E35 -> 3000 | E19: =+Kadur!G35 -> 308880 | F19: =+Kadur!H35 -> 140 | G19: =+Kadur!J35 -> 16422 | H19: =E19+G19 -> 325302 | I19: =+Kadur!K3 -> 159888.9 | J19: =+Kadur!L35 -> 159889 | K19: =H19+I19-J19 -> 325301.9
A20: 19 | B20: Hiriyur(VJNL) | C20: Sri Balaji Agencies | D20: =+'Hiriyur(VJNL)'!E35 -> 3500 | E20: =+'Hiriyur(VJNL)'!G35 -> 349720 | F20: =+'Hiriyur(VJNL)'!H35 -> 175 | G20: =+'Hiriyur(VJNL)'!J35 -> 19572 | H20: =E20+G20 -> 369292 | I20: =+'Hiriyur(VJNL)'!K3 -> 182925.7 | J20: =+'Hiriyur(VJNL)'!L35 -> 332855 | K20: =H20+I20-J20 -> 219362.7
A21: 20 | B21: Chellakere(KUWSDB) | C21: Shivaganga Service Station | D21: =+'Chellakere -1'!E38 -> 4400.71 | E21: =+'Chellakere -1'!G38 -> 439538.91 | F21: =+'Chellakere -1'!H38 -> 245 | G21: =+'Chellakere -1'!J38 -> 27388.55 | H21: =E21+G21 -> 466927.46 | I21: =+'Chellakere -1'!K3 -> 71615.087 | J21: =+'Chellakere -1'!L38 -> 422486 | K21: =H21+I21-J21 -> 116056.55
A22: 21 | B22: Chellakere(KUWSDB)-09 | C22: Shivaganga Service Station | D22: =+' Chellakere-PKG-9'!E36 -> 942.57 | E22: =+' Chellakere-PKG-9'!G36 -> 94143.892 | F22: =+' Chellakere-PKG-9'!H36 -> 81.01 | G22: =+' Chellakere-PKG-9'!J36 -> 9056.0479 | H22: =E22+G22 -> 103199.94 | I22: =+' Chellakere-PKG-9'!M3 -> 0 | J22: =+' Chellakere-PKG-9'!L36 -> 103199.94 | K22: =H22+I22-J22 -> 0
A23: 22 | B23: Molakalmuru | C23: Sri Lakshmi Venkateshwara Filling Station | D23: =+Molakamuru!E35 -> 1040 | E23: =+Molakamuru!G35 -> 103864.8 | F23: =+Molakamuru!H35 -> 127 | G23: =+Molakamuru!J35 -> 14196.06 | H23: =E23+G23 -> 118060.86 | I23: =+Molakamuru!K3 -> 62820 | J23: =+Molakamuru!L35 -> 172000 | K23: =H23+I23-J23 -> 8880.86
A24: 23 | B24: Chennagiri | C24: NA | D24: =+' Chennagiri'!E35 -> 1920 | E24: =+' Chennagiri'!G35 -> 191424 | F24: =+' Chennagiri'!H35 -> 44 | G24: =+' Chennagiri'!J35 -> 4918.32 | H24: =E24+G24 -> 196342.32 | I24: =+' Chennagiri'!K3 -> 0 | J24: =+' Chennagiri'!L35 -> 196342.32 | K24: =H24+I24-J24 -> 0
A25: 24 | B25: Khanapur(PKG-3) | C25: V.V.Varde | D25: =+Khanapur!E35 -> 1216.09 | E25: =+Khanapur!G35 -> 120083.29 | F25: =+Khanapur!H35 -> 110 | G25: =+Khanapur!J35 -> 12193.8 | H25: =E25+G25 -> 132277.09 | I25: =+Khanapur!M3 -> 59025.654 | J25: =+Khanapur!L35 -> 86235 | K25: =H25+I25-J25 -> 105067.75
A26: 25 | B26: Munavalli(PKG-3) | C26: Shre Shiva Petroleum | D26: =+'Munavali-2'!E40 -> 1500 | E26: =+'Munavali-2'!G40 -> 149025 | F26: =+'Munavali-2'!H40 -> 0 | G26: =+'Munavali-2'!J40 -> 0 | H26: =E26+G26 -> 149025 | I26: =+'Munavali-2'!M3 -> 445001.62 | J26: =+'Munavali-2'!L40 -> 594027 | K26: =H26+I26-J26 -> -0.37954
A27: 26 | B27: Munavalli(PKG-3) | C27: Daneshwari Petroleum | D27: =+' Munavali'!E39 -> 14021.29 | E27: =+' Munavali'!G39 -> 1389930.5 | F27: =+' Munavali'!H39 -> 280 | G27: =+' Munavali'!J39 -> 31138.8 | H27: =E27+G27 -> 1421069.3 | I27: =+' Munavali'!M3 -> 277716.15 | J27: =+' Munavali'!L39 -> 1220350 | K27: =H27+I27-J27 -> 478435.42
A28: 27 | B28: Borgaon(PKG-3) | C28: Aadisagar Petrolium | D28: =+Borgaon!E35 -> 0 | E28: =+Borgaon!G35 -> 0 | F28: =+Borgaon!H35 -> 0 | G28: =+Borgaon!J35 -> 0 | H28: =E28+G28 -> 0 | I28: =+Borgaon!K3 -> 276126.39 | J28: =+Borgaon!L35 -> 275918 | K28: =H28+I28-J28 -> 208.3907
A29: 28 | B29: Ugar,Kudichi(PKG-3) | C29: Shiri Bhrhmanath Petrolium | D29: =+'Ugar,Khagwad,Kudichi'!E37 -> 9414.92 | E29: =+'Ugar,Khagwad,Kudichi'!G37 -> 939044.12 | F29: =+'Ugar,Khagwad,Kudichi'!H37 -> 125 | G29: =+'Ugar,Khagwad,Kudichi'!J37 -> 13982.5 | H29: =E29+G29 -> 953026.62 | I29: =+'Ugar,Khagwad,Kudichi'!M3 -> 476633.25 | J29: =+'Ugar,Khagwad,Kudichi'!L37 -> 900000 | K29: =H29+I29-J29 -> 529659.87
A30: 29 | B30: Shedbal | C30: Varad Petroluem | D30: =+shedbal!E35 -> 8870 | E30: =+shedbal!G35 -> 884605.1 | F30: =+shedbal!H35 -> 379 | G30: =+shedbal!J35 -> 42391.15 | H30: =E30+G30 -> 926996.25 | I30: =+shedbal!M3 -> 167956.75 | J30: =+shedbal!L35 -> 798000 | K30: =H30+I30-J30 -> 296953
A31: 30 | B31: Kabbur(PKG-3) | C31: Shri Jai Hanuman Petrolium | D31: =+Kabbur!E35 -> 105 | E31: =+Kabbur!G35 -> 10438.05 | F31: =+Kabbur!H35 -> 15.34 | G31: =+Kabbur!J35 -> 1710.5634 | H31: =E31+G31 -> 12148.613 | I31: 0 | J31: =+Kabbur!L35 -> 12148.613 | K31: =H31+I31-J31 -> 0
A32: 31 | B32: Kumta (PKG-1) | C32: V.M.Mirjankar (Kumta) Bharat | D32: =+kumta!E41 -> 1307.37 | E32: =+kumta!G41 -> 130439 | F32: =+kumta!H41 -> 86.37 | G32: =+kumta!J41 -> 9671.7126 | H32: =E32+G32 -> 140110.71 | I32: =kumta!M3 -> 71321.75 | J32: =+kumta!L41 -> 196373.96 | K32: =H32+I32-J32 -> 15058.507
A33: 32 | B33: Jalgaon-1 | C33: Jai Bajarang Sarvo Senter Bodwad | D33: =+' Jalgaon-1'!E55 -> 3000 | E33: =+' Jalgaon-1'!G55 -> 298530 | F33: =+' Jalgaon-1'!H55 -> 0 | G33: =+' Jalgaon-1'!J55 -> 0 | H33: =E33+G33 -> 298530 | I33: =+' Jalgaon-1'!K3 -> 0 | J33: =+' Jalgaon-1'!L55 -> 298530 | K33: =H33+I33-J33 -> 0
A34: 33 | B34: Jalgaon-2 | C34: Nayara | D34: =+'Jalgoan-2'!E56 -> 27863.47 | E34: ='Jalgoan-2'!G56 -> 2856284.3 | F34: =+'Jalgoan-2'!H56 -> 180 | G34: =+'Jalgoan-2'!J56 -> 21272.4 | H34: =E34+G34 -> 2877556.7 | I34: =+'Jalgoan-2'!M3 -> 2169469.7 | J34: =+'Jalgoan-2'!L56 -> 2500000 | K34: =H34+I34-J34 -> 2547026.4
A35: 34 | B35: Jalgaon-3 | C35: Vasudeo Nivrutti | D35: =+' Jalgaon-3'!E20 -> 7187.16 | E35: =+' Jalgaon-3'!G20 -> 714906.81 | F35: =+' Jalgaon-3'!H20 -> 0 | G35: =+' Jalgaon-3'!J20 -> 0 | H35: =E35+G35 -> 714906.81 | I35: =+' Jalgaon-3'!M3 -> 494713 | J35: =+' Jalgaon-3'!L20 -> 1209619.8 | K35: =H35+I35-J35 -> 0
A36: 35 | B36: Jalgaon-4 | C36: Raksha Auto Fuels | D36: =+'Jalgaon-4'!E19 -> 0 | E36: =+'Jalgaon-4'!G19 -> 0 | F36: =+'Jalgaon-4'!H19 -> 0 | G36: =+'Jalgaon-4'!J19 -> 0 | H36: =E36+G36 -> 0 | I36: =+'Jalgaon-4'!M3 -> 0 | J36: =+'Jalgaon-4'!L19 -> 0 | K36: =H36+I36-J36 -> 0
A37: 36 | B37: Jalgaon-5 C | C37: NA | D37: =+' Jalgaon-5 c'!E39 -> 10.11 | E37: =+' Jalgaon-5 c'!G39 -> 1000.3845 | F37: =+' Jalgaon-5 c'!H39 -> 0 | G37: =+' Jalgaon-5 c'!J39 -> 0 | H37: =E37+G37 -> 1000.3845 | I37: =+' Jalgaon-5 c'!M3 -> 0 | J37: =+' Jalgaon-5 c'!L39 -> 1000.3845 | K37: =H37+I37-J37 -> 0
A38: 37 | B38: MKBD | C38: Shree Sai Samarth Petroleum | D38: =+MKBD!E42 -> 9454.92 | E38: =+MKBD!G42 -> 938428.08 | F38: =+MKBD!H42 -> 100 | G38: =+MKBD!J42 -> 11227 | H38: =E38+G38 -> 949655.08 | I38: =+MKBD!K3 -> 3890914.7 | J38: =+MKBD!L42 -> 4208999 | K38: =H38+I38-J38 -> 631570.81
A39: 38 | B39: Haveri | C39: M/s Magavi City Fuels | D39: =' Haveri-2'!E42 -> 6428.27 | E39: =' Haveri-2'!G42 -> 638327.21 | F39: =' Haveri-2'!H42 -> 127.02 | G39: =' Haveri-2'!J42 -> 14246.372 | H39: =E39+G39 -> 652573.58 | I39: =' Haveri-2'!M3 -> 206223.97 | J39: =+' Haveri-2'!L42 -> 726000.1 | K39: =H39+I39-J39 -> 132797.45
A40: 39 | B40: Guttal-2 | C40: Himagiri Petroleum | D40: =+' Guttal-2'!E35 -> 4080 | E40: =+' Guttal-2'!G35 -> 406368 | F40: =+' Guttal-2'!H35 -> 177 | G40: =+' Guttal-2'!J35 -> 19772.67 | H40: =E40+G40 -> 426140.67 | I40: =+' Guttal-2'!M3 -> 105890.82 | J40: =+' Guttal-2'!L35 -> 440000 | K40: =H40+I40-J40 -> 92031.494
A41: 40 | B41: Rattihali-2 | C41: Shiva Oil Traders | D41: =+'Rattihali-2'!E37 -> 8294.61 | E41: =+'Rattihali-2'!G37 -> 826972.62 | F41: =+'Rattihali-2'!H37 -> 90.34 | G41: =+'Rattihali-2'!J37 -> 10101.819 | H41: =E41+G41 -> 837074.44 | I41: =+'Rattihali-2'!M3 -> 356005.72 | J41: =+'Rattihali-2'!L37 -> 800000 | K41: =H41+I41-J41 -> 393080.16
A42: 41 | B42: Gajendragada | C42: Vanasri Petrol Pump | D42: =+Gajendragada!E36 -> 920 | E42: =+Gajendragada!G36 -> 91668.8 | F42: =+Gajendragada!H36 -> 61 | G42: =+Gajendragada!J36 -> 6817.97 | H42: =E42+G42 -> 98486.77 | I42: =+Gajendragada!K3 -> 43458.638 | J42: =+Gajendragada!L36 -> 62000 | K42: =H42+I42-J42 -> 79945.408
A43: 42 | B43: Gokak(PKG-3) | C43: AJ Petrolinks | D43: =+'Gokak Dharwad PKG 3'!E42 -> 5295.44 | E43: =+'Gokak Dharwad PKG 3'!G42 -> 525784.24 | F43: =+'Gokak Dharwad PKG 3'!H42 -> 25 | G43: =+'Gokak Dharwad PKG 3'!J42 -> 2784.5 | H43: =E43+G43 -> 528568.74 | I43: =+'Gokak Dharwad PKG 3'!K3 -> 236297.72 | J43: =+'Gokak Dharwad PKG 3'!L42 -> 620000 | K43: =H43+I43-J43 -> 144866.46
A44: 43 | B44: Hukkere | C44: TR Assocites | D44: =+' TR Associates'!E34 -> 7642.14 | E44: =+' TR Associates'!G34 -> 757565.34 | F44: =+' TR Associates'!H34 -> 15 | G44: =+' TR Associates'!J34 -> 1668.15 | H44: =E44+G44 -> 759233.49 | I44: =+' TR Associates'!M3 -> 790926.4 | J44: =+' TR Associates'!L34 -> 1250000 | K44: =H44+I44-J44 -> 300159.89
A45: 44 | B45: Ankaligi | C45: Shivaganga | D45: =+Ankalgi!E35 -> 2282.7 | E45: =+Ankalgi!G35 -> 226284.05 | F45: =+Ankalgi!H35 -> 80 | G45: =+Ankalgi!J35 -> 8896.8 | H45: =E45+G45 -> 235180.85 | I45: =+Ankalgi!M3 -> 227226.53 | J45: =+Ankalgi!L35 -> 227000 | K45: =H45+I45-J45 -> 235407.38
A46: 45 | B46: Ghattaprabha | C46: Shri Deshpande | D46: =+'SHRI DESHPANDE'!E35 -> 8051.31 | E46: =+'SHRI DESHPANDE'!G35 -> 800058.67 | F46: =+'SHRI DESHPANDE'!H35 -> 355 | G46: =+'SHRI DESHPANDE'!J35 -> 39568.3 | H46: =E46+G46 -> 839626.97 | I46: =+'SHRI DESHPANDE'!M3 -> 384179.45 | J46: =+'SHRI DESHPANDE'!L35 -> 930000 | K46: =H46+I46-J46 -> 293806.43
A47: 46 | B47: ShankeshWAR | C47: SR Patil | D47: =+' Shankeshwar'!E35 -> 345 | E47: =+' Shankeshwar'!G35 -> 34196.4 | F47: =+' Shankeshwar'!H35 -> 20 | G47: =+' Shankeshwar'!J35 -> 2224 | H47: =E47+G47 -> 36420.4 | I47: =' Shankeshwar'!M3 -> 0 | J47: =+' Shankeshwar'!L35 -> 36420.4 | K47: =H47+I47-J47 -> 0
A48: 47 | B48: Talikote(PKG-1) | C48: Raykar Oil Agencies | D48: =+' Talikote'!E46 -> 393 | E48: =+' Talikote'!G46 -> 39088.454 | F48: =+' Talikote'!H46 -> 75.96 | G48: =+' Talikote'!J46 -> 8566.016 | H48: =E48+G48 -> 47654.47 | I48: =+' Talikote'!N3 -> 14774.411 | J48: =+' Talikote'!L46 -> 49500.393 | K48: =H48+I48-J48 -> 12928.489
A49: 48 | B49: Chadchan(PKG-1) | C49: Khavekar Petrolium | D49: =+Chadchan!E35 -> 1034.11 | E49: =+Chadchan!G35 -> 102500.98 | F49: =+Chadchan!H35 -> 111.53 | G49: =+Chadchan!J35 -> 12624.081 | H49: =E49+G49 -> 115125.06 | I49: =+Chadchan!K3 -> 16237.589 | J49: =+Chadchan!L35 -> 59000 | K49: =H49+I49-J49 -> 72362.652
A50: 49 | B50: Sindagi | C50: G.P.PORWAL | D50: =+Sindagi!E44 -> 240.01 | E50: =+Sindagi!G44 -> 23777.791 | F50: =+Sindagi!H44 -> 2 | G50: =+Sindagi!J44 -> 241.28 | H50: =E50+G50 -> 24019.071 | I50: =+Sindagi!M3 -> 12648.918 | J50: =+Sindagi!L44 -> 23000 | K50: =H50+I50-J50 -> 13667.989
A51: 50 | B51: Muddebihal(PKG-1)2 | C51: PS NAGATHAN PETROLIUM | D51: =+'Muddebhihal-2'!E50 -> 1559.43 | E51: =+'Muddebhihal-2'!G50 -> 154742.24 | F51: =+'Muddebhihal-2'!H50 -> 45 | G51: =+'Muddebhihal-2'!J50 -> 5056.55 | H51: =+'Muddebhihal-2'!K50 -> 159798.79 | I51: =+'Muddebhihal-2'!M3 -> 149809.72 | J51: =+'Muddebhihal-2'!L50 -> 150000 | K51: =+'Muddebhihal-2'!M49 -> 159608.51
A52: 51 | B52: Almela(PKG-1) | C52: Shiddeshwar Petroleums | D52: =+Alemela!E43 -> 930.47 | E52: =+Alemela!G43 -> 92377.062 | F52: =+Alemela!H43 -> 74.09 | G52: =+Alemela!J43 -> 8252.1442 | H52: =E52+G52 -> 100629.21 | I52: =+Alemela!M3 -> 65134 | J52: =+Alemela!L43 -> 96000 | K52: =H52+I52-J52 -> 69763.206
A53: 52 | B53: Nalatwad(PKG-1) | C53: Shri Pawad Basaweshwar Petroleums | D53: =+Nalatwad!E43 -> 40.23 | E53: =+Nalatwad!G43 -> 4000.4712 | F53: =+Nalatwad!H43 -> 17.81 | G53: =+Nalatwad!J43 -> 2052.9707 | H53: =E53+G53 -> 6053.4419 | I53: =+Nalatwad!M3 -> 110295.88 | J53: =+Nalatwad!L43 -> 100000 | K53: =H53+I53-J53 -> 16349.324
A54: 53 | B54: Srirangapatna | C54: Anupama F/S | D54: =+Srirangapatna!E35 -> 91.95 | E54: =+Srirangapatna!G35 -> 9045.1215 | F54: =+Srirangapatna!H35 -> 21.94 | G54: =+Srirangapatna!J35 -> 2398.7848 | H54: =E54+G54 -> 11443.906 | I54: 0 | J54: =+Srirangapatna!L35 -> 11443.906 | K54: =H54+I54-J54 -> 0
A55: 54 | B55: HO(DG) | C55: JSASFuel Genie India Pvt.Ltd | D55: =+'HO(DG)'!E46 -> 1440 | E55: =+'HO(DG)'!G46 -> 149530.4 | F55: =+'HO(DG)'!H46 -> 0 | G55: =+'HO(DG)'!J46 -> 0 | H55: =E55+G55 -> 149530.4 | I55: =+'HO(DG)'!M3 -> 99797.75 | J55: =+'HO(DG)'!L46 -> 66406.4 | K55: =H55+I55-J55 -> 182921.75
A56: Total | D56: =SUM(D2:D55) -> 402194.85 | E56: =SUM(E2:E55) -> 41143910 | F56: =SUM(F2:F55) -> 5659.42 | G56: =SUM(G2:G55) -> 641363.05 | H56: =SUM(H2:H55) -> 41785273 | I56: =SUM(I2:I55) -> 27599933 | J56: =SUM(J2:J55) -> 48553637 | K56: =H56+I56-J56 -> 20831569 | L56: 20751516 | M56: =L56-K56 -> -80053.248
A61: S.no | B61: Site Name | C61: Bunk Name | D61: Diesel(Liters) | E61: Diesel Amount | F61: Petrol(Liters) | G61: Petrol Amount | H61: Total Amount | I61: Opening Blance | J61: Amount Paid | K61: Closing Balances
A62: 39 | B62: {=VLOOKUP(A62,A1:K54,{2,3,4,5,6,7,8,9,10,11},FALSE)} -> Guttal-2 | C62: Himagiri Petroleum | D62: 4080 | E62: 406368 | F62: 177 | G62: 19772.67 | H62: 426140.67 | I62: 105890.82 | J62: 440000 | K62: 92031.494
B64: Site Name | C64: Bunk Name | D64: Diesel(Liters) | E64: Diesel Amount | F64: Petrol(Liters) | G64: Petrol Amount | H64: Total Amount | I64: Opening Blance | J64: Amount Paid | K64: Closing Balances
B65: Jalgaon-2 | C65: {=VLOOKUP(B65,B1:K54,{2,3,4,5,6,7,8,9,10},FALSE)} -> Nayara | D65: 27863.47 | E65: 2856284.3 | F65: 180 | G65: 21272.4 | H65: 2877556.7 | I65: 2169469.7 | J65: 2500000 | K65: 2547026.4
B72: 60000
B73: 18000
B74: 18000
B75: 75000
B76: 360000

Sheet HO(DG)
A1: JSASFuel Genie India Pvt.Ltd
A2: S.No | B2: Date | C2: GRN No | D2: Ind No/Bill No | E2: Diesel (Lts) | F2: Price | G2: Amount | H2: Petrol (Lts) | I2: Price | J2: Amount | K2: Total amount | L2: Amount paid | M2: As on date | N2: Remarks
A3: Opening Balance | K3: 99797.75 | M3: 99797.75 | O3: 2623243.4
A4: 1 | B4: 46174 | G4: =E4*F4 -> 0 | H4: 0 | I4: 0 | J4: =H4*I4 -> 0 | K4: =G4+J4 -> 0 | L4: 0 | M4: =M3+K4-L4 -> 99797.75
A5: 2 | B5: 46175 | G5: =E5*F5 -> 0 | K5: =G5+J5 -> 0 | M5: =M4+K5-L5 -> 99797.75 | R5: HO | S5: 188521.22
A6: 3 | B6: 46176 | E6: 35 | F6: 103.76 | G6: =E6*F6 -> 3631.6 | K6: =G6+J6 -> 3631.6 | L6: =H6+K6 -> 3631.6 | M6: =M5+K6-L6 -> 99797.75 | R6: Khammam | S6: 8227903
A7: 4 | B7: 46177 | E7: 200 | F7: 103.76 | G7: =E7*F7 -> 20752 | K7: =G7+J7 -> 20752 | M7: =M6+K7-L7 -> 120549.75 | R7: Jadcherla | S7: 2453209.4
A8: 5 | B8: 46178 | G8: =E8*F8 -> 0 | K8: =G8+J8 -> 0 | M8: =M7+K8-L8 -> 120549.75 | P8: 5679 | R8: Total | S8: =SUM(S5:S7) -> 10869634
A9: 6 | B9: 46179 | G9: =E9*F9 -> 0 | K9: =G9+J9 -> 0 | M9: =M8+K9-L9 -> 120549.75 | S9: 10869632
A10: 7 | B10: 46180 | G10: =E10*F10 -> 0 | K10: =G10+J10 -> 0 | L10: =H10+K10 -> 0 | M10: =M9+K10-L10 -> 120549.75 | N10: HPCL | S10: =S9-S8 -> -1.6105
B11: 46181 | G11: =E11*F11 -> 0 | K11: =G11+J11 -> 0 | L11: =H11+K11 -> 0 | M11: =M10+K11-L11 -> 120549.75 | N11: HPCL
A12: 8 | B12: 46182 | E12: 100 | F12: 103.76 | G12: =E12*F12 -> 10376 | K12: =G12+J12 -> 10376 | L12: =H12+K12 -> 10376 | M12: =M11+K12-L12 -> 120549.75 | N12: HPCL
A13: 9 | B13: 46183 | E13: 70 | F13: 103.76 | G13: =E13*F13 -> 7263.2 | K13: =G13+J13 -> 7263.2 | L13: =H13+K13 -> 7263.2 | M13: =M12+K13-L13 -> 120549.75 | Q13: 54.98
A14: 10 | B14: 46184 | E14: 70 | F14: 103.76 | G14: =E14*F14 -> 7263.2 | K14: =G14+J14 -> 7263.2 | L14: =H14+K14 -> 7263.2 | M14: =M13+K14-L14 -> 120549.75 | Q14: 54.98
A15: 11 | B15: 46185 | E15: 200 | F15: 104.2 | G15: =E15*F15 -> 20840 | K15: =G15+J15 -> 20840 | M15: =M14+K15-L15 -> 141389.75
A16: 12 | B16: 46186 | G16: =E16*F16 -> 0 | K16: =G16+J16 -> 0 | L16: =H16+K16 -> 0 | M16: =M15+K16-L16 -> 141389.75 | R16: 19166
A17: 13 | B17: 46187 | G17: =E17*F17 -> 0 | K17: =G17+J17 -> 0 | L17: =H17+K17 -> 0 | M17: =M16+K17-L17 -> 141389.75 | R17: 19645
A18: 14 | B18: 46188 | G18: =E18*F18 -> 0 | K18: =G18+J18 -> 0 | L18: =H18+K18 -> 0 | M18: =M17+K18-L18 -> 141389.75 | P18: 1905988 | Q18: =P18-M18 -> 1764598.2 | R18: 21083
A19: 15 | B19: 46189 | G19: =E19*F19 -> 0 | K19: =G19+J19 -> 0 | L19: =H19+K19 -> 0 | M19: =M18+K19-L19 -> 141389.75 | R19: 19140 | S19: 220637
A20: 16 | B20: 46190 | E20: 70 | F20: 103.76 | G20: =E20*F20 -> 7263.2 | K20: =G20+J20 -> 7263.2 | L20: =H20+K20 -> 7263.2 | M20: =M19+K20-L20 -> 141389.75 | N20: HPCL | R20: =SUM(R16:R19) -> 79034 | S20: =S19+R20 -> 299671
A21: 17 | B21: 46191 | E21: 35 | F21: 103.76 | G21: =E21*F21 -> 3631.6 | K21: =G21+J21 -> 3631.6 | L21: =H21+K21 -> 3631.6 | M21: =M20+K21-L21 -> 141389.75 | N21: HPCL
A22: 18 | B22: 46192 | E22: 70 | F22: 103.76 | G22: =E22*F22 -> 7263.2 | K22: =G22+J22 -> 7263.2 | L22: =H22+K22 -> 7263.2 | M22: =M21+K22-L22 -> 141389.75
A23: 19 | B23: 46193 | E23: 35 | F23: 103.76 | G23: =E23*F23 -> 3631.6 | K23: =G23+J23 -> 3631.6 | L23: =H23+K23 -> 3631.6 | M23: =M22+K23-L23 -> 141389.75
A24: 20 | B24: 46194 | G24: =E24*F24 -> 0 | K24: =G24+J24 -> 0 | L24: =H24+K24 -> 0 | M24: =M23+K24-L24 -> 141389.75
A25: 21 | B25: 46195 | E25: 70 | F25: 103.76 | G25: =E25*F25 -> 7263.2 | K25: =G25+J25 -> 7263.2 | L25: =H25+K25 -> 7263.2 | M25: =M24+K25-L25 -> 141389.75
A26: 22 | B26: 46196 | E26: 50 | F26: 103.76 | G26: =E26*F26 -> 5188 | K26: =G26+J26 -> 5188 | L26: =H26+K26 -> 5188 | M26: =M25+K26-L26 -> 141389.75
A27: 23 | B27: 46197 | E27: 200 | F27: 103.83 | G27: =E27*F27 -> 20766 | K27: =G27+J27 -> 20766 | L27: 0 | M27: =M26+K27-L27 -> 162155.75
A28: 24 | B28: 46198 | G28: =E28*F28 -> 0 | K28: =G28+J28 -> 0 | L28: =H28+K28 -> 0 | M28: =M27+K28-L28 -> 162155.75
A29: 25 | B29: 46199 | G29: =E29*F29 -> 0 | K29: =G29+J29 -> 0 | L29: =H29+K29 -> 0 | M29: =M28+K29-L29 -> 162155.75
A30: 26 | B30: 46200 | G30: =E30*F30 -> 0 | K30: =G30+J30 -> 0 | L30: =H30+K30 -> 0 | M30: =M29+K30-L30 -> 162155.75
A31: 27 | B31: 46201 | G31: =E31*F31 -> 0 | K31: =G31+J31 -> 0 | L31: =H31+K31 -> 0 | M31: =M30+K31-L31 -> 162155.75
A32: 28 | B32: 46202 | E32: 200 | F32: 103.83 | G32: =E32*F32 -> 20766 | K32: =G32+J32 -> 20766 | L32: 0 | M32: =M31+K32-L32 -> 182921.75
B33: 46202 | E33: 35 | F33: 103.76 | G33: =E33*F33 -> 3631.6 | K33: =G33+J33 -> 3631.6 | L33: 3631.6 | M33: =M32+K33-L33 -> 182921.75
A34: 29 | B34: 46203 | G34: =E34*F34 -> 0 | K34: =G34+J34 -> 0 | L34: =H34+K34 -> 0 | M34: =M33+K34-L34 -> 182921.75
G35: =E35*F35 -> 0 | K35: =G35+J35 -> 0 | M35: =M34+K35-L35 -> 182921.75
A36: 30 | K36: =G36+J36 -> 0 | M36: =M35+K36-L36 -> 182921.75
A37: 31 | M37: =M36+K37-L37 -> 182921.75
A38: 32 | M38: =M37+K38-L38 -> 182921.75
A39: 33 | M39: =M38+K39-L39 -> 182921.75
A40: 34 | M40: =M39+K40-L40 -> 182921.75
A41: 35
A42: 36
A43: 37
A44: 38 | O44: 2669494 | P44: =O44-M44 -> 2669494
E45: 0 | F45: 0 | G45: =E45*F45 -> 0 | J45: =H45*I45 -> 0 | K45: =G45+J45 -> 0 | M45: =M44+K45-L45 -> 0
E46: =SUM(E4:E44) -> 1440 | G46: =SUM(G4:G44) -> 149530.4 | H46: =SUM(H4:H44) -> 0 | J46: =SUM(J4:J44) -> 0 | K46: =SUM(K4:K44) -> 149530.4 | L46: =SUM(L4:L44) -> 66406.4
M55: 2408309
M56: 5327.86
M57: =M55-M56 -> 2402981.1

Sheet Khammam-1
A1: Divya laxmi ganapathi
A2: S.No | B2: Date | C2: GRN No | D2: Ind No/Bill No | E2: Diesel (Lts) | F2: Price | G2: Amount | H2: Petrol (Lts) | I2: Price | J2: Amount | K2: Total amount | L2: Amount paid | M2: As 0n Date | N2: Remarks
A3: Opening Balance | K3: 2654498.9 | M3: 2654498.9
A4: 1 | B4: 46174 | E4: 5500 | F4: 103.8 | G4: =E4*F4 -> 570900 | K4: =G4+J4 -> 570900 | L4: 200000 | M4: =M3+K4-L4 -> 3025398.9
A5: 2 | B5: 46175 | G5: =E5*F5 -> 0 | K5: =G5+J5 -> 0 | L5: 100000 | M5: =M4+K5-L5 -> 2925398.9
A6: 3 | B6: 46176 | E6: 2700 | F6: 103.8 | G6: =E6*F6 -> 280260 | J6: =H6*I6 -> 0 | K6: =G6+J6 -> 280260 | M6: =M5+K6-L6 -> 3205658.9
A7: 4 | B7: 46177 | E7: 2800 | F7: 103.8 | G7: =E7*F7 -> 290640 | J7: =H7*I7 -> 0 | K7: =G7+J7 -> 290640 | M7: =M6+K7-L7 -> 3496298.9
A8: 5 | B8: 46178 | G8: =E8*F8 -> 0 | J8: =H8*I8 -> 0 | K8: =G8+J8 -> 0 | M8: =M7+K8-L8 -> 3496298.9
A9: 6 | B9: 46179 | G9: =E9*F9 -> 0 | J9: =H9*I9 -> 0 | K9: =G9+J9 -> 0 | M9: =M8+K9-L9 -> 3496298.9
A10: 7 | B10: 46180 | E10: 2650 | F10: 103.8 | G10: =E10*F10 -> 275070 | J10: =H10*I10 -> 0 | K10: =G10+J10 -> 275070 | M10: =M9+K10-L10 -> 3771368.9
A11: 8 | B11: 46181 | E11: 2800 | F11: 103.8 | G11: =E11*F11 -> 290640 | J11: =H11*I11 -> 0 | K11: =G11+J11 -> 290640 | L11: 3771364 | M11: =M10+K11-L11 -> 290644.86
A12: 9 | B12: 46182 | E12: 2700 | F12: 103.8 | G12: =E12*F12 -> 280260 | J12: =H12*I12 -> 0 | K12: =G12+J12 -> 280260 | M12: =M11+K12-L12 -> 570904.86
A13: 10 | B13: 46183 | E13: 5700 | F13: 103.8 | G13: =E13*F13 -> 591660 | H13: 60 | I13: 115.69 | J13: =H13*I13 -> 6941.4 | K13: =G13+J13 -> 598601.4 | M13: =M12+K13-L13 -> 1169506.3
A14: 11 | B14: 46184 | E14: 2800 | F14: 103.8 | G14: =E14*F14 -> 290640 | J14: =H14*I14 -> 0 | K14: =G14+J14 -> 290640 | M14: =M13+K14-L14 -> 1460146.3
A15: 12 | B15: 46185 | E15: 2000 | F15: 103.8 | G15: =E15*F15 -> 207600 | J15: =H15*I15 -> 0 | K15: =G15+J15 -> 207600 | M15: =M14+K15-L15 -> 1667746.3
A16: 13 | B16: 46186 | E16: 2800 | F16: 103.8 | G16: =E16*F16 -> 290640 | J16: =H16*I16 -> 0 | K16: =G16+J16 -> 290640 | M16: =M15+K16-L16 -> 1958386.3
A17: 14 | B17: 46187 | E17: 2700 | F17: 103.8 | G17: =E17*F17 -> 280260 | J17: =H17*I17 -> 0 | K17: =G17+J17 -> 280260 | M17: =M16+K17-L17 -> 2238646.3
A18: 15 | B18: 46188 | E18: 2000 | F18: 103.8 | G18: =E18*F18 -> 207600 | J18: =H18*I18 -> 0 | K18: =G18+J18 -> 207600 | M18: =M17+K18-L18 -> 2446246.3
A19: 16 | B19: 46189 | E19: 3715.22 | F19: 103.8 | G19: =E19*F19 -> 385639.84 | H19: 60 | I19: 115.69 | J19: =H19*I19 -> 6941.4 | K19: =G19+J19 -> 392581.24 | M19: =M18+K19-L19 -> 2838827.5
A20: 17 | B20: 46190 | E20: 1500 | F20: 103.8 | G20: =E20*F20 -> 155700 | J20: =H20*I20 -> 0 | K20: =G20+J20 -> 155700 | M20: =M19+K20-L20 -> 2994527.5
A21: 18 | B21: 46191 | G21: =E21*F21 -> 0 | J21: =H21*I21 -> 0 | K21: =G21+J21 -> 0 | M21: =M20+K21-L21 -> 2994527.5
A22: 19 | B22: 46192 | G22: =E22*F22 -> 0 | J22: =H22*I22 -> 0 | K22: =G22+J22 -> 0 | M22: =M21+K22-L22 -> 2994527.5
A23: 20 | B23: 46193 | E23: 2000 | F23: 103.8 | G23: =E23*F23 -> 207600 | H23: 35 | I23: 115.69 | J23: =H23*I23 -> 4049.15 | K23: =G23+J23 -> 211649.15 | M23: =M22+K23-L23 -> 3206176.6
A24: 21 | B24: 46194 | G24: =E24*F24 -> 0 | J24: =H24*I24 -> 0 | K24: =G24+J24 -> 0 | M24: =M23+K24-L24 -> 3206176.6
A25: 22 | B25: 46195 | E25: 2500 | F25: 103.8 | G25: =E25*F25 -> 259500 | H25: 40 | I25: 115.69 | J25: =H25*I25 -> 4627.6 | K25: =G25+J25 -> 264127.6 | M25: =M24+K25-L25 -> 3470304.2
A26: 23 | B26: 46196 | G26: =E26*F26 -> 0 | J26: =H26*I26 -> 0 | K26: =G26+J26 -> 0 | M26: =M25+K26-L26 -> 3470304.2
A27: 24 | B27: 46197 | E27: 5500 | F27: 103.8 | G27: =E27*F27 -> 570900 | H27: 60 | I27: 115.69 | J27: =H27*I27 -> 6941.4 | K27: =G27+J27 -> 577841.4 | L27: 550000 | M27: =M26+K27-L27 -> 3498145.6
A28: 25 | B28: 46198 | E28: 4200 | F28: 103.8 | G28: =E28*F28 -> 435960 | H28: 55 | I28: 115.69 | J28: =H28*I28 -> 6362.95 | K28: =G28+J28 -> 442322.95 | L28: 400000 | M28: =M27+K28-L28 -> 3540468.6
A29: 26 | B29: 46199 | E29: 2800 | F29: 103.8 | G29: =E29*F29 -> 290640 | H29: 60 | I29: 115.69 | J29: =H29*I29 -> 6941.4 | K29: =G29+J29 -> 297581.4 | L29: 400000 | M29: =M28+K29-L29 -> 3438050
A30: 27 | B30: 46200 | G30: =E30*F30 -> 0 | J30: =H30*I30 -> 0 | K30: =G30+J30 -> 0 | M30: =M29+K30-L30 -> 3438050
A31: 28 | B31: 46201 | E31: 0 | F31: 103.8 | G31: =E31*F31 -> 0 | H31: 0 | I31: 115.69 | J31: =H31*I31 -> 0 | K31: =G31+J31 -> 0 | L31: 2000000 | M31: =M30+K31-L31 -> 1438050
A32: 29 | B32: 46202 | E32: 2700 | F32: 103.8 | G32: =E32*F32 -> 280260 | H32: 40 | I32: 115.69 | J32: =H32*I32 -> 4627.6 | K32: =G32+J32 -> 284887.6 | L32: 600000 | M32: =M31+K32-L32 -> 1122937.6
A33: 30 | B33: 46203 | E33: 4700 | F33: 103.8 | G33: =E33*F33 -> 487860 | H33: 40 | I33: 115.69 | J33: =H33*I33 -> 4627.6 | K33: =G33+J33 -> 492487.6 | M33: =M32+K33-L33 -> 1615425.2
A34: 31 | G34: =E34*F34 -> 0 | K34: =G34+J34 -> 0 | M34: =M33+K34-L34 -> 1615425.2
A35: 32 | G35: =E35*F35 -> 0 | J35: =H35*I35 -> 0 | K35: =G35+J35 -> 0 | M35: =M34+K35-L35 -> 1615425.2
A36: 33 | G36: =E36*F36 -> 0 | J36: =H36*I36 -> 0 | K36: =G36+J36 -> 0 | L36: 0
A37: 34 | G37: =E37*F37 -> 0 | J37: =H37*I37 -> 0 | K37: =G37+J37 -> 0
E38: =SUM(E3:E37) -> 66765.22 | G38: =SUM(G3:G37) -> 6930229.8 | H38: =SUM(H3:H37) -> 450 | J38: =SUM(J3:J37) -> 52060.5 | K38: =SUM(K4:K37) -> 6982290.3 | L38: =SUM(L3:L37) -> 8021364
N45: 4766880.2
N46: 6982290.3

Sheet Khammam-2
A1: Jayasai union bunk
A2: S.No | B2: Date | C2: GRN No | D2: Ind No/Bill No | E2: Diesel (Lts) | F2: Price | G2: Amount | H2: Petrol (Lts) | I2: Price | J2: Amount | K2: Total amount | L2: Amount paid | M2: As 0n Date | N2: Remarks
A3: Opening Balance | K3: 8720097.6 | M3: 8720097.6
A4: 1 | B4: 46174 | E4: 1581.71 | F4: 103.82 | G4: =E4*F4 -> 164213.13 | H4: 60 | I4: 115.72 | J4: =H4*I4 -> 6943.2 | K4: =G4+J4 -> 171156.33 | M4: =M3+K4-L4 -> 8891253.9 | O4: =O3+M4-N4 -> 8891253.9
A5: 2 | B5: 46175 | E5: 1977.66 | F5: 103.82 | G5: =E5*F5 -> 205320.66 | J5: =H5*I5 -> 0 | K5: =G5+J5 -> 205320.66 | M5: =M4+K5-L5 -> 9096574.6
A6: 3 | B6: 46176 | E6: 2724.32 | F6: 103.82 | G6: =E6*F6 -> 282838.9 | J6: =H6*I6 -> 0 | K6: =G6+J6 -> 282838.9 | M6: =M5+K6-L6 -> 9379413.5
A7: 4 | B7: 46177 | E7: 1852.27 | F7: 103.82 | G7: =E7*F7 -> 192302.67 | H7: 100 | I7: 115.72 | J7: =H7*I7 -> 11572 | K7: =G7+J7 -> 203874.67 | M7: =M6+K7-L7 -> 9583288.1
A8: 5 | B8: 46178 | E8: 877.79 | F8: 103.82 | G8: =E8*F8 -> 91132.158 | J8: =H8*I8 -> 0 | K8: =G8+J8 -> 91132.158 | M8: =M7+K8-L8 -> 9674420.3 | O8: 12802499
A9: 6 | B9: 46179 | E9: 2397.47 | F9: 103.82 | G9: =E9*F9 -> 248905.34 | J9: =H9*I9 -> 0 | K9: =G9+J9 -> 248905.34 | M9: =M8+K9-L9 -> 9923325.6
A10: 7 | B10: 46180 | G10: =E10*F10 -> 0 | J10: =H10*I10 -> 0 | K10: =G10+J10 -> 0 | M10: =M9+K10-L10 -> 9923325.6
A11: 8 | B11: 46181 | E11: 233 | F11: 103.82 | G11: =E11*F11 -> 24190.06 | H11: 75 | I11: 115.72 | J11: =H11*I11 -> 8679 | K11: =G11+J11 -> 32869.06 | L11: 5000000 | M11: =M10+K11-L11 -> 4956194.7 | N11: BT
A12: 9 | B12: 46181 | G12: =E12*F12 -> 0 | J12: =H12*I12 -> 0 | K12: =G12+J12 -> 0 | L12: 6086287 | M12: =M11+K12-L12 -> -1130092.3 | N12: HPCL | O12: 6086287
B13: 46181 | L13: =-(1162961.45) -> -1162961.4 | M13: =M12+K13-L13 -> 32869.139 | N13: Dgm Personal cash
A14: 10 | B14: 46182 | E14: 1155.44 | F14: 103.82 | G14: =E14*F14 -> 119957.78 | J14: =H14*I14 -> 0 | K14: =G14+J14 -> 119957.78 | M14: =M13+K14-L14 -> 152826.92
A15: 11 | B15: 46183 | E15: 5565.26 | F15: 103.82 | G15: =E15*F15 -> 577785.29 | J15: =H15*I15 -> 0 | K15: =G15+J15 -> 577785.29 | M15: =M14+K15-L15 -> 730612.21 | S15: 5000000
A16: 12 | B16: 46184 | E16: 5661.33 | F16: 103.82 | G16: =E16*F16 -> 587759.28 | J16: =H16*I16 -> 0 | K16: =G16+J16 -> 587759.28 | M16: =M15+K16-L16 -> 1318371.5 | Q16: 6086287 | S16: 6086287
A17: 13 | B17: 46185 | E17: 6900 | F17: 103.82 | G17: =E17*F17 -> 716358 | H17: 60 | I17: 115.72 | J17: =H17*I17 -> 6943.2 | K17: =G17+J17 -> 723301.2 | M17: =M16+K17-L17 -> 2041672.7 | S17: =SUM(S15:S16) -> 11086287
A18: 14 | B18: 46186 | E18: 6450 | F18: 103.82 | G18: =E18*F18 -> 669639 | J18: =H18*I18 -> 0 | K18: =G18+J18 -> 669639 | M18: =M17+K18-L18 -> 2711311.7 | S18: 1162961.4
A19: 15 | B19: 46187 | E19: 2500 | F19: 103.82 | G19: =E19*F19 -> 259550 | J19: =H19*I19 -> 0 | K19: =G19+J19 -> 259550 | M19: =M18+K19-L19 -> 2970861.7 | S19: =S17-S18 -> 9923325.6
A20: 16 | B20: 46188 | E20: 3015 | F20: 103.82 | G20: =E20*F20 -> 313017.3 | H20: 75 | I20: 115.72 | J20: =H20*I20 -> 8679 | K20: =G20+J20 -> 321696.3 | M20: =M19+K20-L20 -> 3292558 | S20: 32869.06
A21: 17 | B21: 46189 | E21: 6197.2 | F21: 103.82 | G21: =E21*F21 -> 643393.3 | J21: =H21*I21 -> 0 | K21: =G21+J21 -> 643393.3 | M21: =M20+K21-L21 -> 3935951.3 | S21: =S19+S20 -> 9956194.6
A22: 18 | B22: 46190 | E22: 5103.43 | F22: 103.82 | G22: =E22*F22 -> 529838.1 | J22: =H22*I22 -> 0 | K22: =G22+J22 -> 529838.1 | M22: =M21+K22-L22 -> 4465789.4
A23: 19 | B23: 46191 | E23: 6081.9 | F23: 103.82 | G23: =E23*F23 -> 631422.86 | J23: =H23*I23 -> 0 | K23: =G23+J23 -> 631422.86 | M23: =M22+K23-L23 -> 5097212.3
A24: 20 | B24: 46192 | E24: 6041.95 | F24: 103.82 | G24: =E24*F24 -> 627275.25 | H24: 80 | I24: 115.72 | J24: =H24*I24 -> 9257.6 | K24: =G24+J24 -> 636532.85 | M24: =M23+K24-L24 -> 5733745.1
A25: 21 | B25: 46193 | E25: 6219.57 | F25: 103.82 | G25: =E25*F25 -> 645715.76 | J25: =H25*I25 -> 0 | K25: =G25+J25 -> 645715.76 | M25: =M24+K25-L25 -> 6379460.9
A26: 22 | B26: 46194 | E26: 6250.34 | F26: 103.82 | G26: =E26*F26 -> 648910.3 | J26: =H26*I26 -> 0 | K26: =G26+J26 -> 648910.3 | M26: =M25+K26-L26 -> 7028371.2
A27: 23 | B27: 46195 | E27: 5297.67 | F27: 103.82 | G27: =E27*F27 -> 550004.1 | J27: =H27*I27 -> 0 | K27: =G27+J27 -> 550004.1 | M27: =M26+K27-L27 -> 7578375.3
A28: 24 | B28: 46196 | E28: 5138.12 | F28: 103.82 | G28: =E28*F28 -> 533439.62 | J28: =H28*I28 -> 0 | K28: =G28+J28 -> 533439.62 | M28: =M27+K28-L28 -> 8111814.9
A29: 25 | B29: 46197 | E29: 5011.16 | F29: 103.82 | G29: =E29*F29 -> 520258.63 | J29: =H29*I29 -> 0 | K29: =G29+J29 -> 520258.63 | M29: =M28+K29-L29 -> 8632073.5
A30: 26 | B30: 46198 | E30: 3329.48 | F30: 103.82 | G30: =E30*F30 -> 345666.61 | J30: =H30*I30 -> 0 | K30: =G30+J30 -> 345666.61 | M30: =M29+K30-L30 -> 8977740.1
A31: 27 | B31: 46199 | E31: 6511.21 | F31: 103.82 | G31: =E31*F31 -> 675993.82 | J31: =H31*I31 -> 0 | K31: =G31+J31 -> 675993.82 | M31: =M30+K31-L31 -> 9653733.9
A32: 28 | B32: 46200 | E32: 5957.19 | F32: 103.82 | G32: =E32*F32 -> 618475.47 | J32: =H32*I32 -> 0 | K32: =G32+J32 -> 618475.47 | M32: =M31+K32-L32 -> 10272209
A33: 29 | B33: 46201 | E33: 5284.55 | F33: 103.82 | G33: =E33*F33 -> 548641.98 | J33: =H33*I33 -> 0 | K33: =G33+J33 -> 548641.98 | M33: =M32+K33-L33 -> 10820851
A34: 30 | B34: 46202 | E34: 6019.64 | F34: 103.82 | G34: =E34*F34 -> 624959.02 | J34: =H34*I34 -> 0 | K34: =G34+J34 -> 624959.02 | L34: 2500000 | M34: =M33+K34-L34 -> 8945810.4
A35: 31 | B35: 46203 | E35: 6207.22 | F35: 103.82 | G35: =E35*F35 -> 644433.58 | J35: =H35*I35 -> 0 | K35: =G35+J35 -> 644433.58 | M35: =M34+K35-L35 -> 9590244
A36: 32 | B36: 46204 | G36: =E36*F36 -> 0 | J36: =H36*I36 -> 0 | K36: =G36+J36 -> 0 | M36: =M35+K36-L36 -> 9590244
E38: =SUM(E4:E36) -> 127541.88 | G38: =SUM(G4:G36) -> 13241398 | H38: =SUM(H4:H36) -> 450 | J38: =SUM(J4:J36) -> 52074 | K38: =SUM(K4:K36) -> 13293472 | L38: =SUM(L4:L36) -> 12423326

Sheet Khammam-3
A1: JSASFuel Genie India Pvt.Ltd
A2: S.No | B2: Date | C2: GRN No | D2: Ind No/Bill No | E2: Diesel (Lts) | F2: Price | G2: Amount | H2: Petrol (Lts) | I2: Price | J2: Amount | K2: Total amount | L2: Amount paid | M2: As 0n Date | N2: Remarks
A3: Opening Balance | K3: 1572600 | M3: 1572600
A4: 1 | B4: 46174 | G4: =E4*F4 -> 0 | J4: =H4*I4 -> 0 | K4: =G4+J4 -> 0 | M4: =M3+K4-L4 -> 1572600
A5: 2 | B5: 46175 | G5: =E5*F5 -> 0 | J5: =H5*I5 -> 0 | K5: =G5+J5 -> 0 | M5: =M4+K5-L5 -> 1572600
A6: 3 | B6: 46176 | G6: =E6*F6 -> 0 | J6: =H6*I6 -> 0 | K6: =G6+J6 -> 0 | M6: =M5+K6-L6 -> 1572600
A7: 4 | B7: 46177 | G7: =E7*F7 -> 0 | J7: =H7*I7 -> 0 | K7: =G7+J7 -> 0 | M7: =M6+K7-L7 -> 1572600
A8: 5 | B8: 46178 | G8: =E8*F8 -> 0 | J8: =H8*I8 -> 0 | K8: =G8+J8 -> 0 | M8: =M7+K8-L8 -> 1572600
A9: 6 | B9: 46179 | G9: =E9*F9 -> 0 | J9: =H9*I9 -> 0 | K9: =G9+J9 -> 0 | M9: =M8+K9-L9 -> 1572600
A10: 7 | B10: 46180 | G10: =E10*F10 -> 0 | J10: =H10*I10 -> 0 | K10: =G10+J10 -> 0 | M10: =M9+K10-L10 -> 1572600
A11: 8 | B11: 46181 | G11: =E11*F11 -> 0 | J11: =H11*I11 -> 0 | K11: =G11+J11 -> 0 | M11: =M10+K11-L11 -> 1572600
A12: 9 | B12: 46182 | G12: =E12*F12 -> 0 | J12: =H12*I12 -> 0 | K12: =G12+J12 -> 0 | M12: =M11+K12-L12 -> 1572600
A13: 10 | B13: 46183 | G13: =E13*F13 -> 0 | J13: =H13*I13 -> 0 | K13: =G13+J13 -> 0 | M13: =M12+K13-L13 -> 1572600
A14: 11 | B14: 46184 | G14: =E14*F14 -> 0 | J14: =H14*I14 -> 0 | K14: =G14+J14 -> 0 | M14: =M13+K14-L14 -> 1572600
A15: 12 | B15: 46185 | G15: =E15*F15 -> 0 | J15: =H15*I15 -> 0 | K15: =G15+J15 -> 0 | M15: =M14+K15-L15 -> 1572600
... A28: 25 | B28: 46198 | G28: =E28*F28 -> 0 | J28: =H28*I28 -> 0 | K28: =G28+J28 -> 0 | M28: =M27+K28-L28 -> 1572600
A29: 26 | B29: 46199 | G29: =E29*F29 -> 0 | J29: =H29*I29 -> 0 | K29: =G29+J29 -> 0 | L29: 500000 | M29: =M28+K29-L29 -> 1072600
A30: 27 | B30: 46200 | G30: =E30*F30 -> 0 | J30: =H30*I30 -> 0 | K30: =G30+J30 -> 0 | M30: =M29+K30-L30 -> 1072600
A31: 28 | B31: 46201 | G31: =E31*F31 -> 0 | J31: =H31*I31 -> 0 | K31: =G31+J31 -> 0 | M31: =M30+K31-L31 -> 1072600
A32: 29 | B32: 46202 | G32: =E32*F32 -> 0 | J32: =H32*I32 -> 0 | K32: =G32+J32 -> 0 | M32: =M31+K32-L32 -> 1072600
A33: 30 | B33: 46203 | G33: =E33*F33 -> 0 | J33: =H33*I33 -> 0 | K33: =G33+J33 -> 0 | M33: =M32+K33-L33 -> 1072600
A34: 31 | G34: =E34*F34 -> 0 | J34: =H34*I34 -> 0 | K34: =G34+J34 -> 0 | M34: =M33+K34-L34 -> 1072600
E35: =SUM(E4:E34) -> 0 | G35: =SUM(G4:G34) -> 0 | H35: =SUM(H4:H34) -> 0 | J35: =SUM(J4:J34) -> 0 | K35: =SUM(K4:K34) -> 0 | L35: =SUM(L4:L34) -> 500000

Sheet  Khammam&Cash
A1: Cash &Carry
A2: S.No | B2: Date | D2: Ind No/Bill No | E2: Diesel (Lts) | F2: Price | G2: Amount | H2: Petrol (Lts) | I2: Price | J2: Amount | K2: Total amount | L2: Amount paid | M2: As 0n Date | N2: Remarks
A3: Opening Balance | K3: 0 | M3: 0
A4: 1 | B4: 16.06.2025 | C4: Stambhadri Fuel Park HPCL | E4: 2890.1739 | F4: 103.8 | G4: =E4*F4 -> 300000.05 | K4: =G4+J4 -> 300000.05 | L4: =H4+K4 -> 300000.05 | M4: =M3+K4-L4 -> 0
A5: 2 | B5: 18.06.2025 | C5: Stambhadri Fuel Park HPCL | E5: 2890.1739 | F5: 103.8 | G5: =E5*F5 -> 300000.05 | J5: =H5*I5 -> 0 | K5: =G5+J5 -> 300000.05 | L5: =H5+K5 -> 300000.05 | M5: =M4+K5-L5 -> 0
A6: 3 | B6: 20.06.2025 | C6: Stambhadri Fuel Park HPCL | E6: 2890.1739 | F6: 103.8 | G6: =E6*F6 -> 300000.05 | J6: =H6*I6 -> 0 | K6: =G6+J6 -> 300000.05 | L6: =H6+K6 -> 300000.05 | M6: =M5+K6-L6 -> 0
A7: 4 | G7: =E7*F7 -> 0 | J7: =H7*I7 -> 0 | K7: =G7+J7 -> 0 | L7: =H7+K7 -> 0 | M7: =M6+K7-L7 -> 0
A8: 5 | G8: =E8*F8 -> 0 | J8: =H8*I8 -> 0 | K8: =G8+J8 -> 0 | L8: =H8+K8 -> 0 | M8: =M7+K8-L8 -> 0
A9: 6 | G9: =E9*F9 -> 0 | J9: =H9*I9 -> 0 | K9: =G9+J9 -> 0 | L9: =H9+K9 -> 0 | M9: =M8+K9-L9 -> 0
A10: 7 | G10: =E10*F10 -> 0 | J10: =H10*I10 -> 0 | K10: =G10+J10 -> 0 | L10: =H10+K10 -> 0 | M10: =M9+K10-L10 -> 0
A11: 8 | G11: =E11*F11 -> 0 | J11: =H11*I11 -> 0 | K11: =G11+J11 -> 0 | L11: =H11+K11 -> 0 | M11: =M10+K11-L11 -> 0
A12: 9 | G12: =E12*F12 -> 0 | J12: =H12*I12 -> 0 | K12: =G12+J12 -> 0 | L12: =H12+K12 -> 0 | M12: =M11+K12-L12 -> 0
A13: 10 | G13: =E13*F13 -> 0 | J13: =H13*I13 -> 0 | K13: =G13+J13 -> 0 | L13: =H13+K13 -> 0 | M13: =M12+K13-L13 -> 0
A14: 11 | G14: =E14*F14 -> 0 | J14: =H14*I14 -> 0 | K14: =G14+J14 -> 0 | L14: =H14+K14 -> 0 | M14: =M13+K14-L14 -> 0
A15: 12 | G15: =E15*F15 -> 0 | J15: =H15*I15 -> 0 | K15: =G15+J15 -> 0 | L15: =H15+K15 -> 0 | M15: =M14+K15-L15 -> 0
A16: 13 | G16: =E16*F16 -> 0 | J16: =H16*I16 -> 0 | K16: =G16+J16 -> 0 | L16: =H16+K16 -> 0 | M16: =M15+K16-L16 -> 0
A17: 14 | G17: =E17*F17 -> 0 | J17: =H17*I17 -> 0 | K17: =G17+J17 -> 0 | L17: =H17+K17 -> 0 | M17: =M16+K17-L17 -> 0
A18: 15 | G18: =E18*F18 -> 0 | J18: =H18*I18 -> 0 | K18: =G18+J18 -> 0 | L18: =H18+K18 -> 0 | M18: =M17+K18-L18 -> 0
... A22: 19 | G22: =E22*F22 -> 0 | J22: =H22*I22 -> 0 | K22: =G22+J22 -> 0 | L22: =H22+K22 -> 0 | M22: =M21+K22-L22 -> 0
A23: 20 | G23: =E23*F23 -> 0 | J23: =H23*I23 -> 0 | K23: =G23+J23 -> 0 | L23: 0 | M23: =M22+K23-L23 -> 0
A24: 21 | G24: =E24*F24 -> 0 | J24: =H24*I24 -> 0 | K24: =G24+J24 -> 0 | L24: =H24+K24 -> 0 | M24: =M23+K24-L24 -> 0
A25: 22 | G25: =E25*F25 -> 0 | J25: =H25*I25 -> 0 | K25: =G25+J25 -> 0 | L25: =H25+K25 -> 0 | M25: =M24+K25-L25 -> 0
A26: 23 | G26: =E26*F26 -> 0 | J26: =H26*I26 -> 0 | K26: =G26+J26 -> 0 | L26: =H26+K26 -> 0 | M26: =M25+K26-L26 -> 0
A27: 24 | G27: =E27*F27 -> 0 | K27: =G27+J27 -> 0 | L27: =H27+K27 -> 0 | M27: =M26+K27-L27 -> 0
A28: 25 | G28: =E28*F28 -> 0 | J28: =H28*I28 -> 0 | K28: =G28+J28 -> 0 | L28: =H28+K28 -> 0 | M28: =M26+K28-L28 -> 0
A29: 26 | G29: =E29*F29 -> 0 | J29: =H29*I29 -> 0 | K29: =G29+J29 -> 0 | L29: =H29+K29 -> 0 | M29: =M28+K29-L29 -> 0
A30: 27 | G30: =E30*F30 -> 0 | J30: =H30*I30 -> 0 | K30: =G30+J30 -> 0 | L30: =H30+K30 -> 0 | M30: =M29+K30-L30 -> 0
A31: 28 | G31: =E31*F31 -> 0 | J31: =H31*I31 -> 0 | K31: =G31+J31 -> 0 | L31: =H31+K31 -> 0 | M31: =M30+K31-L31 -> 0
A32: 29 | G32: =E32*F32 -> 0 | J32: =H32*I32 -> 0 | K32: =G32+J32 -> 0 | L32: =H32+K32 -> 0 | M32: =M31+K32-L32 -> 0
A33: 30 | G33: =E33*F33 -> 0 | J33: =H33*I33 -> 0 | K33: =G33+J33 -> 0 | L33: =H33+K33 -> 0 | M33: =M32+K33-L33 -> 0
A34: 31 | G34: =E34*F34 -> 0 | J34: =H34*I34 -> 0 | K34: =G34+J34 -> 0 | L34: =H34+K34 -> 0 | M34: =M33+K34-L34 -> 0
A35: 32 | G35: =E35*F35 -> 0 | K35: =G35+J35 -> 0 | L35: =H35+K35 -> 0 | M35: =M34+K35-L35 -> 0
A36: 33 | G36: =E36*F36 -> 0 | J36: =H36*I36 -> 0 | K36: =G36+J36 -> 0 | L36: =H36+K36 -> 0 | M36: =M35+K36-L36 -> 0
A37: 34 | G37: =E37*F37 -> 0 | J37: =H37*I37 -> 0 | K37: =G37+J37 -> 0 | L37: =H37+K37 -> 0 | M37: =M36+K37-L37 -> 0
G38: =E38*F38 -> 0 | K38: =G38+J38 -> 0 | L38: =H38+K38 -> 0 | M38: =M37+K38-L38 -> 0
G39: =E39*F39 -> 0 | K39: =G39+J39 -> 0 | L39: =H39+K39 -> 0 | M39: =M38+K39-L39 -> 0
G40: =E40*F40 -> 0 | K40: =G40+J40 -> 0 | L40: =H40+K40 -> 0 | M40: =M39+K40-L40 -> 0
M41: =M40+K41-L41 -> 0
A45: 35 | G45: =E45*F45 -> 0 | J45: =H45*I45 -> 0 | K45: =G45+J45 -> 0
E46: =SUM(E3:E45) -> 8670.5217 | G46: =SUM(G3:G45) -> 900000.15 | H46: =SUM(H3:H45) -> 0 | J46: =SUM(J3:J45) -> 0 | K46: =SUM(K4:K45) -> 900000.15 | L46: =SUM(L3:L45) -> 900000.15

Sheet Jadcherla-3
A1: JSASFuel Genie India Pvt.Ltd
A2: S.No | B2: Date | C2: GRN No | D2: Ind no/Bill No | E2: Diesel (Lts) | F2: Price | G2: Amount | H2: Petrol (Lts) | I2: Price | J2: Amount | K2: Total amount | L2: Amount paid | M2: As on Date | N2: Remarks
A3: Opening Balance | M3: 1313281.7
A4: 1 | B4: 46174 | G4: =E4*F4 -> 0 | J4: =H4*I4 -> 0 | K4: =G4+J4 -> 0 | L4: 0 | M4: =+M3+K4-L4 -> 1313281.7
A5: 2 | B5: 46175 | G5: =E5*F5 -> 0 | J5: =H5*I5 -> 0 | K5: =G5+J5 -> 0 | L5: 0 | M5: =+M4+K5-L5 -> 1313281.7
A6: 3 | B6: 46176 | G6: =E6*F6 -> 0 | J6: =H6*I6 -> 0 | K6: =G6+J6 -> 0 | L6: 0 | M6: =+M5+K6-L6 -> 1313281.7 | O6: 8032614 | P6: 2453209.4 | Q6: =SUM(O6:P6) -> 10485823
A7: 4 | B7: 46177 | G7: =E7*F7 -> 0 | J7: =H7*I7 -> 0 | K7: =G7+J7 -> 0 | L7: 0 | M7: =+M6+K7-L7 -> 1313281.7
A8: 5 | B8: 46178 | G8: =E8*F8 -> 0 | J8: =H8*I8 -> 0 | K8: =G8+J8 -> 0 | L8: 0 | M8: =+M7+K8-L8 -> 1313281.7
A9: 6 | B9: 46179 | G9: =E9*F9 -> 0 | J9: =H9*I9 -> 0 | K9: =G9+J9 -> 0 | L9: 0 | M9: =+M8+K9-L9 -> 1313281.7
A10: 7 | B10: 46180 | G10: =E10*F10 -> 0 | J10: =H10*I10 -> 0 | K10: =G10+J10 -> 0 | L10: 0 | M10: =+M9+K10-L10 -> 1313281.7 | R10: 700
A11: 8 | B11: 46181 | G11: =E11*F11 -> 0 | J11: =H11*I11 -> 0 | K11: =G11+J11 -> 0 | L11: 0 | M11: =+M10+K11-L11 -> 1313281.7 | S11: 5000
A12: 9 | B12: 46182 | G12: =E12*F12 -> 0 | J12: =H12*I12 -> 0 | K12: =G12+J12 -> 0 | L12: 1313281 | M12: =+M11+K12-L12 -> 0.7 | S12: 1500
A13: 10 | B13: 46183 | G13: =E13*F13 -> 0 | J13: =H13*I13 -> 0 | K13: =G13+J13 -> 0 | L13: 0 | M13: =+M12+K13-L13 -> 0.7 | S13: 500
A14: 11 | B14: 46184 | G14: =E14*F14 -> 0 | J14: =H14*I14 -> 0 | K14: =G14+J14 -> 0 | L14: 0 | M14: =+M13+K14-L14 -> 0.7
A15: 12 | B15: 46185 | G15: =E15*F15 -> 0 | J15: =H15*I15 -> 0 | K15: =G15+J15 -> 0 | L15: 0 | M15: =+M14+K15-L15 -> 0.7
A16: 13 | B16: 46186 | G16: =E16*F16 -> 0 | J16: =H16*I16 -> 0 | K16: =G16+J16 -> 0 | L16: 0 | M16: =+M15+K16-L16 -> 0.7
A17: 14 | B17: 46187 | G17: =E17*F17 -> 0 | J17: =H17*I17 -> 0 | K17: =G17+J17 -> 0 | L17: 0 | M17: =+M16+K17-L17 -> 0.7
A18: 15 | B18: 46188 | G18: =E18*F18 -> 0 | J18: =H18*I18 -> 0 | K18: =G18+J18 -> 0 | L18: 0 | M18: =+M17+K18-L18 -> 0.7
A19: 16 | B19: 46189 | G19: =E19*F19 -> 0 | J19: =H19*I19 -> 0 | K19: =G19+J19 -> 0 | L19: 0 | M19: =+M18+K19-L19 -> 0.7
A20: 17 | B20: 46190 | G20: =E20*F20 -> 0 | J20: =H20*I20 -> 0 | K20: =G20+J20 -> 0 | L20: 0 | M20: =+M19+K20-L20 -> 0.7
A21: 18 | B21: 46191 | J21: =H21*I21 -> 0 | K21: =G21+J21 -> 0 | L21: 0 | M21: =+M20+K21-L21 -> 0.7
A22: 19 | B22: 46192 | J22: =H22*I22 -> 0 | K22: =G22+J22 -> 0 | L22: 0 | M22: =+M21+K22-L22 -> 0.7
A23: 20 | B23: 46193 | J23: =H23*I23 -> 0 | K23: =G23+J23 -> 0 | L23: 0 | M23: =+M22+K23-L23 -> 0.7
A24: 21 | B24: 46194 | J24: =H24*I24 -> 0 | K24: =G24+J24 -> 0 | L24: 0 | M24: =+M23+K24-L24 -> 0.7
A25: 22 | B25: 46195 | G25: =E25*F25 -> 0 | J25: =H25*I25 -> 0 | K25: =G25+J25 -> 0 | L25: 0 | M25: =+M24+K25-L25 -> 0.7
A26: 23 | B26: 46196 | G26: =E26*F26 -> 0 | J26: =H26*I26 -> 0 | K26: =G26+J26 -> 0 | L26: 0 | M26: =+M25+K26-L26 -> 0.7
A27: 24 | B27: 46197 | G27: =E27*F27 -> 0 | J27: =H27*I27 -> 0 | K27: =G27+J27 -> 0 | L27: 0 | M27: =+M26+K27-L27 -> 0.7
A28: 25 | B28: 46198 | G28: =E28*F28 -> 0 | J28: =H28*I28 -> 0 | K28: =G28+J28 -> 0 | L28: 0 | M28: =+M27+K28-L28 -> 0.7
A29: 26 | B29: 46199 | G29: =E29*F29 -> 0 | J29: =H29*I29 -> 0 | K29: =G29+J29 -> 0 | L29: 0 | M29: =+M28+K29-L29 -> 0.7
A30: 27 | B30: 46200 | G30: =E30*F30 -> 0 | J30: =H30*I30 -> 0 | K30: =G30+J30 -> 0 | L30: 0 | M30: =+M29+K30-L30 -> 0.7
A31: 28 | B31: 46201 | G31: =E31*F31 -> 0 | J31: =H31*I31 -> 0 | K31: =G31+J31 -> 0 | L31: 0 | M31: =+M30+K31-L31 -> 0.7
A32: 29 | B32: 46202 | G32: =E32*F32 -> 0 | J32: =H32*I32 -> 0 | K32: =G32+J32 -> 0 | M32: =+M31+K32-L32 -> 0.7
A33: 30 | B33: 46203 | G33: =E33*F33 -> 0 | J33: =H33*I33 -> 0 | K33: =G33+J33 -> 0 | M33: =+M32+K33-L33 -> 0.7
A34: 31 | G34: =E34*F34 -> 0 | H34: 0 | I34: 0 | J34: =H34*I34 -> 0 | K34: =G34+J34 -> 0 | L34: 0 | M34: =+M33+K34-L34 -> 0.7
E35: =SUM(E4:E34) -> 0 | G35: =SUM(G4:G34) -> 0 | H35: =SUM(H4:H34) -> 0 | J35: =SUM(J4:J34) -> 0 | K35: =SUM(K4:K34) -> 0 | L35: =SUM(L4:L34) -> 1313281
F38: /

Sheet Jadcherla-4
A1: Shree Poornima F/S
A2: S.No | B2: Date | C2: GRN No | D2: Ind No/Bill No | E2: Diesel (Lts) | F2: Price | G2: Amount | H2: Petrol (Lts) | I2: Price | J2: Amount | K2: Total amount | L2: Amount paid | M2: As on date | N2: Remarks
A3: Opening Balance | M3: 15788.08
A4: 1 | B4: 46174 | G4: =E4*F4 -> 0 | J4: =H4*I4 -> 0 | K4: =G4+J4 -> 0 | L4: 0 | M4: =M3+K4-L4 -> 15788.08
A5: 2 | B5: 46175 | E5: 0 | F5: 0 | G5: =E5*F5 -> 0 | H5: 40 | I5: 116.33 | J5: =H5*I5 -> 4653.2 | K5: =G5+J5 -> 4653.2 | L5: 0 | M5: =M4+K5-L5 -> 20441.28
A6: 3 | B6: 46176 | G6: =E6*F6 -> 0 | J6: =H6*I6 -> 0 | K6: =G6+J6 -> 0 | L6: 0 | M6: =M5+K6-L6 -> 20441.28
A7: 4 | B7: 46177 | G7: =E7*F7 -> 0 | J7: =H7*I7 -> 0 | K7: =G7+J7 -> 0 | L7: 0 | M7: =M6+K7-L7 -> 20441.28
A8: 5 | B8: 46178 | E8: 2000 | F8: 104.42 | G8: =E8*F8 -> 208840 | J8: =H8*I8 -> 0 | K8: =G8+J8 -> 208840 | L8: 0 | M8: =M7+K8-L8 -> 229281.28
A9: 6 | B9: 46179 | G9: =E9*F9 -> 0 | J9: =H9*I9 -> 0 | K9: =G9+J9 -> 0 | L9: 229281 | M9: =M8+K9-L9 -> 0.28
A10: 7 | B10: 46180 | G10: =E10*F10 -> 0 | J10: =H10*I10 -> 0 | K10: =G10+J10 -> 0 | L10: 0 | M10: =M9+K10-L10 -> 0.28
A11: 8 | B11: 46181 | G11: =E11*F11 -> 0 | J11: =H11*I11 -> 0 | K11: =G11+J11 -> 0 | L11: 0 | M11: =M10+K11-L11 -> 0.28
A12: 9 | B12: 46182 | G12: =E12*F12 -> 0 | J12: =H12*I12 -> 0 | K12: =G12+J12 -> 0 | M12: =M11+K12-L12 -> 0.28
A13: 10 | B13: 46183 | G13: =E13*F13 -> 0 | J13: =H13*I13 -> 0 | K13: =G13+J13 -> 0 | M13: =M12+K13-L13 -> 0.28
A14: 11 | B14: 46184 | G14: =E14*F14 -> 0 | J14: =H14*I14 -> 0 | K14: =G14+J14 -> 0 | M14: =M13+K14-L14 -> 0.28
A15: 12 | B15: 46185 | G15: =E15*F15 -> 0 | J15: =H15*I15 -> 0 | K15: =G15+J15 -> 0 | M15: =M14+K15-L15 -> 0.28
A16: 13 | B16: 46186 | G16: =E16*F16 -> 0 | J16: =H16*I16 -> 0 | K16: =G16+J16 -> 0 | M16: =M15+K16-L16 -> 0.28
A17: 14 | B17: 46187 | G17: =E17*F17 -> 0 | J17: =H17*I17 -> 0 | K17: =G17+J17 -> 0 | M17: =M16+K17-L17 -> 0.28
A18: 15 | B18: 46188 | G18: =E18*F18 -> 0 | J18: =H18*I18 -> 0 | K18: =G18+J18 -> 0 | M18: =M17+K18-L18 -> 0.28
A19: 16 | B19: 46189 | G19: 0 | J19: 0 | K19: 0 | M19: =M18+K19-L19 -> 0.28
A20: 17 | B20: 46190 | G20: =E20*F20 -> 0 | J20: =H20*I20 -> 0 | K20: =G20+J20 -> 0 | M20: =M19+K20-L20 -> 0.28
A21: 18 | B21: 46191 | E21: 500 | F21: 104.42 | G21: =E21*F21 -> 52210 | J21: =H21*I21 -> 0 | K21: =G21+J21 -> 52210 | M21: =M20+K21-L21 -> 52210.28
A22: 19 | B22: 46192 | G22: =E22*F22 -> 0 | J22: =H22*I22 -> 0 | K22: =G22+J22 -> 0 | L22: 0 | M22: =M21+K22-L22 -> 52210.28
A23: 20 | B23: 46193 | G23: =E23*F23 -> 0 | J23: =H23*I23 -> 0 | K23: =G23+J23 -> 0 | L23: 0 | M23: =M22+K23-L23 -> 52210.28
A24: 21 | B24: 46194 | G24: =E24*F24 -> 0 | J24: =H24*I24 -> 0 | K24: =G24+J24 -> 0 | L24: 0 | M24: =M23+K24-L24 -> 52210.28
A25: 22 | B25: 46195 | G25: =E25*F25 -> 0 | J25: =H25*I25 -> 0 | K25: =G25+J25 -> 0 | L25: 0 | M25: =M24+K25-L25 -> 52210.28
A26: 23 | B26: 46196 | G26: =E26*F26 -> 0 | J26: =H26*I26 -> 0 | K26: =G26+J26 -> 0 | L26: 0 | M26: =M25+K26-L26 -> 52210.28
A27: 24 | B27: 46197 | G27: =E27*F27 -> 0 | H27: 40 | I27: 116.33 | J27: =H27*I27 -> 4653.2 | K27: =G27+J27 -> 4653.2 | L27: 0 | M27: =M26+K27-L27 -> 56863.48
A28: 25 | B28: 46198 | E28: 0 | F28: 0 | G28: =E28*F28 -> 0 | J28: =H28*I28 -> 0 | K28: =G28+J28 -> 0 | L28: 50000 | M28: =M27+K28-L28 -> 6863.48
A29: 26 | B29: 46199 | G29: =E29*F29 -> 0 | J29: =H29*I29 -> 0 | K29: =G29+J29 -> 0 | L29: 0 | M29: =M28+K29-L29 -> 6863.48
A30: 27 | B30: 46200 | G30: =E30*F30 -> 0 | J30: =H30*I30 -> 0 | K30: =G30+J30 -> 0 | L30: 0 | M30: =M29+K30-L30 -> 6863.48
A31: 28 | B31: 46201 | G31: =E31*F31 -> 0 | J31: =H31*I31 -> 0 | K31: =G31+J31 -> 0 | L31: 0 | M31: =M30+K31-L31 -> 6863.48
A32: 29 | B32: 46202 | G32: =E32*F32 -> 0 | J32: =H32*I32 -> 0 | K32: =G32+J32 -> 0 | L32: 0 | M32: =M31+K32-L32 -> 6863.48
A33: 30 | B33: 46203 | G33: =E33*F33 -> 0 | H33: 0 | I33: 0 | J33: =H33*I33 -> 0 | K33: =G33+J33 -> 0 | L33: 0 | M33: =M32+K33-L33 -> 6863.48
A34: 31 | G34: =E34*F34 -> 0 | J34: =H34*I34 -> 0 | K34: =G34+J34 -> 0 | M34: =M33+K34-L34 -> 6863.48
E35: =SUM(E4:E34) -> 2500 | G35: =SUM(G4:G34) -> 261050 | H35: =SUM(H4:H34) -> 80 | J35: =SUM(J4:J34) -> 9306.4 | K35: =SUM(K4:K34) -> 270356.4 | L35: =SUM(L4:L34) -> 279281

Sheet  Jadcherla
A1: Sai baba F/S
A2: S.No | B2: Date | C2: GRN No | D2: Ind No/Bill No | E2: Diesel (Lts) | F2: Price | G2: Amount | H2: Petrol (Lts) | I2: Price | J2: Amount | K2: Total amount | L2: Amount paid | M2: As on date | N2: Remarks
A3: Opening Balance | M3: 171115.11
A4: 1 | B4: 46174 | G4: =E4*F4 -> 0 | J4: =H4*I4 -> 0 | K4: =G4+J4 -> 0 | L4: 169080 | M4: =M3+K4-L4 -> 2035.1104 | N4: BT
A5: 2 | B5: 46175 | G5: =E5*F5 -> 0 | J5: =H5*I5 -> 0 | K5: =G5+J5 -> 0 | L5: 2035.11 | M5: =M4+K5-L5 -> 0.00040000001
A6: 3 | B6: 46176 | G6: =E6*F6 -> 0 | J6: =H6*I6 -> 0 | K6: =G6+J6 -> 0 | M6: =M5+K6-L6 -> 0.00040000001
A7: 4 | B7: 46177 | G7: =E7*F7 -> 0 | J7: =H7*I7 -> 0 | K7: =G7+J7 -> 0 | M7: =M6+K7-L7 -> 0.00040000001 | Q7: =1000*96.42 -> 96420
A8: 5 | B8: 46178 | G8: =E8*F8 -> 0 | J8: =H8*I8 -> 0 | K8: =G8+J8 -> 0 | M8: =M7+K8-L8 -> 0.00040000001
A9: 6 | B9: 46179 | G9: =E9*F9 -> 0 | J9: =H9*I9 -> 0 | K9: =G9+J9 -> 0 | M9: =M8+K9-L9 -> 0.00040000001
A10: 7 | B10: 46180 | G10: =E10*F10 -> 0 | J10: =H10*I10 -> 0 | K10: =G10+J10 -> 0 | M10: =M9+K10-L10 -> 0.00040000001
A11: 8 | B11: 46181 | G11: =E11*F11 -> 0 | J11: =H11*I11 -> 0 | K11: =G11+J11 -> 0 | M11: =M10+K11-L11 -> 0.00040000001
A12: 9 | B12: 46182 | G12: =E12*F12 -> 0 | J12: =H12*I12 -> 0 | K12: =G12+J12 -> 0 | M12: =M11+K12-L12 -> 0.00040000001
A13: 10 | B13: 46183 | G13: =E13*F13 -> 0 | J13: =H13*I13 -> 0 | K13: =G13+J13 -> 0 | M13: =M12+K13-L13 -> 0.00040000001
A14: 11 | B14: 46184 | G14: =E14*F14 -> 0 | J14: =H14*I14 -> 0 | K14: =G14+J14 -> 0 | M14: =M13+K14-L14 -> 0.00040000001
A15: 12 | B15: 46185 | G15: =E15*F15 -> 0 | J15: =H15*I15 -> 0 | K15: =G15+J15 -> 0 | M15: =M14+K15-L15 -> 0.00040000001
A16: 13 | B16: 46186 | G16: =E16*F16 -> 0 | J16: =H16*I16 -> 0 | K16: =G16+J16 -> 0 | M16: =M15+K16-L16 -> 0.00040000001
A17: 14 | B17: 46187 | G17: =E17*F17 -> 0 | J17: =H17*I17 -> 0 | K17: =G17+J17 -> 0 | M17: =M16+K17-L17 -> 0.00040000001
A18: 15 | B18: 46188 | G18: =E18*F18 -> 0 | J18: =H18*I18 -> 0 | K18: =G18+J18 -> 0 | M18: =M17+K18-L18 -> 0.00040000001 | N18: BT
A19: 16 | B19: 46189 | G19: =E19*F19 -> 0 | J19: =H19*I19 -> 0 | K19: =G19+J19 -> 0 | M19: =M18+K19-L19 -> 0.00040000001
A20: 17 | B20: 46190 | G20: =E20*F20 -> 0 | J20: =H20*I20 -> 0 | K20: =G20+J20 -> 0 | M20: =M19+K20-L20 -> 0.00040000001
A21: 18 | B21: 46191 | G21: =E21*F21 -> 0 | J21: =H21*I21 -> 0 | K21: =G21+J21 -> 0 | M21: =M20+K21-L21 -> 0.00040000001 | N21: BT
A22: 19 | B22: 46192 | G22: =E22*F22 -> 0 | J22: =H22*I22 -> 0 | K22: =G22+J22 -> 0 | M22: =M21+K22-L22 -> 0.00040000001
A23: 20 | B23: 46193 | G23: =E23*F23 -> 0 | J23: =H23*I23 -> 0 | K23: =G23+J23 -> 0 | M23: =M22+K23-L23 -> 0.00040000001
A24: 21 | B24: 46194 | G24: =E24*F24 -> 0 | J24: =H24*I24 -> 0 | K24: =G24+J24 -> 0 | M24: =M23+K24-L24 -> 0.00040000001
A25: 22 | B25: 46195 | G25: =E25*F25 -> 0 | J25: =H25*I25 -> 0 | K25: =G25+J25 -> 0 | M25: =M24+K25-L25 -> 0.00040000001
A26: 23 | B26: 46196 | G26: =E26*F26 -> 0 | J26: =H26*I26 -> 0 | K26: =G26+J26 -> 0 | M26: =M25+K26-L26 -> 0.00040000001
A27: 24 | B27: 46197 | G27: =E27*F27 -> 0 | J27: =H27*I27 -> 0 | K27: =G27+J27 -> 0 | M27: =M26+K27-L27 -> 0.00040000001
A28: 25 | B28: 46198 | G28: =E28*F28 -> 0 | J28: =H28*I28 -> 0 | K28: =G28+J28 -> 0 | M28: =M27+K28-L28 -> 0.00040000001
A29: 26 | B29: 46199 | G29: =E29*F29 -> 0 | J29: =H29*I29 -> 0 | K29: =G29+J29 -> 0 | M29: =M28+K29-L29 -> 0.00040000001
A30: 27 | B30: 46200 | G30: =E30*F30 -> 0 | J30: =H30*I30 -> 0 | K30: =G30+J30 -> 0 | M30: =M29+K30-L30 -> 0.00040000001
A31: 28 | B31: 46201 | G31: =E31*F31 -> 0 | J31: =H31*I31 -> 0 | K31: =G31+J31 -> 0 | M31: =M30+K31-L31 -> 0.00040000001
A32: 29 | B32: 46202 | G32: =E32*F32 -> 0 | J32: =H32*I32 -> 0 | K32: =G32+J32 -> 0 | M32: =M31+K32-L32 -> 0.00040000001
A33: 30 | B33: 46203 | G33: =E33*F33 -> 0 | H33: 0 | I33: 0 | J33: =H33*I33 -> 0 | K33: =G33+J33 -> 0 | L33: 0 | M33: =M32+K33-L33 -> 0.00040000001
A34: 31 | G34: =E34*F34 -> 0 | J34: =H34*I34 -> 0 | K34: =G34+J34 -> 0 | M34: =M33+K34-L34 -> 0.00040000001
E35: =SUM(E4:E34) -> 0 | G35: =SUM(G4:G34) -> 0 | H35: =SUM(H4:H34) -> 0 | J35: =SUM(J4:J34) -> 0 | K35: =SUM(K4:K34) -> 0 | L35: =SUM(L4:L34) -> 171115.11

Sheet  Sangareddy-2
A1: Durga Bhavani F/S
A2: S.No | B2: Date | C2: GRN No | D2: Ind no/Bill No | E2: Diesel (Lts) | F2: Price | G2: Amount | H2: Petrol (Lts) | I2: Price | J2: Amount | K2: Total amount | L2: Amount paid | M2: As on Date | N2: Remarks
A3: Opening Balance | M3: 108316.17
A4: 1 | B4: 45809 | G4: =E4*F4 -> 0 | J4: =H4*I4 -> 0 | K4: =G4+J4 -> 0 | M4: =M3+K4-L4 -> 108316.17
A5: 2 | B5: 45810 | G5: =E5*F5 -> 0 | J5: =H5*I5 -> 0 | K5: =G5+J5 -> 0 | M5: =M4+K5-L5 -> 108316.17
A6: 3 | B6: 45811 | G6: =E6*F6 -> 0 | J6: =H6*I6 -> 0 | K6: =G6+J6 -> 0 | M6: =M5+K6-L6 -> 108316.17
A7: 4 | B7: 45812 | G7: =E7*F7 -> 0 | J7: =H7*I7 -> 0 | K7: =G7+J7 -> 0 | M7: =M6+K7-L7 -> 108316.17
A8: 5 | B8: 45813 | G8: =E8*F8 -> 0 | J8: =H8*I8 -> 0 | K8: =G8+J8 -> 0 | M8: =M7+K8-L8 -> 108316.17
A9: 6 | B9: 45814 | G9: =E9*F9 -> 0 | J9: =H9*I9 -> 0 | K9: =G9+J9 -> 0 | M9: =M8+K9-L9 -> 108316.17
A10: 7 | B10: 45815 | G10: =E10*F10 -> 0 | J10: =H10*I10 -> 0 | K10: =G10+J10 -> 0 | M10: =M9+K10-L10 -> 108316.17
A11: 8 | B11: 45816 | G11: =E11*F11 -> 0 | J11: =H11*I11 -> 0 | K11: =G11+J11 -> 0 | L11: 108316 | M11: =M10+K11-L11 -> 0.1714
A12: 9 | B12: 45817 | E12: 47.24 | F12: 104.56 | G12: =E12*F12 -> 4939.4144 | J12: =H12*I12 -> 0 | K12: =G12+J12 -> 4939.4144 | M12: =M11+K12-L12 -> 4939.5858
A13: 10 | B13: 45818 | G13: =E13*F13 -> 0 | J13: =H13*I13 -> 0 | K13: =G13+J13 -> 0 | M13: =M12+K13-L13 -> 4939.5858
A14: 11 | B14: 45819 | G14: =E14*F14 -> 0 | J14: =H14*I14 -> 0 | K14: =G14+J14 -> 0 | M14: =M13+K14-L14 -> 4939.5858
A15: 12 | B15: 45820 | E15: 190.32 | F15: 104.56 | G15: =E15*F15 -> 19899.859 | H15: 15 | I15: 116.54 | J15: =H15*I15 -> 1748.1 | K15: =G15+J15 -> 21647.959 | M15: =M14+K15-L15 -> 26587.545
A16: 13 | B16: 45821 | E16: 112 | F16: 104.56 | G16: =E16*F16 -> 11710.72 | J16: =H16*I16 -> 0 | K16: =G16+J16 -> 11710.72 | M16: =M15+K16-L16 -> 38298.265
A17: 14 | B17: 45822 | E17: 0 | F17: 104.56 | G17: =E17*F17 -> 0 | H17: 8 | I17: 116.54 | J17: =H17*I17 -> 932.32 | K17: =G17+J17 -> 932.32 | M17: =M16+K17-L17 -> 39230.585
A18: 15 | B18: 45823 | E18: 564.77 | F18: 104.56 | G18: =E18*F18 -> 59052.351 | H18: 10 | I18: 116.54 | J18: =H18*I18 -> 1165.4 | K18: =G18+J18 -> 60217.751 | M18: =M17+K18-L18 -> 99448.336
A19: 16 | B19: 45824 | E19: 34.9 | F19: 104.56 | G19: =E19*F19 -> 3649.144 | H19: 3 | I19: 116.54 | J19: =H19*I19 -> 349.62 | K19: =G19+J19 -> 3998.764 | M19: =M18+K19-L19 -> 103447.1
A20: 17 | B20: 45825 | E20: 1379.47 | F20: 104.56 | G20: =E20*F20 -> 144237.38 | H20: 13 | I20: 116.54 | J20: =H20*I20 -> 1515.02 | K20: =G20+J20 -> 145752.4 | M20: =M19+K20-L20 -> 249199.5
A21: 18 | B21: 45826 | E21: 373.32 | F21: 104.56 | G21: =E21*F21 -> 39034.339 | J21: =H21*I21 -> 0 | K21: =G21+J21 -> 39034.339 | M21: =M20+K21-L21 -> 288233.84
A22: 19 | B22: 45827 | G22: =E22*F22 -> 0 | H22: 10 | I22: 116.54 | J22: =H22*I22 -> 1165.4 | K22: =G22+J22 -> 1165.4 | M22: =M21+K22-L22 -> 289399.24
A23: 20 | B23: 45828 | E23: 37.2 | F23: 104.56 | G23: =E23*F23 -> 3889.632 | J23: =H23*I23 -> 0 | K23: =G23+J23 -> 3889.632 | M23: =M22+K23-L23 -> 293288.87 | Q23: 96.44
A24: 21 | B24: 45829 | G24: =E24*F24 -> 0 | J24: =H24*I24 -> 0 | K24: =G24+J24 -> 0 | M24: =M23+K24-L24 -> 293288.87
A25: 22 | B25: 45830 | E25: 200 | F25: 104.56 | G25: =E25*F25 -> 20912 | H25: 5 | I25: 116.54 | J25: =H25*I25 -> 582.7 | K25: =G25+J25 -> 21494.7 | M25: =M24+K25-L25 -> 314783.57
A26: 23 | B26: 45831 | E26: 41.93 | F26: 104.56 | G26: =E26*F26 -> 4384.2008 | H26: 5 | I26: 116.54 | J26: =H26*I26 -> 582.7 | K26: =G26+J26 -> 4966.9008 | M26: =M25+K26-L26 -> 319750.48
A27: 24 | B27: 45832 | G27: =E27*F27 -> 0 | H27: 20 | I27: 116.54 | J27: =H27*I27 -> 2330.8 | K27: =G27+J27 -> 2330.8 | M27: =M26+K27-L27 -> 322081.28
A28: 25 | B28: 45833 | E28: 37.75 | F28: 104.56 | G28: =E28*F28 -> 3947.14 | J28: 0 | K28: =G28+J28 -> 3947.14 | L28: 200000 | M28: =M27+K28-L28 -> 126028.42
A29: 26 | B29: 45834 | G29: =E29*F29 -> 0 | J29: =H29*I29 -> 0 | K29: =G29+J29 -> 0 | M29: =M28+K29-L29 -> 126028.42
A30: 27 | B30: 45835 | G30: =E30*F30 -> 0 | H30: 5 | I30: 116.54 | J30: =H30*I30 -> 582.7 | K30: =G30+J30 -> 582.7 | M30: =M29+K30-L30 -> 126611.12
A31: 28 | B31: 45836 | G31: =E31*F31 -> 0 | J31: =H31*I31 -> 0 | K31: =G31+J31 -> 0 | M31: =M30+K31-L31 -> 126611.12
A32: 29 | B32: 45837 | G32: =E32*F32 -> 0 | J32: =H32*I32 -> 0 | K32: =G32+J32 -> 0 | M32: =M31+K32-L32 -> 126611.12
A33: 30 | B33: 45838 | G33: =E33*F33 -> 0 | H33: 15 | I33: 116.54 | J33: =H33*I33 -> 1748.1 | K33: =G33+J33 -> 1748.1 | L33: 0 | M33: =M32+K33-L33 -> 128359.22
A34: 31 | G34: =E34*F34 -> 0 | J34: =H34*I34 -> 0 | K34: =G34+J34 -> 0 | L34: 0 | M34: =M33+K34-L34 -> 128359.22
E35: =SUM(E4:E34) -> 3018.9 | G35: =SUM(G4:G34) -> 315656.18 | H35: =SUM(H4:H34) -> 109 | J35: =SUM(J4:J34) -> 12702.86 | K35: =SUM(K4:K34) -> 328359.04 | L35: =SUM(L4:L34) -> 308316

Sheet  Sangareddy-3
A1: SHIVA PARVATHI FILLING STATION SADASHIVPET
A2: S.No | B2: Date | C2: GRN No | D2: Ind no/Bill No | E2: Diesel (Lts) | F2: Price | G2: Amount | H2: Petrol (Lts) | I2: Price | J2: Amount | K2: Total amount | L2: Amount paid | M2: As on Date | N2: Remarks
A3: Opening Balance | M3: 986125.39
A4: 1 | B4: 45809 | E4: 690 | F4: 104.35 | G4: =E4*F4 -> 72001.5 | J4: =H4*I4 -> 0 | K4: =G4+J4 -> 72001.5 | L4: 300000 | M4: =M3+K4-L4 -> 758126.89
A5: 2 | B5: 45810 | E5: 690 | F5: 104.35 | G5: =E5*F5 -> 72001.5 | H5: 6 | I5: 116.25 | J5: =H5*I5 -> 697.5 | K5: =G5+J5 -> 72699 | L5: 0 | M5: =M4+K5-L5 -> 830825.89
A6: 3 | B6: 45811 | E6: 490 | F6: 104.35 | G6: =E6*F6 -> 51131.5 | J6: =H6*I6 -> 0 | K6: =G6+J6 -> 51131.5 | L6: 0 | M6: =M5+K6-L6 -> 881957.39
A7: 4 | B7: 45812 | G7: =E7*F7 -> 0 | H7: 8 | I7: 126.03 | J7: =H7*I7 -> 1008.24 | K7: =G7+J7 -> 1008.24 | L7: 0 | M7: =M6+K7-L7 -> 882965.63
A8: 5 | B8: 45813 | E8: 690 | F8: 104.35 | G8: =E8*F8 -> 72001.5 | H8: 7 | I8: 116.25 | J8: =H8*I8 -> 813.75 | K8: =G8+J8 -> 72815.25 | L8: 0 | M8: =M7+K8-L8 -> 955780.88
A9: 6 | B9: 45814 | E9: 690 | F9: 104.35 | G9: =E9*F9 -> 72001.5 | H9: 6 | I9: 116.25 | J9: =H9*I9 -> 697.5 | K9: =G9+J9 -> 72699 | L9: 0 | M9: =M8+K9-L9 -> 1028479.9
A10: 7 | B10: 45815 | E10: 690 | F10: 104.35 | G10: =E10*F10 -> 72001.5 | J10: =H10*I10 -> 0 | K10: =G10+J10 -> 72001.5 | L10: 0 | M10: =M9+K10-L10 -> 1100481.4
A11: 8 | B11: 45816 | G11: =E11*F11 -> 0 | J11: =H11*I11 -> 0 | K11: =G11+J11 -> 0 | L11: 900000 | M11: =M10+K11-L11 -> 200481.38
A12: 9 | B12: 45817 | E12: 691 | F12: 104.35 | G12: =E12*F12 -> 72105.85 | H12: 6 | I12: 116.25 | J12: =H12*I12 -> 697.5 | K12: =G12+J12 -> 72803.35 | M12: =M11+K12-L12 -> 273284.73
A13: 10 | B13: 45818 | E13: 690 | F13: 104.35 | G13: =E13*F13 -> 72001.5 | H13: 5 | I13: 116.25 | J13: =H13*I13 -> 581.25 | K13: =G13+J13 -> 72582.75 | M13: =M12+K13-L13 -> 345867.48
A14: 11 | B14: 45819 | G14: =E14*F14 -> 0 | H14: 11 | I14: 126.03 | J14: =H14*I14 -> 1386.33 | K14: =G14+J14 -> 1386.33 | M14: =M13+K14-L14 -> 347253.81 | N14: BT
B15: 45820 | E15: 690 | F15: 104.35 | G15: =E15*F15 -> 72001.5 | K15: =G15+J15 -> 72001.5 | M15: =M14+K15-L15 -> 419255.31
A16: 12 | B16: 45821 | E16: 690 | F16: 104.35 | G16: =E16*F16 -> 72001.5 | J16: =H16*I16 -> 0 | K16: =G16+J16 -> 72001.5 | M16: =M15+K16-L16 -> 491256.81
A17: 13 | B17: 45822 | E17: 690 | F17: 104.35 | G17: =E17*F17 -> 72001.5 | J17: =H17*I17 -> 0 | K17: =G17+J17 -> 72001.5 | M17: =M16+K17-L17 -> 563258.31
A18: 14 | B18: 45823 | G18: =E18*F18 -> 0 | J18: =H18*I18 -> 0 | K18: =G18+J18 -> 0 | M18: =M17+K18-L18 -> 563258.31
A19: 15 | B19: 45824 | E19: 690 | F19: 104.35 | G19: =E19*F19 -> 72001.5 | J19: =H19*I19 -> 0 | K19: =G19+J19 -> 72001.5 | M19: =M18+K19-L19 -> 635259.81
A20: 16 | B20: 45825 | E20: 690 | F20: 104.35 | G20: =E20*F20 -> 72001.5 | J20: =H20*I20 -> 0 | K20: =G20+J20 -> 72001.5 | L20: 500000 | M20: =M19+K20-L20 -> 207261.31
A21: 17 | B21: 45826 | E21: 690 | F21: 104.35 | G21: =E21*F21 -> 72001.5 | J21: =H21*I21 -> 0 | K21: =G21+J21 -> 72001.5 | M21: =M20+K21-L21 -> 279262.81
A22: 18 | B22: 45827 | E22: 690 | F22: 104.35 | G22: =E22*F22 -> 72001.5 | J22: =H22*I22 -> 0 | K22: =G22+J22 -> 72001.5 | M22: =M21+K22-L22 -> 351264.31
A23: 19 | B23: 45828 | E23: 690 | F23: 104.35 | G23: =E23*F23 -> 72001.5 | J23: =H23*I23 -> 0 | K23: =G23+J23 -> 72001.5 | M23: =M22+K23-L23 -> 423265.81
A24: 20 | B24: 45829 | E24: 690 | F24: 104.35 | G24: =E24*F24 -> 72001.5 | J24: =H24*I24 -> 0 | K24: =G24+J24 -> 72001.5 | M24: =M23+K24-L24 -> 495267.31
A25: 21 | B25: 45830 | G25: =E25*F25 -> 0 | J25: =H25*I25 -> 0 | K25: =G25+J25 -> 0 | M25: =M24+K25-L25 -> 495267.31
A26: 22 | B26: 45831 | E26: 655 | F26: 104.35 | G26: =E26*F26 -> 68349.25 | J26: =H26*I26 -> 0 | K26: =G26+J26 -> 68349.25 | M26: =M25+K26-L26 -> 563616.56
A27: 23 | B27: 45832 | E27: 690 | F27: 104.35 | G27: =E27*F27 -> 72001.5 | J27: =H27*I27 -> 0 | K27: =G27+J27 -> 72001.5 | M27: =M26+K27-L27 -> 635618.06
A28: 24 | B28: 45833 | G28: =E28*F28 -> 0 | J28: =H28*I28 -> 0 | K28: =G28+J28 -> 0 | M28: =M27+K28-L28 -> 635618.06
A29: 25 | B29: 45834 | G29: =E29*F29 -> 0 | J29: =H29*I29 -> 0 | K29: =G29+J29 -> 0 | L29: 500000 | M29: =M28+K29-L29 -> 135618.06
A30: 26 | B30: 45835 | G30: =E30*F30 -> 0 | J30: =H30*I30 -> 0 | K30: =G30+J30 -> 0 | M30: =M29+K30-L30 -> 135618.06
A31: 27 | B31: 45836 | G31: =E31*F31 -> 0 | J31: =H31*I31 -> 0 | K31: =G31+J31 -> 0 | M31: =M30+K31-L31 -> 135618.06
A32: 28 | B32: 45837 | G32: =E32*F32 -> 0 | J32: =H32*I32 -> 0 | K32: =G32+J32 -> 0 | M32: =M31+K32-L32 -> 135618.06
A33: 29 | B33: 45838 | E33: 690 | F33: 104.35 | G33: =E33*F33 -> 72001.5 | J33: =H33*I33 -> 0 | K33: =G33+J33 -> 72001.5 | M33: =M32+K33-L33 -> 207619.56
A34: 30 | B34: 45839 | G34: =E34*F34 -> 0 | J34: =H34*I34 -> 0 | K34: =G34+J34 -> 0 | M34: =M33+K34-L34 -> 207619.56
A35: 31 | B35: 45840 | G35: =E35*F35 -> 0 | J35: =H35*I35 -> 0 | K35: =G35+J35 -> 0 | M35: =M34+K35-L35 -> 207619.56
E36: =SUM(E4:E35) -> 13566 | G36: =SUM(G4:G35) -> 1415612.1 | H36: =SUM(H4:H35) -> 49 | J36: =SUM(J4:J35) -> 5882.07 | K36: =SUM(K4:K35) -> 1421494.2 | L36: =SUM(L4:L35) -> 2200000

Sheet Narayankhed
A2: S.No | B2: Date | C2: GRN No | D2: Ind no/Bill No | E2: Diesel (Lts) | F2: Price | G2: Amount | H2: Petrol (Lts) | I2: Price | J2: Amount | K2: Total amount | L2: Amount paid | M2: As on Date | N2: Remarks
A3: Opening Balance | M3: 0
A4: 1 | B4: 45809 | E4: 231.7 | F4: 107.9 | G4: =E4*F4 -> 25000.43 | J4: =H4*I4 -> 0 | K4: =G4+J4 -> 25000.43 | L4: =H4+K4 -> 25000.43 | M4: =M3+K4-L4 -> 0 | N4: BT
A5: 2 | B5: 45810 | G5: =E5*F5 -> 0 | J5: =H5*I5 -> 0 | K5: =G5+J5 -> 0 | L5: =H5+K5 -> 0 | M5: =M4+K5-L5 -> 0
A6: 3 | B6: 45811 | G6: =E6*F6 -> 0 | J6: =H6*I6 -> 0 | K6: =G6+J6 -> 0 | L6: =H6+K6 -> 0 | M6: =M5+K6-L6 -> 0
A7: 4 | B7: 45812 | G7: =E7*F7 -> 0 | J7: =H7*I7 -> 0 | K7: =G7+J7 -> 0 | L7: =H7+K7 -> 0 | M7: =M6+K7-L7 -> 0
A8: 5 | B8: 45813 | G8: =E8*F8 -> 0 | J8: =H8*I8 -> 0 | K8: =G8+J8 -> 0 | L8: =H8+K8 -> 0 | M8: =M7+K8-L8 -> 0
A9: 6 | B9: 45814 | G9: =E9*F9 -> 0 | J9: =H9*I9 -> 0 | K9: =G9+J9 -> 0 | L9: 0 | M9: =M8+K9-L9 -> 0
A10: 7 | B10: 45815 | G10: =E10*F10 -> 0 | J10: =H10*I10 -> 0 | K10: =G10+J10 -> 0 | L10: 0 | M10: =M9+K10-L10 -> 0
A11: 8 | B11: 45816 | G11: =E11*F11 -> 0 | J11: =H11*I11 -> 0 | K11: =G11+J11 -> 0 | L11: 0 | M11: =M10+K11-L11 -> 0
A12: 9 | B12: 45817 | G12: =E12*F12 -> 0 | J12: =H12*I12 -> 0 | K12: =G12+J12 -> 0 | L12: 0 | M12: =M11+K12-L12 -> 0
A13: 10 | B13: 45818 | G13: =E13*F13 -> 0 | J13: =H13*I13 -> 0 | K13: =G13+J13 -> 0 | L13: 0 | M13: =M12+K13-L13 -> 0
A14: 11 | B14: 45819 | G14: =E14*F14 -> 0 | J14: =H14*I14 -> 0 | K14: =G14+J14 -> 0 | L14: =H14+K14 -> 0 | M14: =M13+K14-L14 -> 0
A15: 12 | B15: 45820 | G15: =E15*F15 -> 0 | J15: =H15*I15 -> 0 | K15: =G15+J15 -> 0 | L15: 0 | M15: =M14+K15-L15 -> 0
A16: 13 | B16: 45821 | G16: =E16*F16 -> 0 | J16: =H16*I16 -> 0 | K16: =G16+J16 -> 0 | L16: =H16+K16 -> 0 | M16: =M15+K16-L16 -> 0
A17: 14 | B17: 45822 | G17: =E17*F17 -> 0 | J17: =H17*I17 -> 0 | K17: =G17+J17 -> 0 | L17: =H17+K17 -> 0 | M17: =M16+K17-L17 -> 0 | U17: =50000/107.9 -> 463.39203
A18: 15 | B18: 45823 | G18: =E18*F18 -> 0 | J18: =H18*I18 -> 0 | K18: =G18+J18 -> 0 | L18: =H18+K18 -> 0 | M18: =M17+K18-L18 -> 0 | R18: 185.36
A19: 16 | B19: 45824 | G19: =E19*F19 -> 0 | J19: =H19*I19 -> 0 | K19: =G19+J19 -> 0 | L19: =H19+K19 -> 0 | M19: =M18+K19-L19 -> 0 | R19: 92.68
A20: 17 | B20: 45825 | E20: 463.39 | F20: 107.9 | G20: =E20*F20 -> 49999.781 | J20: =H20*I20 -> 0 | K20: =G20+J20 -> 49999.781 | L20: =H20+K20 -> 49999.781 | M20: =M19+K20-L20 -> 0 | N20: BT | R20: =SUM(R18:R19) -> 278.04
A21: 18 | B21: 45826 | G21: =E21*F21 -> 0 | J21: =H21*I21 -> 0 | K21: =G21+J21 -> 0 | L21: =H21+K21 -> 0 | M21: =M20+K21-L21 -> 0
A22: 19 | B22: 45827 | G22: =E22*F22 -> 0 | J22: =H22*I22 -> 0 | K22: =G22+J22 -> 0 | L22: =H22+K22 -> 0 | M22: =M21+K22-L22 -> 0
A23: 20 | B23: 45828 | G23: =E23*F23 -> 0 | J23: =H23*I23 -> 0 | K23: =G23+J23 -> 0 | L23: =H23+K23 -> 0 | M23: =M22+K23-L23 -> 0
A24: 21 | B24: 45829 | E24: 278.04 | F24: 107.9 | G24: =E24*F24 -> 30000.516 | J24: =H24*I24 -> 0 | K24: =G24+J24 -> 30000.516 | L24: =H24+K24 -> 30000.516 | M24: =M23+K24-L24 -> 0 | N24: BT | U24: 139.2
A25: 22 | B25: 45830 | E25: 185.36 | F25: 107.9 | G25: =E25*F25 -> 20000.344 | J25: =H25*I25 -> 0 | K25: =G25+J25 -> 20000.344 | L25: =H25+K25 -> 20000.344 | M25: =M24+K25-L25 -> 0 | N25: BT | U25: 92.68
A26: 23 | B26: 45831 | G26: =E26*F26 -> 0 | J26: =H26*I26 -> 0 | K26: =G26+J26 -> 0 | L26: =+K26 -> 0 | M26: =M25+K26-L26 -> 0 | U26: =SUM(U24:U25) -> 231.88
A27: 24 | B27: 45832 | G27: =E27*F27 -> 0 | J27: =H27*I27 -> 0 | K27: =G27+J27 -> 0 | L27: =+K27 -> 0 | M27: =M26+K27-L27 -> 0
A28: 25 | B28: 45833 | E28: 231.88 | F28: 107.9 | G28: =E28*F28 -> 25019.852 | J28: =H28*I28 -> 0 | K28: =G28+J28 -> 25019.852 | L28: =+K28 -> 25019.852 | M28: =M27+K28-L28 -> 0 | N28: BT
A29: 26 | B29: 45834 | E29: 231.88 | F29: 107.9 | G29: =E29*F29 -> 25019.852 | J29: =H29*I29 -> 0 | K29: =G29+J29 -> 25019.852 | L29: =+K29 -> 25019.852 | M29: =M28+K29-L29 -> 0 | N29: BT
A30: 27 | B30: 45835 | G30: =E30*F30 -> 0 | J30: =H30*I30 -> 0 | K30: =G30+J30 -> 0 | L30: =+K30 -> 0 | M30: =M29+K30-L30 -> 0
A31: 28 | B31: 45836 | E31: 463.4 | F31: 107.9 | G31: =E31*F31 -> 50000.86 | J31: =H31*I31 -> 0 | K31: =G31+J31 -> 50000.86 | L31: =+K31 -> 50000.86 | M31: =M30+K31-L31 -> 0 | N31: BT
A32: 29 | B32: 45837 | G32: =E32*F32 -> 0 | J32: =H32*I32 -> 0 | K32: =G32+J32 -> 0 | L32: =+K32 -> 0 | M32: =M31+K32-L32 -> 0
A33: 30 | B33: 45838 | G33: =E33*F33 -> 0 | J33: =H33*I33 -> 0 | K33: =G33+J33 -> 0 | L33: =+K33 -> 0 | M33: =M32+K33-L33 -> 0
A34: 31 | G34: =E34*F34 -> 0 | J34: =H34*I34 -> 0 | K34: =G34+J34 -> 0 | L34: =+K34 -> 0 | M34: 0
E35: =SUM(E4:E34) -> 2085.65 | G35: =SUM(G4:G34) -> 225041.64 | H35: =SUM(H4:H34) -> 0 | J35: =SUM(J4:J34) -> 0 | K35: =SUM(K4:K34) -> 225041.64 | L35: =SUM(L4:L34) -> 225041.64

Sheet Dindi
A1: Akarapu Balakistamma Fillling
A2: S.No | B2: Date | C2: GRN No | D2: Ind no/Bill No | E2: Diesel (Lts) | F2: Price | G2: Amount | H2: Petrol (Lts) | I2: Price | J2: Amount | K2: Total amount | L2: Amount paid | M2: As on Date | N2: Remarks
A3: Opening Balance | M3: 0
A4: 1 | B4: 45809 | G4: =E4*F4 -> 0 | H4: 0 | I4: 0 | J4: =H4*I4 -> 0 | K4: =G4+J4 -> 0 | L4: =+K4 -> 0 | M4: 0
A5: 2 | B5: 45810 | G5: =E5*F5 -> 0 | H5: 0 | I5: 0 | J5: =H5*I5 -> 0 | K5: =G5+J5 -> 0 | L5: =+K5 -> 0 | M5: 0
A6: 3 | B6: 45811 | G6: =E6*F6 -> 0 | H6: 0 | I6: 0 | J6: =H6*I6 -> 0 | K6: =G6+J6 -> 0 | L6: =+K6 -> 0 | M6: 0
A7: 4 | B7: 45812 | G7: =E7*F7 -> 0 | H7: 0 | I7: 0 | J7: =H7*I7 -> 0 | K7: =G7+J7 -> 0 | L7: =+K7 -> 0 | M7: 0
A8: 5 | B8: 45813 | G8: =E8*F8 -> 0 | H8: 0 | I8: 0 | J8: =H8*I8 -> 0 | K8: =G8+J8 -> 0 | L8: =+K8 -> 0 | M8: 0
A9: 6 | B9: 45814 | G9: =E9*F9 -> 0 | H9: 0 | I9: 0 | J9: =H9*I9 -> 0 | K9: =G9+J9 -> 0 | L9: =+K9 -> 0 | M9: 0
A10: 7 | B10: 45815 | G10: =E10*F10 -> 0 | H10: 0 | I10: 0 | J10: =H10*I10 -> 0 | K10: =G10+J10 -> 0 | L10: =+K10 -> 0 | M10: 0
A11: 8 | B11: 45816 | G11: =E11*F11 -> 0 | H11: 0 | I11: 0 | J11: =H11*I11 -> 0 | K11: =G11+J11 -> 0 | L11: =+K11 -> 0 | M11: 0
A12: 9 | B12: 45817 | G12: =E12*F12 -> 0 | H12: 0 | I12: 0 | J12: =H12*I12 -> 0 | K12: =G12+J12 -> 0 | L12: =+K12 -> 0 | M12: 0
A13: 10 | B13: 45818 | G13: =E13*F13 -> 0 | H13: 0 | I13: 0 | J13: =H13*I13 -> 0 | K13: =G13+J13 -> 0 | L13: =+K13 -> 0 | M13: 0
A14: 11 | B14: 45819 | G14: =E14*F14 -> 0 | H14: 0 | I14: 0 | J14: =H14*I14 -> 0 | K14: =G14+J14 -> 0 | L14: =+K14 -> 0 | M14: 0
A15: 12 | B15: 45820 | G15: =E15*F15 -> 0 | H15: 0 | I15: 0 | J15: =H15*I15 -> 0 | K15: =G15+J15 -> 0 | L15: =+K15 -> 0 | M15: 0
... A27: 24 | B27: 45832 | G27: =E27*F27 -> 0 | H27: 0 | I27: 0 | J27: =H27*I27 -> 0 | K27: =G27+J27 -> 0 | L27: =+K27 -> 0 | M27: 0
A28: 25 | B28: 45833 | H28: 0 | I28: 0 | J28: =H28*I28 -> 0 | K28: =G28+J28 -> 0 | L28: =+K28 -> 0 | M28: 0
A29: 26 | B29: 45834 | G29: =E29*F29 -> 0 | H29: 0 | I29: 0 | J29: =H29*I29 -> 0 | K29: =G29+J29 -> 0 | L29: =+K29 -> 0 | M29: 0
A30: 27 | B30: 45835 | G30: =E30*F30 -> 0 | H30: 0 | I30: 0 | J30: =H30*I30 -> 0 | K30: =G30+J30 -> 0 | L30: =+K30 -> 0 | M30: 0
A31: 28 | B31: 45836 | G31: =E31*F31 -> 0 | H31: 0 | I31: 0 | J31: =H31*I31 -> 0 | K31: =G31+J31 -> 0 | L31: =+K31 -> 0 | M31: 0
A32: 29 | G32: =E32*F32 -> 0 | H32: 0 | I32: 0 | J32: =H32*I32 -> 0 | K32: =G32+J32 -> 0 | L32: =+K32 -> 0 | M32: 0
A33: 30 | G33: =E33*F33 -> 0 | H33: 0 | I33: 0 | J33: =H33*I33 -> 0 | K33: =G33+J33 -> 0 | L33: =+K33 -> 0 | M33: 0
A34: 31 | G34: =E34*F34 -> 0 | H34: 0 | I34: 0 | J34: =H34*I34 -> 0 | K34: =G34+J34 -> 0 | L34: =+K34 -> 0 | M34: 0
E35: =SUM(E4:E34) -> 0 | G35: =SUM(G4:G34) -> 0 | H35: =SUM(H4:H34) -> 0 | J35: =SUM(J4:J34) -> 0 | K35: =SUM(K4:K34) -> 0 | L35: =SUM(L4:L34) -> 0

Sheet Amalapuram
A2: S.No | B2: Date | C2: GRN No | D2: Ind no/Bill No | E2: Diesel (Lts) | F2: Price | G2: Amount | H2: Petrol (Lts) | I2: Price | J2: Amount | K2: Total amount | L2: Amount paid | M2: As on Date | N2: Remarks
A3: Opening Balance | M3: 0
A4: 1 | B4: 01.06.2026 | C4: Sri Bhimeswara Agencies | D4: Amalapuram | E4: 45.03 | F4: 105.29 | G4: 4741.21 | H4: 0 | J4: 0 | K4: =G4+J4 -> 4741.21 | L4: =+K4 -> 4741.21 | M4: =+M3+K4-L4 -> 0 | N4: BPCL
A5: 2 | B5: 01.06.2026 | C5: Satya Siva Durga Agencie | D5: Chebrolu | E5: 56.11 | F5: 105.21 | G5: 5903.33 | H5: 0 | J5: 0 | K5: =G5+J5 -> 5903.33 | L5: =+K5 -> 5903.33 | M5: =+M4+K5-L5 -> 0 | N5: BPCL
A6: 3 | B6: 01.06.2026 | C6: Satya Siva Durga Agencie | D6: Chebrolu | E6: 56.36 | F6: 105.21 | G6: 5929.64 | H6: 0 | J6: 0 | K6: =G6+J6 -> 5929.64 | L6: =+K6 -> 5929.64 | M6: =+M5+K6-L6 -> 0
A7: 4 | B7: 01.06.2026 | C7: BP- Kovvur Bharat petro | D7: Kovvur | E7: 90 | F7: 104.7 | G7: 9423 | H7: 0 | J7: 0 | K7: =G7+J7 -> 9423 | L7: =+K7 -> 9423 | M7: =+M6+K7-L7 -> 0
A8: 5 | B8: 01.06.2026 | C8: Sri Balaji Agencies | D8: Kakinada | E8: 0 | G8: 0 | H8: 5 | I8: 117.98 | J8: 589.9 | K8: =G8+J8 -> 589.9 | L8: =+K8 -> 589.9 | M8: =+M7+K8-L8 -> 0
A9: 6 | B9: 02.06.2026 | C9: SARDAR SINGH SAHNI | D9: GANNAVARAM | E9: 46.47 | F9: 105.22 | G9: 4889.57 | H9: 0 | J9: 0 | K9: =G9+J9 -> 4889.57 | L9: =+K9 -> 4889.57 | M9: =+M8+K9-L9 -> 0 | N9: BPCL
A10: 7 | B10: 02.06.2026 | C10: BP Kovvur | D10: kovvur | E10: 90 | F10: 104.7 | G10: 9423 | H10: 0 | J10: 0 | K10: =G10+J10 -> 9423 | L10: =+K10 -> 9423 | M10: =+M9+K10-L10 -> 0
A11: 8 | B11: 02.06.2026 | C11: BP Kovvur | D11: kovvur | E11: 0 | G11: 0 | H11: 5 | I11: 116.99 | J11: 584.95 | K11: =G11+J11 -> 584.95 | L11: =+K11 -> 584.95 | M11: =+M10+K11-L11 -> 0 | N11: BPCL
A12: 9 | B12: 02.06.2026 | C12: Satya Siva Durga Agencie | D12: Chebrolu | E12: 50 | F12: 105.21 | G12: 5260.5 | H12: 0 | J12: 0 | K12: =G12+J12 -> 5260.5 | L12: =+K12 -> 5260.5 | M12: =+M11+K12-L12 -> 0 | N12: BPCL
A13: 10 | B13: 02.06.2026 | C13: BP -Kakinada | D13: Kakinada | E13: 48.16 | F13: 105.59 | G13: 5085.21 | H13: 0 | J13: 0 | K13: =G13+J13 -> 5085.21 | L13: =+K13 -> 5085.21 | M13: =+M12+K13-L13 -> 0
A14: 11 | B14: 03.06.2026 | C14: Satya Siva Durga Agencie | D14: Chebrolu | E14: 100 | F14: 105.21 | G14: 10521 | H14: 0 | J14: 0 | K14: =G14+J14 -> 10521 | L14: =+K14 -> 10521 | M14: =+M13+K14-L14 -> 0 | N14: BPCL
A15: 12 | B15: 03.06.2026 | C15: Satya Siva Durga Agencie | D15: Chebrolu | E15: 50 | F15: 105.21 | G15: 5260.5 | H15: 0 | J15: 0 | K15: =G15+J15 -> 5260.5 | L15: =+K15 -> 5260.5 | M15: =+M14+K15-L15 -> 0 | N15: BPCL
A16: 13 | B16: 03.06.2026 | C16: ARM PETRO FILLING STATION | D16: NIDAMOLU | E16: 36.59 | F16: 105.52 | G16: 3860.98 | H16: 0 | J16: 0 | K16: =G16+J16 -> 3860.98 | L16: =+K16 -> 3860.98 | M16: =+M15+K16-L16 -> 0
A17: 14 | B17: 03.06.2026 | C17: SRI BHIMESWARA AGENCIES | D17: AMALAPURAM | E17: 42.09 | F17: 105.29 | G17: 4431.66 | H17: 0 | J17: 0 | K17: =G17+J17 -> 4431.66 | L17: =+K17 -> 4431.66 | M17: =+M16+K17-L17 -> 0 | N17: BPCL
A18: 15 | B18: 03.06.2026 | C18: BP - KOVVUR | D18: KOVVUR | E18: 9.82 | F18: 104.7 | G18: 1028.15 | H18: 0 | J18: 0 | K18: =G18+J18 -> 1028.15 | L18: =+K18 -> 1028.15 | M18: =+M17+K18-L18 -> 0 | N18: BPCL
A19: 16 | B19: 04.06.2026 | C19: BP - LALACHERUVU | D19: RAJAMUNDRY | E19: 47.42 | F19: 104.62 | G19: 4961.08 | H19: 0 | J19: 0 | K19: =G19+J19 -> 4961.08 | L19: =+K19 -> 4961.08 | M19: =+M18+K19-L19 -> 0 | N19: BPCL
A20: 17 | B20: 04.06.2026 | C20: JVVR FILLING STATION | D20: PITHAAPURAM | E20: 53.63 | F20: 105.35 | G20: 5649.92 | H20: 0 | J20: 0 | K20: =G20+J20 -> 5649.92 | L20: =+K20 -> 5649.92 | M20: =+M19+K20-L20 -> 0 | N20: BPCL
A21: 18 | B21: 04.06.2026 | C21: Sri Bhimeswara Agencies | D21: AMALAPURAM | G21: 565.75 | H21: 4.81 | I21: 117.62 | J21: 565.75 | K21: =G21+J21 -> 1131.5 | L21: =+K21 -> 1131.5 | M21: =+M20+K21-L21 -> 0 | N21: IOCL
A22: 19 | B22: 04.06.2026 | C22: Satya Siva Durga Agencie | D22: Chebrolu | E22: 70 | F22: 105.21 | G22: 7364.7 | H22: 0 | J22: 0 | K22: =G22+J22 -> 7364.7 | L22: =+K22 -> 7364.7 | M22: =+M21+K22-L22 -> 0 | N22: BPCL
A23: 20 | B23: 04.06.2026 | C23: Satya Siva Durga Agencie | D23: Chebrolu | E23: 70 | F23: 105.21 | G23: 7364.7 | H23: 0 | J23: 0 | K23: =G23+J23 -> 7364.7 | L23: =+K23 -> 7364.7 | M23: =+M22+K23-L23 -> 0
A24: 21 | B24: 04.06.2026 | C24: Satya Siva Durga Agencie | D24: Chebrolu | E24: 60 | F24: 105.21 | G24: 6312.6 | H24: 0 | J24: 0 | K24: =G24+J24 -> 6312.6 | L24: =+K24 -> 6312.6 | M24: =+M23+K24-L24 -> 0
A25: 22 | B25: 05.06.2026 | C25: Vijay balaji Agencise | D25: Yanam | E25: 31.91 | F25: 94.03 | G25: =E25*F25 -> 3000.4973 | K25: =G25+J25 -> 3000.4973 | L25: =+K25 -> 3000.4973 | M25: =+M24+K25-L25 -> 0
A26: 23 | B26: 05.06.2026 | C26: Satya chandra Petrol Fill | D26: Madiki | E26: 31.9 | F26: 104.72 | G26: =E26*F26 -> 3340.568 | K26: =G26+J26 -> 3340.568 | L26: =+K26 -> 3340.568 | M26: =+M25+K26-L26 -> 0 | N26: IOCL
A27: 24 | B27: 06.06.2026 | C27: Sri balaji agencies | D27: Kakinada | E27: 28.41 | F27: 105.59 | G27: 2999.81 | H27: 0 | J27: 0 | K27: =G27+J27 -> 2999.81 | L27: =+K27 -> 2999.81 | M27: =+M26+K27-L27 -> 0 | N27: BPCL
A28: 25 | B28: 06.06.2026 | C28: Stya siva durga agencies | D28: Chebrolu | E28: 0 | F28: 0 | G28: 0 | H28: 4 | I28: 117.58 | J28: 470.32 | K28: =G28+J28 -> 470.32 | L28: =+K28 -> 470.32 | M28: =+M27+K28-L28 -> 0
A29: 26 | B29: 06.06.2026 | C29: Stya siva durga agencies | D29: Chebrolu | E29: 60 | F29: 105.21 | G29: 6312.6 | H29: 0 | J29: 0 | K29: =G29+J29 -> 6312.6 | L29: =+K29 -> 6312.6 | M29: =+M28+K29-L29 -> 0
A30: 27 | B30: 06.06.2026 | C30: Stya siva durga agencies | D30: Chebrolu | E30: 100.02 | F30: 105.21 | G30: 10523.1 | H30: 0 | J30: 0 | K30: =G30+J30 -> 10523.1 | L30: =+K30 -> 10523.1 | M30: =+M29+K30-L30 -> 0
A31: 28 | B31: 06.06.2026 | C31: BP - LALACHERUVU | D31: RAJAMUNDRY | E31: 0 | F31: 0 | G31: 0 | H31: 5 | I31: 116.9 | J31: 584.5 | K31: =G31+J31 -> 584.5 | L31: =+K31 -> 584.5 | M31: =+M30+K31-L31 -> 0
A32: 29 | B32: 06.06.2026 | C32: BP-KAKINADA | D32: Kakinada | E32: 0 | F32: 0 | G32: 0 | H32: 5 | I32: 117.98 | J32: 589.9 | K32: =G32+J32 -> 589.9 | L32: =+K32 -> 589.9 | M32: =+M31+K32-L32 -> 0
A33: 30 | B33: 06.06.2026 | C33: JVVR FILLING STATION | D33: PITHAAPURAM | E33: 50 | F33: 105.35 | G33: 5267.5 | H33: 0 | J33: 0 | K33: =G33+J33 -> 5267.5 | L33: =+K33 -> 5267.5 | M33: =+M32+K33-L33 -> 0
A34: 30 | B34: 06.06.2026 | C34: Sri balaji agencies | D34: Kakinada | E34: 0 | F34: 0 | G34: 0 | H34: 4 | I34: 117.98 | J34: 471.92 | K34: =G34+J34 -> 471.92 | L34: =+K34 -> 471.92 | M34: =+M33+K34-L34 -> 0
A35: 31 | B35: 06.06.2026 | C35: BP - KOVVUR | D35: Kovvur | E35: 0 | G35: 0 | H35: 5 | I35: 116.99 | J35: 584.95 | K35: =G35+J35 -> 584.95 | L35: =+K35 -> 584.95 | M35: =+M34+K35-L35 -> 0
A36: 32 | B36: 07.06.2026 | C36: BP - KOVVUR | D36: Kovvur | E36: 90 | F36: 104.7 | G36: 9423 | H36: 0 | J36: 0 | K36: =G36+J36 -> 9423 | L36: =+K36 -> 9423 | M36: =+M35+K36-L36 -> 0
A37: 33 | B37: 07.06.2026 | C37: BP - KOVVUR | D37: Kovvur | E37: 10 | F37: 104.7 | G37: 1047 | H37: 0 | J37: 0 | K37: =G37+J37 -> 1047 | L37: =+K37 -> 1047 | M37: =+M36+K37-L37 -> 0
B38: 07.06.2026 | C38: BP-KAKINADA | D38: Kakinada | E38: 0 | G38: 0 | H38: 5 | I38: 117.98 | J38: 589.9 | K38: =G38+J38 -> 589.9 | L38: =+K38 -> 589.9 | M38: =+M37+K38-L38 -> 0
B39: 07.06.2026 | C39: SRI BAlaji Agencies | D39: Kakinada | E39: 0 | G39: 0 | H39: 5 | I39: 117.98 | J39: 589.9 | K39: =G39+J39 -> 589.9 | L39: =+K39 -> 589.9 | M39: =+M38+K39-L39 -> 0
B40: 07.06.2026 | C40: Stya siva durga agencies | D40: Chebrolu | E40: 20 | F40: 105.21 | G40: 2104.2 | H40: 0 | J40: 0 | K40: =G40+J40 -> 2104.2 | L40: =+K40 -> 2104.2 | M40: =+M39+K40-L40 -> 0
B41: 07.06.2026 | C41: Stya siva durga agencies | D41: Chebrolu | E41: 61.78 | F41: 105.21 | G41: 6499.87 | H41: 0 | J41: 0 | K41: =G41+J41 -> 6499.87 | L41: =+K41 -> 6499.87 | M41: =+M40+K41-L41 -> 0
B42: 08.06.2026 | C42: BP-QUARRY MARKET | D42: RAJAMUNDRY | E42: 46.47 | F42: 104.62 | G42: 4861.69 | H42: 0 | J42: 0 | K42: =G42+J42 -> 4861.69 | L42: =+K42 -> 4861.69 | M42: =+M41+K42-L42 -> 0
B43: 08.06.2026 | C43: SRI BHIMESWARA AGENCIES | D43: Amalapuram | E43: 45 | F43: 105.29 | G43: 4738.05 | H43: 0 | J43: 0 | K43: =G43+J43 -> 4738.05 | L43: =+K43 -> 4738.05 | M43: =+M42+K43-L43 -> 0
B44: 08.06.2026 | C44: Satya Siva Durga Agencie | D44: chebrolu | E44: 70 | F44: 105.21 | G44: 7364.7 | H44: 0 | J44: 0 | K44: =G44+J44 -> 7364.7 | L44: =+K44 -> 7364.7 | M44: =+M43+K44-L44 -> 0
B45: 08.06.2026 | C45: Satya Siva Durga Agencie | D45: chebrolu | E45: 70 | F45: 105.21 | G45: 7364.7 | H45: 0 | J45: 0 | K45: =G45+J45 -> 7364.7 | L45: =+K45 -> 7364.7 | M45: =+M44+K45-L45 -> 0
B46: 08.06.2026 | C46: Satya Siva Durga Agencie | D46: chebrolu | E46: 70 | F46: 105.21 | G46: 7364.7 | H46: 0 | J46: 0 | K46: =G46+J46 -> 7364.7 | L46: =+K46 -> 7364.7 | M46: =+M45+K46-L46 -> 0
B47: 08.06.2026 | C47: Sri venkateswara enterprises | D47: yanam | E47: 21.25 | F47: 94.08 | G47: 1999.2 | H47: 0 | J47: 0 | K47: =G47+J47 -> 1999.2 | L47: =+K47 -> 1999.2 | M47: =+M46+K47-L47 -> 0
B48: 09.06.2026 | C48: Satya Siva Durga Agencie | D48: Chebrolu | E48: 30 | F48: 105.21 | G48: =E48*F48 -> 3156.3 | K48: =G48+J48 -> 3156.3 | L48: =+K48 -> 3156.3 | M48: =+M47+K48-L48 -> 0
B49: 09.06.2026 | C49: Satya Siva Durga Agencie | D49: Chebrolu | E49: 20 | F49: 105.21 | G49: =E49*F49 -> 2104.2 | K49: =G49+J49 -> 2104.2 | L49: =+K49 -> 2104.2 | M49: =+M48+K49-L49 -> 0
B50: 09.06.2026 | C50: Satya Siva Durga Agencie | D50: Chebrolu | E50: 5 | F50: 117.58 | G50: =E50*F50 -> 587.9 | K50: =G50+J50 -> 587.9 | L50: =+K50 -> 587.9 | M50: =+M49+K50-L50 -> 0
B51: 09.06.2026 | C51: JVVR FILLING STATION | D51: PITHAAPURAM | E51: 48.25 | F51: 105.35 | G51: =E51*F51 -> 5083.1375 | K51: =G51+J51 -> 5083.1375 | L51: =+K51 -> 5083.1375 | M51: =+M50+K51-L51 -> 0
B52: 09.06.2026 | C52: JVVR FILLING STATION | D52: PITHAAPURAM | E52: 5 | F52: 117.72 | G52: =E52*F52 -> 588.6 | K52: =G52+J52 -> 588.6 | L52: =+K52 -> 588.6 | M52: =+M51+K52-L52 -> 0
B53: 10.06.2026 | C53: SRI SATYA DATTHA APARNA AGENCIES BPCL | E53: 42.81 | F53: 105.16 | G53: 4501.9 | H53: 0 | J53: 0 | K53: =G53+J53 -> 4501.9 | L53: =+K53 -> 4501.9 | M53: =+M52+K53-L53 -> 0
B54: 10.06.2026 | C54: Satya Siva Durga Agencie | D54: Chebrolu | E54: 37.28 | F54: 105.21 | G54: 3922.23 | H54: 0 | J54: 0 | K54: =G54+J54 -> 3922.23 | L54: =+K54 -> 3922.23 | M54: =+M53+K54-L54 -> 0
B55: 10.06.2026 | C55: JVVR FILLING STATION | D55: PITHAAPURAM | E55: 34.11 | F55: 105.35 | G55: 3593.49 | H55: 0 | J55: 0 | K55: =G55+J55 -> 3593.49 | L55: =+K55 -> 3593.49 | M55: =+M54+K55-L55 -> 0
B56: 10.06.2026 | C56: SRI BHIMESWARA AGENCIES | D56: Amalapuram | E56: 0 | G56: 0 | H56: 6.04 | I56: 117.62 | J56: 710.42 | K56: =G56+J56 -> 710.42 | L56: =+K56 -> 710.42 | M56: =+M55+K56-L56 -> 0
B57: 10.06.2026 | C57: Satya Siva Durga Agencie | D57: Chebrolu | E57: 50 | F57: 105.21 | G57: 5260.5 | H57: 0 | J57: 0 | K57: =G57+J57 -> 5260.5 | L57: =+K57 -> 5260.5 | M57: =+M56+K57-L57 -> 0
B58: 10.06.2026 | C58: Satya Siva Durga Agencie | D58: Chebrolu | E58: 100 | F58: 105.21 | G58: 10521 | H58: 0 | J58: 0 | K58: =G58+J58 -> 10521 | L58: =+K58 -> 10521 | M58: =+M57+K58-L58 -> 0
B59: 10.06.2026 | C59: Satya Siva Durga Agencie | D59: Chebrolu | E59: 60 | F59: 105.21 | G59: 6312.6 | H59: 0 | J59: 0 | K59: =G59+J59 -> 6312.6 | L59: =+K59 -> 6312.6 | M59: =+M58+K59-L59 -> 0
B60: 10.06.2026 | C60: Satya Siva Durga Agencie | D60: Chebrolu | E60: 50 | F60: 105.21 | G60: 5260.5 | H60: 0 | J60: 0 | K60: =G60+J60 -> 5260.5 | L60: =+K60 -> 5260.5 | M60: =+M59+K60-L60 -> 0
B61: 10.06.2026 | C61: BP - Kakinada | D61: Kakinada | E61: 0 | F61: 0 | G61: 0 | H61: 8.48 | I61: 117.48 | J61: 996.23 | K61: =G61+J61 -> 996.23 | L61: =+K61 -> 996.23 | M61: =+M60+K61-L61 -> 0
B62: 10.06.2026 | C62: Sai Ganesh Aencies | D62: mummidivaram | E62: 9.49 | F62: 105.34 | G62: 999.68 | H62: 0 | I62: 0 | J62: 0 | K62: =G62+J62 -> 999.68 | L62: =+K62 -> 999.68 | M62: =+M61+K62-L62 -> 0
B63: 11.06.2026 | C63: SATYARAGHAVA FUELS | D63: KOTHAPETA | E63: 28 | F63: 104.96 | G63: 2938.88 | H63: 0 | I63: 0 | J63: 0 | K63: =G63+J63 -> 2938.88 | L63: =+K63 -> 2938.88 | M63: =+M62+K63-L63 -> 0
B64: 11.06.2026 | C64: SREE S.V. Agencies | D64: peddapuram | E64: 0 | G64: 0 | H64: 7 | I64: 117.06 | J64: 819.42 | K64: =G64+J64 -> 819.42 | L64: =+K64 -> 819.42 | M64: =+M63+K64-L64 -> 0
B65: 11.06.2026 | C65: Sri balaji agencies | D65: Kakinada | E65: 0 | G65: 0 | H65: 5 | I65: 177.98 | J65: 889.9 | K65: =G65+J65 -> 889.9 | L65: =+K65 -> 889.9 | M65: =+M64+K65-L65 -> 0
B66: 11.06.2026 | C66: JVVR FILLING STATION | D66: PITHAAPURAM | E66: 44.62 | F66: 105.35 | G66: 4700.72 | H66: 0 | J66: 0 | K66: =G66+J66 -> 4700.72 | L66: =+K66 -> 4700.72 | M66: =+M65+K66-L66 -> 0
B67: 11.06.2026 | C67: JVVR FILLING STATION | D67: PITHAAPURAM | E67: 0 | G67: 0 | H67: 5 | I67: 117.72 | J67: 588.6 | K67: =G67+J67 -> 588.6 | L67: =+K67 -> 588.6 | M67: =+M66+K67-L67 -> 0
B68: 11.06.2026 | C68: BP - LALACHERUVU | D68: RAJAMUNDRY | E68: 0 | G68: 0 | H68: 5 | I68: 116.9 | J68: 584.5 | K68: =G68+J68 -> 584.5 | L68: =+K68 -> 584.5 | M68: =+M67+K68-L68 -> 0
B69: 11.06.2026 | C69: SRI MURALI KRISHNA | D69: KHAMMAM | E69: 80 | F69: 103.88 | G69: 8310.4 | H69: 0 | J69: 0 | K69: =G69+J69 -> 8310.4 | L69: =+K69 -> 8310.4 | M69: =+M68+K69-L69 -> 0
B70: 11.06.2026 | C70: Satya Siva Durga Agencie | D70: Chebrolu | E70: 70 | F70: 105.21 | G70: 7364.7 | H70: 0 | J70: 0 | K70: =G70+J70 -> 7364.7 | L70: =+K70 -> 7364.7 | M70: =+M69+K70-L70 -> 0
B71: 12.06.2026 | C71: BP - KOVVUR | D71: KOVVUR | E71: 0 | G71: 0 | H71: 5 | I71: 116.99 | J71: 584.95 | K71: =G71+J71 -> 584.95 | L71: =+K71 -> 584.95 | M71: =+M70+K71-L71 -> 0
B72: 12.06.2026 | C72: BP - KOVVUR | D72: KOVVUR | E72: 10 | F72: 104.7 | G72: 1047 | H72: 0 | J72: 0 | K72: =G72+J72 -> 1047 | L72: =+K72 -> 1047 | M72: =+M71+K72-L72 -> 0
B73: 12.06.2026 | C73: SRI BHIMESWARA AGENCIES | D73: AMALAPURAM | E73: 47.16 | F73: 105.29 | G73: 4965.48 | H73: 0 | J73: 0 | K73: =G73+J73 -> 4965.48 | L73: =+K73 -> 4965.48 | M73: =+M72+K73-L73 -> 0
B74: 12.06.2026 | C74: JVVR FILLING STATION | D74: PITHAAPURAM | E74: 45.95 | F74: 105.35 | G74: 4840.83 | H74: 0 | J74: 0 | K74: =G74+J74 -> 4840.83 | L74: =+K74 -> 4840.83 | M74: =+M73+K74-L74 -> 0
B75: 12.06.2026 | C75: JVVR FILLING STATION | D75: PITHAAPURAM | E75: 60 | F75: 105.35 | G75: 6321 | H75: 0 | J75: 0 | K75: =G75+J75 -> 6321 | L75: =+K75 -> 6321 | M75: =+M74+K75-L75 -> 0
B76: 12.06.2026 | C76: JVVR FILLING STATION | D76: PITHAAPURAM | E76: 60 | F76: 105.35 | G76: 6321 | H76: 0 | J76: 0 | K76: =G76+J76 -> 6321 | L76: =+K76 -> 6321 | M76: =+M75+K76-L76 -> 0
B77: 12.06.2026 | C77: SATYA SIVA DURGA AGENCIE | D77: Chebrolu | E77: 60 | F77: 105.21 | G77: 6312.6 | H77: 0 | J77: 0 | K77: =G77+J77 -> 6312.6 | L77: =+K77 -> 6312.6 | M77: =+M76+K77-L77 -> 0
B78: 12.06.2026 | C78: Sri Balaji Agencies | D78: Kakinada | E78: 30 | F78: 105.59 | G78: 3167.7 | H78: 0 | J78: 0 | K78: =G78+J78 -> 3167.7 | L78: =+K78 -> 3167.7 | M78: =+M77+K78-L78 -> 0
B79: 12.06.2026 | C79: SRI RADHA PETROL FILLING | D79: mummidivaram | E79: 25 | F79: 104.92 | G79: 2623 | H79: 0 | J79: 0 | K79: =G79+J79 -> 2623 | L79: =+K79 -> 2623 | M79: =+M78+K79-L79 -> 0
B80: 12.06.2026 | C80: SRI RADHA PETROL FILLING | D80: mummidivaram | E80: 29.53 | F80: 104.92 | G80: 3098.39 | H80: 0 | J80: 0 | K80: =G80+J80 -> 3098.39 | L80: =+K80 -> 3098.39 | M80: =+M79+K80-L80 -> 0
B81: 13.06.2026 | C81: BP - KOVVUR | D81: KOVVUR | E81: 20 | F81: 104.7 | G81: 2094 | H81: 0 | J81: 0 | K81: =G81+J81 -> 2094 | L81: =+K81 -> 2094 | M81: =+M80+K81-L81 -> 0
B82: 13.06.2026 | C82: BP - KOVVUR | D82: KOVVUR | E82: 0 | G82: 0 | H82: 2 | I82: 116.99 | J82: 233.98 | K82: =G82+J82 -> 233.98 | L82: =+K82 -> 233.98 | M82: =+M81+K82-L82 -> 0
B83: 13.06.2026 | C83: BP - Kakinada | D83: KIKINADA | E83: 0 | G83: 0 | H83: 5 | I83: 117.98 | J83: 589.9 | K83: =G83+J83 -> 589.9 | L83: =+K83 -> 589.9 | M83: =+M82+K83-L83 -> 0
B84: 13.06.2026 | C84: SATYA SIVA DURGA AGENCIE | D84: CHEBROLU | E84: 100 | F84: 105.21 | G84: 10521 | H84: 0 | J84: 0 | K84: =G84+J84 -> 10521 | L84: =+K84 -> 10521 | M84: =+M83+K84-L84 -> 0
B85: 13.06.2026 | C85: SATYA SIVA DURGA AGENCIE | D85: CHEBROLU | E85: 70 | F85: 105.21 | G85: 7364.7 | H85: 0 | J85: 0 | K85: =G85+J85 -> 7364.7 | L85: =+K85 -> 7364.7 | M85: =+M84+K85-L85 -> 0
B86: 13.06.2026 | C86: SATYA SIVA DURGA AGENCIE | D86: CHEBROLU | E86: 40 | F86: 105.21 | G86: 4208.4 | H86: 0 | J86: 0 | K86: =G86+J86 -> 4208.4 | L86: =+K86 -> 4208.4 | M86: =+M85+K86-L86 -> 0
B87: 14.06.2026 | C87: SRI RADHA PETROL FILLING | D87: mummidivaram | E87: 25 | F87: 104.92 | G87: 2623 | H87: 0 | J87: 0 | K87: =G87+J87 -> 2623 | L87: =+K87 -> 2623 | M87: =+M86+K87-L87 -> 0
B88: 14.06.2026 | C88: JVVR FILLING STATION | D88: PITHAAPURAM | E88: 60 | F88: 105.35 | G88: 6321 | H88: 0 | J88: 0 | K88: =G88+J88 -> 6321 | L88: =+K88 -> 6321 | M88: =+M87+K88-L88 -> 0
B89: 14.06.2026 | C89: SATYA SIVA DURGA AGENCIES | D89: Chebrolu | E89: 80 | F89: 105.2 | G89: 8416 | H89: 0 | J89: 0 | K89: =G89+J89 -> 8416 | L89: =+K89 -> 8416 | M89: =+M88+K89-L89 -> 0
B90: 14.06.2026 | C90: JVVR FILLING STATION | D90: PITHAAPURAM | E90: 37.5 | F90: 105.35 | G90: 3950.63 | H90: 0 | J90: 0 | K90: =G90+J90 -> 3950.63 | L90: =+K90 -> 3950.63 | M90: =+M89+K90-L90 -> 0
B91: 14.06.2026 | C91: SATYA SIVA DURGA AGENCIES | D91: Chebrolu | G91: 0 | H91: 5 | I91: 117.58 | J91: 587.9 | K91: =G91+J91 -> 587.9 | L91: =+K91 -> 587.9 | M91: =+M90+K91-L91 -> 0
B92: 14.06.2026 | C92: SRI SATYA ENTERPRISES | D92: YANAM | G92: 0 | H92: 6.71 | I92: 104.8 | J92: 703.21 | K92: =G92+J92 -> 703.21 | L92: =+K92 -> 703.21 | M92: =+M91+K92-L92 -> 0
B93: 14.06.2026 | C93: BP -QUARRY MARKET | D93: RAJAMUNDRY | E93: 34.49 | F93: 104.62 | G93: 3608.34 | H93: 0 | J93: 0 | K93: =G93+J93 -> 3608.34 | L93: =+K93 -> 3608.34 | M93: =+M92+K93-L93 -> 0
B94: 14.06.2026 | C94: B.P RAJANAGARAM | D94: RAJAMUNDRY | E94: 45.77 | F94: 104.51 | G94: 4783.42 | H94: 0 | J94: 0 | K94: =G94+J94 -> 4783.42 | L94: =+K94 -> 4783.42 | M94: =+M93+K94-L94 -> 0
B95: 15.06.2026 | C95: SRI RAMAKRISHNA ENERGY | D95: KOVVURU | E95: 30 | F95: 104.65 | G95: 3139.5 | H95: 0 | J95: 0 | K95: =G95+J95 -> 3139.5 | L95: =+K95 -> 3139.5 | M95: =+M94+K95-L95 -> 0
B96: 15.06.2026 | C96: SRI RAMAKRISHNA ENERGY | D96: KOVVURU | E96: 30 | F96: 104.64 | G96: 3139.2 | H96: 0 | J96: 0 | K96: =G96+J96 -> 3139.2 | L96: =+K96 -> 3139.2 | M96: =+M95+K96-L96 -> 0
B97: 15.06.2026 | C97: SRI RAMAKRISHNA ENERGY | D97: KOVVURU | G97: 0 | H97: 5.04 | I97: 116.96 | J97: 589.48 | K97: =G97+J97 -> 589.48 | L97: =+K97 -> 589.48 | M97: =+M96+K97-L97 -> 0
B98: 15.06.2026 | C98: SRI BALAJI AGENCIES | D98: Kakinada | E98: 45.04 | F98: 105.59 | G98: 4755.77 | H98: 0 | J98: 0 | K98: =G98+J98 -> 4755.77 | L98: =+K98 -> 4755.77 | M98: =+M97+K98-L98 -> 0
B99: 15.06.2026 | C99: SRI BALAJI AGENCIES | D99: Kakinada | E99: 44.86 | F99: 105.59 | G99: 4736.77 | H99: 0 | J99: 0 | K99: =G99+J99 -> 4736.77 | L99: =+K99 -> 4736.77 | M99: =+M98+K99-L99 -> 0
B100: 15.06.2026 | C100: SATYA SIVA DURGA AGENCIES | D100: CHEBROLU | E100: 80 | F100: 105.21 | G100: 8416.8 | H100: 0 | J100: 0 | K100: =G100+J100 -> 8416.8 | L100: =+K100 -> 8416.8 | M100: =+M99+K100-L100 -> 0
B101: 16.06.2026 | C101: JVVR FILLING STATION | D101: PITHAAPURAM | E101: 70 | F101: 105.35 | G101: 7374.5 | H101: 0 | J101: 0 | K101: =G101+J101 -> 7374.5 | L101: =+K101 -> 7374.5 | M101: =+M100+K101-L101 -> 0
...

Sheet Madana palli
A2: S.No | B2: Date | C2: GRN No | D2: Ind no/Bill No | E2: Diesel (Lts) | F2: Price | G2: Amount | H2: Petrol (Lts) | I2: Price | J2: Amount | K2: Total amount | L2: Amount paid | M2: As on Date | N2: Remarks
A3: Opening Balance | M3: 0
A4: 1 | B4: 46174 | G4: =E4*F4 -> 0 | H4: 9.49 | I4: 105.32 | J4: =H4*I4 -> 999.4868 | K4: =G4+J4 -> 999.4868 | L4: =+K4 -> 999.4868 | M4: 0
B5: 46174 | H5: 3.4 | I5: 117.66 | J5: =H5*I5 -> 400.044 | K5: =G5+J5 -> 400.044 | L5: =+K5 -> 400.044
A6: 2 | B6: 46175 | G6: =E6*F6 -> 0 | J6: =H6*I6 -> 0 | K6: =G6+J6 -> 0 | L6: =+K6 -> 0 | M6: 0 | N6: IOCL
A7: 3 | B7: 46176 | G7: =E7*F7 -> 0 | J7: =H7*I7 -> 0 | K7: =G7+J7 -> 0 | L7: =+K7 -> 0 | M7: 0
A8: 4 | B8: 46177 | G8: =E8*F8 -> 0 | J8: =H8*I8 -> 0 | K8: =G8+J8 -> 0 | L8: =+K8 -> 0 | M8: 0
A9: 5 | B9: 46178 | G9: =E9*F9 -> 0 | J9: =H9*I9 -> 0 | K9: =G9+J9 -> 0 | L9: =+K9 -> 0 | M9: 0
A10: 6 | B10: 46179 | G10: =E10*F10 -> 0 | J10: =H10*I10 -> 0 | K10: =G10+J10 -> 0 | L10: =+K10 -> 0 | M10: 0 | N10: HPCL
A11: 7 | B11: 46180 | G11: =E11*F11 -> 0 | J11: =H11*I11 -> 0 | K11: =G11+J11 -> 0 | L11: =+K11 -> 0 | M11: 0 | O11: 169.99
A12: 8 | B12: 46181 | G12: =E12*F12 -> 0 | J12: =H12*I12 -> 0 | K12: =G12+J12 -> 0 | L12: =+K12 -> 0 | M12: 0 | O12: 80
A13: 9 | B13: 46182 | G13: =E13*F13 -> 0 | J13: =H13*I13 -> 0 | K13: =G13+J13 -> 0 | L13: =+K13 -> 0 | M13: 0 | O13: =SUM(O11:O12) -> 249.99 | P13: 97.76 | Q13: =O13*P13 -> 24439.022
A14: 10 | B14: 46183 | G14: =E14*F14 -> 0 | J14: =H14*I14 -> 0 | K14: =G14+J14 -> 0 | L14: =+K14 -> 0 | M14: 0
A15: 11 | B15: 46184 | G15: =E15*F15 -> 0 | J15: =H15*I15 -> 0 | K15: =G15+J15 -> 0 | L15: =+K15 -> 0 | M15: 0
A16: 12 | B16: 46185 | G16: =E16*F16 -> 0 | J16: =H16*I16 -> 0 | K16: =G16+J16 -> 0 | L16: =+K16 -> 0 | M16: 0 | P16: 7820.8
A17: 13 | B17: 46186 | G17: =E17*F17 -> 0 | J17: =H17*I17 -> 0 | K17: =G17+J17 -> 0 | L17: =+K17 -> 0 | M17: 0 | P17: 16619.2
A18: 14 | B18: 46187 | G18: =E18*F18 -> 0 | J18: =H18*I18 -> 0 | K18: =G18+J18 -> 0 | L18: =+K18 -> 0 | M18: 0 | P18: =SUM(P16:P17) -> 24440
A19: 15 | B19: 46188 | G19: =E19*F19 -> 0 | J19: =H19*I19 -> 0 | K19: =G19+J19 -> 0 | L19: =+K19 -> 0 | M19: 0
A20: 16 | B20: 46189 | G20: =E20*F20 -> 0 | J20: =H20*I20 -> 0 | K20: =G20+J20 -> 0 | L20: =+K20 -> 0 | M20: 0
A21: 17 | B21: 46190 | G21: =E21*F21 -> 0 | J21: =H21*I21 -> 0 | K21: =G21+J21 -> 0 | L21: =+K21 -> 0 | M21: 0
A22: 18 | B22: 46191 | G22: =E22*F22 -> 0 | J22: =H22*I22 -> 0 | K22: =G22+J22 -> 0 | L22: =+K22 -> 0 | M22: 0
A23: 19 | B23: 46192 | G23: =E23*F23 -> 0 | H23: 2.55 | I23: 117.66 | J23: =H23*I23 -> 300.033 | K23: =G23+J23 -> 300.033 | L23: =+K23 -> 300.033 | M23: 0
A24: 20 | B24: 46193 | G24: =E24*F24 -> 0 | J24: =H24*I24 -> 0 | K24: =G24+J24 -> 0 | L24: =+K24 -> 0 | M24: 0
A25: 21 | B25: 46194 | G25: =E25*F25 -> 0 | J25: =H25*I25 -> 0 | K25: =G25+J25 -> 0 | L25: =+K25 -> 0 | M25: 0
A26: 22 | B26: 46195 | G26: =E26*F26 -> 0 | J26: =H26*I26 -> 0 | K26: =G26+J26 -> 0 | L26: =+K26 -> 0 | M26: 0
A27: 23 | B27: 46196 | G27: =E27*F27 -> 0 | J27: =H27*I27 -> 0 | K27: =G27+J27 -> 0 | L27: =+K27 -> 0 | M27: 0
A28: 24 | B28: 46197 | G28: =E28*F28 -> 0 | J28: =H28*I28 -> 0 | K28: =G28+J28 -> 0 | L28: =+K28 -> 0 | M28: 0
A29: 25 | B29: 46198 | G29: =E29*F29 -> 0 | J29: =H29*I29 -> 0 | K29: =G29+J29 -> 0 | L29: =+K29 -> 0 | M29: 0
B30: 46199 | J30: =H30*I30 -> 0 | K30: =G30+J30 -> 0 | L30: =+K30 -> 0
A31: 26 | B31: 46200 | G31: =E31*F31 -> 0 | J31: =H31*I31 -> 0 | K31: =G31+J31 -> 0 | L31: =+K31 -> 0 | M31: 0
A32: 27 | B32: 46201 | G32: =E32*F32 -> 0 | H32: 3.4 | I32: 117.66 | J32: =H32*I32 -> 400.044 | K32: =G32+J32 -> 400.044 | L32: =+K32 -> 400.044 | M32: 0
A33: 28 | B33: 46202 | G33: =E33*F33 -> 0 | J33: =H33*I33 -> 0 | K33: =G33+J33 -> 0 | L33: =+K33 -> 0 | M33: 0
A34: 29 | B34: 46203 | G34: =E34*F34 -> 0 | J34: =H34*I34 -> 0 | K34: =G34+J34 -> 0 | L34: =+K34 -> 0 | M34: 0
A35: 30 | G35: =E35*F35 -> 0 | J35: =H35*I35 -> 0 | K35: =G35+J35 -> 0 | L35: =+K35 -> 0 | M35: 0
A36: 31 | G36: =E36*F36 -> 0 | J36: =H36*I36 -> 0 | K36: =G36+J36 -> 0 | L36: =+K36 -> 0 | M36: 0
E37: =SUM(E4:E36) -> 0 | G37: =SUM(G4:G36) -> 0 | H37: =SUM(H4:H36) -> 18.84 | J37: =SUM(J4:J36) -> 2099.6078 | K37: =SUM(K4:K36) -> 2099.6078 | L37: =SUM(L4:L36) -> 2099.6078

Sheet Kadur
A1: Vishal Service Station
A2: S.No | B2: Date | C2: GRN No | D2: Ind No/Bill No | E2: Diesel (Lts) | F2: Price | G2: Amount | H2: Petrol (Lts) | I2: Price | J2: Amount | K2: Total amount | L2: Amount paid | M2: As on Date | N2: Remarks
A3: Opening Balance | K3: 159888.9 | L3: 0 | M3: 159888.9 | O3: 207239.43
A4: 1 | B4: 45809 | G4: =E4*F4 -> 0 | J4: =H4*I4 -> 0 | K4: =G4+J4 -> 0 | M4: =M3+K4-L4 -> 159888.9
A5: 2 | B5: 45810 | G5: =E5*F5 -> 0 | J5: =H5*I5 -> 0 | K5: =G5+J5 -> 0 | M5: =M4+K5-L5 -> 159888.9
A6: 3 | B6: 45811 | G6: =E6*F6 -> 0 | J6: =H6*I6 -> 0 | K6: =G6+J6 -> 0 | M6: =M5+K6-L6 -> 159888.9
A7: 4 | B7: 45812 | G7: =E7*F7 -> 0 | J7: =H7*I7 -> 0 | K7: =G7+J7 -> 0 | M7: =M6+K7-L7 -> 159888.9
A8: 5 | B8: 45813 | F8: 0 | G8: =E8*F8 -> 0 | H8: 0 | I8: 0 | J8: =H8*I8 -> 0 | K8: =G8+J8 -> 0 | M8: =M7+K8-L8 -> 159888.9
A9: 6 | B9: 45814 | F9: 0 | G9: =E9*F9 -> 0 | H9: 0 | I9: 0 | J9: =H9*I9 -> 0 | K9: =G9+J9 -> 0 | M9: =M8+K9-L9 -> 159888.9
A10: 7 | B10: 45815 | F10: 0 | G10: =E10*F10 -> 0 | H10: 0 | I10: 0 | J10: =H10*I10 -> 0 | K10: =G10+J10 -> 0 | M10: =M9+K10-L10 -> 159888.9
A11: 8 | B11: 45816 | F11: 0 | G11: =E11*F11 -> 0 | H11: 0 | I11: 0 | J11: =H11*I11 -> 0 | K11: =G11+J11 -> 0 | L11: 159889 | M11: =M10+K11-L11 -> -0.1
A12: 9 | B12: 45817 | E12: 1000 | F12: 102.96 | G12: =E12*F12 -> 102960 | H12: 140 | I12: 117.3 | J12: =H12*I12 -> 16422 | K12: =G12+J12 -> 119382 | M12: =M11+K12-L12 -> 119381.9
A13: 10 | B13: 45818 | E13: 1000 | F13: 102.96 | G13: =E13*F13 -> 102960 | H13: 0 | I13: 0 | J13: =H13*I13 -> 0 | K13: =G13+J13 -> 102960 | M13: =M12+K13-L13 -> 222341.9
A14: 11 | B14: 45819 | E14: 1000 | F14: 102.96 | G14: =E14*F14 -> 102960 | H14: 0 | I14: 0 | J14: =H14*I14 -> 0 | K14: =G14+J14 -> 102960 | M14: =M13+K14-L14 -> 325301.9
A15: 12 | B15: 45820 | F15: 0 | G15: =E15*F15 -> 0 | H15: 0 | I15: 0 | J15: =H15*I15 -> 0 | K15: =G15+J15 -> 0 | M15: =M14+K15-L15 -> 325301.9
A16: 13 | B16: 45821 | F16: 0 | G16: =E16*F16 -> 0 | H16: 0 | I16: 0 | J16: =H16*I16 -> 0 | K16: =G16+J16 -> 0 | M16: =M15+K16-L16 -> 325301.9
A17: 14 | B17: 45822 | F17: 0 | G17: =E17*F17 -> 0 | H17: 0 | I17: 0 | J17: =H17*I17 -> 0 | K17: =G17+J17 -> 0 | M17: =M16+K17-L17 -> 325301.9
A18: 15 | B18: 45823 | F18: 0 | G18: =E18*F18 -> 0 | H18: 0 | I18: 0 | J18: =H18*I18 -> 0 | K18: =G18+J18 -> 0 | M18: =M17+K18-L18 -> 325301.9
A19: 16 | B19: 45824 | F19: 0 | G19: =E19*F19 -> 0 | H19: 0 | I19: 0 | J19: =H19*I19 -> 0 | K19: =G19+J19 -> 0 | M19: =M18+K19-L19 -> 325301.9
A20: 17 | B20: 45825 | F20: 0 | G20: =E20*F20 -> 0 | H20: 0 | I20: 0 | J20: =H20*I20 -> 0 | K20: =G20+J20 -> 0 | M20: =M19+K20-L20 -> 325301.9
A21: 18 | B21: 45826 | F21: 0 | G21: =E21*F21 -> 0 | H21: 0 | I21: 0 | J21: =H21*I21 -> 0 | K21: =G21+J21 -> 0 | M21: =M20+K21-L21 -> 325301.9
A22: 19 | B22: 45827 | F22: 0 | H22: 0 | I22: 0 | J22: =H22*I22 -> 0 | K22: =G22+J22 -> 0 | M22: =M21+K22-L22 -> 325301.9
A23: 20 | B23: 45828 | F23: 0 | H23: 0 | I23: 0 | J23: =H23*I23 -> 0 | K23: =G23+J23 -> 0 | M23: =M22+K23-L23 -> 325301.9
A24: 21 | B24: 45829 | F24: 0 | J24: =H24*I24 -> 0 | K24: =G24+J24 -> 0 | M24: =M23+K24-L24 -> 325301.9
A25: 22 | B25: 45830 | F25: 0 | J25: =H25*I25 -> 0 | K25: =G25+J25 -> 0 | M25: =M24+K25-L25 -> 325301.9
A26: 23 | B26: 45831 | F26: 0 | J26: =H26*I26 -> 0 | K26: =G26+J26 -> 0 | M26: =M25+K26-L26 -> 325301.9
A27: 24 | B27: 45832 | F27: 0 | J27: =H27*I27 -> 0 | K27: =G27+J27 -> 0 | M27: =M26+K27-L27 -> 325301.9
A28: 25 | B28: 45833 | F28: 0 | J28: =H28*I28 -> 0 | K28: =G28+J28 -> 0 | M28: =M27+K28-L28 -> 325301.9
A29: 26 | B29: 45834 | F29: 0 | J29: =H29*I29 -> 0 | K29: =G29+J29 -> 0 | M29: =M28+K29-L29 -> 325301.9
A30: 27 | B30: 45835 | F30: 0 | J30: =H30*I30 -> 0 | K30: =G30+J30 -> 0 | M30: =M29+K30-L30 -> 325301.9
A31: 28 | B31: 45836 | F31: 0 | J31: =H31*I31 -> 0 | K31: =G31+J31 -> 0 | M31: =M30+K31-L31 -> 325301.9
A32: 29 | B32: 45837 | F32: 0 | G32: =E32*F32 -> 0 | H32: 0 | I32: 0 | J32: =H32*I32 -> 0 | K32: =G32+J32 -> 0 | M32: =M31+K32-L32 -> 325301.9
A33: 30 | B33: 45838 | F33: 0 | G33: =E33*F33 -> 0 | H33: 0 | I33: 0 | J33: =H33*I33 -> 0 | K33: =G33+J33 -> 0 | M33: =M32+K33-L33 -> 325301.9
A34: 31 | F34: 0 | G34: =E34*F34 -> 0 | J34: =H34*I34 -> 0 | K34: =G34+J34 -> 0
E35: =SUM(E4:E34) -> 3000 | G35: =SUM(G4:G34) -> 308880 | H35: =SUM(H4:H34) -> 140 | J35: =SUM(J4:J34) -> 16422 | K35: =SUM(K4:K34) -> 325302 | L35: =SUM(L4:L31) -> 159889

Sheet YG Gudda
A1: Pankaja HP Fuel Center
A2: S.No | B2: Date | C2: GRN No | D2: Ind No/Bill No | E2: Diesel (Lts) | F2: Price | G2: Amount | H2: Petrol (Lts) | I2: Price | J2: Amount | K2: Total amount | L2: Amount paid | M2: As on Date | N2: Remarks
A3: Opening Balance | K3: 189118.96 | M3: 189118.96
A4: 1 | B4: 46174 | G4: =E4*F4 -> 0 | J4: =H4*I4 -> 0 | K4: =G4+J4 -> 0 | L4: 150000 | M4: =M3+K4-L4 -> 39118.96
B5: 46174 | E5: 300 | F5: 99.14 | G5: =E5*F5 -> 29742 | K5: =G5+J5 -> 29742 | L5: =H5+K5 -> 29742 | M5: =M4+K5-L5 -> 39118.96 | N5: BPCL
A6: 2 | B6: 46175 | E6: 1200 | F6: 99.14 | G6: =E6*F6 -> 118968 | H6: 35 | I6: 111.24 | J6: =H6*I6 -> 3893.4 | K6: =G6+J6 -> 122861.4 | M6: =M4+K6-L6 -> 161980.36
A7: 3 | B7: 46176 | G7: =E7*F7 -> 0 | J7: =H7*I7 -> 0 | K7: =G7+J7 -> 0 | M7: =M6+K7-L7 -> 161980.36
A8: 4 | B8: 46177 | G8: =E8*F8 -> 0 | J8: =H8*I8 -> 0 | K8: =G8+J8 -> 0 | M8: =M7+K8-L8 -> 161980.36
A9: 5 | B9: 46178 | E9: 500 | F9: 99.14 | G9: =E9*F9 -> 49570 | H9: 35 | I9: 111.24 | J9: =H9*I9 -> 3893.4 | K9: =G9+J9 -> 53463.4 | M9: =M8+K9-L9 -> 215443.76
A10: 6 | B10: 46179 | E10: 1200 | F10: 99.14 | G10: =E10*F10 -> 118968 | H10: 35 | I10: 111.24 | J10: =H10*I10 -> 3893.4 | K10: =G10+J10 -> 122861.4 | L10: 200000 | M10: =M9+K10-L10 -> 138305.16
A11: 7 | B11: 46180 | G11: =E11*F11 -> 0 | J11: =H11*I11 -> 0 | K11: =G11+J11 -> 0 | M11: =M10+K11-L11 -> 138305.16
A12: 8 | B12: 46181 | G12: =E12*F12 -> 0 | J12: =H12*I12 -> 0 | K12: =G12+J12 -> 0 | M12: =M11+K12-L12 -> 138305.16
A13: 9 | B13: 46182 | E13: 600 | F13: 99.14 | G13: =E13*F13 -> 59484 | H13: 35 | I13: 111.24 | J13: =H13*I13 -> 3893.4 | K13: =G13+J13 -> 63377.4 | L13: 100000 | M13: =M12+K13-L13 -> 101682.56
A14: 10 | B14: 46183 | E14: 600 | F14: 99.14 | G14: =E14*F14 -> 59484 | J14: =H14*I14 -> 0 | K14: =G14+J14 -> 59484 | M14: =M13+K14-L14 -> 161166.56
A15: 11 | B15: 46184 | G15: =E15*F15 -> 0 | J15: =H15*I15 -> 0 | K15: =G15+J15 -> 0 | M15: =M14+K15-L15 -> 161166.56
A16: 12 | B16: 46185 | E16: 0 | G16: =E16*F16 -> 0 | K16: =G16+J16 -> 0 | M16: =M15+K16-L16 -> 161166.56
A17: 13 | B17: 46186 | G17: =E17*F17 -> 0 | J17: =H17*I17 -> 0 | K17: =G17+J17 -> 0 | M17: =M16+K17-L17 -> 161166.56
A18: 14 | B18: 46187 | G18: =E18*F18 -> 0 | J18: =H18*I18 -> 0 | K18: =G18+J18 -> 0 | M18: =M17+K18-L18 -> 161166.56
A19: 15 | B19: 46188 | G19: =E19*F19 -> 0 | J19: =H19*I19 -> 0 | K19: =G19+J19 -> 0 | M19: =M18+K19-L19 -> 161166.56
A20: 16 | B20: 46189 | G20: =E20*F20 -> 0 | J20: =H20*I20 -> 0 | K20: =G20+J20 -> 0 | L20: 150000 | M20: =M19+K20-L20 -> 11166.56
A21: 17 | B21: 46190 | E21: 1200 | F21: 99.14 | G21: =E21*F21 -> 118968 | H21: 70 | I21: 111.24 | J21: =H21*I21 -> 7786.8 | K21: =G21+J21 -> 126754.8 | M21: =M20+K21-L21 -> 137921.36
A22: 18 | B22: 46191 | G22: =E22*F22 -> 0 | J22: =H22*I22 -> 0 | K22: =G22+J22 -> 0 | M22: =M21+K22-L22 -> 137921.36
A23: 19 | B23: 46192 | E23: 1000 | F23: 99.14 | G23: =E23*F23 -> 99140 | J23: =H23*I23 -> 0 | K23: =G23+J23 -> 99140 | M23: =M22+K23-L23 -> 237061.36
A24: 20 | B24: 46193 | G24: =E24*F24 -> 0 | J24: =H24*I24 -> 0 | K24: =G24+J24 -> 0 | M24: =M23+K24-L24 -> 237061.36
A25: 21 | B25: 46194 | G25: =E25*F25 -> 0 | J25: =H25*I25 -> 0 | K25: =G25+J25 -> 0 | M25: =M24+K25-L25 -> 237061.36
A26: 22 | B26: 46195 | G26: =E26*F26 -> 0 | J26: =H26*I26 -> 0 | K26: =G26+J26 -> 0 | M26: =M25+K26-L26 -> 237061.36
A27: 23 | B27: 46196 | G27: =E27*F27 -> 0 | J27: =H27*I27 -> 0 | K27: =G27+J27 -> 0 | M27: =M26+K27-L27 -> 237061.36
A28: 24 | B28: 46197 | G28: =E28*F28 -> 0 | J28: =H28*I28 -> 0 | K28: =G28+J28 -> 0 | M28: =M27+K28-L28 -> 237061.36
A29: 25 | B29: 46198 | G29: =E29*F29 -> 0 | J29: =H29*I29 -> 0 | K29: =G29+J29 -> 0 | L29: 200000 | M29: =M28+K29-L29 -> 37061.36
A30: 26 | B30: 46199 | E30: 1200 | F30: 99.14 | G30: =E30*F30 -> 118968 | J30: =H30*I30 -> 0 | K30: =G30+J30 -> 118968 | M30: =M29+K30-L30 -> 156029.36
A31: 27 | B31: 46200 | G31: =E31*F31 -> 0 | J31: =H31*I31 -> 0 | K31: =G31+J31 -> 0 | M31: =M30+K31-L31 -> 156029.36
A32: 28 | B32: 46201 | G32: =E32*F32 -> 0 | J32: =H32*I32 -> 0 | K32: =G32+J32 -> 0 | M32: =M31+K32-L32 -> 156029.36
A33: 29 | B33: 46202 | G33: =E33*F33 -> 0 | J33: =H33*I33 -> 0 | K33: =G33+J33 -> 0 | M33: =M32+K33-L33 -> 156029.36
A34: 30 | B34: 46203 | E34: 1200 | F34: 99.14 | G34: =E34*F34 -> 118968 | H34: 70 | I34: 111.24 | J34: =H34*I34 -> 7786.8 | K34: =G34+J34 -> 126754.8 | M34: =M33+K34-L34 -> 282784.16
A35: 31 | G35: =E35*F35 -> 0 | J35: =H35*I35 -> 0 | K35: =G35+J35 -> 0 | M35: =M34+K35-L35 -> 282784.16
A36: 32 | G36: =E36*F36 -> 0 | J36: =H36*I36 -> 0 | K36: =G36+J36 -> 0 | M36: =M35+K36-L36 -> 282784.16
A37: 33 | G37: =E37*F37 -> 0 | J37: =H37*I37 -> 0 | K37: =G37+J37 -> 0 | M37: =M36+K37-L37 -> 282784.16
A38: 34 | G38: =E38*F38 -> 0 | J38: =H38*I38 -> 0 | K38: =G38+J38 -> 0 | M38: =M37+K38-L38 -> 282784.16
E39: =SUM(E4:E38) -> 9000 | G39: =SUM(G4:G38) -> 892260 | H39: =SUM(H4:H38) -> 280 | J39: =SUM(J4:J38) -> 31147.2 | K39: =SUM(K4:K38) -> 923407.2 | L39: =SUM(L4:L38) -> 829742

Sheet  YG Gudda-2
A1: One Stop
A2: S.No | B2: Date | C2: GRN No | D2: Ind No/Bill No | E2: Diesel (Lts) | F2: Price | G2: Amount | H2: Petrol (Lts) | I2: Price | J2: Amount | K2: Total amount | L2: Amount paid | M2: As on Date | N2: Remarks
A3: Opening Balance | K3: 0 | M3: 0
A4: 1 | B4: 46174 | M4: =M3+K4-L4 -> 0
B5: 46174 | M5: =M4+K5-L5 -> 0 | N5: BPCL
A6: 2 | B6: 46175 | M6: =M4+K6-L6 -> 0
A7: 3 | B7: 46176 | M7: =M6+K7-L7 -> 0
A8: 4 | B8: 46177 | M8: =M7+K8-L8 -> 0
A9: 5 | B9: 46178 | M9: =M8+K9-L9 -> 0
A10: 6 | B10: 46179 | M10: =M9+K10-L10 -> 0
A11: 7 | B11: 46180 | M11: =M10+K11-L11 -> 0
A12: 8 | B12: 46181 | M12: =M11+K12-L12 -> 0
A13: 9 | B13: 46182 | M13: =M12+K13-L13 -> 0
A14: 10 | B14: 46183 | M14: =M13+K14-L14 -> 0
A15: 11 | B15: 46184 | M15: =M14+K15-L15 -> 0
A16: 12 | B16: 46185 | E16: 1000 | F16: 99.02 | G16: =E16*F16 -> 99020 | K16: =G16+J16 -> 99020 | M16: =M15+K16-L16 -> 99020
A17: 13 | B17: 46186 | G17: =E17*F17 -> 0 | J17: =H17*I17 -> 0 | K17: =G17+J17 -> 0 | M17: =M16+K17-L17 -> 99020
A18: 14 | B18: 46187 | E18: 1000 | F18: 99.02 | G18: =E18*F18 -> 99020 | H18: 35 | I18: 111.12 | J18: =H18*I18 -> 3889.2 | K18: =G18+J18 -> 102909.2 | M18: =M17+K18-L18 -> 201929.2
A19: 15 | B19: 46188 | G19: =E19*F19 -> 0 | J19: =H19*I19 -> 0 | K19: =G19+J19 -> 0 | M19: =M18+K19-L19 -> 201929.2
A20: 16 | B20: 46189 | G20: =E20*F20 -> 0 | J20: =H20*I20 -> 0 | K20: =G20+J20 -> 0 | L20: 0 | M20: =M19+K20-L20 -> 201929.2
A21: 17 | B21: 46190 | G21: =E21*F21 -> 0 | J21: =H21*I21 -> 0 | K21: =G21+J21 -> 0 | L21: 200000 | M21: =M20+K21-L21 -> 1929.2
A22: 18 | B22: 46191 | G22: =E22*F22 -> 0 | J22: =H22*I22 -> 0 | K22: =G22+J22 -> 0 | M22: =M21+K22-L22 -> 1929.2
A23: 19 | B23: 46192 | G23: =E23*F23 -> 0 | J23: =H23*I23 -> 0 | K23: =G23+J23 -> 0 | M23: =M22+K23-L23 -> 1929.2
A24: 20 | B24: 46193 | G24: =E24*F24 -> 0 | J24: =H24*I24 -> 0 | K24: =G24+J24 -> 0 | M24: =M23+K24-L24 -> 1929.2
A25: 21 | B25: 46194 | G25: =E25*F25 -> 0 | J25: =H25*I25 -> 0 | K25: =G25+J25 -> 0 | M25: =M24+K25-L25 -> 1929.2
A26: 22 | B26: 46195 | E26: 1000 | F26: 99.02 | G26: =E26*F26 -> 99020 | H26: 35 | I26: 111.12 | J26: =H26*I26 -> 3889.2 | K26: =G26+J26 -> 102909.2 | M26: =M25+K26-L26 -> 104838.4
A27: 23 | B27: 46196 | G27: =E27*F27 -> 0 | J27: =H27*I27 -> 0 | K27: =G27+J27 -> 0 | M27: =M26+K27-L27 -> 104838.4
A28: 24 | B28: 46197 | E28: 1000 | F28: 99.02 | G28: =E28*F28 -> 99020 | H28: 35 | I28: 111.12 | J28: =H28*I28 -> 3889.2 | K28: =G28+J28 -> 102909.2 | M28: =M27+K28-L28 -> 207747.6
A29: 25 | B29: 46198 | G29: =E29*F29 -> 0 | J29: =H29*I29 -> 0 | K29: =G29+J29 -> 0 | M29: =M28+K29-L29 -> 207747.6
A30: 26 | B30: 46199 | G30: =E30*F30 -> 0 | J30: =H30*I30 -> 0 | K30: =G30+J30 -> 0 | M30: =M29+K30-L30 -> 207747.6
A31: 27 | B31: 46200 | G31: =E31*F31 -> 0 | J31: =H31*I31 -> 0 | K31: =G31+J31 -> 0 | M31: =M30+K31-L31 -> 207747.6
A32: 28 | B32: 46201 | G32: =E32*F32 -> 0 | J32: =H32*I32 -> 0 | K32: =G32+J32 -> 0 | M32: =M31+K32-L32 -> 207747.6
A33: 29 | B33: 46202 | G33: =E33*F33 -> 0 | J33: =H33*I33 -> 0 | K33: =G33+J33 -> 0 | M33: =M32+K33-L33 -> 207747.6
A34: 30 | B34: 46203 | G34: =E34*F34 -> 0 | J34: =H34*I34 -> 0 | K34: =G34+J34 -> 0 | M34: =M33+K34-L34 -> 207747.6
A35: 31 | G35: =E35*F35 -> 0 | J35: =H35*I35 -> 0 | K35: =G35+J35 -> 0 | M35: =M34+K35-L35 -> 207747.6
A36: 32 | G36: =E36*F36 -> 0 | J36: =H36*I36 -> 0 | K36: =G36+J36 -> 0 | M36: =M35+K36-L36 -> 207747.6
A37: 33 | G37: =E37*F37 -> 0 | J37: =H37*I37 -> 0 | K37: =G37+J37 -> 0 | M37: =M36+K37-L37 -> 207747.6
A38: 34 | G38: =E38*F38 -> 0 | J38: =H38*I38 -> 0 | K38: =G38+J38 -> 0 | M38: =M37+K38-L38 -> 207747.6
E39: =SUM(E4:E38) -> 4000 | G39: =SUM(G4:G38) -> 396080 | H39: =SUM(H4:H38) -> 105 | J39: =SUM(J4:J38) -> 11667.6 | K39: =SUM(K4:K38) -> 407747.6 | L39: =SUM(L4:L38) -> 200000

Sheet Hosadurga -2
A1: Shree Veeraprathap Fuel
A2: S.No | B2: Date | C2: GRN No | D2: Ind No/Bill No | E2: Diesel (Lts) | F2: Price | G2: Amount | H2: Petrol (Lts) | I2: Price | J2: Amount | K2: Total amount | L2: Amount paid | M2: As on Date | N2: Remarks
A3: Opening Balance | K3: 148201.19 | M3: 148201.19
A4: 1 | B4: 46174 | C4: 0 | E4: 0 | F4: 0 | G4: =E4*F4 -> 0 | H4: 0 | I4: 0 | J4: =H4*I4 -> 0 | K4: =G4+J4 -> 0 | L4: 107927 | M4: =M3+K4-L4 -> 40274.194 | N4: BT Anther Bunk
A5: 2 | B5: 46175 | C5: 0 | E5: 1000 | F5: 99.99 | G5: =E5*F5 -> 99990 | J5: =H5*I5 -> 0 | K5: =G5+J5 -> 99990 | M5: =M4+K5-L5 -> 140264.19
A6: 3 | B6: 46176 | C6: 0 | G6: =E6*F6 -> 0 | J6: =H6*I6 -> 0 | K6: =G6+J6 -> 0 | M6: =M5+K6-L6 -> 140264.19
A7: 4 | B7: 46177 | C7: 0 | G7: =E7*F7 -> 0 | J7: =H7*I7 -> 0 | K7: =G7+J7 -> 0 | M7: =M6+K7-L7 -> 140264.19
A8: 5 | B8: 46178 | C8: 0 | G8: =E8*F8 -> 0 | J8: =H8*I8 -> 0 | K8: =G8+J8 -> 0 | M8: =M7+K8-L8 -> 140264.19
A9: 6 | B9: 46179 | C9: 0 | G9: =E9*F9 -> 0 | J9: =H9*I9 -> 0 | K9: =G9+J9 -> 0 | M9: =M8+K9-L9 -> 140264.19
A10: 7 | B10: 46180 | C10: 0 | G10: =E10*F10 -> 0 | J10: =H10*I10 -> 0 | K10: =G10+J10 -> 0 | M10: =M9+K10-L10 -> 140264.19
A11: 8 | B11: 46181 | C11: 0 | G11: =E11*F11 -> 0 | J11: =H11*I11 -> 0 | K11: =G11+J11 -> 0 | L11: 140000 | M11: =M10+K11-L11 -> 264.1941
A12: 9 | B12: 46182 | C12: 0 | E12: 1000 | F12: 99.21 | G12: =E12*F12 -> 99210 | H12: 70 | I12: 111.43 | J12: =H12*I12 -> 7800.1 | K12: =G12+J12 -> 107010.1 | M12: =M11+K12-L12 -> 107274.29
A13: 10 | B13: 46183 | C13: 0 | G13: =E13*F13 -> 0 | J13: =H13*I13 -> 0 | K13: =G13+J13 -> 0 | M13: =M12+K13-L13 -> 107274.29
A14: 11 | B14: 46184 | C14: 0 | G14: =E14*F14 -> 0 | J14: =H14*I14 -> 0 | K14: =G14+J14 -> 0 | M14: =M13+K14-L14 -> 107274.29
A15: 12 | B15: 46185 | C15: 0 | G15: =E15*F15 -> 0 | J15: =H15*I15 -> 0 | K15: =G15+J15 -> 0 | M15: =M14+K15-L15 -> 107274.29
A16: 13 | B16: 46186 | C16: 0 | G16: =E16*F16 -> 0 | J16: =H16*I16 -> 0 | K16: =G16+J16 -> 0 | M16: =M15+K16-L16 -> 107274.29
A17: 14 | B17: 46187 | C17: 0 | G17: =E17*F17 -> 0 | J17: =H17*I17 -> 0 | K17: =G17+J17 -> 0 | M17: =M16+K17-L17 -> 107274.29
A18: 15 | B18: 46188 | C18: 0 | G18: =E18*F18 -> 0 | J18: =H18*I18 -> 0 | K18: =G18+J18 -> 0 | M18: =M17+K18-L18 -> 107274.29
A19: 16 | B19: 46189 | C19: 0 | G19: =E19*F19 -> 0 | J19: =H19*I19 -> 0 | K19: =G19+J19 -> 0 | L19: 100000 | M19: =M18+K19-L19 -> 7274.2941
A20: 17 | B20: 46190 | C20: 0 | G20: =E20*F20 -> 0 | J20: =H20*I20 -> 0 | K20: =G20+J20 -> 0 | M20: =M19+K20-L20 -> 7274.2941
A21: 18 | B21: 46191 | C21: 0 | E21: 1000 | F21: 99.21 | G21: =E21*F21 -> 99210 | H21: 70 | I21: 111.43 | J21: =H21*I21 -> 7800.1 | K21: =G21+J21 -> 107010.1 | M21: =M20+K21-L21 -> 114284.39
A22: 19 | B22: 46192 | C22: 0 | G22: =E22*F22 -> 0 | J22: =H22*I22 -> 0 | K22: =G22+J22 -> 0 | M22: =M21+K22-L22 -> 114284.39
A23: 20 | B23: 46193 | C23: 0 | G23: =E23*F23 -> 0 | J23: =H23*I23 -> 0 | K23: =G23+J23 -> 0 | M23: =M22+K23-L23 -> 114284.39
A24: 21 | B24: 46194 | C24: 0 | G24: =E24*F24 -> 0 | J24: =H24*I24 -> 0 | K24: =G24+J24 -> 0 | M24: =M23+K24-L24 -> 114284.39
A25: 22 | B25: 46195 | C25: 0 | G25: =E25*F25 -> 0 | J25: =H25*I25 -> 0 | K25: =G25+J25 -> 0 | M25: =M24+K25-L25 -> 114284.39
A26: 23 | B26: 46196 | C26: 0 | G26: =E26*F26 -> 0 | J26: =H26*I26 -> 0 | K26: =G26+J26 -> 0 | M26: =M25+K26-L26 -> 114284.39
A27: 24 | B27: 46197 | C27: 0 | G27: =E27*F27 -> 0 | J27: =H27*I27 -> 0 | K27: =G27+J27 -> 0 | M27: =M26+K27-L27 -> 114284.39
A28: 25 | B28: 46198 | C28: 0 | G28: =E28*F28 -> 0 | J28: =H28*I28 -> 0 | K28: =G28+J28 -> 0 | M28: =M27+K28-L28 -> 114284.39
A29: 26 | B29: 46199 | C29: 0 | G29: =E29*F29 -> 0 | J29: =H29*I29 -> 0 | K29: =G29+J29 -> 0 | M29: =M28+K29-L29 -> 114284.39
A30: 27 | B30: 46200 | C30: 0 | G30: =E30*F30 -> 0 | J30: =H30*I30 -> 0 | K30: =G30+J30 -> 0 | M30: =M29+K30-L30 -> 114284.39
A31: 28 | B31: 46201 | C31: 0 | G31: =E31*F31 -> 0 | J31: =H31*I31 -> 0 | K31: =G31+J31 -> 0 | M31: =M30+K31-L31 -> 114284.39
A32: 29 | B32: 46202 | C32: 0 | G32: =E32*F32 -> 0 | J32: =H32*I32 -> 0 | K32: =G32+J32 -> 0 | M32: =M31+K32-L32 -> 114284.39
A33: 30 | B33: 46203 | C33: 0 | G33: =E33*F33 -> 0 | J33: =H33*I33 -> 0 | K33: =G33+J33 -> 0 | M33: =M32+K33-L33 -> 114284.39
A34: 31 | K34: =G34+J34 -> 0
E35: =SUM(E4:E34) -> 3000 | G35: =SUM(G4:G34) -> 298410 | H35: =SUM(H4:H34) -> 140 | J35: =SUM(J4:J34) -> 15600.2 | K35: =SUM(K4:K34) -> 314010.2 | L35: =SUM(L4:L34) -> 347927

Sheet Hiriyur(VJNL)
A1: Sri Balaji Agencies
A2: S.No | B2: Date | C2: GRN No | D2: Ind No/Bill No | E2: Diesel (Lts) | F2: Price | G2: Amount | H2: Petrol (Lts) | I2: Price | J2: Amount | K2: Total amount | L2: Amount paid | M2: As on Date | N2: Remarks
A3: Opening Balance | K3: 182925.7 | M3: 182925.7
A4: 1 | B4: 46174 | G4: =E4*F4 -> 0 | J4: =H4*I4 -> 0 | K4: =G4+J4 -> 0 | L4: 150000 | M4: =M3+K4-L4 -> 32925.7
A5: 2 | B5: 46175 | G5: =E5*F5 -> 0 | J5: =H5*I5 -> 0 | K5: =G5+J5 -> 0 | M5: =M4+K5-L5 -> 32925.7
A6: 3 | B6: 46176 | G6: =E6*F6 -> 0 | J6: =H6*I6 -> 0 | K6: =G6+J6 -> 0 | M6: =M5+K6-L6 -> 32925.7
A7: 4 | B7: 46177 | G7: =E7*F7 -> 0 | J7: =H7*I7 -> 0 | K7: =G7+J7 -> 0 | M7: =M6+K7-L7 -> 32925.7
A8: 5 | B8: 46178 | G8: =E8*F8 -> 0 | J8: =H8*I8 -> 0 | K8: =G8+J8 -> 0 | M8: =M7+K8-L8 -> 32925.7
A9: 6 | B9: 46179 | G9: =E9*F9 -> 0 | J9: =H9*I9 -> 0 | K9: =G9+J9 -> 0 | M9: =M8+K9-L9 -> 32925.7
A10: 7 | B10: 46180 | G10: =E10*F10 -> 0 | J10: =H10*I10 -> 0 | K10: =G10+J10 -> 0 | M10: =M9+K10-L10 -> 32925.7
A11: 8 | B11: 46181 | G11: =E11*F11 -> 0 | J11: =H11*I11 -> 0 | K11: =G11+J11 -> 0 | L11: 32855 | M11: =M10+K11-L11 -> 70.7
A12: 9 | B12: 46182 | E12: 1500 | F12: 99.92 | G12: =E12*F12 -> 149880 | H12: 70 | I12: 111.84 | J12: =H12*I12 -> 7828.8 | K12: =G12+J12 -> 157708.8 | M12: =M11+K12-L12 -> 157779.5
A13: 10 | B13: 46183 | G13: =E13*F13 -> 0 | J13: =H13*I13 -> 0 | K13: =G13+J13 -> 0 | M13: =M12+K13-L13 -> 157779.5
A14: 11 | B14: 46184 | G14: =E14*F14 -> 0 | J14: =H14*I14 -> 0 | K14: =G14+J14 -> 0 | M14: =M13+K14-L14 -> 157779.5
A15: 12 | B15: 46185 | G15: =E15*F15 -> 0 | J15: =H15*I15 -> 0 | K15: =G15+J15 -> 0 | M15: =M14+K15-L15 -> 157779.5
A16: 13 | B16: 46186 | G16: =E16*F16 -> 0 | J16: =H16*I16 -> 0 | K16: =G16+J16 -> 0 | M16: =M15+K16-L16 -> 157779.5
A17: 14 | B17: 46187 | G17: =E17*F17 -> 0 | J17: =H17*I17 -> 0 | K17: =G17+J17 -> 0 | M17: =M16+K17-L17 -> 157779.5
A18: 15 | B18: 46188 | G18: =E18*F18 -> 0 | J18: =H18*I18 -> 0 | K18: =G18+J18 -> 0 | M18: =M17+K18-L18 -> 157779.5
A19: 16 | B19: 46189 | G19: =E19*F19 -> 0 | J19: =H19*I19 -> 0 | K19: =G19+J19 -> 0 | L19: 150000 | M19: =M18+K19-L19 -> 7779.5
A20: 17 | B20: 46190 | E20: 2000 | F20: 99.92 | G20: =E20*F20 -> 199840 | H20: 70 | I20: 111.84 | J20: =H20*I20 -> 7828.8 | K20: =G20+J20 -> 207668.8 | M20: =M19+K20-L20 -> 215448.3
A21: 18 | B21: 46191 | G21: =E21*F21 -> 0 | J21: =H21*I21 -> 0 | K21: =G21+J21 -> 0 | M21: =M20+K21-L21 -> 215448.3
A22: 19 | B22: 46192 | G22: =E22*F22 -> 0 | J22: =H22*I22 -> 0 | K22: =G22+J22 -> 0 | M22: =M21+K22-L22 -> 215448.3
A23: 20 | B23: 46193 | G23: =E23*F23 -> 0 | J23: =H23*I23 -> 0 | K23: =G23+J23 -> 0 | M23: =M22+K23-L23 -> 215448.3
A24: 21 | B24: 46194 | G24: =E24*F24 -> 0 | J24: =H24*I24 -> 0 | K24: =G24+J24 -> 0 | M24: =M23+K24-L24 -> 215448.3
A25: 22 | B25: 46195 | G25: =E25*F25 -> 0 | J25: =H25*I25 -> 0 | K25: =G25+J25 -> 0 | M25: =M24+K25-L25 -> 215448.3
A26: 23 | B26: 46196 | G26: =E26*F26 -> 0 | J26: =H26*I26 -> 0 | K26: =G26+J26 -> 0 | M26: =M25+K26-L26 -> 215448.3
A27: 24 | B27: 46197 | G27: =E27*F27 -> 0 | J27: =H27*I27 -> 0 | K27: =G27+J27 -> 0 | M27: =M26+K27-L27 -> 215448.3
A28: 25 | B28: 46198 | G28: =E28*F28 -> 0 | J28: =H28*I28 -> 0 | K28: =G28+J28 -> 0 | M28: =M27+K28-L28 -> 215448.3
A29: 26 | B29: 46199 | G29: =E29*F29 -> 0 | J29: =H29*I29 -> 0 | K29: =G29+J29 -> 0 | M29: =M28+K29-L29 -> 215448.3
A30: 27 | B30: 46200 | G30: =E30*F30 -> 0 | J30: =H30*I30 -> 0 | K30: =G30+J30 -> 0 | M30: =M29+K30-L30 -> 215448.3
A31: 28 | B31: 46201 | G31: =E31*F31 -> 0 | H31: 35 | I31: 111.84 | J31: =H31*I31 -> 3914.4 | K31: =G31+J31 -> 3914.4 | M31: =M30+K31-L31 -> 219362.7
A32: 29 | B32: 46202 | G32: =E32*F32 -> 0 | J32: =H32*I32 -> 0 | K32: =G32+J32 -> 0 | M32: =M31+K32-L32 -> 219362.7
A33: 30 | B33: 46203 | G33: =E33*F33 -> 0 | J33: =H33*I33 -> 0 | K33: =G33+J33 -> 0 | M33: =M32+K33-L33 -> 219362.7
A34: 31 | G34: =E34*F34 -> 0 | J34: =H34*I34 -> 0 | K34: =G34+J34 -> 0 | M34: =M33+K34-L34 -> 219362.7
E35: =SUM(E4:E34) -> 3500 | G35: =SUM(G4:G34) -> 349720 | H35: =SUM(H4:H34) -> 175 | J35: =SUM(J4:J34) -> 19572 | K35: =SUM(K4:K34) -> 369292 | L35: =SUM(L4:L34) -> 332855

Sheet Malebenur(KUWSDB)
A1: Sree Veerabhadreshwara Service Station
A2: S.No | B2: Date | C2: GRN No | D2: Ind No/Bill No | E2: Diesel (Lts) | F2: Price | G2: Amount | H2: Petrol (Lts) | I2: Price | J2: Amount | K2: Total amount | L2: Amount paid | M2: As on Date | N2: Remarks
A3: Opening Balance | K3: 95753.51 | M3: =+K3 -> 95753.51 | O3: 46138.764
A4: 1 | B4: 45809 | E4: 600 | F4: 99.82 | G4: =E4*F4 -> 59892 | H4: 30 | I4: 111.73 | J4: =H4*I4 -> 3351.9 | K4: =G4+J4 -> 63243.9 | L4: 0 | M4: =M3+K4-L4 -> 158997.41
A5: 2 | B5: 45810 | E5: 0 | F5: 0 | G5: =E5*F5 -> 0 | H5: 0 | I5: 0 | J5: =H5*I5 -> 0 | K5: =G5+J5 -> 0 | L5: 0 | M5: =M4+K5-L5 -> 158997.41
A6: 3 | B6: 45811 | E6: 0 | F6: 0 | G6: =E6*F6 -> 0 | H6: 0 | I6: 0 | J6: =H6*I6 -> 0 | K6: =G6+J6 -> 0 | L6: 0 | M6: =M5+K6-L6 -> 158997.41
A7: 4 | B7: 45812 | E7: 0 | F7: 0 | G7: =E7*F7 -> 0 | H7: 0 | I7: 0 | J7: =H7*I7 -> 0 | K7: =G7+J7 -> 0 | L7: 0 | M7: =M6+K7-L7 -> 158997.41
A8: 5 | B8: 45813 | E8: 600 | F8: 99.82 | G8: =E8*F8 -> 59892 | H8: 20 | I8: 111.73 | J8: =H8*I8 -> 2234.6 | K8: =G8+J8 -> 62126.6 | L8: 0 | M8: =M7+K8-L8 -> 221124.01
A9: 6 | B9: 45814 | E9: 0 | F9: 0 | G9: =E9*F9 -> 0 | H9: 0 | I9: 0 | J9: =H9*I9 -> 0 | K9: =G9+J9 -> 0 | L9: 158000 | M9: =M8+K9-L9 -> 63124.01
A10: 7 | B10: 45815 | E10: 0 | F10: 0 | G10: =E10*F10 -> 0 | H10: 0 | I10: 0 | J10: =H10*I10 -> 0 | K10: =G10+J10 -> 0 | L10: 0 | M10: =M9+K10-L10 -> 63124.01
A11: 8 | B11: 45816 | E11: 0 | F11: 0 | G11: =E11*F11 -> 0 | H11: 0 | I11: 0 | J11: =H11*I11 -> 0 | K11: =G11+J11 -> 0 | L11: 0 | M11: =M10+K11-L11 -> 63124.01
A12: 9 | B12: 45817 | E12: 0 | F12: 0 | G12: =E12*F12 -> 0 | H12: 0 | I12: 0 | J12: =H12*I12 -> 0 | K12: =G12+J12 -> 0 | L12: 0 | M12: =M11+K12-L12 -> 63124.01
A13: 10 | B13: 45818 | E13: 600 | F13: 99.82 | G13: =E13*F13 -> 59892 | H13: 30 | I13: 111.73 | J13: =H13*I13 -> 3351.9 | K13: =G13+J13 -> 63243.9 | L13: 0 | M13: =M12+K13-L13 -> 126367.91
A14: 11 | B14: 45819 | E14: 0 | F14: 0 | G14: =E14*F14 -> 0 | H14: 0 | I14: 0 | J14: =H14*I14 -> 0 | K14: =G14+J14 -> 0 | L14: 0 | M14: =M13+K14-L14 -> 126367.91
A15: 12 | B15: 45820 | E15: 0 | F15: 0 | G15: =E15*F15 -> 0 | H15: 0 | I15: 0 | J15: =H15*I15 -> 0 | K15: =G15+J15 -> 0 | L15: 0 | M15: =M14+K15-L15 -> 126367.91
... A17: 14 | B17: 45822 | E17: 0 | F17: 0 | G17: =E17*F17 -> 0 | H17: 0 | I17: 0 | J17: =H17*I17 -> 0 | K17: =G17+J17 -> 0 | L17: 0 | M17: =M16+K17-L17 -> 189611.81
A18: 15 | B18: 45823 | E18: 0 | F18: 0 | G18: =E18*F18 -> 0 | H18: 0 | I18: 0 | J18: =H18*I18 -> 0 | K18: =G18+J18 -> 0 | L18: 0 | M18: =M17+K18-L18 -> 189611.81 | N18: BT
A19: 16 | B19: 45824 | E19: 0 | F19: 0 | G19: =E19*F19 -> 0 | H19: 0 | I19: 0 | J19: =H19*I19 -> 0 | K19: =G19+J19 -> 0 | L19: 189000 | M19: =M18+K19-L19 -> 611.8097
A20: 17 | B20: 45825 | E20: 600 | F20: 99.82 | G20: =E20*F20 -> 59892 | H20: 0 | I20: 0 | J20: =H20*I20 -> 0 | K20: =G20+J20 -> 59892 | L20: 0 | M20: =M19+K20-L20 -> 60503.81
A21: 18 | B21: 45826 | E21: 0 | F21: 0 | G21: =E21*F21 -> 0 | H21: 0 | I21: 0 | J21: =H21*I21 -> 0 | K21: =G21+J21 -> 0 | L21: 0 | M21: =M20+K21-L21 -> 60503.81
A22: 19 | B22: 45827 | E22: 600 | F22: 99.82 | G22: =E22*F22 -> 59892 | H22: 30 | I22: 111.73 | J22: =H22*I22 -> 3351.9 | K22: =G22+J22 -> 63243.9 | L22: 0 | M22: =M21+K22-L22 -> 123747.71
A23: 20 | B23: 45828 | E23: 0 | F23: 0 | G23: =E23*F23 -> 0 | H23: 0 | I23: 0 | J23: =H23*I23 -> 0 | K23: =G23+J23 -> 0 | L23: 0 | M23: =M22+K23-L23 -> 123747.71
A24: 21 | B24: 45829 | E24: 0 | F24: 0 | G24: =E24*F24 -> 0 | H24: 0 | I24: 0 | J24: =H24*I24 -> 0 | K24: =G24+J24 -> 0 | L24: 0 | M24: =M23+K24-L24 -> 123747.71
A25: 22 | B25: 45830 | E25: 600 | F25: 99.82 | G25: =E25*F25 -> 59892 | H25: 20 | I25: 111.73 | J25: =H25*I25 -> 2234.6 | K25: =G25+J25 -> 62126.6 | L25: 0 | M25: =M24+K25-L25 -> 185874.31
A26: 23 | B26: 45831 | E26: 0 | F26: 0 | G26: =E26*F26 -> 0 | H26: 0 | I26: 0 | J26: =H26*I26 -> 0 | K26: =G26+J26 -> 0 | L26: 0 | M26: =M25+K26-L26 -> 185874.31
A27: 24 | B27: 45832 | E27: 0 | F27: 0 | G27: =E27*F27 -> 0 | H27: 0 | I27: 0 | J27: =H27*I27 -> 0 | K27: =G27+J27 -> 0 | L27: 0 | M27: =M26+K27-L27 -> 185874.31
A28: 25 | B28: 45833 | E28: 0 | F28: 0 | G28: =E28*F28 -> 0 | H28: 0 | I28: 0 | J28: =H28*I28 -> 0 | K28: =G28+J28 -> 0 | L28: 180000 | M28: =M27+K28-L28 -> 5874.3097
A29: 26 | B29: 45834 | E29: 600 | F29: 99.82 | G29: =E29*F29 -> 59892 | H29: 30 | I29: 111.73 | J29: =H29*I29 -> 3351.9 | K29: =G29+J29 -> 63243.9 | L29: 0 | M29: =M28+K29-L29 -> 69118.21
A30: 27 | B30: 45835 | E30: 0 | F30: 0 | G30: =E30*F30 -> 0 | H30: 0 | I30: 0 | J30: =H30*I30 -> 0 | K30: =G30+J30 -> 0 | L30: 0 | M30: =M29+K30-L30 -> 69118.21
... A34: 31 | B34: 45839 | E34: 0 | F34: 0 | G34: =E34*F34 -> 0 | H34: 0 | I34: 0 | J34: =H34*I34 -> 0 | K34: =G34+J34 -> 0 | L34: 0 | M34: =M33+K34-L34 -> 132362.11
E35: 0 | F35: 0 | G35: =E35*F35 -> 0 | H35: 0 | I35: 0 | J35: =H35*I35 -> 0 | K35: =G35+J35 -> 0 | L35: 0 | M35: =M34+K35-L35 -> 132362.11
E36: 0 | F36: 0 | G36: =E36*F36 -> 0 | H36: 0 | I36: 0 | J36: =H36*I36 -> 0 | K36: =G36+J36 -> 0 | L36: 0 | M36: =M35+K36-L36 -> 132362.11
E37: =SUM(E4:E35) -> 5400 | G37: =SUM(G4:G35) -> 539028 | H37: =SUM(H4:H35) -> 220 | J37: =SUM(J4:J35) -> 24580.6 | K37: =SUM(K4:K35) -> 563608.6 | L37: =SUM(L4:L35) -> 527000
E38: 0 | G38: 0 | H38: 0 | J38: 0 | K38: =G38+J38 -> 0 | L38: 0
S43: 9052944708

Sheet Molakamuru
A1: Molakamuru
A2: S.No | B2: Date | C2: GRN No | D2: Ind No/Bill No | E2: Diesel (Lts) | F2: Price | G2: Amount | H2: Petrol (Lts) | I2: Price | J2: Amount | K2: Total amount | L2: Amount paid | M2: As on Date | N2: Remarks
A3: Opening Balance | K3: 62820 | L3: 0 | M3: 62820
A4: 1 | B4: 46174 | G4: =E4*F4 -> 0 | J4: =H4*I4 -> 0 | K4: =G4+J4 -> 0 | M4: =M3+K4-L4 -> 62820
A5: 2 | B5: 46175 | G5: =E5*F5 -> 0 | J5: =H5*I5 -> 0 | K5: =G5+J5 -> 0 | M5: =M4+K5-L5 -> 62820
A6: 3 | B6: 46176 | G6: =E6*F6 -> 0 | J6: =H6*I6 -> 0 | K6: =G6+J6 -> 0 | M6: =M5+K6-L6 -> 62820
A7: 4 | B7: 46177 | G7: =E7*F7 -> 0 | J7: =H7*I7 -> 0 | K7: =G7+J7 -> 0 | M7: =M6+K7-L7 -> 62820
A8: 5 | B8: 46178 | G8: =E8*F8 -> 0 | J8: =H8*I8 -> 0 | K8: =G8+J8 -> 0 | M8: =M7+K8-L8 -> 62820
A9: 6 | B9: 46179 | E9: 340 | F9: 99.87 | G9: =E9*F9 -> 33955.8 | H9: 17 | I9: 111.78 | J9: =H9*I9 -> 1900.26 | K9: =G9+J9 -> 35856.06 | L9: 62000 | M9: =M8+K9-L9 -> 36676.06
A10: 7 | B10: 46180 | G10: =E10*F10 -> 0 | J10: =H10*I10 -> 0 | K10: =G10+J10 -> 0 | M10: =M9+K10-L10 -> 36676.06
A11: 8 | B11: 46181 | G11: =E11*F11 -> 0 | J11: =H11*I11 -> 0 | K11: =G11+J11 -> 0 | M11: =M10+K11-L11 -> 36676.06
A12: 9 | B12: 46182 | G12: =E12*F12 -> 0 | H12: 35 | I12: 111.78 | J12: =H12*I12 -> 3912.3 | K12: =G12+J12 -> 3912.3 | M12: =M11+K12-L12 -> 40588.36
A13: 10 | B13: 46183 | G13: =E13*F13 -> 0 | J13: =H13*I13 -> 0 | K13: =G13+J13 -> 0 | M13: =M12+K13-L13 -> 40588.36
A14: 11 | B14: 46184 | G14: =E14*F14 -> 0 | J14: =H14*I14 -> 0 | K14: =G14+J14 -> 0 | M14: =M13+K14-L14 -> 40588.36
A15: 12 | B15: 46185 | G15: =E15*F15 -> 0 | J15: =H15*I15 -> 0 | K15: =G15+J15 -> 0 | M15: =M14+K15-L15 -> 40588.36
A16: 13 | B16: 46186 | E16: 300 | F16: 99.87 | G16: =E16*F16 -> 29961 | H16: 20 | I16: 111.78 | J16: =H16*I16 -> 2235.6 | K16: =G16+J16 -> 32196.6 | M16: =M15+K16-L16 -> 72784.96
A17: 14 | B17: 46187 | G17: =E17*F17 -> 0 | J17: =H17*I17 -> 0 | K17: =G17+J17 -> 0 | M17: =M16+K17-L17 -> 72784.96
A18: 15 | B18: 46188 | G18: =E18*F18 -> 0 | J18: =H18*I18 -> 0 | K18: =G18+J18 -> 0 | M18: =M17+K18-L18 -> 72784.96
A19: 16 | B19: 46189 | G19: =E19*F19 -> 0 | J19: =H19*I19 -> 0 | K19: =G19+J19 -> 0 | L19: 40000 | M19: =M18+K19-L19 -> 32784.96
A20: 17 | B20: 46190 | G20: =E20*F20 -> 0 | H20: 35 | I20: 111.78 | J20: =H20*I20 -> 3912.3 | K20: =G20+J20 -> 3912.3 | M20: =M19+K20-L20 -> 36697.26
A21: 18 | B21: 46191 | G21: =E21*F21 -> 0 | J21: =H21*I21 -> 0 | K21: =G21+J21 -> 0 | M21: =M20+K21-L21 -> 36697.26
A22: 19 | B22: 46192 | G22: =E22*F22 -> 0 | J22: =H22*I22 -> 0 | K22: =G22+J22 -> 0 | M22: =M21+K22-L22 -> 36697.26
A23: 20 | B23: 46193 | G23: =E23*F23 -> 0 | J23: =H23*I23 -> 0 | K23: =G23+J23 -> 0 | M23: =M22+K23-L23 -> 36697.26
A24: 21 | B24: 46194 | G24: =E24*F24 -> 0 | J24: =H24*I24 -> 0 | K24: =G24+J24 -> 0 | M24: =M23+K24-L24 -> 36697.26
A25: 22 | B25: 46195 | G25: =E25*F25 -> 0 | J25: =H25*I25 -> 0 | K25: =G25+J25 -> 0 | M25: =M24+K25-L25 -> 36697.26
A26: 23 | B26: 46196 | G26: =E26*F26 -> 0 | J26: =H26*I26 -> 0 | K26: =G26+J26 -> 0 | M26: =M25+K26-L26 -> 36697.26
A27: 24 | B27: 46197 | E27: 400 | F27: 99.87 | G27: =E27*F27 -> 39948 | J27: =H27*I27 -> 0 | K27: =G27+J27 -> 39948 | M27: =M26+K27-L27 -> 76645.26
A28: 25 | B28: 46198 | G28: =E28*F28 -> 0 | J28: =H28*I28 -> 0 | K28: =G28+J28 -> 0 | L28: 70000 | M28: =M27+K28-L28 -> 6645.26
A29: 26 | B29: 46199 | G29: =E29*F29 -> 0 | J29: =H29*I29 -> 0 | K29: =G29+J29 -> 0 | M29: =M28+K29-L29 -> 6645.26
A30: 27 | B30: 46200 | G30: =E30*F30 -> 0 | H30: 20 | I30: 111.78 | J30: =H30*I30 -> 2235.6 | K30: =G30+J30 -> 2235.6 | M30: =M29+K30-L30 -> 8880.86
A31: 28 | B31: 46201 | G31: =E31*F31 -> 0 | J31: =H31*I31 -> 0 | K31: =G31+J31 -> 0 | M31: =M30+K31-L31 -> 8880.86
A32: 29 | B32: 46202 | G32: =E32*F32 -> 0 | J32: =H32*I32 -> 0 | K32: =G32+J32 -> 0 | M32: =M31+K32-L32 -> 8880.86
A33: 30 | B33: 46203 | G33: =E33*F33 -> 0 | J33: =H33*I33 -> 0 | K33: =G33+J33 -> 0 | M33: =M32+K33-L33 -> 8880.86
A34: 31 | G34: =E34*F34 -> 0 | K34: =G34+J34 -> 0 | L34: 0 | M34: =M33+K34-L34 -> 8880.86
E35: =SUM(E4:E34) -> 1040 | G35: =SUM(G4:G34) -> 103864.8 | H35: =SUM(H4:H34) -> 127 | J35: =SUM(J4:J34) -> 14196.06 | K35: =SUM(K4:K34) -> 118060.86 | L35: =SUM(L4:L34) -> 172000

Sheet Chellakere -1
A1: Shivaganga Service Station (BPCL)
A2: S.No | B2: Date | C2: GRN No | D2: Ind No/Bill No | E2: Diesel (Lts) | F2: Price | G2: Amount | H2: Petrol (Lts) | I2: Price | J2: Amount | K2: Total amount | L2: Amount paid | M2: As on Date | N2: Remarks
A3: Opening Balance | K3: 71615.087 | L3: 71615.087 | M3: 71615.087
A4: 1 | B4: 46174 | G4: =E4*F4 -> 0 | J4: =H4*I4 -> 0 | K4: =G4+J4 -> 0 | M4: =M3+K4-L4 -> 71615.087
A5: 2 | B5: 46175 | E5: 600.72 | F5: 99.88 | G5: =E5*F5 -> 59999.914 | H5: 35 | I5: 111.79 | J5: =H5*I5 -> 3912.65 | K5: =G5+J5 -> 63912.564 | M5: =M4+K5-L5 -> 135527.65
A6: 3 | B6: 46176 | G6: =E6*F6 -> 0 | J6: =H6*I6 -> 0 | K6: =G6+J6 -> 0 | M6: =M5+K6-L6 -> 135527.65 | R6: =L7+L8 -> 19972
A7: 4 | B7: 46177 | G7: =E7*F7 -> 0 | J7: =H7*I7 -> 0 | K7: =G7+J7 -> 0 | M7: =M6+K7-L7 -> 135527.65
A8: 5 | B8: 46178 | E8: 200 | F8: 99.86 | G8: =E8*F8 -> 19972 | J8: =H8*I8 -> 0 | K8: =G8+J8 -> 19972 | L8: =H8+K8 -> 19972 | M8: =M7+K8-L8 -> 135527.65 | N8: HPCL OTP
A9: 6 | B9: 46179 | E9: 800 | F9: 99.88 | G9: =E9*F9 -> 79904 | H9: 35 | I9: 111.79 | J9: =H9*I9 -> 3912.65 | K9: =G9+J9 -> 83816.65 | L9: 135514 | M9: =M8+K9-L9 -> 83830.3 | Q9: 54242
A10: 7 | B10: 46180 | G10: =E10*F10 -> 0 | J10: =H10*I10 -> 0 | K10: =G10+J10 -> 0 | M10: =M9+K10-L10 -> 83830.3 | S10: 80000
A11: 8 | B11: 46181 | G11: =E11*F11 -> 0 | J11: =H11*I11 -> 0 | K11: =G11+J11 -> 0 | M11: =M10+K11-L11 -> 83830.3 | S11: 18414
A12: 9 | B12: 46182 | G12: =E12*F12 -> 0 | J12: =H12*I12 -> 0 | K12: =G12+J12 -> 0 | M12: =M11+K12-L12 -> 83830.3 | S12: 18414
A13: 10 | B13: 46183 | G13: =E13*F13 -> 0 | J13: =H13*I13 -> 0 | K13: =G13+J13 -> 0 | M13: =M12+K13-L13 -> 83830.3 | S13: 18417.68
A14: 11 | B14: 46184 | G14: =E14*F14 -> 0 | H14: 35 | I14: 111.79 | J14: =H14*I14 -> 3912.65 | K14: =G14+J14 -> 3912.65 | M14: =M13+K14-L14 -> 87742.95 | S14: =SUM(S10:S13) -> 135245.68
A15: 12 | B15: 46185 | G15: =E15*F15 -> 0 | J15: =H15*I15 -> 0 | K15: =G15+J15 -> 0 | M15: =M14+K15-L15 -> 87742.95
A16: 13 | B16: 46186 | G16: =E16*F16 -> 0 | J16: =H16*I16 -> 0 | K16: =G16+J16 -> 0 | M16: =M15+K16-L16 -> 87742.95
A17: 14 | B17: 46187 | G17: =E17*F17 -> 0 | J17: =H17*I17 -> 0 | K17: =G17+J17 -> 0 | M17: =M16+K17-L17 -> 87742.95
A18: 15 | B18: 46188 | E18: 599.99 | F18: 99.88 | G18: =E18*F18 -> 59927.001 | H18: 35 | I18: 111.79 | J18: =H18*I18 -> 3912.65 | K18: =G18+J18 -> 63839.651 | M18: =M17+K18-L18 -> 151582.6
A19: 16 | B19: 46189 | G19: =E19*F19 -> 0 | J19: =H19*I19 -> 0 | K19: =G19+J19 -> 0 | L19: 87000 | M19: =M18+K19-L19 -> 64582.601
A20: 17 | B20: 46190 | G20: =E20*F20 -> 0 | J20: =H20*I20 -> 0 | K20: =G20+J20 -> 0 | M20: =M19+K20-L20 -> 64582.601
A21: 18 | B21: 46191 | E21: 600 | F21: 99.88 | G21: =E21*F21 -> 59928 | H21: 35 | I21: 111.79 | J21: =H21*I21 -> 3912.65 | K21: =G21+J21 -> 63840.65 | M21: =M20+K21-L21 -> 128423.25
A22: 19 | B22: 46192 | G22: =E22*F22 -> 0 | J22: =H22*I22 -> 0 | K22: =G22+J22 -> 0 | M22: =M21+K22-L22 -> 128423.25
A23: 20 | B23: 46193 | G23: =E23*F23 -> 0 | J23: =H23*I23 -> 0 | K23: =G23+J23 -> 0 | M23: =M22+K23-L23 -> 128423.25
B24: 46194 | M24: =M23+K24-L24 -> 128423.25
A25: 21 | B25: 46195 | E25: 600 | F25: 99.88 | G25: =E25*F25 -> 59928 | J25: =H25*I25 -> 0 | K25: =G25+J25 -> 59928 | M25: =M24+K25-L25 -> 188351.25
A26: 22 | B26: 46196 | G26: =E26*F26 -> 0 | J26: =H26*I26 -> 0 | K26: =G26+J26 -> 0 | M26: =M25+K26-L26 -> 188351.25
A27: 23 | B27: 46197 | E27: 400 | F27: 99.88 | G27: =E27*F27 -> 39952 | H27: 35 | I27: 111.79 | J27: =H27*I27 -> 3912.65 | K27: =G27+J27 -> 43864.65 | M27: =M26+K27-L27 -> 232215.9
A28: 24 | B28: 46198 | G28: =E28*F28 -> 0 | J28: =H28*I28 -> 0 | K28: =G28+J28 -> 0 | L28: 180000 | M28: =M27+K28-L28 -> 52215.901
A29: 25 | B29: 46199 | G29: =E29*F29 -> 0 | J29: =H29*I29 -> 0 | K29: =G29+J29 -> 0 | M29: =M28+K29-L29 -> 52215.901
A30: 26 | B30: 46200 | G30: =E30*F30 -> 0 | J30: =H30*I30 -> 0 | K30: =G30+J30 -> 0 | M30: =M29+K30-L30 -> 52215.901
A31: 27 | B31: 46201 | G31: =E31*F31 -> 0 | J31: =H31*I31 -> 0 | K31: =G31+J31 -> 0 | M31: =M30+K31-L31 -> 52215.901
A32: 28 | B32: 46202 | E32: 600 | F32: 99.88 | G32: =E32*F32 -> 59928 | H32: 35 | I32: 111.79 | J32: =H32*I32 -> 3912.65 | K32: =G32+J32 -> 63840.65 | M32: =M31+K32-L32 -> 116056.55
A33: 29 | B33: 46203 | G33: =E33*F33 -> 0 | J33: =H33*I33 -> 0 | K33: =G33+J33 -> 0 | M33: =M32+K33-L33 -> 116056.55
A34: 30 | G34: =E34*F34 -> 0 | J34: =H34*I34 -> 0 | K34: =G34+J34 -> 0 | M34: =M33+K34-L34 -> 116056.55
A35: 31 | G35: =E35*F35 -> 0 | J35: =H35*I35 -> 0 | K35: =G35+J35 -> 0 | M35: =M34+K35-L35 -> 116056.55
E38: =SUM(E4:E35) -> 4400.71 | G38: =SUM(G4:G35) -> 439538.91 | H38: =SUM(H4:H35) -> 245 | J38: =SUM(J4:J35) -> 27388.55 | K38: =SUM(K4:K35) -> 466927.46 | L38: =SUM(L4:L35) -> 422486

Sheet  Chellakere-PKG-9
A1: Chellakere-PKG-09
A2: S.No | B2: Date | C2: GRN No | D2: Ind No/Bill No | E2: Diesel (Lts) | F2: Price | G2: Amount | H2: Petrol (Lts) | I2: Price | J2: Amount | K2: Total amount | L2: Amount paid | M2: As on Date | N2: Remarks
A3: Opening Balance | K3: 0 | L3: 0 | M3: 0
A4: 1 | B4: 46174 | E4: 38.07 | F4: 99.88 | G4: =E4*F4 -> 3802.4316 | H4: 5 | I4: 111.79 | J4: =H4*I4 -> 558.95 | K4: =G4+J4 -> 4361.3816 | L4: =K4 -> 4361.3816 | M4: =M3+K4-L4 -> 0
A5: 2 | B5: 46175 | G5: =E5*F5 -> 0 | J5: =H5*I5 -> 0 | K5: =G5+J5 -> 0 | L5: =K5 -> 0 | M5: =M4+K5-L5 -> 0
A6: 3 | B6: 46176 | E6: 25 | F6: 99.88 | G6: =E6*F6 -> 2497 | H6: 15 | I6: 111.79 | J6: =H6*I6 -> 1676.85 | K6: =G6+J6 -> 4173.85 | L6: =K6 -> 4173.85 | M6: =M5+K6-L6 -> 0
A7: 4 | B7: 46177 | G7: =E7*F7 -> 0 | J7: =H7*I7 -> 0 | K7: =G7+J7 -> 0 | L7: =K7 -> 0 | M7: =M6+K7-L7 -> 0
A8: 5 | B8: 46178 | E8: 75 | F8: 99.88 | G8: =E8*F8 -> 7491 | J8: =H8*I8 -> 0 | K8: =G8+J8 -> 7491 | L8: =K8 -> 7491 | M8: =M7+K8-L8 -> 0
A9: 6 | B9: 46179 | E9: 40 | F9: 99.88 | G9: =E9*F9 -> 3995.2 | J9: =H9*I9 -> 0 | K9: =G9+J9 -> 3995.2 | L9: =K9 -> 3995.2 | M9: =M8+K9-L9 -> 0
A10: 7 | B10: 46180 | G10: =E10*F10 -> 0 | J10: =H10*I10 -> 0 | K10: =G10+J10 -> 0 | L10: =K10 -> 0 | M10: =M9+K10-L10 -> 0
A11: 8 | B11: 46181 | E11: 61.41 | F11: 99.88 | G11: =E11*F11 -> 6133.6308 | J11: =H11*I11 -> 0 | K11: =G11+J11 -> 6133.6308 | L11: =K11 -> 6133.6308 | M11: =M10+K11-L11 -> 0
A12: 9 | B12: 46182 | G12: =E12*F12 -> 0 | J12: =H12*I12 -> 0 | K12: =G12+J12 -> 0 | L12: =K12 -> 0 | M12: =M11+K12-L12 -> 0
A13: 10 | B13: 46183 | E13: 70 | F13: 99.88 | G13: =E13*F13 -> 6991.6 | J13: =H13*I13 -> 0 | K13: =G13+J13 -> 6991.6 | L13: =K13 -> 6991.6 | M13: =M12+K13-L13 -> 0
A14: 11 | B14: 46184 | E14: 160 | F14: 99.88 | G14: =E14*F14 -> 15980.8 | J14: =H14*I14 -> 0 | K14: =G14+J14 -> 15980.8 | L14: =K14 -> 15980.8 | M14: =M13+K14-L14 -> 0
A15: 12 | B15: 46185 | G15: =E15*F15 -> 0 | J15: =H15*I15 -> 0 | K15: =G15+J15 -> 0 | L15: =K15 -> 0 | M15: =M14+K15-L15 -> 0
A16: 13 | B16: 46186 | G16: =E16*F16 -> 0 | J16: =H16*I16 -> 0 | K16: =G16+J16 -> 0 | L16: =K16 -> 0 | M16: =M15+K16-L16 -> 0
A17: 14 | B17: 46187 | E17: 200 | F17: 99.88 | G17: =E17*F17 -> 19976 | H17: 6 | I17: 111.78 | J17: =H17*I17 -> 670.68 | K17: =G17+J17 -> 20646.68 | L17: =K17 -> 20646.68 | M17: =M16+K17-L17 -> 0
A18: 15 | B18: 46188 | G18: =E18*F18 -> 0 | J18: =H18*I18 -> 0 | K18: =G18+J18 -> 0 | L18: =K18 -> 0 | M18: =M17+K18-L18 -> 0
A19: 16 | B19: 46189 | G19: =E19*F19 -> 0 | J19: =H19*I19 -> 0 | K19: =G19+J19 -> 0 | L19: =K19 -> 0 | M19: =M18+K19-L19 -> 0
A20: 17 | B20: 46190 | E20: 40.22 | F20: 99.88 | G20: =E20*F20 -> 4017.1736 | H20: 12 | I20: 111.79 | J20: =H20*I20 -> 1341.48 | K20: =G20+J20 -> 5358.6536 | L20: =K20 -> 5358.6536 | M20: =M19+K20-L20 -> 0 | T20: 54.83
A21: 18 | B21: 46191 | E21: 74.95 | F21: 99.88 | G21: =E21*F21 -> 7486.006 | J21: =H21*I21 -> 0 | K21: =G21+J21 -> 7486.006 | L21: =K21 -> 7486.006 | M21: =M20+K21-L21 -> 0 | T21: 0.55
A22: 19 | B22: 46192 | G22: =E22*F22 -> 0 | H22: 12 | I22: 111.79 | J22: =H22*I22 -> 1341.48 | K22: =G22+J22 -> 1341.48 | L22: =K22 -> 1341.48 | M22: =M21+K22-L22 -> 0
B23: 46193 | G23: =E23*F23 -> 0 | K23: =G23+J23 -> 0 | L23: =K23 -> 0
A24: 20 | B24: 46194 | E24: 66.96 | F24: 99.88 | G24: =E24*F24 -> 6687.9648 | H24: 6 | I24: 111.79 | J24: =H24*I24 -> 670.74 | K24: =G24+J24 -> 7358.7048 | L24: =K24 -> 7358.7048 | M24: =M22+K24-L24 -> 0
A25: 21 | B25: 46195 | G25: =E25*F25 -> 0 | J25: =H25*I25 -> 0 | K25: =G25+J25 -> 0 | L25: =K25 -> 0 | M25: =M24+K25-L25 -> 0
A26: 22 | B26: 46196 | G26: =E26*F26 -> 0 | J26: =H26*I26 -> 0 | K26: =G26+J26 -> 0 | L26: =K26 -> 0 | M26: =M25+K26-L26 -> 0
A27: 23 | B27: 46197 | E27: 44.67 | F27: 99.88 | G27: =E27*F27 -> 4461.6396 | H27: 6 | I27: 111.79 | J27: =H27*I27 -> 670.74 | K27: =G27+J27 -> 5132.3796 | L27: =K27 -> 5132.3796 | M27: =M26+K27-L27 -> 0
A28: 24 | B28: 46198 | G28: =E28*F28 -> 0 | J28: =H28*I28 -> 0 | K28: =G28+J28 -> 0 | L28: =K28 -> 0 | M28: =M27+K28-L28 -> 0
A29: 25 | B29: 46199 | G29: =E29*F29 -> 0 | J29: =H29*I29 -> 0 | K29: =G29+J29 -> 0 | L29: =K29 -> 0 | M29: 0
A30: 26 | B30: 46200 | E30: 46.29 | F30: 99.88 | G30: =E30*F30 -> 4623.4452 | H30: 13.01 | I30: 111.79 | J30: =H30*I30 -> 1454.3879 | K30: =G30+J30 -> 6077.8331 | L30: =K30 -> 6077.8331 | M30: 0
A31: 27 | B31: 46201 | G31: =E31*F31 -> 0 | J31: =H31*I31 -> 0 | K31: =G31+J31 -> 0 | L31: =K31 -> 0 | M31: 0
A32: 28 | B32: 46202 | G32: =E32*F32 -> 0 | H32: 6 | I32: 111.79 | J32: =H32*I32 -> 670.74 | K32: =G32+J32 -> 670.74 | L32: =K32 -> 670.74 | M32: 0
A33: 29 | B33: 46203 | G33: =E33*F33 -> 0 | J33: =H33*I33 -> 0 | K33: =G33+J33 -> 0 | L33: =K33 -> 0
A34: 30 | G34: =E34*F34 -> 0 | J34: =H34*I34 -> 0 | K34: =G34+J34 -> 0 | L34: =K34 -> 0
A35: 31 | G35: =E35*F35 -> 0 | J35: =H35*I35 -> 0 | K35: =G35+J35 -> 0 | L35: =K35 -> 0
E36: =SUM(E4:E35) -> 942.57 | G36: =SUM(G4:G35) -> 94143.892 | H36: =SUM(H4:H35) -> 81.01 | J36: =SUM(J4:J35) -> 9056.0479 | K36: =SUM(K4:K35) -> 103199.94 | L36: =SUM(L4:L35) -> 103199.94

Sheet  Chennagiri
A1: Chennagiri
A2: S.No | B2: Date | C2: GRN No | D2: Ind No/Bill No | E2: Diesel (Lts) | F2: Price | G2: Amount | H2: Petrol (Lts) | I2: Price | J2: Amount | K2: Total amount | L2: Amount paid | M2: As on Date | N2: Remarks
A3: Opening Balance | K3: 0 | L3: 0 | M3: =+K3 -> 0
A4: 1 | B4: 46174 | E4: 100 | F4: 99.7 | G4: =E4*F4 -> 9970 | J4: =H4*I4 -> 0 | K4: =G4+J4 -> 9970 | L4: =K4 -> 9970 | M4: =M3+K4-L4 -> 0
A5: 2 | B5: 46175 | E5: 150 | F5: 99.7 | G5: =E5*F5 -> 14955 | J5: =H5*I5 -> 0 | K5: =G5+J5 -> 14955 | L5: =K5 -> 14955 | M5: =M4+K5-L5 -> 0
A6: 3 | B6: 46176 | G6: =E6*F6 -> 0 | J6: =H6*I6 -> 0 | K6: =G6+J6 -> 0 | L6: =K6 -> 0 | M6: =M5+K6-L6 -> 0
A7: 4 | B7: 46177 | G7: =E7*F7 -> 0 | J7: =H7*I7 -> 0 | K7: =G7+J7 -> 0 | L7: =K7 -> 0 | M7: =M6+K7-L7 -> 0
A8: 5 | B8: 46178 | E8: 100 | F8: 99.7 | G8: =E8*F8 -> 9970 | J8: =H8*I8 -> 0 | K8: =G8+J8 -> 9970 | L8: =K8 -> 9970 | M8: =M7+K8-L8 -> 0
A9: 6 | B9: 46179 | E9: 150 | F9: 99.7 | G9: =E9*F9 -> 14955 | J9: =H9*I9 -> 0 | K9: =G9+J9 -> 14955 | L9: =K9 -> 14955 | M9: =M8+K9-L9 -> 0
A10: 7 | B10: 46180 | G10: =E10*F10 -> 0 | J10: =H10*I10 -> 0 | K10: =G10+J10 -> 0 | L10: =K10 -> 0 | M10: =M9+K10-L10 -> 0
A11: 8 | B11: 46181 | G11: =E11*F11 -> 0 | J11: =H11*I11 -> 0 | K11: =G11+J11 -> 0 | L11: =K11 -> 0 | M11: =M10+K11-L11 -> 0
A12: 9 | B12: 46182 | E12: 100 | F12: 99.7 | G12: =E12*F12 -> 9970 | J12: =H12*I12 -> 0 | K12: =G12+J12 -> 9970 | L12: =K12 -> 9970 | M12: =M11+K12-L12 -> 0 | N12: HPCL
A13: 10 | B13: 46183 | E13: 150 | F13: 99.7 | G13: =E13*F13 -> 14955 | H13: 44 | I13: 111.78 | J13: =H13*I13 -> 4918.32 | K13: =G13+J13 -> 19873.32 | L13: =K13 -> 19873.32 | M13: =M12+K13-L13 -> 0 | N13: HPCL
A14: 11 | B14: 46184 | G14: =E14*F14 -> 0 | J14: =H14*I14 -> 0 | K14: =G14+J14 -> 0 | L14: =K14 -> 0 | M14: =M13+K14-L14 -> 0
A15: 12 | B15: 46185 | G15: =E15*F15 -> 0 | J15: =H15*I15 -> 0 | K15: =G15+J15 -> 0 | L15: =K15 -> 0 | M15: =M14+K15-L15 -> 0
A16: 13 | B16: 46186 | G16: =E16*F16 -> 0 | J16: =H16*I16 -> 0 | K16: =G16+J16 -> 0 | L16: =K16 -> 0 | M16: =M15+K16-L16 -> 0
A17: 14 | B17: 46187 | G17: =E17*F17 -> 0 | J17: =H17*I17 -> 0 | K17: =G17+J17 -> 0 | L17: =K17 -> 0 | M17: =M16+K17-L17 -> 0
A18: 15 | B18: 46188 | G18: =E18*F18 -> 0 | J18: =H18*I18 -> 0 | K18: =G18+J18 -> 0 | L18: =K18 -> 0 | M18: =M17+K18-L18 -> 0
A19: 16 | B19: 46189 | E19: 195 | F19: 99.7 | G19: =E19*F19 -> 19441.5 | J19: =H19*I19 -> 0 | K19: =G19+J19 -> 19441.5 | L19: =K19 -> 19441.5 | M19: =M18+K19-L19 -> 0
A20: 17 | B20: 46190 | G20: =E20*F20 -> 0 | J20: =H20*I20 -> 0 | K20: =G20+J20 -> 0 | L20: =K20 -> 0 | M20: =M19+K20-L20 -> 0 | N20: HPCL
A21: 18 | B21: 46191 | E21: 195 | F21: 99.7 | G21: =E21*F21 -> 19441.5 | J21: =H21*I21 -> 0 | K21: =G21+J21 -> 19441.5 | L21: =K21 -> 19441.5 | M21: =M20+K21-L21 -> 0 | N21: HPCL
A22: 19 | B22: 46192 | G22: =E22*F22 -> 0 | J22: =H22*I22 -> 0 | K22: =G22+J22 -> 0 | L22: =K22 -> 0 | M22: =M21+K22-L22 -> 0
A23: 20 | B23: 46193 | E23: 195 | F23: 99.7 | G23: =E23*F23 -> 19441.5 | J23: =H23*I23 -> 0 | K23: =G23+J23 -> 19441.5 | L23: =K23 -> 19441.5 | M23: =M22+K23-L23 -> 0
A24: 21 | B24: 46194 | G24: =E24*F24 -> 0 | J24: =H24*I24 -> 0 | K24: =G24+J24 -> 0 | L24: =K24 -> 0 | M24: =M23+K24-L24 -> 0
A25: 22 | B25: 46195 | G25: =E25*F25 -> 0 | J25: =H25*I25 -> 0 | K25: =G25+J25 -> 0 | L25: =K25 -> 0 | M25: =M24+K25-L25 -> 0
A26: 23 | B26: 46196 | E26: 195 | F26: 99.7 | G26: =E26*F26 -> 19441.5 | J26: =H26*I26 -> 0 | K26: =G26+J26 -> 19441.5 | L26: =K26 -> 19441.5 | M26: =M25+K26-L26 -> 0
A27: 24 | B27: 46197 | G27: =E27*F27 -> 0 | J27: =H27*I27 -> 0 | K27: =G27+J27 -> 0 | L27: =K27 -> 0 | M27: =M26+K27-L27 -> 0
A28: 25 | B28: 46198 | E28: 195 | F28: 99.7 | G28: =E28*F28 -> 19441.5 | J28: =H28*I28 -> 0 | K28: =G28+J28 -> 19441.5 | L28: =K28 -> 19441.5 | M28: 0
A29: 26 | B29: 46199 | G29: =E29*F29 -> 0 | J29: =H29*I29 -> 0 | K29: =G29+J29 -> 0 | L29: =K29 -> 0 | M29: 0
A30: 27 | B30: 46200 | E30: 195 | F30: 99.7 | G30: =E30*F30 -> 19441.5 | J30: =H30*I30 -> 0 | K30: =G30+J30 -> 19441.5 | L30: =K30 -> 19441.5 | M30: 0 | N30: HPCL
A31: 28 | B31: 46201 | G31: =E31*F31 -> 0 | J31: =H31*I31 -> 0 | K31: =G31+J31 -> 0 | L31: =K31 -> 0 | M31: 0
A32: 29 | B32: 46202 | G32: =E32*F32 -> 0 | J32: =H32*I32 -> 0 | K32: =G32+J32 -> 0 | L32: =K32 -> 0
A33: 30 | B33: 46203 | G33: =E33*F33 -> 0 | J33: =H33*I33 -> 0 | K33: =G33+J33 -> 0 | L33: =K33 -> 0
A34: 31 | B34: 46204 | G34: =E34*F34 -> 0 | K34: =G34+J34 -> 0 | L34: =K34 -> 0
E35: =SUM(E4:E34) -> 1920 | G35: =SUM(G4:G34) -> 191424 | H35: =SUM(H4:H34) -> 44 | J35: =SUM(J4:J34) -> 4918.32 | K35: =SUM(K4:K34) -> 196342.32 | L35: =SUM(L4:L34) -> 196342.32

Sheet Khanapur
A1: V.V.Varde
A2: S.No | B2: Date | C2: GRN No | D2: Ind No/Bill No | E2: Diesel (Lts) | F2: Price | G2: Amount | H2: Petrol (Lts) | I2: Price | J2: Amount | K2: Total amount | L2: Date of payment | M2: Amount paid | N2: Remarks
D3: Opening Balance | K3: 59025.654 | M3: 59025.654
A4: 1 | B4: 46174 | G4: =E4*F4 -> 0 | H4: 5 | I4: 110.74 | J4: =H4*I4 -> 553.7 | K4: =G4+J4 -> 553.7 | M4: =M3+K4-L4 -> 59579.354
A5: 2 | B5: 46175 | G5: =E5*F5 -> 0 | H5: 5 | I5: 110.74 | J5: =H5*I5 -> 553.7 | K5: =G5+J5 -> 553.7 | M5: =M4+K5-L5 -> 60133.054 | S5: 90.88 | T5: 102.77
A6: 3 | B6: 46176 | E6: 76.01 | F6: 98.61 | G6: =E6*F6 -> 7495.3461 | H6: 5 | I6: 110.74 | J6: =H6*I6 -> 553.7 | K6: =G6+J6 -> 8049.0461 | M6: =M5+K6-L6 -> 68182.1
A7: 4 | B7: 46177 | E7: 41.84 | F7: 98.61 | G7: =E7*F7 -> 4125.8424 | H7: 5 | I7: 110.74 | J7: =H7*I7 -> 553.7 | K7: =G7+J7 -> 4679.5424 | M7: =M6+K7-L7 -> 72861.642
A8: 5 | B8: 46178 | G8: =E8*F8 -> 0 | J8: =H8*I8 -> 0 | K8: =G8+J8 -> 0 | M8: =M7+K8-L8 -> 72861.642
A9: 6 | B9: 46179 | E9: 30 | F9: 98.61 | G9: =E9*F9 -> 2958.3 | H9: 5 | I9: 110.74 | J9: =H9*I9 -> 553.7 | K9: =G9+J9 -> 3512 | M9: =M8+K9-L9 -> 76373.642
A10: 7 | B10: 46180 | E10: 100 | F10: 98.61 | G10: =E10*F10 -> 9861 | J10: =H10*I10 -> 0 | K10: =G10+J10 -> 9861 | M10: =M9+K10-L10 -> 86234.642
A11: 8 | B11: 46181 | E11: 48.12 | F11: 98.69 | G11: =E11*F11 -> 4748.9628 | H11: 5 | I11: 110.74 | J11: =H11*I11 -> 553.7 | K11: =G11+J11 -> 5302.6628 | L11: 86235 | M11: =M10+K11-L11 -> 5302.3053
A12: 9 | B12: 46182 | E12: 84 | F12: 98.69 | G12: =E12*F12 -> 8289.96 | J12: =H12*I12 -> 0 | K12: =G12+J12 -> 8289.96 | M12: =M11+K12-L12 -> 13592.265
A13: 10 | B13: 46183 | E13: 5 | F13: 98.69 | G13: =E13*F13 -> 493.45 | H13: 15 | I13: 110.74 | J13: =H13*I13 -> 1661.1 | K13: =G13+J13 -> 2154.55 | M13: =M12+K13-L13 -> 15746.815
A14: 11 | B14: 46184 | E14: 5 | F14: 98.69 | G14: =E14*F14 -> 493.45 | J14: =H14*I14 -> 0 | K14: =G14+J14 -> 493.45 | M14: =M13+K14-L14 -> 16240.265
A15: 12 | B15: 46185 | G15: =E15*F15 -> 0 | J15: =H15*I15 -> 0 | K15: =G15+J15 -> 0 | M15: =M14+K15-L15 -> 16240.265
A16: 13 | B16: 46186 | E16: 125 | F16: 98.69 | G16: =E16*F16 -> 12336.25 | J16: =H16*I16 -> 0 | K16: =G16+J16 -> 12336.25 | M16: =M15+K16-L16 -> 28576.515
A17: 14 | B17: 46187 | E17: 55 | F17: 98.69 | G17: =E17*F17 -> 5427.95 | J17: =H17*I17 -> 0 | K17: =G17+J17 -> 5427.95 | M17: =M16+K17-L17 -> 34004.465
A18: 15 | B18: 46188 | E18: 102.63 | F18: 98.69 | G18: =E18*F18 -> 10128.555 | H18: 5 | I18: 110.74 | J18: =H18*I18 -> 553.7 | K18: =G18+J18 -> 10682.255 | M18: =M17+K18-L18 -> 44686.72
A19: 16 | B19: 46189 | E19: 50 | F19: 98.69 | G19: =E19*F19 -> 4934.5 | H19: 5 | I19: 110.74 | J19: =H19*I19 -> 553.7 | K19: =G19+J19 -> 5488.2 | M19: =M18+K19-L19 -> 50174.92
A20: 17 | B20: 46190 | E20: 80 | F20: 98.69 | G20: =E20*F20 -> 7895.2 | H20: 5 | I20: 110.74 | J20: =H20*I20 -> 553.7 | K20: =G20+J20 -> 8448.9 | M20: =M19+K20-L20 -> 58623.82 | O20: 16.68
A21: 18 | B21: 46191 | E21: 60 | F21: 98.69 | G21: =E21*F21 -> 5921.4 | H21: 10 | I21: 110.74 | J21: =H21*I21 -> 1107.4 | K21: =G21+J21 -> 7028.8 | M21: =M20+K21-L21 -> 65652.62
A22: 19 | B22: 46192 | G22: =E22*F22 -> 0 | H22: 5 | I22: 110.74 | J22: =H22*I22 -> 553.7 | K22: =G22+J22 -> 553.7 | M22: =M21+K22-L22 -> 66206.32
A23: 20 | B23: 46193 | E23: 99.4 | F23: 98.69 | G23: =E23*F23 -> 9809.786 | H23: 5 | I23: 110.74 | J23: =H23*I23 -> 553.7 | K23: =G23+J23 -> 10363.486 | M23: =M22+K23-L23 -> 76569.806 | N23: 0
A24: 21 | B24: 46194 | G24: =E24*F24 -> 0 | H24: 5 | I24: 110.74 | J24: =H24*I24 -> 553.7 | K24: =G24+J24 -> 553.7 | M24: =M23+K24-L24 -> 77123.506
A25: 22 | B25: 46195 | E25: 30 | F25: 98.69 | G25: =E25*F25 -> 2960.7 | H25: 5 | I25: 110.74 | J25: =H25*I25 -> 553.7 | K25: =G25+J25 -> 3514.4 | M25: =M24+K25-L25 -> 80637.906
A26: 23 | B26: 46196 | G26: =E26*F26 -> 0 | J26: =H26*I26 -> 0 | K26: =G26+J26 -> 0 | M26: =M25+K26-L26 -> 80637.906
A27: 24 | B27: 46197 | G27: =E27*F27 -> 0 | J27: =H27*I27 -> 0 | K27: =G27+J27 -> 0 | M27: =M26+K27-L27 -> 80637.906
A28: 25 | B28: 46198 | E28: 101 | F28: 98.69 | G28: =E28*F28 -> 9967.69 | H28: 10 | I28: 110.74 | J28: =H28*I28 -> 1107.4 | K28: =G28+J28 -> 11075.09 | M28: =M27+K28-L28 -> 91712.996
A29: 26 | B29: 46199 | E29: 43.09 | F29: 98.69 | G29: =F29*E29 -> 4252.5521 | J29: =H29*I29 -> 0 | K29: =G29+J29 -> 4252.5521 | M29: =M28+K29-L29 -> 95965.548
A30: 27 | B30: 46200 | E30: 50 | F30: 99.78 | G30: =E30*F30 -> 4989 | H30: 10 | I30: 111.98 | J30: =H30*I30 -> 1119.8 | K30: =G30+J30 -> 6108.8 | M30: =M29+K30-L30 -> 102074.35
A31: 28 | B31: 46201 | E31: 30 | F31: 99.78 | G31: =E31*F31 -> 2993.4 | J31: =H31*I31 -> 0 | K31: =G31+J31 -> 2993.4 | M31: =M30+K31-L31 -> 105067.75
A32: 29 | B32: 46202 | G32: =F32*E32 -> 0 | J32: =H32*I32 -> 0 | K32: =G32+J32 -> 0 | M32: =M31+K32-L32 -> 105067.75
A33: 30 | B33: 46203 | G33: =F33*E33 -> 0 | J33: =H33*I33 -> 0 | K33: =G33+J33 -> 0 | M33: =M32+K33-L33 -> 105067.75
A34: 31 | B34: 46204 | G34: =F34*E34 -> 0 | J34: =H34*I34 -> 0 | K34: =G34+J34 -> 0 | M34: =M33+K34-L34 -> 105067.75
E35: =SUM(E4:E34) -> 1216.09 | G35: =SUM(G4:G34) -> 120083.29 | H35: =SUM(H4:H34) -> 110 | J35: =SUM(J4:J34) -> 12193.8 | K35: =SUM(K4:K34) -> 132277.09 | L35: =SUM(L4:L34) -> 86235 | M35: =SUM(M4:M34) -> 2016904.3

Sheet Munavali-2
A1: Shiri Shiva Petroluem
A2: S.No | B2: Date | C2: GRN No | D2: Ind No/Bill No | E2: Diesel (Lts) | F2: Price | G2: Amount | H2: Petrol (Lts) | I2: Price | J2: Amount | K2: Total amount | L2: Amount paid | M2: As on date | N2: Remarks
D3: Opening Balance | K3: 445001.62 | M3: 445001.62 | O3: 26506.4
A4: 1 | B4: 46174 | E4: 300 | F4: 99.35 | G4: =E4*F4 -> 29805 | J4: =H4*I4 -> 0 | K4: =G4+J4 -> 29805 | L4: 200000 | M4: =M3+K4-L4 -> 274806.62
A5: 2 | B5: 46175 | E5: 300 | F5: 99.35 | G5: =E5*F5 -> 29805 | J5: =H5*I5 -> 0 | K5: =G5+J5 -> 29805 | M5: =M4+K5-L5 -> 304611.62 | N5: HPCl
A6: 3 | B6: 46176 | E6: 300 | F6: 99.35 | G6: =E6*F6 -> 29805 | J6: =H6*I6 -> 0 | K6: =G6+J6 -> 29805 | M6: =M5+K6-L6 -> 334416.62
A7: 4 | B7: 46177 | E7: 300 | F7: 99.35 | G7: =E7*F7 -> 29805 | J7: =H7*I7 -> 0 | K7: =G7+J7 -> 29805 | M7: =M6+K7-L7 -> 364221.62
A8: 5 | B8: 46178 | E8: 300 | F8: 99.35 | G8: =E8*F8 -> 29805 | J8: =H8*I8 -> 0 | K8: =G8+J8 -> 29805 | M8: =M7+K8-L8 -> 394026.62 | R8: SAI SHIVA FILLING STATION
A9: 6 | B9: 46179 | G9: =E9*F9 -> 0 | J9: =H9*I9 -> 0 | K9: =G9+J9 -> 0 | M9: =M8+K9-L9 -> 394026.62
A10: 7 | B10: 46180 | G10: =E10*F10 -> 0 | J10: =H10*I10 -> 0 | K10: =G10+J10 -> 0 | M10: =M9+K10-L10 -> 394026.62 | R10: =PROPER(R8) -> Sai Shiva Filling Station
A11: 8 | B11: 46181 | G11: =E11*F11 -> 0 | J11: =H11*I11 -> 0 | K11: =G11+J11 -> 0 | L11: 394027 | M11: =M10+K11-L11 -> -0.37954
A12: 9 | B12: 46182 | G12: =E12*F12 -> 0 | J12: =H12*I12 -> 0 | K12: =G12+J12 -> 0 | M12: =M11+K12-L12 -> -0.37954
A13: 10 | B13: 46183 | G13: =E13*F13 -> 0 | J13: =H13*I13 -> 0 | K13: =G13+J13 -> 0 | M13: =M12+K13-L13 -> -0.37954
A14: 11 | B14: 46184 | G14: =E14*F14 -> 0 | J14: =H14*I14 -> 0 | K14: =G14+J14 -> 0 | M14: =M13+K14-L14 -> -0.37954
A15: 12 | B15: 46185 | G15: =E15*F15 -> 0 | J15: =H15*I15 -> 0 | K15: =G15+J15 -> 0 | M15: =M14+K15-L15 -> -0.37954
A16: 13 | B16: 46186 | G16: =E16*F16 -> 0 | J16: =H16*I16 -> 0 | K16: =G16+J16 -> 0 | M16: =M15+K16-L16 -> -0.37954
A17: 14 | B17: 46187 | G17: =E17*F17 -> 0 | K17: =G17+J17 -> 0 | M17: =M16+K17-L17 -> -0.37954
A18: 15 | B18: 46188 | D18: 0 | G18: =E18*F18 -> 0 | J18: =H18*I18 -> 0 | K18: =G18+J18 -> 0 | M18: =M17+K18-L18 -> -0.37954
A19: 16 | B19: 46189 | G19: =E19*F19 -> 0 | J19: =H19*I19 -> 0 | K19: =G19+J19 -> 0 | M19: =M18+K19-L19 -> -0.37954
A20: 17 | B20: 46190 | G20: =E20*F20 -> 0 | J20: =H20*I20 -> 0 | K20: =G20+J20 -> 0 | M20: =M19+K20-L20 -> -0.37954
A21: 18 | B21: 46191 | G21: =E21*F21 -> 0 | J21: =H21*I21 -> 0 | K21: =G21+J21 -> 0 | M21: =M20+K21-L21 -> -0.37954
A22: 19 | B22: 46192 | G22: =E22*F22 -> 0 | J22: =H22*I22 -> 0 | K22: =G22+J22 -> 0 | M22: =M21+K22-L22 -> -0.37954
A23: 20 | B23: 46193 | G23: 0 | J23: 0 | K23: 0 | M23: =M22+K23-L23 -> -0.37954
A24: 21 | B24: 46194 | G24: =E24*F24 -> 0 | J24: =H24*I24 -> 0 | K24: =G24+J24 -> 0 | M24: =M23+K24-L24 -> -0.37954
A25: 22 | B25: 46195 | G25: =E25*F25 -> 0 | J25: =H25*I25 -> 0 | K25: =G25+J25 -> 0 | M25: =M24+K25-L25 -> -0.37954
A26: 23 | B26: 46196 | G26: =E26*F26 -> 0 | J26: =H26*I26 -> 0 | K26: =G26+J26 -> 0 | M26: =M25+K26-L26 -> -0.37954
A27: 24 | B27: 46197 | G27: =E27*F27 -> 0 | J27: =H27*I27 -> 0 | K27: =G27+J27 -> 0 | M27: =M26+K27-L27 -> -0.37954
A28: 25 | B28: 46198 | G28: =E28*F28 -> 0 | J28: =H28*I28 -> 0 | K28: =G28+J28 -> 0 | M28: =M27+K28-L28 -> -0.37954
A29: 26 | B29: 46199 | G29: =E29*F29 -> 0 | J29: =H29*I29 -> 0 | K29: =G29+J29 -> 0 | M29: =M28+K29-L29 -> -0.37954
A30: 27 | B30: 46200 | G30: =E30*F30 -> 0 | J30: =H30*I30 -> 0 | K30: =G30+J30 -> 0 | M30: =M29+K30-L30 -> -0.37954
A31: 28 | B31: 46201 | G31: =E31*F31 -> 0 | J31: =H31*I31 -> 0 | K31: =G31+J31 -> 0 | M31: =M30+K31-L31 -> -0.37954
A32: 29 | B32: 46202 | G32: =E32*F32 -> 0 | J32: =H32*I32 -> 0 | K32: =G32+J32 -> 0 | M32: =M31+K32-L32 -> -0.37954 | Q32: 166834
A33: 30 | B33: 46203 | G33: =E33*F33 -> 0 | J33: =H33*I33 -> 0 | K33: =G33+J33 -> 0 | M33: =M32+K33-L33 -> -0.37954
A34: 31 | G34: =E34*F34 -> 0 | J34: =H34*I34 -> 0 | K34: =G34+J34 -> 0 | M34: =M33+K34-L34 -> -0.37954
A35: 32 | G35: =E35*F35 -> 0 | J35: =H35*I35 -> 0 | K35: =G35+J35 -> 0 | M35: =M34+K35-L35 -> -0.37954
A36: 33 | G36: =E36*F36 -> 0 | J36: =H36*I36 -> 0 | K36: =G36+J36 -> 0 | M36: =M35+K36-L36 -> -0.37954
A37: 34 | G37: =E37*F37 -> 0 | J37: =H37*I37 -> 0 | K37: =G37+J37 -> 0 | M37: =M36+K37-L37 -> -0.37954
A38: 35 | G38: =E38*F38 -> 0 | J38: =H38*I38 -> 0 | K38: =G38+J38 -> 0 | M38: =M37+K38-L38 -> -0.37954
A39: 36 | G39: =E39*F39 -> 0 | J39: =H39*I39 -> 0 | K39: =G39+J39 -> 0 | M39: =M38+K39-L39 -> -0.37954
E40: =SUM(E4:E39) -> 1500 | G40: =SUM(G4:G39) -> 149025 | H40: =SUM(H4:H39) -> 0 | J40: =SUM(J4:J39) -> 0 | K40: =SUM(K4:K39) -> 149025 | L40: =SUM(L4:L39) -> 594027

Sheet  Munavali
A1: DANESHWARI PETROLIUM(YERRAGATTI)
A2: S.No | B2: Date | C2: GRN No | D2: Ind No/Bill No | E2: Diesel (Lts) | F2: Price | G2: Amount | H2: Petrol (Lts) | I2: Price | J2: Amount | K2: Total amount | L2: Amount paid | M2: As on date | N2: Remarks
D3: Opening Balance | K3: 277716.15 | M3: 277716.15 | O3: 26506.4
A4: 1 | B4: 46174 | G4: =E4*F4 -> 0 | J4: =H4*I4 -> 0 | K4: =G4+J4 -> 0 | M4: =M3+K4-L4 -> 277716.15
A5: 2 | B5: 46175 | G5: =E5*F5 -> 0 | J5: =H5*I5 -> 0 | K5: =G5+J5 -> 0 | M5: =M4+K5-L5 -> 277716.15 | N5: HPCl
A6: 3 | B6: 46176 | E6: 800 | F6: 99.13 | G6: =E6*F6 -> 79304 | H6: 30 | I6: 111.21 | J6: =H6*I6 -> 3336.3 | K6: =G6+J6 -> 82640.3 | M6: =M5+K6-L6 -> 360356.45
A7: 4 | B7: 46177 | E7: 300 | F7: 99.13 | G7: =E7*F7 -> 29739 | J7: =H7*I7 -> 0 | K7: =G7+J7 -> 29739 | M7: =M6+K7-L7 -> 390095.45
A8: 5 | B8: 46178 | E8: 400 | F8: 99.13 | G8: =E8*F8 -> 39652 | H8: 20 | I8: 111.21 | J8: =H8*I8 -> 2224.2 | K8: =G8+J8 -> 41876.2 | M8: =M7+K8-L8 -> 431971.65 | R8: SAI SHIVA FILLING STATION
A9: 6 | B9: 46179 | E9: 500 | F9: 99.13 | G9: 49565 | J9: =H9*I9 -> 0 | K9: =G9+J9 -> 49565 | M9: =M8+K9-L9 -> 481536.65
A10: 7 | B10: 46180 | E10: 600 | F10: 99.13 | G10: 59478 | J10: =H10*I10 -> 0 | K10: =G10+J10 -> 59478 | M10: =M9+K10-L10 -> 541014.65 | R10: =PROPER(R8) -> Sai Shiva Filling Station
A11: 8 | B11: 46181 | E11: 300 | F11: 99.13 | G11: =E11*F11 -> 29739 | H11: 20 | I11: 111.21 | J11: =H11*I11 -> 2224.2 | K11: =G11+J11 -> 31963.2 | L11: 540350 | M11: =M10+K11-L11 -> 32627.847
A12: 9 | B12: 46182 | E12: 121.29 | F12: 99.13 | G12: =E12*F12 -> 12023.478 | J12: =H12*I12 -> 0 | K12: =G12+J12 -> 12023.478 | M12: =M11+K12-L12 -> 44651.325
A13: 10 | B13: 46183 | E13: 800 | F13: 99.13 | G13: =E13*F13 -> 79304 | H13: 30 | I13: 111.21 | J13: =H13*I13 -> 3336.3 | K13: =G13+J13 -> 82640.3 | M13: =M12+K13-L13 -> 127291.62
A14: 11 | B14: 46184 | E14: 500 | F14: 99.13 | G14: =E14*F14 -> 49565 | J14: =H14*I14 -> 0 | K14: =G14+J14 -> 49565 | M14: =M13+K14-L14 -> 176856.62
A15: 12 | B15: 46185 | E15: 500 | F15: 99.13 | G15: =E15*F15 -> 49565 | J15: =H15*I15 -> 0 | K15: =G15+J15 -> 49565 | M15: =M14+K15-L15 -> 226421.62
A16: 13 | B16: 46186 | E16: 600 | F16: 99.13 | G16: =E16*F16 -> 59478 | H16: 20 | I16: 111.21 | J16: =H16*I16 -> 2224.2 | K16: =G16+J16 -> 61702.2 | M16: =M15+K16-L16 -> 288123.82
A17: 14 | B17: 46187 | E17: 800 | F17: 99.13 | G17: =E17*F17 -> 79304 | J17: =H17*I17 -> 0 | K17: =G17+J17 -> 79304 | M17: =M16+K17-L17 -> 367427.82
A18: 15 | B18: 46188 | D18: 0 | E18: 600 | F18: 99.13 | G18: =E18*F18 -> 59478 | H18: 20 | I18: 111.21 | J18: =H18*I18 -> 2224.2 | K18: =G18+J18 -> 61702.2 | M18: =M17+K18-L18 -> 429130.02
A19: 16 | B19: 46189 | E19: 400 | F19: 99.13 | G19: =E19*F19 -> 39652 | J19: =H19*I19 -> 0 | K19: =G19+J19 -> 39652 | L19: 380000 | M19: =M18+K19-L19 -> 88782.025
A20: 17 | B20: 46190 | E20: 500 | F20: 99.13 | G20: =E20*F20 -> 49565 | H20: 30 | I20: 111.21 | J20: =H20*I20 -> 3336.3 | K20: =G20+J20 -> 52901.3 | M20: =M19+K20-L20 -> 141683.32
A21: 18 | B21: 46191 | E21: 500 | F21: 99.13 | G21: =E21*F21 -> 49565 | J21: =H21*I21 -> 0 | K21: =G21+J21 -> 49565 | M21: =M20+K21-L21 -> 191248.32
A22: 19 | B22: 46192 | E22: 600 | F22: 99.13 | G22: =E22*F22 -> 59478 | J22: =H22*I22 -> 0 | K22: =G22+J22 -> 59478 | M22: =M21+K22-L22 -> 250726.32
A23: 20 | B23: 46193 | E23: 400 | F23: 99.13 | G23: =E23*F23 -> 39652 | H23: 30 | I23: 111.21 | J23: =H23*I23 -> 3336.3 | K23: =G23+J23 -> 42988.3 | M23: =M22+K23-L23 -> 293714.62
A24: 22 | B24: 46194 | E24: 200 | F24: 99.13 | G24: =E24*F24 -> 19826 | J24: =H24*I24 -> 0 | K24: =G24+J24 -> 19826 | M24: =M23+K24-L24 -> 313540.62
A25: 23 | B25: 46195 | E25: 800 | F25: 99.13 | G25: =E25*F25 -> 79304 | J25: =H25*I25 -> 0 | K25: =G25+J25 -> 79304 | M25: =M24+K25-L25 -> 392844.62
A26: 24 | B26: 46196 | E26: 700 | F26: 99.13 | G26: =E26*F26 -> 69391 | H26: 20 | I26: 111.21 | J26: =H26*I26 -> 2224.2 | K26: =G26+J26 -> 71615.2 | M26: =M25+K26-L26 -> 464459.82
A27: 25 | B27: 46197 | E27: 500 | F27: 99.13 | G27: =E27*F27 -> 49565 | J27: =H27*I27 -> 0 | K27: =G27+J27 -> 49565 | M27: =M26+K27-L27 -> 514024.82
A28: 26 | B28: 46198 | E28: 300 | F28: 99.13 | G28: =E28*F28 -> 29739 | H28: 20 | I28: 111.21 | J28: =H28*I28 -> 2224.2 | K28: =G28+J28 -> 31963.2 | L28: 300000 | M28: =M27+K28-L28 -> 245988.02
A29: 27 | B29: 46199 | E29: 700 | F29: 99.13 | G29: =E29*F29 -> 69391 | H29: 20 | I29: 111.21 | J29: =H29*I29 -> 2224.2 | K29: =G29+J29 -> 71615.2 | M29: =M28+K29-L29 -> 317603.22
A30: 28 | B30: 46200 | G30: =E30*F30 -> 0 | J30: =H30*I30 -> 0 | K30: =G30+J30 -> 0 | M30: =M29+K30-L30 -> 317603.22
A31: 29 | B31: 46201 | G31: =E31*F31 -> 0 | J31: =H31*I31 -> 0 | K31: =G31+J31 -> 0 | M31: =M30+K31-L31 -> 317603.22 | Q31: 166834
A32: 30 | B32: 46202 | E32: 800 | F32: 99.13 | G32: =E32*F32 -> 79304 | H32: 20 | I32: 111.21 | J32: =H32*I32 -> 2224.2 | K32: =G32+J32 -> 81528.2 | M32: =M31+K32-L32 -> 399131.42
A33: 31 | B33: 46203 | E33: 800 | F33: 99.13 | G33: =E33*F33 -> 79304 | J33: =H33*I33 -> 0 | K33: =G33+J33 -> 79304 | M33: =M32+K33-L33 -> 478435.42
A34: 32 | G34: =E34*F34 -> 0 | J34: =H34*I34 -> 0 | K34: =G34+J34 -> 0 | M34: =M33+K34-L34 -> 478435.42
A35: 33 | G35: =E35*F35 -> 0 | J35: =H35*I35 -> 0 | K35: =G35+J35 -> 0 | M35: =M34+K35-L35 -> 478435.42
A36: 34 | G36: =E36*F36 -> 0 | J36: =H36*I36 -> 0 | K36: =G36+J36 -> 0 | M36: =M35+K36-L36 -> 478435.42
A37: 35 | G37: =E37*F37 -> 0 | J37: =H37*I37 -> 0 | K37: =G37+J37 -> 0 | M37: =M36+K37-L37 -> 478435.42
A38: 36 | G38: =E38*F38 -> 0 | J38: =H38*I38 -> 0 | K38: =G38+J38 -> 0 | M38: =M37+K38-L38 -> 478435.42
E39: =SUM(E4:E38) -> 14021.29 | G39: =SUM(G4:G38) -> 1389930.5 | H39: =SUM(H4:H38) -> 280 | J39: =SUM(J4:J38) -> 31138.8 | K39: =SUM(K4:K38) -> 1421069.3 | L39: =SUM(L4:L38) -> 1220350

Sheet Borgaon
A1: Aadisagar Petrolium
A2: S.No | B2: Date | C2: GRN No | D2: Ind no/Bill No | E2: Diesel (Lts) | F2: Price | G2: Amount | H2: Petrol (Lts) | I2: Price | J2: Amount | K2: Total amount | L2: Amount paid | M2: As on Date | N2: Remarks
A3: Opening Balance | K3: 276126.39 | M3: 276126.39
A4: 1 | B4: 46174 | G4: =E4*F4 -> 0 | J4: =H4*I4 -> 0 | K4: =G4+J4 -> 0 | M4: =M3+K4-L4 -> 276126.39
A5: 2 | B5: 46175 | G5: =E5*F5 -> 0 | J5: =H5*I5 -> 0 | K5: =G5+J5 -> 0 | M5: =M4+K5-L5 -> 276126.39
A6: 3 | B6: 46176 | G6: =E6*F6 -> 0 | J6: =H6*I6 -> 0 | K6: =G6+J6 -> 0 | M6: =M5+K6-L6 -> 276126.39
A7: 4 | B7: 46177 | G7: =E7*F7 -> 0 | J7: =H7*I7 -> 0 | K7: =G7+J7 -> 0 | M7: =M6+K7-L7 -> 276126.39
A8: 5 | B8: 46178 | G8: =E8*F8 -> 0 | J8: =H8*I8 -> 0 | K8: =G8+J8 -> 0 | M8: =M7+K8-L8 -> 276126.39
A9: 6 | B9: 46179 | G9: =E9*F9 -> 0 | J9: =H9*I9 -> 0 | K9: =G9+J9 -> 0 | M9: =M8+K9-L9 -> 276126.39
A10: 7 | B10: 46180 | G10: =E10*F10 -> 0 | J10: =H10*I10 -> 0 | K10: =G10+J10 -> 0 | M10: =M9+K10-L10 -> 276126.39
A11: 8 | B11: 46181 | G11: =E11*F11 -> 0 | J11: =H11*I11 -> 0 | K11: =G11+J11 -> 0 | M11: =M10+K11-L11 -> 276126.39
A12: 9 | B12: 46182 | G12: =E12*F12 -> 0 | J12: =H12*I12 -> 0 | K12: =G12+J12 -> 0 | L12: 275918 | M12: =M11+K12-L12 -> 208.3907
A13: 10 | B13: 46183 | G13: =E13*F13 -> 0 | J13: =H13*I13 -> 0 | K13: =G13+J13 -> 0 | M13: =M12+K13-L13 -> 208.3907
A14: 11 | B14: 46184 | G14: =E14*F14 -> 0 | J14: =H14*I14 -> 0 | K14: =G14+J14 -> 0 | M14: =M13+K14-L14 -> 208.3907
A15: 12 | B15: 46185 | G15: =E15*F15 -> 0 | J15: =H15*I15 -> 0 | K15: =G15+J15 -> 0 | M15: =M14+K15-L15 -> 208.3907
A16: 13 | B16: 46186 | G16: =E16*F16 -> 0 | J16: =H16*I16 -> 0 | K16: =G16+J16 -> 0 | M16: =M15+K16-L16 -> 208.3907
A17: 14 | B17: 46187 | G17: =E17*F17 -> 0 | J17: =H17*I17 -> 0 | K17: =G17+J17 -> 0 | M17: =M16+K17-L17 -> 208.3907
A18: 15 | B18: 46188 | G18: =E18*F18 -> 0 | J18: =H18*I18 -> 0 | K18: =G18+J18 -> 0 | M18: =M17+K18-L18 -> 208.3907
A19: 16 | B19: 46189 | G19: =E19*F19 -> 0 | J19: =H19*I19 -> 0 | K19: =G19+J19 -> 0 | M19: =M18+K19-L19 -> 208.3907
A20: 17 | B20: 46190 | G20: =E20*F20 -> 0 | J20: =H20*I20 -> 0 | K20: =G20+J20 -> 0 | M20: =M19+K20-L20 -> 208.3907
A21: 18 | B21: 46191 | G21: =E21*F21 -> 0 | J21: =H21*I21 -> 0 | K21: =G21+J21 -> 0 | M21: =M20+K21-L21 -> 208.3907
A22: 19 | B22: 46192 | G22: =E22*F22 -> 0 | J22: =H22*I22 -> 0 | K22: =G22+J22 -> 0 | M22: =M21+K22-L22 -> 208.3907
A23: 20 | B23: 46193 | G23: =E23*F23 -> 0 | J23: =H23*I23 -> 0 | K23: =G23+J23 -> 0 | M23: =M22+K23-L23 -> 208.3907
A24: 21 | B24: 46194 | G24: =E24*F24 -> 0 | J24: =H24*I24 -> 0 | K24: =G24+J24 -> 0 | M24: =M23+K24-L24 -> 208.3907
A25: 22 | B25: 46195 | G25: =E25*F25 -> 0 | J25: =H25*I25 -> 0 | K25: =G25+J25 -> 0 | M25: =M24+K25-L25 -> 208.3907
A26: 23 | B26: 46196 | G26: =E26*F26 -> 0 | J26: =H26*I26 -> 0 | K26: =G26+J26 -> 0 | M26: =M25+K26-L26 -> 208.3907 | Q26: d
A27: 24 | B27: 46197 | G27: =E27*F27 -> 0 | J27: =H27*I27 -> 0 | K27: =G27+J27 -> 0 | M27: =M26+K27-L27 -> 208.3907 | Q27: 30 | R27: 50
A28: 25 | B28: 46198 | G28: =E28*F28 -> 0 | J28: =H28*I28 -> 0 | K28: =G28+J28 -> 0 | M28: =M27+K28-L28 -> 208.3907 | Q28: 50 | R28: 4.51
A29: 26 | B29: 46199 | G29: =E29*F29 -> 0 | J29: =H29*I29 -> 0 | K29: =G29+J29 -> 0 | M29: =M28+K29-L29 -> 208.3907
A30: 27 | B30: 46200 | G30: =E30*F30 -> 0 | J30: =H30*I30 -> 0 | K30: =G30+J30 -> 0 | M30: =M29+K30-L30 -> 208.3907
A31: 28 | B31: 46201 | G31: =E31*F31 -> 0 | J31: =H31*I31 -> 0 | K31: =G31+J31 -> 0 | M31: =M30+K31-L31 -> 208.3907
A32: 29 | B32: 46202 | G32: =E32*F32 -> 0 | J32: =H32*I32 -> 0 | K32: =G32+J32 -> 0 | M32: =M31+K32-L32 -> 208.3907
A33: 30 | B33: 46203 | G33: =E33*F33 -> 0 | J33: =H33*I33 -> 0 | K33: =G33+J33 -> 0 | M33: =M32+K33-L33 -> 208.3907
A34: 31 | G34: =E34*F34 -> 0 | J34: =H34*I34 -> 0 | K34: =G34+J34 -> 0 | M34: =M33+K34-L34 -> 208.3907
E35: =SUM(E4:E34) -> 0 | G35: =SUM(G4:G34) -> 0 | H35: =SUM(H4:H34) -> 0 | J35: =SUM(J4:J34) -> 0 | K35: =SUM(K4:K34) -> 0 | L35: =SUM(L4:L34) -> 275918

Sheet Ugar,Khagwad,Kudichi
A1: Shiri Bhrhmanath Petrolium
A2: S.No | B2: Date | C2: GRN No | D2: Ind No/Bill No | E2: Diesel (Lts) | F2: Price | G2: Amount | H2: Petrol (Lts) | I2: Price | J2: Amount | K2: Total amount | L2: Amount paid | M2: As on Date | N2: Remarks
A3: Opening Balance | K3: 476633.25 | L3: 0 | M3: 476633.25
A4: 1 | B4: 46174 | E4: 385 | F4: 99.74 | G4: =E4*F4 -> 38399.9 | J4: =H4*I4 -> 0 | K4: =G4+J4 -> 38399.9 | L4: 0 | M4: =M3+K4-L4 -> 515033.15
A5: 2 | B5: 46175 | E5: 275 | F5: 99.74 | G5: =E5*F5 -> 27428.5 | J5: =H5*I5 -> 0 | K5: =G5+J5 -> 27428.5 | L5: 0 | M5: =M4+K5-L5 -> 542461.65
A6: 3 | B6: 46176 | E6: 450 | F6: 99.74 | G6: =E6*F6 -> 44883 | J6: =H6*I6 -> 0 | K6: =G6+J6 -> 44883 | L6: 0 | M6: =M5+K6-L6 -> 587344.65
A7: 4 | B7: 46177 | E7: 400 | F7: 99.74 | G7: =E7*F7 -> 39896 | J7: =H7*I7 -> 0 | K7: =G7+J7 -> 39896 | L7: 0 | M7: =M6+K7-L7 -> 627240.65
A8: 5 | B8: 46178 | E8: 400 | F8: 99.74 | G8: =E8*F8 -> 39896 | J8: =H8*I8 -> 0 | K8: =G8+J8 -> 39896 | L8: 0 | M8: =M7+K8-L8 -> 667136.65
A9: 6 | B9: 46179 | E9: 485 | F9: 99.74 | G9: =E9*F9 -> 48373.9 | J9: =H9*I9 -> 0 | K9: =G9+J9 -> 48373.9 | L9: 0 | M9: =M8+K9-L9 -> 715510.55
A10: 7 | B10: 46180 | E10: 199 | F10: 99.74 | G10: =E10*F10 -> 19848.26 | J10: =H10*I10 -> 0 | K10: =G10+J10 -> 19848.26 | L10: 0 | M10: =M9+K10-L10 -> 735358.81
A11: 8 | B11: 46181 | E11: 75 | F11: 99.74 | G11: =E11*F11 -> 7480.5 | J11: =H11*I11 -> 0 | K11: =G11+J11 -> 7480.5 | L11: 500000 | M11: =M10+K11-L11 -> 242839.31
A12: 9 | B12: 46182 | E12: 475 | F12: 99.74 | G12: =E12*F12 -> 47376.5 | H12: 46 | I12: 111.86 | J12: =H12*I12 -> 5145.56 | K12: =G12+J12 -> 52522.06 | L12: 0 | M12: =M11+K12-L12 -> 295361.37
A13: 10 | B13: 46183 | E13: 400 | F13: 99.74 | G13: =E13*F13 -> 39896 | J13: =H13*I13 -> 0 | K13: =G13+J13 -> 39896 | L13: 0 | M13: =M12+K13-L13 -> 335257.37
A14: 11 | B14: 46184 | E14: 270.01 | F14: 99.74 | G14: =E14*F14 -> 26930.797 | J14: =H14*I14 -> 0 | K14: =G14+J14 -> 26930.797 | L14: 0 | M14: =M13+K14-L14 -> 362188.17
A15: 12 | B15: 46185 | E15: 400 | F15: 99.74 | G15: =E15*F15 -> 39896 | H15: 5 | I15: 111.86 | J15: =H15*I15 -> 559.3 | K15: =G15+J15 -> 40455.3 | L15: 0 | M15: =M14+K15-L15 -> 402643.47
A16: 13 | B16: 46186 | E16: 90 | F16: 99.74 | G16: =E16*F16 -> 8976.6 | J16: =H16*I16 -> 0 | K16: =G16+J16 -> 8976.6 | L16: 0 | M16: =M15+K16-L16 -> 411620.07
A17: 14 | B17: 46187 | E17: 40 | F17: 99.74 | G17: =E17*F17 -> 3989.6 | J17: =H17*I17 -> 0 | K17: =G17+J17 -> 3989.6 | L17: 0 | M17: =M16+K17-L17 -> 415609.67
A18: 15 | B18: 46188 | E18: 400 | F18: 99.74 | G18: =E18*F18 -> 39896 | J18: =H18*I18 -> 0 | K18: =G18+J18 -> 39896 | L18: 0 | M18: =M17+K18-L18 -> 455505.67
A19: 16 | B19: 46189 | G19: =E19*F19 -> 0 | J19: =H19*I19 -> 0 | K19: =G19+J19 -> 0 | L19: 400000 | M19: =M18+K19-L19 -> 55505.666
A20: 17 | B20: 46190 | E20: 480 | F20: 99.74 | G20: =E20*F20 -> 47875.2 | H20: 4 | I20: 111.86 | J20: =H20*I20 -> 447.44 | K20: =G20+J20 -> 48322.64 | L20: 0 | M20: =M19+K20-L20 -> 103828.31
B21: 46191 | E21: 310 | F21: 99.74 | G21: =E21*F21 -> 30919.4 | J21: =H21*I21 -> 0 | K21: =G21+J21 -> 30919.4 | L21: 0 | M21: =M20+K21-L21 -> 134747.71
A22: 18 | B22: 46192 | E22: 516.44 | F22: 99.74 | G22: =E22*F22 -> 51509.726 | H22: 25 | I22: 111.86 | J22: =H22*I22 -> 2796.5 | K22: =G22+J22 -> 54306.226 | L22: 0 | M22: =M21+K22-L22 -> 189053.93 | N22: BT
A23: 19 | B23: 46193 | E23: 30 | F23: 99.74 | G23: =E23*F23 -> 2992.2 | J23: =H23*I23 -> 0 | K23: =G23+J23 -> 2992.2 | L23: 0 | M23: =M22+K23-L23 -> 192046.13
A24: 20 | B24: 46194 | E24: 72.9 | F24: 99.74 | G24: =E24*F24 -> 7271.046 | H24: 10 | I24: 111.86 | J24: =H24*I24 -> 1118.6 | K24: =G24+J24 -> 8389.646 | L24: 0 | M24: =M23+K24-L24 -> 200435.78
A25: 21 | B25: 46195 | E25: 400 | F25: 99.74 | G25: =E25*F25 -> 39896 | H25: 4 | I25: 111.86 | J25: =H25*I25 -> 447.44 | K25: =G25+J25 -> 40343.44 | L25: 0 | M25: =M24+K25-L25 -> 240779.22
A26: 22 | B26: 46196 | E26: 70 | F26: 99.74 | G26: =E26*F26 -> 6981.8 | J26: =H26*I26 -> 0 | K26: =G26+J26 -> 6981.8 | L26: 0 | M26: =M25+K26-L26 -> 247761.02
B27: 46197 | E27: 205 | F27: 99.74 | G27: =E27*F27 -> 20446.7 | J27: =H27*I27 -> 0 | K27: =G27+J27 -> 20446.7 | L27: 0 | M27: =M26+K27-L27 -> 268207.72
A28: 23 | B28: 46198 | E28: 130 | F28: 99.74 | G28: =E28*F28 -> 12966.2 | H28: 6 | I28: 111.86 | J28: =H28*I28 -> 671.16 | K28: =G28+J28 -> 13637.36 | L28: 0 | M28: =M27+K28-L28 -> 281845.08
A29: 24 | B29: 46199 | E29: 904.97 | F29: 99.74 | G29: =E29*F29 -> 90261.708 | J29: =H29*I29 -> 0 | K29: =G29+J29 -> 90261.708 | L29: 0 | M29: =M28+K29-L29 -> 372106.78
A30: 25 | B30: 46200 | E30: 276.6 | F30: 99.74 | G30: =E30*F30 -> 27588.084 | J30: =H30*I30 -> 0 | K30: =G30+J30 -> 27588.084 | L30: 0 | M30: =M29+K30-L30 -> 399694.87
A31: 26 | B31: 46201 | E31: 465 | F31: 99.74 | G31: =E31*F31 -> 46379.1 | H31: 20 | I31: 111.86 | J31: =H31*I31 -> 2237.2 | K31: =G31+J31 -> 48616.3 | L31: 0 | M31: =M30+K31-L31 -> 448311.17
A32: 27 | B32: 46202 | E32: 95 | F32: 99.74 | G32: =E32*F32 -> 9475.3 | J32: =H32*I32 -> 0 | K32: =G32+J32 -> 9475.3 | L32: 0 | M32: =M31+K32-L32 -> 457786.47 | P32: =600*99.73 -> 59838
A33: 28 | B33: 46203 | E33: 715 | F33: 99.74 | G33: =E33*F33 -> 71314.1 | H33: 5 | I33: 111.86 | J33: =H33*I33 -> 559.3 | K33: =G33+J33 -> 71873.4 | L33: 0 | M33: =M32+K33-L33 -> 529659.87
A34: 29 | G34: =E34*F34 -> 0 | J34: =H34*I34 -> 0 | K34: =G34+J34 -> 0 | L34: 0 | M34: =M33+K34-L34 -> 529659.87
A35: 30 | G35: =E35*F35 -> 0 | J35: =H35*I35 -> 0 | K35: =G35+J35 -> 0 | L35: 0 | M35: =M34+K35-L35 -> 529659.87
A36: 31 | G36: =E36*F36 -> 0 | J36: =H36*I36 -> 0 | K36: =G36+J36 -> 0 | L36: 0 | M36: =M35+K36-L36 -> 529659.87
E37: =SUM(E4:E36) -> 9414.92 | G37: =SUM(G4:G36) -> 939044.12 | H37: =SUM(H4:H36) -> 125 | J37: =SUM(J4:J36) -> 13982.5 | K37: =SUM(K4:K36) -> 953026.62 | L37: =SUM(L4:L36) -> 900000

Sheet shedbal
A1: VARAD PETROLEUM SHEDBAL
A2: S.No | B2: Date | C2: GRN No | D2: Ind no/Bill No | E2: Diesel (Lts) | F2: Price | G2: Amount | H2: Petrol (Lts) | I2: Price | J2: Amount | K2: Total amount | L2: Amount paid | M2: As on Date | N2: Remarks
A3: Opening Balance | K3: 167956.75 | M3: 167956.75
A4: 1 | B4: 46174 | E4: 600 | F4: 99.73 | G4: =E4*F4 -> 59838 | H4: 35 | I4: 111.85 | J4: =H4*I4 -> 3914.75 | K4: =G4+J4 -> 63752.75 | M4: =M3+K4-L4 -> 231709.5
A5: 2 | B5: 46175 | E5: 400 | F5: 99.73 | G5: =E5*F5 -> 39892 | I5: 111.85 | J5: =H5*I5 -> 0 | K5: =G5+J5 -> 39892 | M5: =M4+K5-L5 -> 271601.5
A6: 3 | B6: 46176 | E6: 200 | F6: 99.73 | G6: =E6*F6 -> 19946 | H6: 5 | I6: 111.85 | J6: =H6*I6 -> 559.25 | K6: =G6+J6 -> 20505.25 | M6: =M5+K6-L6 -> 292106.75
A7: 4 | B7: 46177 | E7: 440 | F7: 99.73 | G7: =E7*F7 -> 43881.2 | H7: 17 | I7: 111.85 | J7: =H7*I7 -> 1901.45 | K7: =G7+J7 -> 45782.65 | M7: =M6+K7-L7 -> 337889.4
A8: 5 | B8: 46178 | E8: 200 | F8: 99.73 | G8: =E8*F8 -> 19946 | H8: 30 | I8: 111.85 | J8: =H8*I8 -> 3355.5 | K8: =G8+J8 -> 23301.5 | M8: =M7+K8-L8 -> 361190.9
A9: 6 | B9: 46179 | E9: 80 | F9: 99.73 | G9: =E9*F9 -> 7978.4 | J9: =H9*I9 -> 0 | K9: =G9+J9 -> 7978.4 | M9: =M8+K9-L9 -> 369169.3
A10: 7 | B10: 46180 | E10: 235 | F10: 99.73 | G10: =E10*F10 -> 23436.55 | H10: 50 | I10: 111.85 | J10: =H10*I10 -> 5592.5 | K10: =G10+J10 -> 29029.05 | M10: =M9+K10-L10 -> 398198.35
A11: 8 | B11: 46181 | E11: 400 | F11: 99.73 | G11: =E11*F11 -> 39892 | H11: 12 | I11: 111.85 | J11: =H11*I11 -> 1342.2 | K11: =G11+J11 -> 41234.2 | L11: 398000 | M11: =M10+K11-L11 -> 41432.55
A12: 9 | B12: 46182 | E12: 15 | F12: 99.73 | G12: =E12*F12 -> 1495.95 | J12: =H12*I12 -> 0 | K12: =G12+J12 -> 1495.95 | M12: =M11+K12-L12 -> 42928.5
A13: 10 | B13: 46183 | E13: 400 | F13: 99.73 | G13: =E13*F13 -> 39892 | J13: =H13*I13 -> 0 | K13: =G13+J13 -> 39892 | M13: =M12+K13-L13 -> 82820.5
A14: 11 | B14: 46184 | E14: 230 | F14: 99.73 | G14: =E14*F14 -> 22937.9 | J14: =H14*I14 -> 0 | K14: =G14+J14 -> 22937.9 | M14: =M13+K14-L14 -> 105758.4
A15: 12 | B15: 46185 | E15: 400 | F15: 99.73 | G15: =E15*F15 -> 39892 | H15: 36 | I15: 111.85 | J15: =H15*I15 -> 4026.6 | K15: =G15+J15 -> 43918.6 | M15: =M14+K15-L15 -> 149677
A16: 13 | B16: 46186 | E16: 440 | F16: 99.73 | G16: =E16*F16 -> 43881.2 | J16: =H16*I16 -> 0 | K16: =G16+J16 -> 43881.2 | M16: =M15+K16-L16 -> 193558.2
A17: 14 | B17: 46187 | E17: 0 | F17: 0 | G17: =E17*F17 -> 0 | J17: =H17*I17 -> 0 | K17: =G17+J17 -> 0 | M17: =M16+K17-L17 -> 193558.2
A18: 15 | B18: 46188 | E18: 300 | F18: 99.73 | G18: =E18*F18 -> 29919 | J18: =H18*I18 -> 0 | K18: =G18+J18 -> 29919 | M18: =M17+K18-L18 -> 223477.2
A19: 16 | B19: 46189 | E19: 30 | F19: 99.73 | G19: =E19*F19 -> 2991.9 | J19: =H19*I19 -> 0 | K19: =G19+J19 -> 2991.9 | M19: =M18+K19-L19 -> 226469.1
A20: 17 | B20: 46190 | E20: 435 | F20: 99.73 | G20: =E20*F20 -> 43382.55 | H20: 38 | I20: 111.85 | J20: =H20*I20 -> 4250.3 | K20: =G20+J20 -> 47632.85 | M20: =M19+K20-L20 -> 274101.95
A21: 18 | B21: 46191 | E21: 350 | F21: 99.73 | G21: =E21*F21 -> 34905.5 | J21: =H21*I21 -> 0 | K21: =G21+J21 -> 34905.5 | M21: =M20+K21-L21 -> 309007.45
A22: 19 | B22: 46192 | E22: 335 | F22: 99.73 | G22: =E22*F22 -> 33409.55 | J22: =H22*I22 -> 0 | K22: =G22+J22 -> 33409.55 | M22: =M21+K22-L22 -> 342417
A23: 20 | B23: 46193 | E23: 400 | F23: 99.73 | G23: =E23*F23 -> 39892 | J23: =H23*I23 -> 0 | K23: =G23+J23 -> 39892 | M23: =M22+K23-L23 -> 382309
A24: 21 | B24: 46194 | G24: =E24*F24 -> 0 | J24: =H24*I24 -> 0 | K24: =G24+J24 -> 0 | M24: =M23+K24-L24 -> 382309
A25: 22 | B25: 46195 | E25: 455 | F25: 99.73 | G25: =E25*F25 -> 45377.15 | H25: 40 | I25: 111.85 | J25: =H25*I25 -> 4474 | K25: =G25+J25 -> 49851.15 | M25: =M24+K25-L25 -> 432160.15
A26: 23 | B26: 46196 | E26: 400 | F26: 99.73 | G26: =E26*F26 -> 39892 | J26: =H26*I26 -> 0 | K26: =G26+J26 -> 39892 | M26: =M25+K26-L26 -> 472052.15 | Q26: d
A27: 24 | B27: 46197 | E27: 485 | F27: 99.73 | G27: =E27*F27 -> 48369.05 | H27: 20 | I27: 111.85 | J27: =H27*I27 -> 2237 | K27: =G27+J27 -> 50606.05 | M27: =M26+K27-L27 -> 522658.2 | Q27: 30 | R27: 50
A28: 25 | B28: 46198 | E28: 460 | F28: 99.73 | G28: =E28*F28 -> 45875.8 | J28: =H28*I28 -> 0 | K28: =G28+J28 -> 45875.8 | L28: 400000 | M28: =M27+K28-L28 -> 168534 | Q28: 50 | R28: 4.51
A29: 26 | B29: 46199 | E29: 70 | F29: 99.73 | G29: =E29*F29 -> 6981.1 | H29: 44 | I29: 111.85 | J29: =H29*I29 -> 4921.4 | K29: =G29+J29 -> 11902.5 | M29: =M28+K29-L29 -> 180436.5
A30: 27 | B30: 46200 | E30: 330 | F30: 99.73 | G30: =E30*F30 -> 32910.9 | J30: =H30*I30 -> 0 | K30: =G30+J30 -> 32910.9 | M30: =M29+K30-L30 -> 213347.4
A31: 28 | B31: 46201 | E31: 230 | F31: 99.73 | G31: =E31*F31 -> 22937.9 | J31: =H31*I31 -> 0 | K31: =G31+J31 -> 22937.9 | M31: =M30+K31-L31 -> 236285.3
A32: 29 | B32: 46202 | E32: 310 | F32: 99.73 | G32: =E32*F32 -> 30916.3 | H32: 17 | I32: 111.85 | J32: =H32*I32 -> 1901.45 | K32: =G32+J32 -> 32817.75 | M32: =M31+K32-L32 -> 269103.05
A33: 30 | B33: 46203 | E33: 240 | F33: 99.73 | G33: =E33*F33 -> 23935.2 | H33: 35 | I33: 111.85 | J33: =H33*I33 -> 3914.75 | K33: =G33+J33 -> 27849.95 | M33: =M32+K33-L33 -> 296953
A34: 31 | G34: =E34*F34 -> 0 | J34: =H34*I34 -> 0 | K34: =G34+J34 -> 0 | M34: =M33+K34-L34 -> 296953
E35: =SUM(E4:E34) -> 8870 | G35: =SUM(G4:G34) -> 884605.1 | H35: =SUM(H4:H34) -> 379 | J35: =SUM(J4:J34) -> 42391.15 | K35: =SUM(K4:K34) -> 926996.25 | L35: =SUM(L4:L34) -> 798000

Sheet Kabbur
A1: Shri Jai Hanuman Petrolium
A2: S.No | B2: Date | C2: GRN No | D2: Ind no/Bill No | E2: Diesel (Lts) | F2: Price | G2: Amount | H2: Petrol (Lts) | I2: Price | J2: Amount | K2: Total amount | L2: Amount paid | M2: As on Date | N2: Remarks
A3: Opening Balance | K3: 0 | M3: =+K3 -> 0
A4: 1 | B4: 46174 | G4: =E4*F4 -> 0 | J4: =H4*I4 -> 0 | K4: =G4+J4 -> 0 | L4: =+K4 -> 0
A5: 2 | B5: 46175 | G5: =E5*F5 -> 0 | J5: =H5*I5 -> 0 | K5: =G5+J5 -> 0 | L5: =+K5 -> 0
A6: 3 | B6: 46176 | G6: =E6*F6 -> 0 | J6: =H6*I6 -> 0 | K6: =G6+J6 -> 0 | L6: =+K6 -> 0
A7: 4 | B7: 46177 | G7: =E7*F7 -> 0 | J7: =H7*I7 -> 0 | K7: =G7+J7 -> 0 | L7: =+K7 -> 0
A8: 5 | B8: 46178 | G8: =E8*F8 -> 0 | H8: 6.84 | I8: 111.51 | J8: =H8*I8 -> 762.7284 | K8: =G8+J8 -> 762.7284 | L8: =+K8 -> 762.7284
A9: 6 | B9: 46179 | G9: =E9*F9 -> 0 | J9: =H9*I9 -> 0 | K9: =G9+J9 -> 0 | L9: =+K9 -> 0
A10: 7 | B10: 46180 | G10: =E10*F10 -> 0 | J10: =H10*I10 -> 0 | K10: =G10+J10 -> 0 | L10: =+K10 -> 0
A11: 8 | B11: 46181 | G11: =E11*F11 -> 0 | J11: =H11*I11 -> 0 | K11: =G11+J11 -> 0 | L11: =+K11 -> 0
A12: 9 | B12: 46182 | G12: =E12*F12 -> 0 | J12: =H12*I12 -> 0 | K12: =G12+J12 -> 0 | L12: =+K12 -> 0
A13: 10 | B13: 46183 | G13: =E13*F13 -> 0 | J13: =H13*I13 -> 0 | K13: =G13+J13 -> 0 | L13: =+K13 -> 0
A14: 11 | B14: 46184 | G14: =E14*F14 -> 0 | J14: =H14*I14 -> 0 | K14: =G14+J14 -> 0 | L14: =+K14 -> 0
A15: 12 | B15: 46185 | G15: =E15*F15 -> 0 | J15: =H15*I15 -> 0 | K15: =G15+J15 -> 0 | L15: =+K15 -> 0
A16: 13 | B16: 46186 | G16: =E16*F16 -> 0 | J16: =H16*I16 -> 0 | K16: =G16+J16 -> 0 | L16: =+K16 -> 0
A17: 14 | B17: 46187 | G17: =E17*F17 -> 0 | J17: =H17*I17 -> 0 | K17: =G17+J17 -> 0 | L17: =+K17 -> 0
A18: 15 | B18: 46188 | G18: =E18*F18 -> 0 | J18: =H18*I18 -> 0 | K18: =G18+J18 -> 0 | L18: =+K18 -> 0
A19: 16 | B19: 46189 | G19: =E19*F19 -> 0 | J19: =H19*I19 -> 0 | K19: =G19+J19 -> 0 | L19: =+K19 -> 0
A20: 17 | B20: 46190 | G20: =E20*F20 -> 0 | J20: =H20*I20 -> 0 | K20: =G20+J20 -> 0 | L20: =+K20 -> 0
... A22: 19 | B22: 46192 | G22: =E22*F22 -> 0 | J22: =H22*I22 -> 0 | K22: =G22+J22 -> 0 | L22: =+K22 -> 0
A23: 20 | B23: 46193 | E23: 45 | F23: 99.41 | G23: =E23*F23 -> 4473.45 | J23: =H23*I23 -> 0 | K23: =G23+J23 -> 4473.45 | L23: =+K23 -> 4473.45
A24: 21 | B24: 46194 | G24: =E24*F24 -> 0 | J24: =H24*I24 -> 0 | K24: =G24+J24 -> 0 | L24: =+K24 -> 0
A25: 22 | B25: 46195 | G25: =E25*F25 -> 0 | J25: =H25*I25 -> 0 | K25: =G25+J25 -> 0 | L25: =+K25 -> 0
A26: 23 | B26: 46196 | G26: =E26*F26 -> 0 | J26: =H26*I26 -> 0 | K26: =G26+J26 -> 0 | L26: =+K26 -> 0
A27: 24 | B27: 46197 | G27: =E27*F27 -> 0 | J27: =H27*I27 -> 0 | K27: =G27+J27 -> 0 | L27: =+K27 -> 0 | O27: 0
A28: 25 | B28: 46198 | E28: 60 | F28: 99.41 | G28: =E28*F28 -> 5964.6 | H28: 8.5 | I28: 111.51 | J28: =H28*I28 -> 947.835 | K28: =G28+J28 -> 6912.435 | L28: =+K28 -> 6912.435
A29: 26 | B29: 46199 | G29: =E29*F29 -> 0 | J29: =H29*I29 -> 0 | K29: =G29+J29 -> 0 | L29: =+K29 -> 0
A30: 27 | B30: 46200 | G30: =E30*F30 -> 0 | J30: =H30*I30 -> 0 | K30: =G30+J30 -> 0 | L30: =+K30 -> 0
A31: 28 | B31: 46201 | G31: =E31*F31 -> 0 | J31: =H31*I31 -> 0 | K31: =G31+J31 -> 0 | L31: =+K31 -> 0
A32: 29 | B32: 46202 | G32: =E32*F32 -> 0 | J32: =H32*I32 -> 0 | K32: =G32+J32 -> 0 | L32: =+K32 -> 0
A33: 30 | B33: 46203 | G33: =E33*F33 -> 0 | J33: =H33*I33 -> 0 | K33: =G33+J33 -> 0 | L33: =+K33 -> 0
A34: 31 | B34: 46204 | G34: =E34*F34 -> 0 | J34: =H34*I34 -> 0 | K34: =G34+J34 -> 0 | L34: =H34+K34 -> 0
E35: =SUM(E4:E34) -> 105 | G35: =SUM(G4:G34) -> 10438.05 | H35: =SUM(H4:H34) -> 15.34 | J35: =SUM(J4:J34) -> 1710.5634 | K35: =SUM(K4:K34) -> 12148.613 | L35: =SUM(L4:L34) -> 12148.613

Sheet kumta
A1: V.M.MIRJANKAR (KUMTA) BHARAT
A2: S.No | B2: Date | C2: GRN No | D2: Ind No/Bill No | E2: Diesel (Lts) | F2: Price | G2: Amount | H2: Petrol (Lts) | I2: Price | J2: Amount | K2: Total amount | L2: Amount paid | M2: As on Date | N2: Remarks
A3: Opening Balance | M3: 71321.75
A4: 1 | B4: 45809 | E4: 50 | F4: 99.78 | G4: =E4*F4 -> 4989 | H4: 2 | I4: 111.98 | J4: =H4*I4 -> 223.96 | K4: =G4+J4 -> 5212.96 | M4: =M3+K4-L4 -> 76534.71
B5: 45809 | E5: =60+20+37.57 -> 117.57 | F5: 99.73 | G5: =E5*F5 -> 11725.256 | H5: 0 | I5: 0 | J5: =H5*I5 -> 0 | K5: =G5+J5 -> 11725.256 | L5: 11725.256 | M5: =M4+K5-L5 -> 76534.71
A6: 2 | B6: 45810 | E6: 50 | F6: 99.78 | G6: =E6*F6 -> 4989 | H6: 15 | I6: 111.98 | J6: =H6*I6 -> 1679.7 | K6: =G6+J6 -> 6668.7 | M6: =M5+K6-L6 -> 83203.41
A7: 3 | B7: 45811 | G7: =E7*F7 -> 0 | H7: 5 | I7: 111.98 | J7: =H7*I7 -> 559.9 | K7: =G7+J7 -> 559.9 | M7: =M6+K7-L7 -> 83763.31
A8: 4 | B8: 45812 | E8: 50 | F8: 99.78 | G8: =E8*F8 -> 4989 | J8: =H8*I8 -> 0 | K8: =G8+J8 -> 4989 | M8: =M7+K8-L8 -> 88752.31
A9: 5 | B9: 45813 | E9: 50 | F9: 99.78 | G9: =E9*F9 -> 4989 | J9: =H9*I9 -> 0 | K9: =G9+J9 -> 4989 | L9: 80000 | M9: =M8+K9-L9 -> 13741.31
B10: 45813 | E10: 40 | F10: 99.73 | G10: =E10*F10 -> 3989.2 | J10: =H10*I10 -> 0 | K10: =G10+J10 -> 3989.2 | L10: 3989.2 | M10: =M9+K10-L10 -> 13741.31
A11: 6 | B11: 45814 | E11: 50 | F11: 99.78 | G11: =E11*F11 -> 4989 | J11: =H11*I11 -> 0 | K11: =G11+J11 -> 4989 | M11: =M10+K11-L11 -> 18730.31
A12: 7 | B12: 45815 | G12: =E12*F12 -> 0 | J12: =H12*I12 -> 0 | K12: =G12+J12 -> 0 | M12: =M11+K12-L12 -> 18730.31
A13: 8 | B13: 45816 | E13: 50 | F13: 99.78 | G13: =E13*F13 -> 4989 | H13: 5 | I13: 111.98 | J13: =H13*I13 -> 559.9 | K13: =G13+J13 -> 5548.9 | L13: 18673 | M13: =M12+K13-L13 -> 5606.2102
A14: 9 | B14: 45817 | G14: =E14*F14 -> 0 | J14: =H14*I14 -> 0 | K14: =G14+J14 -> 0 | M14: =M13+K14-L14 -> 5606.2102 | N14: IOCL
B15: 45818 | E15: 80 | F15: 99.78 | G15: =E15*F15 -> 7982.4 | J15: =H15*I15 -> 0 | K15: =G15+J15 -> 7982.4 | M15: =M14+K15-L15 -> 13588.61
A16: 10 | B16: 45819 | E16: 50 | F16: 99.73 | G16: =E16*F16 -> 4986.5 | J16: =H16*I16 -> 0 | K16: =G16+J16 -> 4986.5 | L16: 4986.5 | M16: =M15+K16-L16 -> 13588.61 | N16: IOCL Card
A17: 11 | B17: 45820 | E17: 50 | F17: 99.78 | G17: =E17*F17 -> 4989 | H17: 10 | I17: 111.98 | J17: =H17*I17 -> 1119.8 | K17: =G17+J17 -> 6108.8 | M17: =M16+K17-L17 -> 19697.41
A18: 12 | B18: 45821 | E18: 90 | F18: 99.78 | G18: =E18*F18 -> 8980.2 | J18: =H18*I18 -> 0 | K18: =G18+J18 -> 8980.2 | M18: =M17+K18-L18 -> 28677.61
A19: 13 | B19: 45822 | E19: 50 | F19: 99.78 | G19: =E19*F19 -> 4989 | J19: =H19*I19 -> 0 | K19: =G19+J19 -> 4989 | M19: =M18+K19-L19 -> 33666.61
A20: 14 | B20: 45823 | E20: 50 | F20: 99.78 | G20: =E20*F20 -> 4989 | H20: 10 | I20: 111.98 | J20: =H20*I20 -> 1119.8 | K20: =G20+J20 -> 6108.8 | M20: =M19+K20-L20 -> 39775.41
A21: 15 | B21: 45824 | E21: 50 | F21: 99.78 | G21: =E21*F21 -> 4989 | J21: =H21*I21 -> 0 | K21: =G21+J21 -> 4989 | L21: 39000 | M21: =M20+K21-L21 -> 5764.4102 | N21: IOCL
B22: 45825 | E22: 50 | F22: 99.78 | G22: =E22*F22 -> 4989 | J22: =H22*I22 -> 0 | K22: =G22+J22 -> 4989 | M22: =M21+K22-L22 -> 10753.41
A23: 16 | B23: 45826 | E23: 50 | F23: 99.78 | G23: =E23*F23 -> 4989 | H23: 5 | I23: 111.98 | J23: =H23*I23 -> 559.9 | K23: =G23+J23 -> 5548.9 | M23: =M22+K23-L23 -> 16302.31
A24: 17 | B24: 45827 | E24: 50 | F24: 99.78 | G24: =E24*F24 -> 4989 | J24: =H24*I24 -> 0 | K24: =G24+J24 -> 4989 | M24: =M23+K24-L24 -> 21291.31
A25: 18 | B25: 45828 | E25: 50 | F25: 99.78 | G25: =E25*F25 -> 4989 | H25: 9.37 | I25: 111.98 | J25: =H25*I25 -> 1049.2526 | K25: =G25+J25 -> 6038.2526 | M25: =M24+K25-L25 -> 27329.563
A26: 19 | B26: 45829 | E26: 50 | F26: 99.78 | G26: =E26*F26 -> 4989 | H26: 10 | I26: 111.98 | J26: =H26*I26 -> 1119.8 | K26: =G26+J26 -> 6108.8 | M26: =M25+K26-L26 -> 33438.363 | R26: Kumta | T26: V.M.Mirjankar
A27: 20 | B27: 45830 | G27: =E27*F27 -> 0 | J27: =H27*I27 -> 0 | K27: =G27+J27 -> 0 | M27: =M26+K27-L27 -> 33438.363 | R27: Month | S27: Disel In Litters | T27: Petrol In Litters | U27: Amount Paid
A28: 21 | B28: 45831 | E28: 29.8 | F28: 99.78 | G28: =E28*F28 -> 2973.444 | J28: =H28*I28 -> 0 | K28: =G28+J28 -> 2973.444 | M28: =M27+K28-L28 -> 36411.807 | R28: Feb'-26 | S28: 2040 | T28: 90 | U28: 169925
A29: 22 | B29: 45832 | G29: =E29*F29 -> 0 | J29: =H29*I29 -> 0 | K29: =G29+J29 -> 0 | M29: =M28+K29-L29 -> 36411.807 | R29: March'-26 | S29: 2115 | T29: 185 | U29: 206053
A30: 23 | B30: 45833 | E30: 20 | F30: 99.78 | G30: =E30*F30 -> 1995.6 | J30: =H30*I30 -> 0 | K30: =G30+J30 -> 1995.6 | L30: 38000 | M30: =M29+K30-L30 -> 407.4068 | R30: April'-26 | S30: 2145 | T30: 177 | U30: 247835
A31: 24 | B31: 45834 | E31: 50 | F31: 99.78 | G31: =E31*F31 -> 4989 | J31: =H31*I31 -> 0 | K31: =G31+J31 -> 4989 | M31: =M30+K31-L31 -> 5396.4068 | R31: May'-26 | S31: 545 | T31: 50 | U31: 44201
A32: 25 | B32: 45835 | F32: 99.78 | G32: =E32*F32 -> 0 | H32: 5 | I32: 111.98 | J32: =H32*I32 -> 559.9 | K32: =G32+J32 -> 559.9 | M32: =M31+K32-L32 -> 5956.3068 | S32: =SUM(S28:S31) -> 6845 | T32: =SUM(T28:T31) -> 502 | U32: =SUM(U28:U31) -> 668014
A33: 26 | B33: 45836 | E33: 30 | F33: 99.78 | G33: =E33*F33 -> 2993.4 | J33: =H33*I33 -> 0 | K33: =G33+J33 -> 2993.4 | M33: =M32+K33-L33 -> 8949.7068
A34: 27 | B34: 45837 | G34: =E34*F34 -> 0 | K34: =G34+J34 -> 0 | M34: =M33+K34-L34 -> 8949.7068
A35: 28 | B35: 45838 | E35: 50 | F35: 99.78 | G35: =E35*F35 -> 4989 | H35: 10 | I35: 111.98 | J35: =H35*I35 -> 1119.8 | K35: =G35+J35 -> 6108.8 | M35: =M34+K35-L35 -> 15058.507
A36: 29 | G36: =E36*F36 -> 0 | J36: =H36*I36 -> 0 | K36: =G36+J36 -> 0 | M36: =M35+K36-L36 -> 15058.507
A37: 30 | G37: =E37*F37 -> 0 | J37: =H37*I37 -> 0 | K37: =G37+J37 -> 0 | M37: =M36+K37-L37 -> 15058.507
A38: 31 | G38: =E38*F38 -> 0 | J38: =H38*I38 -> 0 | K38: =G38+J38 -> 0 | M38: =M37+K38-L38 -> 15058.507
A39: 32 | G39: =E39*F39 -> 0 | J39: =H39*I39 -> 0 | K39: =G39+J39 -> 0 | M39: =M38+K39-L39 -> 15058.507
A40: 33 | G40: =E40*F40 -> 0 | J40: =H40*I40 -> 0 | K40: =G40+J40 -> 0 | M40: =M39+K40-L40 -> 15058.507
E41: =SUM(E4:E40) -> 1307.37 | G41: =SUM(G4:G40) -> 130439 | H41: =SUM(H4:H40) -> 86.37 | J41: =SUM(J4:J40) -> 9671.7126 | K41: =SUM(K4:K40) -> 140110.71 | L41: =SUM(L4:L40) -> 196373.96

Sheet  Jalgaon-1
A1: Jai Bajarang Sarvo Senter Bodwad
A2: S.No | B2: Date | C2: GRN No | D2: Ind No/Bill No | E2: Diesel (Lts) | F2: Price | G2: Amount | H2: Petrol (Lts) | I2: Price | J2: Amount | K2: Total amount | L2: Amount paid | M2: As on Date | N2: Remarks
A3: Opening Balance | K3: 0 | L3: 0 | M3: 0
A4: 1 | B4: 46174 | G4: =E4*F4 -> 0 | J4: =H4*I4 -> 0 | K4: =G4+J4 -> 0 | M4: =M3+K4-L4 -> 0
A5: 2 | B5: 46175 | E5: 2000 | F5: 99.51 | G5: =E5*F5 -> 199020 | J5: =H5*I5 -> 0 | K5: =G5+J5 -> 199020 | M5: =M4+K5-L5 -> 199020
B6: 46176 | G6: =E6*F6 -> 0 | J6: =H6*I6 -> 0 | K6: =G6+J6 -> 0 | M6: =M5+K6-L6 -> 199020
A7: 3 | B7: 46177 | E7: 1000 | F7: 99.51 | G7: =E7*F7 -> 99510 | J7: =H7*I7 -> 0 | K7: =G7+J7 -> 99510 | M7: =M6+K7-L7 -> 298530
A8: 4 | B8: 46178 | G8: =E8*F8 -> 0 | J8: =H8*I8 -> 0 | K8: =G8+J8 -> 0 | M8: =M7+K8-L8 -> 298530
A9: 5 | B9: 46179 | G9: =E9*F9 -> 0 | J9: =H9*I9 -> 0 | K9: =G9+J9 -> 0 | L9: 298530 | M9: =M8+K9-L9 -> 0
A10: 6 | B10: 46180 | G10: =E10*F10 -> 0 | J10: =H10*I10 -> 0 | K10: =G10+J10 -> 0 | M10: =M9+K10-L10 -> 0
A11: 7 | B11: 46181 | G11: =E11*F11 -> 0 | J11: =H11*I11 -> 0 | K11: =G11+J11 -> 0 | M11: =M10+K11-L11 -> 0
A12: 8 | B12: 46182 | G12: =E12*F12 -> 0 | J12: =H12*I12 -> 0 | K12: =G12+J12 -> 0 | M12: =M11+K12-L12 -> 0
A13: 9 | B13: 46183 | G13: =E13*F13 -> 0 | J13: =H13*I13 -> 0 | K13: =G13+J13 -> 0 | M13: =M12+K13-L13 -> 0
A14: 10 | B14: 46184 | G14: =E14*F14 -> 0 | J14: =H14*I14 -> 0 | K14: =G14+J14 -> 0 | M14: =M13+K14-L14 -> 0
A15: 11 | B15: 46185 | G15: =E15*F15 -> 0 | J15: =H15*I15 -> 0 | K15: =G15+J15 -> 0 | M15: =M14+K15-L15 -> 0
A16: 12 | B16: 46186 | G16: =E16*F16 -> 0 | J16: =H16*I16 -> 0 | K16: =G16+J16 -> 0 | M16: =M15+K16-L16 -> 0
A17: 13 | B17: 46187 | G17: =E17*F17 -> 0 | J17: =H17*I17 -> 0 | K17: =G17+J17 -> 0 | M17: =M16+K17-L17 -> 0
A18: 14 | B18: 46188 | G18: =E18*F18 -> 0 | J18: =H18*I18 -> 0 | K18: =G18+J18 -> 0 | M18: =M17+K18-L18 -> 0
A19: 15 | B19: 46189 | G19: =E19*F19 -> 0 | J19: =H19*I19 -> 0 | K19: =G19+J19 -> 0 | M19: =M18+K19-L19 -> 0 | N19: BT
A20: 16 | B20: 46190 | G20: =E20*F20 -> 0 | J20: =H20*I20 -> 0 | K20: =G20+J20 -> 0 | M20: =M19+K20-L20 -> 0
A21: 17 | B21: 46191 | G21: =E21*F21 -> 0 | J21: =H21*I21 -> 0 | K21: =G21+J21 -> 0 | M21: =M20+K21-L21 -> 0
A22: 18 | B22: 46192 | G22: =E22*F22 -> 0 | J22: =H22*I22 -> 0 | K22: =G22+J22 -> 0 | M22: =M21+K22-L22 -> 0
A23: 19 | B23: 46193 | G23: =E23*F23 -> 0 | J23: =H23*I23 -> 0 | K23: =G23+J23 -> 0 | M23: =M22+K23-L23 -> 0
A24: 20 | B24: 46194 | G24: =E24*F24 -> 0 | J24: =H24*I24 -> 0 | K24: =G24+J24 -> 0 | M24: =M23+K24-L24 -> 0
A25: 21 | B25: 46195 | G25: =E25*F25 -> 0 | J25: =H25*I25 -> 0 | K25: =G25+J25 -> 0 | M25: =M24+K25-L25 -> 0
A26: 22 | B26: 46196 | G26: =E26*F26 -> 0 | J26: =H26*I26 -> 0 | K26: =G26+J26 -> 0 | M26: =M25+K26-L26 -> 0
A27: 23 | B27: 46197 | G27: =E27*F27 -> 0 | J27: =H27*I27 -> 0 | K27: =G27+J27 -> 0 | M27: =M26+K27-L27 -> 0
A28: 24 | B28: 46198 | G28: =E28*F28 -> 0 | J28: =H28*I28 -> 0 | K28: =G28+J28 -> 0 | M28: =M27+K28-L28 -> 0
A29: 25 | B29: 46199 | G29: =E29*F29 -> 0 | J29: =H29*I29 -> 0 | K29: =G29+J29 -> 0 | M29: =M28+K29-L29 -> 0
A30: 26 | B30: 46200 | G30: =E30*F30 -> 0 | J30: =H30*I30 -> 0 | K30: =G30+J30 -> 0 | M30: =M29+K30-L30 -> 0
A31: 27 | B31: 46201 | G31: =E31*F31 -> 0 | J31: =H31*I31 -> 0 | K31: =G31+J31 -> 0 | M31: =M30+K31-L31 -> 0
... A33: 29 | B33: 46203 | G33: =E33*F33 -> 0 | J33: =H33*I33 -> 0 | K33: =G33+J33 -> 0 | M33: =M32+K33-L33 -> 0
A34: 30 | G34: =E34*F34 -> 0 | J34: =H34*I34 -> 0 | K34: =G34+J34 -> 0 | M34: =M33+K34-L34 -> 0
A35: 31 | G35: =E35*F35 -> 0 | J35: =H35*I35 -> 0 | K35: =G35+J35 -> 0 | M35: =M34+K35-L35 -> 0
A36: 32 | G36: =E36*F36 -> 0 | J36: =H36*I36 -> 0 | K36: =G36+J36 -> 0 | M36: =M35+K36-L36 -> 0
A37: 33 | G37: =E37*F37 -> 0 | J37: =H37*I37 -> 0 | K37: =G37+J37 -> 0 | M37: =M36+K37-L37 -> 0
A38: 34 | G38: =E38*F38 -> 0 | J38: =H38*I38 -> 0 | K38: =G38+J38 -> 0 | M38: =M37+K38-L38 -> 0 | P38: 41
A39: 35 | G39: =E39*F39 -> 0 | J39: =H39*I39 -> 0 | K39: =G39+J39 -> 0 | M39: =M38+K39-L39 -> 0 | P39: 40 | Q39: 5
A40: 36 | G40: =E40*F40 -> 0 | J40: =H40*I40 -> 0 | K40: =G40+J40 -> 0 | M40: =M39+K40-L40 -> 0
A41: 37 | G41: =E41*F41 -> 0 | J41: =H41*I41 -> 0 | K41: =G41+J41 -> 0 | M41: =M40+K41-L41 -> 0
A42: 38 | G42: =E42*F42 -> 0 | J42: =H42*I42 -> 0 | K42: =G42+J42 -> 0 | M42: =M41+K42-L42 -> 0
A43: 39 | G43: =E43*F43 -> 0 | J43: =H43*I43 -> 0 | K43: =G43+J43 -> 0 | M43: =M42+K43-L43 -> 0
A44: 40 | G44: =E44*F44 -> 0 | J44: =H44*I44 -> 0 | K44: =G44+J44 -> 0 | M44: =M43+K44-L44 -> 0
A45: 41 | G45: =E45*F45 -> 0 | J45: =H45*I45 -> 0 | K45: =G45+J45 -> 0 | M45: =M44+K45-L45 -> 0
A46: 42 | G46: =E46*F46 -> 0 | J46: =H46*I46 -> 0 | K46: =G46+J46 -> 0 | M46: =M45+K46-L46 -> 0
A47: 43 | G47: =E47*F47 -> 0 | J47: =H47*I47 -> 0 | K47: =G47+J47 -> 0 | M47: =M46+K47-L47 -> 0
A48: 44 | G48: =E48*F48 -> 0 | J48: =H48*I48 -> 0 | K48: =G48+J48 -> 0 | M48: =M47+K48-L48 -> 0
A49: 45 | G49: =E49*F49 -> 0 | J49: =H49*I49 -> 0 | K49: =G49+J49 -> 0 | M49: =M48+K49-L49 -> 0
A50: 46 | G50: =E50*F50 -> 0 | J50: =H50*I50 -> 0 | K50: =G50+J50 -> 0 | M50: =M49+K50-L50 -> 0
A51: 47 | G51: =E51*F51 -> 0 | J51: =H51*I51 -> 0 | K51: =G51+J51 -> 0 | L51: 0 | M51: =M50+K51-L51 -> 0
A52: 48 | G52: =E52*F52 -> 0 | J52: =H52*I52 -> 0 | K52: =G52+J52 -> 0 | L52: 0 | M52: =M51+K52-L52 -> 0
A53: 49 | G53: =E53*F53 -> 0 | J53: =H53*I53 -> 0 | K53: =G53+J53 -> 0 | L53: 0 | M53: =M52+K53-L53 -> 0
A54: 50 | G54: =E54*F54 -> 0 | J54: =H54*I54 -> 0 | K54: =G54+J54 -> 0 | L54: 0 | M54: =M53+K54-L54 -> 0 | O54: 1109792.3 | P54: =M54-O54 -> -1109792.3
E55: =SUM(E4:E54) -> 3000 | G55: =SUM(G4:G54) -> 298530 | H55: =SUM(H4:H54) -> 0 | J55: =SUM(J4:J54) -> 0 | K55: =SUM(K4:K54) -> 298530 | L55: =SUM(L4:L54) -> 298530

Sheet Jalgoan-2
A1: Nayara
A2: S.No | B2: Date | C2: GRN No | D2: Ind No/Bill No | E2: Diesel (Lts) | F2: Price | G2: Amount | H2: Petrol (Lts) | I2: Price | J2: Amount | K2: Total amount | L2: Amount paid | M2: As on Date | N2: Remarks
A3: Opening Balance | K3: 2169469.7 | M3: 2169469.7 | P3: 5472110
A4: 1 | B4: 46174 | E4: 0 | F4: 102.51 | G4: =E4*F4 -> 0 | H4: 0 | I4: 118.18 | J4: =H4*I4 -> 0 | K4: =G4+J4 -> 0 | M4: =M3+K4-L4 -> 2169469.7
A5: 2 | B5: 46175 | E5: 1000 | F5: 102.51 | G5: =E5*F5 -> 102510 | H5: 30 | I5: 118.18 | J5: =H5*I5 -> 3545.4 | K5: =G5+J5 -> 106055.4 | M5: =M4+K5-L5 -> 2275525.1
A6: 3 | B6: 46176 | G6: =E6*F6 -> 0 | J6: =H6*I6 -> 0 | K6: =G6+J6 -> 0 | M6: =M5+K6-L6 -> 2275525.1
A7: 4 | B7: 46177 | G7: =E7*F7 -> 0 | J7: =H7*I7 -> 0 | K7: =G7+J7 -> 0 | M7: =M6+K7-L7 -> 2275525.1 | N7: BT
A8: 5 | B8: 46178 | G8: =E8*F8 -> 0 | J8: =H8*I8 -> 0 | K8: =G8+J8 -> 0 | M8: =M7+K8-L8 -> 2275525.1
A9: 6 | B9: 46179 | G9: =E9*F9 -> 0 | J9: =H9*I9 -> 0 | K9: =G9+J9 -> 0 | M9: =M8+K9-L9 -> 2275525.1
A10: 7 | B10: 46180 | G10: =E10*F10 -> 0 | J10: =H10*I10 -> 0 | K10: =G10+J10 -> 0 | M10: =M9+K10-L10 -> 2275525.1
A11: 8 | B11: 46181 | G11: =E11*F11 -> 0 | J11: =H11*I11 -> 0 | K11: =G11+J11 -> 0 | L11: 1000000 | M11: =M10+K11-L11 -> 1275525.1 | N11: BT
A12: 9 | B12: 46182 | E12: 3000 | F12: 102.51 | G12: =E12*F12 -> 307530 | J12: =H12*I12 -> 0 | K12: =G12+J12 -> 307530 | M12: =M11+K12-L12 -> 1583055.1
A13: 10 | B13: 46183 | E13: 2000 | F13: 102.51 | G13: =E13*F13 -> 205020 | H13: 30 | I13: 118.18 | J13: =H13*I13 -> 3545.4 | K13: =G13+J13 -> 208565.4 | M13: =M12+K13-L13 -> 1791620.5
A14: 11 | B14: 46184 | E14: 2150 | F14: 102.51 | G14: =E14*F14 -> 220396.5 | J14: =H14*I14 -> 0 | K14: =G14+J14 -> 220396.5 | M14: =M13+K14-L14 -> 2012017
A15: 12 | B15: 46185 | G15: =E15*F15 -> 0 | J15: =H15*I15 -> 0 | K15: =G15+J15 -> 0 | M15: =M14+K15-L15 -> 2012017
A16: 13 | B16: 46186 | E16: 2500.63 | F16: 102.51 | G16: =E16*F16 -> 256339.58 | J16: =H16*I16 -> 0 | K16: =G16+J16 -> 256339.58 | M16: =M15+K16-L16 -> 2268356.6
A17: 14 | B17: 46187 | E17: 2422.99 | F17: 102.51 | G17: =E17*F17 -> 248380.7 | J17: =H17*I17 -> 0 | K17: =G17+J17 -> 248380.7 | M17: =M16+K17-L17 -> 2516737.3
A18: 15 | B18: 46188 | G18: =E18*F18 -> 0 | J18: =H18*I18 -> 0 | K18: =G18+J18 -> 0 | M18: =M17+K18-L18 -> 2516737.3
A19: 16 | B19: 46189 | E19: 2500 | F19: 102.51 | G19: =E19*F19 -> 256275 | H19: 30 | I19: 118.18 | J19: =H19*I19 -> 3545.4 | K19: =G19+J19 -> 259820.4 | L19: 1000000 | M19: =M18+K19-L19 -> 1776557.7
A20: 17 | B20: 46190 | E20: 2213.99 | F20: 102.51 | G20: =E20*F20 -> 226956.11 | J20: =H20*I20 -> 0 | K20: =G20+J20 -> 226956.11 | M20: =M19+K20-L20 -> 2003513.8
A21: 18 | B21: 46191 | G21: =E21*F21 -> 0 | J21: =H21*I21 -> 0 | K21: =G21+J21 -> 0 | M21: =M20+K21-L21 -> 2003513.8
A22: 19 | B22: 46192 | E22: 2400 | F22: 102.51 | G22: =E22*F22 -> 246024 | H22: 30 | I22: 118.18 | J22: =H22*I22 -> 3545.4 | K22: =G22+J22 -> 249569.4 | M22: =M21+K22-L22 -> 2253083.2
A23: 20 | B23: 46193 | G23: =E23*F23 -> 0 | J23: =H23*I23 -> 0 | K23: =G23+J23 -> 0 | M23: =M22+K23-L23 -> 2253083.2
B24: 46194 | G24: =E24*F24 -> 0 | J24: =H24*I24 -> 0 | K24: =G24+J24 -> 0 | M24: =M23+K24-L24 -> 2253083.2
A25: 21 | B25: 46195 | E25: 2725 | F25: 102.51 | G25: =E25*F25 -> 279339.75 | H25: 30 | I25: 118.18 | J25: =H25*I25 -> 3545.4 | K25: =G25+J25 -> 282885.15 | M25: =M24+K25-L25 -> 2535968.4
A26: 22 | B26: 46196 | G26: =E26*F26 -> 0 | J26: =H26*I26 -> 0 | K26: =G26+J26 -> 0 | M26: =M25+K26-L26 -> 2535968.4
A27: 23 | B27: 46197 | G27: =E27*F27 -> 0 | J27: =H27*I27 -> 0 | K27: =G27+J27 -> 0 | M27: =M26+K27-L27 -> 2535968.4
A28: 24 | B28: 46198 | G28: =E28*F28 -> 0 | J28: =H28*I28 -> 0 | K28: =G28+J28 -> 0 | L28: 500000 | M28: =M27+K28-L28 -> 2035968.4
A29: 25 | B29: 46199 | G29: =E29*F29 -> 0 | J29: =H29*I29 -> 0 | K29: =G29+J29 -> 0 | M29: =M28+K29-L29 -> 2035968.4
A30: 26 | B30: 46200 | E30: 2400.86 | F30: 102.51 | G30: =E30*F30 -> 246112.16 | J30: =H30*I30 -> 0 | K30: =G30+J30 -> 246112.16 | M30: =M29+K30-L30 -> 2282080.5
A31: 27 | B31: 46201 | G31: =E31*F31 -> 0 | J31: =H31*I31 -> 0 | K31: =G31+J31 -> 0 | M31: =M30+K31-L31 -> 2282080.5
A32: 28 | B32: 46202 | E32: 2550 | F32: 102.51 | G32: =E32*F32 -> 261400.5 | H32: 30 | I32: 118.18 | J32: =H32*I32 -> 3545.4 | K32: =G32+J32 -> 264945.9 | M32: =M31+K32-L32 -> 2547026.4
A33: 29 | B33: 46203 | G33: =E33*F33 -> 0 | J33: =H33*I33 -> 0 | K33: =G33+J33 -> 0 | M33: =M32+K33-L33 -> 2547026.4
A34: 30 | G34: =E34*F34 -> 0 | J34: =H34*I34 -> 0 | K34: =G34+J34 -> 0 | M34: =M33+K34-L34 -> 2547026.4
A35: 31 | G35: =E35*F35 -> 0 | J35: =H35*I35 -> 0 | K35: =G35+J35 -> 0 | M35: =M34+K35-L35 -> 2547026.4
A36: 32 | G36: =E36*F36 -> 0 | J36: =H36*I36 -> 0 | K36: =G36+J36 -> 0 | M36: =M35+K36-L36 -> 2547026.4
A37: 33 | G37: =E37*F37 -> 0 | J37: =H37*I37 -> 0 | K37: =G37+J37 -> 0 | M37: =M36+K37-L37 -> 2547026.4
A38: 34 | G38: =E38*F38 -> 0 | J38: =H38*I38 -> 0 | K38: =G38+J38 -> 0 | M38: =M37+K38-L38 -> 2547026.4
A39: 35 | G39: =E39*F39 -> 0 | J39: =H39*I39 -> 0 | K39: =G39+J39 -> 0 | M39: =M38+K39-L39 -> 2547026.4 | P39: 41
A40: 36 | G40: =E40*F40 -> 0 | J40: =H40*I40 -> 0 | K40: =G40+J40 -> 0 | M40: =M39+K40-L40 -> 2547026.4 | P40: 40 | Q40: 5
A41: 37 | G41: =E41*F41 -> 0 | J41: =H41*I41 -> 0 | K41: =G41+J41 -> 0 | M41: =M40+K41-L41 -> 2547026.4
A42: 38 | G42: =E42*F42 -> 0 | J42: =H42*I42 -> 0 | K42: =G42+J42 -> 0 | M42: =M41+K42-L42 -> 2547026.4
A43: 39 | G43: =E43*F43 -> 0 | J43: =H43*I43 -> 0 | K43: =G43+J43 -> 0 | M43: =M42+K43-L43 -> 2547026.4
A44: 40 | G44: =E44*F44 -> 0 | J44: =H44*I44 -> 0 | K44: =G44+J44 -> 0 | M44: =M43+K44-L44 -> 2547026.4
A45: 41 | G45: =E45*F45 -> 0 | J45: =H45*I45 -> 0 | K45: =G45+J45 -> 0 | M45: =M44+K45-L45 -> 2547026.4
A46: 42 | G46: =E46*F46 -> 0 | J46: =H46*I46 -> 0 | K46: =G46+J46 -> 0 | M46: =M45+K46-L46 -> 2547026.4
