Workbook

Sheet  MIs
A2: S.No | B2: NAme | C2: Lacation | D2: Card Number | E2: Card Number | F2: Category | G2: 1st Jan | I2: 2nd Jan | J2: 3rd Jan | K2: 4th Jan | L2: 5th Jan | M2: 6th Jan | N2: 7th Jan | O2: 8th Jan | P2: 9th Jan | Q2: 10th Jan | R2: 11th Jan | S2: 12th Jan | T2: 13th Jan | U2: 14th Jan | V2: 15th Jan | W2: 16th Jan | X2: 17th Jan | Y2: 18th Jan | Z2: 19th Jan | AA2: 20th Jan | AB2: 21st Jan | AC2: 22nd Jan | AD2: 23rd Jan | AE2: 24th Jan | AF2: 25th Jan | AG2: 26th Jan | AH2: 27th Jan | AI2: 28th Jan | AJ2: 29th Jan | AK2: 30th Jan | AL2: 31st Jan | AM2: Total
F3: Diesel
A4: 1 | B4: Rambabu | C4: HO(Two Wheeler) | D4: FC3450563999 | E4: Diesel | F4: 0 | G4: 0 | H4: 0 | I4: 0 | J4: 0 | K4: 0 | L4: 0 | M4: 0 | N4: 0 | O4: 0 | P4: 0 | Q4: 0 | R4: 0 | S4: 0 | T4: 0 | U4: 0 | V4: 0 | W4: 0 | X4: 5.22 | Y4: 0 | Z4: 0 | AA4: 0 | AB4: 0 | AC4: 0 | AD4: 60 | AE4: 0 | AF4: 0 | AG4: 0 | AH4: 4.56 | AI4: 0 | AJ4: 0 | AK4: 0 | AL4: 0 | AM4: =SUM(F4:AL4) -> 69.78
E5: Petrol | F5: 0 | G5: 4.69 | H5: 0 | I5: 0 | J5: 0 | K5: 0 | L5: 0 | M5: 0 | N5: 3.91 | O5: 0 | P5: 6.98 | Q5: 0 | R5: 0 | S5: 0 | T5: 0 | U5: 0 | V5: 0 | W5: 0 | X5: 0 | Y5: 0 | Z5: 0 | AB5: 0 | AC5: 0 | AD5: 0 | AE5: 0 | AF5: 0 | AG5: 0 | AH5: 0 | AI5: 0 | AJ5: 0 | AK5: 0 | AL5: 0 | AM5: =SUM(F5:AL5) -> 15.58
A6: 2 | B6: Hanumanth Rao | C6: HO | D6: FC3450676131 | E6: Diesel | F6: 0 | G6: 0 | H6: 0 | I6: 0 | J6: 0 | K6: 0 | L6: 0 | M6: 0 | N6: 0 | O6: 0 | P6: 0 | Q6: 0 | R6: 0 | S6: 0 | T6: 0 | U6: 0 | V6: 0 | W6: 0 | X6: 0 | Y6: 0 | Z6: 0 | AA6: 0 | AB6: 0 | AC6: 0 | AD6: 0 | AE6: 0 | AF6: 0 | AG6: 0 | AH6: 0 | AI6: 0 | AJ6: 0 | AK6: 0 | AL6: 0 | AM6: =SUM(F6:AL6) -> 0
E7: Petrol | F7: 0 | G7: 0 | H7: 0 | I7: 0 | J7: 0 | K7: 0 | L7: 0 | M7: 0 | N7: 0 | O7: 0 | P7: 0 | Q7: 0 | R7: 0 | S7: 0 | T7: 0 | U7: 0 | V7: 0 | W7: 0 | X7: 0 | Y7: 0 | Z7: 0 | AB7: 0 | AC7: 0 | AD7: 0 | AE7: 0 | AF7: 0 | AG7: 0 | AH7: 0 | AI7: 0 | AJ7: 0 | AK7: 0 | AL7: 0 | AM7: =SUM(F7:AL7) -> 0
A8: 3 | B8: Radhakrishna | C8: HO | D8: FC8000207658 | E8: Diesel | F8: 0 | G8: 0 | H8: 0 | I8: 0 | J8: 33.44 | K8: 0 | L8: 0 | M8: 0 | N8: 0 | O8: 0 | P8: 0 | Q8: 0 | R8: 35.53 | S8: 0 | T8: 0 | U8: 0 | V8: 0 | W8: 0 | X8: 0 | Y8: 0 | Z8: 0 | AA8: 0 | AB8: 33.44 | AC8: 0 | AD8: 0 | AE8: 0 | AF8: 0 | AG8: 0 | AH8: 0 | AI8: 0 | AJ8: 0 | AK8: 0 | AL8: 0 | AM8: =SUM(F8:AL8) -> 102.41
E9: Petrol | F9: 0 | G9: 0 | H9: 0 | I9: 0 | J9: 0 | K9: 0 | L9: 0 | M9: 0 | N9: 0 | O9: 0 | P9: 0 | Q9: 0 | R9: 0 | S9: 0 | T9: 0 | U9: 0 | V9: 0 | W9: 0 | X9: 0 | Y9: 0 | Z9: 0 | AB9: 0 | AC9: 0 | AD9: 0 | AE9: 0 | AF9: 0 | AG9: 0 | AH9: 0 | AI9: 0 | AJ9: 0 | AK9: 0 | AL9: 0 | AM9: =SUM(F9:AL9) -> 0
A10: 4 | B10: VIjay | C10: HO | D10: FC3450698859 | E10: Diesel | F10: 0 | G10: 0 | H10: 0 | I10: 0 | J10: 0 | K10: 0 | L10: 0 | M10: 0 | N10: 0 | O10: 0 | P10: 49.22 | Q10: 0 | R10: 0 | S10: 0 | T10: 0 | U10: 54.57 | V10: 0 | W10: 0 | X10: 0 | Y10: 0 | Z10: 0 | AA10: 0 | AB10: 0 | AC10: 0 | AD10: 49.8 | AE10: 0 | AF10: 0 | AG10: 0 | AH10: 0 | AI10: 0 | AJ10: 0 | AK10: 0 | AL10: 0 | AM10: =SUM(F10:AL10) -> 153.59
E11: Petrol | F11: 0 | G11: 0 | H11: 0 | I11: 0 | J11: 0 | K11: 0 | L11: 0 | M11: 0 | N11: 0 | O11: 0 | P11: 0 | Q11: 0 | R11: 0 | S11: 0 | T11: 0 | U11: 0 | V11: 0 | W11: 0 | X11: 0 | Y11: 0 | Z11: 0 | AB11: 0 | AC11: 0 | AD11: 0 | AE11: 0 | AF11: 0 | AG11: 0 | AH11: 0 | AI11: 0 | AJ11: 0 | AK11: 0 | AL11: 0 | AM11: =SUM(F11:AL11) -> 0
A12: 5 | B12: Client | C12: Hiriyur | D12: FC3450698864 | E12: Diesel | F12: 0 | G12: 0 | H12: 0 | I12: 0 | J12: 0 | K12: 0 | L12: 0 | M12: 0 | N12: 86.29 | O12: 0 | P12: 0 | Q12: 0 | R12: 0 | S12: 0 | T12: 0 | U12: 0 | V12: 0 | W12: 0 | X12: 0 | Y12: 0 | Z12: 0 | AA12: 0 | AB12: 0 | AC12: 0 | AD12: 145.61 | AE12: 0 | AF12: 0 | AG12: 0 | AH12: 0 | AI12: 0 | AJ12: 0 | AK12: 0 | AL12: 0 | AM12: =SUM(F12:AL12) -> 231.9
E13: Petrol | F13: 0 | G13: 0 | H13: 0 | I13: 0 | J13: 0 | K13: 0 | L13: 0 | M13: 0 | N13: 0 | O13: 0 | P13: 0 | Q13: 0 | R13: 0 | S13: 0 | T13: 0 | U13: 0 | V13: 0 | W13: 0 | X13: 0 | Y13: 0 | Z13: 0 | AB13: 0 | AC13: 0 | AD13: 0 | AE13: 0 | AF13: 0 | AG13: 0 | AH13: 0 | AI13: 0 | AJ13: 0 | AK13: 0 | AL13: 0 | AM13: =SUM(F13:AL13) -> 0
A14: 6 | B14: Client | C14: Hosadurga | D14: FC3450698865 | E14: Diesel | F14: 0 | G14: 0 | H14: 0 | I14: 0 | J14: 0 | K14: 0 | L14: 40 | M14: 40 | N14: 0 | O14: 36 | P14: 35 | Q14: 0 | R14: 0 | S14: 0 | T14: 0 | U14: 0 | V14: 0 | W14: 45 | X14: 45 | Y14: 43.53 | Z14: 40 | AA14: 43 | AB14: 0 | AC14: 40 | AD14: 0 | AE14: 40 | AF14: 0 | AG14: 0 | AH14: 0 | AI14: 0 | AJ14: 0 | AK14: 0 | AL14: 0 | AM14: =SUM(F14:AL14) -> 447.53
E15: Petrol | F15: 0 | G15: 0 | H15: 0 | I15: 0 | J15: 0 | K15: 0 | L15: 0 | M15: 0 | N15: 0 | O15: 0 | P15: 0 | Q15: 0 | R15: 0 | S15: 0 | T15: 0 | U15: 0 | V15: 0 | W15: 0 | X15: 0 | Y15: 0 | Z15: 0 | AB15: 0 | AC15: 0 | AD15: 0 | AE15: 0 | AF15: 0 | AG15: 0 | AH15: 0 | AI15: 0 | AJ15: 0 | AK15: 0 | AL15: 0 | AM15: =SUM(F15:AL15) -> 0
G18: Diesel Price

Sheet OCT-26
A1: S.no | B1: Site Name | C1: Bunk Name | D1: Diesel(Liters) | E1: Diesel Amount | F1: Petrol(Liters) | G1: Petrol Amount | H1: Total Amount | I1: Opening Blance | J1: Amount Paid | K1: Closing Balances
A2: 1 | B2: Khammam-1 | C2: Divya laxmi ganapathi | D2: =+'Khammam-1'!E38 -> 5000 | E2: =+'Khammam-1'!G38 -> 519000 | F2: =+'Khammam-1'!H38 -> 350 | G2: =+'Khammam-1'!J38 -> 40491.5 | H2: =E2+G2 -> 559491.5 | I2: =+'Khammam-1'!K3 -> 4131883.8 | J2: =+'Khammam-1'!L38 -> 400000 | K2: =H2+I2-J2 -> 4291375.3
A3: 2 | B3: Khammam-2 | C3: Jayasai union bunk | D3: =+'Khammam-2'!E39 -> 29600 | E3: =+'Khammam-2'!G39 -> 3073072 | F3: =+'Khammam-2'!H39 -> 130 | G3: =+'Khammam-2'!J39 -> 15043.6 | H3: =E3+G3 -> 3088115.6 | I3: =+'Khammam-2'!K3 -> 4248603.6 | J3: =+'Khammam-2'!L39 -> 2000000 | K3: =H3+I3-J3 -> 5336719.2
A4: 4 | B4: Khammam | C4: Sai Madeana Filling Station | D4: =+'Khammam-4'!E35 -> 2700 | E4: =+'Khammam-4'!G35 -> 279774 | F4: =+'Khammam-4'!H35 -> 75 | G4: =+'Khammam-4'!J35 -> 8661.75 | H4: =E4+G4 -> 288435.75 | I4: =+'Khammam-4'!M3 -> 3141611.1 | J4: =+'Khammam-4'!L35 -> 288435.75 | K4: =H4+I4-J4 -> 3141611.1
A5: 5 | B5: Khammam | C5: Vajra mahalakshmi filling station | D5: =+' Khammam-5'!E35 -> 0 | E5: =+' Khammam-5'!G35 -> 0 | F5: =+' Khammam-5'!H35 -> 0 | G5: =+' Khammam-5'!J35 -> 0 | H5: =E5+G5 -> 0 | I5: =+' Khammam-5'!M3 -> 1445001.9 | J5: =+' Khammam-5'!L35 -> 0 | K5: =H5+I5-J5 -> 1445001.9
A6: 6 | B6: Khammam-Cash&Carry | C6: NA | D6: =+' Khammam&Cash'!E46 -> 0 | E6: =+' Khammam&Cash'!G46 -> 0 | F6: =+' Khammam&Cash'!H46 -> 0 | G6: =+' Khammam&Cash'!J46 -> 0 | H6: =E6+G6 -> 0 | I6: =+' Khammam&Cash'!M3 -> 0 | J6: =+' Khammam&Cash'!L46 -> 0 | K6: =H6+I6-J6 -> 0
A7: 7 | B7: Jadcherla-2 | C7: Shree Poornima F/S | D7: =+'Jadcherla-4'!E35 -> 100 | E7: =+'Jadcherla-4'!G35 -> 10442 | F7: =+'Jadcherla-4'!H35 -> 0 | G7: =+'Jadcherla-4'!J35 -> 0 | H7: =E7+G7 -> 10442 | I7: =+'Jadcherla-4'!M3 -> 47858.18 | J7: =+'Jadcherla-4'!L35 -> 50000 | K7: =H7+I7-J7 -> 8300.18
A8: 8 | B8: Sangareddy-2 | C8: Durga Bhavani F/S | D8: =+' Sangareddy-2'!E35 -> 0 | E8: =+' Sangareddy-2'!G35 -> 0 | F8: =+' Sangareddy-2'!H35 -> 0 | G8: =+' Sangareddy-2'!J35 -> 0 | H8: =E8+G8 -> 0 | I8: =+' Sangareddy-2'!M3 -> 0 | J8: =+' Sangareddy-2'!L35 -> 0 | K8: =H8+I8-J8 -> 0
A9: 9 | B9: Sangareddy-3 | C9: Shiva Parvathi Filling Station | D9: =+' Sangareddy-3'!E36 -> 5520 | E9: =+' Sangareddy-3'!G36 -> 576012 | F9: =+' Sangareddy-3'!H36 -> 60 | G9: =+' Sangareddy-3'!J36 -> 6975 | H9: =E9+G9 -> 582987 | I9: =+' Sangareddy-3'!M3 -> 366809.49 | J9: =+' Sangareddy-3'!L36 -> 0 | K9: =H9+I9-J9 -> 949796.49
A10: 10 | B10: NarayanaKhed | C10: Sai Shiva Filling Station | D10: =Narayankhed!E36 -> 1522.561 | E10: =+Narayankhed!G36 -> 160000.2 | F10: =+Narayankhed!H36 -> 0 | G10: =+Narayankhed!J36 -> 0 | H10: =E10+G10 -> 160000.2 | I10: =+Narayankhed!M3 -> 0 | J10: =+Narayankhed!L36 -> 160000.2 | K10: =H10+I10-J10 -> 0
A11: 11 | B11: Dindi | C11: Akarapu Balakistamma Fillling | D11: =+Dindi!E35 -> 67.52 | E11: =+Dindi!G35 -> 7086.224 | F11: =+Dindi!H35 -> 0 | G11: =+Dindi!J35 -> 0 | H11: =E11+G11 -> 7086.224 | I11: =+Dindi!M3 -> 0 | J11: =+Dindi!L35 -> 7086.224 | K11: =H11+I11-J11 -> 0
A12: 12 | B12: Madanapalli | C12: NA | D12: =+'Madana palli'!E37 -> 0 | E12: =+'Madana palli'!G37 -> 0 | F12: =+'Madana palli'!H37 -> 0 | G12: =+'Madana palli'!J37 -> 0 | H12: =E12+G12 -> 0 | I12: =+'Madana palli'!M3 -> 0 | J12: =+'Madana palli'!L37 -> 0 | K12: =H12+I12-J12 -> 0
A13: 13 | B13: Kovvur | C13: Sri Venkateshwara Services | D13: =+'Sri Venkateshwara Services'!E37 -> 2274.37 | E13: =+'Sri Venkateshwara Services'!G37 -> 238081.05 | F13: =+'Sri Venkateshwara Services'!H37 -> 426 | G13: =+'Sri Venkateshwara Services'!J37 -> 49824.96 | H13: =E13+G13 -> 287906.01 | I13: =+'Sri Venkateshwara Services'!M3 -> 115419.84 | J13: =+'Sri Venkateshwara Services'!L37 -> 338000 | K13: =H13+I13-J13 -> 65325.85
A14: 14 | B14: Jangareddygudem | C14: Solasa Krishna Oil Company | D14: =+' Solasa Krishna OIl'!E37 -> 2252.17 | E14: =+' Solasa Krishna OIl'!G37 -> 237378.72 | F14: =+' Solasa Krishna OIl'!H37 -> 40.2 | G14: =+' Solasa Krishna OIl'!J37 -> 4733.148 | H14: =E14+G14 -> 242111.87 | I14: =+' Solasa Krishna OIl'!M3 -> 238901.54 | J14: =+' Solasa Krishna OIl'!L37 -> 200000 | K14: =H14+I14-J14 -> 281013.4
A15: 15 | B15: Amalapuram | C15: Royal Fill 'N' Fly | D15: =+'Amalapuram(KKD)'!E37 -> 5710 | E15: =+'Amalapuram(KKD)'!G37 -> 600977.5 | F15: =+'Amalapuram(KKD)'!H37 -> 113.55 | G15: =+'Amalapuram(KKD)'!J37 -> 13351.209 | H15: =E15+G15 -> 614328.71 | I15: =+'Amalapuram(KKD)'!M3 -> 519637.76 | J15: =+'Amalapuram(KKD)'!L37 -> 1000000 | K15: =H15+I15-J15 -> 133966.47
A16: 16 | B16: Yeleshwaram | C16: Sri sathya Filling Station | D16: =+'Yeleshwaram(KKD)'!E37 -> 1087 | E16: =+'Yeleshwaram(KKD)'!G37 -> 114635.02 | F16: =+'Yeleshwaram(KKD)'!H37 -> 110 | G16: =+'Yeleshwaram(KKD)'!J37 -> 12962.4 | H16: =E16+G16 -> 127597.42 | I16: =+'Yeleshwaram(KKD)'!M3 -> 17080.343 | J16: =+'Yeleshwaram(KKD)'!L37 -> 80000 | K16: =H16+I16-J16 -> 64677.763
A17: 17 | B17: Pitapuam | C17: Satya Siva Durga Agencies, Chebrolu | D17: =+' Pitapram(KKD)'!E37 -> 1222.54 | E17: =+' Pitapram(KKD)'!G37 -> 128623.43 | F17: =+' Pitapram(KKD)'!H37 -> 55 | G17: =+' Pitapram(KKD)'!J37 -> 6466.9 | H17: =E17+G17 -> 135090.33 | I17: =+' Pitapram(KKD)'!M3 -> 291832.98 | J17: =+' Pitapram(KKD)'!L37 -> 423000 | K17: =H17+I17-J17 -> 3923.3177
A18: 18 | B18: Kakinada | C18: Multiple bunks | D18: =+' Pitapram(KKD)'!E38 -> 0 | E18: =+' Pitapram(KKD)'!G38 -> 0 | F18: =+' Pitapram(KKD)'!H38 -> 0 | G18: =+' Pitapram(KKD)'!J38 -> 0 | H18: =E18+G18 -> 0 | I18: =+'Multiple bunks(KKD)'!M3 -> 0 | J18: =+' Pitapram(KKD)'!L38 -> 0 | K18: =H18+I18-J18 -> 0
A19: 19 | B19: YG Gudda-2 | C19: Pankaja HP Fuel Center | D19: =+'YG Gudda'!E39 -> 4600 | E19: =+'YG Gudda'!G39 -> 456044 | F19: =+'YG Gudda'!H39 -> 210 | G19: =+'YG Gudda'!J39 -> 23360.4 | H19: =E19+G19 -> 479404.4 | I19: =+'YG Gudda'!M3 -> 305951.76 | J19: =+'YG Gudda'!L39 -> 600000 | K19: =H19+I19-J19 -> 185356.16
A20: 20 | B20: YG Gudda-2 | C20: One stop | D20: =+' YG Gudda-2'!E39 -> 800 | E20: =+' YG Gudda-2'!G39 -> 79216 | F20: =+' YG Gudda-2'!H39 -> 35 | G20: =+' YG Gudda-2'!J39 -> 3889.2 | H20: =E20+G20 -> 83105.2 | I20: =+' YG Gudda-2'!M3 -> 255923.32 | J20: =+' YG Gudda-2'!L39 -> 200000 | K20: =H20+I20-J20 -> 139028.52
A21: 21 | B21: Hosadurga-2 | C21: Shree Veeraprathap Fuel | D21: =+'Hosadurga -2'!E35 -> 1000 | E21: =+'Hosadurga -2'!G35 -> 99360 | F21: =+'Hosadurga -2'!H35 -> 100 | G21: =+'Hosadurga -2'!J35 -> 11168 | H21: =+'Hosadurga -2'!K35 -> 110528 | I21: =+'Hosadurga -2'!M3 -> 126009.99 | J21: =+'Hosadurga -2'!L35 -> 226000 | K21: =H21+I21-J21 -> 10537.994
A22: 22 | B22: Malebennuru(KUWSDB) | C22: Sri Ramanjuneya Service Station | D22: =+'Malebenur(KUWSDB)'!E39 -> 3866.63 | E22: =+'Malebenur(KUWSDB)'!G39 -> 386591.66 | F22: =+'Malebenur(KUWSDB)'!H39 -> 109.99 | G22: =+'Malebenur(KUWSDB)'!J39 -> 12319.979 | H22: =E22+G22 -> 398911.64 | I22: =+'Malebenur(KUWSDB)'!M3 -> 290892.11 | J22: =+'Malebenur(KUWSDB)'!L39 -> 300029.24 | K22: =H22+I22-J22 -> 389774.51
A23: 23 | B23: kadur | C23: Vishal Service Station | D23: =+Kadur!E35 -> 0 | E23: =+Kadur!G35 -> 0 | F23: =+Kadur!H35 -> 0 | G23: =+Kadur!J35 -> 0 | H23: =E23+G23 -> 0 | I23: =+Kadur!K3 -> 175658 | J23: =+Kadur!L35 -> 100000 | K23: =H23+I23-J23 -> 75658
A24: 24 | B24: Hiriyur(VJNL) | C24: Sri Balaji Agencies | D24: =+'Hiriyur(VJNL)'!E35 -> 2600 | E24: =+'Hiriyur(VJNL)'!G35 -> 260182 | F24: =+'Hiriyur(VJNL)'!H35 -> 120 | G24: =+'Hiriyur(VJNL)'!J35 -> 13450.8 | H24: =E24+G24 -> 273632.8 | I24: =+'Hiriyur(VJNL)'!K3 -> 212444.1 | J24: =+'Hiriyur(VJNL)'!L35 -> 278000 | K24: =H24+I24-J24 -> 208076.9
A25: 25 | B25: Chellakere(KUWSDB) | C25: Shivaganga Service Station | D25: =+'Chellakere -1'!E38 -> 1800 | E25: =+'Chellakere -1'!G38 -> 180054 | F25: =+'Chellakere -1'!H38 -> 105 | G25: =+'Chellakere -1'!J38 -> 11764.2 | H25: =E25+G25 -> 191818.2 | I25: =+'Chellakere -1'!K3 -> 0 | J25: =+'Chellakere -1'!L38 -> 200000 | K25: =H25+I25-J25 -> -8181.8
A26: 26 | B26: Chellakere(KUWSDB)-09 | C26: Shivaganga Service Station | D26: =+' Chellakere-PKG-9'!E38 -> 283.42 | E26: =+' Chellakere-PKG-9'!G38 -> 28349.969 | F26: =+' Chellakere-PKG-9'!H38 -> 30 | G26: =+' Chellakere-PKG-9'!J38 -> 3361.2 | H26: =E26+G26 -> 31711.169 | I26: =+' Chellakere-PKG-9'!M3 -> 0 | J26: =+' Chellakere-PKG-9'!L38 -> 21028.499 | K26: =H26+I26-J26 -> 10682.67
A27: 27 | B27: Molakalmuru | C27: Sri Lakshmi Venkateshwara Filling Station | D27: =+Molakamuru!E35 -> 500 | E27: =+Molakamuru!G35 -> 50015 | F27: =+Molakamuru!H35 -> 40 | G27: =+Molakamuru!J35 -> 4481.2 | H27: =E27+G27 -> 54496.2 | I27: =+Molakamuru!K3 -> 44770.66 | J27: =+Molakamuru!L35 -> 0 | K27: =H27+I27-J27 -> 99266.86
A28: 28 | B28: Chennagiri | C28: NA | D28: =+' Chennagiri'!E35 -> 615 | E28: =+' Chennagiri'!G35 -> 61411.7 | F28: =+' Chennagiri'!H35 -> 35 | G28: =+' Chennagiri'!J35 -> 3921.05 | H28: =E28+G28 -> 65332.75 | I28: =+' Chennagiri'!K3 -> 0 | J28: =+' Chennagiri'!L35 -> 65332.75 | K28: =H28+I28-J28 -> 0
A29: 29 | B29: Khanapur(PKG-3) | C29: V.V.Varde | D29: =+Khanapur!E35 -> 245.6 | E29: =+Khanapur!G35 -> 24266.906 | F29: =+Khanapur!H35 -> 60 | G29: =+Khanapur!J35 -> 6644.4 | H29: =E29+G29 -> 30911.306 | I29: =+Khanapur!M3 -> 120785.13 | J29: =+Khanapur!L35 -> 100000 | K29: =H29+I29-J29 -> 51696.435
A30: 30 | B30: Munavalli(PKG-3) | C30: Shre Shiva Petroleum | D30: =+'Munavali-2'!E40 -> 2000 | E30: =+'Munavali-2'!G40 -> 198700 | F30: =+'Munavali-2'!H40 -> 0 | G30: =+'Munavali-2'!J40 -> 0 | H30: =E30+G30 -> 198700 | I30: =+'Munavali-2'!M3 -> 263421.5 | J30: =+'Munavali-2'!L40 -> 363000 | K30: =H30+I30-J30 -> 99121.5
A31: 31 | B31: Munavalli(PKG-3) | C31: Daneshwari Petroleum | D31: =+' Munavali'!E39 -> 0 | E31: =+' Munavali'!G39 -> 0 | F31: =+' Munavali'!H39 -> 150 | G31: =+' Munavali'!J39 -> 16681.5 | H31: =E31+G31 -> 16681.5 | I31: =+' Munavali'!M3 -> 30045.067 | J31: =+' Munavali'!L39 -> 0 | K31: =H31+I31-J31 -> 46726.567
A32: 33 | B32: Ugar,Kudichi(PKG-3) | C32: Shiri Bhrhmanath Petrolium | D32: =+'Ugar,Khagwad,Kudichi'!E38 -> 2722.45 | E32: =+'Ugar,Khagwad,Kudichi'!G38 -> 271502.24 | F32: =+'Ugar,Khagwad,Kudichi'!H38 -> 215 | G32: =+'Ugar,Khagwad,Kudichi'!J38 -> 24048.8 | H32: =E32+G32 -> 295551.04 | I32: =+'Ugar,Khagwad,Kudichi'!M3 -> 300655.8 | J32: =+'Ugar,Khagwad,Kudichi'!L38 -> 161435.49 | K32: =H32+I32-J32 -> 434771.35
A33: 34 | B33: Shedbal | C33: Varad Petroluem | D33: =+shedbal!E38 -> 1136 | E33: =+shedbal!G38 -> 113293.28 | F33: =+shedbal!H38 -> 77 | G33: =+shedbal!J38 -> 8612.45 | H33: =E33+G33 -> 121905.73 | I33: =+shedbal!M3 -> 158612.05 | J33: =+shedbal!L38 -> 150000 | K33: =H33+I33-J33 -> 130517.78
A34: 35 | B34: Kabbur(PKG-3) | C34: Shri Jai Hanuman Petrolium | D34: =+Kabbur!E35 -> 30 | E34: =+Kabbur!G35 -> 2982.3 | F34: =+Kabbur!H35 -> 0 | G34: =+Kabbur!J35 -> 0 | H34: =E34+G34 -> 2982.3 | I34: 0 | J34: =+Kabbur!L35 -> 2982.3 | K34: =H34+I34-J34 -> 0
A35: 36 | B35: Kumta (PKG-1) | C35: V.M.Mirjankar (Kumta) Bharat | D35: =+kumta!E41 -> 894.82 | E35: =+kumta!G41 -> 89285.14 | F35: =+kumta!H41 -> 39 | G35: =+kumta!J41 -> 4367.22 | H35: =E35+G35 -> 93652.36 | I35: =kumta!M3 -> 84520.658 | J35: =+kumta!L41 -> 100000 | K35: =H35+I35-J35 -> 78173.018
A36: 37 | B36: Jalgaon-2 | C36: Nayara | D36: =+'Jalgoan-2'!E56 -> 0 | E36: ='Jalgoan-2'!G56 -> 0 | F36: =+'Jalgoan-2'!H56 -> 60 | G36: =+'Jalgoan-2'!J56 -> 7090.8 | H36: =E36+G36 -> 7090.8 | I36: =+'Jalgoan-2'!M3 -> 605152.24 | J36: =+'Jalgoan-2'!L56 -> 0 | K36: =H36+I36-J36 -> 612243.04
A37: 38 | B37: MKBD | C37: Shree Sai Samarth Petroleum | D37: =+MKBD!E42 -> 3800 | E37: =+MKBD!G42 -> 375972 | F37: =+MKBD!H42 -> 40 | G37: =+MKBD!J42 -> 4490.8 | H37: =E37+G37 -> 380462.8 | I37: =+MKBD!K3 -> 0 | J37: =+MKBD!L42 -> 0 | K37: =H37+I37-J37 -> 380462.8
A38: 39 | B38: Haveri | C38: M/s Magavi City Fuels | D38: =' Haveri-2'!E42 -> 3207.57 | E38: =' Haveri-2'!G42 -> 318511.7 | F38: =' Haveri-2'!H42 -> 48 | G38: =' Haveri-2'!J42 -> 5347.2 | H38: =E38+G38 -> 323858.9 | I38: =' Haveri-2'!M3 -> 82823.565 | J38: =+' Haveri-2'!L42 -> 350000 | K38: =H38+I38-J38 -> 56682.466
A39: 40 | B39: Guttal-2 | C39: Himagiri Petroleum | D39: =+' Guttal-2'!E35 -> 1664 | E39: =+' Guttal-2'!G35 -> 165734.4 | F39: =+' Guttal-2'!H35 -> 107.61 | G39: =+' Guttal-2'!J35 -> 12021.113 | H39: =E39+G39 -> 177755.51 | I39: =+' Guttal-2'!M3 -> 459610.06 | J39: =+' Guttal-2'!L35 -> 550000 | K39: =H39+I39-J39 -> 87365.57
A40: 41 | B40: Rattihali-2 | C40: Shiva Oil Traders | D40: =+'Rattihali-2'!E37 -> 1647.32 | E40: =+'Rattihali-2'!G37 -> 164237.8 | F40: =+'Rattihali-2'!H37 -> 95 | G40: =+'Rattihali-2'!J37 -> 10622.9 | H40: =E40+G40 -> 174860.7 | I40: =+'Rattihali-2'!M3 -> 161393.37 | J40: =+'Rattihali-2'!L37 -> 200000 | K40: =H40+I40-J40 -> 136254.08
A41: 42 | B41: Gajendragada | C41: Vanasri Petrol Pump | D41: =+Gajendragada!E36 -> 336 | E41: =+Gajendragada!G36 -> 33479.04 | F41: =+Gajendragada!H36 -> 60.73 | G41: =+Gajendragada!J36 -> 6787.7921 | H41: =E41+G41 -> 40266.832 | I41: =+Gajendragada!M3 -> 126924.96 | J41: =+Gajendragada!L36 -> 0 | K41: =H41+I41-J41 -> 167191.79
A42: 43 | B42: Gokak(PKG-3) | C42: AJ Petrolinks | D42: =+'Gokak Dharwad PKG 3'!E42 -> 2123.79 | E42: =+'Gokak Dharwad PKG 3'!G42 -> 210871.11 | F42: =+'Gokak Dharwad PKG 3'!H42 -> 5 | G42: =+'Gokak Dharwad PKG 3'!J42 -> 556.9 | H42: =E42+G42 -> 211428.01 | I42: =+'Gokak Dharwad PKG 3'!K3 -> 458335.94 | J42: =+'Gokak Dharwad PKG 3'!L42 -> 550000 | K42: =H42+I42-J42 -> 119763.95
A43: 44 | B43: Hukkere | C43: TR Assocites | D43: =+' TR Associates'!E35 -> 6567.06 | E43: =+' TR Associates'!G35 -> 650992.66 | F43: =+' TR Associates'!H35 -> 0 | G43: =+' TR Associates'!J35 -> 0 | H43: =E43+G43 -> 650992.66 | I43: =+' TR Associates'!M3 -> 703648.01 | J43: =+' TR Associates'!L35 -> 0 | K43: =H43+I43-J43 -> 1354640.7
A44: 45 | B44: Ankaligi | C44: Shivaganga | D44: =+Ankalgi!E35 -> 1506.28 | E44: =+Ankalgi!G35 -> 149317.54 | F44: =+Ankalgi!H35 -> 15 | G44: =+Ankalgi!J35 -> 1668.15 | H44: =E44+G44 -> 150985.69 | I44: =+Ankalgi!M3 -> 120724.02 | J44: =+Ankalgi!L35 -> 0 | K44: =H44+I44-J44 -> 271709.71
A45: 46 | B45: Ghattaprabha | C45: Shri Deshpande | D45: =+'SHRI DESHPANDE'!E35 -> 5194.61 | E45: =+'SHRI DESHPANDE'!G35 -> 516188.4 | F45: =+'SHRI DESHPANDE'!H35 -> 215 | G45: =+'SHRI DESHPANDE'!J35 -> 23963.9 | H45: =E45+G45 -> 540152.3 | I45: =+'SHRI DESHPANDE'!M3 -> 693317.08 | J45: =+'SHRI DESHPANDE'!L35 -> 0 | K45: =H45+I45-J45 -> 1233469.4
A46: 47 | B46: ShankeshWAR | C46: SR Patil | D46: =+' Shankeshwar'!E35 -> 0 | E46: =+' Shankeshwar'!G35 -> 0 | F46: =+' Shankeshwar'!H35 -> 10 | G46: =+' Shankeshwar'!J35 -> 1112 | H46: =E46+G46 -> 1112 | I46: =' Shankeshwar'!M3 -> 0 | J46: =+' Shankeshwar'!L35 -> 1112 | K46: =H46+I46-J46 -> 0
A47: 48 | B47: Talikote(PKG-1) | C47: Raykar Oil Agencies | D47: =+' Talikote'!E48 -> 25 | E47: =+' Talikote'!G48 -> 2480.75 | F47: =+' Talikote'!H48 -> 0.9 | G47: =+' Talikote'!J48 -> 100.278 | H47: =E47+G47 -> 2581.028 | I47: =+' Talikote'!M3 -> 74297.812 | J47: =+' Talikote'!L48 -> 75100.28 | K47: =H47+I47-J47 -> 1778.5601
A48: 49 | B48: Chadchan(PKG-1) | C48: Khavekar Petrolium | D48: =+Chadchan!E35 -> 405.86 | E48: =+Chadchan!G35 -> 40354.183 | F48: =+Chadchan!H35 -> 50.97 | G48: =+Chadchan!J35 -> 5708.1043 | H48: =E48+G48 -> 46062.288 | I48: =+Chadchan!M3 -> 124570.71 | J48: =+Chadchan!L35 -> 0 | K48: =H48+I48-J48 -> 170633
A49: 50 | B49: Sindagi | C49: G.P.PORWAL | D49: =+Sindagi!E35 -> 150 | E49: =+Sindagi!G35 -> 14860.5 | F49: =+Sindagi!H35 -> 0 | G49: =+Sindagi!J35 -> 0 | H49: =E49+G49 -> 14860.5 | I49: =+Sindagi!M3 -> 27734.19 | J49: =+Sindagi!L35 -> 38500 | K49: =H49+I49-J49 -> 4094.69
A50: 51 | B50: Muddebihal(PKG-1)2 | C50: PS NAGATHAN PETROLIUM | D50: =+'Muddebhihal-2'!E50 -> 1022.29 | E50: =+'Muddebhihal-2'!G50 -> 101441.84 | F50: =+'Muddebhihal-2'!H50 -> 47 | G50: =+'Muddebhihal-2'!J50 -> 5250.84 | H50: =+'Muddebhihal-2'!K50 -> 106692.68 | I50: =+'Muddebhihal-2'!M3 -> 178474.12 | J50: =+'Muddebhihal-2'!L50 -> 150000 | K50: =+'Muddebhihal-2'!M49 -> 135166.8
A51: 52 | B51: Almela(PKG-1) | C51: Shiddeshwar Petroleums | D51: =+Alemela!E43 -> 174.75 | E51: =+Alemela!G43 -> 17349.18 | F51: =+Alemela!H43 -> 22.29 | G51: =+Alemela!J43 -> 2482.6602 | H51: =E51+G51 -> 19831.84 | I51: =+Alemela!M3 -> 23063 | J51: =+Alemela!L43 -> 29000 | K51: =H51+I51-J51 -> 13894.84
A52: 53 | B52: Nalatwad(PKG-1) | C52: Shri Pawad Basaweshwar Petroleums | D52: =+Nalatwad!E43 -> 876.51 | E52: =+Nalatwad!G43 -> 87160.154 | F52: =+Nalatwad!H43 -> 50.33 | G52: =+Nalatwad!J43 -> 5671.8551 | H52: =E52+G52 -> 92832.01 | I52: =+Nalatwad!M3 -> 135406.61 | J52: =+Nalatwad!L43 -> 0 | K52: =H52+I52-J52 -> 228238.62
A53: 54 | B53: Srirangapatna | C53: Anupama F/S | D53: =+Srirangapatna!E35 -> 0 | E53: =+Srirangapatna!G35 -> 0 | F53: =+Srirangapatna!H35 -> 0 | G53: =+Srirangapatna!J35 -> 0 | H53: =E53+G53 -> 0 | I53: 0 | J53: =+Srirangapatna!L35 -> 0 | K53: =H53+I53-J53 -> 0
A54: 55 | B54: HO(DG) | C54: Multiple bunks | D54: =+'HO(DG)'!E48 -> 150 | E54: =+'HO(DG)'!G48 -> 15564 | F54: =+'HO(DG)'!H48 -> - | G54: =+'HO(DG)'!J48 -> - | H54: =E54+G54 -> #VALUE! | I54: =+'HO(DG)'!M3 -> 0 | J54: =+'HO(DG)'!L48 -> 15564 | K54: =H54+I54-J54 -> #VALUE!
A55: Total | D55: =SUM(D2:D54) -> 109001.12 | E55: =SUM(E2:E54) -> 11110852 | F55: =SUM(F2:F54) -> 3513.57 | G55: =SUM(G2:G54) -> 399456.16 | H55: =SUM(H2:H54) -> #VALUE! | I55: =SUM(I2:I54) -> 20909806 | J55: =SUM(J2:J54) -> 9773606.7 | K55: =H55+I55-J55 -> #VALUE!
I56: 36038811
I57: =I55-I56 -> -15129005
A60: S.no | B60: Site Name | C60: Bunk Name | D60: Diesel(Liters) | E60: Diesel Amount | F60: Petrol(Liters) | G60: Petrol Amount | H60: Total Amount | I60: Opening Blance | J60: Amount Paid | K60: Closing Balances
A61: 39 | B61: {=VLOOKUP(A61,A1:K53,{2,3,4,5,6,7,8,9,10,11},FALSE)} -> Haveri | C61: M/s Magavi City Fuels | D61: 3207.57 | E61: 318511.7 | F61: 48 | G61: 5347.2 | H61: 323858.9 | I61: 82823.565 | J61: 350000 | K61: 56682.466
B63: Site Name | C63: Bunk Name | D63: Diesel(Liters) | E63: Diesel Amount | F63: Petrol(Liters) | G63: Petrol Amount | H63: Total Amount | I63: Opening Blance | J63: Amount Paid | K63: Closing Balances
B64: Jalgaon-2 | C64: {=VLOOKUP(B64,B1:K53,{2,3,4,5,6,7,8,9,10},FALSE)} -> Nayara | D64: 0 | E64: 0 | F64: 60 | G64: 7090.8 | H64: 7090.8 | I64: 605152.24 | J64: 0 | K64: 612243.04
B71: 60000
B72: 18000
B73: 18000
B74: 75000
B75: 360000

Sheet HO(DG)
A2: S.No | B2: Date | C2: GRN No | D2: Ind No/Bill No | E2: Diesel (Lts) | F2: Price | G2: Amount | H2: Petrol (Lts) | I2: Price | J2: Amount | K2: Total amount | L2: Amount paid | M2: As on date | N2: Remarks
A3: Opening Balance | K3: - | M3: 0
A4: 1 | B4: 46296 | G4: - | H4: - | I4: - | J4: - | K4: - | L4: - | M4: -
A5: 2 | B5: 46297 | G5: - | H5: - | I5: - | J5: - | K5: - | M5: -
A6: 3 | B6: 46298 | E6: 50 | F6: 103.76 | G6: =E6*F6 -> 5188 | H6: 0 | I6: 0 | J6: =H6*I6 -> 0 | K6: =G6+J6 -> 5188 | L6: 5188 | M6: -
A7: 4 | B7: 46299 | E7: 0 | F7: 0 | G7: =E7*F7 -> 0 | H7: 0 | I7: 0 | J7: =H7*I7 -> 0 | K7: =G7+J7 -> 0 | M7: -
A8: 5 | B8: 46300 | E8: 100 | F8: 103.76 | G8: =E8*F8 -> 10376 | H8: 0 | I8: 0 | J8: =H8*I8 -> 0 | K8: =G8+J8 -> 10376 | L8: 10376 | M8: -
A9: 6 | B9: 46301 | E9: 40 | F9: 103.76 | G9: =E9*F9 -> 4150.4 | H9: 0 | I9: 0 | J9: =H9*I9 -> 0 | K9: =G9+J9 -> 4150.4 | L9: 4150.4 | M9: -
A10: 7 | B10: 46302 | E10: 0 | F10: 0 | G10: =E10*F10 -> 0 | H10: 0 | I10: 0 | J10: =H10*I10 -> 0 | K10: =G10+J10 -> 0 | M10: -
A11: 8 | B11: 46303 | E11: 0 | F11: 0 | G11: =E11*F11 -> 0 | H11: 0 | I11: 0 | J11: =H11*I11 -> 0 | K11: =G11+J11 -> 0 | M11: -
A12: 9 | B12: 46304 | E12: 0 | F12: 0 | G12: =E12*F12 -> 0 | H12: 0 | I12: 0 | J12: =H12*I12 -> 0 | K12: =G12+J12 -> 0 | M12: -
A13: 10 | B13: 46305 | E13: 0 | F13: 0 | G13: =E13*F13 -> 0 | H13: 0 | I13: 0 | J13: =H13*I13 -> 0 | K13: =G13+J13 -> 0 | M13: -
A14: 11 | B14: 46306 | E14: 0 | F14: 0 | G14: =E14*F14 -> 0 | H14: 0 | I14: 0 | J14: =H14*I14 -> 0 | K14: =G14+J14 -> 0 | M14: -
A15: 12 | B15: 46307 | E15: 0 | F15: 0 | G15: =E15*F15 -> 0 | H15: 0 | I15: 0 | J15: =H15*I15 -> 0 | K15: =G15+J15 -> 0 | M15: -
A16: 13 | B16: 46308 | E16: 0 | F16: 0 | G16: =E16*F16 -> 0 | H16: 0 | I16: 0 | J16: =H16*I16 -> 0 | K16: =G16+J16 -> 0 | M16: -
A17: 14 | B17: 46309 | E17: 50 | F17: 103.76 | G17: =E17*F17 -> 5188 | H17: 0 | I17: 0 | J17: =H17*I17 -> 0 | K17: =G17+J17 -> 5188 | M17: -
A18: 15 | B18: 46310 | E18: 0 | F18: 0 | G18: =E18*F18 -> 0 | H18: 0 | I18: 0 | J18: =H18*I18 -> 0 | K18: =G18+J18 -> 0 | M18: -
A19: 16 | B19: 46311 | E19: 0 | F19: 0 | G19: =E19*F19 -> 0 | H19: 0 | I19: 0 | J19: =H19*I19 -> 0 | K19: =G19+J19 -> 0 | M19: -
A20: 17 | B20: 46312 | E20: 0 | F20: 0 | G20: =E20*F20 -> 0 | H20: 0 | I20: 0 | J20: =H20*I20 -> 0 | K20: =G20+J20 -> 0 | M20: -
A21: 18 | B21: 46313 | M21: -
A22: 19 | B22: 46314 | K22: - | M22: -
A23: 20 | B23: 46315 | K23: - | M23: -
A24: 21 | B24: 46316 | G24: - | K24: - | M24: -
A25: 22 | B25: 46317 | G25: - | K25: - | M25: -
A26: 23 | B26: 46318 | G26: - | K26: - | M26: -
A27: 24 | B27: 46319 | G27: - | K27: - | M27: -
A28: 25 | B28: 46320 | G28: - | K28: - | M28: -
A29: 26 | B29: 46321 | G29: - | K29: - | M29: -
A30: 27 | B30: 46322 | G30: - | K30: - | M30: -
A31: 28 | B31: 46323 | G31: - | K31: - | M31: -
A32: 29 | B32: 46324 | G32: - | K32: -
A33: 30 | B33: 46325 | G33: - | K33: - | M33: -
A34: 31 | B34: 46326 | G34: - | K34: - | M34: -
A35: 32 | B35: 46327 | G35: - | K35: - | M35: -
A36: 33 | B36: 46328 | G36: - | K36: - | M36: -
A37: 34 | G37: - | K37: - | M37: -
A38: 35 | K38: - | M38: -
A39: 36 | M39: -
A40: 37 | M40: -
A41: 38
A42: 39
A43: 40
A44: 41
A45: 42
A46: 43 | O46: 2669494 | P46: 2669494
E47: - | F47: - | G47: - | J47: - | K47: - | M47: -
E48: 150 | G48: 15564 | H48: - | J48: - | K48: 15564 | L48: 15564
M57: 2408309
M58: 5327.86
M59: 2402981.1

Sheet Khammam-1
A1: Divya laxmi ganapathi
A2: S.No | B2: Date | C2: GRN No | D2: Ind No/Bill No | E2: Diesel (Lts) | F2: Price | G2: Amount | H2: Petrol (Lts) | I2: Price | J2: Amount | K2: Total amount | L2: Amount paid | M2: As 0n Date | N2: Remarks
A3: Opening Balance | K3: 4131883.8 | M3: 4131883.8 | O3: =K3-M3 -> 0
A4: 1 | B4: 46296 | G4: =E4*F4 -> 0 | K4: =G4+J4 -> 0 | M4: =M3+K4-L4 -> 4131883.8
A5: 2 | B5: 46297 | G5: =E5*F5 -> 0 | K5: =G5+J5 -> 0 | M5: =M4+K5-L5 -> 4131883.8
A6: 3 | B6: 46298 | G6: =E6*F6 -> 0 | K6: =G6+J6 -> 0 | M6: =M5+K6-L6 -> 4131883.8
A7: 4 | B7: 46299 | G7: =E7*F7 -> 0 | K7: =G7+J7 -> 0 | M7: =M6+K7-L7 -> 4131883.8
A8: 5 | B8: 46300 | G8: =E8*F8 -> 0 | K8: =G8+J8 -> 0 | M8: =M7+K8-L8 -> 4131883.8
A9: 6 | B9: 46301 | G9: =E9*F9 -> 0 | K9: =G9+J9 -> 0 | M9: =M8+K9-L9 -> 4131883.8
A10: 7 | B10: 46302 | G10: =E10*F10 -> 0 | K10: =G10+J10 -> 0 | M10: =M9+K10-L10 -> 4131883.8
A11: 8 | B11: 46303 | G11: =E11*F11 -> 0 | K11: =G11+J11 -> 0 | M11: =M10+K11-L11 -> 4131883.8
A12: 9 | B12: 46304 | E12: 2300 | F12: 103.8 | G12: =E12*F12 -> 238740 | H12: 110 | I12: 115.69 | J12: =H12*I12 -> 12725.9 | K12: =G12+J12 -> 251465.9 | M12: =M11+K12-L12 -> 4383349.7
A13: 10 | B13: 46305 | G13: =E13*F13 -> 0 | J13: =H13*I13 -> 0 | K13: =G13+J13 -> 0 | M13: =M12+K13-L13 -> 4383349.7
A14: 11 | B14: 46306 | G14: =E14*F14 -> 0 | J14: =H14*I14 -> 0 | K14: =G14+J14 -> 0 | M14: =M13+K14-L14 -> 4383349.7
A15: 12 | B15: 46307 | G15: =E15*F15 -> 0 | H15: 110 | I15: 115.69 | J15: =H15*I15 -> 12725.9 | K15: =G15+J15 -> 12725.9 | M15: =M14+K15-L15 -> 4396075.6
A16: 13 | B16: 46308 | G16: =E16*F16 -> 0 | J16: =H16*I16 -> 0 | K16: =G16+J16 -> 0 | M16: =M15+K16-L16 -> 4396075.6
A17: 14 | B17: 46309 | G17: =E17*F17 -> 0 | J17: =H17*I17 -> 0 | K17: =G17+J17 -> 0 | M17: =M16+K17-L17 -> 4396075.6
A18: 15 | B18: 46310 | E18: 2700 | F18: 103.8 | G18: =E18*F18 -> 280260 | H18: 130 | I18: 115.69 | J18: =H18*I18 -> 15039.7 | K18: =G18+J18 -> 295299.7 | L18: 400000 | M18: =M17+K18-L18 -> 4291375.3 | N18: HPCL Card
A19: 16 | B19: 46311 | G19: =E19*F19 -> 0 | K19: =G19+J19 -> 0 | M19: =M18+K19-L19 -> 4291375.3
A20: 17 | B20: 46312 | G20: =E20*F20 -> 0 | K20: =G20+J20 -> 0 | M20: =M19+K20-L20 -> 4291375.3
A21: 18 | B21: 46313 | G21: =E21*F21 -> 0 | K21: =G21+J21 -> 0 | M21: =M20+K21-L21 -> 4291375.3
A22: 19 | B22: 46314 | G22: =E22*F22 -> 0 | K22: =G22+J22 -> 0 | M22: =M21+K22-L22 -> 4291375.3
A23: 20 | B23: 46315 | G23: =E23*F23 -> 0 | K23: =G23+J23 -> 0 | M23: =M22+K23-L23 -> 4291375.3
A24: 21 | B24: 46316 | G24: =E24*F24 -> 0 | K24: =G24+J24 -> 0 | M24: =M23+K24-L24 -> 4291375.3
A25: 22 | B25: 46317 | G25: =E25*F25 -> 0 | K25: =G25+J25 -> 0 | M25: =M24+K25-L25 -> 4291375.3
A26: 23 | B26: 46318 | G26: =E26*F26 -> 0 | K26: =G26+J26 -> 0 | M26: =M25+K26-L26 -> 4291375.3
A27: 24 | B27: 46319 | G27: =E27*F27 -> 0 | K27: =G27+J27 -> 0 | M27: =M26+K27-L27 -> 4291375.3
A28: 25 | B28: 46320 | G28: =E28*F28 -> 0 | K28: =G28+J28 -> 0 | M28: =M27+K28-L28 -> 4291375.3
A29: 26 | B29: 46321 | G29: =E29*F29 -> 0 | K29: =G29+J29 -> 0 | M29: =M28+K29-L29 -> 4291375.3
A30: 27 | B30: 46322 | G30: =E30*F30 -> 0 | K30: =G30+J30 -> 0 | M30: =M29+K30-L30 -> 4291375.3
... A34: 31 | B34: 46326 | G34: =E34*F34 -> 0 | K34: =G34+J34 -> 0 | M34: =M33+K34-L34 -> 4291375.3
A35: 32 | G35: =E35*F35 -> 0 | K35: =G35+J35 -> 0 | M35: =M34+K35-L35 -> 4291375.3
A36: 33 | G36: =E36*F36 -> 0 | J36: =H36*I36 -> 0 | K36: =G36+J36 -> 0
A37: 34 | G37: =E37*F37 -> 0 | J37: =H37*I37 -> 0 | K37: =G37+J37 -> 0
E38: =SUM(E3:E37) -> 5000 | G38: =SUM(G3:G37) -> 519000 | H38: =SUM(H3:H37) -> 350 | J38: =SUM(J3:J37) -> 40491.5 | K38: =SUM(K4:K37) -> 559491.5 | L38: =SUM(L3:L37) -> 400000

Sheet Khammam-2
A1: Jayasai union bunk
A2: S.No | B2: Date | C2: GRN No | D2: Ind No/Bill No | E2: Diesel (Lts) | F2: Price | G2: Amount | H2: Petrol (Lts) | I2: Price | J2: Amount | K2: Total amount | L2: Amount paid | M2: As 0n Date | N2: Remarks
A3: Opening Balance | K3: 4248603.6 | M3: 4248603.6
A4: 1 | B4: 46296 | E4: 1000 | F4: 103.82 | G4: =E4*F4 -> 103820 | J4: =H4*I4 -> 0 | K4: =G4+J4 -> 103820 | M4: =M3+K4-L4 -> 4352423.6
A5: 2 | B5: 46297 | E5: =1000+700 -> 1700 | F5: 103.82 | G5: =E5*F5 -> 176494 | J5: =H5*I5 -> 0 | K5: =G5+J5 -> 176494 | M5: =M4+K5-L5 -> 4528917.6
A6: 3 | B6: 46298 | E6: =2700+2500 -> 5200 | F6: 103.82 | G6: =E6*F6 -> 539864 | J6: =H6*I6 -> 0 | K6: =G6+J6 -> 539864 | M6: =M5+K6-L6 -> 5068781.6
A7: 4 | B7: 46299 | E7: 2700 | F7: 103.82 | G7: =E7*F7 -> 280314 | J7: =H7*I7 -> 0 | K7: =G7+J7 -> 280314 | M7: =M6+K7-L7 -> 5349095.6
A8: 5 | B8: 46300 | G8: =E8*F8 -> 0 | J8: =H8*I8 -> 0 | K8: =G8+J8 -> 0 | M8: =M7+K8-L8 -> 5349095.6
A9: 6 | B9: 46301 | E9: 2700 | F9: 103.82 | G9: =E9*F9 -> 280314 | H9: 90 | I9: 115.72 | J9: =H9*I9 -> 10414.8 | K9: =G9+J9 -> 290728.8 | M9: =M8+K9-L9 -> 5639824.4
A10: 7 | B10: 46302 | E10: 2700 | F10: 103.82 | G10: =E10*F10 -> 280314 | H10: 40 | I10: 115.72 | J10: =H10*I10 -> 4628.8 | K10: =G10+J10 -> 284942.8 | M10: =M9+K10-L10 -> 5924767.2
A11: 8 | B11: 46303 | G11: =E11*F11 -> 0 | J11: =H11*I11 -> 0 | K11: =G11+J11 -> 0 | M11: =M10+K11-L11 -> 5924767.2
A12: 9 | B12: 46304 | G12: =E12*F12 -> 0 | J12: =H12*I12 -> 0 | K12: =G12+J12 -> 0 | M12: =M11+K12-L12 -> 5924767.2
A13: 10 | B13: 46305 | E13: 5300 | F13: 103.82 | G13: =E13*F13 -> 550246 | J13: =H13*I13 -> 0 | K13: =G13+J13 -> 550246 | M13: =M12+K13-L13 -> 6475013.2 | V13: 250000
A14: 11 | B14: 46306 | G14: =E14*F14 -> 0 | J14: =H14*I14 -> 0 | K14: =G14+J14 -> 0 | M14: =M13+K14-L14 -> 6475013.2 | V14: 70000
A15: 12 | B15: 46307 | G15: =E15*F15 -> 0 | J15: =H15*I15 -> 0 | K15: =G15+J15 -> 0 | M15: =M14+K15-L15 -> 6475013.2 | V15: 46366
A16: 13 | B16: 46308 | E16: 2800 | F16: 103.82 | G16: =E16*F16 -> 290696 | J16: =H16*I16 -> 0 | K16: =G16+J16 -> 290696 | M16: =M15+K16-L16 -> 6765709.2
A17: 14 | B17: 46309 | E17: 2600 | F17: 103.82 | G17: =E17*F17 -> 269932 | J17: =H17*I17 -> 0 | K17: =G17+J17 -> 269932 | M17: =M16+K17-L17 -> 7035641.2
A18: 15 | B18: 46310 | E18: 2900 | F18: 103.82 | G18: =E18*F18 -> 301078 | J18: =H18*I18 -> 0 | K18: =G18+J18 -> 301078 | L18: 2000000 | M18: =M17+K18-L18 -> 5336719.2
A19: 16 | B19: 46311 | G19: =E19*F19 -> 0 | J19: =H19*I19 -> 0 | K19: =G19+J19 -> 0 | M19: =M18+K19-L19 -> 5336719.2
A20: 17 | B20: 46312 | G20: =E20*F20 -> 0 | J20: =H20*I20 -> 0 | K20: =G20+J20 -> 0 | M20: =M19+K20-L20 -> 5336719.2
A21: 18 | B21: 46313 | G21: =E21*F21 -> 0 | J21: =H21*I21 -> 0 | K21: =G21+J21 -> 0 | M21: =M20+K21-L21 -> 5336719.2
A22: 19 | B22: 46314 | G22: =E22*F22 -> 0 | J22: =H22*I22 -> 0 | K22: =G22+J22 -> 0 | M22: =M21+K22-L22 -> 5336719.2
A23: 20 | B23: 46315 | G23: =E23*F23 -> 0 | J23: =H23*I23 -> 0 | K23: =G23+J23 -> 0 | M23: =M22+K23-L23 -> 5336719.2
A24: 21 | B24: 46316 | G24: =E24*F24 -> 0 | J24: =H24*I24 -> 0 | K24: =G24+J24 -> 0 | M24: =M23+K24-L24 -> 5336719.2
B25: 46317 | G25: =E25*F25 -> 0 | K25: =G25+J25 -> 0 | M25: =M24+K25-L25 -> 5336719.2
A26: 22 | B26: 46318 | G26: =E26*F26 -> 0 | J26: =H26*I26 -> 0 | K26: =G26+J26 -> 0 | M26: =M25+K26-L26 -> 5336719.2
A27: 23 | B27: 46319 | G27: =E27*F27 -> 0 | J27: =H27*I27 -> 0 | K27: =G27+J27 -> 0 | M27: =M26+K27-L27 -> 5336719.2
A28: 24 | B28: 46320 | G28: =E28*F28 -> 0 | J28: =H28*I28 -> 0 | K28: =G28+J28 -> 0 | M28: =M27+K28-L28 -> 5336719.2
A29: 25 | B29: 46321 | G29: =E29*F29 -> 0 | J29: =H29*I29 -> 0 | K29: =G29+J29 -> 0 | M29: =M28+K29-L29 -> 5336719.2
A30: 26 | B30: 46322 | G30: =E30*F30 -> 0 | J30: =H30*I30 -> 0 | K30: =G30+J30 -> 0 | M30: =M29+K30-L30 -> 5336719.2
A31: 27 | B31: 46323 | G31: =E31*F31 -> 0 | J31: =H31*I31 -> 0 | K31: =G31+J31 -> 0 | M31: =M30+K31-L31 -> 5336719.2
A32: 28 | B32: 46324 | G32: =E32*F32 -> 0 | J32: =H32*I32 -> 0 | K32: =G32+J32 -> 0 | M32: =M31+K32-L32 -> 5336719.2
A33: 29 | B33: 46325 | G33: =E33*F33 -> 0 | J33: =H33*I33 -> 0 | K33: =G33+J33 -> 0 | M33: =M32+K33-L33 -> 5336719.2
A34: 30 | B34: 46326 | G34: =E34*F34 -> 0 | J34: =H34*I34 -> 0 | K34: =G34+J34 -> 0 | M34: =M33+K34-L34 -> 5336719.2
A35: 31 | B35: 46327 | G35: =E35*F35 -> 0 | J35: =H35*I35 -> 0 | K35: =G35+J35 -> 0 | M35: =M34+K35-L35 -> 5336719.2
A36: 32 | G36: =E36*F36 -> 0 | J36: =H36*I36 -> 0 | K36: =G36+J36 -> 0 | M36: =M35+K36-L36 -> 5336719.2
A37: 33 | G37: =E37*F37 -> 0 | J37: =H37*I37 -> 0 | K37: =G37+J37 -> 0 | M37: =M36+K37-L37 -> 5336719.2
E39: =SUM(E4:E37) -> 29600 | G39: =SUM(G4:G37) -> 3073072 | H39: =SUM(H4:H37) -> 130 | J39: =SUM(J4:J37) -> 15043.6 | K39: =SUM(K4:K37) -> 3088115.6 | L39: =SUM(L4:L37) -> 2000000

Sheet Khammam-4
A1: Sai Madeana Filling Station
A2: S.No | B2: Date | C2: GRN No | D2: Ind No/Bill No | E2: Diesel (Lts) | F2: Price | G2: Amount | H2: Petrol (Lts) | I2: Price | J2: Amount | K2: Total amount | L2: Amount paid | M2: As 0n Date | N2: Remarks
A3: Opening Balance | K3: 3141611.1 | M3: 3141611.1
A4: 1 | B4: 46296 | G4: =E4*F4 -> 0 | J4: =H4*I4 -> 0 | K4: =G4+J4 -> 0 | M4: =M3+K4-L4 -> 3141611.1
A5: 2 | B5: 46297 | E5: 2700 | F5: 103.62 | G5: =E5*F5 -> 279774 | H5: 75 | I5: 115.49 | J5: =H5*I5 -> 8661.75 | K5: =G5+J5 -> 288435.75 | L5: 288435.75 | M5: =M4+K5-L5 -> 3141611.1
A6: 3 | B6: 46298 | G6: =E6*F6 -> 0 | J6: =H6*I6 -> 0 | K6: =G6+J6 -> 0 | M6: =M5+K6-L6 -> 3141611.1
A7: 4 | B7: 46299 | G7: =E7*F7 -> 0 | J7: =H7*I7 -> 0 | K7: =G7+J7 -> 0 | M7: =M6+K7-L7 -> 3141611.1
A8: 5 | B8: 46300 | G8: =E8*F8 -> 0 | J8: =H8*I8 -> 0 | K8: =G8+J8 -> 0 | M8: =M7+K8-L8 -> 3141611.1
A9: 6 | B9: 46301 | G9: =E9*F9 -> 0 | J9: =H9*I9 -> 0 | K9: =G9+J9 -> 0 | M9: =M8+K9-L9 -> 3141611.1
A10: 7 | B10: 46302 | G10: =E10*F10 -> 0 | J10: =H10*I10 -> 0 | K10: =G10+J10 -> 0 | M10: =M9+K10-L10 -> 3141611.1
A11: 8 | B11: 46303 | G11: =E11*F11 -> 0 | J11: =H11*I11 -> 0 | K11: =G11+J11 -> 0 | M11: =M10+K11-L11 -> 3141611.1
A12: 9 | B12: 46304 | G12: =E12*F12 -> 0 | J12: =H12*I12 -> 0 | K12: =G12+J12 -> 0 | M12: =M11+K12-L12 -> 3141611.1
A13: 10 | B13: 46305 | G13: =E13*F13 -> 0 | J13: =H13*I13 -> 0 | K13: =G13+J13 -> 0 | M13: =M12+K13-L13 -> 3141611.1
A14: 11 | B14: 46306 | G14: =E14*F14 -> 0 | J14: =H14*I14 -> 0 | K14: =G14+J14 -> 0 | M14: =M13+K14-L14 -> 3141611.1
A15: 12 | B15: 46307 | G15: =E15*F15 -> 0 | J15: =H15*I15 -> 0 | K15: =G15+J15 -> 0 | M15: =M14+K15-L15 -> 3141611.1
A16: 13 | B16: 46308 | G16: =E16*F16 -> 0 | J16: =H16*I16 -> 0 | K16: =G16+J16 -> 0 | M16: =M15+K16-L16 -> 3141611.1
A17: 14 | B17: 46309 | G17: =E17*F17 -> 0 | J17: =H17*I17 -> 0 | K17: =G17+J17 -> 0 | M17: =M16+K17-L17 -> 3141611.1
... A34: 31 | B34: 46326 | G34: =E34*F34 -> 0 | J34: =H34*I34 -> 0 | K34: =G34+J34 -> 0 | M34: =M33+K34-L34 -> 3141611.1
E35: =SUM(E4:E34) -> 2700 | G35: =SUM(G4:G34) -> 279774 | H35: =SUM(H4:H34) -> 75 | J35: =SUM(J4:J34) -> 8661.75 | K35: =SUM(K4:K34) -> 288435.75 | L35: =SUM(L4:L34) -> 288435.75

Sheet  Khammam-5
A1: Vajra mahalakshmi filling station
A2: S.No | B2: Date | C2: GRN No | D2: Ind No/Bill No | E2: Diesel (Lts) | F2: Price | G2: Amount | H2: Petrol (Lts) | I2: Price | J2: Amount | K2: Total amount | L2: Amount paid | M2: As 0n Date | N2: Remarks
A3: Opening Balance | K3: 1445001.9 | M3: 1445001.9
A4: 1 | B4: 46296 | G4: =E4*F4 -> 0 | J4: =H4*I4 -> 0 | K4: =G4+J4 -> 0 | M4: =M3+K4-L4 -> 1445001.9
A5: 2 | B5: 46297 | G5: =E5*F5 -> 0 | J5: =H5*I5 -> 0 | K5: =G5+J5 -> 0 | M5: =M4+K5-L5 -> 1445001.9
A6: 3 | B6: 46298 | G6: =E6*F6 -> 0 | J6: =H6*I6 -> 0 | K6: =G6+J6 -> 0 | M6: =M5+K6-L6 -> 1445001.9
A7: 4 | B7: 46299 | G7: =E7*F7 -> 0 | J7: =H7*I7 -> 0 | K7: =G7+J7 -> 0 | M7: =M6+K7-L7 -> 1445001.9
A8: 5 | B8: 46300 | G8: =E8*F8 -> 0 | J8: =H8*I8 -> 0 | K8: =G8+J8 -> 0 | M8: =M7+K8-L8 -> 1445001.9
A9: 6 | B9: 46301 | G9: =E9*F9 -> 0 | J9: =H9*I9 -> 0 | K9: =G9+J9 -> 0 | M9: =M8+K9-L9 -> 1445001.9
A10: 7 | B10: 46302 | G10: =E10*F10 -> 0 | J10: =H10*I10 -> 0 | K10: =G10+J10 -> 0 | M10: =M9+K10-L10 -> 1445001.9
A11: 8 | B11: 46303 | G11: =E11*F11 -> 0 | J11: =H11*I11 -> 0 | K11: =G11+J11 -> 0 | M11: =M10+K11-L11 -> 1445001.9
A12: 9 | B12: 46304 | G12: =E12*F12 -> 0 | J12: =H12*I12 -> 0 | K12: =G12+J12 -> 0 | M12: =M11+K12-L12 -> 1445001.9
A13: 10 | B13: 46305 | G13: =E13*F13 -> 0 | J13: =H13*I13 -> 0 | K13: =G13+J13 -> 0 | M13: =M12+K13-L13 -> 1445001.9
A14: 11 | B14: 46306 | G14: =E14*F14 -> 0 | J14: =H14*I14 -> 0 | K14: =G14+J14 -> 0 | M14: =M13+K14-L14 -> 1445001.9
A15: 12 | B15: 46307 | G15: =E15*F15 -> 0 | J15: =H15*I15 -> 0 | K15: =G15+J15 -> 0 | M15: =M14+K15-L15 -> 1445001.9
... A34: 31 | B34: 46326 | G34: =E34*F34 -> 0 | J34: =H34*I34 -> 0 | K34: =G34+J34 -> 0 | M34: =M33+K34-L34 -> 1445001.9
E35: =SUM(E4:E34) -> 0 | G35: =SUM(G4:G34) -> 0 | H35: =SUM(H4:H34) -> 0 | J35: =SUM(J4:J34) -> 0 | K35: =SUM(K4:K34) -> 0 | L35: =SUM(L4:L34) -> 0

Sheet  Khammam-6
A1: Jai Sreeram
A2: S.No | B2: Date | C2: GRN No | D2: Ind No/Bill No | E2: Diesel (Lts) | F2: Price | G2: Amount | H2: Petrol (Lts) | I2: Price | J2: Amount | K2: Total amount | L2: Amount paid | M2: As 0n Date | N2: Remarks
A3: Opening Balance | K3: 0 | M3: 0
A4: 1 | B4: 46296 | G4: =E4*F4 -> 0 | J4: =H4*I4 -> 0 | K4: =G4+J4 -> 0 | M4: =M3+K4-L4 -> 0
A5: 2 | B5: 46297 | G5: =E5*F5 -> 0 | J5: =H5*I5 -> 0 | K5: =G5+J5 -> 0 | M5: =M4+K5-L5 -> 0
A6: 3 | B6: 46298 | E6: 5400 | F6: 103.84 | G6: =E6*F6 -> 560736 | J6: =H6*I6 -> 0 | K6: =G6+J6 -> 560736 | M6: =M5+K6-L6 -> 560736
A7: 4 | B7: 46299 | G7: =E7*F7 -> 0 | J7: =H7*I7 -> 0 | K7: =G7+J7 -> 0 | M7: =M6+K7-L7 -> 560736
A8: 5 | B8: 46300 | E8: 2700 | F8: 103.84 | G8: =E8*F8 -> 280368 | J8: =H8*I8 -> 0 | K8: =G8+J8 -> 280368 | M8: =M7+K8-L8 -> 841104
A9: 6 | B9: 46301 | E9: 2700 | F9: 103.84 | G9: =E9*F9 -> 280368 | J9: =H9*I9 -> 0 | K9: =G9+J9 -> 280368 | M9: =M8+K9-L9 -> 1121472
A10: 7 | B10: 46302 | E10: 2700 | F10: 103.84 | G10: =E10*F10 -> 280368 | J10: =H10*I10 -> 0 | K10: =G10+J10 -> 280368 | M10: =M9+K10-L10 -> 1401840
A11: 8 | B11: 46303 | E11: 2700 | F11: 103.84 | G11: =E11*F11 -> 280368 | J11: =H11*I11 -> 0 | K11: =G11+J11 -> 280368 | M11: =M10+K11-L11 -> 1682208
A12: 9 | B12: 46304 | E12: 5400 | F12: 103.84 | G12: =E12*F12 -> 560736 | J12: =H12*I12 -> 0 | K12: =G12+J12 -> 560736 | M12: =M11+K12-L12 -> 2242944
A13: 10 | B13: 46305 | E13: 5400 | F13: 103.84 | G13: =E13*F13 -> 560736 | J13: =H13*I13 -> 0 | K13: =G13+J13 -> 560736 | M13: =M12+K13-L13 -> 2803680
A14: 11 | B14: 46306 | E14: 2700 | F14: 103.84 | G14: =E14*F14 -> 280368 | J14: =H14*I14 -> 0 | K14: =G14+J14 -> 280368 | M14: =M13+K14-L14 -> 3084048
A15: 12 | B15: 46307 | E15: 2700 | F15: 103.84 | G15: =E15*F15 -> 280368 | J15: =H15*I15 -> 0 | K15: =G15+J15 -> 280368 | M15: =M14+K15-L15 -> 3364416
A16: 13 | B16: 46308 | E16: 2700 | F16: 103.84 | G16: =E16*F16 -> 280368 | J16: =H16*I16 -> 0 | K16: =G16+J16 -> 280368 | M16: =M15+K16-L16 -> 3644784
A17: 14 | B17: 46309 | E17: 2700 | F17: 103.84 | G17: =E17*F17 -> 280368 | J17: =H17*I17 -> 0 | K17: =G17+J17 -> 280368 | M17: =M16+K17-L17 -> 3925152
A18: 15 | B18: 46310 | E18: 2700 | F18: 103.84 | G18: =E18*F18 -> 280368 | J18: =H18*I18 -> 0 | K18: =G18+J18 -> 280368 | M18: =M17+K18-L18 -> 4205520
A19: 16 | B19: 46311 | G19: =E19*F19 -> 0 | J19: =H19*I19 -> 0 | K19: =G19+J19 -> 0 | M19: =M18+K19-L19 -> 4205520
A20: 17 | B20: 46312 | G20: =E20*F20 -> 0 | J20: =H20*I20 -> 0 | K20: =G20+J20 -> 0 | M20: =M19+K20-L20 -> 4205520
A21: 18 | B21: 46313 | G21: =E21*F21 -> 0 | J21: =H21*I21 -> 0 | K21: =G21+J21 -> 0 | M21: =M20+K21-L21 -> 4205520
A22: 19 | B22: 46314 | G22: =E22*F22 -> 0 | J22: =H22*I22 -> 0 | K22: =G22+J22 -> 0 | M22: =M21+K22-L22 -> 4205520
A23: 20 | B23: 46315 | G23: =E23*F23 -> 0 | J23: =H23*I23 -> 0 | K23: =G23+J23 -> 0 | M23: =M22+K23-L23 -> 4205520
A24: 21 | B24: 46316 | G24: =E24*F24 -> 0 | J24: =H24*I24 -> 0 | K24: =G24+J24 -> 0 | M24: =M23+K24-L24 -> 4205520
A25: 22 | B25: 46317 | G25: =E25*F25 -> 0 | J25: =H25*I25 -> 0 | K25: =G25+J25 -> 0 | M25: =M24+K25-L25 -> 4205520
A26: 23 | B26: 46318 | G26: =E26*F26 -> 0 | J26: =H26*I26 -> 0 | K26: =G26+J26 -> 0 | M26: =M25+K26-L26 -> 4205520
A27: 24 | B27: 46319 | G27: =E27*F27 -> 0 | J27: =H27*I27 -> 0 | K27: =G27+J27 -> 0 | M27: =M26+K27-L27 -> 4205520
A28: 25 | B28: 46320 | G28: =E28*F28 -> 0 | J28: =H28*I28 -> 0 | K28: =G28+J28 -> 0 | M28: =M27+K28-L28 -> 4205520
A29: 26 | B29: 46321 | G29: =E29*F29 -> 0 | J29: =H29*I29 -> 0 | K29: =G29+J29 -> 0 | M29: =M28+K29-L29 -> 4205520
A30: 27 | B30: 46322 | G30: =E30*F30 -> 0 | J30: =H30*I30 -> 0 | K30: =G30+J30 -> 0 | M30: =M29+K30-L30 -> 4205520
... A34: 31 | B34: 46326 | G34: =E34*F34 -> 0 | J34: =H34*I34 -> 0 | K34: =G34+J34 -> 0 | M34: =M33+K34-L34 -> 4205520
E35: =SUM(E4:E34) -> 40500 | G35: =SUM(G4:G34) -> 4205520 | H35: =SUM(H4:H34) -> 0 | J35: =SUM(J4:J34) -> 0 | K35: =SUM(K4:K34) -> 4205520 | L35: =SUM(L4:L34) -> 0

Sheet  Khammam&Cash
A1: Cash &Carry
A2: S.No | B2: Date | D2: Ind No/Bill No | E2: Diesel (Lts) | F2: Price | G2: Amount | H2: Petrol (Lts) | I2: Price | J2: Amount | K2: Total amount | L2: Amount paid | M2: As 0n Date | N2: Remarks
A3: Opening Balance | K3: 0 | M3: 0
A4: 1 | G4: =E4*F4 -> 0 | K4: =G4+J4 -> 0 | L4: =H4+K4 -> 0 | M4: =M3+K4-L4 -> 0
A5: 2 | G5: =E5*F5 -> 0 | J5: =H5*I5 -> 0 | K5: =G5+J5 -> 0 | L5: =H5+K5 -> 0 | M5: =M4+K5-L5 -> 0
A6: 3 | G6: =E6*F6 -> 0 | J6: =H6*I6 -> 0 | K6: =G6+J6 -> 0 | L6: =H6+K6 -> 0 | M6: =M5+K6-L6 -> 0
A7: 4 | G7: =E7*F7 -> 0 | J7: =H7*I7 -> 0 | K7: =G7+J7 -> 0 | L7: =H7+K7 -> 0 | M7: =M6+K7-L7 -> 0
A8: 5 | G8: =E8*F8 -> 0 | J8: =H8*I8 -> 0 | K8: =G8+J8 -> 0 | L8: =H8+K8 -> 0 | M8: =M7+K8-L8 -> 0
A9: 6 | G9: =E9*F9 -> 0 | J9: =H9*I9 -> 0 | K9: =G9+J9 -> 0 | L9: =H9+K9 -> 0 | M9: =M8+K9-L9 -> 0
A10: 7 | G10: =E10*F10 -> 0 | J10: =H10*I10 -> 0 | K10: =G10+J10 -> 0 | L10: =H10+K10 -> 0 | M10: =M9+K10-L10 -> 0
A11: 8 | G11: =E11*F11 -> 0 | J11: =H11*I11 -> 0 | K11: =G11+J11 -> 0 | L11: =H11+K11 -> 0 | M11: =M10+K11-L11 -> 0
A12: 9 | G12: =E12*F12 -> 0 | J12: =H12*I12 -> 0 | K12: =G12+J12 -> 0 | L12: =H12+K12 -> 0 | M12: =M11+K12-L12 -> 0
A13: 10 | G13: =E13*F13 -> 0 | J13: =H13*I13 -> 0 | K13: =G13+J13 -> 0 | L13: =H13+K13 -> 0 | M13: =M12+K13-L13 -> 0
A14: 11 | G14: =E14*F14 -> 0 | J14: =H14*I14 -> 0 | K14: =G14+J14 -> 0 | L14: =H14+K14 -> 0 | M14: =M13+K14-L14 -> 0
A15: 12 | G15: =E15*F15 -> 0 | J15: =H15*I15 -> 0 | K15: =G15+J15 -> 0 | L15: =H15+K15 -> 0 | M15: =M14+K15-L15 -> 0
A16: 13 | G16: =E16*F16 -> 0 | J16: =H16*I16 -> 0 | K16: =G16+J16 -> 0 | L16: =H16+K16 -> 0 | M16: =M15+K16-L16 -> 0
... A22: 19 | G22: =E22*F22 -> 0 | J22: =H22*I22 -> 0 | K22: =G22+J22 -> 0 | L22: =H22+K22 -> 0 | M22: =M21+K22-L22 -> 0
A23: 20 | G23: =E23*F23 -> 0 | J23: =H23*I23 -> 0 | K23: =G23+J23 -> 0 | L23: 0 | M23: =M22+K23-L23 -> 0
A24: 21 | G24: =E24*F24 -> 0 | J24: =H24*I24 -> 0 | K24: =G24+J24 -> 0 | L24: =H24+K24 -> 0 | M24: =M23+K24-L24 -> 0
A25: 22 | G25: =E25*F25 -> 0 | J25: =H25*I25 -> 0 | K25: =G25+J25 -> 0 | L25: =H25+K25 -> 0 | M25: =M24+K25-L25 -> 0
A26: 23 | G26: =E26*F26 -> 0 | J26: =H26*I26 -> 0 | K26: =G26+J26 -> 0 | L26: =H26+K26 -> 0 | M26: =M25+K26-L26 -> 0
A27: 24 | G27: =E27*F27 -> 0 | K27: =G27+J27 -> 0 | L27: =H27+K27 -> 0 | M27: =M26+K27-L27 -> 0
A28: 25 | G28: =E28*F28 -> 0 | J28: =H28*I28 -> 0 | K28: =G28+J28 -> 0 | L28: =H28+K28 -> 0 | M28: =M26+K28-L28 -> 0
A29: 26 | G29: =E29*F29 -> 0 | J29: =H29*I29 -> 0 | K29: =G29+J29 -> 0 | L29: =H29+K29 -> 0 | M29: =M28+K29-L29 -> 0
A30: 27 | G30: =E30*F30 -> 0 | J30: =H30*I30 -> 0 | K30: =G30+J30 -> 0 | L30: =H30+K30 -> 0 | M30: =M29+K30-L30 -> 0
A31: 28 | G31: =E31*F31 -> 0 | J31: =H31*I31 -> 0 | K31: =G31+J31 -> 0 | L31: =H31+K31 -> 0 | M31: =M30+K31-L31 -> 0
A32: 29 | G32: =E32*F32 -> 0 | J32: =H32*I32 -> 0 | K32: =G32+J32 -> 0 | L32: =H32+K32 -> 0 | M32: =M31+K32-L32 -> 0
A33: 30 | G33: =E33*F33 -> 0 | J33: =H33*I33 -> 0 | K33: =G33+J33 -> 0 | L33: =H33+K33 -> 0 | M33: =M32+K33-L33 -> 0
A34: 31 | G34: =E34*F34 -> 0 | J34: =H34*I34 -> 0 | K34: =G34+J34 -> 0 | L34: =H34+K34 -> 0 | M34: =M33+K34-L34 -> 0
A35: 32 | G35: =E35*F35 -> 0 | K35: =G35+J35 -> 0 | L35: =H35+K35 -> 0 | M35: =M34+K35-L35 -> 0
A36: 33 | G36: =E36*F36 -> 0 | J36: =H36*I36 -> 0 | K36: =G36+J36 -> 0 | L36: =H36+K36 -> 0 | M36: =M35+K36-L36 -> 0
A37: 34 | G37: =E37*F37 -> 0 | J37: =H37*I37 -> 0 | K37: =G37+J37 -> 0 | L37: =H37+K37 -> 0 | M37: =M36+K37-L37 -> 0
G38: =E38*F38 -> 0 | K38: =G38+J38 -> 0 | L38: =H38+K38 -> 0 | M38: =M37+K38-L38 -> 0
G39: =E39*F39 -> 0 | K39: =G39+J39 -> 0 | L39: =H39+K39 -> 0 | M39: =M38+K39-L39 -> 0
G40: =E40*F40 -> 0 | K40: =G40+J40 -> 0 | L40: =H40+K40 -> 0 | M40: =M39+K40-L40 -> 0
M41: =M40+K41-L41 -> 0
A45: 35 | G45: =E45*F45 -> 0 | J45: =H45*I45 -> 0 | K45: =G45+J45 -> 0
E46: =SUM(E3:E45) -> 0 | G46: =SUM(G3:G45) -> 0 | H46: =SUM(H3:H45) -> 0 | J46: =SUM(J3:J45) -> 0 | K46: =SUM(K4:K45) -> 0 | L46: =SUM(L3:L45) -> 0

Sheet Jadcherla-4
A1: Shree Poornima F/S
A2: S.No | B2: Date | C2: GRN No | D2: Ind No/Bill No | E2: Diesel (Lts) | F2: Price | G2: Amount | H2: Petrol (Lts) | I2: Price | J2: Amount | K2: Total amount | L2: Amount paid | M2: As on date | N2: Remarks
A3: Opening Balance | K3: 47858.18 | M3: 47858.18
A4: 1 | B4: 46296 | G4: =E4*F4 -> 0 | J4: =H4*I4 -> 0 | K4: =G4+J4 -> 0 | L4: 0 | M4: =M3+K4-L4 -> 47858.18
A5: 2 | B5: 46297 | G5: =E5*F5 -> 0 | J5: =H5*I5 -> 0 | K5: =G5+J5 -> 0 | L5: 0 | M5: =M4+K5-L5 -> 47858.18
A6: 3 | B6: 46298 | G6: =E6*F6 -> 0 | J6: =H6*I6 -> 0 | K6: =G6+J6 -> 0 | L6: 0 | M6: =M5+K6-L6 -> 47858.18
A7: 4 | B7: 46299 | G7: =E7*F7 -> 0 | J7: =H7*I7 -> 0 | K7: =G7+J7 -> 0 | L7: 0 | M7: =M6+K7-L7 -> 47858.18
A8: 5 | B8: 46300 | G8: =E8*F8 -> 0 | J8: =H8*I8 -> 0 | K8: =G8+J8 -> 0 | L8: 0 | M8: =M7+K8-L8 -> 47858.18
A9: 6 | B9: 46301 | G9: =E9*F9 -> 0 | J9: =H9*I9 -> 0 | K9: =G9+J9 -> 0 | L9: 0 | M9: =M8+K9-L9 -> 47858.18
A10: 7 | B10: 46302 | G10: =E10*F10 -> 0 | J10: =H10*I10 -> 0 | K10: =G10+J10 -> 0 | L10: 0 | M10: =M9+K10-L10 -> 47858.18
A11: 8 | B11: 46303 | G11: =E11*F11 -> 0 | J11: =H11*I11 -> 0 | K11: =G11+J11 -> 0 | L11: 0 | M11: =M10+K11-L11 -> 47858.18
A12: 9 | B12: 46304 | E12: 100 | F12: 104.42 | G12: =E12*F12 -> 10442 | J12: =H12*I12 -> 0 | K12: =G12+J12 -> 10442 | L12: 0 | M12: =M11+K12-L12 -> 58300.18
A13: 10 | B13: 46305 | G13: =E13*F13 -> 0 | J13: =H13*I13 -> 0 | K13: =G13+J13 -> 0 | L13: 0 | M13: =M12+K13-L13 -> 58300.18
A14: 11 | B14: 46306 | G14: =E14*F14 -> 0 | J14: =H14*I14 -> 0 | K14: =G14+J14 -> 0 | L14: 0 | M14: =M13+K14-L14 -> 58300.18
A15: 12 | B15: 46307 | G15: =E15*F15 -> 0 | J15: =H15*I15 -> 0 | K15: =G15+J15 -> 0 | L15: 0 | M15: =M14+K15-L15 -> 58300.18
A16: 13 | B16: 46308 | G16: =E16*F16 -> 0 | J16: =H16*I16 -> 0 | K16: =G16+J16 -> 0 | L16: 0 | M16: =M15+K16-L16 -> 58300.18
A17: 14 | B17: 46309 | G17: =E17*F17 -> 0 | J17: =H17*I17 -> 0 | K17: =G17+J17 -> 0 | L17: 0 | M17: =M16+K17-L17 -> 58300.18
A18: 15 | B18: 46310 | G18: =E18*F18 -> 0 | J18: =H18*I18 -> 0 | K18: =G18+J18 -> 0 | L18: 50000 | M18: =M17+K18-L18 -> 8300.18
A19: 16 | B19: 46311 | G19: 0 | J19: 0 | K19: 0 | L19: 0 | M19: =M18+K19-L19 -> 8300.18
A20: 17 | B20: 46312 | G20: =E20*F20 -> 0 | J20: =H20*I20 -> 0 | K20: =G20+J20 -> 0 | L20: 0 | M20: =M19+K20-L20 -> 8300.18
A21: 18 | B21: 46313 | G21: =E21*F21 -> 0 | J21: =H21*I21 -> 0 | K21: =G21+J21 -> 0 | L21: 0 | M21: =M20+K21-L21 -> 8300.18
A22: 19 | B22: 46314 | G22: =E22*F22 -> 0 | J22: =H22*I22 -> 0 | K22: =G22+J22 -> 0 | L22: 0 | M22: =M21+K22-L22 -> 8300.18
A23: 20 | B23: 46315 | G23: =E23*F23 -> 0 | J23: =H23*I23 -> 0 | K23: =G23+J23 -> 0 | L23: 0 | M23: =M22+K23-L23 -> 8300.18
A24: 21 | B24: 46316 | G24: =E24*F24 -> 0 | J24: =H24*I24 -> 0 | K24: =G24+J24 -> 0 | L24: 0 | M24: =M23+K24-L24 -> 8300.18
A25: 22 | B25: 46317 | G25: =E25*F25 -> 0 | J25: =H25*I25 -> 0 | K25: =G25+J25 -> 0 | L25: 0 | M25: =M24+K25-L25 -> 8300.18
A26: 23 | B26: 46318 | G26: =E26*F26 -> 0 | J26: =H26*I26 -> 0 | K26: =G26+J26 -> 0 | L26: 0 | M26: =M25+K26-L26 -> 8300.18
A27: 24 | B27: 46319 | G27: =E27*F27 -> 0 | J27: =H27*I27 -> 0 | K27: =G27+J27 -> 0 | L27: 0 | M27: =M26+K27-L27 -> 8300.18
A28: 25 | B28: 46320 | G28: =E28*F28 -> 0 | J28: =H28*I28 -> 0 | K28: =G28+J28 -> 0 | L28: 0 | M28: =M27+K28-L28 -> 8300.18
A29: 26 | B29: 46321 | G29: =E29*F29 -> 0 | J29: =H29*I29 -> 0 | K29: =G29+J29 -> 0 | L29: 0 | M29: =M28+K29-L29 -> 8300.18
A30: 27 | B30: 46322 | G30: =E30*F30 -> 0 | J30: =H30*I30 -> 0 | K30: =G30+J30 -> 0 | L30: 0 | M30: =M29+K30-L30 -> 8300.18
A31: 28 | B31: 46323 | G31: =E31*F31 -> 0 | J31: =H31*I31 -> 0 | K31: =G31+J31 -> 0 | L31: 0 | M31: =M30+K31-L31 -> 8300.18
... A33: 30 | B33: 46325 | G33: =E33*F33 -> 0 | J33: =H33*I33 -> 0 | K33: =G33+J33 -> 0 | L33: 0 | M33: =M32+K33-L33 -> 8300.18
A34: 31 | B34: 46326 | G34: =E34*F34 -> 0 | J34: =H34*I34 -> 0 | K34: =G34+J34 -> 0 | M34: =M33+K34-L34 -> 8300.18
E35: =SUM(E4:E34) -> 100 | G35: =SUM(G4:G34) -> 10442 | H35: =SUM(H4:H34) -> 0 | J35: =SUM(J4:J34) -> 0 | K35: =SUM(K4:K34) -> 10442 | L35: =SUM(L4:L34) -> 50000

Sheet  Sangareddy-2
A1: Durga Bhavani F/S
A2: S.No | B2: Date | C2: GRN No | D2: Ind no/Bill No | E2: Diesel (Lts) | F2: Price | G2: Amount | H2: Petrol (Lts) | I2: Price | J2: Amount | K2: Total amount | L2: Amount paid | M2: As on Date | N2: Remarks
A3: Opening Balance | M3: 0
A4: 1 | B4: 46266 | G4: =E4*F4 -> 0 | J4: =H4*I4 -> 0 | K4: =G4+J4 -> 0 | M4: =M3+K4-L4 -> 0
A5: 2 | B5: 46267 | G5: =E5*F5 -> 0 | J5: =H5*I5 -> 0 | K5: =G5+J5 -> 0 | M5: =M4+K5-L5 -> 0
A6: 3 | B6: 46268 | G6: =E6*F6 -> 0 | J6: =H6*I6 -> 0 | K6: =G6+J6 -> 0 | M6: =M5+K6-L6 -> 0
A7: 4 | B7: 46269 | G7: =E7*F7 -> 0 | J7: =H7*I7 -> 0 | K7: =G7+J7 -> 0 | M7: =M6+K7-L7 -> 0
A8: 5 | B8: 46270 | G8: =E8*F8 -> 0 | J8: =H8*I8 -> 0 | K8: =G8+J8 -> 0 | M8: =M7+K8-L8 -> 0
A9: 6 | B9: 46271 | G9: =E9*F9 -> 0 | J9: =H9*I9 -> 0 | K9: =G9+J9 -> 0 | M9: =M8+K9-L9 -> 0
A10: 7 | B10: 46272 | G10: =E10*F10 -> 0 | J10: =H10*I10 -> 0 | K10: =G10+J10 -> 0 | M10: =M9+K10-L10 -> 0
A11: 8 | B11: 46273 | G11: =E11*F11 -> 0 | J11: =H11*I11 -> 0 | K11: =G11+J11 -> 0 | M11: =M10+K11-L11 -> 0
A12: 9 | B12: 46274 | G12: =E12*F12 -> 0 | J12: =H12*I12 -> 0 | K12: =G12+J12 -> 0 | M12: =M11+K12-L12 -> 0
A13: 10 | B13: 46275 | G13: =E13*F13 -> 0 | J13: =H13*I13 -> 0 | K13: =G13+J13 -> 0 | M13: =M12+K13-L13 -> 0
A14: 11 | B14: 46276 | G14: =E14*F14 -> 0 | J14: =H14*I14 -> 0 | K14: =G14+J14 -> 0 | M14: =M13+K14-L14 -> 0
A15: 12 | B15: 46277 | G15: =E15*F15 -> 0 | J15: =H15*I15 -> 0 | K15: =G15+J15 -> 0 | M15: =M14+K15-L15 -> 0
... A32: 29 | B32: 46294 | G32: =E32*F32 -> 0 | J32: =H32*I32 -> 0 | K32: =G32+J32 -> 0 | M32: =M31+K32-L32 -> 0
A33: 30 | B33: 46295 | G33: =E33*F33 -> 0 | J33: =H33*I33 -> 0 | K33: =G33+J33 -> 0 | L33: 0 | M33: =M32+K33-L33 -> 0
A34: 31 | G34: =E34*F34 -> 0 | J34: =H34*I34 -> 0 | K34: =G34+J34 -> 0 | L34: 0 | M34: =M33+K34-L34 -> 0
E35: =SUM(E4:E34) -> 0 | G35: =SUM(G4:G34) -> 0 | H35: =SUM(H4:H34) -> 0 | J35: =SUM(J4:J34) -> 0 | K35: =SUM(K4:K34) -> 0 | L35: =SUM(L4:L34) -> 0

Sheet  Sangareddy-3
A1: SHIVA PARVATHI FILLING STATION SADASHIVPET
A2: S.No | B2: Date | C2: GRN No | D2: Ind no/Bill No | E2: Diesel (Lts) | F2: Price | G2: Amount | H2: Petrol (Lts) | I2: Price | J2: Amount | K2: Total amount | L2: Amount paid | M2: As on Date | N2: Remarks
A3: Opening Balance | M3: 366809.49
A4: 1 | B4: 46296 | E4: 690 | F4: 104.35 | G4: =E4*F4 -> 72001.5 | J4: =H4*I4 -> 0 | K4: =G4+J4 -> 72001.5 | M4: =M3+K4-L4 -> 438810.99
A5: 2 | B5: 46297 | G5: =E5*F5 -> 0 | J5: =H5*I5 -> 0 | K5: =G5+J5 -> 0 | M5: =M4+K5-L5 -> 438810.99
A6: 3 | B6: 46298 | E6: 690 | F6: 104.35 | G6: =E6*F6 -> 72001.5 | J6: =H6*I6 -> 0 | K6: =G6+J6 -> 72001.5 | M6: =M5+K6-L6 -> 510812.49
A7: 4 | B7: 46299 | G7: =E7*F7 -> 0 | J7: =H7*I7 -> 0 | K7: =G7+J7 -> 0 | M7: =M6+K7-L7 -> 510812.49
A8: 5 | B8: 46300 | E8: 690 | F8: 104.35 | G8: =E8*F8 -> 72001.5 | H8: 20 | I8: 116.25 | J8: =H8*I8 -> 2325 | K8: =G8+J8 -> 74326.5 | M8: =M7+K8-L8 -> 585138.99
A9: 6 | B9: 46301 | G9: =E9*F9 -> 0 | J9: =H9*I9 -> 0 | K9: =G9+J9 -> 0 | M9: =M8+K9-L9 -> 585138.99
A10: 7 | B10: 46302 | E10: 690 | F10: 104.35 | G10: =E10*F10 -> 72001.5 | J10: =H10*I10 -> 0 | K10: =G10+J10 -> 72001.5 | M10: =M9+K10-L10 -> 657140.49
A11: 8 | B11: 46303 | G11: =E11*F11 -> 0 | J11: =H11*I11 -> 0 | K11: =G11+J11 -> 0 | M11: =M10+K11-L11 -> 657140.49
A12: 9 | B12: 46304 | E12: 690 | F12: 104.35 | G12: =E12*F12 -> 72001.5 | J12: =H12*I12 -> 0 | K12: =G12+J12 -> 72001.5 | M12: =M11+K12-L12 -> 729141.99
A13: 10 | B13: 46305 | E13: 690 | F13: 104.35 | G13: =E13*F13 -> 72001.5 | J13: =H13*I13 -> 0 | K13: =G13+J13 -> 72001.5 | M13: =M12+K13-L13 -> 801143.49
A14: 11 | B14: 46306 | G14: =E14*F14 -> 0 | J14: =H14*I14 -> 0 | K14: =G14+J14 -> 0 | M14: =M13+K14-L14 -> 801143.49
A15: 12 | B15: 46307 | G15: =E15*F15 -> 0 | K15: =G15+J15 -> 0 | M15: =M14+K15-L15 -> 801143.49
A16: 13 | B16: 46308 | E16: 690 | F16: 104.35 | G16: =E16*F16 -> 72001.5 | H16: 20 | I16: 116.25 | J16: =H16*I16 -> 2325 | K16: =G16+J16 -> 74326.5 | M16: =M15+K16-L16 -> 875469.99
A17: 14 | B17: 46309 | G17: =E17*F17 -> 0 | J17: =H17*I17 -> 0 | K17: =G17+J17 -> 0 | M17: =M16+K17-L17 -> 875469.99
A18: 15 | B18: 46310 | E18: 690 | F18: 104.35 | G18: =E18*F18 -> 72001.5 | H18: 20 | I18: 116.25 | J18: =H18*I18 -> 2325 | K18: =G18+J18 -> 74326.5 | M18: =M17+K18-L18 -> 949796.49
A19: 16 | B19: 46311 | G19: =E19*F19 -> 0 | J19: =H19*I19 -> 0 | K19: =G19+J19 -> 0 | M19: =M18+K19-L19 -> 949796.49
A20: 17 | B20: 46312 | G20: =E20*F20 -> 0 | J20: =H20*I20 -> 0 | K20: =G20+J20 -> 0 | M20: =M19+K20-L20 -> 949796.49
A21: 18 | B21: 46313 | G21: =E21*F21 -> 0 | J21: =H21*I21 -> 0 | K21: =G21+J21 -> 0 | M21: =M20+K21-L21 -> 949796.49
A22: 19 | B22: 46314 | G22: =E22*F22 -> 0 | J22: =H22*I22 -> 0 | K22: =G22+J22 -> 0 | M22: =M21+K22-L22 -> 949796.49
A23: 20 | B23: 46315 | G23: =E23*F23 -> 0 | J23: =H23*I23 -> 0 | K23: =G23+J23 -> 0 | M23: =M22+K23-L23 -> 949796.49
A24: 21 | B24: 46316 | G24: =E24*F24 -> 0 | J24: =H24*I24 -> 0 | K24: =G24+J24 -> 0 | M24: =M23+K24-L24 -> 949796.49
A25: 22 | B25: 46317 | G25: =E25*F25 -> 0 | J25: =H25*I25 -> 0 | K25: =G25+J25 -> 0 | M25: =M24+K25-L25 -> 949796.49
A26: 23 | B26: 46318 | G26: =E26*F26 -> 0 | J26: =H26*I26 -> 0 | K26: =G26+J26 -> 0 | M26: =M25+K26-L26 -> 949796.49
A27: 24 | B27: 46319 | G27: =E27*F27 -> 0 | J27: =H27*I27 -> 0 | K27: =G27+J27 -> 0 | M27: =M26+K27-L27 -> 949796.49
A28: 25 | B28: 46320 | G28: =E28*F28 -> 0 | J28: =H28*I28 -> 0 | K28: =G28+J28 -> 0 | M28: =M27+K28-L28 -> 949796.49
A29: 26 | B29: 46321 | G29: =E29*F29 -> 0 | J29: =H29*I29 -> 0 | K29: =G29+J29 -> 0 | M29: =M28+K29-L29 -> 949796.49
A30: 27 | B30: 46322 | G30: =E30*F30 -> 0 | J30: =H30*I30 -> 0 | K30: =G30+J30 -> 0 | M30: =M29+K30-L30 -> 949796.49
... A34: 31 | B34: 46326 | G34: =E34*F34 -> 0 | J34: =H34*I34 -> 0 | K34: =G34+J34 -> 0 | M34: =M33+K34-L34 -> 949796.49
A35: 32 | G35: =E35*F35 -> 0 | J35: =H35*I35 -> 0 | K35: =G35+J35 -> 0 | M35: =M34+K35-L35 -> 949796.49
E36: =SUM(E4:E35) -> 5520 | G36: =SUM(G4:G35) -> 576012 | H36: =SUM(H4:H35) -> 60 | J36: =SUM(J4:J35) -> 6975 | K36: =SUM(K4:K35) -> 582987 | L36: =SUM(L4:L35) -> 0

Sheet Narayankhed
A2: S.No | B2: Date | C2: GRN No | D2: Ind no/Bill No | E2: Diesel (Lts) | F2: Price | G2: Amount | H2: Petrol (Lts) | I2: Price | J2: Amount | K2: Total amount | L2: Amount paid | M2: As on Date | N2: Remarks
A3: Opening Balance
A4: 1 | B4: 46296 | E4: 285.39 | F4: 105.12 | G4: =E4*F4 -> 30000.197 | J4: =H4*I4 -> 0 | K4: =G4+J4 -> 30000.197 | L4: 30000.197 | M4: =M3+K4-L4 -> 0 | N4: BPCL
A5: 2 | B5: 46297 | G5: =E5*F5 -> 0 | J5: =H5*I5 -> 0 | K5: =G5+J5 -> 0 | M5: =M4+K5-L5 -> 0
A6: 3 | B6: 46298 | G6: =E6*F6 -> 0 | J6: =H6*I6 -> 0 | K6: =G6+J6 -> 0 | M6: =M5+K6-L6 -> 0
A7: 4 | B7: 46299 | G7: =E7*F7 -> 0 | J7: =H7*I7 -> 0 | K7: =G7+J7 -> 0 | M7: =M6+K7-L7 -> 0
A8: 5 | B8: 46300 | E8: 285.39 | F8: 105.12 | G8: =E8*F8 -> 30000.197 | J8: =H8*I8 -> 0 | K8: =G8+J8 -> 30000.197 | L8: 30000.197 | M8: =M7+K8-L8 -> 0 | N8: BPCL
A9: 6 | B9: 46301 | E9: 285.63 | F9: 105.03 | G9: =E9*F9 -> 29999.719 | J9: =H9*I9 -> 0 | K9: =G9+J9 -> 29999.719 | L9: =H9+K9 -> 29999.719 | M9: =M8+K9-L9 -> 0 | N9: BPCL
A10: 7 | B10: 46302 | E10: 95.13 | F10: 105.12 | G10: =E10*F10 -> 10000.066 | J10: =H10*I10 -> 0 | K10: =G10+J10 -> 10000.066 | L10: 10000.066 | M10: =M9+K10-L10 -> 0 | N10: BPCL
B11: 46302 | E11: 95.211 | F11: 105.03 | G11: =E11*F11 -> 10000.011 | K11: =G11+J11 -> 10000.011 | L11: 10000.011 | M11: =M10+K11-L11 -> 0 | N11: HPCL
A12: 8 | B12: 46303 | G12: =E12*F12 -> 0 | J12: =H12*I12 -> 0 | K12: =G12+J12 -> 0 | M12: =M10+K12-L12 -> 0
A13: 9 | B13: 46304 | E13: 285.39 | F13: 105.12 | G13: =E13*F13 -> 30000.197 | J13: =H13*I13 -> 0 | K13: =G13+J13 -> 30000.197 | L13: 30000.197 | M13: =M12+K13-L13 -> 0 | N13: BPCL
A14: 10 | B14: 46305 | G14: =E14*F14 -> 0 | J14: =H14*I14 -> 0 | K14: =G14+J14 -> 0 | M14: =M13+K14-L14 -> 0
A15: 11 | B15: 46306 | G15: =E15*F15 -> 0 | J15: =H15*I15 -> 0 | K15: =G15+J15 -> 0 | M15: =M14+K15-L15 -> 0
A16: 12 | B16: 46307 | G16: =E16*F16 -> 0 | J16: =H16*I16 -> 0 | K16: =G16+J16 -> 0 | M16: =M15+K16-L16 -> 0
A17: 13 | B17: 46308 | G17: =E17*F17 -> 0 | J17: =H17*I17 -> 0 | K17: =G17+J17 -> 0 | M17: =M16+K17-L17 -> 0
A18: 14 | B18: 46309 | E18: 190.42 | F18: 105.03 | G18: =E18*F18 -> 19999.813 | J18: =H18*I18 -> 0 | K18: =G18+J18 -> 19999.813 | L18: 19999.813 | M18: =M17+K18-L18 -> 0
A19: 15 | B19: 46310 | G19: =E19*F19 -> 0 | J19: =H19*I19 -> 0 | K19: =G19+J19 -> 0 | M19: =M18+K19-L19 -> 0
A20: 16 | B20: 46311 | G20: =E20*F20 -> 0 | J20: =H20*I20 -> 0 | K20: =G20+J20 -> 0 | M20: =M19+K20-L20 -> 0
A21: 17 | B21: 46312 | G21: =E21*F21 -> 0 | J21: =H21*I21 -> 0 | K21: =G21+J21 -> 0 | M21: =M20+K21-L21 -> 0
A22: 18 | B22: 46313 | G22: =E22*F22 -> 0 | J22: =H22*I22 -> 0 | K22: =G22+J22 -> 0 | M22: =M21+K22-L22 -> 0
A23: 19 | B23: 46314 | G23: =E23*F23 -> 0 | J23: =H23*I23 -> 0 | K23: =G23+J23 -> 0 | M23: =M22+K23-L23 -> 0
A24: 20 | B24: 46315 | G24: =E24*F24 -> 0 | J24: =H24*I24 -> 0 | K24: =G24+J24 -> 0 | M24: =M23+K24-L24 -> 0
A25: 21 | B25: 46316 | G25: =E25*F25 -> 0 | J25: =H25*I25 -> 0 | K25: =G25+J25 -> 0 | M25: =M24+K25-L25 -> 0
A26: 22 | B26: 46317 | G26: =E26*F26 -> 0 | J26: =H26*I26 -> 0 | K26: =G26+J26 -> 0 | M26: =M25+K26-L26 -> 0
A27: 23 | B27: 46318 | G27: =E27*F27 -> 0 | J27: =H27*I27 -> 0 | K27: =G27+J27 -> 0 | M27: =M26+K27-L27 -> 0
A28: 24 | B28: 46319 | G28: =E28*F28 -> 0 | J28: =H28*I28 -> 0 | K28: =G28+J28 -> 0 | M28: =M27+K28-L28 -> 0
A29: 25 | B29: 46320 | G29: =E29*F29 -> 0 | J29: =H29*I29 -> 0 | K29: =G29+J29 -> 0 | M29: =M28+K29-L29 -> 0
A30: 26 | B30: 46321 | G30: =E30*F30 -> 0 | J30: =H30*I30 -> 0 | K30: =G30+J30 -> 0 | M30: =M29+K30-L30 -> 0
... A34: 30 | B34: 46325 | G34: =E34*F34 -> 0 | J34: =H34*I34 -> 0 | K34: =G34+J34 -> 0 | M34: =M33+K34-L34 -> 0
A35: 31 | B35: 46326 | G35: =E35*F35 -> 0 | J35: =H35*I35 -> 0 | K35: =G35+J35 -> 0 | M35: 0
E36: =SUM(E4:E35) -> 1522.561 | G36: =SUM(G4:G35) -> 160000.2 | H36: =SUM(H4:H35) -> 0 | J36: =SUM(J4:J35) -> 0 | K36: =SUM(K4:K35) -> 160000.2 | L36: =SUM(L4:L35) -> 160000.2

Sheet Dindi
A1: Akarapu Balakistamma Fillling
A2: S.No | B2: Date | C2: GRN No | D2: Ind no/Bill No | E2: Diesel (Lts) | F2: Price | G2: Amount | H2: Petrol (Lts) | I2: Price | J2: Amount | K2: Total amount | L2: Amount paid | M2: As on Date | N2: Remarks
A3: Opening Balance | M3: 0
A4: 1 | B4: 45931 | G4: =E4*F4 -> 0 | J4: =H4*I4 -> 0 | K4: =G4+J4 -> 0 | L4: =+K4 -> 0 | M4: 0
A5: 2 | B5: 45932 | G5: =E5*F5 -> 0 | J5: =H5*I5 -> 0 | K5: =G5+J5 -> 0 | L5: =+K5 -> 0 | M5: 0
A6: 3 | B6: 45933 | E6: 28.59 | F6: 104.95 | G6: =E6*F6 -> 3000.5205 | J6: =H6*I6 -> 0 | K6: =G6+J6 -> 3000.5205 | L6: =+K6 -> 3000.5205 | M6: 0
A7: 4 | B7: 45934 | G7: =E7*F7 -> 0 | J7: =H7*I7 -> 0 | K7: =G7+J7 -> 0 | L7: =+K7 -> 0 | M7: 0
A8: 5 | B8: 45935 | G8: =E8*F8 -> 0 | J8: =H8*I8 -> 0 | K8: =G8+J8 -> 0 | L8: =+K8 -> 0 | M8: 0
A9: 6 | B9: 45936 | G9: =E9*F9 -> 0 | J9: =H9*I9 -> 0 | K9: =G9+J9 -> 0 | L9: =+K9 -> 0 | M9: 0
A10: 7 | B10: 45937 | G10: =E10*F10 -> 0 | J10: =H10*I10 -> 0 | K10: =G10+J10 -> 0 | L10: =+K10 -> 0 | M10: 0
A11: 8 | B11: 45938 | G11: =E11*F11 -> 0 | J11: =H11*I11 -> 0 | K11: =G11+J11 -> 0 | L11: =+K11 -> 0 | M11: 0
A12: 9 | B12: 45939 | G12: =E12*F12 -> 0 | J12: =H12*I12 -> 0 | K12: =G12+J12 -> 0 | L12: =+K12 -> 0 | M12: 0
A13: 10 | B13: 45940 | G13: =E13*F13 -> 0 | J13: =H13*I13 -> 0 | K13: =G13+J13 -> 0 | L13: =+K13 -> 0 | M13: 0
A14: 11 | B14: 45941 | G14: =E14*F14 -> 0 | J14: =H14*I14 -> 0 | K14: =G14+J14 -> 0 | L14: =+K14 -> 0 | M14: 0
A15: 12 | B15: 45942 | G15: =E15*F15 -> 0 | J15: =H15*I15 -> 0 | K15: =G15+J15 -> 0 | L15: =+K15 -> 0 | M15: 0
A16: 13 | B16: 45943 | G16: =E16*F16 -> 0 | J16: =H16*I16 -> 0 | K16: =G16+J16 -> 0 | L16: =+K16 -> 0 | M16: 0
A17: 14 | B17: 45944 | G17: =E17*F17 -> 0 | J17: =H17*I17 -> 0 | K17: =G17+J17 -> 0 | L17: =+K17 -> 0 | M17: 0
A18: 15 | B18: 45945 | E18: 38.93 | F18: 104.95 | G18: =E18*F18 -> 4085.7035 | J18: =H18*I18 -> 0 | K18: =G18+J18 -> 4085.7035 | L18: =+K18 -> 4085.7035 | M18: 0
A19: 16 | B19: 45946 | G19: =E19*F19 -> 0 | J19: =H19*I19 -> 0 | K19: =G19+J19 -> 0 | L19: =+K19 -> 0 | M19: 0
A20: 17 | B20: 45947 | G20: =E20*F20 -> 0 | J20: =H20*I20 -> 0 | K20: =G20+J20 -> 0 | L20: =+K20 -> 0 | M20: 0
A21: 18 | B21: 45948 | G21: =E21*F21 -> 0 | J21: =H21*I21 -> 0 | K21: =G21+J21 -> 0 | L21: =+K21 -> 0 | M21: 0
A22: 19 | B22: 45949 | G22: =E22*F22 -> 0 | J22: =H22*I22 -> 0 | K22: =G22+J22 -> 0 | L22: =+K22 -> 0 | M22: 0
A23: 20 | B23: 45950 | G23: =E23*F23 -> 0 | J23: =H23*I23 -> 0 | K23: =G23+J23 -> 0 | L23: =+K23 -> 0 | M23: 0
A24: 21 | B24: 45951 | G24: =E24*F24 -> 0 | J24: =H24*I24 -> 0 | K24: =G24+J24 -> 0 | L24: =+K24 -> 0 | M24: 0
A25: 22 | B25: 45952 | G25: =E25*F25 -> 0 | J25: =H25*I25 -> 0 | K25: =G25+J25 -> 0 | L25: =+K25 -> 0 | M25: 0
A26: 23 | B26: 45953 | G26: =E26*F26 -> 0 | J26: =H26*I26 -> 0 | K26: =G26+J26 -> 0 | L26: =+K26 -> 0 | M26: 0
A27: 24 | B27: 45954 | G27: =E27*F27 -> 0 | J27: =H27*I27 -> 0 | K27: =G27+J27 -> 0 | L27: =+K27 -> 0 | M27: 0
A28: 25 | B28: 45955 | G28: =E28*F28 -> 0 | J28: =H28*I28 -> 0 | K28: =G28+J28 -> 0 | L28: =+K28 -> 0 | M28: 0
A29: 26 | B29: 45956 | G29: =E29*F29 -> 0 | J29: =H29*I29 -> 0 | K29: =G29+J29 -> 0 | L29: =+K29 -> 0 | M29: 0
A30: 27 | B30: 45957 | G30: =E30*F30 -> 0 | J30: =H30*I30 -> 0 | K30: =G30+J30 -> 0 | L30: =+K30 -> 0 | M30: 0
... A34: 31 | B34: 45961 | G34: =E34*F34 -> 0 | J34: =H34*I34 -> 0 | K34: =G34+J34 -> 0 | L34: =+K34 -> 0 | M34: 0
E35: =SUM(E4:E34) -> 67.52 | G35: =SUM(G4:G34) -> 7086.224 | H35: =SUM(H4:H34) -> 0 | J35: =SUM(J4:J34) -> 0 | K35: =SUM(K4:K34) -> 7086.224 | L35: =SUM(L4:L34) -> 7086.224

Sheet Multiple bunks(KKD)
A2: S.No | B2: Date | C2: GRN No | D2: Ind no/Bill No | E2: Diesel (Lts) | F2: Price | G2: Amount | H2: Petrol (Lts) | I2: Price | J2: Amount | K2: Total amount | L2: Amount paid | M2: As on Date | N2: Remarks
A3: Opening Balance
A4: 1 | G4: =E4*F4 -> 0 | J4: =H4*I4 -> 0 | K4: =G4+J4 -> 0 | L4: =+K4 -> 0
A5: 2 | G5: =E5*F5 -> 0 | J5: =H5*I5 -> 0 | K5: =G5+J5 -> 0 | L5: =+K5 -> 0
A6: 3 | G6: =E6*F6 -> 0 | J6: =H6*I6 -> 0 | K6: =G6+J6 -> 0 | L6: =+K6 -> 0
A7: 4 | G7: =E7*F7 -> 0 | J7: =H7*I7 -> 0 | K7: =G7+J7 -> 0 | L7: =+K7 -> 0
A8: 5 | G8: =E8*F8 -> 0 | J8: =H8*I8 -> 0 | K8: =G8+J8 -> 0 | L8: =+K8 -> 0
A9: 6 | G9: =E9*F9 -> 0 | J9: =H9*I9 -> 0 | K9: =G9+J9 -> 0 | L9: =+K9 -> 0
A10: 7 | G10: =E10*F10 -> 0 | J10: =H10*I10 -> 0 | K10: =G10+J10 -> 0 | L10: =+K10 -> 0
A11: 8 | G11: =E11*F11 -> 0 | J11: =H11*I11 -> 0 | K11: =G11+J11 -> 0 | L11: =+K11 -> 0
A12: 9 | G12: =E12*F12 -> 0 | J12: =H12*I12 -> 0 | K12: =G12+J12 -> 0 | L12: =+K12 -> 0
A13: 10 | G13: =E13*F13 -> 0 | J13: =H13*I13 -> 0 | K13: =G13+J13 -> 0 | L13: =+K13 -> 0
A14: 11 | G14: =E14*F14 -> 0 | J14: =H14*I14 -> 0 | K14: =G14+J14 -> 0 | L14: =+K14 -> 0
A15: 12 | G15: =E15*F15 -> 0 | J15: =H15*I15 -> 0 | K15: =G15+J15 -> 0 | L15: =+K15 -> 0
... A30: 27 | G30: =E30*F30 -> 0 | J30: =H30*I30 -> 0 | K30: =G30+J30 -> 0 | L30: =+K30 -> 0
A31: 28 | J31: =H31*I31 -> 0 | K31: =G31+J31 -> 0 | L31: =+K31 -> 0
A32: 29 | J32: =H32*I32 -> 0 | K32: =G32+J32 -> 0 | L32: =+K32 -> 0
A33: 30 | J33: =H33*I33 -> 0 | K33: =G33+J33 -> 0 | L33: =+K33 -> 0
A34: 31 | J34: =H34*I34 -> 0 | K34: =G34+J34 -> 0 | L34: =+K34 -> 0
A35: 32 | J35: =H35*I35 -> 0 | K35: =G35+J35 -> 0 | L35: =+K35 -> 0
A36: 33 | G36: =E36*F36 -> 0 | J36: =H36*I36 -> 0 | K36: =G36+J36 -> 0 | L36: =+K36 -> 0
A37: 34 | G37: =E37*F37 -> 0 | J37: =H37*I37 -> 0 | K37: =G37+J37 -> 0 | L37: =+K37 -> 0
A38: 35 | G38: =E38*F38 -> 0 | J38: =H38*I38 -> 0 | K38: =G38+J38 -> 0 | L38: =+K38 -> 0
A39: 36 | G39: =E39*F39 -> 0 | J39: =H39*I39 -> 0 | K39: =G39+J39 -> 0 | L39: =+K39 -> 0
A40: 37 | G40: =E40*F40 -> 0 | J40: =H40*I40 -> 0 | K40: =G40+J40 -> 0 | L40: =+K40 -> 0
A41: 38 | G41: =E41*F41 -> 0 | J41: =H41*I41 -> 0 | K41: =G41+J41 -> 0 | L41: =+K41 -> 0
A42: 39 | G42: =E42*F42 -> 0 | J42: =H42*I42 -> 0 | K42: =G42+J42 -> 0 | L42: =+K42 -> 0
A43: 40 | G43: =E43*F43 -> 0 | J43: =H43*I43 -> 0 | K43: =G43+J43 -> 0 | L43: =+K43 -> 0
A44: 41 | G44: =E44*F44 -> 0 | J44: =H44*I44 -> 0 | K44: =G44+J44 -> 0 | L44: =+K44 -> 0
A45: 42 | G45: =E45*F45 -> 0 | J45: =H45*I45 -> 0 | K45: =G45+J45 -> 0 | L45: =+K45 -> 0
A46: 43 | G46: =E46*F46 -> 0 | J46: =H46*I46 -> 0 | K46: =G46+J46 -> 0 | L46: =+K46 -> 0
A47: 44 | G47: =E47*F47 -> 0 | J47: =H47*I47 -> 0 | K47: =G47+J47 -> 0 | L47: =+K47 -> 0
... A66: 63 | G66: =E66*F66 -> 0 | J66: =H66*I66 -> 0 | K66: =G66+J66 -> 0 | L66: =+K66 -> 0
A67: 64
E68: =SUM(E4:E67) -> 0 | G68: =SUM(G4:G67) -> 0 | H68: =SUM(H4:H67) -> 0 | J68: =SUM(J4:J67) -> 0 | K68: =SUM(K4:K67) -> 0

Sheet  Pitapram(KKD)
A1: SATYA SIVA DURGA AGENCIES, CHEBROLU (BPCL)
A2: S.No | B2: Date | C2: GRN No | D2: Ind no/Bill No | E2: Diesel (Lts) | F2: Price | G2: Amount | H2: Petrol (Lts) | I2: Price | J2: Amount | K2: Total amount | L2: Amount paid | M2: As on Date | N2: Remarks
A3: Opening Balance | M3: 291832.98
A4: 1 | B4: 46296 | E4: 120 | F4: 105.21 | G4: =E4*F4 -> 12625.2 | J4: =H4*I4 -> 0 | K4: =G4+J4 -> 12625.2 | M4: =M3+K4-L4 -> 304458.18
A5: 2 | B5: 46297 | E5: 430.04 | F5: 105.21 | G5: =E5*F5 -> 45244.508 | H5: 55 | I5: 117.58 | J5: =H5*I5 -> 6466.9 | K5: =G5+J5 -> 51711.408 | M5: =M4+K5-L5 -> 356169.59
A6: 3 | B6: 46298 | E6: 640 | F6: 105.21 | G6: =E6*F6 -> 67334.4 | J6: =H6*I6 -> 0 | K6: =G6+J6 -> 67334.4 | M6: =M5+K6-L6 -> 423503.99
A7: 4 | B7: 46299 | G7: =E7*F7 -> 0 | J7: =H7*I7 -> 0 | K7: =G7+J7 -> 0 | M7: =M6+K7-L7 -> 423503.99
A8: 5 | B8: 46300 | G8: =E8*F8 -> 0 | J8: =H8*I8 -> 0 | K8: =G8+J8 -> 0 | M8: =M7+K8-L8 -> 423503.99
A9: 6 | B9: 46301 | G9: =E9*F9 -> 0 | J9: =H9*I9 -> 0 | K9: =G9+J9 -> 0 | M9: =M8+K9-L9 -> 423503.99
A10: 7 | B10: 46302 | G10: =E10*F10 -> 0 | J10: =H10*I10 -> 0 | K10: =G10+J10 -> 0 | M10: =M9+K10-L10 -> 423503.99
A11: 8 | B11: 46303 | G11: =E11*F11 -> 0 | J11: =H11*I11 -> 0 | K11: =G11+J11 -> 0 | L11: 423000 | M11: =M10+K11-L11 -> 503.9927
A12: 9 | B12: 46304 | E12: 32.5 | F12: 105.21 | G12: =E12*F12 -> 3419.325 | J12: =H12*I12 -> 0 | K12: =G12+J12 -> 3419.325 | M12: =M11+K12-L12 -> 3923.3177
A13: 10 | B13: 46305 | G13: =E13*F13 -> 0 | J13: =H13*I13 -> 0 | K13: =G13+J13 -> 0 | M13: =M12+K13-L13 -> 3923.3177
A14: 11 | B14: 46306 | G14: =E14*F14 -> 0 | J14: =H14*I14 -> 0 | K14: =G14+J14 -> 0 | M14: =M13+K14-L14 -> 3923.3177
A15: 12 | B15: 46307 | G15: =E15*F15 -> 0 | J15: =H15*I15 -> 0 | K15: =G15+J15 -> 0 | M15: =M14+K15-L15 -> 3923.3177
A16: 13 | B16: 46308 | G16: =E16*F16 -> 0 | J16: =H16*I16 -> 0 | K16: =G16+J16 -> 0 | M16: =M15+K16-L16 -> 3923.3177
A17: 14 | B17: 46309 | G17: =E17*F17 -> 0 | J17: =H17*I17 -> 0 | K17: =G17+J17 -> 0 | M17: =M16+K17-L17 -> 3923.3177
A18: 15 | B18: 46310 | G18: =E18*F18 -> 0 | J18: =H18*I18 -> 0 | K18: =G18+J18 -> 0 | M18: =M17+K18-L18 -> 3923.3177
A19: 16 | B19: 46311 | G19: =E19*F19 -> 0 | J19: =H19*I19 -> 0 | K19: =G19+J19 -> 0 | M19: =M18+K19-L19 -> 3923.3177
A20: 17 | B20: 46312 | G20: =E20*F20 -> 0 | J20: =H20*I20 -> 0 | K20: =G20+J20 -> 0 | M20: =M19+K20-L20 -> 3923.3177
A21: 18 | B21: 46313 | G21: =E21*F21 -> 0 | J21: =H21*I21 -> 0 | K21: =G21+J21 -> 0 | M21: =M20+K21-L21 -> 3923.3177
A22: 19 | B22: 46314 | G22: =E22*F22 -> 0 | J22: =H22*I22 -> 0 | K22: =G22+J22 -> 0 | M22: =M21+K22-L22 -> 3923.3177
A23: 20 | B23: 46315 | G23: =E23*F23 -> 0 | J23: =H23*I23 -> 0 | K23: =G23+J23 -> 0 | M23: =M22+K23-L23 -> 3923.3177
A24: 21 | B24: 46316 | G24: =E24*F24 -> 0 | J24: =H24*I24 -> 0 | K24: =G24+J24 -> 0 | M24: =M23+K24-L24 -> 3923.3177
... A34: 31 | B34: 46326 | G34: =E34*F34 -> 0 | J34: =H34*I34 -> 0 | K34: =G34+J34 -> 0 | M34: =M33+K34-L34 -> 3923.3177
A35: 32 | G35: =E35*F35 -> 0 | J35: =H35*I35 -> 0 | K35: =G35+J35 -> 0 | M35: =M34+K35-L35 -> 3923.3177
A36: 33 | G36: =E36*F36 -> 0 | J36: =H36*I36 -> 0 | K36: =G36+J36 -> 0 | M36: =M35+K36-L36 -> 3923.3177
E37: =SUM(E4:E36) -> 1222.54 | G37: =SUM(G4:G36) -> 128623.43 | H37: =SUM(H4:H36) -> 55 | J37: =SUM(J4:J36) -> 6466.9 | K37: =SUM(K4:K36) -> 135090.33 | L37: =SUM(L4:L36) -> 423000

Sheet Yeleshwaram(KKD)
A1: SRI SATYA FILLING STATION, YELESWARAM (BPCL)
A2: S.No | B2: Date | C2: GRN No | D2: Ind no/Bill No | E2: Diesel (Lts) | F2: Price | G2: Amount | H2: Petrol (Lts) | I2: Price | J2: Amount | K2: Total amount | L2: Amount paid | M2: As on Date | N2: Remarks
A3: Opening Balance | M3: 17080.343
A4: 1 | B4: 46296 | G4: =E4*F4 -> 0 | J4: =H4*I4 -> 0 | K4: =G4+J4 -> 0 | M4: =M3+K4-L4 -> 17080.343
A5: 2 | B5: 46297 | G5: =E5*F5 -> 0 | J5: =H5*I5 -> 0 | K5: =G5+J5 -> 0 | M5: =M4+K5-L5 -> 17080.343
A6: 3 | B6: 46298 | G6: =E6*F6 -> 0 | J6: =H6*I6 -> 0 | K6: =G6+J6 -> 0 | M6: =M5+K6-L6 -> 17080.343
A7: 4 | B7: 46299 | G7: =E7*F7 -> 0 | J7: =H7*I7 -> 0 | K7: =G7+J7 -> 0 | M7: =M6+K7-L7 -> 17080.343
A8: 5 | B8: 46300 | E8: 40 | F8: 105.46 | G8: =E8*F8 -> 4218.4 | J8: =H8*I8 -> 0 | K8: =G8+J8 -> 4218.4 | M8: =M7+K8-L8 -> 21298.743
A9: 6 | B9: 46301 | G9: =E9*F9 -> 0 | J9: =H9*I9 -> 0 | K9: =G9+J9 -> 0 | M9: =M8+K9-L9 -> 21298.743
A10: 7 | B10: 46302 | E10: 100 | F10: 105.46 | G10: =E10*F10 -> 10546 | H10: 5 | I10: 117.84 | J10: =H10*I10 -> 589.2 | K10: =G10+J10 -> 11135.2 | M10: =M9+K10-L10 -> 32433.943
A11: 8 | B11: 46303 | E11: 30 | F11: 105.46 | G11: =E11*F11 -> 3163.8 | J11: =H11*I11 -> 0 | K11: =G11+J11 -> 3163.8 | M11: =M10+K11-L11 -> 35597.743
A12: 9 | B12: 46304 | G12: =E12*F12 -> 0 | J12: =H12*I12 -> 0 | K12: =G12+J12 -> 0 | M12: =M11+K12-L12 -> 35597.743
A13: 10 | B13: 46305 | E13: 47 | F13: 105.46 | G13: =E13*F13 -> 4956.62 | J13: =H13*I13 -> 0 | K13: =G13+J13 -> 4956.62 | M13: =M12+K13-L13 -> 40554.363
A14: 11 | B14: 46306 | E14: 400 | F14: 105.46 | G14: =E14*F14 -> 42184 | H14: 50 | I14: 117.84 | J14: =H14*I14 -> 5892 | K14: =G14+J14 -> 48076 | M14: =M13+K14-L14 -> 88630.363
A15: 12 | B15: 46307 | G15: =E15*F15 -> 0 | H15: 5 | I15: 117.84 | J15: =H15*I15 -> 589.2 | K15: =G15+J15 -> 589.2 | M15: =M14+K15-L15 -> 89219.563
A16: 13 | B16: 46308 | G16: =E16*F16 -> 0 | J16: =H16*I16 -> 0 | K16: =G16+J16 -> 0 | M16: =M15+K16-L16 -> 89219.563
A17: 14 | B17: 46309 | G17: =E17*F17 -> 0 | J17: =H17*I17 -> 0 | K17: =G17+J17 -> 0 | M17: =M16+K17-L17 -> 89219.563
A18: 15 | B18: 46310 | E18: 470 | F18: 105.46 | G18: =E18*F18 -> 49566.2 | H18: 50 | I18: 117.84 | J18: =H18*I18 -> 5892 | K18: =G18+J18 -> 55458.2 | L18: 80000 | M18: =M17+K18-L18 -> 64677.763
A19: 16 | B19: 46311 | G19: =E19*F19 -> 0 | J19: =H19*I19 -> 0 | K19: =G19+J19 -> 0 | M19: =M18+K19-L19 -> 64677.763
A20: 17 | B20: 46312 | G20: =E20*F20 -> 0 | J20: =H20*I20 -> 0 | K20: =G20+J20 -> 0 | M20: =M19+K20-L20 -> 64677.763
A21: 18 | B21: 46313 | G21: =E21*F21 -> 0 | J21: =H21*I21 -> 0 | K21: =G21+J21 -> 0 | M21: =M20+K21-L21 -> 64677.763
A22: 19 | B22: 46314 | G22: =E22*F22 -> 0 | J22: =H22*I22 -> 0 | K22: =G22+J22 -> 0 | M22: =M21+K22-L22 -> 64677.763
A23: 20 | B23: 46315 | G23: =E23*F23 -> 0 | J23: =H23*I23 -> 0 | K23: =G23+J23 -> 0 | M23: =M22+K23-L23 -> 64677.763
A24: 21 | B24: 46316 | G24: =E24*F24 -> 0 | J24: =H24*I24 -> 0 | K24: =G24+J24 -> 0 | M24: =M23+K24-L24 -> 64677.763
A25: 22 | B25: 46317 | G25: =E25*F25 -> 0 | J25: =H25*I25 -> 0 | K25: =G25+J25 -> 0 | M25: =M24+K25-L25 -> 64677.763
A26: 23 | B26: 46318 | G26: =E26*F26 -> 0 | J26: =H26*I26 -> 0 | K26: =G26+J26 -> 0 | M26: =M25+K26-L26 -> 64677.763
A27: 24 | B27: 46319 | G27: =E27*F27 -> 0 | J27: =H27*I27 -> 0 | K27: =G27+J27 -> 0 | M27: =M26+K27-L27 -> 64677.763
A28: 25 | B28: 46320 | G28: =E28*F28 -> 0 | J28: =H28*I28 -> 0 | K28: =G28+J28 -> 0 | M28: =M27+K28-L28 -> 64677.763
A29: 26 | B29: 46321 | G29: =E29*F29 -> 0 | J29: =H29*I29 -> 0 | K29: =G29+J29 -> 0 | M29: =M28+K29-L29 -> 64677.763
A30: 27 | B30: 46322 | J30: =H30*I30 -> 0 | K30: =G30+J30 -> 0 | M30: =M29+K30-L30 -> 64677.763
A31: 28 | B31: 46323 | G31: =E31*F31 -> 0 | J31: =H31*I31 -> 0 | K31: =G31+J31 -> 0 | M31: =M30+K31-L31 -> 64677.763
A32: 29 | B32: 46324 | G32: =E32*F32 -> 0 | J32: =H32*I32 -> 0 | K32: =G32+J32 -> 0 | M32: =M31+K32-L32 -> 64677.763
A33: 30 | B33: 46325 | G33: =E33*F33 -> 0 | J33: =H33*I33 -> 0 | K33: =G33+J33 -> 0 | M33: =M32+K33-L33 -> 64677.763
A34: 31 | B34: 46326 | G34: =E34*F34 -> 0 | J34: =H34*I34 -> 0 | K34: =G34+J34 -> 0 | M34: =M33+K34-L34 -> 64677.763
A35: 32 | G35: =E35*F35 -> 0 | J35: =H35*I35 -> 0 | K35: =G35+J35 -> 0 | M35: =M34+K35-L35 -> 64677.763
A36: 33 | G36: =E36*F36 -> 0 | J36: =H36*I36 -> 0 | K36: =G36+J36 -> 0 | M36: =M35+K36-L36 -> 64677.763
E37: =SUM(E4:E36) -> 1087 | G37: =SUM(G4:G36) -> 114635.02 | H37: =SUM(H4:H36) -> 110 | J37: =SUM(J4:J36) -> 12962.4 | K37: =SUM(K4:K36) -> 127597.42 | L37: =SUM(L4:L36) -> 80000

Sheet Amalapuram(KKD)
A1: ROYAL FILL 'N' FLY, AMALAPURAM(HPCL)
A2: S.No | B2: Date | C2: GRN No | D2: Ind no/Bill No | E2: Diesel (Lts) | F2: Price | G2: Amount | H2: Petrol (Lts) | I2: Price | J2: Amount | K2: Total amount | L2: Amount paid | M2: As on Date | N2: Remarks
A3: Opening Balance | M3: 519637.76
A4: 1 | B4: 46296 | E4: 419 | F4: 105.25 | G4: =E4*F4 -> 44099.75 | H4: 6 | I4: 117.58 | J4: =H4*I4 -> 705.48 | K4: =G4+J4 -> 44805.23 | M4: =M3+K4-L4 -> 564442.99
A5: 2 | B5: 46297 | E5: 935 | F5: 105.25 | G5: =E5*F5 -> 98408.75 | H5: 10 | I5: 117.58 | J5: =H5*I5 -> 1175.8 | K5: =G5+J5 -> 99584.55 | M5: =M4+K5-L5 -> 664027.54
A6: 3 | B6: 46298 | G6: =E6*F6 -> 0 | J6: =H6*I6 -> 0 | K6: =G6+J6 -> 0 | L6: 300000 | M6: =M5+K6-L6 -> 364027.54
A7: 4 | B7: 46299 | G7: =E7*F7 -> 0 | H7: 8 | I7: 117.58 | J7: =H7*I7 -> 940.64 | K7: =G7+J7 -> 940.64 | M7: =M6+K7-L7 -> 364968.18
A8: 5 | B8: 46300 | E8: 820 | F8: 105.25 | G8: =E8*F8 -> 86305 | H8: 8.5 | I8: 117.58 | J8: =H8*I8 -> 999.43 | K8: =G8+J8 -> 87304.43 | M8: =M7+K8-L8 -> 452272.61
A9: 6 | B9: 46301 | G9: =E9*F9 -> 0 | H9: 11 | I9: 117.58 | J9: =H9*I9 -> 1293.38 | K9: =G9+J9 -> 1293.38 | M9: =M8+K9-L9 -> 453565.99
A10: 7 | B10: 46302 | E10: 1042 | F10: 105.25 | G10: =E10*F10 -> 109670.5 | H10: 42.05 | I10: 117.58 | J10: =H10*I10 -> 4944.239 | K10: =G10+J10 -> 114614.74 | M10: =M9+K10-L10 -> 568180.73
A11: 8 | B11: 46303 | E11: 254 | F11: 105.25 | G11: =E11*F11 -> 26733.5 | H11: 5 | I11: 117.58 | J11: =H11*I11 -> 587.9 | K11: =G11+J11 -> 27321.4 | L11: 100000 | M11: =M10+K11-L11 -> 495502.13
A12: 9 | B12: 46304 | G12: =E12*F12 -> 0 | J12: =H12*I12 -> 0 | K12: =G12+J12 -> 0 | M12: =M11+K12-L12 -> 495502.13
A13: 10 | B13: 46305 | E13: 1080 | F13: 105.25 | G13: =E13*F13 -> 113670 | H13: 5 | I13: 117.58 | J13: =H13*I13 -> 587.9 | K13: =G13+J13 -> 114257.9 | L13: 300000 | M13: =M12+K13-L13 -> 309760.03
A14: 11 | B14: 46306 | G14: =E14*F14 -> 0 | H14: 6 | I14: 117.58 | J14: =H14*I14 -> 705.48 | K14: =G14+J14 -> 705.48 | M14: =M13+K14-L14 -> 310465.51
A15: 12 | B15: 46307 | E15: 360 | F15: 105.25 | G15: =E15*F15 -> 37890 | J15: =H15*I15 -> 0 | K15: =G15+J15 -> 37890 | M15: =M14+K15-L15 -> 348355.51
A16: 13 | B16: 46308 | G16: =E16*F16 -> 0 | J16: =H16*I16 -> 0 | K16: =G16+J16 -> 0 | M16: =M15+K16-L16 -> 348355.51
A17: 14 | B17: 46309 | E17: 800 | F17: 105.25 | G17: =E17*F17 -> 84200 | H17: 6 | I17: 117.58 | J17: =H17*I17 -> 705.48 | K17: =G17+J17 -> 84905.48 | M17: =M16+K17-L17 -> 433260.99
A18: 15 | B18: 46310 | G18: =E18*F18 -> 0 | H18: 6 | I18: 117.58 | J18: =H18*I18 -> 705.48 | K18: =G18+J18 -> 705.48 | L18: 300000 | M18: =M17+K18-L18 -> 133966.47
A19: 16 | B19: 46311 | G19: =E19*F19 -> 0 | J19: =H19*I19 -> 0 | K19: =G19+J19 -> 0 | M19: =M18+K19-L19 -> 133966.47
A20: 17 | B20: 46312 | G20: =E20*F20 -> 0 | J20: =H20*I20 -> 0 | K20: =G20+J20 -> 0 | M20: =M19+K20-L20 -> 133966.47
A21: 18 | B21: 46313 | G21: =E21*F21 -> 0 | J21: =H21*I21 -> 0 | K21: =G21+J21 -> 0 | M21: =M20+K21-L21 -> 133966.47
A22: 19 | B22: 46314 | G22: =E22*F22 -> 0 | J22: =H22*I22 -> 0 | K22: =G22+J22 -> 0 | M22: =M21+K22-L22 -> 133966.47
A23: 20 | B23: 46315 | G23: =E23*F23 -> 0 | J23: =H23*I23 -> 0 | K23: =G23+J23 -> 0 | M23: =M22+K23-L23 -> 133966.47
A24: 21 | B24: 46316 | G24: =E24*F24 -> 0 | J24: =H24*I24 -> 0 | K24: =G24+J24 -> 0 | M24: =M23+K24-L24 -> 133966.47
A25: 22 | B25: 46317 | G25: =E25*F25 -> 0 | J25: =H25*I25 -> 0 | K25: =G25+J25 -> 0 | M25: =M24+K25-L25 -> 133966.47
A26: 23 | B26: 46318 | G26: =E26*F26 -> 0 | J26: =H26*I26 -> 0 | K26: =G26+J26 -> 0 | M26: =M25+K26-L26 -> 133966.47
A27: 24 | B27: 46319 | G27: =E27*F27 -> 0 | J27: =H27*I27 -> 0 | K27: =G27+J27 -> 0 | M27: =M26+K27-L27 -> 133966.47
A28: 25 | B28: 46320 | G28: =E28*F28 -> 0 | J28: =H28*I28 -> 0 | K28: =G28+J28 -> 0 | M28: =M27+K28-L28 -> 133966.47
A29: 26 | B29: 46321 | G29: =E29*F29 -> 0 | J29: =H29*I29 -> 0 | K29: =G29+J29 -> 0 | M29: =M28+K29-L29 -> 133966.47
A30: 27 | B30: 46322 | G30: =E30*F30 -> 0 | J30: =H30*I30 -> 0 | K30: =G30+J30 -> 0 | M30: =M29+K30-L30 -> 133966.47
... A34: 31 | B34: 46326 | G34: =E34*F34 -> 0 | J34: =H34*I34 -> 0 | K34: =G34+J34 -> 0 | M34: =M33+K34-L34 -> 133966.47
A35: 32 | G35: =E35*F35 -> 0 | J35: =H35*I35 -> 0 | K35: =G35+J35 -> 0 | M35: =M34+K35-L35 -> 133966.47
A36: 33 | G36: =E36*F36 -> 0 | J36: =H36*I36 -> 0 | K36: =G36+J36 -> 0 | M36: =M35+K36-L36 -> 133966.47
E37: =SUM(E4:E36) -> 5710 | G37: =SUM(G4:G36) -> 600977.5 | H37: =SUM(H4:H36) -> 113.55 | J37: =SUM(J4:J36) -> 13351.209 | K37: =SUM(K4:K36) -> 614328.71 | L37: =SUM(L4:L36) -> 1000000

Sheet  Solasa Krishna OIl
A1: SOLASA KRISHNA OIL COMPANY
A2: S.No | B2: Date | C2: GRN No | D2: Ind no/Bill No | E2: Diesel (Lts) | F2: Price | G2: Amount | H2: Petrol (Lts) | I2: Price | J2: Amount | K2: Total amount | L2: Amount paid | M2: As on Date | N2: Remarks
A3: Opening Balance | M3: 238901.54
A4: 1 | B4: 46296 | E4: 227.72 | F4: 105.4 | G4: =E4*F4 -> 24001.688 | J4: =H4*I4 -> 0 | K4: =G4+J4 -> 24001.688 | L4: 0 | M4: =M3+K4-L4 -> 262903.22
A5: 2 | B5: 46297 | E5: 100 | F5: 105.4 | G5: =E5*F5 -> 10540 | J5: =H5*I5 -> 0 | K5: =G5+J5 -> 10540 | M5: =M4+K5-L5 -> 273443.22
A6: 3 | B6: 46298 | E6: 199.01 | F6: 105.4 | G6: =E6*F6 -> 20975.654 | H6: 15 | I6: 117.74 | J6: =H6*I6 -> 1766.1 | K6: =G6+J6 -> 22741.754 | M6: =M5+K6-L6 -> 296184.98
A7: 4 | B7: 46299 | E7: 140 | F7: 105.4 | G7: =E7*F7 -> 14756 | J7: =H7*I7 -> 0 | K7: =G7+J7 -> 14756 | M7: =M6+K7-L7 -> 310940.98
A8: 5 | B8: 46300 | E8: 152.33 | F8: 105.4 | G8: =E8*F8 -> 16055.582 | J8: =H8*I8 -> 0 | K8: =G8+J8 -> 16055.582 | M8: =M7+K8-L8 -> 326996.56
A9: 6 | B9: 46301 | E9: 43.27 | F9: 105.4 | G9: =E9*F9 -> 4560.658 | J9: =H9*I9 -> 0 | K9: =G9+J9 -> 4560.658 | M9: =M8+K9-L9 -> 331557.22
A10: 7 | B10: 46302 | E10: 300 | F10: 105.4 | G10: =E10*F10 -> 31620 | J10: =H10*I10 -> 0 | K10: =G10+J10 -> 31620 | M10: =M9+K10-L10 -> 363177.22
A11: 8 | B11: 46303 | G11: =E11*F11 -> 0 | J11: =H11*I11 -> 0 | K11: =G11+J11 -> 0 | M11: =M10+K11-L11 -> 363177.22
A12: 9 | B12: 46304 | E12: 200 | F12: 105.4 | G12: =E12*F12 -> 21080 | H12: 5.2 | I12: 117.74 | J12: =H12*I12 -> 612.248 | K12: =G12+J12 -> 21692.248 | M12: =M11+K12-L12 -> 384869.47
A13: 10 | B13: 46305 | E13: 39.84 | F13: 105.4 | G13: =E13*F13 -> 4199.136 | J13: =H13*I13 -> 0 | K13: =G13+J13 -> 4199.136 | L13: 200000 | M13: =M12+K13-L13 -> 189068.6
A14: 11 | B14: 46306 | E14: 700 | F14: 105.4 | G14: =E14*F14 -> 73780 | H14: 20 | I14: 117.74 | J14: =H14*I14 -> 2354.8 | K14: =G14+J14 -> 76134.8 | M14: =M13+K14-L14 -> 265203.4
A15: 12 | B15: 46307 | G15: =E15*F15 -> 0 | J15: =H15*I15 -> 0 | K15: =G15+J15 -> 0 | M15: =M14+K15-L15 -> 265203.4
A16: 13 | B16: 46308 | G16: =E16*F16 -> 0 | J16: =H16*I16 -> 0 | K16: =G16+J16 -> 0 | M16: =M15+K16-L16 -> 265203.4
A17: 14 | B17: 46309 | G17: =E17*F17 -> 0 | J17: =H17*I17 -> 0 | K17: =G17+J17 -> 0 | M17: =M16+K17-L17 -> 265203.4
A18: 15 | B18: 46310 | E18: 150 | F18: 105.4 | G18: =E18*F18 -> 15810 | J18: =H18*I18 -> 0 | K18: =G18+J18 -> 15810 | M18: =M17+K18-L18 -> 281013.4
A19: 16 | B19: 46311 | G19: =E19*F19 -> 0 | J19: =H19*I19 -> 0 | K19: =G19+J19 -> 0 | M19: =M18+K19-L19 -> 281013.4
A20: 17 | B20: 46312 | G20: =E20*F20 -> 0 | J20: =H20*I20 -> 0 | K20: =G20+J20 -> 0 | M20: =M19+K20-L20 -> 281013.4
A21: 18 | B21: 46313 | G21: =E21*F21 -> 0 | J21: =H21*I21 -> 0 | K21: =G21+J21 -> 0 | M21: =M20+K21-L21 -> 281013.4
A22: 19 | B22: 46314 | G22: =E22*F22 -> 0 | J22: =H22*I22 -> 0 | K22: =G22+J22 -> 0 | M22: =M21+K22-L22 -> 281013.4
A23: 20 | B23: 46315 | G23: =E23*F23 -> 0 | J23: =H23*I23 -> 0 | K23: =G23+J23 -> 0 | M23: =M22+K23-L23 -> 281013.4
A24: 21 | B24: 46316 | G24: =E24*F24 -> 0 | J24: =H24*I24 -> 0 | K24: =G24+J24 -> 0 | M24: =M23+K24-L24 -> 281013.4
A25: 22 | B25: 46317 | G25: =E25*F25 -> 0 | J25: =H25*I25 -> 0 | K25: =G25+J25 -> 0 | M25: =M24+K25-L25 -> 281013.4
A26: 23 | B26: 46318 | G26: =E26*F26 -> 0 | J26: =H26*I26 -> 0 | K26: =G26+J26 -> 0 | M26: =M25+K26-L26 -> 281013.4
A27: 24 | B27: 46319 | G27: =E27*F27 -> 0 | J27: =H27*I27 -> 0 | K27: =G27+J27 -> 0 | M27: =M26+K27-L27 -> 281013.4
A28: 25 | B28: 46320 | G28: =E28*F28 -> 0 | J28: =H28*I28 -> 0 | K28: =G28+J28 -> 0 | M28: =M27+K28-L28 -> 281013.4
A29: 26 | B29: 46321 | G29: =E29*F29 -> 0 | J29: =H29*I29 -> 0 | K29: =G29+J29 -> 0 | M29: =M28+K29-L29 -> 281013.4
A30: 27 | B30: 46322 | G30: =E30*F30 -> 0 | J30: =H30*I30 -> 0 | K30: =G30+J30 -> 0 | M30: =M29+K30-L30 -> 281013.4
... A34: 31 | B34: 46326 | G34: =E34*F34 -> 0 | J34: =H34*I34 -> 0 | K34: =G34+J34 -> 0 | M34: =M33+K34-L34 -> 281013.4
A35: 32 | G35: =E35*F35 -> 0 | J35: =H35*I35 -> 0 | K35: =G35+J35 -> 0 | M35: =M34+K35-L35 -> 281013.4
A36: 33 | G36: =E36*F36 -> 0 | J36: =H36*I36 -> 0 | K36: =G36+J36 -> 0 | M36: =M35+K36-L36 -> 281013.4
E37: =SUM(E4:E36) -> 2252.17 | G37: =SUM(G4:G36) -> 237378.72 | H37: =SUM(H4:H36) -> 40.2 | J37: =SUM(J4:J36) -> 4733.148 | K37: =SUM(K4:K36) -> 242111.87 | L37: =SUM(L4:L36) -> 200000

Sheet Sri Venkateshwara Services
A1: Sri Venkateshwara Services
A2: S.No | B2: Date | C2: GRN No | D2: Ind no/Bill No | E2: Diesel (Lts) | F2: Price | G2: Amount | H2: Petrol (Lts) | I2: Price | J2: Amount | K2: Total amount | L2: Amount paid | M2: As on Date | N2: Remarks
A3: Opening Balance | M3: 115419.84
A4: 1 | B4: 46296 | E4: 335 | F4: 104.68 | G4: =E4*F4 -> 35067.8 | H4: 65 | I4: 116.96 | J4: =H4*I4 -> 7602.4 | K4: =G4+J4 -> 42670.2 | M4: =M3+K4-L4 -> 158090.04
A5: 2 | B5: 46297 | G5: =E5*F5 -> 0 | H5: 5 | I5: 116.96 | J5: =H5*I5 -> 584.8 | K5: =G5+J5 -> 584.8 | M5: =M4+K5-L5 -> 158674.84
A6: 3 | B6: 46298 | E6: 200 | F6: 104.68 | G6: =E6*F6 -> 20936 | J6: =H6*I6 -> 0 | K6: =G6+J6 -> 20936 | L6: 80000 | M6: =M5+K6-L6 -> 99610.838
A7: 4 | B7: 46299 | E7: 40 | F7: 104.68 | G7: =E7*F7 -> 4187.2 | J7: =H7*I7 -> 0 | K7: =G7+J7 -> 4187.2 | M7: =M6+K7-L7 -> 103798.04
A8: 5 | B8: 46300 | E8: 200 | F8: 104.68 | G8: =E8*F8 -> 20936 | H8: 5 | I8: 116.96 | J8: =H8*I8 -> 584.8 | K8: =G8+J8 -> 21520.8 | M8: =M7+K8-L8 -> 125318.84
A9: 6 | B9: 46301 | E9: 100 | F9: 104.68 | G9: =E9*F9 -> 10468 | H9: 60 | I9: 116.96 | J9: =H9*I9 -> 7017.6 | K9: =G9+J9 -> 17485.6 | M9: =M8+K9-L9 -> 142804.44
A10: 7 | B10: 46302 | E10: 230 | F10: 104.68 | G10: =E10*F10 -> 24076.4 | H10: 80 | I10: 116.96 | J10: =H10*I10 -> 9356.8 | K10: =G10+J10 -> 33433.2 | M10: =M9+K10-L10 -> 176237.64
A11: 8 | B11: 46303 | E11: 21 | F11: 104.68 | G11: =E11*F11 -> 2198.28 | J11: =H11*I11 -> 0 | K11: =G11+J11 -> 2198.28 | M11: =M10+K11-L11 -> 178435.92
A12: 9 | B12: 46304 | J12: =H12*I12 -> 0 | K12: =G12+J12 -> 0 | M12: =M11+K12-L12 -> 178435.92
A13: 10 | B13: 46305 | E13: 732.87 | F13: 104.68 | G13: =E13*F13 -> 76716.832 | H13: 61 | I13: 116.96 | J13: =H13*I13 -> 7134.56 | K13: =G13+J13 -> 83851.392 | L13: 178000 | M13: =M12+K13-L13 -> 84287.31
A14: 11 | B14: 46306 | G14: =E14*F14 -> 0 | J14: =H14*I14 -> 0 | K14: =G14+J14 -> 0 | M14: =M13+K14-L14 -> 84287.31
A15: 12 | B15: 46307 | E15: 40 | F15: 104.68 | G15: =E15*F15 -> 4187.2 | J15: =H15*I15 -> 0 | K15: =G15+J15 -> 4187.2 | M15: =M14+K15-L15 -> 88474.51
A16: 13 | B16: 46308 | E16: 47 | F16: 104.68 | G16: =E16*F16 -> 4919.96 | H16: 20 | I16: 116.96 | J16: =H16*I16 -> 2339.2 | K16: =G16+J16 -> 7259.16 | M16: =M15+K16-L16 -> 95733.67
A17: 14 | B17: 46309 | E17: 328.5 | F17: 104.68 | G17: =E17*F17 -> 34387.38 | H17: 95 | I17: 116.96 | J17: =H17*I17 -> 11111.2 | K17: =G17+J17 -> 45498.58 | M17: =M16+K17-L17 -> 141232.25
A18: 15 | B18: 46310 | G18: =E18*F18 -> 0 | H18: 35 | I18: 116.96 | J18: =H18*I18 -> 4093.6 | K18: =G18+J18 -> 4093.6 | L18: 80000 | M18: =M17+K18-L18 -> 65325.85
A19: 16 | B19: 46311 | G19: =E19*F19 -> 0 | J19: =H19*I19 -> 0 | K19: =G19+J19 -> 0 | M19: =M18+K19-L19 -> 65325.85
A20: 17 | B20: 46312 | G20: =E20*F20 -> 0 | J20: =H20*I20 -> 0 | K20: =G20+J20 -> 0 | M20: =M19+K20-L20 -> 65325.85
A21: 18 | B21: 46313 | G21: =E21*F21 -> 0 | J21: =H21*I21 -> 0 | K21: =G21+J21 -> 0 | M21: =M20+K21-L21 -> 65325.85
A22: 19 | B22: 46314 | G22: =E22*F22 -> 0 | J22: =H22*I22 -> 0 | K22: =G22+J22 -> 0 | M22: =M21+K22-L22 -> 65325.85
A23: 20 | B23: 46315 | G23: =E23*F23 -> 0 | J23: =H23*I23 -> 0 | K23: =G23+J23 -> 0 | M23: =M22+K23-L23 -> 65325.85
A24: 21 | B24: 46316 | G24: =E24*F24 -> 0 | J24: =H24*I24 -> 0 | K24: =G24+J24 -> 0 | M24: =M23+K24-L24 -> 65325.85
A25: 22 | B25: 46317 | G25: =E25*F25 -> 0 | J25: =H25*I25 -> 0 | K25: =G25+J25 -> 0 | M25: =M24+K25-L25 -> 65325.85
A26: 23 | B26: 46318 | G26: =E26*F26 -> 0 | J26: =H26*I26 -> 0 | K26: =G26+J26 -> 0 | M26: =M25+K26-L26 -> 65325.85
A27: 24 | B27: 46319 | G27: =E27*F27 -> 0 | J27: =H27*I27 -> 0 | K27: =G27+J27 -> 0 | M27: =M26+K27-L27 -> 65325.85
A28: 25 | B28: 46320 | G28: =E28*F28 -> 0 | J28: =H28*I28 -> 0 | K28: =G28+J28 -> 0 | M28: =M27+K28-L28 -> 65325.85
A29: 26 | B29: 46321 | G29: =E29*F29 -> 0 | J29: =H29*I29 -> 0 | K29: =G29+J29 -> 0 | M29: =M28+K29-L29 -> 65325.85
A30: 27 | B30: 46322 | G30: =E30*F30 -> 0 | J30: =H30*I30 -> 0 | K30: =G30+J30 -> 0 | M30: =M29+K30-L30 -> 65325.85
... A34: 31 | B34: 46326 | G34: =E34*F34 -> 0 | J34: =H34*I34 -> 0 | K34: =G34+J34 -> 0 | M34: =M33+K34-L34 -> 65325.85
A35: 32 | G35: =E35*F35 -> 0 | J35: =H35*I35 -> 0 | K35: =G35+J35 -> 0 | M35: =M34+K35-L35 -> 65325.85
A36: 33 | G36: =E36*F36 -> 0 | J36: =H36*I36 -> 0 | K36: =G36+J36 -> 0 | M36: =M35+K36-L36 -> 65325.85
E37: =SUM(E4:E36) -> 2274.37 | G37: =SUM(G4:G36) -> 238081.05 | H37: =SUM(H4:H36) -> 426 | J37: =SUM(J4:J36) -> 49824.96 | K37: =SUM(K4:K36) -> 287906.01 | L37: =SUM(L4:L36) -> 338000

Sheet Raja Filling Station
A1: Raja Filling Station
A2: S.No | B2: Date | C2: GRN No | D2: Ind No/Bill No | E2: Diesel (Lts) | F2: Price | G2: Amount | H2: Petrol (Lts) | I2: Price | J2: Amount | K2: Total amount | L2: Amount paid | M2: As on Date | N2: Remarks
A3: Opening Balance | M3: 14216.93
A4: 1 | B4: 45931 | E4: 30 | F4: 105.59 | G4: =E4*F4 -> 3167.7 | H4: 9 | I4: 117.98 | J4: =H4*I4 -> 1061.82 | K4: =G4+J4 -> 4229.52 | M4: =M3+K4-L4 -> 18446.45
A5: 2 | B5: 45932 | G5: =E5*F5 -> 0 | J5: =H5*I5 -> 0 | K5: =G5+J5 -> 0 | M5: =M4+K5-L5 -> 18446.45
A6: 3 | B6: 45933 | G6: =E6*F6 -> 0 | H6: 4 | I6: 117.98 | J6: =H6*I6 -> 471.92 | K6: =G6+J6 -> 471.92 | M6: =M5+K6-L6 -> 18918.37
A7: 4 | B7: 45934 | E7: 80 | F7: 105.59 | G7: =E7*F7 -> 8447.2 | H7: 4 | I7: 117.98 | J7: =H7*I7 -> 471.92 | K7: =G7+J7 -> 8919.12 | M7: =M6+K7-L7 -> 27837.49
A8: 5 | B8: 45935 | E8: 430 | F8: 105.59 | G8: =E8*F8 -> 45403.7 | H8: 59 | I8: 117.98 | J8: =H8*I8 -> 6960.82 | K8: =G8+J8 -> 52364.52 | M8: =M7+K8-L8 -> 80202.01
A9: 6 | B9: 45936 | E9: 460 | F9: 105.59 | G9: =E9*F9 -> 48571.4 | H9: 40 | I9: 117.98 | J9: =H9*I9 -> 4719.2 | K9: =G9+J9 -> 53290.6 | M9: =M8+K9-L9 -> 133492.61
A10: 7 | B10: 45937 | E10: 400 | F10: 105.59 | G10: =E10*F10 -> 42236 | H10: 65 | I10: 117.98 | J10: =H10*I10 -> 7668.7 | K10: =G10+J10 -> 49904.7 | M10: =M9+K10-L10 -> 183397.31
A11: 8 | B11: 45938 | E11: 45.41 | F11: 105.59 | G11: =E11*F11 -> 4794.8419 | J11: =H11*I11 -> 0 | K11: =G11+J11 -> 4794.8419 | M11: =M10+K11-L11 -> 188192.15
A12: 9 | B12: 45939 | E12: 680 | F12: 105.59 | G12: =E12*F12 -> 71801.2 | H12: 30 | I12: 117.98 | J12: =H12*I12 -> 3539.4 | K12: =G12+J12 -> 75340.6 | M12: =M11+K12-L12 -> 263532.75
A13: 10 | B13: 45940 | G13: =E13*F13 -> 0 | J13: =H13*I13 -> 0 | K13: =G13+J13 -> 0 | M13: =M12+K13-L13 -> 263532.75
A14: 11 | B14: 45941 | G14: =E14*F14 -> 0 | J14: =H14*I14 -> 0 | K14: =G14+J14 -> 0 | M14: =M13+K14-L14 -> 263532.75
A15: 12 | B15: 45942 | E15: 30 | F15: 105.59 | G15: =E15*F15 -> 3167.7 | H15: 4 | I15: 117.98 | J15: =H15*I15 -> 471.92 | K15: =G15+J15 -> 3639.62 | M15: =M14+K15-L15 -> 267172.37
A16: 13 | B16: 45943 | E16: 430 | F16: 105.59 | G16: =E16*F16 -> 45403.7 | H16: 20 | I16: 117.98 | J16: =H16*I16 -> 2359.6 | K16: =G16+J16 -> 47763.3 | M16: =M15+K16-L16 -> 314935.67
A17: 14 | B17: 45944 | E17: 200 | F17: 105.59 | G17: =E17*F17 -> 21118 | H17: 39 | I17: 117.98 | J17: =H17*I17 -> 4601.22 | K17: =G17+J17 -> 25719.22 | M17: =M16+K17-L17 -> 340654.89
A18: 15 | B18: 45945 | E18: 40 | F18: 105.59 | G18: =E18*F18 -> 4223.6 | H18: 14 | I18: 117.98 | J18: =H18*I18 -> 1651.72 | K18: =G18+J18 -> 5875.32 | L18: 241000 | M18: =M17+K18-L18 -> 105530.21
A19: 16 | B19: 45946 | G19: =E19*F19 -> 0 | J19: =H19*I19 -> 0 | K19: =G19+J19 -> 0 | M19: =M18+K19-L19 -> 105530.21
A20: 17 | B20: 45947 | G20: =E20*F20 -> 0 | J20: =H20*I20 -> 0 | K20: =G20+J20 -> 0 | M20: =M19+K20-L20 -> 105530.21
A21: 18 | B21: 45948 | G21: =E21*F21 -> 0 | J21: =H21*I21 -> 0 | K21: =G21+J21 -> 0 | M21: =M20+K21-L21 -> 105530.21
A22: 19 | B22: 45949 | H22: 0 | I22: 0 | J22: =H22*I22 -> 0 | K22: =G22+J22 -> 0 | M22: =M21+K22-L22 -> 105530.21
A23: 20 | B23: 45950 | H23: 0 | I23: 0 | J23: =H23*I23 -> 0 | K23: =G23+J23 -> 0 | M23: =M22+K23-L23 -> 105530.21
A24: 21 | B24: 45951 | J24: =H24*I24 -> 0 | K24: =G24+J24 -> 0 | M24: =M23+K24-L24 -> 105530.21
A25: 22 | B25: 45952 | J25: =H25*I25 -> 0 | K25: =G25+J25 -> 0 | M25: =M24+K25-L25 -> 105530.21
A26: 23 | B26: 45953 | J26: =H26*I26 -> 0 | K26: =G26+J26 -> 0 | M26: =M25+K26-L26 -> 105530.21
A27: 24 | B27: 45954 | J27: =H27*I27 -> 0 | K27: =G27+J27 -> 0 | M27: =M26+K27-L27 -> 105530.21
A28: 25 | B28: 45955 | J28: =H28*I28 -> 0 | K28: =G28+J28 -> 0 | M28: =M27+K28-L28 -> 105530.21
A29: 26 | B29: 45956 | J29: =H29*I29 -> 0 | K29: =G29+J29 -> 0 | M29: =M28+K29-L29 -> 105530.21
A30: 27 | B30: 45957 | J30: =H30*I30 -> 0 | K30: =G30+J30 -> 0 | M30: =M29+K30-L30 -> 105530.21
A31: 28 | B31: 45958 | J31: =H31*I31 -> 0 | K31: =G31+J31 -> 0 | M31: =M30+K31-L31 -> 105530.21
A32: 29 | B32: 45959 | G32: =E32*F32 -> 0 | J32: =H32*I32 -> 0 | K32: =G32+J32 -> 0 | M32: =M31+K32-L32 -> 105530.21
A33: 30 | B33: 45960 | G33: =E33*F33 -> 0 | J33: =H33*I33 -> 0 | K33: =G33+J33 -> 0 | M33: =M32+K33-L33 -> 105530.21
A34: 31 | F34: 0 | G34: =E34*F34 -> 0 | J34: =H34*I34 -> 0 | K34: =G34+J34 -> 0
E35: =SUM(E4:E34) -> 2825.41 | G35: =SUM(G4:G34) -> 298335.04 | H35: =SUM(H4:H34) -> 288 | J35: =SUM(J4:J34) -> 33978.24 | K35: =SUM(K4:K34) -> 332313.28 | L35: =SUM(L4:L31) -> 241000

Sheet Madana palli
A2: S.No | B2: Date | C2: GRN No | D2: Ind no/Bill No | E2: Diesel (Lts) | F2: Price | G2: Amount | H2: Petrol (Lts) | I2: Price | J2: Amount | K2: Total amount | L2: Amount paid | M2: As on Date | N2: Remarks
A3: Opening Balance | M3: 0
A4: 1 | B4: 46296 | G4: =E4*F4 -> 0 | J4: =H4*I4 -> 0 | K4: =G4+J4 -> 0 | L4: =+K4 -> 0 | M4: 0
B5: 46297 | J5: =H5*I5 -> 0 | K5: =G5+J5 -> 0 | L5: =+K5 -> 0
A6: 2 | B6: 46298 | G6: =E6*F6 -> 0 | J6: =H6*I6 -> 0 | K6: =G6+J6 -> 0 | L6: =+K6 -> 0 | M6: 0
A7: 3 | B7: 46299 | G7: =E7*F7 -> 0 | J7: =H7*I7 -> 0 | K7: =G7+J7 -> 0 | L7: =+K7 -> 0 | M7: 0
A8: 4 | B8: 46300 | G8: =E8*F8 -> 0 | J8: =H8*I8 -> 0 | K8: =G8+J8 -> 0 | L8: =+K8 -> 0 | M8: 0
A9: 5 | B9: 46301 | G9: =E9*F9 -> 0 | J9: =H9*I9 -> 0 | K9: =G9+J9 -> 0 | L9: =+K9 -> 0 | M9: 0
A10: 6 | B10: 46302 | G10: =E10*F10 -> 0 | J10: =H10*I10 -> 0 | K10: =G10+J10 -> 0 | L10: =+K10 -> 0 | M10: 0
A11: 7 | B11: 46303 | G11: =E11*F11 -> 0 | J11: =H11*I11 -> 0 | K11: =G11+J11 -> 0 | L11: =+K11 -> 0 | M11: 0
A12: 8 | B12: 46304 | G12: =E12*F12 -> 0 | J12: =H12*I12 -> 0 | K12: =G12+J12 -> 0 | L12: =+K12 -> 0 | M12: 0
A13: 9 | B13: 46305 | G13: =E13*F13 -> 0 | J13: =H13*I13 -> 0 | K13: =G13+J13 -> 0 | L13: =+K13 -> 0 | M13: 0
A14: 10 | B14: 46306 | G14: =E14*F14 -> 0 | J14: =H14*I14 -> 0 | K14: =G14+J14 -> 0 | L14: =+K14 -> 0 | M14: 0
A15: 11 | B15: 46307 | G15: =E15*F15 -> 0 | J15: =H15*I15 -> 0 | K15: =G15+J15 -> 0 | L15: =+K15 -> 0 | M15: 0
A16: 12 | B16: 46308 | G16: =E16*F16 -> 0 | J16: =H16*I16 -> 0 | K16: =G16+J16 -> 0 | L16: =+K16 -> 0 | M16: 0
A17: 13 | B17: 46309 | G17: =E17*F17 -> 0 | J17: =H17*I17 -> 0 | K17: =G17+J17 -> 0 | L17: =+K17 -> 0 | M17: 0
... A29: 25 | B29: 46321 | G29: =E29*F29 -> 0 | J29: =H29*I29 -> 0 | K29: =G29+J29 -> 0 | L29: =+K29 -> 0 | M29: 0
B30: 46322 | J30: =H30*I30 -> 0 | K30: =G30+J30 -> 0 | L30: =+K30 -> 0
A31: 26 | B31: 46323 | G31: =E31*F31 -> 0 | J31: =H31*I31 -> 0 | K31: =G31+J31 -> 0 | L31: =+K31 -> 0 | M31: 0
A32: 27 | B32: 46324 | G32: =E32*F32 -> 0 | J32: =H32*I32 -> 0 | K32: =G32+J32 -> 0 | L32: =+K32 -> 0 | M32: 0
A33: 28 | B33: 46325 | G33: =E33*F33 -> 0 | J33: =H33*I33 -> 0 | K33: =G33+J33 -> 0 | L33: =+K33 -> 0 | M33: 0
A34: 29 | B34: 46326 | G34: =E34*F34 -> 0 | J34: =H34*I34 -> 0 | K34: =G34+J34 -> 0 | L34: =+K34 -> 0 | M34: 0
A35: 30 | G35: =E35*F35 -> 0 | J35: =H35*I35 -> 0 | K35: =G35+J35 -> 0 | L35: =+K35 -> 0 | M35: 0
A36: 31 | G36: =E36*F36 -> 0 | J36: =H36*I36 -> 0 | K36: =G36+J36 -> 0 | L36: =+K36 -> 0 | M36: 0
E37: =SUM(E4:E36) -> 0 | G37: =SUM(G4:G36) -> 0 | H37: =SUM(H4:H36) -> 0 | J37: =SUM(J4:J36) -> 0 | K37: =SUM(K4:K36) -> 0 | L37: =SUM(L4:L36) -> 0

Sheet Kadur
A1: Vishal Service Station
A2: S.No | B2: Date | C2: GRN No | D2: Ind No/Bill No | E2: Diesel (Lts) | F2: Price | G2: Amount | H2: Petrol (Lts) | I2: Price | J2: Amount | K2: Total amount | L2: Amount paid | M2: As on Date | N2: Remarks
A3: Opening Balance | K3: 175658 | M3: 175658
A4: 1 | B4: 46296 | G4: =E4*F4 -> 0 | J4: =H4*I4 -> 0 | K4: =G4+J4 -> 0 | M4: =M3+K4-L4 -> 175658
A5: 2 | B5: 46297 | G5: =E5*F5 -> 0 | J5: =H5*I5 -> 0 | K5: =G5+J5 -> 0 | M5: =M4+K5-L5 -> 175658
A6: 3 | B6: 46298 | G6: =E6*F6 -> 0 | J6: =H6*I6 -> 0 | K6: =G6+J6 -> 0 | M6: =M5+K6-L6 -> 175658
A7: 4 | B7: 46299 | G7: =E7*F7 -> 0 | J7: =H7*I7 -> 0 | K7: =G7+J7 -> 0 | M7: =M6+K7-L7 -> 175658
A8: 5 | B8: 46300 | G8: =E8*F8 -> 0 | J8: =H8*I8 -> 0 | K8: =G8+J8 -> 0 | M8: =M7+K8-L8 -> 175658
A9: 6 | B9: 46301 | G9: =E9*F9 -> 0 | J9: =H9*I9 -> 0 | K9: =G9+J9 -> 0 | M9: =M8+K9-L9 -> 175658
A10: 7 | B10: 46302 | G10: =E10*F10 -> 0 | J10: =H10*I10 -> 0 | K10: =G10+J10 -> 0 | M10: =M9+K10-L10 -> 175658
A11: 8 | B11: 46303 | G11: =E11*F11 -> 0 | J11: =H11*I11 -> 0 | K11: =G11+J11 -> 0 | M11: =M10+K11-L11 -> 175658
A12: 9 | B12: 46304 | G12: =E12*F12 -> 0 | J12: =H12*I12 -> 0 | K12: =G12+J12 -> 0 | M12: =M11+K12-L12 -> 175658
A13: 10 | B13: 46305 | G13: =E13*F13 -> 0 | J13: =H13*I13 -> 0 | K13: =G13+J13 -> 0 | L13: 100000 | M13: =M12+K13-L13 -> 75658
A14: 11 | B14: 46306 | G14: =E14*F14 -> 0 | J14: =H14*I14 -> 0 | K14: =G14+J14 -> 0 | M14: =M13+K14-L14 -> 75658
A15: 12 | B15: 46307 | G15: =E15*F15 -> 0 | J15: =H15*I15 -> 0 | K15: =G15+J15 -> 0 | M15: =M14+K15-L15 -> 75658
A16: 13 | B16: 46308 | G16: =E16*F16 -> 0 | J16: =H16*I16 -> 0 | K16: =G16+J16 -> 0 | M16: =M15+K16-L16 -> 75658
A17: 14 | B17: 46309 | G17: =E17*F17 -> 0 | J17: =H17*I17 -> 0 | K17: =G17+J17 -> 0 | M17: =M16+K17-L17 -> 75658
A18: 15 | B18: 46310 | G18: =E18*F18 -> 0 | J18: =H18*I18 -> 0 | K18: =G18+J18 -> 0 | M18: =M17+K18-L18 -> 75658
A19: 16 | B19: 46311 | G19: =E19*F19 -> 0 | J19: =H19*I19 -> 0 | K19: =G19+J19 -> 0 | M19: =M18+K19-L19 -> 75658
A20: 17 | B20: 46312 | G20: =E20*F20 -> 0 | J20: =H20*I20 -> 0 | K20: =G20+J20 -> 0 | M20: =M19+K20-L20 -> 75658
A21: 18 | B21: 46313 | G21: =E21*F21 -> 0 | J21: =H21*I21 -> 0 | K21: =G21+J21 -> 0 | M21: =M20+K21-L21 -> 75658
A22: 19 | B22: 46314 | H22: 0 | I22: 0 | J22: =H22*I22 -> 0 | K22: =G22+J22 -> 0 | M22: =M21+K22-L22 -> 75658
A23: 20 | B23: 46315 | H23: 0 | I23: 0 | J23: =H23*I23 -> 0 | K23: =G23+J23 -> 0 | M23: =M22+K23-L23 -> 75658
A24: 21 | B24: 46316 | J24: =H24*I24 -> 0 | K24: =G24+J24 -> 0 | M24: =M23+K24-L24 -> 75658
A25: 22 | B25: 46317 | J25: =H25*I25 -> 0 | K25: =G25+J25 -> 0 | M25: =M24+K25-L25 -> 75658
A26: 23 | B26: 46318 | J26: =H26*I26 -> 0 | K26: =G26+J26 -> 0 | M26: =M25+K26-L26 -> 75658
A27: 24 | B27: 46319 | J27: =H27*I27 -> 0 | K27: =G27+J27 -> 0 | M27: =M26+K27-L27 -> 75658
A28: 25 | B28: 46320 | J28: =H28*I28 -> 0 | K28: =G28+J28 -> 0 | M28: =M27+K28-L28 -> 75658
A29: 26 | B29: 46321 | J29: =H29*I29 -> 0 | K29: =G29+J29 -> 0 | M29: =M28+K29-L29 -> 75658
A30: 27 | B30: 46322 | J30: =H30*I30 -> 0 | K30: =G30+J30 -> 0 | M30: =M29+K30-L30 -> 75658
A31: 28 | B31: 46323 | J31: =H31*I31 -> 0 | K31: =G31+J31 -> 0 | M31: =M30+K31-L31 -> 75658
A32: 29 | B32: 46324 | G32: =E32*F32 -> 0 | H32: 0 | I32: 0 | J32: =H32*I32 -> 0 | K32: =G32+J32 -> 0 | M32: =M31+K32-L32 -> 75658
A33: 30 | B33: 46325 | F33: 0 | G33: =E33*F33 -> 0 | H33: 0 | I33: 0 | J33: =H33*I33 -> 0 | K33: =G33+J33 -> 0 | M33: =M32+K33-L33 -> 75658
A34: 31 | B34: 46326 | F34: 0 | G34: =E34*F34 -> 0 | J34: =H34*I34 -> 0 | K34: =G34+J34 -> 0
E35: =SUM(E4:E34) -> 0 | G35: =SUM(G4:G34) -> 0 | H35: =SUM(H4:H34) -> 0 | J35: =SUM(J4:J34) -> 0 | K35: =SUM(K4:K34) -> 0 | L35: =SUM(L4:L31) -> 100000

Sheet YG Gudda
A1: Pankaja HP Fuel Center
A2: S.No | B2: Date | C2: GRN No | D2: Ind No/Bill No | E2: Diesel (Lts) | F2: Price | G2: Amount | H2: Petrol (Lts) | I2: Price | J2: Amount | K2: Total amount | L2: Amount paid | M2: As on Date | N2: Remarks
A3: Opening Balance | M3: 305951.76
A4: 1 | B4: 46296 | G4: =E4*F4 -> 0 | J4: =H4*I4 -> 0 | K4: =G4+J4 -> 0 | M4: =M3+K4-L4 -> 305951.76
B5: 46297 | G5: =E5*F5 -> 0 | K5: =G5+J5 -> 0 | M5: =M4+K5-L5 -> 305951.76
A6: 2 | B6: 46298 | E6: 1000 | F6: 99.14 | G6: =E6*F6 -> 99140 | H6: 70 | I6: 111.24 | J6: =H6*I6 -> 7786.8 | K6: =G6+J6 -> 106926.8 | M6: =M5+K6-L6 -> 412878.56
A7: 3 | B7: 46299 | G7: =E7*F7 -> 0 | J7: =H7*I7 -> 0 | K7: =G7+J7 -> 0 | M7: =M6+K7-L7 -> 412878.56
A8: 4 | B8: 46300 | G8: =E8*F8 -> 0 | J8: =H8*I8 -> 0 | K8: =G8+J8 -> 0 | M8: =M7+K8-L8 -> 412878.56
A9: 5 | B9: 46301 | E9: 1200 | F9: 99.14 | G9: =E9*F9 -> 118968 | J9: =H9*I9 -> 0 | K9: =G9+J9 -> 118968 | M9: =M8+K9-L9 -> 531846.56
A10: 6 | B10: 46302 | G10: =E10*F10 -> 0 | J10: =H10*I10 -> 0 | K10: =G10+J10 -> 0 | M10: =M9+K10-L10 -> 531846.56
A11: 7 | B11: 46303 | G11: =E11*F11 -> 0 | J11: =H11*I11 -> 0 | K11: =G11+J11 -> 0 | L11: 200000 | M11: =M10+K11-L11 -> 331846.56
A12: 8 | B12: 46304 | G12: =E12*F12 -> 0 | J12: =H12*I12 -> 0 | K12: =G12+J12 -> 0 | M12: =M11+K12-L12 -> 331846.56
A13: 9 | B13: 46305 | E13: 1200 | F13: 99.14 | G13: =E13*F13 -> 118968 | H13: 105 | I13: 111.24 | J13: =H13*I13 -> 11680.2 | K13: =G13+J13 -> 130648.2 | L13: 150000 | M13: =M12+K13-L13 -> 312494.76
A14: 10 | B14: 46306 | G14: =E14*F14 -> 0 | J14: =H14*I14 -> 0 | K14: =G14+J14 -> 0 | M14: =M13+K14-L14 -> 312494.76
A15: 11 | B15: 46307 | G15: =E15*F15 -> 0 | J15: =H15*I15 -> 0 | K15: =G15+J15 -> 0 | M15: =M14+K15-L15 -> 312494.76
A16: 12 | B16: 46308 | G16: =E16*F16 -> 0 | J16: =H16*I16 -> 0 | K16: =G16+J16 -> 0 | M16: =M15+K16-L16 -> 312494.76
A17: 13 | B17: 46309 | E17: 1200 | F17: 99.14 | G17: =E17*F17 -> 118968 | H17: 35 | I17: 111.24 | J17: =H17*I17 -> 3893.4 | K17: =G17+J17 -> 122861.4 | M17: =M16+K17-L17 -> 435356.16
A18: 14 | B18: 46310 | G18: =E18*F18 -> 0 | J18: =H18*I18 -> 0 | K18: =G18+J18 -> 0 | L18: 250000 | M18: =M17+K18-L18 -> 185356.16
A19: 15 | B19: 46311 | G19: =E19*F19 -> 0 | J19: =H19*I19 -> 0 | K19: =G19+J19 -> 0 | M19: =M18+K19-L19 -> 185356.16
A20: 16 | B20: 46312 | G20: =E20*F20 -> 0 | J20: =H20*I20 -> 0 | K20: =G20+J20 -> 0 | M20: =M19+K20-L20 -> 185356.16
A21: 17 | B21: 46313 | G21: =E21*F21 -> 0 | J21: =H21*I21 -> 0 | K21: =G21+J21 -> 0 | M21: =M20+K21-L21 -> 185356.16
A22: 18 | B22: 46314 | G22: =E22*F22 -> 0 | J22: =H22*I22 -> 0 | K22: =G22+J22 -> 0 | M22: =M21+K22-L22 -> 185356.16
A23: 19 | B23: 46315 | G23: =E23*F23 -> 0 | J23: =H23*I23 -> 0 | K23: =G23+J23 -> 0 | M23: =M22+K23-L23 -> 185356.16
A24: 20 | B24: 46316 | G24: =E24*F24 -> 0 | J24: =H24*I24 -> 0 | K24: =G24+J24 -> 0 | M24: =M23+K24-L24 -> 185356.16
A25: 21 | B25: 46317 | G25: =E25*F25 -> 0 | J25: =H25*I25 -> 0 | K25: =G25+J25 -> 0 | M25: =M24+K25-L25 -> 185356.16
A26: 22 | B26: 46318 | G26: =E26*F26 -> 0 | J26: =H26*I26 -> 0 | K26: =G26+J26 -> 0 | M26: =M25+K26-L26 -> 185356.16
A27: 23 | B27: 46319 | G27: =E27*F27 -> 0 | J27: =H27*I27 -> 0 | K27: =G27+J27 -> 0 | M27: =M26+K27-L27 -> 185356.16
A28: 24 | B28: 46320 | G28: =E28*F28 -> 0 | J28: =H28*I28 -> 0 | K28: =G28+J28 -> 0 | M28: =M27+K28-L28 -> 185356.16
A29: 25 | B29: 46321 | G29: =E29*F29 -> 0 | J29: =H29*I29 -> 0 | K29: =G29+J29 -> 0 | M29: =M28+K29-L29 -> 185356.16
A30: 26 | B30: 46322 | G30: =E30*F30 -> 0 | J30: =H30*I30 -> 0 | K30: =G30+J30 -> 0 | M30: =M29+K30-L30 -> 185356.16
... A34: 30 | B34: 46326 | G34: =E34*F34 -> 0 | J34: =H34*I34 -> 0 | K34: =G34+J34 -> 0 | M34: =M33+K34-L34 -> 185356.16
A35: 31 | G35: =E35*F35 -> 0 | J35: =H35*I35 -> 0 | K35: =G35+J35 -> 0 | M35: =M34+K35-L35 -> 185356.16
A36: 32 | G36: =E36*F36 -> 0 | J36: =H36*I36 -> 0 | K36: =G36+J36 -> 0 | M36: =M35+K36-L36 -> 185356.16
A37: 33 | G37: =E37*F37 -> 0 | J37: =H37*I37 -> 0 | K37: =G37+J37 -> 0 | M37: =M36+K37-L37 -> 185356.16
A38: 34 | G38: =E38*F38 -> 0 | J38: =H38*I38 -> 0 | K38: =G38+J38 -> 0 | M38: =M37+K38-L38 -> 185356.16
E39: =SUM(E4:E38) -> 4600 | G39: =SUM(G4:G38) -> 456044 | H39: =SUM(H4:H38) -> 210 | J39: =SUM(J4:J38) -> 23360.4 | K39: =SUM(K4:K38) -> 479404.4 | L39: =SUM(L4:L38) -> 600000

Sheet  YG Gudda-2
A1: One Stop
A2: S.No | B2: Date | C2: GRN No | D2: Ind No/Bill No | E2: Diesel (Lts) | F2: Price | G2: Amount | H2: Petrol (Lts) | I2: Price | J2: Amount | K2: Total amount | L2: Amount paid | M2: As on Date | N2: Remarks
A3: Opening Balance | K3: 255923.32 | M3: 255923.32
A4: 1 | B4: 46296 | G4: =E4*F4 -> 0 | J4: =H4*I4 -> 0 | K4: =G4+J4 -> 0 | M4: =M3+K4-L4 -> 255923.32
B5: 46297 | G5: =E5*F5 -> 0 | J5: =H5*I5 -> 0 | K5: =G5+J5 -> 0 | M5: =M4+K5-L5 -> 255923.32
A6: 2 | B6: 46298 | G6: =E6*F6 -> 0 | J6: =H6*I6 -> 0 | K6: =G6+J6 -> 0 | M6: =M4+K6-L6 -> 255923.32
A7: 3 | B7: 46299 | G7: =E7*F7 -> 0 | J7: =H7*I7 -> 0 | K7: =G7+J7 -> 0 | M7: =M6+K7-L7 -> 255923.32
A8: 4 | B8: 46300 | E8: 800 | F8: 99.02 | G8: =E8*F8 -> 79216 | H8: 35 | I8: 111.12 | J8: =H8*I8 -> 3889.2 | K8: =G8+J8 -> 83105.2 | M8: =M7+K8-L8 -> 339028.52
A9: 5 | B9: 46301 | G9: =E9*F9 -> 0 | J9: =H9*I9 -> 0 | K9: =G9+J9 -> 0 | M9: =M8+K9-L9 -> 339028.52
A10: 6 | B10: 46302 | G10: =E10*F10 -> 0 | J10: =H10*I10 -> 0 | K10: =G10+J10 -> 0 | M10: =M9+K10-L10 -> 339028.52
A11: 7 | B11: 46303 | G11: =E11*F11 -> 0 | J11: =H11*I11 -> 0 | K11: =G11+J11 -> 0 | M11: =M10+K11-L11 -> 339028.52
A12: 8 | B12: 46304 | G12: =E12*F12 -> 0 | J12: =H12*I12 -> 0 | K12: =G12+J12 -> 0 | M12: =M11+K12-L12 -> 339028.52
A13: 9 | B13: 46305 | G13: =E13*F13 -> 0 | J13: =H13*I13 -> 0 | K13: =G13+J13 -> 0 | M13: =M12+K13-L13 -> 339028.52
A14: 10 | B14: 46306 | G14: =E14*F14 -> 0 | J14: =H14*I14 -> 0 | K14: =G14+J14 -> 0 | L14: 200000 | M14: =M13+K14-L14 -> 139028.52
A15: 11 | B15: 46307 | G15: =E15*F15 -> 0 | J15: =H15*I15 -> 0 | K15: =G15+J15 -> 0 | M15: =M14+K15-L15 -> 139028.52
A16: 12 | B16: 46308 | G16: =E16*F16 -> 0 | J16: =H16*I16 -> 0 | K16: =G16+J16 -> 0 | M16: =M15+K16-L16 -> 139028.52
A17: 13 | B17: 46309 | G17: =E17*F17 -> 0 | J17: =H17*I17 -> 0 | K17: =G17+J17 -> 0 | M17: =M16+K17-L17 -> 139028.52
A18: 14 | B18: 46310 | G18: =E18*F18 -> 0 | J18: =H18*I18 -> 0 | K18: =G18+J18 -> 0 | M18: =M17+K18-L18 -> 139028.52
A19: 15 | B19: 46311 | G19: =E19*F19 -> 0 | J19: =H19*I19 -> 0 | K19: =G19+J19 -> 0 | M19: =M18+K19-L19 -> 139028.52
A20: 16 | B20: 46312 | G20: =E20*F20 -> 0 | J20: =H20*I20 -> 0 | K20: =G20+J20 -> 0 | M20: =M19+K20-L20 -> 139028.52
A21: 17 | B21: 46313 | G21: =E21*F21 -> 0 | J21: =H21*I21 -> 0 | K21: =G21+J21 -> 0 | M21: =M20+K21-L21 -> 139028.52
A22: 18 | B22: 46314 | G22: =E22*F22 -> 0 | J22: =H22*I22 -> 0 | K22: =G22+J22 -> 0 | M22: =M21+K22-L22 -> 139028.52
A23: 19 | B23: 46315 | G23: =E23*F23 -> 0 | J23: =H23*I23 -> 0 | K23: =G23+J23 -> 0 | M23: =M22+K23-L23 -> 139028.52
A24: 20 | B24: 46316 | G24: =E24*F24 -> 0 | J24: =H24*I24 -> 0 | K24: =G24+J24 -> 0 | M24: =M23+K24-L24 -> 139028.52
A25: 21 | B25: 46317 | G25: =E25*F25 -> 0 | J25: =H25*I25 -> 0 | K25: =G25+J25 -> 0 | M25: =M24+K25-L25 -> 139028.52
A26: 22 | B26: 46318 | G26: =E26*F26 -> 0 | J26: =H26*I26 -> 0 | K26: =G26+J26 -> 0 | M26: =M25+K26-L26 -> 139028.52
... A34: 30 | B34: 46326 | G34: =E34*F34 -> 0 | J34: =H34*I34 -> 0 | K34: =G34+J34 -> 0 | M34: =M33+K34-L34 -> 139028.52
A35: 31 | G35: =E35*F35 -> 0 | J35: =H35*I35 -> 0 | K35: =G35+J35 -> 0 | M35: =M34+K35-L35 -> 139028.52
A36: 32 | G36: =E36*F36 -> 0 | J36: =H36*I36 -> 0 | K36: =G36+J36 -> 0 | M36: =M35+K36-L36 -> 139028.52
A37: 33 | G37: =E37*F37 -> 0 | J37: =H37*I37 -> 0 | K37: =G37+J37 -> 0 | M37: =M36+K37-L37 -> 139028.52
A38: 34 | G38: =E38*F38 -> 0 | J38: =H38*I38 -> 0 | K38: =G38+J38 -> 0 | M38: =M37+K38-L38 -> 139028.52
E39: =SUM(E4:E38) -> 800 | G39: =SUM(G4:G38) -> 79216 | H39: =SUM(H4:H38) -> 35 | J39: =SUM(J4:J38) -> 3889.2 | K39: =SUM(K4:K38) -> 83105.2 | L39: =SUM(L4:L38) -> 200000

Sheet Hosadurga -2
A1: Shree Veeraprathap Fuel
A2: S.No | B2: Date | C2: GRN No | D2: Ind No/Bill No | E2: Diesel (Lts) | F2: Price | G2: Amount | H2: Petrol (Lts) | I2: Price | J2: Amount | K2: Total amount | L2: Amount paid | M2: As on Date | N2: Remarks
A3: Opening Balance | K3: 126009.99 | M3: 126009.99
A4: 1 | B4: 46296 | G4: =E4*F4 -> 0 | J4: =H4*I4 -> 0 | K4: =G4+J4 -> 0 | M4: =M3+K4-L4 -> 126009.99
A5: 2 | B5: 46297 | G5: =E5*F5 -> 0 | J5: =H5*I5 -> 0 | K5: =G5+J5 -> 0 | M5: =M4+K5-L5 -> 126009.99
A6: 3 | B6: 46298 | G6: =E6*F6 -> 0 | J6: =H6*I6 -> 0 | K6: =G6+J6 -> 0 | M6: =M5+K6-L6 -> 126009.99
A7: 4 | B7: 46299 | G7: =E7*F7 -> 0 | J7: =H7*I7 -> 0 | K7: =G7+J7 -> 0 | M7: =M6+K7-L7 -> 126009.99
A8: 5 | B8: 46300 | G8: =E8*F8 -> 0 | J8: =H8*I8 -> 0 | K8: =G8+J8 -> 0 | M8: =M7+K8-L8 -> 126009.99
A9: 6 | B9: 46301 | G9: =E9*F9 -> 0 | J9: =H9*I9 -> 0 | K9: =G9+J9 -> 0 | M9: =M8+K9-L9 -> 126009.99
A10: 7 | B10: 46302 | G10: =E10*F10 -> 0 | J10: =H10*I10 -> 0 | K10: =G10+J10 -> 0 | M10: =M9+K10-L10 -> 126009.99
A11: 8 | B11: 46303 | G11: =E11*F11 -> 0 | J11: =H11*I11 -> 0 | K11: =G11+J11 -> 0 | M11: =M10+K11-L11 -> 126009.99
A12: 9 | B12: 46304 | G12: =E12*F12 -> 0 | J12: =H12*I12 -> 0 | K12: =G12+J12 -> 0 | M12: =M11+K12-L12 -> 126009.99
A13: 10 | B13: 46305 | E13: 0 | F13: 0 | G13: =E13*F13 -> 0 | H13: 0 | I13: 0 | J13: =H13*I13 -> 0 | K13: =G13+J13 -> 0 | L13: 0 | M13: =M12+K13-L13 -> 126009.99
A14: 11 | B14: 46306 | E14: 1000 | F14: 99.36 | G14: =E14*F14 -> 99360 | H14: 100 | I14: 111.68 | J14: =H14*I14 -> 11168 | K14: =G14+J14 -> 110528 | L14: 126000 | M14: =M13+K14-L14 -> 110537.99
A15: 12 | B15: 46307 | G15: =E15*F15 -> 0 | J15: =H15*I15 -> 0 | K15: =G15+J15 -> 0 | M15: =M14+K15-L15 -> 110537.99
A16: 13 | B16: 46308 | G16: =E16*F16 -> 0 | J16: =H16*I16 -> 0 | K16: =G16+J16 -> 0 | M16: =M15+K16-L16 -> 110537.99
A17: 14 | B17: 46309 | G17: =E17*F17 -> 0 | J17: =H17*I17 -> 0 | K17: =G17+J17 -> 0 | M17: =M16+K17-L17 -> 110537.99
A18: 15 | B18: 46310 | G18: =E18*F18 -> 0 | J18: =H18*I18 -> 0 | K18: =G18+J18 -> 0 | M18: =M17+K18-L18 -> 110537.99
A19: 16 | B19: 46311 | G19: =E19*F19 -> 0 | J19: =H19*I19 -> 0 | K19: =G19+J19 -> 0 | L19: 100000 | M19: =M18+K19-L19 -> 10537.994
A20: 17 | B20: 46312 | G20: =E20*F20 -> 0 | J20: =H20*I20 -> 0 | K20: =G20+J20 -> 0 | M20: =M19+K20-L20 -> 10537.994
A21: 18 | B21: 46313 | G21: =E21*F21 -> 0 | J21: =H21*I21 -> 0 | K21: =G21+J21 -> 0 | M21: =M20+K21-L21 -> 10537.994
A22: 19 | B22: 46314 | G22: =E22*F22 -> 0 | J22: =H22*I22 -> 0 | K22: =G22+J22 -> 0 | M22: =M21+K22-L22 -> 10537.994
A23: 20 | B23: 46315 | G23: =E23*F23 -> 0 | J23: =H23*I23 -> 0 | K23: =G23+J23 -> 0 | M23: =M22+K23-L23 -> 10537.994
A24: 21 | B24: 46316 | G24: =E24*F24 -> 0 | J24: =H24*I24 -> 0 | K24: =G24+J24 -> 0 | M24: =M23+K24-L24 -> 10537.994
A25: 22 | B25: 46317 | G25: =E25*F25 -> 0 | J25: =H25*I25 -> 0 | K25: =G25+J25 -> 0 | M25: =M24+K25-L25 -> 10537.994
A26: 23 | B26: 46318 | G26: =E26*F26 -> 0 | J26: =H26*I26 -> 0 | K26: =G26+J26 -> 0 | M26: =M25+K26-L26 -> 10537.994
A27: 24 | B27: 46319 | G27: =E27*F27 -> 0 | J27: =H27*I27 -> 0 | K27: =G27+J27 -> 0 | M27: =M26+K27-L27 -> 10537.994
A28: 25 | B28: 46320 | G28: =E28*F28 -> 0 | J28: =H28*I28 -> 0 | K28: =G28+J28 -> 0 | M28: =M27+K28-L28 -> 10537.994
A29: 26 | B29: 46321 | G29: =E29*F29 -> 0 | J29: =H29*I29 -> 0 | K29: =G29+J29 -> 0 | M29: =M28+K29-L29 -> 10537.994
A30: 27 | B30: 46322 | G30: =E30*F30 -> 0 | J30: =H30*I30 -> 0 | K30: =G30+J30 -> 0 | M30: =M29+K30-L30 -> 10537.994
A31: 28 | B31: 46323 | G31: =E31*F31 -> 0 | J31: =H31*I31 -> 0 | K31: =G31+J31 -> 0 | M31: =M30+K31-L31 -> 10537.994
... A33: 30 | B33: 46325 | G33: =E33*F33 -> 0 | J33: =H33*I33 -> 0 | K33: =G33+J33 -> 0 | M33: =M32+K33-L33 -> 10537.994
A34: 31 | B34: 46326 | K34: =G34+J34 -> 0
E35: =SUM(E4:E34) -> 1000 | G35: =SUM(G4:G34) -> 99360 | H35: =SUM(H4:H34) -> 100 | J35: =SUM(J4:J34) -> 11168 | K35: =SUM(K4:K34) -> 110528 | L35: =SUM(L4:L34) -> 226000

Sheet Hiriyur(VJNL)
A1: Sri Balaji Agencies
A2: S.No | B2: Date | C2: GRN No | D2: Ind No/Bill No | E2: Diesel (Lts) | F2: Price | G2: Amount | H2: Petrol (Lts) | I2: Price | J2: Amount | K2: Total amount | L2: Amount paid | M2: As on Date | N2: Remarks
A3: Opening Balance | K3: 212444.1 | M3: 212444.1
A4: 1 | B4: 46296 | G4: =E4*F4 -> 0 | J4: =H4*I4 -> 0 | K4: =G4+J4 -> 0 | M4: =M3+K4-L4 -> 212444.1
A5: 2 | B5: 46297 | G5: =E5*F5 -> 0 | J5: =H5*I5 -> 0 | K5: =G5+J5 -> 0 | M5: =M4+K5-L5 -> 212444.1
A6: 3 | B6: 46298 | E6: 300 | F6: 100.07 | G6: =E6*F6 -> 30021 | J6: =H6*I6 -> 0 | K6: =G6+J6 -> 30021 | M6: =M5+K6-L6 -> 242465.1
A7: 4 | B7: 46299 | G7: =E7*F7 -> 0 | J7: =H7*I7 -> 0 | K7: =G7+J7 -> 0 | M7: =M6+K7-L7 -> 242465.1
A8: 5 | B8: 46300 | G8: =E8*F8 -> 0 | J8: =H8*I8 -> 0 | K8: =G8+J8 -> 0 | M8: =M7+K8-L8 -> 242465.1
A9: 6 | B9: 46301 | G9: =E9*F9 -> 0 | J9: =H9*I9 -> 0 | K9: =G9+J9 -> 0 | M9: =M8+K9-L9 -> 242465.1
A10: 7 | B10: 46302 | G10: =E10*F10 -> 0 | J10: =H10*I10 -> 0 | K10: =G10+J10 -> 0 | M10: =M9+K10-L10 -> 242465.1
A11: 8 | B11: 46303 | G11: =E11*F11 -> 0 | J11: =H11*I11 -> 0 | K11: =G11+J11 -> 0 | M11: =M10+K11-L11 -> 242465.1
A12: 9 | B12: 46304 | E12: 300 | F12: 100.07 | G12: =E12*F12 -> 30021 | H12: 50 | I12: 112.09 | J12: =H12*I12 -> 5604.5 | K12: =G12+J12 -> 35625.5 | L12: 150000 | M12: =M11+K12-L12 -> 128090.6
A13: 10 | B13: 46305 | G13: =E13*F13 -> 0 | J13: =H13*I13 -> 0 | K13: =G13+J13 -> 0 | M13: =M12+K13-L13 -> 128090.6
A14: 11 | B14: 46306 | G14: =E14*F14 -> 0 | J14: =H14*I14 -> 0 | K14: =G14+J14 -> 0 | M14: =M13+K14-L14 -> 128090.6
A15: 12 | B15: 46307 | G15: =E15*F15 -> 0 | J15: =H15*I15 -> 0 | K15: =G15+J15 -> 0 | M15: =M14+K15-L15 -> 128090.6
A16: 13 | B16: 46308 | G16: =E16*F16 -> 0 | J16: =H16*I16 -> 0 | K16: =G16+J16 -> 0 | M16: =M15+K16-L16 -> 128090.6
A17: 14 | B17: 46309 | G17: =E17*F17 -> 0 | J17: =H17*I17 -> 0 | K17: =G17+J17 -> 0 | M17: =M16+K17-L17 -> 128090.6
A18: 15 | B18: 46310 | E18: 2000 | F18: 100.07 | G18: =E18*F18 -> 200140 | H18: 70 | I18: 112.09 | J18: =H18*I18 -> 7846.3 | K18: =G18+J18 -> 207986.3 | L18: 128000 | M18: =M17+K18-L18 -> 208076.9
A19: 16 | B19: 46311 | G19: =E19*F19 -> 0 | J19: =H19*I19 -> 0 | K19: =G19+J19 -> 0 | M19: =M18+K19-L19 -> 208076.9
A20: 17 | B20: 46312 | G20: =E20*F20 -> 0 | J20: =H20*I20 -> 0 | K20: =G20+J20 -> 0 | M20: =M19+K20-L20 -> 208076.9
A21: 18 | B21: 46313 | G21: =E21*F21 -> 0 | J21: =H21*I21 -> 0 | K21: =G21+J21 -> 0 | M21: =M20+K21-L21 -> 208076.9
A22: 19 | B22: 46314 | G22: =E22*F22 -> 0 | J22: =H22*I22 -> 0 | K22: =G22+J22 -> 0 | M22: =M21+K22-L22 -> 208076.9
A23: 20 | B23: 46315 | G23: =E23*F23 -> 0 | J23: =H23*I23 -> 0 | K23: =G23+J23 -> 0 | M23: =M22+K23-L23 -> 208076.9
A24: 21 | B24: 46316 | G24: =E24*F24 -> 0 | J24: =H24*I24 -> 0 | K24: =G24+J24 -> 0 | M24: =M23+K24-L24 -> 208076.9
A25: 22 | B25: 46317 | G25: =E25*F25 -> 0 | J25: =H25*I25 -> 0 | K25: =G25+J25 -> 0 | M25: =M24+K25-L25 -> 208076.9
A26: 23 | B26: 46318 | G26: =E26*F26 -> 0 | J26: =H26*I26 -> 0 | K26: =G26+J26 -> 0 | M26: =M25+K26-L26 -> 208076.9
A27: 24 | B27: 46319 | G27: =E27*F27 -> 0 | J27: =H27*I27 -> 0 | K27: =G27+J27 -> 0 | M27: =M26+K27-L27 -> 208076.9
A28: 25 | B28: 46320 | G28: =E28*F28 -> 0 | J28: =H28*I28 -> 0 | K28: =G28+J28 -> 0 | M28: =M27+K28-L28 -> 208076.9
A29: 26 | B29: 46321 | G29: =E29*F29 -> 0 | J29: =H29*I29 -> 0 | K29: =G29+J29 -> 0 | M29: =M28+K29-L29 -> 208076.9
A30: 27 | B30: 46322 | G30: =E30*F30 -> 0 | J30: =H30*I30 -> 0 | K30: =G30+J30 -> 0 | M30: =M29+K30-L30 -> 208076.9
... A34: 31 | B34: 46326 | G34: =E34*F34 -> 0 | J34: =H34*I34 -> 0 | K34: =G34+J34 -> 0 | M34: =M33+K34-L34 -> 208076.9
E35: =SUM(E4:E34) -> 2600 | G35: =SUM(G4:G34) -> 260182 | H35: =SUM(H4:H34) -> 120 | J35: =SUM(J4:J34) -> 13450.8 | K35: =SUM(K4:K34) -> 273632.8 | L35: =SUM(L4:L34) -> 278000

Sheet Malebenur(KUWSDB)
A1: Sree Veerabhadreshwara Service Station
A2: S.No | B2: Date | C2: GRN No | D2: Ind No/Bill No | E2: Diesel (Lts) | F2: Price | G2: Amount | H2: Petrol (Lts) | I2: Price | J2: Amount | K2: Total amount | L2: Amount paid | M2: As on Date | N2: Remarks
A3: Opening Balance | K3: 290892.11 | M3: 290892.11
A4: 1 | B4: 46296 | E4: 800 | F4: 99.98 | G4: =E4*F4 -> 79984 | H4: 20 | I4: 111.98 | J4: =H4*I4 -> 2239.6 | K4: =G4+J4 -> 82223.6 | M4: =M3+K4-L4 -> 373115.71
A5: 2 | B5: 46297 | G5: =E5*F5 -> 0 | J5: =H5*I5 -> 0 | K5: =G5+J5 -> 0 | M5: =M4+K5-L5 -> 373115.71
A6: 3 | B6: 46298 | G6: =E6*F6 -> 0 | J6: =H6*I6 -> 0 | K6: =G6+J6 -> 0 | M6: =M5+K6-L6 -> 373115.71
A7: 4 | B7: 46299 | E7: 800 | F7: 99.98 | G7: =E7*F7 -> 79984 | H7: 30 | I7: 111.98 | J7: =H7*I7 -> 3359.4 | K7: =G7+J7 -> 83343.4 | M7: =M6+K7-L7 -> 456459.11
A8: 5 | B8: 46300 | G8: =E8*F8 -> 0 | J8: =H8*I8 -> 0 | K8: =G8+J8 -> 0 | M8: =M7+K8-L8 -> 456459.11
A9: 6 | B9: 46301 | G9: =E9*F9 -> 0 | J9: =H9*I9 -> 0 | K9: =G9+J9 -> 0 | M9: =M8+K9-L9 -> 456459.11
A10: 7 | B10: 46302 | G10: =E10*F10 -> 0 | J10: =H10*I10 -> 0 | K10: =G10+J10 -> 0 | M10: =M9+K10-L10 -> 456459.11
A11: 8 | B11: 46303 | G11: =E11*F11 -> 0 | J11: =H11*I11 -> 0 | K11: =G11+J11 -> 0 | M11: =M10+K11-L11 -> 456459.11
A12: 9 | B12: 46304 | G12: =E12*F12 -> 0 | J12: =H12*I12 -> 0 | K12: =G12+J12 -> 0 | M12: =M11+K12-L12 -> 456459.11
A13: 10 | B13: 46305 | E13: 66.63 | F13: 100.07 | G13: =E13*F13 -> 6667.6641 | H13: 29.99 | I13: 112.09 | J13: =H13*I13 -> 3361.5791 | K13: =G13+J13 -> 10029.243 | L13: 10029.243 | M13: =M12+K13-L13 -> 456459.11
A14: 11 | B14: 46305 | L14: 290000 | M14: =M13+K14-L14 -> 166459.11
A15: 12 | B15: 46306 | E15: 800 | F15: 99.98 | G15: =E15*F15 -> 79984 | H15: 30 | I15: 111.98 | J15: =H15*I15 -> 3359.4 | K15: =G15+J15 -> 83343.4 | M15: =M14+K15-L15 -> 249802.51
A16: 13 | B16: 46307 | G16: =E16*F16 -> 0 | J16: =H16*I16 -> 0 | K16: =G16+J16 -> 0 | M16: =M15+K16-L16 -> 249802.51
A17: 14 | B17: 46308 | E17: 600 | F17: 99.98 | G17: =E17*F17 -> 59988 | J17: =H17*I17 -> 0 | K17: =G17+J17 -> 59988 | M17: =M16+K17-L17 -> 309790.51
A18: 15 | B18: 46309 | G18: =E18*F18 -> 0 | J18: =H18*I18 -> 0 | K18: =G18+J18 -> 0 | M18: =M17+K18-L18 -> 309790.51
A19: 16 | B19: 46310 | E19: 800 | F19: 99.98 | G19: =E19*F19 -> 79984 | J19: =H19*I19 -> 0 | K19: =G19+J19 -> 79984 | M19: =M18+K19-L19 -> 389774.51
A20: 17 | B20: 46311 | G20: =E20*F20 -> 0 | J20: =H20*I20 -> 0 | K20: =G20+J20 -> 0 | M20: =M19+K20-L20 -> 389774.51
A21: 18 | B21: 46312 | G21: =E21*F21 -> 0 | J21: =H21*I21 -> 0 | K21: =G21+J21 -> 0 | M21: =M20+K21-L21 -> 389774.51
A22: 19 | B22: 46313 | G22: =E22*F22 -> 0 | J22: =H22*I22 -> 0 | K22: =G22+J22 -> 0 | M22: =M21+K22-L22 -> 389774.51
A23: 20 | B23: 46314 | G23: =E23*F23 -> 0 | J23: =H23*I23 -> 0 | K23: =G23+J23 -> 0 | M23: =M22+K23-L23 -> 389774.51
A24: 21 | B24: 46315 | G24: =E24*F24 -> 0 | J24: =H24*I24 -> 0 | K24: =G24+J24 -> 0 | M24: =M23+K24-L24 -> 389774.51
A25: 22 | B25: 46316 | G25: =E25*F25 -> 0 | J25: =H25*I25 -> 0 | K25: =G25+J25 -> 0 | M25: =M24+K25-L25 -> 389774.51
A26: 23 | B26: 46317 | G26: =E26*F26 -> 0 | J26: =H26*I26 -> 0 | K26: =G26+J26 -> 0 | M26: =M25+K26-L26 -> 389774.51
A27: 24 | B27: 46318 | G27: =E27*F27 -> 0 | J27: =H27*I27 -> 0 | K27: =G27+J27 -> 0 | M27: =M26+K27-L27 -> 389774.51
A28: 25 | B28: 46319 | G28: =E28*F28 -> 0 | K28: =G28+J28 -> 0 | M28: =M27+K28-L28 -> 389774.51
A29: 26 | B29: 46320 | G29: =E29*F29 -> 0 | J29: =H29*I29 -> 0 | K29: =G29+J29 -> 0 | M29: =M28+K29-L29 -> 389774.51
A30: 27 | B30: 46321 | G30: =E30*F30 -> 0 | J30: =H30*I30 -> 0 | K30: =G30+J30 -> 0 | M30: =M29+K30-L30 -> 389774.51
A31: 28 | B31: 46322 | G31: =E31*F31 -> 0 | J31: =H31*I31 -> 0 | K31: =G31+J31 -> 0 | M31: =M30+K31-L31 -> 389774.51
A32: 29 | B32: 46323 | G32: =E32*F32 -> 0 | J32: =H32*I32 -> 0 | K32: =G32+J32 -> 0 | M32: =M31+K32-L32 -> 389774.51
A33: 30 | B33: 46324 | G33: =E33*F33 -> 0 | J33: =H33*I33 -> 0 | K33: =G33+J33 -> 0 | M33: =M32+K33-L33 -> 389774.51
A34: 31 | B34: 46325 | G34: =E34*F34 -> 0 | J34: =H34*I34 -> 0 | K34: =G34+J34 -> 0 | M34: =M33+K34-L34 -> 389774.51
A35: 32 | B35: 46326 | G35: =E35*F35 -> 0 | J35: =H35*I35 -> 0 | K35: =G35+J35 -> 0 | M35: =M34+K35-L35 -> 389774.51
A36: 33 | G36: =E36*F36 -> 0 | J36: =H36*I36 -> 0 | K36: =G36+J36 -> 0 | M36: =M35+K36-L36 -> 389774.51
G37: =E37*F37 -> 0 | J37: =H37*I37 -> 0 | K37: =G37+J37 -> 0 | M37: =M36+K37-L37 -> 389774.51
G38: =E38*F38 -> 0 | J38: =H38*I38 -> 0 | K38: =G38+J38 -> 0 | M38: =M37+K38-L38 -> 389774.51
E39: =SUM(E4:E37) -> 3866.63 | G39: =SUM(G4:G37) -> 386591.66 | H39: =SUM(H4:H37) -> 109.99 | J39: =SUM(J4:J37) -> 12319.979 | K39: =SUM(K4:K37) -> 398911.64 | L39: =SUM(L4:L37) -> 300029.24
S45: 9052944708

Sheet Molakamuru
A1: Priyanka Petroleum
A2: S.No | B2: Date | C2: GRN No | D2: Ind No/Bill No | E2: Diesel (Lts) | F2: Price | G2: Amount | H2: Petrol (Lts) | I2: Price | J2: Amount | K2: Total amount | L2: Amount paid | M2: As on Date | N2: Remarks
A3: Opening Balance | K3: 44770.66 | M3: 44770.66
A4: 1 | B4: 46296 | G4: =E4*F4 -> 0 | J4: =H4*I4 -> 0 | K4: =G4+J4 -> 0 | M4: =M3+K4-L4 -> 44770.66
A5: 2 | B5: 46297 | G5: =E5*F5 -> 0 | J5: =H5*I5 -> 0 | K5: =G5+J5 -> 0 | M5: =M4+K5-L5 -> 44770.66
A6: 3 | B6: 46298 | E6: 300 | F6: 100.03 | G6: =E6*F6 -> 30009 | H6: 20 | I6: 112.03 | J6: =H6*I6 -> 2240.6 | K6: =G6+J6 -> 32249.6 | M6: =M5+K6-L6 -> 77020.26
A7: 4 | B7: 46299 | G7: =E7*F7 -> 0 | J7: =H7*I7 -> 0 | K7: =G7+J7 -> 0 | M7: =M6+K7-L7 -> 77020.26
A8: 5 | B8: 46300 | G8: =E8*F8 -> 0 | J8: =H8*I8 -> 0 | K8: =G8+J8 -> 0 | M8: =M7+K8-L8 -> 77020.26
A9: 6 | B9: 46301 | G9: =E9*F9 -> 0 | J9: =H9*I9 -> 0 | K9: =G9+J9 -> 0 | M9: =M8+K9-L9 -> 77020.26
A10: 7 | B10: 46302 | G10: =E10*F10 -> 0 | J10: =H10*I10 -> 0 | K10: =G10+J10 -> 0 | M10: =M9+K10-L10 -> 77020.26
A11: 8 | B11: 46303 | G11: =E11*F11 -> 0 | J11: =H11*I11 -> 0 | K11: =G11+J11 -> 0 | M11: =M10+K11-L11 -> 77020.26
A12: 9 | B12: 46304 | G12: =E12*F12 -> 0 | J12: =H12*I12 -> 0 | K12: =G12+J12 -> 0 | M12: =M11+K12-L12 -> 77020.26
A13: 10 | B13: 46305 | G13: =E13*F13 -> 0 | J13: =H13*I13 -> 0 | K13: =G13+J13 -> 0 | M13: =M12+K13-L13 -> 77020.26
A14: 11 | B14: 46306 | G14: =E14*F14 -> 0 | J14: =H14*I14 -> 0 | K14: =G14+J14 -> 0 | M14: =M13+K14-L14 -> 77020.26
A15: 12 | B15: 46307 | G15: =E15*F15 -> 0 | J15: =H15*I15 -> 0 | K15: =G15+J15 -> 0 | M15: =M14+K15-L15 -> 77020.26
A16: 13 | B16: 46308 | G16: =E16*F16 -> 0 | J16: =H16*I16 -> 0 | K16: =G16+J16 -> 0 | M16: =M15+K16-L16 -> 77020.26
A17: 14 | B17: 46309 | E17: 200 | F17: 100.03 | G17: =E17*F17 -> 20006 | H17: 20 | I17: 112.03 | J17: =H17*I17 -> 2240.6 | K17: =G17+J17 -> 22246.6 | M17: =M16+K17-L17 -> 99266.86
A18: 15 | B18: 46310 | G18: =E18*F18 -> 0 | J18: =H18*I18 -> 0 | K18: =G18+J18 -> 0 | M18: =M17+K18-L18 -> 99266.86
A19: 16 | B19: 46311 | G19: =E19*F19 -> 0 | J19: =H19*I19 -> 0 | K19: =G19+J19 -> 0 | M19: =M18+K19-L19 -> 99266.86
A20: 17 | B20: 46312 | G20: =E20*F20 -> 0 | J20: =H20*I20 -> 0 | K20: =G20+J20 -> 0 | M20: =M19+K20-L20 -> 99266.86
A21: 18 | B21: 46313 | G21: =E21*F21 -> 0 | J21: =H21*I21 -> 0 | K21: =G21+J21 -> 0 | M21: =M20+K21-L21 -> 99266.86
A22: 19 | B22: 46314 | G22: =E22*F22 -> 0 | J22: =H22*I22 -> 0 | K22: =G22+J22 -> 0 | M22: =M21+K22-L22 -> 99266.86
A23: 20 | B23: 46315 | G23: =E23*F23 -> 0 | J23: =H23*I23 -> 0 | K23: =G23+J23 -> 0 | M23: =M22+K23-L23 -> 99266.86
A24: 21 | B24: 46316 | G24: =E24*F24 -> 0 | J24: =H24*I24 -> 0 | K24: =G24+J24 -> 0 | M24: =M23+K24-L24 -> 99266.86
A25: 22 | B25: 46317 | G25: =E25*F25 -> 0 | J25: =H25*I25 -> 0 | K25: =G25+J25 -> 0 | M25: =M24+K25-L25 -> 99266.86
A26: 23 | B26: 46318 | G26: =E26*F26 -> 0 | J26: =H26*I26 -> 0 | K26: =G26+J26 -> 0 | M26: =M25+K26-L26 -> 99266.86
A27: 24 | B27: 46319 | G27: =E27*F27 -> 0 | J27: =H27*I27 -> 0 | K27: =G27+J27 -> 0 | M27: =M26+K27-L27 -> 99266.86
A28: 25 | B28: 46320 | G28: =E28*F28 -> 0 | J28: =H28*I28 -> 0 | K28: =G28+J28 -> 0 | M28: =M27+K28-L28 -> 99266.86
A29: 26 | B29: 46321 | G29: =E29*F29 -> 0 | J29: =H29*I29 -> 0 | K29: =G29+J29 -> 0 | M29: =M28+K29-L29 -> 99266.86
... A33: 30 | B33: 46325 | G33: =E33*F33 -> 0 | J33: =H33*I33 -> 0 | K33: =G33+J33 -> 0 | M33: =M32+K33-L33 -> 99266.86
A34: 31 | B34: 46326 | G34: =E34*F34 -> 0 | K34: =G34+J34 -> 0 | M34: =M33+K34-L34 -> 99266.86
E35: =SUM(E4:E34) -> 500 | G35: =SUM(G4:G34) -> 50015 | H35: =SUM(H4:H34) -> 40 | J35: =SUM(J4:J34) -> 4481.2 | K35: =SUM(K4:K34) -> 54496.2 | L35: =SUM(L4:L34) -> 0

Sheet Chellakere -1
A1: Shivaganga Service Station (BPCL)
A2: S.No | B2: Date | C2: GRN No | D2: Ind No/Bill No | E2: Diesel (Lts) | F2: Price | G2: Amount | H2: Petrol (Lts) | I2: Price | J2: Amount | K2: Total amount | L2: Amount paid | M2: As on Date | N2: Remarks
A3: Opening Balance | L3: 188792.25 | M3: 188792.25
A4: 1 | B4: 46296 | G4: =E4*F4 -> 0 | J4: =H4*I4 -> 0 | K4: =G4+J4 -> 0 | M4: =M3+K4-L4 -> 188792.25
A5: 2 | B5: 46297 | G5: =E5*F5 -> 0 | J5: =H5*I5 -> 0 | K5: =G5+J5 -> 0 | M5: =M4+K5-L5 -> 188792.25
A6: 3 | B6: 46298 | G6: =E6*F6 -> 0 | J6: =H6*I6 -> 0 | K6: =G6+J6 -> 0 | M6: =M5+K6-L6 -> 188792.25
A7: 4 | B7: 46299 | G7: =E7*F7 -> 0 | J7: =H7*I7 -> 0 | K7: =G7+J7 -> 0 | M7: =M6+K7-L7 -> 188792.25
A8: 5 | B8: 46300 | E8: 600 | F8: 100.03 | G8: =E8*F8 -> 60018 | H8: 35 | I8: 112.04 | J8: =H8*I8 -> 3921.4 | K8: =G8+J8 -> 63939.4 | M8: =M7+K8-L8 -> 252731.65
A9: 6 | B9: 46301 | G9: =E9*F9 -> 0 | J9: =H9*I9 -> 0 | K9: =G9+J9 -> 0 | M9: =M8+K9-L9 -> 252731.65
A10: 7 | B10: 46302 | G10: =E10*F10 -> 0 | J10: =H10*I10 -> 0 | K10: =G10+J10 -> 0 | M10: =M9+K10-L10 -> 252731.65
A11: 8 | B11: 46303 | G11: =E11*F11 -> 0 | J11: =H11*I11 -> 0 | K11: =G11+J11 -> 0 | M11: =M10+K11-L11 -> 252731.65
A12: 9 | B12: 46304 | G12: =E12*F12 -> 0 | J12: =H12*I12 -> 0 | K12: =G12+J12 -> 0 | M12: =M11+K12-L12 -> 252731.65
A13: 10 | B13: 46305 | G13: =E13*F13 -> 0 | J13: =H13*I13 -> 0 | K13: =G13+J13 -> 0 | L13: 200000 | M13: =M12+K13-L13 -> 52731.65
A14: 11 | B14: 46306 | E14: 600 | F14: 100.03 | G14: =E14*F14 -> 60018 | H14: 35 | I14: 112.04 | J14: =H14*I14 -> 3921.4 | K14: =G14+J14 -> 63939.4 | M14: =M13+K14-L14 -> 116671.05
A15: 12 | B15: 46307 | G15: =E15*F15 -> 0 | J15: =H15*I15 -> 0 | K15: =G15+J15 -> 0 | M15: =M14+K15-L15 -> 116671.05
A16: 13 | B16: 46308 | G16: =E16*F16 -> 0 | J16: =H16*I16 -> 0 | K16: =G16+J16 -> 0 | M16: =M15+K16-L16 -> 116671.05
A17: 14 | B17: 46309 | G17: =E17*F17 -> 0 | J17: =H17*I17 -> 0 | K17: =G17+J17 -> 0 | M17: =M16+K17-L17 -> 116671.05
A18: 15 | B18: 46310 | E18: 600 | F18: 100.03 | G18: =E18*F18 -> 60018 | H18: 35 | I18: 112.04 | J18: =H18*I18 -> 3921.4 | K18: =G18+J18 -> 63939.4 | M18: =M17+K18-L18 -> 180610.45
A19: 16 | B19: 46311 | G19: =E19*F19 -> 0 | J19: =H19*I19 -> 0 | K19: =G19+J19 -> 0 | M19: =M18+K19-L19 -> 180610.45
A20: 17 | B20: 46312 | G20: =E20*F20 -> 0 | J20: =H20*I20 -> 0 | K20: =G20+J20 -> 0 | M20: =M19+K20-L20 -> 180610.45
A21: 18 | B21: 46313 | G21: =E21*F21 -> 0 | J21: =H21*I21 -> 0 | K21: =G21+J21 -> 0 | M21: =M20+K21-L21 -> 180610.45
A22: 19 | B22: 46314 | G22: =E22*F22 -> 0 | J22: =H22*I22 -> 0 | K22: =G22+J22 -> 0 | M22: =M21+K22-L22 -> 180610.45
A23: 20 | B23: 46315 | G23: =E23*F23 -> 0 | J23: =H23*I23 -> 0 | K23: =G23+J23 -> 0 | M23: =M22+K23-L23 -> 180610.45
A24: 21 | B24: 46316 | G24: =E24*F24 -> 0 | J24: =H24*I24 -> 0 | K24: =G24+J24 -> 0 | M24: =M23+K24-L24 -> 180610.45
A25: 22 | B25: 46317 | G25: =E25*F25 -> 0 | J25: =H25*I25 -> 0 | K25: =G25+J25 -> 0 | M25: =M24+K25-L25 -> 180610.45
A26: 23 | B26: 46318 | G26: =E26*F26 -> 0 | J26: =H26*I26 -> 0 | K26: =G26+J26 -> 0 | M26: =M25+K26-L26 -> 180610.45
A27: 24 | B27: 46319 | G27: =E27*F27 -> 0 | J27: =H27*I27 -> 0 | K27: =G27+J27 -> 0 | M27: =M26+K27-L27 -> 180610.45
A28: 25 | B28: 46320 | G28: =E28*F28 -> 0 | J28: =H28*I28 -> 0 | K28: =G28+J28 -> 0 | M28: =M27+K28-L28 -> 180610.45
A29: 26 | B29: 46321 | G29: =E29*F29 -> 0 | J29: =H29*I29 -> 0 | K29: =G29+J29 -> 0 | M29: =M28+K29-L29 -> 180610.45
A30: 27 | B30: 46322 | G30: =E30*F30 -> 0 | J30: =H30*I30 -> 0 | K30: =G30+J30 -> 0 | M30: =M29+K30-L30 -> 180610.45
... A34: 31 | B34: 46326 | G34: =E34*F34 -> 0 | J34: =H34*I34 -> 0 | K34: =G34+J34 -> 0 | M34: =M33+K34-L34 -> 180610.45
A35: 32 | G35: =E35*F35 -> 0 | J35: =H35*I35 -> 0 | K35: =G35+J35 -> 0 | M35: =M34+K35-L35 -> 180610.45
E38: =SUM(E4:E35) -> 1800 | G38: =SUM(G4:G35) -> 180054 | H38: =SUM(H4:H35) -> 105 | J38: =SUM(J4:J35) -> 11764.2 | K38: =SUM(K4:K35) -> 191818.2 | L38: =SUM(L4:L35) -> 200000

Sheet  Chellakere-PKG-9
A1: Chellakere-PKG-09
A2: S.No | B2: Date | C2: GRN No | D2: Ind No/Bill No | E2: Diesel (Lts) | F2: Price | G2: Amount | H2: Petrol (Lts) | I2: Price | J2: Amount | K2: Total amount | L2: Amount paid | M2: As on Date | N2: Remarks
A3: Opening Balance
A4: 1 | B4: 46296 | E4: 49.99 | F4: 100.03 | G4: =E4*F4 -> 5000.4997 | H4: 12 | I4: 112.04 | J4: =H4*I4 -> 1344.48 | K4: =G4+J4 -> 6344.9797 | L4: 6344.9797 | M4: =M3+K4-L4 -> 0
A5: 2 | B5: 46297 | G5: =E5*F5 -> 0 | J5: =H5*I5 -> 0 | K5: =G5+J5 -> 0 | M5: =M4+K5-L5 -> 0
A6: 3 | B6: 46298 | G6: =E6*F6 -> 0 | J6: =H6*I6 -> 0 | K6: =G6+J6 -> 0 | M6: =M5+K6-L6 -> 0
A7: 4 | B7: 46299 | G7: =E7*F7 -> 0 | J7: =H7*I7 -> 0 | K7: =G7+J7 -> 0 | M7: =M6+K7-L7 -> 0
A8: 5 | B8: 46300 | G8: =E8*F8 -> 0 | J8: =H8*I8 -> 0 | K8: =G8+J8 -> 0 | M8: =M7+K8-L8 -> 0
A9: 6 | B9: 46301 | G9: =E9*F9 -> 0 | H9: 6 | I9: 112.04 | J9: =H9*I9 -> 672.24 | K9: =G9+J9 -> 672.24 | L9: 672.24 | M9: =M8+K9-L9 -> 0
A10: 7 | B10: 46302 | G10: =E10*F10 -> 0 | J10: =H10*I10 -> 0 | K10: =G10+J10 -> 0 | M10: =M9+K10-L10 -> 0
A11: 8 | B11: 46303 | E11: 47.43 | F11: 100.03 | G11: =E11*F11 -> 4744.4229 | J11: =H11*I11 -> 0 | K11: =G11+J11 -> 4744.4229 | L11: 4744.4229 | M11: =M10+K11-L11 -> 0
A12: 9 | B12: 46304 | G12: =E12*F12 -> 0 | J12: =H12*I12 -> 0 | K12: =G12+J12 -> 0 | M12: =M11+K12-L12 -> 0
A13: 10 | B13: 46305 | G13: =E13*F13 -> 0 | J13: =H13*I13 -> 0 | K13: =G13+J13 -> 0 | M13: =M12+K13-L13 -> 0
A14: 11 | B14: 46306 | G14: =E14*F14 -> 0 | J14: =H14*I14 -> 0 | K14: =G14+J14 -> 0 | M14: =M13+K14-L14 -> 0
A15: 12 | B15: 46307 | E15: 106.8 | F15: 100.025 | G15: =E15*F15 -> 10682.67 | J15: =H15*I15 -> 0 | K15: =G15+J15 -> 10682.67 | M15: =M14+K15-L15 -> 10682.67
A16: 13 | B16: 46308 | G16: =E16*F16 -> 0 | J16: =H16*I16 -> 0 | K16: =G16+J16 -> 0 | M16: =M15+K16-L16 -> 10682.67
A17: 14 | B17: 46309 | G17: =E17*F17 -> 0 | J17: =H17*I17 -> 0 | K17: =G17+J17 -> 0 | M17: =M16+K17-L17 -> 10682.67
A18: 15 | B18: 46310 | E18: 79.2 | F18: 100.03 | G18: =E18*F18 -> 7922.376 | H18: 12 | I18: 112.04 | J18: =H18*I18 -> 1344.48 | K18: =G18+J18 -> 9266.856 | L18: 9266.856 | M18: =M17+K18-L18 -> 10682.67
A19: 16 | B19: 46311 | G19: =E19*F19 -> 0 | J19: =H19*I19 -> 0 | K19: =G19+J19 -> 0 | M19: =M18+K19-L19 -> 10682.67
A20: 17 | B20: 46312 | G20: =E20*F20 -> 0 | J20: =H20*I20 -> 0 | K20: =G20+J20 -> 0 | M20: =M19+K20-L20 -> 10682.67
A21: 18 | B21: 46313 | G21: =E21*F21 -> 0 | J21: =H21*I21 -> 0 | K21: =G21+J21 -> 0 | M21: =M20+K21-L21 -> 10682.67
A22: 19 | B22: 46314 | G22: =E22*F22 -> 0 | J22: =H22*I22 -> 0 | K22: =G22+J22 -> 0 | M22: =M21+K22-L22 -> 10682.67
B23: 46315 | G23: =E23*F23 -> 0 | K23: =G23+J23 -> 0 | M23: =M22+K23-L23 -> 10682.67
A24: 20 | B24: 46316 | G24: =E24*F24 -> 0 | J24: =H24*I24 -> 0 | K24: =G24+J24 -> 0 | M24: =M23+K24-L24 -> 10682.67
A25: 21 | B25: 46317 | G25: =E25*F25 -> 0 | J25: =H25*I25 -> 0 | K25: =G25+J25 -> 0 | M25: =M24+K25-L25 -> 10682.67
B26: 46318 | G26: =E26*F26 -> 0 | J26: =H26*I26 -> 0 | K26: =G26+J26 -> 0 | M26: =M25+K26-L26 -> 10682.67
A27: 22 | B27: 46319 | G27: =E27*F27 -> 0 | J27: =H27*I27 -> 0 | K27: =G27+J27 -> 0 | M27: =M26+K27-L27 -> 10682.67
B28: 46320 | J28: =H28*I28 -> 0 | K28: =G28+J28 -> 0 | M28: =M27+K28-L28 -> 10682.67
A29: 23 | B29: 46321 | G29: =E29*F29 -> 0 | J29: =H29*I29 -> 0 | K29: =G29+J29 -> 0 | M29: =M28+K29-L29 -> 10682.67
A30: 24 | B30: 46322 | G30: =E30*F30 -> 0 | J30: =H30*I30 -> 0 | K30: =G30+J30 -> 0 | M30: =M29+K30-L30 -> 10682.67
A31: 25 | B31: 46323 | G31: =E31*F31 -> 0 | J31: =H31*I31 -> 0 | K31: =G31+J31 -> 0 | M31: =M30+K31-L31 -> 10682.67
A32: 26 | B32: 46324 | G32: =E32*F32 -> 0 | J32: =H32*I32 -> 0 | K32: =G32+J32 -> 0 | M32: =M31+K32-L32 -> 10682.67
A33: 27 | B33: 46325 | G33: =E33*F33 -> 0 | J33: =H33*I33 -> 0 | K33: =G33+J33 -> 0 | M33: =M32+K33-L33 -> 10682.67
A34: 28 | B34: 46326 | G34: =E34*F34 -> 0 | J34: =H34*I34 -> 0 | K34: =G34+J34 -> 0 | M34: 0
A35: 29 | G35: =E35*F35 -> 0 | J35: =H35*I35 -> 0 | K35: =G35+J35 -> 0
A36: 30 | G36: =E36*F36 -> 0 | J36: =H36*I36 -> 0 | K36: =G36+J36 -> 0
A37: 31 | G37: =E37*F37 -> 0 | J37: =H37*I37 -> 0 | K37: =G37+J37 -> 0
E38: =SUM(E4:E37) -> 283.42 | G38: =SUM(G4:G37) -> 28349.969 | H38: =SUM(H4:H37) -> 30 | J38: =SUM(J4:J37) -> 3361.2 | K38: =SUM(K4:K37) -> 31711.169 | L38: =SUM(L4:L37) -> 21028.499

Sheet  Chennagiri
A1: Chennagiri
A2: S.No | B2: Date | C2: GRN No | D2: Ind No/Bill No | E2: Diesel (Lts) | F2: Price | G2: Amount | H2: Petrol (Lts) | I2: Price | J2: Amount | K2: Total amount | L2: Amount paid | M2: As on Date | N2: Remarks
A3: Opening Balance
A4: 1 | B4: 46296 | E4: 75 | F4: 99.88 | G4: =E4*F4 -> 7491 | J4: =H4*I4 -> 0 | K4: =G4+J4 -> 7491 | L4: 7491 | M4: =M3+K4-L4 -> 0
A5: 2 | B5: 46297 | G5: =E5*F5 -> 0 | J5: =H5*I5 -> 0 | K5: =G5+J5 -> 0 | M5: =M4+K5-L5 -> 0
A6: 3 | B6: 46298 | G6: =E6*F6 -> 0 | J6: =H6*I6 -> 0 | K6: =G6+J6 -> 0 | M6: =M5+K6-L6 -> 0
A7: 4 | B7: 46299 | E7: 50 | F7: 99.84 | G7: =E7*F7 -> 4992 | J7: =H7*I7 -> 0 | K7: =G7+J7 -> 4992 | L7: 4992 | M7: =M6+K7-L7 -> 0
A8: 5 | B8: 46300 | G8: =E8*F8 -> 0 | J8: =H8*I8 -> 0 | K8: =G8+J8 -> 0 | M8: =M7+K8-L8 -> 0
A9: 6 | B9: 46301 | E9: 100 | F9: 99.84 | G9: =E9*F9 -> 9984 | J9: =H9*I9 -> 0 | K9: =G9+J9 -> 9984 | L9: 9984 | M9: =M8+K9-L9 -> 0
A10: 7 | B10: 46302 | E10: 30 | F10: 99.84 | G10: =E10*F10 -> 2995.2 | J10: =H10*I10 -> 0 | K10: =G10+J10 -> 2995.2 | L10: 2995.2 | M10: =M9+K10-L10 -> 0
A11: 8 | B11: 46303 | G11: =E11*F11 -> 0 | J11: =H11*I11 -> 0 | K11: =G11+J11 -> 0 | M11: =M10+K11-L11 -> 0
A12: 9 | B12: 46304 | E12: 100 | F12: 99.84 | G12: =E12*F12 -> 9984 | J12: =H12*I12 -> 0 | K12: =G12+J12 -> 9984 | L12: 9984 | M12: =M11+K12-L12 -> 0
A13: 10 | B13: 46305 | G13: =E13*F13 -> 0 | J13: =H13*I13 -> 0 | K13: =G13+J13 -> 0 | M13: =M12+K13-L13 -> 0
A14: 11 | B14: 46306 | G14: =E14*F14 -> 0 | J14: =H14*I14 -> 0 | K14: =G14+J14 -> 0 | M14: =M13+K14-L14 -> 0
A15: 12 | B15: 46307 | E15: 110 | F15: 99.85 | G15: =E15*F15 -> 10983.5 | H15: 35 | I15: 112.03 | J15: =H15*I15 -> 3921.05 | K15: =G15+J15 -> 14904.55 | L15: 14904.55 | M15: =M14+K15-L15 -> 0
A16: 13 | B16: 46308 | G16: =E16*F16 -> 0 | J16: =H16*I16 -> 0 | K16: =G16+J16 -> 0 | M16: =M15+K16-L16 -> 0
A17: 14 | B17: 46309 | E17: 150 | F17: 99.88 | G17: =E17*F17 -> 14982 | J17: =H17*I17 -> 0 | K17: =G17+J17 -> 14982 | L17: 14982 | M17: =M16+K17-L17 -> 0
A18: 15 | B18: 46310 | G18: =E18*F18 -> 0 | J18: =H18*I18 -> 0 | K18: =G18+J18 -> 0 | M18: =M17+K18-L18 -> 0
A19: 16 | B19: 46311 | G19: =E19*F19 -> 0 | J19: =H19*I19 -> 0 | K19: =G19+J19 -> 0 | M19: =M18+K19-L19 -> 0
A20: 17 | B20: 46312 | G20: =E20*F20 -> 0 | J20: =H20*I20 -> 0 | K20: =G20+J20 -> 0 | M20: =M19+K20-L20 -> 0
A21: 18 | B21: 46313 | G21: =E21*F21 -> 0 | J21: =H21*I21 -> 0 | K21: =G21+J21 -> 0 | M21: =M20+K21-L21 -> 0
A22: 19 | B22: 46314 | G22: =E22*F22 -> 0 | J22: =H22*I22 -> 0 | K22: =G22+J22 -> 0 | M22: =M21+K22-L22 -> 0
A23: 20 | B23: 46315 | G23: =E23*F23 -> 0 | J23: =H23*I23 -> 0 | K23: =G23+J23 -> 0 | M23: =M22+K23-L23 -> 0
A24: 21 | B24: 46316 | G24: =E24*F24 -> 0 | J24: =H24*I24 -> 0 | K24: =G24+J24 -> 0 | M24: =M23+K24-L24 -> 0
A25: 22 | B25: 46317 | G25: =E25*F25 -> 0 | J25: =H25*I25 -> 0 | K25: =G25+J25 -> 0 | M25: =M24+K25-L25 -> 0
A26: 23 | B26: 46318 | G26: =E26*F26 -> 0 | J26: =H26*I26 -> 0 | K26: =G26+J26 -> 0 | M26: =M25+K26-L26 -> 0
A27: 24 | B27: 46319 | G27: =E27*F27 -> 0 | J27: =H27*I27 -> 0 | K27: =G27+J27 -> 0 | M27: =M26+K27-L27 -> 0
A28: 25 | B28: 46320 | G28: =E28*F28 -> 0 | J28: =H28*I28 -> 0 | K28: =G28+J28 -> 0 | M28: 0
A29: 26 | B29: 46321 | G29: =E29*F29 -> 0 | J29: =H29*I29 -> 0 | K29: =G29+J29 -> 0 | M29: 0
A30: 27 | B30: 46322 | G30: =E30*F30 -> 0 | J30: =H30*I30 -> 0 | K30: =G30+J30 -> 0 | M30: 0
A31: 28 | B31: 46323 | G31: =E31*F31 -> 0 | J31: =H31*I31 -> 0 | K31: =G31+J31 -> 0 | M31: 0
A32: 29 | B32: 46324 | G32: =E32*F32 -> 0 | J32: =H32*I32 -> 0 | K32: =G32+J32 -> 0
A33: 30 | B33: 46325 | G33: =E33*F33 -> 0 | J33: =H33*I33 -> 0 | K33: =G33+J33 -> 0
A34: 31 | B34: 46326 | G34: =E34*F34 -> 0 | J34: =H34*I34 -> 0 | K34: =G34+J34 -> 0
E35: =SUM(E4:E34) -> 615 | G35: =SUM(G4:G34) -> 61411.7 | H35: =SUM(H4:H34) -> 35 | J35: =SUM(J4:J34) -> 3921.05 | K35: =SUM(K4:K34) -> 65332.75 | L35: =SUM(L4:L34) -> 65332.75

Sheet Khanapur
A1: V.V.Varde
A2: S.No | B2: Date | C2: GRN No | D2: Ind No/Bill No | E2: Diesel (Lts) | F2: Price | G2: Amount | H2: Petrol (Lts) | I2: Price | J2: Amount | K2: Total amount | L2: Date of payment | M2: Amount paid | N2: Remarks
C3: Opening Balance | M3: 120785.13
A4: 1 | B4: 46296 | E4: 71.08 | F4: 98.96 | G4: =E4*F4 -> 7034.0768 | H4: 30 | I4: 110.74 | J4: =H4*I4 -> 3322.2 | K4: =G4+J4 -> 10356.277 | M4: =M3+K4-L4 -> 131141.41
A5: 2 | B5: 46297 | G5: =E5*F5 -> 0 | H5: 5 | I5: 110.74 | J5: =H5*I5 -> 553.7 | K5: =G5+J5 -> 553.7 | M5: =M4+K5-L5 -> 131695.11
A6: 3 | B6: 46298 | G6: =E6*F6 -> 0 | J6: =H6*I6 -> 0 | K6: =G6+J6 -> 0 | M6: =M5+K6-L6 -> 131695.11
A7: 4 | B7: 46299 | G7: =E7*F7 -> 0 | H7: 5 | I7: 110.74 | J7: =H7*I7 -> 553.7 | K7: =G7+J7 -> 553.7 | M7: =M6+K7-L7 -> 132248.81
A8: 5 | B8: 46300 | E8: 35 | F8: 98.96 | G8: =E8*F8 -> 3463.6 | J8: =H8*I8 -> 0 | K8: =G8+J8 -> 3463.6 | M8: =M7+K8-L8 -> 135712.41
A9: 6 | B9: 46301 | E9: 19.77 | F9: 98.69 | G9: =E9*F9 -> 1951.1013 | J9: =H9*I9 -> 0 | K9: =G9+J9 -> 1951.1013 | M9: =M8+K9-L9 -> 137663.51
A10: 7 | B10: 46302 | G10: =E10*F10 -> 0 | J10: =H10*I10 -> 0 | K10: =G10+J10 -> 0 | M10: =M9+K10-L10 -> 137663.51
A11: 8 | B11: 46303 | E11: 30 | F11: 98.69 | G11: =E11*F11 -> 2960.7 | H11: 15 | I11: 110.74 | J11: =H11*I11 -> 1661.1 | K11: =G11+J11 -> 4621.8 | M11: =M10+K11-L11 -> 142285.31
A12: 9 | B12: 46304 | G12: =E12*F12 -> 0 | J12: =H12*I12 -> 0 | K12: =G12+J12 -> 0 | M12: =M11+K12-L12 -> 142285.31
A13: 10 | B13: 46305 | G13: =E13*F13 -> 0 | J13: =H13*I13 -> 0 | K13: =G13+J13 -> 0 | L13: 100000 | M13: =M12+K13-L13 -> 42285.307
A14: 11 | B14: 46306 | G14: =E14*F14 -> 0 | J14: =H14*I14 -> 0 | K14: =G14+J14 -> 0 | M14: =M13+K14-L14 -> 42285.307
A15: 12 | B15: 46307 | E15: 69.75 | F15: 98.69 | G15: =E15*F15 -> 6883.6275 | J15: =H15*I15 -> 0 | K15: =G15+J15 -> 6883.6275 | M15: =M14+K15-L15 -> 49168.935
A16: 13 | B16: 46308 | G16: =E16*F16 -> 0 | J16: =H16*I16 -> 0 | K16: =G16+J16 -> 0 | M16: =M15+K16-L16 -> 49168.935
A17: 14 | B17: 46309 | G17: =E17*F17 -> 0 | J17: =H17*I17 -> 0 | K17: =G17+J17 -> 0 | M17: =M16+K17-L17 -> 49168.935
A18: 15 | B18: 46310 | E18: 20 | F18: 98.69 | G18: =E18*F18 -> 1973.8 | H18: 5 | I18: 110.74 | J18: =H18*I18 -> 553.7 | K18: =G18+J18 -> 2527.5 | M18: =M17+K18-L18 -> 51696.435
A19: 16 | B19: 46311 | G19: =E19*F19 -> 0 | J19: =H19*I19 -> 0 | K19: =G19+J19 -> 0 | M19: =M18+K19-L19 -> 51696.435
A20: 17 | B20: 46312 | G20: =E20*F20 -> 0 | J20: =H20*I20 -> 0 | K20: =G20+J20 -> 0 | M20: =M19+K20-L20 -> 51696.435
A21: 18 | B21: 46313 | G21: =E21*F21 -> 0 | J21: =H21*I21 -> 0 | K21: =G21+J21 -> 0 | M21: =M20+K21-L21 -> 51696.435
A22: 19 | B22: 46314 | G22: =E22*F22 -> 0 | J22: =H22*I22 -> 0 | K22: =G22+J22 -> 0 | M22: =M21+K22-L22 -> 51696.435
A23: 20 | B23: 46315 | G23: =E23*F23 -> 0 | J23: =H23*I23 -> 0 | K23: =G23+J23 -> 0 | M23: =M22+K23-L23 -> 51696.435
A24: 21 | B24: 46316 | G24: =E24*F24 -> 0 | J24: =H24*I24 -> 0 | K24: =G24+J24 -> 0 | M24: =M23+K24-L24 -> 51696.435
A25: 22 | B25: 46317 | G25: =E25*F25 -> 0 | J25: =H25*I25 -> 0 | K25: =G25+J25 -> 0 | M25: =M24+K25-L25 -> 51696.435
A26: 23 | B26: 46318 | G26: =E26*F26 -> 0 | J26: =H26*I26 -> 0 | K26: =G26+J26 -> 0 | M26: =M25+K26-L26 -> 51696.435
A27: 24 | B27: 46319 | G27: =E27*F27 -> 0 | J27: =H27*I27 -> 0 | K27: =G27+J27 -> 0 | M27: =M26+K27-L27 -> 51696.435
A28: 25 | B28: 46320 | G28: =E28*F28 -> 0 | J28: =H28*I28 -> 0 | K28: =G28+J28 -> 0 | M28: =M27+K28-L28 -> 51696.435
A29: 26 | B29: 46321 | G29: =F29*E29 -> 0 | J29: =H29*I29 -> 0 | K29: =G29+J29 -> 0 | M29: =M28+K29-L29 -> 51696.435
A30: 27 | B30: 46322 | G30: =E30*F30 -> 0 | J30: =H30*I30 -> 0 | K30: =G30+J30 -> 0 | M30: =M29+K30-L30 -> 51696.435
A31: 28 | B31: 46323 | G31: =E31*F31 -> 0 | J31: =H31*I31 -> 0 | K31: =G31+J31 -> 0 | M31: =M30+K31-L31 -> 51696.435
A32: 29 | B32: 46324 | G32: =F32*E32 -> 0 | J32: =H32*I32 -> 0 | K32: =G32+J32 -> 0 | M32: =M31+K32-L32 -> 51696.435
A33: 30 | B33: 46325 | G33: =F33*E33 -> 0 | J33: =H33*I33 -> 0 | K33: =G33+J33 -> 0 | M33: =M32+K33-L33 -> 51696.435
A34: 31 | B34: 46326 | G34: =F34*E34 -> 0 | J34: =H34*I34 -> 0 | K34: =G34+J34 -> 0 | M34: =M33+K34-L34 -> 51696.435
E35: =SUM(E4:E34) -> 245.6 | G35: =SUM(G4:G34) -> 24266.906 | H35: =SUM(H4:H34) -> 60 | J35: =SUM(J4:J34) -> 6644.4 | K35: =SUM(K4:K34) -> 30911.306 | L35: =SUM(L4:L34) -> 100000 | M35: =SUM(M4:M34) -> 2333307.3

Sheet Munavali-2
A1: Shiri Shiva Petroluem
A2: S.No | B2: Date | C2: GRN No | D2: Ind No/Bill No | E2: Diesel (Lts) | F2: Price | G2: Amount | H2: Petrol (Lts) | I2: Price | J2: Amount | K2: Total amount | L2: Amount paid | M2: As on date | N2: Remarks
C3: Opening Balance | M3: 263421.5
A4: 1 | B4: 46296 | G4: =E4*F4 -> 0 | J4: =H4*I4 -> 0 | K4: =G4+J4 -> 0 | M4: =M3+K4-L4 -> 263421.5
A5: 2 | B5: 46297 | G5: =E5*F5 -> 0 | J5: =H5*I5 -> 0 | K5: =G5+J5 -> 0 | M5: =M4+K5-L5 -> 263421.5
A6: 3 | B6: 46298 | G6: =E6*F6 -> 0 | J6: =H6*I6 -> 0 | K6: =G6+J6 -> 0 | M6: =M5+K6-L6 -> 263421.5
A7: 4 | B7: 46299 | G7: =E7*F7 -> 0 | J7: =H7*I7 -> 0 | K7: =G7+J7 -> 0 | M7: =M6+K7-L7 -> 263421.5
A8: 5 | B8: 46300 | G8: =E8*F8 -> 0 | J8: =H8*I8 -> 0 | K8: =G8+J8 -> 0 | M8: =M7+K8-L8 -> 263421.5
A9: 6 | B9: 46301 | E9: 1000 | F9: 99.35 | G9: =E9*F9 -> 99350 | J9: =H9*I9 -> 0 | K9: =G9+J9 -> 99350 | M9: =M8+K9-L9 -> 362771.5
A10: 7 | B10: 46302 | G10: =E10*F10 -> 0 | J10: =H10*I10 -> 0 | K10: =G10+J10 -> 0 | M10: =M9+K10-L10 -> 362771.5
A11: 8 | B11: 46303 | G11: =E11*F11 -> 0 | J11: =H11*I11 -> 0 | K11: =G11+J11 -> 0 | M11: =M10+K11-L11 -> 362771.5
A12: 9 | B12: 46304 | G12: =E12*F12 -> 0 | J12: =H12*I12 -> 0 | K12: =G12+J12 -> 0 | M12: =M11+K12-L12 -> 362771.5
A13: 10 | B13: 46305 | G13: =E13*F13 -> 0 | J13: =H13*I13 -> 0 | K13: =G13+J13 -> 0 | M13: =M12+K13-L13 -> 362771.5
A14: 11 | B14: 46306 | G14: =E14*F14 -> 0 | J14: =H14*I14 -> 0 | K14: =G14+J14 -> 0 | M14: =M13+K14-L14 -> 362771.5
A15: 12 | B15: 46307 | G15: =E15*F15 -> 0 | J15: =H15*I15 -> 0 | K15: =G15+J15 -> 0 | M15: =M14+K15-L15 -> 362771.5
A16: 13 | B16: 46308 | E16: 1000 | F16: 99.35 | G16: =E16*F16 -> 99350 | J16: =H16*I16 -> 0 | K16: =G16+J16 -> 99350 | M16: =M15+K16-L16 -> 462121.5
A17: 14 | B17: 46309 | G17: =E17*F17 -> 0 | J17: =H17*I17 -> 0 | K17: =G17+J17 -> 0 | M17: =M16+K17-L17 -> 462121.5
A18: 15 | B18: 46310 | G18: =E18*F18 -> 0 | J18: =H18*I18 -> 0 | K18: =G18+J18 -> 0 | L18: 363000 | M18: =M17+K18-L18 -> 99121.5
A19: 16 | B19: 46311 | G19: =E19*F19 -> 0 | J19: =H19*I19 -> 0 | K19: =G19+J19 -> 0 | M19: =M18+K19-L19 -> 99121.5
A20: 17 | B20: 46312 | G20: =E20*F20 -> 0 | J20: =H20*I20 -> 0 | K20: =G20+J20 -> 0 | M20: =M19+K20-L20 -> 99121.5
A21: 18 | B21: 46313 | G21: =E21*F21 -> 0 | J21: =H21*I21 -> 0 | K21: =G21+J21 -> 0 | M21: =M20+K21-L21 -> 99121.5
A22: 19 | B22: 46314 | G22: =E22*F22 -> 0 | J22: =H22*I22 -> 0 | K22: =G22+J22 -> 0 | M22: =M21+K22-L22 -> 99121.5
A23: 20 | B23: 46315 | G23: =E23*F23 -> 0 | J23: 0 | K23: =G23+J23 -> 0 | M23: =M22+K23-L23 -> 99121.5
A24: 21 | B24: 46316 | G24: =E24*F24 -> 0 | J24: =H24*I24 -> 0 | K24: =G24+J24 -> 0 | M24: =M23+K24-L24 -> 99121.5
A25: 22 | B25: 46317 | G25: =E25*F25 -> 0 | J25: =H25*I25 -> 0 | K25: =G25+J25 -> 0 | M25: =M24+K25-L25 -> 99121.5
A26: 23 | B26: 46318 | G26: =E26*F26 -> 0 | J26: =H26*I26 -> 0 | K26: =G26+J26 -> 0 | M26: =M25+K26-L26 -> 99121.5
A27: 24 | B27: 46319 | G27: =E27*F27 -> 0 | J27: =H27*I27 -> 0 | K27: =G27+J27 -> 0 | M27: =M26+K27-L27 -> 99121.5
A28: 25 | B28: 46320 | G28: =E28*F28 -> 0 | J28: =H28*I28 -> 0 | K28: =G28+J28 -> 0 | M28: =M27+K28-L28 -> 99121.5
A29: 26 | B29: 46321 | G29: =E29*F29 -> 0 | J29: =H29*I29 -> 0 | K29: =G29+J29 -> 0 | M29: =M28+K29-L29 -> 99121.5
A30: 27 | B30: 46322 | G30: =E30*F30 -> 0 | J30: =H30*I30 -> 0 | K30: =G30+J30 -> 0 | M30: =M29+K30-L30 -> 99121.5
A31: 28 | B31: 46323 | G31: =E31*F31 -> 0 | J31: =H31*I31 -> 0 | K31: =G31+J31 -> 0 | M31: =M30+K31-L31 -> 99121.5
A32: 29 | B32: 46324 | G32: =E32*F32 -> 0 | J32: =H32*I32 -> 0 | K32: =G32+J32 -> 0 | M32: =M31+K32-L32 -> 99121.5
A33: 30 | B33: 46325 | G33: =E33*F33 -> 0 | J33: =H33*I33 -> 0 | K33: =G33+J33 -> 0 | M33: =M32+K33-L33 -> 99121.5
A34: 31 | B34: 46326 | G34: =E34*F34 -> 0 | J34: =H34*I34 -> 0 | K34: =G34+J34 -> 0 | M34: =M33+K34-L34 -> 99121.5
A35: 32 | G35: =E35*F35 -> 0 | J35: =H35*I35 -> 0 | K35: =G35+J35 -> 0 | M35: =M34+K35-L35 -> 99121.5
A36: 33 | G36: =E36*F36 -> 0 | J36: =H36*I36 -> 0 | K36: =G36+J36 -> 0 | M36: =M35+K36-L36 -> 99121.5
A37: 34 | G37: =E37*F37 -> 0 | J37: =H37*I37 -> 0 | K37: =G37+J37 -> 0 | M37: =M36+K37-L37 -> 99121.5
A38: 35 | G38: =E38*F38 -> 0 | J38: =H38*I38 -> 0 | K38: =G38+J38 -> 0 | M38: =M37+K38-L38 -> 99121.5
A39: 36 | G39: =E39*F39 -> 0 | J39: =H39*I39 -> 0 | K39: =G39+J39 -> 0 | M39: =M38+K39-L39 -> 99121.5
E40: =SUM(E4:E39) -> 2000 | G40: =SUM(G4:G39) -> 198700 | H40: =SUM(H4:H39) -> 0 | J40: =SUM(J4:J39) -> 0 | K40: =SUM(K4:K39) -> 198700 | L40: =SUM(L4:L39) -> 363000

Sheet  Munavali
A1: DANESHWARI PETROLIUM(YERRAGATTI)
A2: S.No | B2: Date | C2: GRN No | D2: Ind No/Bill No | E2: Diesel (Lts) | F2: Price | G2: Amount | H2: Petrol (Lts) | I2: Price | J2: Amount | K2: Total amount | L2: Amount paid | M2: As on date | N2: Remarks
C3: Opening Balance | M3: 30045.067
A4: 1 | B4: 46296 | G4: =E4*F4 -> 0 | J4: =H4*I4 -> 0 | K4: =G4+J4 -> 0 | M4: =M3+K4-L4 -> 30045.067
A5: 2 | B5: 46297 | G5: =E5*F5 -> 0 | J5: =H5*I5 -> 0 | K5: =G5+J5 -> 0 | M5: =M4+K5-L5 -> 30045.067
A6: 3 | B6: 46298 | G6: =E6*F6 -> 0 | H6: 30 | I6: 111.21 | J6: =H6*I6 -> 3336.3 | K6: =G6+J6 -> 3336.3 | M6: =M5+K6-L6 -> 33381.367
A7: 4 | B7: 46299 | G7: =E7*F7 -> 0 | H7: 0 | I7: 0 | J7: =H7*I7 -> 0 | K7: =G7+J7 -> 0 | M7: =M6+K7-L7 -> 33381.367
A8: 5 | B8: 46300 | G8: =E8*F8 -> 0 | H8: 0 | I8: 0 | J8: =H8*I8 -> 0 | K8: =G8+J8 -> 0 | M8: =M7+K8-L8 -> 33381.367
A9: 6 | B9: 46301 | G9: =E9*F9 -> 0 | H9: 30 | I9: 111.21 | J9: =H9*I9 -> 3336.3 | K9: =G9+J9 -> 3336.3 | M9: =M8+K9-L9 -> 36717.667
A10: 7 | B10: 46302 | G10: =E10*F10 -> 0 | J10: =H10*I10 -> 0 | K10: =G10+J10 -> 0 | M10: =M9+K10-L10 -> 36717.667
A11: 8 | B11: 46303 | G11: =E11*F11 -> 0 | J11: =H11*I11 -> 0 | K11: =G11+J11 -> 0 | M11: =M10+K11-L11 -> 36717.667
A12: 9 | B12: 46304 | G12: =E12*F12 -> 0 | H12: 30 | I12: 111.21 | J12: =H12*I12 -> 3336.3 | K12: =G12+J12 -> 3336.3 | M12: =M11+K12-L12 -> 40053.967
A13: 10 | B13: 46305 | G13: =E13*F13 -> 0 | J13: =H13*I13 -> 0 | K13: =G13+J13 -> 0 | M13: =M12+K13-L13 -> 40053.967
A14: 11 | B14: 46306 | G14: =E14*F14 -> 0 | J14: =H14*I14 -> 0 | K14: =G14+J14 -> 0 | M14: =M13+K14-L14 -> 40053.967
A15: 12 | B15: 46307 | G15: =E15*F15 -> 0 | H15: 30 | I15: 111.21 | J15: =H15*I15 -> 3336.3 | K15: =G15+J15 -> 3336.3 | M15: =M14+K15-L15 -> 43390.267
A16: 13 | B16: 46308 | G16: =E16*F16 -> 0 | J16: =H16*I16 -> 0 | K16: =G16+J16 -> 0 | M16: =M15+K16-L16 -> 43390.267
A17: 14 | B17: 46309 | G17: =E17*F17 -> 0 | J17: =H17*I17 -> 0 | K17: =G17+J17 -> 0 | M17: =M16+K17-L17 -> 43390.267
A18: 15 | B18: 46310 | G18: =E18*F18 -> 0 | H18: 30 | I18: 111.21 | J18: =H18*I18 -> 3336.3 | K18: =G18+J18 -> 3336.3 | M18: =M17+K18-L18 -> 46726.567
A19: 16 | B19: 46311 | G19: =E19*F19 -> 0 | J19: =H19*I19 -> 0 | K19: =G19+J19 -> 0 | M19: =M18+K19-L19 -> 46726.567
A20: 17 | B20: 46312 | G20: =E20*F20 -> 0 | J20: =H20*I20 -> 0 | K20: =G20+J20 -> 0 | M20: =M19+K20-L20 -> 46726.567
A21: 18 | B21: 46313 | G21: =E21*F21 -> 0 | J21: =H21*I21 -> 0 | K21: =G21+J21 -> 0 | M21: =M20+K21-L21 -> 46726.567
A22: 19 | B22: 46314 | G22: =E22*F22 -> 0 | J22: =H22*I22 -> 0 | K22: =G22+J22 -> 0 | M22: =M21+K22-L22 -> 46726.567
A23: 20 | B23: 46315 | G23: =E23*F23 -> 0 | J23: =H23*I23 -> 0 | K23: =G23+J23 -> 0 | M23: =M22+K23-L23 -> 46726.567
A24: 22 | B24: 46316 | G24: =E24*F24 -> 0 | J24: =H24*I24 -> 0 | K24: =G24+J24 -> 0 | M24: =M23+K24-L24 -> 46726.567
A25: 23 | B25: 46317 | G25: =E25*F25 -> 0 | J25: =H25*I25 -> 0 | K25: =G25+J25 -> 0 | M25: =M24+K25-L25 -> 46726.567
A26: 24 | B26: 46318 | G26: =E26*F26 -> 0 | J26: =H26*I26 -> 0 | K26: =G26+J26 -> 0 | M26: =M25+K26-L26 -> 46726.567
A27: 25 | B27: 46319 | G27: =E27*F27 -> 0 | J27: =H27*I27 -> 0 | K27: =G27+J27 -> 0 | M27: =M26+K27-L27 -> 46726.567
A28: 26 | B28: 46320 | G28: =E28*F28 -> 0 | J28: =H28*I28 -> 0 | K28: =G28+J28 -> 0 | M28: =M27+K28-L28 -> 46726.567
A29: 27 | B29: 46321 | G29: =E29*F29 -> 0 | J29: =H29*I29 -> 0 | K29: =G29+J29 -> 0 | M29: =M28+K29-L29 -> 46726.567
A30: 28 | B30: 46322 | G30: =E30*F30 -> 0 | J30: =H30*I30 -> 0 | K30: =G30+J30 -> 0 | M30: =M29+K30-L30 -> 46726.567
... A34: 32 | B34: 46326 | G34: =E34*F34 -> 0 | J34: =H34*I34 -> 0 | K34: =G34+J34 -> 0 | M34: =M33+K34-L34 -> 46726.567
A35: 33 | G35: =E35*F35 -> 0 | J35: =H35*I35 -> 0 | K35: =G35+J35 -> 0 | M35: =M34+K35-L35 -> 46726.567
A36: 34 | G36: =E36*F36 -> 0 | J36: =H36*I36 -> 0 | K36: =G36+J36 -> 0 | M36: =M35+K36-L36 -> 46726.567
A37: 35 | G37: =E37*F37 -> 0 | J37: =H37*I37 -> 0 | K37: =G37+J37 -> 0 | M37: =M36+K37-L37 -> 46726.567
A38: 36 | G38: =E38*F38 -> 0 | J38: =H38*I38 -> 0 | K38: =G38+J38 -> 0 | M38: =M37+K38-L38 -> 46726.567
E39: =SUM(E4:E38) -> 0 | G39: =SUM(G4:G38) -> 0 | H39: =SUM(H4:H38) -> 150 | J39: =SUM(J4:J38) -> 16681.5 | K39: =SUM(K4:K38) -> 16681.5 | L39: =SUM(L4:L38) -> 0

Sheet Ugar,Khagwad,Kudichi
A1: Shiri Bhrhmanath Petrolium
A2: S.No | B2: Date | C2: GRN No | D2: Ind No/Bill No | E2: Diesel (Lts) | F2: Price | G2: Amount | H2: Petrol (Lts) | I2: Price | J2: Amount | K2: Total amount | L2: Amount paid | M2: As on Date | N2: Remarks
A3: Opening Balance | K3: 300655.8 | M3: 300655.8
A4: 1 | B4: 46296 | E4: 650 | F4: 99.74 | G4: =E4*F4 -> 64831 | H4: 55 | I4: 111.85 | J4: =H4*I4 -> 6151.75 | K4: =G4+J4 -> 70982.75 | M4: =M3+K4-L4 -> 371638.55
A5: 2 | B5: 46297 | E5: 50 | F5: 99.74 | G5: =E5*F5 -> 4987 | J5: =H5*I5 -> 0 | K5: =G5+J5 -> 4987 | M5: =M4+K5-L5 -> 376625.55
A6: 3 | B6: 46298 | E6: 200 | F6: 99.74 | G6: =E6*F6 -> 19948 | H6: 45 | I6: 111.85 | J6: =H6*I6 -> 5033.25 | K6: =G6+J6 -> 24981.25 | M6: =M5+K6-L6 -> 401606.8
A7: 4 | B7: 46299 | E7: 28 | F7: 99.74 | G7: =E7*F7 -> 2792.72 | J7: =H7*I7 -> 0 | K7: =G7+J7 -> 2792.72 | M7: =M6+K7-L7 -> 404399.52
A8: 5 | B8: 46300 | G8: =E8*F8 -> 0 | J8: =H8*I8 -> 0 | K8: =G8+J8 -> 0 | M8: =M7+K8-L8 -> 404399.52
A9: 6 | B9: 46301 | E9: 70 | F9: 99.74 | G9: =E9*F9 -> 6981.8 | J9: =H9*I9 -> 0 | K9: =G9+J9 -> 6981.8 | M9: =M8+K9-L9 -> 411381.32
A10: 7 | B10: 46302 | E10: 435 | F10: 99.74 | G10: =E10*F10 -> 43386.9 | H10: 35 | I10: 111.86 | J10: =H10*I10 -> 3915.1 | K10: =G10+J10 -> 47302 | M10: =M9+K10-L10 -> 458683.32
A11: 8 | B11: 46303 | E11: 44.21 | F11: 98.95 | G11: =E11*F11 -> 4374.5795 | J11: =H11*I11 -> 0 | K11: =G11+J11 -> 4374.5795 | L11: 4374.5795 | M11: =M10+K11-L11 -> 458683.32 | N11: BHAVANI PETROLEUMS
B12: 46303 | E12: 500 | F12: 99.74 | G12: =E12*F12 -> 49870 | H12: 35 | I12: 111.86 | J12: =H12*I12 -> 3915.1 | K12: =G12+J12 -> 53785.1 | M12: =M11+K12-L12 -> 512468.42
A13: 9 | B13: 46304 | E13: 430.24 | F13: 99.74 | G13: =E13*F13 -> 42912.138 | H13: 35 | I13: 111.86 | J13: =H13*I13 -> 3915.1 | K13: =G13+J13 -> 46827.238 | M13: =M12+K13-L13 -> 559295.66
A14: 10 | B14: 46305 | E14: 15 | F14: 99.74 | G14: =E14*F14 -> 1496.1 | J14: =H14*I14 -> 0 | K14: =G14+J14 -> 1496.1 | M14: =M13+K14-L14 -> 560791.76
A15: 11 | B15: 46306 | G15: =E15*F15 -> 0 | H15: 5 | I15: 111.85 | J15: =H15*I15 -> 559.25 | K15: =G15+J15 -> 559.25 | M15: =M14+K15-L15 -> 561351.01
A16: 12 | B16: 46307 | G16: =E16*F16 -> 0 | J16: =H16*I16 -> 0 | K16: =G16+J16 -> 0 | M16: =M15+K16-L16 -> 561351.01
A17: 13 | B17: 46308 | E17: 70 | F17: 99.74 | G17: =E17*F17 -> 6981.8 | H17: 5 | I17: 111.85 | J17: =H17*I17 -> 559.25 | K17: =G17+J17 -> 7541.05 | M17: =M16+K17-L17 -> 568892.06
A18: 14 | B18: 46309 | E18: 190 | F18: 99.74 | G18: =E18*F18 -> 18950.6 | J18: =H18*I18 -> 0 | K18: =G18+J18 -> 18950.6 | L18: 157060.91 | M18: =M17+K18-L18 -> 430781.75
A19: 15 | B19: 46310 | E19: 40 | F19: 99.74 | G19: =E19*F19 -> 3989.6 | J19: =H19*I19 -> 0 | K19: =G19+J19 -> 3989.6 | M19: =M18+K19-L19 -> 434771.35
A20: 16 | B20: 46311 | G20: =E20*F20 -> 0 | J20: =H20*I20 -> 0 | K20: =G20+J20 -> 0 | M20: =M19+K20-L20 -> 434771.35
A21: 17 | B21: 46312 | G21: =E21*F21 -> 0 | J21: =H21*I21 -> 0 | K21: =G21+J21 -> 0 | M21: =M20+K21-L21 -> 434771.35
A22: 18 | B22: 46313 | G22: =E22*F22 -> 0 | J22: =H22*I22 -> 0 | K22: =G22+J22 -> 0 | M22: =M21+K22-L22 -> 434771.35
A23: 19 | B23: 46314 | G23: =E23*F23 -> 0 | J23: =H23*I23 -> 0 | K23: =G23+J23 -> 0 | M23: =M22+K23-L23 -> 434771.35
A24: 20 | B24: 46315 | G24: =E24*F24 -> 0 | J24: =H24*I24 -> 0 | K24: =G24+J24 -> 0 | M24: =M23+K24-L24 -> 434771.35
A25: 21 | B25: 46316 | G25: =E25*F25 -> 0 | J25: =H25*I25 -> 0 | K25: =G25+J25 -> 0 | M25: =M24+K25-L25 -> 434771.35
A26: 22 | B26: 46317 | G26: =E26*F26 -> 0 | J26: =H26*I26 -> 0 | K26: =G26+J26 -> 0 | M26: =M25+K26-L26 -> 434771.35
A27: 23 | B27: 46318 | G27: =E27*F27 -> 0 | J27: =H27*I27 -> 0 | K27: =G27+J27 -> 0 | M27: =M26+K27-L27 -> 434771.35
A28: 24 | B28: 46319 | G28: =E28*F28 -> 0 | J28: =H28*I28 -> 0 | K28: =G28+J28 -> 0 | M28: =M27+K28-L28 -> 434771.35
A29: 25 | B29: 46320 | G29: =E29*F29 -> 0 | J29: =H29*I29 -> 0 | K29: =G29+J29 -> 0 | M29: =M28+K29-L29 -> 434771.35
A30: 26 | B30: 46321 | G30: =E30*F30 -> 0 | J30: =H30*I30 -> 0 | K30: =G30+J30 -> 0 | M30: =M29+K30-L30 -> 434771.35
A31: 27 | B31: 46322 | G31: =E31*F31 -> 0 | J31: =H31*I31 -> 0 | K31: =G31+J31 -> 0 | M31: =M30+K31-L31 -> 434771.35
... A35: 31 | B35: 46326 | G35: =E35*F35 -> 0 | J35: =H35*I35 -> 0 | K35: =G35+J35 -> 0 | M35: =M34+K35-L35 -> 434771.35
A36: 32 | G36: =E36*F36 -> 0 | J36: =H36*I36 -> 0 | K36: =G36+J36 -> 0 | M36: =M35+K36-L36 -> 434771.35
A37: 33 | G37: =E37*F37 -> 0 | J37: =H37*I37 -> 0 | K37: =G37+J37 -> 0 | M37: =M36+K37-L37 -> 434771.35
E38: =SUM(E4:E37) -> 2722.45 | G38: =SUM(G4:G37) -> 271502.24 | H38: =SUM(H4:H37) -> 215 | J38: =SUM(J4:J37) -> 24048.8 | K38: =SUM(K4:K37) -> 295551.04 | L38: =SUM(L4:L37) -> 161435.49

Sheet shedbal
A1: VARAD PETROLEUM SHEDBAL
A2: S.No | B2: Date | C2: GRN No | D2: Ind no/Bill No | E2: Diesel (Lts) | F2: Price | G2: Amount | H2: Petrol (Lts) | I2: Price | J2: Amount | K2: Total amount | L2: Amount paid | M2: As on Date | N2: Remarks
A3: Opening Balance | M3: 158612.05
A4: 1 | B4: 46296 | E4: 136 | F4: 99.73 | G4: =E4*F4 -> 13563.28 | J4: =H4*I4 -> 0 | K4: =G4+J4 -> 13563.28 | M4: =M3+K4-L4 -> 172175.33
A5: 2 | B5: 46297 | G5: =E5*F5 -> 0 | J5: =H5*I5 -> 0 | K5: =G5+J5 -> 0 | M5: =M4+K5-L5 -> 172175.33
A6: 3 | B6: 46298 | G6: =E6*F6 -> 0 | H6: 10 | I6: 111.85 | J6: =H6*I6 -> 1118.5 | K6: =G6+J6 -> 1118.5 | M6: =M5+K6-L6 -> 173293.83
A7: 4 | B7: 46299 | G7: =E7*F7 -> 0 | J7: =H7*I7 -> 0 | K7: =G7+J7 -> 0 | M7: =M6+K7-L7 -> 173293.83
A8: 5 | B8: 46300 | E8: 200 | F8: 99.73 | G8: =E8*F8 -> 19946 | J8: =H8*I8 -> 0 | K8: =G8+J8 -> 19946 | M8: =M7+K8-L8 -> 193239.83
A9: 6 | B9: 46301 | E9: 40 | F9: 99.73 | G9: =E9*F9 -> 3989.2 | H9: 10 | I9: 111.85 | J9: =H9*I9 -> 1118.5 | K9: =G9+J9 -> 5107.7 | M9: =M8+K9-L9 -> 198347.53
A10: 7 | B10: 46302 | E10: 100 | F10: 99.73 | G10: =E10*F10 -> 9973 | H10: 7 | I10: 111.85 | J10: =H10*I10 -> 782.95 | K10: =G10+J10 -> 10755.95 | M10: =M9+K10-L10 -> 209103.48
A11: 8 | B11: 46303 | G11: =E11*F11 -> 0 | J11: =H11*I11 -> 0 | K11: =G11+J11 -> 0 | M11: =M10+K11-L11 -> 209103.48
A12: 9 | B12: 46304 | E12: 100 | F12: 99.73 | G12: =E12*F12 -> 9973 | J12: =H12*I12 -> 0 | K12: =G12+J12 -> 9973 | M12: =M11+K12-L12 -> 219076.48
A13: 10 | B13: 46305 | G13: =E13*F13 -> 0 | J13: =H13*I13 -> 0 | K13: =G13+J13 -> 0 | M13: =M12+K13-L13 -> 219076.48
A14: 11 | B14: 46306 | G14: =E14*F14 -> 0 | J14: =H14*I14 -> 0 | K14: =G14+J14 -> 0 | M14: =M13+K14-L14 -> 219076.48
A15: 12 | B15: 46307 | G15: =E15*F15 -> 0 | J15: =H15*I15 -> 0 | K15: =G15+J15 -> 0 | M15: =M14+K15-L15 -> 219076.48
A16: 13 | B16: 46308 | E16: 240 | F16: 99.73 | G16: =E16*F16 -> 23935.2 | H16: 50 | I16: 111.85 | J16: =H16*I16 -> 5592.5 | K16: =G16+J16 -> 29527.7 | M16: =M15+K16-L16 -> 248604.18
A17: 14 | B17: 46309 | E17: 320 | F17: 99.73 | G17: =E17*F17 -> 31913.6 | J17: =H17*I17 -> 0 | K17: =G17+J17 -> 31913.6 | M17: =M16+K17-L17 -> 280517.78
A18: 15 | B18: 46310 | G18: =E18*F18 -> 0 | J18: =H18*I18 -> 0 | K18: =G18+J18 -> 0 | L18: 150000 | M18: =M17+K18-L18 -> 130517.78
A19: 16 | B19: 46311 | G19: =E19*F19 -> 0 | J19: =H19*I19 -> 0 | K19: =G19+J19 -> 0 | M19: =M18+K19-L19 -> 130517.78
A20: 17 | B20: 46312 | G20: =E20*F20 -> 0 | J20: =H20*I20 -> 0 | K20: =G20+J20 -> 0 | M20: =M19+K20-L20 -> 130517.78
A21: 18 | B21: 46313 | G21: =E21*F21 -> 0 | J21: =H21*I21 -> 0 | K21: =G21+J21 -> 0 | M21: =M20+K21-L21 -> 130517.78
A22: 19 | B22: 46314 | G22: =E22*F22 -> 0 | J22: =H22*I22 -> 0 | K22: =G22+J22 -> 0 | M22: =M21+K22-L22 -> 130517.78
A23: 20 | B23: 46315 | G23: =E23*F23 -> 0 | J23: =H23*I23 -> 0 | K23: =G23+J23 -> 0 | M23: =M22+K23-L23 -> 130517.78
A24: 21 | B24: 46316 | G24: =E24*F24 -> 0 | J24: =H24*I24 -> 0 | K24: =G24+J24 -> 0 | M24: =M23+K24-L24 -> 130517.78
A25: 22 | B25: 46317 | G25: =E25*F25 -> 0 | J25: =H25*I25 -> 0 | K25: =G25+J25 -> 0 | M25: =M24+K25-L25 -> 130517.78
A26: 23 | B26: 46318 | G26: =E26*F26 -> 0 | J26: =H26*I26 -> 0 | K26: =G26+J26 -> 0 | M26: =M25+K26-L26 -> 130517.78
A27: 24 | B27: 46319 | G27: =E27*F27 -> 0 | J27: =H27*I27 -> 0 | K27: =G27+J27 -> 0 | M27: =M26+K27-L27 -> 130517.78
A28: 25 | B28: 46320 | G28: =E28*F28 -> 0 | J28: =H28*I28 -> 0 | K28: =G28+J28 -> 0 | M28: =M27+K28-L28 -> 130517.78
A29: 26 | B29: 46321 | G29: =E29*F29 -> 0 | J29: =H29*I29 -> 0 | K29: =G29+J29 -> 0 | M29: =M28+K29-L29 -> 130517.78
A30: 27 | B30: 46322 | G30: =E30*F30 -> 0 | J30: =H30*I30 -> 0 | K30: =G30+J30 -> 0 | M30: =M29+K30-L30 -> 130517.78
A31: 28 | B31: 46323 | G31: =E31*F31 -> 0 | J31: =H31*I31 -> 0 | K31: =G31+J31 -> 0 | M31: =M30+K31-L31 -> 130517.78
B32: 46324 | G32: =E32*F32 -> 0 | K32: =G32+J32 -> 0 | M32: =M31+K32-L32 -> 130517.78
A33: 29 | B33: 46325 | G33: =E33*F33 -> 0 | J33: =H33*I33 -> 0 | K33: =G33+J33 -> 0 | M33: =M32+K33-L33 -> 130517.78
A34: 30 | B34: 46326 | G34: =E34*F34 -> 0 | J34: =H34*I34 -> 0 | K34: =G34+J34 -> 0 | M34: =M33+K34-L34 -> 130517.78
A35: 31 | G35: =E35*F35 -> 0 | J35: =H35*I35 -> 0 | K35: =G35+J35 -> 0 | M35: =M34+K35-L35 -> 130517.78
A36: 32 | G36: =E36*F36 -> 0 | J36: =H36*I36 -> 0 | K36: =G36+J36 -> 0 | M36: =M35+K36-L36 -> 130517.78
A37: 33 | G37: =E37*F37 -> 0 | J37: =H37*I37 -> 0 | K37: =G37+J37 -> 0 | M37: =M36+K37-L37 -> 130517.78
E38: =SUM(E4:E37) -> 1136 | G38: =SUM(G4:G37) -> 113293.28 | H38: =SUM(H4:H37) -> 77 | J38: =SUM(J4:J37) -> 8612.45 | K38: =SUM(K4:K37) -> 121905.73 | L38: =SUM(L4:L37) -> 150000

Sheet Kabbur
A1: Shri Jai Hanuman Petrolium
A2: S.No | B2: Date | C2: GRN No | D2: Ind no/Bill No | E2: Diesel (Lts) | F2: Price | G2: Amount | H2: Petrol (Lts) | I2: Price | J2: Amount | K2: Total amount | L2: Amount paid | M2: As on Date | N2: Remarks
A3: Opening Balance | M3: =+K3 -> 0
A4: 1 | B4: 46296 | G4: =E4*F4 -> 0 | J4: =H4*I4 -> 0 | K4: =G4+J4 -> 0 | M4: =M3+K4-L4 -> 0
A5: 2 | B5: 46297 | G5: =E5*F5 -> 0 | J5: =H5*I5 -> 0 | K5: =G5+J5 -> 0 | M5: =M4+K5-L5 -> 0
A6: 3 | B6: 46298 | G6: =E6*F6 -> 0 | J6: =H6*I6 -> 0 | K6: =G6+J6 -> 0 | M6: =M5+K6-L6 -> 0
A7: 4 | B7: 46299 | G7: =E7*F7 -> 0 | J7: =H7*I7 -> 0 | K7: =G7+J7 -> 0 | M7: =M6+K7-L7 -> 0
A8: 5 | B8: 46300 | G8: =E8*F8 -> 0 | J8: =H8*I8 -> 0 | K8: =G8+J8 -> 0 | M8: =M7+K8-L8 -> 0
A9: 6 | B9: 46301 | G9: =E9*F9 -> 0 | J9: =H9*I9 -> 0 | K9: =G9+J9 -> 0 | M9: =M8+K9-L9 -> 0
A10: 7 | B10: 46302 | G10: =E10*F10 -> 0 | J10: =H10*I10 -> 0 | K10: =G10+J10 -> 0 | M10: =M9+K10-L10 -> 0
A11: 8 | B11: 46303 | G11: =E11*F11 -> 0 | J11: =H11*I11 -> 0 | K11: =G11+J11 -> 0 | M11: =M10+K11-L11 -> 0
A12: 9 | B12: 46304 | E12: 30 | F12: 99.41 | G12: =E12*F12 -> 2982.3 | J12: =H12*I12 -> 0 | K12: =G12+J12 -> 2982.3 | L12: 2982.3 | M12: =M11+K12-L12 -> 0
A13: 10 | B13: 46305 | G13: =E13*F13 -> 0 | J13: =H13*I13 -> 0 | K13: =G13+J13 -> 0 | M13: =M12+K13-L13 -> 0
A14: 11 | B14: 46306 | G14: =E14*F14 -> 0 | J14: =H14*I14 -> 0 | K14: =G14+J14 -> 0 | M14: =M13+K14-L14 -> 0
A15: 12 | B15: 46307 | G15: =E15*F15 -> 0 | J15: =H15*I15 -> 0 | K15: =G15+J15 -> 0 | M15: =M14+K15-L15 -> 0
A16: 13 | B16: 46308 | G16: =E16*F16 -> 0 | J16: =H16*I16 -> 0 | K16: =G16+J16 -> 0 | M16: =M15+K16-L16 -> 0
A17: 14 | B17: 46309 | G17: =E17*F17 -> 0 | J17: =H17*I17 -> 0 | K17: =G17+J17 -> 0 | M17: =M16+K17-L17 -> 0
A18: 15 | B18: 46310 | G18: =E18*F18 -> 0 | J18: =H18*I18 -> 0 | K18: =G18+J18 -> 0 | M18: =M17+K18-L18 -> 0
A19: 16 | B19: 46311 | G19: =E19*F19 -> 0 | J19: =H19*I19 -> 0 | K19: =G19+J19 -> 0 | M19: =M18+K19-L19 -> 0
A20: 17 | B20: 46312 | G20: =E20*F20 -> 0 | J20: =H20*I20 -> 0 | K20: =G20+J20 -> 0 | M20: =M19+K20-L20 -> 0
A21: 18 | B21: 46313 | G21: =E21*F21 -> 0 | J21: =H21*I21 -> 0 | K21: =G21+J21 -> 0 | M21: =M20+K21-L21 -> 0
A22: 19 | B22: 46314 | G22: =E22*F22 -> 0 | J22: =H22*I22 -> 0 | K22: =G22+J22 -> 0 | M22: =M21+K22-L22 -> 0
A23: 20 | B23: 46315 | G23: =E23*F23 -> 0 | J23: =H23*I23 -> 0 | K23: =G23+J23 -> 0 | M23: =M22+K23-L23 -> 0
A24: 21 | B24: 46316 | G24: =E24*F24 -> 0 | J24: =H24*I24 -> 0 | K24: =G24+J24 -> 0 | M24: =M23+K24-L24 -> 0
... A34: 31 | B34: 46326 | G34: =E34*F34 -> 0 | J34: =H34*I34 -> 0 | K34: =G34+J34 -> 0 | M34: =M33+K34-L34 -> 0
E35: =SUM(E4:E34) -> 30 | G35: =SUM(G4:G34) -> 2982.3 | H35: =SUM(H4:H34) -> 0 | J35: =SUM(J4:J34) -> 0 | K35: =SUM(K4:K34) -> 2982.3 | L35: =SUM(L4:L34) -> 2982.3

Sheet kumta
A1: V.M.MIRJANKAR (KUMTA) BHARAT
A2: S.No | B2: Date | C2: GRN No | D2: Ind No/Bill No | E2: Diesel (Lts) | F2: Price | G2: Amount | H2: Petrol (Lts) | I2: Price | J2: Amount | K2: Total amount | L2: Amount paid | M2: As on Date | N2: Remarks
A3: Opening Balance | M3: 84520.658
A4: 1 | B4: 46296 | E4: 113.82 | F4: 99.78 | G4: =E4*F4 -> 11356.96 | J4: =H4*I4 -> 0 | K4: =G4+J4 -> 11356.96 | M4: =M3+K4-L4 -> 95877.618
A5: 2 | B5: 46297 | E5: 30 | F5: 99.78 | G5: =E5*F5 -> 2993.4 | H5: 5 | I5: 111.98 | J5: =H5*I5 -> 559.9 | K5: =G5+J5 -> 3553.3 | M5: =M4+K5-L5 -> 99430.918
A6: 3 | B6: 46298 | E6: 35 | F6: 99.78 | G6: =E6*F6 -> 3492.3 | J6: =H6*I6 -> 0 | K6: =G6+J6 -> 3492.3 | M6: =M5+K6-L6 -> 102923.22
A7: 4 | B7: 46299 | E7: 70 | F7: 99.78 | G7: =E7*F7 -> 6984.6 | J7: =H7*I7 -> 0 | K7: =G7+J7 -> 6984.6 | M7: =M6+K7-L7 -> 109907.82
A8: 5 | B8: 46300 | E8: 30 | F8: 99.78 | G8: =E8*F8 -> 2993.4 | H8: 5 | I8: 111.98 | J8: =H8*I8 -> 559.9 | K8: =G8+J8 -> 3553.3 | M8: =M7+K8-L8 -> 113461.12
A9: 6 | B9: 46301 | E9: 110 | F9: 99.78 | G9: =E9*F9 -> 10975.8 | J9: =H9*I9 -> 0 | K9: =G9+J9 -> 10975.8 | M9: =M8+K9-L9 -> 124436.92
A10: 7 | B10: 46302 | E10: 126 | F10: 99.78 | G10: =E10*F10 -> 12572.28 | H10: 9 | I10: 111.98 | J10: =H10*I10 -> 1007.82 | K10: =G10+J10 -> 13580.1 | M10: =M9+K10-L10 -> 138017.02
A11: 8 | B11: 46303 | G11: =E11*F11 -> 0 | H11: 5 | I11: 111.98 | J11: =H11*I11 -> 559.9 | K11: =G11+J11 -> 559.9 | L11: 100000 | M11: =M10+K11-L11 -> 38576.918
A12: 9 | B12: 46304 | G12: =E12*F12 -> 0 | J12: =H12*I12 -> 0 | K12: =G12+J12 -> 0 | M12: =M11+K12-L12 -> 38576.918
A13: 10 | B13: 46305 | E13: 100 | F13: 99.78 | G13: =E13*F13 -> 9978 | H13: 5 | I13: 111.98 | J13: =H13*I13 -> 559.9 | K13: =G13+J13 -> 10537.9 | M13: =M12+K13-L13 -> 49114.818
A14: 11 | B14: 46306 | G14: =E14*F14 -> 0 | J14: =H14*I14 -> 0 | K14: =G14+J14 -> 0 | M14: =M13+K14-L14 -> 49114.818
A15: 12 | B15: 46307 | E15: 130 | F15: 99.78 | G15: =E15*F15 -> 12971.4 | H15: 5 | I15: 111.98 | J15: =H15*I15 -> 559.9 | K15: =G15+J15 -> 13531.3 | M15: =M14+K15-L15 -> 62646.118
A16: 13 | B16: 46308 | E16: 30 | F16: 99.78 | G16: =E16*F16 -> 2993.4 | J16: =H16*I16 -> 0 | K16: =G16+J16 -> 2993.4 | M16: =M15+K16-L16 -> 65639.518
A17: 14 | B17: 46309 | E17: 30 | F17: 99.78 | G17: =E17*F17 -> 2993.4 | J17: =H17*I17 -> 0 | K17: =G17+J17 -> 2993.4 | M17: =M16+K17-L17 -> 68632.918
A18: 15 | B18: 46310 | E18: 90 | F18: 99.78 | G18: =E18*F18 -> 8980.2 | H18: 5 | I18: 111.98 | J18: =H18*I18 -> 559.9 | K18: =G18+J18 -> 9540.1 | M18: =M17+K18-L18 -> 78173.018
A19: 16 | B19: 46311 | G19: =E19*F19 -> 0 | J19: =H19*I19 -> 0 | K19: =G19+J19 -> 0 | M19: =M18+K19-L19 -> 78173.018
A20: 17 | B20: 46312 | G20: =E20*F20 -> 0 | J20: =H20*I20 -> 0 | K20: =G20+J20 -> 0 | M20: =M19+K20-L20 -> 78173.018
A21: 18 | B21: 46313 | G21: =E21*F21 -> 0 | J21: =H21*I21 -> 0 | K21: =G21+J21 -> 0 | M21: =M20+K21-L21 -> 78173.018
A22: 19 | B22: 46314 | G22: =E22*F22 -> 0 | J22: =H22*I22 -> 0 | K22: =G22+J22 -> 0 | M22: =M21+K22-L22 -> 78173.018
A23: 20 | B23: 46315 | G23: =E23*F23 -> 0 | J23: =H23*I23 -> 0 | K23: =G23+J23 -> 0 | M23: =M22+K23-L23 -> 78173.018
A24: 21 | B24: 46316 | G24: =E24*F24 -> 0 | J24: =H24*I24 -> 0 | K24: =G24+J24 -> 0 | M24: =M23+K24-L24 -> 78173.018
A25: 22 | B25: 46317 | G25: =E25*F25 -> 0 | J25: =H25*I25 -> 0 | K25: =G25+J25 -> 0 | M25: =M24+K25-L25 -> 78173.018
A26: 23 | B26: 46318 | G26: =E26*F26 -> 0 | J26: =H26*I26 -> 0 | K26: =G26+J26 -> 0 | M26: =M25+K26-L26 -> 78173.018 | R26: Kumta | T26: V.M.Mirjankar
A27: 24 | B27: 46319 | G27: =E27*F27 -> 0 | J27: =H27*I27 -> 0 | K27: =G27+J27 -> 0 | M27: =M26+K27-L27 -> 78173.018 | R27: Month | S27: Disel In Litters | T27: Petrol In Litters | U27: Amount Paid
A28: 25 | B28: 46320 | G28: =E28*F28 -> 0 | J28: =H28*I28 -> 0 | K28: =G28+J28 -> 0 | M28: =M27+K28-L28 -> 78173.018 | R28: Feb'-26 | S28: 2040 | T28: 90 | U28: 169925
A29: 26 | B29: 46321 | G29: =E29*F29 -> 0 | J29: =H29*I29 -> 0 | K29: =G29+J29 -> 0 | M29: =M28+K29-L29 -> 78173.018 | R29: March'-26 | S29: 2115 | T29: 185 | U29: 206053
A30: 27 | B30: 46322 | G30: =E30*F30 -> 0 | J30: =H30*I30 -> 0 | K30: =G30+J30 -> 0 | M30: =M29+K30-L30 -> 78173.018 | R30: April'-26 | S30: 2145 | T30: 177 | U30: 247835
A31: 28 | B31: 46323 | G31: =E31*F31 -> 0 | J31: =H31*I31 -> 0 | K31: =G31+J31 -> 0 | M31: =M30+K31-L31 -> 78173.018 | R31: May'-26 | S31: 545 | T31: 50 | U31: 44201
A32: 29 | B32: 46324 | G32: =E32*F32 -> 0 | J32: =H32*I32 -> 0 | K32: =G32+J32 -> 0 | M32: =M31+K32-L32 -> 78173.018 | S32: =SUM(S28:S31) -> 6845 | T32: =SUM(T28:T31) -> 502 | U32: =SUM(U28:U31) -> 668014
A33: 30 | B33: 46325 | G33: =E33*F33 -> 0 | J33: =H33*I33 -> 0 | K33: =G33+J33 -> 0 | M33: =M32+K33-L33 -> 78173.018
A34: 31 | B34: 46326 | G34: =E34*F34 -> 0 | J34: =H34*I34 -> 0 | K34: =G34+J34 -> 0 | M34: =M33+K34-L34 -> 78173.018
A35: 32 | G35: =E35*F35 -> 0 | J35: =H35*I35 -> 0 | K35: =G35+J35 -> 0 | M35: =M34+K35-L35 -> 78173.018
A36: 33 | G36: =E36*F36 -> 0 | J36: =H36*I36 -> 0 | K36: =G36+J36 -> 0 | M36: =M35+K36-L36 -> 78173.018
A37: 34 | G37: =E37*F37 -> 0 | J37: =H37*I37 -> 0 | K37: =G37+J37 -> 0 | M37: =M36+K37-L37 -> 78173.018
A38: 35 | G38: =E38*F38 -> 0 | J38: =H38*I38 -> 0 | K38: =G38+J38 -> 0 | M38: =M37+K38-L38 -> 78173.018
A39: 36 | G39: =E39*F39 -> 0 | J39: =H39*I39 -> 0 | K39: =G39+J39 -> 0 | M39: =M38+K39-L39 -> 78173.018
A40: 37 | G40: =E40*F40 -> 0 | J40: =H40*I40 -> 0 | K40: =G40+J40 -> 0 | M40: =M39+K40-L40 -> 78173.018
E41: =SUM(E4:E40) -> 894.82 | G41: =SUM(G4:G40) -> 89285.14 | H41: =SUM(H4:H40) -> 39 | J41: =SUM(J4:J40) -> 4367.22 | K41: =SUM(K4:K40) -> 93652.36 | L41: =SUM(L4:L40) -> 100000

Sheet Jalgoan-2
A1: Nayara
A2: S.No | B2: Date | C2: GRN No | D2: Ind No/Bill No | E2: Diesel (Lts) | F2: Price | G2: Amount | H2: Petrol (Lts) | I2: Price | J2: Amount | K2: Total amount | L2: Amount paid | M2: As on Date | N2: Remarks
A3: Opening Balance | K3: 605152.24 | M3: 605152.24
A4: 1 | B4: 46296 | G4: =E4*F4 -> 0 | J4: =H4*I4 -> 0 | K4: =G4+J4 -> 0 | M4: =M3+K4-L4 -> 605152.24
A5: 2 | B5: 46297 | G5: =E5*F5 -> 0 | J5: =H5*I5 -> 0 | K5: =G5+J5 -> 0 | M5: =M4+K5-L5 -> 605152.24
A6: 3 | B6: 46298 | G6: =E6*F6 -> 0 | J6: =H6*I6 -> 0 | K6: =G6+J6 -> 0 | M6: =M5+K6-L6 -> 605152.24
A7: 4 | B7: 46299 | G7: =E7*F7 -> 0 | J7: =H7*I7 -> 0 | K7: =G7+J7 -> 0 | M7: =M6+K7-L7 -> 605152.24
A8: 5 | B8: 46300 | G8: =E8*F8 -> 0 | J8: =H8*I8 -> 0 | K8: =G8+J8 -> 0 | M8: =M7+K8-L8 -> 605152.24
A9: 6 | B9: 46301 | G9: =E9*F9 -> 0 | H9: 60 | I9: 118.18 | J9: =H9*I9 -> 7090.8 | K9: =G9+J9 -> 7090.8 | M9: =M8+K9-L9 -> 612243.04
A10: 7 | B10: 46302 | G10: =E10*F10 -> 0 | J10: =H10*I10 -> 0 | K10: =G10+J10 -> 0 | M10: =M9+K10-L10 -> 612243.04
A11: 8 | B11: 46303 | G11: =E11*F11 -> 0 | J11: =H11*I11 -> 0 | K11: =G11+J11 -> 0 | M11: =M10+K11-L11 -> 612243.04
A12: 9 | B12: 46304 | G12: =E12*F12 -> 0 | J12: =H12*I12 -> 0 | K12: =G12+J12 -> 0 | M12: =M11+K12-L12 -> 612243.04
A13: 10 | B13: 46305 | G13: =E13*F13 -> 0 | J13: =H13*I13 -> 0 | K13: =G13+J13 -> 0 | M13: =M12+K13-L13 -> 612243.04
A14: 11 | B14: 46306 | G14: =E14*F14 -> 0 | J14: =H14*I14 -> 0 | K14: =G14+J14 -> 0 | M14: =M13+K14-L14 -> 612243.04
A15: 12 | B15: 46307 | G15: =E15*F15 -> 0 | J15: =H15*I15 -> 0 | K15: =G15+J15 -> 0 | M15: =M14+K15-L15 -> 612243.04
A16: 13 | B16: 46308 | G16: =E16*F16 -> 0 | J16: =H16*I16 -> 0 | K16: =G16+J16 -> 0 | M16: =M15+K16-L16 -> 612243.04
A17: 14 | B17: 46309 | G17: =E17*F17 -> 0 | J17: =H17*I17 -> 0 | K17: =G17+J17 -> 0 | M17: =M16+K17-L17 -> 612243.04
A18: 15 | B18: 46310 | G18: =E18*F18 -> 0 | J18: =H18*I18 -> 0 | K18: =G18+J18 -> 0 | M18: =M17+K18-L18 -> 612243.04
A19: 16 | B19: 46311 | G19: =E19*F19 -> 0 | J19: =H19*I19 -> 0 | K19: =G19+J19 -> 0 | M19: =M18+K19-L19 -> 612243.04
A20: 17 | B20: 46312 | G20: =E20*F20 -> 0 | J20: =H20*I20 -> 0 | K20: =G20+J20 -> 0 | M20: =M19+K20-L20 -> 612243.04
A21: 18 | B21: 46313 | G21: =E21*F21 -> 0 | J21: =H21*I21 -> 0 | K21: =G21+J21 -> 0 | M21: =M20+K21-L21 -> 612243.04
... A34: 31 | B34: 46326 | G34: =E34*F34 -> 0 | J34: =H34*I34 -> 0 | K34: =G34+J34 -> 0 | M34: =M33+K34-L34 -> 612243.04
A35: 32 | G35: =E35*F35 -> 0 | J35: =H35*I35 -> 0 | K35: =G35+J35 -> 0 | M35: =M34+K35-L35 -> 612243.04
A36: 33 | G36: =E36*F36 -> 0 | J36: =H36*I36 -> 0 | K36: =G36+J36 -> 0 | M36: =M35+K36-L36 -> 612243.04
A37: 34 | G37: =E37*F37 -> 0 | J37: =H37*I37 -> 0 | K37: =G37+J37 -> 0 | M37: =M36+K37-L37 -> 612243.04
A38: 35 | G38: =E38*F38 -> 0 | J38: =H38*I38 -> 0 | K38: =G38+J38 -> 0 | M38: =M37+K38-L38 -> 612243.04
A39: 36 | G39: =E39*F39 -> 0 | J39: =H39*I39 -> 0 | K39: =G39+J39 -> 0 | M39: =M38+K39-L39 -> 612243.04
A40: 37 | G40: =E40*F40 -> 0 | J40: =H40*I40 -> 0 | K40: =G40+J40 -> 0 | M40: =M39+K40-L40 -> 612243.04
A41: 38 | G41: =E41*F41 -> 0 | J41: =H41*I41 -> 0 | K41: =G41+J41 -> 0 | M41: =M40+K41-L41 -> 612243.04
A42: 39 | G42: =E42*F42 -> 0 | J42: =H42*I42 -> 0 | K42: =G42+J42 -> 0 | M42: =M41+K42-L42 -> 612243.04
A43: 40 | G43: =E43*F43 -> 0 | J43: =H43*I43 -> 0 | K43: =G43+J43 -> 0 | M43: =M42+K43-L43 -> 612243.04
A44: 41 | G44: =E44*F44 -> 0 | J44: =H44*I44 -> 0 | K44: =G44+J44 -> 0 | M44: =M43+K44-L44 -> 612243.04
A45: 42 | G45: =E45*F45 -> 0 | J45: =H45*I45 -> 0 | K45: =G45+J45 -> 0 | M45: =M44+K45-L45 -> 612243.04
A46: 43 | G46: =E46*F46 -> 0 | J46: =H46*I46 -> 0 | K46: =G46+J46 -> 0 | M46: =M45+K46-L46 -> 612243.04
... A55: 51 | G55: =E55*F55 -> 0 | J55: =H55*I55 -> 0 | K55: =G55+J55 -> 0 | M55: =M54+K55-L55 -> 612243.04
E56: =SUM(E4:E55) -> 0 | G56: =SUM(G4:G55) -> 0 | H56: =SUM(H4:H55) -> 60 | J56: =SUM(J4:J55) -> 7090.8 | K56: =SUM(K4:K55) -> 7090.8 | L56: =SUM(L4:L55) -> 0

Sheet MKBD
A1: Shree Sai Samarth Petroleum
A2: S.No | B2: Date | C2: GRN No | D2: Ind No/Bill No | E2: Diesel (Lts) | F2: Price | G2: Amount | H2: Petrol (Lts) | I2: Price | J2: Amount | K2: Total amount | L2: Amount paid | M2: As on Date | N2: Remarks
D3: Opening Balance | L3: 342407.81 | M3: 342407.81
A4: 1 | B4: 46296 | G4: =E4*F4 -> 0 | J4: =H4*I4 -> 0 | K4: =G4+J4 -> 0 | M4: =M3+K4-L4 -> 342407.81
A5: 2 | B5: 46297 | G5: =E5*F5 -> 0 | J5: =H5*I5 -> 0 | K5: =G5+J5 -> 0 | M5: =M4+K5-L5 -> 342407.81
A6: 3 | B6: 46298 | G6: =E6*F6 -> 0 | J6: =H6*I6 -> 0 | K6: =G6+J6 -> 0 | M6: =M5+K6-L6 -> 342407.81
A7: 3 | B7: 46299 | G7: =E7*F7 -> 0 | J7: =H7*I7 -> 0 | K7: =G7+J7 -> 0 | M7: =M6+K7-L7 -> 342407.81
A8: 4 | B8: 46300 | E8: 600 | F8: 98.94 | G8: =E8*F8 -> 59364 | J8: =H8*I8 -> 0 | K8: =G8+J8 -> 59364 | M8: =M7+K8-L8 -> 401771.81
A9: 5 | B9: 46301 | G9: =E9*F9 -> 0 | J9: 0 | K9: =G9+J9 -> 0 | M9: =M8+K9-L9 -> 401771.81
A10: 6 | B10: 46302 | G10: =E10*F10 -> 0 | J10: =H10*I10 -> 0 | K10: =G10+J10 -> 0 | M10: =M9+K10-L10 -> 401771.81
A11: 7 | B11: 46303 | E11: 2000 | F11: 98.94 | G11: =E11*F11 -> 197880 | H11: 20 | I11: 112.27 | J11: =H11*I11 -> 2245.4 | K11: =G11+J11 -> 200125.4 | M11: =M10+K11-L11 -> 601897.21
A12: 8 | B12: 46304 | G12: =E12*F12 -> 0 | J12: =H12*I12 -> 0 | K12: =G12+J12 -> 0 | M12: =M11+K12-L12 -> 601897.21
A13: 9 | B13: 46305 | G13: =E13*F13 -> 0 | J13: =H13*I13 -> 0 | K13: =G13+J13 -> 0 | M13: =M12+K13-L13 -> 601897.21
A14: 10 | B14: 46306 | G14: =E14*F14 -> 0 | J14: =H14*I14 -> 0 | K14: =G14+J14 -> 0 | M14: =M13+K14-L14 -> 601897.21
A15: 11 | B15: 46307 | G15: =E15*F15 -> 0 | J15: =H15*I15 -> 0 | K15: =G15+J15 -> 0 | M15: =M14+K15-L15 -> 601897.21
A16: 12 | B16: 46308 | G16: =E16*F16 -> 0 | J16: =H16*I16 -> 0 | K16: =G16+J16 -> 0 | M16: =M15+K16-L16 -> 601897.21
A17: 13 | B17: 46309 | E17: 1200 | F17: 98.94 | G17: =E17*F17 -> 118728 | H17: 20 | I17: 112.27 | J17: =H17*I17 -> 2245.4 | K17: =G17+J17 -> 120973.4 | M17: =M16+K17-L17 -> 722870.61
A18: 14 | B18: 46310 | G18: =E18*F18 -> 0 | J18: =H18*I18 -> 0 | K18: =G18+J18 -> 0 | M18: =M17+K18-L18 -> 722870.61
A19: 15 | B19: 46311 | G19: =E19*F19 -> 0 | J19: =H19*I19 -> 0 | K19: =G19+J19 -> 0 | M19: =M18+K19-L19 -> 722870.61
A20: 16 | B20: 46312 | G20: =E20*F20 -> 0 | J20: =H20*I20 -> 0 | K20: =G20+J20 -> 0 | M20: =M19+K20-L20 -> 722870.61
A21: 17 | B21: 46313 | G21: =E21*F21 -> 0 | J21: =H21*I21 -> 0 | K21: =G21+J21 -> 0 | M21: =M20+K21-L21 -> 722870.61
A22: 18 | B22: 46314 | G22: =E22*F22 -> 0 | J22: =H22*I22 -> 0 | K22: =G22+J22 -> 0 | M22: =M21+K22-L22 -> 722870.61
A23: 19 | B23: 46315 | G23: =E23*F23 -> 0 | J23: =H23*I23 -> 0 | K23: =G23+J23 -> 0 | M23: =M22+K23-L23 -> 722870.61
A24: 20 | B24: 46316 | G24: =E24*F24 -> 0 | J24: =H24*I24 -> 0 | K24: =G24+J24 -> 0 | M24: =M23+K24-L24 -> 722870.61
A25: 21 | B25: 46317 | G25: =E25*F25 -> 0 | J25: =H25*I25 -> 0 | K25: =G25+J25 -> 0 | M25: =M24+K25-L25 -> 722870.61
A26: 22 | B26: 46318 | G26: =E26*F26 -> 0 | J26: =H26*I26 -> 0 | K26: =G26+J26 -> 0 | M26: =M25+K26-L26 -> 722870.61
A27: 23 | B27: 46319 | G27: =E27*F27 -> 0 | J27: =H27*I27 -> 0 | K27: =G27+J27 -> 0 | M27: =M26+K27-L27 -> 722870.61
A28: 24 | B28: 46320 | G28: =E28*F28 -> 0 | J28: =H28*I28 -> 0 | K28: =G28+J28 -> 0 | M28: =M27+K28-L28 -> 722870.61
A29: 25 | B29: 46321 | G29: =E29*F29 -> 0 | J29: =H29*I29 -> 0 | K29: =G29+J29 -> 0 | M29: =M28+K29-L29 -> 722870.61
... A34: 30 | B34: 46326 | G34: =E34*F34 -> 0 | J34: =H34*I34 -> 0 | K34: =G34+J34 -> 0 | M34: =M33+K34-L34 -> 722870.61
A35: 31 | G35: =E35*F35 -> 0 | J35: =H35*I35 -> 0 | K35: =G35+J35 -> 0 | M35: =M34+K35-L35 -> 722870.61
A36: 32 | G36: =E36*F36 -> 0 | J36: =H36*I36 -> 0 | K36: =G36+J36 -> 0 | M36: =M35+K36-L36 -> 722870.61
A37: 33 | G37: =E37*F37 -> 0 | J37: 0 | K37: =G37+J37 -> 0 | M37: =M36+K37-L37 -> 722870.61
A38: 34 | G38: 0 | J38: 0 | K38: =G38+J38 -> 0 | M38: =M37+K38-L38 -> 722870.61
A39: 35 | G39: =E39*F39 -> 0 | J39: =H39*I39 -> 0 | K39: =G39+J39 -> 0 | M39: =M38+K39-L39 -> 722870.61
A40: 36 | G40: =E40*F40 -> 0 | J40: =H40*I40 -> 0 | K40: =G40+J40 -> 0 | M40: =M39+K40-L40 -> 722870.61
A41: 37 | E41: 0 | F41: 0 | G41: =E41*F41 -> 0 | J41: =H41*I41 -> 0 | K41: =G41+J41 -> 0 | M41: =M40+K41-L41 -> 722870.61
E42: =SUM(E4:E41) -> 3800 | G42: =SUM(G4:G41) -> 375972 | H42: =SUM(H4:H41) -> 40 | J42: =SUM(J4:J41) -> 4490.8 | K42: =SUM(K4:K41) -> 380462.8 | L42: =SUM(L4:L41) -> 0

Sheet  Haveri-2
A1: Magavi fuel F/S
A2: S.No | B2: Date | C2: GRN No | D2: Ind No/Bill No | E2: Diesel (Lts) | F2: Price | G2: Amount | H2: Petrol (Lts) | I2: Price | J2: Amount | K2: Total amount | L2: Amount paid | M2: As on Date | N2: Remarks
D3: Opening Balance | K3: 82823.565 | M3: 82823.565
A4: 1 | B4: 46296 | E4: 50 | F4: 99.3 | G4: =E4*F4 -> 4965 | J4: =H4*I4 -> 0 | K4: =G4+J4 -> 4965 | M4: =M3+K4-L4 -> 87788.565
A5: 2 | B5: 46297 | E5: 270 | F5: 99.3 | G5: =E5*F5 -> 26811 | J5: =H5*I5 -> 0 | K5: =G5+J5 -> 26811 | M5: =M4+K5-L5 -> 114599.57
A6: 3 | B6: 46298 | E6: 43 | F6: 99.3 | G6: =E6*F6 -> 4269.9 | J6: =H6*I6 -> 0 | K6: =G6+J6 -> 4269.9 | M6: =M5+K6-L6 -> 118869.47
A7: 4 | B7: 46299 | E7: 241.58 | F7: 99.3 | G7: =E7*F7 -> 23988.894 | J7: =H7*I7 -> 0 | K7: =G7+J7 -> 23988.894 | M7: =M6+K7-L7 -> 142858.36
A8: 5 | B8: 46300 | E8: 50 | F8: 99.3 | G8: =E8*F8 -> 4965 | H8: 5 | I8: 111.4 | J8: =H8*I8 -> 557 | K8: =G8+J8 -> 5522 | M8: =M7+K8-L8 -> 148380.36
A9: 6 | B9: 46301 | E9: 511.68 | F9: 99.3 | G9: =E9*F9 -> 50809.824 | J9: =H9*I9 -> 0 | K9: =G9+J9 -> 50809.824 | M9: =M8+K9-L9 -> 199190.18
A10: 7 | B10: 46302 | E10: 477.07 | F10: 99.3 | G10: =E10*F10 -> 47373.051 | J10: =H10*I10 -> 0 | K10: =G10+J10 -> 47373.051 | M10: =M9+K10-L10 -> 246563.23
A11: 8 | B11: 46303 | E11: 443.14 | F11: 99.3 | G11: =E11*F11 -> 44003.802 | J11: =H11*I11 -> 0 | K11: =G11+J11 -> 44003.802 | M11: =M10+K11-L11 -> 290567.04
A12: 9 | B12: 46304 | G12: =E12*F12 -> 0 | J12: =H12*I12 -> 0 | K12: =G12+J12 -> 0 | M12: =M11+K12-L12 -> 290567.04
A13: 10 | B13: 46305 | E13: 530 | F13: 99.3 | G13: =E13*F13 -> 52629 | H13: 10 | I13: 111.4 | J13: =H13*I13 -> 1114 | K13: =G13+J13 -> 53743 | M13: =M12+K13-L13 -> 344310.04
A14: 11 | B14: 46306 | E14: 250 | F14: 99.3 | G14: =E14*F14 -> 24825 | H14: 5 | I14: 111.4 | J14: =H14*I14 -> 557 | K14: =G14+J14 -> 25382 | M14: =M13+K14-L14 -> 369692.04
A15: 12 | B15: 46307 | E15: 85 | F15: 99.3 | G15: =E15*F15 -> 8440.5 | H15: 15 | I15: 111.4 | J15: =H15*I15 -> 1671 | K15: =G15+J15 -> 10111.5 | M15: =M14+K15-L15 -> 379803.54
A16: 13 | B16: 46308 | E16: 137.3 | F16: 99.3 | G16: =E16*F16 -> 13633.89 | J16: =H16*I16 -> 0 | K16: =G16+J16 -> 13633.89 | M16: =M15+K16-L16 -> 393437.43
A17: 14 | B17: 46309 | G17: =E17*F17 -> 0 | H17: 8 | I17: 111.4 | J17: =H17*I17 -> 891.2 | K17: =G17+J17 -> 891.2 | L17: 350000 | M17: =M16+K17-L17 -> 44328.626
A18: 15 | B18: 46310 | E18: 118.8 | F18: 99.3 | G18: =E18*F18 -> 11796.84 | H18: 5 | I18: 111.4 | J18: =H18*I18 -> 557 | K18: =G18+J18 -> 12353.84 | M18: =M17+K18-L18 -> 56682.466
A19: 16 | B19: 46311 | G19: =E19*F19 -> 0 | J19: =H19*I19 -> 0 | K19: =G19+J19 -> 0 | M19: =M18+K19-L19 -> 56682.466
A20: 17 | B20: 46312 | G20: =E20*F20 -> 0 | J20: =H20*I20 -> 0 | K20: =G20+J20 -> 0 | M20: =M19+K20-L20 -> 56682.466
A21: 18 | B21: 46313 | G21: =E21*F21 -> 0 | J21: =H21*I21 -> 0 | K21: =G21+J21 -> 0 | M21: =M20+K21-L21 -> 56682.466
A22: 19 | B22: 46314 | G22: =E22*F22 -> 0 | J22: =H22*I22 -> 0 | K22: =G22+J22 -> 0 | M22: =M21+K22-L22 -> 56682.466
A23: 20 | B23: 46315 | G23: =E23*F23 -> 0 | J23: =H23*I23 -> 0 | K23: =G23+J23 -> 0 | M23: =M22+K23-L23 -> 56682.466
A24: 21 | B24: 46316 | G24: =E24*F24 -> 0 | J24: =H24*I24 -> 0 | K24: =G24+J24 -> 0 | M24: =M23+K24-L24 -> 56682.466
A25: 22 | B25: 46317 | G25: =E25*F25 -> 0 | J25: =H25*I25 -> 0 | K25: =G25+J25 -> 0 | M25: =M24+K25-L25 -> 56682.466
A26: 23 | B26: 46318 | G26: =E26*F26 -> 0 | J26: =H26*I26 -> 0 | K26: =G26+J26 -> 0 | M26: =M25+K26-L26 -> 56682.466
A27: 24 | B27: 46319 | G27: =E27*F27 -> 0 | J27: =H27*I27 -> 0 | K27: =G27+J27 -> 0
A28: 25 | B28: 46320 | G28: =E28*F28 -> 0 | J28: =H28*I28 -> 0 | K28: =G28+J28 -> 0 | M28: =N30+K28-L28 -> 0
A29: 26 | B29: 46321 | G29: =E29*F29 -> 0 | J29: =H29*I29 -> 0 | K29: =G29+J29 -> 0 | M29: =M28+K29-L29 -> 0
A30: 27 | B30: 46322 | G30: =E30*F30 -> 0 | J30: =H30*I30 -> 0 | K30: =G30+J30 -> 0 | M30: =M29+K30-L30 -> 0
A31: 28 | B31: 46323 | G31: =E31*F31 -> 0 | J31: =H31*I31 -> 0 | K31: =G31+J31 -> 0 | M31: =M30+K31-L31 -> 0
A32: 29 | B32: 46324 | G32: =E32*F32 -> 0 | J32: =H32*I32 -> 0 | K32: =G32+J32 -> 0 | M32: =M31+K32-L32 -> 0
A33: 30 | B33: 46325 | G33: =E33*F33 -> 0 | J33: =H33*I33 -> 0 | K33: =G33+J33 -> 0 | M33: =M32+K33-L33 -> 0
A34: 31 | B34: 46326 | G34: =E34*F34 -> 0 | J34: =H34*I34 -> 0 | K34: =G34+J34 -> 0 | M34: =M33+K34-L34 -> 0
A35: 32 | G35: =E35*F35 -> 0 | J35: =H35*I35 -> 0 | K35: =G35+J35 -> 0 | M35: =M34+K35-L35 -> 0
A36: 33 | G36: =E36*F36 -> 0 | J36: =H36*I36 -> 0 | K36: =G36+J36 -> 0 | M36: =M35+K36-L36 -> 0
A37: 34 | G37: =E37*F37 -> 0 | J37: =H37*I37 -> 0 | K37: =G37+J37 -> 0 | M37: =M36+K37-L37 -> 0
A38: 35 | G38: =E38*F38 -> 0 | J38: =H38*I38 -> 0 | K38: =G38+J38 -> 0 | M38: =M37+K38-L38 -> 0
A39: 36 | G39: =E39*F39 -> 0 | J39: =H39*I39 -> 0 | K39: =G39+J39 -> 0 | M39: =M38+K39-L39 -> 0
A40: 37 | G40: =E40*F40 -> 0 | J40: =H40*I40 -> 0 | K40: =G40+J40 -> 0 | L40: 0 | M40: =M39+K40-L40 -> 0
A41: 38 | H41: 0 | I41: 0 | M41: =M40+K41-L41 -> 0
E42: =SUM(E4:E40) -> 3207.57 | G42: =SUM(G4:G40) -> 318511.7 | H42: =SUM(H4:H40) -> 48 | J42: =SUM(J4:J40) -> 5347.2 | K42: =SUM(K4:K40) -> 323858.9 | L42: =SUM(L4:L40) -> 350000
I45: =K29+L29 -> 0

Sheet  Guttal-2
A1: Himagiri Petroleum
A2: S.No | B2: Date | C2: GRN No | D2: Ind No/Bill No | E2: Diesel (Lts) | F2: Price | G2: Amount | H2: Petrol (Lts) | I2: Price | J2: Amount | K2: Total amount | L2: Amount paid | M2: As on Date | N2: Remarks
D3: Opening Balance | K3: 459610.06 | M3: 459610.06
A4: 1 | B4: 46296 | E4: 510 | F4: 99.6 | G4: =E4*F4 -> 50796 | H4: 5 | I4: 111.71 | J4: =H4*I4 -> 558.55 | K4: =G4+J4 -> 51354.55 | M4: =M3+K4-L4 -> 510964.61
A5: 2 | B5: 46297 | E5: 370 | F5: 99.6 | G5: =E5*F5 -> 36852 | H5: 10 | I5: 111.71 | J5: =H5*I5 -> 1117.1 | K5: =G5+J5 -> 37969.1 | M5: =M4+K5-L5 -> 548933.71
A6: 3 | B6: 46298 | E6: 160 | F6: 99.6 | G6: =E6*F6 -> 15936 | J6: =H6*I6 -> 0 | K6: =G6+J6 -> 15936 | M6: =M5+K6-L6 -> 564869.71
A7: 4 | B7: 46299 | G7: =E7*F7 -> 0 | H7: 5 | I7: 111.71 | J7: =H7*I7 -> 558.55 | K7: =G7+J7 -> 558.55 | M7: =M6+K7-L7 -> 565428.26
A8: 5 | B8: 46300 | G8: =E8*F8 -> 0 | H8: 15 | I8: 111.71 | J8: =H8*I8 -> 1675.65 | K8: =G8+J8 -> 1675.65 | M8: =M7+K8-L8 -> 567103.91
A9: 6 | B9: 46301 | G9: =E9*F9 -> 0 | H9: 22.61 | I9: 111.71 | J9: =H9*I9 -> 2525.7631 | K9: =G9+J9 -> 2525.7631 | M9: =M8+K9-L9 -> 569629.67
A10: 7 | B10: 46302 | E10: 24 | F10: 99.6 | G10: =E10*F10 -> 2390.4 | H10: 10 | I10: 111.71 | J10: =H10*I10 -> 1117.1 | K10: =G10+J10 -> 3507.5 | M10: =M9+K10-L10 -> 573137.17
A11: 8 | B11: 46303 | G11: =E11*F11 -> 0 | J11: =H11*I11 -> 0 | K11: =G11+J11 -> 0 | M11: =M10+K11-L11 -> 573137.17
A12: 9 | B12: 46304 | G12: =E12*F12 -> 0 | J12: =H12*I12 -> 0 | K12: =G12+J12 -> 0 | M12: =M11+K12-L12 -> 573137.17
A13: 10 | B13: 46305 | G13: =E13*F13 -> 0 | J13: =H13*I13 -> 0 | K13: =G13+J13 -> 0 | L13: 250000 | M13: =M12+K13-L13 -> 323137.17
A14: 11 | B14: 46306 | G14: =E14*F14 -> 0 | J14: =H14*I14 -> 0 | K14: =G14+J14 -> 0 | M14: =M13+K14-L14 -> 323137.17
A15: 12 | B15: 46307 | G15: =E15*F15 -> 0 | J15: =H15*I15 -> 0 | K15: =G15+J15 -> 0 | M15: =M14+K15-L15 -> 323137.17
A16: 13 | B16: 46308 | E16: 200 | F16: 99.6 | G16: =E16*F16 -> 19920 | H16: 25 | I16: 111.71 | J16: =H16*I16 -> 2792.75 | K16: =G16+J16 -> 22712.75 | M16: =M15+K16-L16 -> 345849.92
A17: 14 | B17: 46309 | E17: 200 | F17: 99.6 | G17: =E17*F17 -> 19920 | H17: 5 | I17: 111.71 | J17: =H17*I17 -> 558.55 | K17: =G17+J17 -> 20478.55 | M17: =M16+K17-L17 -> 366328.47
A18: 15 | B18: 46310 | E18: 200 | F18: 99.6 | G18: =E18*F18 -> 19920 | H18: 10 | I18: 111.71 | J18: =H18*I18 -> 1117.1 | K18: =G18+J18 -> 21037.1 | L18: 300000 | M18: =M17+K18-L18 -> 87365.57
A19: 16 | B19: 46311 | G19: =E19*F19 -> 0 | J19: =H19*I19 -> 0 | K19: =G19+J19 -> 0 | M19: =M18+K19-L19 -> 87365.57
A20: 17 | B20: 46312 | G20: =E20*F20 -> 0 | J20: =H20*I20 -> 0 | K20: =G20+J20 -> 0 | M20: =M19+K20-L20 -> 87365.57
A21: 18 | B21: 46313 | G21: =E21*F21 -> 0 | J21: =H21*I21 -> 0 | K21: =G21+J21 -> 0 | M21: =M20+K21-L21 -> 87365.57
A22: 19 | B22: 46314 | G22: =E22*F22 -> 0 | J22: =H22*I22 -> 0 | K22: =G22+J22 -> 0 | M22: =M21+K22-L22 -> 87365.57
A23: 20 | B23: 46315 | G23: =E23*F23 -> 0 | J23: =H23*I23 -> 0 | K23: =G23+J23 -> 0 | M23: =M22+K23-L23 -> 87365.57
A24: 21 | B24: 46316 | G24: =E24*F24 -> 0 | J24: =H24*I24 -> 0 | K24: =G24+J24 -> 0 | M24: =M23+K24-L24 -> 87365.57
A25: 22 | B25: 46317 | G25: =E25*F25 -> 0 | J25: =H25*I25 -> 0 | K25: =G25+J25 -> 0 | M25: =M24+K25-L25 -> 87365.57
A26: 23 | B26: 46318 | G26: =E26*F26 -> 0 | J26: =H26*I26 -> 0 | K26: =G26+J26 -> 0 | M26: =M25+K26-L26 -> 87365.57
A27: 24 | B27: 46319 | G27: =E27*F27 -> 0 | J27: =H27*I27 -> 0 | K27: =G27+J27 -> 0 | M27: =M26+K27-L27 -> 87365.57
A28: 25 | B28: 46320 | G28: =E28*F28 -> 0 | J28: =H28*I28 -> 0 | K28: =G28+J28 -> 0 | M28: =M27+K28-L28 -> 87365.57
A29: 26 | B29: 46321 | G29: =E29*F29 -> 0 | J29: =H29*I29 -> 0 | K29: =G29+J29 -> 0 | M29: =M28+K29-L29 -> 87365.57
A30: 27 | B30: 46322 | G30: =E30*F30 -> 0 | J30: =H30*I30 -> 0 | K30: =G30+J30 -> 0 | M30: =M29+K30-L30 -> 87365.57
... A34: 31 | B34: 46326 | G34: =E34*F34 -> 0 | J34: =H34*I34 -> 0 | K34: =G34+J34 -> 0 | M34: =M33+K34-L34 -> 87365.57
E35: =SUM(E4:E34) -> 1664 | G35: =SUM(G4:G34) -> 165734.4 | H35: =SUM(H4:H34) -> 107.61 | J35: =SUM(J4:J34) -> 12021.113 | K35: =SUM(K4:K34) -> 177755.51 | L35: =SUM(L4:L34) -> 550000

Sheet Rattihali-2
A1: Shiva Oil Traders
A2: S.No | B2: Date | C2: GRN No | D2: Ind No/Bill No | E2: Diesel (Lts) | F2: Price | G2: Amount | H2: Petrol (Lts) | I2: Price | J2: Amount | K2: Total amount | L2: Amount paid | M2: As on Date | N2: Remarks
D3: Opening Balance | M3: 161393.37
A4: 1 | B4: 46296 | G4: =E4*F4 -> 0 | H4: 11 | I4: 111.82 | J4: =H4*I4 -> 1230.02 | K4: =G4+J4 -> 1230.02 | M4: =M3+K4-L4 -> 162623.39
A5: 2 | B5: 46297 | G5: =E5*F5 -> 0 | J5: =H5*I5 -> 0 | K5: =G5+J5 -> 0 | M5: =M4+K5-L5 -> 162623.39
A6: 3 | B6: 46298 | E6: 30 | F6: 99.7 | G6: =E6*F6 -> 2991 | H6: 5 | I6: 111.82 | J6: =H6*I6 -> 559.1 | K6: =G6+J6 -> 3550.1 | M6: =M5+K6-L6 -> 166173.49
A7: 4 | B7: 46299 | E7: 60 | F7: 99.7 | G7: =E7*F7 -> 5982 | J7: =H7*I7 -> 0 | K7: =G7+J7 -> 5982 | M7: =M6+K7-L7 -> 172155.49
A8: 5 | B8: 46300 | G8: =E8*F8 -> 0 | H8: 15 | I8: 111.82 | J8: =H8*I8 -> 1677.3 | K8: =G8+J8 -> 1677.3 | M8: =M7+K8-L8 -> 173832.79
A9: 6 | B9: 46301 | E9: 195 | F9: 99.7 | G9: =E9*F9 -> 19441.5 | H9: 5 | I9: 111.82 | J9: =H9*I9 -> 559.1 | K9: =G9+J9 -> 20000.6 | M9: =M8+K9-L9 -> 193833.39
A10: 7 | B10: 46302 | E10: 286 | F10: 99.7 | G10: =E10*F10 -> 28514.2 | H10: 16 | I10: 111.82 | J10: =H10*I10 -> 1789.12 | K10: =G10+J10 -> 30303.32 | M10: =M9+K10-L10 -> 224136.71
A11: 8 | B11: 46303 | E11: 80 | F11: 99.7 | G11: =E11*F11 -> 7976 | H11: 10 | I11: 111.82 | J11: =H11*I11 -> 1118.2 | K11: =G11+J11 -> 9094.2 | M11: =M10+K11-L11 -> 233230.91
A12: 9 | B12: 46304 | E12: 310 | F12: 99.7 | G12: =E12*F12 -> 30907 | J12: =H12*I12 -> 0 | K12: =G12+J12 -> 30907 | M12: =M11+K12-L12 -> 264137.91
A13: 10 | B13: 46305 | E13: 150 | F13: 99.7 | G13: =E13*F13 -> 14955 | J13: =H13*I13 -> 0 | K13: =G13+J13 -> 14955 | M13: =M12+K13-L13 -> 279092.91
A14: 11 | B14: 46306 | F14: 99.7 | G14: =E14*F14 -> 0 | J14: =H14*I14 -> 0 | K14: =G14+J14 -> 0 | M14: =M13+K14-L14 -> 279092.91
A15: 12 | B15: 46307 | G15: =E15*F15 -> 0 | H15: 17 | I15: 111.82 | J15: =H15*I15 -> 1900.94 | K15: =G15+J15 -> 1900.94 | M15: =M14+K15-L15 -> 280993.85
A16: 13 | B16: 46308 | E16: 335.31 | F16: 99.7 | G16: =E16*F16 -> 33430.407 | J16: =H16*I16 -> 0 | K16: =G16+J16 -> 33430.407 | M16: =M15+K16-L16 -> 314424.26
A17: 14 | B17: 46309 | E17: 91.01 | F17: 99.7 | G17: =E17*F17 -> 9073.697 | J17: =H17*I17 -> 0 | K17: =G17+J17 -> 9073.697 | M17: =M16+K17-L17 -> 323497.96
A18: 15 | B18: 46310 | E18: 110 | F18: 99.7 | G18: =E18*F18 -> 10967 | H18: 16 | I18: 111.82 | J18: =H18*I18 -> 1789.12 | K18: =G18+J18 -> 12756.12 | L18: 200000 | M18: =M17+K18-L18 -> 136254.08
A19: 16 | B19: 46311 | G19: =E19*F19 -> 0 | J19: =H19*I19 -> 0 | K19: =G19+J19 -> 0 | M19: =M18+K19-L19 -> 136254.08
A20: 17 | B20: 46312 | G20: =E20*F20 -> 0 | J20: =H20*I20 -> 0 | K20: =G20+J20 -> 0 | M20: =M19+K20-L20 -> 136254.08
A21: 18 | B21: 46313 | G21: =E21*F21 -> 0 | J21: =H21*I21 -> 0 | K21: =G21+J21 -> 0 | M21: =M20+K21-L21 -> 136254.08
A22: 19 | B22: 46314 | G22: =E22*F22 -> 0 | J22: =H22*I22 -> 0 | K22: =G22+J22 -> 0 | M22: =M21+K22-L22 -> 136254.08 | U22: =70+20+E2690 -> 90
A23: 20 | B23: 46315 | G23: =E23*F23 -> 0 | J23: =H23*I23 -> 0 | K23: =G23+J23 -> 0 | M23: =M22+K23-L23 -> 136254.08
A24: 21 | B24: 46316 | G24: =E24*F24 -> 0 | J24: =H24*I24 -> 0 | K24: =G24+J24 -> 0 | M24: =M23+K24-L24 -> 136254.08
A25: 22 | B25: 46317 | G25: =E25*F25 -> 0 | J25: =H25*I25 -> 0 | K25: =G25+J25 -> 0 | M25: =M24+K25-L25 -> 136254.08
A26: 23 | B26: 46318 | G26: =E26*F26 -> 0 | J26: =H26*I26 -> 0 | K26: =G26+J26 -> 0 | M26: =M25+K26-L26 -> 136254.08
A27: 24 | B27: 46319 | G27: =E27*F27 -> 0 | J27: =H27*I27 -> 0 | K27: =G27+J27 -> 0 | M27: =M26+K27-L27 -> 136254.08
A28: 25 | B28: 46320 | G28: =E28*F28 -> 0 | J28: =H28*I28 -> 0 | K28: =G28+J28 -> 0 | M28: =M27+K28-L28 -> 136254.08
A29: 26 | B29: 46321 | G29: =E29*F29 -> 0 | J29: =H29*I29 -> 0 | K29: =G29+J29 -> 0 | M29: =M28+K29-L29 -> 136254.08
A30: 27 | B30: 46322 | G30: =E30*F30 -> 0 | J30: =H30*I30 -> 0 | K30: =G30+J30 -> 0 | M30: =M29+K30-L30 -> 136254.08
A31: 28 | B31: 46323 | G31: =E31*F31 -> 0 | J31: =H31*I31 -> 0 | K31: =G31+J31 -> 0 | M31: =M30+K31-L31 -> 136254.08
A32: 29 | B32: 46324 | G32: =E32*F32 -> 0 | J32: =H32*I32 -> 0 | K32: =G32+J32 -> 0 | M32: =M31+K32-L32 -> 136254.08
A33: 30 | B33: 46325 | G33: =E33*F33 -> 0 | J33: =H33*I33 -> 0 | K33: =G33+J33 -> 0 | M33: =M32+K33-L33 -> 136254.08
A34: 31 | B34: 46326 | G34: =E34*F34 -> 0 | J34: =H34*I34 -> 0 | K34: =G34+J34 -> 0 | L34: 0 | M34: =M33+K34-L34 -> 136254.08
A35: 32 | G35: =E35*F35 -> 0 | J35: =H35*I35 -> 0 | K35: =G35+J35 -> 0 | L35: 0 | M35: =M34+K35-L35 -> 136254.08
M36: =M35+K36-L36 -> 136254.08
E37: =SUM(E4:E35) -> 1647.32 | G37: =SUM(G4:G35) -> 164237.8 | H37: =SUM(H4:H35) -> 95 | J37: =SUM(J4:J35) -> 10622.9 | K37: =SUM(K4:K35) -> 174860.7 | L37: =SUM(L4:L35) -> 200000
I40: =K25+L25 -> 0

Sheet Gajendragada
A1: Vanasri Petrol Pump
A2: S.No | B2: Date | C2: GRN No | D2: Ind no/Bill No | E2: Diesel (Lts) | F2: Price | G2: Amount | H2: Petrol (Lts) | I2: Price | J2: Amount | K2: Total amount | L2: Amount paid | M2: As on Date | N2: Remarks
A3: Opening Balance | K3: 126924.96 | M3: 126924.96
A4: 1 | B4: 46296 | E4: 30 | F4: 99.64 | G4: =E4*F4 -> 2989.2 | H4: 5 | I4: 111.77 | J4: =H4*I4 -> 558.85 | K4: =G4+J4 -> 3548.05 | M4: =M3+K4-L4 -> 130473.01
A5: 2 | B5: 46297 | E5: 40 | F5: 99.64 | G5: =E5*F5 -> 3985.6 | H5: 6 | I5: 111.77 | J5: =H5*I5 -> 670.62 | K5: =G5+J5 -> 4656.22 | M5: =M4+K5-L5 -> 135129.23
A6: 3 | B6: 46298 | E6: 30 | F6: 99.64 | G6: =E6*F6 -> 2989.2 | H6: 10 | I6: 111.77 | J6: =H6*I6 -> 1117.7 | K6: =G6+J6 -> 4106.9 | M6: =M5+K6-L6 -> 139236.13
A7: 4 | B7: 46299 | G7: =E7*F7 -> 0 | J7: =H7*I7 -> 0 | K7: =G7+J7 -> 0 | M7: =M6+K7-L7 -> 139236.13
A8: 5 | B8: 46300 | E8: 20 | F8: 99.64 | G8: =E8*F8 -> 1992.8 | J8: =H8*I8 -> 0 | K8: =G8+J8 -> 1992.8 | M8: =M7+K8-L8 -> 141228.93 | O8: 8497892194 | P8: raja bhakshi
A9: 6 | B9: 46301 | E9: 20 | F9: 99.64 | G9: =E9*F9 -> 1992.8 | H9: 5 | I9: 111.77 | J9: =H9*I9 -> 558.85 | K9: =G9+J9 -> 2551.65 | M9: =M8+K9-L9 -> 143780.58
A10: 7 | B10: 46302 | E10: 30 | F10: 99.64 | G10: =E10*F10 -> 2989.2 | H10: 6 | I10: 111.77 | J10: =H10*I10 -> 670.62 | K10: =G10+J10 -> 3659.82 | M10: =M9+K10-L10 -> 147440.4
A11: 8 | B11: 46303 | E11: 20 | F11: 99.64 | G11: =E11*F11 -> 1992.8 | J11: =H11*I11 -> 0 | K11: =G11+J11 -> 1992.8 | M11: =M10+K11-L11 -> 149433.2
A12: 9 | B12: 46304 | E12: 30 | F12: 99.64 | G12: =E12*F12 -> 2989.2 | J12: =H12*I12 -> 0 | K12: =G12+J12 -> 2989.2 | M12: =M11+K12-L12 -> 152422.4
A13: 10 | B13: 46305 | G13: =E13*F13 -> 0 | H13: 6 | I13: 111.77 | J13: =H13*I13 -> 670.62 | K13: =G13+J13 -> 670.62 | M13: =M12+K13-L13 -> 153093.02
A14: 11 | B14: 46306 | E14: 30 | F14: 99.64 | G14: =E14*F14 -> 2989.2 | J14: =H14*I14 -> 0 | K14: =G14+J14 -> 2989.2 | M14: =M13+K14-L14 -> 156082.22
A15: 12 | B15: 46307 | E15: 20 | F15: 99.64 | G15: =E15*F15 -> 1992.8 | J15: =H15*I15 -> 0 | K15: =G15+J15 -> 1992.8 | M15: =M14+K15-L15 -> 158075.02
A16: 13 | B16: 46308 | E16: 46 | F16: 99.64 | G16: =E16*F16 -> 4583.44 | H16: 10 | I16: 111.77 | J16: =H16*I16 -> 1117.7 | K16: =G16+J16 -> 5701.14 | M16: =M15+K16-L16 -> 163776.16
A17: 14 | B17: 46309 | G17: =E17*F17 -> 0 | H17: 7.73 | I17: 111.77 | J17: =H17*I17 -> 863.9821 | K17: =G17+J17 -> 863.9821 | M17: =M16+K17-L17 -> 164640.14
A18: 15 | B18: 46310 | E18: 20 | F18: 99.64 | G18: =E18*F18 -> 1992.8 | H18: 5 | I18: 111.77 | J18: =H18*I18 -> 558.85 | K18: =G18+J18 -> 2551.65 | M18: =M17+K18-L18 -> 167191.79
A19: 16 | B19: 46311 | G19: =E19*F19 -> 0 | J19: =H19*I19 -> 0 | K19: =G19+J19 -> 0 | M19: =M18+K19-L19 -> 167191.79
A20: 17 | B20: 46312 | G20: =E20*F20 -> 0 | J20: =H20*I20 -> 0 | K20: =G20+J20 -> 0 | M20: =M19+K20-L20 -> 167191.79
A21: 18 | B21: 46313 | G21: =E21*F21 -> 0 | J21: =H21*I21 -> 0 | K21: =G21+J21 -> 0 | M21: =M20+K21-L21 -> 167191.79
A22: 19 | B22: 46314 | G22: =E22*F22 -> 0 | J22: =H22*I22 -> 0 | K22: =G22+J22 -> 0 | M22: =M21+K22-L22 -> 167191.79
B23: 46315 | G23: =E23*F23 -> 0 | J23: =H23*I23 -> 0 | K23: =G23+J23 -> 0 | M23: =M22+K23-L23 -> 167191.79
A24: 20 | B24: 46316 | G24: =E24*F24 -> 0 | J24: =H24*I24 -> 0 | K24: =G24+J24 -> 0 | M24: =M23+K24-L24 -> 167191.79
A25: 21 | B25: 46317 | G25: =E25*F25 -> 0 | J25: =H25*I25 -> 0 | K25: =G25+J25 -> 0 | M25: =M24+K25-L25 -> 167191.79
A26: 22 | B26: 46318 | G26: =E26*F26 -> 0 | J26: =H26*I26 -> 0 | K26: =G26+J26 -> 0 | M26: =M25+K26-L26 -> 167191.79
A27: 23 | B27: 46319 | G27: =E27*F27 -> 0 | J27: =H27*I27 -> 0 | K27: =G27+J27 -> 0 | M27: =M26+K27-L27 -> 167191.79
A28: 24 | B28: 46320 | G28: =E28*F28 -> 0 | J28: =H28*I28 -> 0 | K28: =G28+J28 -> 0 | M28: =M27+K28-L28 -> 167191.79
A29: 25 | B29: 46321 | G29: =E29*F29 -> 0 | J29: =H29*I29 -> 0 | K29: =G29+J29 -> 0 | M29: =M28+K29-L29 -> 167191.79
A30: 26 | B30: 46322 | G30: =E30*F30 -> 0 | J30: =H30*I30 -> 0 | K30: =G30+J30 -> 0 | M30: =M29+K30-L30 -> 167191.79
A31: 27 | B31: 46323 | G31: =E31*F31 -> 0 | J31: =H31*I31 -> 0 | K31: =G31+J31 -> 0 | M31: =M30+K31-L31 -> 167191.79
A32: 28 | B32: 46324 | G32: =E32*F32 -> 0 | J32: =H32*I32 -> 0 | K32: =G32+J32 -> 0 | M32: =M31+K32-L32 -> 167191.79
A33: 29 | B33: 46325 | G33: =E33*F33 -> 0 | J33: =H33*I33 -> 0 | K33: =G33+J33 -> 0 | M33: =M32+K33-L33 -> 167191.79
A34: 30 | B34: 46326 | G34: =E34*F34 -> 0 | J34: =H34*I34 -> 0 | K34: =G34+J34 -> 0 | M34: =M33+K34-L34 -> 167191.79
A35: 31 | G35: =E35*F35 -> 0 | J35: =H35*I35 -> 0 | K35: =G35+J35 -> 0 | M35: =M34+K35-L35 -> 167191.79
E36: =SUM(E4:E35) -> 336 | G36: =SUM(G4:G35) -> 33479.04 | H36: =SUM(H4:H35) -> 60.73 | J36: =SUM(J4:J35) -> 6787.7921 | K36: =SUM(K4:K35) -> 40266.832 | L36: =SUM(L4:L35) -> 0

Sheet Gokak Dharwad PKG 3
A1: AJ Petrolinks
A2: S.No | B2: Date | C2: GRN No | D2: Ind No/Bill No | E2: Diesel (Lts) | F2: Price | G2: Amount | H2: Petrol (Lts) | I2: Price | J2: Amount | K2: Total amount | L2: Amount paid | M2: As on Date | N2: Remarks
C3: Opening Balance | K3: 458335.94 | M3: 458335.94
A4: 1 | B4: 46296 | E4: 140.49 | F4: 99.29 | G4: =E4*F4 -> 13949.252 | J4: =H4*I4 -> 0 | K4: =G4+J4 -> 13949.252 | M4: =M3+K4-L4 -> 472285.19
A5: 2 | B5: 46297 | E5: 700 | F5: 99.29 | G5: =E5*F5 -> 69503 | J5: =H5*I5 -> 0 | K5: =G5+J5 -> 69503 | M5: =M4+K5-L5 -> 541788.19
A6: 3 | B6: 46298 | G6: =E6*F6 -> 0 | J6: =H6*I6 -> 0 | K6: =G6+J6 -> 0 | M6: =M5+K6-L6 -> 541788.19
A7: 4 | B7: 46299 | G7: =E7*F7 -> 0 | J7: =H7*I7 -> 0 | K7: =G7+J7 -> 0 | M7: =M6+K7-L7 -> 541788.19
A8: 5 | B8: 46300 | E8: 218.86 | F8: 99.29 | G8: =E8*F8 -> 21730.609 | J8: =H8*I8 -> 0 | K8: =G8+J8 -> 21730.609 | M8: =M7+K8-L8 -> 563518.8
A9: 6 | B9: 46301 | G9: =E9*F9 -> 0 | J9: =H9*I9 -> 0 | K9: =G9+J9 -> 0 | M9: =M8+K9-L9 -> 563518.8
A10: 7 | B10: 46302 | G10: =E10*F10 -> 0 | J10: =H10*I10 -> 0 | K10: =G10+J10 -> 0 | M10: =M9+K10-L10 -> 563518.8
A11: 8 | B11: 46303 | G11: =E11*F11 -> 0 | J11: =H11*I11 -> 0 | K11: =G11+J11 -> 0 | M11: =M10+K11-L11 -> 563518.8
A12: 9 | B12: 46304 | G12: =E12*F12 -> 0 | J12: =H12*I12 -> 0 | K12: =G12+J12 -> 0 | M12: =M11+K12-L12 -> 563518.8
A13: 10 | B13: 46305 | E13: 150 | F13: 99.29 | G13: =E13*F13 -> 14893.5 | J13: =H13*I13 -> 0 | K13: =G13+J13 -> 14893.5 | L13: 250000 | M13: =M12+K13-L13 -> 328412.3
A14: 11 | B14: 46306 | E14: 143.43 | F14: 99.29 | G14: =E14*F14 -> 14241.165 | J14: =H14*I14 -> 0 | K14: =G14+J14 -> 14241.165 | M14: =M13+K14-L14 -> 342653.46
A15: 12 | B15: 46307 | E15: 50.4 | F15: 99.29 | G15: =E15*F15 -> 5004.216 | J15: =H15*I15 -> 0 | K15: =G15+J15 -> 5004.216 | M15: =M14+K15-L15 -> 347657.68
A16: 13 | B16: 46308 | E16: 100 | F16: 99.29 | G16: =E16*F16 -> 9929 | J16: =H16*I16 -> 0 | K16: =G16+J16 -> 9929 | M16: =M15+K16-L16 -> 357586.68
A17: 14 | B17: 46309 | E17: 620.61 | F17: 99.29 | G17: =E17*F17 -> 61620.367 | H17: 5 | I17: 111.38 | J17: =H17*I17 -> 556.9 | K17: =G17+J17 -> 62177.267 | M17: =M16+K17-L17 -> 419763.95
A18: 15 | B18: 46310 | G18: =E18*F18 -> 0 | J18: =H18*I18 -> 0 | K18: =G18+J18 -> 0 | L18: 300000 | M18: =M17+K18-L18 -> 119763.95
A19: 16 | B19: 46311 | G19: =E19*F19 -> 0 | J19: =H19*I19 -> 0 | K19: =G19+J19 -> 0 | M19: =M18+K19-L19 -> 119763.95
A20: 17 | B20: 46312 | G20: =E20*F20 -> 0 | J20: =H20*I20 -> 0 | K20: =G20+J20 -> 0 | M20: =M19+K20-L20 -> 119763.95
A21: 18 | B21: 46313 | G21: =E21*F21 -> 0 | J21: =H21*I21 -> 0 | K21: =G21+J21 -> 0 | M21: =M20+K21-L21 -> 119763.95
A22: 19 | B22: 46314 | G22: =E22*F22 -> 0 | J22: =H22*I22 -> 0 | K22: =G22+J22 -> 0 | M22: =M21+K22-L22 -> 119763.95
A23: 20 | B23: 46315 | G23: =E23*F23 -> 0 | J23: =H23*I23 -> 0 | K23: =G23+J23 -> 0 | M23: =M22+K23-L23 -> 119763.95
A24: 21 | B24: 46316 | G24: =E24*F24 -> 0 | J24: =H24*I24 -> 0 | K24: =G24+J24 -> 0 | M24: =M23+K24-L24 -> 119763.95
A25: 22 | B25: 46317 | G25: =E25*F25 -> 0 | J25: =H25*I25 -> 0 | K25: =G25+J25 -> 0 | M25: =M24+K25-L25 -> 119763.95
A26: 23 | B26: 46318 | G26: =E26*F26 -> 0 | J26: =H26*I26 -> 0 | K26: =G26+J26 -> 0 | M26: =M25+K26-L26 -> 119763.95
A27: 24 | B27: 46319 | G27: =E27*F27 -> 0 | J27: =H27*I27 -> 0 | K27: =G27+J27 -> 0 | M27: =M26+K27-L27 -> 119763.95
A28: 25 | B28: 46320 | G28: =E28*F28 -> 0 | J28: =H28*I28 -> 0 | K28: =G28+J28 -> 0 | M28: =M27+K28-L28 -> 119763.95
A29: 26 | B29: 46321 | G29: =E29*F29 -> 0 | J29: =H29*I29 -> 0 | K29: =G29+J29 -> 0 | M29: =M28+K29-L29 -> 119763.95
A30: 27 | B30: 46322 | G30: =E30*F30 -> 0 | J30: =H30*I30 -> 0 | K30: =G30+J30 -> 0 | M30: =M29+K30-L30 -> 119763.95
... A34: 31 | B34: 46326 | G34: =E34*F34 -> 0 | J34: =H34*I34 -> 0 | K34: =G34+J34 -> 0 | M34: =M33+K34-L34 -> 119763.95
A35: 32 | G35: =E35*F35 -> 0 | J35: =H35*I35 -> 0 | K35: =G35+J35 -> 0 | M35: =M34+K35-L35 -> 119763.95
A36: 33 | G36: =E36*F36 -> 0 | J36: =H36*I36 -> 0 | K36: =G36+J36 -> 0 | M36: =M35+K36-L36 -> 119763.95
A37: 34 | G37: =E37*F37 -> 0 | J37: =H37*I37 -> 0 | K37: =G37+J37 -> 0 | M37: =M36+K37-L37 -> 119763.95
A38: 35 | G38: =E38*F38 -> 0 | J38: =H38*I38 -> 0 | K38: =G38+J38 -> 0 | M38: =M37+K38-L38 -> 119763.95
A39: 36 | G39: =E39*F39 -> 0 | J39: =H39*I39 -> 0 | K39: =G39+J39 -> 0 | M39: =M38+K39-L39 -> 119763.95
A40: 37 | G40: =E40*F40 -> 0 | J40: =H40*I40 -> 0 | K40: =G40+J40 -> 0 | M40: =M39+K40-L40 -> 119763.95
G41: =E41*F41 -> 0 | J41: =H41*I41 -> 0 | K41: =G41+J41 -> 0 | M41: =M40+K41-L41 -> 119763.95
E42: =SUM(E4:E39) -> 2123.79 | G42: =SUM(G4:G39) -> 210871.11 | H42: =SUM(H4:H39) -> 5 | J42: =SUM(J4:J39) -> 556.9 | K42: =SUM(K4:K39) -> 211428.01 | L42: =SUM(L4:L39) -> 550000

Sheet Ankalgi
A1: Shiva ganga
A2: S.No | B2: Date | C2: GRN No | D2: Ind no/Bill No | E2: Diesel (Lts) | F2: Price | G2: Amount | H2: Petrol (Lts) | I2: Price | J2: Amount | K2: Total amount | L2: Amount paid | M2: As on Date | N2: Remarks
