Workbook

Sheet  MIs
A2: S.No | B2: NAme | C2: Lacation | D2: Card Number | E2: Card Number | F2: Category | G2: 1st Jan | I2: 2nd Jan | J2: 3rd Jan | K2: 4th Jan | L2: 5th Jan | M2: 6th Jan | N2: 7th Jan | O2: 8th Jan | P2: 9th Jan | Q2: 10th Jan | R2: 11th Jan | S2: 12th Jan | T2: 13th Jan | U2: 14th Jan | V2: 15th Jan | W2: 16th Jan | X2: 17th Jan | Y2: 18th Jan | Z2: 19th Jan | AA2: 20th Jan | AB2: 21st Jan | AC2: 22nd Jan | AD2: 23rd Jan | AE2: 24th Jan | AF2: 25th Jan | AG2: 26th Jan | AH2: 27th Jan | AI2: 28th Jan | AJ2: 29th Jan | AK2: 30th Jan | AL2: 31st Jan | AM2: Total
F3: Diesel
A4: 1 | B4: Rambabu | C4: HO(Two Wheeler) | D4: FC3450563999 | E4: Diesel | F4: 0 | G4: 0 | H4: 0 | I4: 0 | J4: 0 | K4: 0 | L4: 0 | M4: 0 | N4: 0 | O4: 0 | P4: 0 | Q4: 0 | R4: 0 | S4: 0 | T4: 0 | U4: 0 | V4: 0 | W4: 0 | X4: 5.22 | Y4: 0 | Z4: 0 | AA4: 0 | AB4: 0 | AC4: 0 | AD4: 60 | AE4: 0 | AF4: 0 | AG4: 0 | AH4: 4.56 | AI4: 0 | AJ4: 0 | AK4: 0 | AL4: 0 | AM4: =SUM(F4:AL4) -> 69.78
E5: Petrol | F5: 0 | G5: 4.69 | H5: 0 | I5: 0 | J5: 0 | K5: 0 | L5: 0 | M5: 0 | N5: 3.91 | O5: 0 | P5: 6.98 | Q5: 0 | R5: 0 | S5: 0 | T5: 0 | U5: 0 | V5: 0 | W5: 0 | X5: 0 | Y5: 0 | Z5: 0 | AB5: 0 | AC5: 0 | AD5: 0 | AE5: 0 | AF5: 0 | AG5: 0 | AH5: 0 | AI5: 0 | AJ5: 0 | AK5: 0 | AL5: 0 | AM5: =SUM(F5:AL5) -> 15.58
A6: 2 | B6: Hanumanth Rao | C6: HO | D6: FC3450676131 | E6: Diesel | F6: 0 | G6: 0 | H6: 0 | I6: 0 | J6: 0 | K6: 0 | L6: 0 | M6: 0 | N6: 0 | O6: 0 | P6: 0 | Q6: 0 | R6: 0 | S6: 0 | T6: 0 | U6: 0 | V6: 0 | W6: 0 | X6: 0 | Y6: 0 | Z6: 0 | AA6: 0 | AB6: 0 | AC6: 0 | AD6: 0 | AE6: 0 | AF6: 0 | AG6: 0 | AH6: 0 | AI6: 0 | AJ6: 0 | AK6: 0 | AL6: 0 | AM6: =SUM(F6:AL6) -> 0
E7: Petrol | F7: 0 | G7: 0 | H7: 0 | I7: 0 | J7: 0 | K7: 0 | L7: 0 | M7: 0 | N7: 0 | O7: 0 | P7: 0 | Q7: 0 | R7: 0 | S7: 0 | T7: 0 | U7: 0 | V7: 0 | W7: 0 | X7: 0 | Y7: 0 | Z7: 0 | AB7: 0 | AC7: 0 | AD7: 0 | AE7: 0 | AF7: 0 | AG7: 0 | AH7: 0 | AI7: 0 | AJ7: 0 | AK7: 0 | AL7: 0 | AM7: =SUM(F7:AL7) -> 0
A8: 3 | B8: Radhakrishna | C8: HO | D8: FC8000207658 | E8: Diesel | F8: 0 | G8: 0 | H8: 0 | I8: 0 | J8: 33.44 | K8: 0 | L8: 0 | M8: 0 | N8: 0 | O8: 0 | P8: 0 | Q8: 0 | R8: 35.53 | S8: 0 | T8: 0 | U8: 0 | V8: 0 | W8: 0 | X8: 0 | Y8: 0 | Z8: 0 | AA8: 0 | AB8: 33.44 | AC8: 0 | AD8: 0 | AE8: 0 | AF8: 0 | AG8: 0 | AH8: 0 | AI8: 0 | AJ8: 0 | AK8: 0 | AL8: 0 | AM8: =SUM(F8:AL8) -> 102.41
E9: Petrol | F9: 0 | G9: 0 | H9: 0 | I9: 0 | J9: 0 | K9: 0 | L9: 0 | M9: 0 | N9: 0 | O9: 0 | P9: 0 | Q9: 0 | R9: 0 | S9: 0 | T9: 0 | U9: 0 | V9: 0 | W9: 0 | X9: 0 | Y9: 0 | Z9: 0 | AB9: 0 | AC9: 0 | AD9: 0 | AE9: 0 | AF9: 0 | AG9: 0 | AH9: 0 | AI9: 0 | AJ9: 0 | AK9: 0 | AL9: 0 | AM9: =SUM(F9:AL9) -> 0
A10: 4 | B10: VIjay | C10: HO | D10: FC3450698859 | E10: Diesel | F10: 0 | G10: 0 | H10: 0 | I10: 0 | J10: 0 | K10: 0 | L10: 0 | M10: 0 | N10: 0 | O10: 0 | P10: 49.22 | Q10: 0 | R10: 0 | S10: 0 | T10: 0 | U10: 54.57 | V10: 0 | W10: 0 | X10: 0 | Y10: 0 | Z10: 0 | AA10: 0 | AB10: 0 | AC10: 0 | AD10: 49.8 | AE10: 0 | AF10: 0 | AG10: 0 | AH10: 0 | AI10: 0 | AJ10: 0 | AK10: 0 | AL10: 0 | AM10: =SUM(F10:AL10) -> 153.59
E11: Petrol | F11: 0 | G11: 0 | H11: 0 | I11: 0 | J11: 0 | K11: 0 | L11: 0 | M11: 0 | N11: 0 | O11: 0 | P11: 0 | Q11: 0 | R11: 0 | S11: 0 | T11: 0 | U11: 0 | V11: 0 | W11: 0 | X11: 0 | Y11: 0 | Z11: 0 | AB11: 0 | AC11: 0 | AD11: 0 | AE11: 0 | AF11: 0 | AG11: 0 | AH11: 0 | AI11: 0 | AJ11: 0 | AK11: 0 | AL11: 0 | AM11: =SUM(F11:AL11) -> 0
A12: 5 | B12: Client | C12: Hiriyur | D12: FC3450698864 | E12: Diesel | F12: 0 | G12: 0 | H12: 0 | I12: 0 | J12: 0 | K12: 0 | L12: 0 | M12: 0 | N12: 86.29 | O12: 0 | P12: 0 | Q12: 0 | R12: 0 | S12: 0 | T12: 0 | U12: 0 | V12: 0 | W12: 0 | X12: 0 | Y12: 0 | Z12: 0 | AA12: 0 | AB12: 0 | AC12: 0 | AD12: 145.61 | AE12: 0 | AF12: 0 | AG12: 0 | AH12: 0 | AI12: 0 | AJ12: 0 | AK12: 0 | AL12: 0 | AM12: =SUM(F12:AL12) -> 231.9
E13: Petrol | F13: 0 | G13: 0 | H13: 0 | I13: 0 | J13: 0 | K13: 0 | L13: 0 | M13: 0 | N13: 0 | O13: 0 | P13: 0 | Q13: 0 | R13: 0 | S13: 0 | T13: 0 | U13: 0 | V13: 0 | W13: 0 | X13: 0 | Y13: 0 | Z13: 0 | AB13: 0 | AC13: 0 | AD13: 0 | AE13: 0 | AF13: 0 | AG13: 0 | AH13: 0 | AI13: 0 | AJ13: 0 | AK13: 0 | AL13: 0 | AM13: =SUM(F13:AL13) -> 0
A14: 6 | B14: Client | C14: Hosadurga | D14: FC3450698865 | E14: Diesel | F14: 0 | G14: 0 | H14: 0 | I14: 0 | J14: 0 | K14: 0 | L14: 40 | M14: 40 | N14: 0 | O14: 36 | P14: 35 | Q14: 0 | R14: 0 | S14: 0 | T14: 0 | U14: 0 | V14: 0 | W14: 45 | X14: 45 | Y14: 43.53 | Z14: 40 | AA14: 43 | AB14: 0 | AC14: 40 | AD14: 0 | AE14: 40 | AF14: 0 | AG14: 0 | AH14: 0 | AI14: 0 | AJ14: 0 | AK14: 0 | AL14: 0 | AM14: =SUM(F14:AL14) -> 447.53
E15: Petrol | F15: 0 | G15: 0 | H15: 0 | I15: 0 | J15: 0 | K15: 0 | L15: 0 | M15: 0 | N15: 0 | O15: 0 | P15: 0 | Q15: 0 | R15: 0 | S15: 0 | T15: 0 | U15: 0 | V15: 0 | W15: 0 | X15: 0 | Y15: 0 | Z15: 0 | AB15: 0 | AC15: 0 | AD15: 0 | AE15: 0 | AF15: 0 | AG15: 0 | AH15: 0 | AI15: 0 | AJ15: 0 | AK15: 0 | AL15: 0 | AM15: =SUM(F15:AL15) -> 0
G18: Diesel Price

Sheet March-2026
A1: S.no | B1: Site Name | C1: Bunk Name | D1: Diesel(Liters) | E1: Diesel Amount | F1: Petrol(Liters) | G1: Petrol Amount | H1: Total Amount | I1: Opening Blance | J1: Amount Paid | K1: Closing Balances
A2: 1 | B2: Khammam-1 | C2: Divya laxmi ganapathi | D2: =+'Khammam-1'!E38 -> 4500 | E2: =+'Khammam-1'!G38 -> 430560 | F2: =+'Khammam-1'!H38 -> 80 | G2: =+'Khammam-1'!J38 -> 8596.8 | H2: =E2+G2 -> 439156.8 | I2: =+'Khammam-1'!K3 -> 8237254.9 | J2: =+'Khammam-1'!L38 -> 4500000 | K2: =H2+I2-J2 -> 4176411.7 | L2: k
A3: 2 | B3: Khammam-2 | C3: Jayasai union bunk | D3: =+'Khammam-2'!E35 -> 60358.173 | E3: =+'Khammam-2'!G35 -> 5864453.1 | F3: =+'Khammam-2'!H35 -> 1045 | G3: =+'Khammam-2'!J35 -> 112327.05 | H3: =E3+G3 -> 5976780.1 | I3: =+'Khammam-2'!K3 -> 5555857.2 | J3: =+'Khammam-2'!L35 -> 3500000 | K3: =H3+I3-J3 -> 8032637.3 | L3: k
A4: 3 | B4: Khammam-3 | C4: JSASFuel Genie India Pvt.Ltd | D4: =+'Khammam-3'!E35 -> 138043.93 | E4: =+'Khammam-3'!G35 -> 13087760 | F4: =+'Khammam-3'!H35 -> 0 | G4: =+'Khammam-3'!J35 -> 0 | H4: =E4+G4 -> 13087760 | I4: =+'Khammam-3'!M3 -> 1140143.1 | J4: =+'Khammam-3'!L35 -> 6000000 | K4: =H4+I4-J4 -> 8227903.3 | L4: k
A5: 4 | B5: Khammam-4 | C5: Vajra Mahalakshmi filling station | D5: =+'Khammam-4'!E38 -> 3459.76 | E5: =+'Khammam-4'!G38 -> 330407.08 | F5: =+'Khammam-4'!H38 -> 0 | G5: =+'Khammam-4'!J38 -> 0 | H5: =E5+G5 -> 330407.08 | I5: =+'Khammam-4'!M3 -> 0 | J5: =+'Khammam-4'!L38 -> 0 | K5: =H5+I5-J5 -> 330407.08 | L5: k
A6: 5 | B6: Khammam-5 | C6: SR HP Filling Station ( Dhamsalapuram) | D6: =+'Khammam-5'!E38 -> 6273.16 | E6: =+'Khammam-5'!G38 -> 600215.95 | F6: =+'Khammam-5'!H38 -> 0 | G6: =+'Khammam-5'!J38 -> 0 | H6: =E6+G6 -> 600215.95 | I6: =+'Khammam-5'!M3 -> 0 | J6: =+'Khammam-5'!L38 -> 600215.26 | K6: =H6+I6-J6 -> 0.6864
A7: 6 | B7: Jadcherla-3 | C7: JSASFuel Genie India Pvt.Ltd | D7: =+'Jadcherla-3'!E35 -> 25398 | E7: =+'Jadcherla-3'!G35 -> 2426931.1 | F7: =+'Jadcherla-3'!H35 -> 0 | G7: =+'Jadcherla-3'!J35 -> 0 | H7: =E7+G7 -> 2426931.1 | I7: =+'Jadcherla-3'!M3 -> 1026278.2 | J7: =+'Jadcherla-3'!L35 -> 1000000 | K7: =H7+I7-J7 -> 2453209.4 | L7: k
A8: 7 | B8: Jadcherla-4 | C8: Shree Poornima F/S | D8: =+'Jadcherla-4'!E35 -> 0 | E8: =+'Jadcherla-4'!G35 -> 0 | F8: =+'Jadcherla-4'!H35 -> 210 | G8: =+'Jadcherla-4'!J35 -> 22701 | H8: =E8+G8 -> 22701 | I8: =+'Jadcherla-4'!M3 -> 24863 | J8: =+'Jadcherla-4'!L35 -> 37835 | K8: =H8+I8-J8 -> 9729 | L8: k
A9: 8 | B9: Sangareddy-1 | C9: Durga Indhan | D9: =+' Sangareeddy-1'!E35 -> 2727.69 | E9: =+' Sangareeddy-1'!G35 -> 262867.49 | F9: =+' Sangareeddy-1'!H35 -> 153.31 | G9: =+' Sangareeddy-1'!J35 -> 16583.543 | H9: =E9+G9 -> 279451.03 | I9: =+' Sangareeddy-1'!M3 -> 151710.02 | J9: =+' Sangareeddy-1'!L35 -> 360000 | K9: =H9+I9-J9 -> 71161.048 | L9: k
A10: 9 | B10: Sangareddy-2 | C10: Durga Bhavani F/S | D10: =+' Sangareddy-2'!E35 -> 6245.7 | E10: =+' Sangareddy-2'!G35 -> 602335.31 | F10: =+' Sangareddy-2'!H35 -> 205.97 | G10: =+' Sangareddy-2'!J35 -> 22308.611 | H10: =E10+G10 -> 624643.92 | I10: =+' Sangareddy-2'!M3 -> 0 | J10: =+' Sangareddy-2'!L35 -> 300000 | K10: =H10+I10-J10 -> 324643.92 | L10: k
A11: 10 | B11: Dindi | C11: Akarapu Balakistamma Fillling | D11: =+Dindi!E35 -> 35.41 | E11: =+Dindi!G35 -> 3402.1928 | F11: =+Dindi!H35 -> 0 | G11: =+Dindi!J35 -> 0 | H11: =E11+G11 -> 3402.1928 | I11: =+Dindi!M3 -> 0 | J11: =+Dindi!L35 -> 3402.1928 | K11: =H11+I11-J11 -> 0 | L11: k
A12: 11 | B12: Madanapalli | D12: =+'Madana palli'!E36 -> 430.78 | E12: =+'Madana palli'!G36 -> 42114.895 | F12: =+'Madana palli'!H36 -> 20.97 | G12: =+'Madana palli'!J36 -> 2298.7314 | H12: =E12+G12 -> 44413.627 | I12: =+'Madana palli'!M3 -> 0 | J12: =+'Madana palli'!L36 -> 44413.627 | K12: =H12+I12-J12 -> 0 | L12: k
A13: 12 | B13: Kakinada | D13: =+Amalapuram!E38 -> 491.85 | E13: =+Amalapuram!G38 -> 47376.805 | F13: =+Amalapuram!H38 -> 82.93 | G13: =+Amalapuram!J38 -> 8948.87 | H13: =E13+G13 -> 56325.675 | I13: =+Amalapuram!M3 -> 0 | J13: =+Amalapuram!L38 -> 56325.675 | K13: =H13+I13-J13 -> 0 | L13: k
A14: 13 | B14: YG Gudda-2 | C14: Pankaja HP Fuel Center | D14: =+'YG Gudda-2'!E37 -> 8492.77 | E14: =+'YG Gudda-2'!G37 -> 775644.68 | F14: =+'YG Gudda-2'!H37 -> 245 | G14: =+'YG Gudda-2'!J37 -> 25301.15 | H14: =E14+G14 -> 800945.83 | I14: =+'YG Gudda-2'!M3 -> 531383.8 | J14: =+'YG Gudda-2'!L37 -> 1081999.7 | K14: =H14+I14-J14 -> 250329.91 | L14: k
A15: 14 | B15: Hosadurga-2 | C15: Shree Veeraprathap Fuel | D15: =+'Hosadurga -2'!E35 -> 5200.15 | E15: =+'Hosadurga -2'!G35 -> 476023.72 | F15: =+'Hosadurga -2'!H35 -> 245 | G15: =+'Hosadurga -2'!J35 -> 25413.85 | H15: =+'Hosadurga -2'!K35 -> 501437.57 | I15: =+'Hosadurga -2'!K3 -> 197359.4 | J15: =+'Hosadurga -2'!L35 -> 500000 | K15: =H15+I15-J15 -> 198796.97 | L15: k
A16: 15 | B16: Malebennuru(KUWSDB) | C16: Sri Ramanjuneya Service Station | D16: =+'Malebenur(KUWSDB)'!E37 -> 4600 | E16: =+'Malebenur(KUWSDB)'!G37 -> 423982 | F16: =+'Malebenur(KUWSDB)'!H37 -> 205 | G16: =+'Malebenur(KUWSDB)'!J37 -> 21336.95 | H16: =E16+G16 -> 445318.95 | I16: =+'Malebenur(KUWSDB)'!K3 -> 58952.96 | J16: =+'Malebenur(KUWSDB)'!L37 -> 424793.9 | K16: =H16+I16-J16 -> 79478.01 | L16: k
A17: 16 | B17: kadur | C17: Vishal Service Station | D17: =+Kadur!E35 -> 1600 | E17: =+Kadur!G35 -> 147440 | F17: =+Kadur!H35 -> 140 | G17: =+Kadur!J35 -> 14593.6 | H17: =E17+G17 -> 162033.6 | I17: =+Kadur!K3 -> 240937.03 | J17: =+Kadur!L35 -> 300000 | K17: =H17+I17-J17 -> 102970.63 | L17: k
A18: 17 | B18: Hiriyur(VJNL) | C18: Sri Balaji Agencies | D18: =+'Hiriyur(VJNL)'!E35 -> 4700 | E18: =+'Hiriyur(VJNL)'!G35 -> 433622 | F18: =+'Hiriyur(VJNL)'!H35 -> 245 | G18: =+'Hiriyur(VJNL)'!J35 -> 25511.85 | H18: =E18+G18 -> 459133.85 | I18: =+'Hiriyur(VJNL)'!K3 -> 6935.95 | J18: =+'Hiriyur(VJNL)'!L35 -> 466000 | K18: =H18+I18-J18 -> 69.8 | L18: k
A19: 18 | B19: Chellakere(KUWSDB) | C19: Shivaganga Service Station | D19: =+'Chellakere -1'!E35 -> 4199.64 | E19: =+'Chellakere -1'!G35 -> 387332.8 | F19: =+'Chellakere -1'!H35 -> 140 | G19: =+'Chellakere -1'!J35 -> 14572.6 | H19: =E19+G19 -> 401905.4 | I19: =+'Chellakere -1'!K3 -> 268656.68 | J19: =+'Chellakere -1'!L35 -> 455000 | K19: =H19+I19-J19 -> 215562.07 | L19: k
A20: 19 | B20: Chellakere(KUWSDB)-09 | D20: =+' Chellakere-PKG-9'!E35 -> 215.05 | E20: =+' Chellakere-PKG-9'!G35 -> 19834.061 | F20: =+' Chellakere-PKG-9'!H35 -> 38.99 | G20: =+' Chellakere-PKG-9'!J35 -> 4058.4691 | H20: =E20+G20 -> 23892.531 | I20: =+' Chellakere-PKG-9'!M3 -> 0 | J20: =+' Chellakere-PKG-9'!L35 -> 23892.531 | K20: =H20+I20-J20 -> 0 | L20: k
A21: 20 | B21: Molakalmuru | C21: Sri Lakshmi Venkateshwara Filling Station | D21: =+Molakamuru!E35 -> 200 | E21: =+Molakamuru!G35 -> 18444 | F21: =+Molakamuru!H35 -> 95 | G21: =+Molakamuru!J35 -> 9904.1 | H21: =E21+G21 -> 28348.1 | I21: =+Molakamuru!K3 -> 22607.215 | J21: =+Molakamuru!L35 -> 46775.6 | K21: =H21+I21-J21 -> 4179.7152 | L21: k
A22: 21 | B22: Chennagiri | D22: =+' Chennagiri'!E35 -> 210 | E22: =+' Chennagiri'!G35 -> 19330.5 | F22: =+' Chennagiri'!H35 -> 72 | G22: =+' Chennagiri'!J35 -> 7498.08 | H22: =E22+G22 -> 26828.58 | I22: =+' Chennagiri'!K3 -> 0 | J22: =+' Chennagiri'!L35 -> 26828.58 | K22: =H22+I22-J22 -> 0 | L22: k
A23: 22 | B23: Khanapur(PKG-3) | C23: V.V.Varde | D23: =+Khanapur!E35 -> 2052.69 | E23: =+Khanapur!G35 -> 186548.47 | F23: =+Khanapur!H35 -> 81 | G23: =+Khanapur!J35 -> 8324.37 | H23: =E23+G23 -> 194872.84 | I23: =+Khanapur!M3 -> 68785.913 | J23: =+Khanapur!L35 -> 110000 | K23: =H23+I23-J23 -> 153658.75 | L23: k
A24: 23 | B24: Munavalli(PKG-3)-1 | C24: Shri Daneshwari | D24: =+Munavali!E37 -> 0 | E24: =+Munavali!G37 -> 0 | F24: =+Munavali!H37 -> 0 | G24: =+Munavali!J37 -> 0 | H24: =E24+G24 -> 0 | I24: =+Munavali!M3 -> 0 | J24: =+Munavali!L37 -> 0 | K24: =H24+I24-J24 -> 0 | L24: k
A25: 24 | B25: Munavalli(PKG-3)-2 | C25: Shre Shiva Petroleum | D25: =+'Munavali-2'!E37 -> 15520 | E25: =+'Munavali-2'!G37 -> 1420700.8 | F25: =+'Munavali-2'!H37 -> 165.47 | G25: =+'Munavali-2'!J37 -> 18179.927 | H25: =E25+G25 -> 1438880.7 | I25: =+'Munavali-2'!M3 -> 738510.09 | J25: =+'Munavali-2'!L37 -> 1570331.3 | K25: =H25+I25-J25 -> 607059.51 | L25: 597732 | M25: =K25-L25 -> 9327.5079
A26: 25 | B26: Borgaon(PKG-3) | C26: Aadisagar Petrolium | D26: =+Borgaon!E35 -> 5405 | E26: =+Borgaon!G35 -> 496016.85 | F26: =+Borgaon!H35 -> 95.8 | G26: =+Borgaon!J35 -> 9937.334 | H26: =E26+G26 -> 505954.18 | I26: =+Borgaon!K3 -> 29558.904 | J26: =+Borgaon!L35 -> 450000 | K26: =H26+I26-J26 -> 85513.088 | L26: k
A27: 26 | B27: Ugar,Kudichi(PKG-3) | C27: Shiri Bhrhmanath Petrolium | D27: =+'Ugar,Khagwad,Kudichi'!E35 -> 7528.79 | E27: =+'Ugar,Khagwad,Kudichi'!G35 -> 692121.66 | F27: =+'Ugar,Khagwad,Kudichi'!H35 -> 265 | G27: =+'Ugar,Khagwad,Kudichi'!J35 -> 27860.2 | H27: =E27+G27 -> 719981.86 | I27: =+'Ugar,Khagwad,Kudichi'!M3 -> 215407.75 | J27: =+'Ugar,Khagwad,Kudichi'!L35 -> 500974 | K27: =H27+I27-J27 -> 434415.61 | L27: k
A28: 27 | B28: Kabbur(PKG-3) | C28: Shri Jai Hanuman Petrolium | D28: =+Kabbur!E35 -> 375 | E28: =+Kabbur!G35 -> 34350 | F28: =+Kabbur!H35 -> 34 | G28: =+Kabbur!J35 -> 3520.31 | H28: =E28+G28 -> 37870.31 | I28: 0 | J28: =+Kabbur!L35 -> 37870.31 | K28: =H28+I28-J28 -> 0 | L28: k
A29: 28 | B29: Kumta (PKG-1) | C29: V.M.MIRJANKAR (KUMTA) BHARAT | D29: =+kumta!E35 -> 2115 | E29: =+kumta!G35 -> 194516.55 | F29: =+kumta!H35 -> 185 | G29: =+kumta!J35 -> 19241.85 | H29: =E29+G29 -> 213758.4 | I29: =kumta!M3 -> 27054.7 | J29: =+kumta!L35 -> 206053.8 | K29: =H29+I29-J29 -> 34759.3 | L29: k
A30: 29 | B30: Jalgaon | C30: Jai Bajarang Sarvo Center Bodwad | D30: =+Jalgaon!E55 -> 17988.96 | E30: =+Jalgaon!G55 -> 1649851.5 | F30: =+Jalgaon!H55 -> 112.74 | G30: =+Jalgaon!J55 -> 11859.121 | H30: =E30+G30 -> 1661710.6 | I30: =+Jalgaon!K3 -> 337793.25 | J30: =+Jalgaon!L55 -> 348495.99 | K30: =H30+I30-J30 -> 1651007.9 | L30: k
A31: 30 | B31: Jalgaon-2 | C31: Agrawal Petrol Pump | D31: =+'Jalgoan-2'!E55 -> 56137.39 | E31: ='Jalgoan-2'!G55 -> 5180158.8 | F31: =+'Jalgoan-2'!H55 -> 360 | G31: =+'Jalgoan-2'!J55 -> 38558.4 | H31: =E31+G31 -> 5218717.2 | I31: =+'Jalgoan-2'!M3 -> 2953127.8 | J31: =+'Jalgoan-2'!L55 -> 2700000 | K31: =H31+I31-J31 -> 5471845 | L31: k
A32: 31 | B32: Jalgaon-3 | C32: T R KAPOOR AND CO | D32: =+' Jalgoan-3'!E55 -> 2500 | E32: =+' Jalgoan-3'!G55 -> 229925 | F32: =+' Jalgoan-3'!H55 -> 0 | G32: =+' Jalgoan-3'!J55 -> 0 | H32: =E32+G32 -> 229925 | I32: =+' Jalgoan-3'!M3 -> 0 | J32: =+' Jalgoan-3'!L55 -> 229925 | K32: =H32+I32-J32 -> 0 | L32: k
A33: 32 | B33: Jalgaon-4 | C33: RAKSHA AUTO FUELS BPCL OTP | D33: =+' Jalgoan-4'!E55 -> 4000 | E33: =+' Jalgoan-4'!G55 -> 366680 | F33: =+' Jalgoan-4'!H55 -> 0 | G33: =+' Jalgoan-4'!J55 -> 0 | H33: =E33+G33 -> 366680 | I33: =+' Jalgoan-4'!M3 -> 0 | J33: =+' Jalgoan-4'!L55 -> 366680 | K33: =H33+I33-J33 -> 0 | L33: k
A34: 33 | B34: MKBD | C34: Shree Sai Samarth Petroleum | D34: =+MKBD!E38 -> 14800 | E34: =+MKBD!G38 -> 1348872 | F34: =+MKBD!H38 -> 110.21 | G34: =+MKBD!J38 -> 11527.966 | H34: =E34+G34 -> 1360400 | I34: =+MKBD!K3 -> 103006.58 | J34: =+MKBD!L38 -> 0 | K34: =H34+I34-J34 -> 1463406.5 | L34: k
A35: 34 | B35: Haveri | C35: M/s Magavi City Fuels | D35: =' Haveri-2'!E38 -> 1427.77 | E35: =' Haveri-2'!G38 -> 130626.34 | F35: =' Haveri-2'!H38 -> 75.11 | G35: =' Haveri-2'!J38 -> 7809.1713 | H35: =E35+G35 -> 138435.51 | I35: =' Haveri-2'!M3 -> 90409.199 | J35: =+' Haveri-2'!L38 -> 151559.56 | K35: =H35+I35-J35 -> 77285.143 | L35: k
A36: 35 | B36: Guttal-2 | C36: Himagiri Petroleum | D36: =+' Guttal-2'!E35 -> 4113.96 | E36: =+' Guttal-2'!G35 -> 377579.25 | F36: =+' Guttal-2'!H35 -> 171 | G36: =+' Guttal-2'!J35 -> 17739.54 | H36: =E36+G36 -> 395318.79 | I36: =+' Guttal-2'!M3 -> 118610.55 | J36: =+' Guttal-2'!L35 -> 310000 | K36: =H36+I36-J36 -> 203929.33 | L36: k
A37: 36 | B37: Rattihali | C37: Shree Siri Gowari petroliam | D37: =+Rattihali!E35 -> 0 | E37: =+Rattihali!G35 -> 0 | F37: =+Rattihali!H35 -> 0 | G37: =+Rattihali!J35 -> 0 | H37: =E37+G37 -> 0 | I37: =+Rattihali!M3 -> 6442.724 | J37: =+Rattihali!L35 -> 6442.72 | K37: =H37+I37-J37 -> 0.004 | L37: k
A38: 37 | B38: Rattihali-2 | C38: Shiva Oil Traders | D38: =+'Rattihali-2'!E37 -> 4383.61 | E38: =+'Rattihali-2'!G37 -> 402809.92 | F38: =+'Rattihali-2'!H37 -> 110 | G38: =+'Rattihali-2'!J37 -> 11423.5 | H38: =E38+G38 -> 414233.42 | I38: =+'Rattihali-2'!M3 -> 149508.67 | J38: =+'Rattihali-2'!L37 -> 300000 | K38: =H38+I38-J38 -> 263742.1 | L38: k
A39: 38 | B39: Gajendragada | C39: Vanasri Petrol Pump | D39: =+Gajendragada!E35 -> 1151 | E39: =+Gajendragada!G35 -> 105696.33 | F39: =+Gajendragada!H35 -> 149.96 | G39: =+Gajendragada!J35 -> 15565.848 | H39: =E39+G39 -> 121262.18 | I39: =+Gajendragada!K3 -> 126102.9 | J39: =+Gajendragada!L35 -> 200000 | K39: =H39+I39-J39 -> 47365.079 | L39: k
A40: 39 | B40: Gokak(PKG-3) | C40: AJ Petrolinks | D40: =+'Gokak Dharwad PKG 3'!E40 -> 11542.14 | E40: =+'Gokak Dharwad PKG 3'!G40 -> 1055875 | F40: =+'Gokak Dharwad PKG 3'!H40 -> 330 | G40: =+'Gokak Dharwad PKG 3'!J40 -> 34311.54 | H40: =E40+G40 -> 1090186.5 | I40: =+'Gokak Dharwad PKG 3'!K3 -> 227750.48 | J40: =+'Gokak Dharwad PKG 3'!L40 -> 950000 | K40: =H40+I40-J40 -> 367936.99 | L40: k
A41: 40 | B41: Hukkere | C41: TR Assocites | D41: =+' TR Associates'!E35 -> 12090.88 | E41: =+' TR Associates'!G35 -> 1104139.2 | F41: =+' TR Associates'!H35 -> 6 | G41: =+' TR Associates'!J35 -> 619.38 | H41: =E41+G41 -> 1104758.5 | I41: =+' TR Associates'!M3 -> 301816.69 | J41: =+' TR Associates'!L35 -> 700000 | K41: =H41+I41-J41 -> 706575.23 | L41: k
A42: 41 | B42: Ankaligi | C42: Shivaganga | D42: =+Ankalgi!E35 -> 4182.87 | E42: =+Ankalgi!G35 -> 381948.25 | F42: =+Ankalgi!H35 -> 82 | G42: =+Ankalgi!J35 -> 8465.12 | H42: =E42+G42 -> 390413.37 | I42: =+Ankalgi!M3 -> 94860.976 | J42: =+Ankalgi!L35 -> 300000 | K42: =H42+I42-J42 -> 185274.35 | L42: k
A43: 42 | B43: ShankeshWAR | C43: SR Patil | D43: =+' Shankeshwar'!E35 -> 565 | E43: =+' Shankeshwar'!G35 -> 51584.5 | F43: =+' Shankeshwar'!H35 -> 77.78 | G43: =+' Shankeshwar'!J35 -> 8028.7816 | H43: =E43+G43 -> 59613.282 | I43: =' Shankeshwar'!M3 -> 0 | J43: =+' Shankeshwar'!L35 -> 59613.282 | K43: =H43+I43-J43 -> 0 | L43: k
A44: 43 | B44: Talikote(PKG-1) | C44: Raykar Oil Agencies | D44: =+' Talikote'!E46 -> 367.57 | E44: =+' Talikote'!G46 -> 33754.868 | F44: =+' Talikote'!H46 -> 70.47 | G44: =+' Talikote'!J46 -> 7289.4168 | H44: =E44+G44 -> 41044.285 | I44: =+' Talikote'!N3 -> 2423.9635 | J44: =+' Talikote'!L46 -> 41000 | K44: =H44+I44-J44 -> 2468.2481 | L44: k
A45: 44 | B45: Chadchan(PKG-1) | C45: Khavekar Petrolium | D45: =+Chadchan!E35 -> 1320.99 | E45: =+Chadchan!G35 -> 120513.92 | F45: =+Chadchan!H35 -> 100.52 | G45: =+Chadchan!J35 -> 10350.663 | H45: =E45+G45 -> 130864.58 | I45: =+Chadchan!K3 -> 126345.08 | J45: =+Chadchan!L35 -> 200000 | K45: =H45+I45-J45 -> 57209.665 | L45: k
A46: 45 | B46: Sindagi | C46: G.P.PORWAL | D46: =+Sindagi!E44 -> 751.95 | E46: =+Sindagi!G44 -> 68603.026 | F46: =+Sindagi!H44 -> 20 | G46: =+Sindagi!J44 -> 2231 | H46: =E46+G46 -> 70834.026 | I46: =+Sindagi!M3 -> 4750.3872 | J46: =+Sindagi!L44 -> 60000 | K46: =H46+I46-J46 -> 15584.413 | L46: k
A47: 46 | B47: Muddebihal(PKG-1)2 | C47: PS NAGATHAN PETROLIUM | D47: =+'Muddebhihal-2'!E49 -> 863.72 | E47: =+'Muddebhihal-2'!G49 -> 78961.282 | F47: =+'Muddebhihal-2'!H49 -> 31.48 | G47: =+'Muddebhihal-2'!J49 -> 3286.2732 | H47: =+'Muddebhihal-2'!K49 -> 82247.556 | I47: =+'Muddebhihal-2'!M3 -> 87558.79 | J47: =+'Muddebhihal-2'!L49 -> 110000 | K47: =+'Muddebhihal-2'!M48 -> 59806.346 | L47: k
A48: 47 | B48: Almela(PKG-1) | C48: Shiddeshwar Petroleums | D48: =+Alemela!E43 -> 1435.05 | E48: =+Alemela!G43 -> 131249.67 | F48: =+Alemela!H43 -> 124.94 | G48: =+Alemela!J43 -> 12918.796 | H48: =E48+G48 -> 144168.47 | I48: =+Alemela!M3 -> 57123.167 | J48: =+Alemela!L43 -> 200000 | K48: =H48+I48-J48 -> 1291.6359 | L48: k
A49: 48 | B49: Nalatwad(PKG-1) | C49: Shri Pawad Basaweshwar Petroleums | D49: =+Nalatwad!E43 -> 630.52 | E49: =+Nalatwad!G43 -> 57768.242 | F49: =+Nalatwad!H43 -> 60.49 | G49: =+Nalatwad!J43 -> 6264.9493 | H49: =E49+G49 -> 64033.192 | I49: =+Nalatwad!M3 -> 39139.75 | J49: =+Nalatwad!L43 -> 50000 | K49: =H49+I49-J49 -> 53172.942 | L49: k
A50: 49 | B50: Srirangapatna | C50: Anupama F/S | D50: =+Srirangapatna!E35 -> 0 | E50: =+Srirangapatna!G35 -> 0 | F50: =+Srirangapatna!H35 -> 18.5 | G50: =+Srirangapatna!J35 -> 1895.695 | H50: =E50+G50 -> 1895.695 | I50: 0 | J50: =+Srirangapatna!L35 -> 1895.695 | K50: =H50+I50-J50 -> 0 | L50: k
A51: 50 | B51: HO(DG) | C51: JSASFuel Genie India Pvt.Ltd | D51: =+'HO(DG)'!E39 -> 1068.42 | E51: =+'HO(DG)'!G39 -> 102382.14 | F51: =+'HO(DG)'!H39 -> 0 | G51: =+'HO(DG)'!J39 -> 0 | H51: =E51+G51 -> 102382.14 | I51: =+'HO(DG)'!M3 -> 89488.582 | J51: =+'HO(DG)'!L39 -> 3349.5 | K51: =H51+I51-J51 -> 188521.22 | L51: 191263 | M51: =L51-K51 -> 2741.7795
A52: Total | D52: =SUM(D2:D51) -> 451700.34 | E52: =SUM(E2:E51) -> 42403311 | F52: =SUM(F2:F51) -> 6061.64 | G52: =SUM(G2:G51) -> 639164.41 | H52: =SUM(H2:H51) -> 43042476 | I52: =SUM(I2:I51) -> 23458516 | J52: =SUM(J2:J51) -> 29891673 | K52: =H52+I52-J52 -> 36609319 | L52: 36462814 | M52: =K52-L52 -> 146504.42
A57: S.no | B57: Site Name | C57: Bunk Name | D57: Diesel(Liters) | E57: Diesel Amount | F57: Petrol(Liters) | G57: Petrol Amount | H57: Total Amount | I57: Opening Blance | J57: Amount Paid | K57: Closing Balances
A58: 39 | B58: {=VLOOKUP(A58,A1:K50,{2,3,4,5,6,7,8,9,10,11},FALSE)} -> Gokak(PKG-3) | C58: AJ Petrolinks | D58: 11542.14 | E58: 1055875 | F58: 330 | G58: 34311.54 | H58: 1090186.5 | I58: 227750.48 | J58: 950000 | K58: 367936.99
B60: Site Name | C60: Bunk Name | D60: Diesel(Liters) | E60: Diesel Amount | F60: Petrol(Liters) | G60: Petrol Amount | H60: Total Amount | I60: Opening Blance | J60: Amount Paid | K60: Closing Balances
B61: Jalgaon-2 | C61: {=VLOOKUP(B61,B1:K50,{2,3,4,5,6,7,8,9,10},FALSE)} -> Agrawal Petrol Pump | D61: 56137.39 | E61: 5180158.8 | F61: 360 | G61: 38558.4 | H61: 5218717.2 | I61: 2953127.8 | J61: 2700000 | K61: 5471845
B68: 60000
B69: 18000
B70: 18000
B71: 75000
B72: 360000

Sheet HO(DG)
A1: JSASFuel Genie India Pvt.Ltd
A2: S.No | B2: Date | C2: GRN No | D2: Ind No/Bill No | E2: Diesel (Lts) | F2: Price | G2: Amount | H2: Petrol (Lts) | I2: Price | J2: Amount | K2: Total amount | L2: Amount paid | M2: As on date | N2: Remarks
A3: Opening Balance | M3: 89488.582 | O3: 2623243.4
A4: 1 | B4: 46082 | G4: =E4*F4 -> 0 | H4: 0 | I4: 0 | J4: =H4*I4 -> 0 | K4: =G4+J4 -> 0 | L4: 0 | M4: =M3+K4-L4 -> 89488.582
A5: 2 | B5: 46083 | G5: =E5*F5 -> 0 | H5: 0 | I5: 0 | J5: =H5*I5 -> 0 | K5: =G5+J5 -> 0 | L5: 0 | M5: =M4+K5-L5 -> 89488.582 | S5: 16291
A6: 3 | B6: 46084 | G6: =E6*F6 -> 0 | H6: 0 | I6: 0 | J6: =H6*I6 -> 0 | K6: =G6+J6 -> 0 | L6: 0 | M6: =M5+K6-L6 -> 89488.582 | S6: 16291
A7: 4 | B7: 46085 | E7: 170 | F7: 95.83 | G7: =E7*F7 -> 16291.1 | H7: 0 | I7: 0 | J7: =H7*I7 -> 0 | K7: =G7+J7 -> 16291.1 | L7: 0 | M7: =M6+K7-L7 -> 105779.68 | P7: 5679 | S7: 17249
A8: 5 | B8: 46086 | G8: =E8*F8 -> 0 | H8: 0 | I8: 0 | J8: =H8*I8 -> 0 | K8: =G8+J8 -> 0 | L8: 0 | M8: =M7+K8-L8 -> 105779.68 | S8: 17249
A9: 6 | B9: 46087 | G9: =E9*F9 -> 0 | K9: =G9+J9 -> 0 | L9: 0 | M9: =M8+K9-L9 -> 105779.68 | S9: 14894
A10: 7 | B10: 46088 | G10: =E10*F10 -> 0 | H10: 0 | I10: 0 | J10: =H10*I10 -> 0 | K10: =G10+J10 -> 0 | L10: 0 | M10: =M9+K10-L10 -> 105779.68 | S10: 16578 | T10: 122085
A11: 8 | B11: 46089 | E11: 170 | F11: 95.83 | G11: =E11*F11 -> 16291.1 | H11: 0 | I11: 0 | J11: =H11*I11 -> 0 | K11: =G11+J11 -> 16291.1 | L11: 0 | M11: =M10+K11-L11 -> 122070.78 | S11: =SUM(S5:S10) -> 98552 | T11: =T10+S11 -> 220637
A12: 9 | B12: 46090 | G12: =E12*F12 -> 0 | H12: 0 | I12: 0 | J12: =H12*I12 -> 0 | K12: =G12+J12 -> 0 | L12: 0 | M12: =M11+K12-L12 -> 122070.78
A13: 10 | B13: 46091 | G13: =E13*F13 -> 0 | H13: 0 | I13: 0 | K13: =G13+J13 -> 0 | L13: 0 | M13: =M12+K13-L13 -> 122070.78
A14: 11 | B14: 46092 | G14: =E14*F14 -> 0 | H14: 0 | I14: 0 | K14: =G14+J14 -> 0 | L14: 0 | M14: =M13+K14-L14 -> 122070.78
A15: 12 | B15: 46093 | G15: =E15*F15 -> 0 | H15: 0 | I15: 0 | K15: =G15+J15 -> 0 | L15: 0 | M15: =M14+K15-L15 -> 122070.78 | P15: 1905988 | Q15: =P15-M15 -> 1783917.2
A16: 13 | B16: 46094 | E16: 180 | F16: 95.83 | G16: =E16*F16 -> 17249.4 | H16: 0 | I16: 0 | K16: =G16+J16 -> 17249.4 | L16: 0 | M16: =M15+K16-L16 -> 139320.18
A17: 14 | B17: 46095 | G17: =E17*F17 -> 0 | H17: 0 | I17: 0 | J17: =H17*I17 -> 0 | K17: =G17+J17 -> 0 | L17: 0 | M17: =M16+K17-L17 -> 139320.18
A18: 15 | B18: 46096 | G18: =E18*F18 -> 0 | H18: 0 | I18: 0 | J18: =H18*I18 -> 0 | K18: =G18+J18 -> 0 | L18: 0 | M18: =M17+K18-L18 -> 139320.18
A19: 16 | B19: 46097 | G19: =E19*F19 -> 0 | H19: 0 | I19: 0 | J19: =H19*I19 -> 0 | K19: =G19+J19 -> 0 | L19: 0 | M19: =M18+K19-L19 -> 139320.18
A20: 17 | B20: 46098 | E20: 185 | F20: 95.83 | G20: =E20*F20 -> 17728.55 | H20: 0 | I20: 0 | J20: =H20*I20 -> 0 | K20: =G20+J20 -> 17728.55 | L20: 0 | M20: =M19+K20-L20 -> 157048.73
A21: 18 | B21: 46099 | G21: =E21*F21 -> 0 | J21: =H21*I21 -> 0 | K21: =G21+J21 -> 0 | L21: 0 | M21: =M20+K21-L21 -> 157048.73
A22: 19 | B22: 46100 | G22: =E22*F22 -> 0 | J22: =H22*I22 -> 0 | K22: =G22+J22 -> 0 | L22: 0 | M22: =M21+K22-L22 -> 157048.73
A23: 20 | B23: 46101 | G23: =E23*F23 -> 0 | J23: =H23*I23 -> 0 | K23: =G23+J23 -> 0 | L23: 0 | M23: =M22+K23-L23 -> 157048.73
A24: 21 | B24: 46102 | G24: =E24*F24 -> 0 | J24: =H24*I24 -> 0 | K24: =G24+J24 -> 0 | L24: 0 | M24: =M23+K24-L24 -> 157048.73
A25: 22 | B25: 46103 | G25: =E25*F25 -> 0 | J25: =H25*I25 -> 0 | K25: =G25+J25 -> 0 | L25: 0 | M25: =M24+K25-L25 -> 157048.73
A26: 23 | B26: 46104 | M26: =M25+K26-L26 -> 157048.73
A27: 24 | B27: 46105 | E27: 35 | F27: 95.7 | G27: =E27*F27 -> 3349.5 | J27: =H27*I27 -> 0 | K27: =G27+J27 -> 3349.5 | L27: =H27+K27 -> 3349.5 | M27: =M26+K27-L27 -> 157048.73
B28: 46105 | E28: 173 | F28: 95.83 | G28: =E28*F28 -> 16578.59 | K28: =G28+J28 -> 16578.59 | L28: 0 | M28: =M27+K28-L28 -> 173627.32
A29: 25 | B29: 46106 | G29: =E29*F29 -> 0 | J29: =H29*I29 -> 0 | K29: =G29+J29 -> 0 | L29: 0 | M29: =M28+K29-L29 -> 173627.32
A30: 26 | B30: 46107 | G30: =E30*F30 -> 0 | J30: =H30*I30 -> 0 | K30: =G30+J30 -> 0 | L30: 0 | M30: =M29+K30-L30 -> 173627.32
A31: 27 | B31: 46108 | G31: =E31*F31 -> 0 | J31: =H31*I31 -> 0 | K31: =G31+J31 -> 0 | L31: 0 | M31: =M30+K31-L31 -> 173627.32
A32: 28 | B32: 46109 | E32: 155.42 | F32: 95.83 | G32: =E32*F32 -> 14893.899 | J32: =H32*I32 -> 0 | K32: =G32+J32 -> 14893.899 | L32: 0 | M32: =M31+K32-L32 -> 188521.22
A33: 29 | B33: 46110 | G33: =E33*F33 -> 0 | J33: =H33*I33 -> 0 | K33: =G33+J33 -> 0 | M33: =M32+K33-L33 -> 188521.22
A34: 30 | B34: 46111 | G34: =E34*F34 -> 0 | J34: =H34*I34 -> 0 | K34: =G34+J34 -> 0 | M34: =M33+K34-L34 -> 188521.22
A35: 31 | B35: 46112 | G35: =E35*F35 -> 0 | J35: =H35*I35 -> 0 | K35: =G35+J35 -> 0 | M35: =M34+K35-L35 -> 188521.22
A36: 32 | G36: =E36*F36 -> 0 | J36: =H36*I36 -> 0 | K36: =G36+J36 -> 0 | M36: =M35+K36-L36 -> 188521.22
A37: 33 | G37: =E37*F37 -> 0 | J37: =H37*I37 -> 0 | K37: =G37+J37 -> 0 | L37: 0 | M37: =M36+K37-L37 -> 188521.22 | O37: 2669494 | P37: =O37-M37 -> 2480972.8
E38: 0 | F38: 0 | G38: =E38*F38 -> 0 | J38: =H38*I38 -> 0 | K38: =G38+J38 -> 0 | M38: =M37+K38-L38 -> 188521.22
E39: =SUM(E4:E37) -> 1068.42 | G39: =SUM(G4:G37) -> 102382.14 | H39: =SUM(H4:H37) -> 0 | J39: =SUM(J4:J37) -> 0 | K39: =SUM(K4:K37) -> 102382.14 | L39: =SUM(L4:L37) -> 3349.5
M48: 2408309
M49: 5327.86
M50: =M48-M49 -> 2402981.1

Sheet Khammam-1
A1: Divya laxmi ganapathi
A2: S.No | B2: Date | C2: GRN No | D2: Ind No/Bill No | E2: Diesel (Lts) | F2: Price | G2: Amount | H2: Petrol (Lts) | I2: Price | J2: Amount | K2: Total amount | L2: Amount paid | M2: As 0n Date | N2: Remarks
A3: Opening Balance | K3: 8237254.9 | M3: 8237254.9
A4: 1 | B4: 46082 | G4: =E4*F4 -> 0 | K4: =G4+J4 -> 0 | L4: 0 | M4: =M3+K4-L4 -> 8237254.9
A5: 2 | B5: 46083 | E5: 1800 | F5: 95.68 | G5: =E5*F5 -> 172224 | H5: 60 | I5: 107.46 | J5: =H5*I5 -> 6447.6 | K5: =G5+J5 -> 178671.6 | L5: 0 | M5: =M4+K5-L5 -> 8415926.5
A6: 3 | B6: 46084 | G6: =E6*F6 -> 0 | J6: =H6*I6 -> 0 | K6: =G6+J6 -> 0 | L6: 0 | M6: =M5+K6-L6 -> 8415926.5
A7: 4 | B7: 46085 | G7: =E7*F7 -> 0 | J7: =H7*I7 -> 0 | K7: =G7+J7 -> 0 | L7: 0 | M7: =M6+K7-L7 -> 8415926.5
A8: 5 | B8: 46086 | G8: =E8*F8 -> 0 | J8: =H8*I8 -> 0 | K8: =G8+J8 -> 0 | L8: 0 | M8: =M7+K8-L8 -> 8415926.5
A9: 6 | B9: 46087 | G9: =E9*F9 -> 0 | J9: =H9*I9 -> 0 | K9: =G9+J9 -> 0 | L9: 0 | M9: =M8+K9-L9 -> 8415926.5
A10: 7 | B10: 46088 | G10: =E10*F10 -> 0 | J10: =H10*I10 -> 0 | K10: =G10+J10 -> 0 | L10: 0 | M10: =M9+K10-L10 -> 8415926.5
A11: 8 | B11: 46089 | G11: =E11*F11 -> 0 | J11: =H11*I11 -> 0 | K11: =G11+J11 -> 0 | L11: 0 | M11: =M10+K11-L11 -> 8415926.5
A12: 9 | B12: 46090 | G12: =E12*F12 -> 0 | J12: =H12*I12 -> 0 | K12: =G12+J12 -> 0 | L12: 0 | M12: =M11+K12-L12 -> 8415926.5
A13: 10 | B13: 46091 | G13: =E13*F13 -> 0 | J13: =H13*I13 -> 0 | K13: =G13+J13 -> 0 | L13: 0 | M13: =M12+K13-L13 -> 8415926.5
A14: 11 | B14: 46092 | G14: =E14*F14 -> 0 | J14: =H14*I14 -> 0 | K14: =G14+J14 -> 0 | L14: 0 | M14: =M13+K14-L14 -> 8415926.5
A15: 12 | B15: 46093 | G15: =E15*F15 -> 0 | J15: =H15*I15 -> 0 | K15: =G15+J15 -> 0 | L15: 0 | M15: =M14+K15-L15 -> 8415926.5
A16: 13 | B16: 46094 | G16: =E16*F16 -> 0 | J16: =H16*I16 -> 0 | K16: =G16+J16 -> 0 | L16: 0 | M16: =M15+K16-L16 -> 8415926.5
A17: 14 | B17: 46095 | G17: =E17*F17 -> 0 | J17: =H17*I17 -> 0 | K17: =G17+J17 -> 0 | L17: 0 | M17: =M16+K17-L17 -> 8415926.5
... A30: 27 | B30: 46108 | G30: =E30*F30 -> 0 | J30: =H30*I30 -> 0 | K30: =G30+J30 -> 0 | L30: 0 | M30: =M29+K30-L30 -> 3915926.5
A31: 28 | B31: 46109 | E31: 2700 | F31: 95.68 | G31: =E31*F31 -> 258336 | H31: 20 | I31: 107.46 | J31: =H31*I31 -> 2149.2 | K31: =G31+J31 -> 260485.2 | L31: 0 | M31: =M30+K31-L31 -> 4176411.7
A32: 29 | B32: 46110 | G32: =E32*F32 -> 0 | J32: =H32*I32 -> 0 | K32: =G32+J32 -> 0 | L32: 0 | M32: =M31+K32-L32 -> 4176411.7
A33: 30 | B33: 46111 | G33: =E33*F33 -> 0 | J33: =H33*I33 -> 0 | K33: =G33+J33 -> 0 | L33: 0 | M33: =M32+K33-L33 -> 4176411.7
A34: 31 | B34: 46112 | G34: =E34*F34 -> 0 | K34: =G34+J34 -> 0 | L34: 0 | M34: =M33+K34-L34 -> 4176411.7
A35: 32 | G35: =E35*F35 -> 0 | J35: =H35*I35 -> 0 | K35: =G35+J35 -> 0 | L35: 0 | M35: =M34+K35-L35 -> 4176411.7
A36: 33 | G36: =E36*F36 -> 0 | J36: =H36*I36 -> 0 | K36: =G36+J36 -> 0 | L36: 0
A37: 34 | G37: =E37*F37 -> 0 | J37: =H37*I37 -> 0 | K37: =G37+J37 -> 0
E38: =SUM(E3:E37) -> 4500 | G38: =SUM(G3:G37) -> 430560 | H38: =SUM(H3:H37) -> 80 | J38: =SUM(J3:J37) -> 8596.8 | K38: =SUM(K4:K37) -> 439156.8 | L38: =SUM(L3:L37) -> 4500000

Sheet Khammam-2
A1: Jayasai union bunk
A2: S.No | B2: Date | C2: GRN No | D2: Ind No/Bill No | E2: Diesel (Lts) | F2: Price | G2: Amount | H2: Petrol (Lts) | I2: Price | J2: Amount | K2: Total amount | L2: Amount paid | M2: As 0n Date | N2: Remarks
A3: Opening Balance | K3: 5555857.2 | M3: 5555857.2
A4: 1 | B4: 46082 | G4: =E4*F4 -> 0 | J4: =H4*I4 -> 0 | K4: =G4+J4 -> 0 | M4: =M3+K4-L4 -> 5555857.2 | O4: =O3+M4-N4 -> 5555857.2
A5: 2 | B5: 46083 | E5: 1600 | F5: 95.71 | G5: =E5*F5 -> 153136 | H5: 40 | I5: 107.49 | J5: =H5*I5 -> 4299.6 | K5: =G5+J5 -> 157435.6 | M5: =M4+K5-L5 -> 5713292.8
A6: 3 | B6: 46084 | E6: 2100 | F6: 95.71 | G6: =E6*F6 -> 200991 | H6: 55 | I6: 107.49 | J6: =H6*I6 -> 5911.95 | K6: =G6+J6 -> 206902.95 | M6: =M5+K6-L6 -> 5920195.7
A7: 4 | B7: 46085 | G7: =E7*F7 -> 0 | J7: =H7*I7 -> 0 | K7: =G7+J7 -> 0 | M7: =M6+K7-L7 -> 5920195.7
A8: 5 | B8: 46086 | E8: 2700 | F8: 95.71 | G8: =E8*F8 -> 258417 | H8: 40 | I8: 107.49 | J8: =H8*I8 -> 4299.6 | K8: =G8+J8 -> 262716.6 | M8: =M7+K8-L8 -> 6182912.3 | O8: 12802499
A9: 6 | B9: 46087 | E9: 2700 | F9: 95.71 | G9: =E9*F9 -> 258417 | H9: 40 | I9: 107.49 | J9: =H9*I9 -> 4299.6 | K9: =G9+J9 -> 262716.6 | M9: =M8+K9-L9 -> 6445628.9
A10: 7 | B10: 46088 | E10: 4755.39 | F10: 95.71 | G10: =E10*F10 -> 455138.38 | J10: =H10*I10 -> 0 | K10: =G10+J10 -> 455138.38 | M10: =M9+K10-L10 -> 6900767.3
A11: 8 | B11: 46089 | G11: =E11*F11 -> 0 | J11: =H11*I11 -> 0 | K11: =G11+J11 -> 0 | M11: =M10+K11-L11 -> 6900767.3
A12: 9 | B12: 46090 | G12: =E12*F12 -> 0 | H12: 80 | I12: 107.49 | J12: =H12*I12 -> 8599.2 | K12: =G12+J12 -> 8599.2 | M12: =M11+K12-L12 -> 6909366.5
A13: 10 | B13: 46091 | E13: 4500 | F13: 95.71 | G13: =E13*F13 -> 430695 | H13: 75 | I13: 107.49 | J13: =H13*I13 -> 8061.75 | K13: =G13+J13 -> 438756.75 | M13: =M12+K13-L13 -> 7348123.2
A14: 11 | B14: 46092 | E14: 5500 | F14: 95.71 | G14: =E14*F14 -> 526405 | H14: 40 | I14: 107.49 | J14: =H14*I14 -> 4299.6 | K14: =G14+J14 -> 530704.6 | M14: =M13+K14-L14 -> 7878827.8
A15: 12 | B15: 46093 | E15: 7830 | F15: 95.71 | G15: =E15*F15 -> 749409.3 | H15: 40 | I15: 107.49 | J15: =H15*I15 -> 4299.6 | K15: =G15+J15 -> 753708.9 | M15: =M14+K15-L15 -> 8632536.7
A16: 13 | B16: 46094 | E16: 1044.823 | F16: 95.71 | G16: =E16*F16 -> 100000.01 | J16: =H16*I16 -> 0 | K16: =G16+J16 -> 100000.01 | L16: 0 | M16: =M15+K16-L16 -> 8732536.8 | N16: 100000 Cash &Carry
A17: 14 | B17: 46095 | G17: =E17*F17 -> 0 | J17: =H17*I17 -> 0 | K17: =G17+J17 -> 0 | M17: =M16+K17-L17 -> 8732536.8
A18: 15 | B18: 46096 | G18: =E18*F18 -> 0 | J18: =H18*I18 -> 0 | K18: =G18+J18 -> 0 | M18: =M17+K18-L18 -> 8732536.8
A19: 16 | B19: 46097 | E19: 5152.96 | F19: 95.71 | G19: =E19*F19 -> 493189.8 | H19: 175 | I19: 107.49 | J19: =H19*I19 -> 18810.75 | K19: =G19+J19 -> 512000.55 | M19: =M18+K19-L19 -> 9244537.3 | N19: 512000 Cash &Carry
A20: 17 | B20: 46098 | G20: =E20*F20 -> 0 | J20: =H20*I20 -> 0 | K20: =G20+J20 -> 0 | L20: 3500000 | M20: =M19+K20-L20 -> 5744537.3
A21: 18 | B21: 46099 | G21: =E21*F21 -> 0 | J21: =H21*I21 -> 0 | K21: =G21+J21 -> 0 | M21: =M20+K21-L21 -> 5744537.3
A22: 19 | B22: 46100 | G22: =E22*F22 -> 0 | J22: =H22*I22 -> 0 | K22: =G22+J22 -> 0 | L22: 0 | M22: =M21+K22-L22 -> 5744537.3
A23: 20 | B23: 46101 | G23: =E23*F23 -> 0 | H23: 115 | I23: 107.49 | J23: =H23*I23 -> 12361.35 | K23: =G23+J23 -> 12361.35 | M23: =M22+K23-L23 -> 5756898.7
A24: 21 | B24: 46102 | E24: 2100 | F24: 95.71 | G24: =E24*F24 -> 200991 | H24: 60 | I24: 107.49 | J24: =H24*I24 -> 6449.4 | K24: =G24+J24 -> 207440.4 | M24: =M23+K24-L24 -> 5964339.1
A25: 22 | B25: 46103 | G25: =E25*F25 -> 0 | J25: =H25*I25 -> 0 | K25: =G25+J25 -> 0 | M25: =M24+K25-L25 -> 5964339.1
A26: 23 | B26: 46104 | E26: 2100 | F26: 95.71 | G26: =E26*F26 -> 200991 | H26: 40 | I26: 107.49 | J26: =H26*I26 -> 4299.6 | K26: =G26+J26 -> 205290.6 | M26: =M25+K26-L26 -> 6169629.7
A27: 24 | B27: 46105 | G27: =E27*F27 -> 0 | J27: =H27*I27 -> 0 | K27: =G27+J27 -> 0 | M27: =M26+K27-L27 -> 6169629.7
A28: 25 | B28: 46106 | E28: 2700 | F28: 95.71 | G28: =E28*F28 -> 258417 | H28: 125 | I28: 107.49 | J28: =H28*I28 -> 13436.25 | K28: =G28+J28 -> 271853.25 | M28: =M27+K28-L28 -> 6441482.9
A29: 26 | B29: 46107 | E29: 2700 | F29: 95.71 | G29: =E29*F29 -> 258417 | H29: 20 | I29: 107.49 | J29: =H29*I29 -> 2149.8 | K29: =G29+J29 -> 260566.8 | M29: =M28+K29-L29 -> 6702049.7
A30: 27 | B30: 46108 | E30: 2800 | F30: 95.71 | G30: =E30*F30 -> 267988 | J30: =H30*I30 -> 0 | K30: =G30+J30 -> 267988 | M30: =M29+K30-L30 -> 6970037.7
A31: 28 | B31: 46109 | D31: 25-26/S4 (MP3 Grease) | E31: 546 | F31: 256.0989 | G31: =E31*F31 -> 139830 | H31: 0 | I31: 0 | J31: =H31*I31 -> 0 | K31: =G31+J31 -> 139830 | M31: =M30+K31-L31 -> 7109867.7
A32: 29 | B32: 46109 | E32: 2800 | F32: 95.71 | G32: =E32*F32 -> 267988 | H32: 40 | I32: 107.49 | J32: =H32*I32 -> 4299.6 | K32: =G32+J32 -> 272287.6 | M32: =M31+K32-L32 -> 7382155.3
A33: 30 | B33: 46111 | E33: 4029 | F33: 95.71 | G33: =E33*F33 -> 385615.59 | H33: 60 | I33: 107.49 | J33: =H33*I33 -> 6449.4 | K33: =G33+J33 -> 392064.99 | M33: =M32+K33-L33 -> 7774220.3
A34: 31 | E34: 2700 | F34: 95.71 | G34: =E34*F34 -> 258417 | J34: =H34*I34 -> 0 | K34: =G34+J34 -> 258417 | M34: =M33+K34-L34 -> 8032637.3
E35: =SUM(E4:E34) -> 60358.173 | G35: =SUM(G4:G34) -> 5864453.1 | H35: =SUM(H4:H34) -> 1045 | J35: =SUM(J4:J34) -> 112327.05 | K35: =SUM(K4:K34) -> 5976780.1 | L35: =SUM(L4:L34) -> 3500000

Sheet Khammam-3
A1: JSASFuel Genie India Pvt.Ltd
A2: S.No | B2: Date | C2: GRN No | D2: Ind No/Bill No | E2: Diesel (Lts) | F2: Price | G2: Amount | H2: Petrol (Lts) | I2: Price | J2: Amount | K2: Total amount | L2: Amount paid | M2: As 0n Date | N2: Remarks
A3: Opening Balance | K3: 1140143.1 | M3: 1140143.1
A4: 1 | B4: 46082 | E4: 6000 | F4: 94.7 | G4: =E4*F4 -> 568200 | J4: =H4*I4 -> 0 | K4: =G4+J4 -> 568200 | M4: =M3+K4-L4 -> 1708343.1
A5: 2 | B5: 46083 | E5: 6000 | F5: 94.7 | G5: =E5*F5 -> 568200 | J5: =H5*I5 -> 0 | K5: =G5+J5 -> 568200 | M5: =M4+K5-L5 -> 2276543.1
A6: 3 | B6: 46084 | E6: 6000 | F6: 94.7 | G6: =E6*F6 -> 568200 | J6: =H6*I6 -> 0 | K6: =G6+J6 -> 568200 | M6: =M5+K6-L6 -> 2844743.1
A7: 4 | B7: 46085 | E7: 6000 | F7: 94.7 | G7: =E7*F7 -> 568200 | J7: =H7*I7 -> 0 | K7: =G7+J7 -> 568200 | M7: =M6+K7-L7 -> 3412943.1
A8: 5 | B8: 46086 | E8: 6000 | F8: 94.7 | G8: =E8*F8 -> 568200 | J8: =H8*I8 -> 0 | K8: =G8+J8 -> 568200 | M8: =M7+K8-L8 -> 3981143.1
A9: 6 | B9: 46087 | E9: 6000 | F9: 94.7 | G9: =E9*F9 -> 568200 | J9: =H9*I9 -> 0 | K9: =G9+J9 -> 568200 | M9: =M8+K9-L9 -> 4549343.1
A10: 7 | B10: 46088 | E10: 6000 | F10: 94.7 | G10: =E10*F10 -> 568200 | J10: =H10*I10 -> 0 | K10: =G10+J10 -> 568200 | M10: =M9+K10-L10 -> 5117543.1
A11: 8 | B11: 46089 | E11: 6000 | F11: 94.7 | G11: =E11*F11 -> 568200 | J11: =H11*I11 -> 0 | K11: =G11+J11 -> 568200 | M11: =M10+K11-L11 -> 5685743.1
A12: 9 | B12: 46090 | E12: 12000 | F12: 94.7 | G12: =E12*F12 -> 1136400 | J12: =H12*I12 -> 0 | K12: =G12+J12 -> 1136400 | M12: =M11+K12-L12 -> 6822143.1
A13: 10 | B13: 46091 | E13: 6000 | F13: 94.7 | G13: =E13*F13 -> 568200 | J13: =H13*I13 -> 0 | K13: =G13+J13 -> 568200 | M13: =M12+K13-L13 -> 7390343.1
A14: 11 | B14: 46092 | E14: 6000 | F14: 94.7 | G14: =E14*F14 -> 568200 | J14: =H14*I14 -> 0 | K14: =G14+J14 -> 568200 | M14: =M13+K14-L14 -> 7958543.1
A15: 12 | B15: 46093 | E15: 6050 | F15: 94.7 | G15: =E15*F15 -> 572935 | J15: =H15*I15 -> 0 | K15: =G15+J15 -> 572935 | M15: =M14+K15-L15 -> 8531478.1
A16: 13 | B16: 46094 | E16: 5993.93 | F16: 94.7 | G16: =E16*F16 -> 567625.17 | J16: =H16*I16 -> 0 | K16: =G16+J16 -> 567625.17 | M16: =M15+K16-L16 -> 9099103.3
A17: 14 | B17: 46095 | G17: =E17*F17 -> 0 | J17: =H17*I17 -> 0 | K17: =G17+J17 -> 0 | M17: =M16+K17-L17 -> 9099103.3
A18: 15 | B18: 46096 | G18: =E18*F18 -> 0 | J18: =H18*I18 -> 0 | K18: =G18+J18 -> 0 | M18: =M17+K18-L18 -> 9099103.3
A19: 16 | B19: 46097 | G19: =E19*F19 -> 0 | J19: =H19*I19 -> 0 | K19: =G19+J19 -> 0 | M19: =M18+K19-L19 -> 9099103.3
A20: 17 | B20: 46098 | E20: 6000 | F20: 94.7 | G20: =E20*F20 -> 568200 | J20: =H20*I20 -> 0 | K20: =G20+J20 -> 568200 | M20: =M19+K20-L20 -> 9667303.3
A21: 18 | B21: 46099 | E21: 6000 | F21: 94.7 | G21: =E21*F21 -> 568200 | J21: =H21*I21 -> 0 | K21: =G21+J21 -> 568200 | M21: =M20+K21-L21 -> 10235503
A22: 19 | B22: 46100 | G22: =E22*F22 -> 0 | J22: =H22*I22 -> 0 | K22: =G22+J22 -> 0 | M22: =M21+K22-L22 -> 10235503
A23: 20 | B23: 46101 | E23: 6000 | F23: 94.7 | G23: =E23*F23 -> 568200 | J23: =H23*I23 -> 0 | K23: =G23+J23 -> 568200 | M23: =M22+K23-L23 -> 10803703
A24: 21 | B24: 46102 | E24: 6000 | F24: 94.7 | G24: =E24*F24 -> 568200 | J24: =H24*I24 -> 0 | K24: =G24+J24 -> 568200 | M24: =M23+K24-L24 -> 11371903
A25: 22 | B25: 46103 | G25: =E25*F25 -> 0 | J25: =H25*I25 -> 0 | K25: =G25+J25 -> 0 | M25: =M24+K25-L25 -> 11371903
A26: 23 | B26: 46104 | E26: 6000 | F26: 95.2 | G26: =E26*F26 -> 571200 | J26: =H26*I26 -> 0 | K26: =G26+J26 -> 571200 | L26: 6000000 | M26: =M25+K26-L26 -> 5943103.3
A27: 24 | B27: 46105 | E27: 6000 | F27: 95.2 | G27: =E27*F27 -> 571200 | J27: =H27*I27 -> 0 | K27: =G27+J27 -> 571200 | M27: =M26+K27-L27 -> 6514303.3
A28: 25 | B28: 46106 | E28: 6000 | F28: 95.2 | G28: =E28*F28 -> 571200 | J28: =H28*I28 -> 0 | K28: =G28+J28 -> 571200 | M28: =M27+K28-L28 -> 7085503.3
A29: 26 | B29: 46107 | G29: =E29*F29 -> 0 | J29: =H29*I29 -> 0 | K29: =G29+J29 -> 0 | M29: =M28+K29-L29 -> 7085503.3
A30: 27 | B30: 46108 | G30: =E30*F30 -> 0 | J30: =H30*I30 -> 0 | K30: =G30+J30 -> 0 | M30: =M29+K30-L30 -> 7085503.3
A31: 28 | B31: 46109 | G31: =E31*F31 -> 0 | J31: =H31*I31 -> 0 | K31: =G31+J31 -> 0 | M31: =M30+K31-L31 -> 7085503.3
A32: 29 | B32: 46110 | E32: 6000 | F32: 95.2 | G32: =E32*F32 -> 571200 | J32: =H32*I32 -> 0 | K32: =G32+J32 -> 571200 | M32: =M31+K32-L32 -> 7656703.3
A33: 30 | B33: 46111 | G33: =E33*F33 -> 0 | J33: =H33*I33 -> 0 | K33: =G33+J33 -> 0 | M33: =M32+K33-L33 -> 7656703.3 | O33: 5486 | P33: TDS194Q
A34: 31 | B34: 46112 | E34: 6000 | F34: 95.2 | G34: =E34*F34 -> 571200 | J34: =H34*I34 -> 0 | K34: =G34+J34 -> 571200 | M34: =M33+K34-L34 -> 8227903.3
E35: =SUM(E4:E34) -> 138043.93 | G35: =SUM(G4:G34) -> 13087760 | H35: =SUM(H4:H34) -> 0 | J35: =SUM(J4:J34) -> 0 | K35: =SUM(K4:K34) -> 13087760 | L35: =SUM(L4:L34) -> 6000000

Sheet Khammam-4
A1: Vajra Mahalakshmi filling station
A2: S.No | B2: Date | C2: GRN No | D2: Ind No/Bill No | E2: Diesel (Lts) | F2: Price | G2: Amount | H2: Petrol (Lts) | I2: Price | J2: Amount | K2: Total amount | L2: Amount paid | M2: As 0n Date | N2: Remarks
A3: Opening Balance | K3: 0 | M3: 0
A4: 1 | B4: 46082 | G4: =E4*F4 -> 0 | K4: =G4+J4 -> 0 | L4: 0 | M4: =M3+K4-L4 -> 0
A5: 2 | B5: 46083 | E5: 0 | F5: 0 | G5: =E5*F5 -> 0 | H5: 0 | I5: 0 | J5: =H5*I5 -> 0 | K5: =G5+J5 -> 0 | L5: 0 | M5: =M4+K5-L5 -> 0
A6: 3 | B6: 46084 | G6: =E6*F6 -> 0 | J6: =H6*I6 -> 0 | K6: =G6+J6 -> 0 | L6: 0 | M6: =M5+K6-L6 -> 0
A7: 4 | B7: 46085 | G7: =E7*F7 -> 0 | J7: =H7*I7 -> 0 | K7: =G7+J7 -> 0 | L7: 0 | M7: =M6+K7-L7 -> 0
A8: 5 | B8: 46086 | G8: =E8*F8 -> 0 | J8: =H8*I8 -> 0 | K8: =G8+J8 -> 0 | L8: 0 | M8: =M7+K8-L8 -> 0
A9: 6 | B9: 46087 | G9: =E9*F9 -> 0 | J9: =H9*I9 -> 0 | K9: =G9+J9 -> 0 | L9: 0 | M9: =M8+K9-L9 -> 0
A10: 7 | B10: 46088 | E10: 2700 | F10: 95.5 | G10: =E10*F10 -> 257850 | J10: =H10*I10 -> 0 | K10: =G10+J10 -> 257850 | L10: 0 | M10: =M9+K10-L10 -> 257850
A11: 8 | B11: 46089 | G11: =E11*F11 -> 0 | J11: =H11*I11 -> 0 | K11: =G11+J11 -> 0 | L11: 0 | M11: =M10+K11-L11 -> 257850
A12: 9 | B12: 46090 | G12: =E12*F12 -> 0 | J12: =H12*I12 -> 0 | K12: =G12+J12 -> 0 | L12: 0 | M12: =M11+K12-L12 -> 257850
A13: 10 | B13: 46091 | E13: 759.76 | F13: 95.5 | G13: =E13*F13 -> 72557.08 | J13: =H13*I13 -> 0 | K13: =G13+J13 -> 72557.08 | L13: 0 | M13: =M12+K13-L13 -> 330407.08
A14: 11 | B14: 46092 | G14: =E14*F14 -> 0 | J14: =H14*I14 -> 0 | K14: =G14+J14 -> 0 | L14: 0 | M14: =M13+K14-L14 -> 330407.08
A15: 12 | B15: 46093 | G15: =E15*F15 -> 0 | J15: =H15*I15 -> 0 | K15: =G15+J15 -> 0 | L15: 0 | M15: =M14+K15-L15 -> 330407.08
A16: 13 | B16: 46094 | G16: =E16*F16 -> 0 | J16: =H16*I16 -> 0 | K16: =G16+J16 -> 0 | L16: 0 | M16: =M15+K16-L16 -> 330407.08
A17: 14 | B17: 46095 | G17: =E17*F17 -> 0 | J17: =H17*I17 -> 0 | K17: =G17+J17 -> 0 | L17: 0 | M17: =M16+K17-L17 -> 330407.08
A18: 15 | B18: 46096 | G18: =E18*F18 -> 0 | J18: =H18*I18 -> 0 | K18: =G18+J18 -> 0 | L18: 0 | M18: =M17+K18-L18 -> 330407.08
A19: 16 | B19: 46097 | G19: =E19*F19 -> 0 | J19: =H19*I19 -> 0 | K19: =G19+J19 -> 0 | L19: 0 | M19: =M18+K19-L19 -> 330407.08
A20: 17 | B20: 46098 | G20: =E20*F20 -> 0 | J20: =H20*I20 -> 0 | K20: =G20+J20 -> 0 | L20: 0 | M20: =M19+K20-L20 -> 330407.08
A21: 18 | B21: 46099 | G21: =E21*F21 -> 0 | J21: =H21*I21 -> 0 | K21: =G21+J21 -> 0 | L21: 0 | M21: =M20+K21-L21 -> 330407.08
A22: 19 | B22: 46100 | G22: =E22*F22 -> 0 | J22: =H22*I22 -> 0 | K22: =G22+J22 -> 0 | L22: 0 | M22: =M21+K22-L22 -> 330407.08
A23: 20 | B23: 46101 | G23: =E23*F23 -> 0 | J23: =H23*I23 -> 0 | K23: =G23+J23 -> 0 | L23: 0 | M23: =M22+K23-L23 -> 330407.08
A24: 21 | B24: 46102 | G24: =E24*F24 -> 0 | J24: =H24*I24 -> 0 | K24: =G24+J24 -> 0 | L24: 0 | M24: =M23+K24-L24 -> 330407.08
A25: 22 | B25: 46103 | G25: =E25*F25 -> 0 | J25: =H25*I25 -> 0 | K25: =G25+J25 -> 0 | L25: 0 | M25: =M24+K25-L25 -> 330407.08
... A33: 30 | B33: 46111 | G33: =E33*F33 -> 0 | J33: =H33*I33 -> 0 | K33: =G33+J33 -> 0 | L33: 0 | M33: =M32+K33-L33 -> 330407.08
A34: 31 | B34: 46112 | G34: =E34*F34 -> 0 | K34: =G34+J34 -> 0 | L34: 0 | M34: =M33+K34-L34 -> 330407.08
A35: 32 | G35: =E35*F35 -> 0 | J35: =H35*I35 -> 0 | K35: =G35+J35 -> 0 | L35: 0 | M35: =M34+K35-L35 -> 330407.08
A36: 33 | G36: =E36*F36 -> 0 | J36: =H36*I36 -> 0 | K36: =G36+J36 -> 0 | L36: 0
A37: 34 | G37: =E37*F37 -> 0 | J37: =H37*I37 -> 0 | K37: =G37+J37 -> 0
E38: =SUM(E3:E37) -> 3459.76 | G38: =SUM(G3:G37) -> 330407.08 | H38: =SUM(H3:H37) -> 0 | J38: =SUM(J3:J37) -> 0 | K38: =SUM(K4:K37) -> 330407.08 | L38: =SUM(L3:L37) -> 0

Sheet Khammam-5
A1: SR HP Filling Station ( Dhamsalapuram)
A2: S.No | B2: Date | C2: GRN No | D2: Ind No/Bill No | E2: Diesel (Lts) | F2: Price | G2: Amount | H2: Petrol (Lts) | I2: Price | J2: Amount | K2: Total amount | L2: Amount paid | M2: As 0n Date | N2: Remarks
A3: Opening Balance | K3: 0 | M3: 0
A4: 1 | B4: 46082 | G4: =E4*F4 -> 0 | K4: =G4+J4 -> 0 | L4: 0 | M4: =M3+K4-L4 -> 0
A5: 2 | B5: 46083 | G5: =E5*F5 -> 0 | J5: =H5*I5 -> 0 | K5: =G5+J5 -> 0 | L5: 0 | M5: =M4+K5-L5 -> 0
A6: 3 | B6: 46084 | G6: =E6*F6 -> 0 | J6: =H6*I6 -> 0 | K6: =G6+J6 -> 0 | L6: 0 | M6: =M5+K6-L6 -> 0
A7: 4 | B7: 46085 | G7: =E7*F7 -> 0 | J7: =H7*I7 -> 0 | K7: =G7+J7 -> 0 | L7: 0 | M7: =M6+K7-L7 -> 0
A8: 5 | B8: 46086 | G8: =E8*F8 -> 0 | J8: =H8*I8 -> 0 | K8: =G8+J8 -> 0 | L8: 0 | M8: =M7+K8-L8 -> 0
A9: 6 | B9: 46087 | G9: =E9*F9 -> 0 | J9: =H9*I9 -> 0 | K9: =G9+J9 -> 0 | L9: 0 | M9: =M8+K9-L9 -> 0
A10: 7 | B10: 46088 | G10: =E10*F10 -> 0 | J10: =H10*I10 -> 0 | K10: =G10+J10 -> 0 | L10: 0 | M10: =M9+K10-L10 -> 0
A11: 8 | B11: 46089 | G11: =E11*F11 -> 0 | J11: =H11*I11 -> 0 | K11: =G11+J11 -> 0 | L11: 0 | M11: =M10+K11-L11 -> 0
A12: 9 | B12: 46090 | G12: =E12*F12 -> 0 | J12: =H12*I12 -> 0 | K12: =G12+J12 -> 0 | L12: 0 | M12: =M11+K12-L12 -> 0
A13: 10 | B13: 46091 | G13: =E13*F13 -> 0 | J13: =H13*I13 -> 0 | K13: =G13+J13 -> 0 | L13: 0 | M13: =M12+K13-L13 -> 0
A14: 11 | B14: 46092 | G14: =E14*F14 -> 0 | J14: =H14*I14 -> 0 | K14: =G14+J14 -> 0 | L14: 0 | M14: =M13+K14-L14 -> 0
A15: 12 | B15: 46093 | G15: =E15*F15 -> 0 | J15: =H15*I15 -> 0 | K15: =G15+J15 -> 0 | L15: 0 | M15: =M14+K15-L15 -> 0
A16: 13 | B16: 46094 | G16: =E16*F16 -> 0 | J16: =H16*I16 -> 0 | K16: =G16+J16 -> 0 | L16: 0 | M16: =M15+K16-L16 -> 0
A17: 14 | B17: 46095 | G17: =E17*F17 -> 0 | J17: =H17*I17 -> 0 | K17: =G17+J17 -> 0 | L17: 0 | M17: =M16+K17-L17 -> 0 | U17: 257315
A18: 15 | B18: 46096 | G18: =E18*F18 -> 0 | J18: =H18*I18 -> 0 | K18: =G18+J18 -> 0 | L18: 0 | M18: =M17+K18-L18 -> 0 | U18: 22996
A19: 16 | B19: 46097 | G19: =E19*F19 -> 0 | J19: =H19*I19 -> 0 | K19: =G19+J19 -> 0 | L19: 0 | M19: =M18+K19-L19 -> 0 | U19: =U17+U18 -> 280311
A20: 17 | B20: 46098 | G20: =E20*F20 -> 0 | J20: =H20*I20 -> 0 | K20: =G20+J20 -> 0 | L20: 0 | M20: =M19+K20-L20 -> 0 | U20: =U19-183340 -> 96971
A21: 18 | B21: 46099 | G21: =E21*F21 -> 0 | J21: =H21*I21 -> 0 | K21: =G21+J21 -> 0 | L21: 0 | M21: =M20+K21-L21 -> 0
A22: 19 | B22: 46100 | G22: =E22*F22 -> 0 | J22: =H22*I22 -> 0 | K22: =G22+J22 -> 0 | L22: 0 | M22: =M21+K22-L22 -> 0 | R22: 91.67
A23: 20 | B23: 46101 | G23: =E23*F23 -> 0 | J23: =H23*I23 -> 0 | K23: =G23+J23 -> 0 | L23: 0 | M23: =M22+K23-L23 -> 0 | R23: 2000 | U23: 197391.46
A24: 21 | B24: 46102 | G24: =E24*F24 -> 0 | J24: =H24*I24 -> 0 | K24: =G24+J24 -> 0 | L24: 0 | M24: =M23+K24-L24 -> 0 | R24: =R23*R22 -> 183340
A25: 22 | B25: 46103 | G25: =E25*F25 -> 0 | J25: =H25*I25 -> 0 | K25: =G25+J25 -> 0 | L25: 0 | M25: =M24+K25-L25 -> 0
A26: 23 | B26: 46104 | G26: =E26*F26 -> 0 | J26: =H26*I26 -> 0 | K26: =G26+J26 -> 0 | L26: 0 | M26: =M25+K26-L26 -> 0
A27: 24 | B27: 46105 | E27: 1569.98 | F27: 95.68 | G27: =E27*F27 -> 150215.69 | J27: =H27*I27 -> 0 | K27: =G27+J27 -> 150215.69 | L27: 150215 | M27: =M26+K27-L27 -> 0.6864
A28: 25 | B28: 46106 | G28: =E28*F28 -> 0 | J28: =H28*I28 -> 0 | K28: =G28+J28 -> 0 | L28: 0 | M28: =M27+K28-L28 -> 0.6864
A29: 26 | B29: 46107 | E29: 2612.88 | F29: 95.68 | G29: =E29*F29 -> 250000.36 | J29: =H29*I29 -> 0 | K29: =G29+J29 -> 250000.36 | L29: =H29+K29 -> 250000.36 | M29: =M28+K29-L29 -> 0.6864
A30: 27 | B30: 46108 | E30: 2090.3 | F30: 95.68 | G30: =E30*F30 -> 199999.9 | J30: =H30*I30 -> 0 | K30: =G30+J30 -> 199999.9 | L30: =H30+K30 -> 199999.9 | M30: =M29+K30-L30 -> 0.6864
A31: 28 | B31: 46109 | G31: =E31*F31 -> 0 | J31: =H31*I31 -> 0 | K31: =G31+J31 -> 0 | L31: 0 | M31: =M30+K31-L31 -> 0.6864
A32: 29 | B32: 46110 | G32: =E32*F32 -> 0 | J32: =H32*I32 -> 0 | K32: =G32+J32 -> 0 | L32: 0 | M32: =M31+K32-L32 -> 0.6864
A33: 30 | B33: 46111 | G33: =E33*F33 -> 0 | J33: =H33*I33 -> 0 | K33: =G33+J33 -> 0 | L33: 0 | M33: =M32+K33-L33 -> 0.6864
A34: 31 | B34: 46112 | G34: =E34*F34 -> 0 | K34: =G34+J34 -> 0 | L34: 0 | M34: =M33+K34-L34 -> 0.6864
A35: 32 | G35: =E35*F35 -> 0 | J35: =H35*I35 -> 0 | K35: =G35+J35 -> 0 | L35: 0 | M35: =M34+K35-L35 -> 0.6864
A36: 33 | G36: =E36*F36 -> 0 | J36: =H36*I36 -> 0 | K36: =G36+J36 -> 0 | L36: 0
A37: 34 | G37: =E37*F37 -> 0 | J37: =H37*I37 -> 0 | K37: =G37+J37 -> 0
E38: =SUM(E3:E37) -> 6273.16 | G38: =SUM(G3:G37) -> 600215.95 | H38: =SUM(H3:H37) -> 0 | J38: =SUM(J3:J37) -> 0 | K38: =SUM(K4:K37) -> 600215.95 | L38: =SUM(L3:L37) -> 600215.26

Sheet Jadcherla-3
A1: JSASFuel Genie India Pvt.Ltd
A2: S.No | B2: Date | C2: GRN No | D2: Ind no/Bill No | E2: Diesel (Lts) | F2: Price | G2: Amount | H2: Petrol (Lts) | I2: Price | J2: Amount | K2: Total amount | L2: Amount paid | M2: As on Date | N2: Remarks
A3: Opening Balance | M3: 1026278.2
A4: 1 | B4: 46082 | E4: 2200 | F4: 95.43 | G4: =E4*F4 -> 209946 | H4: 0 | I4: 0 | J4: =H4*I4 -> 0 | K4: =G4+J4 -> 209946 | L4: 0 | M4: =+M3+K4-L4 -> 1236224.2
A5: 2 | B5: 46083 | E5: 2400 | F5: 95.43 | G5: =E5*F5 -> 229032 | H5: 0 | I5: 0 | J5: =H5*I5 -> 0 | K5: =G5+J5 -> 229032 | L5: 0 | M5: =+M4+K5-L5 -> 1465256.2
A6: 3 | B6: 46084 | G6: =E6*F6 -> 0 | H6: 0 | I6: 0 | J6: =H6*I6 -> 0 | K6: =G6+J6 -> 0 | L6: 0 | M6: =+M5+K6-L6 -> 1465256.2
A7: 4 | B7: 46085 | G7: =E7*F7 -> 0 | H7: 0 | I7: 0 | J7: =H7*I7 -> 0 | K7: =G7+J7 -> 0 | L7: 0 | M7: =+M6+K7-L7 -> 1465256.2
A8: 5 | B8: 46086 | G8: =E8*F8 -> 0 | H8: 0 | I8: 0 | J8: =H8*I8 -> 0 | K8: =G8+J8 -> 0 | L8: 0 | M8: =+M7+K8-L8 -> 1465256.2
A9: 6 | B9: 46087 | G9: =E9*F9 -> 0 | H9: 0 | I9: 0 | J9: =H9*I9 -> 0 | K9: =G9+J9 -> 0 | L9: 0 | M9: =+M8+K9-L9 -> 1465256.2
A10: 7 | B10: 46088 | E10: 2000 | F10: 95.43 | G10: =E10*F10 -> 190860 | H10: 0 | I10: 0 | J10: =H10*I10 -> 0 | K10: =G10+J10 -> 190860 | L10: 0 | M10: =+M9+K10-L10 -> 1656116.2 | R10: 700
A11: 8 | B11: 46089 | G11: =E11*F11 -> 0 | H11: 0 | I11: 0 | J11: =H11*I11 -> 0 | K11: =G11+J11 -> 0 | L11: 0 | M11: =+M10+K11-L11 -> 1656116.2 | S11: 5000
A12: 9 | B12: 46090 | E12: 2000 | F12: 95.43 | G12: =E12*F12 -> 190860 | H12: 0 | I12: 0 | J12: =H12*I12 -> 0 | K12: =G12+J12 -> 190860 | L12: 0 | M12: =+M11+K12-L12 -> 1846976.2 | S12: 1500
A13: 10 | B13: 46091 | G13: =E13*F13 -> 0 | H13: 0 | I13: 0 | J13: =H13*I13 -> 0 | K13: =G13+J13 -> 0 | L13: 0 | M13: =+M12+K13-L13 -> 1846976.2 | S13: 500
A14: 11 | B14: 46092 | E14: 1000 | F14: 95.43 | G14: =E14*F14 -> 95430 | H14: 0 | I14: 0 | J14: =H14*I14 -> 0 | K14: =G14+J14 -> 95430 | L14: 0 | M14: =+M13+K14-L14 -> 1942406.2
A15: 12 | B15: 46093 | G15: =E15*F15 -> 0 | H15: 0 | I15: 0 | J15: =H15*I15 -> 0 | K15: =G15+J15 -> 0 | L15: 0 | M15: =+M14+K15-L15 -> 1942406.2
A16: 13 | B16: 46094 | E16: 1998 | F16: 95.43 | G16: =E16*F16 -> 190669.14 | H16: 0 | I16: 0 | J16: =H16*I16 -> 0 | K16: =G16+J16 -> 190669.14 | L16: 0 | M16: =+M15+K16-L16 -> 2133075.4
A17: 14 | B17: 46095 | E17: 2000 | F17: 95.43 | G17: =E17*F17 -> 190860 | H17: 0 | I17: 0 | J17: =H17*I17 -> 0 | K17: =G17+J17 -> 190860 | L17: 0 | M17: =+M16+K17-L17 -> 2323935.4
A18: 15 | B18: 46096 | G18: =E18*F18 -> 0 | H18: 0 | I18: 0 | J18: =H18*I18 -> 0 | K18: =G18+J18 -> 0 | L18: 0 | M18: =+M17+K18-L18 -> 2323935.4
A19: 16 | B19: 46097 | E19: 2400 | F19: 95.43 | G19: =E19*F19 -> 229032 | H19: 0 | I19: 0 | J19: =H19*I19 -> 0 | K19: =G19+J19 -> 229032 | L19: 0 | M19: =+M18+K19-L19 -> 2552967.4
A20: 17 | B20: 46098 | E20: 2000 | F20: 95.43 | G20: =E20*F20 -> 190860 | H20: 0 | I20: 0 | J20: =H20*I20 -> 0 | K20: =G20+J20 -> 190860 | L20: 0 | M20: =+M19+K20-L20 -> 2743827.4
A21: 18 | B21: 46099 | G21: =E21*F21 -> 0 | H21: 0 | I21: 0 | J21: =H21*I21 -> 0 | K21: =G21+J21 -> 0 | M21: =+M20+K21-L21 -> 2743827.4
A22: 19 | B22: 46100 | G22: =E22*F22 -> 0 | H22: 0 | I22: 0 | J22: =H22*I22 -> 0 | K22: =G22+J22 -> 0 | L22: 1000000 | M22: =+M21+K22-L22 -> 1743827.4
A23: 20 | B23: 46101 | E23: 1000 | F23: 95.43 | G23: =E23*F23 -> 95430 | H23: 0 | I23: 0 | J23: =H23*I23 -> 0 | K23: =G23+J23 -> 95430 | L23: 0 | M23: =+M22+K23-L23 -> 1839257.4
A24: 21 | B24: 46102 | G24: =E24*F24 -> 0 | H24: 0 | I24: 0 | J24: =H24*I24 -> 0 | K24: =G24+J24 -> 0 | L24: 0 | M24: =+M23+K24-L24 -> 1839257.4
A25: 22 | B25: 46103 | G25: =E25*F25 -> 0 | H25: 0 | I25: 0 | J25: =H25*I25 -> 0 | K25: =G25+J25 -> 0 | L25: 0 | M25: =+M24+K25-L25 -> 1839257.4
A26: 23 | B26: 46104 | E26: 2000 | F26: 95.93 | G26: =E26*F26 -> 191860 | H26: 0 | I26: 0 | J26: =H26*I26 -> 0 | K26: =G26+J26 -> 191860 | L26: 0 | M26: =+M25+K26-L26 -> 2031117.4
A27: 24 | B27: 46105 | E27: 2400 | F27: 95.93 | G27: =E27*F27 -> 230232 | H27: 0 | I27: 0 | J27: =H27*I27 -> 0 | K27: =G27+J27 -> 230232 | L27: 0 | M27: =+M26+K27-L27 -> 2261349.4
A28: 25 | B28: 46106 | G28: =E28*F28 -> 0 | H28: 0 | I28: 0 | J28: =H28*I28 -> 0 | K28: =G28+J28 -> 0 | L28: 0 | M28: =+M27+K28-L28 -> 2261349.4
A29: 26 | B29: 46107 | E29: 1000 | F29: 95.93 | G29: =E29*F29 -> 95930 | H29: 0 | I29: 0 | J29: =H29*I29 -> 0 | K29: =G29+J29 -> 95930 | M29: =+M28+K29-L29 -> 2357279.4
A30: 27 | B30: 46108 | G30: =E30*F30 -> 0 | H30: 0 | I30: 0 | J30: =H30*I30 -> 0 | K30: =G30+J30 -> 0 | M30: =+M29+K30-L30 -> 2357279.4
A31: 28 | B31: 46109 | G31: =E31*F31 -> 0 | H31: 0 | I31: 0 | J31: =H31*I31 -> 0 | K31: =G31+J31 -> 0 | M31: =+M30+K31-L31 -> 2357279.4
A32: 29 | B32: 46111 | E32: 1000 | F32: 95.93 | G32: =E32*F32 -> 95930 | H32: 0 | I32: 0 | J32: =H32*I32 -> 0 | K32: =G32+J32 -> 95930 | M32: =+M31+K32-L32 -> 2453209.4
A33: 30 | G33: =E33*F33 -> 0 | H33: 0 | I33: 0 | J33: =H33*I33 -> 0 | K33: =G33+J33 -> 0 | M33: =+M32+K33-L33 -> 2453209.4
A34: 31 | G34: =E34*F34 -> 0 | H34: 0 | I34: 0 | J34: =H34*I34 -> 0 | K34: =G34+J34 -> 0 | L34: 0 | M34: =+M33+K34-L34 -> 2453209.4
E35: =SUM(E4:E34) -> 25398 | G35: =SUM(G4:G34) -> 2426931.1 | H35: =SUM(H4:H34) -> 0 | J35: =SUM(J4:J34) -> 0 | K35: =SUM(K4:K34) -> 2426931.1 | L35: =SUM(L4:L34) -> 1000000
F38: /

Sheet Jadcherla-4
A1: Shree Poornima F/S
A2: S.No | B2: Date | C2: GRN No | D2: Ind No/Bill No | E2: Diesel (Lts) | F2: Price | G2: Amount | H2: Petrol (Lts) | I2: Price | J2: Amount | K2: Total amount | L2: Amount paid | M2: As on date | N2: Remarks
A3: Opening Balance | M3: 24863
A4: 1 | B4: 46082 | G4: =E4*F4 -> 0 | H4: 40 | I4: 108.1 | J4: =H4*I4 -> 4324 | K4: =G4+J4 -> 4324 | L4: 0 | M4: =M3+K4-L4 -> 29187
A5: 2 | B5: 46083 | G5: =E5*F5 -> 0 | H5: 0 | I5: 0 | J5: =H5*I5 -> 0 | K5: =G5+J5 -> 0 | L5: 0 | M5: =M4+K5-L5 -> 29187
A6: 3 | B6: 46084 | G6: =E6*F6 -> 0 | H6: 0 | I6: 0 | J6: =H6*I6 -> 0 | K6: =G6+J6 -> 0 | L6: 0 | M6: =M5+K6-L6 -> 29187
A7: 4 | B7: 46085 | G7: =E7*F7 -> 0 | H7: 0 | I7: 0 | J7: =H7*I7 -> 0 | K7: =G7+J7 -> 0 | L7: 0 | M7: =M6+K7-L7 -> 29187
A8: 5 | B8: 46086 | G8: =E8*F8 -> 0 | H8: 40 | I8: 108.1 | J8: =H8*I8 -> 4324 | K8: =G8+J8 -> 4324 | L8: 0 | M8: =M7+K8-L8 -> 33511
A9: 6 | B9: 46087 | G9: =E9*F9 -> 0 | H9: 0 | I9: 0 | J9: =H9*I9 -> 0 | K9: =G9+J9 -> 0 | L9: 0 | M9: =M8+K9-L9 -> 33511
A10: 7 | B10: 46088 | G10: =E10*F10 -> 0 | H10: 0 | I10: 0 | J10: =H10*I10 -> 0 | K10: =G10+J10 -> 0 | L10: 0 | M10: =M9+K10-L10 -> 33511
A11: 8 | B11: 46089 | G11: =E11*F11 -> 0 | H11: 0 | I11: 0 | J11: =H11*I11 -> 0 | K11: =G11+J11 -> 0 | L11: 0 | M11: =M10+K11-L11 -> 33511
A12: 9 | B12: 46090 | G12: =E12*F12 -> 0 | H12: 0 | I12: 0 | J12: =H12*I12 -> 0 | K12: =G12+J12 -> 0 | L12: 0 | M12: =M11+K12-L12 -> 33511
A13: 10 | B13: 46091 | G13: =E13*F13 -> 0 | H13: 0 | I13: 0 | J13: =H13*I13 -> 0 | K13: =G13+J13 -> 0 | L13: 0 | M13: =M12+K13-L13 -> 33511
A14: 11 | B14: 46092 | G14: =E14*F14 -> 0 | H14: 40 | I14: 108.1 | J14: =H14*I14 -> 4324 | K14: =G14+J14 -> 4324 | L14: 0 | M14: =M13+K14-L14 -> 37835
A15: 12 | B15: 46093 | G15: =E15*F15 -> 0 | H15: 0 | I15: 0 | J15: =H15*I15 -> 0 | K15: =G15+J15 -> 0 | L15: 0 | M15: =M14+K15-L15 -> 37835
... A25: 22 | B25: 46103 | G25: =E25*F25 -> 0 | H25: 0 | I25: 0 | J25: =H25*I25 -> 0 | K25: =G25+J25 -> 0 | L25: 0 | M25: =M24+K25-L25 -> 4324
A26: 23 | B26: 46104 | E26: 0 | F26: 0 | G26: =E26*F26 -> 0 | H26: 0 | I26: 0 | J26: =H26*I26 -> 0 | K26: =G26+J26 -> 0 | L26: 0 | M26: =M25+K26-L26 -> 4324
A27: 24 | B27: 46105 | G27: =E27*F27 -> 0 | H27: 0 | I27: 0 | J27: =H27*I27 -> 0 | K27: =G27+J27 -> 0 | L27: 0 | M27: =M26+K27-L27 -> 4324
A28: 25 | B28: 46106 | G28: =E28*F28 -> 0 | H28: 0 | I28: 0 | J28: =H28*I28 -> 0 | K28: =G28+J28 -> 0 | L28: 0 | M28: =M27+K28-L28 -> 4324
A29: 26 | B29: 46107 | G29: =E29*F29 -> 0 | H29: 50 | I29: 108.1 | J29: =H29*I29 -> 5405 | K29: =G29+J29 -> 5405 | L29: 0 | M29: =M28+K29-L29 -> 9729
A30: 27 | B30: 46108 | G30: =E30*F30 -> 0 | H30: 0 | I30: 0 | J30: =H30*I30 -> 0 | K30: =G30+J30 -> 0 | L30: 0 | M30: =M29+K30-L30 -> 9729
A31: 28 | B31: 46109 | G31: =E31*F31 -> 0 | H31: 0 | I31: 0 | J31: =H31*I31 -> 0 | K31: =G31+J31 -> 0 | M31: =M30+K31-L31 -> 9729
A32: 29 | B32: 46110 | G32: =E32*F32 -> 0 | H32: 0 | I32: 0 | J32: =H32*I32 -> 0 | K32: =G32+J32 -> 0 | M32: =M31+K32-L32 -> 9729
A33: 30 | B33: 46111 | G33: =E33*F33 -> 0 | H33: 0 | I33: 0 | J33: =H33*I33 -> 0 | K33: =G33+J33 -> 0 | M33: =M32+K33-L33 -> 9729
A34: 31 | B34: 46112 | G34: =E34*F34 -> 0 | J34: =H34*I34 -> 0 | K34: =G34+J34 -> 0 | M34: =M33+K34-L34 -> 9729
E35: =SUM(E4:E34) -> 0 | G35: =SUM(G4:G34) -> 0 | H35: =SUM(H4:H34) -> 210 | J35: =SUM(J4:J34) -> 22701 | K35: =SUM(K4:K34) -> 22701 | L35: =SUM(L4:L34) -> 37835

Sheet  Sangareeddy-1
A1: Durga Indhan
A2: S.No | B2: Date | C2: GRN No | D2: Ind no/Bill No | E2: Diesel (Lts) | F2: Price | G2: Amount | H2: Petrol (Lts) | I2: Price | J2: Amount | K2: Total amount | L2: Amount paid | M2: As on Date | N2: Remarks
A3: Opening Balance | M3: 151710.02
A4: 1 | B4: 45717 | E4: 200 | F4: 96.37 | G4: =E4*F4 -> 19274 | H4: 5 | I4: 108.17 | J4: =H4*I4 -> 540.85 | K4: =G4+J4 -> 19814.85 | L4: 0 | M4: =M3+K4-L4 -> 171524.87
A5: 2 | B5: 45718 | E5: 37.67 | F5: 96.37 | G5: =E5*F5 -> 3630.2579 | H5: =4+4+5 -> 13 | I5: 108.17 | J5: =H5*I5 -> 1406.21 | K5: =G5+J5 -> 5036.4679 | L5: 0 | M5: =M4+K5-L5 -> 176561.34
A6: 3 | B6: 45719 | E6: =200+49.72 -> 249.72 | F6: 96.37 | G6: =E6*F6 -> 24065.516 | H6: =5+5+5 -> 15 | I6: 108.17 | J6: =H6*I6 -> 1622.55 | K6: =G6+J6 -> 25688.066 | L6: 0 | M6: =M5+K6-L6 -> 202249.4
A7: 4 | B7: 45720 | E7: 30 | F7: 96.37 | G7: =E7*F7 -> 2891.1 | H7: 0 | I7: 108.17 | J7: =H7*I7 -> 0 | K7: =G7+J7 -> 2891.1 | L7: 0 | M7: =M6+K7-L7 -> 205140.5
A8: 5 | B8: 45721 | E8: =200+200+43.89 -> 443.89 | F8: 96.37 | G8: =E8*F8 -> 42777.679 | H8: =5+45.31 -> 50.31 | I8: 108.17 | J8: =H8*I8 -> 5442.0327 | K8: =G8+J8 -> 48219.712 | L8: 0 | M8: =M7+K8-L8 -> 253360.22
A9: 6 | B9: 45722 | E9: 200 | F9: 96.37 | G9: =E9*F9 -> 19274 | H9: 0 | I9: 108.17 | J9: =H9*I9 -> 0 | K9: =G9+J9 -> 19274 | L9: 0 | M9: =M8+K9-L9 -> 272634.22
A10: 7 | B10: 45723 | E10: =19.18+83.81+100+200 -> 402.99 | F10: 96.37 | G10: =E10*F10 -> 38836.146 | H10: =4+5+5 -> 14 | I10: 108.17 | J10: =H10*I10 -> 1514.38 | K10: =G10+J10 -> 40350.526 | L10: 0 | M10: =M9+K10-L10 -> 312984.74
A11: 8 | B11: 45724 | E11: 0 | F11: 96.37 | G11: =E11*F11 -> 0 | H11: 0 | I11: 108.17 | J11: =H11*I11 -> 0 | K11: =G11+J11 -> 0 | L11: 0 | M11: =M10+K11-L11 -> 312984.74
A12: 9 | B12: 45725 | E12: 0 | F12: 96.37 | G12: =E12*F12 -> 0 | H12: 9 | I12: 108.17 | J12: =H12*I12 -> 973.53 | K12: =G12+J12 -> 973.53 | L12: 0 | M12: =M11+K12-L12 -> 313958.27
A13: 10 | B13: 45726 | E13: =59.13+400+30.73 -> 489.86 | F13: 96.37 | G13: =E13*F13 -> 47207.808 | H13: 0 | I13: 108.17 | J13: =H13*I13 -> 0 | K13: =G13+J13 -> 47207.808 | L13: 360000 | M13: =M12+K13-L13 -> 1166.0808
A14: 11 | B14: 45727 | E14: =42.79+61.28 -> 104.07 | F14: 96.37 | G14: =E14*F14 -> 10029.226 | H14: =5+5 -> 10 | I14: 108.17 | J14: =H14*I14 -> 1081.7 | K14: =G14+J14 -> 11110.926 | L14: 0 | M14: =M13+K14-L14 -> 12277.007
A15: 12 | B15: 45728 | E15: 200 | F15: 96.37 | G15: =E15*F15 -> 19274 | H15: 3 | I15: 108.17 | J15: =H15*I15 -> 324.51 | K15: =G15+J15 -> 19598.51 | L15: 0 | M15: =M14+K15-L15 -> 31875.517
A16: 13 | B16: 45729 | E16: =100+67.66+41.08 -> 208.74 | F16: 96.37 | G16: =E16*F16 -> 20116.274 | H16: =5+5+5+4 -> 19 | I16: 108.17 | J16: =H16*I16 -> 2055.23 | K16: =G16+J16 -> 22171.504 | L16: 0 | M16: =M15+K16-L16 -> 54047.021
A17: 14 | B17: 45730 | G17: =E17*F17 -> 0 | H17: 6 | I17: 108.17 | J17: =H17*I17 -> 649.02 | K17: =G17+J17 -> 649.02 | M17: =M16+K17-L17 -> 54696.041
A18: 15 | B18: 45731 | G18: =E18*F18 -> 0 | H18: 0 | I18: 0 | J18: =H18*I18 -> 0 | K18: =G18+J18 -> 0 | L18: =+K18 -> 0 | M18: =M17+K18-L18 -> 54696.041
A19: 16 | B19: 45732 | G19: =E19*F19 -> 0 | H19: 4 | I19: 108.17 | J19: =H19*I19 -> 432.68 | K19: =G19+J19 -> 432.68 | M19: =M18+K19-L19 -> 55128.721
A20: 17 | B20: 45733 | G20: =E20*F20 -> 0 | H20: 5 | I20: 108.17 | J20: =H20*I20 -> 540.85 | K20: =G20+J20 -> 540.85 | M20: =M19+K20-L20 -> 55669.571
A21: 18 | B21: 45734 | E21: 160.75 | F21: 96.37 | G21: =E21*F21 -> 15491.478 | H21: 0 | I21: 0 | J21: =H21*I21 -> 0 | K21: =G21+J21 -> 15491.478 | L21: 0 | M21: =M20+K21-L21 -> 71161.048
A22: 19 | B22: 45735 | G22: =E22*F22 -> 0 | H22: 0 | I22: 0 | J22: =H22*I22 -> 0 | K22: =G22+J22 -> 0 | L22: =+K22 -> 0 | M22: =M21+K22-L22 -> 71161.048
A23: 20 | B23: 45736 | G23: =E23*F23 -> 0 | H23: 0 | I23: 0 | J23: =H23*I23 -> 0 | K23: =G23+J23 -> 0 | L23: =+K23 -> 0 | M23: =M22+K23-L23 -> 71161.048
A24: 21 | B24: 45737 | G24: =E24*F24 -> 0 | H24: 0 | I24: 0 | J24: =H24*I24 -> 0 | K24: =G24+J24 -> 0 | L24: =+K24 -> 0 | M24: =M23+K24-L24 -> 71161.048
A25: 22 | B25: 45738 | G25: =E25*F25 -> 0 | H25: 0 | I25: 0 | J25: =H25*I25 -> 0 | K25: =G25+J25 -> 0 | L25: =+K25 -> 0 | M25: =M24+K25-L25 -> 71161.048
A26: 23 | B26: 45739 | G26: =E26*F26 -> 0 | H26: 0 | I26: 0 | J26: =H26*I26 -> 0 | K26: =G26+J26 -> 0 | L26: =+K26 -> 0 | M26: 0
A27: 24 | B27: 45740 | G27: =E27*F27 -> 0 | H27: 0 | I27: 0 | J27: =H27*I27 -> 0 | K27: =G27+J27 -> 0 | L27: =+K27 -> 0 | M27: 0
A28: 25 | B28: 45741 | H28: 0 | I28: 0 | J28: =H28*I28 -> 0 | K28: =G28+J28 -> 0 | L28: =+K28 -> 0 | M28: 0
A29: 26 | B29: 45742 | G29: =E29*F29 -> 0 | H29: 0 | I29: 0 | J29: =H29*I29 -> 0 | K29: =G29+J29 -> 0 | L29: =+K29 -> 0 | M29: 0
A30: 27 | B30: 45743 | G30: =E30*F30 -> 0 | H30: 0 | I30: 0 | J30: =H30*I30 -> 0 | K30: =G30+J30 -> 0 | L30: =+K30 -> 0 | M30: 0
A31: 28 | B31: 45744 | G31: =E31*F31 -> 0 | H31: 0 | I31: 0 | J31: =H31*I31 -> 0 | K31: =G31+J31 -> 0 | L31: =+K31 -> 0 | M31: 0
A32: 29 | B32: 45745 | G32: =E32*F32 -> 0 | H32: 0 | I32: 0 | J32: =H32*I32 -> 0 | K32: =G32+J32 -> 0 | L32: =+K32 -> 0 | M32: 0
A33: 30 | B33: 45746 | G33: =E33*F33 -> 0 | H33: 0 | I33: 0 | J33: =H33*I33 -> 0 | K33: =G33+J33 -> 0 | L33: =+K33 -> 0 | M33: 0
A34: 31 | B34: 45747 | G34: =E34*F34 -> 0 | H34: 0 | I34: 0 | J34: =H34*I34 -> 0 | K34: =G34+J34 -> 0 | L34: =+K34 -> 0 | M34: 0
E35: =SUM(E4:E34) -> 2727.69 | G35: =SUM(G4:G34) -> 262867.49 | H35: =SUM(H4:H34) -> 153.31 | J35: =SUM(J4:J34) -> 16583.543 | K35: =SUM(K4:K34) -> 279451.03 | L35: =SUM(L4:L34) -> 360000

Sheet  Sangareddy-2
A1: Durga Bhavani F/S
A2: S.No | B2: Date | C2: GRN No | D2: Ind no/Bill No | E2: Diesel (Lts) | F2: Price | G2: Amount | H2: Petrol (Lts) | I2: Price | J2: Amount | K2: Total amount | L2: Amount paid | M2: As on Date | N2: Remarks
A3: Opening Balance | M3: 0
A4: 1 | B4: 45717 | G4: =E4*F4 -> 0 | H4: 0 | I4: 0 | J4: =H4*I4 -> 0 | K4: =G4+J4 -> 0 | L4: =+K4 -> 0 | M4: =M3+K4-L4 -> 0
A5: 2 | B5: 45718 | G5: =E5*F5 -> 0 | H5: 0 | I5: 0 | J5: =H5*I5 -> 0 | K5: =G5+J5 -> 0 | L5: =+K5 -> 0 | M5: =M4+K5-L5 -> 0
A6: 3 | B6: 45719 | E6: 47.79 | F6: 96.44 | G6: =E6*F6 -> 4608.8676 | H6: 0 | I6: 0 | J6: =H6*I6 -> 0 | K6: =G6+J6 -> 4608.8676 | M6: =M5+K6-L6 -> 4608.8676
A7: 4 | B7: 45720 | G7: =E7*F7 -> 0 | H7: 0 | I7: 0 | J7: =H7*I7 -> 0 | K7: =G7+J7 -> 0 | L7: =+K7 -> 0 | M7: =M6+K7-L7 -> 4608.8676
A8: 5 | B8: 45721 | G8: =E8*F8 -> 0 | H8: 0 | I8: 0 | J8: =H8*I8 -> 0 | K8: =G8+J8 -> 0 | L8: =+K8 -> 0 | M8: =M7+K8-L8 -> 4608.8676
A9: 6 | B9: 45722 | G9: =E9*F9 -> 0 | H9: 0 | I9: 0 | J9: =H9*I9 -> 0 | K9: =G9+J9 -> 0 | L9: =+K9 -> 0 | M9: =M8+K9-L9 -> 4608.8676
A10: 7 | B10: 45723 | G10: =E10*F10 -> 0 | H10: 0 | I10: 0 | J10: =H10*I10 -> 0 | K10: =G10+J10 -> 0 | L10: =+K10 -> 0 | M10: =M9+K10-L10 -> 4608.8676
A11: 8 | B11: 45724 | G11: =E11*F11 -> 0 | H11: 0 | I11: 0 | J11: =H11*I11 -> 0 | K11: =G11+J11 -> 0 | L11: =+K11 -> 0 | M11: =M10+K11-L11 -> 4608.8676
A12: 9 | B12: 45725 | G12: =E12*F12 -> 0 | H12: 0 | I12: 0 | J12: =H12*I12 -> 0 | K12: =G12+J12 -> 0 | L12: =+K12 -> 0 | M12: =M11+K12-L12 -> 4608.8676
A13: 10 | B13: 45726 | G13: =E13*F13 -> 0 | H13: 0 | I13: 0 | J13: =H13*I13 -> 0 | K13: =G13+J13 -> 0 | L13: =+K13 -> 0 | M13: =M12+K13-L13 -> 4608.8676
A14: 11 | B14: 45727 | G14: =E14*F14 -> 0 | H14: 0 | I14: 0 | J14: =H14*I14 -> 0 | K14: =G14+J14 -> 0 | L14: =+K14 -> 0 | M14: =M13+K14-L14 -> 4608.8676
A15: 12 | B15: 45728 | G15: =E15*F15 -> 0 | H15: 0 | I15: 0 | J15: =H15*I15 -> 0 | K15: =G15+J15 -> 0 | L15: =+K15 -> 0 | M15: =M14+K15-L15 -> 4608.8676
A16: 13 | B16: 45729 | G16: =E16*F16 -> 0 | H16: 0 | I16: 0 | J16: =H16*I16 -> 0 | K16: =G16+J16 -> 0 | L16: =+K16 -> 0 | M16: =M15+K16-L16 -> 4608.8676
A17: 14 | B17: 45730 | E17: 258 | F17: 96.44 | G17: =E17*F17 -> 24881.52 | H17: 0 | I17: 0 | J17: =H17*I17 -> 0 | K17: =G17+J17 -> 24881.52 | L17: 0 | M17: =M16+K17-L17 -> 29490.388
A18: 15 | B18: 45731 | E18: 254.2 | F18: 96.44 | G18: =E18*F18 -> 24515.048 | H18: 9 | I18: 108.31 | J18: =H18*I18 -> 974.79 | K18: =G18+J18 -> 25489.838 | L18: 0 | M18: =M17+K18-L18 -> 54980.226
A19: 16 | B19: 45732 | E19: 320 | F19: 96.44 | G19: =E19*F19 -> 30860.8 | H19: 5 | I19: 108.31 | J19: =H19*I19 -> 541.55 | K19: =G19+J19 -> 31402.35 | M19: =M18+K19-L19 -> 86382.576
A20: 17 | B20: 45733 | E20: 14 | F20: 96.44 | G20: =E20*F20 -> 1350.16 | H20: 46.66 | I20: 108.31 | J20: =H20*I20 -> 5053.7446 | K20: =G20+J20 -> 6403.9046 | M20: =M19+K20-L20 -> 92786.48
A21: 18 | B21: 45734 | E21: 218.68 | F21: 96.44 | G21: =E21*F21 -> 21089.499 | H21: 10 | I21: 108.31 | J21: =H21*I21 -> 1083.1 | K21: =G21+J21 -> 22172.599 | L21: 0 | M21: =M20+K21-L21 -> 114959.08
A22: 19 | B22: 45735 | E22: 0 | F22: 0 | G22: =E22*F22 -> 0 | H22: 2 | I22: 108.31 | J22: =H22*I22 -> 216.62 | K22: =G22+J22 -> 216.62 | L22: 0 | M22: =M21+K22-L22 -> 115175.7
A23: 20 | B23: 45736 | E23: 400 | F23: 96.44 | G23: =E23*F23 -> 38576 | H23: 3 | I23: 108.31 | J23: =H23*I23 -> 324.93 | K23: =G23+J23 -> 38900.93 | L23: 0 | M23: =M22+K23-L23 -> 154076.63
A24: 21 | B24: 45737 | E24: 200 | F24: 96.44 | G24: =E24*F24 -> 19288 | H24: 13 | I24: 108.31 | J24: =H24*I24 -> 1408.03 | K24: =G24+J24 -> 20696.03 | L24: 0 | M24: =M23+K24-L24 -> 174772.66
A25: 22 | B25: 45738 | E25: 325.82 | F25: 96.44 | G25: =E25*F25 -> 31422.081 | H25: 3 | I25: 108.31 | J25: =H25*I25 -> 324.93 | K25: =G25+J25 -> 31747.011 | L25: 0 | M25: =M24+K25-L25 -> 206519.67
A26: 23 | B26: 45739 | E26: 111.32 | F26: 96.44 | G26: =E26*F26 -> 10735.701 | H26: 8 | I26: 108.31 | J26: =H26*I26 -> 866.48 | K26: =G26+J26 -> 11602.181 | L26: 0 | M26: =M25+K26-L26 -> 218121.85
A27: 24 | B27: 45740 | E27: 1105.21 | F27: 96.44 | G27: =E27*F27 -> 106586.45 | H27: 8 | I27: 108.31 | J27: =H27*I27 -> 866.48 | K27: =G27+J27 -> 107452.93 | L27: 100000 | M27: =M26+K27-L27 -> 225574.78
A28: 25 | B28: 45741 | E28: 885.32 | F28: 96.44 | G28: =E28*F28 -> 85380.261 | H28: 58.31 | I28: 108.31 | J28: =H28*I28 -> 6315.5561 | K28: =G28+J28 -> 91695.817 | L28: 0 | M28: =M27+K28-L28 -> 317270.6
A29: 26 | B29: 45742 | G29: =E29*F29 -> 0 | H29: 5 | I29: 108.31 | J29: =H29*I29 -> 541.55 | K29: =G29+J29 -> 541.55 | L29: 0 | M29: =M28+K29-L29 -> 317812.15
A30: 27 | B30: 45743 | E30: 207.38 | F30: 96.44 | G30: =E30*F30 -> 19999.727 | H30: 10 | I30: 108.31 | J30: =H30*I30 -> 1083.1 | K30: =G30+J30 -> 21082.827 | L30: 0 | M30: =M29+K30-L30 -> 338894.98
A31: 28 | B31: 45744 | E31: =400+34.11+34.83 -> 468.94 | F31: 96.44 | G31: =E31*F31 -> 45224.574 | H31: 5 | I31: 108.31 | J31: =H31*I31 -> 541.55 | K31: =G31+J31 -> 45766.124 | L31: 0 | M31: =M30+K31-L31 -> 384661.1
A32: 29 | B32: 45745 | E32: =81.6+31.43+5+95.35 -> 213.38 | F32: 96.44 | G32: =E32*F32 -> 20578.367 | H32: 0 | I32: 0 | J32: =H32*I32 -> 0 | K32: =G32+J32 -> 20578.367 | L32: 0 | M32: =M31+K32-L32 -> 405239.47
A33: 30 | B33: 45746 | E33: 1083.77 | F33: 96.44 | G33: =E33*F33 -> 104518.78 | H33: 15 | I33: 108.31 | J33: =H33*I33 -> 1624.65 | K33: =G33+J33 -> 106143.43 | L33: 200000 | M33: =M32+K33-L33 -> 311382.9
A34: 31 | B34: 45747 | E34: 131.89 | F34: 96.44 | G34: =E34*F34 -> 12719.472 | H34: 5 | I34: 108.31 | J34: =H34*I34 -> 541.55 | K34: =G34+J34 -> 13261.022 | L34: 0 | M34: =M33+K34-L34 -> 324643.92
E35: =SUM(E4:E34) -> 6245.7 | G35: =SUM(G4:G34) -> 602335.31 | H35: =SUM(H4:H34) -> 205.97 | J35: =SUM(J4:J34) -> 22308.611 | K35: =SUM(K4:K34) -> 624643.92 | L35: =SUM(L4:L34) -> 300000

Sheet Dindi
A1: Akarapu Balakistamma Fillling
A2: S.No | B2: Date | C2: GRN No | D2: Ind no/Bill No | E2: Diesel (Lts) | F2: Price | G2: Amount | H2: Petrol (Lts) | I2: Price | J2: Amount | K2: Total amount | L2: Amount paid | M2: As on Date | N2: Remarks
A3: Opening Balance | M3: 0
A4: 1 | B4: 45717 | G4: =E4*F4 -> 0 | H4: 0 | I4: 0 | J4: =H4*I4 -> 0 | K4: =G4+J4 -> 0 | L4: =+K4 -> 0 | M4: 0
A5: 2 | B5: 45718 | G5: =E5*F5 -> 0 | H5: 0 | I5: 0 | J5: =H5*I5 -> 0 | K5: =G5+J5 -> 0 | L5: =+K5 -> 0 | M5: 0
A6: 3 | B6: 45719 | G6: =E6*F6 -> 0 | H6: 0 | I6: 0 | J6: =H6*I6 -> 0 | K6: =G6+J6 -> 0 | L6: =+K6 -> 0 | M6: 0
A7: 4 | B7: 45720 | G7: =E7*F7 -> 0 | H7: 0 | I7: 0 | J7: =H7*I7 -> 0 | K7: =G7+J7 -> 0 | L7: =+K7 -> 0 | M7: 0
A8: 5 | B8: 45721 | G8: =E8*F8 -> 0 | H8: 0 | I8: 0 | J8: =H8*I8 -> 0 | K8: =G8+J8 -> 0 | L8: =+K8 -> 0 | M8: 0
A9: 6 | B9: 45722 | G9: =E9*F9 -> 0 | H9: 0 | I9: 0 | J9: =H9*I9 -> 0 | K9: =G9+J9 -> 0 | L9: =+K9 -> 0 | M9: 0
A10: 7 | B10: 45723 | G10: =E10*F10 -> 0 | H10: 0 | I10: 0 | J10: =H10*I10 -> 0 | K10: =G10+J10 -> 0 | L10: =+K10 -> 0 | M10: 0
A11: 8 | B11: 45724 | G11: =E11*F11 -> 0 | H11: 0 | I11: 0 | J11: =H11*I11 -> 0 | K11: =G11+J11 -> 0 | L11: =+K11 -> 0 | M11: 0
A12: 9 | B12: 45725 | G12: =E12*F12 -> 0 | H12: 0 | I12: 0 | J12: =H12*I12 -> 0 | K12: =G12+J12 -> 0 | L12: =+K12 -> 0 | M12: 0
A13: 10 | B13: 45726 | G13: =E13*F13 -> 0 | H13: 0 | I13: 0 | J13: =H13*I13 -> 0 | K13: =G13+J13 -> 0 | L13: =+K13 -> 0 | M13: 0
A14: 11 | B14: 45727 | G14: =E14*F14 -> 0 | H14: 0 | I14: 0 | J14: =H14*I14 -> 0 | K14: =G14+J14 -> 0 | L14: =+K14 -> 0 | M14: 0
A15: 12 | B15: 45728 | G15: =E15*F15 -> 0 | H15: 0 | I15: 0 | J15: =H15*I15 -> 0 | K15: =G15+J15 -> 0 | L15: =+K15 -> 0 | M15: 0
... A27: 24 | B27: 45740 | G27: =E27*F27 -> 0 | H27: 0 | I27: 0 | J27: =H27*I27 -> 0 | K27: =G27+J27 -> 0 | L27: =+K27 -> 0 | M27: 0
A28: 25 | B28: 45741 | H28: 0 | I28: 0 | J28: =H28*I28 -> 0 | K28: =G28+J28 -> 0 | L28: =+K28 -> 0 | M28: 0
A29: 26 | B29: 45742 | G29: =E29*F29 -> 0 | H29: 0 | I29: 0 | J29: =H29*I29 -> 0 | K29: =G29+J29 -> 0 | L29: =+K29 -> 0 | M29: 0
A30: 27 | B30: 45743 | G30: =E30*F30 -> 0 | H30: 0 | I30: 0 | J30: =H30*I30 -> 0 | K30: =G30+J30 -> 0 | L30: =+K30 -> 0 | M30: 0
A31: 28 | B31: 45744 | E31: 35.41 | F31: 96.08 | G31: =E31*F31 -> 3402.1928 | H31: 0 | I31: 0 | J31: =H31*I31 -> 0 | K31: =G31+J31 -> 3402.1928 | L31: =+K31 -> 3402.1928 | M31: 0
A32: 29 | G32: =E32*F32 -> 0 | H32: 0 | I32: 0 | J32: =H32*I32 -> 0 | K32: =G32+J32 -> 0 | L32: =+K32 -> 0 | M32: 0
A33: 30 | G33: =E33*F33 -> 0 | H33: 0 | I33: 0 | J33: =H33*I33 -> 0 | K33: =G33+J33 -> 0 | L33: =+K33 -> 0 | M33: 0
A34: 31 | G34: =E34*F34 -> 0 | H34: 0 | I34: 0 | J34: =H34*I34 -> 0 | K34: =G34+J34 -> 0 | L34: =+K34 -> 0 | M34: 0
E35: =SUM(E4:E34) -> 35.41 | G35: =SUM(G4:G34) -> 3402.1928 | H35: =SUM(H4:H34) -> 0 | J35: =SUM(J4:J34) -> 0 | K35: =SUM(K4:K34) -> 3402.1928 | L35: =SUM(L4:L34) -> 3402.1928

Sheet Amalapuram
A2: S.No | B2: Date | C2: GRN No | D2: Ind no/Bill No | E2: Diesel (Lts) | F2: Price | G2: Amount | H2: Petrol (Lts) | I2: Price | J2: Amount | K2: Total amount | L2: Amount paid | M2: As on Date | N2: Remarks
A3: Opening Balance | M3: 0
A4: 1 | G4: 0 | H4: 0 | I4: 0 | J4: 0 | K4: =G4+J4 -> 0 | M4: =+M3+K4-L4 -> 0
A5: 2 | G5: =E5*F5 -> 0 | H5: 0 | I5: 0 | J5: 0 | K5: =G5+J5 -> 0 | M5: =+M4+K5-L5 -> 0
A6: 3 | B6: 46084 | C6: Sri Venkateswara Enterprises | D6: Yanam | E6: 43 | F6: 86.75 | G6: 3730.25 | H6: 9.81 | I6: 96.91 | J6: 950.69 | K6: 4680.94 | L6: 4680.94 | M6: =+M5+K6-L6 -> 0 | N6: BPCL-207659
A7: 4 | C7: Sree Prasad Filling Station | D7: Tuni | E7: 41.19 | F7: 97.12 | G7: 4000.37 | H7: 0 | K7: 4000.37 | L7: 4000.37 | M7: =+M6+K7-L7 -> 0 | N7: IOCL-159657
A8: 5 | B8: 46090 | C8: BP-KAKINADA BHARAT PETROLEUM | D8: KAKINADA | E8: 46.57 | F8: 97.71 | G8: =E8*F8 -> 4550.3547 | H8: 5.12 | I8: 109.94 | J8: 563 | K8: =G8+J8 -> 5113.3547 | L8: 5113.3547 | M8: =+M7+K8-L8 -> 0
A9: 6 | C9: BP-LALLACHERUVU BHARAT PETROLEUM | D9: RAJAHMUNDRY | G9: =E9*F9 -> 0 | H9: 5 | I9: 108.86 | J9: 544.3 | K9: =G9+J9 -> 544.3 | L9: 544.3 | M9: =+M8+K9-L9 -> 0
A10: 7 | B10: 46091 | C10: BP-LALLACHERUVU BHARAT PETROLEUM | D10: RAJAHMUNDRY | G10: =E10*F10 -> 0 | H10: 5 | I10: 108.86 | J10: 544.3 | K10: =G10+J10 -> 544.3 | L10: 544.3 | M10: =+M9+K10-L10 -> 0
A11: 8 | B11: 46092 | C11: JVVR Filling Station BPCL | D11: Gollaprolu | E11: 50.49 | F11: 97.47 | G11: 4921.26 | H11: 0 | K11: 4921.26 | L11: 4921.26 | M11: =+M10+K11-L11 -> 0
A12: 9 | B12: 46094 | C12: APSRTC Petrol Bunk (Rangampeta) | D12: Peddapuram | E12: 42.28 | F12: 96.67 | G12: 4087.21 | H12: 0 | K12: 4087.21 | L12: 4087.21 | M12: =+M11+K12-L12 -> 0
A13: 10 | B13: 46095 | C13: Vishnu Filling Station | D13: Kakinada | E13: 0 | H13: 5 | I13: 109.94 | J13: 549.7 | K13: 549.7 | L13: 549.7 | M13: =+M12+K13-L13 -> 0
A14: 11 | B14: 46096 | C14: BP Kakinada Bhanugudi Junction | D14: Kakinada | E14: 0 | H14: 5 | I14: 109.94 | J14: 550 | K14: 550 | L14: 550 | M14: =+M13+K14-L14 -> 0
A15: 12 | B15: 46099 | C15: BP Kakinada Bhanugudi Junction | D15: Kakinada | E15: 43.76 | F15: 97.91 | G15: 4284.54 | H15: 5 | I15: 109.94 | J15: 549.7 | K15: 4834.24 | L15: 4834.24 | M15: =+M14+K15-L15 -> 0
A16: 13 | B16: 46100 | C16: BP Lalacheruvu | D16: Rajahmundry | E16: 0 | H16: 5 | I16: 108.86 | J16: 544.3 | K16: 544.3 | L16: 544.3 | M16: =+M15+K16-L16 -> 0
A17: 14 | B17: 46103 | C17: BP Lalacheruvu | D17: Rajahmundry | E17: 0 | H17: 5 | I17: 108.86 | J17: 544.3 | K17: 544.3 | L17: 544.3 | M17: =+M16+K17-L17 -> 0
A18: 15 | B18: 46104 | C18: BP Rajanagaram | D18: Rajanagaram(Peddapuram) | E18: 36.23 | F18: 96.63 | G18: 3500.9 | H18: 0 | K18: 3500.9 | L18: 3500.9 | M18: =+M16+K18-L18 -> 0
A19: 16 | B19: 46104 | C19: BP Lalacheruvu | D19: Rajahmundry | E19: 0 | H19: 5 | I19: 108.86 | J19: 544.3 | K19: 544.3 | L19: 544.3 | M19: =+M18+K19-L19 -> 0
A20: 17 | B20: 46105 | C20: BP Lalacheruvu | D20: Rajahmundry | E20: 0 | H20: 3 | I20: 108.86 | J20: 326.58 | K20: 326.58 | L20: 326.58 | M20: =+M19+K20-L20 -> 0
A21: 18 | B21: 46106 | C21: Sri Balaji Agencies BPCL | D21: Kakinada | E21: 0 | H21: 5 | I21: 109.94 | J21: 549.7 | K21: 549.7 | L21: 549.7 | M21: =+M20+K21-L21 -> 0
A22: 19 | B22: 46109 | C22: BP Lalacheruvu | D22: Rajahmundry | E22: 0 | H22: 10 | I22: 108.86 | J22: 1088.6 | K22: 1088.6 | L22: 1088.6 | M22: =+M21+K22-L22 -> 0 | N22: BPCL-207660
A23: 20 | B23: 46109 | C23: Bhaskara Agencies IOCL | D23: Rajahmundry | E23: 51.7 | F23: 96.71 | G23: 5000 | H23: 0 | K23: 5000 | L23: 5000 | M23: =+M22+K23-L23 -> 0 | N23: IOCL-159657
A24: 21 | B24: 46110 | C24: Sri Balaji Agencies BPCL | D24: Kakinada | E24: 45.36 | F24: 97.71 | G24: 4432.13 | H24: 0 | I24: 109.94 | J24: 0 | K24: 4432.13 | L24: 4432.13 | M24: =+M23+K24-L24 -> 0
A25: 22 | B25: 46110 | C25: Vishnu Filling Station | D25: Kakinada | E25: 0 | H25: 5 | I25: 109.94 | J25: 549.7 | K25: 549.7 | L25: 549.7 | M25: =+M24+K25-L25 -> 0
A26: 23 | B26: 46111 | C26: Sri Balaji Agencies BPCL | D26: Kakinada | E26: 45.36 | F26: 97.71 | G26: 4432.13 | H26: 0 | I26: 109.94 | J26: 0 | K26: 4432.13 | L26: 4432.13 | M26: =+M25+K26-L26 -> 0
A27: 24 | B27: 46111 | C27: Vishnu Filling Station | D27: Kakinada | E27: 0 | H27: 5 | I27: 109.94 | J27: 549.7 | K27: 549.7 | L27: 549.7 | M27: =+M26+K27-L27 -> 0
A28: 25 | B28: 46112 | C28: BP Chakradwarabandam | D28: Rajahmundry | E28: 45.91 | F28: 96.66 | G28: 4437.66 | H28: 0 | K28: 4437.66 | L28: 4437.66 | M28: =+M27+K28-L28 -> 0
A29: 26 | M29: =+M28+K29-L29 -> 0
A30: 27 | M30: =+M29+K30-L30 -> 0
A31: 28 | M31: =+M30+K31-L31 -> 0
A32: 29 | M32: =+M31+K32-L32 -> 0
A33: 30 | M33: =+M32+K33-L33 -> 0
A34: 30 | M34: =+M33+K34-L34 -> 0
A35: 31 | M35: =+M34+K35-L35 -> 0
A36: 32 | I36: 0 | J36: =H36*I36 -> 0 | K36: =G36+J36 -> 0 | M36: =+M35+K36-L36 -> 0
A37: 33 | G37: =E37*F37 -> 0 | H37: 0 | I37: 0 | J37: =H37*I37 -> 0 | K37: =G37+J37 -> 0 | M37: =+M36+K37-L37 -> 0
E38: =SUM(E4:E37) -> 491.85 | G38: =SUM(G4:G37) -> 47376.805 | H38: =SUM(H4:H37) -> 82.93 | J38: =SUM(J4:J37) -> 8948.87 | K38: =SUM(K4:K37) -> 56325.675 | L38: =SUM(L4:L37) -> 56325.675

Sheet Madana palli
A2: S.No | B2: Date | C2: GRN No | D2: Ind no/Bill No | E2: Diesel (Lts) | F2: Price | G2: Amount | H2: Petrol (Lts) | I2: Price | J2: Amount | K2: Total amount | L2: Amount paid | M2: As on Date | N2: Remarks
A3: Opening Balance | M3: 0
A4: 1 | B4: 46082 | G4: =E4*F4 -> 0 | H4: 0 | I4: 0 | J4: =H4*I4 -> 0 | K4: =G4+J4 -> 0 | L4: =+K4 -> 0 | M4: 0
A5: 2 | B5: 46083 | E5: 30.78 | F5: 97.43 | G5: =E5*F5 -> 2998.8954 | H5: 6.38 | I5: 109.62 | J5: =H5*I5 -> 699.3756 | K5: =G5+J5 -> 3698.271 | L5: =+K5 -> 3698.271 | M5: 0 | N5: IOCL
A6: 3 | B6: 46084 | G6: =E6*F6 -> 0 | H6: 0 | I6: 0 | J6: =H6*I6 -> 0 | K6: =G6+J6 -> 0 | L6: =+K6 -> 0 | M6: 0
A7: 4 | B7: 46085 | G7: =E7*F7 -> 0 | H7: 0 | I7: 0 | J7: =H7*I7 -> 0 | K7: =G7+J7 -> 0 | L7: =+K7 -> 0 | M7: 0
A8: 5 | B8: 46086 | G8: =E8*F8 -> 0 | H8: 0 | I8: 0 | J8: =H8*I8 -> 0 | K8: =G8+J8 -> 0 | L8: =+K8 -> 0 | M8: 0
A9: 6 | B9: 46087 | E9: 200 | F9: 97.79 | G9: =E9*F9 -> 19558 | H9: 0 | I9: 0 | J9: =H9*I9 -> 0 | K9: =G9+J9 -> 19558 | L9: =+K9 -> 19558 | M9: 0 | N9: HPCL
A10: 7 | B10: 46088 | G10: =E10*F10 -> 0 | H10: 5.47 | I10: 109.62 | J10: =H10*I10 -> 599.6214 | K10: =G10+J10 -> 599.6214 | L10: =+K10 -> 599.6214 | M10: 0 | O10: 169.99
A11: 8 | B11: 46089 | G11: =E11*F11 -> 0 | H11: 0 | I11: 0 | J11: =H11*I11 -> 0 | K11: =G11+J11 -> 0 | L11: =+K11 -> 0 | M11: 0 | O11: 80
A12: 9 | B12: 46090 | G12: =E12*F12 -> 0 | H12: 0 | I12: 0 | J12: =H12*I12 -> 0 | K12: =G12+J12 -> 0 | L12: =+K12 -> 0 | M12: 0 | O12: =SUM(O10:O11) -> 249.99 | P12: 97.76 | Q12: =O12*P12 -> 24439.022
A13: 10 | B13: 46091 | G13: =E13*F13 -> 0 | H13: 0 | I13: 0 | J13: =H13*I13 -> 0 | K13: =G13+J13 -> 0 | L13: =+K13 -> 0 | M13: 0
A14: 11 | B14: 46092 | G14: =E14*F14 -> 0 | H14: 0 | I14: 0 | J14: =H14*I14 -> 0 | K14: =G14+J14 -> 0 | L14: =+K14 -> 0 | M14: 0
A15: 12 | B15: 46093 | G15: =E15*F15 -> 0 | H15: 0 | I15: 0 | J15: =H15*I15 -> 0 | K15: =G15+J15 -> 0 | L15: =+K15 -> 0 | M15: 0 | P15: 7820.8
A16: 13 | B16: 46094 | G16: =E16*F16 -> 0 | H16: 0 | I16: 0 | J16: =H16*I16 -> 0 | K16: =G16+J16 -> 0 | L16: =+K16 -> 0 | M16: 0 | P16: 16619.2
A17: 14 | B17: 46095 | G17: =E17*F17 -> 0 | H17: 0 | I17: 0 | J17: =H17*I17 -> 0 | K17: =G17+J17 -> 0 | L17: =+K17 -> 0 | M17: 0 | P17: =SUM(P15:P16) -> 24440
A18: 15 | B18: 46096 | G18: =E18*F18 -> 0 | H18: 0 | I18: 0 | J18: =H18*I18 -> 0 | K18: =G18+J18 -> 0 | L18: =+K18 -> 0 | M18: 0
A19: 16 | B19: 46097 | G19: =E19*F19 -> 0 | H19: 5.47 | I19: 109.62 | J19: =H19*I19 -> 599.6214 | K19: =G19+J19 -> 599.6214 | L19: =+K19 -> 599.6214 | M19: 0
A20: 17 | B20: 46098 | G20: =E20*F20 -> 0 | H20: 0 | I20: 0 | J20: =H20*I20 -> 0 | K20: =G20+J20 -> 0 | L20: =+K20 -> 0 | M20: 0
A21: 18 | B21: 46099 | G21: =E21*F21 -> 0 | H21: 0 | I21: 0 | J21: =H21*I21 -> 0 | K21: =G21+J21 -> 0 | L21: =+K21 -> 0 | M21: 0
A22: 19 | B22: 46100 | G22: =E22*F22 -> 0 | H22: 0 | I22: 0 | J22: =H22*I22 -> 0 | K22: =G22+J22 -> 0 | L22: =+K22 -> 0 | M22: 0
A23: 20 | B23: 46101 | G23: =E23*F23 -> 0 | H23: 0 | I23: 0 | J23: =H23*I23 -> 0 | K23: =G23+J23 -> 0 | L23: =+K23 -> 0 | M23: 0
A24: 21 | B24: 46102 | G24: =E24*F24 -> 0 | H24: 0 | I24: 0 | J24: =H24*I24 -> 0 | K24: =G24+J24 -> 0 | L24: =+K24 -> 0 | M24: 0
A25: 22 | B25: 46103 | G25: =E25*F25 -> 0 | H25: 0 | I25: 0 | J25: =H25*I25 -> 0 | K25: =G25+J25 -> 0 | L25: =+K25 -> 0 | M25: 0
A26: 23 | B26: 46104 | G26: =E26*F26 -> 0 | H26: 0 | I26: 0 | J26: =H26*I26 -> 0 | K26: =G26+J26 -> 0 | L26: =+K26 -> 0 | M26: 0
A27: 24 | B27: 46105 | G27: =E27*F27 -> 0 | H27: 0 | I27: 0 | J27: =H27*I27 -> 0 | K27: =G27+J27 -> 0 | L27: =+K27 -> 0 | M27: 0
A28: 25 | B28: 46106 | E28: 200 | F28: 97.79 | G28: =E28*F28 -> 19558 | H28: 0 | I28: 0 | J28: =H28*I28 -> 0 | K28: =G28+J28 -> 19558 | L28: =+K28 -> 19558 | M28: 0
B29: 46106 | H29: 3.65 | I29: 109.62 | J29: =H29*I29 -> 400.113 | K29: =G29+J29 -> 400.113 | L29: =+K29 -> 400.113
A30: 26 | B30: 46107 | G30: =E30*F30 -> 0 | H30: 0 | I30: 0 | J30: =H30*I30 -> 0 | K30: =G30+J30 -> 0 | L30: =+K30 -> 0 | M30: 0
A31: 27 | B31: 46108 | G31: =E31*F31 -> 0 | H31: 0 | I31: 0 | J31: =H31*I31 -> 0 | K31: =G31+J31 -> 0 | L31: =+K31 -> 0 | M31: 0
A32: 28 | B32: 46109 | G32: =E32*F32 -> 0 | H32: 0 | I32: 0 | J32: =H32*I32 -> 0 | K32: =G32+J32 -> 0 | L32: =+K32 -> 0 | M32: 0
A33: 29 | G33: =E33*F33 -> 0 | H33: 0 | I33: 0 | J33: =H33*I33 -> 0 | K33: =G33+J33 -> 0 | L33: =+K33 -> 0 | M33: 0
A34: 30 | G34: =E34*F34 -> 0 | H34: 0 | I34: 0 | J34: =H34*I34 -> 0 | K34: =G34+J34 -> 0 | L34: =+K34 -> 0 | M34: 0
A35: 31 | G35: =E35*F35 -> 0 | H35: 0 | I35: 0 | J35: =H35*I35 -> 0 | K35: =G35+J35 -> 0 | L35: =+K35 -> 0 | M35: 0
E36: =SUM(E4:E35) -> 430.78 | G36: =SUM(G4:G35) -> 42114.895 | H36: =SUM(H4:H35) -> 20.97 | J36: =SUM(J4:J35) -> 2298.7314 | K36: =SUM(K4:K35) -> 44413.627 | L36: =SUM(L4:L35) -> 44413.627

Sheet Kadur
A1: Vishal Service Station
A2: S.No | B2: Date | C2: GRN No | D2: Ind No/Bill No | E2: Diesel (Lts) | F2: Price | G2: Amount | H2: Petrol (Lts) | I2: Price | J2: Amount | K2: Total amount | L2: Amount paid | M2: As on Date | N2: Remarks
A3: Opening Balance | K3: 240937.03 | M3: 240937.03 | O3: 207239.43
A4: 1 | B4: 45717 | F4: 0 | G4: =E4*F4 -> 0 | H4: 0 | I4: 0 | J4: =H4*I4 -> 0 | K4: =G4+J4 -> 0 | M4: =M3+K4-L4 -> 240937.03
A5: 2 | B5: 45718 | F5: 0 | G5: =E5*F5 -> 0 | H5: 0 | I5: 0 | J5: =H5*I5 -> 0 | K5: =G5+J5 -> 0 | M5: =M4+K5-L5 -> 240937.03
A6: 3 | B6: 45719 | F6: 0 | G6: =E6*F6 -> 0 | H6: 0 | I6: 0 | J6: =H6*I6 -> 0 | K6: =G6+J6 -> 0 | M6: =M5+K6-L6 -> 240937.03
A7: 4 | B7: 45720 | F7: 0 | G7: =E7*F7 -> 0 | H7: 0 | I7: 0 | J7: =H7*I7 -> 0 | K7: =G7+J7 -> 0 | M7: =M6+K7-L7 -> 240937.03
A8: 5 | B8: 45721 | F8: 0 | G8: =E8*F8 -> 0 | H8: 0 | I8: 0 | J8: =H8*I8 -> 0 | K8: =G8+J8 -> 0 | M8: =M7+K8-L8 -> 240937.03
A9: 6 | B9: 45722 | E9: 1600 | F9: 92.15 | G9: =E9*F9 -> 147440 | H9: 0 | I9: 0 | J9: =H9*I9 -> 0 | K9: =G9+J9 -> 147440 | M9: =M8+K9-L9 -> 388377.03
A10: 7 | B10: 45723 | F10: 0 | G10: =E10*F10 -> 0 | H10: 0 | I10: 0 | J10: =H10*I10 -> 0 | K10: =G10+J10 -> 0 | M10: =M9+K10-L10 -> 388377.03
A11: 8 | B11: 45724 | F11: 0 | G11: =E11*F11 -> 0 | H11: 0 | I11: 0 | J11: =H11*I11 -> 0 | K11: =G11+J11 -> 0 | M11: =M10+K11-L11 -> 388377.03
A12: 9 | B12: 45725 | F12: 0 | G12: =E12*F12 -> 0 | H12: 0 | I12: 0 | J12: =H12*I12 -> 0 | K12: =G12+J12 -> 0 | M12: =M11+K12-L12 -> 388377.03
A13: 10 | B13: 45726 | F13: 0 | G13: =E13*F13 -> 0 | H13: 0 | I13: 0 | J13: =H13*I13 -> 0 | K13: =G13+J13 -> 0 | M13: =M12+K13-L13 -> 388377.03
A14: 11 | B14: 45727 | F14: 0 | G14: =E14*F14 -> 0 | H14: 0 | I14: 0 | J14: =H14*I14 -> 0 | K14: =G14+J14 -> 0 | M14: =M13+K14-L14 -> 388377.03
A15: 12 | B15: 45728 | F15: 0 | G15: =E15*F15 -> 0 | H15: 0 | I15: 0 | J15: =H15*I15 -> 0 | K15: =G15+J15 -> 0 | M15: =M14+K15-L15 -> 388377.03
A16: 13 | B16: 45729 | F16: 0 | G16: =E16*F16 -> 0 | H16: 0 | I16: 0 | J16: =H16*I16 -> 0 | K16: =G16+J16 -> 0 | M16: =M15+K16-L16 -> 388377.03
A17: 14 | B17: 45730 | F17: 0 | G17: =E17*F17 -> 0 | H17: 0 | I17: 0 | J17: =H17*I17 -> 0 | K17: =G17+J17 -> 0 | M17: =M16+K17-L17 -> 388377.03
A18: 15 | B18: 45731 | F18: 0 | G18: =E18*F18 -> 0 | H18: 0 | I18: 0 | J18: =H18*I18 -> 0 | K18: =G18+J18 -> 0 | M18: =M17+K18-L18 -> 388377.03
A19: 16 | B19: 45732 | F19: 0 | G19: =E19*F19 -> 0 | H19: 0 | I19: 0 | J19: =H19*I19 -> 0 | K19: =G19+J19 -> 0 | M19: =M18+K19-L19 -> 388377.03
A20: 17 | B20: 45733 | F20: 0 | G20: =E20*F20 -> 0 | H20: 140 | I20: 104.24 | J20: =H20*I20 -> 14593.6 | K20: =G20+J20 -> 14593.6 | L20: 300000 | M20: =M19+K20-L20 -> 102970.63
A21: 18 | B21: 45734 | F21: 0 | G21: =E21*F21 -> 0 | H21: 0 | I21: 0 | J21: =H21*I21 -> 0 | K21: =G21+J21 -> 0 | M21: =M20+K21-L21 -> 102970.63
A22: 19 | B22: 45735 | F22: 0 | H22: 0 | I22: 0 | J22: =H22*I22 -> 0 | K22: =G22+J22 -> 0 | M22: =M21+K22-L22 -> 102970.63
A23: 20 | B23: 45736 | F23: 0 | J23: =H23*I23 -> 0 | K23: =G23+J23 -> 0 | M23: =M22+K23-L23 -> 102970.63
A24: 21 | B24: 45737 | F24: 0 | J24: =H24*I24 -> 0 | K24: =G24+J24 -> 0 | M24: =M23+K24-L24 -> 102970.63
A25: 22 | B25: 45738 | F25: 0 | J25: =H25*I25 -> 0 | K25: =G25+J25 -> 0 | M25: =M24+K25-L25 -> 102970.63
A26: 23 | B26: 45739 | F26: 0 | J26: =H26*I26 -> 0 | K26: =G26+J26 -> 0 | M26: =M25+K26-L26 -> 102970.63
A27: 24 | B27: 45740 | F27: 0 | J27: =H27*I27 -> 0 | K27: =G27+J27 -> 0 | M27: =M26+K27-L27 -> 102970.63
A28: 25 | B28: 45741 | F28: 0 | J28: =H28*I28 -> 0 | K28: =G28+J28 -> 0 | M28: =M27+K28-L28 -> 102970.63
A29: 26 | B29: 45742 | F29: 0 | J29: =H29*I29 -> 0 | K29: =G29+J29 -> 0 | M29: =M28+K29-L29 -> 102970.63
A30: 27 | B30: 45743 | F30: 0 | J30: =H30*I30 -> 0 | K30: =G30+J30 -> 0 | M30: =M29+K30-L30 -> 102970.63
A31: 28 | B31: 45744 | F31: 0 | J31: =H31*I31 -> 0 | K31: =G31+J31 -> 0 | M31: =M30+K31-L31 -> 102970.63
A32: 29 | B32: 45745 | F32: 0 | G32: =E32*F32 -> 0 | H32: 0 | I32: 0 | J32: =H32*I32 -> 0 | K32: =G32+J32 -> 0 | M32: =M31+K32-L32 -> 102970.63
A33: 30 | B33: 45746 | F33: 0 | G33: =E33*F33 -> 0 | H33: 0 | I33: 0 | J33: =H33*I33 -> 0 | K33: =G33+J33 -> 0 | M33: =M32+K33-L33 -> 102970.63
A34: 31 | B34: 45747 | F34: 0 | G34: =E34*F34 -> 0 | J34: =H34*I34 -> 0 | K34: =G34+J34 -> 0
E35: =SUM(E4:E34) -> 1600 | G35: =SUM(G4:G34) -> 147440 | H35: =SUM(H4:H34) -> 140 | J35: =SUM(J4:J34) -> 14593.6 | K35: =SUM(K4:K34) -> 162033.6 | L35: =SUM(L4:L31) -> 300000

Sheet YG Gudda-2
A1: Pankaja HP Fuel Center
A2: S.No | B2: Date | C2: GRN No | D2: Ind No/Bill No | E2: Diesel (Lts) | F2: Price | G2: Amount | H2: Petrol (Lts) | I2: Price | J2: Amount | K2: Total amount | L2: Amount paid | M2: As on Date | N2: Remarks
A3: Opening Balance | K3: 531383.8 | M3: 531383.8
A4: 1 | B4: 46082 | G4: =E4*F4 -> 0 | J4: =H4*I4 -> 0 | K4: =G4+J4 -> 0 | M4: =M3+K4-L4 -> 531383.8
A5: 2 | B5: 46083 | G5: =E5*F5 -> 0 | J5: =H5*I5 -> 0 | K5: =G5+J5 -> 0 | M5: =M4+K5-L5 -> 531383.8
A6: 3 | B6: 46084 | G6: =E6*F6 -> 0 | J6: =H6*I6 -> 0 | K6: =G6+J6 -> 0 | M6: =M5+K6-L6 -> 531383.8
A7: 4 | B7: 46085 | G7: =E7*F7 -> 0 | J7: =H7*I7 -> 0 | K7: =G7+J7 -> 0 | M7: =M6+K7-L7 -> 531383.8
A8: 5 | B8: 46086 | G8: =E8*F8 -> 0 | J8: =H8*I8 -> 0 | K8: =G8+J8 -> 0 | M8: =M7+K8-L8 -> 531383.8
A9: 6 | B9: 46087 | E9: 1200 | F9: 91.33 | G9: =E9*F9 -> 109596 | H9: 35 | I9: 103.27 | J9: =H9*I9 -> 3614.45 | K9: =G9+J9 -> 113210.45 | M9: =M8+K9-L9 -> 644594.25
A10: 7 | B10: 46088 | G10: =E10*F10 -> 0 | J10: =H10*I10 -> 0 | K10: =G10+J10 -> 0 | M10: =M9+K10-L10 -> 644594.25
A11: 8 | B11: 46089 | G11: =E11*F11 -> 0 | J11: =H11*I11 -> 0 | K11: =G11+J11 -> 0 | M11: =M10+K11-L11 -> 644594.25
A12: 9 | B12: 46090 | E12: 1000 | F12: 91.33 | G12: =E12*F12 -> 91330 | H12: 35 | I12: 103.27 | J12: =H12*I12 -> 3614.45 | K12: =G12+J12 -> 94944.45 | M12: =M11+K12-L12 -> 739538.7
A13: 10 | B13: 46091 | G13: =E13*F13 -> 0 | J13: =H13*I13 -> 0 | K13: =G13+J13 -> 0 | M13: =M12+K13-L13 -> 739538.7
A14: 11 | B14: 46092 | E14: 437.97 | F14: 91.33 | G14: =E14*F14 -> 39999.8 | J14: =H14*I14 -> 0 | K14: =G14+J14 -> 39999.8 | L14: 39999.8 | M14: =M13+K14-L14 -> 739538.7
A15: 12 | B15: 46093 | E15: 1094.93 | F15: 91.33 | G15: =E15*F15 -> 99999.957 | J15: =H15*I15 -> 0 | K15: =G15+J15 -> 99999.957 | L15: 800000 | M15: =M14+K15-L15 -> 39538.66
A16: 13 | B16: 46094 | G16: =E16*F16 -> 0 | J16: =H16*I16 -> 0 | K16: =G16+J16 -> 0 | M16: =M15+K16-L16 -> 39538.66
A17: 14 | B17: 46095 | E17: 1500 | F17: 91.33 | G17: =E17*F17 -> 136995 | H17: 70 | I17: 103.27 | J17: =H17*I17 -> 7228.9 | K17: =G17+J17 -> 144223.9 | M17: =M16+K17-L17 -> 183762.56
A18: 15 | B18: 46096 | G18: =E18*F18 -> 0 | J18: =H18*I18 -> 0 | K18: =G18+J18 -> 0 | M18: =M17+K18-L18 -> 183762.56
A19: 16 | B19: 46097 | G19: =E19*F19 -> 0 | J19: =H19*I19 -> 0 | K19: =G19+J19 -> 0 | M19: =M18+K19-L19 -> 183762.56
A20: 17 | B20: 46098 | G20: =E20*F20 -> 0 | J20: =H20*I20 -> 0 | K20: =G20+J20 -> 0 | M20: =M19+K20-L20 -> 183762.56
A21: 18 | B21: 46099 | G21: =E21*F21 -> 0 | J21: =H21*I21 -> 0 | K21: =G21+J21 -> 0 | M21: =M20+K21-L21 -> 183762.56
A22: 19 | B22: 46100 | G22: =E22*F22 -> 0 | J22: =H22*I22 -> 0 | K22: =G22+J22 -> 0 | M22: =M21+K22-L22 -> 183762.56
A23: 20 | B23: 46101 | E23: 1000 | F23: 91.33 | G23: =E23*F23 -> 91330 | H23: 35 | I23: 103.27 | J23: =H23*I23 -> 3614.45 | K23: =G23+J23 -> 94944.45 | M23: =M22+K23-L23 -> 278707.01
A24: 21 | B24: 46102 | G24: =E24*F24 -> 0 | J24: =H24*I24 -> 0 | K24: =G24+J24 -> 0 | M24: =M23+K24-L24 -> 278707.01
A25: 22 | B25: 46103 | G25: =E25*F25 -> 0 | J25: =H25*I25 -> 0 | K25: =G25+J25 -> 0 | M25: =M24+K25-L25 -> 278707.01
A26: 23 | B26: 46104 | G26: =E26*F26 -> 0 | J26: =H26*I26 -> 0 | K26: =G26+J26 -> 0 | M26: =M25+K26-L26 -> 278707.01
A27: 24 | B27: 46105 | G27: =E27*F27 -> 0 | J27: =H27*I27 -> 0 | K27: =G27+J27 -> 0 | M27: =M26+K27-L27 -> 278707.01
A28: 25 | B28: 46106 | E28: 1200 | F28: 91.33 | G28: =E28*F28 -> 109596 | H28: 35 | I28: 103.27 | J28: =H28*I28 -> 3614.45 | K28: =G28+J28 -> 113210.45 | M28: =M27+K28-L28 -> 391917.46
A29: 26 | B29: 46106 | E29: 459.87 | F29: 91.33 | G29: =E29*F29 -> 41999.927 | J29: =H29*I29 -> 0 | K29: =G29+J29 -> 41999.927 | L29: =H29+K29 -> 41999.927 | M29: =M28+K29-L29 -> 391917.46
A30: 27 | B30: 46107 | G30: =E30*F30 -> 0 | J30: =H30*I30 -> 0 | K30: =G30+J30 -> 0 | M30: =M29+K30-L30 -> 391917.46
A31: 28 | B31: 46108 | G31: =E31*F31 -> 0 | J31: =H31*I31 -> 0 | K31: =G31+J31 -> 0 | M31: =M30+K31-L31 -> 391917.46
A32: 29 | B32: 46109 | G32: =E32*F32 -> 0 | J32: =H32*I32 -> 0 | K32: =G32+J32 -> 0 | M32: =M31+K32-L32 -> 391917.46
A33: 30 | B33: 46110 | G33: =E33*F33 -> 0 | J33: =H33*I33 -> 0 | K33: =G33+J33 -> 0 | M33: =M32+K33-L33 -> 391917.46
A34: 31 | B34: 46111 | G34: =E34*F34 -> 0 | J34: =H34*I34 -> 0 | K34: =G34+J34 -> 0 | L34: 200000 | M34: =M33+K34-L34 -> 191917.46
A35: 32 | B35: 46112 | E35: 600 | F35: 91.33 | G35: =E35*F35 -> 54798 | H35: 35 | I35: 103.27 | J35: =H35*I35 -> 3614.45 | K35: =G35+J35 -> 58412.45 | M35: =M34+K35-L35 -> 250329.91
A36: 33 | G36: =E36*F36 -> 0 | H36: 0 | I36: 0 | J36: =H36*I36 -> 0 | K36: =G36+J36 -> 0 | M36: =M35+K36-L36 -> 250329.91
E37: =SUM(E4:E36) -> 8492.77 | G37: =SUM(G4:G36) -> 775644.68 | H37: =SUM(H4:H36) -> 245 | J37: =SUM(J4:J36) -> 25301.15 | K37: =SUM(K4:K36) -> 800945.83 | L37: =SUM(L4:L36) -> 1081999.7

Sheet Hosadurga -2
A1: Shree Veeraprathap Fuel
A2: S.No | B2: Date | C2: GRN No | D2: Ind No/Bill No | E2: Diesel (Lts) | F2: Price | G2: Amount | H2: Petrol (Lts) | I2: Price | J2: Amount | K2: Total amount | L2: Amount paid | M2: As on Date | N2: Remarks
A3: Opening Balance | K3: 197359.4 | M3: 197359.4
A4: 1 | B4: 46082 | C4: 0 | G4: =E4*F4 -> 0 | J4: =H4*I4 -> 0 | K4: =G4+J4 -> 0 | M4: =M3+K4-L4 -> 197359.4
A5: 2 | B5: 46083 | C5: 0 | G5: =E5*F5 -> 0 | J5: =H5*I5 -> 0 | K5: =G5+J5 -> 0 | M5: =M4+K5-L5 -> 197359.4
A6: 3 | B6: 46084 | C6: 0 | G6: =E6*F6 -> 0 | J6: =H6*I6 -> 0 | K6: =G6+J6 -> 0 | M6: =M5+K6-L6 -> 197359.4
A7: 4 | B7: 46085 | C7: 0 | G7: =E7*F7 -> 0 | J7: =H7*I7 -> 0 | K7: =G7+J7 -> 0 | M7: =M6+K7-L7 -> 197359.4
A8: 5 | B8: 46086 | C8: 0 | G8: =E8*F8 -> 0 | J8: =H8*I8 -> 0 | K8: =G8+J8 -> 0 | M8: =M7+K8-L8 -> 197359.4
A9: 6 | B9: 46087 | C9: 0 | E9: 1400 | F9: 91.55 | G9: =E9*F9 -> 128170 | H9: 70 | I9: 103.73 | J9: =H9*I9 -> 7261.1 | K9: =G9+J9 -> 135431.1 | M9: =M8+K9-L9 -> 332790.5
A10: 7 | B10: 46088 | C10: 0 | G10: =E10*F10 -> 0 | J10: =H10*I10 -> 0 | K10: =G10+J10 -> 0 | M10: =M9+K10-L10 -> 332790.5
A11: 8 | B11: 46089 | C11: 0 | G11: =E11*F11 -> 0 | J11: =H11*I11 -> 0 | K11: =G11+J11 -> 0 | M11: =M10+K11-L11 -> 332790.5
A12: 9 | B12: 46090 | C12: 0 | G12: =E12*F12 -> 0 | J12: =H12*I12 -> 0 | K12: =G12+J12 -> 0 | M12: =M11+K12-L12 -> 332790.5
A13: 10 | B13: 46091 | C13: 0 | G13: =E13*F13 -> 0 | J13: =H13*I13 -> 0 | K13: =G13+J13 -> 0 | M13: =M12+K13-L13 -> 332790.5
A14: 11 | B14: 46092 | C14: 0 | G14: =E14*F14 -> 0 | J14: =H14*I14 -> 0 | K14: =G14+J14 -> 0 | M14: =M13+K14-L14 -> 332790.5
A15: 12 | B15: 46093 | C15: 0 | G15: =E15*F15 -> 0 | J15: =H15*I15 -> 0 | K15: =G15+J15 -> 0 | M15: =M14+K15-L15 -> 332790.5
A16: 13 | B16: 46094 | C16: 0 | G16: =E16*F16 -> 0 | J16: =H16*I16 -> 0 | K16: =G16+J16 -> 0 | L16: 200000 | M16: =M15+K16-L16 -> 132790.5
A17: 14 | B17: 46095 | C17: 0 | E17: 1800 | F17: 91.55 | G17: =E17*F17 -> 164790 | H17: 70 | I17: 103.73 | J17: =H17*I17 -> 7261.1 | K17: =G17+J17 -> 172051.1 | M17: =M16+K17-L17 -> 304841.6
A18: 15 | B18: 46096 | C18: 0 | G18: =E18*F18 -> 0 | J18: =H18*I18 -> 0 | K18: =G18+J18 -> 0 | M18: =M17+K18-L18 -> 304841.6
A19: 16 | B19: 46097 | C19: 0 | G19: =E19*F19 -> 0 | J19: =H19*I19 -> 0 | K19: =G19+J19 -> 0 | M19: =M18+K19-L19 -> 304841.6
A20: 17 | B20: 46098 | C20: 0 | G20: =E20*F20 -> 0 | J20: =H20*I20 -> 0 | K20: =G20+J20 -> 0 | M20: =M19+K20-L20 -> 304841.6
A21: 18 | B21: 46099 | C21: 0 | G21: =E21*F21 -> 0 | J21: =H21*I21 -> 0 | K21: =G21+J21 -> 0 | M21: =M20+K21-L21 -> 304841.6
A22: 19 | B22: 46100 | C22: 0 | G22: =E22*F22 -> 0 | J22: =H22*I22 -> 0 | K22: =G22+J22 -> 0 | M22: =M21+K22-L22 -> 304841.6
A23: 20 | B23: 46101 | C23: 0 | G23: =E23*F23 -> 0 | J23: =H23*I23 -> 0 | K23: =G23+J23 -> 0 | M23: =M22+K23-L23 -> 304841.6
A24: 21 | B24: 46102 | C24: 0 | G24: =E24*F24 -> 0 | J24: =H24*I24 -> 0 | K24: =G24+J24 -> 0 | M24: =M23+K24-L24 -> 304841.6
A25: 22 | B25: 46103 | C25: 0 | G25: =E25*F25 -> 0 | J25: =H25*I25 -> 0 | K25: =G25+J25 -> 0 | M25: =M24+K25-L25 -> 304841.6
A26: 23 | B26: 46104 | C26: 0 | G26: =E26*F26 -> 0 | H26: 70 | I26: 103.73 | J26: =H26*I26 -> 7261.1 | K26: =G26+J26 -> 7261.1 | M26: =M25+K26-L26 -> 312102.7
A27: 24 | B27: 46105 | C27: 0 | G27: =E27*F27 -> 0 | J27: =H27*I27 -> 0 | K27: =G27+J27 -> 0 | M27: =M26+K27-L27 -> 312102.7
A28: 25 | B28: 46106 | C28: 0 | G28: =E28*F28 -> 0 | J28: =H28*I28 -> 0 | K28: =G28+J28 -> 0 | M28: =M27+K28-L28 -> 312102.7
A29: 26 | B29: 46107 | C29: 0 | E29: 1000 | F29: 91.55 | G29: =E29*F29 -> 91550 | H29: 35 | I29: 103.73 | J29: =H29*I29 -> 3630.55 | K29: =G29+J29 -> 95180.55 | M29: =M28+K29-L29 -> 407283.25
A30: 27 | B30: 46108 | C30: 0 | E30: 0 | F30: 0 | G30: =E30*F30 -> 0 | H30: 0 | I30: 0 | J30: =H30*I30 -> 0 | K30: =G30+J30 -> 0 | L30: 300000 | M30: =M29+K30-L30 -> 107283.25
A31: 28 | B31: 46109 | C31: 0 | G31: =E31*F31 -> 0 | J31: =H31*I31 -> 0 | K31: =G31+J31 -> 0 | M31: =M30+K31-L31 -> 107283.25
A32: 29 | B32: 46110 | C32: 0 | E32: 1000.15 | F32: 91.5 | G32: =E32*F32 -> 91513.725 | J32: =H32*I32 -> 0 | K32: =G32+J32 -> 91513.725 | M32: =M31+K32-L32 -> 198796.97
A33: 30 | B33: 46111 | C33: 0 | G33: =E33*F33 -> 0 | J33: =H33*I33 -> 0 | K33: =G33+J33 -> 0 | L33: 0 | M33: =M32+K33-L33 -> 198796.97
A34: 31 | B34: 46112
E35: =SUM(E4:E34) -> 5200.15 | G35: =SUM(G4:G34) -> 476023.72 | H35: =SUM(H4:H34) -> 245 | J35: =SUM(J4:J34) -> 25413.85 | K35: =SUM(K4:K34) -> 501437.57 | L35: =SUM(L4:L34) -> 500000

Sheet Hiriyur(VJNL)
A1: Sri Balaji Agencies
A2: S.No | B2: Date | C2: GRN No | D2: Ind No/Bill No | E2: Diesel (Lts) | F2: Price | G2: Amount | H2: Petrol (Lts) | I2: Price | J2: Amount | K2: Total amount | L2: Amount paid | M2: As on Date | N2: Remarks
A3: Opening Balance | K3: 6935.95 | M3: 6935.95
A4: 1 | B4: 46082 | G4: =E4*F4 -> 0 | J4: =H4*I4 -> 0 | K4: =G4+J4 -> 0 | M4: =M3+K4-L4 -> 6935.95
A5: 2 | B5: 46083 | E5: 2500 | F5: 92.26 | G5: =E5*F5 -> 230650 | H5: 70 | I5: 104.13 | J5: =H5*I5 -> 7289.1 | K5: =G5+J5 -> 237939.1 | M5: =M4+K5-L5 -> 244875.05
A6: 3 | B6: 46084 | G6: =E6*F6 -> 0 | J6: =H6*I6 -> 0 | K6: =G6+J6 -> 0 | M6: =M5+K6-L6 -> 244875.05
A7: 4 | B7: 46085 | G7: =E7*F7 -> 0 | J7: =H7*I7 -> 0 | K7: =G7+J7 -> 0 | M7: =M6+K7-L7 -> 244875.05
A8: 5 | B8: 46086 | G8: =E8*F8 -> 0 | J8: =H8*I8 -> 0 | K8: =G8+J8 -> 0 | M8: =M7+K8-L8 -> 244875.05
A9: 6 | B9: 46087 | G9: =E9*F9 -> 0 | J9: =H9*I9 -> 0 | K9: =G9+J9 -> 0 | M9: =M8+K9-L9 -> 244875.05
A10: 7 | B10: 46088 | G10: =E10*F10 -> 0 | J10: =H10*I10 -> 0 | K10: =G10+J10 -> 0 | M10: =M9+K10-L10 -> 244875.05
A11: 8 | B11: 46089 | G11: =E11*F11 -> 0 | J11: =H11*I11 -> 0 | K11: =G11+J11 -> 0 | M11: =M10+K11-L11 -> 244875.05
A12: 9 | B12: 46090 | G12: =E12*F12 -> 0 | J12: =H12*I12 -> 0 | K12: =G12+J12 -> 0 | M12: =M11+K12-L12 -> 244875.05
A13: 10 | B13: 46091 | G13: =E13*F13 -> 0 | J13: =H13*I13 -> 0 | K13: =G13+J13 -> 0 | M13: =M12+K13-L13 -> 244875.05
A14: 11 | B14: 46092 | G14: =E14*F14 -> 0 | H14: 70 | I14: 104.13 | J14: =H14*I14 -> 7289.1 | K14: =G14+J14 -> 7289.1 | M14: =M13+K14-L14 -> 252164.15
A15: 12 | B15: 46093 | G15: =E15*F15 -> 0 | J15: =H15*I15 -> 0 | K15: =G15+J15 -> 0 | L15: 200000 | M15: =M14+K15-L15 -> 52164.15
A16: 13 | B16: 46094 | G16: =E16*F16 -> 0 | J16: =H16*I16 -> 0 | K16: =G16+J16 -> 0 | M16: =M15+K16-L16 -> 52164.15
A17: 14 | B17: 46095 | G17: =E17*F17 -> 0 | J17: =H17*I17 -> 0 | K17: =G17+J17 -> 0 | M17: =M16+K17-L17 -> 52164.15
A18: 15 | B18: 46096 | G18: =E18*F18 -> 0 | J18: =H18*I18 -> 0 | K18: =G18+J18 -> 0 | M18: =M17+K18-L18 -> 52164.15
A19: 16 | B19: 46097 | E19: 2200 | F19: 92.26 | G19: =E19*F19 -> 202972 | H19: 35 | I19: 104.13 | J19: =H19*I19 -> 3644.55 | K19: =G19+J19 -> 206616.55 | M19: =M18+K19-L19 -> 258780.7
A20: 17 | B20: 46098 | G20: =E20*F20 -> 0 | J20: =H20*I20 -> 0 | K20: =G20+J20 -> 0 | M20: =M19+K20-L20 -> 258780.7
A21: 18 | B21: 46099 | G21: =E21*F21 -> 0 | J21: =H21*I21 -> 0 | K21: =G21+J21 -> 0 | M21: =M20+K21-L21 -> 258780.7
A22: 19 | B22: 46100 | G22: =E22*F22 -> 0 | J22: =H22*I22 -> 0 | K22: =G22+J22 -> 0 | M22: =M21+K22-L22 -> 258780.7
A23: 20 | B23: 46101 | G23: =E23*F23 -> 0 | J23: =H23*I23 -> 0 | K23: =G23+J23 -> 0 | M23: =M22+K23-L23 -> 258780.7
A24: 21 | B24: 46102 | G24: =E24*F24 -> 0 | J24: =H24*I24 -> 0 | K24: =G24+J24 -> 0 | M24: =M23+K24-L24 -> 258780.7
A25: 22 | B25: 46103 | G25: =E25*F25 -> 0 | J25: =H25*I25 -> 0 | K25: =G25+J25 -> 0 | M25: =M24+K25-L25 -> 258780.7
A26: 23 | B26: 46104 | G26: =E26*F26 -> 0 | J26: =H26*I26 -> 0 | K26: =G26+J26 -> 0 | M26: =M25+K26-L26 -> 258780.7
A27: 24 | B27: 46105 | G27: =E27*F27 -> 0 | J27: =H27*I27 -> 0 | K27: =G27+J27 -> 0 | M27: =M26+K27-L27 -> 258780.7
A28: 25 | B28: 46106 | G28: =E28*F28 -> 0 | J28: =H28*I28 -> 0 | K28: =G28+J28 -> 0 | M28: =M27+K28-L28 -> 258780.7
A29: 26 | B29: 46107 | G29: =E29*F29 -> 0 | J29: =H29*I29 -> 0 | K29: =G29+J29 -> 0 | M29: =M28+K29-L29 -> 258780.7
A30: 27 | B30: 46108 | E30: 0 | G30: =E30*F30 -> 0 | H30: 70 | I30: 104.13 | J30: =H30*I30 -> 7289.1 | K30: =G30+J30 -> 7289.1 | M30: =M29+K30-L30 -> 266069.8
A31: 28 | B31: 46109 | G31: =E31*F31 -> 0 | J31: =H31*I31 -> 0 | K31: =G31+J31 -> 0 | L31: 266000 | M31: =M30+K31-L31 -> 69.8
A32: 29 | B32: 46110 | G32: =E32*F32 -> 0 | J32: =H32*I32 -> 0 | K32: =G32+J32 -> 0 | M32: =M31+K32-L32 -> 69.8
A33: 30 | B33: 46111 | G33: =E33*F33 -> 0 | J33: =H33*I33 -> 0 | K33: =G33+J33 -> 0 | M33: =M32+K33-L33 -> 69.8
A34: 31 | B34: 46112 | G34: =E34*F34 -> 0 | J34: =H34*I34 -> 0 | K34: =G34+J34 -> 0 | M34: =M33+K34-L34 -> 69.8
E35: =SUM(E4:E34) -> 4700 | G35: =SUM(G4:G34) -> 433622 | H35: =SUM(H4:H34) -> 245 | J35: =SUM(J4:J34) -> 25511.85 | K35: =SUM(K4:K34) -> 459133.85 | L35: =SUM(L4:L34) -> 466000

Sheet Malebenur(KUWSDB)
A1: Sree Veerabhadreshwara Service Station
A2: S.No | B2: Date | C2: GRN No | D2: Ind No/Bill No | E2: Diesel (Lts) | F2: Price | G2: Amount | H2: Petrol (Lts) | I2: Price | J2: Amount | K2: Total amount | L2: Amount paid | M2: As on Date | N2: Remarks
A3: Opening Balance | K3: 58952.96 | M3: =+K3 -> 58952.96 | O3: 46138.764
A4: 1 | B4: 45717 | E4: 0 | F4: 0 | G4: =E4*F4 -> 0 | H4: 0 | I4: 0 | J4: =H4*I4 -> 0 | K4: =G4+J4 -> 0 | L4: 0 | M4: =M3+K4-L4 -> 58952.96
A5: 2 | B5: 45718 | E5: 0 | F5: 0 | G5: =E5*F5 -> 0 | H5: 0 | I5: 0 | J5: =H5*I5 -> 0 | K5: =G5+J5 -> 0 | L5: 0 | M5: =M4+K5-L5 -> 58952.96
A6: 3 | B6: 45719 | E6: 600 | F6: 92.17 | G6: 55302 | H6: 20 | I6: 104.03 | J6: 2080.6 | K6: =G6+J6 -> 57382.6 | L6: 0 | M6: =M5+K6-L6 -> 116335.56
A7: 4 | B7: 45720 | E7: 0 | F7: 0 | G7: =E7*F7 -> 0 | H7: 0 | I7: 0 | J7: =H7*I7 -> 0 | K7: =G7+J7 -> 0 | L7: 0 | M7: =M6+K7-L7 -> 116335.56
A8: 5 | B8: 45721 | E8: 0 | F8: 0 | G8: =E8*F8 -> 0 | H8: 0 | I8: 0 | J8: =H8*I8 -> 0 | K8: =G8+J8 -> 0 | L8: 0 | M8: =M7+K8-L8 -> 116335.56
A9: 6 | B9: 45722 | E9: 600 | F9: 92.17 | G9: =E9*F9 -> 55302 | H9: 35 | I9: 104.03 | J9: =H9*I9 -> 3641.05 | K9: =G9+J9 -> 58943.05 | L9: 0 | M9: =M8+K9-L9 -> 175278.61
A10: 7 | B10: 45723 | E10: 0 | F10: 0 | G10: =E10*F10 -> 0 | H10: 0 | I10: 0 | J10: =H10*I10 -> 0 | K10: =G10+J10 -> 0 | L10: 0 | M10: =M9+K10-L10 -> 175278.61
A11: 8 | B11: 45724 | E11: 0 | F11: 0 | G11: =E11*F11 -> 0 | H11: 0 | I11: 0 | J11: =H11*I11 -> 0 | K11: =G11+J11 -> 0 | L11: 0 | M11: =M10+K11-L11 -> 175278.61
A12: 9 | B12: 45725 | E12: 400 | F12: 92.17 | G12: =E12*F12 -> 36868 | H12: 0 | I12: 0 | J12: =H12*I12 -> 0 | K12: =G12+J12 -> 36868 | L12: 0 | M12: =M11+K12-L12 -> 212146.61
A13: 10 | B13: 45726 | E13: 0 | F13: 0 | G13: =E13*F13 -> 0 | H13: 0 | I13: 0 | J13: =H13*I13 -> 0 | K13: =G13+J13 -> 0 | L13: 0 | M13: =M12+K13-L13 -> 212146.61
A14: 11 | B14: 45727 | E14: 600 | F14: 92.17 | G14: =E14*F14 -> 55302 | H14: 35 | I14: 104.03 | J14: =H14*I14 -> 3641.05 | K14: =G14+J14 -> 58943.05 | L14: 0 | M14: =M13+K14-L14 -> 271089.66
A15: 12 | B15: 45728 | E15: 0 | F15: 0 | G15: =E15*F15 -> 0 | H15: 0 | I15: 0 | J15: =H15*I15 -> 0 | K15: =G15+J15 -> 0 | L15: 212137 | M15: =M14+K15-L15 -> 58952.66
A16: 13 | B16: 45729 | E16: 0 | F16: 0 | G16: =E16*F16 -> 0 | H16: 0 | I16: 0 | J16: =H16*I16 -> 0 | K16: =G16+J16 -> 0 | L16: 0 | M16: =M15+K16-L16 -> 58952.66
A17: 14 | B17: 45730 | E17: 0 | F17: 0 | G17: =E17*F17 -> 0 | H17: 0 | I17: 0 | J17: =H17*I17 -> 0 | K17: =G17+J17 -> 0 | L17: 0 | M17: =M16+K17-L17 -> 58952.66
A18: 15 | B18: 45731 | E18: 600 | F18: 92.17 | G18: =E18*F18 -> 55302 | H18: 20 | I18: 104.3 | J18: =H18*I18 -> 2086 | K18: =G18+J18 -> 57388 | L18: 0 | M18: =M17+K18-L18 -> 116340.66
... A33: 30 | B33: 45746 | E33: 0 | F33: 0 | G33: =E33*F33 -> 0 | H33: 0 | I33: 0 | J33: =H33*I33 -> 0 | K33: =G33+J33 -> 0 | L33: 0 | M33: =M32+K33-L33 -> 40529.41
A34: 31 | B34: 45747 | E34: 400 | F34: 92.17 | G34: 36868 | H34: 20 | I34: 104.03 | J34: =H34*I34 -> 2080.6 | K34: =G34+J34 -> 38948.6 | L34: 0 | M34: =M33+K34-L34 -> 79478.01
E35: 0 | F35: 0 | G35: =E35*F35 -> 0 | H35: 0 | I35: 0 | J35: =H35*I35 -> 0 | K35: =G35+J35 -> 0 | L35: 0 | M35: =M34+K35-L35 -> 79478.01
E36: 0 | F36: 0 | G36: =E36*F36 -> 0 | H36: 0 | I36: 0 | J36: =H36*I36 -> 0 | K36: =G36+J36 -> 0 | L36: 0 | M36: =M35+K36-L36 -> 79478.01
E37: =SUM(E4:E35) -> 4600 | G37: =SUM(G4:G35) -> 423982 | H37: =SUM(H4:H35) -> 205 | J37: =SUM(J4:J35) -> 21336.95 | K37: =SUM(K4:K35) -> 445318.95 | L37: =SUM(L4:L35) -> 424793.9
E38: 0 | G38: 0 | H38: 0 | J38: 0 | K38: =G38+J38 -> 0 | L38: 0
S43: 9052944708

Sheet Molakamuru
A1: Molakamuru
A2: S.No | B2: Date | C2: GRN No | D2: Ind No/Bill No | E2: Diesel (Lts) | F2: Price | G2: Amount | H2: Petrol (Lts) | I2: Price | J2: Amount | K2: Total amount | L2: Amount paid | M2: As on Date | N2: Remarks
A3: Opening Balance | K3: 22607.215 | L3: 0 | M3: 22607.215
A4: 1 | B4: 46082 | G4: =E4*F4 -> 0 | J4: =H4*I4 -> 0 | K4: =G4+J4 -> 0 | M4: =M3+K4-L4 -> 22607.215
A5: 2 | B5: 46083 | G5: =E5*F5 -> 0 | J5: =H5*I5 -> 0 | K5: =G5+J5 -> 0 | M5: =M4+K5-L5 -> 22607.215
A6: 3 | B6: 46084 | G6: =E6*F6 -> 0 | J6: =H6*I6 -> 0 | K6: =G6+J6 -> 0 | M6: =M5+K6-L6 -> 22607.215
A7: 4 | B7: 46085 | G7: =E7*F7 -> 0 | J7: =H7*I7 -> 0 | K7: =G7+J7 -> 0 | M7: =M6+K7-L7 -> 22607.215
A8: 5 | B8: 46086 | G8: =E8*F8 -> 0 | J8: =H8*I8 -> 0 | K8: =G8+J8 -> 0 | M8: =M7+K8-L8 -> 22607.215
A9: 6 | B9: 46087 | E9: 200 | F9: 92.22 | G9: =E9*F9 -> 18444 | H9: 55 | I9: 104.38 | J9: =H9*I9 -> 5740.9 | K9: =G9+J9 -> 24184.9 | M9: =M8+K9-L9 -> 46792.115
A10: 7 | B10: 46088 | G10: =E10*F10 -> 0 | J10: =H10*I10 -> 0 | K10: =G10+J10 -> 0 | M10: =M9+K10-L10 -> 46792.115
A11: 8 | B11: 46089 | G11: =E11*F11 -> 0 | J11: =H11*I11 -> 0 | K11: =G11+J11 -> 0 | M11: =M10+K11-L11 -> 46792.115
A12: 9 | B12: 46090 | G12: =E12*F12 -> 0 | J12: =H12*I12 -> 0 | K12: =G12+J12 -> 0 | M12: =M11+K12-L12 -> 46792.115
A13: 10 | B13: 46091 | G13: =E13*F13 -> 0 | J13: =H13*I13 -> 0 | K13: =G13+J13 -> 0 | M13: =M12+K13-L13 -> 46792.115
A14: 11 | B14: 46092 | G14: =E14*F14 -> 0 | J14: =H14*I14 -> 0 | K14: =G14+J14 -> 0 | M14: =M13+K14-L14 -> 46792.115
A15: 12 | B15: 46093 | G15: =E15*F15 -> 0 | J15: =H15*I15 -> 0 | K15: =G15+J15 -> 0 | L15: 46775.6 | M15: =M14+K15-L15 -> 16.5152
A16: 13 | B16: 46094 | G16: =E16*F16 -> 0 | J16: =H16*I16 -> 0 | K16: =G16+J16 -> 0 | M16: =M15+K16-L16 -> 16.5152
A17: 14 | B17: 46095 | G17: =E17*F17 -> 0 | J17: =H17*I17 -> 0 | K17: =G17+J17 -> 0 | M17: =M16+K17-L17 -> 16.5152
A18: 15 | B18: 46096 | G18: =E18*F18 -> 0 | J18: =H18*I18 -> 0 | K18: =G18+J18 -> 0 | M18: =M17+K18-L18 -> 16.5152
A19: 16 | B19: 46097 | G19: =E19*F19 -> 0 | J19: =H19*I19 -> 0 | K19: =G19+J19 -> 0 | M19: =M18+K19-L19 -> 16.5152
A20: 17 | B20: 46098 | G20: =E20*F20 -> 0 | J20: =H20*I20 -> 0 | K20: =G20+J20 -> 0 | M20: =M19+K20-L20 -> 16.5152
A21: 18 | B21: 46099 | G21: =E21*F21 -> 0 | J21: =H21*I21 -> 0 | K21: =G21+J21 -> 0 | M21: =M20+K21-L21 -> 16.5152
A22: 19 | B22: 46100 | G22: =E22*F22 -> 0 | J22: =H22*I22 -> 0 | K22: =G22+J22 -> 0 | M22: =M21+K22-L22 -> 16.5152
A23: 20 | B23: 46101 | G23: =E23*F23 -> 0 | J23: =H23*I23 -> 0 | K23: =G23+J23 -> 0 | M23: =M22+K23-L23 -> 16.5152
A24: 21 | B24: 46102 | G24: =E24*F24 -> 0 | J24: =H24*I24 -> 0 | K24: =G24+J24 -> 0 | M24: =M23+K24-L24 -> 16.5152
A25: 22 | B25: 46103 | G25: =E25*F25 -> 0 | J25: =H25*I25 -> 0 | K25: =G25+J25 -> 0 | M25: =M24+K25-L25 -> 16.5152
A26: 23 | B26: 46104 | G26: =E26*F26 -> 0 | H26: 20 | I26: 104.08 | J26: =H26*I26 -> 2081.6 | K26: =G26+J26 -> 2081.6 | M26: =M25+K26-L26 -> 2098.1152
A27: 24 | B27: 46105 | G27: =E27*F27 -> 0 | J27: =H27*I27 -> 0 | K27: =G27+J27 -> 0 | M27: =M26+K27-L27 -> 2098.1152
A28: 25 | B28: 46106 | G28: =E28*F28 -> 0 | J28: =H28*I28 -> 0 | K28: =G28+J28 -> 0 | M28: =M27+K28-L28 -> 2098.1152
A29: 26 | B29: 46107 | G29: =E29*F29 -> 0 | J29: =H29*I29 -> 0 | K29: =G29+J29 -> 0 | M29: =M28+K29-L29 -> 2098.1152
A30: 27 | B30: 46108 | G30: =E30*F30 -> 0 | J30: =H30*I30 -> 0 | K30: =G30+J30 -> 0 | M30: =M29+K30-L30 -> 2098.1152
A31: 28 | B31: 46109 | G31: =E31*F31 -> 0 | H31: 20 | I31: 104.08 | J31: =H31*I31 -> 2081.6 | K31: =G31+J31 -> 2081.6 | M31: =M30+K31-L31 -> 4179.7152
A32: 29 | B32: 46110 | G32: =E32*F32 -> 0 | J32: =H32*I32 -> 0 | K32: =G32+J32 -> 0 | L32: =K32 -> 0 | M32: =M31+K32-L32 -> 4179.7152
A33: 30 | B33: 46111 | G33: =E33*F33 -> 0 | J33: =H33*I33 -> 0 | K33: =G33+J33 -> 0 | L33: =K33 -> 0 | M33: =M32+K33-L33 -> 4179.7152
A34: 31 | B34: 46112 | G34: =E34*F34 -> 0 | K34: =G34+J34 -> 0 | L34: 0 | M34: =M33+K34-L34 -> 4179.7152
E35: =SUM(E4:E34) -> 200 | G35: =SUM(G4:G34) -> 18444 | H35: =SUM(H4:H34) -> 95 | J35: =SUM(J4:J34) -> 9904.1 | K35: =SUM(K4:K34) -> 28348.1 | L35: =SUM(L4:L34) -> 46775.6

Sheet Chellakere -1
A1: Shivaganga Service Station (BPCL)
A2: S.No | B2: Date | C2: GRN No | D2: Ind No/Bill No | E2: Diesel (Lts) | F2: Price | G2: Amount | H2: Petrol (Lts) | I2: Price | J2: Amount | K2: Total amount | L2: Amount paid | M2: As on Date | N2: Remarks
A3: Opening Balance | K3: 268656.68 | L3: 268656.68 | M3: 268656.68
A4: 1 | B4: 46082 | E4: 0 | F4: 0 | G4: 0 | H4: 0 | I4: 0 | J4: 0 | K4: =G4+J4 -> 0 | M4: =M3+K4-L4 -> 268656.68
A5: 2 | B5: 46083 | E5: 0 | F5: 0 | G5: 0 | H5: 0 | I5: 0 | J5: 0 | K5: =G5+J5 -> 0 | M5: =M4+K5-L5 -> 268656.68
A6: 3 | B6: 46084 | E6: 400 | F6: 92.23 | G6: =E6*F6 -> 36892 | H6: 0 | I6: 0 | J6: =H6*I6 -> 0 | K6: =G6+J6 -> 36892 | M6: =M5+K6-L6 -> 305548.68
A7: 4 | B7: 46085 | E7: 0 | F7: 0 | G7: =E7*F7 -> 0 | H7: 0 | I7: 0 | J7: =H7*I7 -> 0 | K7: =G7+J7 -> 0 | M7: =M6+K7-L7 -> 305548.68
A8: 5 | B8: 46086 | E8: 0 | F8: 0 | G8: =E8*F8 -> 0 | H8: 0 | I8: 0 | J8: =H8*I8 -> 0 | K8: =G8+J8 -> 0 | L8: 125000 | M8: =M7+K8-L8 -> 180548.68
A9: 6 | B9: 46087 | E9: 400 | F9: 92.23 | G9: =E9*F9 -> 36892 | H9: 35 | I9: 104.09 | J9: =H9*I9 -> 3643.15 | K9: =G9+J9 -> 40535.15 | M9: =M8+K9-L9 -> 221083.83
A10: 7 | B10: 46088 | E10: 0 | F10: 0 | G10: =E10*F10 -> 0 | H10: 0 | I10: 0 | J10: =H10*I10 -> 0 | K10: =G10+J10 -> 0 | M10: =M9+K10-L10 -> 221083.83
A11: 8 | B11: 46089 | E11: 0 | F11: 0 | G11: =E11*F11 -> 0 | H11: 0 | I11: 0 | J11: =H11*I11 -> 0 | K11: =G11+J11 -> 0 | M11: =M10+K11-L11 -> 221083.83
A12: 9 | B12: 46090 | E12: 599.64 | F12: 92.23 | G12: =E12*F12 -> 55304.797 | H12: 35 | I12: 104.09 | J12: =H12*I12 -> 3643.15 | K12: =G12+J12 -> 58947.947 | M12: =M11+K12-L12 -> 280031.77
A13: 10 | B13: 46091 | E13: 0 | F13: 0 | G13: =E13*F13 -> 0 | H13: 0 | I13: 0 | J13: =H13*I13 -> 0 | K13: =G13+J13 -> 0 | M13: =M12+K13-L13 -> 280031.77
A14: 11 | B14: 46092 | E14: 600 | F14: 92.23 | G14: =E14*F14 -> 55338 | H14: 0 | I14: 0 | J14: =H14*I14 -> 0 | K14: =G14+J14 -> 55338 | M14: =M13+K14-L14 -> 335369.77
A15: 12 | B15: 46093 | E15: 0 | F15: 0 | G15: =E15*F15 -> 0 | H15: 0 | I15: 0 | J15: =H15*I15 -> 0 | K15: =G15+J15 -> 0 | L15: 330000 | M15: =M14+K15-L15 -> 5369.7744
A16: 13 | B16: 46094 | E16: 0 | F16: 0 | G16: =E16*F16 -> 0 | H16: 0 | I16: 0 | J16: =H16*I16 -> 0 | K16: =G16+J16 -> 0 | M16: =M15+K16-L16 -> 5369.7744
A17: 14 | B17: 46095 | E17: 500 | F17: 92.23 | G17: =E17*F17 -> 46115 | H17: 0 | I17: 0 | J17: =H17*I17 -> 0 | K17: =G17+J17 -> 46115 | M17: =M16+K17-L17 -> 51484.774
A18: 15 | B18: 46096 | E18: 0 | F18: 0 | G18: =E18*F18 -> 0 | H18: 0 | I18: 0 | J18: =H18*I18 -> 0 | K18: =G18+J18 -> 0 | M18: =M17+K18-L18 -> 51484.774
A19: 16 | B19: 46097 | E19: 0 | F19: 0 | G19: =E19*F19 -> 0 | H19: 0 | I19: 0 | J19: =H19*I19 -> 0 | K19: =G19+J19 -> 0 | M19: =M18+K19-L19 -> 51484.774
A20: 17 | B20: 46098 | E20: 0 | F20: 0 | G20: =E20*F20 -> 0 | H20: 0 | I20: 0 | J20: =H20*I20 -> 0 | K20: =G20+J20 -> 0 | M20: =M19+K20-L20 -> 51484.774
A21: 18 | B21: 46099 | E21: 600 | F21: 92.23 | G21: =E21*F21 -> 55338 | H21: 35 | I21: 104.09 | J21: =H21*I21 -> 3643.15 | K21: =G21+J21 -> 58981.15 | M21: =M20+K21-L21 -> 110465.92
A22: 19 | B22: 46100 | E22: 0 | F22: 0 | G22: =E22*F22 -> 0 | H22: 0 | I22: 0 | J22: =H22*I22 -> 0 | K22: =G22+J22 -> 0 | M22: =M21+K22-L22 -> 110465.92
A23: 20 | B23: 46101 | E23: 0 | F23: 0 | G23: =E23*F23 -> 0 | H23: 0 | I23: 0 | J23: =H23*I23 -> 0 | K23: =G23+J23 -> 0 | M23: =M22+K23-L23 -> 110465.92
A24: 21 | B24: 46102 | E24: 0 | F24: 0 | G24: =E24*F24 -> 0 | H24: 0 | I24: 0 | J24: =H24*I24 -> 0 | K24: =G24+J24 -> 0 | M24: =M23+K24-L24 -> 110465.92
A25: 22 | B25: 46103 | E25: 0 | F25: 0 | G25: =E25*F25 -> 0 | H25: 0 | I25: 0 | J25: =H25*I25 -> 0 | K25: =G25+J25 -> 0 | M25: =M24+K25-L25 -> 110465.92
A26: 23 | B26: 46104 | E26: 0 | F26: 0 | G26: =E26*F26 -> 0 | H26: 0 | I26: 0 | J26: =H26*I26 -> 0 | K26: =G26+J26 -> 0 | M26: =M25+K26-L26 -> 110465.92
A27: 24 | B27: 46105 | E27: 0 | F27: 0 | G27: =E27*F27 -> 0 | H27: 0 | I27: 0 | J27: =H27*I27 -> 0 | K27: =G27+J27 -> 0 | M27: =M26+K27-L27 -> 110465.92
A28: 25 | B28: 46106 | E28: 600 | F28: 92.23 | G28: =E28*F28 -> 55338 | H28: 35 | I28: 104.09 | J28: =H28*I28 -> 3643.15 | K28: =G28+J28 -> 58981.15 | M28: =M27+K28-L28 -> 169447.07
A29: 26 | B29: 46107 | E29: 0 | F29: 0 | G29: =E29*F29 -> 0 | H29: 0 | I29: 0 | J29: 0 | K29: =G29+J29 -> 0 | M29: =M28+K29-L29 -> 169447.07
A30: 27 | B30: 46108 | E30: 500 | F30: 92.23 | G30: =E30*F30 -> 46115 | H30: 0 | I30: 0 | J30: 0 | K30: =G30+J30 -> 46115 | M30: =M29+K30-L30 -> 215562.07
A31: 28 | B31: 46109 | E31: 0 | F31: 0 | G31: 0 | H31: 0 | I31: 0 | J31: 0 | K31: =G31+J31 -> 0 | M31: =M30+K31-L31 -> 215562.07
A32: 29 | B32: 46110 | E32: 0 | F32: 0 | G32: 0 | H32: 0 | I32: 0 | J32: 0 | K32: =G32+J32 -> 0 | M32: =M31+K32-L32 -> 215562.07
A33: 30 | B33: 46111 | E33: 0 | F33: 0 | G33: 0 | H33: 0 | I33: 0 | J33: 0 | K33: =G33+J33 -> 0 | M33: =M32+K33-L33 -> 215562.07
A34: 31 | B34: 46112
E35: =SUM(E4:E34) -> 4199.64 | G35: =SUM(G4:G34) -> 387332.8 | H35: =SUM(H4:H34) -> 140 | J35: =SUM(J4:J34) -> 14572.6 | K35: =SUM(K4:K34) -> 401905.4 | L35: =SUM(L4:L34) -> 455000

Sheet  Chellakere-PKG-9
A1: Chellakere-PKG-09
A2: S.No | B2: Date | C2: GRN No | D2: Ind No/Bill No | E2: Diesel (Lts) | F2: Price | G2: Amount | H2: Petrol (Lts) | I2: Price | J2: Amount | K2: Total amount | L2: Amount paid | M2: As on Date | N2: Remarks
A3: Opening Balance | K3: 0 | L3: 0 | M3: 0
A4: 1 | B4: 46082 | G4: =E4*F4 -> 0 | J4: =H4*I4 -> 0 | K4: =G4+J4 -> 0 | L4: =K4 -> 0 | M4: =M3+K4-L4 -> 0
A5: 2 | B5: 46083 | G5: =E5*F5 -> 0 | J5: =H5*I5 -> 0 | K5: =G5+J5 -> 0 | L5: =K5 -> 0 | M5: =M4+K5-L5 -> 0
A6: 3 | B6: 46084 | G6: =E6*F6 -> 0 | J6: =H6*I6 -> 0 | K6: =G6+J6 -> 0 | L6: =K6 -> 0 | M6: =M5+K6-L6 -> 0
A7: 4 | B7: 46085 | G7: =E7*F7 -> 0 | J7: =H7*I7 -> 0 | K7: =G7+J7 -> 0 | L7: =K7 -> 0 | M7: =M6+K7-L7 -> 0
A8: 5 | B8: 46086 | E8: 40 | F8: 92.23 | G8: =E8*F8 -> 3689.2 | J8: =H8*I8 -> 0 | K8: =G8+J8 -> 3689.2 | L8: =K8 -> 3689.2 | M8: =M7+K8-L8 -> 0
A9: 6 | B9: 46087 | G9: =E9*F9 -> 0 | J9: =H9*I9 -> 0 | K9: =G9+J9 -> 0 | L9: =K9 -> 0 | M9: =M8+K9-L9 -> 0
A10: 7 | B10: 46088 | G10: =E10*F10 -> 0 | H10: 6 | I10: 104.09 | J10: =H10*I10 -> 624.54 | K10: =G10+J10 -> 624.54 | L10: =K10 -> 624.54 | M10: =M9+K10-L10 -> 0
A11: 8 | B11: 46089 | E11: 35 | F11: 92.23 | G11: =E11*F11 -> 3228.05 | J11: =H11*I11 -> 0 | K11: =G11+J11 -> 3228.05 | L11: =K11 -> 3228.05 | M11: =M10+K11-L11 -> 0
A12: 9 | B12: 46090 | G12: =E12*F12 -> 0 | J12: =H12*I12 -> 0 | K12: =G12+J12 -> 0 | L12: =K12 -> 0 | M12: =M11+K12-L12 -> 0
A13: 10 | B13: 46091 | G13: =E13*F13 -> 0 | J13: =H13*I13 -> 0 | K13: =G13+J13 -> 0 | L13: =K13 -> 0 | M13: =M12+K13-L13 -> 0
A14: 11 | B14: 46092 | G14: =E14*F14 -> 0 | J14: =H14*I14 -> 0 | K14: =G14+J14 -> 0 | L14: =K14 -> 0 | M14: =M13+K14-L14 -> 0
A15: 12 | B15: 46093 | G15: =E15*F15 -> 0 | J15: =H15*I15 -> 0 | K15: =G15+J15 -> 0 | L15: =K15 -> 0 | M15: =M14+K15-L15 -> 0
A16: 13 | B16: 46094 | E16: 20 | F16: 92.23 | G16: =E16*F16 -> 1844.6 | H16: 12 | I16: 104.09 | J16: =H16*I16 -> 1249.08 | K16: =G16+J16 -> 3093.68 | L16: =K16 -> 3093.68 | M16: =M15+K16-L16 -> 0
A17: 14 | B17: 46095 | G17: =E17*F17 -> 0 | J17: =H17*I17 -> 0 | K17: =G17+J17 -> 0 | L17: =K17 -> 0 | M17: =M16+K17-L17 -> 0
A18: 15 | B18: 46096 | G18: =E18*F18 -> 0 | J18: =H18*I18 -> 0 | K18: =G18+J18 -> 0 | L18: =K18 -> 0 | M18: =M17+K18-L18 -> 0
A19: 16 | B19: 46097 | G19: =E19*F19 -> 0 | J19: =H19*I19 -> 0 | K19: =G19+J19 -> 0 | L19: =K19 -> 0 | M19: =M18+K19-L19 -> 0
A20: 17 | B20: 46098 | G20: =E20*F20 -> 0 | J20: =H20*I20 -> 0 | K20: =G20+J20 -> 0 | L20: =K20 -> 0 | M20: =M19+K20-L20 -> 0
A21: 18 | B21: 46099 | E21: 35 | F21: 92.23 | G21: =E21*F21 -> 3228.05 | H21: 6 | I21: 104.09 | J21: =H21*I21 -> 624.54 | K21: =G21+J21 -> 3852.59 | L21: =K21 -> 3852.59 | M21: =M20+K21-L21 -> 0
A22: 19 | B22: 46100 | G22: =E22*F22 -> 0 | J22: =H22*I22 -> 0 | K22: =G22+J22 -> 0 | L22: =K22 -> 0 | M22: =M21+K22-L22 -> 0
A23: 20 | B23: 46101 | G23: =E23*F23 -> 0 | J23: =H23*I23 -> 0 | K23: =G23+J23 -> 0 | L23: =K23 -> 0 | M23: =M22+K23-L23 -> 0
A24: 21 | B24: 46102 | G24: =E24*F24 -> 0 | J24: =H24*I24 -> 0 | K24: =G24+J24 -> 0 | L24: =K24 -> 0 | M24: =M23+K24-L24 -> 0
A25: 22 | B25: 46103 | G25: =E25*F25 -> 0 | J25: =H25*I25 -> 0 | K25: =G25+J25 -> 0 | L25: =K25 -> 0 | M25: =M24+K25-L25 -> 0
A26: 23 | B26: 46104 | G26: =E26*F26 -> 0 | J26: =H26*I26 -> 0 | K26: =G26+J26 -> 0 | L26: =K26 -> 0 | M26: =M25+K26-L26 -> 0
A27: 24 | B27: 46105 | G27: =E27*F27 -> 0 | H27: 9.99 | I27: 104.09 | J27: =H27*I27 -> 1039.8591 | K27: =G27+J27 -> 1039.8591 | L27: =K27 -> 1039.8591 | M27: =M26+K27-L27 -> 0
A28: 25 | B28: 46106 | G28: =E28*F28 -> 0 | J28: =H28*I28 -> 0 | K28: =G28+J28 -> 0 | L28: =K28 -> 0 | M28: 0
A29: 26 | B29: 46107 | G29: =E29*F29 -> 0 | J29: =H29*I29 -> 0 | K29: =G29+J29 -> 0 | L29: =K29 -> 0 | M29: 0
A30: 27 | B30: 46108 | E30: 30 | F30: 92.23 | G30: =E30*F30 -> 2766.9 | J30: =H30*I30 -> 0 | K30: =G30+J30 -> 2766.9 | L30: =K30 -> 2766.9 | M30: 0
A31: 28 | B31: 46109 | G31: =E31*F31 -> 0 | J31: =H31*I31 -> 0 | K31: =G31+J31 -> 0 | L31: =K31 -> 0 | M31: 0
A32: 29 | B32: 46110 | G32: =E32*F32 -> 0 | J32: =H32*I32 -> 0 | K32: =G32+J32 -> 0 | L32: =K32 -> 0
A33: 30 | B33: 46111 | E33: 55.05 | F33: 92.23 | G33: =E33*F33 -> 5077.2615 | H33: 5 | I33: 104.09 | J33: =H33*I33 -> 520.45 | K33: =G33+J33 -> 5597.7115 | L33: =K33 -> 5597.7115
A34: 31 | B34: 46112 | G34: =E34*F34 -> 0 | J34: =H34*I34 -> 0 | K34: =G34+J34 -> 0 | L34: =K34 -> 0
E35: =SUM(E4:E34) -> 215.05 | G35: =SUM(G4:G34) -> 19834.061 | H35: =SUM(H4:H34) -> 38.99 | J35: =SUM(J4:J34) -> 4058.4691 | K35: =SUM(K4:K34) -> 23892.531 | L35: =SUM(L4:L34) -> 23892.531

Sheet  Chennagiri
A1: Chennagiri
A2: S.No | B2: Date | C2: GRN No | D2: Ind No/Bill No | E2: Diesel (Lts) | F2: Price | G2: Amount | H2: Petrol (Lts) | I2: Price | J2: Amount | K2: Total amount | L2: Amount paid | M2: As on Date | N2: Remarks
A3: Opening Balance | K3: 0 | L3: 0 | M3: =+K3 -> 0
A4: 1 | B4: 46082 | G4: =E4*F4 -> 0 | J4: =H4*I4 -> 0 | K4: =G4+J4 -> 0 | L4: =K4 -> 0 | M4: =M3+K4-L4 -> 0
A5: 2 | B5: 46083 | G5: =E5*F5 -> 0 | H5: 24 | I5: 104.14 | J5: =H5*I5 -> 2499.36 | K5: =G5+J5 -> 2499.36 | L5: =K5 -> 2499.36 | M5: =M4+K5-L5 -> 0 | N5: HPCL
A6: 3 | B6: 46084 | G6: =E6*F6 -> 0 | J6: =H6*I6 -> 0 | K6: =G6+J6 -> 0 | L6: =K6 -> 0 | M6: =M5+K6-L6 -> 0
A7: 4 | B7: 46085 | G7: =E7*F7 -> 0 | J7: =H7*I7 -> 0 | K7: =G7+J7 -> 0 | L7: =K7 -> 0 | M7: =M6+K7-L7 -> 0
A8: 5 | B8: 46086 | G8: =E8*F8 -> 0 | J8: =H8*I8 -> 0 | K8: =G8+J8 -> 0 | L8: =K8 -> 0 | M8: =M7+K8-L8 -> 0 | N8: HPCL
A9: 6 | B9: 46087 | G9: =E9*F9 -> 0 | J9: =H9*I9 -> 0 | K9: =G9+J9 -> 0 | L9: =K9 -> 0 | M9: =M8+K9-L9 -> 0
A10: 7 | B10: 46088 | E10: 210 | F10: 92.05 | G10: =E10*F10 -> 19330.5 | J10: =H10*I10 -> 0 | K10: =G10+J10 -> 19330.5 | L10: =K10 -> 19330.5 | M10: =M9+K10-L10 -> 0
A11: 8 | B11: 46089 | G11: =E11*F11 -> 0 | J11: =H11*I11 -> 0 | K11: =G11+J11 -> 0 | L11: =K11 -> 0 | M11: =M10+K11-L11 -> 0
A12: 9 | B12: 46090 | G12: =E12*F12 -> 0 | J12: =H12*I12 -> 0 | K12: =G12+J12 -> 0 | L12: =K12 -> 0 | M12: =M11+K12-L12 -> 0
A13: 10 | B13: 46091 | G13: =E13*F13 -> 0 | H13: 24 | I13: 104.14 | J13: =H13*I13 -> 2499.36 | K13: =G13+J13 -> 2499.36 | L13: =K13 -> 2499.36 | M13: =M12+K13-L13 -> 0
A14: 11 | B14: 46092 | G14: =E14*F14 -> 0 | J14: =H14*I14 -> 0 | K14: =G14+J14 -> 0 | L14: =K14 -> 0 | M14: =M13+K14-L14 -> 0
A15: 12 | B15: 46093 | G15: =E15*F15 -> 0 | J15: =H15*I15 -> 0 | K15: =G15+J15 -> 0 | L15: =K15 -> 0 | M15: =M14+K15-L15 -> 0
A16: 13 | B16: 46094 | G16: =E16*F16 -> 0 | J16: =H16*I16 -> 0 | K16: =G16+J16 -> 0 | L16: =K16 -> 0 | M16: =M15+K16-L16 -> 0
A17: 14 | B17: 46095 | G17: =E17*F17 -> 0 | J17: =H17*I17 -> 0 | K17: =G17+J17 -> 0 | L17: =K17 -> 0 | M17: =M16+K17-L17 -> 0
A18: 15 | B18: 46096 | G18: =E18*F18 -> 0 | J18: =H18*I18 -> 0 | K18: =G18+J18 -> 0 | L18: =K18 -> 0 | M18: =M17+K18-L18 -> 0
A19: 16 | B19: 46097 | G19: =E19*F19 -> 0 | J19: =H19*I19 -> 0 | K19: =G19+J19 -> 0 | L19: =K19 -> 0 | M19: =M18+K19-L19 -> 0
A20: 17 | B20: 46098 | G20: =E20*F20 -> 0 | J20: =H20*I20 -> 0 | K20: =G20+J20 -> 0 | L20: =K20 -> 0 | M20: =M19+K20-L20 -> 0
A21: 18 | B21: 46099 | G21: =E21*F21 -> 0 | J21: =H21*I21 -> 0 | K21: =G21+J21 -> 0 | L21: =K21 -> 0 | M21: =M20+K21-L21 -> 0
A22: 19 | B22: 46100 | G22: =E22*F22 -> 0 | J22: =H22*I22 -> 0 | K22: =G22+J22 -> 0 | L22: =K22 -> 0 | M22: =M21+K22-L22 -> 0
A23: 20 | B23: 46101 | G23: =E23*F23 -> 0 | J23: =H23*I23 -> 0 | K23: =G23+J23 -> 0 | L23: =K23 -> 0 | M23: =M22+K23-L23 -> 0
A24: 21 | B24: 46102 | G24: =E24*F24 -> 0 | J24: =H24*I24 -> 0 | K24: =G24+J24 -> 0 | L24: =K24 -> 0 | M24: =M23+K24-L24 -> 0
A25: 22 | B25: 46103 | G25: =E25*F25 -> 0 | J25: =H25*I25 -> 0 | K25: =G25+J25 -> 0 | L25: =K25 -> 0 | M25: =M24+K25-L25 -> 0
A26: 23 | B26: 46104 | G26: =E26*F26 -> 0 | J26: =H26*I26 -> 0 | K26: =G26+J26 -> 0 | L26: =K26 -> 0 | M26: =M25+K26-L26 -> 0
A27: 24 | B27: 46105 | G27: =E27*F27 -> 0 | H27: 24 | I27: 104.14 | J27: =H27*I27 -> 2499.36 | K27: =G27+J27 -> 2499.36 | L27: =K27 -> 2499.36 | M27: =M26+K27-L27 -> 0
A28: 25 | B28: 46106 | G28: =E28*F28 -> 0 | J28: =H28*I28 -> 0 | K28: =G28+J28 -> 0 | L28: =K28 -> 0 | M28: 0
A29: 26 | B29: 46107 | G29: =E29*F29 -> 0 | J29: =H29*I29 -> 0 | K29: =G29+J29 -> 0 | L29: =K29 -> 0 | M29: 0
A30: 27 | B30: 46108 | G30: =E30*F30 -> 0 | J30: =H30*I30 -> 0 | K30: =G30+J30 -> 0 | L30: =K30 -> 0 | M30: 0
A31: 28 | B31: 46109 | G31: =E31*F31 -> 0 | J31: =H31*I31 -> 0 | K31: =G31+J31 -> 0 | L31: =K31 -> 0 | M31: 0
A32: 29 | B32: 46110 | G32: =E32*F32 -> 0 | J32: =H32*I32 -> 0 | K32: =G32+J32 -> 0 | L32: =K32 -> 0
A33: 30 | B33: 46111 | G33: =E33*F33 -> 0 | J33: =H33*I33 -> 0 | K33: =G33+J33 -> 0 | L33: =K33 -> 0
A34: 31 | B34: 46112 | G34: =E34*F34 -> 0 | K34: =G34+J34 -> 0 | L34: =K34 -> 0
E35: =SUM(E4:E34) -> 210 | G35: =SUM(G4:G34) -> 19330.5 | H35: =SUM(H4:H34) -> 72 | J35: =SUM(J4:J34) -> 7498.08 | K35: =SUM(K4:K34) -> 26828.58 | L35: =SUM(L4:L34) -> 26828.58

Sheet Khanapur
A1: V.V.Varde
A2: S.No | B2: Date | C2: GRN No | D2: Ind No/Bill No | E2: Diesel (Lts) | F2: Price | G2: Amount | H2: Petrol (Lts) | I2: Price | J2: Amount | K2: Total amount | L2: Date of payment | M2: Amount paid | N2: Remarks
D3: Opening Balance | K3: 68785.913 | M3: 68785.913
A4: 1 | B4: 46082 | E4: 40 | F4: 90.88 | G4: =F4*E4 -> 3635.2 | H4: 5 | I4: 102.77 | J4: =H4*I4 -> 513.85 | K4: =G4+J4 -> 4149.05 | M4: =M3+K4-L4 -> 72934.963
A5: 2 | B5: 46083 | G5: =F5*E5 -> 0 | J5: =H5*I5 -> 0 | K5: =G5+J5 -> 0 | M5: =M4+K5-L5 -> 72934.963 | S5: 90.88 | T5: 102.77
A6: 3 | B6: 46084 | E6: 30 | F6: 90.88 | G6: =F6*E6 -> 2726.4 | J6: =H6*I6 -> 0 | K6: =G6+J6 -> 2726.4 | M6: =M5+K6-L6 -> 75661.363
A7: 4 | B7: 46085 | E7: 30 | F7: 90.88 | G7: =F7*E7 -> 2726.4 | H7: 10 | I7: 102.77 | J7: =H7*I7 -> 1027.7 | K7: =G7+J7 -> 3754.1 | M7: =M6+K7-L7 -> 79415.463
A8: 5 | B8: 46086 | E8: 60 | F8: 90.88 | G8: =F8*E8 -> 5452.8 | H8: 4 | I8: 102.77 | J8: =H8*I8 -> 411.08 | K8: =G8+J8 -> 5863.88 | M8: =M7+K8-L8 -> 85279.343
A9: 6 | B9: 46087 | E9: 110 | F9: 90.88 | G9: =F9*E9 -> 9996.8 | J9: =H9*I9 -> 0 | K9: =G9+J9 -> 9996.8 | M9: =M8+K9-L9 -> 95276.143
A10: 7 | B10: 46088 | E10: 90 | F10: 90.88 | G10: =F10*E10 -> 8179.2 | H10: 3 | I10: 102.77 | J10: =H10*I10 -> 308.31 | K10: =G10+J10 -> 8487.51 | M10: =M9+K10-L10 -> 103763.65
A11: 8 | B11: 46089 | E11: 10 | F11: 90.88 | G11: =F11*E11 -> 908.8 | J11: =H11*I11 -> 0 | K11: =G11+J11 -> 908.8 | M11: =M10+K11-L11 -> 104672.45
A12: 9 | B12: 46090 | E12: 170 | F12: 90.88 | G12: =F12*E12 -> 15449.6 | H12: 5 | I12: 102.77 | J12: =H12*I12 -> 513.85 | K12: =G12+J12 -> 15963.45 | M12: =M11+K12-L12 -> 120635.9
A13: 10 | B13: 46091 | E13: 70.97 | F13: 90.88 | G13: =F13*E13 -> 6449.7536 | J13: =H13*I13 -> 0 | K13: =G13+J13 -> 6449.7536 | M13: =M12+K13-L13 -> 127085.66
A14: 11 | B14: 46092 | E14: 90 | F14: 90.88 | G14: =F14*E14 -> 8179.2 | J14: =H14*I14 -> 0 | K14: =G14+J14 -> 8179.2 | M14: =M13+K14-L14 -> 135264.86
A15: 12 | B15: 46093 | E15: 30 | F15: 90.88 | G15: =F15*E15 -> 2726.4 | H15: 12 | I15: 102.77 | J15: =H15*I15 -> 1233.24 | K15: =G15+J15 -> 3959.64 | L15: 110000 | M15: =M14+K15-L15 -> 29224.496
A16: 13 | B16: 46094 | E16: 100 | F16: 90.88 | G16: =F16*E16 -> 9088 | J16: =H16*I16 -> 0 | K16: =G16+J16 -> 9088 | M16: =M15+K16-L16 -> 38312.496
A17: 14 | B17: 46095 | E17: 140 | F17: 90.88 | G17: =F17*E17 -> 12723.2 | H17: 5 | I17: 102.77 | J17: =H17*I17 -> 513.85 | K17: =G17+J17 -> 13237.05 | M17: =M16+K17-L17 -> 51549.546
A18: 15 | B18: 46096 | E18: 20 | F18: 90.88 | G18: =F18*E18 -> 1817.6 | J18: =H18*I18 -> 0 | K18: =G18+J18 -> 1817.6 | M18: =M17+K18-L18 -> 53367.146
A19: 16 | B19: 46097 | E19: 48.41 | F19: 90.88 | G19: =F19*E19 -> 4399.5008 | H19: 5 | I19: 102.77 | J19: =H19*I19 -> 513.85 | K19: =G19+J19 -> 4913.3508 | M19: =M18+K19-L19 -> 58280.497
A20: 17 | B20: 46098 | E20: 80 | F20: 90.88 | G20: =F20*E20 -> 7270.4 | J20: =H20*I20 -> 0 | K20: =G20+J20 -> 7270.4 | M20: =M19+K20-L20 -> 65550.897 | O20: 16.68
A21: 18 | B21: 46099 | E21: 60 | F21: 90.88 | G21: =F21*E21 -> 5452.8 | J21: =H21*I21 -> 0 | K21: =G21+J21 -> 5452.8 | M21: =M20+K21-L21 -> 71003.697
A22: 19 | B22: 46100 | G22: =F22*E22 -> 0 | J22: =H22*I22 -> 0 | K22: =G22+J22 -> 0 | M22: =M21+K22-L22 -> 71003.697
A23: 20 | B23: 46101 | E23: 196.39 | F23: 90.88 | G23: =F23*E23 -> 17847.923 | J23: =H23*I23 -> 0 | K23: =G23+J23 -> 17847.923 | M23: =M22+K23-L23 -> 88851.62 | N23: 0
A24: 21 | B24: 46102 | G24: =F24*E24 -> 0 | J24: =H24*I24 -> 0 | K24: =G24+J24 -> 0 | M24: =M23+K24-L24 -> 88851.62
A25: 22 | B25: 46103 | E25: 50 | F25: 90.88 | G25: =F25*E25 -> 4544 | J25: =H25*I25 -> 0 | K25: =G25+J25 -> 4544 | M25: =M24+K25-L25 -> 93395.62
A26: 23 | B26: 46104 | G26: =F26*E26 -> 0 | J26: =H26*I26 -> 0 | K26: =G26+J26 -> 0 | M26: =M25+K26-L26 -> 93395.62
A27: 24 | B27: 46105 | E27: 429.19 | F27: 90.88 | G27: =F27*E27 -> 39004.787 | H27: 17 | I27: 102.77 | J27: =H27*I27 -> 1747.09 | K27: =G27+J27 -> 40751.877 | M27: =M26+K27-L27 -> 134147.5
A28: 25 | B28: 46106 | G28: =F28*E28 -> 0 | J28: =H28*I28 -> 0 | K28: =G28+J28 -> 0 | M28: =M27+K28-L28 -> 134147.5
A29: 26 | B29: 46107 | E29: 60 | F29: 90.88 | G29: =F29*E29 -> 5452.8 | J29: =H29*I29 -> 0 | K29: =G29+J29 -> 5452.8 | M29: =M28+K29-L29 -> 139600.3
A30: 27 | B30: 46108 | E30: 50 | F30: 90.88 | G30: =F30*E30 -> 4544 | J30: =H30*I30 -> 0 | K30: =G30+J30 -> 4544 | M30: =M29+K30-L30 -> 144144.3
A31: 28 | B31: 46109 | G31: =F31*E31 -> 0 | J31: =H31*I31 -> 0 | K31: =G31+J31 -> 0 | M31: =M30+K31-L31 -> 144144.3
A32: 29 | B32: 46110 | G32: =F32*E32 -> 0 | J32: =H32*I32 -> 0 | K32: =G32+J32 -> 0 | M32: =M31+K32-L32 -> 144144.3
A33: 30 | B33: 46111 | E33: 50 | F33: 90.88 | G33: =F33*E33 -> 4544 | H33: 10 | I33: 102.77 | J33: =H33*I33 -> 1027.7 | K33: =G33+J33 -> 5571.7 | M33: =M32+K33-L33 -> 149716
A34: 31 | B34: 46112 | E34: 37.73 | F34: 90.88 | G34: =F34*E34 -> 3428.9024 | H34: 5 | I34: 102.77 | J34: =H34*I34 -> 513.85 | K34: =G34+J34 -> 3942.7524 | M34: =M33+K34-L34 -> 153658.75
E35: =SUM(E4:E34) -> 2052.69 | G35: =SUM(G4:G34) -> 186548.47 | H35: =SUM(H4:H34) -> 81 | J35: =SUM(J4:J34) -> 8324.37 | K35: =SUM(K4:K34) -> 194872.84 | L35: =SUM(L4:L34) -> 110000 | M35: =SUM(M4:M34) -> 3019414.6

Sheet Munavali
A1: Shri Daneshwari
A2: S.No | B2: Date | C2: GRN No | D2: Ind No/Bill No | E2: Diesel (Lts) | F2: Price | G2: Amount | H2: Petrol (Lts) | I2: Price | J2: Amount | K2: Total amount | L2: Amount paid | M2: As on date | N2: Remarks
D3: Opening Balance | K3: 0 | M3: 0 | O3: 26506.4
A4: 1 | B4: 46082 | E4: 0 | F4: 0 | G4: =E4*F4 -> 0 | J4: =H4*I4 -> 0 | K4: =G4+J4 -> 0 | M4: 0
A5: 2 | B5: 46083 | E5: 0 | F5: 0 | G5: =E5*F5 -> 0 | J5: =H5*I5 -> 0 | K5: =G5+J5 -> 0 | M5: =M4+K5-L5 -> 0
A6: 3 | B6: 46084 | E6: 0 | F6: 0 | G6: =E6*F6 -> 0 | J6: =H6*I6 -> 0 | K6: =G6+J6 -> 0 | M6: =M5+K6-L6 -> 0
A7: 4 | B7: 46085 | E7: 0 | F7: 0 | G7: =E7*F7 -> 0 | J7: =H7*I7 -> 0 | K7: =G7+J7 -> 0 | M7: =M6+K7-L7 -> 0
A8: 5 | B8: 46086 | E8: 0 | F8: 0 | G8: =E8*F8 -> 0 | J8: =H8*I8 -> 0 | K8: =G8+J8 -> 0 | M8: =M7+K8-L8 -> 0
A9: 6 | B9: 46087 | E9: 0 | F9: 0 | G9: =E9*F9 -> 0 | J9: =H9*I9 -> 0 | K9: =G9+J9 -> 0 | M9: =M8+K9-L9 -> 0
A10: 7 | B10: 46088 | E10: 0 | F10: 0 | G10: =E10*F10 -> 0 | J10: =H10*I10 -> 0 | K10: =G10+J10 -> 0 | M10: =M9+K10-L10 -> 0
A11: 8 | B11: 46089 | E11: 0 | F11: 0 | G11: =E11*F11 -> 0 | J11: =H11*I11 -> 0 | K11: =G11+J11 -> 0 | M11: =M10+K11-L11 -> 0
A12: 9 | B12: 46090 | E12: 0 | F12: 0 | G12: =E12*F12 -> 0 | J12: =H12*I12 -> 0 | K12: =G12+J12 -> 0 | M12: =M11+K12-L12 -> 0
A13: 10 | B13: 46091 | E13: 0 | F13: 0 | G13: =E13*F13 -> 0 | J13: =H13*I13 -> 0 | K13: =G13+J13 -> 0 | M13: =M12+K13-L13 -> 0
A14: 11 | B14: 46092 | E14: 0 | F14: 0 | G14: =E14*F14 -> 0 | J14: =H14*I14 -> 0 | K14: =G14+J14 -> 0 | M14: =M13+K14-L14 -> 0
A15: 12 | B15: 46093 | E15: 0 | F15: 0 | G15: =E15*F15 -> 0 | J15: =H15*I15 -> 0 | K15: =G15+J15 -> 0 | M15: =M14+K15-L15 -> 0
A16: 13 | B16: 46094 | D16: 0 | G16: =E16*F16 -> 0 | J16: =H16*I16 -> 0 | K16: =G16+J16 -> 0 | M16: =M15+K16-L16 -> 0
A17: 14 | B17: 46095 | G17: =E17*F17 -> 0 | J17: =H17*I17 -> 0 | K17: =G17+J17 -> 0 | M17: =M16+K17-L17 -> 0
A18: 15 | B18: 46096 | G18: =E18*F18 -> 0 | J18: =H18*I18 -> 0 | K18: =G18+J18 -> 0 | M18: =M17+K18-L18 -> 0
A19: 16 | B19: 46097 | G19: =E19*F19 -> 0 | J19: =H19*I19 -> 0 | K19: =G19+J19 -> 0 | M19: =M18+K19-L19 -> 0
A20: 17 | B20: 46098 | G20: =E20*F20 -> 0 | J20: =H20*I20 -> 0 | K20: =G20+J20 -> 0 | M20: =M19+K20-L20 -> 0
A21: 18 | B21: 46099 | G21: =E21*F21 -> 0 | J21: =H21*I21 -> 0 | K21: =G21+J21 -> 0 | M21: =M20+K21-L21 -> 0
A22: 19 | B22: 46100 | G22: =E22*F22 -> 0 | J22: =H22*I22 -> 0 | K22: =G22+J22 -> 0 | M22: =M21+K22-L22 -> 0
A23: 20 | B23: 46101 | G23: =E23*F23 -> 0 | J23: =H23*I23 -> 0 | K23: =G23+J23 -> 0 | M23: =M22+K23-L23 -> 0
A24: 21 | B24: 46102 | G24: =E24*F24 -> 0 | J24: =H24*I24 -> 0 | K24: =G24+J24 -> 0 | M24: =M23+K24-L24 -> 0
A25: 22 | B25: 46103 | G25: =E25*F25 -> 0 | J25: =H25*I25 -> 0 | K25: =G25+J25 -> 0 | M25: =M24+K25-L25 -> 0
A26: 23 | B26: 46104 | G26: =E26*F26 -> 0 | J26: =H26*I26 -> 0 | K26: =G26+J26 -> 0 | M26: =M25+K26-L26 -> 0
A27: 24 | B27: 46105 | G27: =E27*F27 -> 0 | J27: =H27*I27 -> 0 | K27: =G27+J27 -> 0 | M27: =M26+K27-L27 -> 0
A28: 25 | B28: 46106 | G28: =E28*F28 -> 0 | J28: =H28*I28 -> 0 | K28: =G28+J28 -> 0 | M28: =M27+K28-L28 -> 0
... A32: 29 | B32: 46110 | G32: =E32*F32 -> 0 | J32: =H32*I32 -> 0 | K32: =G32+J32 -> 0 | M32: =M31+K32-L32 -> 0
A33: 30 | B33: 46111 | G33: =E33*F33 -> 0 | J33: =H33*I33 -> 0 | K33: =G33+J33 -> 0 | L33: 0 | M33: =M32+K33-L33 -> 0
A34: 31 | G34: =E34*F34 -> 0 | J34: =H34*I34 -> 0 | K34: =G34+J34 -> 0 | L34: 0 | M34: =M33+K34-L34 -> 0
A35: 32 | G35: =E35*F35 -> 0 | J35: =H35*I35 -> 0 | K35: =G35+J35 -> 0 | L35: 0 | M35: =M34+K35-L35 -> 0
A36: 33 | G36: =E36*F36 -> 0 | J36: =H36*I36 -> 0 | K36: =G36+J36 -> 0 | L36: 0 | M36: =M35+K36-L36 -> 0
E37: =SUM(E4:E36) -> 0 | G37: =SUM(G4:G36) -> 0 | H37: =SUM(H4:H36) -> 0 | J37: =SUM(J4:J36) -> 0 | K37: =SUM(K4:K36) -> 0 | L37: =SUM(L4:L36) -> 0

Sheet Munavali-2
A1: Shiri Shva Petroluem
A2: S.No | B2: Date | C2: GRN No | D2: Ind No/Bill No | E2: Diesel (Lts) | F2: Price | G2: Amount | H2: Petrol (Lts) | I2: Price | J2: Amount | K2: Total amount | L2: Amount paid | M2: As on date | N2: Remarks
D3: Opening Balance | K3: 738510.09 | M3: 738510.09 | O3: 26506.4
A4: 1 | B4: 46082 | J4: =H4*I4 -> 0 | K4: =G4+J4 -> 0 | M4: =M3+K4-L4 -> 738510.09
A5: 2 | B5: 46083 | C5: Start | G5: =E5*F5 -> 0 | J5: =H5*I5 -> 0 | K5: =G5+J5 -> 0 | M5: =M4+K5-L5 -> 738510.09
A6: 3 | B6: 46084 | E6: 800 | F6: 91.54 | G6: =E6*F6 -> 73232 | H6: 20 | I6: 111.24 | J6: =H6*I6 -> 2224.8 | K6: =G6+J6 -> 75456.8 | M6: =M5+K6-L6 -> 813966.89
A7: 4 | B7: 46085 | G7: =E7*F7 -> 0 | J7: =H7*I7 -> 0 | K7: =G7+J7 -> 0 | M7: =M6+K7-L7 -> 813966.89
A8: 5 | B8: 46086 | E8: 1400 | F8: 91.54 | G8: =E8*F8 -> 128156 | J8: =H8*I8 -> 0 | K8: =G8+J8 -> 128156 | M8: =M7+K8-L8 -> 942122.89
A9: 6 | B9: 46087 | G9: =E9*F9 -> 0 | H9: 11 | I9: 103.48 | J9: =H9*I9 -> 1138.28 | K9: =G9+J9 -> 1138.28 | L9: 500000 | M9: =M8+K9-L9 -> 443261.17
A10: 7 | B10: 46088 | E10: 700 | F10: 91.54 | G10: =E10*F10 -> 64078 | J10: =H10*I10 -> 0 | K10: =G10+J10 -> 64078 | M10: =M9+K10-L10 -> 507339.17
A11: 8 | B11: 46089 | E11: 1300 | F11: 91.54 | G11: =E11*F11 -> 119002 | J11: =H11*I11 -> 0 | K11: =G11+J11 -> 119002 | M11: =M10+K11-L11 -> 626341.17
A12: 9 | B12: 46090 | E12: 1100 | F12: 91.54 | G12: =E12*F12 -> 100694 | J12: =H12*I12 -> 0 | K12: =G12+J12 -> 100694 | M12: =M11+K12-L12 -> 727035.17
A13: 10 | B13: 46091 | E13: 1000 | F13: 91.54 | G13: =E13*F13 -> 91540 | J13: =H13*I13 -> 0 | K13: =G13+J13 -> 91540 | L13: 0 | M13: =M12+K13-L13 -> 818575.17
A14: 11 | B14: 46092 | E14: 1300 | F14: 91.54 | G14: =E14*F14 -> 119002 | H14: 24.15 | I14: 103.44 | J14: =H14*I14 -> 2498.076 | K14: =G14+J14 -> 121500.08 | L14: 2498.08 | M14: =M13+K14-L14 -> 937577.17
A15: 12 | B15: 46093 | G15: =E15*F15 -> 0 | H15: 9.66 | I15: 103.44 | J15: =H15*I15 -> 999.2304 | K15: =G15+J15 -> 999.2304 | L15: 999.23 | M15: =M14+K15-L15 -> 937577.17
A16: 13 | B16: 46094 | D16: 0 | E16: 1400 | F16: 91.54 | G16: =E16*F16 -> 128156 | J16: =H16*I16 -> 0 | K16: =G16+J16 -> 128156 | L16: 600000 | M16: =M15+K16-L16 -> 465733.17
A17: 14 | B17: 46095 | G17: =E17*F17 -> 0 | J17: =H17*I17 -> 0 | K17: =G17+J17 -> 0 | M17: =M16+K17-L17 -> 465733.17
A18: 15 | B18: 46096 | G18: =E18*F18 -> 0 | J18: =H18*I18 -> 0 | K18: =G18+J18 -> 0 | M18: =M17+K18-L18 -> 465733.17
A19: 16 | B19: 46097 | E19: 700 | F19: 91.54 | G19: =E19*F19 -> 64078 | J19: =H19*I19 -> 0 | K19: =G19+J19 -> 64078 | M19: =M18+K19-L19 -> 529811.17
A20: 17 | B20: 46098 | G20: =E20*F20 -> 0 | J20: =H20*I20 -> 0 | K20: =G20+J20 -> 0 | M20: =M19+K20-L20 -> 529811.17
A21: 18 | B21: 46099 | E21: 300 | F21: 91.54 | G21: =E21*F21 -> 27462 | H21: 20 | I21: 113.41 | J21: =H21*I21 -> 2268.2 | K21: =G21+J21 -> 29730.2 | M21: =M20+K21-L21 -> 559541.37
A22: 19 | B22: 46100 | E22: 200 | F22: 91.54 | G22: =E22*F22 -> 18308 | H22: 10 | I22: 113.41 | J22: =H22*I22 -> 1134.1 | K22: =G22+J22 -> 19442.1 | M22: =M21+K22-L22 -> 578983.47
A23: 20 | B23: 46101 | E23: 240 | F23: 91.54 | G23: =E23*F23 -> 21969.6 | H23: 10 | I23: 113.41 | J23: =H23*I23 -> 1134.1 | K23: =G23+J23 -> 23103.7 | M23: =M22+K23-L23 -> 602087.17
A24: 21 | B24: 46102 | G24: =E24*F24 -> 0 | J24: =H24*I24 -> 0 | K24: =G24+J24 -> 0 | M24: =M23+K24-L24 -> 602087.17
A25: 22 | B25: 46103 | E25: 400 | F25: 91.54 | G25: =E25*F25 -> 36616 | H25: 20 | I25: 113.41 | J25: =H25*I25 -> 2268.2 | K25: =G25+J25 -> 38884.2 | M25: =M24+K25-L25 -> 640971.37
A26: 23 | B26: 46104 | E26: 200 | F26: 91.54 | G26: =E26*F26 -> 18308 | J26: =H26*I26 -> 0 | K26: =G26+J26 -> 18308 | M26: =M25+K26-L26 -> 659279.37
A27: 24 | B27: 46105 | E27: 900 | F27: 91.54 | G27: =E27*F27 -> 82386 | H27: 20 | I27: 113.41 | J27: =H27*I27 -> 2268.2 | K27: =G27+J27 -> 84654.2 | M27: =M26+K27-L27 -> 743933.57
A28: 25 | B28: 46106 | E28: 800 | F28: 91.54 | G28: =E28*F28 -> 73232 | J28: =H28*I28 -> 0 | K28: =G28+J28 -> 73232 | L28: 300000 | M28: =M27+K28-L28 -> 517165.57
A29: 26 | B29: 46107 | G29: =E29*F29 -> 0 | J29: =H29*I29 -> 0 | K29: =G29+J29 -> 0 | M29: =M28+K29-L29 -> 517165.57 | Q29: 166834
A30: 27 | B30: 46108 | E30: 1000 | F30: 91.54 | G30: =E30*F30 -> 91540 | J30: =H30*I30 -> 0 | K30: =G30+J30 -> 91540 | L30: 0 | M30: =M29+K30-L30 -> 608705.57
A31: 28 | B31: 46109 | E31: 840 | F31: 91.54 | G31: =E31*F31 -> 76893.6 | H31: 9.66 | I31: 103.44 | J31: =H31*I31 -> 999.2304 | K31: =G31+J31 -> 77892.83 | L31: 166834 | M31: =M30+K31-L31 -> 519764.4
A32: 29 | B32: 46110 | G32: =E32*F32 -> 0 | J32: =H32*I32 -> 0 | K32: =G32+J32 -> 0 | M32: =M31+K32-L32 -> 519764.4
A33: 30 | B33: 46111 | G33: =E33*F33 -> 0 | H33: 6 | I33: 113.41 | J33: =H33*I33 -> 680.46 | K33: =G33+J33 -> 680.46 | M33: =M32+K33-L33 -> 520444.86
A34: 31 | B34: 46112 | E34: 940 | F34: 91.54 | G34: =E34*F34 -> 86047.6 | H34: 5 | I34: 113.41 | J34: =H34*I34 -> 567.05 | K34: =G34+J34 -> 86614.65 | M34: =M33+K34-L34 -> 607059.51
A35: 32 | G35: =E35*F35 -> 0 | J35: =H35*I35 -> 0 | K35: =G35+J35 -> 0 | M35: =M34+K35-L35 -> 607059.51
A36: 33 | G36: =E36*F36 -> 0 | J36: =H36*I36 -> 0 | K36: =G36+J36 -> 0 | M36: =M35+K36-L36 -> 607059.51
E37: =SUM(E4:E36) -> 15520 | G37: =SUM(G4:G36) -> 1420700.8 | H37: =SUM(H4:H36) -> 165.47 | J37: =SUM(J4:J36) -> 18179.927 | K37: =SUM(K4:K36) -> 1438880.7 | L37: =SUM(L4:L36) -> 1570331.3

Sheet Borgaon
A1: Aadisagar Petrolium
A2: S.No | B2: Date | C2: GRN No | D2: Ind no/Bill No | E2: Diesel (Lts) | F2: Price | G2: Amount | H2: Petrol (Lts) | I2: Price | J2: Amount | K2: Total amount | L2: Amount paid | M2: As on Date | N2: Remarks
A3: Opening Balance | K3: 29558.904 | M3: 29558.904
A4: 1 | B4: 46082 | G4: =E4*F4 -> 0 | H4: 5 | I4: 103.73 | J4: =H4*I4 -> 518.65 | K4: =G4+J4 -> 518.65 | M4: =M3+K4-L4 -> 30077.554
A5: 2 | B5: 46083 | E5: 95 | F5: 91.77 | G5: =E5*F5 -> 8718.15 | H5: 11 | I5: 103.73 | J5: =H5*I5 -> 1141.03 | K5: =G5+J5 -> 9859.18 | M5: =M4+K5-L5 -> 39936.734
A6: 3 | B6: 46084 | G6: =E6*F6 -> 0 | H6: 3 | I6: 103.73 | J6: =H6*I6 -> 311.19 | K6: =G6+J6 -> 311.19 | M6: =M5+K6-L6 -> 40247.924
A7: 4 | B7: 46085 | G7: =E7*F7 -> 0 | H7: 5.01 | I7: 103.73 | J7: =H7*I7 -> 519.6873 | K7: =G7+J7 -> 519.6873 | M7: =M6+K7-L7 -> 40767.611
A8: 5 | B8: 46086 | G8: =E8*F8 -> 0 | H8: 6 | I8: 103.73 | J8: =H8*I8 -> 622.38 | K8: =G8+J8 -> 622.38 | M8: =M7+K8-L8 -> 41389.991
A9: 6 | B9: 46087 | E9: 170 | F9: 91.77 | G9: =E9*F9 -> 15600.9 | J9: =H9*I9 -> 0 | K9: =G9+J9 -> 15600.9 | M9: =M8+K9-L9 -> 56990.891
A10: 7 | B10: 46088 | E10: 770 | F10: 91.77 | G10: =E10*F10 -> 70662.9 | J10: =H10*I10 -> 0 | K10: =G10+J10 -> 70662.9 | M10: =M9+K10-L10 -> 127653.79
A11: 8 | B11: 46089 | E11: 5 | F11: 91.77 | G11: =E11*F11 -> 458.85 | J11: =H11*I11 -> 0 | K11: =G11+J11 -> 458.85 | M11: =M10+K11-L11 -> 128112.64
A12: 9 | B12: 46090 | G12: =E12*F12 -> 0 | J12: =H12*I12 -> 0 | K12: =G12+J12 -> 0 | M12: =M11+K12-L12 -> 128112.64
A13: 10 | B13: 46091 | G13: =E13*F13 -> 0 | J13: =H13*I13 -> 0 | K13: =G13+J13 -> 0 | M13: =M12+K13-L13 -> 128112.64
A14: 11 | B14: 46092 | G14: =E14*F14 -> 0 | H14: 23 | I14: 103.73 | J14: =H14*I14 -> 2385.79 | K14: =G14+J14 -> 2385.79 | M14: =M13+K14-L14 -> 130498.43
A15: 12 | B15: 46093 | G15: =E15*F15 -> 0 | J15: =H15*I15 -> 0 | K15: =G15+J15 -> 0 | L15: 100000 | M15: =M14+K15-L15 -> 30498.431
A16: 13 | B16: 46094 | G16: =E16*F16 -> 0 | J16: =H16*I16 -> 0 | K16: =G16+J16 -> 0 | M16: =M15+K16-L16 -> 30498.431
A17: 14 | B17: 46095 | G17: =E17*F17 -> 0 | H17: 5 | I17: 103.73 | J17: =H17*I17 -> 518.65 | K17: =G17+J17 -> 518.65 | M17: =M16+K17-L17 -> 31017.081
A18: 15 | B18: 46096 | G18: =E18*F18 -> 0 | J18: =H18*I18 -> 0 | K18: =G18+J18 -> 0 | M18: =M17+K18-L18 -> 31017.081
A19: 16 | B19: 46097 | E19: 620 | F19: 91.77 | G19: =E19*F19 -> 56897.4 | J19: =H19*I19 -> 0 | K19: =G19+J19 -> 56897.4 | M19: =M18+K19-L19 -> 87914.481
A20: 17 | B20: 46098 | E20: 200 | F20: 91.77 | G20: =E20*F20 -> 18354 | J20: =H20*I20 -> 0 | K20: =G20+J20 -> 18354 | M20: =M19+K20-L20 -> 106268.48
A21: 18 | B21: 46099 | E21: 830 | F21: 91.77 | G21: =E21*F21 -> 76169.1 | H21: 11 | I21: 103.73 | J21: =H21*I21 -> 1141.03 | K21: =G21+J21 -> 77310.13 | M21: =M20+K21-L21 -> 183578.61
A22: 19 | B22: 46100 | G22: =E22*F22 -> 0 | H22: 6 | I22: 103.73 | J22: =H22*I22 -> 622.38 | K22: =G22+J22 -> 622.38 | M22: =M21+K22-L22 -> 184200.99
A23: 20 | B23: 46101 | E23: 400 | F23: 91.77 | G23: =E23*F23 -> 36708 | J23: =H23*I23 -> 0 | K23: =G23+J23 -> 36708 | M23: =M22+K23-L23 -> 220908.99
A24: 21 | B24: 46102 | G24: =E24*F24 -> 0 | J24: =H24*I24 -> 0 | K24: =G24+J24 -> 0 | M24: =M23+K24-L24 -> 220908.99
A25: 22 | B25: 46103 | G25: =E25*F25 -> 0 | J25: =H25*I25 -> 0 | K25: =G25+J25 -> 0 | M25: =M24+K25-L25 -> 220908.99
A26: 23 | B26: 46104 | E26: 680 | F26: 91.77 | G26: =E26*F26 -> 62403.6 | J26: =H26*I26 -> 0 | K26: =G26+J26 -> 62403.6 | L26: 150000 | M26: =M25+K26-L26 -> 133312.59 | Q26: d
A27: 24 | B27: 46105 | E27: 435 | F27: 91.77 | G27: =E27*F27 -> 39919.95 | H27: 12.79 | I27: 103.73 | J27: =H27*I27 -> 1326.7067 | K27: =G27+J27 -> 41246.657 | M27: =M26+K27-L27 -> 174559.25 | Q27: 30 | R27: 50
A28: 25 | B28: 46106 | G28: =E28*F28 -> 0 | J28: =H28*I28 -> 0 | K28: =G28+J28 -> 0 | M28: =M27+K28-L28 -> 174559.25 | Q28: 50 | R28: 4.51
A29: 26 | B29: 46107 | E29: 600 | F29: 91.77 | G29: =E29*F29 -> 55062 | J29: =H29*I29 -> 0 | K29: =G29+J29 -> 55062 | M29: =M28+K29-L29 -> 229621.25
A30: 27 | B30: 46108 | G30: =E30*F30 -> 0 | J30: =H30*I30 -> 0 | K30: =G30+J30 -> 0 | M30: =M29+K30-L30 -> 229621.25
A31: 28 | B31: 46109 | E31: 600 | F31: 91.77 | G31: =E31*F31 -> 55062 | H31: 8 | I31: 103.73 | J31: =H31*I31 -> 829.84 | K31: =G31+J31 -> 55891.84 | M31: =M30+K31-L31 -> 285513.09
A32: 29 | B32: 46110 | G32: =E32*F32 -> 0 | J32: =H32*I32 -> 0 | K32: =G32+J32 -> 0 | M32: =M31+K32-L32 -> 285513.09
A33: 30 | B33: 46111 | G33: =E33*F33 -> 0 | J33: =H33*I33 -> 0 | K33: =G33+J33 -> 0 | M33: =M32+K33-L33 -> 285513.09
A34: 31 | B34: 46112 | G34: =E34*F34 -> 0 | J34: =H34*I34 -> 0 | K34: =G34+J34 -> 0 | L34: 200000 | M34: =M33+K34-L34 -> 85513.088
E35: =SUM(E4:E34) -> 5405 | G35: =SUM(G4:G34) -> 496016.85 | H35: =SUM(H4:H34) -> 95.8 | J35: =SUM(J4:J34) -> 9937.334 | K35: =SUM(K4:K34) -> 505954.18 | L35: =SUM(L4:L34) -> 450000

Sheet Ugar,Khagwad,Kudichi
A1: Shiri Bhrhmanath Petrolium
A2: S.No | B2: Date | C2: GRN No | D2: Ind No/Bill No | E2: Diesel (Lts) | F2: Price | G2: Amount | H2: Petrol (Lts) | I2: Price | J2: Amount | K2: Total amount | L2: Amount paid | M2: As on Date | N2: Remarks
A3: Opening Balance | K3: 215407.75 | L3: 0 | M3: 215407.75
A4: 1 | B4: 46082 | E4: 215 | F4: 91.93 | G4: =E4*F4 -> 19764.95 | J4: =H4*I4 -> 0 | K4: =G4+J4 -> 19764.95 | L4: 0 | M4: =M3+K4-L4 -> 235172.7
A5: 2 | B5: 46083 | E5: 280 | F5: 91.93 | G5: =E5*F5 -> 25740.4 | H5: 45 | I5: 103.89 | J5: =H5*I5 -> 4675.05 | K5: =G5+J5 -> 30415.45 | L5: 0 | M5: =M4+K5-L5 -> 265588.15
A6: 3 | B6: 46084 | G6: =E6*F6 -> 0 | J6: =H6*I6 -> 0 | K6: =G6+J6 -> 0 | L6: 0 | M6: =M5+K6-L6 -> 265588.15
A7: 4 | B7: 46085 | G7: =E7*F7 -> 0 | J7: =H7*I7 -> 0 | K7: =G7+J7 -> 0 | L7: 0 | M7: =M6+K7-L7 -> 265588.15
A8: 5 | B8: 46086 | E8: 405 | F8: 91.93 | G8: =E8*F8 -> 37231.65 | J8: =H8*I8 -> 0 | K8: =G8+J8 -> 37231.65 | L8: 0 | M8: =M7+K8-L8 -> 302819.8
A9: 6 | B9: 46087 | G9: =E9*F9 -> 0 | H9: 5 | I9: 103.89 | J9: =H9*I9 -> 519.45 | K9: =G9+J9 -> 519.45 | L9: 0 | M9: =M8+K9-L9 -> 303339.25
A10: 7 | B10: 46088 | E10: 0 | F10: 91.93 | G10: =E10*F10 -> 0 | H10: 15 | I10: 103.89 | J10: =H10*I10 -> 1558.35 | K10: =G10+J10 -> 1558.35 | L10: 0 | M10: =M9+K10-L10 -> 304897.6
A11: 8 | B11: 46089 | E11: 570 | F11: 91.93 | G11: =E11*F11 -> 52400.1 | H11: 30 | I11: 103.89 | J11: =H11*I11 -> 3116.7 | K11: =G11+J11 -> 55516.8 | L11: 0 | M11: =M10+K11-L11 -> 360414.4
A12: 9 | B12: 46090 | E12: 370 | F12: 91.93 | G12: =E12*F12 -> 34014.1 | H12: 5 | I12: 103.89 | J12: =H12*I12 -> 519.45 | K12: =G12+J12 -> 34533.55 | L12: 0 | M12: =M11+K12-L12 -> 394947.95
A13: 10 | B13: 46091 | E13: 95 | F13: 91.93 | G13: =E13*F13 -> 8733.35 | J13: =H13*I13 -> 0 | K13: =G13+J13 -> 8733.35 | L13: 0 | M13: =M12+K13-L13 -> 403681.3
A14: 11 | B14: 46092 | G14: =E14*F14 -> 0 | J14: =H14*I14 -> 0 | K14: =G14+J14 -> 0 | L14: 0 | M14: =M13+K14-L14 -> 403681.3
A15: 12 | B15: 46093 | E15: 235 | F15: 91.93 | G15: =E15*F15 -> 21603.55 | J15: =H15*I15 -> 0 | K15: =G15+J15 -> 21603.55 | L15: 250000 | M15: =M14+K15-L15 -> 175284.85
A16: 13 | B16: 46094 | E16: 100 | F16: 91.93 | G16: =E16*F16 -> 9193 | H16: 45 | I16: 103.89 | J16: =H16*I16 -> 4675.05 | K16: =G16+J16 -> 13868.05 | L16: 0 | M16: =M15+K16-L16 -> 189152.9
A17: 14 | B17: 46095 | E17: 670 | F17: 91.93 | G17: =E17*F17 -> 61593.1 | J17: =H17*I17 -> 0 | K17: =G17+J17 -> 61593.1 | L17: 0 | M17: =M16+K17-L17 -> 250746
A18: 15 | B18: 46096 | G18: =E18*F18 -> 0 | J18: =H18*I18 -> 0 | K18: =G18+J18 -> 0 | L18: 0 | M18: =M17+K18-L18 -> 250746
A19: 16 | B19: 46097 | E19: 195 | F19: 91.93 | G19: =E19*F19 -> 17926.35 | J19: =H19*I19 -> 0 | K19: =G19+J19 -> 17926.35 | L19: 0 | M19: =M18+K19-L19 -> 268672.35
A20: 17 | B20: 46098 | E20: 435 | F20: 91.93 | G20: =E20*F20 -> 39989.55 | H20: 30 | I20: 103.89 | J20: =H20*I20 -> 3116.7 | K20: =G20+J20 -> 43106.25 | L20: 0 | M20: =M19+K20-L20 -> 311778.6
A21: 18 | B21: 46099 | E21: 485 | F21: 91.93 | G21: =E21*F21 -> 44586.05 | J21: =H21*I21 -> 0 | K21: =G21+J21 -> 44586.05 | L21: 0 | M21: =M20+K21-L21 -> 356364.65
A22: 19 | B22: 46100 | G22: =E22*F22 -> 0 | J22: =H22*I22 -> 0 | K22: =G22+J22 -> 0 | L22: 0 | M22: =M21+K22-L22 -> 356364.65
A23: 20 | B23: 46101 | E23: 144.66 | F23: 91.93 | G23: =E23*F23 -> 13298.594 | J23: =H23*I23 -> 0 | K23: =G23+J23 -> 13298.594 | L23: 0 | M23: =M22+K23-L23 -> 369663.24
A24: 21 | B24: 46102 | E24: 35 | F24: 91.93 | G24: =E24*F24 -> 3217.55 | J24: =H24*I24 -> 0 | K24: =G24+J24 -> 3217.55 | L24: 0 | M24: =M23+K24-L24 -> 372880.79
A25: 22 | B25: 46103 | G25: =E25*F25 -> 0 | J25: =H25*I25 -> 0 | K25: =G25+J25 -> 0 | L25: 0 | M25: =M24+K25-L25 -> 372880.79
A26: 23 | B26: 46104 | E26: 430 | F26: 91.93 | G26: =E26*F26 -> 39529.9 | J26: =H26*I26 -> 0 | K26: =G26+J26 -> 39529.9 | L26: 200000 | M26: =M25+K26-L26 -> 212410.69
A27: 24 | B27: 46105 | E27: 20 | F27: 91.93 | G27: =E27*F27 -> 1838.6 | H27: 5 | I27: 113.3 | J27: =H27*I27 -> 566.5 | K27: =G27+J27 -> 2405.1 | L27: 0 | M27: =M26+K27-L27 -> 214815.79
A28: 25 | B28: 46106 | E28: 353.6 | F28: 91.93 | G28: =E28*F28 -> 32506.448 | J28: =H28*I28 -> 0 | K28: =G28+J28 -> 32506.448 | L28: 0 | M28: =M27+K28-L28 -> 247322.24
A29: 26 | B29: 46107 | E29: 65 | F29: 91.93 | G29: =E29*F29 -> 5975.45 | J29: =H29*I29 -> 0 | K29: =G29+J29 -> 5975.45 | L29: 0 | M29: =M28+K29-L29 -> 253297.69
A30: 27 | B30: 46108 | E30: 631.53 | F30: 91.93 | G30: =E30*F30 -> 58056.553 | H30: 30 | I30: 113.3 | J30: =H30*I30 -> 3399 | K30: =G30+J30 -> 61455.553 | L30: 50974 | M30: =M29+K30-L30 -> 263779.24
A31: 28 | B31: 46109 | E31: 355 | F31: 91.93 | G31: =E31*F31 -> 32635.15 | J31: =H31*I31 -> 0 | K31: =G31+J31 -> 32635.15 | L31: 0 | M31: =M30+K31-L31 -> 296414.39
A32: 29 | B32: 46110 | E32: 230 | F32: 91.93 | G32: =E32*F32 -> 21143.9 | J32: =H32*I32 -> 0 | K32: =G32+J32 -> 21143.9 | L32: 0 | M32: =M31+K32-L32 -> 317558.29
A33: 30 | B33: 46111 | E33: 924 | F33: 91.93 | G33: =E33*F33 -> 84943.32 | H33: 55 | I33: 103.89 | J33: =H33*I33 -> 5713.95 | K33: =G33+J33 -> 90657.27 | L33: 0 | M33: =M32+K33-L33 -> 408215.56
A34: 31 | B34: 46112 | E34: 285 | F34: 91.93 | G34: =E34*F34 -> 26200.05 | J34: =H34*I34 -> 0 | K34: =G34+J34 -> 26200.05 | L34: 0 | M34: =M33+K34-L34 -> 434415.61
E35: =SUM(E4:E34) -> 7528.79 | G35: =SUM(G4:G34) -> 692121.66 | H35: =SUM(H4:H34) -> 265 | J35: =SUM(J4:J34) -> 27860.2 | K35: =SUM(K4:K34) -> 719981.86 | L35: =SUM(L4:L34) -> 500974 | M35: =M34+K35-L35 -> 653423.48

Sheet Kabbur
A1: Shri Jai Hanuman Petrolium
A2: S.No | B2: Date | C2: GRN No | D2: Ind no/Bill No | E2: Diesel (Lts) | F2: Price | G2: Amount | H2: Petrol (Lts) | I2: Price | J2: Amount | K2: Total amount | L2: Amount paid | M2: As on Date | N2: Remarks
A3: Opening Balance | K3: 0 | M3: =+K3 -> 0
A4: 1 | B4: 46082 | G4: =E4*F4 -> 0 | J4: =H4*I4 -> 0 | K4: =G4+J4 -> 0 | L4: =+K4 -> 0
A5: 2 | B5: 46083 | G5: =E5*F5 -> 0 | J5: =H5*I5 -> 0 | K5: =G5+J5 -> 0 | L5: =+K5 -> 0
A6: 3 | B6: 46084 | G6: =E6*F6 -> 0 | J6: =H6*I6 -> 0 | K6: =G6+J6 -> 0 | L6: =+K6 -> 0
A7: 4 | B7: 46085 | G7: =E7*F7 -> 0 | J7: =H7*I7 -> 0 | K7: =G7+J7 -> 0 | L7: =+K7 -> 0
A8: 5 | B8: 46086 | E8: 90 | F8: 91.6 | G8: =E8*F8 -> 8244 | J8: =H8*I8 -> 0 | K8: =G8+J8 -> 8244 | L8: =+K8 -> 8244
A9: 6 | B9: 46087 | G9: =E9*F9 -> 0 | J9: =H9*I9 -> 0 | K9: =G9+J9 -> 0 | L9: =+K9 -> 0
A10: 7 | B10: 46088 | G10: =E10*F10 -> 0 | J10: =H10*I10 -> 0 | K10: =G10+J10 -> 0 | L10: =+K10 -> 0
A11: 8 | B11: 46089 | G11: =E11*F11 -> 0 | J11: =H11*I11 -> 0 | K11: =G11+J11 -> 0 | L11: =+K11 -> 0
A12: 9 | B12: 46090 | E12: 25 | F12: 91.6 | G12: =E12*F12 -> 2290 | J12: =H12*I12 -> 0 | K12: =G12+J12 -> 2290 | L12: =+K12 -> 2290
A13: 10 | B13: 46091 | E13: 80 | F13: 91.6 | G13: =E13*F13 -> 7328 | J13: =H13*I13 -> 0 | K13: =G13+J13 -> 7328 | L13: =+K13 -> 7328
A14: 11 | B14: 46092 | E14: 25 | F14: 91.6 | G14: =E14*F14 -> 2290 | J14: =H14*I14 -> 0 | K14: =G14+J14 -> 2290 | L14: =+K14 -> 2290
A15: 12 | B15: 46093 | G15: =E15*F15 -> 0 | J15: =H15*I15 -> 0 | K15: =G15+J15 -> 0 | L15: =+K15 -> 0
A16: 13 | B16: 46094 | G16: =E16*F16 -> 0 | J16: =H16*I16 -> 0 | K16: =G16+J16 -> 0 | L16: =+K16 -> 0
A17: 14 | B17: 46095 | E17: 90 | F17: 91.6 | G17: =E17*F17 -> 8244 | H17: 8 | I17: 103.54 | J17: =H17*I17 -> 828.32 | K17: =G17+J17 -> 9072.32 | L17: =+K17 -> 9072.32
A18: 15 | B18: 46096 | G18: =E18*F18 -> 0 | H18: 8 | I18: 103.54 | J18: =H18*I18 -> 828.32 | K18: =G18+J18 -> 828.32 | L18: =+K18 -> 828.32
A19: 16 | B19: 46097 | G19: =E19*F19 -> 0 | J19: =H19*I19 -> 0 | K19: =G19+J19 -> 0 | L19: =+K19 -> 0
A20: 17 | B20: 46098 | G20: =E20*F20 -> 0 | J20: =H20*I20 -> 0 | K20: =G20+J20 -> 0 | L20: =+K20 -> 0
A21: 18 | B21: 46099 | G21: =E21*F21 -> 0 | J21: =H21*I21 -> 0 | K21: =G21+J21 -> 0 | L21: =+K21 -> 0
A22: 19 | B22: 46100 | G22: =E22*F22 -> 0 | J22: =H22*I22 -> 0 | K22: =G22+J22 -> 0 | L22: =+K22 -> 0
A23: 20 | B23: 46101 | G23: =E23*F23 -> 0 | J23: =H23*I23 -> 0 | K23: =G23+J23 -> 0 | L23: =+K23 -> 0
A24: 21 | B24: 46102 | G24: =E24*F24 -> 0 | J24: =H24*I24 -> 0 | K24: =G24+J24 -> 0 | L24: =+K24 -> 0
A25: 22 | B25: 46103 | G25: =E25*F25 -> 0 | J25: =H25*I25 -> 0 | K25: =G25+J25 -> 0 | L25: =+K25 -> 0
A26: 23 | B26: 46104 | G26: =E26*F26 -> 0 | J26: =H26*I26 -> 0 | K26: =G26+J26 -> 0 | L26: =+K26 -> 0
A27: 24 | B27: 46105 | G27: =E27*F27 -> 0 | J27: =H27*I27 -> 0 | K27: =G27+J27 -> 0 | L27: =+K27 -> 0 | O27: 0
A28: 25 | B28: 46106 | G28: =E28*F28 -> 0 | J28: =H28*I28 -> 0 | K28: =G28+J28 -> 0 | L28: =+K28 -> 0
A29: 26 | B29: 46107 | G29: =E29*F29 -> 0 | J29: =H29*I29 -> 0 | K29: =G29+J29 -> 0 | L29: =+K29 -> 0
A30: 27 | B30: 46108 | G30: =E30*F30 -> 0 | J30: =H30*I30 -> 0 | K30: =G30+J30 -> 0 | L30: =+K30 -> 0
A31: 28 | B31: 46109 | E31: 65 | F31: 91.6 | G31: =E31*F31 -> 5954 | H31: 13 | I31: 103.54 | J31: =H31*I31 -> 1346.02 | K31: =G31+J31 -> 7300.02 | L31: =+K31 -> 7300.02
A32: 29 | B32: 46110 | G32: =E32*F32 -> 0 | J32: =H32*I32 -> 0 | K32: =G32+J32 -> 0 | L32: =+K32 -> 0
A33: 30 | B33: 46111 | G33: =E33*F33 -> 0 | J33: =H33*I33 -> 0 | K33: =G33+J33 -> 0 | L33: =+K33 -> 0
A34: 31 | B34: 46112 | G34: =E34*F34 -> 0 | H34: 5 | I34: 103.53 | J34: =H34*I34 -> 517.65 | K34: =G34+J34 -> 517.65 | L34: =+K34 -> 517.65
E35: =SUM(E4:E34) -> 375 | G35: =SUM(G4:G34) -> 34350 | H35: =SUM(H4:H34) -> 34 | J35: =SUM(J4:J34) -> 3520.31 | K35: =SUM(K4:K34) -> 37870.31 | L35: =SUM(L4:L34) -> 37870.31

Sheet kumta
A1: V.M.MIRJANKAR (KUMTA) BHARAT
A2: S.No | B2: Date | C2: GRN No | D2: Ind No/Bill No | E2: Diesel (Lts) | F2: Price | G2: Amount | H2: Petrol (Lts) | I2: Price | J2: Amount | K2: Total amount | L2: Amount paid | M2: As on Date | N2: Remarks
A3: Opening Balance | M3: 27054.7
A4: 1 | B4: 46082 | E4: 170 | F4: 91.97 | G4: =E4*F4 -> 15634.9 | H4: 5 | I4: 104.01 | J4: =H4*I4 -> 520.05 | K4: =G4+J4 -> 16154.95 | L4: 0 | M4: =M3+K4-L4 -> 43209.65
A5: 2 | B5: 46083 | G5: =E5*F5 -> 0 | H5: 10 | I5: 104.01 | J5: =H5*I5 -> 1040.1 | K5: =G5+J5 -> 1040.1 | L5: 0 | M5: =M4+K5-L5 -> 44249.75
A6: 3 | B6: 46084 | E6: 100 | F6: 91.97 | G6: =E6*F6 -> 9197 | J6: =H6*I6 -> 0 | K6: =G6+J6 -> 9197 | L6: 0 | M6: =M5+K6-L6 -> 53446.75
A7: 4 | B7: 46085 | G7: =E7*F7 -> 0 | J7: =H7*I7 -> 0 | K7: =G7+J7 -> 0 | L7: 0 | M7: =M6+K7-L7 -> 53446.75
A8: 5 | B8: 46086 | E8: 90 | F8: 91.97 | G8: =E8*F8 -> 8277.3 | H8: 5 | I8: 104.01 | J8: =H8*I8 -> 520.05 | K8: =G8+J8 -> 8797.35 | L8: 27053.8 | M8: =M7+K8-L8 -> 35190.3
A9: 6 | B9: 46087 | E9: 50 | F9: 91.97 | G9: =E9*F9 -> 4598.5 | H9: 5 | I9: 104.01 | J9: =H9*I9 -> 520.05 | K9: =G9+J9 -> 5118.55 | L9: 0 | M9: =M8+K9-L9 -> 40308.85
A10: 7 | B10: 46088 | E10: 130 | F10: 91.97 | G10: =E10*F10 -> 11956.1 | J10: =H10*I10 -> 0 | K10: =G10+J10 -> 11956.1 | L10: 0 | M10: =M9+K10-L10 -> 52264.95
A11: 8 | B11: 46089 | G11: =E11*F11 -> 0 | J11: =H11*I11 -> 0 | K11: =G11+J11 -> 0 | L11: 0 | M11: =M10+K11-L11 -> 52264.95
A12: 9 | B12: 46090 | E12: 100 | F12: 91.97 | G12: =E12*F12 -> 9197 | H12: 15 | I12: 104.01 | J12: =H12*I12 -> 1560.15 | K12: =G12+J12 -> 10757.15 | L12: 0 | M12: =M11+K12-L12 -> 63022.1
A13: 10 | B13: 46091 | E13: 155 | F13: 91.97 | G13: =E13*F13 -> 14255.35 | J13: =H13*I13 -> 0 | K13: =G13+J13 -> 14255.35 | L13: 0 | M13: =M12+K13-L13 -> 77277.45
A14: 11 | B14: 46092 | E14: 30 | F14: 91.97 | G14: =E14*F14 -> 2759.1 | H14: 10 | I14: 104.01 | J14: =H14*I14 -> 1040.1 | K14: =G14+J14 -> 3799.2 | L14: 0 | M14: =M13+K14-L14 -> 81076.65
A15: 12 | B15: 46093 | G15: =E15*F15 -> 0 | H15: 10 | I15: 104.01 | J15: =H15*I15 -> 1040.1 | K15: =G15+J15 -> 1040.1 | L15: 0 | M15: =M14+K15-L15 -> 82116.75
A16: 13 | B16: 46094 | E16: 130 | F16: 91.97 | G16: =E16*F16 -> 11956.1 | J16: =H16*I16 -> 0 | K16: =G16+J16 -> 11956.1 | L16: 80000 | M16: =M15+K16-L16 -> 14072.85
A17: 14 | B17: 46095 | G17: =E17*F17 -> 0 | H17: 5 | I17: 104.01 | J17: =H17*I17 -> 520.05 | K17: =G17+J17 -> 520.05 | L17: 0 | M17: =M16+K17-L17 -> 14592.9
A18: 15 | B18: 46096 | E18: 130 | F18: 91.97 | G18: =E18*F18 -> 11956.1 | H18: 5 | I18: 104.01 | J18: =H18*I18 -> 520.05 | K18: =G18+J18 -> 12476.15 | L18: 0 | M18: =M17+K18-L18 -> 27069.05
A19: 16 | B19: 46097 | E19: 80 | F19: 91.97 | G19: =E19*F19 -> 7357.6 | J19: =H19*I19 -> 0 | K19: =G19+J19 -> 7357.6 | L19: 0 | M19: =M18+K19-L19 -> 34426.65
A20: 17 | B20: 46098 | E20: 90 | F20: 91.97 | G20: =E20*F20 -> 8277.3 | J20: =H20*I20 -> 0 | K20: =G20+J20 -> 8277.3 | L20: 0 | M20: =M19+K20-L20 -> 42703.95
A21: 18 | B21: 46099 | G21: =E21*F21 -> 0 | H21: 15 | I21: 104.01 | J21: =H21*I21 -> 1560.15 | K21: =G21+J21 -> 1560.15 | L21: 0 | M21: =M20+K21-L21 -> 44264.1
A22: 19 | B22: 46100 | E22: 120 | F22: 91.97 | G22: =E22*F22 -> 11036.4 | J22: =H22*I22 -> 0 | K22: =G22+J22 -> 11036.4 | L22: 0 | M22: =M21+K22-L22 -> 55300.5
A23: 20 | B23: 46101 | E23: 120 | F23: 91.97 | G23: =E23*F23 -> 11036.4 | H23: 5 | I23: 104.01 | J23: =H23*I23 -> 520.05 | K23: =G23+J23 -> 11556.45 | L23: 0 | M23: =M22+K23-L23 -> 66856.95
A24: 21 | B24: 46102 | G24: =E24*F24 -> 0 | J24: =H24*I24 -> 0 | K24: =G24+J24 -> 0 | L24: 0 | M24: =M23+K24-L24 -> 66856.95
A25: 22 | B25: 46103 | G25: =E25*F25 -> 0 | H25: 5 | I25: 104.01 | J25: =H25*I25 -> 520.05 | K25: =G25+J25 -> 520.05 | L25: 0 | M25: =M24+K25-L25 -> 67377
A26: 23 | B26: 46104 | E26: 25 | F26: 91.97 | G26: =E26*F26 -> 2299.25 | J26: =H26*I26 -> 0 | K26: =G26+J26 -> 2299.25 | L26: 67000 | M26: =M25+K26-L26 -> 2676.25
A27: 24 | B27: 46105 | E27: 130 | F27: 91.97 | G27: =E27*F27 -> 11956.1 | H27: 5 | I27: 104.01 | J27: =H27*I27 -> 520.05 | K27: =G27+J27 -> 12476.15 | L27: 0 | M27: =M26+K27-L27 -> 15152.4
A28: 25 | B28: 46106 | E28: 35 | F28: 91.97 | G28: =E28*F28 -> 3218.95 | H28: 15 | I28: 104.01 | J28: =H28*I28 -> 1560.15 | K28: =G28+J28 -> 4779.1 | L28: 0 | M28: =M27+K28-L28 -> 19931.5
A29: 26 | B29: 46107 | E29: 130 | F29: 91.97 | G29: =E29*F29 -> 11956.1 | H29: 5 | I29: 104.01 | J29: =H29*I29 -> 520.05 | K29: =G29+J29 -> 12476.15 | L29: 0 | M29: =M28+K29-L29 -> 32407.65
A30: 27 | B30: 46108 | G30: =E30*F30 -> 0 | H30: 5 | I30: 104.01 | J30: =H30*I30 -> 520.05 | K30: =G30+J30 -> 520.05 | L30: 0 | M30: =M29+K30-L30 -> 32927.7
A31: 28 | B31: 46109 | E31: 50 | F31: 91.97 | G31: =E31*F31 -> 4598.5 | H31: 40 | I31: 104.01 | J31: =H31*I31 -> 4160.4 | K31: =G31+J31 -> 8758.9 | L31: 0 | M31: =M30+K31-L31 -> 41686.6
A32: 29 | B32: 46110 | E32: 100 | F32: 91.97 | G32: =E32*F32 -> 9197 | J32: =H32*I32 -> 0 | K32: =G32+J32 -> 9197 | L32: 0 | M32: =M31+K32-L32 -> 50883.6
A33: 30 | B33: 46111 | E33: 50 | F33: 91.97 | G33: =E33*F33 -> 4598.5 | H33: 5 | I33: 104.01 | J33: =H33*I33 -> 520.05 | K33: =G33+J33 -> 5118.55 | L33: 32000 | M33: =M32+K33-L33 -> 24002.15
A34: 31 | B34: 46112 | E34: 100 | F34: 91.97 | G34: =E34*F34 -> 9197 | H34: 15 | I34: 104.01 | J34: =H34*I34 -> 1560.15 | K34: =G34+J34 -> 10757.15 | L34: 0 | M34: =M33+K34-L34 -> 34759.3
E35: =SUM(E4:E34) -> 2115 | G35: =SUM(G4:G34) -> 194516.55 | H35: =SUM(H4:H34) -> 185 | J35: =SUM(J4:J34) -> 19241.85 | K35: =SUM(K4:K34) -> 213758.4 | L35: =SUM(L4:L34) -> 206053.8

Sheet Jalgaon
A1: Jai Bajarang Sarvo Senter Bodwad
A2: S.No | B2: Date | C2: GRN No | D2: Ind No/Bill No | E2: Diesel (Lts) | F2: Price | G2: Amount | H2: Petrol (Lts) | I2: Price | J2: Amount | K2: Total amount | L2: Amount paid | M2: As on Date | N2: Remarks
A3: Opening Balance | K3: 337793.25 | M3: =+K3 -> 337793.25
A4: 1 | B4: 46082 | G4: =E4*F4 -> 0 | J4: =H4*I4 -> 0 | K4: =G4+J4 -> 0 | M4: =M3+K4-L4 -> 337793.25
A5: 2 | B5: 46083 | E5: 2800 | F5: 91.71 | G5: =E5*F5 -> 256788 | H5: 25 | I5: 105.19 | J5: =H5*I5 -> 2629.75 | K5: =G5+J5 -> 259417.75 | M5: =M4+K5-L5 -> 597211
B6: 46083 | E6: 46.51 | F6: 95.7 | G6: =E6*F6 -> 4451.007 | K6: =G6+J6 -> 4451.007 | L6: 4451.01 | M6: =M5+K6-L6 -> 597211
A7: 3 | B7: 46084 | E7: 0 | F7: 0 | G7: =E7*F7 -> 0 | J7: =H7*I7 -> 0 | K7: =G7+J7 -> 0 | M7: =M6+K7-L7 -> 597211
A8: 4 | B8: 46085 | E8: 2200 | F8: 91.71 | G8: =E8*F8 -> 201762 | H8: 25 | I8: 105.19 | J8: =H8*I8 -> 2629.75 | K8: =G8+J8 -> 204391.75 | M8: =M7+K8-L8 -> 801602.75 | N8: IOCL
A9: 5 | B9: 46086 | E9: 2800 | F9: 91.71 | G9: =E9*F9 -> 256788 | J9: =H9*I9 -> 0 | K9: =G9+J9 -> 256788 | M9: =M8+K9-L9 -> 1058390.8 | N9: HPCL
A10: 6 | B10: 46087 | G10: =E10*F10 -> 0 | J10: =H10*I10 -> 0 | K10: =G10+J10 -> 0 | M10: =M9+K10-L10 -> 1058390.8
A11: 7 | B11: 46088 | G11: =E11*F11 -> 0 | J11: =H11*I11 -> 0 | K11: =G11+J11 -> 0 | M11: =M10+K11-L11 -> 1058390.8
A12: 8 | B12: 46089 | E12: 2200 | F12: 91.71 | G12: =E12*F12 -> 201762 | J12: =H12*I12 -> 0 | K12: =G12+J12 -> 201762 | M12: =M11+K12-L12 -> 1260152.8
A13: 9 | B13: 46090 | E13: 0 | F13: 91.71 | G13: =E13*F13 -> 0 | H13: 0 | I13: 0 | J13: =H13*I13 -> 0 | K13: =G13+J13 -> 0 | M13: =M12+K13-L13 -> 1260152.8
A14: 10 | B14: 46091 | E14: 895.61 | F14: 91.71 | G14: =E14*F14 -> 82136.393 | H14: 62.74 | I14: 105.19 | J14: =H14*I14 -> 6599.6206 | K14: =G14+J14 -> 88736.014 | M14: =M13+K14-L14 -> 1348888.8
A15: 11 | B15: 46091 | E15: 54.96 | F15: 91.71 | G15: =E15*F15 -> 5040.3816 | J15: =H15*I15 -> 0 | K15: =G15+J15 -> 5040.3816 | L15: =H15+K15 -> 5040.3816 | M15: =M14+K15-L15 -> 1348888.8
A16: 12 | B16: 46092 | E16: 2200 | F16: 91.71 | G16: =E16*F16 -> 201762 | J16: =H16*I16 -> 0 | K16: =G16+J16 -> 201762 | M16: =M15+K16-L16 -> 1550650.8
A17: 13 | B17: 46093 | E17: 2911.88 | F17: 91.71 | G17: =E17*F17 -> 267048.51 | J17: =H17*I17 -> 0 | K17: =G17+J17 -> 267048.51 | M17: =M16+K17-L17 -> 1817699.3
A18: 14 | B18: 46093 | E18: 40 | F18: 91.79 | G18: =E18*F18 -> 3671.6 | J18: =H18*I18 -> 0 | K18: =G18+J18 -> 3671.6 | L18: =H18+K18 -> 3671.6 | M18: =M17+K18-L18 -> 1817699.3
A19: 15 | B19: 46094 | E19: 440 | F19: 91.79 | G19: =E19*F19 -> 40387.6 | J19: =H19*I19 -> 0 | K19: =G19+J19 -> 40387.6 | L19: 335333 | M19: =M18+K19-L19 -> 1522753.9
A20: 16 | B20: 46094 | E20: 700 | F20: 91.61 | G20: =E20*F20 -> 64127 | J20: =H20*I20 -> 0 | K20: =G20+J20 -> 64127 | M20: =M19+K20-L20 -> 1586880.9
A21: 17 | B21: 46095 | E21: 700 | F21: 91.61 | G21: =E21*F21 -> 64127 | J21: =H21*I21 -> 0 | K21: =G21+J21 -> 64127 | M21: =M20+K21-L21 -> 1651007.9
A22: 18 | B22: 46096 | G22: =E22*F22 -> 0 | J22: =H22*I22 -> 0 | K22: =G22+J22 -> 0 | M22: =M21+K22-L22 -> 1651007.9
A23: 19 | B23: 46096 | G23: =E23*F23 -> 0 | J23: =H23*I23 -> 0 | K23: =G23+J23 -> 0 | M23: =M22+K23-L23 -> 1651007.9
A24: 20 | B24: 46101 | G24: =E24*F24 -> 0 | J24: =H24*I24 -> 0 | K24: =G24+J24 -> 0 | M24: =M23+K24-L24 -> 1651007.9
A25: 21 | B25: 46102 | G25: =E25*F25 -> 0 | J25: =H25*I25 -> 0 | K25: =G25+J25 -> 0 | M25: =M24+K25-L25 -> 1651007.9
A26: 22 | B26: 46103 | G26: =E26*F26 -> 0 | J26: =H26*I26 -> 0 | K26: =G26+J26 -> 0 | M26: =M25+K26-L26 -> 1651007.9
A27: 23 | B27: 46104 | G27: =E27*F27 -> 0 | J27: =H27*I27 -> 0 | K27: =G27+J27 -> 0 | M27: =M26+K27-L27 -> 1651007.9
A28: 24 | B28: 46105 | G28: =E28*F28 -> 0 | J28: =H28*I28 -> 0 | K28: =G28+J28 -> 0 | M28: =M27+K28-L28 -> 1651007.9
A29: 25 | B29: 46106 | G29: =E29*F29 -> 0 | J29: =H29*I29 -> 0 | K29: =G29+J29 -> 0 | M29: =M28+K29-L29 -> 1651007.9
A30: 26 | B30: 46107 | G30: =E30*F30 -> 0 | J30: =H30*I30 -> 0 | K30: =G30+J30 -> 0 | M30: =M29+K30-L30 -> 1651007.9
A31: 27 | B31: 46108 | G31: =E31*F31 -> 0 | J31: =H31*I31 -> 0 | K31: =G31+J31 -> 0 | M31: =M30+K31-L31 -> 1651007.9
A32: 28 | B32: 46109 | G32: =E32*F32 -> 0 | J32: =H32*I32 -> 0 | K32: =G32+J32 -> 0 | M32: =M31+K32-L32 -> 1651007.9
A33: 29 | B33: 46110 | G33: =E33*F33 -> 0 | J33: =H33*I33 -> 0 | K33: =G33+J33 -> 0 | M33: =M32+K33-L33 -> 1651007.9
... A35: 31 | B35: 46112 | G35: =E35*F35 -> 0 | J35: =H35*I35 -> 0 | K35: =G35+J35 -> 0 | M35: =M34+K35-L35 -> 1651007.9
A36: 32 | G36: =E36*F36 -> 0 | J36: =H36*I36 -> 0 | K36: =G36+J36 -> 0 | M36: =M35+K36-L36 -> 1651007.9
A37: 33 | G37: =E37*F37 -> 0 | J37: =H37*I37 -> 0 | K37: =G37+J37 -> 0 | M37: =M36+K37-L37 -> 1651007.9
A38: 34 | G38: =E38*F38 -> 0 | J38: =H38*I38 -> 0 | K38: =G38+J38 -> 0 | M38: =M37+K38-L38 -> 1651007.9 | P38: 41
A39: 35 | G39: =E39*F39 -> 0 | J39: =H39*I39 -> 0 | K39: =G39+J39 -> 0 | M39: =M38+K39-L39 -> 1651007.9 | P39: 40 | Q39: 5
A40: 36 | G40: =E40*F40 -> 0 | J40: =H40*I40 -> 0 | K40: =G40+J40 -> 0 | M40: =M39+K40-L40 -> 1651007.9
A41: 37 | G41: =E41*F41 -> 0 | J41: =H41*I41 -> 0 | K41: =G41+J41 -> 0 | M41: =M40+K41-L41 -> 1651007.9
A42: 38 | G42: =E42*F42 -> 0 | J42: =H42*I42 -> 0 | K42: =G42+J42 -> 0 | M42: =M41+K42-L42 -> 1651007.9
A43: 39 | G43: =E43*F43 -> 0 | J43: =H43*I43 -> 0 | K43: =G43+J43 -> 0 | M43: =M42+K43-L43 -> 1651007.9
A44: 40 | G44: =E44*F44 -> 0 | J44: =H44*I44 -> 0 | K44: =G44+J44 -> 0 | M44: =M43+K44-L44 -> 1651007.9
A45: 41 | G45: =E45*F45 -> 0 | J45: =H45*I45 -> 0 | K45: =G45+J45 -> 0 | M45: =M44+K45-L45 -> 1651007.9
A46: 42 | G46: =E46*F46 -> 0 | J46: =H46*I46 -> 0 | K46: =G46+J46 -> 0 | M46: =M45+K46-L46 -> 1651007.9
A47: 43 | G47: =E47*F47 -> 0 | J47: =H47*I47 -> 0 | K47: =G47+J47 -> 0 | M47: =M46+K47-L47 -> 1651007.9
A48: 44 | G48: =E48*F48 -> 0 | J48: =H48*I48 -> 0 | K48: =G48+J48 -> 0 | M48: =M47+K48-L48 -> 1651007.9
A49: 45 | G49: =E49*F49 -> 0 | J49: =H49*I49 -> 0 | K49: =G49+J49 -> 0 | M49: =M48+K49-L49 -> 1651007.9
A50: 46 | G50: =E50*F50 -> 0 | J50: =H50*I50 -> 0 | K50: =G50+J50 -> 0 | M50: =M49+K50-L50 -> 1651007.9
A51: 47 | G51: =E51*F51 -> 0 | J51: =H51*I51 -> 0 | K51: =G51+J51 -> 0 | L51: 0 | M51: =M50+K51-L51 -> 1651007.9
A52: 48 | G52: =E52*F52 -> 0 | J52: =H52*I52 -> 0 | K52: =G52+J52 -> 0 | L52: 0 | M52: =M51+K52-L52 -> 1651007.9
A53: 49 | G53: =E53*F53 -> 0 | J53: =H53*I53 -> 0 | K53: =G53+J53 -> 0 | L53: 0 | M53: =M52+K53-L53 -> 1651007.9
A54: 50 | G54: =E54*F54 -> 0 | J54: =H54*I54 -> 0 | K54: =G54+J54 -> 0 | L54: 0 | M54: =M53+K54-L54 -> 1651007.9 | O54: 1109792.3 | P54: =M54-O54 -> 541215.6
E55: =SUM(E4:E54) -> 17988.96 | G55: =SUM(G4:G54) -> 1649851.5 | H55: =SUM(H4:H54) -> 112.74 | J55: =SUM(J4:J54) -> 11859.121 | K55: =SUM(K4:K54) -> 1661710.6 | L55: =SUM(L4:L54) -> 348495.99

Sheet Jalgoan-2
A1: Nayara
A2: S.No | B2: Date | C2: GRN No | D2: Ind No/Bill No | E2: Diesel (Lts) | F2: Price | G2: Amount | H2: Petrol (Lts) | I2: Price | J2: Amount | K2: Total amount | L2: Amount paid | M2: As on Date | N2: Remarks
A3: Opening Balance | K3: 2953127.8 | M3: 2953127.8
A4: 1 | B4: 46082 | E4: 2700 | F4: 91.71 | G4: =E4*F4 -> 247617 | H4: 15 | I4: 105.44 | J4: =H4*I4 -> 1581.6 | K4: =G4+J4 -> 249198.6 | M4: =M3+K4-L4 -> 3202326.4
A5: 2 | B5: 46086 | E5: 2100 | F5: 91.71 | G5: =E5*F5 -> 192591 | J5: =H5*I5 -> 0 | K5: =G5+J5 -> 192591 | M5: =M4+K5-L5 -> 3394917.4
A6: 3 | B6: 46087 | E6: 40 | F6: 91.71 | G6: =E6*F6 -> 3668.4 | H6: 40 | I6: 105.44 | J6: =H6*I6 -> 4217.6 | K6: =G6+J6 -> 7886 | M6: =M5+K6-L6 -> 3402803.4
A7: 4 | B7: 46088 | E7: 2499.81 | F7: 91.71 | G7: =E7*F7 -> 229257.58 | J7: =H7*I7 -> 0 | K7: =G7+J7 -> 229257.58 | M7: =M6+K7-L7 -> 3632061
A8: 5 | B8: 46089 | E8: 2500 | F8: 91.71 | G8: =E8*F8 -> 229275 | J8: =H8*I8 -> 0 | K8: =G8+J8 -> 229275 | M8: =M7+K8-L8 -> 3861336
A9: 6 | B9: 46090 | E9: 400 | F9: 91.71 | G9: =E9*F9 -> 36684 | J9: =H9*I9 -> 0 | K9: =G9+J9 -> 36684 | M9: =M8+K9-L9 -> 3898020
A10: 7 | B10: 46091 | C10: 100 | E10: 120 | F10: 91.71 | G10: =E10*F10 -> 11005.2 | J10: =H10*I10 -> 0 | K10: =G10+J10 -> 11005.2 | M10: =M9+K10-L10 -> 3909025.2
A11: 8 | B11: 46092 | E11: 1099.64 | F11: 91.71 | G11: =E11*F11 -> 100847.98 | J11: =H11*I11 -> 0 | K11: =G11+J11 -> 100847.98 | M11: =M10+K11-L11 -> 4009873.1
A12: 9 | B12: 46094 | C12: 2700 | E12: 2800 | F12: 91.71 | G12: =E12*F12 -> 256788 | H12: 25 | I12: 105.44 | J12: =H12*I12 -> 2636 | K12: =G12+J12 -> 259424 | M12: =M11+K12-L12 -> 4269297.1
A13: 10 | B13: 46095 | E13: 2959 | F13: 91.71 | G13: =E13*F13 -> 271369.89 | J13: =H13*I13 -> 0 | K13: =G13+J13 -> 271369.89 | M13: =M12+K13-L13 -> 4540667
A14: 11 | B14: 46096 | E14: 2100 | F14: 91.71 | G14: =E14*F14 -> 192591 | J14: =H14*I14 -> 0 | K14: =G14+J14 -> 192591 | M14: =M13+K14-L14 -> 4733258
A15: 12 | B15: 46097 | C15: 3100 | E15: 3310 | F15: 91.71 | G15: =E15*F15 -> 303560.1 | H15: 55 | I15: 105.44 | J15: =H15*I15 -> 5799.2 | K15: =G15+J15 -> 309359.3 | M15: =M14+K15-L15 -> 5042617.3
A16: 13 | B16: 46098 | E16: 2700 | F16: 91.71 | G16: =E16*F16 -> 247617 | J16: =H16*I16 -> 0 | K16: =G16+J16 -> 247617 | L16: 1000000 | M16: =M15+K16-L16 -> 4290234.3
A17: 14 | B17: 46099 | E17: 2850 | F17: 91.71 | G17: =E17*F17 -> 261373.5 | J17: =H17*I17 -> 0 | K17: =G17+J17 -> 261373.5 | M17: =M16+K17-L17 -> 4551607.8
A18: 15 | B18: 46100 | E18: 900 | F18: 91.71 | G18: =E18*F18 -> 82539 | J18: =H18*I18 -> 0 | K18: =G18+J18 -> 82539 | M18: =M17+K18-L18 -> 4634146.8
A19: 16 | B19: 46101 | C19: 2929.35 | E19: 3129.35 | F19: 91.71 | G19: =E19*F19 -> 286992.69 | H19: 50 | I19: 105.44 | J19: =H19*I19 -> 5272 | K19: =G19+J19 -> 292264.69 | M19: =M18+K19-L19 -> 4926411.5
A20: 17 | B20: 46102 | E20: 1400 | F20: 91.71 | G20: =E20*F20 -> 128394 | J20: =H20*I20 -> 0 | K20: =G20+J20 -> 128394 | M20: =M19+K20-L20 -> 5054805.5
A21: 18 | B21: 46103 | E21: 2900 | F21: 91.71 | G21: =E21*F21 -> 265959 | J21: =H21*I21 -> 0 | K21: =G21+J21 -> 265959 | M21: =M20+K21-L21 -> 5320764.5
A22: 19 | B22: 46104 | E22: 5930 | F22: 91.71 | G22: =E22*F22 -> 543840.3 | H22: 55 | I22: 105.44 | J22: =H22*I22 -> 5799.2 | K22: =G22+J22 -> 549639.5 | L22: 1700000 | M22: =M21+K22-L22 -> 4170404
A23: 20 | B23: 46105 | E23: 3100 | F23: 91.71 | G23: =E23*F23 -> 284301 | J23: =H23*I23 -> 0 | K23: =G23+J23 -> 284301 | M23: =M22+K23-L23 -> 4454705
A24: 21 | B24: 46107 | E24: 5899.59 | F24: 94.71 | G24: =E24*F24 -> 558750.17 | H24: 60 | I24: 110.44 | J24: =H24*I24 -> 6626.4 | K24: =G24+J24 -> 565376.57 | M24: =M23+K24-L24 -> 5020081.6
A25: 22 | B25: 46108 | E25: 0 | F25: 0 | G25: =E25*F25 -> 0 | J25: =H25*I25 -> 0 | K25: =G25+J25 -> 0 | L25: =H25+K25 -> 0 | M25: =M24+K25-L25 -> 5020081.6 | N25: RAKSHA AUTO FUELS BPCL OTP
A26: 23 | B26: 46110 | G26: =E26*F26 -> 0 | H26: 35 | I26: 110.44 | J26: =H26*I26 -> 3865.4 | K26: =G26+J26 -> 3865.4 | M26: =M25+K26-L26 -> 5023947
A27: 24 | B27: 46112 | E27: 4700 | F27: 94.71 | G27: =E27*F27 -> 445137 | H27: 25 | I27: 110.44 | J27: =H27*I27 -> 2761 | K27: =G27+J27 -> 447898 | M27: =M26+K27-L27 -> 5471845
A28: 25 | G28: =E28*F28 -> 0 | J28: =H28*I28 -> 0 | K28: =G28+J28 -> 0 | M28: =M27+K28-L28 -> 5471845
A29: 26 | G29: =E29*F29 -> 0 | J29: =H29*I29 -> 0 | K29: =G29+J29 -> 0 | M29: =M28+K29-L29 -> 5471845
A30: 27 | G30: =E30*F30 -> 0 | J30: =H30*I30 -> 0 | K30: =G30+J30 -> 0 | M30: =M29+K30-L30 -> 5471845
A31: 28 | G31: =E31*F31 -> 0 | J31: =H31*I31 -> 0 | K31: =G31+J31 -> 0 | M31: =M30+K31-L31 -> 5471845
A32: 29 | G32: =E32*F32 -> 0 | J32: =H32*I32 -> 0 | K32: =G32+J32 -> 0 | M32: =M31+K32-L32 -> 5471845
A33: 30 | G33: =E33*F33 -> 0 | J33: =H33*I33 -> 0 | K33: =G33+J33 -> 0 | M33: =M32+K33-L33 -> 5471845
A34: 31 | G34: =E34*F34 -> 0 | J34: =H34*I34 -> 0 | K34: =G34+J34 -> 0 | M34: =M33+K34-L34 -> 5471845
A35: 32 | G35: =E35*F35 -> 0 | J35: =H35*I35 -> 0 | K35: =G35+J35 -> 0 | M35: =M34+K35-L35 -> 5471845
A36: 33 | G36: =E36*F36 -> 0 | J36: =H36*I36 -> 0 | K36: =G36+J36 -> 0 | M36: =M35+K36-L36 -> 5471845
A37: 34 | G37: =E37*F37 -> 0 | J37: =H37*I37 -> 0 | K37: =G37+J37 -> 0 | M37: =M36+K37-L37 -> 5471845
A38: 35 | G38: =E38*F38 -> 0 | J38: =H38*I38 -> 0 | K38: =G38+J38 -> 0 | M38: =M37+K38-L38 -> 5471845 | P38: 41
A39: 36 | G39: =E39*F39 -> 0 | J39: =H39*I39 -> 0 | K39: =G39+J39 -> 0 | M39: =M38+K39-L39 -> 5471845 | P39: 40 | Q39: 5
A40: 37 | G40: =E40*F40 -> 0 | J40: =H40*I40 -> 0 | K40: =G40+J40 -> 0 | M40: =M39+K40-L40 -> 5471845
A41: 38 | G41: =E41*F41 -> 0 | J41: =H41*I41 -> 0 | K41: =G41+J41 -> 0 | M41: =M40+K41-L41 -> 5471845
A42: 39 | G42: =E42*F42 -> 0 | J42: =H42*I42 -> 0 | K42: =G42+J42 -> 0 | M42: =M41+K42-L42 -> 5471845
A43: 40 | G43: =E43*F43 -> 0 | J43: =H43*I43 -> 0 | K43: =G43+J43 -> 0 | M43: =M42+K43-L43 -> 5471845
A44: 41 | G44: =E44*F44 -> 0 | J44: =H44*I44 -> 0 | K44: =G44+J44 -> 0 | M44: =M43+K44-L44 -> 5471845
A45: 42 | G45: =E45*F45 -> 0 | J45: =H45*I45 -> 0 | K45: =G45+J45 -> 0 | M45: =M44+K45-L45 -> 5471845
A46: 43 | G46: =E46*F46 -> 0 | J46: =H46*I46 -> 0 | K46: =G46+J46 -> 0 | M46: =M45+K46-L46 -> 5471845
A47: 44 | G47: =E47*F47 -> 0 | J47: =H47*I47 -> 0 | K47: =G47+J47 -> 0 | M47: =M46+K47-L47 -> 5471845
A48: 45 | G48: =E48*F48 -> 0 | J48: =H48*I48 -> 0 | K48: =G48+J48 -> 0 | M48: =M47+K48-L48 -> 5471845
A49: 46 | G49: =E49*F49 -> 0 | J49: =H49*I49 -> 0 | K49: =G49+J49 -> 0 | M49: =M48+K49-L49 -> 5471845
A50: 47 | G50: =E50*F50 -> 0 | J50: =H50*I50 -> 0 | K50: =G50+J50 -> 0 | M50: =M49+K50-L50 -> 5471845
A51: 48 | G51: =E51*F51 -> 0 | J51: =H51*I51 -> 0 | K51: =G51+J51 -> 0 | L51: 0 | M51: =M50+K51-L51 -> 5471845
A52: 49 | G52: =E52*F52 -> 0 | J52: =H52*I52 -> 0 | K52: =G52+J52 -> 0 | L52: 0 | M52: =M51+K52-L52 -> 5471845
A53: 50 | G53: =E53*F53 -> 0 | J53: =H53*I53 -> 0 | K53: =G53+J53 -> 0 | L53: 0 | M53: =M52+K53-L53 -> 5471845
A54: 51 | G54: =E54*F54 -> 0 | J54: =H54*I54 -> 0 | K54: =G54+J54 -> 0 | L54: 0 | M54: =M53+K54-L54 -> 5471845 | O54: 1109792.3 | P54: =M54-O54 -> 4362052.7
E55: =SUM(E4:E54) -> 56137.39 | G55: =SUM(G4:G54) -> 5180158.8 | H55: =SUM(H4:H54) -> 360 | J55: =SUM(J4:J54) -> 38558.4 | K55: =SUM(K4:K54) -> 5218717.2 | L55: =SUM(L4:L54) -> 2700000

Sheet  Jalgoan-3
A1: T R KAPOOR AND CO
A2: S.No | B2: Date | C2: GRN No | D2: Ind No/Bill No | E2: Diesel (Lts) | F2: Price | G2: Amount | H2: Petrol (Lts) | I2: Price | J2: Amount | K2: Total amount | L2: Amount paid | M2: As on Date | N2: Remarks
A3: Opening Balance | K3: 0 | M3: =+K3 -> 0
A4: 1 | B4: 46082 | G4: =E4*F4 -> 0 | J4: =H4*I4 -> 0 | K4: =G4+J4 -> 0 | M4: =M3+K4-L4 -> 0
A5: 2 | B5: 46083 | G5: =E5*F5 -> 0 | J5: =H5*I5 -> 0 | K5: =G5+J5 -> 0 | M5: =M4+K5-L5 -> 0
B6: 46083 | G6: =E6*F6 -> 0 | K6: =G6+J6 -> 0 | M6: =M5+K6-L6 -> 0
A7: 3 | B7: 46084 | G7: =E7*F7 -> 0 | J7: =H7*I7 -> 0 | K7: =G7+J7 -> 0 | M7: =M6+K7-L7 -> 0
A8: 4 | B8: 46085 | G8: =E8*F8 -> 0 | J8: =H8*I8 -> 0 | K8: =G8+J8 -> 0 | M8: =M7+K8-L8 -> 0 | N8: IOCL
A9: 5 | B9: 46086 | G9: =E9*F9 -> 0 | J9: =H9*I9 -> 0 | K9: =G9+J9 -> 0 | M9: =M8+K9-L9 -> 0 | N9: HPCL
A10: 6 | B10: 46087 | G10: =E10*F10 -> 0 | J10: =H10*I10 -> 0 | K10: =G10+J10 -> 0 | M10: =M9+K10-L10 -> 0
A11: 7 | B11: 46088 | G11: =E11*F11 -> 0 | J11: =H11*I11 -> 0 | K11: =G11+J11 -> 0 | M11: =M10+K11-L11 -> 0
A12: 8 | B12: 46089 | G12: =E12*F12 -> 0 | J12: =H12*I12 -> 0 | K12: =G12+J12 -> 0 | M12: =M11+K12-L12 -> 0
A13: 9 | B13: 46090 | G13: =E13*F13 -> 0 | J13: =H13*I13 -> 0 | K13: =G13+J13 -> 0 | M13: =M12+K13-L13 -> 0
A14: 10 | B14: 46091 | G14: =E14*F14 -> 0 | J14: =H14*I14 -> 0 | K14: =G14+J14 -> 0 | M14: =M13+K14-L14 -> 0
A15: 11 | B15: 46091 | G15: =E15*F15 -> 0 | J15: =H15*I15 -> 0 | K15: =G15+J15 -> 0 | M15: =M14+K15-L15 -> 0
A16: 12 | B16: 46092 | G16: =E16*F16 -> 0 | J16: =H16*I16 -> 0 | K16: =G16+J16 -> 0 | M16: =M15+K16-L16 -> 0
A17: 13 | B17: 46093 | G17: =E17*F17 -> 0 | J17: =H17*I17 -> 0 | K17: =G17+J17 -> 0 | M17: =M16+K17-L17 -> 0
A18: 14 | B18: 46093 | G18: =E18*F18 -> 0 | J18: =H18*I18 -> 0 | K18: =G18+J18 -> 0 | M18: =M17+K18-L18 -> 0
A19: 15 | B19: 46094 | G19: =E19*F19 -> 0 | J19: =H19*I19 -> 0 | K19: =G19+J19 -> 0 | M19: =M18+K19-L19 -> 0
A20: 16 | B20: 46094 | G20: =E20*F20 -> 0 | J20: =H20*I20 -> 0 | K20: =G20+J20 -> 0 | M20: =M19+K20-L20 -> 0
A21: 17 | B21: 46095 | G21: =E21*F21 -> 0 | J21: =H21*I21 -> 0 | K21: =G21+J21 -> 0 | M21: =M20+K21-L21 -> 0
... A30: 26 | B30: 46107 | G30: =E30*F30 -> 0 | J30: =H30*I30 -> 0 | K30: =G30+J30 -> 0 | M30: =M29+K30-L30 -> 0
A31: 27 | B31: 46108 | E31: 1000 | F31: 91.97 | G31: =E31*F31 -> 91970 | J31: =H31*I31 -> 0 | K31: =G31+J31 -> 91970 | M31: =M30+K31-L31 -> 91970
A32: 28 | B32: 46109 | G32: =E32*F32 -> 0 | J32: =H32*I32 -> 0 | K32: =G32+J32 -> 0 | L32: 91970 | M32: =M31+K32-L32 -> 0
A33: 29 | B33: 46110 | G33: =E33*F33 -> 0 | J33: =H33*I33 -> 0 | K33: =G33+J33 -> 0 | M33: =M32+K33-L33 -> 0
A34: 30 | B34: 46111 | E34: 1500 | F34: 91.97 | G34: =E34*F34 -> 137955 | J34: =H34*I34 -> 0 | K34: =G34+J34 -> 137955 | L34: =H34+K34 -> 137955 | M34: =M33+K34-L34 -> 0
A35: 31 | B35: 46112 | G35: =E35*F35 -> 0 | J35: =H35*I35 -> 0 | K35: =G35+J35 -> 0 | M35: =M34+K35-L35 -> 0
A36: 32 | G36: =E36*F36 -> 0 | J36: =H36*I36 -> 0 | K36: =G36+J36 -> 0 | M36: =M35+K36-L36 -> 0
A37: 33 | G37: =E37*F37 -> 0 | J37: =H37*I37 -> 0 | K37: =G37+J37 -> 0 | M37: =M36+K37-L37 -> 0
A38: 34 | G38: =E38*F38 -> 0 | J38: =H38*I38 -> 0 | K38: =G38+J38 -> 0 | M38: =M37+K38-L38 -> 0
A39: 35 | G39: =E39*F39 -> 0 | J39: =H39*I39 -> 0 | K39: =G39+J39 -> 0 | M39: =M38+K39-L39 -> 0
A40: 36 | G40: =E40*F40 -> 0 | J40: =H40*I40 -> 0 | K40: =G40+J40 -> 0 | M40: =M39+K40-L40 -> 0
A41: 37 | G41: =E41*F41 -> 0 | J41: =H41*I41 -> 0 | K41: =G41+J41 -> 0 | M41: =M40+K41-L41 -> 0
A42: 38 | G42: =E42*F42 -> 0 | J42: =H42*I42 -> 0 | K42: =G42+J42 -> 0 | M42: =M41+K42-L42 -> 0
A43: 39 | G43: =E43*F43 -> 0 | J43: =H43*I43 -> 0 | K43: =G43+J43 -> 0 | M43: =M42+K43-L43 -> 0
A44: 40 | G44: =E44*F44 -> 0 | J44: =H44*I44 -> 0 | K44: =G44+J44 -> 0 | M44: =M43+K44-L44 -> 0
A45: 41 | G45: =E45*F45 -> 0 | J45: =H45*I45 -> 0 | K45: =G45+J45 -> 0 | M45: =M44+K45-L45 -> 0
A46: 42 | G46: =E46*F46 -> 0 | J46: =H46*I46 -> 0 | K46: =G46+J46 -> 0 | M46: =M45+K46-L46 -> 0
A47: 43 | G47: =E47*F47 -> 0 | J47: =H47*I47 -> 0 | K47: =G47+J47 -> 0 | M47: =M46+K47-L47 -> 0
... A50: 46 | G50: =E50*F50 -> 0 | J50: =H50*I50 -> 0 | K50: =G50+J50 -> 0 | M50: =M49+K50-L50 -> 0
A51: 47 | G51: =E51*F51 -> 0 | J51: =H51*I51 -> 0 | K51: =G51+J51 -> 0 | L51: 0 | M51: =M50+K51-L51 -> 0
A52: 48 | G52: =E52*F52 -> 0 | J52: =H52*I52 -> 0 | K52: =G52+J52 -> 0 | L52: 0 | M52: =M51+K52-L52 -> 0
A53: 49 | G53: =E53*F53 -> 0 | J53: =H53*I53 -> 0 | K53: =G53+J53 -> 0 | L53: 0 | M53: =M52+K53-L53 -> 0
A54: 50 | G54: =E54*F54 -> 0 | J54: =H54*I54 -> 0 | K54: =G54+J54 -> 0 | L54: 0 | M54: =M53+K54-L54 -> 0
E55: =SUM(E4:E54) -> 2500 | G55: =SUM(G4:G54) -> 229925 | H55: =SUM(H4:H54) -> 0 | J55: =SUM(J4:J54) -> 0 | K55: =SUM(K4:K54) -> 229925 | L55: =SUM(L4:L54) -> 229925

Sheet  Jalgoan-4
A1: Cash &Carry
A2: S.No | B2: Date | C2: GRN No | D2: Ind No/Bill No | E2: Diesel (Lts) | F2: Price | G2: Amount | H2: Petrol (Lts) | I2: Price | J2: Amount | K2: Total amount | L2: Amount paid | M2: As on Date | N2: Remarks
A3: Opening Balance | K3: 0 | M3: =+K3 -> 0
A4: 1 | B4: 46082 | G4: =E4*F4 -> 0 | J4: =H4*I4 -> 0 | K4: =G4+J4 -> 0 | M4: =M3+K4-L4 -> 0
A5: 2 | B5: 46083 | G5: =E5*F5 -> 0 | J5: =H5*I5 -> 0 | K5: =G5+J5 -> 0 | M5: =M4+K5-L5 -> 0
B6: 46083 | G6: =E6*F6 -> 0 | K6: =G6+J6 -> 0 | M6: =M5+K6-L6 -> 0
A7: 3 | B7: 46084 | G7: =E7*F7 -> 0 | J7: =H7*I7 -> 0 | K7: =G7+J7 -> 0 | M7: =M6+K7-L7 -> 0
A8: 4 | B8: 46085 | G8: =E8*F8 -> 0 | J8: =H8*I8 -> 0 | K8: =G8+J8 -> 0 | M8: =M7+K8-L8 -> 0 | N8: IOCL
A9: 5 | B9: 46086 | G9: =E9*F9 -> 0 | J9: =H9*I9 -> 0 | K9: =G9+J9 -> 0 | M9: =M8+K9-L9 -> 0 | N9: HPCL
A10: 6 | B10: 46087 | G10: =E10*F10 -> 0 | J10: =H10*I10 -> 0 | K10: =G10+J10 -> 0 | M10: =M9+K10-L10 -> 0
A11: 7 | B11: 46088 | G11: =E11*F11 -> 0 | J11: =H11*I11 -> 0 | K11: =G11+J11 -> 0 | M11: =M10+K11-L11 -> 0
A12: 8 | B12: 46089 | G12: =E12*F12 -> 0 | J12: =H12*I12 -> 0 | K12: =G12+J12 -> 0 | M12: =M11+K12-L12 -> 0
A13: 9 | B13: 46090 | G13: =E13*F13 -> 0 | J13: =H13*I13 -> 0 | K13: =G13+J13 -> 0 | M13: =M12+K13-L13 -> 0
A14: 10 | B14: 46091 | G14: =E14*F14 -> 0 | J14: =H14*I14 -> 0 | K14: =G14+J14 -> 0 | M14: =M13+K14-L14 -> 0
A15: 11 | B15: 46091 | G15: =E15*F15 -> 0 | J15: =H15*I15 -> 0 | K15: =G15+J15 -> 0 | M15: =M14+K15-L15 -> 0
A16: 12 | B16: 46092 | G16: =E16*F16 -> 0 | J16: =H16*I16 -> 0 | K16: =G16+J16 -> 0 | M16: =M15+K16-L16 -> 0
A17: 13 | B17: 46093 | G17: =E17*F17 -> 0 | J17: =H17*I17 -> 0 | K17: =G17+J17 -> 0 | M17: =M16+K17-L17 -> 0
A18: 14 | B18: 46093 | G18: =E18*F18 -> 0 | J18: =H18*I18 -> 0 | K18: =G18+J18 -> 0 | M18: =M17+K18-L18 -> 0
A19: 15 | B19: 46094 | G19: =E19*F19 -> 0 | J19: =H19*I19 -> 0 | K19: =G19+J19 -> 0 | M19: =M18+K19-L19 -> 0
A20: 16 | B20: 46094 | G20: =E20*F20 -> 0 | J20: =H20*I20 -> 0 | K20: =G20+J20 -> 0 | M20: =M19+K20-L20 -> 0
A21: 17 | B21: 46095 | G21: =E21*F21 -> 0 | J21: =H21*I21 -> 0 | K21: =G21+J21 -> 0 | M21: =M20+K21-L21 -> 0
... A30: 26 | B30: 46107 | G30: =E30*F30 -> 0 | J30: =H30*I30 -> 0 | K30: =G30+J30 -> 0 | M30: =M29+K30-L30 -> 0
A31: 27 | B31: 46108 | E31: 1000 | F31: 91.67 | G31: =E31*F31 -> 91670 | J31: =H31*I31 -> 0 | K31: =G31+J31 -> 91670 | L31: =H31+K31 -> 91670 | M31: =M30+K31-L31 -> 0 | N31: RAKSHA AUTO FUELS BPCL OTP
A32: 28 | B32: 46109 | E32: 2000 | F32: 91.67 | G32: =E32*F32 -> 183340 | J32: =H32*I32 -> 0 | K32: =G32+J32 -> 183340 | L32: =H32+K32 -> 183340 | M32: =M31+K32-L32 -> 0
A33: 29 | B33: 46110 | E33: 1000 | F33: 91.67 | G33: =E33*F33 -> 91670 | J33: =H33*I33 -> 0 | K33: =G33+J33 -> 91670 | L33: =H33+K33 -> 91670 | M33: =M32+K33-L33 -> 0
A34: 30 | B34: 46111 | G34: =E34*F34 -> 0 | J34: =H34*I34 -> 0 | K34: =G34+J34 -> 0 | M34: =M33+K34-L34 -> 0
A35: 31 | B35: 46112 | G35: =E35*F35 -> 0 | J35: =H35*I35 -> 0 | K35: =G35+J35 -> 0 | M35: =M34+K35-L35 -> 0
A36: 32 | G36: =E36*F36 -> 0 | J36: =H36*I36 -> 0 | K36: =G36+J36 -> 0 | M36: =M35+K36-L36 -> 0
A37: 33 | G37: =E37*F37 -> 0 | J37: =H37*I37 -> 0 | K37: =G37+J37 -> 0 | M37: =M36+K37-L37 -> 0
A38: 34 | G38: =E38*F38 -> 0 | J38: =H38*I38 -> 0 | K38: =G38+J38 -> 0 | M38: =M37+K38-L38 -> 0
A39: 35 | G39: =E39*F39 -> 0 | J39: =H39*I39 -> 0 | K39: =G39+J39 -> 0 | M39: =M38+K39-L39 -> 0
A40: 36 | G40: =E40*F40 -> 0 | J40: =H40*I40 -> 0 | K40: =G40+J40 -> 0 | M40: =M39+K40-L40 -> 0
A41: 37 | G41: =E41*F41 -> 0 | J41: =H41*I41 -> 0 | K41: =G41+J41 -> 0 | M41: =M40+K41-L41 -> 0
A42: 38 | G42: =E42*F42 -> 0 | J42: =H42*I42 -> 0 | K42: =G42+J42 -> 0 | M42: =M41+K42-L42 -> 0
A43: 39 | G43: =E43*F43 -> 0 | J43: =H43*I43 -> 0 | K43: =G43+J43 -> 0 | M43: =M42+K43-L43 -> 0
A44: 40 | G44: =E44*F44 -> 0 | J44: =H44*I44 -> 0 | K44: =G44+J44 -> 0 | M44: =M43+K44-L44 -> 0
A45: 41 | G45: =E45*F45 -> 0 | J45: =H45*I45 -> 0 | K45: =G45+J45 -> 0 | M45: =M44+K45-L45 -> 0
A46: 42 | G46: =E46*F46 -> 0 | J46: =H46*I46 -> 0 | K46: =G46+J46 -> 0 | M46: =M45+K46-L46 -> 0
A47: 43 | G47: =E47*F47 -> 0 | J47: =H47*I47 -> 0 | K47: =G47+J47 -> 0 | M47: =M46+K47-L47 -> 0
... A50: 46 | G50: =E50*F50 -> 0 | J50: =H50*I50 -> 0 | K50: =G50+J50 -> 0 | M50: =M49+K50-L50 -> 0
A51: 47 | G51: =E51*F51 -> 0 | J51: =H51*I51 -> 0 | K51: =G51+J51 -> 0 | L51: 0 | M51: =M50+K51-L51 -> 0
A52: 48 | G52: =E52*F52 -> 0 | J52: =H52*I52 -> 0 | K52: =G52+J52 -> 0 | L52: 0 | M52: =M51+K52-L52 -> 0
A53: 49 | G53: =E53*F53 -> 0 | J53: =H53*I53 -> 0 | K53: =G53+J53 -> 0 | L53: 0 | M53: =M52+K53-L53 -> 0
A54: 50 | G54: =E54*F54 -> 0 | J54: =H54*I54 -> 0 | K54: =G54+J54 -> 0 | L54: 0 | M54: =M53+K54-L54 -> 0
E55: =SUM(E4:E54) -> 4000 | G55: =SUM(G4:G54) -> 366680 | H55: =SUM(H4:H54) -> 0 | J55: =SUM(J4:J54) -> 0 | K55: =SUM(K4:K54) -> 366680 | L55: =SUM(L4:L54) -> 366680

Sheet MKBD
A1: Shree Sai Samarth Petroleum
A2: S.No | B2: Date | C2: GRN No | D2: Ind No/Bill No | E2: Diesel (Lts) | F2: Price | G2: Amount | H2: Petrol (Lts) | I2: Price | J2: Amount | K2: Total amount | L2: Amount paid | M2: As on Date | N2: Remarks
A3: Opening Balance | K3: 103006.58 | M3: =+K3 -> 103006.58 | O3: 1194597
A4: 1 | B4: 45717 | G4: =E4*F4 -> 0 | J4: =H4*I4 -> 0 | K4: =G4+J4 -> 0 | M4: =M3+K4-L4 -> 103006.58
A5: 2 | B5: 45718 | G5: =E5*F5 -> 0 | J5: =H5*I5 -> 0 | K5: =G5+J5 -> 0 | M5: =M4+K5-L5 -> 103006.58
A6: 3 | B6: 45719 | G6: =E6*F6 -> 0 | J6: =H6*I6 -> 0 | K6: =G6+J6 -> 0 | M6: =M5+K6-L6 -> 103006.58
A7: 4 | B7: 45720 | G7: 0 | J7: 0 | K7: 0 | M7: =M6+K7-L7 -> 103006.58
A8: 5 | B8: 45721 | G8: =E8*F8 -> 0 | J8: =H8*I8 -> 0 | K8: =G8+J8 -> 0 | M8: =M7+K8-L8 -> 103006.58
A9: 6 | B9: 45722 | G9: =E9*F9 -> 0 | H9: 20 | I9: 104.6 | J9: =H9*I9 -> 2092 | K9: =G9+J9 -> 2092 | M9: =M8+K9-L9 -> 105098.58
A10: 7 | B10: 45723 | G10: =E10*F10 -> 0 | J10: =H10*I10 -> 0 | K10: =G10+J10 -> 0 | M10: =M9+K10-L10 -> 105098.58
A11: 8 | B11: 45724 | G11: =E11*F11 -> 0 | J11: =H11*I11 -> 0 | K11: =G11+J11 -> 0 | M11: =M10+K11-L11 -> 105098.58
A12: 9 | B12: 45725 | G12: =E12*F12 -> 0 | J12: =H12*I12 -> 0 | K12: =G12+J12 -> 0 | M12: =M11+K12-L12 -> 105098.58
A13: 10 | B13: 45726 | G13: =E13*F13 -> 0 | H13: 20.21 | I13: 104.6 | J13: =H13*I13 -> 2113.966 | K13: =G13+J13 -> 2113.966 | M13: =M12+K13-L13 -> 107212.55
A14: 11 | B14: 45727 | E14: 3000 | F14: 91.14 | G14: =E14*F14 -> 273420 | H14: 10 | I14: 104.6 | J14: =H14*I14 -> 1046 | K14: =G14+J14 -> 274466 | M14: =M13+K14-L14 -> 381678.55
A15: 12 | B15: 45728 | E15: 1000 | F15: 91.14 | G15: =E15*F15 -> 91140 | J15: =H15*I15 -> 0 | K15: =G15+J15 -> 91140 | M15: =M14+K15-L15 -> 472818.55
A16: 13 | B16: 45729 | G16: =E16*F16 -> 0 | J16: =H16*I16 -> 0 | K16: =G16+J16 -> 0 | M16: =M15+K16-L16 -> 472818.55
A17: 14 | B17: 45730 | G17: =E17*F17 -> 0 | J17: =H17*I17 -> 0 | K17: =G17+J17 -> 0 | M17: =M16+K17-L17 -> 472818.55
A18: 15 | B18: 45731 | G18: =E18*F18 -> 0 | J18: =H18*I18 -> 0 | K18: =G18+J18 -> 0 | M18: =M17+K18-L18 -> 472818.55
A19: 16 | B19: 45732 | G19: =E19*F19 -> 0 | J19: =H19*I19 -> 0 | K19: =G19+J19 -> 0 | M19: =M18+K19-L19 -> 472818.55
A20: 17 | B20: 45733 | G20: =E20*F20 -> 0 | J20: =H20*I20 -> 0 | K20: =G20+J20 -> 0 | M20: =M19+K20-L20 -> 472818.55
A21: 18 | B21: 45734 | E21: 3000 | F21: 91.14 | G21: =E21*F21 -> 273420 | H21: 20 | I21: 104.6 | J21: =H21*I21 -> 2092 | K21: =G21+J21 -> 275512 | M21: =M20+K21-L21 -> 748330.55
A22: 19 | B22: 45735 | G22: =E22*F22 -> 0 | J22: =H22*I22 -> 0 | K22: =G22+J22 -> 0 | M22: =M21+K22-L22 -> 748330.55 | Q22: =3800/26 -> 146.15385
A23: 20 | B23: 45736 | J23: =H23*I23 -> 0 | K23: =G23+J23 -> 0 | M23: =M22+K23-L23 -> 748330.55 | O23: Lubricant Purchaged
A24: 21 | B24: 45737 | G24: =E24*F24 -> 0 | J24: =H24*I24 -> 0 | K24: =G24+J24 -> 0 | M24: =M23+K24-L24 -> 748330.55
A25: 22 | B25: 45738 | G25: =E25*F25 -> 0 | J25: =H25*I25 -> 0 | K25: =G25+J25 -> 0 | M25: =M24+K25-L25 -> 748330.55
A26: 23 | B26: 45739 | E26: 2000 | F26: 91.14 | G26: =E26*F26 -> 182280 | H26: 10 | I26: 104.6 | J26: =H26*I26 -> 1046 | K26: =G26+J26 -> 183326 | M26: =M25+K26-L26 -> 931656.55
A27: 24 | B27: 45740 | G27: =E27*F27 -> 0 | J27: =H27*I27 -> 0 | K27: =G27+J27 -> 0 | M27: =M26+K27-L27 -> 931656.55
A28: 25 | B28: 45741 | G28: =E28*F28 -> 0 | J28: =H28*I28 -> 0 | K28: =G28+J28 -> 0 | M28: =M27+K28-L28 -> 931656.55
A29: 26 | B29: 45742 | E29: 400 | F29: 91.14 | G29: =E29*F29 -> 36456 | H29: 10 | I29: 104.6 | J29: =H29*I29 -> 1046 | K29: =G29+J29 -> 37502 | M29: =M28+K29-L29 -> 969158.55
A30: 27 | B30: 45743 | G30: =E30*F30 -> 0 | J30: =H30*I30 -> 0 | K30: =G30+J30 -> 0 | M30: =M29+K30-L30 -> 969158.55
A31: 28 | B31: 45744 | E31: 2000 | F31: 91.14 | G31: =E31*F31 -> 182280 | H31: 10 | I31: 104.6 | J31: =H31*I31 -> 1046 | K31: =G31+J31 -> 183326 | M31: =M30+K31-L31 -> 1152484.5
A32: 29 | B32: 45745 | G32: =E32*F32 -> 0 | J32: =H32*I32 -> 0 | K32: =G32+J32 -> 0 | M32: =M31+K32-L32 -> 1152484.5
A33: 30 | B33: 45746 | E33: 3400 | F33: 91.14 | G33: =E33*F33 -> 309876 | H33: 10 | I33: 104.6 | J33: =H33*I33 -> 1046 | K33: =G33+J33 -> 310922 | M33: =M32+K33-L33 -> 1463406.5
A34: 31 | B34: 45747 | G34: =E34*F34 -> 0 | J34: =H34*I34 -> 0 | K34: =G34+J34 -> 0 | M34: =M33+K34-L34 -> 1463406.5
A35: 32 | G35: =E35*F35 -> 0 | J35: =H35*I35 -> 0 | K35: =G35+J35 -> 0 | M35: =M34+K35-L35 -> 1463406.5
A36: 31 | G36: =E36*F36 -> 0 | J36: =H36*I36 -> 0 | K36: =G36+J36 -> 0 | M36: =M35+K36-L36 -> 1463406.5
A37: 32 | E37: 0 | F37: 0 | G37: =E37*F37 -> 0 | J37: =H37*I37 -> 0 | K37: =G37+J37 -> 0 | M37: =M36+K37-L37 -> 1463406.5 | P37: 1194597.7 | Q37: =P37-M37 -> -268808.84
E38: =SUM(E4:E37) -> 14800 | G38: =SUM(G4:G37) -> 1348872 | H38: =SUM(H4:H37) -> 110.21 | J38: =SUM(J4:J37) -> 11527.966 | K38: =SUM(K4:K37) -> 1360400 | L38: =SUM(L4:L37) -> 0

Sheet  Haveri-2
A1: Magavi fuel F/S
A2: S.No | B2: Date | C2: GRN No | D2: Ind No/Bill No | E2: Diesel (Lts) | F2: Price | G2: Amount | H2: Petrol (Lts) | I2: Price | J2: Amount | K2: Total amount | L2: Amount paid | M2: As on Date | N2: Remarks
D3: Opening Balance | L3: 90409.199 | M3: 90409.199
A4: 1 | B4: 46082 | E4: 71 | F4: 91.49 | G4: =E4*F4 -> 6495.79 | I4: 103.43 | J4: =H4*I4 -> 0 | K4: =G4+J4 -> 6495.79 | L4: 0 | M4: =M3+K4-L4 -> 96904.989
A5: 2 | B5: 46083 | G5: =E5*F5 -> 0 | J5: =H5*I5 -> 0 | K5: =G5+J5 -> 0 | L5: 0 | M5: =M4+K5-L5 -> 96904.989
A6: 3 | B6: 46084 | E6: 80.01 | F6: 91.49 | G6: =E6*F6 -> 7320.1149 | H6: 9.01 | I6: 103.43 | J6: =H6*I6 -> 931.9043 | K6: =G6+J6 -> 8252.0192 | L6: 0 | M6: =M5+K6-L6 -> 105157.01
A7: 4 | B7: 46085 | E7: 65 | F7: 91.49 | G7: =E7*F7 -> 5946.85 | J7: =H7*I7 -> 0 | K7: =G7+J7 -> 5946.85 | L7: 0 | M7: =M6+K7-L7 -> 111103.86
A8: 5 | B8: 46086 | E8: 165.2 | F8: 91.49 | G8: =E8*F8 -> 15114.148 | H8: 11 | I8: 103.43 | J8: =H8*I8 -> 1137.73 | K8: =G8+J8 -> 16251.878 | L8: 0 | M8: =M7+K8-L8 -> 127355.74
A9: 6 | B9: 46087 | G9: =E9*F9 -> 0 | J9: =H9*I9 -> 0 | K9: =G9+J9 -> 0 | L9: 0 | M9: =M8+K9-L9 -> 127355.74
A10: 7 | B10: 46088 | E10: 110 | F10: 91.49 | G10: =E10*F10 -> 10063.9 | H10: 10 | I10: 103.43 | J10: =H10*I10 -> 1034.3 | K10: =G10+J10 -> 11098.2 | L10: 0 | M10: =M9+K10-L10 -> 138453.94
A11: 8 | B11: 46089 | E11: 20 | F11: 91.49 | G11: =E11*F11 -> 1829.8 | H11: 0 | I11: 103.43 | J11: =H11*I11 -> 0 | K11: =G11+J11 -> 1829.8 | L11: 0 | M11: =M10+K11-L11 -> 140283.74
A12: 9 | B12: 46090 | E12: 37.1 | F12: 91.49 | G12: =E12*F12 -> 3394.279 | H12: 13 | I12: 103.43 | J12: =H12*I12 -> 1344.59 | K12: =G12+J12 -> 4738.869 | L12: 0 | M12: =M11+K12-L12 -> 145022.6 | O12: .
A13: 10 | B13: 46091 | E13: 45 | F13: 91.49 | G13: =E13*F13 -> 4117.05 | J13: =H13*I13 -> 0 | K13: =G13+J13 -> 4117.05 | L13: 0 | M13: =M12+K13-L13 -> 149139.65
A14: 11 | B14: 46092 | E14: 17.05 | F14: 91.47 | G14: =E14*F14 -> 1559.5635 | H14: 0 | I14: 0 | J14: =H14*I14 -> 0 | K14: =G14+J14 -> 1559.5635 | L14: =H14+K14 -> 1559.5635 | M14: =M13+K14-L14 -> 149139.65
B15: 46092 | H15: 6 | I15: 103.43 | J15: =H15*I15 -> 620.58 | K15: =G15+J15 -> 620.58 | M15: =M14+K15-L15 -> 149760.23
A16: 12 | B16: 46093 | E16: 156 | F16: 91.49 | G16: =E16*F16 -> 14272.44 | J16: =H16*I16 -> 0 | K16: =G16+J16 -> 14272.44 | L16: 150000 | M16: =M15+K16-L16 -> 14032.675
A17: 13 | B17: 46094 | E17: 15.67 | F17: 91.49 | G17: =E17*F17 -> 1433.6483 | H17: 5.6 | I17: 110.67 | J17: =H17*I17 -> 619.752 | K17: =G17+J17 -> 2053.4003 | L17: 0 | M17: =M16+K17-L17 -> 16086.075
A18: 14 | B18: 46095 | E18: 118 | F18: 91.49 | G18: =E18*F18 -> 10795.82 | H18: 14.5 | I18: 103.43 | J18: =H18*I18 -> 1499.735 | K18: =G18+J18 -> 12295.555 | L18: 0 | M18: =M17+K18-L18 -> 28381.63
A19: 15 | B19: 46096 | G19: =E19*F19 -> 0 | J19: =H19*I19 -> 0 | K19: =G19+J19 -> 0 | L19: 0 | M19: =M18+K19-L19 -> 28381.63
A20: 16 | B20: 46097 | E20: 257.73 | F20: 91.49 | G20: =E20*F20 -> 23579.718 | J20: =H20*I20 -> 0 | K20: =G20+J20 -> 23579.718 | L20: 0 | M20: =M19+K20-L20 -> 51961.348
A21: 17 | B21: 46098 | G21: =E21*F21 -> 0 | J21: =H21*I21 -> 0 | K21: =G21+J21 -> 0 | L21: 0 | M21: =M20+K21-L21 -> 51961.348 | R21: 141649
A22: 18 | B22: 46099 | E22: 35 | F22: 91.49 | G22: =E22*F22 -> 3202.15 | H22: 6 | I22: 103.43 | J22: =H22*I22 -> 620.58 | K22: =G22+J22 -> 3822.73 | L22: 0 | M22: =M21+K22-L22 -> 55784.078
A23: 19 | B23: 46100 | E23: 235.01 | F23: 91.49 | G23: =E23*F23 -> 21501.065 | J23: =H23*I23 -> 0 | K23: =G23+J23 -> 21501.065 | L23: 0 | M23: =M22+K23-L23 -> 77285.143
A24: 20 | B24: 46101 | G24: =E24*F24 -> 0 | J24: =H24*I24 -> 0 | K24: =G24+J24 -> 0 | L24: 0 | M24: =M23+K24-L24 -> 77285.143
A25: 21 | B25: 46102 | G25: =E25*F25 -> 0 | J25: =H25*I25 -> 0 | K25: =G25+J25 -> 0 | L25: 0 | M25: =M24+K25-L25 -> 77285.143
A26: 22 | B26: 46103 | G26: =E26*F26 -> 0 | J26: =H26*I26 -> 0 | K26: =G26+J26 -> 0 | L26: 0 | M26: =M25+K26-L26 -> 77285.143
A27: 23 | B27: 46104 | G27: =E27*F27 -> 0 | J27: =H27*I27 -> 0 | K27: =G27+J27 -> 0 | L27: 0 | M27: =M26+K27-L27 -> 77285.143
A28: 24 | B28: 46105 | G28: =E28*F28 -> 0 | J28: =H28*I28 -> 0 | K28: =G28+J28 -> 0 | L28: 0 | M28: =M27+K28-L28 -> 77285.143
A29: 25 | B29: 46106 | G29: =E29*F29 -> 0 | J29: =H29*I29 -> 0 | K29: =G29+J29 -> 0 | L29: 0 | M29: =M28+K29-L29 -> 77285.143
A30: 26 | B30: 46107 | G30: =E30*F30 -> 0 | J30: =H30*I30 -> 0 | K30: =G30+J30 -> 0 | L30: 0 | M30: =M29+K30-L30 -> 77285.143
A31: 27 | B31: 46108 | G31: =E31*F31 -> 0 | J31: =H31*I31 -> 0 | K31: =G31+J31 -> 0 | L31: 0 | M31: =M30+K31-L31 -> 77285.143
A32: 28 | B32: 46109 | G32: =E32*F32 -> 0 | J32: =H32*I32 -> 0 | K32: =G32+J32 -> 0 | L32: 0 | M32: =M31+K32-L32 -> 77285.143 | R32: 46.61
A33: 29 | B33: 46110 | G33: =E33*F33 -> 0 | J33: =H33*I33 -> 0 | K33: =G33+J33 -> 0 | L33: 0 | M33: =M32+K33-L33 -> 77285.143 | R33: 100
A34: 30 | B34: 46111 | G34: =E34*F34 -> 0 | J34: =H34*I34 -> 0 | K34: =G34+J34 -> 0 | L34: 0 | M34: =M33+K34-L34 -> 77285.143 | R34: 35
A35: 31 | B35: 46112 | G35: =E35*F35 -> 0 | J35: =H35*I35 -> 0 | K35: =G35+J35 -> 0 | L35: 0 | M35: =M34+K35-L35 -> 77285.143 | N35: BPCL OTP
A36: 32 | G36: =E36*F36 -> 0 | J36: =H36*I36 -> 0 | K36: =G36+J36 -> 0 | L36: 0 | M36: =M35+K36-L36 -> 77285.143
H37: 0 | I37: 0 | M37: =M36+K37-L37 -> 77285.143
E38: =SUM(E4:E36) -> 1427.77 | G38: =SUM(G4:G36) -> 130626.34 | H38: =SUM(H4:H36) -> 75.11 | J38: =SUM(J4:J36) -> 7809.1713 | K38: =SUM(K4:K36) -> 138435.51 | L38: =SUM(L4:L36) -> 151559.56
I41: =K26+L26 -> 0

Sheet  Guttal-2
A1: Himagiri Petroleum
A2: S.No | B2: Date | C2: GRN No | D2: Ind No/Bill No | E2: Diesel (Lts) | F2: Price | G2: Amount | H2: Petrol (Lts) | I2: Price | J2: Amount | K2: Total amount | L2: Amount paid | M2: As on Date | N2: Remarks
D3: Opening Balance | K3: 118610.55 | L3: 0 | M3: 118610.55
A4: 1 | B4: 45717 | G4: =E4*F4 -> 0 | J4: =H4*I4 -> 0 | K4: =G4+J4 -> 0 | M4: =M3+K4-L4 -> 118610.55
A5: 2 | B5: 45718 | E5: 60 | F5: 91.78 | G5: =E5*F5 -> 5506.8 | H5: 15 | I5: 103.74 | J5: =H5*I5 -> 1556.1 | K5: =G5+J5 -> 7062.9 | M5: =M4+K5-L5 -> 125673.45
A6: 3 | B6: 45719 | E6: 75 | F6: 91.78 | G6: =E6*F6 -> 6883.5 | H6: 5 | I6: 103.74 | J6: =H6*I6 -> 518.7 | K6: =G6+J6 -> 7402.2 | M6: =M5+K6-L6 -> 133075.65
A7: 4 | B7: 45720 | G7: =E7*F7 -> 0 | J7: =H7*I7 -> 0 | K7: =G7+J7 -> 0 | M7: =M6+K7-L7 -> 133075.65
A8: 5 | B8: 45721 | E8: 60 | F8: 91.78 | G8: =E8*F8 -> 5506.8 | J8: =H8*I8 -> 0 | K8: =G8+J8 -> 5506.8 | M8: =M7+K8-L8 -> 138582.45
A9: 6 | B9: 45722 | E9: 90 | F9: 91.78 | G9: =E9*F9 -> 8260.2 | J9: =H9*I9 -> 0 | K9: =G9+J9 -> 8260.2 | M9: =M8+K9-L9 -> 146842.65
A10: 7 | B10: 45723 | E10: 97.4 | F10: 91.78 | G10: =E10*F10 -> 8939.372 | H10: 13 | I10: 103.74 | J10: =H10*I10 -> 1348.62 | K10: =G10+J10 -> 10287.992 | M10: =M9+K10-L10 -> 157130.64
A11: 8 | B11: 45724 | E11: 100 | F11: 91.78 | G11: =E11*F11 -> 9178 | J11: =H11*I11 -> 0 | K11: =G11+J11 -> 9178 | M11: =M10+K11-L11 -> 166308.64
A12: 9 | B12: 45725 | E12: 60 | F12: 91.78 | G12: =E12*F12 -> 5506.8 | H12: 5 | I12: 103.74 | J12: =H12*I12 -> 518.7 | K12: =G12+J12 -> 6025.5 | M12: =M11+K12-L12 -> 172334.14 | O12: .
A13: 10 | B13: 45726 | E13: 344.01 | F13: 91.78 | G13: =E13*F13 -> 31573.238 | H13: 10 | I13: 103.74 | J13: =H13*I13 -> 1037.4 | K13: =G13+J13 -> 32610.638 | M13: =M12+K13-L13 -> 204944.78
A14: 11 | B14: 45727 | G14: =E14*F14 -> 0 | J14: =H14*I14 -> 0 | K14: =G14+J14 -> 0 | M14: =M13+K14-L14 -> 204944.78
A15: 12 | B15: 45728 | E15: 185 | F15: 91.78 | G15: =E15*F15 -> 16979.3 | H15: 5 | I15: 103.74 | J15: =H15*I15 -> 518.7 | K15: =G15+J15 -> 17498 | L15: 160000 | M15: =M14+K15-L15 -> 62442.776
A16: 13 | B16: 45729 | E16: 280 | F16: 91.78 | G16: =E16*F16 -> 25698.4 | H16: 5 | I16: 103.74 | J16: =H16*I16 -> 518.7 | K16: =G16+J16 -> 26217.1 | M16: =M15+K16-L16 -> 88659.876
A17: 14 | B17: 45730 | E17: 65 | F17: 91.78 | G17: =E17*F17 -> 5965.7 | J17: =H17*I17 -> 0 | K17: =G17+J17 -> 5965.7 | M17: =M16+K17-L17 -> 94625.576
A18: 15 | B18: 45731 | E18: 320 | F18: 91.78 | G18: =E18*F18 -> 29369.6 | J18: =H18*I18 -> 0 | K18: =G18+J18 -> 29369.6 | M18: =M17+K18-L18 -> 123995.18
A19: 16 | B19: 45732 | E19: 214 | F19: 91.78 | G19: =E19*F19 -> 19640.92 | H19: 5 | I19: 103.74 | J19: =H19*I19 -> 518.7 | K19: =G19+J19 -> 20159.62 | M19: =M18+K19-L19 -> 144154.8
A20: 17 | B20: 45733 | E20: 235 | F20: 91.78 | G20: =E20*F20 -> 21568.3 | J20: =H20*I20 -> 0 | K20: =G20+J20 -> 21568.3 | M20: =M19+K20-L20 -> 165723.1
A21: 18 | B21: 45734 | E21: 190 | F21: 91.78 | G21: =E21*F21 -> 17438.2 | J21: =H21*I21 -> 0 | K21: =G21+J21 -> 17438.2 | M21: =M20+K21-L21 -> 183161.3
A22: 19 | B22: 45735 | G22: =E22*F22 -> 0 | J22: =H22*I22 -> 0 | K22: =G22+J22 -> 0 | M22: =M21+K22-L22 -> 183161.3
A23: 20 | B23: 45736 | E23: 150 | F23: 91.78 | G23: =E23*F23 -> 13767 | H23: 15 | I23: 103.74 | J23: =H23*I23 -> 1556.1 | K23: =G23+J23 -> 15323.1 | M23: =M22+K23-L23 -> 198484.4
A24: 21 | B24: 45737 | G24: =E24*F24 -> 0 | H24: 5 | I24: 103.74 | J24: =H24*I24 -> 518.7 | K24: =G24+J24 -> 518.7 | M24: =M23+K24-L24 -> 199003.1
A25: 22 | B25: 45738 | E25: 285 | F25: 91.78 | G25: =E25*F25 -> 26157.3 | J25: =H25*I25 -> 0 | K25: =G25+J25 -> 26157.3 | M25: =M24+K25-L25 -> 225160.4
A26: 23 | B26: 45739 | E26: 135 | F26: 91.78 | G26: =E26*F26 -> 12390.3 | H26: 7 | I26: 103.74 | J26: =H26*I26 -> 726.18 | K26: =G26+J26 -> 13116.48 | M26: =M25+K26-L26 -> 238276.88
A27: 24 | B27: 45740 | E27: 353 | F27: 91.78 | G27: =E27*F27 -> 32398.34 | H27: 11 | I27: 103.74 | J27: =H27*I27 -> 1141.14 | K27: =G27+J27 -> 33539.48 | M27: =M26+K27-L27 -> 271816.36
A28: 25 | B28: 45741 | E28: 342.55 | F28: 91.78 | G28: =E28*F28 -> 31439.239 | H28: 20 | I28: 103.74 | J28: =H28*I28 -> 2074.8 | K28: =G28+J28 -> 33514.039 | M28: =M27+K28-L28 -> 305330.39 | R28: `
A29: 26 | B29: 45742 | E29: 15 | F29: 91.78 | G29: =E29*F29 -> 1376.7 | H29: 10 | I29: 103.74 | J29: =H29*I29 -> 1037.4 | K29: =G29+J29 -> 2414.1 | L29: 150000 | M29: =M28+K29-L29 -> 157744.49 | Q29: 30
A30: 27 | B30: 45743 | E30: 116 | F30: 91.78 | G30: =E30*F30 -> 10646.48 | H30: 15 | I30: 103.74 | J30: =H30*I30 -> 1556.1 | K30: =G30+J30 -> 12202.58 | M30: =M29+K30-L30 -> 169947.07 | Q30: 20.02
A31: 28 | B31: 45744 | E31: 80 | F31: 91.78 | G31: =E31*F31 -> 7342.4 | J31: =H31*I31 -> 0 | K31: =G31+J31 -> 7342.4 | M31: =M30+K31-L31 -> 177289.47
A32: 29 | B32: 45745 | G32: =E32*F32 -> 0 | J32: =H32*I32 -> 0 | K32: =G32+J32 -> 0 | M32: =M31+K32-L32 -> 177289.47
A33: 30 | B33: 45746 | E33: 132 | F33: 91.78 | G33: =E33*F33 -> 12114.96 | H33: 0 | I33: 0 | J33: =H33*I33 -> 0 | K33: =G33+J33 -> 12114.96 | M33: =M32+K33-L33 -> 189404.43
A34: 31 | B34: 45747 | E34: 130 | F34: 91.78 | G34: =E34*F34 -> 11931.4 | H34: 25 | I34: 103.74 | J34: =H34*I34 -> 2593.5 | K34: =G34+J34 -> 14524.9 | L34: 0 | M34: =M33+K34-L34 -> 203929.33
E35: =SUM(E4:E34) -> 4113.96 | G35: =SUM(G4:G34) -> 377579.25 | H35: =SUM(H4:H34) -> 171 | J35: =SUM(J4:J34) -> 17739.54 | K35: =SUM(K4:K34) -> 395318.79 | L35: =SUM(L4:L34) -> 310000
I38: =K24+L24 -> 518.7

Sheet Rattihali
A1: Shree Siri Gowari petroliam
A2: S.No | B2: Date | C2: GRN No | D2: Ind No/Bill No | E2: Diesel (Lts) | F2: Price | G2: Amount | H2: Petrol (Lts) | I2: Price | J2: Amount | K2: Total amount | L2: Amount paid | M2: As on Date | N2: Remarks
D3: Opening Balance | K3: 6442.724 | M3: 6442.724
A4: 1 | B4: 46082 | F4: 0 | G4: =E4*F4 -> 0 | H4: 0 | I4: 0 | J4: =H4*I4 -> 0 | K4: =G4+J4 -> 0 | L4: 0 | M4: =M3+K4-L4 -> 6442.724
A5: 2 | B5: 46083 | F5: 0 | G5: =E5*F5 -> 0 | H5: 0 | I5: 0 | J5: =H5*I5 -> 0 | K5: =G5+J5 -> 0 | L5: 6422 | M5: =M4+K5-L5 -> 20.724
A6: 3 | B6: 46084 | F6: 0 | G6: =E6*F6 -> 0 | H6: 0 | I6: 0 | J6: =H6*I6 -> 0 | K6: =G6+J6 -> 0 | L6: 20.72 | M6: =M5+K6-L6 -> 0.004 | N6: Round off
A7: 4 | B7: 46085 | F7: 0 | G7: =E7*F7 -> 0 | H7: 0 | I7: 0 | J7: =H7*I7 -> 0 | K7: =G7+J7 -> 0 | L7: 0 | M7: =M6+K7-L7 -> 0.004
A8: 5 | B8: 46086 | F8: 0 | G8: =E8*F8 -> 0 | H8: 0 | I8: 0 | J8: =H8*I8 -> 0 | K8: =G8+J8 -> 0 | L8: 0 | M8: =M7+K8-L8 -> 0.004
A9: 6 | B9: 46087 | F9: 0 | G9: =E9*F9 -> 0 | H9: 0 | I9: 0 | J9: =H9*I9 -> 0 | K9: =G9+J9 -> 0 | L9: 0 | M9: =M8+K9-L9 -> 0.004
A10: 7 | B10: 46088 | F10: 0 | G10: =E10*F10 -> 0 | H10: 0 | I10: 0 | J10: =H10*I10 -> 0 | K10: =G10+J10 -> 0 | L10: 0 | M10: =M9+K10-L10 -> 0.004
A11: 8 | B11: 46089 | F11: 0 | G11: =E11*F11 -> 0 | H11: 0 | I11: 0 | J11: =H11*I11 -> 0 | K11: =G11+J11 -> 0 | L11: 0 | M11: =M10+K11-L11 -> 0.004
A12: 9 | B12: 46090 | F12: 0 | G12: =E12*F12 -> 0 | H12: 0 | I12: 0 | J12: =H12*I12 -> 0 | K12: =G12+J12 -> 0 | L12: 0 | M12: =M11+K12-L12 -> 0.004 | O12: .
A13: 10 | B13: 46091 | F13: 0 | G13: =E13*F13 -> 0 | H13: 0 | I13: 0 | J13: =H13*I13 -> 0 | K13: =G13+J13 -> 0 | L13: 0 | M13: =M12+K13-L13 -> 0.004
A14: 11 | B14: 46092 | F14: 0 | G14: =E14*F14 -> 0 | H14: 0 | I14: 0 | J14: =H14*I14 -> 0 | K14: =G14+J14 -> 0 | L14: 0 | M14: =M13+K14-L14 -> 0.004
A15: 12 | B15: 46093 | F15: 0 | G15: =E15*F15 -> 0 | H15: 0 | I15: 0 | J15: =H15*I15 -> 0 | K15: =G15+J15 -> 0 | L15: 0 | M15: =M14+K15-L15 -> 0.004
A16: 13 | B16: 46094 | F16: 0 | G16: =E16*F16 -> 0 | H16: 0 | I16: 0 | J16: =H16*I16 -> 0 | K16: =G16+J16 -> 0 | L16: 0 | M16: =M15+K16-L16 -> 0.004
A17: 14 | B17: 46095 | F17: 0 | G17: =E17*F17 -> 0 | H17: 0 | I17: 0 | J17: =H17*I17 -> 0 | K17: =G17+J17 -> 0 | L17: 0 | M17: =M16+K17-L17 -> 0.004
A18: 15 | B18: 46096 | F18: 0 | G18: =E18*F18 -> 0 | H18: 0 | I18: 0 | J18: =H18*I18 -> 0 | K18: =G18+J18 -> 0 | L18: 0 | M18: =M17+K18-L18 -> 0.004
A19: 16 | B19: 46097 | F19: 0 | G19: =E19*F19 -> 0 | H19: 0 | I19: 0 | J19: =H19*I19 -> 0 | K19: =G19+J19 -> 0 | L19: 0 | M19: =M18+K19-L19 -> 0.004
A20: 17 | B20: 46098 | F20: 0 | G20: =E20*F20 -> 0 | H20: 0 | I20: 0 | J20: =H20*I20 -> 0 | K20: =G20+J20 -> 0 | L20: 0 | M20: =M19+K20-L20 -> 0.004
A21: 18 | B21: 46099 | F21: 0 | G21: =E21*F21 -> 0 | H21: 0 | I21: 0 | J21: =H21*I21 -> 0 | K21: =G21+J21 -> 0 | L21: 0 | M21: =M20+K21-L21 -> 0.004
A22: 19 | B22: 46100 | G22: =E22*F22 -> 0 | H22: 0 | I22: 0 | J22: =H22*I22 -> 0 | K22: =G22+J22 -> 0 | L22: 0 | M22: =M21+K22-L22 -> 0.004
A23: 20 | B23: 46101 | G23: =E23*F23 -> 0 | H23: 0 | I23: 0 | J23: =H23*I23 -> 0 | K23: =G23+J23 -> 0 | L23: 0 | M23: =M22+K23-L23 -> 0.004
A24: 21 | B24: 46102 | G24: =E24*F24 -> 0 | H24: 0 | I24: 0 | J24: =H24*I24 -> 0 | K24: =G24+J24 -> 0 | L24: 0 | M24: =M23+K24-L24 -> 0.004
A25: 22 | B25: 46103 | G25: =E25*F25 -> 0 | H25: 0 | I25: 0 | J25: =H25*I25 -> 0 | K25: =G25+J25 -> 0 | L25: 0 | M25: =M24+K25-L25 -> 0.004
