Workbook

Sheet Feb-2026
A1: S.no | B1: Site Name | C1: Bunk Name | D1: Diesel(Liters) | E1: Diesel Amount | F1: Petrol(Liters) | G1: Petrol Amount | H1: Total Amount | I1: Opening Blance | J1: Amount Paid | K1: Closing Balances
A2: 1 | B2: Khammam-1 | C2: Divya laxmi ganapathi | D2: =+'Khammam-1'!E38 -> 87280.64 | E2: =+'Khammam-1'!G38 -> 8351011.6 | F2: =+'Khammam-1'!H38 -> 455 | G2: =+'Khammam-1'!J38 -> 48894.3 | H2: =E2+G2 -> 8399905.9 | I2: =+'Khammam-1'!K3 -> 2836061 | J2: =+'Khammam-1'!L38 -> 2998712 | K2: =H2+I2-J2 -> 8237254.9
A3: 2 | B3: Khammam-2 | C3: Jayasai union bunk | D3: =+'Khammam-2'!E35 -> 81063.05 | E3: =+'Khammam-2'!G35 -> 7758252 | F3: =+'Khammam-2'!H35 -> 630 | G3: =+'Khammam-2'!J35 -> 67714.35 | H3: =E3+G3 -> 7825966.4 | I3: =+'Khammam-2'!K3 -> 4435776.8 | J3: =+'Khammam-2'!L35 -> 6705886 | K3: =H3+I3-J3 -> 5555857.2
A4: 3 | B4: Khammam-3 | C4: JSASFuel Genie India Pvt.Ltd | D4: =+'Khammam-3'!E35 -> 101973 | E4: =+'Khammam-3'!G35 -> 9656843.1 | F4: =+'Khammam-3'!H35 -> 0 | G4: =+'Khammam-3'!J35 -> 0 | H4: =E4+G4 -> 9656843.1 | I4: =+'Khammam-3'!M3 -> 120400 | J4: =+'Khammam-3'!L35 -> 8637100 | K4: =H4+I4-J4 -> 1140143.1
A5: 4 | B5: Jadcherla-3 | C5: JSASFuel Genie India Pvt.Ltd | D5: =+'Jadcherla-3'!E35 -> 25225 | E5: =+'Jadcherla-3'!G35 -> 2407221.8 | F5: =+'Jadcherla-3'!H35 -> 0 | G5: =+'Jadcherla-3'!J35 -> 0 | H5: =E5+G5 -> 2407221.8 | I5: =+'Jadcherla-3'!M3 -> 299056.5 | J5: =+'Jadcherla-3'!L35 -> 1680000 | K5: =H5+I5-J5 -> 1026278.2
A6: 5 | B6: Jadcherla-4 | C6: Shree Poornima F/S | D6: =+'Jadcherla-4'!E35 -> 0 | E6: =+'Jadcherla-4'!G35 -> 0 | F6: =+'Jadcherla-4'!H35 -> 180 | G6: =+'Jadcherla-4'!J35 -> 19458 | H6: =E6+G6 -> 19458 | I6: =+'Jadcherla-4'!M3 -> 5405 | J6: =+'Jadcherla-4'!L35 -> 0 | K6: =H6+I6-J6 -> 24863
A7: 6 | B7: Dindi | C7: Akarapu Balakistamma Fillling | D7: =+Dindi!E35 -> 0 | E7: =+Dindi!G35 -> 0 | F7: =+Dindi!H35 -> 0 | G7: =+Dindi!J35 -> 0 | H7: =E7+G7 -> 0 | I7: =+Dindi!M3 -> 0 | J7: =+Dindi!L35 -> 0 | K7: =H7+I7-J7 -> 0
A8: 7 | B8: Devarkhadra-1 | C8: Kurumurthy Swami F/S | D8: =+Devarakhadra!E35 -> 10 | E8: =+Devarakhadra!G35 -> 971 | F8: =+Devarakhadra!H35 -> 13 | G8: =+Devarakhadra!J35 -> 1414.79 | H8: =E8+G8 -> 2385.79 | I8: =+Devarakhadra!M3 -> 5856.2924 | J8: =+Devarakhadra!L35 -> 8242.08 | K8: =H8+I8-J8 -> 0.0023999999
A9: 8 | B9: Sangareddy | C9: Durga indhan | D9: =+' Sanga reddy-1'!E35 -> 1553.08 | E9: =+' Sanga reddy-1'!G35 -> 149654.79 | F9: =+' Sanga reddy-1'!H35 -> 19 | G9: =+' Sanga reddy-1'!J35 -> 2055.23 | H9: =E9+G9 -> 151710.02 | I9: =+' Sanga reddy-1'!M3 -> 0 | J9: =+' Sanga reddy-1'!L35 -> 0 | K9: =H9+I9-J9 -> 151710.02
A10: 9 | B10: Madanapalli | D10: =+'Madana palli'!E35 -> 215.39 | E10: =+'Madana palli'!G35 -> 21057.448 | F10: =+'Madana palli'!H35 -> 23.33 | G10: =+'Madana palli'!J35 -> 2557.2013 | H10: =E10+G10 -> 23614.649 | I10: =+'Madana palli'!M3 -> 0 | J10: =+'Madana palli'!L35 -> 23614.649 | K10: =H10+I10-J10 -> 0
A11: 10 | B11: Amalapuram | C11: Sathya Filling Station | D11: =+Amalapuram!E38 -> 530.07 | E11: =+Amalapuram!G38 -> 49919.954 | F11: =+Amalapuram!H38 -> 171.5 | G11: =+Amalapuram!J38 -> 18448.05 | H11: =E11+G11 -> 68368.004 | I11: =+Amalapuram!M3 -> 0 | J11: =+Amalapuram!L38 -> 68366.97 | K11: =H11+I11-J11 -> 1.0336
A12: 11 | B12: YG Gudda-2 | C12: Pankaja HP Fuel Center | D12: =+'YG Gudda-2'!E36 -> 12500 | E12: =+'YG Gudda-2'!G36 -> 1141625 | F12: =+'YG Gudda-2'!H36 -> 385 | G12: =+'YG Gudda-2'!J36 -> 39758.95 | H12: =E12+G12 -> 1181383.9 | I12: =+'YG Gudda-2'!M3 -> 478336.85 | J12: =+'YG Gudda-2'!L36 -> 1128337 | K12: =H12+I12-J12 -> 531383.8
A13: 12 | B13: Hosadurga-1 | C13: Merchant Petroliums | D13: =+Hosadurga!E35 -> 0 | E13: =+Hosadurga!G35 -> 0 | F13: =+Hosadurga!H35 -> 0 | G13: =+Hosadurga!J35 -> 0 | H13: =E13+G13 -> 0 | I13: =+Hosadurga!K3 -> 2258.6 | J13: =+Hosadurga!L35 -> 2260 | K13: =H13+I13-J13 -> -1.4
A14: 13 | B14: Hosadurga-2 | C14: Shree Veeraprathap Fuel | D14: =+'Hosadurga -2'!E35 -> 7300 | E14: =+'Hosadurga -2'!G35 -> 668315 | F14: =+'Hosadurga -2'!H35 -> 280 | G14: =+'Hosadurga -2'!J35 -> 29044.4 | H14: =+'Hosadurga -2'!K35 -> 697359.4 | I14: =+'Hosadurga -2'!K3 -> 325898.2 | J14: =+'Hosadurga -2'!L35 -> 825898.2 | K14: =H14+I14-J14 -> 197359.4
A15: 14 | B15: Malebennuru(KUWSDB) | C15: Sri Ramanjuneya Service Station | D15: =+'Malebenur(KUWSDB)'!E37 -> 4200 | E15: =+'Malebenur(KUWSDB)'!G37 -> 387114 | F15: =+'Malebenur(KUWSDB)'!H37 -> 180 | G15: =+'Malebenur(KUWSDB)'!J37 -> 18725.4 | H15: =E15+G15 -> 405839.4 | I15: =+'Malebenur(KUWSDB)'!K3 -> 213698.56 | J15: =+'Malebenur(KUWSDB)'!L37 -> 560585 | K15: =H15+I15-J15 -> 58952.96
A16: 15 | B16: kadur | C16: Vishal Service Station | D16: =+Kadur!E35 -> 2500 | E16: =+Kadur!G35 -> 230375 | F16: =+Kadur!H35 -> 100 | G16: =+Kadur!J35 -> 10427 | H16: =E16+G16 -> 240802 | I16: =+Kadur!K3 -> 14627.031 | J16: =+Kadur!L35 -> 14492 | K16: =H16+I16-J16 -> 240937.03
A17: 16 | B17: Hiriyur(VJNL) | C17: Sri Balaji Agencies | D17: =+'Hiriyur(VJNL)'!E35 -> 2400 | E17: =+'Hiriyur(VJNL)'!G35 -> 221424 | F17: =+'Hiriyur(VJNL)'!H35 -> 245 | G17: =+'Hiriyur(VJNL)'!J35 -> 25511.85 | H17: =E17+G17 -> 246935.85 | I17: =+'Hiriyur(VJNL)'!K3 -> 219486.1 | J17: =+'Hiriyur(VJNL)'!L35 -> 459486 | K17: =H17+I17-J17 -> 6935.95
A18: 17 | B18: Chellakere(KUWSDB) | C18: Shivaganga Service Station | D18: =+'Chellakere -1'!E35 -> 5000 | E18: =+'Chellakere -1'!G35 -> 461150 | F18: =+'Chellakere -1'!H35 -> 195.04 | G18: =+'Chellakere -1'!J35 -> 20301.714 | H18: =E18+G18 -> 481451.71 | I18: =+'Chellakere -1'!K3 -> 161104.96 | J18: =+'Chellakere -1'!L35 -> 373900 | K18: =H18+I18-J18 -> 268656.68
A19: 18 | B19: Chellakere(KUWSDB)-09 | D19: =+' Chellakere-PKG-9'!E35 -> 410.01 | E19: =+' Chellakere-PKG-9'!G35 -> 37777.422 | F19: =+' Chellakere-PKG-9'!H35 -> 18.04 | G19: =+' Chellakere-PKG-9'!J35 -> 1877.7836 | H19: =E19+G19 -> 39655.206 | I19: =+' Chellakere-PKG-9'!M3 -> 0 | J19: =+' Chellakere-PKG-9'!L35 -> 39655.206 | K19: =H19+I19-J19 -> 0
A20: 19 | B20: Molakalmuru | C20: Sri Lakshmi Venkateshwara Filling Station | D20: =+Molakamuru!E35 -> 600 | E20: =+Molakamuru!G35 -> 55332 | F20: =+Molakamuru!H35 -> 100 | G20: =+Molakamuru!J35 -> 10408 | H20: =E20+G20 -> 65740 | I20: =+Molakamuru!K3 -> 27990.595 | J20: =+Molakamuru!L35 -> 71123.38 | K20: =H20+I20-J20 -> 22607.215
A21: 20 | B21: Chennagiri | D21: =+' Chennagiri'!E35 -> 427.27 | E21: =+' Chennagiri'!G35 -> 39330.204 | F21: =+' Chennagiri'!H35 -> 68 | G21: =+' Chennagiri'!J35 -> 7078.88 | H21: =E21+G21 -> 46409.084 | I21: =+' Chennagiri'!K3 -> 0 | J21: =+' Chennagiri'!L35 -> 46409.084 | K21: =H21+I21-J21 -> 0
A22: 21 | B22: Khanapur(PKG-3) | C22: V.V.Varde | D22: =+Khanapur!E35 -> 1766.61 | E22: =+Khanapur!G35 -> 160549.52 | F22: =+Khanapur!H35 -> 79.78 | G22: =+Khanapur!J35 -> 8198.9906 | H22: =E22+G22 -> 168748.51 | I22: =+Khanapur!M3 -> 103942.75 | J22: =+Khanapur!L35 -> 203905.34 | K22: =H22+I22-J22 -> 68785.913
A23: 22 | B23: Munavalli(PKG-3)-1 | C23: Shri Daneshwari | D23: =+Munavali!E37 -> 0 | E23: =+Munavali!G37 -> 0 | F23: =+Munavali!H37 -> 0 | G23: =+Munavali!J37 -> 0 | H23: =E23+G23 -> 0 | I23: =+Munavali!M3 -> 0 | J23: =+Munavali!L37 -> 0 | K23: =H23+I23-J23 -> 0
A24: 23 | B24: Munavalli(PKG-3)-2 | C24: Shre Shiva Petroleum | D24: =+'Munavali-2'!E38 -> 17172.676 | E24: =+'Munavali-2'!G38 -> 1571967.1 | F24: =+'Munavali-2'!H38 -> 261 | G24: =+'Munavali-2'!J38 -> 27163.48 | H24: =E24+G24 -> 1599130.6 | I24: =+'Munavali-2'!M3 -> 343617.68 | J24: =+'Munavali-2'!L38 -> 1204238.2 | K24: =H24+I24-J24 -> 738510.09
A25: 24 | B25: Borgaon(PKG-3) | C25: Aadisagar Petrolium | D25: =+Borgaon!E35 -> 1395.17 | E25: =+Borgaon!G35 -> 128034.75 | F25: =+Borgaon!H35 -> 117.74 | G25: =+Borgaon!J35 -> 12213.17 | H25: =E25+G25 -> 140247.92 | I25: =+Borgaon!K3 -> 115310.98 | J25: =+Borgaon!L35 -> 226000 | K25: =H25+I25-J25 -> 29558.904
A26: 25 | B26: Ugar,Kudichi(PKG-3) | C26: Shiri Bhrhmanath Petrolium | D26: =+'Ugar,Khagwad,Kudichi'!E35 -> 4214.84 | E26: =+'Ugar,Khagwad,Kudichi'!G35 -> 387470.24 | F26: =+'Ugar,Khagwad,Kudichi'!H35 -> 264 | G26: =+'Ugar,Khagwad,Kudichi'!J35 -> 27426.96 | H26: =E26+G26 -> 414897.2 | I26: =+'Ugar,Khagwad,Kudichi'!M3 -> 151510.55 | J26: =+'Ugar,Khagwad,Kudichi'!L35 -> 351000 | K26: =H26+I26-J26 -> 215407.75
A27: 26 | B27: Kabbur(PKG-3) | C27: Shri Jai Hanuman Petrolium | D27: =+Kabbur!E35 -> 444.44 | E27: =+Kabbur!G35 -> 40798.574 | F27: =+Kabbur!H35 -> 11.66 | G27: =+Kabbur!J35 -> 1207.1598 | H27: =E27+G27 -> 42005.734 | I27: 0 | J27: =+Kabbur!L35 -> 42005.734 | K27: =H27+I27-J27 -> 0
A28: 27 | B28: Kumta (PKG-1) | C28: V.M.MIRJANKAR (KUMTA) BHARAT | D28: =+kumta!E35 -> 2040 | E28: =+kumta!G35 -> 187618.8 | F28: =+kumta!H35 -> 90 | G28: =+kumta!J35 -> 9360.9 | H28: =E28+G28 -> 196979.7 | I28: 0 | J28: =+kumta!L35 -> 169925 | K28: =H28+I28-J28 -> 27054.7
A29: 28 | B29: Jalgaon | C29: Sri Sai Petrol Pump | D29: =+Jalgaon!E54 -> 15971.286 | E29: =+Jalgaon!G54 -> 1464609.4 | F29: =+Jalgaon!H54 -> 140 | G29: =+Jalgaon!J54 -> 14726.6 | H29: =E29+G29 -> 1479336 | I29: =+Jalgaon!K3 -> 1368586.5 | J29: =+Jalgaon!L54 -> 2510129.2 | K29: =H29+I29-J29 -> 337793.25
A30: 29 | B30: Jalgaon-2 | C30: Nayara | D30: =+'Jalgoan-2'!E55 -> 42840.22 | E30: ='Jalgoan-2'!G55 -> 3928876.6 | F30: =+'Jalgoan-2'!H55 -> 230 | G30: =+'Jalgoan-2'!J55 -> 24251.2 | H30: =E30+G30 -> 3953127.8 | I30: =+'Jalgoan-2'!M3 -> 0 | J30: =+'Jalgoan-2'!L55 -> 1000000 | K30: =H30+I30-J30 -> 2953127.8
A31: 30 | B31: MKBD | C31: Shree Sai Samarth Petroleum | D31: =+MKBD!E38 -> 8000 | E31: =+MKBD!G38 -> 729120 | F31: =+MKBD!H38 -> 75 | G31: =+MKBD!J38 -> 7845 | H31: =E31+G31 -> 736965 | I31: =+MKBD!K3 -> 366041.65 | J31: =+MKBD!L38 -> 1000000 | K31: =H31+I31-J31 -> 103006.65
A32: 31 | B32: Haveri | C32: M/s Magavi City Fuels | D32: =' Haveri-2'!E37 -> 2590.84 | E32: =' Haveri-2'!G37 -> 237035.95 | F32: =' Haveri-2'!H37 -> 107.73 | G32: =' Haveri-2'!J37 -> 11142.514 | H32: =E32+G32 -> 248178.47 | I32: =' Haveri-2'!M3 -> 150830.73 | J32: =+' Haveri-2'!L37 -> 308600 | K32: =H32+I32-J32 -> 90409.199
A33: 32 | B33: Guttal-2 | C33: Himagiri Petroleum | D33: =+' Guttal-2'!E35 -> 5890.6 | E33: =+' Guttal-2'!G35 -> 540639.27 | F33: =+' Guttal-2'!H35 -> 160 | G33: =+' Guttal-2'!J35 -> 16598.4 | H33: =E33+G33 -> 557237.67 | I33: =+' Guttal-2'!M3 -> 532276.88 | J33: =+' Guttal-2'!L35 -> 970904 | K33: =H33+I33-J33 -> 118610.55
A34: 33 | B34: Rattihali | C34: Shree Siri Gowari petroliam | D34: =+Rattihali!E35 -> 0 | E34: =+Rattihali!G35 -> 0 | F34: =+Rattihali!H35 -> 0 | G34: =+Rattihali!J35 -> 0 | H34: =E34+G34 -> 0 | I34: =+Rattihali!M3 -> 6442.724 | J34: =+Rattihali!L35 -> 0 | K34: =H34+I34-J34 -> 6442.724
A35: 34 | B35: Rattihali-2 | C35: Shiva Oil Traders | D35: =+'Rattihali-2'!E37 -> 3706.11 | E35: =+'Rattihali-2'!G37 -> 340554.45 | F35: =+'Rattihali-2'!H37 -> 129 | G35: =+'Rattihali-2'!J37 -> 13474.35 | H35: =E35+G35 -> 354028.8 | I35: =+'Rattihali-2'!M3 -> 162379.88 | J35: =+'Rattihali-2'!L37 -> 366900 | K35: =H35+I35-J35 -> 149508.67
A36: 35 | B36: Gajendragada | C36: Vanasri Petrol Pump | D36: =+Gajendragada!E35 -> 1238 | E36: =+Gajendragada!G35 -> 113685.54 | F36: =+Gajendragada!H35 -> 120 | G36: =+Gajendragada!J35 -> 12456 | H36: =E36+G36 -> 126141.54 | I36: =+Gajendragada!K3 -> 10249.402 | J36: =+Gajendragada!L35 -> 10288.04 | K36: =H36+I36-J36 -> 126102.9
A37: 36 | B37: Gokak(PKG-3) | C37: AJ Petrolinks | D37: =+'Gokak Dharwad PKG 3'!E40 -> 10361.89 | E37: =+'Gokak Dharwad PKG 3'!G40 -> 947905.7 | F37: =+'Gokak Dharwad PKG 3'!H40 -> 289 | G37: =+'Gokak Dharwad PKG 3'!J40 -> 29885.49 | H37: =E37+G37 -> 977791.19 | I37: =+'Gokak Dharwad PKG 3'!K3 -> 437987.29 | J37: =+'Gokak Dharwad PKG 3'!L40 -> 1188028 | K37: =H37+I37-J37 -> 227750.48
A38: 37 | B38: Hukkere | C38: TR Assocites | D38: =+' TR Associates'!E35 -> 9861.75 | E38: =+' TR Associates'!G35 -> 900575.01 | F38: =+' TR Associates'!H35 -> 12.02 | G38: =+' TR Associates'!J35 -> 1240.8848 | H38: =E38+G38 -> 901815.89 | I38: =+' TR Associates'!M3 -> 647689.79 | J38: =+' TR Associates'!L35 -> 1247689 | K38: =H38+I38-J38 -> 301816.69
A39: 38 | B39: Ankaligi | C39: Shivaganga | D39: =+Ankalgi!E35 -> 4209.09 | E39: =+Ankalgi!G35 -> 384332.01 | F39: =+Ankalgi!H35 -> 102 | G39: =+Ankalgi!J35 -> 10529.46 | H39: =E39+G39 -> 394861.47 | I39: =+Ankalgi!M3 -> 306662.51 | J39: =+Ankalgi!L35 -> 606663 | K39: =H39+I39-J39 -> 94860.976
A40: 39 | B40: ShankeshWAR | C40: SR Patil | D40: =+' Shankeshwar'!E35 -> 590.04 | E40: =+' Shankeshwar'!G35 -> 53871.752 | F40: =+' Shankeshwar'!H35 -> 135 | G40: =+' Shankeshwar'!J35 -> 13934.7 | H40: =E40+G40 -> 67806.452 | J40: =+' Shankeshwar'!L35 -> 67806.452 | K40: =H40+I40-J40 -> 0
A41: 40 | B41: Talikote(PKG-1) | C41: Raykar Oil Agencies | D41: =+' Talikote'!E46 -> 318.88 | E41: =+' Talikote'!G46 -> 29177.52 | F41: =+' Talikote'!H46 -> 68.27 | G41: =+' Talikote'!J46 -> 7061.8488 | H41: =E41+G41 -> 36239.369 | I41: =+' Talikote'!N3 -> 27659.595 | J41: =+' Talikote'!L46 -> 61475 | K41: =H41+I41-J41 -> 2423.9635
A42: 41 | B42: Chadchan(PKG-1) | C42: Khavekar Petrolium | D42: =+Chadchan!E35 -> 1322.98 | E42: =+Chadchan!G35 -> 120695.47 | F42: =+Chadchan!H35 -> 79.59 | G42: =+Chadchan!J35 -> 8210.5044 | H42: =E42+G42 -> 128905.97 | I42: =+Chadchan!K3 -> 86951.114 | J42: =+Chadchan!L35 -> 89512 | K42: =H42+I42-J42 -> 126345.08
A43: 42 | B43: Sindagi | C43: G.P.PORWAL | D43: =+Sindagi!E44 -> 706.95 | E43: =+Sindagi!G44 -> 64495.048 | F43: =+Sindagi!H44 -> 10 | G43: =+Sindagi!J44 -> 1068.1 | H43: =E43+G43 -> 65563.148 | I43: =+Sindagi!M3 -> 4187.2387 | J43: =+Sindagi!L44 -> 65000 | K43: =H43+I43-J43 -> 4750.3872
A44: 43 | B44: Muddebihal(PKG-1)2 | C44: PS NAGATHAN PETROLIUM | D44: =+'Muddebhihal-2'!E48 -> 1116.19 | E44: =+'Muddebhihal-2'!G48 -> 102042.09 | F44: =+'Muddebhihal-2'!H48 -> 35 | G44: =+'Muddebhihal-2'!J48 -> 3617.25 | H44: =+'Muddebhihal-2'!K48 -> 105659.34 | I44: =+'Muddebhihal-2'!M3 -> 81899.45 | J44: =+'Muddebhihal-2'!L48 -> 100000 | K44: =+'Muddebhihal-2'!M47 -> 87558.79
A45: 44 | B45: Almela(PKG-1) | C45: Shiddeshwar Petroleums | D45: =+Alemela!E43 -> 1271.27 | E45: =+Alemela!G43 -> 116270.35 | F45: =+Alemela!H43 -> 101.18 | G45: =+Alemela!J43 -> 10462.012 | H45: =E45+G45 -> 126732.37 | I45: =+Alemela!M3 -> 52390.801 | J45: =+Alemela!L43 -> 122000 | K45: =H45+I45-J45 -> 57123.167
A46: 45 | B46: Nalatwad(PKG-1) | C46: Shri Pawad Basaweshwar Petroleums | D46: =+Nalatwad!E43 -> 1056.01 | E46: =+Nalatwad!G43 -> 96751.636 | F46: =+Nalatwad!H43 -> 31.09 | G46: =+Nalatwad!J43 -> 3219.9913 | H46: =E46+G46 -> 99971.628 | I46: =+Nalatwad!M3 -> 59168.12 | J46: =+Nalatwad!L43 -> 120000 | K46: =H46+I46-J46 -> 39139.748
A47: 46 | B47: Srirangapatna | C47: Anupama F/S | D47: =+Srirangapatna!E35 -> 25.65 | E47: =+Srirangapatna!G35 -> 2499.0795 | F47: =+Srirangapatna!H35 -> 19.52 | G47: =+Srirangapatna!J35 -> 2000.0192 | H47: =E47+G47 -> 4499.0987 | I47: 0 | J47: =+Srirangapatna!L35 -> 4499.0987 | K47: =H47+I47-J47 -> 0
A48: 47 | B48: HO(DG) | C48: JSASFuel Genie India Pvt.Ltd | D48: =+'HO(DG)'!E39 -> 1087.93 | E48: =+'HO(DG)'!G39 -> 104232.99 | F48: =+'HO(DG)'!H39 -> 0 | G48: =+'HO(DG)'!J39 -> 0 | H48: =E48+G48 -> 104232.99 | I48: =+'HO(DG)'!M3 -> 32600.613 | J48: =+'HO(DG)'!L39 -> 47345.02 | K48: =H48+I48-J48 -> 89488.582
A49: Total | D49: =SUM(D2:D48) -> 472386.93 | E49: =SUM(E2:E48) -> 44391183 | F49: =SUM(F2:F48) -> 5731.49 | G49: =SUM(G2:G48) -> 600970.88 | H49: =SUM(H2:H48) -> 44992154 | I49: =SUM(I2:I48) -> 14194343 | J49: =SUM(J2:J48) -> 35727981 | K49: =H49+I49-J49 -> 23458516 | L49: 23361980 | M49: =L49-K49 -> -96536.041
A54: S.no | B54: Site Name | C54: Bunk Name | D54: Diesel(Liters) | E54: Diesel Amount | F54: Petrol(Liters) | G54: Petrol Amount | H54: Total Amount | I54: Opening Blance | J54: Amount Paid | K54: Closing Balances
A55: 46 | B55: {=VLOOKUP(A55,A1:K48,{2,3,4,5,6,7,8,9,10,11},FALSE)} -> Srirangapatna | C55: Anupama F/S | D55: 25.65 | E55: 2499.0795 | F55: 19.52 | G55: 2000.0192 | H55: 4499.0987 | I55: 0 | J55: 4499.0987 | K55: 0
B57: Site Name | C57: Bunk Name | D57: Diesel(Liters) | E57: Diesel Amount | F57: Petrol(Liters) | G57: Petrol Amount | H57: Total Amount | I57: Opening Blance | J57: Amount Paid | K57: Closing Balances
B58: HO(DG) | C58: {=VLOOKUP(B58,B1:K48,{2,3,4,5,6,7,8,9,10},FALSE)} -> JSASFuel Genie India Pvt.Ltd | D58: 1087.93 | E58: 104232.99 | F58: 0 | G58: 0 | H58: 104232.99 | I58: 32600.613 | J58: 47345.02 | K58: 89488.582
B65: 60000
B66: 18000
B67: 18000
B68: 75000
B69: 360000

Sheet Sheet2
A2: S.No | B2: NAme | C2: Lacation | D2: Card Number | E2: Card Number | F2: Category | G2: 1st Jan | I2: 2nd Jan | J2: 3rd Jan | K2: 4th Jan | L2: 5th Jan | M2: 6th Jan | N2: 7th Jan | O2: 8th Jan | P2: 9th Jan | Q2: 10th Jan | R2: 11th Jan | S2: 12th Jan | T2: 13th Jan | U2: 14th Jan | V2: 15th Jan | W2: 16th Jan | X2: 17th Jan | Y2: 18th Jan | Z2: 19th Jan | AA2: 20th Jan | AB2: 21st Jan | AC2: 22nd Jan | AD2: 23rd Jan | AE2: 24th Jan | AF2: 25th Jan | AG2: 26th Jan | AH2: 27th Jan | AI2: 28th Jan | AJ2: 29th Jan | AK2: 30th Jan | AL2: 31st Jan | AM2: Total
F3: Diesel
A4: 1 | B4: Rambabu | C4: HO(Two Wheeler) | D4: FC3450563999 | E4: Diesel | F4: 0 | G4: 0 | H4: 0 | I4: 0 | J4: 0 | K4: 0 | L4: 0 | M4: 0 | N4: 0 | O4: 0 | P4: 0 | Q4: 0 | R4: 0 | S4: 0 | T4: 0 | U4: 0 | V4: 0 | W4: 0 | X4: 5.22 | Y4: 0 | Z4: 0 | AA4: 0 | AB4: 0 | AC4: 0 | AD4: 60 | AE4: 0 | AF4: 0 | AG4: 0 | AH4: 4.56 | AI4: 0 | AJ4: 0 | AK4: 0 | AL4: 0 | AM4: =SUM(F4:AL4) -> 69.78
E5: Petrol | F5: 0 | G5: 4.69 | H5: 0 | I5: 0 | J5: 0 | K5: 0 | L5: 0 | M5: 0 | N5: 3.91 | O5: 0 | P5: 6.98 | Q5: 0 | R5: 0 | S5: 0 | T5: 0 | U5: 0 | V5: 0 | W5: 0 | X5: 0 | Y5: 0 | Z5: 0 | AB5: 0 | AC5: 0 | AD5: 0 | AE5: 0 | AF5: 0 | AG5: 0 | AH5: 0 | AI5: 0 | AJ5: 0 | AK5: 0 | AL5: 0 | AM5: =SUM(F5:AL5) -> 15.58
A6: 2 | B6: Hanumanth Rao | C6: HO | D6: FC3450676131 | E6: Diesel | F6: 0 | G6: 0 | H6: 0 | I6: 0 | J6: 0 | K6: 0 | L6: 0 | M6: 0 | N6: 0 | O6: 0 | P6: 0 | Q6: 0 | R6: 0 | S6: 0 | T6: 0 | U6: 0 | V6: 0 | W6: 0 | X6: 0 | Y6: 0 | Z6: 0 | AA6: 0 | AB6: 0 | AC6: 0 | AD6: 0 | AE6: 0 | AF6: 0 | AG6: 0 | AH6: 0 | AI6: 0 | AJ6: 0 | AK6: 0 | AL6: 0 | AM6: =SUM(F6:AL6) -> 0
E7: Petrol | F7: 0 | G7: 0 | H7: 0 | I7: 0 | J7: 0 | K7: 0 | L7: 0 | M7: 0 | N7: 0 | O7: 0 | P7: 0 | Q7: 0 | R7: 0 | S7: 0 | T7: 0 | U7: 0 | V7: 0 | W7: 0 | X7: 0 | Y7: 0 | Z7: 0 | AB7: 0 | AC7: 0 | AD7: 0 | AE7: 0 | AF7: 0 | AG7: 0 | AH7: 0 | AI7: 0 | AJ7: 0 | AK7: 0 | AL7: 0 | AM7: =SUM(F7:AL7) -> 0
A8: 3 | B8: Radhakrishna | C8: HO | D8: FC8000207658 | E8: Diesel | F8: 0 | G8: 0 | H8: 0 | I8: 0 | J8: 33.44 | K8: 0 | L8: 0 | M8: 0 | N8: 0 | O8: 0 | P8: 0 | Q8: 0 | R8: 35.53 | S8: 0 | T8: 0 | U8: 0 | V8: 0 | W8: 0 | X8: 0 | Y8: 0 | Z8: 0 | AA8: 0 | AB8: 33.44 | AC8: 0 | AD8: 0 | AE8: 0 | AF8: 0 | AG8: 0 | AH8: 0 | AI8: 0 | AJ8: 0 | AK8: 0 | AL8: 0 | AM8: =SUM(F8:AL8) -> 102.41
E9: Petrol | F9: 0 | G9: 0 | H9: 0 | I9: 0 | J9: 0 | K9: 0 | L9: 0 | M9: 0 | N9: 0 | O9: 0 | P9: 0 | Q9: 0 | R9: 0 | S9: 0 | T9: 0 | U9: 0 | V9: 0 | W9: 0 | X9: 0 | Y9: 0 | Z9: 0 | AB9: 0 | AC9: 0 | AD9: 0 | AE9: 0 | AF9: 0 | AG9: 0 | AH9: 0 | AI9: 0 | AJ9: 0 | AK9: 0 | AL9: 0 | AM9: =SUM(F9:AL9) -> 0
A10: 4 | B10: VIjay | C10: HO | D10: FC3450698859 | E10: Diesel | F10: 0 | G10: 0 | H10: 0 | I10: 0 | J10: 0 | K10: 0 | L10: 0 | M10: 0 | N10: 0 | O10: 0 | P10: 49.22 | Q10: 0 | R10: 0 | S10: 0 | T10: 0 | U10: 54.57 | V10: 0 | W10: 0 | X10: 0 | Y10: 0 | Z10: 0 | AA10: 0 | AB10: 0 | AC10: 0 | AD10: 49.8 | AE10: 0 | AF10: 0 | AG10: 0 | AH10: 0 | AI10: 0 | AJ10: 0 | AK10: 0 | AL10: 0 | AM10: =SUM(F10:AL10) -> 153.59
E11: Petrol | F11: 0 | G11: 0 | H11: 0 | I11: 0 | J11: 0 | K11: 0 | L11: 0 | M11: 0 | N11: 0 | O11: 0 | P11: 0 | Q11: 0 | R11: 0 | S11: 0 | T11: 0 | U11: 0 | V11: 0 | W11: 0 | X11: 0 | Y11: 0 | Z11: 0 | AB11: 0 | AC11: 0 | AD11: 0 | AE11: 0 | AF11: 0 | AG11: 0 | AH11: 0 | AI11: 0 | AJ11: 0 | AK11: 0 | AL11: 0 | AM11: =SUM(F11:AL11) -> 0
A12: 5 | B12: Client | C12: Hiriyur | D12: FC3450698864 | E12: Diesel | F12: 0 | G12: 0 | H12: 0 | I12: 0 | J12: 0 | K12: 0 | L12: 0 | M12: 0 | N12: 86.29 | O12: 0 | P12: 0 | Q12: 0 | R12: 0 | S12: 0 | T12: 0 | U12: 0 | V12: 0 | W12: 0 | X12: 0 | Y12: 0 | Z12: 0 | AA12: 0 | AB12: 0 | AC12: 0 | AD12: 145.61 | AE12: 0 | AF12: 0 | AG12: 0 | AH12: 0 | AI12: 0 | AJ12: 0 | AK12: 0 | AL12: 0 | AM12: =SUM(F12:AL12) -> 231.9
E13: Petrol | F13: 0 | G13: 0 | H13: 0 | I13: 0 | J13: 0 | K13: 0 | L13: 0 | M13: 0 | N13: 0 | O13: 0 | P13: 0 | Q13: 0 | R13: 0 | S13: 0 | T13: 0 | U13: 0 | V13: 0 | W13: 0 | X13: 0 | Y13: 0 | Z13: 0 | AB13: 0 | AC13: 0 | AD13: 0 | AE13: 0 | AF13: 0 | AG13: 0 | AH13: 0 | AI13: 0 | AJ13: 0 | AK13: 0 | AL13: 0 | AM13: =SUM(F13:AL13) -> 0
A14: 6 | B14: Client | C14: Hosadurga | D14: FC3450698865 | E14: Diesel | F14: 0 | G14: 0 | H14: 0 | I14: 0 | J14: 0 | K14: 0 | L14: 40 | M14: 40 | N14: 0 | O14: 36 | P14: 35 | Q14: 0 | R14: 0 | S14: 0 | T14: 0 | U14: 0 | V14: 0 | W14: 45 | X14: 45 | Y14: 43.53 | Z14: 40 | AA14: 43 | AB14: 0 | AC14: 40 | AD14: 0 | AE14: 40 | AF14: 0 | AG14: 0 | AH14: 0 | AI14: 0 | AJ14: 0 | AK14: 0 | AL14: 0 | AM14: =SUM(F14:AL14) -> 447.53
E15: Petrol | F15: 0 | G15: 0 | H15: 0 | I15: 0 | J15: 0 | K15: 0 | L15: 0 | M15: 0 | N15: 0 | O15: 0 | P15: 0 | Q15: 0 | R15: 0 | S15: 0 | T15: 0 | U15: 0 | V15: 0 | W15: 0 | X15: 0 | Y15: 0 | Z15: 0 | AB15: 0 | AC15: 0 | AD15: 0 | AE15: 0 | AF15: 0 | AG15: 0 | AH15: 0 | AI15: 0 | AJ15: 0 | AK15: 0 | AL15: 0 | AM15: =SUM(F15:AL15) -> 0
G18: Diesel Price

Sheet HO(DG)
A1: JSASFuel Genie India Pvt.Ltd
A2: S.No | B2: Date | C2: GRN No | D2: Ind No/Bill No | E2: Diesel (Lts) | F2: Price | G2: Amount | H2: Petrol (Lts) | I2: Price | J2: Amount | K2: Total amount | L2: Amount paid | M2: As on date | N2: Remarks
A3: Opening Balance | M3: 32600.613
A4: 1 | B4: 46054 | G4: =E4*F4 -> 0 | H4: 0 | I4: 0 | J4: =H4*I4 -> 0 | K4: =G4+J4 -> 0 | L4: 0 | M4: =M3+K4-L4 -> 32600.613
A5: 2 | B5: 46055 | G5: =E5*F5 -> 0 | H5: 0 | I5: 0 | J5: =H5*I5 -> 0 | K5: =G5+J5 -> 0 | L5: 0 | M5: =M4+K5-L5 -> 32600.613
A6: 3 | B6: 46056 | G6: =E6*F6 -> 0 | H6: 0 | I6: 0 | J6: =H6*I6 -> 0 | K6: =G6+J6 -> 0 | L6: 0 | M6: =M5+K6-L6 -> 32600.613
A7: 4 | B7: 46057 | E7: 55.14 | F7: 95.64 | G7: =E7*F7 -> 5273.5896 | H7: 0 | I7: 0 | J7: =H7*I7 -> 0 | K7: =G7+J7 -> 5273.5896 | L7: 5273.59 | M7: =M6+K7-L7 -> 32600.612 | N7: HPCL
B8: 46057 | L8: 32600 | M8: =M7+K8-L8 -> 0.6123
A9: 5 | B9: 46058 | E9: 170 | F9: 95.83 | G9: =E9*F9 -> 16291.1 | H9: 0 | I9: 0 | J9: =H9*I9 -> 0 | K9: =G9+J9 -> 16291.1 | L9: 0 | M9: =M8+K9-L9 -> 16291.712
A10: 6 | B10: 46058 | E10: 68.97 | F10: 95.7 | G10: =E10*F10 -> 6600.429 | K10: =G10+J10 -> 6600.429 | L10: 6600.43 | M10: =M9+K10-L10 -> 16291.711 | N10: BPCL
A11: 7 | B11: 46058 | E11: 0 | F11: 0 | G11: =E11*F11 -> 0 | H11: 0 | I11: 0 | J11: =H11*I11 -> 0 | K11: =G11+J11 -> 0 | L11: =H11+K11 -> 0 | M11: =M10+K11-L11 -> 16291.711
A12: 8 | B12: 46060 | G12: =E12*F12 -> 0 | H12: 0 | I12: 0 | J12: =H12*I12 -> 0 | K12: =G12+J12 -> 0 | L12: 0 | M12: =M11+K12-L12 -> 16291.711
A13: 9 | B13: 46061 | G13: =E13*F13 -> 0 | H13: 0 | I13: 0 | J13: =H13*I13 -> 0 | K13: =G13+J13 -> 0 | L13: 0 | M13: =M12+K13-L13 -> 16291.711
A14: 10 | B14: 46062 | G14: =E14*F14 -> 0 | H14: 0 | I14: 0 | K14: =G14+J14 -> 0 | L14: 0 | M14: =M13+K14-L14 -> 16291.711
A15: 11 | B15: 46063 | G15: =E15*F15 -> 0 | H15: 0 | I15: 0 | K15: =G15+J15 -> 0 | L15: 0 | M15: =M14+K15-L15 -> 16291.711
A16: 12 | B16: 46064 | E16: 200 | F16: 95.83 | G16: =E16*F16 -> 19166 | H16: 0 | I16: 0 | K16: =G16+J16 -> 19166 | L16: 0 | M16: =M15+K16-L16 -> 35457.711
A17: 13 | B17: 46065 | G17: =E17*F17 -> 0 | H17: 0 | I17: 0 | K17: =G17+J17 -> 0 | L17: 0 | M17: =M16+K17-L17 -> 35457.711
A18: 14 | B18: 46066 | G18: =E18*F18 -> 0 | H18: 0 | I18: 0 | J18: =H18*I18 -> 0 | K18: =G18+J18 -> 0 | L18: 0 | M18: =M17+K18-L18 -> 35457.711
A19: 15 | B19: 46067 | G19: =E19*F19 -> 0 | H19: 0 | I19: 0 | J19: =H19*I19 -> 0 | K19: =G19+J19 -> 0 | L19: 0 | M19: =M18+K19-L19 -> 35457.711
A20: 16 | B20: 46068 | G20: =E20*F20 -> 0 | H20: 0 | I20: 0 | J20: =H20*I20 -> 0 | K20: =G20+J20 -> 0 | L20: 0 | M20: =M19+K20-L20 -> 35457.711 | S20: 16291
A21: 17 | B21: 46069 | G21: =E21*F21 -> 0 | H21: 0 | I21: 0 | J21: =H21*I21 -> 0 | K21: =G21+J21 -> 0 | L21: 0 | M21: =M20+K21-L21 -> 35457.711 | S21: 19166
A22: 18 | B22: 46070 | E22: 190.1 | F22: 95.83 | G22: =E22*F22 -> 18217.283 | J22: =H22*I22 -> 0 | K22: =G22+J22 -> 18217.283 | L22: 0 | M22: =M21+K22-L22 -> 53674.994 | S22: 18217
A23: 19 | B23: 46071 | G23: =E23*F23 -> 0 | J23: =H23*I23 -> 0 | K23: =G23+J23 -> 0 | L23: 0 | M23: =M22+K23-L23 -> 53674.994 | S23: 16291
A24: 20 | B24: 46072 | G24: =E24*F24 -> 0 | J24: =H24*I24 -> 0 | K24: =G24+J24 -> 0 | L24: 0 | M24: =M23+K24-L24 -> 53674.994 | S24: 19522 | T24: 32598
A25: 21 | B25: 46073 | E25: 0 | G25: =E25*F25 -> 0 | J25: =H25*I25 -> 0 | K25: =G25+J25 -> 0 | L25: 0 | M25: =M24+K25-L25 -> 53674.994 | S25: =SUM(S20:S24) -> 89487 | T25: =T24+S25 -> 122085
A26: 22 | B26: 46074 | E26: 170 | F26: 95.83 | G26: =E26*F26 -> 16291.1 | J26: =H26*I26 -> 0 | K26: =G26+J26 -> 16291.1 | L26: 0 | M26: =M25+K26-L26 -> 69966.094
A27: 23 | B27: 46075 | G27: =E27*F27 -> 0 | J27: =H27*I27 -> 0 | K27: =G27+J27 -> 0 | L27: 0 | M27: =M26+K27-L27 -> 69966.094
A28: 24 | B28: 46076 | G28: =E28*F28 -> 0 | J28: =H28*I28 -> 0 | K28: =G28+J28 -> 0 | L28: 0 | M28: =M27+K28-L28 -> 69966.094
A29: 25 | B29: 46077 | G29: =E29*F29 -> 0 | J29: =H29*I29 -> 0 | K29: =G29+J29 -> 0 | L29: 0 | M29: =M28+K29-L29 -> 69966.094
A30: 26 | B30: 46078 | G30: =E30*F30 -> 0 | J30: =H30*I30 -> 0 | K30: =G30+J30 -> 0 | L30: 0 | M30: =M29+K30-L30 -> 69966.094
A31: 27 | B31: 46079 | G31: =E31*F31 -> 0 | J31: =H31*I31 -> 0 | K31: =G31+J31 -> 0 | L31: 0 | M31: =M30+K31-L31 -> 69966.094
A32: 28 | B32: 46080 | G32: =E32*F32 -> 0 | J32: =H32*I32 -> 0 | K32: =G32+J32 -> 0 | M32: =M31+K32-L32 -> 69966.094 | R32: 203.72 | S32: 95.83 | T32: 19522.488
A33: 29 | B33: 46080 | E33: 203.72 | F33: 95.83 | G33: =E33*F33 -> 19522.488 | K33: =G33+J33 -> 19522.488 | L33: 0 | M33: =M32+K33-L33 -> 89488.582 | R33: 30 | S33: 95.7 | T33: 2871
A34: 30 | B34: 46081 | E34: 30 | F34: 95.7 | G34: =E34*F34 -> 2871 | J34: =H34*I34 -> 0 | K34: =G34+J34 -> 2871 | L34: =H34+K34 -> 2871 | M34: =M33+K34-L34 -> 89488.582
A35: 31 | G35: =E35*F35 -> 0 | J35: =H35*I35 -> 0 | K35: =G35+J35 -> 0 | M35: =M34+K35-L35 -> 89488.582
A36: 32 | G36: =E36*F36 -> 0 | J36: =H36*I36 -> 0 | K36: =G36+J36 -> 0 | M36: =M35+K36-L36 -> 89488.582
A37: 33 | G37: =E37*F37 -> 0 | J37: =H37*I37 -> 0 | K37: =G37+J37 -> 0 | L37: 0 | M37: =M36+K37-L37 -> 89488.582 | O37: 2669494 | P37: =O37-M37 -> 2580005.4
E38: 0 | F38: 0 | G38: =E38*F38 -> 0 | J38: =H38*I38 -> 0 | K38: =G38+J38 -> 0 | M38: =M37+K38-L38 -> 89488.582
E39: =SUM(E4:E37) -> 1087.93 | G39: =SUM(G4:G37) -> 104232.99 | H39: =SUM(H4:H37) -> 0 | J39: =SUM(J4:J37) -> 0 | K39: =SUM(K4:K37) -> 104232.99 | L39: =SUM(L4:L37) -> 47345.02
M48: 2408309
M49: 5327.86
M50: =M48-M49 -> 2402981.1

Sheet Khammam-1
A1: Divya Lakshmi Ganapathi Auto Services
A2: S.No | B2: Date | C2: GRN No | D2: Ind No/Bill No | E2: Diesel (Lts) | F2: Price | G2: Amount | H2: Petrol (Lts) | I2: Price | J2: Amount | K2: Total amount | L2: Amount paid | M2: As 0n Date | N2: Remarks
A3: Opening Balance | K3: 2836061 | M3: 2836061 | O3: 11178224
A4: 1 | B4: 46054 | E4: 4200 | F4: 95.68 | G4: =E4*F4 -> 401856 | K4: =G4+J4 -> 401856 | L4: 0 | M4: =M3+K4-L4 -> 3237917
A5: 2 | B5: 46055 | E5: 5300 | F5: 95.68 | G5: =E5*F5 -> 507104 | H5: 40 | I5: 107.46 | J5: =H5*I5 -> 4298.4 | K5: =G5+J5 -> 511402.4 | L5: 2998712 | M5: =M4+K5-L5 -> 750607.35
A6: 3 | B6: 46056 | E6: 5200 | F6: 95.68 | G6: =E6*F6 -> 497536 | J6: =H6*I6 -> 0 | K6: =G6+J6 -> 497536 | L6: 0 | M6: =M5+K6-L6 -> 1248143.4
A7: 4 | B7: 46057 | E7: 1000 | F7: 95.68 | G7: =E7*F7 -> 95680 | J7: =H7*I7 -> 0 | K7: =G7+J7 -> 95680 | L7: 0 | M7: =M6+K7-L7 -> 1343823.4
A8: 5 | B8: 46058 | E8: 1000 | F8: 95.68 | G8: =E8*F8 -> 95680 | J8: =H8*I8 -> 0 | K8: =G8+J8 -> 95680 | L8: 0 | M8: =M7+K8-L8 -> 1439503.4
A9: 6 | B9: 46059 | E9: 4900 | F9: 95.68 | G9: =E9*F9 -> 468832 | H9: 75 | I9: 107.46 | J9: =H9*I9 -> 8059.5 | K9: =G9+J9 -> 476891.5 | L9: 0 | M9: =M8+K9-L9 -> 1916394.9
A10: 7 | B10: 46060 | E10: 1200 | F10: 95.68 | G10: =E10*F10 -> 114816 | J10: =H10*I10 -> 0 | K10: =G10+J10 -> 114816 | L10: 0 | M10: =M9+K10-L10 -> 2031210.9
A11: 8 | B11: 46061 | E11: 1200 | F11: 95.68 | G11: =E11*F11 -> 114816 | J11: =H11*I11 -> 0 | K11: =G11+J11 -> 114816 | L11: 0 | M11: =M10+K11-L11 -> 2146026.9
A12: 9 | B12: 46062 | E12: 4400 | F12: 95.68 | G12: =E12*F12 -> 420992 | H12: 40 | I12: 107.46 | J12: =H12*I12 -> 4298.4 | K12: =G12+J12 -> 425290.4 | L12: 0 | M12: =M11+K12-L12 -> 2571317.3
A13: 10 | B13: 46063 | E13: 1200 | F13: 95.68 | G13: =E13*F13 -> 114816 | J13: =H13*I13 -> 0 | K13: =G13+J13 -> 114816 | L13: 0 | M13: =M12+K13-L13 -> 2686133.3
A14: 11 | B14: 46064 | E14: 3900 | F14: 95.68 | G14: =E14*F14 -> 373152 | H14: 20 | I14: 107.46 | J14: =H14*I14 -> 2149.2 | K14: =G14+J14 -> 375301.2 | L14: 0 | M14: =M13+K14-L14 -> 3061434.5
A15: 12 | B15: 46065 | E15: 4900 | F15: 95.68 | G15: =E15*F15 -> 468832 | H15: 20 | I15: 107.46 | J15: =H15*I15 -> 2149.2 | K15: =G15+J15 -> 470981.2 | L15: 0 | M15: =M14+K15-L15 -> 3532415.7
A16: 13 | B16: 46066 | E16: 1200 | F16: 95.68 | G16: =E16*F16 -> 114816 | J16: =H16*I16 -> 0 | K16: =G16+J16 -> 114816 | L16: 0 | M16: =M15+K16-L16 -> 3647231.7
A17: 14 | B17: 46067 | E17: 1200 | F17: 95.68 | G17: =E17*F17 -> 114816 | J17: =H17*I17 -> 0 | K17: =G17+J17 -> 114816 | L17: 0 | M17: =M16+K17-L17 -> 3762047.7
A18: 15 | B18: 46068 | G18: =E18*F18 -> 0 | J18: =H18*I18 -> 0 | K18: =G18+J18 -> 0 | L18: 0 | M18: =M17+K18-L18 -> 3762047.7
A19: 16 | B19: 46069 | E19: 2000 | F19: 95.68 | G19: =E19*F19 -> 191360 | J19: =H19*I19 -> 0 | K19: =G19+J19 -> 191360 | L19: 0 | M19: =M18+K19-L19 -> 3953407.7
A20: 17 | B20: 46070 | E20: 2000 | F20: 95.68 | G20: =E20*F20 -> 191360 | J20: =H20*I20 -> 0 | K20: =G20+J20 -> 191360 | L20: 0 | M20: =M19+K20-L20 -> 4144767.7
A21: 18 | B21: 46071 | E21: 4780.64 | F21: 95.68 | G21: =E21*F21 -> 457411.64 | J21: =H21*I21 -> 0 | K21: =G21+J21 -> 457411.64 | L21: 0 | M21: =M20+K21-L21 -> 4602179.3
A22: 19 | B22: 46072 | E22: 4200 | F22: 95.68 | G22: =E22*F22 -> 401856 | H22: 60 | I22: 107.46 | J22: =H22*I22 -> 6447.6 | K22: =G22+J22 -> 408303.6 | L22: 0 | M22: =M21+K22-L22 -> 5010482.9
A23: 20 | B23: 46073 | E23: 4100 | F23: 95.68 | G23: =E23*F23 -> 392288 | J23: =H23*I23 -> 0 | K23: =G23+J23 -> 392288 | L23: 0 | M23: =M22+K23-L23 -> 5402770.9
A24: 21 | B24: 46074 | E24: 4900 | F24: 95.68 | G24: =E24*F24 -> 468832 | J24: =H24*I24 -> 0 | K24: =G24+J24 -> 468832 | L24: 0 | M24: =M23+K24-L24 -> 5871602.9
A25: 22 | B25: 46075 | E25: 1500 | F25: 95.68 | G25: =E25*F25 -> 143520 | J25: =H25*I25 -> 0 | K25: =G25+J25 -> 143520 | L25: 0 | M25: =M24+K25-L25 -> 6015122.9
A26: 23 | B26: 46076 | E26: 4700 | F26: 95.68 | G26: =E26*F26 -> 449696 | H26: 60 | I26: 107.46 | J26: =H26*I26 -> 6447.6 | K26: =G26+J26 -> 456143.6 | L26: 0 | M26: =M25+K26-L26 -> 6471266.5
A27: 24 | B27: 46077 | E27: 4900 | F27: 95.68 | G27: =E27*F27 -> 468832 | H27: 40 | I27: 107.46 | J27: =H27*I27 -> 4298.4 | K27: =G27+J27 -> 473130.4 | L27: 0 | M27: =M26+K27-L27 -> 6944396.9
A28: 25 | B28: 46078 | E28: 3600 | F28: 95.68 | G28: =E28*F28 -> 344448 | H28: 20 | I28: 107.46 | J28: =H28*I28 -> 2149.2 | K28: =G28+J28 -> 346597.2 | L28: 0 | M28: =M27+K28-L28 -> 7290994.1
A29: 26 | B29: 46079 | E29: 4400 | F29: 95.68 | G29: =E29*F29 -> 420992 | H29: 40 | I29: 107.46 | J29: =H29*I29 -> 4298.4 | K29: =G29+J29 -> 425290.4 | L29: 0 | M29: =M28+K29-L29 -> 7716284.5
A30: 27 | B30: 46080 | E30: 3800 | F30: 95.68 | G30: =E30*F30 -> 363584 | H30: 40 | I30: 107.46 | J30: =H30*I30 -> 4298.4 | K30: =G30+J30 -> 367882.4 | L30: 0 | M30: =M29+K30-L30 -> 8084166.9
A31: 28 | B31: 46081 | E31: 1600 | F31: 95.68 | G31: =E31*F31 -> 153088 | J31: =H31*I31 -> 0 | K31: =G31+J31 -> 153088 | L31: 0 | M31: =M30+K31-L31 -> 8237254.9
A32: 29 | G32: =E32*F32 -> 0 | J32: =H32*I32 -> 0 | K32: =G32+J32 -> 0 | L32: 0 | M32: =M31+K32-L32 -> 8237254.9
A33: 30 | G33: =E33*F33 -> 0 | J33: =H33*I33 -> 0 | K33: =G33+J33 -> 0 | L33: 0 | M33: =M32+K33-L33 -> 8237254.9
A34: 31 | G34: =E34*F34 -> 0 | K34: =G34+J34 -> 0 | L34: 0 | M34: =M33+K34-L34 -> 8237254.9
A35: 32 | G35: =E35*F35 -> 0 | J35: =H35*I35 -> 0 | K35: =G35+J35 -> 0 | L35: 0 | M35: =M34+K35-L35 -> 8237254.9
A36: 33 | G36: =E36*F36 -> 0 | J36: =H36*I36 -> 0 | K36: =G36+J36 -> 0 | L36: 0
A37: 34 | G37: =E37*F37 -> 0 | J37: =H37*I37 -> 0 | K37: =G37+J37 -> 0
E38: =SUM(E3:E37) -> 87280.64 | G38: =SUM(G3:G37) -> 8351011.6 | H38: =SUM(H3:H37) -> 455 | J38: =SUM(J3:J37) -> 48894.3 | K38: =SUM(K4:K37) -> 8399905.9 | L38: =SUM(L3:L37) -> 2998712

Sheet Khammam-2
A1: Jayasai union bunk
A2: S.No | B2: Date | C2: GRN No | D2: Ind No/Bill No | E2: Diesel (Lts) | F2: Price | G2: Amount | H2: Petrol (Lts) | I2: Price | J2: Amount | K2: Total amount | L2: Amount paid | M2: As 0n Date | N2: Remarks
A3: Opening Balance | K3: 4435776.8 | M3: 4435776.8
A4: 1 | B4: 46054 | E4: 2800 | F4: 95.7 | G4: =E4*F4 -> 267960 | H4: 20 | I4: 107.48 | J4: =H4*I4 -> 2149.6 | K4: =G4+J4 -> 270109.6 | M4: =M3+K4-L4 -> 4705886.4 | O4: =O3+M4-N4 -> 4705886.4
A5: 2 | B5: 46055 | E5: 2700 | F5: 95.7 | G5: =E5*F5 -> 258390 | J5: =H5*I5 -> 0 | K5: =G5+J5 -> 258390 | M5: =M4+K5-L5 -> 4964276.4
A6: 3 | B6: 46056 | E6: 2800 | F6: 95.7 | G6: =E6*F6 -> 267960 | H6: 60 | I6: 107.48 | J6: =H6*I6 -> 6448.8 | K6: =G6+J6 -> 274408.8 | L6: 4705886 | M6: =M5+K6-L6 -> 532799.2
A7: 4 | B7: 46057 | E7: 2800 | F7: 95.7 | G7: =E7*F7 -> 267960 | H7: 40 | I7: 107.48 | J7: =H7*I7 -> 4299.2 | K7: =G7+J7 -> 272259.2 | M7: =M6+K7-L7 -> 805058.4
A8: 5 | B8: 46058 | G8: =E8*F8 -> 0 | J8: =H8*I8 -> 0 | K8: =G8+J8 -> 0 | M8: =M7+K8-L8 -> 805058.4 | O8: 12802499
A9: 6 | B9: 46059 | G9: =E9*F9 -> 0 | J9: =H9*I9 -> 0 | K9: =G9+J9 -> 0 | M9: =M8+K9-L9 -> 805058.4
A10: 7 | B10: 46060 | E10: 2800 | F10: 95.7 | G10: =E10*F10 -> 267960 | H10: 40 | I10: 107.48 | J10: =H10*I10 -> 4299.2 | K10: =G10+J10 -> 272259.2 | L10: 0 | M10: =M9+K10-L10 -> 1077317.6
A11: 8 | B11: 46061 | G11: =E11*F11 -> 0 | J11: =H11*I11 -> 0 | K11: =G11+J11 -> 0 | M11: =M10+K11-L11 -> 1077317.6
A12: 9 | B12: 46062 | G12: =E12*F12 -> 0 | J12: =H12*I12 -> 0 | K12: =G12+J12 -> 0 | M12: =M11+K12-L12 -> 1077317.6
A13: 10 | B13: 46063 | E13: 5400 | F13: 95.7 | G13: =E13*F13 -> 516780 | H13: 75 | I13: 107.48 | J13: =H13*I13 -> 8061 | K13: =G13+J13 -> 524841 | M13: =M12+K13-L13 -> 1602158.6
A14: 11 | B14: 46064 | E14: 2800 | F14: 95.7 | G14: =E14*F14 -> 267960 | H14: 40 | I14: 107.48 | J14: =H14*I14 -> 4299.2 | K14: =G14+J14 -> 272259.2 | M14: =M13+K14-L14 -> 1874417.8
A15: 12 | B15: 46065 | E15: 2500 | F15: 95.7 | G15: =E15*F15 -> 239250 | J15: =H15*I15 -> 0 | K15: =G15+J15 -> 239250 | M15: =M14+K15-L15 -> 2113667.8
A16: 13 | B16: 46066 | G16: =E16*F16 -> 0 | J16: =H16*I16 -> 0 | K16: =G16+J16 -> 0 | M16: =M15+K16-L16 -> 2113667.8
A17: 14 | B17: 46067 | E17: 2650 | F17: 95.7 | G17: =E17*F17 -> 253605 | H17: 60 | I17: 107.48 | J17: =H17*I17 -> 6448.8 | K17: =G17+J17 -> 260053.8 | M17: =M16+K17-L17 -> 2373721.6
A18: 15 | B18: 46068 | E18: 2000 | F18: 95.7 | G18: =E18*F18 -> 191400 | H18: 40 | I18: 107.48 | J18: =H18*I18 -> 4299.2 | K18: =G18+J18 -> 195699.2 | M18: =M17+K18-L18 -> 2569420.8
A19: 16 | B19: 46069 | E19: 9030.29 | F19: 95.71 | G19: =E19*F19 -> 864289.06 | H19: 60 | I19: 107.48 | J19: =H19*I19 -> 6448.8 | K19: =G19+J19 -> 870737.86 | M19: =M18+K19-L19 -> 3440158.7
A20: 17 | B20: 46070 | E20: 2700 | F20: 95.71 | G20: =E20*F20 -> 258417 | H20: 40 | I20: 107.49 | J20: =H20*I20 -> 4299.6 | K20: =G20+J20 -> 262716.6 | M20: =M19+K20-L20 -> 3702875.3
A21: 18 | B21: 46071 | E21: 9336.48 | F21: 95.71 | G21: =E21*F21 -> 893594.5 | H21: 20 | I21: 107.49 | J21: =H21*I21 -> 2149.8 | K21: =G21+J21 -> 895744.3 | M21: =M20+K21-L21 -> 4598619.6
A22: 19 | B22: 46072 | G22: =E22*F22 -> 0 | J22: =H22*I22 -> 0 | K22: =G22+J22 -> 0 | L22: 0 | M22: =M21+K22-L22 -> 4598619.6
A23: 20 | B23: 46073 | E23: 6863.58 | F23: 95.71 | G23: =E23*F23 -> 656913.24 | H23: 60 | I23: 107.49 | J23: =H23*I23 -> 6449.4 | K23: =G23+J23 -> 663362.64 | M23: =M22+K23-L23 -> 5261982.2
A24: 21 | B24: 46074 | E24: 5500 | F24: 95.71 | G24: =E24*F24 -> 526405 | H24: 75 | I24: 107.49 | J24: =H24*I24 -> 8061.75 | K24: =G24+J24 -> 534466.75 | M24: =M23+K24-L24 -> 5796449
A25: 22 | B25: 46075 | E25: 2200 | F25: 95.71 | G25: =E25*F25 -> 210562 | J25: =H25*I25 -> 0 | K25: =G25+J25 -> 210562 | M25: =M24+K25-L25 -> 6007011
A26: 23 | B26: 46076 | G26: =E26*F26 -> 0 | J26: =H26*I26 -> 0 | K26: =G26+J26 -> 0 | M26: =M25+K26-L26 -> 6007011
A27: 24 | B27: 46077 | E27: 5896.01 | F27: 95.71 | G27: =E27*F27 -> 564307.12 | J27: =H27*I27 -> 0 | K27: =G27+J27 -> 564307.12 | M27: =M26+K27-L27 -> 6571318.1
A28: 25 | B28: 46078 | E28: 4173.42 | F28: 95.71 | G28: =E28*F28 -> 399438.03 | J28: =H28*I28 -> 0 | K28: =G28+J28 -> 399438.03 | M28: =M27+K28-L28 -> 6970756.1
A29: 26 | B29: 46079 | E29: 6113.27 | F29: 95.71 | G29: =E29*F29 -> 585101.07 | J29: =H29*I29 -> 0 | K29: =G29+J29 -> 585101.07 | L29: 2000000 | M29: =M28+K29-L29 -> 5555857.2
A30: 27 | B30: 46080 | G30: =E30*F30 -> 0 | J30: =H30*I30 -> 0 | K30: =G30+J30 -> 0 | M30: =M29+K30-L30 -> 5555857.2
A31: 28 | B31: 46081 | G31: =E31*F31 -> 0 | J31: =H31*I31 -> 0 | K31: =G31+J31 -> 0 | M31: =M30+K31-L31 -> 5555857.2
A32: 29 | G32: =E32*F32 -> 0 | J32: =H32*I32 -> 0 | K32: =G32+J32 -> 0 | M32: =M31+K32-L32 -> 5555857.2
A33: 30 | G33: =E33*F33 -> 0 | J33: =H33*I33 -> 0 | K33: =G33+J33 -> 0 | M33: =M32+K33-L33 -> 5555857.2
A34: 31 | G34: =E34*F34 -> 0 | J34: =H34*I34 -> 0 | K34: =G34+J34 -> 0 | M34: =M33+K34-L34 -> 5555857.2
E35: =SUM(E4:E34) -> 81063.05 | G35: =SUM(G4:G34) -> 7758252 | H35: =SUM(H4:H34) -> 630 | J35: =SUM(J4:J34) -> 67714.35 | K35: =SUM(K4:K34) -> 7825966.4 | L35: =SUM(L4:L34) -> 6705886

Sheet Khammam-3
A1: JSASFuel Genie India Pvt.Ltd
A2: S.No | B2: Date | C2: GRN No | D2: Ind No/Bill No | E2: Diesel (Lts) | F2: Price | G2: Amount | H2: Petrol (Lts) | I2: Price | J2: Amount | K2: Total amount | L2: Amount paid | M2: As 0n Date | N2: Remarks
A3: Opening Balance | K3: 0 | M3: 120400
A4: 1 | B4: 46054 | G4: =E4*F4 -> 0 | J4: =H4*I4 -> 0 | K4: =G4+J4 -> 0 | M4: =M3+K4-L4 -> 120400 | O4: =O3+M4-N4 -> 120400
A5: 2 | B5: 46055 | G5: =E5*F5 -> 0 | J5: =H5*I5 -> 0 | K5: =G5+J5 -> 0 | L5: 0 | M5: =M4+K5-L5 -> 120400
A6: 3 | B6: 46056 | G6: =E6*F6 -> 0 | J6: =H6*I6 -> 0 | K6: =G6+J6 -> 0 | M6: =M5+K6-L6 -> 120400
A7: 4 | B7: 46057 | E7: 6000 | F7: 94.7 | G7: =E7*F7 -> 568200 | J7: =H7*I7 -> 0 | K7: =G7+J7 -> 568200 | L7: 117100 | M7: =M6+K7-L7 -> 571500
A8: 5 | B8: 46058 | E8: 6000 | F8: 94.7 | G8: =E8*F8 -> 568200 | J8: =H8*I8 -> 0 | K8: =G8+J8 -> 568200 | M8: =M7+K8-L8 -> 1139700
A9: 6 | B9: 46059 | E9: 6000 | F9: 94.7 | G9: =E9*F9 -> 568200 | J9: =H9*I9 -> 0 | K9: =G9+J9 -> 568200 | M9: =M8+K9-L9 -> 1707900
A10: 7 | B10: 46060 | E10: 6000 | F10: 94.7 | G10: =E10*F10 -> 568200 | J10: =H10*I10 -> 0 | K10: =G10+J10 -> 568200 | M10: =M9+K10-L10 -> 2276100
A11: 8 | B11: 46061 | E11: 6000 | F11: 94.7 | G11: =E11*F11 -> 568200 | J11: =H11*I11 -> 0 | K11: =G11+J11 -> 568200 | M11: =M10+K11-L11 -> 2844300
A12: 9 | B12: 46062 | E12: 6000 | F12: 94.7 | G12: =E12*F12 -> 568200 | J12: =H12*I12 -> 0 | K12: =G12+J12 -> 568200 | M12: =M11+K12-L12 -> 3412500
A13: 10 | B13: 46063 | E13: 5973 | F13: 94.7 | G13: =E13*F13 -> 565643.1 | J13: =H13*I13 -> 0 | K13: =G13+J13 -> 565643.1 | M13: =M12+K13-L13 -> 3978143.1
A14: 11 | B14: 46064 | E14: 0 | G14: =E14*F14 -> 0 | J14: =H14*I14 -> 0 | K14: =G14+J14 -> 0 | M14: =M13+K14-L14 -> 3978143.1
A15: 12 | B15: 46065 | E15: 6000 | F15: 94.7 | G15: =E15*F15 -> 568200 | J15: =H15*I15 -> 0 | K15: =G15+J15 -> 568200 | M15: =M14+K15-L15 -> 4546343.1
A16: 13 | B16: 46066 | E16: 6000 | F16: 94.7 | G16: =E16*F16 -> 568200 | J16: =H16*I16 -> 0 | K16: =G16+J16 -> 568200 | M16: =M15+K16-L16 -> 5114543.1
A17: 14 | B17: 46067 | E17: 6000 | F17: 94.7 | G17: =E17*F17 -> 568200 | J17: =H17*I17 -> 0 | K17: =G17+J17 -> 568200 | M17: =M16+K17-L17 -> 5682743.1
A18: 15 | B18: 46068 | E18: 6000 | F18: 94.7 | G18: =E18*F18 -> 568200 | J18: =H18*I18 -> 0 | K18: =G18+J18 -> 568200 | M18: =M17+K18-L18 -> 6250943.1
A19: 16 | B19: 46069 | G19: =E19*F19 -> 0 | J19: =H19*I19 -> 0 | K19: =G19+J19 -> 0 | M19: =M18+K19-L19 -> 6250943.1
A20: 17 | B20: 46070 | E20: 6000 | F20: 94.7 | G20: =E20*F20 -> 568200 | J20: =H20*I20 -> 0 | K20: =G20+J20 -> 568200 | M20: =M19+K20-L20 -> 6819143.1
A21: 18 | B21: 46071 | G21: =E21*F21 -> 0 | J21: =H21*I21 -> 0 | K21: =G21+J21 -> 0 | M21: =M20+K21-L21 -> 6819143.1
A22: 19 | B22: 46072 | E22: 6000 | F22: 94.7 | G22: =E22*F22 -> 568200 | J22: =H22*I22 -> 0 | K22: =G22+J22 -> 568200 | M22: =M21+K22-L22 -> 7387343.1
A23: 20 | B23: 46073 | G23: =E23*F23 -> 0 | J23: =H23*I23 -> 0 | K23: =G23+J23 -> 0 | M23: =M22+K23-L23 -> 7387343.1
A24: 21 | B24: 46074 | G24: =E24*F24 -> 0 | J24: =H24*I24 -> 0 | K24: =G24+J24 -> 0 | M24: =M23+K24-L24 -> 7387343.1
A25: 22 | B25: 46075 | E25: 6000 | F25: 94.7 | G25: =E25*F25 -> 568200 | J25: =H25*I25 -> 0 | K25: =G25+J25 -> 568200 | M25: =M24+K25-L25 -> 7955543.1
A26: 23 | B26: 46076 | E26: 6000 | F26: 94.7 | G26: =E26*F26 -> 568200 | J26: =H26*I26 -> 0 | K26: =G26+J26 -> 568200 | M26: =M25+K26-L26 -> 8523743.1
A27: 24 | B27: 46077 | G27: =E27*F27 -> 0 | J27: =H27*I27 -> 0 | K27: =G27+J27 -> 0 | M27: =M26+K27-L27 -> 8523743.1
A28: 25 | B28: 46078 | G28: =E28*F28 -> 0 | J28: =H28*I28 -> 0 | K28: =G28+J28 -> 0 | M28: =M27+K28-L28 -> 8523743.1
A29: 26 | B29: 46079 | G29: =E29*F29 -> 0 | J29: =H29*I29 -> 0 | K29: =G29+J29 -> 0 | L29: 8520000 | M29: =M28+K29-L29 -> 3743.1
A30: 27 | B30: 46080 | E30: 6000 | F30: 94.7 | G30: =E30*F30 -> 568200 | J30: =H30*I30 -> 0 | K30: =G30+J30 -> 568200 | M30: =M29+K30-L30 -> 571943.1
A31: 28 | B31: 46081 | E31: 6000 | F31: 94.7 | G31: =E31*F31 -> 568200 | J31: =H31*I31 -> 0 | K31: =G31+J31 -> 568200 | M31: =M30+K31-L31 -> 1140143.1
A32: 29 | G32: =E32*F32 -> 0 | J32: =H32*I32 -> 0 | K32: =G32+J32 -> 0 | M32: =M31+K32-L32 -> 1140143.1
A33: 30 | G33: =E33*F33 -> 0 | J33: =H33*I33 -> 0 | K33: =G33+J33 -> 0 | M33: =M32+K33-L33 -> 1140143.1
A34: 31 | G34: =E34*F34 -> 0 | J34: =H34*I34 -> 0 | K34: =G34+J34 -> 0 | M34: =M33+K34-L34 -> 1140143.1
E35: =SUM(E4:E34) -> 101973 | G35: =SUM(G4:G34) -> 9656843.1 | H35: =SUM(H4:H34) -> 0 | J35: =SUM(J4:J34) -> 0 | K35: =SUM(K4:K34) -> 9656843.1 | L35: =SUM(L4:L34) -> 8637100

Sheet  Sanga reddy-1
A1: Durga indhan
A2: S.No | B2: Date | C2: GRN No | D2: Ind No/Bill No | E2: Diesel (Lts) | F2: Price | G2: Amount | H2: Petrol (Lts) | I2: Price | J2: Amount | K2: Total amount | L2: Amount paid | M2: As 0n Date | N2: Remarks
A3: Opening Balance
A4: 1 | B4: 46054 | G4: =E4*F4 -> 0 | J4: =H4*I4 -> 0 | K4: =G4+J4 -> 0 | M4: =M3+K4-L4 -> 0 | O4: =O3+M4-N4 -> 0
A5: 2 | B5: 46055 | G5: =E5*F5 -> 0 | J5: =H5*I5 -> 0 | K5: =G5+J5 -> 0 | L5: 0 | M5: =M4+K5-L5 -> 0
A6: 3 | B6: 46056 | G6: =E6*F6 -> 0 | J6: =H6*I6 -> 0 | K6: =G6+J6 -> 0 | M6: =M5+K6-L6 -> 0
A7: 4 | B7: 46057 | G7: =E7*F7 -> 0 | J7: =H7*I7 -> 0 | K7: =G7+J7 -> 0 | M7: =M6+K7-L7 -> 0
A8: 5 | B8: 46058 | G8: =E8*F8 -> 0 | J8: =H8*I8 -> 0 | K8: =G8+J8 -> 0 | M8: =M7+K8-L8 -> 0
A9: 6 | B9: 46059 | G9: =E9*F9 -> 0 | J9: =H9*I9 -> 0 | K9: =G9+J9 -> 0 | M9: =M8+K9-L9 -> 0
A10: 7 | B10: 46060 | G10: =E10*F10 -> 0 | J10: =H10*I10 -> 0 | K10: =G10+J10 -> 0 | M10: =M9+K10-L10 -> 0
A11: 8 | B11: 46061 | G11: =E11*F11 -> 0 | J11: =H11*I11 -> 0 | K11: =G11+J11 -> 0 | M11: =M10+K11-L11 -> 0
A12: 9 | B12: 46062 | G12: =E12*F12 -> 0 | J12: =H12*I12 -> 0 | K12: =G12+J12 -> 0 | M12: =M11+K12-L12 -> 0
A13: 10 | B13: 46063 | G13: =E13*F13 -> 0 | J13: =H13*I13 -> 0 | K13: =G13+J13 -> 0 | M13: =M12+K13-L13 -> 0
A14: 11 | B14: 46064 | G14: =E14*F14 -> 0 | J14: =H14*I14 -> 0 | K14: =G14+J14 -> 0 | M14: =M13+K14-L14 -> 0
A15: 12 | B15: 46065 | G15: =E15*F15 -> 0 | J15: =H15*I15 -> 0 | K15: =G15+J15 -> 0 | M15: =M14+K15-L15 -> 0
A16: 13 | B16: 46066 | G16: =E16*F16 -> 0 | J16: =H16*I16 -> 0 | K16: =G16+J16 -> 0 | M16: =M15+K16-L16 -> 0
A17: 14 | B17: 46067 | G17: =E17*F17 -> 0 | J17: =H17*I17 -> 0 | K17: =G17+J17 -> 0 | M17: =M16+K17-L17 -> 0
... A20: 17 | B20: 46070 | G20: =E20*F20 -> 0 | J20: =H20*I20 -> 0 | K20: =G20+J20 -> 0 | M20: =M19+K20-L20 -> 0
A21: 18 | B21: 46071 | E21: 200 | F21: 96.36 | G21: =E21*F21 -> 19272 | H21: 5 | I21: 108.17 | J21: =H21*I21 -> 540.85 | K21: =G21+J21 -> 19812.85 | M21: =M20+K21-L21 -> 19812.85
A22: 19 | B22: 46072 | E22: 50 | F22: 96.36 | G22: =E22*F22 -> 4818 | H22: 4 | I22: 108.17 | J22: =H22*I22 -> 432.68 | K22: =G22+J22 -> 5250.68 | M22: =M21+K22-L22 -> 25063.53
A23: 20 | B23: 46073 | E23: 67.47 | F23: 96.36 | G23: =E23*F23 -> 6501.4092 | H23: 0 | I23: 108.17 | J23: =H23*I23 -> 0 | K23: =G23+J23 -> 6501.4092 | M23: =M22+K23-L23 -> 31564.939
A24: 21 | B24: 46074 | E24: 200 | F24: 96.36 | G24: =E24*F24 -> 19272 | H24: 0 | I24: 108.17 | J24: =H24*I24 -> 0 | K24: =G24+J24 -> 19272 | M24: =M23+K24-L24 -> 50836.939
A25: 22 | B25: 46075 | E25: 0 | F25: 96.36 | G25: =E25*F25 -> 0 | H25: 0 | I25: 108.17 | J25: =H25*I25 -> 0 | K25: =G25+J25 -> 0 | M25: =M24+K25-L25 -> 50836.939
A26: 23 | B26: 46076 | E26: 0 | F26: 96.36 | G26: =E26*F26 -> 0 | H26: 0 | I26: 108.17 | J26: =H26*I26 -> 0 | K26: =G26+J26 -> 0 | M26: =M25+K26-L26 -> 50836.939
A27: 24 | B27: 46077 | E27: 435.61 | F27: 96.36 | G27: =E27*F27 -> 41975.38 | H27: 5 | I27: 108.17 | J27: =H27*I27 -> 540.85 | K27: =G27+J27 -> 42516.23 | M27: =M26+K27-L27 -> 93353.169
A28: 25 | B28: 46078 | E28: 0 | F28: 96.36 | G28: =E28*F28 -> 0 | H28: 0 | I28: 108.17 | J28: =H28*I28 -> 0 | K28: =G28+J28 -> 0 | M28: =M27+K28-L28 -> 93353.169
A29: 26 | B29: 46079 | E29: 400 | F29: 96.36 | G29: =E29*F29 -> 38544 | H29: 0 | I29: 108.17 | J29: =H29*I29 -> 0 | K29: =G29+J29 -> 38544 | M29: =M28+K29-L29 -> 131897.17
A30: 27 | B30: 46080 | E30: 0 | F30: 96.36 | G30: =E30*F30 -> 0 | H30: 5 | I30: 108.17 | J30: =H30*I30 -> 540.85 | K30: =G30+J30 -> 540.85 | M30: =M29+K30-L30 -> 132438.02
A31: 28 | B31: 46081 | E31: 200 | F31: 96.36 | G31: =E31*F31 -> 19272 | H31: 0 | I31: 108.17 | J31: =H31*I31 -> 0 | K31: =G31+J31 -> 19272 | M31: =M30+K31-L31 -> 151710.02
A32: 29 | G32: =E32*F32 -> 0 | J32: =H32*I32 -> 0 | K32: =G32+J32 -> 0 | M32: =M31+K32-L32 -> 151710.02
A33: 30 | G33: =E33*F33 -> 0 | J33: =H33*I33 -> 0 | K33: =G33+J33 -> 0 | M33: =M32+K33-L33 -> 151710.02
A34: 31 | G34: =E34*F34 -> 0 | J34: =H34*I34 -> 0 | K34: =G34+J34 -> 0 | M34: =M33+K34-L34 -> 151710.02
E35: =SUM(E4:E34) -> 1553.08 | G35: =SUM(G4:G34) -> 149654.79 | H35: =SUM(H4:H34) -> 19 | J35: =SUM(J4:J34) -> 2055.23 | K35: =SUM(K4:K34) -> 151710.02 | L35: =SUM(L4:L34) -> 0

Sheet Sangareddy -2

Sheet Jadcherla-3
A1: JSASFuel Genie India Pvt.Ltd
A2: S.No | B2: Date | C2: GRN No | D2: Ind no/Bill No | E2: Diesel (Lts) | F2: Price | G2: Amount | H2: Petrol (Lts) | I2: Price | J2: Amount | K2: Total amount | L2: Amount paid | M2: As on Date | N2: Remarks
A3: Opening Balance | M3: 299056.5
A4: 1 | B4: 46054 | G4: =E4*F4 -> 0 | H4: 0 | I4: 0 | J4: =H4*I4 -> 0 | K4: =G4+J4 -> 0 | L4: 0 | M4: =+M3+K4-L4 -> 299056.5
A5: 2 | B5: 46055 | G5: =E5*F5 -> 0 | H5: 0 | I5: 0 | J5: =H5*I5 -> 0 | K5: =G5+J5 -> 0 | L5: 0 | M5: =+M4+K5-L5 -> 299056.5
A6: 3 | B6: 46056 | G6: =E6*F6 -> 0 | H6: 0 | I6: 0 | J6: =H6*I6 -> 0 | K6: =G6+J6 -> 0 | M6: =+M5+K6-L6 -> 299056.5
A7: 4 | B7: 46057 | G7: =E7*F7 -> 0 | H7: 0 | I7: 0 | J7: =H7*I7 -> 0 | K7: =G7+J7 -> 0 | L7: 200000 | M7: =+M6+K7-L7 -> 99056.5
A8: 5 | B8: 46058 | G8: =E8*F8 -> 0 | H8: 0 | I8: 0 | J8: =H8*I8 -> 0 | K8: =G8+J8 -> 0 | M8: =+M7+K8-L8 -> 99056.5
A9: 6 | B9: 46059 | E9: 2000 | F9: 95.43 | G9: =E9*F9 -> 190860 | H9: 0 | I9: 0 | J9: =H9*I9 -> 0 | K9: =G9+J9 -> 190860 | M9: =+M8+K9-L9 -> 289916.5
A10: 7 | B10: 46060 | G10: =E10*F10 -> 0 | H10: 0 | I10: 0 | J10: =H10*I10 -> 0 | K10: =G10+J10 -> 0 | M10: =+M9+K10-L10 -> 289916.5 | R10: 700
A11: 8 | B11: 46061 | E11: 1500 | F11: 95.43 | G11: =E11*F11 -> 143145 | H11: 0 | I11: 0 | J11: =H11*I11 -> 0 | K11: =G11+J11 -> 143145 | M11: =+M10+K11-L11 -> 433061.5 | S11: 5000
A12: 9 | B12: 46062 | G12: =E12*F12 -> 0 | H12: 0 | I12: 0 | J12: =H12*I12 -> 0 | K12: =G12+J12 -> 0 | M12: =+M11+K12-L12 -> 433061.5 | S12: 1500
A13: 10 | B13: 46063 | E13: 2500 | F13: 95.43 | G13: =E13*F13 -> 238575 | H13: 0 | I13: 0 | J13: =H13*I13 -> 0 | K13: =G13+J13 -> 238575 | M13: =+M12+K13-L13 -> 671636.5 | S13: 500
A14: 11 | B14: 46064 | G14: =E14*F14 -> 0 | H14: 0 | I14: 0 | J14: =H14*I14 -> 0 | K14: =G14+J14 -> 0 | M14: =+M13+K14-L14 -> 671636.5
A15: 12 | B15: 46065 | G15: =E15*F15 -> 0 | H15: 0 | I15: 0 | J15: =H15*I15 -> 0 | K15: =G15+J15 -> 0 | M15: =+M14+K15-L15 -> 671636.5
A16: 13 | B16: 46066 | E16: 2000 | F16: 95.43 | G16: =E16*F16 -> 190860 | H16: 0 | I16: 0 | J16: =H16*I16 -> 0 | K16: =G16+J16 -> 190860 | M16: =+M15+K16-L16 -> 862496.5
A17: 14 | B17: 46067 | E17: 2400 | F17: 95.43 | G17: =E17*F17 -> 229032 | H17: 0 | I17: 0 | J17: =H17*I17 -> 0 | K17: =G17+J17 -> 229032 | M17: =+M16+K17-L17 -> 1091528.5
A18: 15 | B18: 46068 | G18: =E18*F18 -> 0 | H18: 0 | I18: 0 | J18: =H18*I18 -> 0 | K18: =G18+J18 -> 0 | M18: =+M17+K18-L18 -> 1091528.5
A19: 16 | B19: 46069 | G19: =E19*F19 -> 0 | H19: 0 | I19: 0 | J19: =H19*I19 -> 0 | K19: =G19+J19 -> 0 | M19: =+M18+K19-L19 -> 1091528.5
A20: 17 | B20: 46070 | E20: 2192 | F20: 95.43 | G20: =E20*F20 -> 209182.56 | H20: 0 | I20: 0 | J20: =H20*I20 -> 0 | K20: =G20+J20 -> 209182.56 | M20: =+M19+K20-L20 -> 1300711.1
A21: 18 | B21: 46071 | E21: 2033 | F21: 95.43 | G21: =E21*F21 -> 194009.19 | H21: 0 | I21: 0 | J21: =H21*I21 -> 0 | K21: =G21+J21 -> 194009.19 | M21: =+M20+K21-L21 -> 1494720.2
A22: 19 | B22: 46072 | G22: =E22*F22 -> 0 | H22: 0 | I22: 0 | J22: =H22*I22 -> 0 | K22: =G22+J22 -> 0 | M22: =+M21+K22-L22 -> 1494720.2
A23: 20 | B23: 46073 | E23: 2000 | F23: 95.43 | G23: =E23*F23 -> 190860 | H23: 0 | I23: 0 | J23: =H23*I23 -> 0 | K23: =G23+J23 -> 190860 | L23: 1000000 | M23: =+M22+K23-L23 -> 685580.25
A24: 21 | B24: 46074 | E24: 2000 | F24: 95.43 | G24: =E24*F24 -> 190860 | H24: 0 | I24: 0 | J24: =H24*I24 -> 0 | K24: =G24+J24 -> 190860 | M24: =+M23+K24-L24 -> 876440.25
A25: 22 | B25: 46075 | F25: 95.43 | G25: =E25*F25 -> 0 | H25: 0 | I25: 0 | J25: =H25*I25 -> 0 | K25: =G25+J25 -> 0 | M25: =+M24+K25-L25 -> 876440.25
A26: 23 | B26: 46076 | E26: 2200 | F26: 95.43 | G26: =E26*F26 -> 209946 | H26: 0 | I26: 0 | J26: =H26*I26 -> 0 | K26: =G26+J26 -> 209946 | M26: =+M25+K26-L26 -> 1086386.2
A27: 24 | B27: 46077 | G27: =E27*F27 -> 0 | H27: 0 | I27: 0 | J27: =H27*I27 -> 0 | K27: =G27+J27 -> 0 | M27: =+M26+K27-L27 -> 1086386.2
A28: 25 | B28: 46078 | E28: 2200 | F28: 95.43 | G28: =E28*F28 -> 209946 | H28: 0 | I28: 0 | J28: =H28*I28 -> 0 | K28: =G28+J28 -> 209946 | M28: =+M27+K28-L28 -> 1296332.2
A29: 26 | B29: 46079 | E29: 2200 | F29: 95.43 | G29: =E29*F29 -> 209946 | H29: 0 | I29: 0 | J29: =H29*I29 -> 0 | K29: =G29+J29 -> 209946 | L29: 480000 | M29: =+M28+K29-L29 -> 1026278.2
A30: 27 | B30: 46080 | G30: =E30*F30 -> 0 | H30: 0 | I30: 0 | J30: =H30*I30 -> 0 | K30: =G30+J30 -> 0 | M30: =+M29+K30-L30 -> 1026278.2
A31: 28 | B31: 46081 | G31: =E31*F31 -> 0 | H31: 0 | I31: 0 | J31: =H31*I31 -> 0 | K31: =G31+J31 -> 0 | M31: =+M30+K31-L31 -> 1026278.2
A32: 29 | G32: =E32*F32 -> 0 | H32: 0 | I32: 0 | J32: =H32*I32 -> 0 | K32: =G32+J32 -> 0 | M32: =+M31+K32-L32 -> 1026278.2
A33: 30 | E33: 0 | F33: 0 | G33: =E33*F33 -> 0 | H33: 0 | I33: 0 | J33: =H33*I33 -> 0 | K33: =G33+J33 -> 0 | M33: =+M32+K33-L33 -> 1026278.2
A34: 31 | G34: =E34*F34 -> 0 | H34: 0 | I34: 0 | J34: =H34*I34 -> 0 | K34: =G34+J34 -> 0 | L34: 0 | M34: =+M33+K34-L34 -> 1026278.2
E35: =SUM(E4:E34) -> 25225 | G35: =SUM(G4:G34) -> 2407221.8 | H35: =SUM(H4:H34) -> 0 | J35: =SUM(J4:J34) -> 0 | K35: =SUM(K4:K34) -> 2407221.8 | L35: =SUM(L4:L34) -> 1680000
F38: /

Sheet Jadcherla-4
A1: Poornima Filling Station
A2: S.No | B2: Date | C2: GRN No | D2: Ind No/Bill No | E2: Diesel (Lts) | F2: Price | G2: Amount | H2: Petrol (Lts) | I2: Price | J2: Amount | K2: Total amount | L2: Amount paid | M2: As on date | N2: Remarks
A3: Opening Balance | M3: 5405
A4: 1 | B4: 46054 | G4: =E4*F4 -> 0 | H4: 0 | I4: 0 | J4: =H4*I4 -> 0 | K4: =G4+J4 -> 0 | L4: 0 | M4: =M3+K4-L4 -> 5405
A5: 2 | B5: 46055 | G5: =E5*F5 -> 0 | H5: 0 | I5: 0 | J5: =H5*I5 -> 0 | K5: =G5+J5 -> 0 | L5: 0 | M5: =M4+K5-L5 -> 5405
A6: 3 | B6: 46056 | G6: =E6*F6 -> 0 | H6: 0 | I6: 0 | J6: =H6*I6 -> 0 | K6: =G6+J6 -> 0 | L6: 0 | M6: =M5+K6-L6 -> 5405
A7: 4 | B7: 46057 | G7: =E7*F7 -> 0 | H7: 0 | I7: 0 | J7: =H7*I7 -> 0 | K7: =G7+J7 -> 0 | L7: 0 | M7: =M6+K7-L7 -> 5405
A8: 5 | B8: 46058 | G8: =E8*F8 -> 0 | H8: 0 | I8: 0 | J8: =H8*I8 -> 0 | K8: =G8+J8 -> 0 | L8: 0 | M8: =M7+K8-L8 -> 5405
A9: 6 | B9: 46059 | G9: =E9*F9 -> 0 | H9: 40 | I9: 108.1 | J9: =H9*I9 -> 4324 | K9: =G9+J9 -> 4324 | L9: 0 | M9: =M8+K9-L9 -> 9729
A10: 7 | B10: 46060 | G10: =E10*F10 -> 0 | H10: 0 | I10: 0 | J10: =H10*I10 -> 0 | K10: =G10+J10 -> 0 | L10: 0 | M10: =M9+K10-L10 -> 9729
A11: 8 | B11: 46061 | G11: =E11*F11 -> 0 | H11: 0 | I11: 0 | J11: =H11*I11 -> 0 | K11: =G11+J11 -> 0 | L11: 0 | M11: =M10+K11-L11 -> 9729
A12: 9 | B12: 46062 | G12: =E12*F12 -> 0 | H12: 0 | I12: 0 | J12: =H12*I12 -> 0 | K12: =G12+J12 -> 0 | L12: 0 | M12: =M11+K12-L12 -> 9729
A13: 10 | B13: 46063 | G13: =E13*F13 -> 0 | H13: 0 | I13: 0 | J13: =H13*I13 -> 0 | K13: =G13+J13 -> 0 | L13: 0 | M13: =M12+K13-L13 -> 9729
A14: 11 | B14: 46064 | G14: =E14*F14 -> 0 | H14: 0 | I14: 0 | J14: =H14*I14 -> 0 | K14: =G14+J14 -> 0 | L14: 0 | M14: =M13+K14-L14 -> 9729
A15: 12 | B15: 46065 | G15: =E15*F15 -> 0 | H15: 50 | I15: 108.1 | J15: =H15*I15 -> 5405 | K15: =G15+J15 -> 5405 | L15: 0 | M15: =M14+K15-L15 -> 15134
... A25: 22 | B25: 46075 | G25: =E25*F25 -> 0 | H25: 0 | I25: 0 | J25: =H25*I25 -> 0 | K25: =G25+J25 -> 0 | L25: 0 | M25: =M24+K25-L25 -> 20539
A26: 23 | B26: 46076 | E26: 0 | F26: 0 | G26: =E26*F26 -> 0 | H26: 40 | I26: 108.1 | J26: =H26*I26 -> 4324 | K26: =G26+J26 -> 4324 | L26: 0 | M26: =M25+K26-L26 -> 24863
A27: 24 | B27: 46077 | G27: =E27*F27 -> 0 | H27: 0 | I27: 0 | J27: =H27*I27 -> 0 | K27: =G27+J27 -> 0 | L27: 0 | M27: =M26+K27-L27 -> 24863
A28: 25 | B28: 46078 | G28: =E28*F28 -> 0 | H28: 0 | I28: 0 | J28: =H28*I28 -> 0 | K28: =G28+J28 -> 0 | L28: 0 | M28: =M27+K28-L28 -> 24863
A29: 26 | B29: 46079 | G29: =E29*F29 -> 0 | H29: 0 | I29: 0 | J29: =H29*I29 -> 0 | K29: =G29+J29 -> 0 | L29: 0 | M29: =M28+K29-L29 -> 24863
A30: 27 | B30: 46080 | G30: =E30*F30 -> 0 | H30: 0 | I30: 0 | J30: =H30*I30 -> 0 | K30: =G30+J30 -> 0 | L30: 0 | M30: =M29+K30-L30 -> 24863
A31: 28 | B31: 46081 | G31: =E31*F31 -> 0 | H31: 0 | I31: 0 | J31: =H31*I31 -> 0 | K31: =G31+J31 -> 0 | M31: =M30+K31-L31 -> 24863
A32: 28 | G32: =E32*F32 -> 0 | H32: 0 | I32: 0 | J32: =H32*I32 -> 0 | K32: =G32+J32 -> 0 | M32: =M31+K32-L32 -> 24863
A33: 28 | G33: =E33*F33 -> 0 | H33: 0 | I33: 0 | J33: =H33*I33 -> 0 | K33: =G33+J33 -> 0 | M33: =M32+K33-L33 -> 24863
A34: 28 | G34: =E34*F34 -> 0 | J34: =H34*I34 -> 0 | K34: =G34+J34 -> 0 | M34: =M33+K34-L34 -> 24863
E35: =SUM(E4:E34) -> 0 | G35: =SUM(G4:G34) -> 0 | H35: =SUM(H4:H34) -> 180 | J35: =SUM(J4:J34) -> 19458 | K35: =SUM(K4:K34) -> 19458 | L35: =SUM(L4:L34) -> 0

Sheet Devarakhadra
A1: Kurumurthy Swami F/S
A2: S.No | B2: Date | C2: GRN No | D2: Ind no/Bill No | E2: Diesel (Lts) | F2: Price | G2: Amount | H2: Petrol (Lts) | I2: Price | J2: Amount | K2: Total amount | L2: Amount paid | M2: As on Date | N2: Remarks
A3: Opening Balance | M3: 5856.2924 | O3: 121213.37
A4: 1 | B4: 46054 | E4: 10 | F4: 97.1 | G4: =E4*F4 -> 971 | H4: 0 | I4: 0 | J4: =H4*I4 -> 0 | K4: =G4+J4 -> 971 | M4: =+M3+K4-L4 -> 6827.2924
A5: 2 | B5: 46055 | E5: 0 | F5: 0 | G5: =E5*F5 -> 0 | J5: =H5*I5 -> 0 | K5: =G5+J5 -> 0 | L5: 7000 | M5: =+M4+K5-L5 -> -172.7076
A6: 3 | B6: 46056 | E6: 0 | F6: 0 | G6: =E6*F6 -> 0 | J6: =H6*I6 -> 0 | K6: =G6+J6 -> 0 | M6: =+M5+K6-L6 -> -172.7076
A7: 4 | B7: 46057 | E7: 0 | F7: 0 | G7: =E7*F7 -> 0 | H7: 13 | I7: 108.83 | J7: =H7*I7 -> 1414.79 | K7: =G7+J7 -> 1414.79 | M7: =+M6+K7-L7 -> 1242.0824 | O7: 1307 | P7: =O7-M7 -> 64.9176
A8: 5 | B8: 46058 | E8: 0 | F8: 0 | G8: =E8*F8 -> 0 | J8: =H8*I8 -> 0 | K8: =G8+J8 -> 0 | M8: =+M7+K8-L8 -> 1242.0824
A9: 6 | B9: 46059 | E9: 0 | F9: 0 | G9: =E9*F9 -> 0 | J9: =H9*I9 -> 0 | K9: =G9+J9 -> 0 | M9: =+M8+K9-L9 -> 1242.0824
A10: 7 | B10: 46060 | E10: 0 | F10: 0 | G10: =E10*F10 -> 0 | J10: =H10*I10 -> 0 | K10: =G10+J10 -> 0 | M10: =+M9+K10-L10 -> 1242.0824
A11: 8 | B11: 46061 | E11: 0 | F11: 0 | G11: =E11*F11 -> 0 | J11: =H11*I11 -> 0 | K11: =G11+J11 -> 0 | M11: =+M10+K11-L11 -> 1242.0824
A12: 9 | B12: 46062 | E12: 0 | F12: 0 | G12: =E12*F12 -> 0 | J12: =H12*I12 -> 0 | K12: =G12+J12 -> 0 | M12: =+M11+K12-L12 -> 1242.0824
A13: 10 | B13: 46063 | E13: 0 | F13: 0 | G13: =E13*F13 -> 0 | J13: =H13*I13 -> 0 | K13: =G13+J13 -> 0 | M13: =+M12+K13-L13 -> 1242.0824
A14: 11 | B14: 46064 | E14: 0 | F14: 0 | G14: =E14*F14 -> 0 | J14: =H14*I14 -> 0 | K14: =G14+J14 -> 0 | L14: 1307 | M14: =+M13+K14-L14 -> -64.9176
A15: 12 | B15: 46065 | E15: 0 | F15: 0 | G15: =E15*F15 -> 0 | J15: =H15*I15 -> 0 | K15: =G15+J15 -> 0 | L15: -64.92 | M15: =+M14+K15-L15 -> 0.0023999999 | N15: rounoff
A16: 13 | B16: 46066 | E16: 0 | F16: 0 | G16: =E16*F16 -> 0 | J16: =H16*I16 -> 0 | K16: =G16+J16 -> 0 | M16: =+M15+K16-L16 -> 0.0023999999
A17: 14 | B17: 46067 | E17: 0 | F17: 0 | G17: =E17*F17 -> 0 | J17: =H17*I17 -> 0 | K17: =G17+J17 -> 0 | M17: =+M16+K17-L17 -> 0.0023999999
A18: 15 | B18: 46068 | E18: 0 | F18: 0 | G18: =E18*F18 -> 0 | J18: =H18*I18 -> 0 | K18: =G18+J18 -> 0 | M18: =+M17+K18-L18 -> 0.0023999999
A19: 16 | B19: 46069 | E19: 0 | F19: 0 | G19: =E19*F19 -> 0 | J19: =H19*I19 -> 0 | K19: =G19+J19 -> 0 | M19: =+M18+K19-L19 -> 0.0023999999 | N19: Fuel bills
A20: 17 | B20: 46070 | E20: 0 | F20: 0 | G20: =E20*F20 -> 0 | J20: =H20*I20 -> 0 | K20: =G20+J20 -> 0 | M20: =+M19+K20-L20 -> 0.0023999999
A21: 18 | B21: 46071 | E21: 0 | F21: 0 | G21: =E21*F21 -> 0 | J21: =H21*I21 -> 0 | K21: =G21+J21 -> 0 | M21: =+M20+K21-L21 -> 0.0023999999
A22: 19 | B22: 46072 | E22: 0 | F22: 0 | G22: =E22*F22 -> 0 | J22: =H22*I22 -> 0 | K22: =G22+J22 -> 0 | M22: =+M21+K22-L22 -> 0.0023999999
A23: 20 | B23: 46073 | E23: 0 | F23: 0 | G23: =E23*F23 -> 0 | J23: =H23*I23 -> 0 | K23: =G23+J23 -> 0 | M23: =+M22+K23-L23 -> 0.0023999999
A24: 21 | B24: 46074 | E24: 0 | F24: 0 | G24: =E24*F24 -> 0 | J24: =H24*I24 -> 0 | K24: =G24+J24 -> 0 | M24: =+M23+K24-L24 -> 0.0023999999
A25: 22 | B25: 46075 | E25: 0 | F25: 0 | G25: =E25*F25 -> 0 | J25: =H25*I25 -> 0 | K25: =G25+J25 -> 0 | M25: =+M24+K25-L25 -> 0.0023999999
A26: 23 | B26: 46076 | E26: 0 | F26: 0 | G26: =E26*F26 -> 0 | J26: =H26*I26 -> 0 | K26: =G26+J26 -> 0 | M26: =+M25+K26-L26 -> 0.0023999999
A27: 24 | B27: 46077 | E27: 0 | F27: 0 | G27: =E27*F27 -> 0 | J27: =H27*I27 -> 0 | K27: =G27+J27 -> 0 | M27: =+M26+K27-L27 -> 0.0023999999
A28: 25 | B28: 46078 | E28: 0 | F28: 0 | G28: =E28*F28 -> 0 | J28: =H28*I28 -> 0 | K28: =G28+J28 -> 0 | M28: =+M27+K28-L28 -> 0.0023999999
A29: 26 | B29: 46079 | E29: 0 | F29: 0 | G29: =E29*F29 -> 0 | J29: =H29*I29 -> 0 | K29: =G29+J29 -> 0 | M29: =+M28+K29-L29 -> 0.0023999999
A30: 27 | B30: 46080 | E30: 0 | F30: 0 | G30: =E30*F30 -> 0 | J30: =H30*I30 -> 0 | K30: =G30+J30 -> 0 | M30: =+M29+K30-L30 -> 0.0023999999
A31: 28 | B31: 46081 | E31: 0 | F31: 0 | G31: =E31*F31 -> 0 | J31: =H31*I31 -> 0 | K31: =G31+J31 -> 0 | M31: =+M30+K31-L31 -> 0.0023999999
A32: 29 | E32: 0 | F32: 0 | G32: =E32*F32 -> 0 | J32: =H32*I32 -> 0 | K32: =G32+J32 -> 0 | M32: =+M31+K32-L32 -> 0.0023999999
A33: 30 | E33: 0 | F33: 0 | G33: =E33*F33 -> 0 | J33: =H33*I33 -> 0 | K33: =G33+J33 -> 0 | M33: =+M32+K33-L33 -> 0.0023999999
A34: 31 | G34: =E34*F34 -> 0 | J34: =H34*I34 -> 0 | K34: =G34+J34 -> 0 | M34: =+M33+K34-L34 -> 0.0023999999
E35: =SUM(E4:E34) -> 10 | G35: =SUM(G4:G34) -> 971 | H35: =SUM(H4:H34) -> 13 | J35: =SUM(J4:J34) -> 1414.79 | K35: =SUM(K4:K34) -> 2385.79 | L35: =SUM(L4:L34) -> 8242.08

Sheet Dindi
A1: Akarapu Balakistamma Fillling
A2: S.No | B2: Date | C2: GRN No | D2: Ind no/Bill No | E2: Diesel (Lts) | F2: Price | G2: Amount | H2: Petrol (Lts) | I2: Price | J2: Amount | K2: Total amount | L2: Amount paid | M2: As on Date | N2: Remarks
A3: Opening Balance | M3: 0
A4: 1 | B4: 45689 | G4: =E4*F4 -> 0 | H4: 0 | I4: 0 | J4: =H4*I4 -> 0 | K4: =G4+J4 -> 0 | L4: =+K4 -> 0 | M4: 0
A5: 2 | B5: 45690 | G5: =E5*F5 -> 0 | H5: 0 | I5: 0 | J5: =H5*I5 -> 0 | K5: =G5+J5 -> 0 | L5: =+K5 -> 0 | M5: 0
A6: 3 | B6: 45691 | G6: =E6*F6 -> 0 | H6: 0 | I6: 0 | J6: =H6*I6 -> 0 | K6: =G6+J6 -> 0 | L6: =+K6 -> 0 | M6: 0
A7: 4 | B7: 45692 | G7: =E7*F7 -> 0 | H7: 0 | I7: 0 | J7: =H7*I7 -> 0 | K7: =G7+J7 -> 0 | L7: =+K7 -> 0 | M7: 0
A8: 5 | B8: 45693 | G8: =E8*F8 -> 0 | H8: 0 | I8: 0 | J8: =H8*I8 -> 0 | K8: =G8+J8 -> 0 | L8: =+K8 -> 0 | M8: 0
A9: 6 | B9: 45694 | G9: =E9*F9 -> 0 | H9: 0 | I9: 0 | J9: =H9*I9 -> 0 | K9: =G9+J9 -> 0 | L9: =+K9 -> 0 | M9: 0
A10: 7 | B10: 45695 | G10: =E10*F10 -> 0 | H10: 0 | I10: 0 | J10: =H10*I10 -> 0 | K10: =G10+J10 -> 0 | L10: =+K10 -> 0 | M10: 0
A11: 8 | B11: 45696 | G11: =E11*F11 -> 0 | H11: 0 | I11: 0 | J11: =H11*I11 -> 0 | K11: =G11+J11 -> 0 | L11: =+K11 -> 0 | M11: 0
A12: 9 | B12: 45697 | G12: =E12*F12 -> 0 | H12: 0 | I12: 0 | J12: =H12*I12 -> 0 | K12: =G12+J12 -> 0 | L12: =+K12 -> 0 | M12: 0
A13: 10 | B13: 45698 | G13: =E13*F13 -> 0 | H13: 0 | I13: 0 | J13: =H13*I13 -> 0 | K13: =G13+J13 -> 0 | L13: =+K13 -> 0 | M13: 0
A14: 11 | B14: 45699 | G14: =E14*F14 -> 0 | H14: 0 | I14: 0 | J14: =H14*I14 -> 0 | K14: =G14+J14 -> 0 | L14: =+K14 -> 0 | M14: 0
A15: 12 | B15: 45700 | G15: =E15*F15 -> 0 | H15: 0 | I15: 0 | J15: =H15*I15 -> 0 | K15: =G15+J15 -> 0 | L15: =+K15 -> 0 | M15: 0
... A27: 24 | B27: 45712 | G27: =E27*F27 -> 0 | H27: 0 | I27: 0 | J27: =H27*I27 -> 0 | K27: =G27+J27 -> 0 | L27: =+K27 -> 0 | M27: 0
A28: 25 | B28: 45713 | H28: 0 | I28: 0 | J28: =H28*I28 -> 0 | K28: =G28+J28 -> 0 | L28: =+K28 -> 0 | M28: 0
A29: 26 | B29: 45714 | G29: =E29*F29 -> 0 | H29: 0 | I29: 0 | J29: =H29*I29 -> 0 | K29: =G29+J29 -> 0 | L29: =+K29 -> 0 | M29: 0
A30: 27 | B30: 45715 | G30: =E30*F30 -> 0 | H30: 0 | I30: 0 | J30: =H30*I30 -> 0 | K30: =G30+J30 -> 0 | L30: =+K30 -> 0 | M30: 0
A31: 28 | B31: 45716 | G31: =E31*F31 -> 0 | H31: 0 | I31: 0 | J31: =H31*I31 -> 0 | K31: =G31+J31 -> 0 | L31: =+K31 -> 0 | M31: 0
A32: 29 | G32: =E32*F32 -> 0 | H32: 0 | I32: 0 | J32: =H32*I32 -> 0 | K32: =G32+J32 -> 0 | L32: =+K32 -> 0 | M32: 0
A33: 30 | G33: =E33*F33 -> 0 | H33: 0 | I33: 0 | J33: =H33*I33 -> 0 | K33: =G33+J33 -> 0 | L33: =+K33 -> 0 | M33: 0
A34: 31 | G34: =E34*F34 -> 0 | H34: 0 | I34: 0 | J34: =H34*I34 -> 0 | K34: =G34+J34 -> 0 | L34: =+K34 -> 0 | M34: 0
E35: =SUM(E4:E34) -> 0 | G35: =SUM(G4:G34) -> 0 | H35: =SUM(H4:H34) -> 0 | J35: =SUM(J4:J34) -> 0 | K35: =SUM(K4:K34) -> 0 | L35: =SUM(L4:L34) -> 0

Sheet Amalapuram
A2: S.No | B2: Date | C2: GRN No | D2: Ind no/Bill No | E2: Diesel (Lts) | F2: Price | G2: Amount | H2: Petrol (Lts) | I2: Price | J2: Amount | K2: Total amount | L2: Amount paid | M2: As on Date | N2: Remarks
A3: Opening Balance | M3: 0
A4: 1 | B4: 01.02.2026 | C4: Sri Sathya Dattha Aparna -BPCL | D4: Chendurthi(Yeleswaram) | E4: 0 | G4: 0 | H4: 20.63 | I4: 97.28 | J4: 2006.55 | K4: =G4+J4 -> 2006.55 | L4: 2006.55 | M4: =+M3+K4-L4 -> 0
A5: 2 | B5: 02.02.2026 | C5: BP Lala Cheruvu Bharat Petroleum | D5: Rajahmundry | E5: 46.14 | F5: 96.74 | G5: =E5*F5 -> 4463.5836 | H5: 5 | I5: 108.86 | J5: 544.3 | K5: =G5+J5 -> 5007.8836 | L5: 5007.88 | M5: =+M4+K5-L5 -> 0.0036
A6: 3 | B6: 05.02.2026 | C6: Sri Venkateswara Enterprises | D6: Yanam | E6: 46.69 | F6: 86.75 | G6: =E6*F6 -> 4050.3575 | H6: 0 | I6: 0 | J6: 0 | K6: =G6+J6 -> 4050.3575 | L6: 4050 | M6: =+M5+K6-L6 -> 0.3611
A7: 4 | B7: 05.02.2026 | C7: Sri Radha krishna Agencies | D7: Kakinada | H7: 10 | I7: 110.05 | J7: 1100.5 | K7: =G7+J7 -> 1100.5 | L7: 1100.5 | M7: =+M6+K7-L7 -> 0.3611
A8: 5 | B8: 09.02.2026 | C8: Sri Venkateswara Enterprises | D8: Yanam | E8: 47.7 | F8: 86.75 | G8: =E8*F8 -> 4137.975 | H8: 10 | I8: 96.91 | J8: 969.1 | K8: =G8+J8 -> 5107.075 | L8: 5107.08 | M8: =+M7+K8-L8 -> 0.3561
A9: 6 | B9: 09.02.2026 | C9: Sathya Filling Station | D9: Amalapuram | E9: 0 | G9: =E9*F9 -> 0 | H9: 10 | I9: 109.55 | J9: 1095.5 | K9: =G9+J9 -> 1095.5 | L9: 1095.5 | M9: =+M8+K9-L9 -> 0.3561
A10: 7 | B10: 11.02.2026 | C10: Sri Sathya Enterprises Bharat Petroleum | D10: Mettacur(Yanam) | E10: 44.61 | F10: 86.75 | G10: =E10*F10 -> 3869.9175 | K10: =G10+J10 -> 3869.9175 | L10: 3869.92 | M10: =+M9+K10-L10 -> 0.3536
A11: 8 | B11: 12.02.2026 | C11: BP Lala Cheruvu Bharat Petroleum | D11: Lalacheruvu | E11: 23.19 | F11: 96.74 | G11: 2243.4 | H11: 0 | K11: =G11+J11 -> 2243.4 | L11: 2243.4 | M11: =+M10+K11-L11 -> 0.3536
A12: 9 | B12: 12.02.2026 | C12: BP Kakinada Bhanugudi | D12: Kakinada | E12: 0 | H12: 10 | I12: 109.94 | J12: 1099.4 | K12: =G12+J12 -> 1099.4 | L12: 1099.4 | M12: =+M11+K12-L12 -> 0.3536
A13: 10 | B13: 15.02.2026 | C13: BP Lala Cheruvu Bharat Petroleum | D13: Lalacheruvu | E13: 158.78 | F13: 96.74 | G13: 15360.38 | H13: 5 | I13: 108.86 | J13: 544.3 | K13: =G13+J13 -> 15904.68 | L13: 15904 | M13: =+M12+K13-L13 -> 1.0336
A14: 11 | B14: 17.02.2026 | C14: BP Lala Cheruvu Bharat Petroleum | D14: Lalacheruvu | E14: 42.83 | F14: 96.74 | G14: 4143.37 | K14: =G14+J14 -> 4143.37 | L14: 4143.37 | M14: =+M13+K14-L14 -> 1.0336
A15: 12 | B15: 18.02.2026 | C15: BP Kakinada Bhanugudi | D15: Kakinada | E15: 0 | H15: 40.87 | I15: 109.94 | J15: 4493.25 | K15: =G15+J15 -> 4493.25 | L15: 4493.25 | M15: =+M14+K15-L15 -> 1.0336
A16: 13 | B16: 19.02.2026 | C16: BP Lala Cheruvu Bharat Petroleum | D16: Lalacheruvu | E16: 0 | H16: 10 | I16: 108.86 | J16: 1088.6 | K16: =G16+J16 -> 1088.6 | L16: 1088.6 | M16: =+M15+K16-L16 -> 1.0336
A17: 14 | B17: 20.02.2026 | C17: SRI LALITHA AGENCIES BHARAT PETROLEUM DEALERS | D17: PEDDAPURAM | E17: 37.37 | F17: 96.88 | G17: 3620.41 | K17: =G17+J17 -> 3620.41 | L17: 3620.41 | M17: =+M16+K17-L17 -> 1.0336
A18: 15 | B18: 21.02.2026 | C18: JVVR Filling Station Bharat Petroleum | D18: Pitapuram | E18: 0 | H18: 15 | I18: 109.68 | J18: 1645.2 | K18: 1645.2 | L18: 1645.2 | M18: =+M16+K18-L18 -> 1.0336
A19: 16 | B19: 25.02.2026 | C19: Sri Sathya Dattha Aparna -BPCL | D19: Chendurthi(Yeleswaram) | E19: 45.1 | F19: 97.28 | G19: 4387.33 | H19: 15 | I19: 109.47 | J19: 1642.05 | K19: 6029.38 | L19: 6029.38 | M19: =+M18+K19-L19 -> 1.0336
A20: 17 | B20: 25.02.2026 | C20: BP Lala Cheruvu Bharat Petroleum | D20: Lalacheruvu | E20: 0 | H20: 5 | I20: 108.86 | J20: 544.3 | K20: 544.3 | L20: 544.3 | M20: =+M19+K20-L20 -> 1.0336
A21: 18 | B21: 26.02.2026 | C21: Sri Balaji Agencies BPCL | D21: Kakinada | E21: 0 | H21: 5 | I21: 109.94 | J21: 550 | K21: 550 | L21: 550 | M21: =+M20+K21-L21 -> 1.0336
A22: 19 | B22: 28.02.2026 | C22: BP Lala Cheruvu Bharat Petroleum | D22: Lalacheruvu | E22: 37.66 | F22: 96.74 | G22: 3643.23 | H22: 5 | I22: 108.86 | J22: 544.3 | K22: 4187.53 | L22: 4187.53 | M22: =+M21+K22-L22 -> 1.0336
A23: 20 | B23: 28.02.2026 | C23: BP Lala Cheruvu Bharat Petroleum | D23: Lalacheruvu | E23: 0 | F23: 0 | G23: 0 | H23: 5 | I23: 116.14 | J23: 580.7 | K23: 580.7 | L23: 580.7 | M23: =+M22+K23-L23 -> 1.0336
A24: 21 | M24: =+M23+K24-L24 -> 1.0336
A25: 22 | M25: =+M24+K25-L25 -> 1.0336
A26: 23 | M26: =+M25+K26-L26 -> 1.0336
A27: 24 | M27: =+M26+K27-L27 -> 1.0336
A28: 25 | M28: =+M27+K28-L28 -> 1.0336
A29: 26 | M29: =+M28+K29-L29 -> 1.0336
A30: 27 | M30: =+M29+K30-L30 -> 1.0336
A31: 28 | M31: =+M30+K31-L31 -> 1.0336
A32: 29 | M32: =+M31+K32-L32 -> 1.0336
A33: 30 | M33: =+M32+K33-L33 -> 1.0336
A34: 30 | M34: =+M33+K34-L34 -> 1.0336
A35: 31 | M35: =+M34+K35-L35 -> 1.0336
A36: 32 | I36: 0 | J36: =H36*I36 -> 0 | K36: =G36+J36 -> 0 | M36: =+M35+K36-L36 -> 1.0336
A37: 33 | G37: =E37*F37 -> 0 | H37: 0 | I37: 0 | J37: =H37*I37 -> 0 | K37: =G37+J37 -> 0 | M37: =+M36+K37-L37 -> 1.0336
E38: =SUM(E4:E37) -> 530.07 | G38: =SUM(G4:G37) -> 49919.954 | H38: =SUM(H4:H37) -> 171.5 | J38: =SUM(J4:J37) -> 18448.05 | K38: =SUM(K4:K37) -> 68368.004 | L38: =SUM(L4:L37) -> 68366.97

Sheet Madana palli
A2: S.No | B2: Date | C2: GRN No | D2: Ind no/Bill No | E2: Diesel (Lts) | F2: Price | G2: Amount | H2: Petrol (Lts) | I2: Price | J2: Amount | K2: Total amount | L2: Amount paid | M2: As on Date | N2: Remarks
A3: Opening Balance | M3: 0
A4: 1 | B4: 46054 | G4: =E4*F4 -> 0 | H4: 0 | I4: 0 | J4: =H4*I4 -> 0 | K4: =G4+J4 -> 0 | L4: =+K4 -> 0 | M4: 0
A5: 2 | B5: 46055 | G5: =E5*F5 -> 0 | H5: 0 | I5: 0 | J5: =H5*I5 -> 0 | K5: =G5+J5 -> 0 | L5: =+K5 -> 0 | M5: 0
A6: 3 | B6: 46056 | G6: =E6*F6 -> 0 | H6: 5.11 | I6: 109.61 | J6: =H6*I6 -> 560.1071 | K6: =G6+J6 -> 560.1071 | L6: =+K6 -> 560.1071 | M6: 0 | N6: IOCL
A7: 4 | B7: 46057 | G7: =E7*F7 -> 0 | H7: 0 | I7: 0 | J7: =H7*I7 -> 0 | K7: =G7+J7 -> 0 | L7: =+K7 -> 0 | M7: 0
A8: 5 | B8: 46058 | E8: 200 | F8: 97.79 | G8: =E8*F8 -> 19558 | H8: 0 | I8: 0 | J8: =H8*I8 -> 0 | K8: =G8+J8 -> 19558 | L8: =+K8 -> 19558 | M8: 0 | N8: HP
A9: 6 | B9: 46059 | G9: =E9*F9 -> 0 | H9: 0 | I9: 0 | J9: =H9*I9 -> 0 | K9: =G9+J9 -> 0 | L9: =+K9 -> 0 | M9: 0
A10: 7 | B10: 46060 | G10: =E10*F10 -> 0 | H10: 0 | I10: 0 | J10: =H10*I10 -> 0 | K10: =G10+J10 -> 0 | L10: =+K10 -> 0 | M10: 0 | O10: 169.99
A11: 8 | B11: 46061 | G11: =E11*F11 -> 0 | H11: 0 | I11: 0 | J11: =H11*I11 -> 0 | K11: =G11+J11 -> 0 | L11: =+K11 -> 0 | M11: 0 | O11: 80
A12: 9 | B12: 46062 | G12: =E12*F12 -> 0 | H12: 0 | I12: 0 | J12: =H12*I12 -> 0 | K12: =G12+J12 -> 0 | L12: =+K12 -> 0 | M12: 0 | O12: =SUM(O10:O11) -> 249.99 | P12: 97.76 | Q12: =O12*P12 -> 24439.022
A13: 10 | B13: 46063 | G13: =E13*F13 -> 0 | H13: 0 | I13: 0 | J13: =H13*I13 -> 0 | K13: =G13+J13 -> 0 | L13: =+K13 -> 0 | M13: 0
A14: 11 | B14: 46064 | G14: =E14*F14 -> 0 | H14: 5.96 | I14: 109.61 | J14: =H14*I14 -> 653.2756 | K14: =G14+J14 -> 653.2756 | L14: =+K14 -> 653.2756 | M14: 0
A15: 12 | B15: 46065 | G15: =E15*F15 -> 0 | H15: 0 | I15: 0 | J15: =H15*I15 -> 0 | K15: =G15+J15 -> 0 | L15: =+K15 -> 0 | M15: 0 | P15: 7820.8
A16: 13 | B16: 46066 | G16: =E16*F16 -> 0 | H16: 0 | I16: 0 | J16: =H16*I16 -> 0 | K16: =G16+J16 -> 0 | L16: =+K16 -> 0 | M16: 0 | P16: 16619.2
A17: 14 | B17: 46067 | G17: =E17*F17 -> 0 | H17: 0 | I17: 0 | J17: =H17*I17 -> 0 | K17: =G17+J17 -> 0 | L17: =+K17 -> 0 | M17: 0 | P17: =SUM(P15:P16) -> 24440
A18: 15 | B18: 46068 | G18: =E18*F18 -> 0 | H18: 0 | I18: 0 | J18: =H18*I18 -> 0 | K18: =G18+J18 -> 0 | L18: =+K18 -> 0 | M18: 0
A19: 16 | B19: 46069 | G19: =E19*F19 -> 0 | H19: 0 | I19: 0 | J19: =H19*I19 -> 0 | K19: =G19+J19 -> 0 | L19: =+K19 -> 0 | M19: 0
A20: 17 | B20: 46070 | G20: =E20*F20 -> 0 | H20: 6.1 | I20: 109.61 | J20: =H20*I20 -> 668.621 | K20: =G20+J20 -> 668.621 | L20: =+K20 -> 668.621 | M20: 0
A21: 18 | B21: 46071 | G21: =E21*F21 -> 0 | H21: 0 | I21: 0 | J21: =H21*I21 -> 0 | K21: =G21+J21 -> 0 | L21: =+K21 -> 0 | M21: 0
A22: 19 | B22: 46072 | G22: =E22*F22 -> 0 | H22: 0 | I22: 0 | J22: =H22*I22 -> 0 | K22: =G22+J22 -> 0 | L22: =+K22 -> 0 | M22: 0
A23: 20 | B23: 46073 | G23: =E23*F23 -> 0 | H23: 0 | I23: 0 | J23: =H23*I23 -> 0 | K23: =G23+J23 -> 0 | L23: =+K23 -> 0 | M23: 0
A24: 21 | B24: 46074 | G24: =E24*F24 -> 0 | H24: 0 | I24: 0 | J24: =H24*I24 -> 0 | K24: =G24+J24 -> 0 | L24: =+K24 -> 0 | M24: 0
A25: 22 | B25: 46075 | G25: =E25*F25 -> 0 | H25: 0 | I25: 0 | J25: =H25*I25 -> 0 | K25: =G25+J25 -> 0 | L25: =+K25 -> 0 | M25: 0
A26: 23 | B26: 46076 | E26: 15.39 | F26: 97.43 | G26: =E26*F26 -> 1499.4477 | H26: 6.16 | I26: 109.61 | J26: =H26*I26 -> 675.1976 | K26: =G26+J26 -> 2174.6453 | L26: =+K26 -> 2174.6453 | M26: 0
A27: 24 | B27: 46077 | G27: =E27*F27 -> 0 | H27: 0 | I27: 0 | J27: =H27*I27 -> 0 | K27: =G27+J27 -> 0 | L27: =+K27 -> 0 | M27: 0
A28: 25 | B28: 46078 | G28: =E28*F28 -> 0 | H28: 0 | I28: 0 | J28: =H28*I28 -> 0 | K28: =G28+J28 -> 0 | L28: =+K28 -> 0 | M28: 0
A29: 26 | B29: 46079 | G29: =E29*F29 -> 0 | H29: 0 | I29: 0 | J29: =H29*I29 -> 0 | K29: =G29+J29 -> 0 | L29: =+K29 -> 0 | M29: 0
A30: 27 | B30: 46080 | G30: =E30*F30 -> 0 | H30: 0 | I30: 0 | J30: =H30*I30 -> 0 | K30: =G30+J30 -> 0 | L30: =+K30 -> 0 | M30: 0
A31: 28 | B31: 46081 | G31: =E31*F31 -> 0 | H31: 0 | I31: 0 | J31: =H31*I31 -> 0 | K31: =G31+J31 -> 0 | L31: =+K31 -> 0 | M31: 0
A32: 29 | G32: =E32*F32 -> 0 | H32: 0 | I32: 0 | J32: =H32*I32 -> 0 | K32: =G32+J32 -> 0 | L32: =+K32 -> 0 | M32: 0
A33: 30 | G33: =E33*F33 -> 0 | H33: 0 | I33: 0 | J33: =H33*I33 -> 0 | K33: =G33+J33 -> 0 | L33: =+K33 -> 0 | M33: 0
A34: 31 | G34: =E34*F34 -> 0 | H34: 0 | I34: 0 | J34: =H34*I34 -> 0 | K34: =G34+J34 -> 0 | L34: =+K34 -> 0 | M34: 0
E35: =SUM(E4:E34) -> 215.39 | G35: =SUM(G4:G34) -> 21057.448 | H35: =SUM(H4:H34) -> 23.33 | J35: =SUM(J4:J34) -> 2557.2013 | K35: =SUM(K4:K34) -> 23614.649 | L35: =SUM(L4:L34) -> 23614.649

Sheet Kadur
A1: Vishal Service Station
A2: S.No | B2: Date | C2: GRN No | D2: Ind No/Bill No | E2: Diesel (Lts) | F2: Price | G2: Amount | H2: Petrol (Lts) | I2: Price | J2: Amount | K2: Total amount | L2: Amount paid | M2: As on Date | N2: Remarks
A3: Opening Balance | K3: 14627.031 | M3: 14627.031 | O3: 207239.43
A4: 1 | B4: 45689 | F4: 0 | G4: =E4*F4 -> 0 | H4: 0 | I4: 0 | J4: =H4*I4 -> 0 | K4: =G4+J4 -> 0 | M4: =M3+K4-L4 -> 14627.031
A5: 2 | B5: 45690 | F5: 0 | G5: =E5*F5 -> 0 | H5: 0 | I5: 0 | J5: =H5*I5 -> 0 | K5: =G5+J5 -> 0 | L5: 14492 | M5: =M4+K5-L5 -> 135.031
A6: 3 | B6: 45691 | F6: 0 | G6: =E6*F6 -> 0 | H6: 0 | I6: 0 | J6: =H6*I6 -> 0 | K6: =G6+J6 -> 0 | M6: =M5+K6-L6 -> 135.031
A7: 4 | B7: 45692 | F7: 0 | G7: =E7*F7 -> 0 | H7: 0 | I7: 0 | J7: =H7*I7 -> 0 | K7: =G7+J7 -> 0 | M7: =M6+K7-L7 -> 135.031
A8: 5 | B8: 45693 | F8: 0 | G8: =E8*F8 -> 0 | H8: 0 | I8: 0 | J8: =H8*I8 -> 0 | K8: =G8+J8 -> 0 | M8: =M7+K8-L8 -> 135.031
A9: 6 | B9: 45694 | F9: 0 | G9: =E9*F9 -> 0 | H9: 0 | I9: 0 | J9: =H9*I9 -> 0 | K9: =G9+J9 -> 0 | M9: =M8+K9-L9 -> 135.031
A10: 7 | B10: 45695 | F10: 0 | G10: =E10*F10 -> 0 | H10: 0 | I10: 0 | J10: =H10*I10 -> 0 | K10: =G10+J10 -> 0 | M10: =M9+K10-L10 -> 135.031
A11: 8 | B11: 45696 | E11: 2500 | F11: 92.15 | G11: =E11*F11 -> 230375 | H11: 100 | I11: 104.27 | J11: =H11*I11 -> 10427 | K11: =G11+J11 -> 240802 | M11: =M10+K11-L11 -> 240937.03
A12: 9 | B12: 45697 | F12: 0 | G12: =E12*F12 -> 0 | H12: 0 | I12: 0 | J12: =H12*I12 -> 0 | K12: =G12+J12 -> 0 | M12: =M11+K12-L12 -> 240937.03
A13: 10 | B13: 45698 | F13: 0 | G13: =E13*F13 -> 0 | H13: 0 | I13: 0 | J13: =H13*I13 -> 0 | K13: =G13+J13 -> 0 | M13: =M12+K13-L13 -> 240937.03
A14: 11 | B14: 45699 | F14: 0 | G14: =E14*F14 -> 0 | H14: 0 | I14: 0 | J14: =H14*I14 -> 0 | K14: =G14+J14 -> 0 | M14: =M13+K14-L14 -> 240937.03
A15: 12 | B15: 45700 | F15: 0 | G15: =E15*F15 -> 0 | H15: 0 | I15: 0 | J15: =H15*I15 -> 0 | K15: =G15+J15 -> 0 | M15: =M14+K15-L15 -> 240937.03
A16: 13 | B16: 45701 | F16: 0 | G16: =E16*F16 -> 0 | H16: 0 | I16: 0 | J16: =H16*I16 -> 0 | K16: =G16+J16 -> 0 | M16: =M15+K16-L16 -> 240937.03
A17: 14 | B17: 45702 | F17: 0 | G17: =E17*F17 -> 0 | H17: 0 | I17: 0 | J17: =H17*I17 -> 0 | K17: =G17+J17 -> 0 | M17: =M16+K17-L17 -> 240937.03
A18: 15 | B18: 45703 | F18: 0 | G18: =E18*F18 -> 0 | H18: 0 | I18: 0 | J18: =H18*I18 -> 0 | K18: =G18+J18 -> 0 | M18: =M17+K18-L18 -> 240937.03
A19: 16 | B19: 45704 | F19: 0 | G19: =E19*F19 -> 0 | H19: 0 | I19: 0 | J19: =H19*I19 -> 0 | K19: =G19+J19 -> 0 | M19: =M18+K19-L19 -> 240937.03
A20: 17 | B20: 45705 | F20: 0 | G20: =E20*F20 -> 0 | H20: 0 | I20: 0 | J20: =H20*I20 -> 0 | K20: =G20+J20 -> 0 | M20: =M19+K20-L20 -> 240937.03
A21: 18 | B21: 45706 | F21: 0 | G21: =E21*F21 -> 0 | H21: 0 | I21: 0 | J21: =H21*I21 -> 0 | K21: =G21+J21 -> 0 | M21: =M20+K21-L21 -> 240937.03
A22: 19 | B22: 45707 | F22: 0 | H22: 0 | I22: 0 | J22: =H22*I22 -> 0 | K22: =G22+J22 -> 0 | M22: =M21+K22-L22 -> 240937.03
A23: 20 | B23: 45708 | F23: 0 | J23: =H23*I23 -> 0 | K23: =G23+J23 -> 0 | M23: =M22+K23-L23 -> 240937.03
A24: 21 | B24: 45709 | F24: 0 | J24: =H24*I24 -> 0 | K24: =G24+J24 -> 0 | M24: =M23+K24-L24 -> 240937.03
A25: 22 | B25: 45710 | F25: 0 | J25: =H25*I25 -> 0 | K25: =G25+J25 -> 0 | M25: =M24+K25-L25 -> 240937.03
A26: 23 | B26: 45711 | F26: 0 | J26: =H26*I26 -> 0 | K26: =G26+J26 -> 0 | M26: =M25+K26-L26 -> 240937.03
A27: 24 | B27: 45712 | F27: 0 | J27: =H27*I27 -> 0 | K27: =G27+J27 -> 0 | M27: =M26+K27-L27 -> 240937.03
A28: 25 | B28: 45713 | F28: 0 | J28: =H28*I28 -> 0 | K28: =G28+J28 -> 0 | M28: =M27+K28-L28 -> 240937.03
A29: 26 | B29: 45714 | F29: 0 | J29: =H29*I29 -> 0 | K29: =G29+J29 -> 0 | M29: =M28+K29-L29 -> 240937.03
A30: 27 | B30: 45715 | F30: 0 | J30: =H30*I30 -> 0 | K30: =G30+J30 -> 0 | M30: =M29+K30-L30 -> 240937.03
A31: 28 | B31: 45716 | F31: 0 | J31: =H31*I31 -> 0 | K31: =G31+J31 -> 0 | M31: =M30+K31-L31 -> 240937.03
A32: 29 | F32: 0 | G32: =E32*F32 -> 0 | H32: 0 | I32: 0 | J32: =H32*I32 -> 0 | K32: =G32+J32 -> 0 | M32: =M31+K32-L32 -> 240937.03
A33: 30 | F33: 0 | G33: =E33*F33 -> 0 | H33: 0 | I33: 0 | J33: =H33*I33 -> 0 | K33: =G33+J33 -> 0 | M33: =M32+K33-L33 -> 240937.03
A34: 31 | F34: 0 | G34: =E34*F34 -> 0 | J34: =H34*I34 -> 0 | K34: =G34+J34 -> 0
E35: =SUM(E4:E34) -> 2500 | G35: =SUM(G4:G34) -> 230375 | H35: =SUM(H4:H34) -> 100 | J35: =SUM(J4:J34) -> 10427 | K35: =SUM(K4:K34) -> 240802 | L35: =SUM(L4:L31) -> 14492

Sheet YG Gudda-2
A1: Pankaja Hp Fuel Center
A2: S.No | B2: Date | C2: GRN No | D2: Ind No/Bill No | E2: Diesel (Lts) | F2: Price | G2: Amount | H2: Petrol (Lts) | I2: Price | J2: Amount | K2: Total amount | L2: Amount paid | M2: As on Date | N2: Remarks
A3: Opening Balance | K3: 0 | M3: 478336.85 | O3: 99992.615
A4: 1 | B4: 46054 | G4: =E4*F4 -> 0 | J4: =H4*I4 -> 0 | K4: =G4+J4 -> 0 | M4: =M3+K4-L4 -> 478336.85
A5: 2 | B5: 46055 | G5: =E5*F5 -> 0 | J5: =H5*I5 -> 0 | K5: =G5+J5 -> 0 | L5: 478337 | M5: =M4+K5-L5 -> -0.147097
A6: 3 | B6: 46056 | G6: =E6*F6 -> 0 | J6: =H6*I6 -> 0 | K6: =G6+J6 -> 0 | M6: =M5+K6-L6 -> -0.147097
A7: 4 | B7: 46057 | E7: 2000 | F7: 91.33 | G7: =E7*F7 -> 182660 | H7: 105 | I7: 103.27 | J7: =H7*I7 -> 10843.35 | K7: =G7+J7 -> 193503.35 | M7: =M6+K7-L7 -> 193503.2 | O7: 1 | P7: Bill No
A8: 5 | B8: 46058 | G8: =E8*F8 -> 0 | J8: =H8*I8 -> 0 | K8: =G8+J8 -> 0 | M8: =M7+K8-L8 -> 193503.2
A9: 6 | B9: 46059 | G9: =E9*F9 -> 0 | J9: =H9*I9 -> 0 | K9: =G9+J9 -> 0 | M9: =M8+K9-L9 -> 193503.2
A10: 7 | B10: 46060 | G10: =E10*F10 -> 0 | J10: =H10*I10 -> 0 | K10: =G10+J10 -> 0 | M10: =M9+K10-L10 -> 193503.2
A11: 8 | B11: 46061 | G11: =E11*F11 -> 0 | J11: =H11*I11 -> 0 | K11: =G11+J11 -> 0 | M11: =M10+K11-L11 -> 193503.2
A12: 9 | B12: 46062 | E12: 2000 | F12: 91.33 | G12: =E12*F12 -> 182660 | H12: 35 | I12: 103.27 | J12: =H12*I12 -> 3614.45 | K12: =G12+J12 -> 186274.45 | M12: =M11+K12-L12 -> 379777.65 | O12: 2 | P12: Bill No
A13: 10 | B13: 46063 | G13: =E13*F13 -> 0 | J13: =H13*I13 -> 0 | K13: =G13+J13 -> 0 | M13: =M12+K13-L13 -> 379777.65
A14: 11 | B14: 46064 | G14: =E14*F14 -> 0 | J14: =H14*I14 -> 0 | K14: =G14+J14 -> 0 | M14: =M13+K14-L14 -> 379777.65
A15: 12 | B15: 46065 | G15: =E15*F15 -> 0 | J15: =H15*I15 -> 0 | K15: =G15+J15 -> 0 | M15: =M14+K15-L15 -> 379777.65
A16: 13 | B16: 46066 | E16: 500 | F16: 91.33 | G16: =E16*F16 -> 45665 | J16: =H16*I16 -> 0 | K16: =G16+J16 -> 45665 | M16: =M15+K16-L16 -> 425442.65 | O16: 3 | P16: Bill No
A17: 14 | B17: 46067 | E17: 2000 | F17: 91.33 | G17: =E17*F17 -> 182660 | H17: 70 | I17: 103.27 | J17: =H17*I17 -> 7228.9 | K17: =G17+J17 -> 189888.9 | M17: =M16+K17-L17 -> 615331.55
A18: 15 | B18: 46068 | G18: =E18*F18 -> 0 | J18: =H18*I18 -> 0 | K18: =G18+J18 -> 0 | M18: =M17+K18-L18 -> 615331.55
A19: 16 | B19: 46069 | G19: =E19*F19 -> 0 | J19: =H19*I19 -> 0 | K19: =G19+J19 -> 0 | M19: =M18+K19-L19 -> 615331.55
A20: 17 | B20: 46070 | G20: =E20*F20 -> 0 | J20: =H20*I20 -> 0 | K20: =G20+J20 -> 0 | M20: =M19+K20-L20 -> 615331.55
A21: 18 | B21: 46071 | E21: 2000 | F21: 91.33 | G21: =E21*F21 -> 182660 | H21: 70 | I21: 103.27 | J21: =H21*I21 -> 7228.9 | K21: =G21+J21 -> 189888.9 | M21: =M20+K21-L21 -> 805220.45
A22: 19 | B22: 46072 | G22: =E22*F22 -> 0 | J22: =H22*I22 -> 0 | K22: =G22+J22 -> 0 | M22: =M21+K22-L22 -> 805220.45
A23: 20 | B23: 46073 | G23: =E23*F23 -> 0 | J23: =H23*I23 -> 0 | K23: =G23+J23 -> 0 | L23: 500000 | M23: =M22+K23-L23 -> 305220.45
A24: 21 | B24: 46074 | G24: =E24*F24 -> 0 | J24: =H24*I24 -> 0 | K24: =G24+J24 -> 0 | M24: =M23+K24-L24 -> 305220.45 | O24: 4 | P24: Bill No
A25: 22 | B25: 46075 | G25: =E25*F25 -> 0 | J25: =H25*I25 -> 0 | K25: =G25+J25 -> 0 | M25: =M24+K25-L25 -> 305220.45
A26: 23 | B26: 46076 | E26: 2000 | F26: 91.33 | G26: =E26*F26 -> 182660 | H26: 35 | I26: 103.27 | J26: =H26*I26 -> 3614.45 | K26: =G26+J26 -> 186274.45 | M26: =M25+K26-L26 -> 491494.9
A27: 24 | B27: 46077 | G27: =E27*F27 -> 0 | J27: =H27*I27 -> 0 | K27: =G27+J27 -> 0 | M27: =M26+K27-L27 -> 491494.9
A28: 25 | B28: 46078 | G28: =E28*F28 -> 0 | J28: =H28*I28 -> 0 | K28: =G28+J28 -> 0 | M28: =M27+K28-L28 -> 491494.9
A29: 26 | B29: 46079 | G29: =E29*F29 -> 0 | J29: =H29*I29 -> 0 | K29: =G29+J29 -> 0 | L29: 150000 | M29: =M28+K29-L29 -> 341494.9
A30: 27 | B30: 46080 | G30: =E30*F30 -> 0 | J30: =H30*I30 -> 0 | K30: =G30+J30 -> 0 | M30: =M29+K30-L30 -> 341494.9
A31: 28 | B31: 46081 | E31: 2000 | F31: 91.33 | G31: =E31*F31 -> 182660 | H31: 70 | I31: 103.27 | J31: =H31*I31 -> 7228.9 | K31: =G31+J31 -> 189888.9 | M31: =M30+K31-L31 -> 531383.8
A32: 29 | G32: =E32*F32 -> 0 | J32: =H32*I32 -> 0 | K32: =G32+J32 -> 0 | M32: =M31+K32-L32 -> 531383.8
A33: 30 | G33: =E33*F33 -> 0 | J33: =H33*I33 -> 0 | K33: =G33+J33 -> 0 | M33: =M32+K33-L33 -> 531383.8
A34: 31 | G34: =E34*F34 -> 0 | J34: =H34*I34 -> 0 | K34: =G34+J34 -> 0 | M34: =M33+K34-L34 -> 531383.8
A35: 32 | G35: =E35*F35 -> 0 | H35: 0 | I35: 0 | J35: =H35*I35 -> 0 | K35: =G35+J35 -> 0 | M35: =M34+K35-L35 -> 531383.8
E36: =SUM(E4:E35) -> 12500 | G36: =SUM(G4:G35) -> 1141625 | H36: =SUM(H4:H35) -> 385 | J36: =SUM(J4:J35) -> 39758.95 | K36: =SUM(K4:K35) -> 1181383.9 | L36: =SUM(L4:L35) -> 1128337

Sheet Hosadurga
A1: Merchant Petroliums
A2: S.No | B2: Date | C2: GRN No | D2: Ind No/Bill No | E2: Diesel (Lts) | F2: Price | G2: Amount | H2: Petrol (Lts) | I2: Price | J2: Amount | K2: Total amount | L2: Amount paid | M2: As on Date | N2: Remarks
A3: Opening Balance | K3: 2258.6 | M3: =+K3 -> 2258.6
A4: 1 | B4: 46054 | G4: =E4*F4 -> 0 | H4: 0 | J4: =H4*I4 -> 0 | K4: =G4+J4 -> 0 | L4: 0 | M4: =M3+K4-L4 -> 2258.6
A5: 2 | B5: 46055 | G5: =E5*F5 -> 0 | H5: 0 | I5: 0 | J5: =H5*I5 -> 0 | K5: =G5+J5 -> 0 | L5: 0 | M5: =M4+K5-L5 -> 2258.6
A6: 3 | B6: 46056 | G6: =E6*F6 -> 0 | H6: 0 | I6: 0 | J6: =H6*I6 -> 0 | K6: =G6+J6 -> 0 | L6: 2260 | M6: =M5+K6-L6 -> -1.4
A7: 4 | B7: 46057 | G7: =E7*F7 -> 0 | H7: 0 | I7: 0 | J7: =H7*I7 -> 0 | K7: =G7+J7 -> 0 | L7: 0 | M7: =M6+K7-L7 -> -1.4
A8: 5 | B8: 46058 | G8: =E8*F8 -> 0 | H8: 0 | I8: 0 | J8: =H8*I8 -> 0 | K8: =G8+J8 -> 0 | L8: 0 | M8: =M7+K8-L8 -> -1.4
A9: 6 | B9: 46059 | G9: =E9*F9 -> 0 | H9: 0 | I9: 0 | J9: =H9*I9 -> 0 | K9: =G9+J9 -> 0 | L9: 0 | M9: =M8+K9-L9 -> -1.4
A10: 7 | B10: 46060 | G10: =E10*F10 -> 0 | J10: =H10*I10 -> 0 | K10: =G10+J10 -> 0 | L10: 0 | M10: =M9+K10-L10 -> -1.4
A11: 8 | B11: 46061 | G11: =E11*F11 -> 0 | H11: 0 | I11: 0 | J11: =H11*I11 -> 0 | K11: =G11+J11 -> 0 | L11: 0 | M11: =M10+K11-L11 -> -1.4
A12: 9 | B12: 46062 | G12: =E12*F12 -> 0 | H12: 0 | I12: 0 | J12: =H12*I12 -> 0 | K12: =G12+J12 -> 0 | L12: 0 | M12: =M11+K12-L12 -> -1.4
A13: 10 | B13: 46063 | G13: =E13*F13 -> 0 | H13: 0 | I13: 0 | J13: =H13*I13 -> 0 | K13: =G13+J13 -> 0 | L13: 0 | M13: =M12+K13-L13 -> -1.4
A14: 11 | B14: 46064 | G14: =E14*F14 -> 0 | H14: 0 | I14: 0 | J14: =H14*I14 -> 0 | K14: =G14+J14 -> 0 | L14: 0 | M14: =M13+K14-L14 -> -1.4
A15: 12 | B15: 46065 | G15: =E15*F15 -> 0 | H15: 0 | I15: 0 | J15: =H15*I15 -> 0 | K15: =G15+J15 -> 0 | L15: 0 | M15: =M14+K15-L15 -> -1.4
A16: 13 | B16: 46066 | G16: =E16*F16 -> 0 | H16: 0 | I16: 0 | J16: =H16*I16 -> 0 | K16: =G16+J16 -> 0 | L16: 0 | M16: =M15+K16-L16 -> -1.4 | X16: =100*104 -> 10400
A17: 14 | B17: 46067 | G17: =E17*F17 -> 0 | H17: 0 | I17: 0 | J17: =H17*I17 -> 0 | K17: =G17+J17 -> 0 | L17: 0 | M17: =M16+K17-L17 -> -1.4
A18: 15 | B18: 46068 | G18: =E18*F18 -> 0 | H18: 0 | I18: 0 | J18: =H18*I18 -> 0 | K18: =G18+J18 -> 0 | M18: =M17+K18-L18 -> -1.4
A19: 16 | B19: 46069 | G19: =E19*F19 -> 0 | H19: 0 | I19: 0 | J19: =H19*I19 -> 0 | K19: =G19+J19 -> 0 | M19: =M18+K19-L19 -> -1.4
A20: 17 | B20: 46070 | G20: =E20*F20 -> 0 | H20: 0 | I20: 0 | J20: =H20*I20 -> 0 | K20: =G20+J20 -> 0 | M20: =M19+K20-L20 -> -1.4
A21: 18 | B21: 46071 | G21: =E21*F21 -> 0 | H21: 0 | I21: 0 | J21: =H21*I21 -> 0 | K21: =G21+J21 -> 0 | M21: =M20+K21-L21 -> -1.4
A22: 19 | B22: 46072 | G22: =E22*F22 -> 0 | H22: 0 | I22: 0 | J22: =H22*I22 -> 0 | K22: =G22+J22 -> 0 | M22: =M21+K22-L22 -> -1.4
A23: 20 | B23: 46073 | G23: =E23*F23 -> 0 | H23: 0 | I23: 0 | J23: =H23*I23 -> 0 | K23: =G23+J23 -> 0 | M23: =M22+K23-L23 -> -1.4
A24: 21 | B24: 46074 | G24: =E24*F24 -> 0 | H24: 0 | I24: 0 | J24: =H24*I24 -> 0 | K24: =G24+J24 -> 0 | M24: =M23+K24-L24 -> -1.4
A25: 22 | B25: 46075 | G25: =E25*F25 -> 0 | H25: 0 | I25: 0 | J25: =H25*I25 -> 0 | K25: =G25+J25 -> 0 | M25: =M24+K25-L25 -> -1.4
A26: 23 | B26: 46076 | G26: =E26*F26 -> 0 | H26: 0 | I26: 0 | J26: =H26*I26 -> 0 | K26: =G26+J26 -> 0 | M26: =M25+K26-L26 -> -1.4
A27: 24 | B27: 46077 | G27: =E27*F27 -> 0 | H27: 0 | I27: 0 | J27: =H27*I27 -> 0 | K27: =G27+J27 -> 0 | M27: =M26+K27-L27 -> -1.4
A28: 25 | B28: 46078 | G28: =E28*F28 -> 0 | H28: 0 | I28: 0 | J28: =H28*I28 -> 0 | K28: =G28+J28 -> 0 | M28: =M27+K28-L28 -> -1.4
A29: 26 | B29: 46079 | G29: =E29*F29 -> 0 | H29: 0 | I29: 0 | J29: =H29*I29 -> 0 | K29: =G29+J29 -> 0 | M29: =M28+K29-L29 -> -1.4
... A31: 28 | B31: 46081 | G31: =E31*F31 -> 0 | H31: 0 | I31: 0 | J31: =H31*I31 -> 0 | K31: =G31+J31 -> 0 | M31: =M30+K31-L31 -> -1.4
A32: 29 | G32: =E32*F32 -> 0 | H32: 0 | I32: 0 | J32: =H32*I32 -> 0 | K32: =G32+J32 -> 0 | M32: =M31+K32-L32 -> -1.4
A33: 30 | G33: =E33*F33 -> 0 | H33: 0 | I33: 0 | J33: =H33*I33 -> 0 | K33: =G33+J33 -> 0 | M33: =M32+K33-L33 -> -1.4
A34: 31 | G34: =E34*F34 -> 0 | H34: 0 | I34: 0 | J34: =H34*I34 -> 0 | K34: =G34+J34 -> 0 | L34: 0 | M34: =M33+K34-L34 -> -1.4
E35: =SUM(E4:E34) -> 0 | G35: =SUM(G4:G34) -> 0 | H35: =SUM(H4:H34) -> 0 | J35: =SUM(J4:J34) -> 0 | K35: =SUM(K4:K34) -> 0 | L35: =SUM(L4:L34) -> 2260

Sheet Hosadurga -2
A1: Shree Veera Prathap Fuels
A2: S.No | B2: Date | C2: GRN No | D2: Ind No/Bill No | E2: Diesel (Lts) | F2: Price | G2: Amount | H2: Petrol (Lts) | I2: Price | J2: Amount | K2: Total amount | L2: Amount paid | M2: As on Date | N2: Remarks
A3: Opening Balance | K3: 325898.2 | M3: 325898.2
A4: 1 | B4: 46054 | C4: 0 | G4: =E4*F4 -> 0 | J4: =H4*I4 -> 0 | K4: =G4+J4 -> 0 | M4: =M3+K4-L4 -> 325898.2
A5: 2 | B5: 46055 | C5: 0 | E5: 1700 | F5: 91.55 | G5: =E5*F5 -> 155635 | H5: 70 | I5: 103.73 | J5: =H5*I5 -> 7261.1 | K5: =G5+J5 -> 162896.1 | L5: 325898.2 | M5: =M4+K5-L5 -> 162896.1
A6: 3 | B6: 46056 | C6: 0 | G6: =E6*F6 -> 0 | J6: =H6*I6 -> 0 | K6: =G6+J6 -> 0 | M6: =M5+K6-L6 -> 162896.1
A7: 4 | B7: 46057 | C7: 0 | G7: =E7*F7 -> 0 | J7: =H7*I7 -> 0 | K7: =G7+J7 -> 0 | M7: =M6+K7-L7 -> 162896.1
A8: 5 | B8: 46058 | C8: 0 | G8: =E8*F8 -> 0 | J8: =H8*I8 -> 0 | K8: =G8+J8 -> 0 | M8: =M7+K8-L8 -> 162896.1
A9: 6 | B9: 46059 | C9: 0 | G9: =E9*F9 -> 0 | J9: =H9*I9 -> 0 | K9: =G9+J9 -> 0 | M9: =M8+K9-L9 -> 162896.1
A10: 7 | B10: 46060 | C10: 0 | G10: =E10*F10 -> 0 | J10: =H10*I10 -> 0 | K10: =G10+J10 -> 0 | M10: =M9+K10-L10 -> 162896.1
A11: 8 | B11: 46061 | C11: 0 | G11: =E11*F11 -> 0 | J11: =H11*I11 -> 0 | K11: =G11+J11 -> 0 | M11: =M10+K11-L11 -> 162896.1
A12: 9 | B12: 46062 | C12: 0 | G12: =E12*F12 -> 0 | J12: =H12*I12 -> 0 | K12: =G12+J12 -> 0 | M12: =M11+K12-L12 -> 162896.1
A13: 10 | B13: 46063 | C13: 0 | E13: 1800 | F13: 91.55 | G13: =E13*F13 -> 164790 | H13: 70 | I13: 103.73 | J13: =H13*I13 -> 7261.1 | K13: =G13+J13 -> 172051.1 | M13: =M12+K13-L13 -> 334947.2
A14: 11 | B14: 46064 | C14: 0 | G14: =E14*F14 -> 0 | J14: =H14*I14 -> 0 | K14: =G14+J14 -> 0 | M14: =M13+K14-L14 -> 334947.2
A15: 12 | B15: 46065 | C15: 0 | G15: =E15*F15 -> 0 | J15: =H15*I15 -> 0 | K15: =G15+J15 -> 0 | M15: =M14+K15-L15 -> 334947.2
A16: 13 | B16: 46066 | C16: 0 | G16: =E16*F16 -> 0 | J16: =H16*I16 -> 0 | K16: =G16+J16 -> 0 | M16: =M15+K16-L16 -> 334947.2
A17: 14 | B17: 46067 | C17: 0 | G17: =E17*F17 -> 0 | J17: =H17*I17 -> 0 | K17: =G17+J17 -> 0 | M17: =M16+K17-L17 -> 334947.2
A18: 15 | B18: 46068 | C18: 0 | G18: =E18*F18 -> 0 | J18: =H18*I18 -> 0 | K18: =G18+J18 -> 0 | M18: =M17+K18-L18 -> 334947.2
A19: 16 | B19: 46069 | C19: 0 | G19: =E19*F19 -> 0 | J19: =H19*I19 -> 0 | K19: =G19+J19 -> 0 | M19: =M18+K19-L19 -> 334947.2
A20: 17 | B20: 46070 | C20: 0 | G20: =E20*F20 -> 0 | J20: =H20*I20 -> 0 | K20: =G20+J20 -> 0 | M20: =M19+K20-L20 -> 334947.2
A21: 18 | B21: 46071 | C21: 0 | G21: =E21*F21 -> 0 | J21: =H21*I21 -> 0 | K21: =G21+J21 -> 0 | M21: =M20+K21-L21 -> 334947.2
A22: 19 | B22: 46072 | C22: 0 | E22: 2000 | F22: 91.55 | G22: =E22*F22 -> 183100 | H22: 70 | I22: 103.73 | J22: =H22*I22 -> 7261.1 | K22: =G22+J22 -> 190361.1 | M22: =M21+K22-L22 -> 525308.3
A23: 20 | B23: 46073 | C23: 0 | G23: =E23*F23 -> 0 | J23: =H23*I23 -> 0 | K23: =G23+J23 -> 0 | M23: =M22+K23-L23 -> 525308.3
A24: 21 | B24: 46074 | C24: 0 | G24: =E24*F24 -> 0 | J24: =H24*I24 -> 0 | K24: =G24+J24 -> 0 | M24: =M23+K24-L24 -> 525308.3
A25: 22 | B25: 46075 | C25: 0 | G25: =E25*F25 -> 0 | J25: =H25*I25 -> 0 | K25: =G25+J25 -> 0 | M25: =M24+K25-L25 -> 525308.3
A26: 23 | B26: 46076 | C26: 0 | G26: =E26*F26 -> 0 | J26: =H26*I26 -> 0 | K26: =G26+J26 -> 0 | M26: =M25+K26-L26 -> 525308.3
A27: 24 | B27: 46077 | C27: 0 | G27: =E27*F27 -> 0 | J27: =H27*I27 -> 0 | K27: =G27+J27 -> 0 | M27: =M26+K27-L27 -> 525308.3
A28: 25 | B28: 46078 | C28: 0 | G28: =E28*F28 -> 0 | J28: =H28*I28 -> 0 | K28: =G28+J28 -> 0 | M28: =M27+K28-L28 -> 525308.3
A29: 26 | B29: 46079 | C29: 0 | E29: 1800 | F29: 91.55 | G29: =E29*F29 -> 164790 | H29: 70 | I29: 103.73 | J29: =H29*I29 -> 7261.1 | K29: =G29+J29 -> 172051.1 | L29: 500000 | M29: =M28+K29-L29 -> 197359.4
A30: 27 | B30: 46080 | C30: 0 | G30: =E30*F30 -> 0 | J30: =H30*I30 -> 0 | K30: =G30+J30 -> 0 | M30: =M29+K30-L30 -> 197359.4
A31: 28 | B31: 46081 | C31: 0 | G31: =E31*F31 -> 0 | J31: =H31*I31 -> 0 | K31: =G31+J31 -> 0 | M31: =M30+K31-L31 -> 197359.4
A32: 29 | C32: 0 | G32: =E32*F32 -> 0 | J32: =H32*I32 -> 0 | K32: =G32+J32 -> 0 | M32: =M31+K32-L32 -> 197359.4
A33: 30 | C33: 0 | G33: =E33*F33 -> 0 | J33: =H33*I33 -> 0 | K33: =G33+J33 -> 0 | L33: 0 | M33: =M32+K33-L33 -> 197359.4
A34: 31
E35: =SUM(E4:E34) -> 7300 | G35: =SUM(G4:G34) -> 668315 | H35: =SUM(H4:H34) -> 280 | J35: =SUM(J4:J34) -> 29044.4 | K35: =SUM(K4:K34) -> 697359.4 | L35: =SUM(L4:L34) -> 825898.2

Sheet Hiriyur(VJNL)
A1: Sri Balaji Agencies
A2: S.No | B2: Date | C2: GRN No | D2: Ind No/Bill No | E2: Diesel (Lts) | F2: Price | G2: Amount | H2: Petrol (Lts) | I2: Price | J2: Amount | K2: Total amount | L2: Amount paid | M2: As on Date | N2: Remarks
A3: Opening Balance | K3: 219486.1 | M3: =+K3 -> 219486.1
A4: 1 | B4: 46054 | G4: =E4*F4 -> 0 | J4: =H4*I4 -> 0 | K4: =G4+J4 -> 0 | M4: =M3+K4-L4 -> 219486.1
A5: 2 | B5: 46055 | G5: =E5*F5 -> 0 | J5: =H5*I5 -> 0 | K5: =G5+J5 -> 0 | L5: 219486 | M5: =M4+K5-L5 -> 0.1
A6: 3 | B6: 46056 | G6: =E6*F6 -> 0 | H6: 70 | I6: 104.13 | J6: =H6*I6 -> 7289.1 | K6: =G6+J6 -> 7289.1 | M6: =M5+K6-L6 -> 7289.2
A7: 4 | B7: 46057 | G7: =E7*F7 -> 0 | J7: =H7*I7 -> 0 | K7: =G7+J7 -> 0 | M7: =M6+K7-L7 -> 7289.2
A8: 5 | B8: 46058 | G8: =E8*F8 -> 0 | J8: =H8*I8 -> 0 | K8: =G8+J8 -> 0 | M8: =M7+K8-L8 -> 7289.2
A9: 6 | B9: 46059 | G9: =E9*F9 -> 0 | J9: =H9*I9 -> 0 | K9: =G9+J9 -> 0 | M9: =M8+K9-L9 -> 7289.2
A10: 7 | B10: 46060 | E10: 2400 | F10: 92.26 | G10: =E10*F10 -> 221424 | H10: 35 | I10: 104.13 | J10: =H10*I10 -> 3644.55 | K10: =G10+J10 -> 225068.55 | M10: =M9+K10-L10 -> 232357.75
A11: 8 | B11: 46061 | G11: =E11*F11 -> 0 | J11: =H11*I11 -> 0 | K11: =G11+J11 -> 0 | M11: =M10+K11-L11 -> 232357.75
A12: 9 | B12: 46062 | G12: =E12*F12 -> 0 | J12: =H12*I12 -> 0 | K12: =G12+J12 -> 0 | M12: =M11+K12-L12 -> 232357.75
A13: 10 | B13: 46063 | G13: =E13*F13 -> 0 | J13: =H13*I13 -> 0 | K13: =G13+J13 -> 0 | M13: =M12+K13-L13 -> 232357.75
A14: 11 | B14: 46064 | G14: =E14*F14 -> 0 | J14: =H14*I14 -> 0 | K14: =G14+J14 -> 0 | M14: =M13+K14-L14 -> 232357.75
A15: 12 | B15: 46065 | G15: =E15*F15 -> 0 | J15: =H15*I15 -> 0 | K15: =G15+J15 -> 0 | M15: =M14+K15-L15 -> 232357.75
A16: 13 | B16: 46066 | G16: =E16*F16 -> 0 | J16: =H16*I16 -> 0 | K16: =G16+J16 -> 0 | M16: =M15+K16-L16 -> 232357.75
A17: 14 | B17: 46067 | G17: =E17*F17 -> 0 | H17: 70 | I17: 104.13 | J17: =H17*I17 -> 7289.1 | K17: =G17+J17 -> 7289.1 | M17: =M16+K17-L17 -> 239646.85
A18: 15 | B18: 46068 | G18: =E18*F18 -> 0 | J18: =H18*I18 -> 0 | K18: =G18+J18 -> 0 | M18: =M17+K18-L18 -> 239646.85
A19: 16 | B19: 46069 | G19: =E19*F19 -> 0 | J19: =H19*I19 -> 0 | K19: =G19+J19 -> 0 | M19: =M18+K19-L19 -> 239646.85
A20: 17 | B20: 46070 | G20: =E20*F20 -> 0 | J20: =H20*I20 -> 0 | K20: =G20+J20 -> 0 | M20: =M19+K20-L20 -> 239646.85
A21: 18 | B21: 46071 | G21: =E21*F21 -> 0 | J21: =H21*I21 -> 0 | K21: =G21+J21 -> 0 | M21: =M20+K21-L21 -> 239646.85
A22: 19 | B22: 46072 | G22: =E22*F22 -> 0 | J22: =H22*I22 -> 0 | K22: =G22+J22 -> 0 | M22: =M21+K22-L22 -> 239646.85
A23: 20 | B23: 46073 | G23: =E23*F23 -> 0 | J23: =H23*I23 -> 0 | K23: =G23+J23 -> 0 | M23: =M22+K23-L23 -> 239646.85
A24: 21 | B24: 46074 | G24: =E24*F24 -> 0 | J24: =H24*I24 -> 0 | K24: =G24+J24 -> 0 | M24: =M23+K24-L24 -> 239646.85
A25: 22 | B25: 46075 | G25: =E25*F25 -> 0 | J25: =H25*I25 -> 0 | K25: =G25+J25 -> 0 | M25: =M24+K25-L25 -> 239646.85
A26: 23 | B26: 46076 | G26: =E26*F26 -> 0 | H26: 70 | I26: 104.13 | J26: =H26*I26 -> 7289.1 | K26: =G26+J26 -> 7289.1 | M26: =M25+K26-L26 -> 246935.95
A27: 24 | B27: 46077 | G27: =E27*F27 -> 0 | J27: =H27*I27 -> 0 | K27: =G27+J27 -> 0 | M27: =M26+K27-L27 -> 246935.95
A28: 25 | B28: 46078 | G28: =E28*F28 -> 0 | J28: =H28*I28 -> 0 | K28: =G28+J28 -> 0 | M28: =M27+K28-L28 -> 246935.95
A29: 26 | B29: 46079 | G29: =E29*F29 -> 0 | J29: =H29*I29 -> 0 | K29: =G29+J29 -> 0 | M29: =M28+K29-L29 -> 246935.95
A30: 27 | B30: 46080 | G30: =E30*F30 -> 0 | J30: =H30*I30 -> 0 | K30: =G30+J30 -> 0 | L30: 240000 | M30: =M29+K30-L30 -> 6935.95
A31: 28 | B31: 46081 | G31: =E31*F31 -> 0 | J31: =H31*I31 -> 0 | K31: =G31+J31 -> 0 | M31: =M30+K31-L31 -> 6935.95
A32: 29 | G32: =E32*F32 -> 0 | J32: =H32*I32 -> 0 | K32: =G32+J32 -> 0 | M32: =M31+K32-L32 -> 6935.95
A33: 30 | G33: =E33*F33 -> 0 | J33: =H33*I33 -> 0 | K33: =G33+J33 -> 0 | M33: =M32+K33-L33 -> 6935.95
A34: 31 | G34: =E34*F34 -> 0 | J34: =H34*I34 -> 0 | K34: =G34+J34 -> 0 | M34: =M33+K34-L34 -> 6935.95
E35: =SUM(E4:E34) -> 2400 | G35: =SUM(G4:G34) -> 221424 | H35: =SUM(H4:H34) -> 245 | J35: =SUM(J4:J34) -> 25511.85 | K35: =SUM(K4:K34) -> 246935.85 | L35: =SUM(L4:L34) -> 459486

Sheet Malebenur(KUWSDB)
A1: Sree Veerabhadreshwara Service Station
A2: S.No | B2: Date | C2: GRN No | D2: Ind No/Bill No | E2: Diesel (Lts) | F2: Price | G2: Amount | H2: Petrol (Lts) | I2: Price | J2: Amount | K2: Total amount | L2: Amount paid | M2: As on Date | N2: Remarks
A3: Opening Balance | K3: 213698.56 | M3: =+K3 -> 213698.56 | O3: 46138.764
A4: 1 | B4: 45689 | E4: 0 | F4: 0 | G4: =E4*F4 -> 0 | H4: 0 | I4: 0 | J4: =H4*I4 -> 0 | K4: =G4+J4 -> 0 | L4: 0 | M4: =M3+K4-L4 -> 213698.56
A5: 2 | B5: 45690 | E5: 600 | F5: 92.17 | G5: =E5*F5 -> 55302 | H5: 30 | I5: 104.03 | J5: =H5*I5 -> 3120.9 | K5: =G5+J5 -> 58422.9 | L5: 213689 | M5: =M4+K5-L5 -> 58432.46
A6: 3 | B6: 45691 | E6: 0 | F6: 0 | G6: =E6*F6 -> 0 | H6: 0 | I6: 0 | J6: =H6*I6 -> 0 | K6: =G6+J6 -> 0 | L6: 0 | M6: =M5+K6-L6 -> 58432.46
A7: 4 | B7: 45692 | E7: 0 | F7: 0 | G7: =E7*F7 -> 0 | H7: 0 | I7: 0 | J7: =H7*I7 -> 0 | K7: =G7+J7 -> 0 | L7: 0 | M7: =M6+K7-L7 -> 58432.46
A8: 5 | B8: 45693 | E8: 0 | F8: 0 | G8: =E8*F8 -> 0 | H8: 0 | I8: 0 | J8: =H8*I8 -> 0 | K8: =G8+J8 -> 0 | L8: 0 | M8: =M7+K8-L8 -> 58432.46
A9: 6 | B9: 45694 | E9: 0 | F9: 0 | G9: =E9*F9 -> 0 | H9: 0 | I9: 0 | J9: =H9*I9 -> 0 | K9: =G9+J9 -> 0 | L9: 0 | M9: =M8+K9-L9 -> 58432.46
A10: 7 | B10: 45695 | E10: 600 | F10: 92.17 | G10: =E10*F10 -> 55302 | H10: 25 | I10: 104.03 | J10: =H10*I10 -> 2600.75 | K10: =G10+J10 -> 57902.75 | L10: 0 | M10: =M9+K10-L10 -> 116335.21
A11: 8 | B11: 45696 | E11: 0 | F11: 0 | G11: =E11*F11 -> 0 | H11: 0 | I11: 0 | J11: =H11*I11 -> 0 | K11: =G11+J11 -> 0 | L11: 0 | M11: =M10+K11-L11 -> 116335.21
A12: 9 | B12: 45697 | E12: 0 | F12: 0 | G12: =E12*F12 -> 0 | H12: 0 | I12: 0 | J12: =H12*I12 -> 0 | K12: =G12+J12 -> 0 | L12: 0 | M12: =M11+K12-L12 -> 116335.21
A13: 10 | B13: 45698 | E13: 0 | F13: 0 | G13: =E13*F13 -> 0 | H13: 0 | I13: 0 | J13: =H13*I13 -> 0 | K13: =G13+J13 -> 0 | L13: 0 | M13: =M12+K13-L13 -> 116335.21
A14: 11 | B14: 45699 | E14: 600 | F14: 92.17 | G14: =E14*F14 -> 55302 | H14: 35 | I14: 104.03 | J14: =H14*I14 -> 3641.05 | K14: =G14+J14 -> 58943.05 | L14: 0 | M14: =M13+K14-L14 -> 175278.26
A15: 12 | B15: 45700 | E15: 0 | F15: 0 | G15: =E15*F15 -> 0 | H15: 0 | I15: 0 | J15: =H15*I15 -> 0 | K15: =G15+J15 -> 0 | L15: 0 | M15: =M14+K15-L15 -> 175278.26
... A17: 14 | B17: 45702 | E17: 600 | F17: 92.17 | G17: =E17*F17 -> 55302 | H17: 0 | I17: 0 | J17: =H17*I17 -> 0 | K17: =G17+J17 -> 55302 | L17: 0 | M17: =M16+K17-L17 -> 230580.26
A18: 15 | B18: 45703 | E18: 0 | F18: 0 | G18: =E18*F18 -> 0 | H18: 0 | I18: 0 | J18: =H18*I18 -> 0 | K18: =G18+J18 -> 0 | L18: 0 | M18: =M17+K18-L18 -> 230580.26 | Q18: 2767.8 | S18: =Q18-M19 -> -227812.46
A19: 16 | B19: 45704 | E19: 0 | F19: 0 | G19: =E19*F19 -> 0 | H19: 0 | I19: 0 | J19: =H19*I19 -> 0 | K19: =G19+J19 -> 0 | L19: 0 | M19: =M18+K19-L19 -> 230580.26
A20: 17 | B20: 45705 | E20: 400 | F20: 92.17 | G20: =E20*F20 -> 36868 | H20: 35 | I20: 104.03 | J20: =H20*I20 -> 3641.05 | K20: =G20+J20 -> 40509.05 | L20: 175000 | M20: =M19+K20-L20 -> 96089.31
A21: 18 | B21: 45706 | E21: 0 | F21: 0 | G21: =E21*F21 -> 0 | H21: 0 | I21: 0 | J21: =H21*I21 -> 0 | K21: =G21+J21 -> 0 | L21: 0 | M21: =M20+K21-L21 -> 96089.31 | V21: =400*90.23 -> 36092
A22: 19 | B22: 45707 | E22: 400 | F22: 92.17 | G22: =E22*F22 -> 36868 | H22: 0 | I22: 0 | J22: =H22*I22 -> 0 | K22: =G22+J22 -> 36868 | L22: 0 | M22: =M21+K22-L22 -> 132957.31 | V22: =35*104.14 -> 3644.9
A23: 20 | B23: 45708 | E23: 0 | F23: 0 | G23: =E23*F23 -> 0 | H23: 0 | I23: 0 | J23: =H23*I23 -> 0 | K23: =G23+J23 -> 0 | L23: 0 | M23: =M22+K23-L23 -> 132957.31
A24: 21 | B24: 45709 | E24: 0 | F24: 0 | G24: =E24*F24 -> 0 | H24: 0 | I24: 0 | J24: =H24*I24 -> 0 | K24: =G24+J24 -> 0 | L24: 0 | M24: =M23+K24-L24 -> 132957.31
A25: 22 | B25: 45710 | E25: 400 | F25: 92.17 | G25: =E25*F25 -> 36868 | H25: 20 | I25: 104.03 | J25: =H25*I25 -> 2080.6 | K25: =G25+J25 -> 38948.6 | L25: 0 | M25: =M24+K25-L25 -> 171905.91
A26: 23 | B26: 45711 | E26: 0 | F26: 0 | G26: =E26*F26 -> 0 | H26: 0 | I26: 0 | J26: =H26*I26 -> 0 | K26: =G26+J26 -> 0 | L26: 0 | M26: =M25+K26-L26 -> 171905.91
A27: 24 | B27: 45712 | E27: 0 | F27: 0 | G27: =E27*F27 -> 0 | H27: 0 | I27: 0 | J27: =H27*I27 -> 0 | K27: =G27+J27 -> 0 | L27: 0 | M27: =M26+K27-L27 -> 171905.91
A28: 25 | B28: 45713 | E28: 0 | F28: 0 | G28: =E28*F28 -> 0 | H28: 0 | I28: 0 | J28: =H28*I28 -> 0 | K28: =G28+J28 -> 0 | L28: 0 | M28: =M27+K28-L28 -> 171905.91
A29: 26 | B29: 45714 | E29: 600 | F29: 92.17 | G29: =E29*F29 -> 55302 | H29: 35 | I29: 104.03 | J29: =H29*I29 -> 3641.05 | K29: =G29+J29 -> 58943.05 | L29: 171896 | M29: =M28+K29-L29 -> 58952.96
A30: 27 | B30: 45715 | E30: 0 | F30: 0 | G30: =E30*F30 -> 0 | H30: 0 | I30: 0 | J30: =H30*I30 -> 0 | K30: =G30+J30 -> 0 | L30: 0 | M30: =M29+K30-L30 -> 58952.96
A31: 28 | B31: 45716 | E31: 0 | F31: 0 | G31: =E31*F31 -> 0 | H31: 0 | I31: 0 | J31: =H31*I31 -> 0 | K31: =G31+J31 -> 0 | L31: 0 | M31: =M30+K31-L31 -> 58952.96 | P31: 29774.14
A32: 29 | E32: 0 | F32: 0 | G32: =E32*F32 -> 0 | H32: 0 | I32: 0 | J32: =H32*I32 -> 0 | K32: =G32+J32 -> 0 | L32: 0 | M32: =M31+K32-L32 -> 58952.96 | P32: 50000
A33: 30 | E33: 0 | F33: 0 | G33: =E33*F33 -> 0 | H33: 0 | I33: 0 | J33: =H33*I33 -> 0 | K33: =G33+J33 -> 0 | L33: 0 | M33: =M32+K33-L33 -> 58952.96 | P33: =SUM(P31:P32) -> 79774.14
A34: 31 | E34: 0 | F34: 0 | G34: =E34*F34 -> 0 | H34: 0 | I34: 0 | J34: =H34*I34 -> 0 | K34: =G34+J34 -> 0 | L34: 0 | M34: =M33+K34-L34 -> 58952.96
E35: 0 | F35: 0 | G35: =E35*F35 -> 0 | H35: 0 | I35: 0 | J35: =H35*I35 -> 0 | K35: =G35+J35 -> 0 | L35: 0 | M35: =M34+K35-L35 -> 58952.96
E36: 0 | F36: 0 | G36: =E36*F36 -> 0 | H36: 0 | J36: =H36*I36 -> 0 | K36: =G36+J36 -> 0 | L36: 0 | M36: =M35+K36-L36 -> 58952.96
E37: =SUM(E4:E35) -> 4200 | G37: =SUM(G4:G35) -> 387114 | H37: =SUM(H4:H35) -> 180 | J37: =SUM(J4:J35) -> 18725.4 | K37: =SUM(K4:K35) -> 405839.4 | L37: =SUM(L4:L35) -> 560585
E38: 0 | G38: 0 | H38: 0 | J38: 0 | K38: =G38+J38 -> 0 | L38: 0
S43: 9052944708

Sheet Molakamuru
A1: Priyanka Petroleum
A2: S.No | B2: Date | C2: GRN No | D2: Ind No/Bill No | E2: Diesel (Lts) | F2: Price | G2: Amount | H2: Petrol (Lts) | I2: Price | J2: Amount | K2: Total amount | L2: Amount paid | M2: As on Date | N2: Remarks
A3: Opening Balance | K3: 27990.595 | L3: 27990.595 | M3: 27990.595
A4: 1 | B4: 46054 | G4: =E4*F4 -> 0 | J4: =H4*I4 -> 0 | K4: =G4+J4 -> 0 | L4: =K4 -> 0 | M4: =M3+K4-L4 -> 27990.595
A5: 2 | B5: 46055 | E5: 200 | F5: 92.22 | G5: =E5*F5 -> 18444 | H5: 20 | I5: 104.08 | J5: =H5*I5 -> 2081.6 | K5: =G5+J5 -> 20525.6 | L5: 27990.58 | M5: =M4+K5-L5 -> 20525.615
A6: 3 | B6: 46056 | G6: =E6*F6 -> 0 | J6: =H6*I6 -> 0 | K6: =G6+J6 -> 0 | L6: =K6 -> 0 | M6: =M5+K6-L6 -> 20525.615
A7: 4 | B7: 46057 | G7: =E7*F7 -> 0 | J7: =H7*I7 -> 0 | K7: =G7+J7 -> 0 | L7: =K7 -> 0 | M7: =M6+K7-L7 -> 20525.615
A8: 5 | B8: 46058 | G8: =E8*F8 -> 0 | J8: =H8*I8 -> 0 | K8: =G8+J8 -> 0 | L8: =K8 -> 0 | M8: =M7+K8-L8 -> 20525.615
A9: 6 | B9: 46059 | G9: =E9*F9 -> 0 | J9: =H9*I9 -> 0 | K9: =G9+J9 -> 0 | L9: =K9 -> 0 | M9: =M8+K9-L9 -> 20525.615
A10: 7 | B10: 46060 | G10: =E10*F10 -> 0 | J10: =H10*I10 -> 0 | K10: =G10+J10 -> 0 | L10: =K10 -> 0 | M10: =M9+K10-L10 -> 20525.615
A11: 8 | B11: 46061 | G11: =E11*F11 -> 0 | H11: 20 | I11: 104.08 | J11: =H11*I11 -> 2081.6 | K11: =G11+J11 -> 2081.6 | L11: 0 | M11: =M10+K11-L11 -> 22607.215
A12: 9 | B12: 46062 | G12: =E12*F12 -> 0 | J12: =H12*I12 -> 0 | K12: =G12+J12 -> 0 | L12: =K12 -> 0 | M12: =M11+K12-L12 -> 22607.215
A13: 10 | B13: 46063 | G13: =E13*F13 -> 0 | J13: =H13*I13 -> 0 | K13: =G13+J13 -> 0 | L13: =K13 -> 0 | M13: =M12+K13-L13 -> 22607.215
A14: 11 | B14: 46064 | G14: =E14*F14 -> 0 | J14: =H14*I14 -> 0 | K14: =G14+J14 -> 0 | L14: =K14 -> 0 | M14: =M13+K14-L14 -> 22607.215
A15: 12 | B15: 46065 | G15: =E15*F15 -> 0 | J15: =H15*I15 -> 0 | K15: =G15+J15 -> 0 | L15: =K15 -> 0 | M15: =M14+K15-L15 -> 22607.215
A16: 13 | B16: 46066 | G16: =E16*F16 -> 0 | J16: =H16*I16 -> 0 | K16: =G16+J16 -> 0 | L16: =K16 -> 0 | M16: =M15+K16-L16 -> 22607.215
A17: 14 | B17: 46067 | E17: 200 | F17: 92.22 | G17: =E17*F17 -> 18444 | H17: 20 | I17: 104.08 | J17: =H17*I17 -> 2081.6 | K17: =G17+J17 -> 20525.6 | L17: 0 | M17: =M16+K17-L17 -> 43132.815
A18: 15 | B18: 46068 | G18: =E18*F18 -> 0 | J18: =H18*I18 -> 0 | K18: =G18+J18 -> 0 | L18: =K18 -> 0 | M18: =M17+K18-L18 -> 43132.815
A19: 16 | B19: 46069 | G19: =E19*F19 -> 0 | J19: =H19*I19 -> 0 | K19: =G19+J19 -> 0 | L19: =K19 -> 0 | M19: =M18+K19-L19 -> 43132.815
A20: 17 | B20: 46070 | G20: =E20*F20 -> 0 | J20: =H20*I20 -> 0 | K20: =G20+J20 -> 0 | L20: =K20 -> 0 | M20: =M19+K20-L20 -> 43132.815
A21: 18 | B21: 46071 | G21: =E21*F21 -> 0 | J21: =H21*I21 -> 0 | K21: =G21+J21 -> 0 | L21: =K21 -> 0 | M21: =M20+K21-L21 -> 43132.815
A22: 19 | B22: 46072 | G22: =E22*F22 -> 0 | J22: =H22*I22 -> 0 | K22: =G22+J22 -> 0 | L22: =K22 -> 0 | M22: =M21+K22-L22 -> 43132.815
A23: 20 | B23: 46073 | G23: =E23*F23 -> 0 | H23: 20 | I23: 104.08 | J23: =H23*I23 -> 2081.6 | K23: =G23+J23 -> 2081.6 | L23: 43132.8 | M23: =M22+K23-L23 -> 2081.6152
A24: 21 | B24: 46074 | G24: =E24*F24 -> 0 | J24: =H24*I24 -> 0 | K24: =G24+J24 -> 0 | L24: =K24 -> 0 | M24: =M23+K24-L24 -> 2081.6152
A25: 22 | B25: 46075 | G25: =E25*F25 -> 0 | J25: =H25*I25 -> 0 | K25: =G25+J25 -> 0 | L25: =K25 -> 0 | M25: =M24+K25-L25 -> 2081.6152
A26: 23 | B26: 46076 | G26: =E26*F26 -> 0 | J26: =H26*I26 -> 0 | K26: =G26+J26 -> 0 | L26: =K26 -> 0 | M26: =M25+K26-L26 -> 2081.6152
A27: 24 | B27: 46077 | G27: =E27*F27 -> 0 | J27: =H27*I27 -> 0 | K27: =G27+J27 -> 0 | L27: =K27 -> 0 | M27: =M26+K27-L27 -> 2081.6152
A28: 25 | B28: 46078 | G28: =E28*F28 -> 0 | J28: =H28*I28 -> 0 | K28: =G28+J28 -> 0 | L28: =K28 -> 0 | M28: =M27+K28-L28 -> 2081.6152
A29: 26 | B29: 46079 | G29: =E29*F29 -> 0 | J29: =H29*I29 -> 0 | K29: =G29+J29 -> 0 | L29: =K29 -> 0 | M29: =M28+K29-L29 -> 2081.6152
A30: 27 | B30: 46080 | G30: =E30*F30 -> 0 | J30: =H30*I30 -> 0 | K30: =G30+J30 -> 0 | L30: =K30 -> 0 | M30: =M29+K30-L30 -> 2081.6152
A31: 28 | B31: 46081 | E31: 200 | F31: 92.22 | G31: =E31*F31 -> 18444 | H31: 20 | I31: 104.08 | J31: =H31*I31 -> 2081.6 | K31: =G31+J31 -> 20525.6 | L31: 0 | M31: =M30+K31-L31 -> 22607.215
A32: 29 | G32: =E32*F32 -> 0 | J32: =H32*I32 -> 0 | K32: =G32+J32 -> 0 | L32: =K32 -> 0 | M32: =M31+K32-L32 -> 22607.215
A33: 30 | G33: =E33*F33 -> 0 | J33: =H33*I33 -> 0 | K33: =G33+J33 -> 0 | L33: =K33 -> 0 | M33: =M32+K33-L33 -> 22607.215
A34: 31 | G34: =E34*F34 -> 0 | K34: =G34+J34 -> 0 | L34: 0 | M34: =M33+K34-L34 -> 22607.215
E35: =SUM(E4:E34) -> 600 | G35: =SUM(G4:G34) -> 55332 | H35: =SUM(H4:H34) -> 100 | J35: =SUM(J4:J34) -> 10408 | K35: =SUM(K4:K34) -> 65740 | L35: =SUM(L4:L34) -> 71123.38

Sheet Chellakere -1
A1: Shivaganga Service Station (BPCL)
A2: S.No | B2: Date | C2: GRN No | D2: Ind No/Bill No | E2: Diesel (Lts) | F2: Price | G2: Amount | H2: Petrol (Lts) | I2: Price | J2: Amount | K2: Total amount | L2: Amount paid | M2: As on Date | N2: Remarks
A3: Opening Balance | K3: 161104.96 | L3: 161104.96 | M3: 161104.96
A4: 1 | B4: 46054 | E4: 0 | F4: 0 | G4: 0 | H4: 0 | I4: 0 | J4: 0 | K4: =G4+J4 -> 0 | M4: =M3+K4-L4 -> 161104.96
A5: 2 | B5: 46055 | E5: 0 | F5: 0 | G5: 0 | H5: 0 | I5: 0 | J5: 0 | K5: =G5+J5 -> 0 | L5: 161105 | M5: =M4+K5-L5 -> -0.0364
A6: 3 | B6: 46056 | E6: 600 | F6: 92.23 | G6: =E6*F6 -> 55338 | H6: 35 | I6: 104.09 | J6: =H6*I6 -> 3643.15 | K6: =G6+J6 -> 58981.15 | M6: =M5+K6-L6 -> 58981.114
A7: 4 | B7: 46057 | E7: 0 | F7: 0 | G7: =E7*F7 -> 0 | H7: 0 | I7: 0 | J7: =H7*I7 -> 0 | K7: =G7+J7 -> 0 | M7: =M6+K7-L7 -> 58981.114
A8: 5 | B8: 46058 | E8: 400 | F8: 92.23 | G8: =E8*F8 -> 36892 | H8: 25 | I8: 104.09 | J8: =H8*I8 -> 2602.25 | K8: =G8+J8 -> 39494.25 | M8: =M7+K8-L8 -> 98475.364
A9: 6 | B9: 46059 | E9: 0 | F9: 0 | G9: =E9*F9 -> 0 | H9: 0 | I9: 0 | J9: =H9*I9 -> 0 | K9: =G9+J9 -> 0 | M9: =M8+K9-L9 -> 98475.364
A10: 7 | B10: 46060 | E10: 0 | F10: 0 | G10: =E10*F10 -> 0 | H10: 0 | I10: 0 | J10: =H10*I10 -> 0 | K10: =G10+J10 -> 0 | M10: =M9+K10-L10 -> 98475.364
A11: 8 | B11: 46061 | E11: 0 | F11: 0 | G11: =E11*F11 -> 0 | H11: 0 | I11: 0 | J11: =H11*I11 -> 0 | K11: =G11+J11 -> 0 | M11: =M10+K11-L11 -> 98475.364
A12: 9 | B12: 46062 | E12: 600 | F12: 92.23 | G12: =E12*F12 -> 55338 | H12: 0 | I12: 0 | J12: =H12*I12 -> 0 | K12: =G12+J12 -> 55338 | M12: =M11+K12-L12 -> 153813.36
A13: 10 | B13: 46063 | E13: 0 | F13: 0 | G13: =E13*F13 -> 0 | H13: 0 | I13: 0 | J13: =H13*I13 -> 0 | K13: =G13+J13 -> 0 | M13: =M12+K13-L13 -> 153813.36
A14: 11 | B14: 46064 | E14: 0 | F14: 0 | G14: =E14*F14 -> 0 | H14: 0 | I14: 0 | J14: =H14*I14 -> 0 | K14: =G14+J14 -> 0 | M14: =M13+K14-L14 -> 153813.36
A15: 12 | B15: 46065 | E15: 600 | F15: 92.23 | G15: =E15*F15 -> 55338 | H15: 35 | I15: 104.09 | J15: =H15*I15 -> 3643.15 | K15: =G15+J15 -> 58981.15 | M15: =M14+K15-L15 -> 212794.51
A16: 13 | B16: 46066 | E16: 0 | F16: 0 | G16: =E16*F16 -> 0 | H16: 0 | I16: 0 | J16: =H16*I16 -> 0 | K16: =G16+J16 -> 0 | M16: =M15+K16-L16 -> 212794.51
A17: 14 | B17: 46067 | E17: 0 | F17: 0 | G17: =E17*F17 -> 0 | H17: 0 | I17: 0 | J17: =H17*I17 -> 0 | K17: =G17+J17 -> 0 | M17: =M16+K17-L17 -> 212794.51
... A22: 19 | B22: 46072 | E22: 0 | F22: 0 | G22: =E22*F22 -> 0 | H22: 0 | I22: 0 | J22: =H22*I22 -> 0 | K22: =G22+J22 -> 0 | M22: =M21+K22-L22 -> 327113.66
A23: 20 | B23: 46073 | E23: 0 | F23: 0 | G23: =E23*F23 -> 0 | H23: 0 | I23: 0 | J23: =H23*I23 -> 0 | K23: =G23+J23 -> 0 | L23: 212795 | M23: =M22+K23-L23 -> 114318.66
A24: 21 | B24: 46074 | E24: 0 | F24: 0 | G24: =E24*F24 -> 0 | H24: 0 | I24: 0 | J24: =H24*I24 -> 0 | K24: =G24+J24 -> 0 | M24: =M23+K24-L24 -> 114318.66
A25: 22 | B25: 46075 | E25: 0 | F25: 0 | G25: =E25*F25 -> 0 | H25: 0 | I25: 0 | J25: =H25*I25 -> 0 | K25: =G25+J25 -> 0 | M25: =M24+K25-L25 -> 114318.66
A26: 23 | B26: 46076 | E26: 400 | F26: 92.23 | G26: =E26*F26 -> 36892 | H26: 35.04 | I26: 104.09 | J26: =H26*I26 -> 3647.3136 | K26: =G26+J26 -> 40539.314 | M26: =M25+K26-L26 -> 154857.98
A27: 24 | B27: 46077 | E27: 0 | F27: 0 | G27: =E27*F27 -> 0 | H27: 0 | I27: 0 | J27: =H27*I27 -> 0 | K27: =G27+J27 -> 0 | M27: =M26+K27-L27 -> 154857.98
A28: 25 | B28: 46078 | E28: 0 | F28: 0 | G28: =E28*F28 -> 0 | H28: 0 | I28: 0 | J28: =H28*I28 -> 0 | K28: =G28+J28 -> 0 | M28: =M27+K28-L28 -> 154857.98
A29: 26 | B29: 46079 | E29: 600 | F29: 92.23 | G29: =E29*F29 -> 55338 | H29: 0 | I29: 0 | J29: =H29*I29 -> 0 | K29: =G29+J29 -> 55338 | M29: =M28+K29-L29 -> 210195.98
A30: 27 | B30: 46080 | E30: 0 | F30: 0 | G30: =E30*F30 -> 0 | H30: 0 | I30: 0 | J30: =H30*I30 -> 0 | K30: =G30+J30 -> 0 | M30: =M29+K30-L30 -> 210195.98
A31: 28 | B31: 46081 | E31: 600 | F31: 92.23 | G31: =E31*F31 -> 55338 | H31: 30 | I31: 104.09 | J31: =H31*I31 -> 3122.7 | K31: =G31+J31 -> 58460.7 | M31: =M30+K31-L31 -> 268656.68
A32: 29 | E32: 0 | F32: 0 | G32: 0 | H32: 0 | I32: 0 | J32: 0 | K32: =G32+J32 -> 0 | M32: =M31+K32-L32 -> 268656.68
A33: 30 | E33: 0 | F33: 0 | G33: 0 | H33: 0 | I33: 0 | J33: 0 | K33: =G33+J33 -> 0 | M33: =M32+K33-L33 -> 268656.68
A34: 31
E35: =SUM(E4:E34) -> 5000 | G35: =SUM(G4:G34) -> 461150 | H35: =SUM(H4:H34) -> 195.04 | J35: =SUM(J4:J34) -> 20301.714 | K35: =SUM(K4:K34) -> 481451.71 | L35: =SUM(L4:L34) -> 373900

Sheet  Chellakere-PKG-9
A1: Chellakere-PKG-09
A2: S.No | B2: Date | C2: GRN No | D2: Ind No/Bill No | E2: Diesel (Lts) | F2: Price | G2: Amount | H2: Petrol (Lts) | I2: Price | J2: Amount | K2: Total amount | L2: Amount paid | M2: As on Date | N2: Remarks
A3: Opening Balance | K3: 0 | L3: 0 | M3: 0
A4: 1 | B4: 46054 | G4: =E4*F4 -> 0 | J4: =H4*I4 -> 0 | K4: =G4+J4 -> 0 | L4: =K4 -> 0 | M4: =M3+K4-L4 -> 0
A5: 2 | B5: 46055 | E5: 65 | F5: 92.23 | G5: =E5*F5 -> 5994.95 | J5: =H5*I5 -> 0 | K5: =G5+J5 -> 5994.95 | L5: =K5 -> 5994.95 | M5: =M4+K5-L5 -> 0
A6: 3 | B6: 46056 | G6: =E6*F6 -> 0 | J6: =H6*I6 -> 0 | K6: =G6+J6 -> 0 | L6: =K6 -> 0 | M6: =M5+K6-L6 -> 0
A7: 4 | B7: 46057 | G7: =E7*F7 -> 0 | J7: =H7*I7 -> 0 | K7: =G7+J7 -> 0 | L7: =K7 -> 0 | M7: =M6+K7-L7 -> 0
A8: 5 | B8: 46058 | E8: 55 | F8: 92.23 | G8: =E8*F8 -> 5072.65 | J8: =H8*I8 -> 0 | K8: =G8+J8 -> 5072.65 | L8: =K8 -> 5072.65 | M8: =M7+K8-L8 -> 0
A9: 6 | B9: 46059 | G9: =E9*F9 -> 0 | J9: =H9*I9 -> 0 | K9: =G9+J9 -> 0 | L9: =K9 -> 0 | M9: =M8+K9-L9 -> 0
A10: 7 | B10: 46060 | G10: =E10*F10 -> 0 | J10: =H10*I10 -> 0 | K10: =G10+J10 -> 0 | L10: =K10 -> 0 | M10: =M9+K10-L10 -> 0
A11: 8 | B11: 46061 | G11: =E11*F11 -> 0 | J11: =H11*I11 -> 0 | K11: =G11+J11 -> 0 | L11: =K11 -> 0 | M11: =M10+K11-L11 -> 0
A12: 9 | B12: 46062 | G12: =E12*F12 -> 0 | J12: =H12*I12 -> 0 | K12: =G12+J12 -> 0 | L12: =K12 -> 0 | M12: =M11+K12-L12 -> 0
A13: 10 | B13: 46063 | G13: =E13*F13 -> 0 | J13: =H13*I13 -> 0 | K13: =G13+J13 -> 0 | L13: =K13 -> 0 | M13: =M12+K13-L13 -> 0
A14: 11 | B14: 46064 | G14: =E14*F14 -> 0 | J14: =H14*I14 -> 0 | K14: =G14+J14 -> 0 | L14: =K14 -> 0 | M14: =M13+K14-L14 -> 0
A15: 12 | B15: 46065 | G15: =E15*F15 -> 0 | H15: 5 | I15: 104.09 | J15: =H15*I15 -> 520.45 | K15: =G15+J15 -> 520.45 | L15: =K15 -> 520.45 | M15: =M14+K15-L15 -> 0
A16: 13 | B16: 46066 | E16: 40 | F16: 92.23 | G16: =E16*F16 -> 3689.2 | H16: 5.04 | I16: 104.09 | J16: =H16*I16 -> 524.6136 | K16: =G16+J16 -> 4213.8136 | L16: =K16 -> 4213.8136 | M16: =M15+K16-L16 -> 0
A17: 14 | B17: 46067 | G17: =E17*F17 -> 0 | J17: =H17*I17 -> 0 | K17: =G17+J17 -> 0 | L17: =K17 -> 0 | M17: =M16+K17-L17 -> 0
A18: 15 | B18: 46068 | G18: =E18*F18 -> 0 | J18: =H18*I18 -> 0 | K18: =G18+J18 -> 0 | L18: =K18 -> 0 | M18: =M17+K18-L18 -> 0
A19: 16 | B19: 46069 | G19: =E19*F19 -> 0 | J19: =H19*I19 -> 0 | K19: =G19+J19 -> 0 | L19: =K19 -> 0 | M19: =M18+K19-L19 -> 0
A20: 17 | B20: 46070 | G20: =E20*F20 -> 0 | J20: =H20*I20 -> 0 | K20: =G20+J20 -> 0 | L20: =K20 -> 0 | M20: =M19+K20-L20 -> 0
A21: 18 | B21: 46071 | G21: =E21*F21 -> 0 | J21: =H21*I21 -> 0 | K21: =G21+J21 -> 0 | L21: =K21 -> 0 | M21: =M20+K21-L21 -> 0
A22: 19 | B22: 46072 | G22: =E22*F22 -> 0 | J22: =H22*I22 -> 0 | K22: =G22+J22 -> 0 | L22: =K22 -> 0 | M22: =M21+K22-L22 -> 0
A23: 20 | B23: 46073 | G23: =E23*F23 -> 0 | J23: =H23*I23 -> 0 | K23: =G23+J23 -> 0 | L23: =K23 -> 0 | M23: =M22+K23-L23 -> 0
A24: 21 | B24: 46074 | G24: =E24*F24 -> 0 | J24: =H24*I24 -> 0 | K24: =G24+J24 -> 0 | L24: =K24 -> 0 | M24: =M23+K24-L24 -> 0
A25: 22 | B25: 46075 | G25: =E25*F25 -> 0 | J25: =H25*I25 -> 0 | K25: =G25+J25 -> 0 | L25: =K25 -> 0 | M25: =M24+K25-L25 -> 0
A26: 23 | B26: 46076 | E26: 40.01 | F26: 92.23 | G26: =E26*F26 -> 3690.1223 | H26: 8 | I26: 104.09 | J26: =H26*I26 -> 832.72 | K26: =G26+J26 -> 4522.8423 | L26: =K26 -> 4522.8423 | M26: =M25+K26-L26 -> 0
A27: 24 | B27: 46077 | G27: =E27*F27 -> 0 | J27: =H27*I27 -> 0 | K27: =G27+J27 -> 0 | L27: =K27 -> 0 | M27: =M26+K27-L27 -> 0
A28: 25 | B28: 46078 | G28: =E28*F28 -> 0 | J28: =H28*I28 -> 0 | K28: =G28+J28 -> 0 | L28: =K28 -> 0 | M28: 0
A29: 26 | B29: 46079 | E29: 210 | F29: 92.05 | G29: =E29*F29 -> 19330.5 | J29: =H29*I29 -> 0 | K29: =G29+J29 -> 19330.5 | L29: =K29 -> 19330.5 | M29: 0
A30: 27 | B30: 46080 | G30: =E30*F30 -> 0 | J30: =H30*I30 -> 0 | K30: =G30+J30 -> 0 | L30: =K30 -> 0 | M30: 0
A31: 28 | B31: 46081 | G31: =E31*F31 -> 0 | J31: =H31*I31 -> 0 | K31: =G31+J31 -> 0 | L31: =K31 -> 0 | M31: 0
A32: 29 | B32: 46082 | G32: =E32*F32 -> 0 | J32: =H32*I32 -> 0 | K32: =G32+J32 -> 0 | L32: =K32 -> 0
A33: 30 | B33: 46083 | G33: =E33*F33 -> 0 | J33: =H33*I33 -> 0 | K33: =G33+J33 -> 0 | L33: =K33 -> 0
A34: 31 | B34: 46084 | G34: =E34*F34 -> 0 | J34: =H34*I34 -> 0 | K34: =G34+J34 -> 0 | L34: =K34 -> 0
E35: =SUM(E4:E34) -> 410.01 | G35: =SUM(G4:G34) -> 37777.422 | H35: =SUM(H4:H34) -> 18.04 | J35: =SUM(J4:J34) -> 1877.7836 | K35: =SUM(K4:K34) -> 39655.206 | L35: =SUM(L4:L34) -> 39655.206

Sheet  Chennagiri
A1: Tumcos Fuel Station
A2: S.No | B2: Date | C2: GRN No | D2: Ind No/Bill No | E2: Diesel (Lts) | F2: Price | G2: Amount | H2: Petrol (Lts) | I2: Price | J2: Amount | K2: Total amount | L2: Amount paid | M2: As on Date | N2: Remarks
A3: Opening Balance | K3: 0 | L3: 0 | M3: =+K3 -> 0
A4: 1 | B4: 46054 | G4: =E4*F4 -> 0 | J4: =H4*I4 -> 0 | K4: =G4+J4 -> 0 | L4: =K4 -> 0 | M4: =M3+K4-L4 -> 0
A5: 2 | B5: 46055 | G5: =E5*F5 -> 0 | J5: =H5*I5 -> 0 | K5: =G5+J5 -> 0 | L5: =K5 -> 0 | M5: =M4+K5-L5 -> 0 | N5: HPCL
A6: 3 | B6: 46056 | E6: 0 | F6: 0 | G6: =E6*F6 -> 0 | H6: 24 | I6: 104.08 | J6: =H6*I6 -> 2497.92 | K6: =G6+J6 -> 2497.92 | L6: =K6 -> 2497.92 | M6: =M5+K6-L6 -> 0
A7: 4 | B7: 46057 | G7: =E7*F7 -> 0 | J7: =H7*I7 -> 0 | K7: =G7+J7 -> 0 | L7: =K7 -> 0 | M7: =M6+K7-L7 -> 0
A8: 5 | B8: 46058 | G8: =E8*F8 -> 0 | J8: =H8*I8 -> 0 | K8: =G8+J8 -> 0 | L8: =K8 -> 0 | M8: =M7+K8-L8 -> 0 | N8: HPCL
A9: 6 | B9: 46059 | G9: =E9*F9 -> 0 | J9: =H9*I9 -> 0 | K9: =G9+J9 -> 0 | L9: =K9 -> 0 | M9: =M8+K9-L9 -> 0
A10: 7 | B10: 46060 | E10: 217.27 | F10: 92.05 | G10: =E10*F10 -> 19999.703 | J10: =H10*I10 -> 0 | K10: =G10+J10 -> 19999.703 | L10: =K10 -> 19999.703 | M10: =M9+K10-L10 -> 0
A11: 8 | B11: 46061 | G11: =E11*F11 -> 0 | J11: =H11*I11 -> 0 | K11: =G11+J11 -> 0 | L11: =K11 -> 0 | M11: =M10+K11-L11 -> 0
A12: 9 | B12: 46062 | G12: =E12*F12 -> 0 | J12: =H12*I12 -> 0 | K12: =G12+J12 -> 0 | L12: =K12 -> 0 | M12: =M11+K12-L12 -> 0
A13: 10 | B13: 46063 | G13: =E13*F13 -> 0 | J13: =H13*I13 -> 0 | K13: =G13+J13 -> 0 | L13: =K13 -> 0 | M13: =M12+K13-L13 -> 0
A14: 11 | B14: 46064 | G14: =E14*F14 -> 0 | J14: =H14*I14 -> 0 | K14: =G14+J14 -> 0 | L14: =K14 -> 0 | M14: =M13+K14-L14 -> 0
A15: 12 | B15: 46065 | G15: =E15*F15 -> 0 | J15: =H15*I15 -> 0 | K15: =G15+J15 -> 0 | L15: =K15 -> 0 | M15: =M14+K15-L15 -> 0
A16: 13 | B16: 46066 | G16: =E16*F16 -> 0 | H16: 24 | I16: 104.14 | J16: =H16*I16 -> 2499.36 | K16: =G16+J16 -> 2499.36 | L16: =K16 -> 2499.36 | M16: =M15+K16-L16 -> 0
A17: 14 | B17: 46067 | G17: =E17*F17 -> 0 | J17: =H17*I17 -> 0 | K17: =G17+J17 -> 0 | L17: =K17 -> 0 | M17: =M16+K17-L17 -> 0
A18: 15 | B18: 46068 | G18: =E18*F18 -> 0 | J18: =H18*I18 -> 0 | K18: =G18+J18 -> 0 | L18: =K18 -> 0 | M18: =M17+K18-L18 -> 0
A19: 16 | B19: 46069 | E19: 210 | F19: 92.05 | G19: =E19*F19 -> 19330.5 | J19: =H19*I19 -> 0 | K19: =G19+J19 -> 19330.5 | L19: =K19 -> 19330.5 | M19: =M18+K19-L19 -> 0
A20: 17 | B20: 46070 | G20: =E20*F20 -> 0 | J20: =H20*I20 -> 0 | K20: =G20+J20 -> 0 | L20: =K20 -> 0 | M20: =M19+K20-L20 -> 0
A21: 18 | B21: 46071 | G21: =E21*F21 -> 0 | J21: =H21*I21 -> 0 | K21: =G21+J21 -> 0 | L21: =K21 -> 0 | M21: =M20+K21-L21 -> 0
A22: 19 | B22: 46072 | G22: =E22*F22 -> 0 | J22: =H22*I22 -> 0 | K22: =G22+J22 -> 0 | L22: =K22 -> 0 | M22: =M21+K22-L22 -> 0
A23: 20 | B23: 46073 | G23: =E23*F23 -> 0 | J23: =H23*I23 -> 0 | K23: =G23+J23 -> 0 | L23: =K23 -> 0 | M23: =M22+K23-L23 -> 0
A24: 21 | B24: 46074 | G24: =E24*F24 -> 0 | J24: =H24*I24 -> 0 | K24: =G24+J24 -> 0 | L24: =K24 -> 0 | M24: =M23+K24-L24 -> 0
A25: 22 | B25: 46075 | G25: =E25*F25 -> 0 | J25: =H25*I25 -> 0 | K25: =G25+J25 -> 0 | L25: =K25 -> 0 | M25: =M24+K25-L25 -> 0
A26: 23 | B26: 46076 | G26: =E26*F26 -> 0 | J26: =H26*I26 -> 0 | K26: =G26+J26 -> 0 | L26: =K26 -> 0 | M26: =M25+K26-L26 -> 0
A27: 24 | B27: 46077 | G27: =E27*F27 -> 0 | H27: 20 | I27: 104.08 | J27: =H27*I27 -> 2081.6 | K27: =G27+J27 -> 2081.6 | L27: =K27 -> 2081.6 | M27: =M26+K27-L27 -> 0
A28: 25 | B28: 46078 | G28: =E28*F28 -> 0 | J28: =H28*I28 -> 0 | K28: =G28+J28 -> 0 | L28: =K28 -> 0 | M28: 0
A29: 26 | B29: 46079 | G29: =E29*F29 -> 0 | J29: =H29*I29 -> 0 | K29: =G29+J29 -> 0 | L29: =K29 -> 0 | M29: 0
A30: 27 | B30: 46080 | G30: =E30*F30 -> 0 | J30: =H30*I30 -> 0 | K30: =G30+J30 -> 0 | L30: =K30 -> 0 | M30: 0
A31: 28 | B31: 46081 | G31: =E31*F31 -> 0 | J31: =H31*I31 -> 0 | K31: =G31+J31 -> 0 | L31: =K31 -> 0 | M31: 0
A32: 29 | B32: 46082 | G32: =E32*F32 -> 0 | J32: =H32*I32 -> 0 | K32: =G32+J32 -> 0 | L32: =K32 -> 0
A33: 30 | B33: 46083 | G33: =E33*F33 -> 0 | J33: =H33*I33 -> 0 | K33: =G33+J33 -> 0 | L33: =K33 -> 0
A34: 31 | B34: 46084 | G34: =E34*F34 -> 0 | K34: =G34+J34 -> 0 | L34: =K34 -> 0
E35: =SUM(E4:E34) -> 427.27 | G35: =SUM(G4:G34) -> 39330.204 | H35: =SUM(H4:H34) -> 68 | J35: =SUM(J4:J34) -> 7078.88 | K35: =SUM(K4:K34) -> 46409.084 | L35: =SUM(L4:L34) -> 46409.084

Sheet Khanapur
A1: V.V.Varde
A2: S.No | B2: Date | C2: GRN No | D2: Ind No/Bill No | E2: Diesel (Lts) | F2: Price | G2: Amount | H2: Petrol (Lts) | I2: Price | J2: Amount | K2: Total amount | L2: Date of payment | M2: Amount paid | N2: Remarks
D3: Opening Balance | K3: 103942.75 | M3: 103942.75
A4: 1 | B4: 46054 | G4: =F4*E4 -> 0 | J4: =H4*I4 -> 0 | K4: =G4+J4 -> 0 | M4: =M3+K4-L4 -> 103942.75
A5: 2 | B5: 46055 | G5: =F5*E5 -> 0 | J5: =H5*I5 -> 0 | K5: =G5+J5 -> 0 | L5: 103905.34 | M5: =M4+K5-L5 -> 37.4052 | S5: 90.88 | T5: 102.77
A6: 3 | B6: 46056 | E6: 50 | F6: 90.88 | G6: =F6*E6 -> 4544 | H6: 5 | I6: 102.77 | J6: =H6*I6 -> 513.85 | K6: =G6+J6 -> 5057.85 | M6: =M5+K6-L6 -> 5095.2552
A7: 4 | B7: 46057 | E7: 30 | F7: 90.88 | G7: =F7*E7 -> 2726.4 | J7: =H7*I7 -> 0 | K7: =G7+J7 -> 2726.4 | M7: =M6+K7-L7 -> 7821.6552
A8: 5 | B8: 46058 | E8: 90 | F8: 90.88 | G8: =F8*E8 -> 8179.2 | H8: 10 | I8: 102.77 | J8: =H8*I8 -> 1027.7 | K8: =G8+J8 -> 9206.9 | M8: =M7+K8-L8 -> 17028.555
A9: 6 | B9: 46059 | E9: 160 | F9: 90.88 | G9: =F9*E9 -> 14540.8 | J9: =H9*I9 -> 0 | K9: =G9+J9 -> 14540.8 | M9: =M8+K9-L9 -> 31569.355
A10: 7 | B10: 46060 | E10: 10 | F10: 90.88 | G10: =F10*E10 -> 908.8 | H10: 5 | I10: 102.77 | J10: =H10*I10 -> 513.85 | K10: =G10+J10 -> 1422.65 | M10: =M9+K10-L10 -> 32992.005
A11: 8 | B11: 46061 | E11: 135 | F11: 90.88 | G11: =F11*E11 -> 12268.8 | J11: =H11*I11 -> 0 | K11: =G11+J11 -> 12268.8 | M11: =M10+K11-L11 -> 45260.805
A12: 9 | B12: 46062 | E12: 220 | F12: 90.88 | G12: =F12*E12 -> 19993.6 | J12: =H12*I12 -> 0 | K12: =G12+J12 -> 19993.6 | M12: =M11+K12-L12 -> 65254.405
A13: 10 | B13: 46063 | E13: 110 | F13: 90.88 | G13: =F13*E13 -> 9996.8 | H13: 12.78 | I13: 102.77 | J13: =H13*I13 -> 1313.4006 | K13: =G13+J13 -> 11310.201 | M13: =M12+K13-L13 -> 76564.606
A14: 11 | B14: 46064 | G14: =F14*E14 -> 0 | H14: 5 | I14: 102.77 | J14: =H14*I14 -> 513.85 | K14: =G14+J14 -> 513.85 | M14: =M13+K14-L14 -> 77078.456
A15: 12 | B15: 46065 | G15: =F15*E15 -> 0 | H15: 5 | I15: 102.77 | J15: =H15*I15 -> 513.85 | K15: =G15+J15 -> 513.85 | M15: =M14+K15-L15 -> 77592.306
A16: 13 | B16: 46066 | G16: =F16*E16 -> 0 | H16: 5 | I16: 102.77 | J16: =H16*I16 -> 513.85 | K16: =G16+J16 -> 513.85 | M16: =M15+K16-L16 -> 78106.156
A17: 14 | B17: 46067 | E17: 70 | F17: 90.88 | G17: =F17*E17 -> 6361.6 | H17: 2 | I17: 102.77 | J17: =H17*I17 -> 205.54 | K17: =G17+J17 -> 6567.14 | M17: =M16+K17-L17 -> 84673.296
A18: 15 | B18: 46068 | G18: =F18*E18 -> 0 | J18: =H18*I18 -> 0 | K18: =G18+J18 -> 0 | M18: =M17+K18-L18 -> 84673.296
A19: 16 | B19: 46069 | E19: 120 | F19: 90.88 | G19: =F19*E19 -> 10905.6 | H19: 5 | I19: 102.77 | J19: =H19*I19 -> 513.85 | K19: =G19+J19 -> 11419.45 | M19: =M18+K19-L19 -> 96092.746
A20: 17 | B20: 46070 | E20: 80 | F20: 90.88 | G20: =F20*E20 -> 7270.4 | J20: =H20*I20 -> 0 | K20: =G20+J20 -> 7270.4 | M20: =M19+K20-L20 -> 103363.15 | O20: 16.68
A21: 18 | B21: 46071 | G21: =F21*E21 -> 0 | J21: =H21*I21 -> 0 | K21: =G21+J21 -> 0 | M21: =M20+K21-L21 -> 103363.15
A22: 19 | B22: 46072 | G22: =F22*E22 -> 0 | J22: =H22*I22 -> 0 | K22: =G22+J22 -> 0 | M22: =M21+K22-L22 -> 103363.15
A23: 20 | B23: 46073 | G23: =F23*E23 -> 0 | J23: =H23*I23 -> 0 | K23: =G23+J23 -> 0 | L23: 100000 | M23: =M22+K23-L23 -> 3363.1458 | N23: 0
A24: 21 | B24: 46074 | E24: 30 | F24: 90.88 | G24: =F24*E24 -> 2726.4 | J24: =H24*I24 -> 0 | K24: =G24+J24 -> 2726.4 | M24: =M23+K24-L24 -> 6089.5458
A25: 22 | B25: 46075 | E25: 221.61 | F25: 90.88 | G25: =F25*E25 -> 20139.917 | H25: 5 | I25: 102.77 | J25: =H25*I25 -> 513.85 | K25: =G25+J25 -> 20653.767 | M25: =M24+K25-L25 -> 26743.313
A26: 23 | B26: 46076 | E26: 60 | F26: 90.88 | G26: =F26*E26 -> 5452.8 | H26: 5 | I26: 102.77 | J26: =H26*I26 -> 513.85 | K26: =G26+J26 -> 5966.65 | M26: =M25+K26-L26 -> 32709.963
A27: 24 | B27: 46077 | E27: 50 | F27: 90.88 | G27: =F27*E27 -> 4544 | H27: 10 | I27: 102.77 | J27: =H27*I27 -> 1027.7 | K27: =G27+J27 -> 5571.7 | M27: =M26+K27-L27 -> 38281.663
A28: 25 | B28: 46078 | E28: 20 | F28: 90.88 | G28: =F28*E28 -> 1817.6 | J28: =H28*I28 -> 0 | K28: =G28+J28 -> 1817.6 | M28: =M27+K28-L28 -> 40099.263
A29: 26 | B29: 46079 | E29: 40 | F29: 90.88 | G29: =F29*E29 -> 3635.2 | H29: 5 | I29: 102.77 | J29: =H29*I29 -> 513.85 | K29: =G29+J29 -> 4149.05 | M29: =M28+K29-L29 -> 44248.313
A30: 27 | B30: 46080 | E30: 120 | F30: 90.88 | G30: =F30*E30 -> 10905.6 | J30: =H30*I30 -> 0 | K30: =G30+J30 -> 10905.6 | M30: =M29+K30-L30 -> 55153.913
A31: 28 | B31: 46081 | E31: 150 | F31: 90.88 | G31: =F31*E31 -> 13632 | J31: =H31*I31 -> 0 | K31: =G31+J31 -> 13632 | M31: =M30+K31-L31 -> 68785.913
A32: 29 | G32: =F32*E32 -> 0 | J32: =H32*I32 -> 0 | K32: =G32+J32 -> 0 | M32: =M31+K32-L32 -> 68785.913
A33: 30 | G33: =F33*E33 -> 0 | J33: =H33*I33 -> 0 | K33: =G33+J33 -> 0 | M33: =M32+K33-L33 -> 68785.913
A34: 31 | B34: 46084 | G34: =F34*E34 -> 0 | J34: =H34*I34 -> 0 | K34: =G34+J34 -> 0 | M34: =M33+K34-L34 -> 68785.913
E35: =SUM(E4:E34) -> 1766.61 | G35: =SUM(G4:G34) -> 160549.52 | H35: =SUM(H4:H34) -> 79.78 | J35: =SUM(J4:J34) -> 8198.9906 | K35: =SUM(K4:K34) -> 168748.51 | L35: =SUM(L4:L34) -> 203905.34 | M35: =SUM(M4:M34) -> 1715705.3
E36: 1541.87
E37: 1661 | H37: 43.92
E38: =E37-E36 -> 119.13

Sheet Munavali
A1: Shri Daneshwari
A2: S.No | B2: Date | C2: GRN No | D2: Ind No/Bill No | E2: Diesel (Lts) | F2: Price | G2: Amount | H2: Petrol (Lts) | I2: Price | J2: Amount | K2: Total amount | L2: Amount paid | M2: As on date | N2: Remarks
D3: Opening Balance | K3: 0 | M3: 0 | O3: 26506.4
A4: 1 | B4: 46054 | E4: 0 | F4: 0 | G4: =E4*F4 -> 0 | J4: =H4*I4 -> 0 | K4: =G4+J4 -> 0 | M4: 0
A5: 2 | B5: 46055 | E5: 0 | F5: 0 | G5: =E5*F5 -> 0 | J5: =H5*I5 -> 0 | K5: =G5+J5 -> 0 | M5: =M4+K5-L5 -> 0
A6: 3 | B6: 46056 | E6: 0 | F6: 0 | G6: =E6*F6 -> 0 | J6: =H6*I6 -> 0 | K6: =G6+J6 -> 0 | M6: =M5+K6-L6 -> 0
A7: 4 | B7: 46057 | E7: 0 | F7: 0 | G7: =E7*F7 -> 0 | J7: =H7*I7 -> 0 | K7: =G7+J7 -> 0 | M7: =M6+K7-L7 -> 0
A8: 5 | B8: 46058 | E8: 0 | F8: 0 | G8: =E8*F8 -> 0 | J8: =H8*I8 -> 0 | K8: =G8+J8 -> 0 | M8: =M7+K8-L8 -> 0
A9: 6 | B9: 46059 | E9: 0 | F9: 0 | G9: =E9*F9 -> 0 | J9: =H9*I9 -> 0 | K9: =G9+J9 -> 0 | M9: =M8+K9-L9 -> 0
A10: 7 | B10: 46060 | E10: 0 | F10: 0 | G10: =E10*F10 -> 0 | J10: =H10*I10 -> 0 | K10: =G10+J10 -> 0 | M10: =M9+K10-L10 -> 0
A11: 8 | B11: 46061 | E11: 0 | F11: 0 | G11: =E11*F11 -> 0 | J11: =H11*I11 -> 0 | K11: =G11+J11 -> 0 | M11: =M10+K11-L11 -> 0
A12: 9 | B12: 46062 | E12: 0 | F12: 0 | G12: =E12*F12 -> 0 | J12: =H12*I12 -> 0 | K12: =G12+J12 -> 0 | M12: =M11+K12-L12 -> 0
A13: 10 | B13: 46063 | E13: 0 | F13: 0 | G13: =E13*F13 -> 0 | J13: =H13*I13 -> 0 | K13: =G13+J13 -> 0 | M13: =M12+K13-L13 -> 0
A14: 11 | B14: 46064 | E14: 0 | F14: 0 | G14: =E14*F14 -> 0 | J14: =H14*I14 -> 0 | K14: =G14+J14 -> 0 | M14: =M13+K14-L14 -> 0
A15: 12 | B15: 46065 | E15: 0 | F15: 0 | G15: =E15*F15 -> 0 | J15: =H15*I15 -> 0 | K15: =G15+J15 -> 0 | M15: =M14+K15-L15 -> 0
A16: 13 | B16: 46066 | D16: 0 | G16: =E16*F16 -> 0 | J16: =H16*I16 -> 0 | K16: =G16+J16 -> 0 | M16: =M15+K16-L16 -> 0
A17: 14 | B17: 46067 | G17: =E17*F17 -> 0 | J17: =H17*I17 -> 0 | K17: =G17+J17 -> 0 | M17: =M16+K17-L17 -> 0
A18: 15 | B18: 46068 | G18: =E18*F18 -> 0 | J18: =H18*I18 -> 0 | K18: =G18+J18 -> 0 | M18: =M17+K18-L18 -> 0
A19: 16 | B19: 46069 | G19: =E19*F19 -> 0 | J19: =H19*I19 -> 0 | K19: =G19+J19 -> 0 | M19: =M18+K19-L19 -> 0
A20: 17 | B20: 46070 | G20: =E20*F20 -> 0 | J20: =H20*I20 -> 0 | K20: =G20+J20 -> 0 | M20: =M19+K20-L20 -> 0
A21: 18 | B21: 46071 | G21: =E21*F21 -> 0 | J21: =H21*I21 -> 0 | K21: =G21+J21 -> 0 | M21: =M20+K21-L21 -> 0
A22: 19 | B22: 46072 | G22: =E22*F22 -> 0 | J22: =H22*I22 -> 0 | K22: =G22+J22 -> 0 | M22: =M21+K22-L22 -> 0
A23: 20 | B23: 46073 | G23: =E23*F23 -> 0 | J23: =H23*I23 -> 0 | K23: =G23+J23 -> 0 | M23: =M22+K23-L23 -> 0
A24: 21 | B24: 46074 | G24: =E24*F24 -> 0 | J24: =H24*I24 -> 0 | K24: =G24+J24 -> 0 | M24: =M23+K24-L24 -> 0
A25: 22 | B25: 46075 | G25: =E25*F25 -> 0 | J25: =H25*I25 -> 0 | K25: =G25+J25 -> 0 | M25: =M24+K25-L25 -> 0
A26: 23 | B26: 46076 | G26: =E26*F26 -> 0 | J26: =H26*I26 -> 0 | K26: =G26+J26 -> 0 | M26: =M25+K26-L26 -> 0
A27: 24 | B27: 46077 | G27: =E27*F27 -> 0 | J27: =H27*I27 -> 0 | K27: =G27+J27 -> 0 | M27: =M26+K27-L27 -> 0
A28: 25 | B28: 46078 | G28: =E28*F28 -> 0 | J28: =H28*I28 -> 0 | K28: =G28+J28 -> 0 | M28: =M27+K28-L28 -> 0
... A32: 29 | B32: 46082 | G32: =E32*F32 -> 0 | J32: =H32*I32 -> 0 | K32: =G32+J32 -> 0 | M32: =M31+K32-L32 -> 0
A33: 30 | B33: 46083 | G33: =E33*F33 -> 0 | J33: =H33*I33 -> 0 | K33: =G33+J33 -> 0 | L33: 0 | M33: =M32+K33-L33 -> 0
A34: 31 | G34: =E34*F34 -> 0 | J34: =H34*I34 -> 0 | K34: =G34+J34 -> 0 | L34: 0 | M34: =M33+K34-L34 -> 0
A35: 32 | G35: =E35*F35 -> 0 | J35: =H35*I35 -> 0 | K35: =G35+J35 -> 0 | L35: 0 | M35: =M34+K35-L35 -> 0
A36: 33 | G36: =E36*F36 -> 0 | J36: =H36*I36 -> 0 | K36: =G36+J36 -> 0 | L36: 0 | M36: =M35+K36-L36 -> 0
E37: =SUM(E4:E36) -> 0 | G37: =SUM(G4:G36) -> 0 | H37: =SUM(H4:H36) -> 0 | J37: =SUM(J4:J36) -> 0 | K37: =SUM(K4:K36) -> 0 | L37: =SUM(L4:L36) -> 0

Sheet Munavali-2
A1: Shiri Shva Petroluem
A2: S.No | B2: Date | C2: GRN No | D2: Ind No/Bill No | E2: Diesel (Lts) | F2: Price | G2: Amount | H2: Petrol (Lts) | I2: Price | J2: Amount | K2: Total amount | L2: Amount paid | M2: As on date | N2: Remarks
D3: Opening Balance | K3: 0 | M3: 343617.68 | O3: 26506.4
A4: 1 | B4: 46054 | J4: =H4*I4 -> 0 | K4: =G4+J4 -> 0 | M4: =M3+K4-L4 -> 343617.68
A5: 2 | B5: 46055 | C5: Start | E5: 327.833 | F5: 91.51 | G5: =E5*F5 -> 29999.998 | J5: =H5*I5 -> 0 | K5: =G5+J5 -> 29999.998 | L5: 30000 | M5: =M4+K5-L5 -> 343617.68
A6: 3 | B6: 46056 | E6: 327.833 | F6: 91.51 | G6: =E6*F6 -> 29999.998 | H6: 6 | I6: 103.48 | J6: =H6*I6 -> 620.88 | K6: =G6+J6 -> 30620.878 | L6: 30620.88 | M6: =M5+K6-L6 -> 343617.68
A7: 4 | B7: 46057 | E7: 400 | F7: 91.54 | G7: =E7*F7 -> 36616 | H7: 12 | I7: 103.48 | J7: =H7*I7 -> 1241.76 | K7: =G7+J7 -> 37857.76 | M7: =M6+K7-L7 -> 381475.44
A8: 5 | B8: 46058 | E8: 600 | F8: 91.54 | G8: =E8*F8 -> 54924 | H8: 20 | I8: 103.48 | J8: =H8*I8 -> 2069.6 | K8: =G8+J8 -> 56993.6 | L8: 343617.28 | M8: =M7+K8-L8 -> 94851.756
A9: 6 | B9: 46059 | E9: 950 | F9: 91.54 | G9: =E9*F9 -> 86963 | H9: 20 | I9: 103.48 | J9: =H9*I9 -> 2069.6 | K9: =G9+J9 -> 89032.6 | M9: =M8+K9-L9 -> 183884.36
A10: 7 | B10: 46060 | E10: 800 | F10: 91.54 | G10: =E10*F10 -> 73232 | H10: 5 | I10: 103.48 | J10: =H10*I10 -> 517.4 | K10: =G10+J10 -> 73749.4 | M10: =M9+K10-L10 -> 257633.76
A11: 8 | B11: 46061 | G11: =E11*F11 -> 0 | J11: =H11*I11 -> 0 | K11: =G11+J11 -> 0 | M11: =M10+K11-L11 -> 257633.76
A12: 9 | B12: 46062 | E12: 400 | F12: 91.54 | G12: =E12*F12 -> 36616 | H12: 20 | I12: 103.48 | J12: =H12*I12 -> 2069.6 | K12: =G12+J12 -> 38685.6 | M12: =M11+K12-L12 -> 296319.36
A13: 10 | B13: 46063 | E13: 800 | F13: 91.54 | G13: =E13*F13 -> 73232 | H13: 20 | I13: 103.48 | J13: =H13*I13 -> 2069.6 | K13: =G13+J13 -> 75301.6 | M13: =M12+K13-L13 -> 371620.96
A14: 11 | B14: 46064 | G14: =E14*F14 -> 0 | J14: =H14*I14 -> 0 | K14: =G14+J14 -> 0 | M14: =M13+K14-L14 -> 371620.96
A15: 12 | B15: 46065 | E15: 800 | F15: 91.54 | G15: =E15*F15 -> 73232 | H15: 20 | I15: 103.48 | J15: =H15*I15 -> 2069.6 | K15: =G15+J15 -> 75301.6 | M15: =M14+K15-L15 -> 446922.56
A16: 13 | B16: 46066 | D16: 0 | E16: 800 | F16: 91.54 | G16: =E16*F16 -> 73232 | J16: =H16*I16 -> 0 | K16: =G16+J16 -> 73232 | M16: =M15+K16-L16 -> 520154.56
A17: 14 | B17: 46067 | E17: 400 | F17: 91.54 | G17: =E17*F17 -> 36616 | J17: =H17*I17 -> 0 | K17: =G17+J17 -> 36616 | M17: =M16+K17-L17 -> 556770.56
A18: 15 | B18: 46068 | G18: =E18*F18 -> 0 | J18: =H18*I18 -> 0 | K18: =G18+J18 -> 0 | M18: =M17+K18-L18 -> 556770.56
A19: 16 | B19: 46069 | E19: 1330 | F19: 91.54 | G19: =E19*F19 -> 121748.2 | J19: =H19*I19 -> 0 | K19: =G19+J19 -> 121748.2 | M19: =M18+K19-L19 -> 678518.76
A20: 17 | B20: 46070 | E20: 837.01 | F20: 91.54 | G20: =E20*F20 -> 76619.895 | H20: 26 | I20: 103.48 | J20: =H20*I20 -> 2690.48 | K20: =G20+J20 -> 79310.375 | M20: =M19+K20-L20 -> 757829.13
A21: 18 | B21: 46071 | G21: =E21*F21 -> 0 | H21: 5 | I21: 103.48 | J21: =H21*I21 -> 517.4 | K21: =G21+J21 -> 517.4 | M21: =M20+K21-L21 -> 758346.53
A22: 19 | B22: 46072 | E22: 1700 | F22: 91.54 | G22: =E22*F22 -> 155618 | H22: 20 | I22: 103.48 | J22: =H22*I22 -> 2069.6 | K22: =G22+J22 -> 157687.6 | M22: =M21+K22-L22 -> 916034.13
A23: 20 | B23: 46073 | E23: 500 | F23: 91.54 | G23: =E23*F23 -> 45770 | J23: =H23*I23 -> 0 | K23: =G23+J23 -> 45770 | L23: 500000 | M23: =M22+K23-L23 -> 461804.13
A24: 21 | B24: 46074 | E24: 1600 | F24: 91.54 | G24: =E24*F24 -> 146464 | H24: 6 | I24: 103.48 | J24: =H24*I24 -> 620.88 | K24: =G24+J24 -> 147084.88 | M24: =M23+K24-L24 -> 608889.01
A25: 22 | B25: 46075 | E25: 700 | F25: 91.54 | G25: =E25*F25 -> 64078 | J25: =H25*I25 -> 0 | K25: =G25+J25 -> 64078 | M25: =M24+K25-L25 -> 672967.01
A26: 23 | B26: 46076 | E26: 800 | F26: 91.54 | G26: =E26*F26 -> 73232 | H26: 30 | I26: 103.48 | J26: =H26*I26 -> 3104.4 | K26: =G26+J26 -> 76336.4 | M26: =M25+K26-L26 -> 749303.41
A27: 24 | B27: 46077 | E27: 1100 | F27: 91.54 | G27: =E27*F27 -> 100694 | H27: 6 | I27: 103.48 | J27: =H27*I27 -> 620.88 | K27: =G27+J27 -> 101314.88 | M27: =M26+K27-L27 -> 850618.29
A28: 25 | B28: 46078 | E28: 500 | F28: 91.54 | G28: =E28*F28 -> 45770 | J28: =H28*I28 -> 0 | K28: =G28+J28 -> 45770 | M28: =M27+K28-L28 -> 896388.29
A29: 26 | B29: 46079 | E29: 800 | F29: 91.54 | G29: =E29*F29 -> 73232 | H29: 20 | I29: 111.24 | J29: =H29*I29 -> 2224.8 | K29: =G29+J29 -> 75456.8 | L29: 300000 | M29: =M28+K29-L29 -> 671845.09
B30: 46079 | G30: =E30*F30 -> 0 | H30: 5 | I30: 103.48 | J30: =H30*I30 -> 517.4 | K30: =G30+J30 -> 517.4 | M30: =M29+K30-L30 -> 672362.49
A31: 27 | B31: 46080 | E31: 100 | F31: 91.54 | G31: =E31*F31 -> 9154 | J31: =H31*I31 -> 0 | K31: =G31+J31 -> 9154 | M31: =M30+K31-L31 -> 681516.49
A32: 28 | B32: 46081 | E32: 600 | F32: 91.54 | G32: =E32*F32 -> 54924 | H32: 20 | I32: 103.48 | J32: =H32*I32 -> 2069.6 | K32: =G32+J32 -> 56993.6 | M32: =M31+K32-L32 -> 738510.09
A33: 29 | G33: =E33*F33 -> 0 | J33: =H33*I33 -> 0 | K33: =G33+J33 -> 0 | M33: =M32+K33-L33 -> 738510.09
A34: 30 | G34: =E34*F34 -> 0 | J34: =H34*I34 -> 0 | K34: =G34+J34 -> 0 | L34: 0 | M34: =M33+K34-L34 -> 738510.09
A35: 31 | G35: =E35*F35 -> 0 | J35: =H35*I35 -> 0 | K35: =G35+J35 -> 0 | L35: 0 | M35: =M34+K35-L35 -> 738510.09
A36: 32 | G36: =E36*F36 -> 0 | J36: =H36*I36 -> 0 | K36: =G36+J36 -> 0 | L36: 0 | M36: =M35+K36-L36 -> 738510.09
A37: 33 | G37: =E37*F37 -> 0 | J37: =H37*I37 -> 0 | K37: =G37+J37 -> 0 | L37: 0 | M37: =M36+K37-L37 -> 738510.09
E38: =SUM(E4:E37) -> 17172.676 | G38: =SUM(G4:G37) -> 1571967.1 | H38: =SUM(H4:H37) -> 261 | J38: =SUM(J4:J37) -> 27163.48 | K38: =SUM(K4:K37) -> 1599130.6 | L38: =SUM(L4:L37) -> 1204238.2

Sheet Borgaon
A1: Aadisagar Petrolium
A2: S.No | B2: Date | C2: GRN No | D2: Ind no/Bill No | E2: Diesel (Lts) | F2: Price | G2: Amount | H2: Petrol (Lts) | I2: Price | J2: Amount | K2: Total amount | L2: Amount paid | M2: As on Date | N2: Remarks
A3: Opening Balance | K3: 115310.98 | M3: 115310.98
A4: 1 | B4: 46054 | E4: 116.79 | F4: 91.77 | G4: =E4*F4 -> 10717.818 | H4: 6 | I4: 103.73 | J4: =H4*I4 -> 622.38 | K4: =G4+J4 -> 11340.198 | M4: =M3+K4-L4 -> 126651.18
A5: 2 | B5: 46055 | G5: =E5*F5 -> 0 | H5: 11 | I5: 103.73 | J5: =H5*I5 -> 1141.03 | K5: =G5+J5 -> 1141.03 | L5: 126000 | M5: =M4+K5-L5 -> 1792.2114
A6: 3 | B6: 46056 | G6: =E6*F6 -> 0 | J6: =H6*I6 -> 0 | K6: =G6+J6 -> 0 | M6: =M5+K6-L6 -> 1792.2114
A7: 4 | B7: 46057 | E7: 120 | F7: 91.77 | G7: =E7*F7 -> 11012.4 | H7: 10 | I7: 103.73 | J7: =H7*I7 -> 1037.3 | K7: =G7+J7 -> 12049.7 | M7: =M6+K7-L7 -> 13841.911
A8: 5 | B8: 46058 | E8: 284.2 | F8: 91.77 | G8: =E8*F8 -> 26081.034 | J8: =H8*I8 -> 0 | K8: =G8+J8 -> 26081.034 | M8: =M7+K8-L8 -> 39922.945
A9: 6 | B9: 46059 | E9: 600 | F9: 91.77 | G9: =E9*F9 -> 55062 | H9: 5 | I9: 103.73 | J9: =H9*I9 -> 518.65 | K9: =G9+J9 -> 55580.65 | M9: =M8+K9-L9 -> 95503.595
A10: 7 | B10: 46060 | G10: =E10*F10 -> 0 | H10: 6 | I10: 103.73 | J10: =H10*I10 -> 622.38 | K10: =G10+J10 -> 622.38 | M10: =M9+K10-L10 -> 96125.975
A11: 8 | B11: 46061 | G11: =E11*F11 -> 0 | H11: 6 | I11: 103.73 | J11: =H11*I11 -> 622.38 | K11: =G11+J11 -> 622.38 | M11: =M10+K11-L11 -> 96748.355
A12: 9 | B12: 46062 | G12: =E12*F12 -> 0 | H12: 4.93 | I12: 103.73 | J12: =H12*I12 -> 511.3889 | K12: =G12+J12 -> 511.3889 | M12: =M11+K12-L12 -> 97259.744
A13: 10 | B13: 46063 | G13: =E13*F13 -> 0 | H13: 5 | I13: 103.73 | J13: =H13*I13 -> 518.65 | K13: =G13+J13 -> 518.65 | M13: =M12+K13-L13 -> 97778.394
A14: 11 | B14: 46064 | G14: =E14*F14 -> 0 | H14: 5 | I14: 103.73 | J14: =H14*I14 -> 518.65 | K14: =G14+J14 -> 518.65 | M14: =M13+K14-L14 -> 98297.044
A15: 12 | B15: 46065 | G15: =E15*F15 -> 0 | H15: 5 | I15: 103.73 | J15: =H15*I15 -> 518.65 | K15: =G15+J15 -> 518.65 | M15: =M14+K15-L15 -> 98815.694
A16: 13 | B16: 46066 | G16: =E16*F16 -> 0 | J16: =H16*I16 -> 0 | K16: =G16+J16 -> 0 | M16: =M15+K16-L16 -> 98815.694
A17: 14 | B17: 46067 | G17: =E17*F17 -> 0 | J17: =H17*I17 -> 0 | K17: =G17+J17 -> 0 | M17: =M16+K17-L17 -> 98815.694
A18: 15 | B18: 46068 | G18: =E18*F18 -> 0 | J18: =H18*I18 -> 0 | K18: =G18+J18 -> 0 | M18: =M17+K18-L18 -> 98815.694
A19: 16 | B19: 46069 | G19: =E19*F19 -> 0 | H19: 10 | I19: 103.73 | J19: =H19*I19 -> 1037.3 | K19: =G19+J19 -> 1037.3 | M19: =M18+K19-L19 -> 99852.994
A20: 17 | B20: 46070 | G20: =E20*F20 -> 0 | H20: 10 | I20: 103.73 | J20: =H20*I20 -> 1037.3 | K20: =G20+J20 -> 1037.3 | M20: =M19+K20-L20 -> 100890.29
A21: 18 | B21: 46071 | G21: =E21*F21 -> 0 | J21: =H21*I21 -> 0 | K21: =G21+J21 -> 0 | M21: =M20+K21-L21 -> 100890.29
A22: 19 | B22: 46072 | E22: 20 | F22: 91.77 | G22: =E22*F22 -> 1835.4 | J22: =H22*I22 -> 0 | K22: =G22+J22 -> 1835.4 | M22: =M21+K22-L22 -> 102725.69
A23: 20 | B23: 46073 | G23: =E23*F23 -> 0 | J23: =H23*I23 -> 0 | K23: =G23+J23 -> 0 | L23: 100000 | M23: =M22+K23-L23 -> 2725.6943
A24: 21 | B24: 46074 | E24: 35 | F24: 91.77 | G24: =E24*F24 -> 3211.95 | H24: 5 | I24: 103.73 | J24: =H24*I24 -> 518.65 | K24: =G24+J24 -> 3730.6 | M24: =M23+K24-L24 -> 6456.2943
A25: 22 | B25: 46075 | G25: =E25*F25 -> 0 | H25: 12.8 | I25: 103.73 | J25: =H25*I25 -> 1327.744 | K25: =G25+J25 -> 1327.744 | M25: =M24+K25-L25 -> 7784.0383
A26: 23 | B26: 46076 | E26: 119.18 | F26: 91.77 | G26: =E26*F26 -> 10937.149 | H26: 6 | I26: 103.73 | J26: =H26*I26 -> 622.38 | K26: =G26+J26 -> 11559.529 | M26: =M25+K26-L26 -> 19343.567 | Q26: d
A27: 24 | B27: 46077 | G27: =E27*F27 -> 0 | H27: 6 | I27: 103.73 | J27: =H27*I27 -> 622.38 | K27: =G27+J27 -> 622.38 | M27: =M26+K27-L27 -> 19965.947 | Q27: 30 | R27: 50
A28: 25 | B28: 46078 | G28: =E28*F28 -> 0 | J28: =H28*I28 -> 0 | K28: =G28+J28 -> 0 | M28: =M27+K28-L28 -> 19965.947 | Q28: 50 | R28: 4.51
A29: 26 | B29: 46079 | E29: 70 | F29: 91.77 | G29: =E29*F29 -> 6423.9 | J29: =H29*I29 -> 0 | K29: =G29+J29 -> 6423.9 | M29: =M28+K29-L29 -> 26389.847
A30: 27 | B30: 46080 | E30: 30 | F30: 91.77 | G30: =E30*F30 -> 2753.1 | H30: 4.01 | I30: 103.73 | J30: =H30*I30 -> 415.9573 | K30: =G30+J30 -> 3169.0573 | M30: =M29+K30-L30 -> 29558.904
A31: 28 | B31: 46081 | G31: =E31*F31 -> 0 | J31: =H31*I31 -> 0 | K31: =G31+J31 -> 0 | M31: =M30+K31-L31 -> 29558.904
A32: 29 | B32: 46082 | G32: =E32*F32 -> 0 | J32: =H32*I32 -> 0 | K32: =G32+J32 -> 0 | M32: =M31+K32-L32 -> 29558.904
A33: 30 | B33: 46083 | G33: =E33*F33 -> 0 | J33: =H33*I33 -> 0 | K33: =G33+J33 -> 0 | M33: =M32+K33-L33 -> 29558.904
A34: 31 | B34: 46084 | G34: =E34*F34 -> 0 | J34: =H34*I34 -> 0 | K34: =G34+J34 -> 0 | M34: =M33+K34-L34 -> 29558.904
E35: =SUM(E4:E34) -> 1395.17 | G35: =SUM(G4:G34) -> 128034.75 | H35: =SUM(H4:H34) -> 117.74 | J35: =SUM(J4:J34) -> 12213.17 | K35: =SUM(K4:K34) -> 140247.92 | L35: =SUM(L4:L34) -> 226000

Sheet Ugar,Khagwad,Kudichi
A1: Shiri Bhrhmanath Petrolium
A2: S.No | B2: Date | C2: GRN No | D2: Ind No/Bill No | E2: Diesel (Lts) | F2: Price | G2: Amount | H2: Petrol (Lts) | I2: Price | J2: Amount | K2: Total amount | L2: Amount paid | M2: As on Date | N2: Remarks
A3: Opening Balance | K3: 151510.55 | M3: 151510.55 | O3: 235015.76 | P3: =O3-M3 -> 83505.213
A4: 1 | B4: 46054 | E4: 225 | F4: 91.93 | G4: =E4*F4 -> 20684.25 | H4: 20 | I4: 103.89 | J4: =H4*I4 -> 2077.8 | K4: =G4+J4 -> 22762.05 | L4: 0 | M4: =M3+K4-L4 -> 174272.6 | Q4: 235410
A5: 2 | B5: 46055 | E5: 0 | F5: 0 | G5: =E5*F5 -> 0 | H5: 0 | I5: 0 | J5: =H5*I5 -> 0 | K5: =G5+J5 -> 0 | L5: 0 | M5: =M4+K5-L5 -> 174272.6
A6: 3 | B6: 46056 | E6: 74.85 | F6: 91.93 | G6: =E6*F6 -> 6880.9605 | H6: 40 | I6: 103.89 | J6: =H6*I6 -> 4155.6 | K6: =G6+J6 -> 11036.56 | L6: 0 | M6: =M5+K6-L6 -> 185309.16
A7: 4 | B7: 46057 | E7: 130 | F7: 91.93 | G7: =E7*F7 -> 11950.9 | H7: 0 | I7: 0 | J7: =H7*I7 -> 0 | K7: =G7+J7 -> 11950.9 | L7: 0 | M7: =M6+K7-L7 -> 197260.06
A8: 5 | B8: 46058 | E8: 435 | F8: 91.93 | G8: =E8*F8 -> 39989.55 | H8: 0 | I8: 0 | J8: =H8*I8 -> 0 | K8: =G8+J8 -> 39989.55 | L8: 0 | M8: =M7+K8-L8 -> 237249.61 | O8: 237248.96 | P8: =O8-M8 -> -0.6469
A9: 6 | B9: 46059 | E9: 0 | F9: 0 | G9: =E9*F9 -> 0 | H9: 0 | I9: 0 | J9: =H9*I9 -> 0 | K9: =G9+J9 -> 0 | L9: 0 | M9: =M8+K9-L9 -> 237249.61
A10: 7 | B10: 46060 | E10: 187 | F10: 91.93 | G10: =E10*F10 -> 17190.91 | H10: 0 | I10: 0 | J10: =H10*I10 -> 0 | K10: =G10+J10 -> 17190.91 | L10: 0 | M10: =M9+K10-L10 -> 254440.52
A11: 8 | B11: 46061 | E11: 0 | F11: 0 | G11: =E11*F11 -> 0 | H11: 0 | I11: 0 | J11: =H11*I11 -> 0 | K11: =G11+J11 -> 0 | L11: 0 | M11: =M10+K11-L11 -> 254440.52
A12: 9 | B12: 46062 | E12: 30 | F12: 91.93 | G12: =E12*F12 -> 2757.9 | H12: 34 | I12: 103.89 | J12: =H12*I12 -> 3532.26 | K12: =G12+J12 -> 6290.16 | L12: 0 | M12: =M11+K12-L12 -> 260730.68
A13: 10 | B13: 46063 | E13: 70 | F13: 91.93 | G13: =E13*F13 -> 6435.1 | H13: 0 | I13: 0 | J13: =H13*I13 -> 0 | K13: =G13+J13 -> 6435.1 | L13: 151000 | M13: =M12+K13-L13 -> 116165.78
A14: 11 | B14: 46064 | E14: 470 | F14: 91.93 | G14: =E14*F14 -> 43207.1 | H14: 25 | I14: 103.89 | J14: =H14*I14 -> 2597.25 | K14: =G14+J14 -> 45804.35 | L14: 0 | M14: =M13+K14-L14 -> 161970.13
A15: 12 | B15: 46065 | E15: 140 | F15: 91.93 | G15: =E15*F15 -> 12870.2 | H15: 0 | I15: 0 | J15: =H15*I15 -> 0 | K15: =G15+J15 -> 12870.2 | L15: 0 | M15: =M14+K15-L15 -> 174840.33
A16: 13 | B16: 46066 | E16: 135 | F16: 91.93 | G16: =E16*F16 -> 12410.55 | H16: 0 | I16: 0 | J16: =H16*I16 -> 0 | K16: =G16+J16 -> 12410.55 | L16: 0 | M16: =M15+K16-L16 -> 187250.88
A17: 14 | B17: 46067 | E17: 69.99 | F17: 91.93 | G17: =E17*F17 -> 6434.1807 | H17: 30 | I17: 103.89 | J17: =H17*I17 -> 3116.7 | K17: =G17+J17 -> 9550.8807 | L17: 0 | M17: =M16+K17-L17 -> 196801.76
A18: 15 | B18: 46068 | E18: 0 | F18: 0 | G18: =E18*F18 -> 0 | H18: 0 | I18: 0 | J18: =H18*I18 -> 0 | K18: =G18+J18 -> 0 | L18: 0 | M18: =M17+K18-L18 -> 196801.76
A19: 16 | B19: 46069 | E19: 435 | F19: 91.93 | G19: =E19*F19 -> 39989.55 | H19: 40 | I19: 103.89 | J19: =H19*I19 -> 4155.6 | K19: =G19+J19 -> 44145.15 | L19: 0 | M19: =M18+K19-L19 -> 240946.91
A20: 17 | B20: 46070 | E20: 138 | F20: 91.93 | G20: =E20*F20 -> 12686.34 | H20: 0 | I20: 0 | J20: =H20*I20 -> 0 | K20: =G20+J20 -> 12686.34 | L20: 0 | M20: =M19+K20-L20 -> 253633.25
... A31: 28 | B31: 46081 | E31: 0 | F31: 0 | G31: =E31*F31 -> 0 | H31: 0 | I31: 0 | J31: =H31*I31 -> 0 | K31: =G31+J31 -> 0 | L31: 0 | M31: =M30+K31-L31 -> 215407.75
A32: 29 | E32: 0 | F32: 0 | G32: =E32*F32 -> 0 | H32: 0 | I32: 0 | J32: =H32*I32 -> 0 | K32: =G32+J32 -> 0 | L32: 0 | M32: =M31+K32-L32 -> 215407.75
A33: 30 | E33: 0 | F33: 0 | G33: =E33*F33 -> 0 | H33: 0 | I33: 0 | J33: =H33*I33 -> 0 | K33: =G33+J33 -> 0 | L33: 0 | M33: =M32+K33-L33 -> 215407.75
A34: 31 | E34: 0 | F34: 0 | G34: =E34*F34 -> 0 | H34: 0 | I34: 0 | J34: =H34*I34 -> 0 | K34: =G34+J34 -> 0 | L34: 0 | M34: =M33+K34-L34 -> 215407.75
E35: =SUM(E4:E34) -> 4214.84 | G35: =SUM(G4:G34) -> 387470.24 | H35: =SUM(H4:H34) -> 264 | J35: =SUM(J4:J34) -> 27426.96 | K35: =SUM(K4:K34) -> 414897.2 | L35: =SUM(L4:L34) -> 351000

Sheet Kabbur
A1: Shri Jai Hanuman Petrolium
A2: S.No | B2: Date | C2: GRN No | D2: Ind no/Bill No | E2: Diesel (Lts) | F2: Price | G2: Amount | H2: Petrol (Lts) | I2: Price | J2: Amount | K2: Total amount | L2: Amount paid | M2: As on Date | N2: Remarks
A3: Opening Balance | K3: 0 | M3: =+K3 -> 0
A4: 1 | B4: 46054 | G4: =E4*F4 -> 0 | J4: =H4*I4 -> 0 | K4: =G4+J4 -> 0 | L4: =+K4 -> 0
A5: 2 | B5: 46055 | G5: =E5*F5 -> 0 | J5: =H5*I5 -> 0 | K5: =G5+J5 -> 0 | L5: =+K5 -> 0
A6: 3 | B6: 46056 | G6: =E6*F6 -> 0 | J6: =H6*I6 -> 0 | K6: =G6+J6 -> 0 | L6: =+K6 -> 0
A7: 4 | B7: 46057 | G7: =E7*F7 -> 0 | J7: =H7*I7 -> 0 | K7: =G7+J7 -> 0 | L7: =+K7 -> 0
A8: 5 | B8: 46058 | G8: =E8*F8 -> 0 | J8: =H8*I8 -> 0 | K8: =G8+J8 -> 0 | L8: =+K8 -> 0
A9: 6 | B9: 46059 | G9: =E9*F9 -> 0 | J9: =H9*I9 -> 0 | K9: =G9+J9 -> 0 | L9: =+K9 -> 0
A10: 7 | B10: 46060 | G10: =E10*F10 -> 0 | J10: =H10*I10 -> 0 | K10: =G10+J10 -> 0 | L10: =+K10 -> 0
A11: 8 | B11: 46061 | F11: 16.11 | G11: 91.59 | J11: =H11*I11 -> 0 | K11: =G11+J11 -> 91.59 | L11: =+K11 -> 91.59
A12: 9 | B12: 46062 | G12: =E12*F12 -> 0 | J12: =H12*I12 -> 0 | K12: =G12+J12 -> 0 | L12: =+K12 -> 0
A13: 10 | B13: 46063 | E13: 20 | F13: 91.59 | G13: =E13*F13 -> 1831.8 | J13: =H13*I13 -> 0 | K13: =G13+J13 -> 1831.8 | L13: =+K13 -> 1831.8
A14: 11 | B14: 46064 | E14: 66.01 | F14: 91.59 | G14: =E14*F14 -> 6045.8559 | J14: =H14*I14 -> 0 | K14: =G14+J14 -> 6045.8559 | L14: =+K14 -> 6045.8559
A15: 12 | B15: 46065 | G15: =E15*F15 -> 0 | J15: =H15*I15 -> 0 | K15: =G15+J15 -> 0 | L15: =+K15 -> 0
A16: 13 | B16: 46066 | E16: 70 | F16: 91.59 | G16: =E16*F16 -> 6411.3 | J16: =H16*I16 -> 0 | K16: =G16+J16 -> 6411.3 | L16: =+K16 -> 6411.3
A17: 14 | B17: 46067 | G17: =E17*F17 -> 0 | H17: 3.66 | I17: 103.53 | J17: =H17*I17 -> 378.9198 | K17: =G17+J17 -> 378.9198 | L17: =+K17 -> 378.9198
A18: 15 | B18: 46068 | G18: =E18*F18 -> 0 | J18: =H18*I18 -> 0 | K18: =G18+J18 -> 0 | L18: =+K18 -> 0
A19: 16 | B19: 46069 | G19: =E19*F19 -> 0 | J19: =H19*I19 -> 0 | K19: =G19+J19 -> 0 | L19: =+K19 -> 0
A20: 17 | B20: 46070 | G20: =E20*F20 -> 0 | J20: =H20*I20 -> 0 | K20: =G20+J20 -> 0 | L20: =+K20 -> 0
A21: 18 | B21: 46071 | E21: 72.43 | F21: 91.6 | G21: =E21*F21 -> 6634.588 | J21: =H21*I21 -> 0 | K21: =G21+J21 -> 6634.588 | L21: =+K21 -> 6634.588
A22: 19 | B22: 46072 | G22: =E22*F22 -> 0 | J22: =H22*I22 -> 0 | K22: =G22+J22 -> 0 | L22: =+K22 -> 0
A23: 20 | B23: 46073 | E23: 16 | F23: 91.59 | G23: =E23*F23 -> 1465.44 | J23: =H23*I23 -> 0 | K23: =G23+J23 -> 1465.44 | L23: =+K23 -> 1465.44
A24: 21 | B24: 46074 | E24: 25 | F24: 91.59 | G24: =E24*F24 -> 2289.75 | J24: =H24*I24 -> 0 | K24: =G24+J24 -> 2289.75 | L24: =+K24 -> 2289.75
A25: 22 | B25: 46075 | G25: =E25*F25 -> 0 | J25: =H25*I25 -> 0 | K25: =G25+J25 -> 0 | L25: =+K25 -> 0
A26: 23 | B26: 46076 | E26: 25 | F26: 91.59 | G26: =E26*F26 -> 2289.75 | J26: =H26*I26 -> 0 | K26: =G26+J26 -> 2289.75 | L26: =+K26 -> 2289.75
A27: 24 | B27: 46077 | G27: =E27*F27 -> 0 | J27: =H27*I27 -> 0 | K27: =G27+J27 -> 0 | L27: =+K27 -> 0 | O27: 0
A28: 25 | B28: 46078 | E28: 115 | F28: 91.59 | G28: =E28*F28 -> 10532.85 | J28: =H28*I28 -> 0 | K28: =G28+J28 -> 10532.85 | L28: =+K28 -> 10532.85
A29: 26 | B29: 46079 | G29: =E29*F29 -> 0 | J29: =H29*I29 -> 0 | K29: =G29+J29 -> 0 | L29: =+K29 -> 0
A30: 27 | B30: 46080 | E30: 25 | F30: 91.59 | G30: =E30*F30 -> 2289.75 | H30: 8 | I30: 103.53 | J30: =H30*I30 -> 828.24 | K30: =G30+J30 -> 3117.99 | L30: =+K30 -> 3117.99
A31: 28 | B31: 46081 | E31: 10 | F31: 91.59 | G31: =E31*F31 -> 915.9 | J31: =H31*I31 -> 0 | K31: =G31+J31 -> 915.9 | L31: =+K31 -> 915.9
A32: 29 | B32: 46082 | G32: =E32*F32 -> 0 | J32: =H32*I32 -> 0 | K32: =G32+J32 -> 0 | L32: =+K32 -> 0
A33: 30 | B33: 46083 | G33: =E33*F33 -> 0 | J33: =H33*I33 -> 0 | K33: =G33+J33 -> 0 | L33: =+K33 -> 0
A34: 31 | G34: =E34*F34 -> 0 | J34: =H34*I34 -> 0 | K34: =G34+J34 -> 0
E35: =SUM(E4:E34) -> 444.44 | G35: =SUM(G4:G34) -> 40798.574 | H35: =SUM(H4:H34) -> 11.66 | J35: =SUM(J4:J34) -> 1207.1598 | K35: =SUM(K4:K34) -> 42005.734 | L35: =SUM(L4:L34) -> 42005.734

Sheet kumta
A1: V.M.MIRJANKAR (KUMTA) BHARAT
A2: S.No | B2: Date | C2: GRN No | D2: Ind No/Bill No | E2: Diesel (Lts) | F2: Price | G2: Amount | H2: Petrol (Lts) | I2: Price | J2: Amount | K2: Total amount | L2: Amount paid | M2: As on Date | N2: Remarks
A3: Opening Balance | K3: 0 | M3: =+K3 -> 0
A4: 1 | B4: 45689 | E4: 100 | F4: 91.97 | G4: =E4*F4 -> 9197 | J4: =H4*I4 -> 0 | K4: =G4+J4 -> 9197 | L4: 0 | M4: =M3+K4-L4 -> 9197
A5: 2 | B5: 45690 | E5: 0 | F5: 0 | G5: =E5*F5 -> 0 | J5: =H5*I5 -> 0 | K5: =G5+J5 -> 0 | L5: =+K5 -> 0 | M5: =M4+K5-L5 -> 9197
A6: 3 | B6: 45691 | E6: 100 | F6: 91.97 | G6: =E6*F6 -> 9197 | H6: 5 | I6: 104.01 | J6: =H6*I6 -> 520.05 | K6: =G6+J6 -> 9717.05 | L6: 0 | M6: =M5+K6-L6 -> 18914.05
A7: 4 | B7: 45692 | E7: 90 | F7: 91.97 | G7: =E7*F7 -> 8277.3 | H7: 10 | I7: 104.01 | J7: =H7*I7 -> 1040.1 | K7: =G7+J7 -> 9317.4 | L7: 0 | M7: =M6+K7-L7 -> 28231.45
A8: 5 | B8: 45693 | E8: 100 | F8: 91.97 | G8: =E8*F8 -> 9197 | J8: =H8*I8 -> 0 | K8: =G8+J8 -> 9197 | L8: 0 | M8: =M7+K8-L8 -> 37428.45
A9: 6 | B9: 45694 | E9: 0 | F9: 0 | G9: =E9*F9 -> 0 | J9: =H9*I9 -> 0 | K9: =G9+J9 -> 0 | L9: =+K9 -> 0 | M9: =M8+K9-L9 -> 37428.45 | R9: 91.92
A10: 7 | B10: 45695 | E10: 100 | F10: 91.97 | G10: =E10*F10 -> 9197 | H10: 10 | I10: 104.01 | J10: =H10*I10 -> 1040.1 | K10: =G10+J10 -> 10237.1 | L10: 0 | M10: =M9+K10-L10 -> 47665.55
A11: 8 | B11: 45696 | E11: 120 | F11: 91.97 | G11: =E11*F11 -> 11036.4 | J11: =H11*I11 -> 0 | K11: =G11+J11 -> 11036.4 | L11: 0 | M11: =M10+K11-L11 -> 58701.95 | R11: =6.5/675.74 -> 0.0096190843
A12: 9 | B12: 45697 | E12: 120 | F12: 91.97 | G12: =E12*F12 -> 11036.4 | H12: 5 | I12: 104.01 | J12: =H12*I12 -> 520.05 | K12: =G12+J12 -> 11556.45 | L12: 0 | M12: =M11+K12-L12 -> 70258.4
A13: 10 | B13: 45698 | E13: 110 | F13: 91.97 | G13: =E13*F13 -> 10116.7 | J13: =H13*I13 -> 0 | K13: =G13+J13 -> 10116.7 | L13: 0 | M13: =M12+K13-L13 -> 80375.1 | R13: =675.74/6.5 -> 103.96
A14: 11 | B14: 45699 | E14: 120 | F14: 91.97 | G14: =E14*F14 -> 11036.4 | H14: 5 | I14: 104.01 | J14: =H14*I14 -> 520.05 | K14: =G14+J14 -> 11556.45 | L14: 0 | M14: =M13+K14-L14 -> 91931.55
A15: 12 | B15: 45700 | E15: 90 | F15: 91.97 | G15: =E15*F15 -> 8277.3 | J15: =H15*I15 -> 0 | K15: =G15+J15 -> 8277.3 | L15: 0 | M15: =M14+K15-L15 -> 100208.85
A16: 13 | B16: 45701 | E16: 100 | F16: 91.97 | G16: =E16*F16 -> 9197 | H16: 5 | I16: 104.01 | J16: =H16*I16 -> 520.05 | K16: =G16+J16 -> 9717.05 | L16: 0 | M16: =M15+K16-L16 -> 109925.9
A17: 14 | B17: 45702 | E17: 0 | F17: 0 | G17: =E17*F17 -> 0 | J17: =H17*I17 -> 0 | K17: =G17+J17 -> 0 | L17: 109925 | M17: =M16+K17-L17 -> 0.9
A18: 15 | B18: 45703 | E18: 0 | F18: 0 | G18: =E18*F18 -> 0 | H18: 5 | I18: 104.01 | J18: =H18*I18 -> 520.05 | K18: =G18+J18 -> 520.05 | L18: 0 | M18: =M17+K18-L18 -> 520.95
A19: 16 | B19: 45704 | E19: 130 | F19: 91.97 | G19: =E19*F19 -> 11956.1 | H19: 5 | I19: 104.01 | J19: =H19*I19 -> 520.05 | K19: =G19+J19 -> 12476.15 | L19: 0 | M19: =M18+K19-L19 -> 12997.1
A20: 17 | B20: 45705 | E20: 80 | F20: 91.97 | G20: =E20*F20 -> 7357.6 | J20: =H20*I20 -> 0 | K20: =G20+J20 -> 7357.6 | L20: 0 | M20: =M19+K20-L20 -> 20354.7
A21: 18 | B21: 45706 | E21: 0 | F21: 0 | G21: =E21*F21 -> 0 | J21: =H21*I21 -> 0 | K21: =G21+J21 -> 0 | L21: =+K21 -> 0 | M21: =M20+K21-L21 -> 20354.7
A22: 19 | B22: 45707 | E22: 130 | F22: 91.97 | G22: =E22*F22 -> 11956.1 | H22: 5 | I22: 104.01 | J22: =H22*I22 -> 520.05 | K22: =G22+J22 -> 12476.15 | L22: 0 | M22: =M21+K22-L22 -> 32830.85
A23: 20 | B23: 45708 | E23: 100 | F23: 91.97 | G23: =E23*F23 -> 9197 | H23: 15 | I23: 104.01 | J23: =H23*I23 -> 1560.15 | K23: =G23+J23 -> 10757.15 | L23: 0 | M23: =M22+K23-L23 -> 43588
A24: 21 | B24: 45709 | E24: 100 | F24: 91.97 | G24: =E24*F24 -> 9197 | J24: =H24*I24 -> 0 | K24: =G24+J24 -> 9197 | L24: 0 | M24: =M23+K24-L24 -> 52785
A25: 22 | B25: 45710 | E25: 0 | F25: 0 | G25: =E25*F25 -> 0 | J25: =H25*I25 -> 0 | K25: =G25+J25 -> 0 | L25: =+K25 -> 0 | M25: =M24+K25-L25 -> 52785
A26: 23 | B26: 45711 | E26: 90 | F26: 91.97 | G26: =E26*F26 -> 8277.3 | H26: 10 | I26: 104.01 | J26: =H26*I26 -> 1040.1 | K26: =G26+J26 -> 9317.4 | L26: 0 | M26: =M25+K26-L26 -> 62102.4
A27: 24 | B27: 45712 | E27: 60 | F27: 91.97 | G27: =E27*F27 -> 5518.2 | J27: =H27*I27 -> 0 | K27: =G27+J27 -> 5518.2 | L27: 0 | M27: =M26+K27-L27 -> 67620.6
A28: 25 | B28: 45713 | E28: 0 | F28: 0 | G28: =E28*F28 -> 0 | J28: =H28*I28 -> 0 | K28: =G28+J28 -> 0 | L28: =+K28 -> 0 | M28: =M27+K28-L28 -> 67620.6
A29: 26 | B29: 45714 | E29: 100 | F29: 91.97 | G29: =E29*F29 -> 9197 | H29: 10 | I29: 104.01 | J29: =H29*I29 -> 1040.1 | K29: =G29+J29 -> 10237.1 | L29: 60000 | M29: =M28+K29-L29 -> 17857.7
A30: 27 | B30: 45715 | E30: 0 | F30: 0 | G30: =E30*F30 -> 0 | J30: =H30*I30 -> 0 | K30: =G30+J30 -> 0 | L30: =+K30 -> 0 | M30: =M29+K30-L30 -> 17857.7
A31: 28 | B31: 45716 | E31: 100 | F31: 91.97 | G31: =E31*F31 -> 9197 | J31: =H31*I31 -> 0 | K31: =G31+J31 -> 9197 | L31: 0 | M31: =M30+K31-L31 -> 27054.7
A32: 29 | B32: 45717 | E32: 0 | F32: 0 | G32: =E32*F32 -> 0 | J32: =H32*I32 -> 0 | K32: =G32+J32 -> 0 | L32: =+K32 -> 0 | M32: =M31+K32-L32 -> 27054.7
A33: 30 | B33: 45718 | E33: 0 | F33: 0 | G33: =E33*F33 -> 0 | J33: =H33*I33 -> 0 | K33: =G33+J33 -> 0 | L33: =+K33 -> 0 | M33: =M32+K33-L33 -> 27054.7
A34: 31 | B34: 45719 | E34: 0 | F34: 0 | G34: =E34*F34 -> 0 | J34: =H34*I34 -> 0 | K34: =G34+J34 -> 0 | L34: =+K34 -> 0 | M34: =M33+K34-L34 -> 27054.7
E35: =SUM(E4:E34) -> 2040 | G35: =SUM(G4:G34) -> 187618.8 | H35: =SUM(H4:H34) -> 90 | J35: =SUM(J4:J34) -> 9360.9 | K35: =SUM(K4:K34) -> 196979.7 | L35: =SUM(L4:L34) -> 169925

Sheet Jalgaon
A1: Jai Bajarang Sarvo Senter Bodwad
A2: S.No | B2: Date | C2: GRN No | D2: Ind No/Bill No | E2: Diesel (Lts) | F2: Price | G2: Amount | H2: Petrol (Lts) | I2: Price | J2: Amount | K2: Total amount | L2: Amount paid | M2: As on Date | N2: Remarks
A3: Opening Balance | K3: 1368586.5 | M3: =+K3 -> 1368586.5
A4: 1 | B4: 01.2.2026 | E4: 1500 | F4: 91.71 | G4: =E4*F4 -> 137565 | J4: =H4*I4 -> 0 | K4: =G4+J4 -> 137565 | M4: =M3+K4-L4 -> 1506151.5
A5: 2 | B5: 02.2.2026 | E5: 32.93 | F5: 91.09 | G5: =E5*F5 -> 2999.5937 | J5: =H5*I5 -> 0 | K5: =G5+J5 -> 2999.5937 | L5: 1503000 | M5: =M4+K5-L5 -> 6151.0586
A6: 3 | B6: 12.2.2026 | E6: 2900 | F6: 91.71 | G6: =E6*F6 -> 265959 | H6: 45 | I6: 105.19 | J6: =H6*I6 -> 4733.55 | K6: =G6+J6 -> 270692.55 | M6: =M5+K6-L6 -> 276843.61
A7: 4 | B7: 12.2.2026 | D7: N. L. GANDHI & CO. | E7: 38.356 | F7: 91.25 | G7: =E7*F7 -> 3499.985 | J7: =H7*I7 -> 0 | K7: =G7+J7 -> 3499.985 | L7: 3499.99 | M7: =M6+K7-L7 -> 276843.6 | N7: IOCL
A8: 5 | B8: 12.2.2026 | D8: GULSHAN AUTOMOBILES, GONDKHAIRI | E8: 40 | F8: 90.73 | G8: =E8*F8 -> 3629.2 | J8: =H8*I8 -> 0 | K8: =G8+J8 -> 3629.2 | L8: 3629.2 | M8: =M7+K8-L8 -> 276843.6 | N8: HPCL
A9: 6 | B9: 13.2.2026 | E9: 500 | F9: 91.71 | G9: =E9*F9 -> 45855 | J9: =H9*I9 -> 0 | K9: =G9+J9 -> 45855 | M9: =M8+K9-L9 -> 322698.6
A10: 7 | B10: 14.2.2026 | E10: 860 | F10: 91.71 | G10: =E10*F10 -> 78870.6 | J10: =H10*I10 -> 0 | K10: =G10+J10 -> 78870.6 | M10: =M9+K10-L10 -> 401569.2
A11: 8 | B11: 15.2.2026 | E11: 2000 | F11: 91.71 | G11: =E11*F11 -> 183420 | H11: 50 | I11: 105.19 | J11: =H11*I11 -> 5259.5 | K11: =G11+J11 -> 188679.5 | M11: =M10+K11-L11 -> 590248.7
A12: 9 | B12: 16.2.2026 | E12: 2500 | F12: 91.71 | G12: =E12*F12 -> 229275 | J12: =H12*I12 -> 0 | K12: =G12+J12 -> 229275 | M12: =M11+K12-L12 -> 819523.7
A13: 10 | B13: 17.2.2026 | E13: 2700 | F13: 91.71 | G13: =E13*F13 -> 247617 | J13: =H13*I13 -> 0 | K13: =G13+J13 -> 247617 | M13: =M12+K13-L13 -> 1067140.7
A14: 11 | B14: 17.2.2026 | E14: 400 | F14: 91.61 | G14: =E14*F14 -> 36644 | J14: =H14*I14 -> 0 | K14: =G14+J14 -> 36644 | M14: =M13+K14-L14 -> 1103784.7
A15: 12 | B15: 18.2.2026 | E15: 2500 | F15: 91.71 | G15: =E15*F15 -> 229275 | H15: 45 | I15: 105.19 | J15: =H15*I15 -> 4733.55 | K15: =G15+J15 -> 234008.55 | M15: =M14+K15-L15 -> 1337793.3
A16: 13 | B16: 26.2.2026 | G16: =E16*F16 -> 0 | J16: =H16*I16 -> 0 | K16: =G16+J16 -> 0 | L16: 1000000 | M16: =M15+K16-L16 -> 337793.25
A17: 14 | G17: =E17*F17 -> 0 | J17: =H17*I17 -> 0 | K17: =G17+J17 -> 0 | M17: =M16+K17-L17 -> 337793.25
A18: 15 | G18: =E18*F18 -> 0 | J18: =H18*I18 -> 0 | K18: =G18+J18 -> 0 | M18: =M17+K18-L18 -> 337793.25
A19: 16 | G19: =E19*F19 -> 0 | J19: =H19*I19 -> 0 | K19: =G19+J19 -> 0 | M19: =M18+K19-L19 -> 337793.25
A20: 17 | G20: =E20*F20 -> 0 | J20: =H20*I20 -> 0 | K20: =G20+J20 -> 0 | M20: =M19+K20-L20 -> 337793.25
A21: 18 | G21: =E21*F21 -> 0 | J21: =H21*I21 -> 0 | K21: =G21+J21 -> 0 | M21: =M20+K21-L21 -> 337793.25
A22: 19 | G22: =E22*F22 -> 0 | J22: =H22*I22 -> 0 | K22: =G22+J22 -> 0 | M22: =M21+K22-L22 -> 337793.25
A23: 20 | G23: =E23*F23 -> 0 | J23: =H23*I23 -> 0 | K23: =G23+J23 -> 0 | M23: =M22+K23-L23 -> 337793.25
A24: 21 | G24: =E24*F24 -> 0 | J24: =H24*I24 -> 0 | K24: =G24+J24 -> 0 | M24: =M23+K24-L24 -> 337793.25
A25: 22 | G25: =E25*F25 -> 0 | J25: =H25*I25 -> 0 | K25: =G25+J25 -> 0 | M25: =M24+K25-L25 -> 337793.25
A26: 23 | G26: =E26*F26 -> 0 | J26: =H26*I26 -> 0 | K26: =G26+J26 -> 0 | M26: =M25+K26-L26 -> 337793.25
A27: 24 | G27: =E27*F27 -> 0 | J27: =H27*I27 -> 0 | K27: =G27+J27 -> 0 | M27: =M26+K27-L27 -> 337793.25
A28: 25 | G28: =E28*F28 -> 0 | J28: =H28*I28 -> 0 | K28: =G28+J28 -> 0 | M28: =M27+K28-L28 -> 337793.25
... A36: 33 | G36: =E36*F36 -> 0 | J36: =H36*I36 -> 0 | K36: =G36+J36 -> 0 | M36: =M35+K36-L36 -> 337793.25
A37: 34 | G37: =E37*F37 -> 0 | J37: =H37*I37 -> 0 | K37: =G37+J37 -> 0 | M37: =M36+K37-L37 -> 337793.25 | P37: 41
A38: 35 | G38: =E38*F38 -> 0 | J38: =H38*I38 -> 0 | K38: =G38+J38 -> 0 | M38: =M37+K38-L38 -> 337793.25 | P38: 40 | Q38: 5
A39: 36 | G39: =E39*F39 -> 0 | J39: =H39*I39 -> 0 | K39: =G39+J39 -> 0 | M39: =M38+K39-L39 -> 337793.25
A40: 37 | G40: =E40*F40 -> 0 | J40: =H40*I40 -> 0 | K40: =G40+J40 -> 0 | M40: =M39+K40-L40 -> 337793.25
A41: 38 | G41: =E41*F41 -> 0 | J41: =H41*I41 -> 0 | K41: =G41+J41 -> 0 | M41: =M40+K41-L41 -> 337793.25
A42: 39 | G42: =E42*F42 -> 0 | J42: =H42*I42 -> 0 | K42: =G42+J42 -> 0 | M42: =M41+K42-L42 -> 337793.25
A43: 40 | G43: =E43*F43 -> 0 | J43: =H43*I43 -> 0 | K43: =G43+J43 -> 0 | M43: =M42+K43-L43 -> 337793.25
A44: 41 | G44: =E44*F44 -> 0 | J44: =H44*I44 -> 0 | K44: =G44+J44 -> 0 | M44: =M43+K44-L44 -> 337793.25
A45: 42 | G45: =E45*F45 -> 0 | J45: =H45*I45 -> 0 | K45: =G45+J45 -> 0 | M45: =M44+K45-L45 -> 337793.25
A46: 43 | G46: =E46*F46 -> 0 | J46: =H46*I46 -> 0 | K46: =G46+J46 -> 0 | M46: =M45+K46-L46 -> 337793.25
A47: 44 | G47: =E47*F47 -> 0 | J47: =H47*I47 -> 0 | K47: =G47+J47 -> 0 | M47: =M46+K47-L47 -> 337793.25
A48: 45 | G48: =E48*F48 -> 0 | J48: =H48*I48 -> 0 | K48: =G48+J48 -> 0 | M48: =M47+K48-L48 -> 337793.25
A49: 46 | G49: =E49*F49 -> 0 | J49: =H49*I49 -> 0 | K49: =G49+J49 -> 0 | M49: =M48+K49-L49 -> 337793.25
A50: 47 | G50: =E50*F50 -> 0 | J50: =H50*I50 -> 0 | K50: =G50+J50 -> 0 | L50: 0 | M50: =M49+K50-L50 -> 337793.25
A51: 48 | G51: =E51*F51 -> 0 | J51: =H51*I51 -> 0 | K51: =G51+J51 -> 0 | L51: 0 | M51: =M50+K51-L51 -> 337793.25
A52: 49 | G52: =E52*F52 -> 0 | J52: =H52*I52 -> 0 | K52: =G52+J52 -> 0 | L52: 0 | M52: =M51+K52-L52 -> 337793.25
A53: 50 | G53: =E53*F53 -> 0 | J53: =H53*I53 -> 0 | K53: =G53+J53 -> 0 | L53: 0 | M53: =M52+K53-L53 -> 337793.25 | O53: 1109792.3 | P53: =M53-O53 -> -771999.03
E54: =SUM(E4:E53) -> 15971.286 | G54: =SUM(G4:G53) -> 1464609.4 | H54: =SUM(H4:H53) -> 140 | J54: =SUM(J4:J53) -> 14726.6 | K54: =SUM(K4:K53) -> 1479336 | L54: =SUM(L4:L53) -> 2510129.2

Sheet Jalgoan-2
A1: Agrawal Petrol Pump
A2: S.No | B2: Date | C2: GRN No | D2: Ind No/Bill No | E2: Diesel (Lts) | F2: Price | G2: Amount | H2: Petrol (Lts) | I2: Price | J2: Amount | K2: Total amount | L2: Amount paid | M2: As on Date | N2: Remarks
A3: Opening Balance | K3: 0 | M3: =+K3 -> 0
A4: 1 | B4: 01.2.2026 | E4: 0 | F4: 0 | G4: =E4*F4 -> 0 | J4: =H4*I4 -> 0 | K4: =G4+J4 -> 0 | M4: =M3+K4-L4 -> 0
A5: 2 | B5: 02.2.2026 | E5: 4000 | F5: 91.71 | G5: =E5*F5 -> 366840 | J5: =H5*I5 -> 0 | K5: =G5+J5 -> 366840 | M5: =M4+K5-L5 -> 366840
A6: 3 | B6: 03.2.2026 | E6: 500 | F6: 91.71 | G6: =E6*F6 -> 45855 | J6: =H6*I6 -> 0 | K6: =G6+J6 -> 45855 | M6: =M5+K6-L6 -> 412695
A7: 4 | B7: 04.2.2026 | E7: 400 | F7: 91.71 | G7: =E7*F7 -> 36684 | H7: 30 | I7: 105.44 | J7: =H7*I7 -> 3163.2 | K7: =G7+J7 -> 39847.2 | M7: =M6+K7-L7 -> 452542.2
A8: 5 | B8: 05.2.2026 | E8: 2000 | F8: 91.71 | G8: =E8*F8 -> 183420 | J8: =H8*I8 -> 0 | K8: =G8+J8 -> 183420 | M8: =M7+K8-L8 -> 635962.2
A9: 6 | B9: 06.2.2026 | E9: 2400 | F9: 91.71 | G9: =E9*F9 -> 220104 | H9: 40 | I9: 105.44 | J9: =H9*I9 -> 4217.6 | K9: =G9+J9 -> 224321.6 | M9: =M8+K9-L9 -> 860283.8
B10: 06.2.2026
A11: 7 | B11: 07.2.2026 | E11: 900 | F11: 91.71 | G11: =E11*F11 -> 82539 | J11: =H11*I11 -> 0 | K11: =G11+J11 -> 82539 | M11: =M9+K11-L11 -> 942822.8
A12: 8 | B12: 09.2.2026 | E12: 400 | F12: 91.71 | G12: =E12*F12 -> 36684 | J12: =H12*I12 -> 0 | K12: =G12+J12 -> 36684 | M12: =M11+K12-L12 -> 979506.8
A13: 9 | B13: 10.2.2026 | E13: 3230.42 | F13: 91.71 | G13: =E13*F13 -> 296261.82 | H13: 35 | I13: 105.44 | J13: =H13*I13 -> 3690.4 | K13: =G13+J13 -> 299952.22 | M13: =M12+K13-L13 -> 1279459
A14: 10 | B14: 11.2.2026 | E14: 400 | F14: 91.71 | G14: =E14*F14 -> 36684 | J14: =H14*I14 -> 0 | K14: =G14+J14 -> 36684 | M14: =M13+K14-L14 -> 1316143
A15: 11 | B15: 12.2.2026 | E15: 2000 | F15: 91.71 | G15: =E15*F15 -> 183420 | J15: =H15*I15 -> 0 | K15: =G15+J15 -> 183420 | M15: =M14+K15-L15 -> 1499563
A16: 12 | B16: 19.2.2026 | E16: 1100 | F16: 91.71 | G16: =E16*F16 -> 100881 | J16: =H16*I16 -> 0 | K16: =G16+J16 -> 100881 | M16: =M15+K16-L16 -> 1600444
A17: 13 | B17: 20.2.2026 | E17: 2500 | F17: 91.71 | G17: =E17*F17 -> 229275 | H17: 15 | I17: 105.44 | J17: =H17*I17 -> 1581.6 | K17: =G17+J17 -> 230856.6 | M17: =M16+K17-L17 -> 1831300.6
A18: 14 | B18: 21.2.2026 | E18: 2200 | F18: 91.71 | G18: =E18*F18 -> 201762 | J18: =H18*I18 -> 0 | K18: =G18+J18 -> 201762 | M18: =M17+K18-L18 -> 2033062.6
A19: 15 | B19: 22.2.2026 | E19: 2700 | F19: 91.71 | G19: =E19*F19 -> 247617 | J19: =H19*I19 -> 0 | K19: =G19+J19 -> 247617 | M19: =M18+K19-L19 -> 2280679.6
A20: 16 | B20: 23.2.2026 | E20: 2898 | F20: 91.71 | G20: =E20*F20 -> 265775.58 | H20: 50 | I20: 105.44 | J20: =H20*I20 -> 5272 | K20: =G20+J20 -> 271047.58 | M20: =M19+K20-L20 -> 2551727.2
A21: 17 | B21: 24.2.2026 | E21: 2200 | F21: 91.71 | G21: =E21*F21 -> 201762 | J21: =H21*I21 -> 0 | K21: =G21+J21 -> 201762 | M21: =M20+K21-L21 -> 2753489.2
A22: 18 | B22: 25.2.2026 | E22: 4700 | F22: 91.71 | G22: =E22*F22 -> 431037 | H22: 45 | I22: 105.44 | J22: =H22*I22 -> 4744.8 | K22: =G22+J22 -> 435781.8 | M22: =M21+K22-L22 -> 3189271
A23: 19 | B23: 26.2.2026 | E23: 2200 | F23: 91.71 | G23: =E23*F23 -> 201762 | J23: =H23*I23 -> 0 | K23: =G23+J23 -> 201762 | L23: 1000000 | M23: =M22+K23-L23 -> 2391033
A24: 20 | B24: 27.2.2026 | E24: 911.8 | F24: 91.71 | G24: =E24*F24 -> 83621.178 | J24: =H24*I24 -> 0 | K24: =G24+J24 -> 83621.178 | M24: =M23+K24-L24 -> 2474654.2
A25: 21 | B25: 28.2.2026 | E25: 5200 | F25: 91.71 | G25: =E25*F25 -> 476892 | H25: 15 | I25: 105.44 | J25: =H25*I25 -> 1581.6 | K25: =G25+J25 -> 478473.6 | M25: =M24+K25-L25 -> 2953127.8
A26: 22 | G26: =E26*F26 -> 0 | J26: =H26*I26 -> 0 | K26: =G26+J26 -> 0 | M26: =M25+K26-L26 -> 2953127.8
A27: 23 | G27: =E27*F27 -> 0 | J27: =H27*I27 -> 0 | K27: =G27+J27 -> 0 | M27: =M26+K27-L27 -> 2953127.8
A28: 24 | G28: =E28*F28 -> 0 | J28: =H28*I28 -> 0 | K28: =G28+J28 -> 0 | M28: =M27+K28-L28 -> 2953127.8
A29: 25 | G29: =E29*F29 -> 0 | J29: =H29*I29 -> 0 | K29: =G29+J29 -> 0 | M29: =M28+K29-L29 -> 2953127.8
A30: 26 | G30: =E30*F30 -> 0 | J30: =H30*I30 -> 0 | K30: =G30+J30 -> 0 | M30: =M29+K30-L30 -> 2953127.8
A31: 27 | G31: =E31*F31 -> 0 | J31: =H31*I31 -> 0 | K31: =G31+J31 -> 0 | M31: =M30+K31-L31 -> 2953127.8
A32: 28 | G32: =E32*F32 -> 0 | J32: =H32*I32 -> 0 | K32: =G32+J32 -> 0 | M32: =M31+K32-L32 -> 2953127.8
A33: 29 | G33: =E33*F33 -> 0 | J33: =H33*I33 -> 0 | K33: =G33+J33 -> 0 | M33: =M32+K33-L33 -> 2953127.8
A34: 30 | G34: =E34*F34 -> 0 | J34: =H34*I34 -> 0 | K34: =G34+J34 -> 0 | M34: =M33+K34-L34 -> 2953127.8
A35: 31 | G35: =E35*F35 -> 0 | J35: =H35*I35 -> 0 | K35: =G35+J35 -> 0 | M35: =M34+K35-L35 -> 2953127.8
A36: 32 | G36: =E36*F36 -> 0 | J36: =H36*I36 -> 0 | K36: =G36+J36 -> 0 | M36: =M35+K36-L36 -> 2953127.8
A37: 33 | G37: =E37*F37 -> 0 | J37: =H37*I37 -> 0 | K37: =G37+J37 -> 0 | M37: =M36+K37-L37 -> 2953127.8
A38: 34 | G38: =E38*F38 -> 0 | J38: =H38*I38 -> 0 | K38: =G38+J38 -> 0 | M38: =M37+K38-L38 -> 2953127.8 | P38: 41
A39: 35 | G39: =E39*F39 -> 0 | J39: =H39*I39 -> 0 | K39: =G39+J39 -> 0 | M39: =M38+K39-L39 -> 2953127.8 | P39: 40 | Q39: 5
A40: 36 | G40: =E40*F40 -> 0 | J40: =H40*I40 -> 0 | K40: =G40+J40 -> 0 | M40: =M39+K40-L40 -> 2953127.8
A41: 37 | G41: =E41*F41 -> 0 | J41: =H41*I41 -> 0 | K41: =G41+J41 -> 0 | M41: =M40+K41-L41 -> 2953127.8
A42: 38 | G42: =E42*F42 -> 0 | J42: =H42*I42 -> 0 | K42: =G42+J42 -> 0 | M42: =M41+K42-L42 -> 2953127.8
A43: 39 | G43: =E43*F43 -> 0 | J43: =H43*I43 -> 0 | K43: =G43+J43 -> 0 | M43: =M42+K43-L43 -> 2953127.8
A44: 40 | G44: =E44*F44 -> 0 | J44: =H44*I44 -> 0 | K44: =G44+J44 -> 0 | M44: =M43+K44-L44 -> 2953127.8
A45: 41 | G45: =E45*F45 -> 0 | J45: =H45*I45 -> 0 | K45: =G45+J45 -> 0 | M45: =M44+K45-L45 -> 2953127.8
A46: 42 | G46: =E46*F46 -> 0 | J46: =H46*I46 -> 0 | K46: =G46+J46 -> 0 | M46: =M45+K46-L46 -> 2953127.8
A47: 43 | G47: =E47*F47 -> 0 | J47: =H47*I47 -> 0 | K47: =G47+J47 -> 0 | M47: =M46+K47-L47 -> 2953127.8
A48: 44 | G48: =E48*F48 -> 0 | J48: =H48*I48 -> 0 | K48: =G48+J48 -> 0 | M48: =M47+K48-L48 -> 2953127.8
A49: 45 | G49: =E49*F49 -> 0 | J49: =H49*I49 -> 0 | K49: =G49+J49 -> 0 | M49: =M48+K49-L49 -> 2953127.8
A50: 46 | G50: =E50*F50 -> 0 | J50: =H50*I50 -> 0 | K50: =G50+J50 -> 0 | M50: =M49+K50-L50 -> 2953127.8
A51: 47 | G51: =E51*F51 -> 0 | J51: =H51*I51 -> 0 | K51: =G51+J51 -> 0 | L51: 0 | M51: =M50+K51-L51 -> 2953127.8
A52: 48 | G52: =E52*F52 -> 0 | J52: =H52*I52 -> 0 | K52: =G52+J52 -> 0 | L52: 0 | M52: =M51+K52-L52 -> 2953127.8
A53: 49 | G53: =E53*F53 -> 0 | J53: =H53*I53 -> 0 | K53: =G53+J53 -> 0 | L53: 0 | M53: =M52+K53-L53 -> 2953127.8
A54: 50 | G54: =E54*F54 -> 0 | J54: =H54*I54 -> 0 | K54: =G54+J54 -> 0 | L54: 0 | M54: =M53+K54-L54 -> 2953127.8 | O54: 1109792.3 | P54: =M54-O54 -> 1843335.5
E55: =SUM(E4:E54) -> 42840.22 | G55: =SUM(G4:G54) -> 3928876.6 | H55: =SUM(H4:H54) -> 230 | J55: =SUM(J4:J54) -> 24251.2 | K55: =SUM(K4:K54) -> 3953127.8 | L55: =SUM(L4:L54) -> 1000000

Sheet MKBD
A1: Shree Sai Samarth Petroleum
A2: S.No | B2: Date | C2: GRN No | D2: Ind No/Bill No | E2: Diesel (Lts) | F2: Price | G2: Amount | H2: Petrol (Lts) | I2: Price | J2: Amount | K2: Total amount | L2: Amount paid | M2: As on Date | N2: Remarks
A3: Opening Balance | K3: 366041.65 | M3: =+K3 -> 366041.65 | O3: 1194597
A4: 1 | B4: 46054 | C4: 0 | G4: =E4*F4 -> 0 | J4: =H4*I4 -> 0 | K4: =G4+J4 -> 0 | M4: =M3+K4-L4 -> 366041.65
A5: 2 | B5: 46055 | C5: 0 | G5: =E5*F5 -> 0 | J5: =H5*I5 -> 0 | K5: =G5+J5 -> 0 | M5: =M4+K5-L5 -> 366041.65
A6: 3 | B6: 46056 | C6: 0 | G6: =E6*F6 -> 0 | J6: =H6*I6 -> 0 | K6: =G6+J6 -> 0 | M6: =M5+K6-L6 -> 366041.65
A7: 4 | B7: 46057 | C7: 0 | G7: 0 | J7: 0 | K7: 0 | M7: =M6+K7-L7 -> 366041.65
A8: 5 | B8: 46058 | C8: 0 | E8: 3000 | F8: 91.14 | G8: =E8*F8 -> 273420 | J8: =H8*I8 -> 0 | K8: =G8+J8 -> 273420 | M8: =M7+K8-L8 -> 639461.65
A9: 6 | B9: 46059 | C9: 0 | G9: =E9*F9 -> 0 | J9: =H9*I9 -> 0 | K9: =G9+J9 -> 0 | M9: =M8+K9-L9 -> 639461.65
A10: 7 | B10: 46060 | C10: 0 | G10: =E10*F10 -> 0 | J10: =H10*I10 -> 0 | K10: =G10+J10 -> 0 | M10: =M9+K10-L10 -> 639461.65
A11: 8 | B11: 46061 | C11: 0 | G11: =E11*F11 -> 0 | J11: =H11*I11 -> 0 | K11: =G11+J11 -> 0 | M11: =M10+K11-L11 -> 639461.65
A12: 9 | B12: 46062 | C12: 0 | G12: =E12*F12 -> 0 | J12: =H12*I12 -> 0 | K12: =G12+J12 -> 0 | M12: =M11+K12-L12 -> 639461.65
A13: 10 | B13: 46063 | C13: 0 | G13: =E13*F13 -> 0 | J13: =H13*I13 -> 0 | K13: =G13+J13 -> 0 | M13: =M12+K13-L13 -> 639461.65
A14: 11 | B14: 46064 | C14: 0 | E14: 1000 | F14: 91.14 | G14: =E14*F14 -> 91140 | H14: 20 | I14: 104.6 | J14: =H14*I14 -> 2092 | K14: =G14+J14 -> 93232 | M14: =M13+K14-L14 -> 732693.65
A15: 12 | B15: 46065 | C15: 0 | G15: =E15*F15 -> 0 | J15: =H15*I15 -> 0 | K15: =G15+J15 -> 0 | M15: =M14+K15-L15 -> 732693.65
A16: 13 | B16: 46066 | C16: 0 | G16: =E16*F16 -> 0 | H16: 25 | I16: 104.6 | J16: =H16*I16 -> 2615 | K16: =G16+J16 -> 2615 | M16: =M15+K16-L16 -> 735308.65
A17: 14 | B17: 46067 | C17: 0 | G17: =E17*F17 -> 0 | J17: =H17*I17 -> 0 | K17: =G17+J17 -> 0 | M17: =M16+K17-L17 -> 735308.65
A18: 15 | B18: 46068 | C18: 0 | G18: =E18*F18 -> 0 | J18: =H18*I18 -> 0 | K18: =G18+J18 -> 0 | M18: =M17+K18-L18 -> 735308.65
A19: 16 | B19: 46069 | C19: 0 | G19: =E19*F19 -> 0 | J19: =H19*I19 -> 0 | K19: =G19+J19 -> 0 | M19: =M18+K19-L19 -> 735308.65
A20: 17 | B20: 46070 | C20: 0 | E20: 3000 | F20: 91.14 | G20: =E20*F20 -> 273420 | H20: 10 | I20: 104.6 | J20: =H20*I20 -> 1046 | K20: =G20+J20 -> 274466 | M20: =M19+K20-L20 -> 1009774.6
A21: 18 | B21: 46071 | C21: 0 | G21: =E21*F21 -> 0 | J21: =H21*I21 -> 0 | K21: =G21+J21 -> 0 | M21: =M20+K21-L21 -> 1009774.6
A22: 19 | B22: 46072 | C22: 0 | G22: =E22*F22 -> 0 | J22: =H22*I22 -> 0 | K22: =G22+J22 -> 0 | M22: =M21+K22-L22 -> 1009774.6
A23: 20 | B23: 46073 | J23: =H23*I23 -> 0 | K23: =G23+J23 -> 0 | M23: =M22+K23-L23 -> 1009774.6 | O23: Lubricant Purchaged
A24: 21 | B24: 46074 | C24: 0 | G24: =E24*F24 -> 0 | J24: =H24*I24 -> 0 | K24: =G24+J24 -> 0 | M24: =M23+K24-L24 -> 1009774.6
A25: 22 | B25: 46075 | C25: 0 | G25: =E25*F25 -> 0 | J25: =H25*I25 -> 0 | K25: =G25+J25 -> 0 | M25: =M24+K25-L25 -> 1009774.6
A26: 23 | B26: 46076 | C26: 0 | G26: =E26*F26 -> 0 | J26: =H26*I26 -> 0 | K26: =G26+J26 -> 0 | M26: =M25+K26-L26 -> 1009774.6
A27: 24 | B27: 46077 | C27: 0 | G27: =E27*F27 -> 0 | J27: =H27*I27 -> 0 | K27: =G27+J27 -> 0 | M27: =M26+K27-L27 -> 1009774.6
A28: 25 | B28: 46078 | C28: 0 | E28: 1000 | F28: 91.14 | G28: =E28*F28 -> 91140 | H28: 20 | I28: 104.6 | J28: =H28*I28 -> 2092 | K28: =G28+J28 -> 93232 | M28: =M27+K28-L28 -> 1103006.6
A29: 26 | B29: 46079 | J29: =H29*I29 -> 0 | K29: =G29+J29 -> 0 | L29: 1000000 | M29: =M28+K29-L29 -> 103006.65
A30: 27 | B30: 46080 | C30: 0 | G30: =E30*F30 -> 0 | J30: =H30*I30 -> 0 | K30: =G30+J30 -> 0 | M30: =M29+K30-L30 -> 103006.65
A31: 28 | B31: 46081 | C31: 0 | G31: =E31*F31 -> 0 | J31: =H31*I31 -> 0 | K31: =G31+J31 -> 0 | M31: =M30+K31-L31 -> 103006.65
A32: 29 | C32: 0 | G32: =E32*F32 -> 0 | J32: =H32*I32 -> 0 | K32: =G32+J32 -> 0 | M32: =M31+K32-L32 -> 103006.65
A33: 30 | C33: 0 | G33: =E33*F33 -> 0 | J33: =H33*I33 -> 0 | K33: =G33+J33 -> 0 | M33: =M32+K33-L33 -> 103006.65
A34: 31 | C34: 0 | G34: =E34*F34 -> 0 | J34: =H34*I34 -> 0 | K34: =G34+J34 -> 0 | M34: =M33+K34-L34 -> 103006.65
A35: 32 | C35: 0 | G35: =E35*F35 -> 0 | J35: =H35*I35 -> 0 | K35: =G35+J35 -> 0 | M35: =M34+K35-L35 -> 103006.65
A36: 31 | C36: 0 | G36: =E36*F36 -> 0 | J36: =H36*I36 -> 0 | K36: =G36+J36 -> 0 | M36: =M35+K36-L36 -> 103006.65
A37: 32 | E37: 0 | F37: 0 | G37: =E37*F37 -> 0 | J37: =H37*I37 -> 0 | K37: =G37+J37 -> 0 | M37: =M36+K37-L37 -> 103006.65
E38: =SUM(E4:E37) -> 8000 | G38: =SUM(G4:G37) -> 729120 | H38: =SUM(H4:H37) -> 75 | J38: =SUM(J4:J37) -> 7845 | K38: =SUM(K4:K37) -> 736965 | L38: =SUM(L4:L37) -> 1000000

Sheet  Haveri-2
A1: Magavi fuel F/S
A2: S.No | B2: Date | C2: GRN No | D2: Ind No/Bill No | E2: Diesel (Lts) | F2: Price | G2: Amount | H2: Petrol (Lts) | I2: Price | J2: Amount | K2: Total amount | L2: Amount paid | M2: As on Date | N2: Remarks
D3: Opening Balance | L3: 150830.73 | M3: 150830.73
A4: 1 | B4: 46054 | E4: 85 | F4: 91.49 | G4: =E4*F4 -> 7776.65 | J4: =H4*I4 -> 0 | K4: =G4+J4 -> 7776.65 | L4: 0 | M4: =M3+K4-L4 -> 158607.38
A5: 2 | B5: 46055 | E5: 200 | F5: 91.49 | G5: =E5*F5 -> 18298 | H5: 27.73 | I5: 103.43 | J5: =H5*I5 -> 2868.1139 | K5: =G5+J5 -> 21166.114 | L5: 158600 | M5: =M4+K5-L5 -> 21173.497
A6: 3 | B6: 46056 | E6: 238.05 | F6: 91.49 | G6: =E6*F6 -> 21779.195 | J6: =H6*I6 -> 0 | K6: =G6+J6 -> 21779.195 | L6: 0 | M6: =M5+K6-L6 -> 42952.692
A7: 4 | B7: 46057 | E7: 45 | F7: 91.49 | G7: =E7*F7 -> 4117.05 | J7: =H7*I7 -> 0 | K7: =G7+J7 -> 4117.05 | L7: 0 | M7: =M6+K7-L7 -> 47069.742
A8: 5 | B8: 46058 | E8: 55 | F8: 91.49 | G8: =E8*F8 -> 5031.95 | J8: =H8*I8 -> 0 | K8: =G8+J8 -> 5031.95 | L8: 0 | M8: =M7+K8-L8 -> 52101.692
A9: 6 | B9: 46059 | E9: 80 | F9: 91.49 | G9: =E9*F9 -> 7319.2 | H9: 15 | I9: 103.43 | J9: =H9*I9 -> 1551.45 | K9: =G9+J9 -> 8870.65 | L9: 0 | M9: =M8+K9-L9 -> 60972.342
A10: 7 | B10: 46060 | E10: 36 | F10: 91.49 | G10: =E10*F10 -> 3293.64 | H10: 6 | I10: 103.43 | J10: =H10*I10 -> 620.58 | K10: =G10+J10 -> 3914.22 | L10: 0 | M10: =M9+K10-L10 -> 64886.562
A11: 8 | B11: 46061 | E11: 29 | F11: 91.49 | G11: =E11*F11 -> 2653.21 | J11: =H11*I11 -> 0 | K11: =G11+J11 -> 2653.21 | L11: 0 | M11: =M10+K11-L11 -> 67539.772
A12: 9 | B12: 46062 | E12: 30 | F12: 91.49 | G12: =E12*F12 -> 2744.7 | J12: =H12*I12 -> 0 | K12: =G12+J12 -> 2744.7 | L12: 0 | M12: =M11+K12-L12 -> 70284.472 | O12: .
A13: 10 | B13: 46063 | E13: 298 | F13: 91.49 | G13: =E13*F13 -> 27264.02 | H13: 5 | I13: 103.43 | J13: =H13*I13 -> 517.15 | K13: =G13+J13 -> 27781.17 | L13: 0 | M13: =M12+K13-L13 -> 98065.642
A14: 11 | B14: 46064 | E14: 140 | F14: 91.49 | G14: =E14*F14 -> 12808.6 | H14: 6 | I14: 103.43 | J14: =H14*I14 -> 620.58 | K14: =G14+J14 -> 13429.18 | L14: 0 | M14: =M13+K14-L14 -> 111494.82
A15: 12 | B15: 46065 | E15: 30 | F15: 91.49 | G15: =E15*F15 -> 2744.7 | J15: =H15*I15 -> 0 | K15: =G15+J15 -> 2744.7 | L15: 0 | M15: =M14+K15-L15 -> 114239.52
A16: 13 | B16: 46066 | E16: 48 | F16: 91.49 | G16: =E16*F16 -> 4391.52 | J16: =H16*I16 -> 0 | K16: =G16+J16 -> 4391.52 | L16: 0 | M16: =M15+K16-L16 -> 118631.04
A17: 14 | B17: 46067 | E17: 75 | F17: 91.49 | G17: =E17*F17 -> 6861.75 | H17: 12 | I17: 103.43 | J17: =H17*I17 -> 1241.16 | K17: =G17+J17 -> 8102.91 | L17: 0 | M17: =M16+K17-L17 -> 126733.95
A18: 15 | B18: 46068 | E18: 179.1 | F18: 91.49 | G18: =E18*F18 -> 16385.859 | J18: =H18*I18 -> 0 | K18: =G18+J18 -> 16385.859 | L18: 0 | M18: =M17+K18-L18 -> 143119.81
A19: 16 | B19: 46069 | G19: =E19*F19 -> 0 | J19: =H19*I19 -> 0 | K19: =G19+J19 -> 0 | L19: 0 | M19: =M18+K19-L19 -> 143119.81
A20: 17 | B20: 46070 | E20: 92.87 | F20: 91.49 | G20: =E20*F20 -> 8496.6763 | H20: 6 | I20: 103.43 | J20: =H20*I20 -> 620.58 | K20: =G20+J20 -> 9117.2563 | L20: 0 | M20: =M19+K20-L20 -> 152237.07 | R20: 141649
A21: 18 | B21: 46071 | E21: 57 | F21: 91.49 | G21: =E21*F21 -> 5214.93 | H21: 6 | I21: 103.43 | J21: =H21*I21 -> 620.58 | K21: =G21+J21 -> 5835.51 | L21: 0 | M21: =M20+K21-L21 -> 158072.58
A22: 19 | B22: 46072 | E22: 40 | F22: 91.49 | G22: =E22*F22 -> 3659.6 | J22: =H22*I22 -> 0 | K22: =G22+J22 -> 3659.6 | L22: 0 | M22: =M21+K22-L22 -> 161732.18
A23: 20 | B23: 46073 | E23: 88 | F23: 91.49 | G23: =E23*F23 -> 8051.12 | J23: =H23*I23 -> 0 | K23: =G23+J23 -> 8051.12 | L23: 150000 | M23: =M22+K23-L23 -> 19783.297
A24: 21 | B24: 46074 | G24: =E24*F24 -> 0 | H24: 5 | I24: 103.43 | J24: =H24*I24 -> 517.15 | K24: =G24+J24 -> 517.15 | L24: 0 | M24: =M23+K24-L24 -> 20300.447
A25: 22 | B25: 46075 | E25: 30 | F25: 91.49 | G25: =E25*F25 -> 2744.7 | J25: =H25*I25 -> 0 | K25: =G25+J25 -> 2744.7 | L25: 0 | M25: =M24+K25-L25 -> 23045.147
A26: 23 | B26: 46076 | E26: 286 | F26: 91.49 | G26: =E26*F26 -> 26166.14 | H26: 6 | I26: 103.43 | J26: =H26*I26 -> 620.58 | K26: =G26+J26 -> 26786.72 | L26: 0 | M26: =M25+K26-L26 -> 49831.867
A27: 24 | B27: 46077 | E27: 85 | F27: 91.49 | G27: =E27*F27 -> 7776.65 | J27: =H27*I27 -> 0 | K27: =G27+J27 -> 7776.65 | L27: 0 | M27: =M26+K27-L27 -> 57608.517
A28: 25 | B28: 46078 | E28: 30 | F28: 91.49 | G28: =E28*F28 -> 2744.7 | J28: =H28*I28 -> 0 | K28: =G28+J28 -> 2744.7 | L28: 0 | M28: =M27+K28-L28 -> 60353.217
A29: 26 | B29: 46079 | E29: 155 | F29: 91.49 | G29: =E29*F29 -> 14180.95 | J29: =H29*I29 -> 0 | K29: =G29+J29 -> 14180.95 | L29: 0 | M29: =M28+K29-L29 -> 74534.167
A30: 27 | B30: 46080 | E30: 110 | F30: 91.49 | G30: =E30*F30 -> 10063.9 | H30: 13 | I30: 103.43 | J30: =H30*I30 -> 1344.59 | K30: =G30+J30 -> 11408.49 | L30: 0 | M30: =M29+K30-L30 -> 85942.657
A31: 28 | B31: 46081 | E31: 48.82 | F31: 91.49 | G31: =E31*F31 -> 4466.5418 | J31: =H31*I31 -> 0 | K31: =G31+J31 -> 4466.5418 | L31: 0 | M31: =M30+K31-L31 -> 90409.199 | R31: 46.61
A32: 29 | B32: 46082 | G32: =E32*F32 -> 0 | J32: =H32*I32 -> 0 | K32: =G32+J32 -> 0 | L32: 0 | M32: =M31+K32-L32 -> 90409.199 | R32: 100
A33: 30 | B33: 46083 | G33: =E33*F33 -> 0 | J33: =H33*I33 -> 0 | K33: =G33+J33 -> 0 | L33: 0 | M33: =M32+K33-L33 -> 90409.199 | R33: 35
A34: 31 | B34: 46084 | G34: =E34*F34 -> 0 | J34: =H34*I34 -> 0 | K34: =G34+J34 -> 0 | L34: 0 | M34: =M33+K34-L34 -> 90409.199
A35: 32 | B35: 46085 | G35: =E35*F35 -> 0 | J35: =H35*I35 -> 0 | K35: =G35+J35 -> 0 | L35: 0 | M35: =M34+K35-L35 -> 90409.199
H36: 0 | I36: 0 | M36: =M35+K36-L36 -> 90409.199
E37: =SUM(E4:E35) -> 2590.84 | G37: =SUM(G4:G35) -> 237035.95 | H37: =SUM(H4:H35) -> 107.73 | J37: =SUM(J4:J35) -> 11142.514 | K37: =SUM(K4:K35) -> 248178.47 | L37: =SUM(L4:L35) -> 308600
I40: =K25+L25 -> 2744.7

Sheet  Guttal-2
A1: Himagiri Petroleum
A2: S.No | B2: Date | C2: GRN No | D2: Ind No/Bill No | E2: Diesel (Lts) | F2: Price | G2: Amount | H2: Petrol (Lts) | I2: Price | J2: Amount | K2: Total amount | L2: Amount paid | M2: As on Date | N2: Remarks
D3: Opening Balance | K3: 0 | L3: 532276.88 | M3: 532276.88
A4: 1 | B4: 45689 | E4: 230 | F4: 91.78 | G4: =E4*F4 -> 21109.4 | H4: 5 | I4: 103.74 | J4: =H4*I4 -> 518.7 | K4: =G4+J4 -> 21628.1 | L4: 0 | M4: =M3+K4-L4 -> 553904.98
A5: 2 | B5: 45690 | E5: 450 | F5: 91.78 | G5: =E5*F5 -> 41301 | H5: 5 | I5: 103.74 | J5: =H5*I5 -> 518.7 | K5: =G5+J5 -> 41819.7 | L5: 553904 | M5: =M4+K5-L5 -> 41820.678
A6: 3 | B6: 45691 | E6: 150 | F6: 91.78 | G6: =E6*F6 -> 13767 | H6: 10 | I6: 103.74 | J6: =H6*I6 -> 1037.4 | K6: =G6+J6 -> 14804.4 | M6: =M5+K6-L6 -> 56625.078
A7: 4 | B7: 45692 | E7: 60 | F7: 91.78 | G7: =E7*F7 -> 5506.8 | H7: 0 | I7: 0 | J7: =H7*I7 -> 0 | K7: =G7+J7 -> 5506.8 | M7: =M6+K7-L7 -> 62131.878
A8: 5 | B8: 45693 | E8: 255 | F8: 91.78 | G8: =E8*F8 -> 23403.9 | H8: 0 | I8: 0 | J8: =H8*I8 -> 0 | K8: =G8+J8 -> 23403.9 | M8: =M7+K8-L8 -> 85535.778
A9: 6 | B9: 45694 | E9: 428 | F9: 91.78 | G9: =E9*F9 -> 39281.84 | H9: 15 | I9: 103.74 | J9: =H9*I9 -> 1556.1 | K9: =G9+J9 -> 40837.94 | M9: =M8+K9-L9 -> 126373.72
A10: 7 | B10: 45695 | E10: 330 | F10: 91.78 | G10: =E10*F10 -> 30287.4 | H10: 5 | I10: 103.74 | J10: =H10*I10 -> 518.7 | K10: =G10+J10 -> 30806.1 | M10: =M9+K10-L10 -> 157179.82
A11: 8 | B11: 45696 | E11: 50 | F11: 91.78 | G11: =E11*F11 -> 4589 | H11: 0 | I11: 0 | J11: =H11*I11 -> 0 | K11: =G11+J11 -> 4589 | M11: =M10+K11-L11 -> 161768.82
A12: 9 | B12: 45697 | E12: 200 | F12: 91.78 | G12: =E12*F12 -> 18356 | H12: 5 | I12: 103.74 | J12: =H12*I12 -> 518.7 | K12: =G12+J12 -> 18874.7 | M12: =M11+K12-L12 -> 180643.52 | O12: .
A13: 10 | B13: 45698 | E13: 206 | F13: 91.78 | G13: =E13*F13 -> 18906.68 | H13: 0 | I13: 0 | J13: =H13*I13 -> 0 | K13: =G13+J13 -> 18906.68 | M13: =M12+K13-L13 -> 199550.2
A14: 11 | B14: 45699 | E14: 50 | F14: 91.78 | G14: =E14*F14 -> 4589 | H14: 15 | I14: 103.74 | J14: =H14*I14 -> 1556.1 | K14: =G14+J14 -> 6145.1 | M14: =M13+K14-L14 -> 205695.3
A15: 12 | B15: 45700 | E15: 0 | F15: 0 | G15: =E15*F15 -> 0 | H15: 5 | I15: 103.74 | J15: =H15*I15 -> 518.7 | K15: =G15+J15 -> 518.7 | M15: =M14+K15-L15 -> 206214
A16: 13 | B16: 45701 | E16: 188 | F16: 91.78 | G16: =E16*F16 -> 17254.64 | H16: 5 | I16: 103.74 | J16: =H16*I16 -> 518.7 | K16: =G16+J16 -> 17773.34 | M16: =M15+K16-L16 -> 223987.34
A17: 14 | B17: 45702 | E17: 175 | F17: 91.78 | G17: =E17*F17 -> 16061.5 | H17: 0 | I17: 0 | J17: =H17*I17 -> 0 | K17: =G17+J17 -> 16061.5 | M17: =M16+K17-L17 -> 240048.84
A18: 15 | B18: 45703 | E18: 350 | F18: 91.78 | G18: =E18*F18 -> 32123 | H18: 0 | I18: 0 | J18: =H18*I18 -> 0 | K18: =G18+J18 -> 32123 | M18: =M17+K18-L18 -> 272171.84
A19: 16 | B19: 45704 | E19: 188.6 | F19: 91.78 | G19: =E19*F19 -> 17309.708 | H19: 15 | I19: 103.74 | J19: =H19*I19 -> 1556.1 | K19: =G19+J19 -> 18865.808 | M19: =M18+K19-L19 -> 291037.65
A20: 17 | B20: 45705 | E20: 200 | F20: 91.78 | G20: =E20*F20 -> 18356 | H20: 5 | I20: 103.74 | J20: =H20*I20 -> 518.7 | K20: =G20+J20 -> 18874.7 | M20: =M19+K20-L20 -> 309912.35
A21: 18 | B21: 45706 | E21: 220 | F21: 91.78 | G21: =E21*F21 -> 20191.6 | H21: 5 | I21: 103.74 | J21: =H21*I21 -> 518.7 | K21: =G21+J21 -> 20710.3 | M21: =M20+K21-L21 -> 330622.65
A22: 19 | B22: 45707 | E22: 190 | F22: 91.78 | G22: =E22*F22 -> 17438.2 | H22: 5 | I22: 103.74 | J22: =H22*I22 -> 518.7 | K22: =G22+J22 -> 17956.9 | M22: =M21+K22-L22 -> 348579.55
A23: 20 | B23: 45708 | E23: 160 | F23: 91.78 | G23: =E23*F23 -> 14684.8 | H23: 5 | I23: 103.74 | J23: =H23*I23 -> 518.7 | K23: =G23+J23 -> 15203.5 | L23: 217000 | M23: =M22+K23-L23 -> 146783.05
A24: 21 | B24: 45709 | E24: 100 | F24: 91.78 | G24: =E24*F24 -> 9178 | H24: 0 | I24: 0 | J24: =H24*I24 -> 0 | K24: =G24+J24 -> 9178 | M24: =M23+K24-L24 -> 155961.05
A25: 22 | B25: 45710 | E25: 240 | F25: 91.78 | G25: =E25*F25 -> 22027.2 | H25: 0 | I25: 0 | J25: =H25*I25 -> 0 | K25: =G25+J25 -> 22027.2 | M25: =M24+K25-L25 -> 177988.25
A26: 23 | B26: 45711 | E26: 225 | F26: 91.78 | G26: =E26*F26 -> 20650.5 | H26: 15 | I26: 103.74 | J26: =H26*I26 -> 1556.1 | K26: =G26+J26 -> 22206.6 | M26: =M25+K26-L26 -> 200194.85
A27: 24 | B27: 45712 | E27: 240 | F27: 91.78 | G27: =E27*F27 -> 22027.2 | H27: 15 | I27: 103.74 | J27: =H27*I27 -> 1556.1 | K27: =G27+J27 -> 23583.3 | M27: =M26+K27-L27 -> 223778.15
A28: 25 | B28: 45713 | E28: 255 | F28: 91.78 | G28: =E28*F28 -> 23403.9 | H28: 0 | I28: 0 | J28: =H28*I28 -> 0 | K28: =G28+J28 -> 23403.9 | M28: =M27+K28-L28 -> 247182.05
A29: 26 | B29: 45714 | E29: 270 | F29: 91.78 | G29: =E29*F29 -> 24780.6 | H29: 10 | I29: 103.74 | J29: =H29*I29 -> 1037.4 | K29: =G29+J29 -> 25818 | L29: 200000 | M29: =M28+K29-L29 -> 73000.046 | Q29: 30
A30: 27 | B30: 45715 | E30: 200 | F30: 91.78 | G30: =E30*F30 -> 18356 | H30: 15 | I30: 103.74 | J30: =H30*I30 -> 1556.1 | K30: =G30+J30 -> 19912.1 | M30: =M29+K30-L30 -> 92912.146 | Q30: 20.02
A31: 28 | B31: 45716 | E31: 280 | F31: 91.78 | G31: =E31*F31 -> 25698.4 | H31: 0 | I31: 0 | J31: =H31*I31 -> 0 | K31: =G31+J31 -> 25698.4 | M31: =M30+K31-L31 -> 118610.55
A32: 29 | B32: 45717 | E32: 0 | F32: 0 | G32: =E32*F32 -> 0 | H32: 0 | I32: 0 | J32: =H32*I32 -> 0 | K32: =G32+J32 -> 0 | M32: =M31+K32-L32 -> 118610.55
A33: 30 | B33: 45718 | E33: 0 | F33: 0 | G33: =E33*F33 -> 0 | H33: 0 | I33: 0 | J33: =H33*I33 -> 0 | K33: =G33+J33 -> 0 | M33: =M32+K33-L33 -> 118610.55
A34: 31 | B34: 45719 | E34: 0 | F34: 0 | G34: =E34*F34 -> 0 | H34: 0 | I34: 0 | J34: =H34*I34 -> 0 | K34: =G34+J34 -> 0 | L34: 0 | M34: =M33+K34-L34 -> 118610.55
E35: =SUM(E4:E34) -> 5890.6 | G35: =SUM(G4:G34) -> 540639.27 | H35: =SUM(H4:H34) -> 160 | J35: =SUM(J4:J34) -> 16598.4 | K35: =SUM(K4:K34) -> 557237.67 | L35: =SUM(L4:L34) -> 970904
I38: =K24+L24 -> 9178

Sheet Rattihali
A1: Shree Siri Gowari petroliam
A2: S.No | B2: Date | C2: GRN No | D2: Ind No/Bill No | E2: Diesel (Lts) | F2: Price | G2: Amount | H2: Petrol (Lts) | I2: Price | J2: Amount | K2: Total amount | L2: Amount paid | M2: As on Date | N2: Remarks
D3: Opening Balance | K3: 6442.724 | M3: 6442.724
A4: 1 | B4: 46054 | F4: 0 | G4: =E4*F4 -> 0 | H4: 0 | I4: 0 | J4: =H4*I4 -> 0 | K4: =G4+J4 -> 0 | L4: 0 | M4: =M3+K4-L4 -> 6442.724
A5: 2 | B5: 46055 | F5: 0 | G5: =E5*F5 -> 0 | H5: 0 | I5: 0 | J5: =H5*I5 -> 0 | K5: =G5+J5 -> 0 | L5: 0 | M5: =M4+K5-L5 -> 6442.724
A6: 3 | B6: 46056 | F6: 0 | G6: =E6*F6 -> 0 | H6: 0 | I6: 0 | J6: =H6*I6 -> 0 | K6: =G6+J6 -> 0 | L6: 0 | M6: =M5+K6-L6 -> 6442.724
A7: 4 | B7: 46057 | F7: 0 | G7: =E7*F7 -> 0 | H7: 0 | I7: 0 | J7: =H7*I7 -> 0 | K7: =G7+J7 -> 0 | L7: 0 | M7: =M6+K7-L7 -> 6442.724
A8: 5 | B8: 46058 | F8: 0 | G8: =E8*F8 -> 0 | H8: 0 | I8: 0 | J8: =H8*I8 -> 0 | K8: =G8+J8 -> 0 | L8: 0 | M8: =M7+K8-L8 -> 6442.724
A9: 6 | B9: 46059 | F9: 0 | G9: =E9*F9 -> 0 | H9: 0 | I9: 0 | J9: =H9*I9 -> 0 | K9: =G9+J9 -> 0 | L9: 0 | M9: =M8+K9-L9 -> 6442.724
A10: 7 | B10: 46060 | F10: 0 | G10: =E10*F10 -> 0 | H10: 0 | I10: 0 | J10: =H10*I10 -> 0 | K10: =G10+J10 -> 0 | L10: 0 | M10: =M9+K10-L10 -> 6442.724
A11: 8 | B11: 46061 | F11: 0 | G11: =E11*F11 -> 0 | H11: 0 | I11: 0 | J11: =H11*I11 -> 0 | K11: =G11+J11 -> 0 | L11: 0 | M11: =M10+K11-L11 -> 6442.724
A12: 9 | B12: 46062 | F12: 0 | G12: =E12*F12 -> 0 | H12: 0 | I12: 0 | J12: =H12*I12 -> 0 | K12: =G12+J12 -> 0 | L12: 0 | M12: =M11+K12-L12 -> 6442.724 | O12: .
A13: 10 | B13: 46063 | F13: 0 | G13: =E13*F13 -> 0 | H13: 0 | I13: 0 | J13: =H13*I13 -> 0 | K13: =G13+J13 -> 0 | L13: 0 | M13: =M12+K13-L13 -> 6442.724
A14: 11 | B14: 46064 | F14: 0 | G14: =E14*F14 -> 0 | H14: 0 | I14: 0 | J14: =H14*I14 -> 0 | K14: =G14+J14 -> 0 | L14: 0 | M14: =M13+K14-L14 -> 6442.724
A15: 12 | B15: 46065 | F15: 0 | G15: =E15*F15 -> 0 | H15: 0 | I15: 0 | J15: =H15*I15 -> 0 | K15: =G15+J15 -> 0 | L15: 0 | M15: =M14+K15-L15 -> 6442.724
A16: 13 | B16: 46066 | F16: 0 | G16: =E16*F16 -> 0 | H16: 0 | I16: 0 | J16: =H16*I16 -> 0 | K16: =G16+J16 -> 0 | L16: 0 | M16: =M15+K16-L16 -> 6442.724
A17: 14 | B17: 46067 | F17: 0 | G17: =E17*F17 -> 0 | H17: 0 | I17: 0 | J17: =H17*I17 -> 0 | K17: =G17+J17 -> 0 | L17: 0 | M17: =M16+K17-L17 -> 6442.724
A18: 15 | B18: 46068 | F18: 0 | G18: =E18*F18 -> 0 | H18: 0 | I18: 0 | J18: =H18*I18 -> 0 | K18: =G18+J18 -> 0 | L18: 0 | M18: =M17+K18-L18 -> 6442.724
A19: 16 | B19: 46069 | F19: 0 | G19: =E19*F19 -> 0 | H19: 0 | I19: 0 | J19: =H19*I19 -> 0 | K19: =G19+J19 -> 0 | L19: 0 | M19: =M18+K19-L19 -> 6442.724
A20: 17 | B20: 46070 | F20: 0 | G20: =E20*F20 -> 0 | H20: 0 | I20: 0 | J20: =H20*I20 -> 0 | K20: =G20+J20 -> 0 | L20: 0 | M20: =M19+K20-L20 -> 6442.724
A21: 18 | B21: 46071 | F21: 0 | G21: =E21*F21 -> 0 | H21: 0 | I21: 0 | J21: =H21*I21 -> 0 | K21: =G21+J21 -> 0 | L21: 0 | M21: =M20+K21-L21 -> 6442.724
A22: 19 | B22: 46072 | G22: =E22*F22 -> 0 | H22: 0 | I22: 0 | J22: =H22*I22 -> 0 | K22: =G22+J22 -> 0 | L22: 0 | M22: =M21+K22-L22 -> 6442.724
A23: 20 | B23: 46073 | G23: =E23*F23 -> 0 | H23: 0 | I23: 0 | J23: =H23*I23 -> 0 | K23: =G23+J23 -> 0 | L23: 0 | M23: =M22+K23-L23 -> 6442.724
A24: 21 | B24: 46074 | G24: =E24*F24 -> 0 | H24: 0 | I24: 0 | J24: =H24*I24 -> 0 | K24: =G24+J24 -> 0 | L24: 0 | M24: =M23+K24-L24 -> 6442.724
A25: 22 | B25: 46075 | G25: =E25*F25 -> 0 | H25: 0 | I25: 0 | J25: =H25*I25 -> 0 | K25: =G25+J25 -> 0 | L25: 0 | M25: =M24+K25-L25 -> 6442.724
A26: 23 | B26: 46076 | G26: =E26*F26 -> 0 | H26: 0 | I26: 0 | J26: =H26*I26 -> 0 | K26: =G26+J26 -> 0 | L26: 0 | M26: =M25+K26-L26 -> 6442.724
A27: 24 | B27: 46077 | G27: =E27*F27 -> 0 | H27: 0 | I27: 0 | J27: =H27*I27 -> 0 | K27: =G27+J27 -> 0 | L27: 0 | M27: =M26+K27-L27 -> 6442.724
A28: 25 | B28: 46078 | G28: =E28*F28 -> 0 | H28: 0 | I28: 0 | J28: =H28*I28 -> 0 | K28: =G28+J28 -> 0 | L28: 0 | M28: =M27+K28-L28 -> 6442.724
A29: 26 | B29: 46079 | G29: =E29*F29 -> 0 | H29: 0 | I29: 0 | J29: =H29*I29 -> 0 | K29: =G29+J29 -> 0 | L29: 0 | M29: =M28+K29-L29 -> 6442.724
A30: 27 | B30: 46080 | G30: =E30*F30 -> 0 | H30: 0 | I30: 0 | J30: =H30*I30 -> 0 | K30: =G30+J30 -> 0 | L30: 0 | M30: =M29+K30-L30 -> 6442.724
A31: 28 | B31: 46081 | G31: =E31*F31 -> 0 | H31: 0 | I31: 0 | J31: =H31*I31 -> 0 | K31: =G31+J31 -> 0 | L31: 0 | M31: =M30+K31-L31 -> 6442.724
A32: 29 | B32: 46082 | G32: =E32*F32 -> 0 | H32: 0 | I32: 0 | J32: =H32*I32 -> 0 | K32: =G32+J32 -> 0 | L32: 0 | M32: =M31+K32-L32 -> 6442.724
A33: 30 | B33: 46083 | G33: =E33*F33 -> 0 | H33: 0 | I33: 0 | J33: =H33*I33 -> 0 | K33: =G33+J33 -> 0 | L33: 0 | M33: =M32+K33-L33 -> 6442.724 | Q33: 30
A34: 31 | E34: 0 | F34: 0 | G34: =E34*F34 -> 0 | H34: 0 | I34: 0 | J34: =H34*I34 -> 0 | K34: =G34+J34 -> 0 | L34: =+K34 -> 0 | M34: =M33+K34-L34 -> 6442.724
E35: =SUM(E4:E34) -> 0 | G35: =SUM(G4:G34) -> 0 | H35: =SUM(H4:H34) -> 0 | J35: =SUM(J4:J34) -> 0 | K35: =SUM(K4:K34) -> 0 | L35: =SUM(L4:L34) -> 0
I38: =K24+L24 -> 0

Sheet Rattihali-2
A1: Shiva Oil Traders
A2: S.No | B2: Date | C2: GRN No | D2: Ind No/Bill No | E2: Diesel (Lts) | F2: Price | G2: Amount | H2: Petrol (Lts) | I2: Price | J2: Amount | K2: Total amount | L2: Amount paid | M2: As on Date | N2: Remarks
D3: Opening Balance | L3: 162379.88 | M3: 162379.88
A4: 1 | B4: 46054 | E4: 50 | F4: 91.89 | G4: =E4*F4 -> 4594.5 | H4: 0 | I4: 0 | J4: =H4*I4 -> 0 | K4: =G4+J4 -> 4594.5 | L4: 0 | M4: =M3+K4-L4 -> 166974.38
A5: 2 | B5: 46055 | E5: 100 | F5: 91.89 | G5: =E5*F5 -> 9189 | H5: 10 | I5: 103.85 | J5: =H5*I5 -> 1038.5 | K5: =G5+J5 -> 10227.5 | L5: 166900 | M5: =M4+K5-L5 -> 10301.877
A6: 3 | B6: 46055 | G6: =E6*F6 -> 0 | H6: 10 | I6: 111.62 | J6: =H6*I6 -> 1116.2 | K6: =G6+J6 -> 1116.2 | L6: 0 | M6: =M5+K6-L6 -> 11418.077
A7: 4 | B7: 46056 | E7: 447 | F7: 91.89 | G7: =E7*F7 -> 41074.83 | H7: 0 | I7: 0 | J7: =H7*I7 -> 0 | K7: =G7+J7 -> 41074.83 | L7: 0 | M7: =M6+K7-L7 -> 52492.907
A8: 5 | B8: 46057 | E8: 85 | F8: 91.89 | G8: =E8*F8 -> 7810.65 | H8: 0 | I8: 0 | J8: =H8*I8 -> 0 | K8: =G8+J8 -> 7810.65 | L8: 0 | M8: =M7+K8-L8 -> 60303.557
A9: 6 | B9: 46058 | E9: 120 | F9: 91.89 | G9: =E9*F9 -> 11026.8 | H9: 6 | I9: 103.85 | J9: =H9*I9 -> 623.1 | K9: =G9+J9 -> 11649.9 | L9: 0 | M9: =M8+K9-L9 -> 71953.457
A10: 7 | B10: 46059 | E10: 395.01 | F10: 91.89 | G10: =E10*F10 -> 36297.469 | H10: 0 | I10: 0 | J10: =H10*I10 -> 0 | K10: =G10+J10 -> 36297.469 | L10: 0 | M10: =M9+K10-L10 -> 108250.93
A11: 8 | B11: 46060 | E11: 100 | F11: 91.89 | G11: =E11*F11 -> 9189 | H11: 0 | I11: 0 | J11: =H11*I11 -> 0 | K11: =G11+J11 -> 9189 | L11: 0 | M11: =M10+K11-L11 -> 117439.93
A12: 9 | B12: 46061 | E12: 220 | F12: 91.89 | G12: =E12*F12 -> 20215.8 | H12: 0 | I12: 0 | J12: =H12*I12 -> 0 | K12: =G12+J12 -> 20215.8 | L12: 0 | M12: =M11+K12-L12 -> 137655.73 | O12: .
A13: 10 | B13: 46062 | E13: 35 | F13: 91.89 | G13: =E13*F13 -> 3216.15 | H13: 5 | I13: 103.85 | J13: =H13*I13 -> 519.25 | K13: =G13+J13 -> 3735.4 | L13: 0 | M13: =M12+K13-L13 -> 141391.13
A14: 11 | B14: 46063 | E14: 142 | F14: 91.89 | G14: =E14*F14 -> 13048.38 | H14: 5 | I14: 103.85 | J14: =H14*I14 -> 519.25 | K14: =G14+J14 -> 13567.63 | L14: 0 | M14: =M13+K14-L14 -> 154958.76
A15: 12 | B15: 46064 | E15: 185 | F15: 91.89 | G15: =E15*F15 -> 16999.65 | H15: 6 | I15: 103.85 | J15: =H15*I15 -> 623.1 | K15: =G15+J15 -> 17622.75 | L15: 0 | M15: =M14+K15-L15 -> 172581.51
A16: 13 | B16: 46065 | E16: 85 | F16: 91.89 | G16: =E16*F16 -> 7810.65 | H16: 0 | I16: 0 | J16: =H16*I16 -> 0 | K16: =G16+J16 -> 7810.65 | L16: 0 | M16: =M15+K16-L16 -> 180392.16
A17: 14 | B17: 46067 | E17: 285 | F17: 91.89 | G17: =E17*F17 -> 26188.65 | H17: 15 | I17: 103.85 | J17: =H17*I17 -> 1557.75 | K17: =G17+J17 -> 27746.4 | L17: 0 | M17: =M16+K17-L17 -> 208138.56
A18: 15 | B18: 46068 | G18: =E18*F18 -> 0 | H18: 0 | I18: 0 | J18: =H18*I18 -> 0 | K18: =G18+J18 -> 0 | L18: 0 | M18: =M17+K18-L18 -> 208138.56
A19: 16 | B19: 46069 | E19: 317 | F19: 91.89 | G19: =E19*F19 -> 29129.13 | H19: 16 | I19: 103.85 | J19: =H19*I19 -> 1661.6 | K19: =G19+J19 -> 30790.73 | L19: 0 | M19: =M18+K19-L19 -> 238929.29
A20: 17 | B20: 46070 | E20: 35 | F20: 91.89 | G20: =E20*F20 -> 3216.15 | H20: 0 | I20: 103.85 | J20: =H20*I20 -> 0 | K20: =G20+J20 -> 3216.15 | L20: 0 | M20: =M19+K20-L20 -> 242145.44
A21: 18 | B21: 46071 | E21: 210 | F21: 91.89 | G21: =E21*F21 -> 19296.9 | H21: 5 | I21: 103.85 | J21: =H21*I21 -> 519.25 | K21: =G21+J21 -> 19816.15 | L21: 0 | M21: =M20+K21-L21 -> 261961.59
A22: 19 | B22: 46072 | G22: =E22*F22 -> 0 | H22: 0 | I22: 103.85 | J22: =H22*I22 -> 0 | K22: =G22+J22 -> 0 | L22: 200000 | M22: =M21+K22-L22 -> 61961.585
A23: 20 | B23: 46073 | G23: =E23*F23 -> 0 | H23: 15 | I23: 103.85 | J23: =H23*I23 -> 1557.75 | K23: =G23+J23 -> 1557.75 | L23: 0 | M23: =M22+K23-L23 -> 63519.335
A24: 21 | B24: 46074 | G24: =E24*F24 -> 0 | H24: 5 | I24: 103.85 | J24: =H24*I24 -> 519.25 | K24: =G24+J24 -> 519.25 | L24: 0 | M24: =M23+K24-L24 -> 64038.585
A25: 22 | B25: 46075 | G25: =E25*F25 -> 0 | H25: 5 | I25: 103.85 | J25: =H25*I25 -> 519.25 | K25: =G25+J25 -> 519.25 | L25: 0 | M25: =M24+K25-L25 -> 64557.835
A26: 23 | B26: 46076 | E26: 135.1 | F26: 91.89 | G26: =E26*F26 -> 12414.339 | H26: 0 | I26: 0 | J26: =H26*I26 -> 0 | K26: =G26+J26 -> 12414.339 | L26: 0 | M26: =M25+K26-L26 -> 76972.174
A27: 24 | B27: 46077 | E27: 100 | F27: 91.89 | G27: =E27*F27 -> 9189 | H27: 5 | I27: 103.85 | J27: =H27*I27 -> 519.25 | K27: =G27+J27 -> 9708.25 | L27: 0 | M27: =M26+K27-L27 -> 86680.424
A28: 25 | B28: 46078 | G28: =E28*F28 -> 0 | H28: 0 | I28: 103.85 | J28: =H28*I28 -> 0 | K28: =G28+J28 -> 0 | L28: 0 | M28: =M27+K28-L28 -> 86680.424
A29: 26 | B29: 46079 | E29: 70 | F29: 91.89 | G29: =E29*F29 -> 6432.3 | H29: 11 | I29: 103.85 | J29: =H29*I29 -> 1142.35 | K29: =G29+J29 -> 7574.65 | L29: 0 | M29: =M28+K29-L29 -> 94255.074
A30: 27 | B30: 46080 | E30: 390 | F30: 91.89 | G30: =E30*F30 -> 35837.1 | H30: 5 | I30: 103.85 | J30: =H30*I30 -> 519.25 | K30: =G30+J30 -> 36356.35 | L30: 0 | M30: =M29+K30-L30 -> 130611.42
A31: 28 | B31: 46081 | E31: 200 | F31: 91.89 | G31: =E31*F31 -> 18378 | H31: 5 | I31: 103.85 | J31: =H31*I31 -> 519.25 | K31: =G31+J31 -> 18897.25 | L31: 0 | M31: =M30+K31-L31 -> 149508.67 | R31: 46.61
A32: 29 | B32: 46082 | G32: =E32*F32 -> 0 | H32: 0 | I32: 0 | J32: =H32*I32 -> 0 | K32: =G32+J32 -> 0 | L32: 0 | M32: =M31+K32-L32 -> 149508.67 | R32: 100
A33: 30 | B33: 46083 | G33: =E33*F33 -> 0 | H33: 0 | I33: 0 | J33: =H33*I33 -> 0 | K33: =G33+J33 -> 0 | L33: 0 | M33: =M32+K33-L33 -> 149508.67 | R33: 35
A34: 31 | B34: 46084 | G34: =E34*F34 -> 0 | H34: 0 | I34: 0 | J34: =H34*I34 -> 0 | K34: =G34+J34 -> 0 | L34: 0 | M34: =M33+K34-L34 -> 149508.67
A35: 32 | B35: 46085 | G35: =E35*F35 -> 0 | H35: 0 | I35: 0 | J35: =H35*I35 -> 0 | K35: =G35+J35 -> 0 | L35: 0 | M35: =M34+K35-L35 -> 149508.67
H36: 0 | I36: 0 | M36: =M35+K36-L36 -> 149508.67
E37: =SUM(E4:E35) -> 3706.11 | G37: =SUM(G4:G35) -> 340554.45 | H37: =SUM(H4:H35) -> 129 | J37: =SUM(J4:J35) -> 13474.35 | K37: =SUM(K4:K35) -> 354028.8 | L37: =SUM(L4:L35) -> 366900
I40: =K25+L25 -> 519.25

Sheet Gajendragada
A1: Vanasri Petrol Pump
A2: S.No | B2: Date | C2: GRN No | D2: Ind no/Bill No | E2: Diesel (Lts) | F2: Price | G2: Amount | H2: Petrol (Lts) | I2: Price | J2: Amount | K2: Total amount | L2: Amount paid | M2: As on Date | N2: Remarks
A3: Opening Balance | K3: 10249.402 | M3: 10249.402
A4: 1 | B4: 46054 | E4: 0 | F4: 0 | G4: =E4*F4 -> 0 | H4: 0 | I4: 103.8 | J4: =H4*I4 -> 0 | K4: =G4+J4 -> 0 | M4: =M3+K4-L4 -> 10249.402
A5: 2 | B5: 46055 | E5: 0 | F5: 0 | G5: =E5*F5 -> 0 | H5: 5 | I5: 103.8 | J5: =H5*I5 -> 519 | K5: =G5+J5 -> 519 | L5: 10288.04 | M5: =M4+K5-L5 -> 480.3615
A6: 3 | B6: 46056 | E6: 0 | F6: 0 | G6: =E6*F6 -> 0 | H6: 0 | I6: 0 | J6: =H6*I6 -> 0 | K6: =G6+J6 -> 0 | M6: =M5+K6-L6 -> 480.3615
A7: 4 | B7: 46057 | E7: 130 | F7: 91.83 | G7: =E7*F7 -> 11937.9 | H7: 0 | I7: 0 | J7: =H7*I7 -> 0 | K7: =G7+J7 -> 11937.9 | M7: =M6+K7-L7 -> 12418.262
A8: 5 | B8: 46058 | E8: 50 | F8: 91.83 | G8: =E8*F8 -> 4591.5 | H8: 5 | I8: 103.8 | J8: =H8*I8 -> 519 | K8: =G8+J8 -> 5110.5 | M8: =M7+K8-L8 -> 17528.762 | O8: 8497892194 | P8: raja bhakshi
A9: 6 | B9: 46059 | E9: 0 | F9: 0 | G9: =E9*F9 -> 0 | H9: 10 | I9: 103.8 | J9: =H9*I9 -> 1038 | K9: =G9+J9 -> 1038 | M9: =M8+K9-L9 -> 18566.762
A10: 7 | B10: 46060 | E10: 0 | F10: 0 | G10: =E10*F10 -> 0 | H10: 5 | I10: 103.8 | J10: =H10*I10 -> 519 | K10: =G10+J10 -> 519 | M10: =M9+K10-L10 -> 19085.762
A11: 8 | B11: 46061 | E11: 80 | F11: 91.83 | G11: =E11*F11 -> 7346.4 | H11: 0 | I11: 0 | J11: =H11*I11 -> 0 | K11: =G11+J11 -> 7346.4 | M11: =M10+K11-L11 -> 26432.162
A12: 9 | B12: 46062 | E12: 30 | F12: 91.83 | G12: =E12*F12 -> 2754.9 | H12: 0 | I12: 0 | J12: =H12*I12 -> 0 | K12: =G12+J12 -> 2754.9 | M12: =M11+K12-L12 -> 29187.062
A13: 10 | B13: 46063 | E13: 30 | F13: 91.83 | G13: =E13*F13 -> 2754.9 | H13: 10 | I13: 103.8 | J13: =H13*I13 -> 1038 | K13: =G13+J13 -> 3792.9 | M13: =M12+K13-L13 -> 32979.962
A14: 11 | B14: 46064 | E14: 0 | F14: 0 | G14: =E14*F14 -> 0 | H14: 0 | I14: 0 | J14: =H14*I14 -> 0 | K14: =G14+J14 -> 0 | M14: =M13+K14-L14 -> 32979.962
A15: 12 | B15: 46065 | E15: 98 | F15: 91.83 | G15: =E15*F15 -> 8999.34 | H15: 10 | I15: 103.8 | J15: =H15*I15 -> 1038 | K15: =G15+J15 -> 10037.34 | M15: =M14+K15-L15 -> 43017.302
A16: 13 | B16: 46066 | E16: 100 | F16: 91.83 | G16: =E16*F16 -> 9183 | H16: 0 | I16: 0 | J16: =H16*I16 -> 0 | K16: =G16+J16 -> 9183 | M16: =M15+K16-L16 -> 52200.302
A17: 14 | B17: 46067 | E17: 0 | F17: 0 | G17: =E17*F17 -> 0 | H17: 5 | I17: 103.8 | J17: =H17*I17 -> 519 | K17: =G17+J17 -> 519 | M17: =M16+K17-L17 -> 52719.302
A18: 15 | B18: 46068 | E18: 0 | F18: 0 | G18: =E18*F18 -> 0 | H18: 0 | I18: 0 | J18: =H18*I18 -> 0 | K18: =G18+J18 -> 0 | M18: =M17+K18-L18 -> 52719.302
A19: 16 | B19: 46069 | E19: 50 | F19: 91.83 | G19: =E19*F19 -> 4591.5 | H19: 5 | I19: 103.8 | J19: =H19*I19 -> 519 | K19: =G19+J19 -> 5110.5 | M19: =M18+K19-L19 -> 57829.802
A20: 17 | B20: 46070 | E20: 90 | F20: 91.83 | G20: =E20*F20 -> 8264.7 | H20: 10 | I20: 103.8 | J20: =H20*I20 -> 1038 | K20: =G20+J20 -> 9302.7 | M20: =M19+K20-L20 -> 67132.502
... A26: 23 | B26: 46076 | E26: 100 | F26: 91.83 | G26: =E26*F26 -> 9183 | H26: 0 | I26: 0 | J26: =H26*I26 -> 0 | K26: =G26+J26 -> 9183 | M26: =M25+K26-L26 -> 98993.402
A27: 24 | B27: 46077 | E27: 30 | F27: 91.83 | G27: =E27*F27 -> 2754.9 | H27: 15 | I27: 103.8 | J27: =H27*I27 -> 1557 | K27: =G27+J27 -> 4311.9 | M27: =M26+K27-L27 -> 103305.3 | R27: 66742
A28: 25 | B28: 46078 | E28: 0 | F28: 0 | G28: =E28*F28 -> 0 | H28: 10 | I28: 103.8 | J28: =H28*I28 -> 1038 | K28: =G28+J28 -> 1038 | M28: =M27+K28-L28 -> 104343.3
A29: 26 | B29: 46079 | E29: 210 | F29: 91.83 | G29: =E29*F29 -> 19284.3 | H29: 5 | I29: 103.8 | J29: =H29*I29 -> 519 | K29: =G29+J29 -> 19803.3 | M29: =M28+K29-L29 -> 124146.6
A30: 27 | B30: 46080 | E30: 10 | F30: 91.83 | G30: =E30*F30 -> 918.3 | H30: 10 | I30: 103.8 | J30: =H30*I30 -> 1038 | K30: =G30+J30 -> 1956.3 | M30: =M29+K30-L30 -> 126102.9
A31: 28 | B31: 46081 | E31: 0 | F31: 0 | G31: =E31*F31 -> 0 | H31: 0 | I31: 0 | J31: =H31*I31 -> 0 | K31: =G31+J31 -> 0 | M31: =M30+K31-L31 -> 126102.9
A32: 29 | B32: 46082 | E32: 0 | F32: 0 | G32: =E32*F32 -> 0 | H32: 0 | I32: 0 | J32: =H32*I32 -> 0 | K32: =G32+J32 -> 0 | M32: =M31+K32-L32 -> 126102.9
A33: 30 | B33: 46083 | E33: 0 | F33: 0 | G33: =E33*F33 -> 0 | H33: 0 | I33: 0 | J33: =H33*I33 -> 0 | K33: =G33+J33 -> 0 | M33: =M32+K33-L33 -> 126102.9
A34: 31 | B34: 46084 | E34: 0 | F34: 0 | G34: =E34*F34 -> 0 | H34: 0 | I34: 0 | J34: =H34*I34 -> 0 | K34: =G34+J34 -> 0 | M34: =M33+K34-L34 -> 126102.9
E35: =SUM(E4:E34) -> 1238 | G35: =SUM(G4:G34) -> 113685.54 | H35: =SUM(H4:H34) -> 120 | J35: =SUM(J4:J34) -> 12456 | K35: =SUM(K4:K34) -> 126141.54 | L35: =SUM(L4:L34) -> 10288.04

Sheet Gokak Dharwad PKG 3
A1: AJ Petrolinks
A2: S.No | B2: Date | C2: GRN No | D2: Ind No/Bill No | E2: Diesel (Lts) | F2: Price | G2: Amount | H2: Petrol (Lts) | I2: Price | J2: Amount | K2: Total amount | L2: Amount paid | M2: As on Date | N2: Remarks
D3: Opening Balance | K3: 437987.29 | M3: 437987.29 | N3: 0 | O3: 0 | P3: 0
A4: 1 | B4: 46054 | G4: =E4*F4 -> 0 | J4: =H4*I4 -> 0 | K4: =G4+J4 -> 0 | M4: =M3+K4-L4 -> 437987.29
A5: 2 | B5: 46055 | E5: 110.66 | F5: 91.48 | G5: =E5*F5 -> 10123.177 | H5: 27 | I5: 103.41 | J5: =H5*I5 -> 2792.07 | K5: =G5+J5 -> 12915.247 | L5: 438028 | M5: =M4+K5-L5 -> 12874.539 | Q5: 437979
A6: 3 | B6: 46056 | E6: 420.29 | F6: 91.48 | G6: =E6*F6 -> 38448.129 | H6: 35 | I6: 103.41 | J6: =H6*I6 -> 3619.35 | K6: =G6+J6 -> 42067.479 | M6: =M5+K6-L6 -> 54942.018
A7: 4 | B7: 46057 | E7: 458.6 | F7: 91.48 | G7: =E7*F7 -> 41952.728 | H7: 12 | I7: 103.41 | J7: =H7*I7 -> 1240.92 | K7: =G7+J7 -> 43193.648 | M7: =M6+K7-L7 -> 98135.666
A8: 5 | B8: 46058 | E8: 232.73 | F8: 91.48 | G8: =E8*F8 -> 21290.14 | H8: 6 | I8: 103.41 | J8: =H8*I8 -> 620.46 | K8: =G8+J8 -> 21910.6 | M8: =M7+K8-L8 -> 120046.27
A9: 6 | B9: 46059 | E9: 525.8 | F9: 91.48 | G9: =E9*F9 -> 48100.184 | J9: =H9*I9 -> 0 | K9: =G9+J9 -> 48100.184 | M9: =M8+K9-L9 -> 168146.45
A10: 7 | B10: 46060 | E10: 158.55 | F10: 91.48 | G10: =E10*F10 -> 14504.154 | H10: 26 | I10: 103.41 | J10: =H10*I10 -> 2688.66 | K10: =G10+J10 -> 17192.814 | M10: =M9+K10-L10 -> 185339.26
A11: 8 | B11: 46061 | E11: 85.96 | F11: 91.48 | G11: =E11*F11 -> 7863.6208 | J11: =H11*I11 -> 0 | K11: =G11+J11 -> 7863.6208 | M11: =M10+K11-L11 -> 193202.89
A12: 9 | B12: 46062 | E12: 1552.32 | F12: 91.48 | G12: =E12*F12 -> 142006.23 | H12: 6 | I12: 103.41 | J12: =H12*I12 -> 620.46 | K12: =G12+J12 -> 142626.69 | M12: =M11+K12-L12 -> 335829.58 | O12: 1032881 | P12: =M12-O12 -> -697051.42
A13: 10 | B13: 46063 | E13: 455.3 | F13: 91.48 | G13: =E13*F13 -> 41650.844 | J13: =H13*I13 -> 0 | K13: =G13+J13 -> 41650.844 | M13: =M12+K13-L13 -> 377480.42
A14: 11 | B14: 46064 | E14: 398.21 | F14: 91.48 | G14: =E14*F14 -> 36428.251 | J14: =H14*I14 -> 0 | K14: =G14+J14 -> 36428.251 | M14: =M13+K14-L14 -> 413908.67
A15: 12 | B15: 46065 | E15: 780.55 | F15: 91.48 | G15: =E15*F15 -> 71404.714 | H15: 20 | I15: 103.41 | J15: =H15*I15 -> 2068.2 | K15: =G15+J15 -> 73472.914 | M15: =M14+K15-L15 -> 487381.59
A16: 13 | B16: 46066 | E16: 457.75 | F16: 91.48 | G16: =E16*F16 -> 41874.97 | H16: 21 | I16: 103.41 | J16: =H16*I16 -> 2171.61 | K16: =G16+J16 -> 44046.58 | M16: =M15+K16-L16 -> 531428.17
A17: 14 | B17: 46067 | E17: 462.05 | F17: 91.48 | G17: =E17*F17 -> 42268.334 | J17: =H17*I17 -> 0 | K17: =G17+J17 -> 42268.334 | M17: =M16+K17-L17 -> 573696.5
A18: 15 | B18: 46068 | E18: 358.69 | F18: 91.48 | G18: =E18*F18 -> 32812.961 | J18: =H18*I18 -> 0 | K18: =G18+J18 -> 32812.961 | M18: =M17+K18-L18 -> 606509.46
