Workbook

Sheet  MIs
A2: S.No | B2: NAme | C2: Lacation | D2: Card Number | E2: Card Number | F2: Category | G2: 1st Jan | I2: 2nd Jan | J2: 3rd Jan | K2: 4th Jan | L2: 5th Jan | M2: 6th Jan | N2: 7th Jan | O2: 8th Jan | P2: 9th Jan | Q2: 10th Jan | R2: 11th Jan | S2: 12th Jan | T2: 13th Jan | U2: 14th Jan | V2: 15th Jan | W2: 16th Jan | X2: 17th Jan | Y2: 18th Jan | Z2: 19th Jan | AA2: 20th Jan | AB2: 21st Jan | AC2: 22nd Jan | AD2: 23rd Jan | AE2: 24th Jan | AF2: 25th Jan | AG2: 26th Jan | AH2: 27th Jan | AI2: 28th Jan | AJ2: 29th Jan | AK2: 30th Jan | AL2: 31st Jan | AM2: Total
F3: Diesel
A4: 1 | B4: Rambabu | C4: HO(Two Wheeler) | D4: FC3450563999 | E4: Diesel | F4: 0 | G4: 0 | H4: 0 | I4: 0 | J4: 0 | K4: 0 | L4: 0 | M4: 0 | N4: 0 | O4: 0 | P4: 0 | Q4: 0 | R4: 0 | S4: 0 | T4: 0 | U4: 0 | V4: 0 | W4: 0 | X4: 5.22 | Y4: 0 | Z4: 0 | AA4: 0 | AB4: 0 | AC4: 0 | AD4: 60 | AE4: 0 | AF4: 0 | AG4: 0 | AH4: 4.56 | AI4: 0 | AJ4: 0 | AK4: 0 | AL4: 0 | AM4: =SUM(F4:AL4) -> 69.78
E5: Petrol | F5: 0 | G5: 4.69 | H5: 0 | I5: 0 | J5: 0 | K5: 0 | L5: 0 | M5: 0 | N5: 3.91 | O5: 0 | P5: 6.98 | Q5: 0 | R5: 0 | S5: 0 | T5: 0 | U5: 0 | V5: 0 | W5: 0 | X5: 0 | Y5: 0 | Z5: 0 | AB5: 0 | AC5: 0 | AD5: 0 | AE5: 0 | AF5: 0 | AG5: 0 | AH5: 0 | AI5: 0 | AJ5: 0 | AK5: 0 | AL5: 0 | AM5: =SUM(F5:AL5) -> 15.58
A6: 2 | B6: Hanumanth Rao | C6: HO | D6: FC3450676131 | E6: Diesel | F6: 0 | G6: 0 | H6: 0 | I6: 0 | J6: 0 | K6: 0 | L6: 0 | M6: 0 | N6: 0 | O6: 0 | P6: 0 | Q6: 0 | R6: 0 | S6: 0 | T6: 0 | U6: 0 | V6: 0 | W6: 0 | X6: 0 | Y6: 0 | Z6: 0 | AA6: 0 | AB6: 0 | AC6: 0 | AD6: 0 | AE6: 0 | AF6: 0 | AG6: 0 | AH6: 0 | AI6: 0 | AJ6: 0 | AK6: 0 | AL6: 0 | AM6: =SUM(F6:AL6) -> 0
E7: Petrol | F7: 0 | G7: 0 | H7: 0 | I7: 0 | J7: 0 | K7: 0 | L7: 0 | M7: 0 | N7: 0 | O7: 0 | P7: 0 | Q7: 0 | R7: 0 | S7: 0 | T7: 0 | U7: 0 | V7: 0 | W7: 0 | X7: 0 | Y7: 0 | Z7: 0 | AB7: 0 | AC7: 0 | AD7: 0 | AE7: 0 | AF7: 0 | AG7: 0 | AH7: 0 | AI7: 0 | AJ7: 0 | AK7: 0 | AL7: 0 | AM7: =SUM(F7:AL7) -> 0
A8: 3 | B8: Radhakrishna | C8: HO | D8: FC8000207658 | E8: Diesel | F8: 0 | G8: 0 | H8: 0 | I8: 0 | J8: 33.44 | K8: 0 | L8: 0 | M8: 0 | N8: 0 | O8: 0 | P8: 0 | Q8: 0 | R8: 35.53 | S8: 0 | T8: 0 | U8: 0 | V8: 0 | W8: 0 | X8: 0 | Y8: 0 | Z8: 0 | AA8: 0 | AB8: 33.44 | AC8: 0 | AD8: 0 | AE8: 0 | AF8: 0 | AG8: 0 | AH8: 0 | AI8: 0 | AJ8: 0 | AK8: 0 | AL8: 0 | AM8: =SUM(F8:AL8) -> 102.41
E9: Petrol | F9: 0 | G9: 0 | H9: 0 | I9: 0 | J9: 0 | K9: 0 | L9: 0 | M9: 0 | N9: 0 | O9: 0 | P9: 0 | Q9: 0 | R9: 0 | S9: 0 | T9: 0 | U9: 0 | V9: 0 | W9: 0 | X9: 0 | Y9: 0 | Z9: 0 | AB9: 0 | AC9: 0 | AD9: 0 | AE9: 0 | AF9: 0 | AG9: 0 | AH9: 0 | AI9: 0 | AJ9: 0 | AK9: 0 | AL9: 0 | AM9: =SUM(F9:AL9) -> 0
A10: 4 | B10: VIjay | C10: HO | D10: FC3450698859 | E10: Diesel | F10: 0 | G10: 0 | H10: 0 | I10: 0 | J10: 0 | K10: 0 | L10: 0 | M10: 0 | N10: 0 | O10: 0 | P10: 49.22 | Q10: 0 | R10: 0 | S10: 0 | T10: 0 | U10: 54.57 | V10: 0 | W10: 0 | X10: 0 | Y10: 0 | Z10: 0 | AA10: 0 | AB10: 0 | AC10: 0 | AD10: 49.8 | AE10: 0 | AF10: 0 | AG10: 0 | AH10: 0 | AI10: 0 | AJ10: 0 | AK10: 0 | AL10: 0 | AM10: =SUM(F10:AL10) -> 153.59
E11: Petrol | F11: 0 | G11: 0 | H11: 0 | I11: 0 | J11: 0 | K11: 0 | L11: 0 | M11: 0 | N11: 0 | O11: 0 | P11: 0 | Q11: 0 | R11: 0 | S11: 0 | T11: 0 | U11: 0 | V11: 0 | W11: 0 | X11: 0 | Y11: 0 | Z11: 0 | AB11: 0 | AC11: 0 | AD11: 0 | AE11: 0 | AF11: 0 | AG11: 0 | AH11: 0 | AI11: 0 | AJ11: 0 | AK11: 0 | AL11: 0 | AM11: =SUM(F11:AL11) -> 0
A12: 5 | B12: Client | C12: Hiriyur | D12: FC3450698864 | E12: Diesel | F12: 0 | G12: 0 | H12: 0 | I12: 0 | J12: 0 | K12: 0 | L12: 0 | M12: 0 | N12: 86.29 | O12: 0 | P12: 0 | Q12: 0 | R12: 0 | S12: 0 | T12: 0 | U12: 0 | V12: 0 | W12: 0 | X12: 0 | Y12: 0 | Z12: 0 | AA12: 0 | AB12: 0 | AC12: 0 | AD12: 145.61 | AE12: 0 | AF12: 0 | AG12: 0 | AH12: 0 | AI12: 0 | AJ12: 0 | AK12: 0 | AL12: 0 | AM12: =SUM(F12:AL12) -> 231.9
E13: Petrol | F13: 0 | G13: 0 | H13: 0 | I13: 0 | J13: 0 | K13: 0 | L13: 0 | M13: 0 | N13: 0 | O13: 0 | P13: 0 | Q13: 0 | R13: 0 | S13: 0 | T13: 0 | U13: 0 | V13: 0 | W13: 0 | X13: 0 | Y13: 0 | Z13: 0 | AB13: 0 | AC13: 0 | AD13: 0 | AE13: 0 | AF13: 0 | AG13: 0 | AH13: 0 | AI13: 0 | AJ13: 0 | AK13: 0 | AL13: 0 | AM13: =SUM(F13:AL13) -> 0
A14: 6 | B14: Client | C14: Hosadurga | D14: FC3450698865 | E14: Diesel | F14: 0 | G14: 0 | H14: 0 | I14: 0 | J14: 0 | K14: 0 | L14: 40 | M14: 40 | N14: 0 | O14: 36 | P14: 35 | Q14: 0 | R14: 0 | S14: 0 | T14: 0 | U14: 0 | V14: 0 | W14: 45 | X14: 45 | Y14: 43.53 | Z14: 40 | AA14: 43 | AB14: 0 | AC14: 40 | AD14: 0 | AE14: 40 | AF14: 0 | AG14: 0 | AH14: 0 | AI14: 0 | AJ14: 0 | AK14: 0 | AL14: 0 | AM14: =SUM(F14:AL14) -> 447.53
E15: Petrol | F15: 0 | G15: 0 | H15: 0 | I15: 0 | J15: 0 | K15: 0 | L15: 0 | M15: 0 | N15: 0 | O15: 0 | P15: 0 | Q15: 0 | R15: 0 | S15: 0 | T15: 0 | U15: 0 | V15: 0 | W15: 0 | X15: 0 | Y15: 0 | Z15: 0 | AB15: 0 | AC15: 0 | AD15: 0 | AE15: 0 | AF15: 0 | AG15: 0 | AH15: 0 | AI15: 0 | AJ15: 0 | AK15: 0 | AL15: 0 | AM15: =SUM(F15:AL15) -> 0
G18: Diesel Price

Sheet  July-26
A1: S.no | B1: Site Name | C1: Bunk Name | D1: Diesel(Liters) | E1: Diesel Amount | F1: Petrol(Liters) | G1: Petrol Amount | H1: Total Amount | I1: Opening Blance | J1: Amount Paid | K1: Closing Balances
A2: 1 | B2: Khammam-1 | C2: Divya laxmi ganapathi | D2: =+'Khammam-1'!E38 -> 25629.86 | E2: =+'Khammam-1'!G38 -> 2660379.5 | F2: =+'Khammam-1'!H38 -> 245 | G2: =+'Khammam-1'!J38 -> 28344.05 | H2: =E2+G2 -> 2688723.5 | I2: =+'Khammam-1'!K3 -> 1615425.2 | J2: =+'Khammam-1'!L38 -> 470000 | K2: =H2+I2-J2 -> 3834148.7
A3: 2 | B3: Khammam-2 | C3: Jayasai union bunk | D3: =+'Khammam-2'!E38 -> 90723.14 | E3: =+'Khammam-2'!G38 -> 9543877.6 | F3: =+'Khammam-2'!H38 -> 745 | G3: =+'Khammam-2'!J38 -> 86211.4 | H3: =E3+G3 -> 9630089 | I3: =+'Khammam-2'!K3 -> 9590244 | J3: =+'Khammam-2'!L38 -> 290696 | K3: =H3+I3-J3 -> 18929637
A4: 3 | B4: Khammam-3 | C4: JSASFuel Genie India Pvt.Ltd | D4: =+'Khammam-3'!E35 -> 10000 | E4: =+'Khammam-3'!G35 -> 1038080 | F4: =+'Khammam-3'!H35 -> 0 | G4: =+'Khammam-3'!J35 -> 0 | H4: =E4+G4 -> 1038080 | I4: =+'Khammam-3'!M3 -> 1072600 | J4: =+'Khammam-3'!L35 -> 600000 | K4: =H4+I4-J4 -> 1510680
A5: 4 | B5: Khammam-Cash&Carry | C5: NA | D5: =+' Khammam&Cash'!E46 -> 8008.48 | E5: =+' Khammam&Cash'!G46 -> 831280.22 | F5: =+' Khammam&Cash'!H46 -> 0 | G5: =+' Khammam&Cash'!J46 -> 0 | H5: =E5+G5 -> 831280.22 | I5: =+' Khammam&Cash'!M3 -> 0 | J5: =+' Khammam&Cash'!L46 -> 831280.22 | K5: =H5+I5-J5 -> 0
A6: 5 | B6: Jadcherla-2 | C6: Shree Poornima F/S | D6: =+'Jadcherla-4'!E35 -> 850 | E6: =+'Jadcherla-4'!G35 -> 88757 | F6: =+'Jadcherla-4'!H35 -> 40 | G6: =+'Jadcherla-4'!J35 -> 4653.2 | H6: =E6+G6 -> 93410.2 | I6: =+'Jadcherla-4'!M3 -> 6863.48 | J6: =+'Jadcherla-4'!L35 -> 50000 | K6: =H6+I6-J6 -> 50273.68
A7: 6 | B7: Sangareddy-2 | C7: Durga Bhavani F/S | D7: =+' Sangareddy-2'!E35 -> 930.16 | E7: =+' Sangareddy-2'!G35 -> 97257.53 | F7: =+' Sangareddy-2'!H35 -> 60 | G7: =+' Sangareddy-2'!J35 -> 6992.4 | H7: =E7+G7 -> 104249.93 | I7: =+' Sangareddy-2'!M3 -> 128359.22 | J7: =+' Sangareddy-2'!L35 -> 180000 | K7: =H7+I7-J7 -> 52609.145
A8: 7 | B8: Sangareddy-3 | C8: Shiva Parvathi Filling Station | D8: =+' Sangareddy-3'!E36 -> 10935 | E8: =+' Sangareddy-3'!G36 -> 1141067.2 | F8: =+' Sangareddy-3'!H36 -> 53.76 | G8: =+' Sangareddy-3'!J36 -> 6249.6 | H8: =E8+G8 -> 1147316.9 | I8: =+' Sangareddy-3'!M3 -> 207619.56 | J8: =+' Sangareddy-3'!L36 -> 600000 | K8: =H8+I8-J8 -> 754936.41
A9: 8 | B9: NarayanaKhed | C9: Sai Shiva Filling Station | D9: =Narayankhed!E35 -> 2859.86 | E9: =+Narayankhed!G35 -> 299999.31 | F9: =+Narayankhed!H35 -> 0 | G9: =+Narayankhed!J35 -> 0 | H9: =E9+G9 -> 299999.31 | I9: =+Narayankhed!M3 -> 0 | J9: =+Narayankhed!L35 -> 299999.31 | K9: =H9+I9-J9 -> 0
A10: 9 | B10: Dindi | C10: Akarapu Balakistamma Fillling | D10: =+Dindi!E35 -> 162.288 | E10: =+Dindi!G35 -> 17004.489 | F10: =+Dindi!H35 -> 0 | G10: =+Dindi!J35 -> 0 | H10: =E10+G10 -> 17004.489 | I10: =+Dindi!M3 -> 0 | J10: =+Dindi!L35 -> 17004.489 | K10: =H10+I10-J10 -> 0
A11: 10 | B11: Madanapalli | C11: NA | D11: =+'Madana palli'!E37 -> 0 | E11: =+'Madana palli'!G37 -> 0 | F11: =+'Madana palli'!H37 -> 3.4 | G11: =+'Madana palli'!J37 -> 399.364 | H11: =E11+G11 -> 399.364 | I11: =+'Madana palli'!M3 -> 0 | J11: =+'Madana palli'!L37 -> 399.364 | K11: =H11+I11-J11 -> 0
A12: 11 | B12: Yeleshwaram | C12: Sri sathya Filling Station | D12: =+'Yeleshwaram(KKD)'!E37 -> 170 | E12: =+'Yeleshwaram(KKD)'!G37 -> 17928.2 | F12: =+'Yeleshwaram(KKD)'!H37 -> 10 | G12: =+'Yeleshwaram(KKD)'!J37 -> 1178.4 | H12: =E12+G12 -> 19106.6 | I12: =+'Yeleshwaram(KKD)'!M3 -> 0 | J12: =+'Yeleshwaram(KKD)'!L37 -> 0 | K12: =H12+I12-J12 -> 19106.6
A13: 12 | B13: Pitapuam | C13: Satya Siva Durga Agencies, Chebrolu | D13: =+' Pitapram(KKD)'!E37 -> 2262.13 | E13: =+' Pitapram(KKD)'!G37 -> 237998.7 | F13: =+' Pitapram(KKD)'!H37 -> 37 | G13: =+' Pitapram(KKD)'!J37 -> 4350.46 | H13: =E13+G13 -> 242349.16 | I13: =+' Pitapram(KKD)'!M3 -> 0 | J13: =+' Pitapram(KKD)'!L37 -> 150000 | K13: =H13+I13-J13 -> 92349.157
A14: 13 | B14: Kakinada | C14: Multiple bunks | D14: =+'Multiple bunks(KKD)'!E289 -> 9882.089 | E14: =+'Multiple bunks(KKD)'!G289 -> 1038084.8 | F14: =+'Multiple bunks(KKD)'!H289 -> 553.673 | G14: =+'Multiple bunks(KKD)'!J289 -> 67413.977 | H14: =E14+G14 -> 1105498.8 | I14: =+'Multiple bunks(KKD)'!M3 -> 0 | J14: =+'Multiple bunks(KKD)'!L289 -> 1105498.8 | K14: =H14+I14-J14 -> 0
A15: 14 | B15: YG Gudda-2 | C15: Pankaja HP Fuel Center | D15: =+'YG Gudda'!E39 -> 8500 | E15: =+'YG Gudda'!G39 -> 842690 | F15: =+'YG Gudda'!H39 -> 280 | G15: =+'YG Gudda'!J39 -> 31147.2 | H15: =E15+G15 -> 873837.2 | I15: =+'YG Gudda'!M3 -> 282784.16 | J15: =+'YG Gudda'!L39 -> 860000 | K15: =H15+I15-J15 -> 296621.36
A16: 15 | B16: YG Gudda-2 | C16: One stop | D16: =+' YG Gudda-2'!E39 -> 4603.96 | E16: =+' YG Gudda-2'!G39 -> 455884.12 | F16: =+' YG Gudda-2'!H39 -> 105 | G16: =+' YG Gudda-2'!J39 -> 11667.6 | H16: =E16+G16 -> 467551.72 | I16: =+' YG Gudda-2'!M3 -> 207747.6 | J16: =+' YG Gudda-2'!L39 -> 675000 | K16: =H16+I16-J16 -> 299.3192
A17: 16 | B17: Hosadurga-2 | C17: Shree Veeraprathap Fuel | D17: =+'Hosadurga -2'!E35 -> 1000 | E17: =+'Hosadurga -2'!G35 -> 99380 | F17: =+'Hosadurga -2'!H35 -> 70 | G17: =+'Hosadurga -2'!J35 -> 7820.4 | H17: =+'Hosadurga -2'!K35 -> 107200.4 | I17: =+'Hosadurga -2'!K3 -> 114284.39 | J17: =+'Hosadurga -2'!L35 -> 221000 | K17: =H17+I17-J17 -> 484.7941
A18: 17 | B18: Malebennuru(KUWSDB) | C18: Sri Ramanjuneya Service Station | D18: =+'Malebenur(KUWSDB)'!E37 -> 5132.39 | E18: =+'Malebenur(KUWSDB)'!G37 -> 513239.31 | F18: =+'Malebenur(KUWSDB)'!H37 -> 180 | G18: =+'Malebenur(KUWSDB)'!J37 -> 20164.8 | H18: =E18+G18 -> 533404.11 | I18: =+'Malebenur(KUWSDB)'!K3 -> 132362.11 | J18: =+'Malebenur(KUWSDB)'!L37 -> 534999.51 | K18: =H18+I18-J18 -> 130766.71
A19: 18 | B19: kadur | C19: Vishal Service Station | D19: =+Kadur!E35 -> 3400 | E19: =+Kadur!G35 -> 339864 | F19: =+Kadur!H35 -> 70 | G19: =+Kadur!J35 -> 7861 | H19: =E19+G19 -> 347725 | I19: =+Kadur!K3 -> 325301.9 | J19: =+Kadur!L35 -> 0 | K19: =H19+I19-J19 -> 673026.9
A20: 19 | B20: Hiriyur(VJNL) | C20: Sri Balaji Agencies | D20: =+'Hiriyur(VJNL)'!E35 -> 4000 | E20: =+'Hiriyur(VJNL)'!G35 -> 400360 | F20: =+'Hiriyur(VJNL)'!H35 -> 210 | G20: =+'Hiriyur(VJNL)'!J35 -> 23545.2 | H20: =E20+G20 -> 423905.2 | I20: =+'Hiriyur(VJNL)'!K3 -> 219362.7 | J20: =+'Hiriyur(VJNL)'!L35 -> 435000 | K20: =H20+I20-J20 -> 208267.9
A21: 20 | B21: Chellakere(KUWSDB) | C21: Shivaganga Service Station | D21: =+'Chellakere -1'!E38 -> 3600 | E21: =+'Chellakere -1'!G38 -> 360180 | F21: =+'Chellakere -1'!H38 -> 310 | G21: =+'Chellakere -1'!J38 -> 34741.7 | H21: =E21+G21 -> 394921.7 | I21: =+'Chellakere -1'!K3 -> 116056.55 | J21: =+'Chellakere -1'!L38 -> 300000 | K21: =H21+I21-J21 -> 210978.25
A22: 21 | B22: Chellakere(KUWSDB)-09 | C22: Shivaganga Service Station | D22: =+' Chellakere-PKG-9'!E36 -> 715.754 | E22: =+' Chellakere-PKG-9'!G36 -> 71610.788 | F22: =+' Chellakere-PKG-9'!H36 -> 58.34 | G22: =+' Chellakere-PKG-9'!J36 -> 6538.1638 | H22: =E22+G22 -> 78148.952 | I22: =+' Chellakere-PKG-9'!M3 -> 0 | J22: =+' Chellakere-PKG-9'!L36 -> 78148.952 | K22: =H22+I22-J22 -> 0
A23: 22 | B23: Molakalmuru | C23: Sri Lakshmi Venkateshwara Filling Station | D23: =+Molakamuru!E35 -> 1470 | E23: =+Molakamuru!G35 -> 147057.1 | F23: =+Molakamuru!H35 -> 135 | G23: =+Molakamuru!J35 -> 15128.1 | H23: =E23+G23 -> 162185.2 | I23: =+Molakamuru!K3 -> 8880.86 | J23: =+Molakamuru!L35 -> 120366.9 | K23: =H23+I23-J23 -> 50699.16
A24: 23 | B24: Chennagiri | C24: NA | D24: =+' Chennagiri'!E35 -> 1332.17 | E24: =+' Chennagiri'!G35 -> 133046.82 | F24: =+' Chennagiri'!H35 -> 89.99 | G24: =+' Chennagiri'!J35 -> 10084.279 | H24: =E24+G24 -> 143131.1 | I24: =+' Chennagiri'!K3 -> 0 | J24: =+' Chennagiri'!L35 -> 143131.1 | K24: =H24+I24-J24 -> 0
A25: 24 | B25: Khanapur(PKG-3) | C25: V.V.Varde | D25: =+Khanapur!E35 -> 717.32 | E25: =+Khanapur!G35 -> 70792.311 | F25: =+Khanapur!H35 -> 80 | G25: =+Khanapur!J35 -> 8871.6 | H25: =E25+G25 -> 79663.911 | I25: =+Khanapur!M3 -> 105067.75 | J25: =+Khanapur!L35 -> 100000 | K25: =H25+I25-J25 -> 84731.659
A26: 25 | B26: Munavalli(PKG-3) | C26: Shre Shiva Petroleum | D26: =+'Munavali-2'!E40 -> 3400 | E26: =+'Munavali-2'!G40 -> 337790 | F26: =+'Munavali-2'!H40 -> 80 | G26: =+'Munavali-2'!J40 -> 8918 | H26: =E26+G26 -> 346708 | I26: =+'Munavali-2'!M3 -> 0 | J26: =+'Munavali-2'!L40 -> 200000 | K26: =H26+I26-J26 -> 146708
A27: 26 | B27: Munavalli(PKG-3) | C27: Daneshwari Petroleum | D27: =+' Munavali'!E39 -> 4800 | E27: =+' Munavali'!G39 -> 475824 | F27: =+' Munavali'!H39 -> 180 | G27: =+' Munavali'!J39 -> 20017.8 | H27: =E27+G27 -> 495841.8 | I27: =+' Munavali'!M3 -> 478435.42 | J27: =+' Munavali'!L39 -> 700000 | K27: =H27+I27-J27 -> 274277.22
A28: 27 | B28: Borgaon(PKG-3) | C28: Aadisagar Petrolium | D28: =+Borgaon!E35 -> 0 | E28: =+Borgaon!G35 -> 0 | F28: =+Borgaon!H35 -> 0 | G28: =+Borgaon!J35 -> 0 | H28: =E28+G28 -> 0 | I28: =+Borgaon!K3 -> 208.3907 | J28: =+Borgaon!L35 -> 0 | K28: =H28+I28-J28 -> 208.3907
A29: 28 | B29: Ugar,Kudichi(PKG-3) | C29: Shiri Bhrhmanath Petrolium | D29: =+'Ugar,Khagwad,Kudichi'!E37 -> 5853.82 | E29: =+'Ugar,Khagwad,Kudichi'!G37 -> 583860.01 | F29: =+'Ugar,Khagwad,Kudichi'!H37 -> 76 | G29: =+'Ugar,Khagwad,Kudichi'!J37 -> 8500.6 | H29: =E29+G29 -> 592360.61 | I29: =+'Ugar,Khagwad,Kudichi'!M3 -> 529659.87 | J29: =+'Ugar,Khagwad,Kudichi'!L37 -> 780000 | K29: =H29+I29-J29 -> 342020.48
A30: 29 | B30: Shedbal | C30: Varad Petroluem | D30: =+shedbal!E37 -> 5814.96 | E30: =+shedbal!G37 -> 579957.15 | F30: =+shedbal!H37 -> 352 | G30: =+shedbal!J37 -> 39371.2 | H30: =E30+G30 -> 619328.35 | I30: =+shedbal!M3 -> 296953 | J30: =+shedbal!L37 -> 410000.2 | K30: =H30+I30-J30 -> 506281.15
A31: 30 | B31: Kabbur(PKG-3) | C31: Shri Jai Hanuman Petrolium | D31: =+Kabbur!E35 -> 140.48 | E31: =+Kabbur!G35 -> 13965.117 | F31: =+Kabbur!H35 -> 0 | G31: =+Kabbur!J35 -> 0 | H31: =E31+G31 -> 13965.117 | I31: 0 | J31: =+Kabbur!L35 -> 13965.117 | K31: =H31+I31-J31 -> 0
A32: 31 | B32: Kumta (PKG-1) | C32: V.M.Mirjankar (Kumta) Bharat | D32: =+kumta!E41 -> 1060 | E32: =+kumta!G41 -> 105766.8 | F32: =+kumta!H41 -> 85 | G32: =+kumta!J41 -> 9518.3 | H32: =E32+G32 -> 115285.1 | I32: =kumta!M3 -> 15058.507 | J32: =+kumta!L41 -> 70000 | K32: =H32+I32-J32 -> 60343.607
A33: 32 | B33: Jalgaon-1 | C33: Jai Bajarang Sarvo Senter Bodwad | D33: =+' Jalgaon-1'!E55 -> 0 | E33: =+' Jalgaon-1'!G55 -> 0 | F33: =+' Jalgaon-1'!H55 -> 0 | G33: =+' Jalgaon-1'!J55 -> 0 | H33: =E33+G33 -> 0 | I33: =+' Jalgaon-1'!K3 -> 0 | J33: =+' Jalgaon-1'!L55 -> 0 | K33: =H33+I33-J33 -> 0
A34: 33 | B34: Jalgaon-2 | C34: Nayara | D34: =+'Jalgoan-2'!E56 -> 19809.44 | E34: ='Jalgoan-2'!G56 -> 1971173.4 | F34: =+'Jalgoan-2'!H56 -> 150 | G34: =+'Jalgoan-2'!J56 -> 16977 | H34: =E34+G34 -> 1988150.4 | I34: =+'Jalgoan-2'!M3 -> 2547026.4 | J34: =+'Jalgoan-2'!L56 -> 4068.6941 | K34: =H34+I34-J34 -> 4531108.2
A35: 34 | B35: MKBD | C35: Shree Sai Samarth Petroleum | D35: =+MKBD!E42 -> 3000 | E35: =+MKBD!G42 -> 296820 | F35: =+MKBD!H42 -> 10 | G35: =+MKBD!J42 -> 1122.7 | H35: =E35+G35 -> 297942.7 | I35: =+MKBD!K3 -> 631570.81 | J35: =+MKBD!L42 -> 0 | K35: =H35+I35-J35 -> 929513.51
A36: 35 | B36: Haveri | C36: M/s Magavi City Fuels | D36: =' Haveri-2'!E42 -> 3772.15 | E36: =' Haveri-2'!G42 -> 374561.75 | F36: =' Haveri-2'!H42 -> 113.79 | G36: =' Haveri-2'!J42 -> 12676.206 | H36: =E36+G36 -> 387237.96 | I36: =' Haveri-2'!M3 -> 132797.45 | J36: =+' Haveri-2'!L42 -> 401000.02 | K36: =H36+I36-J36 -> 119035.39
A37: 36 | B37: Guttal-2 | C37: Himagiri Petroleum | D37: =+' Guttal-2'!E35 -> 7568.35 | E37: =+' Guttal-2'!G35 -> 753807.66 | F37: =+' Guttal-2'!H35 -> 166.06 | G37: =+' Guttal-2'!J35 -> 18550.563 | H37: =E37+G37 -> 772358.22 | I37: =+' Guttal-2'!M3 -> 92031.494 | J37: =+' Guttal-2'!L35 -> 700000 | K37: =H37+I37-J37 -> 164389.72
A38: 37 | B38: Rattihali-2 | C38: Shiva Oil Traders | D38: =+'Rattihali-2'!E37 -> 5892.11 | E38: =+'Rattihali-2'!G37 -> 587443.37 | F38: =+'Rattihali-2'!H37 -> 119.01 | G38: =+'Rattihali-2'!J37 -> 13357.398 | H38: =E38+G38 -> 600800.77 | I38: =+'Rattihali-2'!M3 -> 393080.16 | J38: =+'Rattihali-2'!L37 -> 650000 | K38: =H38+I38-J38 -> 343880.92
A39: 38 | B39: Gajendragada | C39: Vanasri Petrol Pump | D39: =+Gajendragada!E36 -> 750 | E39: =+Gajendragada!G36 -> 74730 | F39: =+Gajendragada!H36 -> 46.63 | G39: =+Gajendragada!J36 -> 5211.8351 | H39: =E39+G39 -> 79941.835 | I39: =+Gajendragada!K3 -> 79945.408 | J39: =+Gajendragada!L36 -> 100000 | K39: =H39+I39-J39 -> 59887.243
A40: 39 | B40: Gokak(PKG-3) | C40: AJ Petrolinks | D40: =+'Gokak Dharwad PKG 3'!E42 -> 7986.06 | E40: =+'Gokak Dharwad PKG 3'!G42 -> 792935.9 | F40: =+'Gokak Dharwad PKG 3'!H42 -> 45 | G40: =+'Gokak Dharwad PKG 3'!J42 -> 5012.1 | H40: =E40+G40 -> 797948 | I40: =+'Gokak Dharwad PKG 3'!K3 -> 144866.46 | J40: =+'Gokak Dharwad PKG 3'!L42 -> 500000 | K40: =H40+I40-J40 -> 442814.46
A41: 40 | B41: Hukkere | C41: TR Assocites | D41: =+' TR Associates'!E35 -> 11076.66 | E41: =+' TR Associates'!G35 -> 1098029.3 | F41: =+' TR Associates'!H35 -> 0 | G41: =+' TR Associates'!J35 -> 0 | H41: =E41+G41 -> 1098029.3 | I41: =+' TR Associates'!M3 -> 300159.89 | J41: =+' TR Associates'!L35 -> 0 | K41: =H41+I41-J41 -> 1398189.2
A42: 41 | B42: Ankaligi | C42: Shivaganga | D42: =+Ankalgi!E35 -> 773.16 | E42: =+Ankalgi!G35 -> 76643.351 | F42: =+Ankalgi!H35 -> 20 | G42: =+Ankalgi!J35 -> 2224.2 | H42: =E42+G42 -> 78867.551 | I42: =+Ankalgi!M3 -> 235407.38 | J42: =+Ankalgi!L35 -> 200000 | K42: =H42+I42-J42 -> 114274.94
A43: 42 | B43: Ghattaprabha | C43: Shri Deshpande | D43: =+'SHRI DESHPANDE'!E35 -> 7079.58 | E43: =+'SHRI DESHPANDE'!G35 -> 703499.33 | F43: =+'SHRI DESHPANDE'!H35 -> 439 | G43: =+'SHRI DESHPANDE'!J35 -> 48930.94 | H43: =E43+G43 -> 752430.27 | I43: =+'SHRI DESHPANDE'!M3 -> 293806.43 | J43: =+'SHRI DESHPANDE'!L35 -> 0 | K43: =H43+I43-J43 -> 1046236.7
A44: 43 | B44: ShankeshWAR | C44: SR Patil | D44: =+' Shankeshwar'!E35 -> 60 | E44: =+' Shankeshwar'!G35 -> 5947.2 | F44: =+' Shankeshwar'!H35 -> 14 | G44: =+' Shankeshwar'!J35 -> 1556.8 | H44: =E44+G44 -> 7504 | I44: =' Shankeshwar'!M3 -> 0 | J44: =+' Shankeshwar'!L35 -> 7504 | K44: =H44+I44-J44 -> 0
A45: 44 | B45: Talikote(PKG-1) | C45: Raykar Oil Agencies | D45: =+' Talikote'!E48 -> 655.19 | E45: =+' Talikote'!G48 -> 64972.611 | F45: =+' Talikote'!H48 -> 68.67 | G45: =+' Talikote'!J48 -> 7651.2114 | H45: =E45+G45 -> 72623.823 | I45: =+' Talikote'!N3 -> 12987.919 | J45: =+' Talikote'!L48 -> 65430.793 | K45: =H45+I45-J45 -> 20180.949
A46: 45 | B46: Chadchan(PKG-1) | C46: Khavekar Petrolium | D46: =+Chadchan!E35 -> 1345.79 | E46: =+Chadchan!G35 -> 133394.7 | F46: =+Chadchan!H35 -> 112.57 | G46: =+Chadchan!J35 -> 12552.818 | H46: =E46+G46 -> 145947.52 | I46: =+Chadchan!K3 -> 72362.652 | J46: =+Chadchan!L35 -> 100000 | K46: =H46+I46-J46 -> 118310.18
A47: 46 | B47: Sindagi | C47: G.P.PORWAL | D47: =+Sindagi!E36 -> 699.73 | E47: =+Sindagi!G36 -> 69322.251 | F47: =+Sindagi!H36 -> 5 | G47: =+Sindagi!J36 -> 603.2 | H47: =E47+G47 -> 69925.451 | I47: =+Sindagi!M3 -> 13667.989 | J47: =+Sindagi!L36 -> 60000 | K47: =H47+I47-J47 -> 23593.44
A48: 47 | B48: Muddebihal(PKG-1)2 | C48: PS NAGATHAN PETROLIUM | D48: =+'Muddebhihal-2'!E50 -> 1715.21 | E48: =+'Muddebhihal-2'!G50 -> 170200.29 | F48: =+'Muddebhihal-2'!H50 -> 40 | G48: =+'Muddebhihal-2'!J50 -> 4499.95 | H48: =+'Muddebhihal-2'!K50 -> 174700.24 | I48: =+'Muddebhihal-2'!M3 -> 159608.51 | J48: =+'Muddebhihal-2'!L50 -> 150000 | K48: =+'Muddebhihal-2'!M49 -> 184308.75
A49: 48 | B49: Almela(PKG-1) | C49: Shiddeshwar Petroleums | D49: =+Alemela!E43 -> 471.07 | E49: =+Alemela!G43 -> 46767.83 | F49: =+Alemela!H43 -> 55.73 | G49: =+Alemela!J43 -> 6199.2469 | H49: =E49+G49 -> 52967.076 | I49: =+Alemela!M3 -> 69763.206 | J49: =+Alemela!L43 -> 94199.962 | K49: =H49+I49-J49 -> 28530.32
A50: 49 | B50: Nalatwad(PKG-1) | C50: Shri Pawad Basaweshwar Petroleums | D50: =+Nalatwad!E43 -> 1031.16 | E50: =+Nalatwad!G43 -> 102538.55 | F50: =+Nalatwad!H43 -> 18.25 | G50: =+Nalatwad!J43 -> 2144.3335 | H50: =E50+G50 -> 104682.88 | I50: =+Nalatwad!M3 -> 16349.324 | J50: =+Nalatwad!L43 -> 0 | K50: =H50+I50-J50 -> 121032.21
A51: 50 | B51: Srirangapatna | C51: Anupama F/S | D51: =+Srirangapatna!E35 -> 121.96 | E51: =+Srirangapatna!G35 -> 11999.644 | F51: =+Srirangapatna!H35 -> 28.85 | G51: =+Srirangapatna!J35 -> 2632.784 | H51: =E51+G51 -> 14632.428 | I51: 0 | J51: =+Srirangapatna!L35 -> 14632.428 | K51: =H51+I51-J51 -> 0
A52: 51 | B52: HO(DG) | C52: JSASFuel Genie India Pvt.Ltd | D52: =+'HO(DG)'!E46 -> 1080 | E52: =+'HO(DG)'!G46 -> 112108.8 | F52: =+'HO(DG)'!H46 -> 0 | G52: =+'HO(DG)'!J46 -> 0 | H52: =E52+G52 -> 112108.8 | I52: =+'HO(DG)'!M3 -> 182921.75 | J52: =+'HO(DG)'!L46 -> 29052.8 | K52: =H52+I52-J52 -> 265977.75
A53: Total | D53: =SUM(D2:D52) -> 292841.48 | E53: =SUM(E2:E52) -> 29989878 | F53: =SUM(F2:F52) -> 5561.723 | G53: =SUM(G2:G52) -> 631592.08 | H53: =SUM(H2:H52) -> 30621470 | I53: =SUM(I2:I52) -> 20831628 | J53: =SUM(J2:J52) -> 13312379 | K53: =H53+I53-J53 -> 38140719
A58: S.no | B58: Site Name | C58: Bunk Name | D58: Diesel(Liters) | E58: Diesel Amount | F58: Petrol(Liters) | G58: Petrol Amount | H58: Total Amount | I58: Opening Blance | J58: Amount Paid | K58: Closing Balances
A59: 39 | B59: {=VLOOKUP(A59,A1:K51,{2,3,4,5,6,7,8,9,10,11},FALSE)} -> Gokak(PKG-3) | C59: AJ Petrolinks | D59: 7986.06 | E59: 792935.9 | F59: 45 | G59: 5012.1 | H59: 797948 | I59: 144866.46 | J59: 500000 | K59: 442814.46
B61: Site Name | C61: Bunk Name | D61: Diesel(Liters) | E61: Diesel Amount | F61: Petrol(Liters) | G61: Petrol Amount | H61: Total Amount | I61: Opening Blance | J61: Amount Paid | K61: Closing Balances
B62: Jalgaon-2 | C62: {=VLOOKUP(B62,B1:K51,{2,3,4,5,6,7,8,9,10},FALSE)} -> Nayara | D62: 19809.44 | E62: 1971173.4 | F62: 150 | G62: 16977 | H62: 1988150.4 | I62: 2547026.4 | J62: 4068.6941 | K62: 4531108.2

Sheet HO(DG)
A1: JSASFuel Genie India Pvt.Ltd
A2: S.No | B2: Date | C2: GRN No | D2: Ind No/Bill No | E2: Diesel (Lts) | F2: Price | G2: Amount | H2: Petrol (Lts) | I2: Price | J2: Amount | K2: Total amount | L2: Amount paid | M2: As on date | N2: Remarks
A3: Opening Balance | K3: 182921.75 | M3: 182921.75 | O3: 2623243.4
A4: 1 | B4: 46204 | G4: =E4*F4 -> 0 | H4: 0 | I4: 0 | J4: =H4*I4 -> 0 | K4: =G4+J4 -> 0 | L4: 0 | M4: =M3+K4-L4 -> 182921.75
A5: 2 | B5: 46205 | G5: =E5*F5 -> 0 | K5: =G5+J5 -> 0 | M5: =M4+K5-L5 -> 182921.75 | R5: HO | S5: 188521.22
A6: 3 | B6: 46206 | E6: 200 | F6: 103.82 | G6: =E6*F6 -> 20764 | K6: =G6+J6 -> 20764 | L6: 0 | M6: =M5+K6-L6 -> 203685.75 | R6: Khammam | S6: 8227903
A7: 4 | B7: 46207 | G7: =E7*F7 -> 0 | K7: =G7+J7 -> 0 | M7: =M6+K7-L7 -> 203685.75 | R7: Jadcherla | S7: 2453209.4
A8: 5 | B8: 46208 | G8: =E8*F8 -> 0 | K8: =G8+J8 -> 0 | M8: =M7+K8-L8 -> 203685.75 | P8: 5679 | R8: Total | S8: =SUM(S5:S7) -> 10869634
A9: 6 | B9: 46209 | G9: =E9*F9 -> 0 | K9: =G9+J9 -> 0 | M9: =M8+K9-L9 -> 203685.75 | S9: 10869632
A10: 7 | B10: 46210 | G10: =E10*F10 -> 0 | K10: =G10+J10 -> 0 | L10: =H10+K10 -> 0 | M10: =M9+K10-L10 -> 203685.75 | N10: HPCL | S10: =S9-S8 -> -1.6105
B11: 46211 | G11: =E11*F11 -> 0 | K11: =G11+J11 -> 0 | L11: =H11+K11 -> 0 | M11: =M10+K11-L11 -> 203685.75 | N11: HPCL
A12: 8 | B12: 46212 | G12: =E12*F12 -> 0 | K12: =G12+J12 -> 0 | L12: =H12+K12 -> 0 | M12: =M11+K12-L12 -> 203685.75 | N12: HPCL
A13: 9 | B13: 46213 | E13: 35 | F13: 103.76 | G13: =E13*F13 -> 3631.6 | K13: =G13+J13 -> 3631.6 | L13: =H13+K13 -> 3631.6 | M13: =M12+K13-L13 -> 203685.75 | Q13: 54.98
A14: 10 | B14: 46214 | E14: 35 | F14: 103.76 | G14: =E14*F14 -> 3631.6 | K14: =G14+J14 -> 3631.6 | L14: =H14+K14 -> 3631.6 | M14: =M13+K14-L14 -> 203685.75 | Q14: 54.98
A15: 11 | B15: 46215 | E15: 200 | F15: 103.82 | G15: =E15*F15 -> 20764 | K15: =G15+J15 -> 20764 | M15: =M14+K15-L15 -> 224449.75
A16: 12 | B16: 46216 | G16: =E16*F16 -> 0 | K16: =G16+J16 -> 0 | L16: =H16+K16 -> 0 | M16: =M15+K16-L16 -> 224449.75 | R16: 19166
A17: 13 | B17: 46217 | G17: =E17*F17 -> 0 | K17: =G17+J17 -> 0 | L17: =H17+K17 -> 0 | M17: =M16+K17-L17 -> 224449.75 | R17: 19645
A18: 14 | B18: 46218 | G18: =E18*F18 -> 0 | K18: =G18+J18 -> 0 | L18: =H18+K18 -> 0 | M18: =M17+K18-L18 -> 224449.75 | P18: 1905988 | Q18: =P18-M18 -> 1681538.2 | R18: 21083
A19: 15 | B19: 46219 | E19: 70 | F19: 103.76 | G19: =E19*F19 -> 7263.2 | K19: =G19+J19 -> 7263.2 | L19: =H19+K19 -> 7263.2 | M19: =M18+K19-L19 -> 224449.75 | R19: 19140 | S19: 220637
A20: 16 | B20: 46220 | E20: 200 | F20: 103.82 | G20: =E20*F20 -> 20764 | K20: =G20+J20 -> 20764 | M20: =M19+K20-L20 -> 245213.75 | N20: HPCL | R20: =SUM(R16:R19) -> 79034 | S20: =S19+R20 -> 299671
A21: 17 | B21: 46221 | G21: =E21*F21 -> 0 | K21: =G21+J21 -> 0 | L21: =H21+K21 -> 0 | M21: =M20+K21-L21 -> 245213.75 | N21: HPCL
A22: 18 | B22: 46222 | G22: =E22*F22 -> 0 | K22: =G22+J22 -> 0 | L22: =H22+K22 -> 0 | M22: =M21+K22-L22 -> 245213.75
A23: 19 | B23: 46223 | G23: =E23*F23 -> 0 | K23: =G23+J23 -> 0 | L23: =H23+K23 -> 0 | M23: =M22+K23-L23 -> 245213.75
A24: 20 | B24: 46224 | G24: =E24*F24 -> 0 | K24: =G24+J24 -> 0 | L24: =H24+K24 -> 0 | M24: =M23+K24-L24 -> 245213.75
A25: 21 | B25: 46225 | E25: 200 | F25: 103.82 | G25: =E25*F25 -> 20764 | K25: =G25+J25 -> 20764 | L25: 0 | M25: =M24+K25-L25 -> 265977.75
A26: 22 | B26: 46226 | G26: =E26*F26 -> 0 | K26: =G26+J26 -> 0 | L26: =H26+K26 -> 0 | M26: =M25+K26-L26 -> 265977.75
A27: 23 | B27: 46227 | G27: =E27*F27 -> 0 | K27: =G27+J27 -> 0 | L27: 0 | M27: =M26+K27-L27 -> 265977.75
A28: 24 | B28: 46228 | G28: =E28*F28 -> 0 | K28: =G28+J28 -> 0 | L28: =H28+K28 -> 0 | M28: =M27+K28-L28 -> 265977.75
A29: 25 | B29: 46229 | G29: =E29*F29 -> 0 | K29: =G29+J29 -> 0 | L29: =H29+K29 -> 0 | M29: =M28+K29-L29 -> 265977.75
A30: 26 | B30: 46230 | G30: =E30*F30 -> 0 | K30: =G30+J30 -> 0 | M30: =M29+K30-L30 -> 265977.75
A31: 27 | B31: 46231 | E31: 70 | F31: 103.76 | G31: =E31*F31 -> 7263.2 | K31: =G31+J31 -> 7263.2 | L31: 7263.2 | M31: =M30+K31-L31 -> 265977.75
A32: 28 | B32: 46232 | G32: =E32*F32 -> 0 | K32: =G32+J32 -> 0 | M32: =M31+K32-L32 -> 265977.75
B33: 46233 | G33: =E33*F33 -> 0 | M33: =M32+K33-L33 -> 265977.75
A34: 29 | B34: 46234 | E34: 70 | F34: 103.76 | G34: =E34*F34 -> 7263.2 | K34: =G34+J34 -> 7263.2 | L34: =H34+K34 -> 7263.2 | M34: =M33+K34-L34 -> 265977.75
G35: =E35*F35 -> 0 | K35: =G35+J35 -> 0 | M35: =M34+K35-L35 -> 265977.75
A36: 30 | K36: =G36+J36 -> 0 | M36: =M35+K36-L36 -> 265977.75
A37: 31 | M37: =M36+K37-L37 -> 265977.75
A38: 32 | M38: =M37+K38-L38 -> 265977.75 | O38: 265910 | P38: =M38-O38 -> 67.75
A39: 33
A40: 34
A41: 35
A42: 36
A43: 37
A44: 38 | O44: 2669494 | P44: =O44-M44 -> 2669494
E45: 0 | F45: 0 | G45: =E45*F45 -> 0 | J45: =H45*I45 -> 0 | K45: =G45+J45 -> 0 | M45: =M44+K45-L45 -> 0
E46: =SUM(E4:E44) -> 1080 | G46: =SUM(G4:G44) -> 112108.8 | H46: =SUM(H4:H44) -> 0 | J46: =SUM(J4:J44) -> 0 | K46: =SUM(K4:K44) -> 112108.8 | L46: =SUM(L4:L44) -> 29052.8
M55: 2408309
M56: 5327.86
M57: =M55-M56 -> 2402981.1

Sheet Khammam-1
A1: Divya laxmi ganapathi
A2: S.No | B2: Date | C2: GRN No | D2: Ind No/Bill No | E2: Diesel (Lts) | F2: Price | G2: Amount | H2: Petrol (Lts) | I2: Price | J2: Amount | K2: Total amount | L2: Amount paid | M2: As 0n Date | N2: Remarks
A3: Opening Balance | K3: 1615425.2 | M3: 1615425.2
A4: 1 | B4: 46204 | G4: =E4*F4 -> 0 | K4: =G4+J4 -> 0 | M4: =M3+K4-L4 -> 1615425.2
A5: 2 | B5: 46205 | E5: 2800 | F5: 103.8 | G5: =E5*F5 -> 290640 | H5: 60 | I5: 115.69 | J5: =H5*I5 -> 6941.4 | K5: =G5+J5 -> 297581.4 | M5: =M4+K5-L5 -> 1913006.6
A6: 3 | B6: 46206 | E6: 2892.67 | F6: 103.8 | G6: =E6*F6 -> 300259.15 | H6: 40 | I6: 115.69 | J6: =H6*I6 -> 4627.6 | K6: =G6+J6 -> 304886.75 | M6: =M5+K6-L6 -> 2217893.3
A7: 4 | B7: 46207 | E7: 2000 | F7: 103.8 | G7: =E7*F7 -> 207600 | H7: 50 | I7: 115.69 | J7: =H7*I7 -> 5784.5 | K7: =G7+J7 -> 213384.5 | M7: =M6+K7-L7 -> 2431277.8
A8: 5 | B8: 46208 | E8: 1500 | F8: 103.8 | G8: =E8*F8 -> 155700 | J8: =H8*I8 -> 0 | K8: =G8+J8 -> 155700 | M8: =M7+K8-L8 -> 2586977.8
A9: 6 | B9: 46209 | G9: =E9*F9 -> 0 | J9: =H9*I9 -> 0 | K9: =G9+J9 -> 0 | M9: =M8+K9-L9 -> 2586977.8
A10: 7 | B10: 46210 | E10: 2700 | F10: 103.8 | G10: =E10*F10 -> 280260 | J10: =H10*I10 -> 0 | K10: =G10+J10 -> 280260 | M10: =M9+K10-L10 -> 2867237.8
A11: 8 | B11: 46211 | G11: =E11*F11 -> 0 | J11: =H11*I11 -> 0 | K11: =G11+J11 -> 0 | M11: =M10+K11-L11 -> 2867237.8
A12: 9 | B12: 46212 | G12: =E12*F12 -> 0 | J12: =H12*I12 -> 0 | K12: =G12+J12 -> 0 | M12: =M11+K12-L12 -> 2867237.8
A13: 10 | B13: 46213 | G13: =E13*F13 -> 0 | J13: =H13*I13 -> 0 | K13: =G13+J13 -> 0 | M13: =M12+K13-L13 -> 2867237.8
A14: 11 | B14: 46214 | G14: =E14*F14 -> 0 | J14: =H14*I14 -> 0 | K14: =G14+J14 -> 0 | M14: =M13+K14-L14 -> 2867237.8
A15: 12 | B15: 46215 | G15: =E15*F15 -> 0 | J15: =H15*I15 -> 0 | K15: =G15+J15 -> 0 | M15: =M14+K15-L15 -> 2867237.8
A16: 13 | B16: 46216 | G16: =E16*F16 -> 0 | J16: =H16*I16 -> 0 | K16: =G16+J16 -> 0 | M16: =M15+K16-L16 -> 2867237.8
A17: 14 | B17: 46217 | E17: 3000 | F17: 103.8 | G17: =E17*F17 -> 311400 | H17: 60 | I17: 115.69 | J17: =H17*I17 -> 6941.4 | K17: =G17+J17 -> 318341.4 | M17: =M16+K17-L17 -> 3185579.2 | N17: DGM Sir | O17: 250000
A18: 15 | B18: 46218 | E18: 2500 | F18: 103.8 | G18: =E18*F18 -> 259500 | H18: 35 | I18: 115.69 | J18: =H18*I18 -> 4049.15 | K18: =G18+J18 -> 263549.15 | M18: =M17+K18-L18 -> 3449128.4
A19: 16 | B19: 46219 | E19: 2408.47 | F19: 103.8 | G19: =E19*F19 -> 249999.19 | J19: =H19*I19 -> 0 | K19: =G19+J19 -> 249999.19 | M19: =M18+K19-L19 -> 3699127.6 | N19: DGM Sir | O19: 250000
A20: 17 | B20: 46220 | G20: =E20*F20 -> 0 | J20: =H20*I20 -> 0 | K20: =G20+J20 -> 0 | M20: =M19+K20-L20 -> 3699127.6
A21: 18 | B21: 46221 | G21: =E21*F21 -> 0 | J21: =H21*I21 -> 0 | K21: =G21+J21 -> 0 | M21: =M20+K21-L21 -> 3699127.6
A22: 19 | B22: 46222 | G22: =E22*F22 -> 0 | J22: =H22*I22 -> 0 | K22: =G22+J22 -> 0 | M22: =M21+K22-L22 -> 3699127.6
A23: 20 | B23: 46223 | E23: 1300 | F23: 103.8 | G23: =E23*F23 -> 134940 | J23: =H23*I23 -> 0 | K23: =G23+J23 -> 134940 | M23: =M22+K23-L23 -> 3834067.6 | N23: DGM Sir | O23: 100000
A24: 21 | B24: 46224 | G24: =E24*F24 -> 0 | J24: =H24*I24 -> 0 | K24: =G24+J24 -> 0 | M24: =M23+K24-L24 -> 3834067.6
A25: 22 | B25: 46225 | G25: =E25*F25 -> 0 | J25: =H25*I25 -> 0 | K25: =G25+J25 -> 0 | M25: =M24+K25-L25 -> 3834067.6
A26: 23 | B26: 46226 | G26: =E26*F26 -> 0 | J26: =H26*I26 -> 0 | K26: =G26+J26 -> 0 | M26: =M25+K26-L26 -> 3834067.6 | O26: =SUM(O17:O25) -> 600000
A27: 24 | B27: 46227 | G27: =E27*F27 -> 0 | J27: =H27*I27 -> 0 | K27: =G27+J27 -> 0 | M27: =M26+K27-L27 -> 3834067.6
A28: 25 | B28: 46228 | G28: =E28*F28 -> 0 | J28: =H28*I28 -> 0 | K28: =G28+J28 -> 0 | M28: =M27+K28-L28 -> 3834067.6
A29: 26 | B29: 46229 | G29: =E29*F29 -> 0 | J29: =H29*I29 -> 0 | K29: =G29+J29 -> 0 | M29: =M28+K29-L29 -> 3834067.6
A30: 27 | B30: 46230 | E30: 2120 | F30: 103.8 | G30: =E30*F30 -> 220056 | J30: =H30*I30 -> 0 | K30: =G30+J30 -> 220056 | L30: 220000 | M30: =M29+K30-L30 -> 3834123.6 | N30: HPCL
A31: 28 | B31: 46231 | G31: =E31*F31 -> 0 | J31: =H31*I31 -> 0 | K31: =G31+J31 -> 0 | M31: =M30+K31-L31 -> 3834123.6
A32: 29 | B32: 46232 | E32: 2408.72 | F32: 103.8 | G32: =E32*F32 -> 250025.14 | J32: =H32*I32 -> 0 | K32: =G32+J32 -> 250025.14 | L32: 250000 | M32: =M31+K32-L32 -> 3834148.7 | N32: HPCL
A33: 30 | B33: 46233 | G33: =E33*F33 -> 0 | J33: =H33*I33 -> 0 | K33: =G33+J33 -> 0 | M33: =M32+K33-L33 -> 3834148.7
A34: 31 | G34: =E34*F34 -> 0 | K34: =G34+J34 -> 0 | M34: =M33+K34-L34 -> 3834148.7
A35: 32 | G35: =E35*F35 -> 0 | J35: =H35*I35 -> 0 | K35: =G35+J35 -> 0 | M35: =M34+K35-L35 -> 3834148.7
A36: 33 | G36: =E36*F36 -> 0 | J36: =H36*I36 -> 0 | K36: =G36+J36 -> 0
A37: 34 | G37: =E37*F37 -> 0 | J37: =H37*I37 -> 0 | K37: =G37+J37 -> 0
E38: =SUM(E3:E37) -> 25629.86 | G38: =SUM(G3:G37) -> 2660379.5 | H38: =SUM(H3:H37) -> 245 | J38: =SUM(J3:J37) -> 28344.05 | K38: =SUM(K4:K37) -> 2688723.5 | L38: =SUM(L3:L37) -> 470000

Sheet Khammam-2
A1: Jayasai union bunk
A2: S.No | B2: Date | C2: GRN No | D2: Ind No/Bill No | E2: Diesel (Lts) | F2: Price | G2: Amount | H2: Petrol (Lts) | I2: Price | J2: Amount | K2: Total amount | L2: Amount paid | M2: As 0n Date | N2: Remarks
A3: Opening Balance | K3: 9590244 | M3: 9590244
A4: 1 | B4: 46204 | E4: 6229.42 | F4: 103.82 | G4: =E4*F4 -> 646738.38 | J4: =H4*I4 -> 0 | K4: =G4+J4 -> 646738.38 | M4: =M3+K4-L4 -> 10236982
A5: 2 | B5: 46205 | E5: 6193.54 | F5: 103.82 | G5: =E5*F5 -> 643013.32 | J5: =H5*I5 -> 0 | K5: =G5+J5 -> 643013.32 | M5: =M4+K5-L5 -> 10879996
A6: 3 | B6: 46206 | E6: 7217.38 | F6: 103.82 | G6: =E6*F6 -> 749308.39 | J6: =H6*I6 -> 0 | K6: =G6+J6 -> 749308.39 | M6: =M5+K6-L6 -> 11629304
A7: 4 | B7: 46207 | E7: 6415.09 | F7: 103.82 | G7: =E7*F7 -> 666014.64 | J7: =H7*I7 -> 0 | K7: =G7+J7 -> 666014.64 | M7: =M6+K7-L7 -> 12295319
A8: 5 | B8: 46208 | E8: 6004 | F8: 103.82 | G8: =E8*F8 -> 623335.28 | J8: =H8*I8 -> 0 | K8: =G8+J8 -> 623335.28 | M8: =M7+K8-L8 -> 12918654
A9: 6 | B9: 46209 | E9: 6433.17 | F9: 103.82 | G9: =E9*F9 -> 667891.71 | J9: =H9*I9 -> 0 | K9: =G9+J9 -> 667891.71 | M9: =M8+K9-L9 -> 13586546
A10: 7 | B10: 46210 | E10: 5000 | F10: 103.82 | G10: =E10*F10 -> 519100 | H10: 95 | I10: 115.72 | J10: =H10*I10 -> 10993.4 | K10: =G10+J10 -> 530093.4 | M10: =M9+K10-L10 -> 14116639
A11: 8 | B11: 46211 | E11: 2800 | F11: 103.82 | G11: =E11*F11 -> 290696 | H11: 40 | I11: 115.72 | J11: =H11*I11 -> 4628.8 | K11: =G11+J11 -> 295324.8 | M11: =M10+K11-L11 -> 14411964
A12: 9 | B12: 46212 | E12: 2700 | F12: 103.82 | G12: =E12*F12 -> 280314 | H12: 20 | I12: 115.72 | J12: =H12*I12 -> 2314.4 | K12: =G12+J12 -> 282628.4 | M12: =M11+K12-L12 -> 14694592
A13: 10 | B13: 46213 | E13: 5500 | F13: 103.82 | G13: =E13*F13 -> 571010 | H13: 40 | I13: 115.72 | J13: =H13*I13 -> 4628.8 | K13: =G13+J13 -> 575638.8 | M13: =M12+K13-L13 -> 15270231
A14: 11 | B14: 46214 | E14: 6150 | F14: 103.82 | G14: =E14*F14 -> 638493 | H14: 40 | I14: 115.72 | J14: =H14*I14 -> 4628.8 | K14: =G14+J14 -> 643121.8 | M14: =M13+K14-L14 -> 15913353
A15: 12 | B15: 46215 | E15: 2500 | F15: 103.82 | G15: =E15*F15 -> 259550 | J15: =H15*I15 -> 0 | K15: =G15+J15 -> 259550 | M15: =M14+K15-L15 -> 16172903 | S15: 5000000
A16: 13 | B16: 46216 | E16: 2000 | F16: 103.82 | G16: =E16*F16 -> 207640 | H16: 60 | I16: 115.72 | J16: =H16*I16 -> 6943.2 | K16: =G16+J16 -> 214583.2 | M16: =M15+K16-L16 -> 16387486 | Q16: 6086287 | S16: 6086287
A17: 14 | B17: 46217 | G17: =E17*F17 -> 0 | J17: =H17*I17 -> 0 | K17: =G17+J17 -> 0 | M17: =M16+K17-L17 -> 16387486 | S17: =SUM(S15:S16) -> 11086287
A18: 15 | B18: 46218 | E18: 3000 | F18: 103.82 | G18: =E18*F18 -> 311460 | J18: =H18*I18 -> 0 | K18: =G18+J18 -> 311460 | M18: =M17+K18-L18 -> 16698946 | S18: 1162961.4
A19: 16 | B19: 46219 | E19: 2000 | F19: 103.82 | G19: =E19*F19 -> 207640 | H19: 20 | I19: 115.72 | J19: =H19*I19 -> 2314.4 | K19: =G19+J19 -> 209954.4 | M19: =M18+K19-L19 -> 16908901 | S19: =S17-S18 -> 9923325.6
A20: 17 | B20: 46220 | E20: 2000 | F20: 103.82 | G20: =E20*F20 -> 207640 | H20: 75 | I20: 115.72 | J20: =H20*I20 -> 8679 | K20: =G20+J20 -> 216319 | M20: =M19+K20-L20 -> 17125220 | S20: 32869.06
A21: 18 | B21: 46221 | E21: 4115.59 | F21: 103.82 | G21: =E21*F21 -> 427280.55 | J21: =H21*I21 -> 0 | K21: =G21+J21 -> 427280.55 | M21: =M20+K21-L21 -> 17552500 | N21: DGM Sir | O21: 350000 | S21: =S19+S20 -> 9956194.6
A22: 19 | B22: 46222 | G22: =E22*F22 -> 0 | J22: =H22*I22 -> 0 | K22: =G22+J22 -> 0 | M22: =M21+K22-L22 -> 17552500
A23: 20 | B23: 46223 | E23: 5716.02 | F23: 103.82 | G23: =E23*F23 -> 593437.2 | H23: 80 | I23: 115.72 | J23: =H23*I23 -> 9257.6 | K23: =G23+J23 -> 602694.8 | M23: =M22+K23-L23 -> 18155195 | N23: DGM Sir | O23: 500000
A24: 21 | B24: 46224 | G24: =E24*F24 -> 0 | J24: =H24*I24 -> 0 | K24: =G24+J24 -> 0 | M24: =M23+K24-L24 -> 18155195
A25: 22 | B25: 46225 | E25: 2800 | F25: 103.82 | G25: =E25*F25 -> 290696 | J25: =H25*I25 -> 0 | K25: =G25+J25 -> 290696 | L25: 290696 | M25: =M24+K25-L25 -> 18155195 | N25: IOCL Card
A26: 23 | B26: 46226 | G26: =E26*F26 -> 0 | H26: 75 | I26: 115.72 | J26: =H26*I26 -> 8679 | K26: =G26+J26 -> 8679 | M26: =M25+K26-L26 -> 18163874
A27: 24 | B27: 46227 | D27: 26-27/S1 (MP3 Grease) | E27: 546 | F27: 332.76 | G27: =E27*F27 -> 181686.96 | J27: =H27*I27 -> 0 | K27: =G27+J27 -> 181686.96 | M27: =M26+K27-L27 -> 18345561
A28: 25 | B28: 46228 | G28: =E28*F28 -> 0 | H28: 95 | I28: 115.72 | J28: =H28*I28 -> 10993.4 | K28: =G28+J28 -> 10993.4 | M28: =M27+K28-L28 -> 18356554
A29: 26 | B29: 46229 | G29: =E29*F29 -> 0 | J29: =H29*I29 -> 0 | K29: =G29+J29 -> 0 | M29: =M28+K29-L29 -> 18356554
A30: 27 | B30: 46230 | G30: =E30*F30 -> 0 | J30: =H30*I30 -> 0 | K30: =G30+J30 -> 0 | M30: =M29+K30-L30 -> 18356554
A31: 28 | B31: 46231 | E31: 2802.93 | F31: 103.82 | G31: =E31*F31 -> 291000.19 | H31: 105 | I31: 115.72 | J31: =H31*I31 -> 12150.6 | K31: =G31+J31 -> 303150.79 | M31: =M30+K31-L31 -> 18659705 | N31: DGM Sir | O31: 291000
A32: 29 | B32: 46232 | E32: 2600 | F32: 103.82 | G32: =E32*F32 -> 269932 | J32: =H32*I32 -> 0 | K32: =G32+J32 -> 269932 | M32: =M31+K32-L32 -> 18929637 | N32: DGM Sir | O32: 269932
A33: 30 | B33: 46233 | G33: =E33*F33 -> 0 | J33: =H33*I33 -> 0 | K33: =G33+J33 -> 0 | M33: =M32+K33-L33 -> 18929637 | O33: =SUM(O21:O32) -> 1410932
A34: 31 | B34: 46234 | G34: =E34*F34 -> 0 | J34: =H34*I34 -> 0 | K34: =G34+J34 -> 0 | M34: =M33+K34-L34 -> 18929637
A35: 32 | G35: =E35*F35 -> 0 | J35: =H35*I35 -> 0 | K35: =G35+J35 -> 0 | M35: =M34+K35-L35 -> 18929637
A36: 33 | G36: =E36*F36 -> 0 | J36: =H36*I36 -> 0 | K36: =G36+J36 -> 0 | M36: =M35+K36-L36 -> 18929637
E38: =SUM(E4:E36) -> 90723.14 | G38: =SUM(G4:G36) -> 9543877.6 | H38: =SUM(H4:H36) -> 745 | J38: =SUM(J4:J36) -> 86211.4 | K38: =SUM(K4:K36) -> 9630089 | L38: =SUM(L4:L36) -> 290696

Sheet Khammam-3
A1: JSASFuel Genie India Pvt.Ltd
A2: S.No | B2: Date | C2: GRN No | D2: Ind No/Bill No | E2: Diesel (Lts) | F2: Price | G2: Amount | H2: Petrol (Lts) | I2: Price | J2: Amount | K2: Total amount | L2: Amount paid | M2: As 0n Date | N2: Remarks
A3: Opening Balance | K3: 1072600 | M3: 1072600
A4: 1 | B4: 46204 | G4: =E4*F4 -> 0 | J4: =H4*I4 -> 0 | K4: =G4+J4 -> 0 | M4: =M3+K4-L4 -> 1072600
A5: 2 | B5: 46205 | G5: =E5*F5 -> 0 | J5: =H5*I5 -> 0 | K5: =G5+J5 -> 0 | M5: =M4+K5-L5 -> 1072600
A6: 3 | B6: 46206 | G6: =E6*F6 -> 0 | J6: =H6*I6 -> 0 | K6: =G6+J6 -> 0 | M6: =M5+K6-L6 -> 1072600
A7: 4 | B7: 46207 | G7: =E7*F7 -> 0 | J7: =H7*I7 -> 0 | K7: =G7+J7 -> 0 | M7: =M6+K7-L7 -> 1072600
A8: 5 | B8: 46208 | G8: =E8*F8 -> 0 | J8: =H8*I8 -> 0 | K8: =G8+J8 -> 0 | M8: =M7+K8-L8 -> 1072600
A9: 6 | B9: 46209 | G9: =E9*F9 -> 0 | J9: =H9*I9 -> 0 | K9: =G9+J9 -> 0 | M9: =M8+K9-L9 -> 1072600
A10: 7 | B10: 46210 | G10: =E10*F10 -> 0 | J10: =H10*I10 -> 0 | K10: =G10+J10 -> 0 | M10: =M9+K10-L10 -> 1072600
A11: 8 | B11: 46211 | G11: =E11*F11 -> 0 | J11: =H11*I11 -> 0 | K11: =G11+J11 -> 0 | M11: =M10+K11-L11 -> 1072600
A12: 9 | B12: 46212 | G12: =E12*F12 -> 0 | J12: =H12*I12 -> 0 | K12: =G12+J12 -> 0 | M12: =M11+K12-L12 -> 1072600
A13: 10 | B13: 46213 | G13: =E13*F13 -> 0 | J13: =H13*I13 -> 0 | K13: =G13+J13 -> 0 | M13: =M12+K13-L13 -> 1072600
A14: 11 | B14: 46214 | G14: =E14*F14 -> 0 | J14: =H14*I14 -> 0 | K14: =G14+J14 -> 0 | M14: =M13+K14-L14 -> 1072600
A15: 12 | B15: 46215 | G15: =E15*F15 -> 0 | J15: =H15*I15 -> 0 | K15: =G15+J15 -> 0 | M15: =M14+K15-L15 -> 1072600
... A25: 22 | B25: 46225 | G25: =E25*F25 -> 0 | J25: =H25*I25 -> 0 | K25: =G25+J25 -> 0 | M25: =M24+K25-L25 -> 1072600
A26: 23 | B26: 46226 | E26: 6000 | F26: 103.8 | G26: =E26*F26 -> 622800 | J26: =H26*I26 -> 0 | K26: =G26+J26 -> 622800 | M26: =M25+K26-L26 -> 1695400
A27: 24 | B27: 46227 | E27: 4000 | F27: 103.82 | G27: =E27*F27 -> 415280 | J27: =H27*I27 -> 0 | K27: =G27+J27 -> 415280 | M27: =M26+K27-L27 -> 2110680
A28: 25 | B28: 46228 | G28: =E28*F28 -> 0 | J28: =H28*I28 -> 0 | K28: =G28+J28 -> 0 | L28: 600000 | M28: =M27+K28-L28 -> 1510680
A29: 26 | B29: 46229 | G29: =E29*F29 -> 0 | J29: =H29*I29 -> 0 | K29: =G29+J29 -> 0 | M29: =M28+K29-L29 -> 1510680
A30: 27 | B30: 46230 | G30: =E30*F30 -> 0 | J30: =H30*I30 -> 0 | K30: =G30+J30 -> 0 | M30: =M29+K30-L30 -> 1510680
A31: 28 | B31: 46231 | G31: =E31*F31 -> 0 | J31: =H31*I31 -> 0 | K31: =G31+J31 -> 0 | M31: =M30+K31-L31 -> 1510680
A32: 29 | B32: 46232 | G32: =E32*F32 -> 0 | J32: =H32*I32 -> 0 | K32: =G32+J32 -> 0 | M32: =M31+K32-L32 -> 1510680
A33: 30 | B33: 46233 | G33: =E33*F33 -> 0 | J33: =H33*I33 -> 0 | K33: =G33+J33 -> 0 | M33: =M32+K33-L33 -> 1510680
A34: 31 | G34: =E34*F34 -> 0 | J34: =H34*I34 -> 0 | K34: =G34+J34 -> 0 | M34: =M33+K34-L34 -> 1510680
E35: =SUM(E4:E34) -> 10000 | G35: =SUM(G4:G34) -> 1038080 | H35: =SUM(H4:H34) -> 0 | J35: =SUM(J4:J34) -> 0 | K35: =SUM(K4:K34) -> 1038080 | L35: =SUM(L4:L34) -> 600000

Sheet  Khammam&Cash
A1: Cash &Carry
A2: S.No | B2: Date | D2: Ind No/Bill No | E2: Diesel (Lts) | F2: Price | G2: Amount | H2: Petrol (Lts) | I2: Price | J2: Amount | K2: Total amount | L2: Amount paid | M2: As 0n Date | N2: Remarks
A3: Opening Balance | K3: 0 | M3: 0
A4: 1 | G4: =E4*F4 -> 0 | K4: =G4+J4 -> 0 | L4: =H4+K4 -> 0 | M4: =M3+K4-L4 -> 0
A5: 2 | G5: =E5*F5 -> 0 | J5: =H5*I5 -> 0 | K5: =G5+J5 -> 0 | L5: =H5+K5 -> 0 | M5: =M4+K5-L5 -> 0
A6: 3 | G6: =E6*F6 -> 0 | J6: =H6*I6 -> 0 | K6: =G6+J6 -> 0 | L6: =H6+K6 -> 0 | M6: =M5+K6-L6 -> 0
A7: 4 | G7: =E7*F7 -> 0 | J7: =H7*I7 -> 0 | K7: =G7+J7 -> 0 | L7: =H7+K7 -> 0 | M7: =M6+K7-L7 -> 0
A8: 5 | G8: =E8*F8 -> 0 | J8: =H8*I8 -> 0 | K8: =G8+J8 -> 0 | L8: =H8+K8 -> 0 | M8: =M7+K8-L8 -> 0
A9: 6 | G9: =E9*F9 -> 0 | J9: =H9*I9 -> 0 | K9: =G9+J9 -> 0 | L9: =H9+K9 -> 0 | M9: =M8+K9-L9 -> 0
A10: 7 | G10: =E10*F10 -> 0 | J10: =H10*I10 -> 0 | K10: =G10+J10 -> 0 | L10: =H10+K10 -> 0 | M10: =M9+K10-L10 -> 0
A11: 8 | G11: =E11*F11 -> 0 | J11: =H11*I11 -> 0 | K11: =G11+J11 -> 0 | L11: =H11+K11 -> 0 | M11: =M10+K11-L11 -> 0
A12: 9 | G12: =E12*F12 -> 0 | J12: =H12*I12 -> 0 | K12: =G12+J12 -> 0 | L12: =H12+K12 -> 0 | M12: =M11+K12-L12 -> 0
A13: 10 | G13: =E13*F13 -> 0 | J13: =H13*I13 -> 0 | K13: =G13+J13 -> 0 | L13: =H13+K13 -> 0 | M13: =M12+K13-L13 -> 0
A14: 11 | G14: =E14*F14 -> 0 | J14: =H14*I14 -> 0 | K14: =G14+J14 -> 0 | L14: =H14+K14 -> 0 | M14: =M13+K14-L14 -> 0
A15: 12 | G15: =E15*F15 -> 0 | J15: =H15*I15 -> 0 | K15: =G15+J15 -> 0 | L15: =H15+K15 -> 0 | M15: =M14+K15-L15 -> 0
A16: 13 | G16: =E16*F16 -> 0 | J16: =H16*I16 -> 0 | K16: =G16+J16 -> 0 | L16: =H16+K16 -> 0 | M16: =M15+K16-L16 -> 0
... A22: 19 | G22: =E22*F22 -> 0 | J22: =H22*I22 -> 0 | K22: =G22+J22 -> 0 | L22: =H22+K22 -> 0 | M22: =M21+K22-L22 -> 0
A23: 20 | G23: =E23*F23 -> 0 | J23: =H23*I23 -> 0 | K23: =G23+J23 -> 0 | L23: 0 | M23: =M22+K23-L23 -> 0
A24: 21 | G24: =E24*F24 -> 0 | J24: =H24*I24 -> 0 | K24: =G24+J24 -> 0 | L24: =H24+K24 -> 0 | M24: =M23+K24-L24 -> 0
A25: 22 | G25: =E25*F25 -> 0 | J25: =H25*I25 -> 0 | K25: =G25+J25 -> 0 | L25: =H25+K25 -> 0 | M25: =M24+K25-L25 -> 0
A26: 23 | G26: =E26*F26 -> 0 | J26: =H26*I26 -> 0 | K26: =G26+J26 -> 0 | L26: =H26+K26 -> 0 | M26: =M25+K26-L26 -> 0
A27: 24 | G27: =E27*F27 -> 0 | K27: =G27+J27 -> 0 | L27: =H27+K27 -> 0 | M27: =M26+K27-L27 -> 0
A28: 25 | B28: 46227 | C28: Stambhadri Fuel Park HPCL | E28: 2800 | F28: 103.8 | G28: =E28*F28 -> 290640 | J28: =H28*I28 -> 0 | K28: =G28+J28 -> 290640 | L28: =H28+K28 -> 290640 | M28: =M26+K28-L28 -> 0
A29: 26 | B29: 46228 | C29: Stambhadri Fuel Park HPCL | E29: 2800 | F29: 103.8 | G29: =E29*F29 -> 290640 | J29: =H29*I29 -> 0 | K29: =G29+J29 -> 290640 | L29: =H29+K29 -> 290640 | M29: =M28+K29-L29 -> 0
A30: 27 | B30: 46234 | C30: Stambhadri Fuel Park HPCL | E30: 2408.48 | F30: 103.8 | G30: =E30*F30 -> 250000.22 | J30: =H30*I30 -> 0 | K30: =G30+J30 -> 250000.22 | L30: =H30+K30 -> 250000.22 | M30: =M29+K30-L30 -> 0
A31: 28 | G31: =E31*F31 -> 0 | J31: =H31*I31 -> 0 | K31: =G31+J31 -> 0 | L31: =H31+K31 -> 0 | M31: =M30+K31-L31 -> 0
A32: 29 | G32: =E32*F32 -> 0 | J32: =H32*I32 -> 0 | K32: =G32+J32 -> 0 | L32: =H32+K32 -> 0 | M32: =M31+K32-L32 -> 0
A33: 30 | G33: =E33*F33 -> 0 | J33: =H33*I33 -> 0 | K33: =G33+J33 -> 0 | L33: =H33+K33 -> 0 | M33: =M32+K33-L33 -> 0
A34: 31 | G34: =E34*F34 -> 0 | J34: =H34*I34 -> 0 | K34: =G34+J34 -> 0 | L34: =H34+K34 -> 0 | M34: =M33+K34-L34 -> 0
A35: 32 | G35: =E35*F35 -> 0 | K35: =G35+J35 -> 0 | L35: =H35+K35 -> 0 | M35: =M34+K35-L35 -> 0
A36: 33 | G36: =E36*F36 -> 0 | J36: =H36*I36 -> 0 | K36: =G36+J36 -> 0 | L36: =H36+K36 -> 0 | M36: =M35+K36-L36 -> 0
A37: 34 | G37: =E37*F37 -> 0 | J37: =H37*I37 -> 0 | K37: =G37+J37 -> 0 | L37: =H37+K37 -> 0 | M37: =M36+K37-L37 -> 0
G38: =E38*F38 -> 0 | K38: =G38+J38 -> 0 | L38: =H38+K38 -> 0 | M38: =M37+K38-L38 -> 0
G39: =E39*F39 -> 0 | K39: =G39+J39 -> 0 | L39: =H39+K39 -> 0 | M39: =M38+K39-L39 -> 0
G40: =E40*F40 -> 0 | K40: =G40+J40 -> 0 | L40: =H40+K40 -> 0 | M40: =M39+K40-L40 -> 0
M41: =M40+K41-L41 -> 0
A45: 35 | G45: =E45*F45 -> 0 | J45: =H45*I45 -> 0 | K45: =G45+J45 -> 0
E46: =SUM(E3:E45) -> 8008.48 | G46: =SUM(G3:G45) -> 831280.22 | H46: =SUM(H3:H45) -> 0 | J46: =SUM(J3:J45) -> 0 | K46: =SUM(K4:K45) -> 831280.22 | L46: =SUM(L3:L45) -> 831280.22

Sheet Jadcherla-4
A1: Shree Poornima F/S
A2: S.No | B2: Date | C2: GRN No | D2: Ind No/Bill No | E2: Diesel (Lts) | F2: Price | G2: Amount | H2: Petrol (Lts) | I2: Price | J2: Amount | K2: Total amount | L2: Amount paid | M2: As on date | N2: Remarks
A3: Opening Balance | M3: 6863.48
A4: 1 | B4: 46204 | G4: =E4*F4 -> 0 | J4: =H4*I4 -> 0 | K4: =G4+J4 -> 0 | L4: 0 | M4: =M3+K4-L4 -> 6863.48
A5: 2 | B5: 46205 | G5: =E5*F5 -> 0 | J5: =H5*I5 -> 0 | K5: =G5+J5 -> 0 | L5: 0 | M5: =M4+K5-L5 -> 6863.48
A6: 3 | B6: 46206 | E6: 100 | F6: 104.42 | G6: =E6*F6 -> 10442 | J6: =H6*I6 -> 0 | K6: =G6+J6 -> 10442 | L6: 0 | M6: =M5+K6-L6 -> 17305.48
A7: 4 | B7: 46207 | E7: 500 | F7: 104.42 | G7: =E7*F7 -> 52210 | J7: =H7*I7 -> 0 | K7: =G7+J7 -> 52210 | L7: 0 | M7: =M6+K7-L7 -> 69515.48
A8: 5 | B8: 46208 | G8: =E8*F8 -> 0 | J8: =H8*I8 -> 0 | K8: =G8+J8 -> 0 | L8: 0 | M8: =M7+K8-L8 -> 69515.48
A9: 6 | B9: 46209 | G9: =E9*F9 -> 0 | J9: =H9*I9 -> 0 | K9: =G9+J9 -> 0 | L9: 0 | M9: =M8+K9-L9 -> 69515.48
A10: 7 | B10: 46210 | G10: =E10*F10 -> 0 | J10: =H10*I10 -> 0 | K10: =G10+J10 -> 0 | L10: 0 | M10: =M9+K10-L10 -> 69515.48
A11: 8 | B11: 46211 | G11: =E11*F11 -> 0 | J11: =H11*I11 -> 0 | K11: =G11+J11 -> 0 | L11: 0 | M11: =M10+K11-L11 -> 69515.48
A12: 9 | B12: 46212 | G12: =E12*F12 -> 0 | J12: =H12*I12 -> 0 | K12: =G12+J12 -> 0 | L12: 0 | M12: =M11+K12-L12 -> 69515.48
A13: 10 | B13: 46213 | G13: =E13*F13 -> 0 | J13: =H13*I13 -> 0 | K13: =G13+J13 -> 0 | L13: 0 | M13: =M12+K13-L13 -> 69515.48
A14: 11 | B14: 46214 | G14: =E14*F14 -> 0 | H14: 20 | I14: 116.33 | J14: =H14*I14 -> 2326.6 | K14: =G14+J14 -> 2326.6 | M14: =M13+K14-L14 -> 71842.08
A15: 12 | B15: 46215 | G15: =E15*F15 -> 0 | J15: =H15*I15 -> 0 | K15: =G15+J15 -> 0 | M15: =M14+K15-L15 -> 71842.08
A16: 13 | B16: 46216 | G16: =E16*F16 -> 0 | J16: =H16*I16 -> 0 | K16: =G16+J16 -> 0 | M16: =M15+K16-L16 -> 71842.08
A17: 14 | B17: 46217 | G17: =E17*F17 -> 0 | J17: =H17*I17 -> 0 | K17: =G17+J17 -> 0 | M17: =M16+K17-L17 -> 71842.08
A18: 15 | B18: 46218 | G18: =E18*F18 -> 0 | J18: =H18*I18 -> 0 | K18: =G18+J18 -> 0 | M18: =M17+K18-L18 -> 71842.08
A19: 16 | B19: 46219 | G19: 0 | J19: 0 | K19: 0 | M19: =M18+K19-L19 -> 71842.08
A20: 17 | B20: 46220 | G20: =E20*F20 -> 0 | J20: =H20*I20 -> 0 | K20: =G20+J20 -> 0 | L20: 50000 | M20: =M19+K20-L20 -> 21842.08 | N20: Poornima f/s machine not working swiping the same amont Sri Srinivasa Filling Station
A21: 18 | B21: 46221 | E21: 250 | F21: 104.42 | G21: =E21*F21 -> 26105 | J21: =H21*I21 -> 0 | K21: =G21+J21 -> 26105 | M21: =M20+K21-L21 -> 47947.08
A22: 19 | B22: 46222 | G22: =E22*F22 -> 0 | J22: =H22*I22 -> 0 | K22: =G22+J22 -> 0 | L22: 0 | M22: =M21+K22-L22 -> 47947.08
A23: 20 | B23: 46223 | G23: =E23*F23 -> 0 | J23: =H23*I23 -> 0 | K23: =G23+J23 -> 0 | L23: 0 | M23: =M22+K23-L23 -> 47947.08
A24: 21 | B24: 46224 | G24: =E24*F24 -> 0 | J24: =H24*I24 -> 0 | K24: =G24+J24 -> 0 | L24: 0 | M24: =M23+K24-L24 -> 47947.08
A25: 22 | B25: 46225 | G25: =E25*F25 -> 0 | J25: =H25*I25 -> 0 | K25: =G25+J25 -> 0 | L25: 0 | M25: =M24+K25-L25 -> 47947.08
A26: 23 | B26: 46226 | G26: =E26*F26 -> 0 | J26: =H26*I26 -> 0 | K26: =G26+J26 -> 0 | L26: 0 | M26: =M25+K26-L26 -> 47947.08
A27: 24 | B27: 46227 | G27: =E27*F27 -> 0 | J27: =H27*I27 -> 0 | K27: =G27+J27 -> 0 | L27: 0 | M27: =M26+K27-L27 -> 47947.08
A28: 25 | B28: 46228 | G28: =E28*F28 -> 0 | H28: 20 | I28: 116.33 | J28: =H28*I28 -> 2326.6 | K28: =G28+J28 -> 2326.6 | L28: 0 | M28: =M27+K28-L28 -> 50273.68
A29: 26 | B29: 46229 | G29: =E29*F29 -> 0 | J29: =H29*I29 -> 0 | K29: =G29+J29 -> 0 | L29: 0 | M29: =M28+K29-L29 -> 50273.68
A30: 27 | B30: 46230 | G30: =E30*F30 -> 0 | J30: =H30*I30 -> 0 | K30: =G30+J30 -> 0 | L30: 0 | M30: =M29+K30-L30 -> 50273.68
A31: 28 | B31: 46231 | G31: =E31*F31 -> 0 | J31: =H31*I31 -> 0 | K31: =G31+J31 -> 0 | L31: 0 | M31: =M30+K31-L31 -> 50273.68
A32: 29 | B32: 46232 | G32: =E32*F32 -> 0 | J32: =H32*I32 -> 0 | K32: =G32+J32 -> 0 | L32: 0 | M32: =M31+K32-L32 -> 50273.68
A33: 30 | B33: 46233 | G33: =E33*F33 -> 0 | H33: 0 | I33: 0 | J33: =H33*I33 -> 0 | K33: =G33+J33 -> 0 | L33: 0 | M33: =M32+K33-L33 -> 50273.68
A34: 31 | G34: =E34*F34 -> 0 | J34: =H34*I34 -> 0 | K34: =G34+J34 -> 0 | M34: =M33+K34-L34 -> 50273.68
E35: =SUM(E4:E34) -> 850 | G35: =SUM(G4:G34) -> 88757 | H35: =SUM(H4:H34) -> 40 | J35: =SUM(J4:J34) -> 4653.2 | K35: =SUM(K4:K34) -> 93410.2 | L35: =SUM(L4:L34) -> 50000

Sheet  Sangareddy-2
A1: Durga Bhavani F/S
A2: S.No | B2: Date | C2: GRN No | D2: Ind no/Bill No | E2: Diesel (Lts) | F2: Price | G2: Amount | H2: Petrol (Lts) | I2: Price | J2: Amount | K2: Total amount | L2: Amount paid | M2: As on Date | N2: Remarks
A3: Opening Balance | M3: 128359.22
A4: 1 | B4: 45839 | E4: 438 | F4: 104.56 | G4: =E4*F4 -> 45797.28 | H4: 5 | I4: 116.54 | J4: =H4*I4 -> 582.7 | K4: =G4+J4 -> 46379.98 | M4: =M3+K4-L4 -> 174739.2
A5: 2 | B5: 45840 | E5: 43.8 | F5: 104.56 | G5: =E5*F5 -> 4579.728 | J5: =H5*I5 -> 0 | K5: =G5+J5 -> 4579.728 | M5: =M4+K5-L5 -> 179318.92
A6: 3 | B6: 45841 | E6: 37.65 | F6: 104.56 | G6: =E6*F6 -> 3936.684 | J6: =H6*I6 -> 0 | K6: =G6+J6 -> 3936.684 | M6: =M5+K6-L6 -> 183255.61
A7: 4 | B7: 45842 | G7: =E7*F7 -> 0 | J7: =H7*I7 -> 0 | K7: =G7+J7 -> 0 | M7: =M6+K7-L7 -> 183255.61
A8: 5 | B8: 45843 | G8: =E8*F8 -> 0 | J8: =H8*I8 -> 0 | K8: =G8+J8 -> 0 | M8: =M7+K8-L8 -> 183255.61
A9: 6 | B9: 45844 | G9: =E9*F9 -> 0 | J9: =H9*I9 -> 0 | K9: =G9+J9 -> 0 | M9: =M8+K9-L9 -> 183255.61
A10: 7 | B10: 45845 | G10: =E10*F10 -> 0 | J10: =H10*I10 -> 0 | K10: =G10+J10 -> 0 | M10: =M9+K10-L10 -> 183255.61
A11: 8 | B11: 45846 | G11: =E11*F11 -> 0 | H11: 15 | I11: 116.54 | J11: =H11*I11 -> 1748.1 | K11: =G11+J11 -> 1748.1 | M11: =M10+K11-L11 -> 185003.71
A12: 9 | B12: 45847 | G12: =E12*F12 -> 0 | J12: =H12*I12 -> 0 | K12: =G12+J12 -> 0 | M12: =M11+K12-L12 -> 185003.71
A13: 10 | B13: 45848 | G13: =E13*F13 -> 0 | H13: 5 | I13: 116.54 | J13: =H13*I13 -> 582.7 | K13: =G13+J13 -> 582.7 | M13: =M12+K13-L13 -> 185586.41
A14: 11 | B14: 45849 | G14: =E14*F14 -> 0 | J14: =H14*I14 -> 0 | K14: =G14+J14 -> 0 | M14: =M13+K14-L14 -> 185586.41
A15: 12 | B15: 45850 | G15: =E15*F15 -> 0 | H15: 5 | I15: 116.54 | J15: =H15*I15 -> 582.7 | K15: =G15+J15 -> 582.7 | M15: =M14+K15-L15 -> 186169.11
A16: 13 | B16: 45851 | G16: =E16*F16 -> 0 | J16: =H16*I16 -> 0 | K16: =G16+J16 -> 0 | M16: =M15+K16-L16 -> 186169.11
A17: 14 | B17: 45852 | G17: =E17*F17 -> 0 | J17: =H17*I17 -> 0 | K17: =G17+J17 -> 0 | M17: =M16+K17-L17 -> 186169.11
A18: 15 | B18: 45853 | G18: =E18*F18 -> 0 | J18: =H18*I18 -> 0 | K18: =G18+J18 -> 0 | L18: 180000 | M18: =M17+K18-L18 -> 6169.1074
A19: 16 | B19: 45854 | G19: =E19*F19 -> 0 | J19: =H19*I19 -> 0 | K19: =G19+J19 -> 0 | M19: =M18+K19-L19 -> 6169.1074
A20: 17 | B20: 45855 | G20: =E20*F20 -> 0 | J20: =H20*I20 -> 0 | K20: =G20+J20 -> 0 | M20: =M19+K20-L20 -> 6169.1074
A21: 18 | B21: 45856 | G21: =E21*F21 -> 0 | J21: =H21*I21 -> 0 | K21: =G21+J21 -> 0 | M21: =M20+K21-L21 -> 6169.1074
A22: 19 | B22: 45857 | G22: =E22*F22 -> 0 | J22: =H22*I22 -> 0 | K22: =G22+J22 -> 0 | M22: =M21+K22-L22 -> 6169.1074
A23: 20 | B23: 45858 | G23: =E23*F23 -> 0 | J23: =H23*I23 -> 0 | K23: =G23+J23 -> 0 | M23: =M22+K23-L23 -> 6169.1074 | Q23: 96.44
A24: 21 | B24: 45859 | G24: =E24*F24 -> 0 | J24: =H24*I24 -> 0 | K24: =G24+J24 -> 0 | M24: =M23+K24-L24 -> 6169.1074
A25: 22 | B25: 45860 | G25: =E25*F25 -> 0 | J25: =H25*I25 -> 0 | K25: =G25+J25 -> 0 | M25: =M24+K25-L25 -> 6169.1074
A26: 23 | B26: 45861 | E26: 245 | F26: 104.56 | G26: =E26*F26 -> 25617.2 | J26: =H26*I26 -> 0 | K26: =G26+J26 -> 25617.2 | M26: =M25+K26-L26 -> 31786.307
A27: 24 | B27: 45862 | G27: =E27*F27 -> 0 | H27: 10 | I27: 116.54 | J27: =H27*I27 -> 1165.4 | K27: =G27+J27 -> 1165.4 | M27: =M26+K27-L27 -> 32951.707
A28: 25 | B28: 45863 | E28: 0 | F28: 104.56 | G28: =E28*F28 -> 0 | H28: 15 | I28: 116.54 | J28: =H28*I28 -> 1748.1 | K28: =G28+J28 -> 1748.1 | M28: =M27+K28-L28 -> 34699.807
A29: 26 | B29: 45864 | E29: 130 | F29: 104.56 | G29: =E29*F29 -> 13592.8 | H29: 5 | I29: 116.54 | J29: =H29*I29 -> 582.7 | K29: =G29+J29 -> 14175.5 | M29: =M28+K29-L29 -> 48875.307
A30: 27 | B30: 45865 | G30: =E30*F30 -> 0 | J30: =H30*I30 -> 0 | K30: =G30+J30 -> 0 | M30: =M29+K30-L30 -> 48875.307
A31: 28 | B31: 45866 | E31: 35.71 | F31: 104.56 | G31: =E31*F31 -> 3733.8376 | J31: =H31*I31 -> 0 | K31: =G31+J31 -> 3733.8376 | M31: =M30+K31-L31 -> 52609.145
A32: 29 | B32: 45867 | G32: =E32*F32 -> 0 | J32: =H32*I32 -> 0 | K32: =G32+J32 -> 0 | M32: =M31+K32-L32 -> 52609.145
A33: 30 | B33: 45868 | G33: =E33*F33 -> 0 | J33: =H33*I33 -> 0 | K33: =G33+J33 -> 0 | L33: 0 | M33: =M32+K33-L33 -> 52609.145
A34: 31 | G34: =E34*F34 -> 0 | J34: =H34*I34 -> 0 | K34: =G34+J34 -> 0 | L34: 0 | M34: =M33+K34-L34 -> 52609.145
E35: =SUM(E4:E34) -> 930.16 | G35: =SUM(G4:G34) -> 97257.53 | H35: =SUM(H4:H34) -> 60 | J35: =SUM(J4:J34) -> 6992.4 | K35: =SUM(K4:K34) -> 104249.93 | L35: =SUM(L4:L34) -> 180000

Sheet  Sangareddy-3
A1: SHIVA PARVATHI FILLING STATION SADASHIVPET
A2: S.No | B2: Date | C2: GRN No | D2: Ind no/Bill No | E2: Diesel (Lts) | F2: Price | G2: Amount | H2: Petrol (Lts) | I2: Price | J2: Amount | K2: Total amount | L2: Amount paid | M2: As on Date | N2: Remarks
A3: Opening Balance | M3: 207619.56
A4: 1 | B4: 45839 | E4: 690 | F4: 104.35 | G4: =E4*F4 -> 72001.5 | J4: =H4*I4 -> 0 | K4: =G4+J4 -> 72001.5 | M4: =M3+K4-L4 -> 279621.06
A5: 2 | B5: 45840 | G5: =E5*F5 -> 0 | H5: 5 | I5: 116.25 | J5: =H5*I5 -> 581.25 | K5: =G5+J5 -> 581.25 | M5: =M4+K5-L5 -> 280202.31
A6: 3 | B6: 45841 | E6: 690 | F6: 104.35 | G6: =E6*F6 -> 72001.5 | J6: =H6*I6 -> 0 | K6: =G6+J6 -> 72001.5 | M6: =M5+K6-L6 -> 352203.81
A7: 4 | B7: 45842 | G7: =E7*F7 -> 0 | H7: 5 | I7: 116.25 | J7: =H7*I7 -> 581.25 | K7: =G7+J7 -> 581.25 | M7: =M6+K7-L7 -> 352785.06
A8: 5 | B8: 45843 | E8: 690 | F8: 104.35 | G8: =E8*F8 -> 72001.5 | J8: =H8*I8 -> 0 | K8: =G8+J8 -> 72001.5 | M8: =M7+K8-L8 -> 424786.56
A9: 6 | B9: 45844 | G9: =E9*F9 -> 0 | H9: 5 | I9: 116.25 | J9: =H9*I9 -> 581.25 | K9: =G9+J9 -> 581.25 | M9: =M8+K9-L9 -> 425367.81
A10: 7 | B10: 45845 | E10: 725 | F10: 104.35 | G10: =E10*F10 -> 75653.75 | J10: =H10*I10 -> 0 | K10: =G10+J10 -> 75653.75 | M10: =M9+K10-L10 -> 501021.56
A11: 8 | B11: 45846 | E11: 690 | F11: 104.35 | G11: =E11*F11 -> 72001.5 | J11: =H11*I11 -> 0 | K11: =G11+J11 -> 72001.5 | M11: =M10+K11-L11 -> 573023.06
A12: 9 | B12: 45847 | E12: 730 | F12: 104.35 | G12: =E12*F12 -> 76175.5 | J12: =H12*I12 -> 0 | K12: =G12+J12 -> 76175.5 | M12: =M11+K12-L12 -> 649198.56
A13: 10 | B13: 45848 | E13: 690 | F13: 104.35 | G13: =E13*F13 -> 72001.5 | J13: =H13*I13 -> 0 | K13: =G13+J13 -> 72001.5 | M13: =M12+K13-L13 -> 721200.06
A14: 11 | B14: 45849 | E14: 690 | F14: 104.35 | G14: =E14*F14 -> 72001.5 | J14: =H14*I14 -> 0 | K14: =G14+J14 -> 72001.5 | M14: =M13+K14-L14 -> 793201.56 | N14: BT
A15: 12 | B15: 45850 | E15: 600 | F15: 104.35 | G15: =E15*F15 -> 62610 | K15: =G15+J15 -> 62610 | M15: =M14+K15-L15 -> 855811.56
A16: 13 | B16: 45851 | E16: 690 | F16: 104.35 | G16: =E16*F16 -> 72001.5 | H16: 6 | I16: 116.25 | J16: =H16*I16 -> 697.5 | K16: =G16+J16 -> 72699 | M16: =M15+K16-L16 -> 928510.56
A17: 14 | B17: 45852 | E17: 690 | F17: 104.35 | G17: =E17*F17 -> 72001.5 | J17: =H17*I17 -> 0 | K17: =G17+J17 -> 72001.5 | M17: =M16+K17-L17 -> 1000512.1
A18: 15 | B18: 45853 | E18: 690 | F18: 104.35 | G18: =E18*F18 -> 72001.5 | J18: =H18*I18 -> 0 | K18: =G18+J18 -> 72001.5 | M18: =M17+K18-L18 -> 1072513.6
A19: 16 | B19: 45854 | E19: 600 | F19: 104.35 | G19: =E19*F19 -> 62610 | J19: =H19*I19 -> 0 | K19: =G19+J19 -> 62610 | M19: =M18+K19-L19 -> 1135123.6
A20: 17 | B20: 45855 | G20: =E20*F20 -> 0 | H20: 12 | I20: 116.25 | J20: =H20*I20 -> 1395 | K20: =G20+J20 -> 1395 | M20: =M19+K20-L20 -> 1136518.6
A21: 18 | B21: 45856 | G21: =E21*F21 -> 0 | H21: 6 | I21: 116.25 | J21: =H21*I21 -> 697.5 | K21: =G21+J21 -> 697.5 | M21: =M20+K21-L21 -> 1137216.1
A22: 19 | B22: 45857 | G22: =E22*F22 -> 0 | J22: =H22*I22 -> 0 | K22: =G22+J22 -> 0 | M22: =M21+K22-L22 -> 1137216.1
A23: 20 | B23: 45858 | E23: 690 | F23: 104.35 | G23: =E23*F23 -> 72001.5 | J23: =H23*I23 -> 0 | K23: =G23+J23 -> 72001.5 | L23: 300000 | M23: =M22+K23-L23 -> 909217.56
A24: 21 | B24: 45859 | G24: =E24*F24 -> 0 | H24: 8.76 | I24: 116.25 | J24: =H24*I24 -> 1018.35 | K24: =G24+J24 -> 1018.35 | M24: =M23+K24-L24 -> 910235.91
A25: 22 | B25: 45860 | G25: =E25*F25 -> 0 | J25: =H25*I25 -> 0 | K25: =G25+J25 -> 0 | M25: =M24+K25-L25 -> 910235.91
A26: 23 | B26: 45861 | G26: =E26*F26 -> 0 | J26: =H26*I26 -> 0 | K26: =G26+J26 -> 0 | M26: =M25+K26-L26 -> 910235.91
A27: 24 | B27: 45862 | G27: =E27*F27 -> 0 | J27: =H27*I27 -> 0 | K27: =G27+J27 -> 0 | M27: =M26+K27-L27 -> 910235.91
A28: 25 | B28: 45863 | E28: 690 | F28: 104.35 | G28: =E28*F28 -> 72001.5 | I28: 116.25 | J28: =H28*I28 -> 0 | K28: =G28+J28 -> 72001.5 | M28: =M27+K28-L28 -> 982237.41
A29: 26 | B29: 45864 | G29: =E29*F29 -> 0 | H29: 6 | I29: 116.25 | J29: =H29*I29 -> 697.5 | K29: =G29+J29 -> 697.5 | M29: =M28+K29-L29 -> 982934.91
A30: 27 | B30: 45865 | E30: 690 | F30: 104.35 | G30: =E30*F30 -> 72001.5 | J30: =H30*I30 -> 0 | K30: =G30+J30 -> 72001.5 | M30: =M29+K30-L30 -> 1054936.4
A31: 28 | B31: 45866 | G31: =E31*F31 -> 0 | J31: =H31*I31 -> 0 | K31: =G31+J31 -> 0 | M31: =M30+K31-L31 -> 1054936.4
A32: 29 | B32: 45867 | G32: =E32*F32 -> 0 | J32: =H32*I32 -> 0 | K32: =G32+J32 -> 0 | M32: =M31+K32-L32 -> 1054936.4
A33: 30 | B33: 45868 | G33: =E33*F33 -> 0 | J33: =H33*I33 -> 0 | K33: =G33+J33 -> 0 | M33: =M32+K33-L33 -> 1054936.4
A34: 31 | B34: 45869 | G34: =E34*F34 -> 0 | J34: =H34*I34 -> 0 | K34: =G34+J34 -> 0 | L34: 300000 | M34: =M33+K34-L34 -> 754936.41
A35: 32 | G35: =E35*F35 -> 0 | J35: =H35*I35 -> 0 | K35: =G35+J35 -> 0 | M35: =M34+K35-L35 -> 754936.41
E36: =SUM(E4:E35) -> 10935 | G36: =SUM(G4:G35) -> 1141067.2 | H36: =SUM(H4:H35) -> 53.76 | J36: =SUM(J4:J35) -> 6249.6 | K36: =SUM(K4:K35) -> 1147316.9 | L36: =SUM(L4:L35) -> 600000

Sheet Narayankhed
A2: S.No | B2: Date | C2: GRN No | D2: Ind no/Bill No | E2: Diesel (Lts) | F2: Price | G2: Amount | H2: Petrol (Lts) | I2: Price | J2: Amount | K2: Total amount | L2: Amount paid | M2: As on Date | N2: Remarks
A3: Opening Balance | M3: 0
A4: 1 | B4: 45839 | G4: =E4*F4 -> 0 | J4: =H4*I4 -> 0 | K4: =G4+J4 -> 0 | L4: =H4+K4 -> 0 | M4: =M3+K4-L4 -> 0
A5: 2 | B5: 45840 | E5: 190.66 | F5: 104.9 | G5: =E5*F5 -> 20000.234 | J5: =H5*I5 -> 0 | K5: =G5+J5 -> 20000.234 | L5: =H5+K5 -> 20000.234 | M5: =M4+K5-L5 -> 0 | N5: BT | S5: 185.65
A6: 3 | B6: 45841 | E6: 285.99 | F6: 104.9 | G6: =E6*F6 -> 30000.351 | J6: =H6*I6 -> 0 | K6: =G6+J6 -> 30000.351 | L6: =H6+K6 -> 30000.351 | M6: =M5+K6-L6 -> 0 | N6: BT | S6: 5
A7: 4 | B7: 45842 | G7: =E7*F7 -> 0 | J7: =H7*I7 -> 0 | K7: =G7+J7 -> 0 | L7: =H7+K7 -> 0 | M7: =M6+K7-L7 -> 0 | S7: 95.33
A8: 5 | B8: 45843 | G8: =E8*F8 -> 0 | J8: =H8*I8 -> 0 | K8: =G8+J8 -> 0 | L8: =H8+K8 -> 0 | M8: =M7+K8-L8 -> 0
A9: 6 | B9: 45844 | G9: =E9*F9 -> 0 | J9: =H9*I9 -> 0 | K9: =G9+J9 -> 0 | L9: 0 | M9: =M8+K9-L9 -> 0
A10: 7 | B10: 45845 | G10: =E10*F10 -> 0 | J10: =H10*I10 -> 0 | K10: =G10+J10 -> 0 | L10: 0 | M10: =M9+K10-L10 -> 0
A11: 8 | B11: 45846 | E11: 476.64 | F11: 104.9 | G11: =E11*F11 -> 49999.536 | J11: =H11*I11 -> 0 | K11: =G11+J11 -> 49999.536 | L11: =H11+K11 -> 49999.536 | M11: =M10+K11-L11 -> 0 | N11: BT
A12: 9 | B12: 45847 | G12: =E12*F12 -> 0 | J12: =H12*I12 -> 0 | K12: =G12+J12 -> 0 | L12: 0 | M12: =M11+K12-L12 -> 0
A13: 10 | B13: 45848 | E13: 476.64 | F13: 104.9 | G13: =E13*F13 -> 49999.536 | J13: =H13*I13 -> 0 | K13: =G13+J13 -> 49999.536 | L13: =H13+K13 -> 49999.536 | M13: =M12+K13-L13 -> 0 | N13: BT
A14: 11 | B14: 45849 | G14: =E14*F14 -> 0 | J14: =H14*I14 -> 0 | K14: =G14+J14 -> 0 | L14: =H14+K14 -> 0 | M14: =M13+K14-L14 -> 0
A15: 12 | B15: 45850 | E15: 190.65 | F15: 104.9 | G15: =E15*F15 -> 19999.185 | J15: =H15*I15 -> 0 | K15: =G15+J15 -> 19999.185 | L15: =H15+K15 -> 19999.185 | M15: =M14+K15-L15 -> 0 | N15: BT
A16: 13 | B16: 45851 | E16: 95.33 | F16: 104.9 | G16: =E16*F16 -> 10000.117 | J16: =H16*I16 -> 0 | K16: =G16+J16 -> 10000.117 | L16: =H16+K16 -> 10000.117 | M16: =M15+K16-L16 -> 0 | N16: BT
A17: 14 | B17: 45852 | E17: 190.65 | F17: 104.9 | G17: =E17*F17 -> 19999.185 | J17: =H17*I17 -> 0 | K17: =G17+J17 -> 19999.185 | L17: =H17+K17 -> 19999.185 | M17: =M16+K17-L17 -> 0 | N17: BT
A18: 15 | B18: 45853 | E18: 0 | F18: 0 | G18: =E18*F18 -> 0 | J18: =H18*I18 -> 0 | K18: =G18+J18 -> 0 | L18: =H18+K18 -> 0 | M18: =M17+K18-L18 -> 0
A19: 16 | B19: 45854 | E19: 190.66 | F19: 104.9 | G19: =E19*F19 -> 20000.234 | J19: =H19*I19 -> 0 | K19: =G19+J19 -> 20000.234 | L19: =H19+K19 -> 20000.234 | M19: =M18+K19-L19 -> 0 | N19: BT
A20: 17 | B20: 45855 | E20: 285.99 | F20: 104.9 | G20: =E20*F20 -> 30000.351 | J20: =H20*I20 -> 0 | K20: =G20+J20 -> 30000.351 | L20: =H20+K20 -> 30000.351 | M20: =M19+K20-L20 -> 0 | N20: BT
A21: 18 | B21: 45856 | G21: =E21*F21 -> 0 | J21: =H21*I21 -> 0 | K21: =G21+J21 -> 0 | L21: =H21+K21 -> 0 | M21: =M20+K21-L21 -> 0
A22: 19 | B22: 45857 | G22: =E22*F22 -> 0 | J22: =H22*I22 -> 0 | K22: =G22+J22 -> 0 | L22: =H22+K22 -> 0 | M22: =M21+K22-L22 -> 0
A23: 20 | B23: 45858 | G23: =E23*F23 -> 0 | J23: =H23*I23 -> 0 | K23: =G23+J23 -> 0 | L23: =H23+K23 -> 0 | M23: =M22+K23-L23 -> 0
A24: 21 | B24: 45859 | G24: =E24*F24 -> 0 | J24: =H24*I24 -> 0 | K24: =G24+J24 -> 0 | L24: =H24+K24 -> 0 | M24: =M23+K24-L24 -> 0
A25: 22 | B25: 45860 | E25: 190.66 | F25: 104.9 | G25: =E25*F25 -> 20000.234 | J25: =H25*I25 -> 0 | K25: =G25+J25 -> 20000.234 | L25: =H25+K25 -> 20000.234 | M25: =M24+K25-L25 -> 0 | N25: BT
A26: 23 | B26: 45861 | E26: 190.66 | F26: 104.9 | G26: =E26*F26 -> 20000.234 | J26: =H26*I26 -> 0 | K26: =G26+J26 -> 20000.234 | L26: =+K26 -> 20000.234 | M26: =M25+K26-L26 -> 0 | N26: BT
A27: 24 | B27: 45862 | G27: =E27*F27 -> 0 | J27: =H27*I27 -> 0 | K27: =G27+J27 -> 0 | L27: =+K27 -> 0 | M27: =M26+K27-L27 -> 0
A28: 25 | B28: 45863 | E28: 95.33 | F28: 104.9 | G28: =E28*F28 -> 10000.117 | J28: =H28*I28 -> 0 | K28: =G28+J28 -> 10000.117 | L28: =+K28 -> 10000.117 | M28: =M27+K28-L28 -> 0 | N28: BT
A29: 26 | B29: 45864 | G29: =E29*F29 -> 0 | J29: =H29*I29 -> 0 | K29: =G29+J29 -> 0 | L29: =+K29 -> 0 | M29: =M28+K29-L29 -> 0
A30: 27 | B30: 45865 | G30: =E30*F30 -> 0 | J30: =H30*I30 -> 0 | K30: =G30+J30 -> 0 | L30: =+K30 -> 0 | M30: =M29+K30-L30 -> 0
A31: 28 | B31: 45866 | G31: =E31*F31 -> 0 | J31: =H31*I31 -> 0 | K31: =G31+J31 -> 0 | L31: =+K31 -> 0 | M31: =M30+K31-L31 -> 0
A32: 29 | B32: 45867 | G32: =E32*F32 -> 0 | J32: =H32*I32 -> 0 | K32: =G32+J32 -> 0 | L32: =+K32 -> 0 | M32: =M31+K32-L32 -> 0
A33: 30 | B33: 45868 | G33: =E33*F33 -> 0 | J33: =H33*I33 -> 0 | K33: =G33+J33 -> 0 | L33: =+K33 -> 0 | M33: =M32+K33-L33 -> 0
A34: 31 | G34: =E34*F34 -> 0 | J34: =H34*I34 -> 0 | K34: =G34+J34 -> 0 | L34: =+K34 -> 0 | M34: 0
E35: =SUM(E4:E34) -> 2859.86 | G35: =SUM(G4:G34) -> 299999.31 | H35: =SUM(H4:H34) -> 0 | J35: =SUM(J4:J34) -> 0 | K35: =SUM(K4:K34) -> 299999.31 | L35: =SUM(L4:L34) -> 299999.31

Sheet Dindi
A1: Akarapu Balakistamma Fillling
A2: S.No | B2: Date | C2: GRN No | D2: Ind no/Bill No | E2: Diesel (Lts) | F2: Price | G2: Amount | H2: Petrol (Lts) | I2: Price | J2: Amount | K2: Total amount | L2: Amount paid | M2: As on Date | N2: Remarks
A3: Opening Balance | M3: 0
A4: 1 | B4: 45839 | G4: =E4*F4 -> 0 | H4: 0 | I4: 0 | J4: =H4*I4 -> 0 | K4: =G4+J4 -> 0 | L4: =+K4 -> 0 | M4: 0
A5: 2 | B5: 45840 | G5: =E5*F5 -> 0 | H5: 0 | I5: 0 | J5: =H5*I5 -> 0 | K5: =G5+J5 -> 0 | L5: =+K5 -> 0 | M5: 0
A6: 3 | B6: 45841 | G6: =E6*F6 -> 0 | H6: 0 | I6: 0 | J6: =H6*I6 -> 0 | K6: =G6+J6 -> 0 | L6: =+K6 -> 0 | M6: 0
A7: 4 | B7: 45842 | G7: =E7*F7 -> 0 | H7: 0 | I7: 0 | J7: =H7*I7 -> 0 | K7: =G7+J7 -> 0 | L7: =+K7 -> 0 | M7: 0
A8: 5 | B8: 45843 | G8: =E8*F8 -> 0 | H8: 0 | I8: 0 | J8: =H8*I8 -> 0 | K8: =G8+J8 -> 0 | L8: =+K8 -> 0 | M8: 0
A9: 6 | B9: 45844 | E9: 37.858 | F9: 104.22 | G9: =E9*F9 -> 3945.5608 | H9: 0 | I9: 0 | J9: =H9*I9 -> 0 | K9: =G9+J9 -> 3945.5608 | L9: =+K9 -> 3945.5608 | M9: 0
A10: 7 | B10: 45845 | G10: =E10*F10 -> 0 | H10: 0 | I10: 0 | J10: =H10*I10 -> 0 | K10: =G10+J10 -> 0 | L10: =+K10 -> 0 | M10: 0
A11: 8 | B11: 45846 | G11: =E11*F11 -> 0 | H11: 0 | I11: 0 | J11: =H11*I11 -> 0 | K11: =G11+J11 -> 0 | L11: =+K11 -> 0 | M11: 0
A12: 9 | B12: 45847 | G12: =E12*F12 -> 0 | H12: 0 | I12: 0 | J12: =H12*I12 -> 0 | K12: =G12+J12 -> 0 | L12: =+K12 -> 0 | M12: 0
A13: 10 | B13: 45848 | G13: =E13*F13 -> 0 | H13: 0 | I13: 0 | J13: =H13*I13 -> 0 | K13: =G13+J13 -> 0 | L13: =+K13 -> 0 | M13: 0
A14: 11 | B14: 45849 | G14: =E14*F14 -> 0 | H14: 0 | I14: 0 | J14: =H14*I14 -> 0 | K14: =G14+J14 -> 0 | L14: =+K14 -> 0 | M14: 0
A15: 12 | B15: 45850 | G15: =E15*F15 -> 0 | H15: 0 | I15: 0 | J15: =H15*I15 -> 0 | K15: =G15+J15 -> 0 | L15: =+K15 -> 0 | M15: 0
A16: 13 | B16: 45851 | G16: =E16*F16 -> 0 | H16: 0 | I16: 0 | J16: =H16*I16 -> 0 | K16: =G16+J16 -> 0 | L16: =+K16 -> 0 | M16: 0
A17: 14 | B17: 45852 | G17: =E17*F17 -> 0 | H17: 0 | I17: 0 | J17: =H17*I17 -> 0 | K17: =G17+J17 -> 0 | L17: =+K17 -> 0 | M17: 0
A18: 15 | B18: 45853 | G18: =E18*F18 -> 0 | H18: 0 | I18: 0 | J18: =H18*I18 -> 0 | K18: =G18+J18 -> 0 | L18: =+K18 -> 0 | M18: 0
A19: 16 | B19: 45854 | E19: 38.44 | F19: 104.95 | G19: =E19*F19 -> 4034.278 | H19: 0 | I19: 0 | J19: =H19*I19 -> 0 | K19: =G19+J19 -> 4034.278 | L19: =+K19 -> 4034.278 | M19: 0
A20: 17 | B20: 45855 | G20: =E20*F20 -> 0 | H20: 0 | I20: 0 | J20: =H20*I20 -> 0 | K20: =G20+J20 -> 0 | L20: =+K20 -> 0 | M20: 0
A21: 18 | B21: 45856 | G21: =E21*F21 -> 0 | H21: 0 | I21: 0 | J21: =H21*I21 -> 0 | K21: =G21+J21 -> 0 | L21: =+K21 -> 0 | M21: 0
A22: 19 | B22: 45857 | G22: =E22*F22 -> 0 | H22: 0 | I22: 0 | J22: =H22*I22 -> 0 | K22: =G22+J22 -> 0 | L22: =+K22 -> 0 | M22: 0
A23: 20 | B23: 45858 | G23: =E23*F23 -> 0 | H23: 0 | I23: 0 | J23: =H23*I23 -> 0 | K23: =G23+J23 -> 0 | L23: =+K23 -> 0 | M23: 0
A24: 21 | B24: 45859 | G24: =E24*F24 -> 0 | H24: 0 | I24: 0 | J24: =H24*I24 -> 0 | K24: =G24+J24 -> 0 | L24: =+K24 -> 0 | M24: 0
A25: 22 | B25: 45860 | E25: 42.43 | F25: 104.95 | G25: =E25*F25 -> 4453.0285 | H25: 0 | I25: 0 | J25: =H25*I25 -> 0 | K25: =G25+J25 -> 4453.0285 | L25: =+K25 -> 4453.0285 | M25: 0
A26: 23 | B26: 45861 | G26: =E26*F26 -> 0 | H26: 0 | I26: 0 | J26: =H26*I26 -> 0 | K26: =G26+J26 -> 0 | L26: =+K26 -> 0 | M26: 0
A27: 24 | B27: 45862 | G27: =E27*F27 -> 0 | H27: 0 | I27: 0 | J27: =H27*I27 -> 0 | K27: =G27+J27 -> 0 | L27: =+K27 -> 0 | M27: 0
A28: 25 | B28: 45863 | H28: 0 | I28: 0 | J28: =H28*I28 -> 0 | K28: =G28+J28 -> 0 | L28: =+K28 -> 0 | M28: 0
A29: 26 | B29: 45864 | G29: =E29*F29 -> 0 | H29: 0 | I29: 0 | J29: =H29*I29 -> 0 | K29: =G29+J29 -> 0 | L29: =+K29 -> 0 | M29: 0
A30: 27 | B30: 45865 | G30: =E30*F30 -> 0 | H30: 0 | I30: 0 | J30: =H30*I30 -> 0 | K30: =G30+J30 -> 0 | L30: =+K30 -> 0 | M30: 0
A31: 28 | B31: 45866 | G31: =E31*F31 -> 0 | H31: 0 | I31: 0 | J31: =H31*I31 -> 0 | K31: =G31+J31 -> 0 | L31: =+K31 -> 0 | M31: 0
A32: 29 | B32: 45867 | G32: =E32*F32 -> 0 | H32: 0 | I32: 0 | J32: =H32*I32 -> 0 | K32: =G32+J32 -> 0 | L32: =+K32 -> 0 | M32: 0
A33: 30 | B33: 45868 | E33: 43.56 | F33: 104.95 | G33: =E33*F33 -> 4571.622 | H33: 0 | I33: 0 | J33: =H33*I33 -> 0 | K33: =G33+J33 -> 4571.622 | L33: =+K33 -> 4571.622 | M33: 0
A34: 31 | G34: =E34*F34 -> 0 | H34: 0 | I34: 0 | J34: =H34*I34 -> 0 | K34: =G34+J34 -> 0 | L34: =+K34 -> 0 | M34: 0
E35: =SUM(E4:E34) -> 162.288 | G35: =SUM(G4:G34) -> 17004.489 | H35: =SUM(H4:H34) -> 0 | J35: =SUM(J4:J34) -> 0 | K35: =SUM(K4:K34) -> 17004.489 | L35: =SUM(L4:L34) -> 17004.489

Sheet Multiple bunks(KKD)
A2: S.No | B2: Date | C2: GRN No | D2: Ind no/Bill No | E2: Diesel (Lts) | F2: Price | G2: Amount | H2: Petrol (Lts) | I2: Price | J2: Amount | K2: Total amount | L2: Amount paid | M2: As on Date | N2: Remarks
A3: Opening Balance | M3: 0
A4: 1 | B4: 46204 | C4: SATYA SIVA DURGA AGENCIES | D4: GOLLAPROLLU | E4: 40 | F4: =G4/E4 -> 105.21 | G4: 4208.4 | J4: =H4*I4 -> 0 | K4: =G4+J4 -> 4208.4 | L4: =+K4 -> 4208.4
A5: 2 | B5: 46204 | C5: RAJ PETROS | D5: RAVULAPALEM | E5: 40 | F5: =G5/E5 -> 104.93 | G5: 4197.2 | J5: =H5*I5 -> 0 | K5: =G5+J5 -> 4197.2 | L5: =+K5 -> 4197.2
A6: 3 | B6: 46204 | C6: SATYA SIVA DURGA AGENCIES | D6: GOLLAPROLLU | E6: 180 | F6: =G6/E6 -> 105.21 | G6: 18937.8 | J6: =H6*I6 -> 0 | K6: =G6+J6 -> 18937.8 | L6: =+K6 -> 18937.8
A7: 4 | B7: 46204 | C7: SATYA SIVA DURGA AGENCIES | D7: GOLLAPROLLU | E7: 20 | F7: =G7/E7 -> 105.21 | G7: 2104.2 | J7: =H7*I7 -> 0 | K7: =G7+J7 -> 2104.2 | L7: =+K7 -> 2104.2
A8: 5 | B8: 46204 | C8: SRI BALAJI AGENCIES | D8: KAKINADA | G8: =E8*F8 -> 0 | H8: 5 | I8: 589.9 | J8: =H8*I8 -> 2949.5 | K8: =G8+J8 -> 2949.5 | L8: =+K8 -> 2949.5
A9: 6 | B9: 46204 | C9: SRI RADHA PETRO FILL | D9: MUMMIDIVARAM | E9: 47.655 | F9: 104.92 | G9: =E9*F9 -> 4999.9626 | J9: =H9*I9 -> 0 | K9: =G9+J9 -> 4999.9626 | L9: =+K9 -> 4999.9626
A10: 7 | B10: 46205 | C10: SRI BALAJI AGENCIES | D10: KAKINADA | E10: 44.74 | F10: =G10/E10 -> 105.59008 | G10: 4724.1 | J10: =H10*I10 -> 0 | K10: =G10+J10 -> 4724.1 | L10: =+K10 -> 4724.1
A11: 8 | B11: 46205 | C11: BP - LALLACHERUVU | D11: RAJHAMUNDRY | E11: 41.78 | F11: =G11/E11 -> 104.61991 | G11: 4371.02 | J11: =H11*I11 -> 0 | K11: =G11+J11 -> 4371.02 | L11: =+K11 -> 4371.02
A12: 9 | B12: 46205 | C12: RAJ PETROS | D12: RAVULAPALEM | E12: 37.57 | F12: =G12/E12 -> 104.93 | G12: 3942.22 | J12: =H12*I12 -> 0 | K12: =G12+J12 -> 3942.22 | L12: =+K12 -> 3942.22
A13: 10 | B13: 46205 | C13: SRI BALAJI AGENCIES | D13: KAKINADA | E13: 42.75 | F13: =G13/E13 -> 105.58994 | G13: 4513.97 | J13: =H13*I13 -> 0 | K13: =G13+J13 -> 4513.97 | L13: =+K13 -> 4513.97
A14: 11 | B14: 46205 | C14: BP - LALLACHERUVU | D14: RAJHAMUNDRY | E14: 43.82 | F14: =G14/E14 -> 104.62004 | G14: 4584.45 | J14: =H14*I14 -> 0 | K14: =G14+J14 -> 4584.45 | L14: =+K14 -> 4584.45
A15: 12 | B15: 46205 | C15: JVVR FILLING STATION | D15: PITHAPURAM | E15: 18 | F15: =G15/E15 -> 105.35 | G15: 1896.3 | J15: =H15*I15 -> 0 | K15: =G15+J15 -> 1896.3 | L15: =+K15 -> 1896.3
A16: 13 | B16: 46205 | C16: SRI BHIMESWARA AGENCIES | D16: AMALAPURAM | G16: =E16*F16 -> 0 | H16: 6 | I16: =J16/H16 -> 117.62 | J16: 705.72 | K16: =G16+J16 -> 705.72 | L16: =+K16 -> 705.72
A17: 14 | B17: 46205 | C17: BP - KOVVUR | D17: KOVVUR | G17: =E17*F17 -> 0 | H17: 5 | I17: =J17/H17 -> 116.99 | J17: 584.95 | K17: =G17+J17 -> 584.95 | L17: =+K17 -> 584.95
A18: 15 | B18: 46205 | C18: SRI BALAJI AGENCIES | D18: KAKINADA | E18: 45.07 | F18: =G18/E18 -> 105.58997 | G18: 4758.94 | J18: =H18*I18 -> 0 | K18: =G18+J18 -> 4758.94 | L18: =+K18 -> 4758.94
A19: 16 | B19: 46205 | C19: SRI SATYA FILLING STATION | D19: ELESWARAM | E19: 40 | F19: =G19/E19 -> 105.46 | G19: 4218.4 | J19: =H19*I19 -> 0 | K19: =G19+J19 -> 4218.4 | L19: =+K19 -> 4218.4
A20: 17 | B20: 46205 | C20: SRI RADHA PETRO FILL | D20: MUMMIDIVARAM | E20: 60 | F20: =G20/E20 -> 104.92 | G20: 6295.2 | J20: =H20*I20 -> 0 | K20: =G20+J20 -> 6295.2 | L20: =+K20 -> 6295.2
A21: 18 | B21: 46206 | C21: TIRUMALA AGENCIES | D21: ANATHAVARAM | E21: 69.15 | F21: =G21/E21 -> 105.34996 | G21: 7284.95 | J21: =H21*I21 -> 0 | K21: =G21+J21 -> 7284.95 | L21: =+K21 -> 7284.95
A22: 19 | B22: 46206 | C22: SRI VENKATESWARA ENTERPRISES | D22: YANAM | E22: 51.03 | F22: =G22/E22 -> 94.079953 | G22: 4800.9 | J22: =H22*I22 -> 0 | K22: =G22+J22 -> 4800.9 | L22: =+K22 -> 4800.9
A23: 20 | B23: 46206 | C23: JVVR FILLING STATION | D23: PITHAPURAM | G23: =E23*F23 -> 0 | H23: 5 | I23: =J23/H23 -> 117.72 | J23: 588.6 | K23: =G23+J23 -> 588.6 | L23: =+K23 -> 588.6
A24: 21 | B24: 46206 | C24: BP - KOVVUR | D24: KOVVUR | E24: 10 | F24: =G24/E24 -> 104.7 | G24: 1047 | J24: =H24*I24 -> 0 | K24: =G24+J24 -> 1047 | L24: =+K24 -> 1047
A25: 22 | B25: 46206 | C25: BP - KOVVUR | D25: KOVVUR | G25: =E25*F25 -> 0 | H25: 5 | I25: =J25/H25 -> 116.99 | J25: 584.95 | K25: =G25+J25 -> 584.95 | L25: =+K25 -> 584.95
A26: 23 | B26: 46206 | C26: JVVR FILLING STATION | D26: PITHAPURAM | G26: =E26*F26 -> 0 | H26: 5 | I26: =J26/H26 -> 117.72 | J26: 588.6 | K26: =G26+J26 -> 588.6 | L26: =+K26 -> 588.6
A27: 24 | B27: 46206 | C27: JVVR FILLING STATION | D27: PITHAPURAM | G27: =E27*F27 -> 0 | H27: 5 | I27: =J27/H27 -> 117.72 | J27: 588.6 | K27: =G27+J27 -> 588.6 | L27: =+K27 -> 588.6
A28: 25 | B28: 46206 | C28: JVVR FILLING STATION | D28: PITHAPURAM | E28: 190 | F28: =G28/E28 -> 105.35 | G28: 20016.5 | J28: =H28*I28 -> 0 | K28: =G28+J28 -> 20016.5 | L28: =+K28 -> 20016.5
A29: 26 | B29: 46206 | C29: SRI RADHA PETRO FILL | D29: MUMMIDIVARAM | E29: 30 | F29: =G29/E29 -> 104.92 | G29: 3147.6 | J29: =H29*I29 -> 0 | K29: =G29+J29 -> 3147.6 | L29: =+K29 -> 3147.6
A30: 27 | B30: 46207 | C30: SRI SATYA FILLING STATION | D30: YELESWARAM | G30: =E30*F30 -> 0 | H30: 5 | I30: 117.84 | J30: =H30*I30 -> 589.2 | K30: =G30+J30 -> 589.2 | L30: =+K30 -> 589.2
A31: 28 | B31: 46207 | C31: SRI SATYA FILLING STATION | D31: YELESWARAM | E31: 10 | F31: 105.46 | G31: =E31*F31 -> 1054.6 | J31: =H31*I31 -> 0 | K31: =G31+J31 -> 1054.6 | L31: =+K31 -> 1054.6
A32: 29 | B32: 46207 | C32: TIRUMALA AGENCIES | D32: ANATHAVARAM | E32: 40.24 | F32: 105.35 | G32: =E32*F32 -> 4239.284 | J32: =H32*I32 -> 0 | K32: =G32+J32 -> 4239.284 | L32: =+K32 -> 4239.284
A33: 30 | B33: 46207 | C33: JVVR FILLING STATION | D33: PITHAPURAM | G33: =E33*F33 -> 0 | H33: 5 | I33: 117.72 | J33: =H33*I33 -> 588.6 | K33: =G33+J33 -> 588.6 | L33: =+K33 -> 588.6
A34: 31 | B34: 46207 | C34: SRI RADHA PETRO FILL | D34: MUMMIDIVARAM | E34: 19.062 | F34: 104.92 | G34: =E34*F34 -> 1999.985 | J34: =H34*I34 -> 0 | K34: =G34+J34 -> 1999.985 | L34: =+K34 -> 1999.985
A35: 32 | B35: 46207 | C35: SRI SATYA FILLING STATION | D35: YELESWARAM | E35: 30 | F35: 105.46 | G35: =E35*F35 -> 3163.8 | J35: =H35*I35 -> 0 | K35: =G35+J35 -> 3163.8 | L35: =+K35 -> 3163.8
A36: 33 | B36: 46207 | C36: SRI RADHA PETRO FILL | D36: MUMMIDIVARAM | E36: 190 | F36: 104.92 | G36: =E36*F36 -> 19934.8 | J36: =H36*I36 -> 0 | K36: =G36+J36 -> 19934.8 | L36: =+K36 -> 19934.8
A37: 34 | B37: 46207 | C37: SRI BALAJI AGENCIES | D37: KAKINADA | E37: 40.73 | F37: 105.59 | G37: =E37*F37 -> 4300.6807 | J37: =H37*I37 -> 0 | K37: =G37+J37 -> 4300.6807 | L37: =+K37 -> 4300.6807
A38: 35 | B38: 46207 | C38: SRI BALAJI AGENCIES | D38: KAKINADA | F38: 117.98 | G38: =E38*F38 -> 0 | H38: 5 | I38: 117.98 | J38: =H38*I38 -> 589.9 | K38: =G38+J38 -> 589.9 | L38: =+K38 -> 589.9
A39: 36 | B39: 46207 | C39: SATYA SIVA DURGA AGENCIES | D39: KAKINADA | E39: 120 | F39: 105.21 | G39: =E39*F39 -> 12625.2 | J39: =H39*I39 -> 0 | K39: =G39+J39 -> 12625.2 | L39: =+K39 -> 12625.2
A40: 37 | B40: 46207 | C40: SRI RADHA PETRO FILL | D40: MUMMIDIVARAM | E40: 19.062 | F40: 104.92 | G40: =E40*F40 -> 1999.985 | J40: =H40*I40 -> 0 | K40: =G40+J40 -> 1999.985 | L40: =+K40 -> 1999.985
A41: 38 | B41: 46207 | C41: JVVR FILLING STATION | D41: PITHAPURAM | E41: 40.01 | F41: 105.35 | G41: =E41*F41 -> 4215.0535 | J41: =H41*I41 -> 0 | K41: =G41+J41 -> 4215.0535 | L41: =+K41 -> 4215.0535
A42: 39 | B42: 46207 | C42: TIRUMALA AGENCIES | D42: ANATHAVARAM | E42: 26.1 | F42: 105.35 | G42: =E42*F42 -> 2749.635 | J42: =H42*I42 -> 0 | K42: =G42+J42 -> 2749.635 | L42: =+K42 -> 2749.635
A43: 40 | B43: 46208 | C43: JVVR FILLING STATION | D43: PITHAPURAM | G43: =E43*F43 -> 0 | H43: 5 | I43: =J43/H43 -> 117.72 | J43: 588.6 | K43: =G43+J43 -> 588.6 | L43: =+K43 -> 588.6
A44: 41 | B44: 46208 | C44: SATYA SIVA DURGA AGENCIES | D44: GOLLAPROLLU | E44: 10 | F44: =G44/E44 -> 105.21 | G44: 1052.1 | J44: =H44*I44 -> 0 | K44: =G44+J44 -> 1052.1 | L44: =+K44 -> 1052.1
A45: 42 | B45: 46208 | C45: BP - KOVVUR | D45: KOVVUR | E45: 0 | F45: 0 | G45: 0 | H45: 10.25 | I45: 116.99 | J45: =H45*I45 -> 1199.1475 | K45: =G45+J45 -> 1199.1475 | L45: =+K45 -> 1199.1475
A46: 43 | B46: 46208 | C46: SATYA SIVA DURGA AGENCIES | D46: GOLLAPROLLU | E46: 44.2 | F46: =G46/E46 -> 105.20995 | G46: 4650.28 | J46: =H46*I46 -> 0 | K46: =G46+J46 -> 4650.28 | L46: =+K46 -> 4650.28
A47: 44 | B47: 46208 | C47: JVVR FILLING STATION | D47: PITHAPURAM | E47: 48.07 | F47: =G47/E47 -> 105.34991 | G47: 5064.17 | J47: =H47*I47 -> 0 | K47: =G47+J47 -> 5064.17 | L47: =+K47 -> 5064.17
A48: 45 | B48: 46208 | C48: JVVR FILLING STATION | D48: PITHAPURAM | G48: =E48*F48 -> 0 | H48: 5 | I48: =J48/H48 -> 117.72 | J48: 588.6 | K48: =G48+J48 -> 588.6 | L48: =+K48 -> 588.6
A49: 46 | B49: 46208 | C49: BP - KOVVUR | D49: KOVVUR | E49: 48.96 | F49: =G49/E49 -> 104.6201 | G49: 5122.2 | J49: =H49*I49 -> 0 | K49: =G49+J49 -> 5122.2 | L49: =+K49 -> 5122.2
A50: 47 | B50: 46208 | C50: JVVR FILLING STATION | D50: PITHAPURAM | E50: 30 | F50: =G50/E50 -> 105.35 | G50: 3160.5 | J50: =H50*I50 -> 0 | K50: =G50+J50 -> 3160.5 | L50: =+K50 -> 3160.5
A51: 48 | B51: 46208 | C51: SRI BALAJI AGENCIES | D51: KAKINADA | G51: =E51*F51 -> 0 | H51: 5 | I51: =J51/H51 -> 117.98 | J51: 589.9 | K51: =G51+J51 -> 589.9 | L51: =+K51 -> 589.9
A52: 49 | B52: 46208 | C52: SATYA SIVA DURGA AGENCIES | D52: GOLLAPROLLU | E52: 100 | F52: =G52/E52 -> 105.21 | G52: 10521 | J52: =H52*I52 -> 0 | K52: =G52+J52 -> 10521 | L52: =+K52 -> 10521
A53: 50 | B53: 46208 | C53: JVVR FILLING STATION | D53: PITHAPURAM | G53: =E53*F53 -> 0 | H53: 5 | I53: =J53/H53 -> 117.72 | J53: 588.6 | K53: =G53+J53 -> 588.6 | L53: =+K53 -> 588.6
A54: 51 | B54: 46208 | C54: SRI BHIMESWARA AGENCIES | D54: AMALAPURAM | G54: =E54*F54 -> 0 | H54: 5.99 | I54: =J54/H54 -> 117.61937 | J54: 704.54 | K54: =G54+J54 -> 704.54 | L54: =+K54 -> 704.54
A55: 52 | B55: 46208 | C55: SRI BHIMESWARA AGENCIES | D55: AMALAPURAM | G55: =E55*F55 -> 0 | H55: 7 | I55: =J55/H55 -> 117.62 | J55: 823.34 | K55: =G55+J55 -> 823.34 | L55: =+K55 -> 823.34
A56: 53 | B56: 46210 | C56: SRI BALAJI AGENCIES | D56: KAKINADA | G56: =E56*F56 -> 0 | H56: 6 | I56: =J56/H56 -> 117.98 | J56: 707.88 | K56: =G56+J56 -> 707.88 | L56: =+K56 -> 707.88
A57: 54 | B57: 46210 | C57: BP - KOVVUR | D57: KOVVUR | E57: 10 | F57: =G57/E57 -> 104.7 | G57: 1047 | J57: =H57*I57 -> 0 | K57: =G57+J57 -> 1047 | L57: =+K57 -> 1047
A58: 55 | B58: 46210 | C58: KINGMEI FILLING STATION | D58: ELURU | E58: 50.52 | F58: =G58/E58 -> 105.57997 | G58: 5333.9 | J58: =H58*I58 -> 0 | K58: =G58+J58 -> 5333.9 | L58: =+K58 -> 5333.9
A59: 56 | B59: 46210 | C59: SRI SATYA FILLING STATION | D59: ELESWARAM | E59: 30 | F59: =G59/E59 -> 105.46 | G59: 3163.8 | J59: 0 | K59: =G59+J59 -> 3163.8 | L59: =+K59 -> 3163.8
A60: 57 | B60: 46210 | C60: SRI BALAJI AGENCIES | D60: KAKINADA | G60: =E60*F60 -> 0 | H60: 5 | I60: =J60/H60 -> 117.98 | J60: 589.9 | K60: =G60+J60 -> 589.9 | L60: =+K60 -> 589.9
A61: 58 | B61: 46210 | C61: SATYA SIVA DURGA AGENCIES | D61: GOLLAPROLLU | E61: 120 | F61: =G61/E61 -> 105.21 | G61: 12625.2 | J61: =H61*I61 -> 0 | K61: =G61+J61 -> 12625.2 | L61: =+K61 -> 12625.2
A62: 59 | B62: 46211 | C62: BP - KOVVUR | D62: KOVVUR | H62: 5 | I62: =J62/H62 -> 116.99 | J62: 584.95 | K62: =G62+J62 -> 584.95 | L62: =+K62 -> 584.95
A63: 60 | B63: 46211 | C63: TIRUMALA AGENCIES | D63: ANATHAVARAM | E63: 60 | F63: =G63/E63 -> 105.35 | G63: 6321 | J63: =H63*I63 -> 0 | K63: =G63+J63 -> 6321 | L63: =+K63 -> 6321
A64: 61 | B64: 46211 | C64: TIRUMALA AGENCIES | D64: ANATHAVARAM | E64: 40 | F64: =G64/E64 -> 105.35 | G64: 4214 | J64: =H64*I64 -> 0 | K64: =G64+J64 -> 4214 | L64: =+K64 -> 4214
A65: 62 | B65: 46211 | C65: JVVR FILLING STATION | D65: PITHAPURAM | E65: 70 | F65: =G65/E65 -> 105.35 | G65: 7374.5 | J65: =H65*I65 -> 0 | K65: =G65+J65 -> 7374.5 | L65: =+K65 -> 7374.5
A66: 63 | B66: 46211 | C66: SRI BALAJI AGENCIES | D66: KAKINADA | G66: =E66*F66 -> 0 | H66: 5 | I66: =J66/H66 -> 117.98 | J66: 589.9 | K66: =G66+J66 -> 589.9 | L66: =+K66 -> 589.9
A67: 64 | B67: 46211 | C67: SRI BALAJI AGENCIES | D67: KAKINADA | E67: 35.68 | F67: =G67/E67 -> 105.58997 | G67: 3767.45 | J67: =H67*I67 -> 0 | K67: =G67+J67 -> 3767.45 | L67: =+K67 -> 3767.45
A68: 65 | B68: 46211 | C68: SRI SATYA FILLING STATION | D68: ELESWARAM | E68: 20 | F68: =G68/E68 -> 105.46 | G68: 2109.2 | J68: =H68*I68 -> 0 | K68: =G68+J68 -> 2109.2 | L68: =+K68 -> 2109.2
A69: 66 | B69: 46211 | C69: BP - KOVVUR | D69: KOVVUR | E69: 51.25 | F69: =G69/E69 -> 104.7001 | G69: 5365.88 | J69: =H69*I69 -> 0 | K69: =G69+J69 -> 5365.88 | L69: =+K69 -> 5365.88
A70: 67 | B70: 46211 | C70: JVVR FILLING STATION | D70: PITHAPURAM | E70: 39.95 | F70: =G70/E70 -> 105.34994 | G70: 4208.73 | J70: =H70*I70 -> 0 | K70: =G70+J70 -> 4208.73 | L70: =+K70 -> 4208.73
A71: 68 | B71: 46211 | C71: JVVR FILLING STATION | D71: PITHAPURAM | E71: 20.3 | F71: =G71/E71 -> 105.34975 | G71: 2138.6 | J71: =H71*I71 -> 0 | K71: =G71+J71 -> 2138.6 | L71: =+K71 -> 2138.6
A72: 69 | B72: 46211 | C72: SATYA SIVA DURGA AGENCIES | D72: GOLLAPROLLU | E72: 170 | F72: =G72/E72 -> 105.21 | G72: 17885.7 | J72: =H72*I72 -> 0 | K72: =G72+J72 -> 17885.7 | L72: =+K72 -> 17885.7
A73: 70 | B73: 46211 | C73: SRI SATYA FILLING STATION | D73: ELESWARAM | E73: 20 | F73: =G73/E73 -> 105.46 | G73: 2109.2 | J73: =H73*I73 -> 0 | K73: =G73+J73 -> 2109.2 | L73: =+K73 -> 2109.2
A74: 71 | B74: 46211 | C74: SATYA SIVA DURGA AGENCIES | D74: GOLLAPROLLU | E74: 43.54 | F74: =G74/E74 -> 105.20992 | G74: 4580.84 | J74: =H74*I74 -> 0 | K74: =G74+J74 -> 4580.84 | L74: =+K74 -> 4580.84
A75: 72 | B75: 46212 | C75: BP - KOVVUR | D75: KOVVUR | G75: =E75*F75 -> 0 | H75: 5 | I75: =J75/H75 -> 116.99 | J75: 584.95 | K75: =G75+J75 -> 584.95 | L75: =+K75 -> 584.95
A76: 73 | B76: 46212 | C76: SATYA SIVA DURGA AGENCIES | D76: GOLLAPROLLU | E76: 160 | F76: =G76/E76 -> 105.21 | G76: 16833.6 | J76: =H76*I76 -> 0 | K76: =G76+J76 -> 16833.6 | L76: =+K76 -> 16833.6
A77: 74 | B77: 46212 | C77: SRI SATYA FILLING STATION | D77: ELESWARAM | G77: =E77*F77 -> 0 | H77: 8 | I77: =J77/H77 -> 117.84 | J77: 942.72 | K77: =G77+J77 -> 942.72 | L77: =+K77 -> 942.72
A78: 75 | B78: 46212 | C78: JVVR FILLING STATION | D78: PITHAPURAM | G78: =E78*F78 -> 0 | H78: 5 | I78: =J78/H78 -> 117.72 | J78: 588.6 | K78: =G78+J78 -> 588.6 | L78: =+K78 -> 588.6
A79: 76 | B79: 46212 | C79: BP - KOVVUR | D79: KOVVUR | G79: =E79*F79 -> 0 | H79: 5 | I79: =J79/H79 -> 116.99 | J79: 584.95 | K79: =G79+J79 -> 584.95 | L79: =+K79 -> 584.95
A80: 77 | B80: 46212 | C80: BP - KAKINADA | D80: KAKINADA | G80: =E80*F80 -> 0 | H80: 5 | I80: =J80/H80 -> 117.98 | J80: 589.9 | K80: =G80+J80 -> 589.9 | L80: =+K80 -> 589.9
A81: 78 | B81: 46212 | C81: BP - LALLACHERUVU | D81: RAJHAMUNDRY | E81: 48.14 | F81: =G81/E81 -> 104.62007 | G81: 5036.41 | J81: =H81*I81 -> 0 | K81: =G81+J81 -> 5036.41 | L81: =+K81 -> 5036.41
A82: 79 | B82: 46212 | C82: TIRUMALA AGENCIES | D82: MUMMIDIVARAM | E82: 48.35 | F82: =G82/E82 -> 105.34995 | G82: 5093.67 | J82: =H82*I82 -> 0 | K82: =G82+J82 -> 5093.67 | L82: =+K82 -> 5093.67
A83: 80 | B83: 46212 | C83: SATYA SIVA DURGA AGENCIES | D83: GOLLAPROLLU | E83: 240 | F83: =G83/E83 -> 105.21 | G83: 25250.4 | J83: =H83*I83 -> 0 | K83: =G83+J83 -> 25250.4 | L83: =+K83 -> 25250.4
A84: 81 | B84: 46212 | C84: JVVR FILLING STATION | D84: PITHAPURAM | G84: =E84*F84 -> 0 | H84: 5 | I84: =J84/H84 -> 117.72 | J84: 588.6 | K84: =G84+J84 -> 588.6 | L84: =+K84 -> 588.6
A85: 82 | B85: 46213 | C85: SATYA SIVA DURGA AGENCIES | D85: GOLLAPROLLU | E85: 50 | F85: =G85/E85 -> 105.2 | G85: 5260 | J85: =H85*I85 -> 0 | K85: =G85+J85 -> 5260 | L85: =+K85 -> 5260
A86: 83 | B86: 46213 | C86: SATYA SIVA DURGA AGENCIES | D86: GOLLAPROLLU | G86: =E86*F86 -> 0 | H86: 5 | I86: =J86/H86 -> 117.58 | J86: 587.9 | K86: =G86+J86 -> 587.9 | L86: =+K86 -> 587.9
A87: 84 | B87: 46213 | C87: SATYA SIVA DURGA AGENCIES | D87: GOLLAPROLLU | E87: 40 | F87: =G87/E87 -> 105.21 | G87: 4208.4 | J87: =H87*I87 -> 0 | K87: =G87+J87 -> 4208.4 | L87: =+K87 -> 4208.4
A88: 85 | B88: 46213 | C88: SRI BALAJI AGENCIES | D88: KAKINADA | E88: 28.02 | F88: =G88/E88 -> 105.58994 | G88: 2958.63 | J88: =H88*I88 -> 0 | K88: =G88+J88 -> 2958.63 | L88: =+K88 -> 2958.63
A89: 86 | B89: 46213 | C89: SRI BHIMESWARA AGENCIES | D89: AMALAPURAM | G89: =E89*F89 -> 0 | H89: 6 | I89: =J89/H89 -> 117.62 | J89: 705.72 | K89: =G89+J89 -> 705.72 | L89: =+K89 -> 705.72
A90: 87 | B90: 46213 | C90: BP - KOVVUR | D90: KOVVUR | E90: 41.83 | F90: =G90/E90 -> 104.69998 | G90: 4379.6 | J90: =H90*I90 -> 0 | K90: =G90+J90 -> 4379.6 | L90: =+K90 -> 4379.6
A91: 88 | B91: 46213 | C91: SATYA SIVA DURGA AGENCIES | D91: GOLLAPROLLU | E91: 70 | F91: =G91/E91 -> 105.21 | G91: 7364.7 | J91: =H91*I91 -> 0 | K91: =G91+J91 -> 7364.7 | L91: =+K91 -> 7364.7
A92: 89 | B92: 46213 | C92: SRI BALAJI AGENCIES | D92: KAKINADA | G92: =E92*F92 -> 0 | H92: 5 | I92: =J92/H92 -> 117.98 | J92: 589.9 | K92: =G92+J92 -> 589.9 | L92: =+K92 -> 589.9
A93: 90 | B93: 46213 | C93: JVVR FILLING STATION | D93: PITHAPURAM | E93: 20 | F93: =G93/E93 -> 105.35 | G93: 2107 | J93: =H93*I93 -> 0 | K93: =G93+J93 -> 2107 | L93: =+K93 -> 2107
A94: 91 | B94: 46213 | C94: JVVR FILLING STATION | D94: PITHAPURAM | G94: =E94*F94 -> 0 | H94: 5 | I94: =J94/H94 -> 117.72 | J94: 588.6 | K94: =G94+J94 -> 588.6 | L94: =+K94 -> 588.6
A95: 92 | B95: 46214 | C95: SRI BHIMESWARA AGENCIES | D95: AMALAPURAM | E95: 42.02 | F95: =G95/E95 -> 117.81842 | G95: 4950.73 | J95: =H95*I95 -> 0 | K95: =G95+J95 -> 4950.73 | L95: =+K95 -> 4950.73
A96: 93 | B96: 46214 | C96: TIRUMALA AGENCIES | D96: MUMMIDIVARAM | E96: 20 | F96: =G96/E96 -> 105.35 | G96: 2107 | J96: =H96*I96 -> 0 | K96: =G96+J96 -> 2107 | L96: =+K96 -> 2107
A97: 94 | B97: 46214 | C97: BP - KOVVUR | D97: KOVVUR | E97: 10 | F97: =G97/E97 -> 104.7 | G97: 1047 | J97: =H97*I97 -> 0 | K97: =G97+J97 -> 1047 | L97: =+K97 -> 1047
A98: 95 | B98: 46214 | C98: BP - KOVVUR | D98: KOVVUR | G98: 0 | H98: 5 | I98: =J98/H98 -> 116.99 | J98: 584.95 | K98: =G98+J98 -> 584.95 | L98: =+K98 -> 584.95
A99: 96 | B99: 46214 | C99: GSR VANADURGA FILLING STATION | D99: VIJAYAWADA | E99: 145 | F99: =G99/E99 -> 104.75 | G99: 15188.75 | J99: =H99*I99 -> 0 | K99: =G99+J99 -> 15188.75 | L99: =+K99 -> 15188.75
A100: 97 | B100: 46214 | C100: JVVR FILLING STATION | D100: PITHAPURAM | E100: 110 | F100: =G100/E100 -> 105.35 | G100: 11588.5 | J100: =H100*I100 -> 0 | K100: =G100+J100 -> 11588.5 | L100: =+K100 -> 11588.5
A101: 98 | B101: 46214 | C101: SRI BALAJI AGENCIES | D101: KAKINADA | E101: 44.45 | F101: =G101/E101 -> 105.5901 | G101: 4693.48 | J101: =H101*I101 -> 0 | K101: =G101+J101 -> 4693.48 | L101: =+K101 -> 4693.48
...

Sheet  Pitapram(KKD)
A1: SATYA SIVA DURGA AGENCIES, CHEBROLU (BPCL)
A2: S.No | B2: Date | C2: GRN No | D2: Ind no/Bill No | E2: Diesel (Lts) | F2: Price | G2: Amount | H2: Petrol (Lts) | I2: Price | J2: Amount | K2: Total amount | L2: Amount paid | M2: As on Date | N2: Remarks
A3: Opening Balance | M3: 0
A4: 1 | B4: 46204 | G4: =E4*F4 -> 0 | J4: =H4*I4 -> 0 | K4: =G4+J4 -> 0 | M4: =M3+K4-L4 -> 0
B5: 46205 | J5: =H5*I5 -> 0 | K5: =G5+J5 -> 0 | M5: =M4+K5-L5 -> 0
A6: 2 | B6: 46206 | G6: =E6*F6 -> 0 | J6: =H6*I6 -> 0 | K6: =G6+J6 -> 0 | M6: =M5+K6-L6 -> 0
A7: 3 | B7: 46207 | G7: =E7*F7 -> 0 | J7: =H7*I7 -> 0 | K7: =G7+J7 -> 0 | M7: =M6+K7-L7 -> 0
A8: 4 | B8: 46208 | G8: =E8*F8 -> 0 | J8: =H8*I8 -> 0 | K8: =G8+J8 -> 0 | M8: =M7+K8-L8 -> 0
A9: 5 | B9: 46209 | G9: =E9*F9 -> 0 | J9: =H9*I9 -> 0 | K9: =G9+J9 -> 0 | M9: =M8+K9-L9 -> 0
A10: 6 | B10: 46210 | G10: =E10*F10 -> 0 | J10: =H10*I10 -> 0 | K10: =G10+J10 -> 0 | M10: =M9+K10-L10 -> 0
A11: 7 | B11: 46211 | G11: =E11*F11 -> 0 | J11: =H11*I11 -> 0 | K11: =G11+J11 -> 0 | M11: =M10+K11-L11 -> 0
A12: 8 | B12: 46212 | G12: =E12*F12 -> 0 | J12: =H12*I12 -> 0 | K12: =G12+J12 -> 0 | M12: =M11+K12-L12 -> 0
A13: 9 | B13: 46213 | G13: =E13*F13 -> 0 | J13: =H13*I13 -> 0 | K13: =G13+J13 -> 0 | M13: =M12+K13-L13 -> 0
A14: 10 | B14: 46214 | G14: =E14*F14 -> 0 | J14: =H14*I14 -> 0 | K14: =G14+J14 -> 0 | M14: =M13+K14-L14 -> 0
A15: 11 | B15: 46215 | G15: =E15*F15 -> 0 | J15: =H15*I15 -> 0 | K15: =G15+J15 -> 0 | M15: =M14+K15-L15 -> 0
A16: 12 | B16: 46216 | G16: =E16*F16 -> 0 | J16: =H16*I16 -> 0 | K16: =G16+J16 -> 0 | M16: =M15+K16-L16 -> 0
A17: 13 | B17: 46217 | G17: =E17*F17 -> 0 | J17: =H17*I17 -> 0 | K17: =G17+J17 -> 0 | M17: =M16+K17-L17 -> 0
... A23: 19 | B23: 46223 | G23: =E23*F23 -> 0 | J23: =H23*I23 -> 0 | K23: =G23+J23 -> 0 | M23: =M22+K23-L23 -> 0
A24: 20 | B24: 46224 | E24: 360 | F24: 105.21 | G24: =E24*F24 -> 37875.6 | J24: =H24*I24 -> 0 | K24: =G24+J24 -> 37875.6 | M24: =M23+K24-L24 -> 37875.6
A25: 21 | B25: 46225 | E25: 296 | F25: 105.21 | G25: =E25*F25 -> 31142.16 | J25: =H25*I25 -> 0 | K25: =G25+J25 -> 31142.16 | M25: =M24+K25-L25 -> 69017.76
A26: 22 | B26: 46226 | E26: 210.08 | F26: 105.21 | G26: =E26*F26 -> 22102.517 | J26: =H26*I26 -> 0 | K26: =G26+J26 -> 22102.517 | M26: =M25+K26-L26 -> 91120.277
A27: 23 | B27: 46227 | E27: 188.55 | F27: 105.21 | G27: =E27*F27 -> 19837.345 | H27: 5 | I27: 117.58 | J27: =H27*I27 -> 587.9 | K27: =G27+J27 -> 20425.246 | M27: =M26+K27-L27 -> 111545.52
A28: 24 | B28: 46228 | E28: 113 | F28: 105.21 | G28: =E28*F28 -> 11888.73 | H28: 5 | I28: 117.58 | J28: =H28*I28 -> 587.9 | K28: =G28+J28 -> 12476.63 | M28: =M27+K28-L28 -> 124022.15
A29: 25 | B29: 46229 | E29: 245 | F29: 105.21 | G29: =E29*F29 -> 25776.45 | J29: =H29*I29 -> 0 | K29: =G29+J29 -> 25776.45 | M29: =M28+K29-L29 -> 149798.6
B30: 46230 | E30: 220 | F30: 105.21 | G30: =E30*F30 -> 23146.2 | H30: 10 | I30: 117.58 | J30: =H30*I30 -> 1175.8 | K30: =G30+J30 -> 24322 | M30: =M29+K30-L30 -> 174120.6
A31: 26 | B31: 46231 | E31: 186 | F31: 105.21 | G31: =E31*F31 -> 19569.06 | J31: =H31*I31 -> 0 | K31: =G31+J31 -> 19569.06 | M31: =M30+K31-L31 -> 193689.66
A32: 27 | B32: 46232 | E32: 15 | F32: 105.21 | G32: =E32*F32 -> 1578.15 | H32: 10 | I32: 117.58 | J32: =H32*I32 -> 1175.8 | K32: =G32+J32 -> 2753.95 | L32: 150000 | M32: =M31+K32-L32 -> 46443.612
A33: 28 | B33: 46233 | E33: 279.5 | F33: 105.21 | G33: =E33*F33 -> 29406.195 | J33: =H33*I33 -> 0 | K33: =G33+J33 -> 29406.195 | M33: =M32+K33-L33 -> 75849.807
A34: 29 | B34: 46234 | E34: 149 | F34: 105.21 | G34: =E34*F34 -> 15676.29 | H34: 7 | I34: 117.58 | J34: =H34*I34 -> 823.06 | K34: =G34+J34 -> 16499.35 | M34: =M33+K34-L34 -> 92349.157
A35: 30 | G35: =E35*F35 -> 0 | J35: =H35*I35 -> 0 | K35: =G35+J35 -> 0 | M35: =M34+K35-L35 -> 92349.157
A36: 31 | G36: =E36*F36 -> 0 | J36: =H36*I36 -> 0 | K36: =G36+J36 -> 0 | M36: =M35+K36-L36 -> 92349.157
E37: =SUM(E4:E36) -> 2262.13 | G37: =SUM(G4:G36) -> 237998.7 | H37: =SUM(H4:H36) -> 37 | J37: =SUM(J4:J36) -> 4350.46 | K37: =SUM(K4:K36) -> 242349.16 | L37: =SUM(L4:L36) -> 150000

Sheet Yeleshwaram(KKD)
A1: SRI SATYA FILLING STATION, YELESWARAM (BPCL)
A2: S.No | B2: Date | C2: GRN No | D2: Ind no/Bill No | E2: Diesel (Lts) | F2: Price | G2: Amount | H2: Petrol (Lts) | I2: Price | J2: Amount | K2: Total amount | L2: Amount paid | M2: As on Date | N2: Remarks
A3: Opening Balance | M3: 0
A4: 1 | B4: 46204 | G4: =E4*F4 -> 0 | J4: =H4*I4 -> 0 | K4: 0 | L4: 0 | M4: =M3+K4-L4 -> 0
A5: 2 | B5: 46205 | J5: =H5*I5 -> 0 | K5: =G5+J5 -> 0 | L5: =+K5 -> 0 | M5: =M4+K5-L5 -> 0
A6: 3 | B6: 46206 | G6: =E6*F6 -> 0 | J6: =H6*I6 -> 0 | K6: =G6+J6 -> 0 | L6: =+K6 -> 0 | M6: =M5+K6-L6 -> 0
A7: 4 | B7: 46207 | G7: =E7*F7 -> 0 | J7: =H7*I7 -> 0 | K7: =G7+J7 -> 0 | L7: =+K7 -> 0 | M7: =M6+K7-L7 -> 0
A8: 5 | B8: 46208 | G8: =E8*F8 -> 0 | J8: =H8*I8 -> 0 | K8: =G8+J8 -> 0 | L8: =+K8 -> 0 | M8: =M7+K8-L8 -> 0
A9: 6 | B9: 46209 | G9: =E9*F9 -> 0 | J9: =H9*I9 -> 0 | K9: =G9+J9 -> 0 | L9: =+K9 -> 0 | M9: =M8+K9-L9 -> 0
A10: 7 | B10: 46210 | G10: =E10*F10 -> 0 | J10: =H10*I10 -> 0 | K10: =G10+J10 -> 0 | L10: =+K10 -> 0 | M10: =M9+K10-L10 -> 0
A11: 8 | B11: 46211 | G11: =E11*F11 -> 0 | J11: =H11*I11 -> 0 | K11: =G11+J11 -> 0 | L11: =+K11 -> 0 | M11: =M10+K11-L11 -> 0
A12: 9 | B12: 46212 | G12: =E12*F12 -> 0 | J12: =H12*I12 -> 0 | K12: =G12+J12 -> 0 | L12: =+K12 -> 0 | M12: =M11+K12-L12 -> 0
A13: 10 | B13: 46213 | G13: =E13*F13 -> 0 | J13: =H13*I13 -> 0 | K13: =G13+J13 -> 0 | L13: =+K13 -> 0 | M13: =M12+K13-L13 -> 0
A14: 11 | B14: 46214 | G14: =E14*F14 -> 0 | J14: =H14*I14 -> 0 | K14: =G14+J14 -> 0 | L14: =+K14 -> 0 | M14: =M13+K14-L14 -> 0
A15: 12 | B15: 46215 | G15: =E15*F15 -> 0 | J15: =H15*I15 -> 0 | K15: =G15+J15 -> 0 | L15: =+K15 -> 0 | M15: =M14+K15-L15 -> 0
A16: 13 | B16: 46216 | G16: =E16*F16 -> 0 | J16: =H16*I16 -> 0 | K16: =G16+J16 -> 0 | L16: =+K16 -> 0 | M16: =M15+K16-L16 -> 0
A17: 14 | B17: 46217 | G17: =E17*F17 -> 0 | J17: =H17*I17 -> 0 | K17: =G17+J17 -> 0 | L17: =+K17 -> 0 | M17: =M16+K17-L17 -> 0
... A23: 20 | B23: 46223 | G23: =E23*F23 -> 0 | J23: =H23*I23 -> 0 | K23: =G23+J23 -> 0 | L23: =+K23 -> 0 | M23: =M22+K23-L23 -> 0
A24: 21 | B24: 46224 | E24: 40 | F24: 105.46 | G24: =E24*F24 -> 4218.4 | H24: 5 | I24: 117.84 | J24: =H24*I24 -> 589.2 | K24: =G24+J24 -> 4807.6 | L24: 0 | M24: =M23+K24-L24 -> 4807.6
A25: 22 | B25: 46225 | G25: =E25*F25 -> 0 | J25: =H25*I25 -> 0 | K25: =G25+J25 -> 0 | L25: 0 | M25: =M24+K25-L25 -> 4807.6
A26: 23 | B26: 46226 | E26: 30 | F26: 105.46 | G26: =E26*F26 -> 3163.8 | J26: =H26*I26 -> 0 | K26: =G26+J26 -> 3163.8 | L26: 0 | M26: =M25+K26-L26 -> 7971.4
A27: 24 | B27: 46227 | G27: =E27*F27 -> 0 | J27: =H27*I27 -> 0 | K27: =G27+J27 -> 0 | L27: 0 | M27: =M26+K27-L27 -> 7971.4
A28: 25 | B28: 46228 | G28: =E28*F28 -> 0 | J28: =H28*I28 -> 0 | K28: =G28+J28 -> 0 | L28: 0 | M28: =M27+K28-L28 -> 7971.4
A29: 26 | B29: 46229 | E29: 40 | F29: 105.46 | G29: =E29*F29 -> 4218.4 | H29: 5 | I29: 117.84 | J29: =H29*I29 -> 589.2 | K29: =G29+J29 -> 4807.6 | L29: 0 | M29: =M28+K29-L29 -> 12779
A30: 27 | B30: 46230 | J30: =H30*I30 -> 0 | K30: =G30+J30 -> 0 | L30: 0 | M30: =M29+K30-L30 -> 12779
A31: 28 | B31: 46231 | G31: =E31*F31 -> 0 | J31: =H31*I31 -> 0 | K31: =G31+J31 -> 0 | L31: =+K31 -> 0 | M31: =M30+K31-L31 -> 12779
A32: 29 | B32: 46232 | G32: =E32*F32 -> 0 | J32: =H32*I32 -> 0 | K32: =G32+J32 -> 0 | L32: =+K32 -> 0 | M32: =M31+K32-L32 -> 12779
A33: 30 | B33: 46233 | E33: 60 | F33: 105.46 | G33: =E33*F33 -> 6327.6 | J33: =H33*I33 -> 0 | K33: =G33+J33 -> 6327.6 | L33: 0 | M33: =M32+K33-L33 -> 19106.6
A34: 31 | B34: 46234 | G34: =E34*F34 -> 0 | J34: =H34*I34 -> 0 | K34: =G34+J34 -> 0 | L34: =+K34 -> 0 | M34: =M33+K34-L34 -> 19106.6
A35: 32 | G35: =E35*F35 -> 0 | J35: =H35*I35 -> 0 | K35: =G35+J35 -> 0 | L35: =+K35 -> 0 | M35: =M34+K35-L35 -> 19106.6
A36: 33 | G36: =E36*F36 -> 0 | J36: =H36*I36 -> 0 | K36: =G36+J36 -> 0 | L36: =+K36 -> 0 | M36: =M35+K36-L36 -> 19106.6
E37: =SUM(E4:E36) -> 170 | G37: =SUM(G4:G36) -> 17928.2 | H37: =SUM(H4:H36) -> 10 | J37: =SUM(J4:J36) -> 1178.4 | K37: =SUM(K4:K36) -> 19106.6 | L37: =SUM(L4:L36) -> 0

Sheet Madana palli
A2: S.No | B2: Date | C2: GRN No | D2: Ind no/Bill No | E2: Diesel (Lts) | F2: Price | G2: Amount | H2: Petrol (Lts) | I2: Price | J2: Amount | K2: Total amount | L2: Amount paid | M2: As on Date | N2: Remarks
A3: Opening Balance | M3: 0
A4: 1 | B4: 46204 | G4: =E4*F4 -> 0 | J4: =H4*I4 -> 0 | K4: =G4+J4 -> 0 | L4: =+K4 -> 0 | M4: 0
B5: 46205 | J5: =H5*I5 -> 0 | K5: =G5+J5 -> 0 | L5: =+K5 -> 0
A6: 2 | B6: 46206 | G6: =E6*F6 -> 0 | J6: =H6*I6 -> 0 | K6: =G6+J6 -> 0 | L6: =+K6 -> 0 | M6: 0 | N6: IOCL
A7: 3 | B7: 46207 | G7: =E7*F7 -> 0 | J7: =H7*I7 -> 0 | K7: =G7+J7 -> 0 | L7: =+K7 -> 0 | M7: 0
A8: 4 | B8: 46208 | G8: =E8*F8 -> 0 | J8: =H8*I8 -> 0 | K8: =G8+J8 -> 0 | L8: =+K8 -> 0 | M8: 0
A9: 5 | B9: 46209 | G9: =E9*F9 -> 0 | J9: =H9*I9 -> 0 | K9: =G9+J9 -> 0 | L9: =+K9 -> 0 | M9: 0
A10: 6 | B10: 46210 | G10: =E10*F10 -> 0 | J10: =H10*I10 -> 0 | K10: =G10+J10 -> 0 | L10: =+K10 -> 0 | M10: 0 | N10: HPCL
A11: 7 | B11: 46211 | G11: =E11*F11 -> 0 | J11: =H11*I11 -> 0 | K11: =G11+J11 -> 0 | L11: =+K11 -> 0 | M11: 0 | O11: 169.99
A12: 8 | B12: 46212 | G12: =E12*F12 -> 0 | J12: =H12*I12 -> 0 | K12: =G12+J12 -> 0 | L12: =+K12 -> 0 | M12: 0 | O12: 80
A13: 9 | B13: 46213 | G13: =E13*F13 -> 0 | J13: =H13*I13 -> 0 | K13: =G13+J13 -> 0 | L13: =+K13 -> 0 | M13: 0 | O13: =SUM(O11:O12) -> 249.99 | P13: 97.76 | Q13: =O13*P13 -> 24439.022
A14: 10 | B14: 46214 | G14: =E14*F14 -> 0 | J14: =H14*I14 -> 0 | K14: =G14+J14 -> 0 | L14: =+K14 -> 0 | M14: 0
A15: 11 | B15: 46215 | G15: =E15*F15 -> 0 | J15: =H15*I15 -> 0 | K15: =G15+J15 -> 0 | L15: =+K15 -> 0 | M15: 0
A16: 12 | B16: 46216 | G16: =E16*F16 -> 0 | J16: =H16*I16 -> 0 | K16: =G16+J16 -> 0 | L16: =+K16 -> 0 | M16: 0 | P16: 7820.8
A17: 13 | B17: 46217 | G17: =E17*F17 -> 0 | H17: 3.4 | I17: 117.46 | J17: =H17*I17 -> 399.364 | K17: =G17+J17 -> 399.364 | L17: =+K17 -> 399.364 | M17: 0 | P17: 16619.2
A18: 14 | B18: 46218 | G18: =E18*F18 -> 0 | J18: =H18*I18 -> 0 | K18: =G18+J18 -> 0 | L18: =+K18 -> 0 | M18: 0 | P18: =SUM(P16:P17) -> 24440
A19: 15 | B19: 46219 | G19: =E19*F19 -> 0 | J19: =H19*I19 -> 0 | K19: =G19+J19 -> 0 | L19: =+K19 -> 0 | M19: 0
A20: 16 | B20: 46220 | G20: =E20*F20 -> 0 | J20: =H20*I20 -> 0 | K20: =G20+J20 -> 0 | L20: =+K20 -> 0 | M20: 0
A21: 17 | B21: 46221 | G21: =E21*F21 -> 0 | J21: =H21*I21 -> 0 | K21: =G21+J21 -> 0 | L21: =+K21 -> 0 | M21: 0
A22: 18 | B22: 46222 | G22: =E22*F22 -> 0 | J22: =H22*I22 -> 0 | K22: =G22+J22 -> 0 | L22: =+K22 -> 0 | M22: 0
A23: 19 | B23: 46223 | G23: =E23*F23 -> 0 | J23: =H23*I23 -> 0 | K23: =G23+J23 -> 0 | L23: =+K23 -> 0 | M23: 0
A24: 20 | B24: 46224 | G24: =E24*F24 -> 0 | J24: =H24*I24 -> 0 | K24: =G24+J24 -> 0 | L24: =+K24 -> 0 | M24: 0
A25: 21 | B25: 46225 | G25: =E25*F25 -> 0 | J25: =H25*I25 -> 0 | K25: =G25+J25 -> 0 | L25: =+K25 -> 0 | M25: 0
A26: 22 | B26: 46226 | G26: =E26*F26 -> 0 | J26: =H26*I26 -> 0 | K26: =G26+J26 -> 0 | L26: =+K26 -> 0 | M26: 0
A27: 23 | B27: 46227 | G27: =E27*F27 -> 0 | J27: =H27*I27 -> 0 | K27: =G27+J27 -> 0 | L27: =+K27 -> 0 | M27: 0
A28: 24 | B28: 46228 | G28: =E28*F28 -> 0 | J28: =H28*I28 -> 0 | K28: =G28+J28 -> 0 | L28: =+K28 -> 0 | M28: 0
A29: 25 | B29: 46229 | G29: =E29*F29 -> 0 | J29: =H29*I29 -> 0 | K29: =G29+J29 -> 0 | L29: =+K29 -> 0 | M29: 0
B30: 46230 | J30: =H30*I30 -> 0 | K30: =G30+J30 -> 0 | L30: =+K30 -> 0
A31: 26 | B31: 46231 | G31: =E31*F31 -> 0 | J31: =H31*I31 -> 0 | K31: =G31+J31 -> 0 | L31: =+K31 -> 0 | M31: 0
A32: 27 | B32: 46232 | G32: =E32*F32 -> 0 | J32: =H32*I32 -> 0 | K32: =G32+J32 -> 0 | L32: =+K32 -> 0 | M32: 0
A33: 28 | B33: 46233 | G33: =E33*F33 -> 0 | J33: =H33*I33 -> 0 | K33: =G33+J33 -> 0 | L33: =+K33 -> 0 | M33: 0
A34: 29 | B34: 46234 | G34: =E34*F34 -> 0 | J34: =H34*I34 -> 0 | K34: =G34+J34 -> 0 | L34: =+K34 -> 0 | M34: 0
A35: 30 | G35: =E35*F35 -> 0 | J35: =H35*I35 -> 0 | K35: =G35+J35 -> 0 | L35: =+K35 -> 0 | M35: 0
A36: 31 | G36: =E36*F36 -> 0 | J36: =H36*I36 -> 0 | K36: =G36+J36 -> 0 | L36: =+K36 -> 0 | M36: 0
E37: =SUM(E4:E36) -> 0 | G37: =SUM(G4:G36) -> 0 | H37: =SUM(H4:H36) -> 3.4 | J37: =SUM(J4:J36) -> 399.364 | K37: =SUM(K4:K36) -> 399.364 | L37: =SUM(L4:L36) -> 399.364

Sheet Kadur
A1: Vishal Service Station
A2: S.No | B2: Date | C2: GRN No | D2: Ind No/Bill No | E2: Diesel (Lts) | F2: Price | G2: Amount | H2: Petrol (Lts) | I2: Price | J2: Amount | K2: Total amount | L2: Amount paid | M2: As on Date | N2: Remarks
A3: Opening Balance | K3: 325301.9 | L3: 0 | M3: 325301.9 | O3: 207239.43
A4: 1 | B4: 45839 | G4: =E4*F4 -> 0 | J4: =H4*I4 -> 0 | K4: =G4+J4 -> 0 | M4: =M3+K4-L4 -> 325301.9
A5: 2 | B5: 45840 | G5: =E5*F5 -> 0 | J5: =H5*I5 -> 0 | K5: =G5+J5 -> 0 | M5: =M4+K5-L5 -> 325301.9
A6: 3 | B6: 45841 | G6: =E6*F6 -> 0 | J6: =H6*I6 -> 0 | K6: =G6+J6 -> 0 | M6: =M5+K6-L6 -> 325301.9
A7: 4 | B7: 45842 | G7: =E7*F7 -> 0 | J7: =H7*I7 -> 0 | K7: =G7+J7 -> 0 | M7: =M6+K7-L7 -> 325301.9
A8: 5 | B8: 45843 | G8: =E8*F8 -> 0 | J8: =H8*I8 -> 0 | K8: =G8+J8 -> 0 | M8: =M7+K8-L8 -> 325301.9
A9: 6 | B9: 45844 | G9: =E9*F9 -> 0 | J9: =H9*I9 -> 0 | K9: =G9+J9 -> 0 | M9: =M8+K9-L9 -> 325301.9
A10: 7 | B10: 45845 | G10: =E10*F10 -> 0 | J10: =H10*I10 -> 0 | K10: =G10+J10 -> 0 | M10: =M9+K10-L10 -> 325301.9
A11: 8 | B11: 45846 | G11: =E11*F11 -> 0 | J11: =H11*I11 -> 0 | K11: =G11+J11 -> 0 | M11: =M10+K11-L11 -> 325301.9
A12: 9 | B12: 45847 | G12: =E12*F12 -> 0 | J12: =H12*I12 -> 0 | K12: =G12+J12 -> 0 | M12: =M11+K12-L12 -> 325301.9
A13: 10 | B13: 45848 | G13: =E13*F13 -> 0 | J13: =H13*I13 -> 0 | K13: =G13+J13 -> 0 | M13: =M12+K13-L13 -> 325301.9
A14: 11 | B14: 45849 | G14: =E14*F14 -> 0 | J14: =H14*I14 -> 0 | K14: =G14+J14 -> 0 | M14: =M13+K14-L14 -> 325301.9
A15: 12 | B15: 45850 | G15: =E15*F15 -> 0 | J15: =H15*I15 -> 0 | K15: =G15+J15 -> 0 | M15: =M14+K15-L15 -> 325301.9
... A18: 15 | B18: 45853 | G18: =E18*F18 -> 0 | J18: =H18*I18 -> 0 | K18: =G18+J18 -> 0 | M18: =M17+K18-L18 -> 325301.9
A19: 16 | B19: 45854 | E19: 2000 | F19: 99.96 | G19: =E19*F19 -> 199920 | H19: 35 | I19: 112.3 | J19: =H19*I19 -> 3930.5 | K19: =G19+J19 -> 203850.5 | M19: =M18+K19-L19 -> 529152.4
A20: 17 | B20: 45855 | E20: 1400 | F20: 99.96 | G20: =E20*F20 -> 139944 | H20: 35 | I20: 112.3 | J20: =H20*I20 -> 3930.5 | K20: =G20+J20 -> 143874.5 | M20: =M19+K20-L20 -> 673026.9
A21: 18 | B21: 45856 | G21: =E21*F21 -> 0 | H21: 0 | I21: 0 | J21: =H21*I21 -> 0 | K21: =G21+J21 -> 0 | M21: =M20+K21-L21 -> 673026.9
A22: 19 | B22: 45857 | H22: 0 | I22: 0 | J22: =H22*I22 -> 0 | K22: =G22+J22 -> 0 | M22: =M21+K22-L22 -> 673026.9
A23: 20 | B23: 45858 | H23: 0 | I23: 0 | J23: =H23*I23 -> 0 | K23: =G23+J23 -> 0 | M23: =M22+K23-L23 -> 673026.9
A24: 21 | B24: 45859 | J24: =H24*I24 -> 0 | K24: =G24+J24 -> 0 | M24: =M23+K24-L24 -> 673026.9
A25: 22 | B25: 45860 | J25: =H25*I25 -> 0 | K25: =G25+J25 -> 0 | M25: =M24+K25-L25 -> 673026.9
A26: 23 | B26: 45861 | J26: =H26*I26 -> 0 | K26: =G26+J26 -> 0 | M26: =M25+K26-L26 -> 673026.9
A27: 24 | B27: 45862 | J27: =H27*I27 -> 0 | K27: =G27+J27 -> 0 | M27: =M26+K27-L27 -> 673026.9
A28: 25 | B28: 45863 | J28: =H28*I28 -> 0 | K28: =G28+J28 -> 0 | M28: =M27+K28-L28 -> 673026.9
A29: 26 | B29: 45864 | J29: =H29*I29 -> 0 | K29: =G29+J29 -> 0 | M29: =M28+K29-L29 -> 673026.9
A30: 27 | B30: 45865 | J30: =H30*I30 -> 0 | K30: =G30+J30 -> 0 | M30: =M29+K30-L30 -> 673026.9
A31: 28 | B31: 45866 | J31: =H31*I31 -> 0 | K31: =G31+J31 -> 0 | M31: =M30+K31-L31 -> 673026.9
A32: 29 | B32: 45867 | G32: =E32*F32 -> 0 | H32: 0 | I32: 0 | J32: =H32*I32 -> 0 | K32: =G32+J32 -> 0 | M32: =M31+K32-L32 -> 673026.9
A33: 30 | B33: 45868 | F33: 0 | G33: =E33*F33 -> 0 | H33: 0 | I33: 0 | J33: =H33*I33 -> 0 | K33: =G33+J33 -> 0 | M33: =M32+K33-L33 -> 673026.9
A34: 31 | F34: 0 | G34: =E34*F34 -> 0 | J34: =H34*I34 -> 0 | K34: =G34+J34 -> 0
E35: =SUM(E4:E34) -> 3400 | G35: =SUM(G4:G34) -> 339864 | H35: =SUM(H4:H34) -> 70 | J35: =SUM(J4:J34) -> 7861 | K35: =SUM(K4:K34) -> 347725 | L35: =SUM(L4:L31) -> 0

Sheet YG Gudda
A1: Pankaja HP Fuel Center
A2: S.No | B2: Date | C2: GRN No | D2: Ind No/Bill No | E2: Diesel (Lts) | F2: Price | G2: Amount | H2: Petrol (Lts) | I2: Price | J2: Amount | K2: Total amount | L2: Amount paid | M2: As on Date | N2: Remarks
A3: Opening Balance | K3: 282784.16 | M3: 282784.16
A4: 1 | B4: 46204 | G4: =E4*F4 -> 0 | J4: =H4*I4 -> 0 | K4: =G4+J4 -> 0 | L4: 150000 | M4: =M3+K4-L4 -> 132784.16
B5: 46205 | E5: 1200 | F5: 99.14 | G5: =E5*F5 -> 118968 | K5: =G5+J5 -> 118968 | M5: =M4+K5-L5 -> 251752.16 | N5: BPCL
A6: 2 | B6: 46206 | G6: =E6*F6 -> 0 | J6: =H6*I6 -> 0 | K6: =G6+J6 -> 0 | M6: =M5+K6-L6 -> 251752.16
A7: 3 | B7: 46207 | G7: =E7*F7 -> 0 | J7: =H7*I7 -> 0 | K7: =G7+J7 -> 0 | M7: =M6+K7-L7 -> 251752.16
A8: 4 | B8: 46208 | G8: =E8*F8 -> 0 | J8: =H8*I8 -> 0 | K8: =G8+J8 -> 0 | M8: =M7+K8-L8 -> 251752.16
A9: 5 | B9: 46209 | G9: =E9*F9 -> 0 | J9: =H9*I9 -> 0 | K9: =G9+J9 -> 0 | M9: =M8+K9-L9 -> 251752.16
A10: 6 | B10: 46210 | G10: =E10*F10 -> 0 | J10: =H10*I10 -> 0 | K10: =G10+J10 -> 0 | M10: =M9+K10-L10 -> 251752.16
A11: 7 | B11: 46211 | E11: 1200 | F11: 99.14 | G11: =E11*F11 -> 118968 | H11: 70 | I11: 111.24 | J11: =H11*I11 -> 7786.8 | K11: =G11+J11 -> 126754.8 | L11: 150000 | M11: =M10+K11-L11 -> 228506.96
A12: 8 | B12: 46212 | G12: =E12*F12 -> 0 | J12: =H12*I12 -> 0 | K12: =G12+J12 -> 0 | M12: =M11+K12-L12 -> 228506.96
A13: 9 | B13: 46213 | G13: =E13*F13 -> 0 | J13: =H13*I13 -> 0 | K13: =G13+J13 -> 0 | M13: =M12+K13-L13 -> 228506.96
A14: 10 | B14: 46214 | G14: =E14*F14 -> 0 | J14: =H14*I14 -> 0 | K14: =G14+J14 -> 0 | M14: =M13+K14-L14 -> 228506.96
A15: 11 | B15: 46215 | G15: =E15*F15 -> 0 | J15: =H15*I15 -> 0 | K15: =G15+J15 -> 0 | M15: =M14+K15-L15 -> 228506.96
A16: 12 | B16: 46216 | G16: =E16*F16 -> 0 | K16: =G16+J16 -> 0 | M16: =M15+K16-L16 -> 228506.96
A17: 13 | B17: 46217 | G17: =E17*F17 -> 0 | J17: =H17*I17 -> 0 | K17: =G17+J17 -> 0 | M17: =M16+K17-L17 -> 228506.96
A18: 14 | B18: 46218 | G18: =E18*F18 -> 0 | J18: =H18*I18 -> 0 | K18: =G18+J18 -> 0 | L18: 150000 | M18: =M17+K18-L18 -> 78506.96
A19: 15 | B19: 46219 | E19: 1200 | F19: 99.14 | G19: =E19*F19 -> 118968 | H19: 70 | I19: 111.24 | J19: =H19*I19 -> 7786.8 | K19: =G19+J19 -> 126754.8 | M19: =M18+K19-L19 -> 205261.76
A20: 16 | B20: 46220 | G20: =E20*F20 -> 0 | J20: =H20*I20 -> 0 | K20: =G20+J20 -> 0 | M20: =M19+K20-L20 -> 205261.76
A21: 17 | B21: 46221 | G21: =E21*F21 -> 0 | J21: =H21*I21 -> 0 | K21: =G21+J21 -> 0 | M21: =M20+K21-L21 -> 205261.76
A22: 18 | B22: 46222 | G22: =E22*F22 -> 0 | J22: =H22*I22 -> 0 | K22: =G22+J22 -> 0 | M22: =M21+K22-L22 -> 205261.76
A23: 19 | B23: 46223 | E23: 1000 | F23: 99.14 | G23: =E23*F23 -> 99140 | H23: 35 | I23: 111.24 | J23: =H23*I23 -> 3893.4 | K23: =G23+J23 -> 103033.4 | M23: =M22+K23-L23 -> 308295.16
A24: 20 | B24: 46224 | G24: =E24*F24 -> 0 | J24: =H24*I24 -> 0 | K24: =G24+J24 -> 0 | M24: =M23+K24-L24 -> 308295.16
A25: 21 | B25: 46225 | G25: =E25*F25 -> 0 | J25: =H25*I25 -> 0 | K25: =G25+J25 -> 0 | M25: =M24+K25-L25 -> 308295.16
A26: 22 | B26: 46226 | G26: =E26*F26 -> 0 | J26: =H26*I26 -> 0 | K26: =G26+J26 -> 0 | L26: 250000 | M26: =M25+K26-L26 -> 58295.16
A27: 23 | B27: 46227 | G27: =E27*F27 -> 0 | J27: =H27*I27 -> 0 | K27: =G27+J27 -> 0 | M27: =M26+K27-L27 -> 58295.16
A28: 24 | B28: 46228 | E28: 1200 | F28: 99.14 | G28: =E28*F28 -> 118968 | H28: 35 | I28: 111.24 | J28: =H28*I28 -> 3893.4 | K28: =G28+J28 -> 122861.4 | M28: =M27+K28-L28 -> 181156.56
A29: 25 | B29: 46229 | G29: =E29*F29 -> 0 | J29: =H29*I29 -> 0 | K29: =G29+J29 -> 0 | M29: =M28+K29-L29 -> 181156.56
A30: 26 | B30: 46230 | E30: 1200 | F30: 99.14 | G30: =E30*F30 -> 118968 | J30: =H30*I30 -> 0 | K30: =G30+J30 -> 118968 | M30: =M29+K30-L30 -> 300124.56
A31: 27 | B31: 46231 | G31: =E31*F31 -> 0 | J31: =H31*I31 -> 0 | K31: =G31+J31 -> 0 | M31: =M30+K31-L31 -> 300124.56
A32: 28 | B32: 46232 | E32: 1500 | F32: 99.14 | G32: =E32*F32 -> 148710 | H32: 70 | I32: 111.24 | J32: =H32*I32 -> 7786.8 | K32: =G32+J32 -> 156496.8 | M32: =M31+K32-L32 -> 456621.36
A33: 29 | B33: 46233 | G33: =E33*F33 -> 0 | J33: =H33*I33 -> 0 | K33: =G33+J33 -> 0 | M33: =M32+K33-L33 -> 456621.36
A34: 30 | B34: 46234 | G34: =E34*F34 -> 0 | J34: =H34*I34 -> 0 | K34: =G34+J34 -> 0 | L34: 160000 | M34: =M33+K34-L34 -> 296621.36
A35: 31 | G35: =E35*F35 -> 0 | J35: =H35*I35 -> 0 | K35: =G35+J35 -> 0 | M35: =M34+K35-L35 -> 296621.36
A36: 32 | G36: =E36*F36 -> 0 | J36: =H36*I36 -> 0 | K36: =G36+J36 -> 0 | M36: =M35+K36-L36 -> 296621.36
A37: 33 | G37: =E37*F37 -> 0 | J37: =H37*I37 -> 0 | K37: =G37+J37 -> 0 | M37: =M36+K37-L37 -> 296621.36
A38: 34 | G38: =E38*F38 -> 0 | J38: =H38*I38 -> 0 | K38: =G38+J38 -> 0 | M38: =M37+K38-L38 -> 296621.36
E39: =SUM(E4:E38) -> 8500 | G39: =SUM(G4:G38) -> 842690 | H39: =SUM(H4:H38) -> 280 | J39: =SUM(J4:J38) -> 31147.2 | K39: =SUM(K4:K38) -> 873837.2 | L39: =SUM(L4:L38) -> 860000

Sheet  YG Gudda-2
A1: One Stop
A2: S.No | B2: Date | C2: GRN No | D2: Ind No/Bill No | E2: Diesel (Lts) | F2: Price | G2: Amount | H2: Petrol (Lts) | I2: Price | J2: Amount | K2: Total amount | L2: Amount paid | M2: As on Date | N2: Remarks
A3: Opening Balance | K3: 207747.6 | M3: 207747.6
A4: 1 | B4: 46204 | L4: 200000 | M4: =M3+K4-L4 -> 7747.6
B5: 46205 | M5: =M4+K5-L5 -> 7747.6 | N5: BPCL
A6: 2 | B6: 46206 | M6: =M4+K6-L6 -> 7747.6
A7: 3 | B7: 46207 | E7: 1000 | F7: 99.02 | G7: =E7*F7 -> 99020 | H7: 35 | I7: 111.12 | J7: =H7*I7 -> 3889.2 | K7: =G7+J7 -> 102909.2 | M7: =M6+K7-L7 -> 110656.8
A8: 4 | B8: 46208 | G8: =E8*F8 -> 0 | K8: =G8+J8 -> 0 | M8: =M7+K8-L8 -> 110656.8
A9: 5 | B9: 46209 | E9: 1000 | F9: 99.02 | G9: =E9*F9 -> 99020 | K9: =G9+J9 -> 99020 | M9: =M8+K9-L9 -> 209676.8
A10: 6 | B10: 46210 | M10: =M9+K10-L10 -> 209676.8
A11: 7 | B11: 46211 | M11: =M10+K11-L11 -> 209676.8
A12: 8 | B12: 46212 | M12: =M11+K12-L12 -> 209676.8
A13: 9 | B13: 46213 | M13: =M12+K13-L13 -> 209676.8
A14: 10 | B14: 46214 | M14: =M13+K14-L14 -> 209676.8
A15: 11 | B15: 46215 | M15: =M14+K15-L15 -> 209676.8
A16: 12 | B16: 46216 | E16: 1000 | F16: 99.02 | G16: =E16*F16 -> 99020 | H16: 35 | I16: 111.12 | J16: =H16*I16 -> 3889.2 | K16: =G16+J16 -> 102909.2 | M16: =M15+K16-L16 -> 312586
A17: 13 | B17: 46217 | G17: =E17*F17 -> 0 | J17: =H17*I17 -> 0 | K17: =G17+J17 -> 0 | M17: =M16+K17-L17 -> 312586
A18: 14 | B18: 46218 | G18: =E18*F18 -> 0 | J18: =H18*I18 -> 0 | K18: =G18+J18 -> 0 | L18: 150000 | M18: =M17+K18-L18 -> 162586
A19: 15 | B19: 46219 | G19: =E19*F19 -> 0 | J19: =H19*I19 -> 0 | K19: =G19+J19 -> 0 | M19: =M18+K19-L19 -> 162586
A20: 16 | B20: 46220 | G20: =E20*F20 -> 0 | J20: =H20*I20 -> 0 | K20: =G20+J20 -> 0 | M20: =M19+K20-L20 -> 162586
A21: 17 | B21: 46221 | G21: =E21*F21 -> 0 | J21: =H21*I21 -> 0 | K21: =G21+J21 -> 0 | M21: =M20+K21-L21 -> 162586
A22: 18 | B22: 46222 | G22: =E22*F22 -> 0 | J22: =H22*I22 -> 0 | K22: =G22+J22 -> 0 | M22: =M21+K22-L22 -> 162586
A23: 19 | B23: 46223 | G23: =E23*F23 -> 0 | J23: =H23*I23 -> 0 | K23: =G23+J23 -> 0 | M23: =M22+K23-L23 -> 162586
A24: 20 | B24: 46224 | G24: =E24*F24 -> 0 | J24: =H24*I24 -> 0 | K24: =G24+J24 -> 0 | M24: =M23+K24-L24 -> 162586
A25: 21 | B25: 46225 | E25: 1200 | F25: 99.02 | G25: =E25*F25 -> 118824 | H25: 35 | I25: 111.12 | J25: =H25*I25 -> 3889.2 | K25: =G25+J25 -> 122713.2 | L25: 150000 | M25: =M24+K25-L25 -> 135299.2
A26: 22 | B26: 46226 | G26: =E26*F26 -> 0 | J26: =H26*I26 -> 0 | K26: =G26+J26 -> 0 | M26: =M25+K26-L26 -> 135299.2
A27: 23 | B27: 46227 | G27: =E27*F27 -> 0 | J27: =H27*I27 -> 0 | K27: =G27+J27 -> 0 | M27: =M26+K27-L27 -> 135299.2
A28: 24 | B28: 46228 | G28: =E28*F28 -> 0 | J28: =H28*I28 -> 0 | K28: =G28+J28 -> 0 | M28: =M27+K28-L28 -> 135299.2
A29: 25 | B29: 46229 | G29: =E29*F29 -> 0 | J29: =H29*I29 -> 0 | K29: =G29+J29 -> 0 | M29: =M28+K29-L29 -> 135299.2
A30: 26 | B30: 46230 | G30: =E30*F30 -> 0 | J30: =H30*I30 -> 0 | K30: =G30+J30 -> 0 | M30: =M29+K30-L30 -> 135299.2
A31: 27 | B31: 46231 | G31: =E31*F31 -> 0 | J31: =H31*I31 -> 0 | K31: =G31+J31 -> 0 | M31: =M30+K31-L31 -> 135299.2
A32: 28 | B32: 46232 | G32: =E32*F32 -> 0 | J32: =H32*I32 -> 0 | K32: =G32+J32 -> 0 | M32: =M31+K32-L32 -> 135299.2
A33: 29 | B33: 46233 | G33: =E33*F33 -> 0 | J33: =H33*I33 -> 0 | K33: =G33+J33 -> 0 | M33: =M32+K33-L33 -> 135299.2
A34: 30 | B34: 46234 | E34: 403.96 | F34: 99.02 | G34: =E34*F34 -> 40000.119 | J34: =H34*I34 -> 0 | K34: =G34+J34 -> 40000.119 | L34: 175000 | M34: =M33+K34-L34 -> 299.3192
A35: 31 | G35: =E35*F35 -> 0 | J35: =H35*I35 -> 0 | K35: =G35+J35 -> 0 | M35: =M34+K35-L35 -> 299.3192
A36: 32 | G36: =E36*F36 -> 0 | J36: =H36*I36 -> 0 | K36: =G36+J36 -> 0 | M36: =M35+K36-L36 -> 299.3192
A37: 33 | G37: =E37*F37 -> 0 | J37: =H37*I37 -> 0 | K37: =G37+J37 -> 0 | M37: =M36+K37-L37 -> 299.3192
A38: 34 | G38: =E38*F38 -> 0 | J38: =H38*I38 -> 0 | K38: =G38+J38 -> 0 | M38: =M37+K38-L38 -> 299.3192
E39: =SUM(E4:E38) -> 4603.96 | G39: =SUM(G4:G38) -> 455884.12 | H39: =SUM(H4:H38) -> 105 | J39: =SUM(J4:J38) -> 11667.6 | K39: =SUM(K4:K38) -> 467551.72 | L39: =SUM(L4:L38) -> 675000

Sheet Hosadurga -2
A1: Shree Veeraprathap Fuel
A2: S.No | B2: Date | C2: GRN No | D2: Ind No/Bill No | E2: Diesel (Lts) | F2: Price | G2: Amount | H2: Petrol (Lts) | I2: Price | J2: Amount | K2: Total amount | L2: Amount paid | M2: As on Date | N2: Remarks
A3: Opening Balance | K3: 114284.39 | M3: 114284.39
A4: 1 | B4: 46204 | C4: 0 | E4: 0 | F4: 0 | G4: =E4*F4 -> 0 | J4: =H4*I4 -> 0 | K4: =G4+J4 -> 0 | L4: 100000 | M4: =M3+K4-L4 -> 14284.394
A5: 2 | B5: 46205 | C5: 0 | E5: 1000 | F5: 99.38 | G5: =E5*F5 -> 99380 | H5: 70 | I5: 111.72 | J5: =H5*I5 -> 7820.4 | K5: =G5+J5 -> 107200.4 | M5: =M4+K5-L5 -> 121484.79
A6: 3 | B6: 46206 | C6: 0 | G6: =E6*F6 -> 0 | J6: =H6*I6 -> 0 | K6: =G6+J6 -> 0 | M6: =M5+K6-L6 -> 121484.79
A7: 4 | B7: 46207 | C7: 0 | G7: =E7*F7 -> 0 | J7: =H7*I7 -> 0 | K7: =G7+J7 -> 0 | M7: =M6+K7-L7 -> 121484.79
A8: 5 | B8: 46208 | C8: 0 | G8: =E8*F8 -> 0 | J8: =H8*I8 -> 0 | K8: =G8+J8 -> 0 | M8: =M7+K8-L8 -> 121484.79
A9: 6 | B9: 46209 | C9: 0 | G9: =E9*F9 -> 0 | J9: =H9*I9 -> 0 | K9: =G9+J9 -> 0 | M9: =M8+K9-L9 -> 121484.79
A10: 7 | B10: 46210 | C10: 0 | G10: =E10*F10 -> 0 | J10: =H10*I10 -> 0 | K10: =G10+J10 -> 0 | M10: =M9+K10-L10 -> 121484.79
A11: 8 | B11: 46211 | C11: 0 | G11: =E11*F11 -> 0 | J11: =H11*I11 -> 0 | K11: =G11+J11 -> 0 | M11: =M10+K11-L11 -> 121484.79
A12: 9 | B12: 46212 | C12: 0 | G12: =E12*F12 -> 0 | J12: =H12*I12 -> 0 | K12: =G12+J12 -> 0 | M12: =M11+K12-L12 -> 121484.79
A13: 10 | B13: 46213 | C13: 0 | G13: =E13*F13 -> 0 | J13: =H13*I13 -> 0 | K13: =G13+J13 -> 0 | M13: =M12+K13-L13 -> 121484.79
A14: 11 | B14: 46214 | C14: 0 | G14: =E14*F14 -> 0 | J14: =H14*I14 -> 0 | K14: =G14+J14 -> 0 | M14: =M13+K14-L14 -> 121484.79
A15: 12 | B15: 46215 | C15: 0 | G15: =E15*F15 -> 0 | J15: =H15*I15 -> 0 | K15: =G15+J15 -> 0 | M15: =M14+K15-L15 -> 121484.79
A16: 13 | B16: 46216 | C16: 0 | G16: =E16*F16 -> 0 | J16: =H16*I16 -> 0 | K16: =G16+J16 -> 0 | M16: =M15+K16-L16 -> 121484.79
A17: 14 | B17: 46217 | C17: 0 | G17: =E17*F17 -> 0 | J17: =H17*I17 -> 0 | K17: =G17+J17 -> 0 | M17: =M16+K17-L17 -> 121484.79
... A24: 21 | B24: 46224 | C24: 0 | G24: =E24*F24 -> 0 | J24: =H24*I24 -> 0 | K24: =G24+J24 -> 0 | M24: =M23+K24-L24 -> 121484.79
A25: 22 | B25: 46225 | C25: 0 | G25: =E25*F25 -> 0 | J25: =H25*I25 -> 0 | K25: =G25+J25 -> 0 | L25: 121000 | M25: =M24+K25-L25 -> 484.7941
A26: 23 | B26: 46226 | C26: 0 | G26: =E26*F26 -> 0 | J26: =H26*I26 -> 0 | K26: =G26+J26 -> 0 | M26: =M25+K26-L26 -> 484.7941
A27: 24 | B27: 46227 | C27: 0 | G27: =E27*F27 -> 0 | J27: =H27*I27 -> 0 | K27: =G27+J27 -> 0 | M27: =M26+K27-L27 -> 484.7941
A28: 25 | B28: 46228 | C28: 0 | G28: =E28*F28 -> 0 | J28: =H28*I28 -> 0 | K28: =G28+J28 -> 0 | M28: =M27+K28-L28 -> 484.7941
A29: 26 | B29: 46229 | C29: 0 | G29: =E29*F29 -> 0 | J29: =H29*I29 -> 0 | K29: =G29+J29 -> 0 | M29: =M28+K29-L29 -> 484.7941
A30: 27 | B30: 46230 | C30: 0 | G30: =E30*F30 -> 0 | J30: =H30*I30 -> 0 | K30: =G30+J30 -> 0 | M30: =M29+K30-L30 -> 484.7941
A31: 28 | B31: 46231 | C31: 0 | G31: =E31*F31 -> 0 | J31: =H31*I31 -> 0 | K31: =G31+J31 -> 0 | M31: =M30+K31-L31 -> 484.7941
A32: 29 | B32: 46232 | C32: 0 | G32: =E32*F32 -> 0 | J32: =H32*I32 -> 0 | K32: =G32+J32 -> 0 | M32: =M31+K32-L32 -> 484.7941
A33: 30 | B33: 46233 | C33: 0 | G33: =E33*F33 -> 0 | J33: =H33*I33 -> 0 | K33: =G33+J33 -> 0 | M33: =M32+K33-L33 -> 484.7941
A34: 31 | K34: =G34+J34 -> 0
E35: =SUM(E4:E34) -> 1000 | G35: =SUM(G4:G34) -> 99380 | H35: =SUM(H4:H34) -> 70 | J35: =SUM(J4:J34) -> 7820.4 | K35: =SUM(K4:K34) -> 107200.4 | L35: =SUM(L4:L34) -> 221000

Sheet Hiriyur(VJNL)
A1: Sri Balaji Agencies
A2: S.No | B2: Date | C2: GRN No | D2: Ind No/Bill No | E2: Diesel (Lts) | F2: Price | G2: Amount | H2: Petrol (Lts) | I2: Price | J2: Amount | K2: Total amount | L2: Amount paid | M2: As on Date | N2: Remarks
A3: Opening Balance | K3: 219362.7 | M3: 219362.7
A4: 1 | B4: 46204 | E4: 2000 | F4: 100.09 | G4: =E4*F4 -> 200180 | H4: 70 | I4: 112.12 | J4: =H4*I4 -> 7848.4 | K4: =G4+J4 -> 208028.4 | L4: 219000 | M4: =M3+K4-L4 -> 208391.1
A5: 2 | B5: 46205 | G5: =E5*F5 -> 0 | J5: =H5*I5 -> 0 | K5: =G5+J5 -> 0 | M5: =M4+K5-L5 -> 208391.1
A6: 3 | B6: 46206 | G6: =E6*F6 -> 0 | J6: =H6*I6 -> 0 | K6: =G6+J6 -> 0 | M6: =M5+K6-L6 -> 208391.1
A7: 4 | B7: 46207 | G7: =E7*F7 -> 0 | J7: =H7*I7 -> 0 | K7: =G7+J7 -> 0 | M7: =M6+K7-L7 -> 208391.1
A8: 5 | B8: 46208 | G8: =E8*F8 -> 0 | J8: =H8*I8 -> 0 | K8: =G8+J8 -> 0 | M8: =M7+K8-L8 -> 208391.1
A9: 6 | B9: 46209 | G9: =E9*F9 -> 0 | J9: =H9*I9 -> 0 | K9: =G9+J9 -> 0 | M9: =M8+K9-L9 -> 208391.1
A10: 7 | B10: 46210 | G10: =E10*F10 -> 0 | J10: =H10*I10 -> 0 | K10: =G10+J10 -> 0 | M10: =M9+K10-L10 -> 208391.1
A11: 8 | B11: 46211 | G11: =E11*F11 -> 0 | J11: =H11*I11 -> 0 | K11: =G11+J11 -> 0 | M11: =M10+K11-L11 -> 208391.1
A12: 9 | B12: 46212 | G12: =E12*F12 -> 0 | J12: =H12*I12 -> 0 | K12: =G12+J12 -> 0 | M12: =M11+K12-L12 -> 208391.1
A13: 10 | B13: 46213 | G13: =E13*F13 -> 0 | J13: =H13*I13 -> 0 | K13: =G13+J13 -> 0 | M13: =M12+K13-L13 -> 208391.1
A14: 11 | B14: 46214 | G14: =E14*F14 -> 0 | H14: 70 | I14: 112.12 | J14: =H14*I14 -> 7848.4 | K14: =G14+J14 -> 7848.4 | M14: =M13+K14-L14 -> 216239.5
A15: 12 | B15: 46215 | G15: =E15*F15 -> 0 | J15: =H15*I15 -> 0 | K15: =G15+J15 -> 0 | M15: =M14+K15-L15 -> 216239.5
A16: 13 | B16: 46216 | G16: =E16*F16 -> 0 | J16: =H16*I16 -> 0 | K16: =G16+J16 -> 0 | M16: =M15+K16-L16 -> 216239.5
A17: 14 | B17: 46217 | G17: =E17*F17 -> 0 | J17: =H17*I17 -> 0 | K17: =G17+J17 -> 0 | M17: =M16+K17-L17 -> 216239.5
A18: 15 | B18: 46218 | G18: =E18*F18 -> 0 | J18: =H18*I18 -> 0 | K18: =G18+J18 -> 0 | M18: =M17+K18-L18 -> 216239.5
A19: 16 | B19: 46219 | G19: =E19*F19 -> 0 | J19: =H19*I19 -> 0 | K19: =G19+J19 -> 0 | M19: =M18+K19-L19 -> 216239.5
A20: 17 | B20: 46220 | G20: =E20*F20 -> 0 | J20: =H20*I20 -> 0 | K20: =G20+J20 -> 0 | M20: =M19+K20-L20 -> 216239.5
A21: 18 | B21: 46221 | G21: =E21*F21 -> 0 | J21: =H21*I21 -> 0 | K21: =G21+J21 -> 0 | M21: =M20+K21-L21 -> 216239.5
A22: 19 | B22: 46222 | G22: =E22*F22 -> 0 | J22: =H22*I22 -> 0 | K22: =G22+J22 -> 0 | M22: =M21+K22-L22 -> 216239.5
A23: 20 | B23: 46223 | G23: =E23*F23 -> 0 | J23: =H23*I23 -> 0 | K23: =G23+J23 -> 0 | M23: =M22+K23-L23 -> 216239.5
A24: 21 | B24: 46224 | G24: =E24*F24 -> 0 | J24: =H24*I24 -> 0 | K24: =G24+J24 -> 0 | M24: =M23+K24-L24 -> 216239.5
A25: 22 | B25: 46225 | G25: =E25*F25 -> 0 | J25: =H25*I25 -> 0 | K25: =G25+J25 -> 0 | L25: 216000 | M25: =M24+K25-L25 -> 239.5
A26: 23 | B26: 46226 | G26: =E26*F26 -> 0 | J26: =H26*I26 -> 0 | K26: =G26+J26 -> 0 | M26: =M25+K26-L26 -> 239.5
A27: 24 | B27: 46227 | G27: =E27*F27 -> 0 | J27: =H27*I27 -> 0 | K27: =G27+J27 -> 0 | M27: =M26+K27-L27 -> 239.5
A28: 25 | B28: 46228 | E28: 2000 | F28: 100.09 | G28: =E28*F28 -> 200180 | H28: 70 | I28: 112.12 | J28: =H28*I28 -> 7848.4 | K28: =G28+J28 -> 208028.4 | M28: =M27+K28-L28 -> 208267.9
A29: 26 | B29: 46229 | G29: =E29*F29 -> 0 | J29: =H29*I29 -> 0 | K29: =G29+J29 -> 0 | M29: =M28+K29-L29 -> 208267.9
A30: 27 | B30: 46230 | G30: =E30*F30 -> 0 | J30: =H30*I30 -> 0 | K30: =G30+J30 -> 0 | M30: =M29+K30-L30 -> 208267.9
A31: 28 | B31: 46231 | G31: =E31*F31 -> 0 | J31: =H31*I31 -> 0 | K31: =G31+J31 -> 0 | M31: =M30+K31-L31 -> 208267.9
A32: 29 | B32: 46232 | G32: =E32*F32 -> 0 | J32: =H32*I32 -> 0 | K32: =G32+J32 -> 0 | M32: =M31+K32-L32 -> 208267.9
A33: 30 | B33: 46233 | G33: =E33*F33 -> 0 | J33: =H33*I33 -> 0 | K33: =G33+J33 -> 0 | M33: =M32+K33-L33 -> 208267.9
A34: 31 | G34: =E34*F34 -> 0 | J34: =H34*I34 -> 0 | K34: =G34+J34 -> 0 | M34: =M33+K34-L34 -> 208267.9
E35: =SUM(E4:E34) -> 4000 | G35: =SUM(G4:G34) -> 400360 | H35: =SUM(H4:H34) -> 210 | J35: =SUM(J4:J34) -> 23545.2 | K35: =SUM(K4:K34) -> 423905.2 | L35: =SUM(L4:L34) -> 435000

Sheet Malebenur(KUWSDB)
A1: Sree Veerabhadreshwara Service Station
A2: S.No | B2: Date | C2: GRN No | D2: Ind No/Bill No | E2: Diesel (Lts) | F2: Price | G2: Amount | H2: Petrol (Lts) | I2: Price | J2: Amount | K2: Total amount | L2: Amount paid | M2: As on Date | N2: Remarks
A3: Opening Balance | K3: 132362.11 | M3: =+K3 -> 132362.11 | O3: 46138.764
A4: 1 | B4: 45839 | G4: =E4*F4 -> 0 | J4: =H4*I4 -> 0 | K4: =G4+J4 -> 0 | L4: 0 | M4: =M3+K4-L4 -> 132362.11
A5: 2 | B5: 45840 | G5: =E5*F5 -> 0 | J5: =H5*I5 -> 0 | K5: =G5+J5 -> 0 | L5: 0 | M5: =M4+K5-L5 -> 132362.11
A6: 3 | B6: 45841 | G6: =E6*F6 -> 0 | J6: =H6*I6 -> 0 | K6: =G6+J6 -> 0 | M6: =M5+K6-L6 -> 132362.11
A7: 4 | B7: 45842 | E7: 600 | F7: 99.99 | G7: =E7*F7 -> 59994 | H7: 30 | I7: 112.02 | J7: =H7*I7 -> 3360.6 | K7: =G7+J7 -> 63354.6 | M7: =M6+K7-L7 -> 195716.71
A8: 5 | B8: 45843 | G8: =E8*F8 -> 0 | J8: =H8*I8 -> 0 | K8: =G8+J8 -> 0 | M8: =M7+K8-L8 -> 195716.71
A9: 6 | B9: 45844 | G9: =E9*F9 -> 0 | J9: =H9*I9 -> 0 | K9: =G9+J9 -> 0 | M9: =M8+K9-L9 -> 195716.71
A10: 7 | B10: 45845 | E10: 600 | F10: 99.99 | G10: =E10*F10 -> 59994 | J10: =H10*I10 -> 0 | K10: =G10+J10 -> 59994 | L10: 195000 | M10: =M9+K10-L10 -> 60710.71
A11: 8 | B11: 45846 | G11: =E11*F11 -> 0 | J11: =H11*I11 -> 0 | K11: =G11+J11 -> 0 | M11: =M10+K11-L11 -> 60710.71
A12: 9 | B12: 45847 | E12: 800 | F12: 99.99 | G12: =E12*F12 -> 79992 | H12: 30 | I12: 112.02 | J12: =H12*I12 -> 3360.6 | K12: =G12+J12 -> 83352.6 | M12: =M11+K12-L12 -> 144063.31
A13: 10 | B13: 45848 | G13: =E13*F13 -> 0 | J13: =H13*I13 -> 0 | K13: =G13+J13 -> 0 | M13: =M12+K13-L13 -> 144063.31
A14: 11 | B14: 45849 | E14: 600 | F14: 99.99 | G14: =E14*F14 -> 59994 | J14: =H14*I14 -> 0 | K14: =G14+J14 -> 59994 | M14: =M13+K14-L14 -> 204057.31
A15: 12 | B15: 45850 | G15: =E15*F15 -> 0 | J15: =H15*I15 -> 0 | K15: =G15+J15 -> 0 | M15: =M14+K15-L15 -> 204057.31
A16: 13 | B16: 45851 | G16: =E16*F16 -> 0 | J16: =H16*I16 -> 0 | K16: =G16+J16 -> 0 | M16: =M15+K16-L16 -> 204057.31
A17: 14 | B17: 45852 | G17: =E17*F17 -> 0 | H17: 30 | I17: 112.02 | J17: =H17*I17 -> 3360.6 | K17: =G17+J17 -> 3360.6 | M17: =M16+K17-L17 -> 207417.91
A18: 15 | B18: 45853 | E18: 600 | F18: 99.99 | G18: =E18*F18 -> 59994 | H18: 30 | I18: 112.02 | J18: =H18*I18 -> 3360.6 | K18: =G18+J18 -> 63354.6 | M18: =M17+K18-L18 -> 270772.51 | N18: BT
A19: 16 | B19: 45854 | G19: =E19*F19 -> 0 | J19: =H19*I19 -> 0 | K19: =G19+J19 -> 0 | M19: =M18+K19-L19 -> 270772.51
A20: 17 | B20: 45855 | G20: =E20*F20 -> 0 | J20: =H20*I20 -> 0 | K20: =G20+J20 -> 0 | M20: =M19+K20-L20 -> 270772.51
A21: 18 | B21: 45856 | G21: =E21*F21 -> 0 | J21: =H21*I21 -> 0 | K21: =G21+J21 -> 0 | M21: =M20+K21-L21 -> 270772.51
A22: 19 | B22: 45857 | G22: =E22*F22 -> 0 | J22: =H22*I22 -> 0 | K22: =G22+J22 -> 0 | M22: =M21+K22-L22 -> 270772.51
A23: 20 | B23: 45858 | E23: 199.94 | F23: 100.03 | G23: =E23*F23 -> 19999.998 | J23: =H23*I23 -> 0 | K23: =G23+J23 -> 19999.998 | L23: =H23+K23 -> 19999.998 | M23: =M22+K23-L23 -> 270772.51 | N23: HPCL OTP Si Laxmi Ranganath
A24: 21 | B24: 45859 | G24: =E24*F24 -> 0 | J24: =H24*I24 -> 0 | K24: =G24+J24 -> 0 | L24: 0 | M24: =M23+K24-L24 -> 270772.51
A25: 22 | B25: 45860 | E25: 266.42 | F25: 99.99 | G25: =E25*F25 -> 26639.336 | H25: 30 | I25: 112.02 | J25: =H25*I25 -> 3360.6 | K25: =G25+J25 -> 29999.936 | L25: 29999.936 | M25: =M24+K25-L25 -> 270772.51
A26: 23 | B26: 45861 | G26: =E26*F26 -> 0 | J26: =H26*I26 -> 0 | K26: =G26+J26 -> 0 | M26: =M25+K26-L26 -> 270772.51
A27: 24 | B27: 45862 | G27: =E27*F27 -> 0 | J27: =H27*I27 -> 0 | K27: =G27+J27 -> 0 | M27: =M26+K27-L27 -> 270772.51
A28: 25 | B28: 45863 | E28: 299.91 | F28: 100.03 | G28: =E28*F28 -> 29999.997 | J28: =H28*I28 -> 0 | K28: =G28+J28 -> 29999.997 | L28: =H28+K28 -> 29999.997 | M28: =M27+K28-L28 -> 270772.51
A29: 26 | B29: 45864 | G29: =E29*F29 -> 0 | J29: =H29*I29 -> 0 | K29: =G29+J29 -> 0 | M29: =M28+K29-L29 -> 270772.51
A30: 27 | B30: 45865 | E30: 266.3 | F30: 100.03 | G30: =E30*F30 -> 26637.989 | H30: 30 | I30: 112.06 | J30: =H30*I30 -> 3361.8 | K30: =G30+J30 -> 29999.789 | L30: 29999.789 | M30: =M29+K30-L30 -> 270772.51
A31: 28 | B31: 45866 | E31: 299.82 | F31: 100.06 | G31: =E31*F31 -> 29999.989 | J31: =H31*I31 -> 0 | K31: =G31+J31 -> 29999.989 | L31: 29999.789 | M31: =M30+K31-L31 -> 270772.71 | N31: BHN FULES(BPCL) OTP
A32: 29 | B32: 45867 | G32: =E32*F32 -> 0 | J32: =H32*I32 -> 0 | K32: =G32+J32 -> 0 | L32: 200000 | M32: =M31+K32-L32 -> 70772.71 | N32: BT
A33: 30 | B33: 45868 | E33: 600 | F33: 99.99 | G33: =E33*F33 -> 59994 | J33: =H33*I33 -> 0 | K33: =G33+J33 -> 59994 | M33: =M32+K33-L33 -> 130766.71
A34: 31 | B34: 45869 | G34: =E34*F34 -> 0 | J34: =H34*I34 -> 0 | K34: =G34+J34 -> 0 | L34: 0 | M34: =M33+K34-L34 -> 130766.71
G35: =E35*F35 -> 0 | J35: =H35*I35 -> 0 | K35: =G35+J35 -> 0 | L35: 0 | M35: =M34+K35-L35 -> 130766.71
E36: 0 | F36: 0 | G36: =E36*F36 -> 0 | H36: 0 | I36: 0 | J36: =H36*I36 -> 0 | K36: =G36+J36 -> 0 | L36: 0 | M36: =M35+K36-L36 -> 130766.71
E37: =SUM(E4:E35) -> 5132.39 | G37: =SUM(G4:G35) -> 513239.31 | H37: =SUM(H4:H35) -> 180 | J37: =SUM(J4:J35) -> 20164.8 | K37: =SUM(K4:K35) -> 533404.11 | L37: =SUM(L4:L35) -> 534999.51
E38: 0 | G38: 0 | H38: 0 | J38: 0 | K38: =G38+J38 -> 0 | L38: 0
S43: 9052944708

Sheet Molakamuru
A1: Molakamuru
A2: S.No | B2: Date | C2: GRN No | D2: Ind No/Bill No | E2: Diesel (Lts) | F2: Price | G2: Amount | H2: Petrol (Lts) | I2: Price | J2: Amount | K2: Total amount | L2: Amount paid | M2: As on Date | N2: Remarks
A3: Opening Balance | K3: 8880.86 | L3: 0 | M3: 8880.86
A4: 1 | B4: 46204 | G4: =E4*F4 -> 0 | J4: =H4*I4 -> 0 | K4: =G4+J4 -> 0 | M4: =M3+K4-L4 -> 8880.86
A5: 2 | B5: 46205 | G5: =E5*F5 -> 0 | J5: =H5*I5 -> 0 | K5: =G5+J5 -> 0 | M5: =M4+K5-L5 -> 8880.86
A6: 3 | B6: 46206 | G6: =E6*F6 -> 0 | J6: =H6*I6 -> 0 | K6: =G6+J6 -> 0 | M6: =M5+K6-L6 -> 8880.86
A7: 4 | B7: 46207 | G7: =E7*F7 -> 0 | J7: =H7*I7 -> 0 | K7: =G7+J7 -> 0 | M7: =M6+K7-L7 -> 8880.86
A8: 5 | B8: 46208 | G8: =E8*F8 -> 0 | J8: =H8*I8 -> 0 | K8: =G8+J8 -> 0 | M8: =M7+K8-L8 -> 8880.86
A9: 6 | B9: 46209 | G9: =E9*F9 -> 0 | J9: =H9*I9 -> 0 | K9: =G9+J9 -> 0 | M9: =M8+K9-L9 -> 8880.86
A10: 7 | B10: 46210 | G10: =E10*F10 -> 0 | H10: 35 | I10: 112.06 | J10: =H10*I10 -> 3922.1 | K10: =G10+J10 -> 3922.1 | M10: =M9+K10-L10 -> 12802.96
A11: 8 | B11: 46211 | E11: 200 | F11: 100.04 | G11: =E11*F11 -> 20008 | J11: =H11*I11 -> 0 | K11: =G11+J11 -> 20008 | M11: =M10+K11-L11 -> 32810.96
A12: 9 | B12: 46212 | G12: =E12*F12 -> 0 | J12: =H12*I12 -> 0 | K12: =G12+J12 -> 0 | M12: =M11+K12-L12 -> 32810.96
A13: 10 | B13: 46213 | G13: =E13*F13 -> 0 | J13: =H13*I13 -> 0 | K13: =G13+J13 -> 0 | M13: =M12+K13-L13 -> 32810.96
A14: 11 | B14: 46214 | E14: 400 | F14: 100.04 | G14: =E14*F14 -> 40016 | J14: =H14*I14 -> 0 | K14: =G14+J14 -> 40016 | M14: =M13+K14-L14 -> 72826.96
A15: 12 | B15: 46215 | G15: =E15*F15 -> 0 | J15: =H15*I15 -> 0 | K15: =G15+J15 -> 0 | M15: =M14+K15-L15 -> 72826.96
A16: 13 | B16: 46216 | G16: =E16*F16 -> 0 | J16: =H16*I16 -> 0 | K16: =G16+J16 -> 0 | M16: =M15+K16-L16 -> 72826.96
A17: 14 | B17: 46217 | G17: =E17*F17 -> 0 | H17: 35 | I17: 112.06 | J17: =H17*I17 -> 3922.1 | K17: =G17+J17 -> 3922.1 | M17: =M16+K17-L17 -> 76749.06
A18: 15 | B18: 46218 | E18: 400 | F18: 100.04 | G18: =E18*F18 -> 40016 | J18: =H18*I18 -> 0 | K18: =G18+J18 -> 40016 | M18: =M17+K18-L18 -> 116765.06
A19: 16 | B19: 46219 | G19: =E19*F19 -> 0 | J19: =H19*I19 -> 0 | K19: =G19+J19 -> 0 | M19: =M18+K19-L19 -> 116765.06
A20: 17 | B20: 46220 | G20: =E20*F20 -> 0 | H20: 35 | I20: 112.06 | J20: =H20*I20 -> 3922.1 | K20: =G20+J20 -> 3922.1 | M20: =M19+K20-L20 -> 120687.16
A21: 18 | B21: 46221 | G21: =E21*F21 -> 0 | J21: =H21*I21 -> 0 | K21: =G21+J21 -> 0 | M21: =M20+K21-L21 -> 120687.16
A22: 19 | B22: 46222 | G22: =E22*F22 -> 0 | J22: =H22*I22 -> 0 | K22: =G22+J22 -> 0 | M22: =M21+K22-L22 -> 120687.16
A23: 20 | B23: 46223 | G23: =E23*F23 -> 0 | J23: =H23*I23 -> 0 | K23: =G23+J23 -> 0 | M23: =M22+K23-L23 -> 120687.16
A24: 21 | B24: 46224 | G24: =E24*F24 -> 0 | J24: =H24*I24 -> 0 | K24: =G24+J24 -> 0 | M24: =M23+K24-L24 -> 120687.16
A25: 22 | B25: 46225 | E25: 300 | F25: 100.04 | G25: =E25*F25 -> 30012 | J25: =H25*I25 -> 0 | K25: =G25+J25 -> 30012 | M25: =M24+K25-L25 -> 150699.16
A26: 23 | B26: 46226 | G26: =E26*F26 -> 0 | J26: =H26*I26 -> 0 | K26: =G26+J26 -> 0 | M26: =M25+K26-L26 -> 150699.16
A27: 24 | B27: 46227 | G27: =E27*F27 -> 0 | J27: =H27*I27 -> 0 | K27: =G27+J27 -> 0 | M27: =M26+K27-L27 -> 150699.16
A28: 25 | B28: 46228 | G28: =E28*F28 -> 0 | J28: =H28*I28 -> 0 | K28: =G28+J28 -> 0 | M28: =M27+K28-L28 -> 150699.16
A29: 26 | B29: 46229 | G29: =E29*F29 -> 0 | J29: =H29*I29 -> 0 | K29: =G29+J29 -> 0 | M29: =M28+K29-L29 -> 150699.16
A30: 27 | B30: 46230 | E30: 85 | F30: 100.03 | G30: =E30*F30 -> 8502.55 | H30: 20 | I30: 112.06 | J30: =H30*I30 -> 2241.2 | K30: =G30+J30 -> 10743.75 | L30: 10743.75 | M30: =M29+K30-L30 -> 150699.16
A31: 28 | B31: 46231 | G31: =E31*F31 -> 0 | J31: =H31*I31 -> 0 | K31: =G31+J31 -> 0 | M31: =M30+K31-L31 -> 150699.16
A32: 29 | B32: 46232 | G32: =E32*F32 -> 0 | J32: =H32*I32 -> 0 | K32: =G32+J32 -> 0 | M32: =M31+K32-L32 -> 150699.16
A33: 30 | B33: 46233 | E33: 85 | F33: 100.03 | G33: =E33*F33 -> 8502.55 | H33: 10 | I33: 112.06 | J33: =H33*I33 -> 1120.6 | K33: =G33+J33 -> 9623.15 | L33: 9623.15 | M33: =M32+K33-L33 -> 150699.16
A34: 31 | G34: =E34*F34 -> 0 | K34: =G34+J34 -> 0 | L34: 100000 | M34: =M33+K34-L34 -> 50699.16
E35: =SUM(E4:E34) -> 1470 | G35: =SUM(G4:G34) -> 147057.1 | H35: =SUM(H4:H34) -> 135 | J35: =SUM(J4:J34) -> 15128.1 | K35: =SUM(K4:K34) -> 162185.2 | L35: =SUM(L4:L34) -> 120366.9

Sheet Chellakere -1
A1: Shivaganga Service Station (BPCL)
A2: S.No | B2: Date | C2: GRN No | D2: Ind No/Bill No | E2: Diesel (Lts) | F2: Price | G2: Amount | H2: Petrol (Lts) | I2: Price | J2: Amount | K2: Total amount | L2: Amount paid | M2: As on Date | N2: Remarks
A3: Opening Balance | K3: 116056.55 | L3: 160498.02 | M3: 116056.55
A4: 1 | B4: 46204 | G4: =E4*F4 -> 0 | J4: =H4*I4 -> 0 | K4: =G4+J4 -> 0 | M4: =M3+K4-L4 -> 116056.55
A5: 2 | B5: 46205 | G5: =E5*F5 -> 0 | J5: =H5*I5 -> 0 | K5: =G5+J5 -> 0 | M5: =M4+K5-L5 -> 116056.55
A6: 3 | B6: 46206 | G6: =E6*F6 -> 0 | J6: =H6*I6 -> 0 | K6: =G6+J6 -> 0 | M6: =M5+K6-L6 -> 116056.55 | R6: =L7+L8 -> 0
A7: 4 | B7: 46207 | E7: 600 | F7: 100.05 | G7: =E7*F7 -> 60030 | H7: 35 | I7: 112.07 | J7: =H7*I7 -> 3922.45 | K7: =G7+J7 -> 63952.45 | M7: =M6+K7-L7 -> 180009
A8: 5 | B8: 46208 | G8: =E8*F8 -> 0 | J8: =H8*I8 -> 0 | K8: =G8+J8 -> 0 | M8: =M7+K8-L8 -> 180009
A9: 6 | B9: 46209 | G9: =E9*F9 -> 0 | J9: =H9*I9 -> 0 | K9: =G9+J9 -> 0 | M9: =M8+K9-L9 -> 180009 | Q9: 54242
A10: 7 | B10: 46210 | G10: =E10*F10 -> 0 | J10: =H10*I10 -> 0 | K10: =G10+J10 -> 0 | M10: =M9+K10-L10 -> 180009 | S10: 80000
A11: 8 | B11: 46211 | G11: =E11*F11 -> 0 | J11: =H11*I11 -> 0 | K11: =G11+J11 -> 0 | M11: =M10+K11-L11 -> 180009 | S11: 18414
A12: 9 | B12: 46212 | E12: 600 | F12: 100.05 | G12: =E12*F12 -> 60030 | H12: 35 | I12: 112.07 | J12: =H12*I12 -> 3922.45 | K12: =G12+J12 -> 63952.45 | M12: =M11+K12-L12 -> 243961.45 | S12: 18414
A13: 10 | B13: 46213 | G13: =E13*F13 -> 0 | J13: =H13*I13 -> 0 | K13: =G13+J13 -> 0 | M13: =M12+K13-L13 -> 243961.45 | S13: 18417.68
A14: 11 | B14: 46214 | G14: =E14*F14 -> 0 | J14: =H14*I14 -> 0 | K14: =G14+J14 -> 0 | M14: =M13+K14-L14 -> 243961.45 | S14: =SUM(S10:S13) -> 135245.68
A15: 12 | B15: 46215 | G15: =E15*F15 -> 0 | J15: =H15*I15 -> 0 | K15: =G15+J15 -> 0 | M15: =M14+K15-L15 -> 243961.45
A16: 13 | B16: 46216 | G16: =E16*F16 -> 0 | J16: =H16*I16 -> 0 | K16: =G16+J16 -> 0 | M16: =M15+K16-L16 -> 243961.45
A17: 14 | B17: 46217 | E17: 600 | F17: 100.05 | G17: =E17*F17 -> 60030 | H17: 70 | I17: 112.07 | J17: =H17*I17 -> 7844.9 | K17: =G17+J17 -> 67874.9 | M17: =M16+K17-L17 -> 311836.35
A18: 15 | B18: 46218 | G18: =E18*F18 -> 0 | J18: =H18*I18 -> 0 | K18: =G18+J18 -> 0 | M18: =M17+K18-L18 -> 311836.35
A19: 16 | B19: 46219 | G19: =E19*F19 -> 0 | J19: =H19*I19 -> 0 | K19: =G19+J19 -> 0 | M19: =M18+K19-L19 -> 311836.35
A20: 17 | B20: 46220 | G20: =E20*F20 -> 0 | J20: =H20*I20 -> 0 | K20: =G20+J20 -> 0 | M20: =M19+K20-L20 -> 311836.35
A21: 18 | B21: 46221 | E21: 600 | F21: 100.05 | G21: =E21*F21 -> 60030 | H21: 35 | I21: 112.07 | J21: =H21*I21 -> 3922.45 | K21: =G21+J21 -> 63952.45 | M21: =M20+K21-L21 -> 375788.8
A22: 19 | B22: 46222 | G22: =E22*F22 -> 0 | J22: =H22*I22 -> 0 | K22: =G22+J22 -> 0 | M22: =M21+K22-L22 -> 375788.8
A23: 20 | B23: 46223 | G23: =E23*F23 -> 0 | J23: =H23*I23 -> 0 | K23: =G23+J23 -> 0 | M23: =M22+K23-L23 -> 375788.8
B24: 46224 | M24: =M23+K24-L24 -> 375788.8
A25: 21 | B25: 46225 | G25: =E25*F25 -> 0 | J25: =H25*I25 -> 0 | K25: =G25+J25 -> 0 | L25: 300000 | M25: =M24+K25-L25 -> 75788.801 | N25: BPCL Cardb Card No-863
A26: 22 | B26: 46226 | E26: 600 | F26: 100.05 | G26: =E26*F26 -> 60030 | H26: 70 | I26: 112.07 | J26: =H26*I26 -> 7844.9 | K26: =G26+J26 -> 67874.9 | M26: =M25+K26-L26 -> 143663.7
A27: 23 | B27: 46227 | G27: =E27*F27 -> 0 | J27: =H27*I27 -> 0 | K27: =G27+J27 -> 0 | M27: =M26+K27-L27 -> 143663.7
A28: 24 | B28: 46228 | G28: =E28*F28 -> 0 | J28: =H28*I28 -> 0 | K28: =G28+J28 -> 0 | M28: =M27+K28-L28 -> 143663.7
A29: 25 | B29: 46229 | G29: =E29*F29 -> 0 | J29: =H29*I29 -> 0 | K29: =G29+J29 -> 0 | M29: =M28+K29-L29 -> 143663.7
A30: 26 | B30: 46230 | G30: =E30*F30 -> 0 | J30: =H30*I30 -> 0 | K30: =G30+J30 -> 0 | M30: =M29+K30-L30 -> 143663.7
A31: 27 | B31: 46231 | G31: =E31*F31 -> 0 | J31: =H31*I31 -> 0 | K31: =G31+J31 -> 0 | M31: =M30+K31-L31 -> 143663.7
A32: 28 | B32: 46232 | E32: 600 | F32: 100.05 | G32: =E32*F32 -> 60030 | H32: 65 | I32: 112.07 | J32: =H32*I32 -> 7284.55 | K32: =G32+J32 -> 67314.55 | M32: =M31+K32-L32 -> 210978.25
A33: 29 | B33: 46233 | G33: =E33*F33 -> 0 | J33: =H33*I33 -> 0 | K33: =G33+J33 -> 0 | M33: =M32+K33-L33 -> 210978.25
A34: 30 | B34: 46234 | G34: =E34*F34 -> 0 | J34: =H34*I34 -> 0 | K34: =G34+J34 -> 0 | M34: =M33+K34-L34 -> 210978.25
A35: 31 | G35: =E35*F35 -> 0 | J35: =H35*I35 -> 0 | K35: =G35+J35 -> 0 | M35: =M34+K35-L35 -> 210978.25
E38: =SUM(E4:E35) -> 3600 | G38: =SUM(G4:G35) -> 360180 | H38: =SUM(H4:H35) -> 310 | J38: =SUM(J4:J35) -> 34741.7 | K38: =SUM(K4:K35) -> 394921.7 | L38: =SUM(L4:L35) -> 300000

Sheet  Chellakere-PKG-9
A1: Chellakere-PKG-09
A2: S.No | B2: Date | C2: GRN No | D2: Ind No/Bill No | E2: Diesel (Lts) | F2: Price | G2: Amount | H2: Petrol (Lts) | I2: Price | J2: Amount | K2: Total amount | L2: Amount paid | M2: As on Date | N2: Remarks
A3: Opening Balance | K3: 0 | L3: 0 | M3: 0
A4: 1 | B4: 46204 | E4: 140 | F4: 100.05 | G4: =E4*F4 -> 14007 | J4: =H4*I4 -> 0 | K4: =G4+J4 -> 14007 | L4: =K4 -> 14007 | M4: =M3+K4-L4 -> 0
A5: 2 | B5: 46205 | G5: =E5*F5 -> 0 | J5: =H5*I5 -> 0 | K5: =G5+J5 -> 0 | L5: =K5 -> 0 | M5: =M4+K5-L5 -> 0
A6: 3 | B6: 46206 | G6: =E6*F6 -> 0 | J6: =H6*I6 -> 0 | K6: =G6+J6 -> 0 | L6: =K6 -> 0 | M6: =M5+K6-L6 -> 0
A7: 4 | B7: 46207 | G7: =E7*F7 -> 0 | J7: =H7*I7 -> 0 | K7: =G7+J7 -> 0 | L7: =K7 -> 0 | M7: =M6+K7-L7 -> 0
A8: 5 | B8: 46208 | G8: =E8*F8 -> 0 | J8: =H8*I8 -> 0 | K8: =G8+J8 -> 0 | L8: =K8 -> 0 | M8: =M7+K8-L8 -> 0
A9: 6 | B9: 46209 | G9: =E9*F9 -> 0 | H9: 12 | I9: 112.07 | J9: =H9*I9 -> 1344.84 | K9: =G9+J9 -> 1344.84 | L9: =K9 -> 1344.84 | M9: =M8+K9-L9 -> 0
A10: 7 | B10: 46210 | E10: 20 | F10: 100.05 | G10: =E10*F10 -> 2001 | J10: =H10*I10 -> 0 | K10: =G10+J10 -> 2001 | L10: =K10 -> 2001 | M10: =M9+K10-L10 -> 0
A11: 8 | B11: 46211 | G11: =E11*F11 -> 0 | J11: =H11*I11 -> 0 | K11: =G11+J11 -> 0 | L11: =K11 -> 0 | M11: =M10+K11-L11 -> 0
A12: 9 | B12: 46212 | E12: 39 | F12: 100.05 | G12: =E12*F12 -> 3901.95 | J12: =H12*I12 -> 0 | K12: =G12+J12 -> 3901.95 | L12: =K12 -> 3901.95 | M12: =M11+K12-L12 -> 0
A13: 10 | B13: 46213 | G13: =E13*F13 -> 0 | J13: =H13*I13 -> 0 | K13: =G13+J13 -> 0 | L13: =K13 -> 0 | M13: =M12+K13-L13 -> 0
A14: 11 | B14: 46214 | E14: 70 | F14: 100.05 | G14: =E14*F14 -> 7003.5 | H14: 4.37 | I14: 112.07 | J14: =H14*I14 -> 489.7459 | K14: =G14+J14 -> 7493.2459 | L14: =K14 -> 7493.2459 | M14: =M13+K14-L14 -> 0
A15: 12 | B15: 46215 | G15: =E15*F15 -> 0 | J15: =H15*I15 -> 0 | K15: =G15+J15 -> 0 | L15: =K15 -> 0 | M15: =M14+K15-L15 -> 0
A16: 13 | B16: 46216 | E16: 48 | F16: 100.05 | G16: =E16*F16 -> 4802.4 | J16: =H16*I16 -> 0 | K16: =G16+J16 -> 4802.4 | L16: =K16 -> 4802.4 | M16: =M15+K16-L16 -> 0
A17: 14 | B17: 46217 | E17: 70 | F17: 100.05 | G17: =E17*F17 -> 7003.5 | J17: =H17*I17 -> 0 | K17: =G17+J17 -> 7003.5 | L17: =K17 -> 7003.5 | M17: =M16+K17-L17 -> 0
A18: 15 | B18: 46218 | G18: =E18*F18 -> 0 | J18: =H18*I18 -> 0 | K18: =G18+J18 -> 0 | L18: =K18 -> 0 | M18: =M17+K18-L18 -> 0
A19: 16 | B19: 46219 | E19: 89 | F19: 100.05 | G19: =E19*F19 -> 8904.45 | H19: 6 | I19: 112.07 | J19: =H19*I19 -> 672.42 | K19: =G19+J19 -> 9576.87 | L19: =K19 -> 9576.87 | M19: =M18+K19-L19 -> 0
A20: 17 | B20: 46220 | G20: =E20*F20 -> 0 | J20: =H20*I20 -> 0 | K20: =G20+J20 -> 0 | L20: =K20 -> 0 | M20: =M19+K20-L20 -> 0 | T20: 54.83
A21: 18 | B21: 46221 | E21: 80.16 | F21: 100.05 | G21: =E21*F21 -> 8020.008 | J21: =H21*I21 -> 0 | K21: =G21+J21 -> 8020.008 | L21: =K21 -> 8020.008 | M21: =M20+K21-L21 -> 0 | T21: 0.55
A22: 19 | B22: 46222 | G22: =E22*F22 -> 0 | H22: 11.97 | I22: 112.07 | J22: =H22*I22 -> 1341.4779 | K22: =G22+J22 -> 1341.4779 | L22: =K22 -> 1341.4779 | M22: =M21+K22-L22 -> 0
B23: 46223 | G23: =E23*F23 -> 0 | K23: =G23+J23 -> 0 | L23: =K23 -> 0
A24: 20 | B24: 46224 | G24: =E24*F24 -> 0 | J24: =H24*I24 -> 0 | K24: =G24+J24 -> 0 | L24: =K24 -> 0 | M24: =M22+K24-L24 -> 0
A25: 21 | B25: 46225 | E25: 43 | F25: 100.05 | G25: =E25*F25 -> 4302.15 | J25: =H25*I25 -> 0 | K25: =G25+J25 -> 4302.15 | L25: =K25 -> 4302.15 | M25: =M24+K25-L25 -> 0
A26: 22 | B26: 46226 | G26: =E26*F26 -> 0 | H26: 12 | I26: 112.07 | J26: =H26*I26 -> 1344.84 | K26: =G26+J26 -> 1344.84 | L26: =K26 -> 1344.84 | M26: =M25+K26-L26 -> 0
A27: 23 | B27: 46227 | G27: =E27*F27 -> 0 | J27: =H27*I27 -> 0 | K27: =G27+J27 -> 0 | L27: =K27 -> 0 | M27: =M26+K27-L27 -> 0
A28: 24 | B28: 46228 | E28: 39.984 | F28: 100.04 | G28: =E28*F28 -> 3999.9994 | J28: =H28*I28 -> 0 | K28: =G28+J28 -> 3999.9994 | L28: =K28 -> 3999.9994 | M28: =M27+K28-L28 -> 0 | N28: Received from Maruthi filling station
A29: 25 | B29: 46229 | G29: =E29*F29 -> 0 | J29: =H29*I29 -> 0 | K29: =G29+J29 -> 0 | L29: =K29 -> 0 | M29: 0
A30: 26 | B30: 46230 | G30: =E30*F30 -> 0 | J30: =H30*I30 -> 0 | K30: =G30+J30 -> 0 | L30: =K30 -> 0 | M30: 0
A31: 27 | B31: 46231 | E31: 37 | F31: 100.05 | G31: =E31*F31 -> 3701.85 | H31: 6 | I31: 112.07 | J31: =H31*I31 -> 672.42 | K31: =G31+J31 -> 4374.27 | L31: =K31 -> 4374.27 | M31: 0
A32: 28 | B32: 46232 | G32: =E32*F32 -> 0 | J32: =H32*I32 -> 0 | K32: =G32+J32 -> 0 | L32: =K32 -> 0 | M32: 0
A33: 29 | B33: 46233 | E33: 39.61 | F33: 100.05 | G33: =E33*F33 -> 3962.9805 | H33: 6 | I33: 112.07 | J33: =H33*I33 -> 672.42 | K33: =G33+J33 -> 4635.4005 | L33: =K33 -> 4635.4005
A34: 30 | G34: =E34*F34 -> 0 | J34: =H34*I34 -> 0 | K34: =G34+J34 -> 0 | L34: =K34 -> 0
A35: 31 | G35: =E35*F35 -> 0 | J35: =H35*I35 -> 0 | K35: =G35+J35 -> 0 | L35: =K35 -> 0
E36: =SUM(E4:E35) -> 715.754 | G36: =SUM(G4:G35) -> 71610.788 | H36: =SUM(H4:H35) -> 58.34 | J36: =SUM(J4:J35) -> 6538.1638 | K36: =SUM(K4:K35) -> 78148.952 | L36: =SUM(L4:L35) -> 78148.952

Sheet  Chennagiri
A1: Chennagiri
A2: S.No | B2: Date | C2: GRN No | D2: Ind No/Bill No | E2: Diesel (Lts) | F2: Price | G2: Amount | H2: Petrol (Lts) | I2: Price | J2: Amount | K2: Total amount | L2: Amount paid | M2: As on Date | N2: Remarks
A3: Opening Balance | K3: 0 | L3: 0 | M3: =+K3 -> 0
A4: 1 | B4: 46204 | E4: 160 | F4: 99.87 | G4: =E4*F4 -> 15979.2 | H4: 29.99 | I4: 112.06 | J4: =H4*I4 -> 3360.6794 | K4: =G4+J4 -> 19339.879 | L4: =K4 -> 19339.879 | M4: =M3+K4-L4 -> 0
A5: 2 | B5: 46205 | G5: =E5*F5 -> 0 | J5: =H5*I5 -> 0 | K5: =G5+J5 -> 0 | L5: =K5 -> 0 | M5: =M4+K5-L5 -> 0
A6: 3 | B6: 46206 | G6: =E6*F6 -> 0 | J6: =H6*I6 -> 0 | K6: =G6+J6 -> 0 | L6: =K6 -> 0 | M6: =M5+K6-L6 -> 0
A7: 4 | B7: 46207 | E7: 200 | F7: 99.87 | G7: =E7*F7 -> 19974 | J7: =H7*I7 -> 0 | K7: =G7+J7 -> 19974 | L7: =K7 -> 19974 | M7: =M6+K7-L7 -> 0
A8: 5 | B8: 46208 | G8: =E8*F8 -> 0 | J8: =H8*I8 -> 0 | K8: =G8+J8 -> 0 | L8: =K8 -> 0 | M8: =M7+K8-L8 -> 0
A9: 6 | B9: 46209 | G9: =E9*F9 -> 0 | J9: =H9*I9 -> 0 | K9: =G9+J9 -> 0 | L9: =K9 -> 0 | M9: =M8+K9-L9 -> 0
A10: 7 | B10: 46210 | G10: =E10*F10 -> 0 | J10: =H10*I10 -> 0 | K10: =G10+J10 -> 0 | L10: =K10 -> 0 | M10: =M9+K10-L10 -> 0
A11: 8 | B11: 46211 | G11: =E11*F11 -> 0 | J11: =H11*I11 -> 0 | K11: =G11+J11 -> 0 | L11: =K11 -> 0 | M11: =M10+K11-L11 -> 0
A12: 9 | B12: 46212 | E12: 160 | F12: 99.87 | G12: =E12*F12 -> 15979.2 | J12: =H12*I12 -> 0 | K12: =G12+J12 -> 15979.2 | L12: =K12 -> 15979.2 | M12: =M11+K12-L12 -> 0
A13: 10 | B13: 46213 | G13: =E13*F13 -> 0 | J13: =H13*I13 -> 0 | K13: =G13+J13 -> 0 | L13: =K13 -> 0 | M13: =M12+K13-L13 -> 0
A14: 11 | B14: 46214 | G14: =E14*F14 -> 0 | J14: =H14*I14 -> 0 | K14: =G14+J14 -> 0 | L14: =K14 -> 0 | M14: =M13+K14-L14 -> 0
A15: 12 | B15: 46215 | G15: =E15*F15 -> 0 | J15: =H15*I15 -> 0 | K15: =G15+J15 -> 0 | L15: =K15 -> 0 | M15: =M14+K15-L15 -> 0
A16: 13 | B16: 46216 | E16: 150 | F16: 99.87 | G16: =E16*F16 -> 14980.5 | J16: =H16*I16 -> 0 | K16: =G16+J16 -> 14980.5 | L16: =K16 -> 14980.5 | M16: =M15+K16-L16 -> 0
A17: 14 | B17: 46217 | G17: =E17*F17 -> 0 | J17: =H17*I17 -> 0 | K17: =G17+J17 -> 0 | L17: =K17 -> 0 | M17: =M16+K17-L17 -> 0
A18: 15 | B18: 46218 | G18: =E18*F18 -> 0 | J18: =H18*I18 -> 0 | K18: =G18+J18 -> 0 | L18: =K18 -> 0 | M18: =M17+K18-L18 -> 0
A19: 16 | B19: 46219 | E19: 116 | F19: 99.87 | G19: =E19*F19 -> 11584.92 | H19: 30 | I19: 112.06 | J19: =H19*I19 -> 3361.8 | K19: =G19+J19 -> 14946.72 | L19: =K19 -> 14946.72 | M19: =M18+K19-L19 -> 0
A20: 17 | B20: 46220 | G20: =E20*F20 -> 0 | J20: =H20*I20 -> 0 | K20: =G20+J20 -> 0 | L20: =K20 -> 0 | M20: =M19+K20-L20 -> 0
A21: 18 | B21: 46221 | G21: =E21*F21 -> 0 | J21: =H21*I21 -> 0 | K21: =G21+J21 -> 0 | L21: =K21 -> 0 | M21: =M20+K21-L21 -> 0
A22: 19 | B22: 46222 | G22: =E22*F22 -> 0 | J22: =H22*I22 -> 0 | K22: =G22+J22 -> 0 | L22: =K22 -> 0 | M22: =M21+K22-L22 -> 0
A23: 20 | B23: 46223 | G23: =E23*F23 -> 0 | J23: =H23*I23 -> 0 | K23: =G23+J23 -> 0 | L23: =K23 -> 0 | M23: =M22+K23-L23 -> 0
A24: 21 | B24: 46224 | G24: =E24*F24 -> 0 | J24: =H24*I24 -> 0 | K24: =G24+J24 -> 0 | L24: =K24 -> 0 | M24: =M23+K24-L24 -> 0
A25: 22 | B25: 46225 | E25: 130.17 | F25: 99.87 | G25: =E25*F25 -> 13000.078 | J25: =H25*I25 -> 0 | K25: =G25+J25 -> 13000.078 | L25: =K25 -> 13000.078 | M25: =M24+K25-L25 -> 0
A26: 23 | B26: 46226 | G26: =E26*F26 -> 0 | J26: =H26*I26 -> 0 | K26: =G26+J26 -> 0 | L26: =K26 -> 0 | M26: =M25+K26-L26 -> 0
A27: 24 | B27: 46227 | E27: 200 | F27: 99.87 | G27: =E27*F27 -> 19974 | J27: =H27*I27 -> 0 | K27: =G27+J27 -> 19974 | L27: =K27 -> 19974 | M27: =M26+K27-L27 -> 0
A28: 25 | B28: 46228 | G28: =E28*F28 -> 0 | J28: =H28*I28 -> 0 | K28: =G28+J28 -> 0 | L28: =K28 -> 0 | M28: 0
A29: 26 | B29: 46229 | G29: =E29*F29 -> 0 | J29: =H29*I29 -> 0 | K29: =G29+J29 -> 0 | L29: =K29 -> 0 | M29: 0
A30: 27 | B30: 46230 | G30: =E30*F30 -> 0 | J30: =H30*I30 -> 0 | K30: =G30+J30 -> 0 | L30: =K30 -> 0 | M30: 0
A31: 28 | B31: 46231 | E31: 100 | F31: 99.9 | G31: =E31*F31 -> 9990 | J31: =H31*I31 -> 0 | K31: =G31+J31 -> 9990 | L31: =K31 -> 9990 | M31: 0
A32: 29 | B32: 46232 | G32: =E32*F32 -> 0 | J32: =H32*I32 -> 0 | K32: =G32+J32 -> 0 | L32: =K32 -> 0
A33: 30 | B33: 46233 | G33: =E33*F33 -> 0 | J33: =H33*I33 -> 0 | K33: =G33+J33 -> 0 | L33: =K33 -> 0
A34: 31 | B34: 46234 | E34: 116 | F34: 99.87 | G34: 11584.92 | H34: 30 | I34: 112.06 | J34: 3361.8 | K34: =G34+J34 -> 14946.72 | L34: =K34 -> 14946.72
E35: =SUM(E4:E34) -> 1332.17 | G35: =SUM(G4:G34) -> 133046.82 | H35: =SUM(H4:H34) -> 89.99 | J35: =SUM(J4:J34) -> 10084.279 | K35: =SUM(K4:K34) -> 143131.1 | L35: =SUM(L4:L34) -> 143131.1

Sheet Khanapur
A1: V.V.Varde
A2: S.No | B2: Date | C2: GRN No | D2: Ind No/Bill No | E2: Diesel (Lts) | F2: Price | G2: Amount | H2: Petrol (Lts) | I2: Price | J2: Amount | K2: Total amount | L2: Date of payment | M2: Amount paid | N2: Remarks
D3: Opening Balance | K3: 105067.75 | M3: 105067.75
A4: 1 | B4: 46204 | E4: 47.18 | F4: 98.69 | G4: =E4*F4 -> 4656.1942 | J4: =H4*I4 -> 0 | K4: =G4+J4 -> 4656.1942 | M4: =M3+K4-L4 -> 109723.94
A5: 2 | B5: 46205 | E5: 5 | F5: 98.69 | G5: =E5*F5 -> 493.45 | H5: 5 | I5: 111.98 | J5: =H5*I5 -> 559.9 | K5: =G5+J5 -> 1053.35 | M5: =M4+K5-L5 -> 110777.29 | S5: 90.88 | T5: 102.77
A6: 3 | B6: 46206 | G6: =E6*F6 -> 0 | J6: =H6*I6 -> 0 | K6: =G6+J6 -> 0 | M6: =M5+K6-L6 -> 110777.29
A7: 4 | B7: 46207 | E7: 31.6 | F7: 98.69 | G7: =E7*F7 -> 3118.604 | H7: 5 | I7: 111.98 | J7: =H7*I7 -> 559.9 | K7: =G7+J7 -> 3678.504 | M7: =M6+K7-L7 -> 114455.8
A8: 5 | B8: 46208 | E8: 199.31 | F8: 98.69 | G8: =E8*F8 -> 19669.904 | J8: =H8*I8 -> 0 | K8: =G8+J8 -> 19669.904 | M8: =M7+K8-L8 -> 134125.7
A9: 6 | B9: 46209 | E9: 50 | F9: 98.69 | G9: =E9*F9 -> 4934.5 | H9: 10 | I9: 110.74 | J9: =H9*I9 -> 1107.4 | K9: =G9+J9 -> 6041.9 | M9: =M8+K9-L9 -> 140167.6
A10: 7 | B10: 46210 | E10: 48.32 | F10: 98.69 | G10: =E10*F10 -> 4768.7008 | H10: 5 | I10: 110.74 | J10: =H10*I10 -> 553.7 | K10: =G10+J10 -> 5322.4008 | M10: =M9+K10-L10 -> 145490
A11: 8 | B11: 46211 | E11: 70 | F11: 98.69 | G11: =E11*F11 -> 6908.3 | J11: =H11*I11 -> 0 | K11: =G11+J11 -> 6908.3 | M11: =M10+K11-L11 -> 152398.3
A12: 9 | B12: 46212 | G12: =E12*F12 -> 0 | H12: 5 | I12: 110.74 | J12: =H12*I12 -> 553.7 | K12: =G12+J12 -> 553.7 | M12: =M11+K12-L12 -> 152952
A13: 10 | B13: 46213 | E13: 19.51 | F13: 98.69 | G13: =E13*F13 -> 1925.4419 | H13: 10 | I13: 110.74 | J13: =H13*I13 -> 1107.4 | K13: =G13+J13 -> 3032.8419 | M13: =M12+K13-L13 -> 155984.84
A14: 11 | B14: 46214 | G14: =E14*F14 -> 0 | J14: =H14*I14 -> 0 | K14: =G14+J14 -> 0 | M14: =M13+K14-L14 -> 155984.84
A15: 12 | B15: 46215 | G15: =E15*F15 -> 0 | J15: =H15*I15 -> 0 | K15: =G15+J15 -> 0 | M15: =M14+K15-L15 -> 155984.84
A16: 13 | B16: 46216 | G16: =E16*F16 -> 0 | J16: =H16*I16 -> 0 | K16: =G16+J16 -> 0 | M16: =M15+K16-L16 -> 155984.84
A17: 14 | B17: 46217 | E17: 30 | F17: 98.69 | G17: =E17*F17 -> 2960.7 | J17: =H17*I17 -> 0 | K17: =G17+J17 -> 2960.7 | M17: =M16+K17-L17 -> 158945.54
A18: 15 | B18: 46218 | G18: =E18*F18 -> 0 | J18: =H18*I18 -> 0 | K18: =G18+J18 -> 0 | L18: 100000 | M18: =M17+K18-L18 -> 58945.543
A19: 16 | B19: 46219 | E19: 50 | F19: 98.69 | G19: =E19*F19 -> 4934.5 | J19: =H19*I19 -> 0 | K19: =G19+J19 -> 4934.5 | M19: =M18+K19-L19 -> 63880.043
A20: 17 | B20: 46220 | E20: 5 | F20: 98.69 | G20: =E20*F20 -> 493.45 | H20: 10 | I20: 110.74 | J20: =H20*I20 -> 1107.4 | K20: =G20+J20 -> 1600.85 | M20: =M19+K20-L20 -> 65480.893
A21: 18 | B21: 46221 | G21: =E21*F21 -> 0 | J21: =H21*I21 -> 0 | K21: =G21+J21 -> 0 | M21: =M20+K21-L21 -> 65480.893
A22: 19 | B22: 46222 | G22: =E22*F22 -> 0 | J22: =H22*I22 -> 0 | K22: =G22+J22 -> 0 | M22: =M21+K22-L22 -> 65480.893
A23: 20 | B23: 46223 | E23: 44.21 | F23: 98.69 | G23: =E23*F23 -> 4363.0849 | H23: 5 | I23: 110.74 | J23: =H23*I23 -> 553.7 | K23: =G23+J23 -> 4916.7849 | M23: =M22+K23-L23 -> 70397.678 | N23: 0
A24: 21 | B24: 46224 | G24: =E24*F24 -> 0 | J24: =H24*I24 -> 0 | K24: =G24+J24 -> 0 | M24: =M23+K24-L24 -> 70397.678
A25: 22 | B25: 46225 | G25: =E25*F25 -> 0 | H25: 5 | I25: 110.74 | J25: =H25*I25 -> 553.7 | K25: =G25+J25 -> 553.7 | M25: =M24+K25-L25 -> 70951.378
A26: 23 | B26: 46226 | G26: =E26*F26 -> 0 | J26: =H26*I26 -> 0 | K26: =G26+J26 -> 0 | M26: =M25+K26-L26 -> 70951.378
A27: 24 | B27: 46227 | G27: =E27*F27 -> 0 | J27: =H27*I27 -> 0 | K27: =G27+J27 -> 0 | M27: =M26+K27-L27 -> 70951.378
A28: 25 | B28: 46228 | G28: =E28*F28 -> 0 | J28: =H28*I28 -> 0 | K28: =G28+J28 -> 0 | M28: =M27+K28-L28 -> 70951.378
A29: 26 | B29: 46229 | G29: =F29*E29 -> 0 | H29: 10 | I29: 110.74 | J29: =H29*I29 -> 1107.4 | K29: =G29+J29 -> 1107.4 | M29: =M28+K29-L29 -> 72058.778
A30: 27 | B30: 46230 | E30: 87.19 | F30: 98.69 | G30: =E30*F30 -> 8604.7811 | J30: =H30*I30 -> 0 | K30: =G30+J30 -> 8604.7811 | M30: =M29+K30-L30 -> 80663.559
A31: 28 | B31: 46231 | G31: =E31*F31 -> 0 | J31: =H31*I31 -> 0 | K31: =G31+J31 -> 0 | M31: =M30+K31-L31 -> 80663.559
A32: 29 | B32: 46232 | G32: =F32*E32 -> 0 | J32: =H32*I32 -> 0 | K32: =G32+J32 -> 0 | M32: =M31+K32-L32 -> 80663.559
A33: 30 | B33: 46233 | E33: 30 | F33: 98.69 | G33: =F33*E33 -> 2960.7 | H33: 10 | I33: 110.74 | J33: =H33*I33 -> 1107.4 | K33: =G33+J33 -> 4068.1 | M33: =M32+K33-L33 -> 84731.659
A34: 31 | B34: 46234 | G34: =F34*E34 -> 0 | J34: =H34*I34 -> 0 | K34: =G34+J34 -> 0 | M34: =M33+K34-L34 -> 84731.659
E35: =SUM(E4:E34) -> 717.32 | G35: =SUM(G4:G34) -> 70792.311 | H35: =SUM(H4:H34) -> 80 | J35: =SUM(J4:J34) -> 8871.6 | K35: =SUM(K4:K34) -> 79663.911 | L35: =SUM(L4:L34) -> 100000 | M35: =SUM(M4:M34) -> 3181134.7

Sheet Munavali-2
A1: Shiri Shiva Petroluem
A2: S.No | B2: Date | C2: GRN No | D2: Ind No/Bill No | E2: Diesel (Lts) | F2: Price | G2: Amount | H2: Petrol (Lts) | I2: Price | J2: Amount | K2: Total amount | L2: Amount paid | M2: As on date | N2: Remarks
D3: Opening Balance | K3: 0 | M3: 0
A4: 1 | B4: 46204 | G4: =E4*F4 -> 0 | J4: =H4*I4 -> 0 | K4: =G4+J4 -> 0 | M4: =M3+K4-L4 -> 0
A5: 2 | B5: 46205 | G5: =E5*F5 -> 0 | J5: =H5*I5 -> 0 | K5: =G5+J5 -> 0 | M5: =M4+K5-L5 -> 0 | N5: HPCl
A6: 3 | B6: 46206 | G6: =E6*F6 -> 0 | J6: =H6*I6 -> 0 | K6: =G6+J6 -> 0 | M6: =M5+K6-L6 -> 0
A7: 4 | B7: 46207 | G7: =E7*F7 -> 0 | J7: =H7*I7 -> 0 | K7: =G7+J7 -> 0 | M7: =M6+K7-L7 -> 0
A8: 5 | B8: 46208 | G8: =E8*F8 -> 0 | J8: =H8*I8 -> 0 | K8: =G8+J8 -> 0 | M8: =M7+K8-L8 -> 0
A9: 6 | B9: 46209 | G9: =E9*F9 -> 0 | J9: =H9*I9 -> 0 | K9: =G9+J9 -> 0 | M9: =M8+K9-L9 -> 0
A10: 7 | B10: 46210 | G10: =E10*F10 -> 0 | J10: =H10*I10 -> 0 | K10: =G10+J10 -> 0 | M10: =M9+K10-L10 -> 0
A11: 8 | B11: 46211 | G11: =E11*F11 -> 0 | J11: =H11*I11 -> 0 | K11: =G11+J11 -> 0 | M11: =M10+K11-L11 -> 0
A12: 9 | B12: 46212 | G12: =E12*F12 -> 0 | J12: =H12*I12 -> 0 | K12: =G12+J12 -> 0 | M12: =M11+K12-L12 -> 0
A13: 10 | B13: 46213 | G13: =E13*F13 -> 0 | J13: =H13*I13 -> 0 | K13: =G13+J13 -> 0 | M13: =M12+K13-L13 -> 0
A14: 11 | B14: 46214 | G14: =E14*F14 -> 0 | J14: =H14*I14 -> 0 | K14: =G14+J14 -> 0 | M14: =M13+K14-L14 -> 0
A15: 12 | B15: 46215 | G15: =E15*F15 -> 0 | J15: =H15*I15 -> 0 | K15: =G15+J15 -> 0 | M15: =M14+K15-L15 -> 0
A16: 13 | B16: 46216 | G16: =E16*F16 -> 0 | H16: 30 | I16: 111.45 | J16: =H16*I16 -> 3343.5 | K16: =G16+J16 -> 3343.5 | M16: =M15+K16-L16 -> 3343.5
A17: 14 | B17: 46217 | E17: 1000 | F17: 99.35 | G17: =E17*F17 -> 99350 | K17: =G17+J17 -> 99350 | M17: =M16+K17-L17 -> 102693.5
A18: 15 | B18: 46218 | D18: 0 | G18: =E18*F18 -> 0 | J18: =H18*I18 -> 0 | K18: =G18+J18 -> 0 | M18: =M17+K18-L18 -> 102693.5
A19: 16 | B19: 46219 | E19: 500 | F19: 99.35 | G19: =E19*F19 -> 49675 | H19: 30 | I19: 111.49 | J19: =H19*I19 -> 3344.7 | K19: =G19+J19 -> 53019.7 | M19: =M18+K19-L19 -> 155713.2
A20: 17 | B20: 46220 | G20: =E20*F20 -> 0 | J20: =H20*I20 -> 0 | K20: =G20+J20 -> 0 | M20: =M19+K20-L20 -> 155713.2
A21: 18 | B21: 46221 | E21: 500 | F21: 99.35 | G21: =E21*F21 -> 49675 | H21: 20 | I21: 111.49 | J21: =H21*I21 -> 2229.8 | K21: =G21+J21 -> 51904.8 | M21: =M20+K21-L21 -> 207618
A22: 19 | B22: 46222 | G22: =E22*F22 -> 0 | J22: =H22*I22 -> 0 | K22: =G22+J22 -> 0 | M22: =M21+K22-L22 -> 207618
A23: 20 | B23: 46223 | G23: 0 | J23: 0 | K23: 0 | M23: =M22+K23-L23 -> 207618
A24: 21 | B24: 46224 | G24: =E24*F24 -> 0 | J24: =H24*I24 -> 0 | K24: =G24+J24 -> 0 | M24: =M23+K24-L24 -> 207618
A25: 22 | B25: 46225 | G25: =E25*F25 -> 0 | J25: =H25*I25 -> 0 | K25: =G25+J25 -> 0 | L25: 200000 | M25: =M24+K25-L25 -> 7618
A26: 23 | B26: 46226 | G26: =E26*F26 -> 0 | J26: =H26*I26 -> 0 | K26: =G26+J26 -> 0 | M26: =M25+K26-L26 -> 7618
A27: 24 | B27: 46227 | E27: 800 | F27: 99.35 | G27: =E27*F27 -> 79480 | J27: =H27*I27 -> 0 | K27: =G27+J27 -> 79480 | M27: =M26+K27-L27 -> 87098
A28: 25 | B28: 46228 | G28: =E28*F28 -> 0 | J28: =H28*I28 -> 0 | K28: =G28+J28 -> 0 | M28: =M27+K28-L28 -> 87098
A29: 26 | B29: 46229 | G29: =E29*F29 -> 0 | J29: =H29*I29 -> 0 | K29: =G29+J29 -> 0 | M29: =M28+K29-L29 -> 87098
A30: 27 | B30: 46230 | G30: =E30*F30 -> 0 | J30: =H30*I30 -> 0 | K30: =G30+J30 -> 0 | M30: =M29+K30-L30 -> 87098
A31: 28 | B31: 46231 | G31: =E31*F31 -> 0 | J31: =H31*I31 -> 0 | K31: =G31+J31 -> 0 | M31: =M30+K31-L31 -> 87098
A32: 29 | B32: 46232 | G32: =E32*F32 -> 0 | J32: =H32*I32 -> 0 | K32: =G32+J32 -> 0 | M32: =M31+K32-L32 -> 87098
A33: 30 | B33: 46233 | E33: 600 | F33: 99.35 | G33: =E33*F33 -> 59610 | J33: =H33*I33 -> 0 | K33: =G33+J33 -> 59610 | M33: =M32+K33-L33 -> 146708
A34: 31 | G34: =E34*F34 -> 0 | J34: =H34*I34 -> 0 | K34: =G34+J34 -> 0 | M34: =M33+K34-L34 -> 146708
A35: 32 | G35: =E35*F35 -> 0 | J35: =H35*I35 -> 0 | K35: =G35+J35 -> 0 | M35: =M34+K35-L35 -> 146708
A36: 33 | G36: =E36*F36 -> 0 | J36: =H36*I36 -> 0 | K36: =G36+J36 -> 0 | M36: =M35+K36-L36 -> 146708
A37: 34 | G37: =E37*F37 -> 0 | J37: =H37*I37 -> 0 | K37: =G37+J37 -> 0 | M37: =M36+K37-L37 -> 146708
A38: 35 | G38: =E38*F38 -> 0 | J38: =H38*I38 -> 0 | K38: =G38+J38 -> 0 | M38: =M37+K38-L38 -> 146708
A39: 36 | G39: =E39*F39 -> 0 | J39: =H39*I39 -> 0 | K39: =G39+J39 -> 0 | M39: =M38+K39-L39 -> 146708
E40: =SUM(E4:E39) -> 3400 | G40: =SUM(G4:G39) -> 337790 | H40: =SUM(H4:H39) -> 80 | J40: =SUM(J4:J39) -> 8918 | K40: =SUM(K4:K39) -> 346708 | L40: =SUM(L4:L39) -> 200000

Sheet  Munavali
A1: DANESHWARI PETROLIUM(YERRAGATTI)
A2: S.No | B2: Date | C2: GRN No | D2: Ind No/Bill No | E2: Diesel (Lts) | F2: Price | G2: Amount | H2: Petrol (Lts) | I2: Price | J2: Amount | K2: Total amount | L2: Amount paid | M2: As on date | N2: Remarks
D3: Opening Balance | K3: 478435.42 | M3: 478435.42
A4: 1 | B4: 46204 | E4: 500 | F4: 99.13 | G4: =E4*F4 -> 49565 | J4: =H4*I4 -> 0 | K4: =G4+J4 -> 49565 | M4: =M3+K4-L4 -> 528000.42
A5: 2 | B5: 46205 | E5: 600 | F5: 99.13 | G5: =E5*F5 -> 59478 | H5: 20 | I5: 111.21 | J5: =H5*I5 -> 2224.2 | K5: =G5+J5 -> 61702.2 | M5: =M4+K5-L5 -> 589702.62 | N5: HPCl
A6: 3 | B6: 46206 | E6: 400 | F6: 99.13 | G6: =E6*F6 -> 39652 | H6: 20 | I6: 111.21 | J6: =H6*I6 -> 2224.2 | K6: =G6+J6 -> 41876.2 | M6: =M5+K6-L6 -> 631578.82
A7: 4 | B7: 46207 | E7: 400 | F7: 99.13 | G7: =E7*F7 -> 39652 | J7: =H7*I7 -> 0 | K7: =G7+J7 -> 39652 | M7: =M6+K7-L7 -> 671230.82
A8: 5 | B8: 46208 | E8: 200 | F8: 99.13 | G8: =E8*F8 -> 19826 | J8: =H8*I8 -> 0 | K8: =G8+J8 -> 19826 | M8: =M7+K8-L8 -> 691056.82
A9: 6 | B9: 46209 | E9: 400 | F9: 99.13 | G9: =E9*F9 -> 39652 | H9: 20 | I9: 111.21 | J9: =H9*I9 -> 2224.2 | K9: =G9+J9 -> 41876.2 | M9: =M8+K9-L9 -> 732933.02
A10: 7 | B10: 46210 | E10: 200 | F10: 99.13 | G10: =E10*F10 -> 19826 | J10: =H10*I10 -> 0 | K10: =G10+J10 -> 19826 | M10: =M9+K10-L10 -> 752759.02
A11: 8 | B11: 46211 | E11: 400 | F11: 99.13 | G11: =E11*F11 -> 39652 | J11: =H11*I11 -> 0 | K11: =G11+J11 -> 39652 | M11: =M10+K11-L11 -> 792411.02
A12: 9 | B12: 46212 | E12: 600 | F12: 99.13 | G12: =E12*F12 -> 59478 | J12: =H12*I12 -> 0 | K12: =G12+J12 -> 59478 | M12: =M11+K12-L12 -> 851889.02
A13: 10 | B13: 46213 | E13: 400 | F13: 99.13 | G13: =E13*F13 -> 39652 | H13: 20 | I13: 111.21 | J13: =H13*I13 -> 2224.2 | K13: =G13+J13 -> 41876.2 | M13: =M12+K13-L13 -> 893765.22
A14: 11 | B14: 46214 | E14: 200 | F14: 99.13 | G14: =E14*F14 -> 19826 | J14: =H14*I14 -> 0 | K14: =G14+J14 -> 19826 | M14: =M13+K14-L14 -> 913591.22
A15: 12 | B15: 46215 | G15: =E15*F15 -> 0 | J15: =H15*I15 -> 0 | K15: =G15+J15 -> 0 | M15: =M14+K15-L15 -> 913591.22
A16: 13 | B16: 46216 | G16: =E16*F16 -> 0 | J16: =H16*I16 -> 0 | K16: =G16+J16 -> 0 | M16: =M15+K16-L16 -> 913591.22
A17: 14 | B17: 46217 | G17: =E17*F17 -> 0 | J17: =H17*I17 -> 0 | K17: =G17+J17 -> 0 | M17: =M16+K17-L17 -> 913591.22
A18: 15 | B18: 46218 | D18: 0 | G18: =E18*F18 -> 0 | J18: =H18*I18 -> 0 | K18: =G18+J18 -> 0 | L18: 200000 | M18: =M17+K18-L18 -> 713591.22
A19: 16 | B19: 46219 | G19: =E19*F19 -> 0 | J19: =H19*I19 -> 0 | K19: =G19+J19 -> 0 | M19: =M18+K19-L19 -> 713591.22
A20: 17 | B20: 46220 | G20: =E20*F20 -> 0 | J20: =H20*I20 -> 0 | K20: =G20+J20 -> 0 | M20: =M19+K20-L20 -> 713591.22
A21: 18 | B21: 46221 | G21: =E21*F21 -> 0 | J21: =H21*I21 -> 0 | K21: =G21+J21 -> 0 | M21: =M20+K21-L21 -> 713591.22
A22: 19 | B22: 46222 | G22: =E22*F22 -> 0 | J22: =H22*I22 -> 0 | K22: =G22+J22 -> 0 | M22: =M21+K22-L22 -> 713591.22
A23: 20 | B23: 46223 | G23: =E23*F23 -> 0 | J23: =H23*I23 -> 0 | K23: =G23+J23 -> 0 | L23: 300000 | M23: =M22+K23-L23 -> 413591.22
A24: 22 | B24: 46224 | E24: 500 | F24: 99.13 | G24: =E24*F24 -> 49565 | H24: 30 | I24: 111.21 | J24: =H24*I24 -> 3336.3 | K24: =G24+J24 -> 52901.3 | M24: =M23+K24-L24 -> 466492.52
A25: 23 | B25: 46225 | G25: =E25*F25 -> 0 | J25: =H25*I25 -> 0 | K25: =G25+J25 -> 0 | M25: =M24+K25-L25 -> 466492.52
A26: 24 | B26: 46226 | G26: =E26*F26 -> 0 | J26: =H26*I26 -> 0 | K26: =G26+J26 -> 0 | M26: =M25+K26-L26 -> 466492.52
A27: 25 | B27: 46227 | G27: =E27*F27 -> 0 | H27: 30 | I27: 111.21 | J27: =H27*I27 -> 3336.3 | K27: =G27+J27 -> 3336.3 | M27: =M26+K27-L27 -> 469828.82
A28: 26 | B28: 46228 | G28: =E28*F28 -> 0 | J28: =H28*I28 -> 0 | K28: =G28+J28 -> 0 | M28: =M27+K28-L28 -> 469828.82
A29: 27 | B29: 46229 | G29: =E29*F29 -> 0 | J29: =H29*I29 -> 0 | K29: =G29+J29 -> 0 | M29: =M28+K29-L29 -> 469828.82
A30: 28 | B30: 46230 | G30: =E30*F30 -> 0 | J30: =H30*I30 -> 0 | K30: =G30+J30 -> 0 | M30: =M29+K30-L30 -> 469828.82
A31: 29 | B31: 46231 | G31: =E31*F31 -> 0 | J31: =H31*I31 -> 0 | K31: =G31+J31 -> 0 | M31: =M30+K31-L31 -> 469828.82 | Q31: 166834
A32: 30 | B32: 46232 | G32: =E32*F32 -> 0 | J32: =H32*I32 -> 0 | K32: =G32+J32 -> 0 | M32: =M31+K32-L32 -> 469828.82
A33: 31 | B33: 46233 | G33: =E33*F33 -> 0 | J33: =H33*I33 -> 0 | K33: =G33+J33 -> 0 | M33: =M32+K33-L33 -> 469828.82
A34: 32 | B34: 46234 | G34: =E34*F34 -> 0 | H34: 40 | I34: 111.21 | J34: =H34*I34 -> 4448.4 | K34: =G34+J34 -> 4448.4 | L34: 200000 | M34: =M33+K34-L34 -> 274277.22
A35: 33 | G35: =E35*F35 -> 0 | J35: =H35*I35 -> 0 | K35: =G35+J35 -> 0 | M35: =M34+K35-L35 -> 274277.22
A36: 34 | G36: =E36*F36 -> 0 | J36: =H36*I36 -> 0 | K36: =G36+J36 -> 0 | M36: =M35+K36-L36 -> 274277.22
A37: 35 | G37: =E37*F37 -> 0 | J37: =H37*I37 -> 0 | K37: =G37+J37 -> 0 | M37: =M36+K37-L37 -> 274277.22
A38: 36 | G38: =E38*F38 -> 0 | J38: =H38*I38 -> 0 | K38: =G38+J38 -> 0 | M38: =M37+K38-L38 -> 274277.22
E39: =SUM(E4:E38) -> 4800 | G39: =SUM(G4:G38) -> 475824 | H39: =SUM(H4:H38) -> 180 | J39: =SUM(J4:J38) -> 20017.8 | K39: =SUM(K4:K38) -> 495841.8 | L39: =SUM(L4:L38) -> 700000

Sheet Borgaon
A1: Aadisagar Petrolium
A2: S.No | B2: Date | C2: GRN No | D2: Ind no/Bill No | E2: Diesel (Lts) | F2: Price | G2: Amount | H2: Petrol (Lts) | I2: Price | J2: Amount | K2: Total amount | L2: Amount paid | M2: As on Date | N2: Remarks
A3: Opening Balance | K3: 208.3907 | M3: 208.3907
A4: 1 | B4: 46204 | G4: =E4*F4 -> 0 | J4: =H4*I4 -> 0 | K4: =G4+J4 -> 0 | M4: =M3+K4-L4 -> 208.3907
A5: 2 | B5: 46205 | G5: =E5*F5 -> 0 | J5: =H5*I5 -> 0 | K5: =G5+J5 -> 0 | M5: =M4+K5-L5 -> 208.3907
A6: 3 | B6: 46206 | G6: =E6*F6 -> 0 | J6: =H6*I6 -> 0 | K6: =G6+J6 -> 0 | M6: =M5+K6-L6 -> 208.3907
A7: 4 | B7: 46207 | G7: =E7*F7 -> 0 | J7: =H7*I7 -> 0 | K7: =G7+J7 -> 0 | M7: =M6+K7-L7 -> 208.3907
A8: 5 | B8: 46208 | G8: =E8*F8 -> 0 | J8: =H8*I8 -> 0 | K8: =G8+J8 -> 0 | M8: =M7+K8-L8 -> 208.3907
A9: 6 | B9: 46209 | G9: =E9*F9 -> 0 | J9: =H9*I9 -> 0 | K9: =G9+J9 -> 0 | M9: =M8+K9-L9 -> 208.3907
A10: 7 | B10: 46210 | G10: =E10*F10 -> 0 | J10: =H10*I10 -> 0 | K10: =G10+J10 -> 0 | M10: =M9+K10-L10 -> 208.3907
A11: 8 | B11: 46211 | G11: =E11*F11 -> 0 | J11: =H11*I11 -> 0 | K11: =G11+J11 -> 0 | M11: =M10+K11-L11 -> 208.3907
A12: 9 | B12: 46212 | G12: =E12*F12 -> 0 | J12: =H12*I12 -> 0 | K12: =G12+J12 -> 0 | M12: =M11+K12-L12 -> 208.3907
A13: 10 | B13: 46213 | G13: =E13*F13 -> 0 | J13: =H13*I13 -> 0 | K13: =G13+J13 -> 0 | M13: =M12+K13-L13 -> 208.3907
A14: 11 | B14: 46214 | G14: =E14*F14 -> 0 | J14: =H14*I14 -> 0 | K14: =G14+J14 -> 0 | M14: =M13+K14-L14 -> 208.3907
A15: 12 | B15: 46215 | G15: =E15*F15 -> 0 | J15: =H15*I15 -> 0 | K15: =G15+J15 -> 0 | M15: =M14+K15-L15 -> 208.3907
... A25: 22 | B25: 46225 | G25: =E25*F25 -> 0 | J25: =H25*I25 -> 0 | K25: =G25+J25 -> 0 | M25: =M24+K25-L25 -> 208.3907
A26: 23 | B26: 46226 | G26: =E26*F26 -> 0 | J26: =H26*I26 -> 0 | K26: =G26+J26 -> 0 | M26: =M25+K26-L26 -> 208.3907 | Q26: d
A27: 24 | B27: 46227 | G27: =E27*F27 -> 0 | J27: =H27*I27 -> 0 | K27: =G27+J27 -> 0 | M27: =M26+K27-L27 -> 208.3907 | Q27: 30 | R27: 50
A28: 25 | B28: 46228 | G28: =E28*F28 -> 0 | J28: =H28*I28 -> 0 | K28: =G28+J28 -> 0 | M28: =M27+K28-L28 -> 208.3907 | Q28: 50 | R28: 4.51
A29: 26 | B29: 46229 | G29: =E29*F29 -> 0 | J29: =H29*I29 -> 0 | K29: =G29+J29 -> 0 | M29: =M28+K29-L29 -> 208.3907
A30: 27 | B30: 46230 | G30: =E30*F30 -> 0 | J30: =H30*I30 -> 0 | K30: =G30+J30 -> 0 | M30: =M29+K30-L30 -> 208.3907
A31: 28 | B31: 46231 | G31: =E31*F31 -> 0 | J31: =H31*I31 -> 0 | K31: =G31+J31 -> 0 | M31: =M30+K31-L31 -> 208.3907
A32: 29 | B32: 46232 | G32: =E32*F32 -> 0 | J32: =H32*I32 -> 0 | K32: =G32+J32 -> 0 | M32: =M31+K32-L32 -> 208.3907
A33: 30 | B33: 46233 | G33: =E33*F33 -> 0 | J33: =H33*I33 -> 0 | K33: =G33+J33 -> 0 | M33: =M32+K33-L33 -> 208.3907
A34: 31 | G34: =E34*F34 -> 0 | J34: =H34*I34 -> 0 | K34: =G34+J34 -> 0 | M34: =M33+K34-L34 -> 208.3907
E35: =SUM(E4:E34) -> 0 | G35: =SUM(G4:G34) -> 0 | H35: =SUM(H4:H34) -> 0 | J35: =SUM(J4:J34) -> 0 | K35: =SUM(K4:K34) -> 0 | L35: =SUM(L4:L34) -> 0

Sheet Ugar,Khagwad,Kudichi
A1: Shiri Bhrhmanath Petrolium
A2: S.No | B2: Date | C2: GRN No | D2: Ind No/Bill No | E2: Diesel (Lts) | F2: Price | G2: Amount | H2: Petrol (Lts) | I2: Price | J2: Amount | K2: Total amount | L2: Amount paid | M2: As on Date | N2: Remarks
A3: Opening Balance | K3: 529659.87 | L3: 0 | M3: 529659.87
A4: 1 | B4: 46204 | G4: =E4*F4 -> 0 | J4: =H4*I4 -> 0 | K4: =G4+J4 -> 0 | L4: 0 | M4: =M3+K4-L4 -> 529659.87
A5: 2 | B5: 46205 | E5: 720 | F5: 99.74 | G5: =E5*F5 -> 71812.8 | J5: =H5*I5 -> 0 | K5: =G5+J5 -> 71812.8 | L5: 0 | M5: =M4+K5-L5 -> 601472.67
A6: 3 | B6: 46206 | E6: 130 | F6: 99.74 | G6: =E6*F6 -> 12966.2 | J6: =H6*I6 -> 0 | K6: =G6+J6 -> 12966.2 | M6: =M5+K6-L6 -> 614438.87
A7: 4 | B7: 46207 | E7: 55 | F7: 99.74 | G7: =E7*F7 -> 5485.7 | J7: =H7*I7 -> 0 | K7: =G7+J7 -> 5485.7 | M7: =M6+K7-L7 -> 619924.57
A8: 5 | B8: 46208 | E8: 180 | F8: 99.74 | G8: =E8*F8 -> 17953.2 | J8: =H8*I8 -> 0 | K8: =G8+J8 -> 17953.2 | M8: =M7+K8-L8 -> 637877.77
A9: 6 | B9: 46209 | E9: 420 | F9: 99.74 | G9: =E9*F9 -> 41890.8 | J9: =H9*I9 -> 0 | K9: =G9+J9 -> 41890.8 | M9: =M8+K9-L9 -> 679768.57
A10: 7 | B10: 46210 | E10: 35 | F10: 99.74 | G10: =E10*F10 -> 3490.9 | J10: =H10*I10 -> 0 | K10: =G10+J10 -> 3490.9 | L10: 530000 | M10: =M9+K10-L10 -> 153259.47
A11: 8 | B11: 46211 | E11: 153.01 | F11: 99.74 | G11: =E11*F11 -> 15261.217 | J11: =H11*I11 -> 0 | K11: =G11+J11 -> 15261.217 | M11: =M10+K11-L11 -> 168520.69
A12: 9 | B12: 46212 | E12: 521 | F12: 99.74 | G12: =E12*F12 -> 51964.54 | J12: =H12*I12 -> 0 | K12: =G12+J12 -> 51964.54 | M12: =M11+K12-L12 -> 220485.23
A13: 10 | B13: 46213 | E13: 40 | F13: 99.74 | G13: =E13*F13 -> 3989.6 | J13: =H13*I13 -> 0 | K13: =G13+J13 -> 3989.6 | M13: =M12+K13-L13 -> 224474.83
A14: 11 | B14: 46214 | E14: 118.88 | F14: 99.74 | G14: =E14*F14 -> 11857.091 | J14: =H14*I14 -> 0 | K14: =G14+J14 -> 11857.091 | M14: =M13+K14-L14 -> 236331.92
A15: 12 | B15: 46215 | E15: 525 | F15: 99.74 | G15: =E15*F15 -> 52363.5 | H15: 35 | I15: 111.85 | J15: =H15*I15 -> 3914.75 | K15: =G15+J15 -> 56278.25 | M15: =M14+K15-L15 -> 292610.17
A16: 13 | B16: 46216 | E16: 80 | F16: 99.74 | G16: =E16*F16 -> 7979.2 | J16: =H16*I16 -> 0 | K16: =G16+J16 -> 7979.2 | M16: =M15+K16-L16 -> 300589.37
A17: 14 | B17: 46217 | E17: 50 | F17: 99.74 | G17: =E17*F17 -> 4987 | J17: =H17*I17 -> 0 | K17: =G17+J17 -> 4987 | M17: =M16+K17-L17 -> 305576.37
A18: 15 | B18: 46218 | E18: 636.23 | F18: 99.74 | G18: =E18*F18 -> 63457.58 | H18: 6 | I18: 111.85 | J18: =H18*I18 -> 671.1 | K18: =G18+J18 -> 64128.68 | M18: =M17+K18-L18 -> 369705.05
A19: 16 | B19: 46219 | E19: 570 | F19: 99.74 | G19: =E19*F19 -> 56851.8 | H19: 35 | I19: 111.85 | J19: =H19*I19 -> 3914.75 | K19: =G19+J19 -> 60766.55 | M19: =M18+K19-L19 -> 430471.6
A20: 17 | B20: 46220 | E20: 364.19 | F20: 99.74 | G20: =E20*F20 -> 36324.311 | J20: =H20*I20 -> 0 | K20: =G20+J20 -> 36324.311 | M20: =M19+K20-L20 -> 466795.91
B21: 46221 | E21: 400 | F21: 99.74 | G21: =E21*F21 -> 39896 | J21: =H21*I21 -> 0 | K21: =G21+J21 -> 39896 | M21: =M20+K21-L21 -> 506691.91
A22: 18 | B22: 46222 | G22: =E22*F22 -> 0 | J22: =H22*I22 -> 0 | K22: =G22+J22 -> 0 | M22: =M21+K22-L22 -> 506691.91 | N22: BT
A23: 19 | B23: 46223 | E23: 35 | F23: 99.74 | G23: =E23*F23 -> 3490.9 | J23: =H23*I23 -> 0 | K23: =G23+J23 -> 3490.9 | M23: =M22+K23-L23 -> 510182.81
A24: 20 | B24: 46224 | E24: 50 | F24: 99.74 | G24: =E24*F24 -> 4987 | J24: =H24*I24 -> 0 | K24: =G24+J24 -> 4987 | L24: 0 | M24: =M23+K24-L24 -> 515169.81
A25: 21 | B25: 46225 | E25: 570.51 | F25: 99.74 | G25: =E25*F25 -> 56902.667 | J25: =H25*I25 -> 0 | K25: =G25+J25 -> 56902.667 | L25: 0 | M25: =M24+K25-L25 -> 572072.48
A26: 22 | B26: 46226 | E26: 200 | F26: 99.74 | G26: =E26*F26 -> 19948 | J26: =H26*I26 -> 0 | K26: =G26+J26 -> 19948 | L26: 0 | M26: =M25+K26-L26 -> 592020.48
B27: 46227 | G27: =E27*F27 -> 0 | J27: =H27*I27 -> 0 | K27: =G27+J27 -> 0 | L27: 0 | M27: =M26+K27-L27 -> 592020.48
A28: 23 | B28: 46228 | G28: =E28*F28 -> 0 | J28: =H28*I28 -> 0 | K28: =G28+J28 -> 0 | L28: 0 | M28: =M27+K28-L28 -> 592020.48
A29: 24 | B29: 46229 | G29: =E29*F29 -> 0 | J29: =H29*I29 -> 0 | K29: =G29+J29 -> 0 | L29: 0 | M29: =M28+K29-L29 -> 592020.48
A30: 25 | B30: 46230 | G30: =E30*F30 -> 0 | J30: =H30*I30 -> 0 | K30: =G30+J30 -> 0 | L30: 0 | M30: =M29+K30-L30 -> 592020.48
A31: 26 | B31: 46231 | G31: =E31*F31 -> 0 | J31: =H31*I31 -> 0 | K31: =G31+J31 -> 0 | L31: 0 | M31: =M30+K31-L31 -> 592020.48
A32: 27 | B32: 46232 | G32: =E32*F32 -> 0 | J32: =H32*I32 -> 0 | K32: =G32+J32 -> 0 | L32: 0 | M32: =M31+K32-L32 -> 592020.48 | P32: =600*99.73 -> 59838
A33: 28 | B33: 46233 | G33: =E33*F33 -> 0 | J33: =H33*I33 -> 0 | K33: =G33+J33 -> 0 | L33: 0 | M33: =M32+K33-L33 -> 592020.48
A34: 29 | B34: 46234 | G34: =E34*F34 -> 0 | J34: =H34*I34 -> 0 | K34: =G34+J34 -> 0 | L34: 250000 | M34: =M33+K34-L34 -> 342020.48
A35: 30 | G35: =E35*F35 -> 0 | J35: =H35*I35 -> 0 | K35: =G35+J35 -> 0 | L35: 0 | M35: =M34+K35-L35 -> 342020.48
A36: 31 | G36: =E36*F36 -> 0 | J36: =H36*I36 -> 0 | K36: =G36+J36 -> 0 | L36: 0 | M36: =M35+K36-L36 -> 342020.48
E37: =SUM(E4:E36) -> 5853.82 | G37: =SUM(G4:G36) -> 583860.01 | H37: =SUM(H4:H36) -> 76 | J37: =SUM(J4:J36) -> 8500.6 | K37: =SUM(K4:K36) -> 592360.61 | L37: =SUM(L4:L36) -> 780000

Sheet shedbal
A1: VARAD PETROLEUM SHEDBAL
A2: S.No | B2: Date | C2: GRN No | D2: Ind no/Bill No | E2: Diesel (Lts) | F2: Price | G2: Amount | H2: Petrol (Lts) | I2: Price | J2: Amount | K2: Total amount | L2: Amount paid | M2: As on Date | N2: Remarks
A3: Opening Balance | K3: 296953 | M3: 296953
A4: 1 | B4: 46204 | G4: =E4*F4 -> 0 | J4: =H4*I4 -> 0 | K4: =G4+J4 -> 0 | M4: =M3+K4-L4 -> 296953
A5: 2 | B5: 46205 | E5: 470 | F5: 99.73 | G5: =E5*F5 -> 46873.1 | J5: =H5*I5 -> 0 | K5: =G5+J5 -> 46873.1 | M5: =M4+K5-L5 -> 343826.1
A6: 3 | B6: 46206 | E6: 20 | F6: 99.73 | G6: =E6*F6 -> 1994.6 | J6: =H6*I6 -> 0 | K6: =G6+J6 -> 1994.6 | M6: =M5+K6-L6 -> 345820.7
A7: 4 | B7: 46207 | E7: 430 | F7: 99.73 | G7: =E7*F7 -> 42883.9 | H7: 40 | I7: 111.85 | J7: =H7*I7 -> 4474 | K7: =G7+J7 -> 47357.9 | M7: =M6+K7-L7 -> 393178.6
A8: 5 | B8: 46208 | G8: =E8*F8 -> 0 | J8: =H8*I8 -> 0 | K8: =G8+J8 -> 0 | M8: =M7+K8-L8 -> 393178.6
A9: 6 | B9: 46209 | E9: 40 | F9: 99.73 | G9: =E9*F9 -> 3989.2 | J9: =H9*I9 -> 0 | K9: =G9+J9 -> 3989.2 | M9: =M8+K9-L9 -> 397167.8
A10: 7 | B10: 46210 | E10: 500 | F10: 99.73 | G10: =E10*F10 -> 49865 | H10: 23 | I10: 111.85 | J10: =H10*I10 -> 2572.55 | K10: =G10+J10 -> 52437.55 | M10: =M9+K10-L10 -> 449605.35
A11: 8 | B11: 46211 | G11: =E11*F11 -> 0 | J11: =H11*I11 -> 0 | K11: =G11+J11 -> 0 | M11: =M10+K11-L11 -> 449605.35
A12: 9 | B12: 46212 | E12: 305 | F12: 99.73 | G12: =E12*F12 -> 30417.65 | H12: 30 | I12: 111.85 | J12: =H12*I12 -> 3355.5 | K12: =G12+J12 -> 33773.15 | M12: =M11+K12-L12 -> 483378.5
A13: 10 | B13: 46213 | E13: 100 | F13: 99.73 | G13: =E13*F13 -> 9973 | H13: 5 | I13: 111.85 | J13: =H13*I13 -> 559.25 | K13: =G13+J13 -> 10532.25 | M13: =M12+K13-L13 -> 493910.75
A14: 11 | B14: 46214 | E14: 445 | F14: 99.73 | G14: =E14*F14 -> 44379.85 | J14: =H14*I14 -> 0 | K14: =G14+J14 -> 44379.85 | M14: =M13+K14-L14 -> 538290.6
A15: 12 | B15: 46215 | E15: 100 | F15: 99.73 | G15: =E15*F15 -> 9973 | H15: 23 | I15: 111.85 | J15: =H15*I15 -> 2572.55 | K15: =G15+J15 -> 12545.55 | M15: =M14+K15-L15 -> 550836.15
A16: 13 | B16: 46216 | E16: 35 | F16: 99.73 | G16: =E16*F16 -> 3490.55 | J16: =H16*I16 -> 0 | K16: =G16+J16 -> 3490.55 | M16: =M15+K16-L16 -> 554326.7
A17: 14 | B17: 46217 | E17: 40 | F17: 99.73 | G17: =E17*F17 -> 3989.2 | J17: =H17*I17 -> 0 | K17: =G17+J17 -> 3989.2 | M17: =M16+K17-L17 -> 558315.9
A18: 15 | B18: 46218 | E18: 100 | F18: 99.73 | G18: =E18*F18 -> 9973 | H18: 17 | I18: 111.85 | J18: =H18*I18 -> 1901.45 | K18: =G18+J18 -> 11874.45 | M18: =M17+K18-L18 -> 570190.35
A19: 16 | B19: 46219 | G19: =E19*F19 -> 0 | H19: 6 | I19: 111.85 | J19: =H19*I19 -> 671.1 | K19: =G19+J19 -> 671.1 | M19: =M18+K19-L19 -> 570861.45
A20: 17 | B20: 46220 | E20: 85 | F20: 99.73 | G20: =E20*F20 -> 8477.05 | J20: =H20*I20 -> 0 | K20: =G20+J20 -> 8477.05 | M20: =M19+K20-L20 -> 579338.5
B21: 46220 | E21: 69.98 | F21: 100.03 | G21: =E21*F21 -> 7000.0994 | K21: =G21+J21 -> 7000.0994 | L21: =H21+K21 -> 7000.0994 | M21: =M20+K21-L21 -> 579338.5 | N21: ADHNC NAVATEJ FC HP OTP
B22: 46220 | E22: 29.98 | F22: 100.07 | G22: =E22*F22 -> 3000.0986 | K22: =G22+J22 -> 3000.0986 | L22: =H22+K22 -> 3000.0986 | M22: =M21+K22-L22 -> 579338.5 | N22: VEERA BHADRESHWARA BP CASH
A23: 18 | B23: 46221 | E23: 400 | F23: 99.73 | G23: =E23*F23 -> 39892 | H23: 20 | I23: 111.85 | J23: =H23*I23 -> 2237 | K23: =G23+J23 -> 42129 | M23: =M22+K23-L23 -> 621467.5
A24: 19 | B24: 46222 | G24: =E24*F24 -> 0 | H24: 35 | I24: 111.85 | J24: =H24*I24 -> 3914.75 | K24: =G24+J24 -> 3914.75 | M24: =M23+K24-L24 -> 625382.25
A25: 20 | B25: 46223 | G25: =E25*F25 -> 0 | J25: =H25*I25 -> 0 | K25: =G25+J25 -> 0 | M25: =M24+K25-L25 -> 625382.25
A26: 21 | B26: 46224 | E26: 195 | F26: 99.73 | G26: =E26*F26 -> 19447.35 | H26: 35 | I26: 111.85 | J26: =H26*I26 -> 3914.75 | K26: =G26+J26 -> 23362.1 | M26: =M25+K26-L26 -> 648744.35
A27: 22 | B27: 46225 | E27: 35 | F27: 99.73 | G27: =E27*F27 -> 3490.55 | J27: =H27*I27 -> 0 | K27: =G27+J27 -> 3490.55 | L27: 400000 | M27: =M26+K27-L27 -> 252234.9
A28: 23 | B28: 46226 | E28: 235 | F28: 99.73 | G28: =E28*F28 -> 23436.55 | J28: =H28*I28 -> 0 | K28: =G28+J28 -> 23436.55 | M28: =M27+K28-L28 -> 275671.45 | Q28: d
A29: 24 | B29: 46227 | G29: =E29*F29 -> 0 | J29: =H29*I29 -> 0 | K29: =G29+J29 -> 0 | M29: =M28+K29-L29 -> 275671.45 | Q29: 30 | R29: 50
A30: 25 | B30: 46228 | E30: 70 | F30: 99.73 | G30: =E30*F30 -> 6981.1 | H30: 17 | I30: 111.85 | J30: =H30*I30 -> 1901.45 | K30: =G30+J30 -> 8882.55 | M30: =M29+K30-L30 -> 284554 | Q30: 50 | R30: 4.51
A31: 26 | B31: 46229 | E31: 400 | F31: 99.73 | G31: =E31*F31 -> 39892 | H31: 35 | I31: 111.85 | J31: =H31*I31 -> 3914.75 | K31: =G31+J31 -> 43806.75 | M31: =M30+K31-L31 -> 328360.75
A32: 27 | B32: 46230 | E32: 620 | F32: 99.73 | G32: =E32*F32 -> 61832.6 | H32: 46 | I32: 111.85 | J32: =H32*I32 -> 5145.1 | K32: =G32+J32 -> 66977.7 | M32: =M31+K32-L32 -> 395338.45
A33: 28 | B33: 46231 | E33: 270 | F33: 99.73 | G33: =E33*F33 -> 26927.1 | J33: =H33*I33 -> 0 | K33: =G33+J33 -> 26927.1 | M33: =M32+K33-L33 -> 422265.55
A34: 29 | B34: 46232 | E34: 390 | F34: 99.73 | G34: =E34*F34 -> 38894.7 | H34: 20 | I34: 111.85 | J34: =H34*I34 -> 2237 | K34: =G34+J34 -> 41131.7 | M34: =M33+K34-L34 -> 463397.25
A35: 30 | B35: 46233 | E35: 30 | F35: 99.73 | G35: =E35*F35 -> 2991.9 | J35: =H35*I35 -> 0 | K35: =G35+J35 -> 2991.9 | M35: =M34+K35-L35 -> 466389.15
A36: 31 | B36: 46234 | E36: 400 | F36: 99.73 | G36: =E36*F36 -> 39892 | J36: =H36*I36 -> 0 | K36: =G36+J36 -> 39892 | M36: =M35+K36-L36 -> 506281.15
E37: =SUM(E4:E36) -> 5814.96 | G37: =SUM(G4:G36) -> 579957.15 | H37: =SUM(H4:H36) -> 352 | J37: =SUM(J4:J36) -> 39371.2 | K37: =SUM(K4:K36) -> 619328.35 | L37: =SUM(L4:L36) -> 410000.2

Sheet Kabbur
A1: Shri Jai Hanuman Petrolium
A2: S.No | B2: Date | C2: GRN No | D2: Ind no/Bill No | E2: Diesel (Lts) | F2: Price | G2: Amount | H2: Petrol (Lts) | I2: Price | J2: Amount | K2: Total amount | L2: Amount paid | M2: As on Date | N2: Remarks
A3: Opening Balance | K3: 0 | M3: =+K3 -> 0
A4: 1 | B4: 46204 | G4: =E4*F4 -> 0 | J4: =H4*I4 -> 0 | K4: =G4+J4 -> 0 | L4: =+K4 -> 0
A5: 2 | B5: 46205 | G5: =E5*F5 -> 0 | J5: =H5*I5 -> 0 | K5: =G5+J5 -> 0 | L5: =+K5 -> 0
A6: 3 | B6: 46206 | G6: =E6*F6 -> 0 | J6: =H6*I6 -> 0 | K6: =G6+J6 -> 0 | L6: =+K6 -> 0
A7: 4 | B7: 46207 | G7: =E7*F7 -> 0 | J7: =H7*I7 -> 0 | K7: =G7+J7 -> 0 | L7: =+K7 -> 0
A8: 5 | B8: 46208 | G8: =E8*F8 -> 0 | J8: =H8*I8 -> 0 | K8: =G8+J8 -> 0 | L8: =+K8 -> 0
A9: 6 | B9: 46209 | G9: =E9*F9 -> 0 | J9: =H9*I9 -> 0 | K9: =G9+J9 -> 0 | L9: =+K9 -> 0
A10: 7 | B10: 46210 | G10: =E10*F10 -> 0 | J10: =H10*I10 -> 0 | K10: =G10+J10 -> 0 | L10: =+K10 -> 0
A11: 8 | B11: 46211 | G11: =E11*F11 -> 0 | J11: =H11*I11 -> 0 | K11: =G11+J11 -> 0 | L11: =+K11 -> 0
A12: 9 | B12: 46212 | G12: =E12*F12 -> 0 | J12: =H12*I12 -> 0 | K12: =G12+J12 -> 0 | L12: =+K12 -> 0
A13: 10 | B13: 46213 | G13: =E13*F13 -> 0 | J13: =H13*I13 -> 0 | K13: =G13+J13 -> 0 | L13: =+K13 -> 0
A14: 11 | B14: 46214 | G14: =E14*F14 -> 0 | J14: =H14*I14 -> 0 | K14: =G14+J14 -> 0 | L14: =+K14 -> 0
A15: 12 | B15: 46215 | G15: =E15*F15 -> 0 | J15: =H15*I15 -> 0 | K15: =G15+J15 -> 0 | L15: =+K15 -> 0
... A17: 14 | B17: 46217 | G17: =E17*F17 -> 0 | J17: =H17*I17 -> 0 | K17: =G17+J17 -> 0 | L17: =+K17 -> 0
A18: 15 | B18: 46218 | E18: 80.48 | F18: 99.41 | G18: =E18*F18 -> 8000.5168 | J18: =H18*I18 -> 0 | K18: =G18+J18 -> 8000.5168 | L18: =+K18 -> 8000.5168
A19: 16 | B19: 46219 | E19: 60 | F19: 99.41 | G19: =E19*F19 -> 5964.6 | J19: =H19*I19 -> 0 | K19: =G19+J19 -> 5964.6 | L19: =+K19 -> 5964.6
A20: 17 | B20: 46220 | G20: =E20*F20 -> 0 | J20: =H20*I20 -> 0 | K20: =G20+J20 -> 0 | L20: =+K20 -> 0
A21: 18 | B21: 46221 | G21: =E21*F21 -> 0 | J21: =H21*I21 -> 0 | K21: =G21+J21 -> 0 | L21: =+K21 -> 0
A22: 19 | B22: 46222 | G22: =E22*F22 -> 0 | J22: =H22*I22 -> 0 | K22: =G22+J22 -> 0 | L22: =+K22 -> 0
A23: 20 | B23: 46223 | G23: =E23*F23 -> 0 | J23: =H23*I23 -> 0 | K23: =G23+J23 -> 0 | L23: =+K23 -> 0
A24: 21 | B24: 46224 | G24: =E24*F24 -> 0 | J24: =H24*I24 -> 0 | K24: =G24+J24 -> 0 | L24: =+K24 -> 0
A25: 22 | B25: 46225 | G25: =E25*F25 -> 0 | J25: =H25*I25 -> 0 | K25: =G25+J25 -> 0 | L25: =+K25 -> 0
A26: 23 | B26: 46226 | G26: =E26*F26 -> 0 | J26: =H26*I26 -> 0 | K26: =G26+J26 -> 0 | L26: =+K26 -> 0
A27: 24 | B27: 46227 | G27: =E27*F27 -> 0 | J27: =H27*I27 -> 0 | K27: =G27+J27 -> 0 | L27: =+K27 -> 0 | O27: 0
A28: 25 | B28: 46228 | G28: =E28*F28 -> 0 | J28: =H28*I28 -> 0 | K28: =G28+J28 -> 0 | L28: =+K28 -> 0
A29: 26 | B29: 46229 | G29: =E29*F29 -> 0 | J29: =H29*I29 -> 0 | K29: =G29+J29 -> 0 | L29: =+K29 -> 0
A30: 27 | B30: 46230 | G30: =E30*F30 -> 0 | J30: =H30*I30 -> 0 | K30: =G30+J30 -> 0 | L30: =+K30 -> 0
A31: 28 | B31: 46231 | G31: =E31*F31 -> 0 | J31: =H31*I31 -> 0 | K31: =G31+J31 -> 0 | L31: =+K31 -> 0
A32: 29 | B32: 46232 | G32: =E32*F32 -> 0 | J32: =H32*I32 -> 0 | K32: =G32+J32 -> 0 | L32: =+K32 -> 0
A33: 30 | B33: 46233 | G33: =E33*F33 -> 0 | J33: =H33*I33 -> 0 | K33: =G33+J33 -> 0 | L33: =+K33 -> 0
A34: 31 | B34: 46204 | G34: =E34*F34 -> 0 | J34: =H34*I34 -> 0 | K34: =G34+J34 -> 0 | L34: =H34+K34 -> 0
E35: =SUM(E4:E34) -> 140.48 | G35: =SUM(G4:G34) -> 13965.117 | H35: =SUM(H4:H34) -> 0 | J35: =SUM(J4:J34) -> 0 | K35: =SUM(K4:K34) -> 13965.117 | L35: =SUM(L4:L34) -> 13965.117

Sheet kumta
A1: V.M.MIRJANKAR (KUMTA) BHARAT
A2: S.No | B2: Date | C2: GRN No | D2: Ind No/Bill No | E2: Diesel (Lts) | F2: Price | G2: Amount | H2: Petrol (Lts) | I2: Price | J2: Amount | K2: Total amount | L2: Amount paid | M2: As on Date | N2: Remarks
A3: Opening Balance | M3: 15058.507
A4: 1 | B4: 45839 | G4: =E4*F4 -> 0 | J4: =H4*I4 -> 0 | K4: =G4+J4 -> 0 | M4: =M3+K4-L4 -> 15058.507
A5: 2 | B5: 45840 | G5: =E5*F5 -> 0 | J5: =H5*I5 -> 0 | K5: =G5+J5 -> 0 | M5: =M4+K5-L5 -> 15058.507
A6: 3 | B6: 45841 | E6: 50 | F6: 99.78 | G6: =E6*F6 -> 4989 | J6: =H6*I6 -> 0 | K6: =G6+J6 -> 4989 | M6: =M5+K6-L6 -> 20047.507
A7: 4 | B7: 45842 | G7: =E7*F7 -> 0 | J7: =H7*I7 -> 0 | K7: =G7+J7 -> 0 | M7: =M6+K7-L7 -> 20047.507
A8: 5 | B8: 45843 | G8: =E8*F8 -> 0 | J8: =H8*I8 -> 0 | K8: =G8+J8 -> 0 | M8: =M7+K8-L8 -> 20047.507
A9: 6 | B9: 45844 | G9: =E9*F9 -> 0 | J9: =H9*I9 -> 0 | K9: =G9+J9 -> 0 | M9: =M8+K9-L9 -> 20047.507
A10: 7 | B10: 45845 | E10: 45 | F10: 99.78 | G10: =E10*F10 -> 4490.1 | H10: 5 | I10: 111.98 | J10: =H10*I10 -> 559.9 | K10: =G10+J10 -> 5050 | L10: 20000 | M10: =M9+K10-L10 -> 5097.5068
A11: 8 | B11: 45846 | E11: 50 | F11: 99.78 | G11: =E11*F11 -> 4989 | H11: 5 | I11: 111.98 | J11: =H11*I11 -> 559.9 | K11: =G11+J11 -> 5548.9 | M11: =M10+K11-L11 -> 10646.407
A12: 9 | B12: 45847 | E12: 50 | F12: 99.78 | G12: =E12*F12 -> 4989 | H12: 15 | I12: 111.98 | J12: =H12*I12 -> 1679.7 | K12: =G12+J12 -> 6668.7 | M12: =M11+K12-L12 -> 17315.107
A13: 10 | B13: 45848 | G13: =E13*F13 -> 0 | J13: =H13*I13 -> 0 | K13: =G13+J13 -> 0 | M13: =M12+K13-L13 -> 17315.107
A14: 11 | B14: 45849 | G14: =E14*F14 -> 0 | J14: =H14*I14 -> 0 | K14: =G14+J14 -> 0 | M14: =M13+K14-L14 -> 17315.107
A15: 12 | B15: 45850 | G15: =E15*F15 -> 0 | H15: 5 | I15: 111.98 | J15: =H15*I15 -> 559.9 | K15: =G15+J15 -> 559.9 | M15: =M14+K15-L15 -> 17875.007
A16: 13 | B16: 45851 | E16: 60 | F16: 99.78 | G16: =E16*F16 -> 5986.8 | J16: =H16*I16 -> 0 | K16: =G16+J16 -> 5986.8 | M16: =M15+K16-L16 -> 23861.807
A17: 14 | B17: 45852 | E17: 50 | F17: 99.78 | G17: =E17*F17 -> 4989 | H17: 10 | I17: 111.98 | J17: =H17*I17 -> 1119.8 | K17: =G17+J17 -> 6108.8 | M17: =M16+K17-L17 -> 29970.607
A18: 15 | B18: 45853 | E18: 40 | F18: 99.78 | G18: =E18*F18 -> 3991.2 | J18: =H18*I18 -> 0 | K18: =G18+J18 -> 3991.2 | M18: =M17+K18-L18 -> 33961.807
A19: 16 | B19: 45854 | E19: 60 | F19: 99.78 | G19: =E19*F19 -> 5986.8 | J19: =H19*I19 -> 0 | K19: =G19+J19 -> 5986.8 | M19: =M18+K19-L19 -> 39948.607
A20: 17 | B20: 45855 | E20: 50 | F20: 99.78 | G20: =E20*F20 -> 4989 | J20: =H20*I20 -> 0 | K20: =G20+J20 -> 4989 | M20: =M19+K20-L20 -> 44937.607
A21: 18 | B21: 45856 | E21: 70 | F21: 99.78 | G21: =E21*F21 -> 6984.6 | H21: 5 | I21: 111.98 | J21: =H21*I21 -> 559.9 | K21: =G21+J21 -> 7544.5 | M21: =M20+K21-L21 -> 52482.107
A22: 19 | B22: 45857 | G22: =E22*F22 -> 0 | J22: =H22*I22 -> 0 | K22: =G22+J22 -> 0 | M22: =M21+K22-L22 -> 52482.107
A23: 20 | B23: 45858 | G23: =E23*F23 -> 0 | H23: 5 | I23: 111.98 | J23: =H23*I23 -> 559.9 | K23: =G23+J23 -> 559.9 | M23: =M22+K23-L23 -> 53042.007
A24: 21 | B24: 45859 | G24: =E24*F24 -> 0 | J24: =H24*I24 -> 0 | K24: =G24+J24 -> 0 | M24: =M23+K24-L24 -> 53042.007
A25: 22 | B25: 45860 | E25: 50 | F25: 99.78 | G25: =E25*F25 -> 4989 | J25: =H25*I25 -> 0 | K25: =G25+J25 -> 4989 | M25: =M24+K25-L25 -> 58031.007
A26: 23 | B26: 45861 | E26: 60 | F26: 99.78 | G26: =E26*F26 -> 5986.8 | J26: =H26*I26 -> 0 | K26: =G26+J26 -> 5986.8 | M26: =M25+K26-L26 -> 64017.807 | R26: Kumta | T26: V.M.Mirjankar
A27: 24 | B27: 45862 | E27: 60 | F27: 99.78 | G27: =E27*F27 -> 5986.8 | J27: =H27*I27 -> 0 | K27: =G27+J27 -> 5986.8 | M27: =M26+K27-L27 -> 70004.607 | R27: Month | S27: Disel In Litters | T27: Petrol In Litters | U27: Amount Paid
A28: 25 | B28: 45863 | E28: 80 | F28: 99.78 | G28: =E28*F28 -> 7982.4 | H28: 10 | I28: 111.98 | J28: =H28*I28 -> 1119.8 | K28: =G28+J28 -> 9102.2 | M28: =M27+K28-L28 -> 79106.807 | R28: Feb'-26 | S28: 2040 | T28: 90 | U28: 169925
A29: 26 | B29: 45864 | E29: 50 | F29: 99.78 | G29: =E29*F29 -> 4989 | J29: =H29*I29 -> 0 | K29: =G29+J29 -> 4989 | M29: =M28+K29-L29 -> 84095.807 | R29: March'-26 | S29: 2115 | T29: 185 | U29: 206053
A30: 27 | B30: 45865 | G30: =E30*F30 -> 0 | J30: =H30*I30 -> 0 | K30: =G30+J30 -> 0 | M30: =M29+K30-L30 -> 84095.807 | R30: April'-26 | S30: 2145 | T30: 177 | U30: 247835
A31: 28 | B31: 45866 | E31: 50 | F31: 99.78 | G31: =E31*F31 -> 4989 | J31: =H31*I31 -> 0 | K31: =G31+J31 -> 4989 | M31: =M30+K31-L31 -> 89084.807 | R31: May'-26 | S31: 545 | T31: 50 | U31: 44201
A32: 29 | B32: 45867 | E32: 70 | F32: 99.78 | G32: =E32*F32 -> 6984.6 | H32: 15 | I32: 111.98 | J32: =H32*I32 -> 1679.7 | K32: =G32+J32 -> 8664.3 | L32: 50000 | M32: =M31+K32-L32 -> 47749.107 | S32: =SUM(S28:S31) -> 6845 | T32: =SUM(T28:T31) -> 502 | U32: =SUM(U28:U31) -> 668014
A33: 30 | B33: 45868 | G33: =E33*F33 -> 0 | J33: =H33*I33 -> 0 | K33: =G33+J33 -> 0 | M33: =M32+K33-L33 -> 47749.107
A34: 31 | B34: 45869 | E34: 115 | F34: 99.78 | G34: =E34*F34 -> 11474.7 | H34: 10 | I34: 111.98 | J34: =H34*I34 -> 1119.8 | K34: =G34+J34 -> 12594.5 | M34: =M33+K34-L34 -> 60343.607
A35: 32 | B35: 45870 | G35: =E35*F35 -> 0 | J35: =H35*I35 -> 0 | K35: =G35+J35 -> 0 | M35: =M34+K35-L35 -> 60343.607
A36: 33 | G36: =E36*F36 -> 0 | J36: =H36*I36 -> 0 | K36: =G36+J36 -> 0 | M36: =M35+K36-L36 -> 60343.607
A37: 34 | G37: =E37*F37 -> 0 | J37: =H37*I37 -> 0 | K37: =G37+J37 -> 0 | M37: =M36+K37-L37 -> 60343.607
A38: 35 | G38: =E38*F38 -> 0 | J38: =H38*I38 -> 0 | K38: =G38+J38 -> 0 | M38: =M37+K38-L38 -> 60343.607
A39: 36 | G39: =E39*F39 -> 0 | J39: =H39*I39 -> 0 | K39: =G39+J39 -> 0 | M39: =M38+K39-L39 -> 60343.607
A40: 37 | G40: =E40*F40 -> 0 | J40: =H40*I40 -> 0 | K40: =G40+J40 -> 0 | M40: =M39+K40-L40 -> 60343.607
E41: =SUM(E4:E40) -> 1060 | G41: =SUM(G4:G40) -> 105766.8 | H41: =SUM(H4:H40) -> 85 | J41: =SUM(J4:J40) -> 9518.3 | K41: =SUM(K4:K40) -> 115285.1 | L41: =SUM(L4:L40) -> 70000

Sheet  Jalgaon-1
A1: Jai Bajarang Sarvo Senter Bodwad
A2: S.No | B2: Date | C2: GRN No | D2: Ind No/Bill No | E2: Diesel (Lts) | F2: Price | G2: Amount | H2: Petrol (Lts) | I2: Price | J2: Amount | K2: Total amount | L2: Amount paid | M2: As on Date | N2: Remarks
A3: Opening Balance | K3: 0 | L3: 0 | M3: 0
A4: 1 | B4: 46204 | G4: =E4*F4 -> 0 | J4: =H4*I4 -> 0 | K4: =G4+J4 -> 0 | M4: =M3+K4-L4 -> 0
A5: 2 | B5: 46205 | G5: =E5*F5 -> 0 | J5: =H5*I5 -> 0 | K5: =G5+J5 -> 0 | M5: =M4+K5-L5 -> 0
B6: 46206 | G6: =E6*F6 -> 0 | J6: =H6*I6 -> 0 | K6: =G6+J6 -> 0 | M6: =M5+K6-L6 -> 0
A7: 3 | B7: 46207 | G7: =E7*F7 -> 0 | J7: =H7*I7 -> 0 | K7: =G7+J7 -> 0 | M7: =M6+K7-L7 -> 0
A8: 4 | B8: 46208 | G8: =E8*F8 -> 0 | J8: =H8*I8 -> 0 | K8: =G8+J8 -> 0 | M8: =M7+K8-L8 -> 0
A9: 5 | B9: 46209 | G9: =E9*F9 -> 0 | J9: =H9*I9 -> 0 | K9: =G9+J9 -> 0 | M9: =M8+K9-L9 -> 0
A10: 6 | B10: 46210 | G10: =E10*F10 -> 0 | J10: =H10*I10 -> 0 | K10: =G10+J10 -> 0 | M10: =M9+K10-L10 -> 0
A11: 7 | B11: 46211 | G11: =E11*F11 -> 0 | J11: =H11*I11 -> 0 | K11: =G11+J11 -> 0 | M11: =M10+K11-L11 -> 0
A12: 8 | B12: 46212 | G12: =E12*F12 -> 0 | J12: =H12*I12 -> 0 | K12: =G12+J12 -> 0 | M12: =M11+K12-L12 -> 0
A13: 9 | B13: 46213 | G13: =E13*F13 -> 0 | J13: =H13*I13 -> 0 | K13: =G13+J13 -> 0 | M13: =M12+K13-L13 -> 0
A14: 10 | B14: 46214 | G14: =E14*F14 -> 0 | J14: =H14*I14 -> 0 | K14: =G14+J14 -> 0 | M14: =M13+K14-L14 -> 0
A15: 11 | B15: 46215 | G15: =E15*F15 -> 0 | J15: =H15*I15 -> 0 | K15: =G15+J15 -> 0 | M15: =M14+K15-L15 -> 0
A16: 12 | B16: 46216 | G16: =E16*F16 -> 0 | J16: =H16*I16 -> 0 | K16: =G16+J16 -> 0 | M16: =M15+K16-L16 -> 0
A17: 13 | B17: 46217 | G17: =E17*F17 -> 0 | J17: =H17*I17 -> 0 | K17: =G17+J17 -> 0 | M17: =M16+K17-L17 -> 0
A18: 14 | B18: 46218 | G18: =E18*F18 -> 0 | J18: =H18*I18 -> 0 | K18: =G18+J18 -> 0 | M18: =M17+K18-L18 -> 0
A19: 15 | B19: 46219 | G19: =E19*F19 -> 0 | J19: =H19*I19 -> 0 | K19: =G19+J19 -> 0 | M19: =M18+K19-L19 -> 0 | N19: BT
A20: 16 | B20: 46220 | G20: =E20*F20 -> 0 | J20: =H20*I20 -> 0 | K20: =G20+J20 -> 0 | M20: =M19+K20-L20 -> 0
A21: 17 | B21: 46221 | G21: =E21*F21 -> 0 | J21: =H21*I21 -> 0 | K21: =G21+J21 -> 0 | M21: =M20+K21-L21 -> 0
A22: 18 | B22: 46222 | G22: =E22*F22 -> 0 | J22: =H22*I22 -> 0 | K22: =G22+J22 -> 0 | M22: =M21+K22-L22 -> 0
A23: 19 | B23: 46223 | G23: =E23*F23 -> 0 | J23: =H23*I23 -> 0 | K23: =G23+J23 -> 0 | M23: =M22+K23-L23 -> 0
A24: 20 | B24: 46224 | G24: =E24*F24 -> 0 | J24: =H24*I24 -> 0 | K24: =G24+J24 -> 0 | M24: =M23+K24-L24 -> 0
A25: 21 | B25: 46225 | G25: =E25*F25 -> 0 | J25: =H25*I25 -> 0 | K25: =G25+J25 -> 0 | M25: =M24+K25-L25 -> 0
A26: 22 | B26: 46226 | G26: =E26*F26 -> 0 | J26: =H26*I26 -> 0 | K26: =G26+J26 -> 0 | M26: =M25+K26-L26 -> 0
A27: 23 | B27: 46227 | G27: =E27*F27 -> 0 | J27: =H27*I27 -> 0 | K27: =G27+J27 -> 0 | M27: =M26+K27-L27 -> 0
A28: 24 | B28: 46228 | G28: =E28*F28 -> 0 | J28: =H28*I28 -> 0 | K28: =G28+J28 -> 0 | M28: =M27+K28-L28 -> 0
A29: 25 | B29: 46229 | G29: =E29*F29 -> 0 | J29: =H29*I29 -> 0 | K29: =G29+J29 -> 0 | M29: =M28+K29-L29 -> 0
A30: 26 | B30: 46230 | G30: =E30*F30 -> 0 | J30: =H30*I30 -> 0 | K30: =G30+J30 -> 0 | M30: =M29+K30-L30 -> 0
A31: 27 | B31: 46231 | G31: =E31*F31 -> 0 | J31: =H31*I31 -> 0 | K31: =G31+J31 -> 0 | M31: =M30+K31-L31 -> 0
... A33: 29 | B33: 46233 | G33: =E33*F33 -> 0 | J33: =H33*I33 -> 0 | K33: =G33+J33 -> 0 | M33: =M32+K33-L33 -> 0
A34: 30 | G34: =E34*F34 -> 0 | J34: =H34*I34 -> 0 | K34: =G34+J34 -> 0 | M34: =M33+K34-L34 -> 0
A35: 31 | G35: =E35*F35 -> 0 | J35: =H35*I35 -> 0 | K35: =G35+J35 -> 0 | M35: =M34+K35-L35 -> 0
A36: 32 | G36: =E36*F36 -> 0 | J36: =H36*I36 -> 0 | K36: =G36+J36 -> 0 | M36: =M35+K36-L36 -> 0
A37: 33 | G37: =E37*F37 -> 0 | J37: =H37*I37 -> 0 | K37: =G37+J37 -> 0 | M37: =M36+K37-L37 -> 0
A38: 34 | G38: =E38*F38 -> 0 | J38: =H38*I38 -> 0 | K38: =G38+J38 -> 0 | M38: =M37+K38-L38 -> 0 | P38: 41
A39: 35 | G39: =E39*F39 -> 0 | J39: =H39*I39 -> 0 | K39: =G39+J39 -> 0 | M39: =M38+K39-L39 -> 0 | P39: 40 | Q39: 5
A40: 36 | G40: =E40*F40 -> 0 | J40: =H40*I40 -> 0 | K40: =G40+J40 -> 0 | M40: =M39+K40-L40 -> 0
A41: 37 | G41: =E41*F41 -> 0 | J41: =H41*I41 -> 0 | K41: =G41+J41 -> 0 | M41: =M40+K41-L41 -> 0
A42: 38 | G42: =E42*F42 -> 0 | J42: =H42*I42 -> 0 | K42: =G42+J42 -> 0 | M42: =M41+K42-L42 -> 0
A43: 39 | G43: =E43*F43 -> 0 | J43: =H43*I43 -> 0 | K43: =G43+J43 -> 0 | M43: =M42+K43-L43 -> 0
A44: 40 | G44: =E44*F44 -> 0 | J44: =H44*I44 -> 0 | K44: =G44+J44 -> 0 | M44: =M43+K44-L44 -> 0
A45: 41 | G45: =E45*F45 -> 0 | J45: =H45*I45 -> 0 | K45: =G45+J45 -> 0 | M45: =M44+K45-L45 -> 0
A46: 42 | G46: =E46*F46 -> 0 | J46: =H46*I46 -> 0 | K46: =G46+J46 -> 0 | M46: =M45+K46-L46 -> 0
A47: 43 | G47: =E47*F47 -> 0 | J47: =H47*I47 -> 0 | K47: =G47+J47 -> 0 | M47: =M46+K47-L47 -> 0
A48: 44 | G48: =E48*F48 -> 0 | J48: =H48*I48 -> 0 | K48: =G48+J48 -> 0 | M48: =M47+K48-L48 -> 0
A49: 45 | G49: =E49*F49 -> 0 | J49: =H49*I49 -> 0 | K49: =G49+J49 -> 0 | M49: =M48+K49-L49 -> 0
A50: 46 | G50: =E50*F50 -> 0 | J50: =H50*I50 -> 0 | K50: =G50+J50 -> 0 | M50: =M49+K50-L50 -> 0
A51: 47 | G51: =E51*F51 -> 0 | J51: =H51*I51 -> 0 | K51: =G51+J51 -> 0 | L51: 0 | M51: =M50+K51-L51 -> 0
A52: 48 | G52: =E52*F52 -> 0 | J52: =H52*I52 -> 0 | K52: =G52+J52 -> 0 | L52: 0 | M52: =M51+K52-L52 -> 0
A53: 49 | G53: =E53*F53 -> 0 | J53: =H53*I53 -> 0 | K53: =G53+J53 -> 0 | L53: 0 | M53: =M52+K53-L53 -> 0
A54: 50 | G54: =E54*F54 -> 0 | J54: =H54*I54 -> 0 | K54: =G54+J54 -> 0 | L54: 0 | M54: =M53+K54-L54 -> 0 | O54: 1109792.3 | P54: =M54-O54 -> -1109792.3
E55: =SUM(E4:E54) -> 0 | G55: =SUM(G4:G54) -> 0 | H55: =SUM(H4:H54) -> 0 | J55: =SUM(J4:J54) -> 0 | K55: =SUM(K4:K54) -> 0 | L55: =SUM(L4:L54) -> 0

Sheet Jalgoan-2
A1: Nayara
A2: S.No | B2: Date | C2: GRN No | D2: Ind No/Bill No | E2: Diesel (Lts) | F2: Price | G2: Amount | H2: Petrol (Lts) | I2: Price | J2: Amount | K2: Total amount | L2: Amount paid | M2: As on Date | N2: Remarks
A3: Opening Balance | K3: 2547026.4 | M3: 2547026.4 | P3: 5472110
A4: 1 | B4: 46204 | G4: =E4*F4 -> 0 | J4: =H4*I4 -> 0 | K4: =G4+J4 -> 0 | M4: =M3+K4-L4 -> 2547026.4
A5: 2 | B5: 46205 | G5: =E5*F5 -> 0 | J5: =H5*I5 -> 0 | K5: =G5+J5 -> 0 | M5: =M4+K5-L5 -> 2547026.4
A6: 3 | B6: 46206 | E6: 2700 | F6: 99.51 | G6: =E6*F6 -> 268677 | J6: =H6*I6 -> 0 | K6: =G6+J6 -> 268677 | M6: =M5+K6-L6 -> 2815703.4
A7: 4 | B7: 46207 | G7: =E7*F7 -> 0 | J7: =H7*I7 -> 0 | K7: =G7+J7 -> 0 | M7: =M6+K7-L7 -> 2815703.4
A8: 5 | B8: 46208 | G8: =E8*F8 -> 0 | J8: =H8*I8 -> 0 | K8: =G8+J8 -> 0 | M8: =M7+K8-L8 -> 2815703.4
A9: 6 | B9: 46209 | G9: =E9*F9 -> 0 | J9: =H9*I9 -> 0 | K9: =G9+J9 -> 0 | M9: =M8+K9-L9 -> 2815703.4
A10: 7 | B10: 46210 | G10: =E10*F10 -> 0 | J10: =H10*I10 -> 0 | K10: =G10+J10 -> 0 | M10: =M9+K10-L10 -> 2815703.4
A11: 8 | B11: 46211 | G11: =E11*F11 -> 0 | J11: =H11*I11 -> 0 | K11: =G11+J11 -> 0 | M11: =M10+K11-L11 -> 2815703.4
A12: 9 | B12: 46212 | G12: =E12*F12 -> 0 | H12: 30 | I12: 113.18 | J12: =H12*I12 -> 3395.4 | K12: =G12+J12 -> 3395.4 | M12: =M11+K12-L12 -> 2819098.8
A13: 10 | B13: 46213 | E13: 2850 | F13: 99.51 | G13: =E13*F13 -> 283603.5 | J13: =H13*I13 -> 0 | K13: =G13+J13 -> 283603.5 | M13: =M12+K13-L13 -> 3102702.3
A14: 11 | B14: 46214 | G14: =E14*F14 -> 0 | J14: =H14*I14 -> 0 | K14: =G14+J14 -> 0 | M14: =M13+K14-L14 -> 3102702.3
A15: 12 | B15: 46215 | G15: =E15*F15 -> 0 | J15: =H15*I15 -> 0 | K15: =G15+J15 -> 0 | M15: =M14+K15-L15 -> 3102702.3
A16: 13 | B16: 46216 | E16: 2745 | F16: 99.51 | G16: =E16*F16 -> 273154.95 | H16: 30 | I16: 113.18 | J16: =H16*I16 -> 3395.4 | K16: =G16+J16 -> 276550.35 | M16: =M15+K16-L16 -> 3379252.7
A17: 14 | B17: 46217 | E17: 41.53 | F17: 97.97 | G17: =E17*F17 -> 4068.6941 | J17: =H17*I17 -> 0 | K17: =G17+J17 -> 4068.6941 | L17: =H17+K17 -> 4068.6941 | M17: =M16+K17-L17 -> 3379252.7 | N17: CASH purchese
A18: 15 | B18: 46218 | G18: =E18*F18 -> 0 | J18: =H18*I18 -> 0 | K18: =G18+J18 -> 0 | M18: =M17+K18-L18 -> 3379252.7
A19: 16 | B19: 46219 | E19: 2872.91 | F19: 99.51 | G19: =E19*F19 -> 285883.27 | H19: 30 | I19: 113.18 | J19: =H19*I19 -> 3395.4 | K19: =G19+J19 -> 289278.67 | M19: =M18+K19-L19 -> 3668531.4
A20: 17 | B20: 46220 | G20: =E20*F20 -> 0 | J20: =H20*I20 -> 0 | K20: =G20+J20 -> 0 | M20: =M19+K20-L20 -> 3668531.4
A21: 18 | B21: 46221 | G21: =E21*F21 -> 0 | J21: =H21*I21 -> 0 | K21: =G21+J21 -> 0 | M21: =M20+K21-L21 -> 3668531.4
A22: 19 | B22: 46222 | E22: 2904 | F22: 99.51 | G22: =E22*F22 -> 288977.04 | J22: =H22*I22 -> 0 | K22: =G22+J22 -> 288977.04 | M22: =M21+K22-L22 -> 3957508.4
A23: 20 | B23: 46223 | G23: =E23*F23 -> 0 | J23: =H23*I23 -> 0 | K23: =G23+J23 -> 0 | M23: =M22+K23-L23 -> 3957508.4
A24: 21 | B24: 46224 | G24: =E24*F24 -> 0 | J24: =H24*I24 -> 0 | K24: =G24+J24 -> 0 | M24: =M23+K24-L24 -> 3957508.4
A25: 22 | B25: 46225 | G25: =E25*F25 -> 0 | J25: =H25*I25 -> 0 | K25: =G25+J25 -> 0 | M25: =M24+K25-L25 -> 3957508.4
A26: 23 | B26: 46226 | E26: 2906 | F26: 99.51 | G26: =E26*F26 -> 289176.06 | H26: 30 | I26: 113.18 | J26: =H26*I26 -> 3395.4 | K26: =G26+J26 -> 292571.46 | M26: =M25+K26-L26 -> 4250079.9
A27: 24 | B27: 46227 | G27: =E27*F27 -> 0 | J27: =H27*I27 -> 0 | K27: =G27+J27 -> 0 | M27: =M26+K27-L27 -> 4250079.9
A28: 25 | B28: 46228 | G28: =E28*F28 -> 0 | J28: =H28*I28 -> 0 | K28: =G28+J28 -> 0 | M28: =M27+K28-L28 -> 4250079.9
A29: 26 | B29: 46229 | G29: =E29*F29 -> 0 | J29: =H29*I29 -> 0 | K29: =G29+J29 -> 0 | M29: =M28+K29-L29 -> 4250079.9
A30: 27 | B30: 46230 | E30: 2790 | F30: 99.51 | G30: =E30*F30 -> 277632.9 | H30: 30 | I30: 113.18 | J30: =H30*I30 -> 3395.4 | K30: =G30+J30 -> 281028.3 | M30: =M29+K30-L30 -> 4531108.2
A31: 28 | B31: 46231 | G31: =E31*F31 -> 0 | J31: =H31*I31 -> 0 | K31: =G31+J31 -> 0 | M31: =M30+K31-L31 -> 4531108.2
A32: 29 | B32: 46232 | G32: =E32*F32 -> 0 | J32: =H32*I32 -> 0 | K32: =G32+J32 -> 0 | M32: =M31+K32-L32 -> 4531108.2
A33: 30 | B33: 46233 | G33: =E33*F33 -> 0 | J33: =H33*I33 -> 0 | K33: =G33+J33 -> 0 | M33: =M32+K33-L33 -> 4531108.2
A34: 31 | G34: =E34*F34 -> 0 | J34: =H34*I34 -> 0 | K34: =G34+J34 -> 0 | M34: =M33+K34-L34 -> 4531108.2
A35: 32 | G35: =E35*F35 -> 0 | J35: =H35*I35 -> 0 | K35: =G35+J35 -> 0 | M35: =M34+K35-L35 -> 4531108.2
A36: 33 | G36: =E36*F36 -> 0 | J36: =H36*I36 -> 0 | K36: =G36+J36 -> 0 | M36: =M35+K36-L36 -> 4531108.2
A37: 34 | G37: =E37*F37 -> 0 | J37: =H37*I37 -> 0 | K37: =G37+J37 -> 0 | M37: =M36+K37-L37 -> 4531108.2
A38: 35 | G38: =E38*F38 -> 0 | J38: =H38*I38 -> 0 | K38: =G38+J38 -> 0 | M38: =M37+K38-L38 -> 4531108.2
A39: 36 | G39: =E39*F39 -> 0 | J39: =H39*I39 -> 0 | K39: =G39+J39 -> 0 | M39: =M38+K39-L39 -> 4531108.2 | P39: 41
A40: 37 | G40: =E40*F40 -> 0 | J40: =H40*I40 -> 0 | K40: =G40+J40 -> 0 | M40: =M39+K40-L40 -> 4531108.2 | P40: 40 | Q40: 5
A41: 38 | G41: =E41*F41 -> 0 | J41: =H41*I41 -> 0 | K41: =G41+J41 -> 0 | M41: =M40+K41-L41 -> 4531108.2
A42: 39 | G42: =E42*F42 -> 0 | J42: =H42*I42 -> 0 | K42: =G42+J42 -> 0 | M42: =M41+K42-L42 -> 4531108.2
A43: 40 | G43: =E43*F43 -> 0 | J43: =H43*I43 -> 0 | K43: =G43+J43 -> 0 | M43: =M42+K43-L43 -> 4531108.2
A44: 41 | G44: =E44*F44 -> 0 | J44: =H44*I44 -> 0 | K44: =G44+J44 -> 0 | M44: =M43+K44-L44 -> 4531108.2
A45: 42 | G45: =E45*F45 -> 0 | J45: =H45*I45 -> 0 | K45: =G45+J45 -> 0 | M45: =M44+K45-L45 -> 4531108.2
A46: 43 | G46: =E46*F46 -> 0 | J46: =H46*I46 -> 0 | K46: =G46+J46 -> 0 | M46: =M45+K46-L46 -> 4531108.2
A47: 44 | G47: =E47*F47 -> 0 | J47: =H47*I47 -> 0 | K47: =G47+J47 -> 0 | M47: =M46+K47-L47 -> 4531108.2
A48: 45 | G48: =E48*F48 -> 0 | J48: =H48*I48 -> 0 | K48: =G48+J48 -> 0 | M48: =M47+K48-L48 -> 4531108.2
A49: 46 | G49: =E49*F49 -> 0 | J49: =H49*I49 -> 0 | K49: =G49+J49 -> 0 | M49: =M48+K49-L49 -> 4531108.2
A50: 47 | G50: =E50*F50 -> 0 | J50: =H50*I50 -> 0 | K50: =G50+J50 -> 0 | M50: =M49+K50-L50 -> 4531108.2
A51: 48 | G51: =E51*F51 -> 0 | J51: =H51*I51 -> 0 | K51: =G51+J51 -> 0 | M51: =M50+K51-L51 -> 4531108.2
A52: 49 | G52: =E52*F52 -> 0 | J52: =H52*I52 -> 0 | K52: =G52+J52 -> 0 | L52: 0 | M52: =M51+K52-L52 -> 4531108.2
A53: 50 | G53: =E53*F53 -> 0 | J53: =H53*I53 -> 0 | K53: =G53+J53 -> 0 | L53: 0 | M53: =M52+K53-L53 -> 4531108.2
A54: 50 | G54: =E54*F54 -> 0 | J54: =H54*I54 -> 0 | K54: =G54+J54 -> 0 | L54: 0 | M54: =M53+K54-L54 -> 4531108.2
A55: 51 | G55: =E55*F55 -> 0 | J55: =H55*I55 -> 0 | K55: =G55+J55 -> 0 | L55: 0 | M55: =M54+K55-L55 -> 4531108.2 | O55: 1109792.3 | P55: =M55-O55 -> 3421315.9
E56: =SUM(E4:E55) -> 19809.44 | G56: =SUM(G4:G55) -> 1971173.4 | H56: =SUM(H4:H55) -> 150 | J56: =SUM(J4:J55) -> 16977 | K56: =SUM(K4:K55) -> 1988150.4 | L56: =SUM(L4:L55) -> 4068.6941

Sheet MKBD
A1: Shree Sai Samarth Petroleum
A2: S.No | B2: Date | C2: GRN No | D2: Ind No/Bill No | E2: Diesel (Lts) | F2: Price | G2: Amount | H2: Petrol (Lts) | I2: Price | J2: Amount | K2: Total amount | L2: Amount paid | M2: As on Date | N2: Remarks
A3: Opening Balance | K3: 631570.81 | M3: 631570.81
A4: 1 | B4: 46204 | G4: =E4*F4 -> 0 | J4: =H4*I4 -> 0 | K4: =G4+J4 -> 0 | M4: =M3+K4-L4 -> 631570.81
A5: 2 | B5: 46205 | G5: =E5*F5 -> 0 | J5: =H5*I5 -> 0 | K5: =G5+J5 -> 0 | M5: =M4+K5-L5 -> 631570.81
A6: 3 | B6: 46206 | G6: =E6*F6 -> 0 | J6: =H6*I6 -> 0 | K6: =G6+J6 -> 0 | M6: =M5+K6-L6 -> 631570.81
A7: 3 | B7: 46207 | G7: =E7*F7 -> 0 | J7: =H7*I7 -> 0 | K7: =G7+J7 -> 0 | M7: =M6+K7-L7 -> 631570.81
A8: 4 | B8: 46208 | G8: =E8*F8 -> 0 | J8: =H8*I8 -> 0 | K8: =G8+J8 -> 0 | M8: =M7+K8-L8 -> 631570.81
A9: 5 | B9: 46209 | G9: =E9*F9 -> 0 | J9: 0 | K9: =G9+J9 -> 0 | M9: =M8+K9-L9 -> 631570.81
A10: 6 | B10: 46210 | G10: =E10*F10 -> 0 | J10: =H10*I10 -> 0 | K10: =G10+J10 -> 0 | M10: =M9+K10-L10 -> 631570.81
A11: 7 | B11: 46211 | G11: =E11*F11 -> 0 | J11: =H11*I11 -> 0 | K11: =G11+J11 -> 0 | M11: =M10+K11-L11 -> 631570.81
A12: 8 | B12: 46212 | G12: =E12*F12 -> 0 | J12: =H12*I12 -> 0 | K12: =G12+J12 -> 0 | M12: =M11+K12-L12 -> 631570.81
A13: 9 | B13: 46213 | G13: 0 | J13: 0 | K13: =G13+J13 -> 0 | M13: =M12+K13-L13 -> 631570.81
A14: 10 | B14: 46214 | G14: =E14*F14 -> 0 | J14: =H14*I14 -> 0 | K14: =G14+J14 -> 0 | M14: =M13+K14-L14 -> 631570.81
A15: 11 | B15: 46215 | G15: =E15*F15 -> 0 | J15: =H15*I15 -> 0 | K15: =G15+J15 -> 0 | M15: =M14+K15-L15 -> 631570.81
A16: 12 | B16: 46216 | G16: =E16*F16 -> 0 | K16: =G16+J16 -> 0 | M16: =M15+K16-L16 -> 631570.81
A17: 13 | B17: 46217 | E17: 3000 | F17: 98.94 | G17: =E17*F17 -> 296820 | K17: =G17+J17 -> 296820 | M17: =M16+K17-L17 -> 928390.81
A18: 14 | B18: 46218 | G18: =E18*F18 -> 0 | J18: =H18*I18 -> 0 | K18: =G18+J18 -> 0 | M18: =M17+K18-L18 -> 928390.81
A19: 15 | B19: 46219 | G19: =E19*F19 -> 0 | J19: =H19*I19 -> 0 | K19: =G19+J19 -> 0 | M19: =M18+K19-L19 -> 928390.81
A20: 16 | B20: 46220 | G20: =E20*F20 -> 0 | J20: =H20*I20 -> 0 | K20: =G20+J20 -> 0 | M20: =M19+K20-L20 -> 928390.81
A21: 17 | B21: 46221 | G21: =E21*F21 -> 0 | J21: =H21*I21 -> 0 | K21: =G21+J21 -> 0 | M21: =M20+K21-L21 -> 928390.81
A22: 18 | B22: 46222 | G22: =E22*F22 -> 0 | J22: =H22*I22 -> 0 | K22: =G22+J22 -> 0 | M22: =M21+K22-L22 -> 928390.81
A23: 19 | B23: 46223 | G23: =E23*F23 -> 0 | J23: =H23*I23 -> 0 | K23: =G23+J23 -> 0 | M23: =M22+K23-L23 -> 928390.81
A24: 20 | B24: 46224 | J24: =H24*I24 -> 0 | K24: =G24+J24 -> 0 | M24: =M23+K24-L24 -> 928390.81
A25: 21 | B25: 46225 | G25: =E25*F25 -> 0 | J25: =H25*I25 -> 0 | K25: =G25+J25 -> 0 | M25: =M24+K25-L25 -> 928390.81
A26: 22 | B26: 46226 | G26: =E26*F26 -> 0 | J26: =H26*I26 -> 0 | K26: =G26+J26 -> 0 | M26: =M25+K26-L26 -> 928390.81
A27: 23 | B27: 46227 | G27: =E27*F27 -> 0 | J27: =H27*I27 -> 0 | K27: =G27+J27 -> 0 | M27: =M26+K27-L27 -> 928390.81
A28: 24 | B28: 46228 | G28: =E28*F28 -> 0 | J28: =H28*I28 -> 0 | K28: =G28+J28 -> 0 | M28: =M27+K28-L28 -> 928390.81
A29: 25 | B29: 46229 | G29: =E29*F29 -> 0 | J29: =H29*I29 -> 0 | K29: =G29+J29 -> 0 | M29: =M28+K29-L29 -> 928390.81
A30: 26 | B30: 46230 | G30: =E30*F30 -> 0 | J30: =H30*I30 -> 0 | K30: =G30+J30 -> 0 | M30: =M29+K30-L30 -> 928390.81
A31: 27 | B31: 46231 | G31: =E31*F31 -> 0 | H31: 10 | I31: 112.27 | J31: =H31*I31 -> 1122.7 | K31: =G31+J31 -> 1122.7 | M31: =M30+K31-L31 -> 929513.51
A32: 28 | B32: 46232 | G32: =E32*F32 -> 0 | J32: =H32*I32 -> 0 | K32: =G32+J32 -> 0 | M32: =M31+K32-L32 -> 929513.51
A33: 29 | B33: 46233 | G33: =E33*F33 -> 0 | J33: =H33*I33 -> 0 | K33: =G33+J33 -> 0 | M33: =M32+K33-L33 -> 929513.51
A34: 30 | B34: 46234 | G34: =E34*F34 -> 0 | J34: =H34*I34 -> 0 | K34: =G34+J34 -> 0 | M34: =M33+K34-L34 -> 929513.51
A35: 31 | G35: =E35*F35 -> 0 | J35: =H35*I35 -> 0 | K35: =G35+J35 -> 0 | M35: =M34+K35-L35 -> 929513.51
A36: 32 | G36: =E36*F36 -> 0 | J36: =H36*I36 -> 0 | K36: =G36+J36 -> 0 | M36: =M35+K36-L36 -> 929513.51
A37: 33 | G37: =E37*F37 -> 0 | J37: 0 | K37: =G37+J37 -> 0 | M37: =M36+K37-L37 -> 929513.51
A38: 34 | G38: 0 | J38: 0 | K38: =G38+J38 -> 0 | M38: =M37+K38-L38 -> 929513.51
A39: 35 | G39: =E39*F39 -> 0 | J39: =H39*I39 -> 0 | K39: =G39+J39 -> 0 | M39: =M38+K39-L39 -> 929513.51
A40: 36 | G40: =E40*F40 -> 0 | J40: =H40*I40 -> 0 | K40: =G40+J40 -> 0 | M40: =M39+K40-L40 -> 929513.51
A41: 37 | E41: 0 | F41: 0 | G41: =E41*F41 -> 0 | J41: =H41*I41 -> 0 | K41: =G41+J41 -> 0 | M41: =M40+K41-L41 -> 929513.51
E42: =SUM(E4:E41) -> 3000 | G42: =SUM(G4:G41) -> 296820 | H42: =SUM(H4:H41) -> 10 | J42: =SUM(J4:J41) -> 1122.7 | K42: =SUM(K4:K41) -> 297942.7 | L42: =SUM(L4:L41) -> 0

Sheet  Haveri-2
A1: Magavi fuel F/S
A2: S.No | B2: Date | C2: GRN No | D2: Ind No/Bill No | E2: Diesel (Lts) | F2: Price | G2: Amount | H2: Petrol (Lts) | I2: Price | J2: Amount | K2: Total amount | L2: Amount paid | M2: As on Date | N2: Remarks
D3: Opening Balance | L3: 132797.45 | M3: 132797.45
A4: 1 | B4: 46204 | E4: 325 | F4: 99.3 | G4: =E4*F4 -> 32272.5 | J4: =H4*I4 -> 0 | K4: =G4+J4 -> 32272.5 | M4: =M3+K4-L4 -> 165069.95
A5: 2 | B5: 46205 | E5: 135.01 | F5: 99.3 | G5: =E5*F5 -> 13406.493 | J5: =H5*I5 -> 0 | K5: =G5+J5 -> 13406.493 | M5: =M4+K5-L5 -> 178476.44
