Workbook

Sheet  MIs
A2: S.No | B2: NAme | C2: Lacation | D2: Card Number | E2: Card Number | F2: Category | G2: 1st Jan | I2: 2nd Jan | J2: 3rd Jan | K2: 4th Jan | L2: 5th Jan | M2: 6th Jan | N2: 7th Jan | O2: 8th Jan | P2: 9th Jan | Q2: 10th Jan | R2: 11th Jan | S2: 12th Jan | T2: 13th Jan | U2: 14th Jan | V2: 15th Jan | W2: 16th Jan | X2: 17th Jan | Y2: 18th Jan | Z2: 19th Jan | AA2: 20th Jan | AB2: 21st Jan | AC2: 22nd Jan | AD2: 23rd Jan | AE2: 24th Jan | AF2: 25th Jan | AG2: 26th Jan | AH2: 27th Jan | AI2: 28th Jan | AJ2: 29th Jan | AK2: 30th Jan | AL2: 31st Jan | AM2: Total
F3: Diesel
A4: 1 | B4: Rambabu | C4: HO(Two Wheeler) | D4: FC3450563999 | E4: Diesel | F4: 0 | G4: 0 | H4: 0 | I4: 0 | J4: 0 | K4: 0 | L4: 0 | M4: 0 | N4: 0 | O4: 0 | P4: 0 | Q4: 0 | R4: 0 | S4: 0 | T4: 0 | U4: 0 | V4: 0 | W4: 0 | X4: 5.22 | Y4: 0 | Z4: 0 | AA4: 0 | AB4: 0 | AC4: 0 | AD4: 60 | AE4: 0 | AF4: 0 | AG4: 0 | AH4: 4.56 | AI4: 0 | AJ4: 0 | AK4: 0 | AL4: 0 | AM4: =SUM(F4:AL4) -> 69.78
E5: Petrol | F5: 0 | G5: 4.69 | H5: 0 | I5: 0 | J5: 0 | K5: 0 | L5: 0 | M5: 0 | N5: 3.91 | O5: 0 | P5: 6.98 | Q5: 0 | R5: 0 | S5: 0 | T5: 0 | U5: 0 | V5: 0 | W5: 0 | X5: 0 | Y5: 0 | Z5: 0 | AB5: 0 | AC5: 0 | AD5: 0 | AE5: 0 | AF5: 0 | AG5: 0 | AH5: 0 | AI5: 0 | AJ5: 0 | AK5: 0 | AL5: 0 | AM5: =SUM(F5:AL5) -> 15.58
A6: 2 | B6: Hanumanth Rao | C6: HO | D6: FC3450676131 | E6: Diesel | F6: 0 | G6: 0 | H6: 0 | I6: 0 | J6: 0 | K6: 0 | L6: 0 | M6: 0 | N6: 0 | O6: 0 | P6: 0 | Q6: 0 | R6: 0 | S6: 0 | T6: 0 | U6: 0 | V6: 0 | W6: 0 | X6: 0 | Y6: 0 | Z6: 0 | AA6: 0 | AB6: 0 | AC6: 0 | AD6: 0 | AE6: 0 | AF6: 0 | AG6: 0 | AH6: 0 | AI6: 0 | AJ6: 0 | AK6: 0 | AL6: 0 | AM6: =SUM(F6:AL6) -> 0
E7: Petrol | F7: 0 | G7: 0 | H7: 0 | I7: 0 | J7: 0 | K7: 0 | L7: 0 | M7: 0 | N7: 0 | O7: 0 | P7: 0 | Q7: 0 | R7: 0 | S7: 0 | T7: 0 | U7: 0 | V7: 0 | W7: 0 | X7: 0 | Y7: 0 | Z7: 0 | AB7: 0 | AC7: 0 | AD7: 0 | AE7: 0 | AF7: 0 | AG7: 0 | AH7: 0 | AI7: 0 | AJ7: 0 | AK7: 0 | AL7: 0 | AM7: =SUM(F7:AL7) -> 0
A8: 3 | B8: Radhakrishna | C8: HO | D8: FC8000207658 | E8: Diesel | F8: 0 | G8: 0 | H8: 0 | I8: 0 | J8: 33.44 | K8: 0 | L8: 0 | M8: 0 | N8: 0 | O8: 0 | P8: 0 | Q8: 0 | R8: 35.53 | S8: 0 | T8: 0 | U8: 0 | V8: 0 | W8: 0 | X8: 0 | Y8: 0 | Z8: 0 | AA8: 0 | AB8: 33.44 | AC8: 0 | AD8: 0 | AE8: 0 | AF8: 0 | AG8: 0 | AH8: 0 | AI8: 0 | AJ8: 0 | AK8: 0 | AL8: 0 | AM8: =SUM(F8:AL8) -> 102.41
E9: Petrol | F9: 0 | G9: 0 | H9: 0 | I9: 0 | J9: 0 | K9: 0 | L9: 0 | M9: 0 | N9: 0 | O9: 0 | P9: 0 | Q9: 0 | R9: 0 | S9: 0 | T9: 0 | U9: 0 | V9: 0 | W9: 0 | X9: 0 | Y9: 0 | Z9: 0 | AB9: 0 | AC9: 0 | AD9: 0 | AE9: 0 | AF9: 0 | AG9: 0 | AH9: 0 | AI9: 0 | AJ9: 0 | AK9: 0 | AL9: 0 | AM9: =SUM(F9:AL9) -> 0
A10: 4 | B10: VIjay | C10: HO | D10: FC3450698859 | E10: Diesel | F10: 0 | G10: 0 | H10: 0 | I10: 0 | J10: 0 | K10: 0 | L10: 0 | M10: 0 | N10: 0 | O10: 0 | P10: 49.22 | Q10: 0 | R10: 0 | S10: 0 | T10: 0 | U10: 54.57 | V10: 0 | W10: 0 | X10: 0 | Y10: 0 | Z10: 0 | AA10: 0 | AB10: 0 | AC10: 0 | AD10: 49.8 | AE10: 0 | AF10: 0 | AG10: 0 | AH10: 0 | AI10: 0 | AJ10: 0 | AK10: 0 | AL10: 0 | AM10: =SUM(F10:AL10) -> 153.59
E11: Petrol | F11: 0 | G11: 0 | H11: 0 | I11: 0 | J11: 0 | K11: 0 | L11: 0 | M11: 0 | N11: 0 | O11: 0 | P11: 0 | Q11: 0 | R11: 0 | S11: 0 | T11: 0 | U11: 0 | V11: 0 | W11: 0 | X11: 0 | Y11: 0 | Z11: 0 | AB11: 0 | AC11: 0 | AD11: 0 | AE11: 0 | AF11: 0 | AG11: 0 | AH11: 0 | AI11: 0 | AJ11: 0 | AK11: 0 | AL11: 0 | AM11: =SUM(F11:AL11) -> 0
A12: 5 | B12: Client | C12: Hiriyur | D12: FC3450698864 | E12: Diesel | F12: 0 | G12: 0 | H12: 0 | I12: 0 | J12: 0 | K12: 0 | L12: 0 | M12: 0 | N12: 86.29 | O12: 0 | P12: 0 | Q12: 0 | R12: 0 | S12: 0 | T12: 0 | U12: 0 | V12: 0 | W12: 0 | X12: 0 | Y12: 0 | Z12: 0 | AA12: 0 | AB12: 0 | AC12: 0 | AD12: 145.61 | AE12: 0 | AF12: 0 | AG12: 0 | AH12: 0 | AI12: 0 | AJ12: 0 | AK12: 0 | AL12: 0 | AM12: =SUM(F12:AL12) -> 231.9
E13: Petrol | F13: 0 | G13: 0 | H13: 0 | I13: 0 | J13: 0 | K13: 0 | L13: 0 | M13: 0 | N13: 0 | O13: 0 | P13: 0 | Q13: 0 | R13: 0 | S13: 0 | T13: 0 | U13: 0 | V13: 0 | W13: 0 | X13: 0 | Y13: 0 | Z13: 0 | AB13: 0 | AC13: 0 | AD13: 0 | AE13: 0 | AF13: 0 | AG13: 0 | AH13: 0 | AI13: 0 | AJ13: 0 | AK13: 0 | AL13: 0 | AM13: =SUM(F13:AL13) -> 0
A14: 6 | B14: Client | C14: Hosadurga | D14: FC3450698865 | E14: Diesel | F14: 0 | G14: 0 | H14: 0 | I14: 0 | J14: 0 | K14: 0 | L14: 40 | M14: 40 | N14: 0 | O14: 36 | P14: 35 | Q14: 0 | R14: 0 | S14: 0 | T14: 0 | U14: 0 | V14: 0 | W14: 45 | X14: 45 | Y14: 43.53 | Z14: 40 | AA14: 43 | AB14: 0 | AC14: 40 | AD14: 0 | AE14: 40 | AF14: 0 | AG14: 0 | AH14: 0 | AI14: 0 | AJ14: 0 | AK14: 0 | AL14: 0 | AM14: =SUM(F14:AL14) -> 447.53
E15: Petrol | F15: 0 | G15: 0 | H15: 0 | I15: 0 | J15: 0 | K15: 0 | L15: 0 | M15: 0 | N15: 0 | O15: 0 | P15: 0 | Q15: 0 | R15: 0 | S15: 0 | T15: 0 | U15: 0 | V15: 0 | W15: 0 | X15: 0 | Y15: 0 | Z15: 0 | AB15: 0 | AC15: 0 | AD15: 0 | AE15: 0 | AF15: 0 | AG15: 0 | AH15: 0 | AI15: 0 | AJ15: 0 | AK15: 0 | AL15: 0 | AM15: =SUM(F15:AL15) -> 0
G18: Diesel Price

Sheet  May-2026
A1: S.no | B1: Site Name | C1: Bunk Name | D1: Diesel(Liters) | E1: Diesel Amount | F1: Petrol(Liters) | G1: Petrol Amount | H1: Total Amount | I1: Opening Blance | J1: Amount Paid | K1: Closing Balances
A2: 1 | B2: Khammam-1 | C2: Divya laxmi ganapathi | D2: =+'Khammam-1'!E38 -> 48265.34 | E2: =+'Khammam-1'!G38 -> 4766880.2 | F2: =+'Khammam-1'!H38 -> 0 | G2: =+'Khammam-1'!J38 -> 0 | H2: =E2+G2 -> 4766880.2 | I2: =+'Khammam-1'!K3 -> 1769630.7 | J2: =+'Khammam-1'!L38 -> 3882012 | K2: =H2+I2-J2 -> 2654498.9
A3: 2 | B3: Khammam-2 | C3: Jayasai union bunk | D3: =+'Khammam-2'!E36 -> 49055.57 | E3: =+'Khammam-2'!G36 -> 4879543.5 | F3: =+'Khammam-2'!H36 -> 1040 | G3: =+'Khammam-2'!J36 -> 114901.15 | H3: =E3+G3 -> 4994444.6 | I3: =+'Khammam-2'!K3 -> 3725653 | J3: =+'Khammam-2'!L36 -> 0 | K3: =H3+I3-J3 -> 8720097.6
A4: 3 | B4: Khammam-3 | C4: JSASFuel Genie India Pvt.Ltd | D4: =+'Khammam-3'!E35 -> 0 | E4: =+'Khammam-3'!G35 -> 0 | F4: =+'Khammam-3'!H35 -> 0 | G4: =+'Khammam-3'!J35 -> 0 | H4: =E4+G4 -> 0 | I4: =+'Khammam-3'!M3 -> 2572600.3 | J4: =+'Khammam-3'!L35 -> 1000000 | K4: =H4+I4-J4 -> 1572600.3
A5: 4 | B5: Khammam-Cash&Carry | C5: NA | D5: =+' Khammam&Cash'!E46 -> 22238.479 | E5: =+' Khammam&Cash'!G46 -> 2148660 | F5: =+' Khammam&Cash'!H46 -> 0 | G5: =+' Khammam&Cash'!J46 -> 0 | H5: =E5+G5 -> 2148660 | I5: =+' Khammam&Cash'!M3 -> 0 | J5: =+' Khammam&Cash'!L46 -> 2148660 | K5: =H5+I5-J5 -> 0
A6: 5 | B6: Jadcherla-1 | C6: JSASFuel Genie India Pvt.Ltd | D6: =+'Jadcherla-3'!E35 -> 0 | E6: =+'Jadcherla-3'!G35 -> 0 | F6: =+'Jadcherla-3'!H35 -> 0 | G6: =+'Jadcherla-3'!J35 -> 0 | H6: =E6+G6 -> 0 | I6: =+'Jadcherla-3'!M3 -> 1313281.7 | J6: =+'Jadcherla-3'!L35 -> 0 | K6: =H6+I6-J6 -> 1313281.7
A7: 6 | B7: Jadcherla-2 | C7: Shree Poornima F/S | D7: =+'Jadcherla-4'!E35 -> 1000 | E7: =+'Jadcherla-4'!G35 -> 96300 | F7: =+'Jadcherla-4'!H35 -> 112 | G7: =+'Jadcherla-4'!J35 -> 12264.88 | H7: =E7+G7 -> 108564.88 | I7: =+'Jadcherla-4'!M3 -> 3523.2 | J7: =+'Jadcherla-4'!L35 -> 96300 | K7: =H7+I7-J7 -> 15788.08
A8: 7 | B8: Jadcherla-3 | C8: Sai Baba Filling Station | D8: =+' Jadcherla'!E35 -> 10537.12 | E8: =+' Jadcherla'!G35 -> 1049374.1 | F8: =+' Jadcherla'!H35 -> 0 | G8: =+' Jadcherla'!J35 -> 0 | H8: =E8+G8 -> 1049374.1 | I8: =+' Jadcherla'!M3 -> 44630 | J8: =+' Jadcherla'!L35 -> 922889 | K8: =H8+I8-J8 -> 171115.11
A9: 8 | B9: Sangareddy-2 | C9: Durga Bhavani F/S | D9: =+' Sangareddy-2'!E35 -> 6343.62 | E9: =+' Sangareddy-2'!G35 -> 620418.55 | F9: =+' Sangareddy-2'!H35 -> 261.72 | G9: =+' Sangareddy-2'!J35 -> 28902.223 | H9: =E9+G9 -> 649320.78 | I9: =+' Sangareddy-2'!M3 -> 258995.39 | J9: =+' Sangareddy-2'!L35 -> 800000 | K9: =H9+I9-J9 -> 108316.17 | M9: VASUDEO NIVRUTTI
A10: 9 | B10: Sangareddy-3 | C10: Shiva Parvathi Filling Station | D10: =+' Sangareddy-3'!E35 -> 18194.62 | E10: =+' Sangareddy-3'!G35 -> 1819638.1 | F10: =+' Sangareddy-3'!H35 -> 25.36 | G10: =+' Sangareddy-3'!J35 -> 2948.1 | H10: =E10+G10 -> 1822586.2 | I10: =+' Sangareddy-3'!M3 -> 163539.24 | J10: =+' Sangareddy-3'!L35 -> 1000000 | K10: =H10+I10-J10 -> 986125.39
A11: 10 | B11: NarayanaKhed | C11: Sai Shiva Filling Station | D11: =Narayankhed!E35 -> 1537.82 | E11: =+Narayankhed!G35 -> 152799.64 | F11: =+Narayankhed!H35 -> 0 | G11: =+Narayankhed!J35 -> 0 | H11: =E11+G11 -> 152799.64 | I11: =+Narayankhed!M3 -> 0 | J11: =+Narayankhed!L35 -> 152799.64 | K11: =H11+I11-J11 -> 0
A12: 11 | B12: Dindi | C12: Akarapu Balakistamma Fillling | D12: =+Dindi!E35 -> 0 | E12: =+Dindi!G35 -> 0 | F12: =+Dindi!H35 -> 0 | G12: =+Dindi!J35 -> 0 | H12: =E12+G12 -> 0 | I12: =+Dindi!M3 -> 0 | J12: =+Dindi!L35 -> 0 | K12: =H12+I12-J12 -> 0 | M12: =PROPER(M9) -> Vasudeo Nivrutti
A13: 12 | B13: Madanapalli | C13: NA | D13: =+'Madana palli'!E36 -> 18.98 | E13: =+'Madana palli'!G36 -> 1998.9736 | F13: =+'Madana palli'!H36 -> 4.25 | G13: =+'Madana palli'!J36 -> 500.055 | H13: =E13+G13 -> 2499.0286 | I13: =+'Madana palli'!M3 -> 0 | J13: =+'Madana palli'!L36 -> 2499.0286 | K13: =H13+I13-J13 -> 0
A14: 13 | B14: Kakinada | C14: NA | D14: =+Amalapuram!E102 -> 3362.44 | E14: =+Amalapuram!G102 -> 340456.85 | F14: =+Amalapuram!H102 -> 258.11 | G14: =+Amalapuram!J102 -> 29399.14 | H14: =E14+G14 -> 369855.99 | I14: =+Amalapuram!M3 -> 0 | J14: =+Amalapuram!L102 -> 369855.99 | K14: =H14+I14-J14 -> 0.00049999991
A15: 14 | B15: YG Gudda-2 | C15: Pankaja HP Fuel Center | D15: =+'YG Gudda-2'!E38 -> 9000 | E15: =+'YG Gudda-2'!G38 -> 848355 | F15: =+'YG Gudda-2'!H38 -> 280 | G15: =+'YG Gudda-2'!J38 -> 29456 | H15: =E15+G15 -> 877811 | I15: =+'YG Gudda-2'!M3 -> 194105.96 | J15: =+'YG Gudda-2'!L38 -> 882798 | K15: =H15+I15-J15 -> 189118.96
A16: 15 | B16: Hosadurga-2 | C16: Shree Veeraprathap Fuel | D16: =+'Hosadurga -2'!E35 -> 2700.44 | E16: =+'Hosadurga -2'!G35 -> 260751.02 | F16: =+'Hosadurga -2'!H35 -> 155.43 | G16: =+'Hosadurga -2'!J35 -> 16960.59 | H16: =+'Hosadurga -2'!K35 -> 277711.61 | I16: =+'Hosadurga -2'!K3 -> 248489.28 | J16: =+'Hosadurga -2'!L35 -> 377999.69 | K16: =H16+I16-J16 -> 148201.19
A17: 16 | B17: Malebennuru(KUWSDB) | C17: Sri Ramanjuneya Service Station | D17: =+'Malebenur(KUWSDB)'!E37 -> 4600 | E17: =+'Malebenur(KUWSDB)'!G37 -> 434664 | F17: =+'Malebenur(KUWSDB)'!H37 -> 145 | G17: =+'Malebenur(KUWSDB)'!J37 -> 15440.3 | H17: =E17+G17 -> 450104.3 | I17: =+'Malebenur(KUWSDB)'!K3 -> 193649.21 | J17: =+'Malebenur(KUWSDB)'!L37 -> 548000 | K17: =H17+I17-J17 -> 95753.51
A18: 17 | B18: kadur | C18: Vishal Service Station | D18: =+Kadur!E35 -> 1600 | E18: =+Kadur!G35 -> 152240 | F18: =+Kadur!H35 -> 70 | G18: =+Kadur!J35 -> 7648.9 | H18: =E18+G18 -> 159888.9 | I18: =+Kadur!K3 -> 0 | J18: =+Kadur!L35 -> 0 | K18: =H18+I18-J18 -> 159888.9
A19: 18 | B19: Hiriyur(VJNL) | C19: Sri Balaji Agencies | D19: =+'Hiriyur(VJNL)'!E35 -> 3500 | E19: =+'Hiriyur(VJNL)'!G35 -> 328440 | F19: =+'Hiriyur(VJNL)'!H35 -> 245 | G19: =+'Hiriyur(VJNL)'!J35 -> 25740.4 | H19: =E19+G19 -> 354180.4 | I19: =+'Hiriyur(VJNL)'!K3 -> 278745.3 | J19: =+'Hiriyur(VJNL)'!L35 -> 450000 | K19: =H19+I19-J19 -> 182925.7
A20: 19 | B20: Chellakere(KUWSDB) | C20: Shivaganga Service Station | D20: =+'Chellakere -1'!E38 -> 3200.08 | E20: =+'Chellakere -1'!G38 -> 305200.07 | F20: =+'Chellakere -1'!H38 -> 210.03 | G20: =+'Chellakere -1'!J38 -> 22624.204 | H20: =E20+G20 -> 327824.27 | I20: =+'Chellakere -1'!K3 -> 249803.37 | J20: =+'Chellakere -1'!L38 -> 506012.56 | K20: =H20+I20-J20 -> 71615.087
A21: 20 | B21: Chellakere(KUWSDB)-09 | C21: Shivaganga Service Station | D21: =+' Chellakere-PKG-9'!E36 -> 600.65 | E21: =+' Chellakere-PKG-9'!G36 -> 57117.949 | F21: =+' Chellakere-PKG-9'!H36 -> 46 | G21: =+' Chellakere-PKG-9'!J36 -> 4960.94 | H21: =E21+G21 -> 62078.889 | I21: =+' Chellakere-PKG-9'!M3 -> 0 | J21: =+' Chellakere-PKG-9'!L36 -> 62078.889 | K21: =H21+I21-J21 -> 0
A22: 21 | B22: Molakalmuru | C22: Sri Lakshmi Venkateshwara Filling Station | D22: =+Molakamuru!E35 -> 1200 | E22: =+Molakamuru!G35 -> 114030 | F22: =+Molakamuru!H35 -> 45 | G22: =+Molakamuru!J35 -> 4876.8 | H22: =E22+G22 -> 118906.8 | I22: =+Molakamuru!K3 -> 56291.815 | J22: =+Molakamuru!L35 -> 112377.94 | K22: =H22+I22-J22 -> 62820.675
A23: 22 | B23: Chennagiri | C23: NA | D23: =+' Chennagiri'!E35 -> 965 | E23: =+' Chennagiri'!G35 -> 92635.8 | F23: =+' Chennagiri'!H35 -> 44.73 | G23: =+' Chennagiri'!J35 -> 4999.9194 | H23: =E23+G23 -> 97635.719 | I23: =+' Chennagiri'!K3 -> 0 | J23: =+' Chennagiri'!L35 -> 97635.719 | K23: =H23+I23-J23 -> 0
A24: 23 | B24: Khanapur(PKG-3) | C24: V.V.Varde | D24: =+Khanapur!E35 -> 1755.95 | E24: =+Khanapur!G35 -> 164273.6 | F24: =+Khanapur!H35 -> 85 | G24: =+Khanapur!J35 -> 8971.5 | H24: =E24+G24 -> 173245.1 | I24: =+Khanapur!M3 -> 114295.13 | J24: =+Khanapur!L35 -> 228514.58 | K24: =H24+I24-J24 -> 59025.654
A25: 24 | B25: Munavalli(PKG-3) | C25: Shre Shiva Petroleum | D25: =+'Munavali-2'!E40 -> 9550 | E25: =+'Munavali-2'!G40 -> 899267 | F25: =+'Munavali-2'!H40 -> 162.75 | G25: =+'Munavali-2'!J40 -> 17029.498 | H25: =E25+G25 -> 916296.5 | I25: =+'Munavali-2'!M3 -> 567608.01 | J25: =+'Munavali-2'!L40 -> 1038902.9 | K25: =H25+I25-J25 -> 445001.62
A26: 25 | B26: Munavalli(PKG-3) | C26: Daneshwari Petroleum | D26: =+' Munavali'!E39 -> 5841.67 | E26: =+' Munavali'!G39 -> 564521.75 | F26: =+' Munavali'!H39 -> 120 | G26: =+' Munavali'!J39 -> 13194.4 | H26: =E26+G26 -> 577716.15 | I26: =+' Munavali'!M3 -> 0 | J26: =+' Munavali'!L39 -> 300000 | K26: =H26+I26-J26 -> 277716.15
A27: 26 | B27: Borgaon(PKG-3) | C27: Aadisagar Petrolium | D27: =+Borgaon!E35 -> 5710.55 | E27: =+Borgaon!G35 -> 546400.84 | F27: =+Borgaon!H35 -> 76 | G27: =+Borgaon!J35 -> 8070.16 | H27: =E27+G27 -> 554471 | I27: =+Borgaon!K3 -> 106655.39 | J27: =+Borgaon!L35 -> 385000 | K27: =H27+I27-J27 -> 276126.39
A28: 27 | B28: Ugar,Kudichi(PKG-3) | C28: Shiri Bhrhmanath Petrolium | D28: =+'Ugar,Khagwad,Kudichi'!E37 -> 12026.84 | E28: =+'Ugar,Khagwad,Kudichi'!G37 -> 1132213.3 | F28: =+'Ugar,Khagwad,Kudichi'!H37 -> 241 | G28: =+'Ugar,Khagwad,Kudichi'!J37 -> 26148.23 | H28: =E28+G28 -> 1158361.5 | I28: =+'Ugar,Khagwad,Kudichi'!M3 -> 584214.75 | J28: =+'Ugar,Khagwad,Kudichi'!L37 -> 1265943 | K28: =H28+I28-J28 -> 476633.25
A29: 28 | B29: Shedbal | C29: Varad Petroluem | D29: =+shedbal!E35 -> 1600 | E29: =+shedbal!G35 -> 159568 | F29: =+shedbal!H35 -> 75 | G29: =+shedbal!J35 -> 8388.75 | H29: =E29+G29 -> 167956.75 | I29: =+shedbal!M3 -> 0 | J29: =+shedbal!L35 -> 0 | K29: =H29+I29-J29 -> 167956.75
A30: 29 | B30: Kabbur(PKG-3) | C30: Shri Jai Hanuman Petrolium | D30: =+Kabbur!E35 -> 1179.59 | E30: =+Kabbur!G35 -> 114899.78 | F30: =+Kabbur!H35 -> 24.95 | G30: =+Kabbur!J35 -> 2650.523 | H30: =E30+G30 -> 117550.31 | I30: 0 | J30: =+Kabbur!L35 -> 117550.31 | K30: =H30+I30-J30 -> 0
A31: 30 | B31: Kumta (PKG-1) | C31: V.M.MIRJANKAR (KUMTA) BHARAT | D31: =+kumta!E39 -> 1445 | E31: =+kumta!G39 -> 137309.75 | F31: =+kumta!H39 -> 179.62 | G31: =+kumta!J39 -> 19391.78 | H31: =E31+G31 -> 156701.53 | I31: =kumta!M3 -> 2607.22 | J31: =+kumta!L39 -> 87987 | K31: =H31+I31-J31 -> 71321.75
A32: 31 | B32: Jalgaon-1 | C32: Jai Bajarang Sarvo Senter Bodwad | D32: =+' Jalgaon-1'!E55 -> 0 | E32: =+' Jalgaon-1'!G55 -> 0 | F32: =+' Jalgaon-1'!H55 -> 0 | G32: =+' Jalgaon-1'!J55 -> 0 | H32: =E32+G32 -> 0 | I32: =+' Jalgaon-1'!K3 -> 93813.679 | J32: =+' Jalgaon-1'!L55 -> 93813 | K32: =H32+I32-J32 -> 0.6791
A33: 32 | B33: Jalgaon-2 | C33: Nayara | D33: =+'Jalgoan-2'!E56 -> 21903.53 | E33: ='Jalgoan-2'!G56 -> 2088961 | F33: =+'Jalgoan-2'!H56 -> 415 | G33: =+'Jalgoan-2'!J56 -> 46926.1 | H33: =E33+G33 -> 2135887.1 | I33: =+'Jalgoan-2'!M3 -> 2665456 | J33: =+'Jalgoan-2'!L56 -> 2631873.3 | K33: =H33+I33-J33 -> 2169469.7
A34: 33 | B34: Jalgaon-3 | C34: Vasudeo Nivrutti | D34: =+' Jalgaon-3'!E19 -> 20133.17 | E34: =+' Jalgaon-3'!G19 -> 1896800.9 | F34: =+' Jalgaon-3'!H19 -> 0 | G34: =+' Jalgaon-3'!J19 -> 0 | H34: =E34+G34 -> 1896800.9 | I34: =+' Jalgaon-3'!M3 -> 0 | J34: =+' Jalgaon-3'!L19 -> 1402087.9 | K34: =H34+I34-J34 -> 494713.05
A35: 34 | B35: Jalgaon-4 | C35: Raksha Auto Fuels | D35: =+'Jalgaon-4'!E19 -> 12037.21 | E35: =+'Jalgaon-4'!G19 -> 1108054.6 | F35: =+'Jalgaon-4'!H19 -> 0 | G35: =+'Jalgaon-4'!J19 -> 0 | H35: =E35+G35 -> 1108054.6 | I35: =+'Jalgaon-4'!M3 -> 0 | J35: =+'Jalgaon-4'!L19 -> 1108054.6 | K35: =H35+I35-J35 -> 0
A36: 35 | B36: Jalgaon-5 C | C36: NA | D36: =+' Jalgaon-5 c'!E39 -> 39436.77 | E36: =+' Jalgaon-5 c'!G39 -> 3690231.3 | F36: =+' Jalgaon-5 c'!H39 -> 0 | G36: =+' Jalgaon-5 c'!J39 -> 0 | H36: =E36+G36 -> 3690231.3 | I36: =+' Jalgaon-5 c'!M3 -> 0 | J36: =+' Jalgaon-5 c'!L39 -> 3690231.3 | K36: =H36+I36-J36 -> 0.0039999997
A37: 36 | B37: MKBD | C37: Shree Sai Samarth Petroleum | D37: =+MKBD!E41 -> 24319.62 | E37: =+MKBD!G41 -> 2308313.2 | F37: =+MKBD!H41 -> 115 | G37: =+MKBD!J41 -> 12326 | H37: =E37+G37 -> 2320639.2 | I37: =+MKBD!K3 -> 2570275.5 | J37: =+MKBD!L41 -> 1000000 | K37: =H37+I37-J37 -> 3890914.7
A38: 37 | B38: Haveri | C38: M/s Magavi City Fuels | D38: =' Haveri-2'!E42 -> 8690.58 | E38: =' Haveri-2'!G42 -> 817553.99 | F38: =' Haveri-2'!H42 -> 196.08 | G38: =' Haveri-2'!J42 -> 21168.399 | H38: =E38+G38 -> 838722.38 | I38: =' Haveri-2'!M3 -> 60112.508 | J38: =+' Haveri-2'!L42 -> 692610.93 | K38: =H38+I38-J38 -> 206223.97
A39: 38 | B39: Guttal-2 | C39: Himagiri Petroleum | D39: =+' Guttal-2'!E35 -> 3290 | E39: =+' Guttal-2'!G35 -> 310419.4 | F39: =+' Guttal-2'!H35 -> 137 | G39: =+' Guttal-2'!J35 -> 14876.32 | H39: =E39+G39 -> 325295.72 | I39: =+' Guttal-2'!M3 -> 200595.1 | J39: =+' Guttal-2'!L35 -> 420000 | K39: =H39+I39-J39 -> 105890.82
A40: 39 | B40: Rattihali-2 | C40: Shiva Oil Traders | D40: =+'Rattihali-2'!E37 -> 5535.6 | E40: =+'Rattihali-2'!G37 -> 529300.29 | F40: =+'Rattihali-2'!H37 -> 100 | G40: =+'Rattihali-2'!J37 -> 10687.53 | H40: =E40+G40 -> 539987.82 | I40: =+'Rattihali-2'!M3 -> 266017.9 | J40: =+'Rattihali-2'!L37 -> 450000 | K40: =H40+I40-J40 -> 356005.72
A41: 40 | B41: Gajendragada | C41: Vanasri Petrol Pump | D41: =+Gajendragada!E36 -> 522.35 | E41: =+Gajendragada!G36 -> 50389.98 | F41: =+Gajendragada!H36 -> 111.16 | G41: =+Gajendragada!J36 -> 11805.468 | H41: =E41+G41 -> 62195.448 | I41: =+Gajendragada!K3 -> 41263.189 | J41: =+Gajendragada!L36 -> 60000 | K41: =H41+I41-J41 -> 43458.638
A42: 41 | B42: Gokak(PKG-3) | C42: AJ Petrolinks | D42: =+'Gokak Dharwad PKG 3'!E42 -> 7041.79 | E42: =+'Gokak Dharwad PKG 3'!G42 -> 658929.04 | F42: =+'Gokak Dharwad PKG 3'!H42 -> 117 | G42: =+'Gokak Dharwad PKG 3'!J42 -> 12325.15 | H42: =E42+G42 -> 671254.19 | I42: =+'Gokak Dharwad PKG 3'!K3 -> 326043.53 | J42: =+'Gokak Dharwad PKG 3'!L42 -> 761000 | K42: =H42+I42-J42 -> 236297.72
A43: 42 | B43: Hukkere | C43: TR Assocites | D43: =+' TR Associates'!E34 -> 11496.31 | E43: =+' TR Associates'!G34 -> 1082763.1 | F43: =+' TR Associates'!H34 -> 102 | G43: =+' TR Associates'!J34 -> 10843.28 | H43: =E43+G43 -> 1093606.4 | I43: =+' TR Associates'!M3 -> 497320.03 | J43: =+' TR Associates'!L34 -> 800000 | K43: =H43+I43-J43 -> 790926.4
A44: 43 | B44: Ankaligi | C44: Shivaganga | D44: =+Ankalgi!E35 -> 5019.2 | E44: =+Ankalgi!G35 -> 473753.83 | F44: =+Ankalgi!H35 -> 68 | G44: =+Ankalgi!J35 -> 7220.77 | H44: =E44+G44 -> 480974.6 | I44: =+Ankalgi!M3 -> 96251.93 | J44: =+Ankalgi!L35 -> 350000 | K44: =H44+I44-J44 -> 227226.53
A45: 44 | B45: Ghattaprabha | C45: Shri Deshpande | D45: =+'SHRI DESHPANDE'!E35 -> 3736.67 | E45: =+'SHRI DESHPANDE'!G35 -> 367925.14 | F45: =+'SHRI DESHPANDE'!H35 -> 146 | G45: =+'SHRI DESHPANDE'!J35 -> 16254.31 | H45: =E45+G45 -> 384179.45 | I45: =+'SHRI DESHPANDE'!M3 -> 0 | J45: =+'SHRI DESHPANDE'!L35 -> 0 | K45: =H45+I45-J45 -> 384179.45
A46: 45 | B46: ShankeshWAR | C46: SR Patil | D46: =+' Shankeshwar'!E35 -> 450.36 | E46: =+' Shankeshwar'!G35 -> 42110.831 | F46: =+' Shankeshwar'!H35 -> 38 | G46: =+' Shankeshwar'!J35 -> 3987.73 | H46: =E46+G46 -> 46098.561 | I46: =' Shankeshwar'!M3 -> 0 | J46: =+' Shankeshwar'!L35 -> 46098.561 | K46: =H46+I46-J46 -> 0
A47: 46 | B47: Talikote(PKG-1) | C47: Raykar Oil Agencies | D47: =+' Talikote'!E47 -> 862.11 | E47: =+' Talikote'!G47 -> 81316.767 | F47: =+' Talikote'!H47 -> 58.77 | G47: =+' Talikote'!J47 -> 6333.9333 | H47: =E47+G47 -> 87650.7 | I47: =+' Talikote'!N3 -> 18468.864 | J47: =+' Talikote'!L47 -> 91345.153 | K47: =H47+I47-J47 -> 14774.411
A48: 47 | B48: Chadchan(PKG-1) | C48: Khavekar Petrolium | D48: =+Chadchan!E35 -> 416.59 | E48: =+Chadchan!G35 -> 39342.874 | F48: =+Chadchan!H35 -> 66.76 | G48: =+Chadchan!J35 -> 7186.3061 | H48: =E48+G48 -> 46529.18 | I48: =+Chadchan!K3 -> 119708.41 | J48: =+Chadchan!L35 -> 150000 | K48: =H48+I48-J48 -> 16237.589
A49: 48 | B49: Sindagi | C49: G.P.PORWAL | D49: =+Sindagi!E44 -> 273.65 | E49: =+Sindagi!G44 -> 26031.105 | F49: =+Sindagi!H44 -> 0 | G49: =+Sindagi!J44 -> 0 | H49: =E49+G49 -> 26031.105 | I49: =+Sindagi!M3 -> 5617.8127 | J49: =+Sindagi!L44 -> 19000 | K49: =H49+I49-J49 -> 12648.918
A50: 49 | B50: Muddebihal(PKG-1)2 | C50: PS NAGATHAN PETROLIUM | D50: =+'Muddebhihal-2'!E50 -> 1309.7 | E50: =+'Muddebhihal-2'!G50 -> 127569.64 | F50: =+'Muddebhihal-2'!H50 -> 41.01 | G50: =+'Muddebhihal-2'!J50 -> 4468.8648 | H50: =+'Muddebhihal-2'!K50 -> 132038.5 | I50: =+'Muddebhihal-2'!M3 -> 137771.22 | J50: =+'Muddebhihal-2'!L50 -> 120000 | K50: =+'Muddebhihal-2'!M49 -> 149809.72
A51: 50 | B51: Almela(PKG-1) | C51: Shiddeshwar Petroleums | D51: =+Alemela!E43 -> 904.76 | E51: =+Alemela!G43 -> 85929.813 | F51: =+Alemela!H43 -> 125.63 | G51: =+Alemela!J43 -> 13353.94 | H51: =E51+G51 -> 99283.753 | I51: =+Alemela!M3 -> 15850.339 | J51: =+Alemela!L43 -> 50000.49 | K51: =H51+I51-J51 -> 65133.602
A52: 51 | B52: Nalatwad(PKG-1) | C52: Shri Pawad Basaweshwar Petroleums | D52: =+Nalatwad!E43 -> 207.77 | E52: =+Nalatwad!G43 -> 19235.761 | F52: =+Nalatwad!H43 -> 73.8 | G52: =+Nalatwad!J43 -> 7970.1867 | H52: =E52+G52 -> 27205.948 | I52: =+Nalatwad!M3 -> 83089.934 | J52: =+Nalatwad!L43 -> 0 | K52: =H52+I52-J52 -> 110295.88
A53: 52 | B53: Srirangapatna | C53: Anupama F/S | D53: =+Srirangapatna!E35 -> 152.72 | E53: =+Srirangapatna!G35 -> 14679.637 | F53: =+Srirangapatna!H35 -> 21.14 | G53: =+Srirangapatna!J35 -> 2260.4863 | H53: =E53+G53 -> 16940.123 | I53: 0 | J53: =+Srirangapatna!L35 -> 16940.123 | K53: =H53+I53-J53 -> 0
A54: 53 | B54: HO(DG) | C54: JSASFuel Genie India Pvt.Ltd | D54: =+'HO(DG)'!E45 -> 1414.96 | E54: =+'HO(DG)'!G45 -> 140530.52 | F54: =+'HO(DG)'!H45 -> 0 | G54: =+'HO(DG)'!J45 -> 0 | H54: =E54+G54 -> 140530.52 | I54: =+'HO(DG)'!M3 -> 79033.75 | J54: =+'HO(DG)'!L45 -> 119766.52 | K54: =H54+I54-J54 -> 99797.75
A55: Total | D55: =SUM(D2:D54) -> 396185.18 | E55: =SUM(E2:E54) -> 38148100 | F55: =SUM(F2:F54) -> 5839.3 | G55: =SUM(G2:G54) -> 635463.22 | H55: =SUM(H2:H54) -> 38783564 | I55: =SUM(I2:I54) -> 19725009 | J55: =SUM(J2:J54) -> 30908638 | K55: =H55+I55-J55 -> 27599934 | L55: 27515633 | M55: =K55-L55 -> 84300.957
A60: S.no | B60: Site Name | C60: Bunk Name | D60: Diesel(Liters) | E60: Diesel Amount | F60: Petrol(Liters) | G60: Petrol Amount | H60: Total Amount | I60: Opening Blance | J60: Amount Paid | K60: Closing Balances
A61: 39 | B61: {=VLOOKUP(A61,A1:K53,{2,3,4,5,6,7,8,9,10,11},FALSE)} -> Rattihali-2 | C61: Shiva Oil Traders | D61: 5535.6 | E61: 529300.29 | F61: 100 | G61: 10687.53 | H61: 539987.82 | I61: 266017.9 | J61: 450000 | K61: 356005.72
B63: Site Name | C63: Bunk Name | D63: Diesel(Liters) | E63: Diesel Amount | F63: Petrol(Liters) | G63: Petrol Amount | H63: Total Amount | I63: Opening Blance | J63: Amount Paid | K63: Closing Balances
B64: Jalgaon-2 | C64: {=VLOOKUP(B64,B1:K53,{2,3,4,5,6,7,8,9,10},FALSE)} -> Nayara | D64: 21903.53 | E64: 2088961 | F64: 415 | G64: 46926.1 | H64: 2135887.1 | I64: 2665456 | J64: 2631873.3 | K64: 2169469.7
B71: 60000
B72: 18000
B73: 18000
B74: 75000
B75: 360000

Sheet HO(DG)
A1: JSASFuel Genie India Pvt.Ltd
A2: S.No | B2: Date | C2: GRN No | D2: Ind No/Bill No | E2: Diesel (Lts) | F2: Price | G2: Amount | H2: Petrol (Lts) | I2: Price | J2: Amount | K2: Total amount | L2: Amount paid | M2: As on date | N2: Remarks
A3: Opening Balance | K3: 79033.75 | M3: 79033.75 | O3: 2623243.4
A4: 1 | B4: 46143 | G4: =E4*F4 -> 0 | H4: 0 | I4: 0 | J4: =H4*I4 -> 0 | K4: =G4+J4 -> 0 | L4: 0 | M4: =M3+K4-L4 -> 79033.75
A5: 2 | B5: 46144 | G5: =E5*F5 -> 0 | K5: =G5+J5 -> 0 | M5: =M4+K5-L5 -> 79033.75 | R5: HO | S5: 188521.22
A6: 3 | B6: 46145 | G6: =E6*F6 -> 0 | K6: =G6+J6 -> 0 | M6: =M5+K6-L6 -> 79033.75 | R6: Khammam | S6: 8227903
A7: 4 | B7: 46146 | E7: 110 | F7: 95.64 | G7: =E7*F7 -> 10520.4 | K7: =G7+J7 -> 10520.4 | L7: =H7+K7 -> 10520.4 | M7: =M6+K7-L7 -> 79033.75 | R7: Jadcherla | S7: 2453209.4
A8: 5 | B8: 46147 | G8: =E8*F8 -> 0 | K8: =G8+J8 -> 0 | M8: =M7+K8-L8 -> 79033.75 | P8: 5679 | R8: Total | S8: =SUM(S5:S7) -> 10869634
A9: 6 | B9: 46148 | G9: =E9*F9 -> 0 | K9: =G9+J9 -> 0 | M9: =M8+K9-L9 -> 79033.75 | S9: 10869632
A10: 7 | B10: 46149 | E10: 35 | F10: 95.64 | G10: =E10*F10 -> 3347.4 | K10: =G10+J10 -> 3347.4 | L10: =H10+K10 -> 3347.4 | M10: =M9+K10-L10 -> 79033.75 | N10: HPCL | S10: =S9-S8 -> -1.6105
B11: 46149 | E11: 70 | F11: 95.64 | G11: =E11*F11 -> 6694.8 | K11: =G11+J11 -> 6694.8 | L11: =H11+K11 -> 6694.8 | M11: =M10+K11-L11 -> 79033.75 | N11: HPCL
A12: 8 | B12: 46150 | E12: 120 | F12: 95.64 | G12: =E12*F12 -> 11476.8 | K12: =G12+J12 -> 11476.8 | L12: =H12+K12 -> 11476.8 | M12: =M11+K12-L12 -> 79033.75
A13: 9 | B13: 46151 | G13: =E13*F13 -> 0 | K13: =G13+J13 -> 0 | M13: =M12+K13-L13 -> 79033.75 | Q13: 54.98
A14: 10 | B14: 46152 | G14: =E14*F14 -> 0 | K14: =G14+J14 -> 0 | M14: =M13+K14-L14 -> 79033.75 | Q14: 54.98
A15: 11 | B15: 46153 | E15: 110 | F15: 95.64 | G15: =E15*F15 -> 10520.4 | K15: =G15+J15 -> 10520.4 | L15: =H15+K15 -> 10520.4 | M15: =M14+K15-L15 -> 79033.75
A16: 12 | B16: 46154 | G16: =E16*F16 -> 0 | K16: =G16+J16 -> 0 | L16: =H16+K16 -> 0 | M16: =M15+K16-L16 -> 79033.75 | R16: 19166
A17: 13 | B17: 46155 | G17: =E17*F17 -> 0 | K17: =G17+J17 -> 0 | L17: =H17+K17 -> 0 | M17: =M16+K17-L17 -> 79033.75 | R17: 19645
A18: 14 | B18: 46156 | E18: 109.96 | F18: 95.64 | G18: =E18*F18 -> 10516.574 | K18: =G18+J18 -> 10516.574 | L18: =H18+K18 -> 10516.574 | M18: =M17+K18-L18 -> 79033.75 | P18: 1905988 | Q18: =P18-M18 -> 1826954.2 | R18: 21083
A19: 15 | B19: 46157 | G19: =E19*F19 -> 0 | K19: =G19+J19 -> 0 | L19: =H19+K19 -> 0 | M19: =M18+K19-L19 -> 79033.75 | R19: 19140 | S19: 220637
A20: 16 | B20: 46158 | K20: =G20+J20 -> 0 | L20: =H20+K20 -> 0 | M20: =M19+K20-L20 -> 79033.75 | N20: HPCL | R20: =SUM(R16:R19) -> 79034 | S20: =S19+R20 -> 299671
A21: 17 | B21: 46159 | K21: =G21+J21 -> 0 | L21: =H21+K21 -> 0 | M21: =M20+K21-L21 -> 79033.75 | N21: HPCL
A22: 18 | B22: 46160 | E22: 70 | F22: 98.9 | G22: =E22*F22 -> 6923 | K22: =G22+J22 -> 6923 | L22: =H22+K22 -> 6923 | M22: =M21+K22-L22 -> 79033.75 | N22: Credit Card
A23: 19 | B23: 46161 | E23: 70 | F23: 99.89 | G23: =E23*F23 -> 6992.3 | K23: =G23+J23 -> 6992.3 | L23: =H23+K23 -> 6992.3 | M23: =M22+K23-L23 -> 79033.75
A24: 20 | B24: 46162 | E24: 70 | F24: 99.89 | G24: =E24*F24 -> 6992.3 | K24: =G24+J24 -> 6992.3 | L24: =H24+K24 -> 6992.3 | M24: =M23+K24-L24 -> 79033.75
A25: 21 | B25: 46163 | E25: 95 | F25: 99.89 | G25: =E25*F25 -> 9489.55 | K25: =G25+J25 -> 9489.55 | L25: =H25+K25 -> 9489.55 | M25: =M24+K25-L25 -> 79033.75
A26: 22 | B26: 46164 | E26: 70 | F26: 99.89 | G26: =E26*F26 -> 6992.3 | K26: =G26+J26 -> 6992.3 | L26: =H26+K26 -> 6992.3 | M26: =M25+K26-L26 -> 79033.75
A27: 23 | B27: 46165 | E27: 70 | F27: 99.89 | G27: =E27*F27 -> 6992.3 | K27: =G27+J27 -> 6992.3 | L27: =H27+K27 -> 6992.3 | M27: =M26+K27-L27 -> 79033.75
A28: 24 | B28: 46166 | G28: =E28*F28 -> 0 | K28: =G28+J28 -> 0 | L28: =H28+K28 -> 0 | M28: =M27+K28-L28 -> 79033.75
A29: 25 | B29: 46167 | E29: 70 | F29: 103.76 | G29: =E29*F29 -> 7263.2 | K29: =G29+J29 -> 7263.2 | L29: =H29+K29 -> 7263.2 | M29: =M28+K29-L29 -> 79033.75
A30: 26 | B30: 46168 | E30: 110 | F30: 103.76 | G30: =E30*F30 -> 11413.6 | K30: =G30+J30 -> 11413.6 | L30: =H30+K30 -> 11413.6 | M30: =M29+K30-L30 -> 79033.75
A31: 27 | B31: 46169 | G31: =E31*F31 -> 0 | K31: =G31+J31 -> 0 | L31: =H31+K31 -> 0 | M31: =M30+K31-L31 -> 79033.75
A32: 28 | B32: 46170 | G32: =E32*F32 -> 0 | K32: =G32+J32 -> 0 | L32: =H32+K32 -> 0 | M32: =M31+K32-L32 -> 79033.75
A33: 29 | B33: 46171 | E33: 35 | F33: 103.76 | G33: =E33*F33 -> 3631.6 | K33: =G33+J33 -> 3631.6 | L33: =H33+K33 -> 3631.6 | M33: =M32+K33-L33 -> 79033.75
B34: 46171 | E34: 200 | F34: 103.82 | G34: =E34*F34 -> 20764 | K34: =G34+J34 -> 20764 | M34: =M33+K34-L34 -> 99797.75
A35: 30 | B35: 46172 | K35: =G35+J35 -> 0 | M35: =M34+K35-L35 -> 99797.75
A36: 31 | B36: 46173 | M36: =M35+K36-L36 -> 99797.75
A37: 32 | B37: 46174
A38: 33 | B38: 46175
A39: 34 | B39: 46176
A40: 35
A41: 36
A42: 37
A43: 38 | O43: 2669494 | P43: =O43-M43 -> 2669494
E44: 0 | F44: 0 | G44: =E44*F44 -> 0 | J44: =H44*I44 -> 0 | K44: =G44+J44 -> 0 | M44: =M43+K44-L44 -> 0
E45: =SUM(E4:E43) -> 1414.96 | G45: =SUM(G4:G43) -> 140530.52 | H45: =SUM(H4:H43) -> 0 | J45: =SUM(J4:J43) -> 0 | K45: =SUM(K4:K43) -> 140530.52 | L45: =SUM(L4:L43) -> 119766.52
M54: 2408309
M55: 5327.86
M56: =M54-M55 -> 2402981.1

Sheet Khammam-1
A1: Divya laxmi ganapathi
A2: S.No | B2: Date | C2: GRN No | D2: Ind No/Bill No | E2: Diesel (Lts) | F2: Price | G2: Amount | H2: Petrol (Lts) | I2: Price | J2: Amount | K2: Total amount | L2: Amount paid | M2: As 0n Date | N2: Remarks
A3: Opening Balance | K3: 1769630.7 | M3: 1769630.7
A4: 1 | B4: 46143 | G4: =E4*F4 -> 0 | K4: =G4+J4 -> 0 | L4: 0 | M4: =M3+K4-L4 -> 1769630.7
A5: 2 | B5: 46144 | E5: 2700 | F5: 95.68 | G5: =E5*F5 -> 258336 | K5: =G5+J5 -> 258336 | L5: =H5+K5 -> 258336 | M5: =M4+K5-L5 -> 1769630.7
A6: 3 | B6: 46145 | E6: 2000 | F6: 95.68 | G6: =E6*F6 -> 191360 | J6: =H6*I6 -> 0 | K6: =G6+J6 -> 191360 | L6: =H6+K6 -> 191360 | M6: =M5+K6-L6 -> 1769630.7
A7: 4 | B7: 46146 | E7: 1500 | F7: 95.68 | G7: =E7*F7 -> 143520 | J7: =H7*I7 -> 0 | K7: =G7+J7 -> 143520 | L7: =H7+K7 -> 143520 | M7: =M6+K7-L7 -> 1769630.7
A8: 5 | B8: 46147 | E8: 2700 | F8: 95.68 | G8: =E8*F8 -> 258336 | J8: =H8*I8 -> 0 | K8: =G8+J8 -> 258336 | L8: =H8+K8 -> 258336 | M8: =M7+K8-L8 -> 1769630.7
A9: 6 | B9: 46148 | E9: 1400 | F9: 95.68 | G9: =E9*F9 -> 133952 | J9: =H9*I9 -> 0 | K9: =G9+J9 -> 133952 | L9: =H9+K9 -> 133952 | M9: =M8+K9-L9 -> 1769630.7
A10: 7 | B10: 46149 | G10: =E10*F10 -> 0 | J10: =H10*I10 -> 0 | K10: =G10+J10 -> 0 | L10: 0 | M10: =M9+K10-L10 -> 1769630.7
A11: 8 | B11: 46150 | E11: 2800 | F11: 95.68 | G11: =E11*F11 -> 267904 | J11: =H11*I11 -> 0 | K11: =G11+J11 -> 267904 | L11: 267904 | M11: =M10+K11-L11 -> 1769630.7
A12: 9 | B12: 46151 | G12: =E12*F12 -> 0 | J12: =H12*I12 -> 0 | K12: =G12+J12 -> 0 | L12: 0 | M12: =M11+K12-L12 -> 1769630.7
A13: 10 | B13: 46152 | E13: 2500 | F13: 95.68 | G13: =E13*F13 -> 239200 | J13: =H13*I13 -> 0 | K13: =G13+J13 -> 239200 | L13: =H13+K13 -> 239200 | M13: =M12+K13-L13 -> 1769630.7
A14: 11 | B14: 46153 | G14: =E14*F14 -> 0 | J14: =H14*I14 -> 0 | K14: =G14+J14 -> 0 | L14: 0 | M14: =M13+K14-L14 -> 1769630.7
A15: 12 | B15: 46154 | G15: =E15*F15 -> 0 | J15: =H15*I15 -> 0 | K15: =G15+J15 -> 0 | L15: 0 | M15: =M14+K15-L15 -> 1769630.7
A16: 13 | B16: 46155 | E16: 4875.88 | F16: 95.68 | G16: =E16*F16 -> 466524.2 | J16: =H16*I16 -> 0 | K16: =G16+J16 -> 466524.2 | L16: 466524 | M16: =M15+K16-L16 -> 1769630.9
A17: 14 | B17: 46156 | G17: =E17*F17 -> 0 | J17: =H17*I17 -> 0 | K17: =G17+J17 -> 0 | L17: 0 | M17: =M16+K17-L17 -> 1769630.9
A18: 15 | B18: 46157 | E18: 2728.93 | F18: 98.94 | G18: =E18*F18 -> 270000.33 | K18: =G18+J18 -> 270000.33 | L18: 270000 | M18: =M17+K18-L18 -> 1769631.2
A19: 16 | B19: 46158 | E19: 2800 | F19: 98.94 | G19: =E19*F19 -> 277032 | K19: =G19+J19 -> 277032 | L19: 0 | M19: =M18+K19-L19 -> 2046663.2
A20: 17 | B20: 46159 | E20: 2080.53 | F20: 98.94 | G20: =E20*F20 -> 205847.64 | K20: =G20+J20 -> 205847.64 | L20: 285000 | M20: =M19+K20-L20 -> 1967510.9
A21: 18 | B21: 46160 | E21: 2800 | F21: 98.94 | G21: =E21*F21 -> 277032 | K21: =G21+J21 -> 277032 | L21: 197880 | M21: =M20+K21-L21 -> 2046662.9
A22: 19 | B22: 46161 | G22: =E22*F22 -> 0 | K22: =G22+J22 -> 0 | L22: 0 | M22: =M21+K22-L22 -> 2046662.9
A23: 20 | B23: 46162 | E23: 2800 | F23: 99.93 | G23: =E23*F23 -> 279804 | K23: =G23+J23 -> 279804 | L23: 200000 | M23: =M22+K23-L23 -> 2126466.9
A24: 21 | B24: 46163 | E24: 2000 | F24: 99.93 | G24: =E24*F24 -> 199860 | K24: =G24+J24 -> 199860 | L24: 250000 | M24: =M23+K24-L24 -> 2076326.9
A25: 22 | B25: 46164 | G25: =E25*F25 -> 0 | K25: =G25+J25 -> 0 | L25: 0 | M25: =M24+K25-L25 -> 2076326.9
A26: 23 | B26: 46165 | G26: =E26*F26 -> 0 | K26: =G26+J26 -> 0 | L26: 0 | M26: =M25+K26-L26 -> 2076326.9
A27: 24 | B27: 46166 | E27: 2650 | F27: 100.92 | G27: =E27*F27 -> 267438 | K27: =G27+J27 -> 267438 | M27: =M26+K27-L27 -> 2343764.9 | O27: 250000 | P27: CASH DG Sir
A28: 25 | B28: 46167 | E28: 2000 | F28: 103.8 | G28: =E28*F28 -> 207600 | K28: =G28+J28 -> 207600 | L28: 0 | M28: =M27+K28-L28 -> 2551364.9
A29: 26 | B29: 46168 | E29: 2700 | F29: 103.8 | G29: =E29*F29 -> 280260 | K29: =G29+J29 -> 280260 | L29: 600000 | M29: =M28+K29-L29 -> 2231624.9
A30: 27 | B30: 46169 | G30: =E30*F30 -> 0 | K30: =G30+J30 -> 0 | L30: 0 | M30: =M29+K30-L30 -> 2231624.9
A31: 28 | B31: 46170 | E31: 1000 | F31: 103.8 | G31: =E31*F31 -> 103800 | K31: =G31+J31 -> 103800 | L31: 120000 | M31: =M30+K31-L31 -> 2215424.9
A32: 29 | B32: 46171 | E32: 2000 | F32: 103.8 | G32: =E32*F32 -> 207600 | K32: =G32+J32 -> 207600 | L32: 0 | M32: =M31+K32-L32 -> 2423024.9
A33: 30 | B33: 46172 | G33: =E33*F33 -> 0 | K33: =G33+J33 -> 0 | L33: 0 | M33: =M32+K33-L33 -> 2423024.9
A34: 31 | B34: 46173 | E34: 2230 | F34: 103.8 | G34: =E34*F34 -> 231474 | K34: =G34+J34 -> 231474 | M34: =M33+K34-L34 -> 2654498.9 | O34: 156000 | P34: CASH DG Sir
A35: 32 | G35: =E35*F35 -> 0 | J35: =H35*I35 -> 0 | K35: =G35+J35 -> 0 | L35: 0 | M35: =M34+K35-L35 -> 2654498.9
A36: 33 | G36: =E36*F36 -> 0 | J36: =H36*I36 -> 0 | K36: =G36+J36 -> 0 | L36: 0
A37: 34 | G37: =E37*F37 -> 0 | J37: =H37*I37 -> 0 | K37: =G37+J37 -> 0
E38: =SUM(E3:E37) -> 48265.34 | G38: =SUM(G3:G37) -> 4766880.2 | H38: =SUM(H3:H37) -> 0 | J38: =SUM(J3:J37) -> 0 | K38: =SUM(K4:K37) -> 4766880.2 | L38: =SUM(L3:L37) -> 3882012

Sheet Khammam-2
A1: Jayasai union bunk
A2: S.No | B2: Date | C2: GRN No | D2: Ind No/Bill No | E2: Diesel (Lts) | F2: Price | G2: Amount | H2: Petrol (Lts) | I2: Price | J2: Amount | K2: Total amount | L2: Amount paid | M2: As 0n Date | N2: Remarks
A3: Opening Balance | K3: 3725653 | M3: 3725653
A4: 1 | B4: 46143 | G4: =E4*F4 -> 0 | J4: =H4*I4 -> 0 | K4: =G4+J4 -> 0 | M4: =M3+K4-L4 -> 3725653 | O4: =O3+M4-N4 -> 3725653
A5: 2 | B5: 46144 | G5: =E5*F5 -> 0 | H5: 100 | I5: 107.49 | J5: =H5*I5 -> 10749 | K5: =G5+J5 -> 10749 | M5: =M4+K5-L5 -> 3736402
A6: 3 | B6: 46145 | G6: =E6*F6 -> 0 | J6: =H6*I6 -> 0 | K6: =G6+J6 -> 0 | M6: =M5+K6-L6 -> 3736402
A7: 4 | B7: 46146 | G7: =E7*F7 -> 0 | J7: =H7*I7 -> 0 | K7: =G7+J7 -> 0 | M7: =M6+K7-L7 -> 3736402
A8: 5 | B8: 46147 | G8: =E8*F8 -> 0 | H8: 95 | I8: 107.49 | J8: =H8*I8 -> 10211.55 | K8: =G8+J8 -> 10211.55 | M8: =M7+K8-L8 -> 3746613.5 | O8: 12802499
A9: 6 | B9: 46148 | E9: 2994.21 | F9: 95.71 | G9: =E9*F9 -> 286575.84 | H9: 80 | I9: 107.49 | J9: =H9*I9 -> 8599.2 | K9: =G9+J9 -> 295175.04 | M9: =M8+K9-L9 -> 4041788.5
A10: 7 | B10: 46149 | E10: 1744.02 | F10: 95.71 | G10: =E10*F10 -> 166920.15 | J10: =H10*I10 -> 0 | K10: =G10+J10 -> 166920.15 | M10: =M9+K10-L10 -> 4208708.7
A11: 8 | B11: 46150 | E11: 1742.41 | F11: 95.71 | G11: =E11*F11 -> 166766.06 | H11: 60 | I11: 107.49 | J11: =H11*I11 -> 6449.4 | K11: =G11+J11 -> 173215.46 | M11: =M10+K11-L11 -> 4381924.2
A12: 9 | B12: 46151 | E12: 2760.94 | F12: 95.71 | G12: =E12*F12 -> 264249.57 | J12: =H12*I12 -> 0 | K12: =G12+J12 -> 264249.57 | M12: =M11+K12-L12 -> 4646173.7 | O12: 166834
A13: 10 | B13: 46152 | E13: 747 | F13: 95.71 | G13: =E13*F13 -> 71495.37 | J13: =H13*I13 -> 0 | K13: =G13+J13 -> 71495.37 | M13: =M12+K13-L13 -> 4717669.1 | O13: =K10-O12 -> 86.1542
A14: 11 | B14: 46153 | E14: 2145.86 | F14: 95.71 | G14: =E14*F14 -> 205380.26 | H14: 80 | I14: 107.49 | J14: =H14*I14 -> 8599.2 | K14: =G14+J14 -> 213979.46 | M14: =M13+K14-L14 -> 4931648.6
A15: 12 | B15: 46154 | E15: 2517.61 | F15: 95.71 | G15: =E15*F15 -> 240960.45 | J15: =H15*I15 -> 0 | K15: =G15+J15 -> 240960.45 | M15: =M14+K15-L15 -> 5172609
A16: 13 | B16: 46155 | E16: 3076.46 | F16: 95.71 | G16: =E16*F16 -> 294447.99 | H16: 85 | I16: 107.49 | J16: =H16*I16 -> 9136.65 | K16: =G16+J16 -> 303584.64 | M16: =M15+K16-L16 -> 5476193.6
A17: 14 | B17: 46156 | E17: 1699.85 | F17: 95.71 | G17: =E17*F17 -> 162692.64 | J17: =H17*I17 -> 0 | K17: =G17+J17 -> 162692.64 | M17: =M16+K17-L17 -> 5638886.3
A18: 15 | B18: 46157 | E18: 1878.23 | F18: 98.97 | G18: =E18*F18 -> 185888.42 | H18: 80 | I18: 110.88 | J18: =H18*I18 -> 8870.4 | K18: =G18+J18 -> 194758.82 | M18: =M17+K18-L18 -> 5833645.1
A19: 16 | B19: 46158 | G19: =E19*F19 -> 0 | J19: =H19*I19 -> 0 | K19: =G19+J19 -> 0 | M19: =M18+K19-L19 -> 5833645.1
A20: 17 | B20: 46159 | G20: =E20*F20 -> 0 | J20: =H20*I20 -> 0 | K20: =G20+J20 -> 0 | M20: =M19+K20-L20 -> 5833645.1
A21: 18 | B21: 46160 | E21: 1200 | F21: 98.97 | G21: =E21*F21 -> 118764 | H21: 80 | I21: 110.88 | J21: =H21*I21 -> 8870.4 | K21: =G21+J21 -> 127634.4 | M21: =M20+K21-L21 -> 5961279.5
A22: 19 | B22: 46161 | E22: 1500 | F22: 99.95 | G22: =E22*F22 -> 149925 | J22: =H22*I22 -> 0 | K22: =G22+J22 -> 149925 | M22: =M21+K22-L22 -> 6111204.5
A23: 20 | B23: 46162 | E23: 3001 | F23: 99.95 | G23: =E23*F23 -> 299949.95 | H23: 95 | I23: 111.87 | J23: =H23*I23 -> 10627.65 | K23: =G23+J23 -> 310577.6 | M23: =M22+K23-L23 -> 6421782.1
A24: 21 | B24: 46163 | E24: 1670 | F24: 99.95 | G24: =E24*F24 -> 166916.5 | J24: =H24*I24 -> 0 | K24: =G24+J24 -> 166916.5 | M24: =M23+K24-L24 -> 6588698.6
A25: 22 | B25: 46164 | E25: 2466.77 | F25: 99.95 | G25: =E25*F25 -> 246553.66 | H25: 50 | I25: 111.87 | J25: =H25*I25 -> 5593.5 | K25: =G25+J25 -> 252147.16 | M25: =M24+K25-L25 -> 6840845.8
A26: 23 | B26: 46165 | E26: 2598.69 | F26: 100.94 | G26: =E26*F26 -> 262311.77 | J26: =H26*I26 -> 0 | K26: =G26+J26 -> 262311.77 | M26: =M25+K26-L26 -> 7103157.5
A27: 24 | B27: 46166 | G27: =E27*F27 -> 0 | J27: =H27*I27 -> 0 | K27: =G27+J27 -> 0 | M27: =M26+K27-L27 -> 7103157.5
A28: 25 | B28: 46167 | E28: 3590.27 | F28: 103.82 | G28: =E28*F28 -> 372741.83 | H28: 100 | I28: 115.72 | J28: =H28*I28 -> 11572 | K28: =G28+J28 -> 384313.83 | M28: =M27+K28-L28 -> 7487471.4
A29: 26 | B29: 46168 | E29: 1239.03 | F29: 103.82 | G29: =E29*F29 -> 128636.09 | J29: =H29*I29 -> 0 | K29: =G29+J29 -> 128636.09 | M29: =M28+K29-L29 -> 7616107.5
A30: 27 | B30: 46169 | E30: 2313.22 | F30: 103.82 | G30: =E30*F30 -> 240158.5 | H30: 55 | I30: 115.72 | J30: =H30*I30 -> 6364.6 | K30: =G30+J30 -> 246523.1 | M30: =M29+K30-L30 -> 7862630.6
A31: 28 | B31: 46170 | E31: 2138.07 | F31: 103.82 | G31: =E31*F31 -> 221974.43 | J31: =H31*I31 -> 0 | K31: =G31+J31 -> 221974.43 | M31: =M30+K31-L31 -> 8084605
A32: 29 | B32: 46171 | E32: 1662.76 | F32: 103.82 | G32: =E32*F32 -> 172627.74 | H32: 80 | I32: 115.72 | J32: =H32*I32 -> 9257.6 | K32: =G32+J32 -> 181885.34 | M32: =M31+K32-L32 -> 8266490.3
A33: 30 | B33: 46172 | E33: 1073.79 | F33: 103.82 | G33: =E33*F33 -> 111480.88 | J33: =H33*I33 -> 0 | K33: =G33+J33 -> 111480.88 | M33: =M32+K33-L33 -> 8377971.2
A34: 31 | B34: 46173 | E34: 3295.38 | F34: 103.82 | G34: =E34*F34 -> 342126.35 | J34: =H34*I34 -> 0 | K34: =G34+J34 -> 342126.35 | M34: =M33+K34-L34 -> 8720097.6
E36: =SUM(E4:E34) -> 49055.57 | G36: =SUM(G4:G34) -> 4879543.5 | H36: =SUM(H4:H34) -> 1040 | J36: =SUM(J4:J34) -> 114901.15 | K36: =SUM(K4:K34) -> 4994444.6 | L36: =SUM(L4:L34) -> 0
M39: 4994360
M40: =K36-M39 -> 84.6152

Sheet Khammam-3
A1: JSASFuel Genie India Pvt.Ltd
A2: S.No | B2: Date | C2: GRN No | D2: Ind No/Bill No | E2: Diesel (Lts) | F2: Price | G2: Amount | H2: Petrol (Lts) | I2: Price | J2: Amount | K2: Total amount | L2: Amount paid | M2: As 0n Date | N2: Remarks
A3: Opening Balance | K3: 2572600.3 | M3: 2572600.3
A4: 1 | B4: 46143 | G4: =E4*F4 -> 0 | J4: =H4*I4 -> 0 | K4: =G4+J4 -> 0 | M4: =M3+K4-L4 -> 2572600.3
A5: 2 | B5: 46144 | G5: =E5*F5 -> 0 | J5: =H5*I5 -> 0 | K5: =G5+J5 -> 0 | M5: =M4+K5-L5 -> 2572600.3
A6: 3 | B6: 46145 | G6: =E6*F6 -> 0 | J6: =H6*I6 -> 0 | K6: =G6+J6 -> 0 | M6: =M5+K6-L6 -> 2572600.3
A7: 4 | B7: 46146 | G7: =E7*F7 -> 0 | J7: =H7*I7 -> 0 | K7: =G7+J7 -> 0 | L7: 1000000 | M7: =M6+K7-L7 -> 1572600.3
A8: 5 | B8: 46147 | G8: =E8*F8 -> 0 | J8: =H8*I8 -> 0 | K8: =G8+J8 -> 0 | M8: =M7+K8-L8 -> 1572600.3
A9: 6 | B9: 46148 | G9: =E9*F9 -> 0 | J9: =H9*I9 -> 0 | K9: =G9+J9 -> 0 | M9: =M8+K9-L9 -> 1572600.3
A10: 7 | B10: 46149 | G10: =E10*F10 -> 0 | J10: =H10*I10 -> 0 | K10: =G10+J10 -> 0 | M10: =M9+K10-L10 -> 1572600.3
A11: 8 | B11: 46150 | G11: =E11*F11 -> 0 | J11: =H11*I11 -> 0 | K11: =G11+J11 -> 0 | M11: =M10+K11-L11 -> 1572600.3
A12: 9 | B12: 46151 | G12: =E12*F12 -> 0 | J12: =H12*I12 -> 0 | K12: =G12+J12 -> 0 | M12: =M11+K12-L12 -> 1572600.3
A13: 10 | B13: 46152 | G13: =E13*F13 -> 0 | J13: =H13*I13 -> 0 | K13: =G13+J13 -> 0 | M13: =M12+K13-L13 -> 1572600.3
A14: 11 | B14: 46153 | G14: =E14*F14 -> 0 | J14: =H14*I14 -> 0 | K14: =G14+J14 -> 0 | M14: =M13+K14-L14 -> 1572600.3
A15: 12 | B15: 46154 | G15: =E15*F15 -> 0 | J15: =H15*I15 -> 0 | K15: =G15+J15 -> 0 | M15: =M14+K15-L15 -> 1572600.3
A16: 13 | B16: 46155 | G16: =E16*F16 -> 0 | J16: =H16*I16 -> 0 | K16: =G16+J16 -> 0 | M16: =M15+K16-L16 -> 1572600.3
A17: 14 | B17: 46156 | G17: =E17*F17 -> 0 | J17: =H17*I17 -> 0 | K17: =G17+J17 -> 0 | M17: =M16+K17-L17 -> 1572600.3
A18: 15 | B18: 46157 | G18: =E18*F18 -> 0 | J18: =H18*I18 -> 0 | K18: =G18+J18 -> 0 | M18: =M17+K18-L18 -> 1572600.3
A19: 16 | B19: 46158 | G19: =E19*F19 -> 0 | J19: =H19*I19 -> 0 | K19: =G19+J19 -> 0 | M19: =M18+K19-L19 -> 1572600.3
... A33: 30 | B33: 46172 | G33: =E33*F33 -> 0 | J33: =H33*I33 -> 0 | K33: =G33+J33 -> 0 | M33: =M32+K33-L33 -> 1572600.3
A34: 31 | G34: =E34*F34 -> 0 | J34: =H34*I34 -> 0 | K34: =G34+J34 -> 0 | M34: =M33+K34-L34 -> 1572600.3
E35: =SUM(E4:E34) -> 0 | G35: =SUM(G4:G34) -> 0 | H35: =SUM(H4:H34) -> 0 | J35: =SUM(J4:J34) -> 0 | K35: =SUM(K4:K34) -> 0 | L35: =SUM(L4:L34) -> 1000000

Sheet  Khammam&Cash
A1: Cash &Carry
A2: S.No | B2: Date | D2: Ind No/Bill No | E2: Diesel (Lts) | F2: Price | G2: Amount | H2: Petrol (Lts) | I2: Price | J2: Amount | K2: Total amount | L2: Amount paid | M2: As 0n Date | N2: Remarks
A3: Opening Balance | K3: 0 | M3: 0
A4: 1 | G4: =E4*F4 -> 0 | K4: =G4+J4 -> 0 | L4: 0 | M4: =M3+K4-L4 -> 0
A5: 2 | B5: 02.05.2026 | C5: Stambhadri Fuel Park (HP) | E5: 2800 | F5: 95.68 | G5: =E5*F5 -> 267904 | J5: =H5*I5 -> 0 | K5: =G5+J5 -> 267904 | L5: =H5+K5 -> 267904 | M5: =M4+K5-L5 -> 0
A6: 3 | B6: 04.05.2026 | C6: Sri Sri Sri Filling Station (HP) | E6: 2000 | F6: 95.68 | G6: =E6*F6 -> 191360 | J6: =H6*I6 -> 0 | K6: =G6+J6 -> 191360 | L6: 95680 | M6: =M5+K6-L6 -> 95680
A7: 4 | B7: 05.05.2026 | C7: Sri Sri Sri Filling Station (HP) | G7: =E7*F7 -> 0 | J7: =H7*I7 -> 0 | K7: =G7+J7 -> 0 | L7: 95680 | M7: =M6+K7-L7 -> 0
A8: 5 | B8: 05.05.2026 | C8: Stambhadri Fuel Park (HP) | E8: 2800 | F8: 95.68 | G8: =E8*F8 -> 267904 | J8: =H8*I8 -> 0 | K8: =G8+J8 -> 267904 | L8: =H8+K8 -> 267904 | M8: =M7+K8-L8 -> 0
A9: 6 | B9: 06.05.2026 | C9: Stambhadri Fuel Park (HP) | E9: 2800 | F9: 95.68 | G9: =E9*F9 -> 267904 | J9: =H9*I9 -> 0 | K9: =G9+J9 -> 267904 | L9: =H9+K9 -> 267904 | M9: =M8+K9-L9 -> 0
A10: 7 | B10: 07.05.2026 | C10: Stambhadri Fuel Park (HP) | E10: 2597.199 | F10: 95.68 | G10: =E10*F10 -> 248500 | J10: =H10*I10 -> 0 | K10: =G10+J10 -> 248500 | L10: =H10+K10 -> 248500 | M10: =M9+K10-L10 -> 0
A11: 8 | B11: 09.05.2026 | C11: Stambhadri Fuel Park (HP) | E11: 2800 | F11: 95.68 | G11: =E11*F11 -> 267904 | J11: =H11*I11 -> 0 | K11: =G11+J11 -> 267904 | L11: =H11+K11 -> 267904 | M11: =M10+K11-L11 -> 0
A12: 9 | B12: 12.05.2026 | C12: Stambhadri Fuel Park (HP) | E12: 3020 | F12: 95.68 | G12: =E12*F12 -> 288953.6 | J12: =H12*I12 -> 0 | K12: =G12+J12 -> 288953.6 | L12: =H12+K12 -> 288953.6 | M12: =M11+K12-L12 -> 0
A13: 10 | B13: 46160 | C13: Stambhadri Fuel Park (HP) | E13: 1021.28 | F13: 98.94 | G13: =E13*F13 -> 101045.44 | J13: =H13*I13 -> 0 | K13: =G13+J13 -> 101045.44 | L13: =H13+K13 -> 101045.44 | M13: =M12+K13-L13 -> 0
A14: 11 | B14: 46163 | C14: Sri Sri Sri Filling Station (HPCL) | E14: 500 | F14: 99.93 | G14: =E14*F14 -> 49965 | J14: =H14*I14 -> 0 | K14: =G14+J14 -> 49965 | L14: =H14+K14 -> 49965 | M14: =M13+K14-L14 -> 0
A15: 12 | B15: 46170 | C15: Stambhadri Fuel Park (HPCL) | E15: 1200 | F15: 103.8 | G15: =E15*F15 -> 124560 | J15: =H15*I15 -> 0 | K15: =G15+J15 -> 124560 | L15: =H15+K15 -> 124560 | M15: =M14+K15-L15 -> 0
A16: 13 | B16: 46170 | C16: Sri Sri Sri Filling Station (HPCL) | E16: 700 | F16: 103.8 | G16: =E16*F16 -> 72660 | J16: =H16*I16 -> 0 | K16: =G16+J16 -> 72660 | L16: =H16+K16 -> 72660 | M16: =M15+K16-L16 -> 0
A17: 14 | G17: =E17*F17 -> 0 | J17: =H17*I17 -> 0 | K17: =G17+J17 -> 0 | L17: 0 | M17: =M16+K17-L17 -> 0
A18: 15 | G18: =E18*F18 -> 0 | J18: =H18*I18 -> 0 | K18: =G18+J18 -> 0 | L18: 0 | M18: =M17+K18-L18 -> 0
A19: 16 | G19: =E19*F19 -> 0 | J19: =H19*I19 -> 0 | K19: =G19+J19 -> 0 | L19: 0 | M19: =M18+K19-L19 -> 0
A20: 17 | G20: =E20*F20 -> 0 | J20: =H20*I20 -> 0 | K20: =G20+J20 -> 0 | L20: 0 | M20: =M19+K20-L20 -> 0
A21: 18 | G21: =E21*F21 -> 0 | J21: =H21*I21 -> 0 | K21: =G21+J21 -> 0 | L21: 0 | M21: =M20+K21-L21 -> 0
A22: 19 | G22: =E22*F22 -> 0 | J22: =H22*I22 -> 0 | K22: =G22+J22 -> 0 | L22: 0 | M22: =M21+K22-L22 -> 0
A23: 20 | G23: =E23*F23 -> 0 | J23: =H23*I23 -> 0 | K23: =G23+J23 -> 0 | L23: 0 | M23: =M22+K23-L23 -> 0
A24: 21 | G24: =E24*F24 -> 0 | J24: =H24*I24 -> 0 | K24: =G24+J24 -> 0 | L24: =H24+K24 -> 0 | M24: =M23+K24-L24 -> 0
A25: 22 | G25: =E25*F25 -> 0 | J25: =H25*I25 -> 0 | K25: =G25+J25 -> 0 | L25: =H25+K25 -> 0 | M25: =M24+K25-L25 -> 0
A26: 23 | G26: =E26*F26 -> 0 | J26: =H26*I26 -> 0 | K26: =G26+J26 -> 0 | L26: =H26+K26 -> 0 | M26: =M25+K26-L26 -> 0
A27: 24 | G27: =E27*F27 -> 0 | K27: =G27+J27 -> 0 | L27: =H27+K27 -> 0 | M27: =M26+K27-L27 -> 0
A28: 25 | G28: =E28*F28 -> 0 | J28: =H28*I28 -> 0 | K28: =G28+J28 -> 0 | L28: =H28+K28 -> 0 | M28: =M26+K28-L28 -> 0
A29: 26 | G29: =E29*F29 -> 0 | J29: =H29*I29 -> 0 | K29: =G29+J29 -> 0 | L29: =H29+K29 -> 0 | M29: =M28+K29-L29 -> 0 | O29: 354016 paid to dted 24.04.2026
A30: 27 | G30: =E30*F30 -> 0 | J30: =H30*I30 -> 0 | K30: =G30+J30 -> 0 | L30: =H30+K30 -> 0 | M30: =M29+K30-L30 -> 0
A31: 28 | G31: =E31*F31 -> 0 | J31: =H31*I31 -> 0 | K31: =G31+J31 -> 0 | L31: =H31+K31 -> 0 | M31: =M30+K31-L31 -> 0
A32: 29 | G32: =E32*F32 -> 0 | J32: =H32*I32 -> 0 | K32: =G32+J32 -> 0 | L32: =H32+K32 -> 0 | M32: =M31+K32-L32 -> 0
A33: 30 | G33: =E33*F33 -> 0 | J33: =H33*I33 -> 0 | K33: =G33+J33 -> 0 | L33: =H33+K33 -> 0 | M33: =M32+K33-L33 -> 0
A34: 31 | G34: =E34*F34 -> 0 | J34: =H34*I34 -> 0 | K34: =G34+J34 -> 0 | L34: =H34+K34 -> 0 | M34: =M33+K34-L34 -> 0
A35: 32 | G35: =E35*F35 -> 0 | K35: =G35+J35 -> 0 | L35: =H35+K35 -> 0 | M35: =M34+K35-L35 -> 0
A36: 33 | G36: =E36*F36 -> 0 | J36: =H36*I36 -> 0 | K36: =G36+J36 -> 0 | L36: =H36+K36 -> 0 | M36: =M35+K36-L36 -> 0
A37: 34 | G37: =E37*F37 -> 0 | J37: =H37*I37 -> 0 | K37: =G37+J37 -> 0 | L37: =H37+K37 -> 0 | M37: =M36+K37-L37 -> 0
G38: =E38*F38 -> 0 | K38: =G38+J38 -> 0 | L38: =H38+K38 -> 0 | M38: =M37+K38-L38 -> 0
G39: =E39*F39 -> 0 | K39: =G39+J39 -> 0 | L39: =H39+K39 -> 0 | M39: =M38+K39-L39 -> 0
G40: =E40*F40 -> 0 | K40: =G40+J40 -> 0 | L40: =H40+K40 -> 0 | M40: =M39+K40-L40 -> 0
M41: =M40+K41-L41 -> 0
A45: 35 | G45: =E45*F45 -> 0 | J45: =H45*I45 -> 0 | K45: =G45+J45 -> 0
E46: =SUM(E3:E45) -> 22238.479 | G46: =SUM(G3:G45) -> 2148660 | H46: =SUM(H3:H45) -> 0 | J46: =SUM(J3:J45) -> 0 | K46: =SUM(K4:K45) -> 2148660 | L46: =SUM(L3:L45) -> 2148660

Sheet Jadcherla-3
A1: JSASFuel Genie India Pvt.Ltd
A2: S.No | B2: Date | C2: GRN No | D2: Ind no/Bill No | E2: Diesel (Lts) | F2: Price | G2: Amount | H2: Petrol (Lts) | I2: Price | J2: Amount | K2: Total amount | L2: Amount paid | M2: As on Date | N2: Remarks
A3: Opening Balance | M3: 1313281.7
A4: 1 | B4: 46143 | G4: =E4*F4 -> 0 | J4: =H4*I4 -> 0 | K4: =G4+J4 -> 0 | L4: 0 | M4: =+M3+K4-L4 -> 1313281.7
A5: 2 | B5: 46144 | G5: =E5*F5 -> 0 | J5: =H5*I5 -> 0 | K5: =G5+J5 -> 0 | L5: 0 | M5: =+M4+K5-L5 -> 1313281.7
A6: 3 | B6: 46145 | G6: =E6*F6 -> 0 | J6: =H6*I6 -> 0 | K6: =G6+J6 -> 0 | L6: 0 | M6: =+M5+K6-L6 -> 1313281.7 | O6: 8032614 | P6: 2453209.4 | Q6: =SUM(O6:P6) -> 10485823
A7: 4 | B7: 46146 | G7: =E7*F7 -> 0 | J7: =H7*I7 -> 0 | K7: =G7+J7 -> 0 | L7: 0 | M7: =+M6+K7-L7 -> 1313281.7
A8: 5 | B8: 46147 | G8: =E8*F8 -> 0 | J8: =H8*I8 -> 0 | K8: =G8+J8 -> 0 | L8: 0 | M8: =+M7+K8-L8 -> 1313281.7
A9: 6 | B9: 46148 | G9: =E9*F9 -> 0 | J9: =H9*I9 -> 0 | K9: =G9+J9 -> 0 | L9: 0 | M9: =+M8+K9-L9 -> 1313281.7
A10: 7 | B10: 46149 | G10: =E10*F10 -> 0 | J10: =H10*I10 -> 0 | K10: =G10+J10 -> 0 | L10: 0 | M10: =+M9+K10-L10 -> 1313281.7 | R10: 700
A11: 8 | B11: 46150 | G11: =E11*F11 -> 0 | J11: =H11*I11 -> 0 | K11: =G11+J11 -> 0 | L11: 0 | M11: =+M10+K11-L11 -> 1313281.7 | S11: 5000
A12: 9 | B12: 46151 | G12: =E12*F12 -> 0 | J12: =H12*I12 -> 0 | K12: =G12+J12 -> 0 | L12: 0 | M12: =+M11+K12-L12 -> 1313281.7 | S12: 1500
A13: 10 | B13: 46152 | G13: =E13*F13 -> 0 | J13: =H13*I13 -> 0 | K13: =G13+J13 -> 0 | L13: 0 | M13: =+M12+K13-L13 -> 1313281.7 | S13: 500
A14: 11 | B14: 46153 | G14: =E14*F14 -> 0 | J14: =H14*I14 -> 0 | K14: =G14+J14 -> 0 | L14: 0 | M14: =+M13+K14-L14 -> 1313281.7
A15: 12 | B15: 46154 | G15: =E15*F15 -> 0 | J15: =H15*I15 -> 0 | K15: =G15+J15 -> 0 | L15: 0 | M15: =+M14+K15-L15 -> 1313281.7
A16: 13 | B16: 46155 | G16: =E16*F16 -> 0 | J16: =H16*I16 -> 0 | K16: =G16+J16 -> 0 | L16: 0 | M16: =+M15+K16-L16 -> 1313281.7
A17: 14 | B17: 46156 | G17: =E17*F17 -> 0 | J17: =H17*I17 -> 0 | K17: =G17+J17 -> 0 | L17: 0 | M17: =+M16+K17-L17 -> 1313281.7
A18: 15 | B18: 46157 | G18: =E18*F18 -> 0 | J18: =H18*I18 -> 0 | K18: =G18+J18 -> 0 | L18: 0 | M18: =+M17+K18-L18 -> 1313281.7
A19: 16 | B19: 46158 | G19: =E19*F19 -> 0 | J19: =H19*I19 -> 0 | K19: =G19+J19 -> 0 | L19: 0 | M19: =+M18+K19-L19 -> 1313281.7
A20: 17 | B20: 46159 | G20: =E20*F20 -> 0 | J20: =H20*I20 -> 0 | K20: =G20+J20 -> 0 | L20: 0 | M20: =+M19+K20-L20 -> 1313281.7
A21: 18 | B21: 46160 | G21: =E21*F21 -> 0 | J21: =H21*I21 -> 0 | K21: =G21+J21 -> 0 | L21: 0 | M21: =+M20+K21-L21 -> 1313281.7
A22: 19 | B22: 46161 | G22: =E22*F22 -> 0 | J22: =H22*I22 -> 0 | K22: =G22+J22 -> 0 | L22: 0 | M22: =+M21+K22-L22 -> 1313281.7
A23: 20 | B23: 46162 | G23: =E23*F23 -> 0 | J23: =H23*I23 -> 0 | K23: =G23+J23 -> 0 | L23: 0 | M23: =+M22+K23-L23 -> 1313281.7
A24: 21 | B24: 46163 | G24: =E24*F24 -> 0 | J24: =H24*I24 -> 0 | K24: =G24+J24 -> 0 | L24: 0 | M24: =+M23+K24-L24 -> 1313281.7
A25: 22 | B25: 46164 | G25: =E25*F25 -> 0 | J25: =H25*I25 -> 0 | K25: =G25+J25 -> 0 | L25: 0 | M25: =+M24+K25-L25 -> 1313281.7
... A31: 28 | B31: 46170 | G31: =E31*F31 -> 0 | J31: =H31*I31 -> 0 | K31: =G31+J31 -> 0 | L31: 0 | M31: =+M30+K31-L31 -> 1313281.7
A32: 29 | B32: 46171 | G32: =E32*F32 -> 0 | J32: =H32*I32 -> 0 | K32: =G32+J32 -> 0 | M32: =+M31+K32-L32 -> 1313281.7
A33: 30 | B33: 46172 | G33: =E33*F33 -> 0 | J33: =H33*I33 -> 0 | K33: =G33+J33 -> 0 | M33: =+M32+K33-L33 -> 1313281.7
A34: 31 | G34: =E34*F34 -> 0 | H34: 0 | I34: 0 | J34: =H34*I34 -> 0 | K34: =G34+J34 -> 0 | L34: 0 | M34: =+M33+K34-L34 -> 1313281.7
E35: =SUM(E4:E34) -> 0 | G35: =SUM(G4:G34) -> 0 | H35: =SUM(H4:H34) -> 0 | J35: =SUM(J4:J34) -> 0 | K35: =SUM(K4:K34) -> 0 | L35: =SUM(L4:L34) -> 0
F38: /

Sheet Jadcherla-4
A1: Shree Poornima F/S
A2: S.No | B2: Date | C2: GRN No | D2: Ind No/Bill No | E2: Diesel (Lts) | F2: Price | G2: Amount | H2: Petrol (Lts) | I2: Price | J2: Amount | K2: Total amount | L2: Amount paid | M2: As on date | N2: Remarks
A3: Opening Balance | M3: 3523.2
A4: 1 | B4: 46143 | G4: =E4*F4 -> 0 | J4: =H4*I4 -> 0 | K4: =G4+J4 -> 0 | L4: 0 | M4: =M3+K4-L4 -> 3523.2
A5: 2 | B5: 46144 | G5: =E5*F5 -> 0 | H5: 40 | I5: 108.1 | J5: =H5*I5 -> 4324 | K5: =G5+J5 -> 4324 | L5: 0 | M5: =M4+K5-L5 -> 7847.2
A6: 3 | B6: 46145 | G6: =E6*F6 -> 0 | J6: =H6*I6 -> 0 | K6: =G6+J6 -> 0 | L6: 0 | M6: =M5+K6-L6 -> 7847.2
A7: 4 | B7: 46146 | G7: =E7*F7 -> 0 | J7: =H7*I7 -> 0 | K7: =G7+J7 -> 0 | L7: 0 | M7: =M6+K7-L7 -> 7847.2
A8: 5 | B8: 46147 | G8: =E8*F8 -> 0 | J8: =H8*I8 -> 0 | K8: =G8+J8 -> 0 | L8: 0 | M8: =M7+K8-L8 -> 7847.2
A9: 6 | B9: 46148 | G9: =E9*F9 -> 0 | J9: =H9*I9 -> 0 | K9: =G9+J9 -> 0 | L9: 0 | M9: =M8+K9-L9 -> 7847.2
A10: 7 | B10: 46149 | G10: =E10*F10 -> 0 | J10: =H10*I10 -> 0 | K10: =G10+J10 -> 0 | L10: 0 | M10: =M9+K10-L10 -> 7847.2
A11: 8 | B11: 46150 | G11: =E11*F11 -> 0 | J11: =H11*I11 -> 0 | K11: =G11+J11 -> 0 | L11: 0 | M11: =M10+K11-L11 -> 7847.2
A12: 9 | B12: 46151 | G12: =E12*F12 -> 0 | J12: =H12*I12 -> 0 | K12: =G12+J12 -> 0 | L12: 0 | M12: =M11+K12-L12 -> 7847.2
A13: 10 | B13: 46152 | G13: =E13*F13 -> 0 | J13: =H13*I13 -> 0 | K13: =G13+J13 -> 0 | L13: 0 | M13: =M12+K13-L13 -> 7847.2
A14: 11 | B14: 46153 | G14: =E14*F14 -> 0 | J14: =H14*I14 -> 0 | K14: =G14+J14 -> 0 | L14: 0 | M14: =M13+K14-L14 -> 7847.2
A15: 12 | B15: 46154 | E15: 500 | F15: 96.3 | G15: =E15*F15 -> 48150 | H15: 36 | I15: 108.1 | J15: =H15*I15 -> 3891.6 | K15: =G15+J15 -> 52041.6 | L15: 48150 | M15: =M14+K15-L15 -> 11738.8
A16: 13 | B16: 46155 | E16: 500 | F16: 96.3 | G16: =E16*F16 -> 48150 | J16: =H16*I16 -> 0 | K16: =G16+J16 -> 48150 | L16: 48150 | M16: =M15+K16-L16 -> 11738.8
A17: 14 | B17: 46156 | G17: =E17*F17 -> 0 | J17: =H17*I17 -> 0 | K17: =G17+J17 -> 0 | L17: 0 | M17: =M16+K17-L17 -> 11738.8
A18: 15 | B18: 46157 | G18: =E18*F18 -> 0 | J18: =H18*I18 -> 0 | K18: =G18+J18 -> 0 | L18: 0 | M18: =M17+K18-L18 -> 11738.8
A19: 16 | B19: 46158 | E19: 0 | F19: 0 | G19: 0 | H19: 0 | I19: 0 | J19: 0 | K19: 0 | L19: 0 | M19: =M18+K19-L19 -> 11738.8
A20: 17 | B20: 46159 | G20: =E20*F20 -> 0 | J20: =H20*I20 -> 0 | K20: =G20+J20 -> 0 | L20: 0 | M20: =M19+K20-L20 -> 11738.8
A21: 18 | B21: 46160 | G21: =E21*F21 -> 0 | J21: =H21*I21 -> 0 | K21: =G21+J21 -> 0 | L21: 0 | M21: =M20+K21-L21 -> 11738.8
A22: 19 | B22: 46161 | G22: =E22*F22 -> 0 | J22: =H22*I22 -> 0 | K22: =G22+J22 -> 0 | L22: 0 | M22: =M21+K22-L22 -> 11738.8
A23: 20 | B23: 46162 | G23: =E23*F23 -> 0 | J23: =H23*I23 -> 0 | K23: =G23+J23 -> 0 | L23: 0 | M23: =M22+K23-L23 -> 11738.8
A24: 21 | B24: 46163 | E24: 0 | F24: 100.67 | G24: =E24*F24 -> 0 | H24: 36 | I24: 112.48 | J24: =H24*I24 -> 4049.28 | K24: =G24+J24 -> 4049.28 | L24: 0 | M24: =M23+K24-L24 -> 15788.08
A25: 22 | B25: 46164 | E25: 0 | F25: 0 | G25: =E25*F25 -> 0 | J25: =H25*I25 -> 0 | K25: =G25+J25 -> 0 | L25: 0 | M25: =M24+K25-L25 -> 15788.08
A26: 23 | B26: 46165 | E26: 0 | F26: 0 | G26: =E26*F26 -> 0 | J26: =H26*I26 -> 0 | K26: =G26+J26 -> 0 | L26: 0 | M26: =M25+K26-L26 -> 15788.08
A27: 24 | B27: 46166 | E27: 0 | F27: 0 | G27: =E27*F27 -> 0 | J27: =H27*I27 -> 0 | K27: =G27+J27 -> 0 | L27: 0 | M27: =M26+K27-L27 -> 15788.08
A28: 25 | B28: 46167 | E28: 0 | F28: 0 | G28: =E28*F28 -> 0 | J28: =H28*I28 -> 0 | K28: =G28+J28 -> 0 | L28: 0 | M28: =M27+K28-L28 -> 15788.08
A29: 26 | B29: 46168 | G29: =E29*F29 -> 0 | J29: =H29*I29 -> 0 | K29: =G29+J29 -> 0 | L29: 0 | M29: =M28+K29-L29 -> 15788.08
A30: 27 | B30: 46169 | G30: =E30*F30 -> 0 | J30: =H30*I30 -> 0 | K30: =G30+J30 -> 0 | L30: 0 | M30: =M29+K30-L30 -> 15788.08
A31: 28 | B31: 46170 | G31: =E31*F31 -> 0 | J31: =H31*I31 -> 0 | K31: =G31+J31 -> 0 | L31: 0 | M31: =M30+K31-L31 -> 15788.08
A32: 29 | B32: 46171 | G32: =E32*F32 -> 0 | J32: =H32*I32 -> 0 | K32: =G32+J32 -> 0 | L32: 0 | M32: =M31+K32-L32 -> 15788.08
A33: 30 | B33: 46172 | G33: =E33*F33 -> 0 | H33: 0 | I33: 0 | J33: =H33*I33 -> 0 | K33: =G33+J33 -> 0 | L33: 0 | M33: =M32+K33-L33 -> 15788.08
A34: 31 | B34: 46173 | G34: =E34*F34 -> 0 | J34: =H34*I34 -> 0 | K34: =G34+J34 -> 0 | M34: =M33+K34-L34 -> 15788.08
E35: =SUM(E4:E34) -> 1000 | G35: =SUM(G4:G34) -> 96300 | H35: =SUM(H4:H34) -> 112 | J35: =SUM(J4:J34) -> 12264.88 | K35: =SUM(K4:K34) -> 108564.88 | L35: =SUM(L4:L34) -> 96300

Sheet  Jadcherla
A1: Sai baba F/S
A2: S.No | B2: Date | C2: GRN No | D2: Ind No/Bill No | E2: Diesel (Lts) | F2: Price | G2: Amount | H2: Petrol (Lts) | I2: Price | J2: Amount | K2: Total amount | L2: Amount paid | M2: As on date | N2: Remarks
A3: Opening Balance | M3: 44630
A4: 1 | B4: 46143 | G4: =E4*F4 -> 0 | J4: =H4*I4 -> 0 | K4: =G4+J4 -> 0 | L4: 0 | M4: =M3+K4-L4 -> 44630
A5: 2 | B5: 46144 | G5: =E5*F5 -> 0 | J5: =H5*I5 -> 0 | K5: =G5+J5 -> 0 | L5: 0 | M5: =M4+K5-L5 -> 44630
A6: 3 | B6: 46145 | G6: =E6*F6 -> 0 | J6: =H6*I6 -> 0 | K6: =G6+J6 -> 0 | L6: 0 | M6: =M5+K6-L6 -> 44630
A7: 4 | B7: 46146 | E7: 1500 | F7: 96.42 | G7: =E7*F7 -> 144630 | J7: =H7*I7 -> 0 | K7: =G7+J7 -> 144630 | L7: =H7+K7 -> 144630 | M7: =M6+K7-L7 -> 44630
A8: 5 | B8: 46147 | G8: =E8*F8 -> 0 | J8: =H8*I8 -> 0 | K8: =G8+J8 -> 0 | L8: 0 | M8: =M7+K8-L8 -> 44630
A9: 6 | B9: 46148 | E9: 1037.12 | F9: 96.42 | G9: =E9*F9 -> 99999.11 | J9: =H9*I9 -> 0 | K9: =G9+J9 -> 99999.11 | L9: 100000 | M9: =M8+K9-L9 -> 44629.11
A10: 7 | B10: 46149 | G10: =E10*F10 -> 0 | J10: =H10*I10 -> 0 | K10: =G10+J10 -> 0 | L10: 0 | M10: =M9+K10-L10 -> 44629.11
A11: 8 | B11: 46150 | E11: 1000 | F11: 96.42 | G11: =E11*F11 -> 96420 | J11: =H11*I11 -> 0 | K11: =G11+J11 -> 96420 | L11: 0 | M11: =M10+K11-L11 -> 141049.11
A12: 9 | B12: 46151 | G12: =E12*F12 -> 0 | J12: =H12*I12 -> 0 | K12: =G12+J12 -> 0 | L12: 0 | M12: =M11+K12-L12 -> 141049.11
A13: 10 | B13: 46152 | G13: =E13*F13 -> 0 | J13: =H13*I13 -> 0 | K13: =G13+J13 -> 0 | L13: 0 | M13: =M12+K13-L13 -> 141049.11
A14: 11 | B14: 46153 | G14: =E14*F14 -> 0 | J14: =H14*I14 -> 0 | K14: =G14+J14 -> 0 | L14: 0 | M14: =M13+K14-L14 -> 141049.11
A15: 12 | B15: 46154 | G15: =E15*F15 -> 0 | J15: =H15*I15 -> 0 | K15: =G15+J15 -> 0 | L15: =H15+K15 -> 0 | M15: =M14+K15-L15 -> 141049.11
A16: 13 | B16: 46155 | G16: =E16*F16 -> 0 | J16: =H16*I16 -> 0 | K16: =G16+J16 -> 0 | L16: 141049 | M16: =M15+K16-L16 -> 0.1104
A17: 14 | B17: 46156 | E17: 500 | F17: 96.42 | G17: =E17*F17 -> 48210 | J17: =H17*I17 -> 0 | K17: =G17+J17 -> 48210 | L17: 0 | M17: =M16+K17-L17 -> 48210.11
A18: 15 | B18: 46157 | E18: 1000 | F18: 99.68 | G18: =E18*F18 -> 99680 | J18: =H18*I18 -> 0 | K18: =G18+J18 -> 99680 | L18: 48210 | M18: =M17+K18-L18 -> 99680.11 | N18: BT
A19: 16 | B19: 46158 | G19: =E19*F19 -> 0 | J19: =H19*I19 -> 0 | K19: =G19+J19 -> 0 | L19: 0 | M19: =M18+K19-L19 -> 99680.11
A20: 17 | B20: 46159 | G20: =E20*F20 -> 0 | J20: =H20*I20 -> 0 | K20: =G20+J20 -> 0 | L20: 0 | M20: =M19+K20-L20 -> 99680.11
A21: 18 | B21: 46160 | E21: 1500 | F21: 99.68 | G21: =E21*F21 -> 149520 | J21: =H21*I21 -> 0 | K21: =G21+J21 -> 149520 | L21: 100000 | M21: =M20+K21-L21 -> 149200.11 | N21: BT
A22: 19 | B22: 46161 | G22: =E22*F22 -> 0 | J22: =H22*I22 -> 0 | K22: =G22+J22 -> 0 | L22: 0 | M22: =M21+K22-L22 -> 149200.11
A23: 20 | B23: 46162 | G23: =E23*F23 -> 0 | J23: =H23*I23 -> 0 | K23: =G23+J23 -> 0 | L23: 0 | M23: =M22+K23-L23 -> 149200.11
A24: 21 | B24: 46163 | E24: 500 | F24: 100.67 | G24: =E24*F24 -> 50335 | J24: =H24*I24 -> 0 | K24: =G24+J24 -> 50335 | L24: 149000 | M24: =M23+K24-L24 -> 50535.11
A25: 22 | B25: 46164 | E25: 1000 | F25: 100.67 | G25: =E25*F25 -> 100670 | J25: =H25*I25 -> 0 | K25: =G25+J25 -> 100670 | L25: 0 | M25: =M24+K25-L25 -> 151205.11
A26: 23 | B26: 46165 | E26: 500 | F26: 101.66 | G26: =E26*F26 -> 50830 | J26: =H26*I26 -> 0 | K26: =G26+J26 -> 50830 | M26: =M25+K26-L26 -> 202035.11
A27: 24 | B27: 46166 | G27: =E27*F27 -> 0 | J27: =H27*I27 -> 0 | K27: =G27+J27 -> 0 | L27: 0 | M27: =M26+K27-L27 -> 202035.11
A28: 25 | B28: 46167 | E28: 1000 | F28: 104.54 | G28: =E28*F28 -> 104540 | J28: =H28*I28 -> 0 | K28: =G28+J28 -> 104540 | L28: 200000 | M28: =M27+K28-L28 -> 106575.11
A29: 26 | B29: 46168 | E29: 500 | F29: 104.54 | G29: =E29*F29 -> 52270 | J29: =H29*I29 -> 0 | K29: =G29+J29 -> 52270 | L29: 0 | M29: =M28+K29-L29 -> 158845.11
A30: 27 | B30: 46169 | G30: =E30*F30 -> 0 | J30: =H30*I30 -> 0 | K30: =G30+J30 -> 0 | L30: 40000 | M30: =M29+K30-L30 -> 118845.11
A31: 28 | B31: 46170 | E31: 500 | F31: 104.54 | G31: =E31*F31 -> 52270 | J31: =H31*I31 -> 0 | K31: =G31+J31 -> 52270 | L31: 0 | M31: =M30+K31-L31 -> 171115.11
A32: 29 | B32: 46171 | G32: =E32*F32 -> 0 | J32: =H32*I32 -> 0 | K32: =G32+J32 -> 0 | L32: 0 | M32: =M31+K32-L32 -> 171115.11
A33: 30 | B33: 46172 | G33: =E33*F33 -> 0 | H33: 0 | I33: 0 | J33: =H33*I33 -> 0 | K33: =G33+J33 -> 0 | L33: 0 | M33: =M32+K33-L33 -> 171115.11
A34: 31 | B34: 46173 | G34: =E34*F34 -> 0 | J34: =H34*I34 -> 0 | K34: =G34+J34 -> 0 | M34: =M33+K34-L34 -> 171115.11
E35: =SUM(E4:E34) -> 10537.12 | G35: =SUM(G4:G34) -> 1049374.1 | H35: =SUM(H4:H34) -> 0 | J35: =SUM(J4:J34) -> 0 | K35: =SUM(K4:K34) -> 1049374.1 | L35: =SUM(L4:L34) -> 922889

Sheet  Sangareddy-2
A1: Durga Bhavani F/S
A2: S.No | B2: Date | C2: GRN No | D2: Ind no/Bill No | E2: Diesel (Lts) | F2: Price | G2: Amount | H2: Petrol (Lts) | I2: Price | J2: Amount | K2: Total amount | L2: Amount paid | M2: As on Date | N2: Remarks
A3: Opening Balance | M3: 258995.39
A4: 1 | B4: 45778 | G4: =E4*F4 -> 0 | J4: =H4*I4 -> 0 | K4: =G4+J4 -> 0 | M4: =M3+K4-L4 -> 258995.39
A5: 2 | B5: 45779 | F5: 96.44 | G5: =E5*F5 -> 0 | H5: 47.1 | I5: 108.31 | J5: =H5*I5 -> 5101.401 | K5: =G5+J5 -> 5101.401 | M5: =M4+K5-L5 -> 264096.8
A6: 3 | B6: 45780 | G6: =E6*F6 -> 0 | J6: =H6*I6 -> 0 | K6: =G6+J6 -> 0 | M6: =M5+K6-L6 -> 264096.8
A7: 4 | B7: 45781 | G7: =E7*F7 -> 0 | J7: =H7*I7 -> 0 | K7: =G7+J7 -> 0 | L7: 250000 | M7: =M6+K7-L7 -> 14096.795
A8: 5 | B8: 45782 | G8: =E8*F8 -> 0 | H8: 5 | I8: 108.31 | J8: =H8*I8 -> 541.55 | K8: =G8+J8 -> 541.55 | M8: =M7+K8-L8 -> 14638.345
A9: 6 | B9: 45783 | E9: 810.61 | F9: 96.44 | G9: =E9*F9 -> 78175.228 | H9: 23 | I9: 108.31 | J9: =H9*I9 -> 2491.13 | K9: =G9+J9 -> 80666.358 | M9: =M8+K9-L9 -> 95304.704
A10: 7 | B10: 45784 | E10: 651.32 | F10: 96.44 | G10: =E10*F10 -> 62813.301 | H10: 5 | I10: 108.31 | J10: =H10*I10 -> 541.55 | K10: =G10+J10 -> 63354.851 | M10: =M9+K10-L10 -> 158659.55
A11: 8 | B11: 45785 | E11: 2.26 | F11: 96.44 | G11: =E11*F11 -> 217.9544 | H11: 5 | I11: 108.31 | J11: =H11*I11 -> 541.55 | K11: =G11+J11 -> 759.5044 | M11: =M10+K11-L11 -> 159419.06
A12: 9 | B12: 45786 | G12: =E12*F12 -> 0 | J12: =H12*I12 -> 0 | K12: =G12+J12 -> 0 | M12: =M11+K12-L12 -> 159419.06
A13: 10 | B13: 45787 | G13: =E13*F13 -> 0 | J13: =H13*I13 -> 0 | K13: =G13+J13 -> 0 | M13: =M12+K13-L13 -> 159419.06
A14: 11 | B14: 45788 | G14: =E14*F14 -> 0 | H14: 10 | I14: 108.31 | J14: =H14*I14 -> 1083.1 | K14: =G14+J14 -> 1083.1 | M14: =M13+K14-L14 -> 160502.16
A15: 12 | B15: 45789 | E15: 970.94 | F15: 96.44 | G15: =E15*F15 -> 93637.454 | H15: 15 | I15: 108.31 | J15: =H15*I15 -> 1624.65 | K15: =G15+J15 -> 95262.104 | M15: =M14+K15-L15 -> 255764.26
A16: 13 | B16: 45790 | E16: 908.44 | F16: 96.44 | G16: =E16*F16 -> 87609.954 | H16: 3 | I16: 108.31 | J16: =H16*I16 -> 324.93 | K16: =G16+J16 -> 87934.884 | M16: =M15+K16-L16 -> 343699.15
A17: 14 | B17: 45791 | E17: 646.95 | F17: 96.44 | G17: =E17*F17 -> 62391.858 | H17: 5 | I17: 108.31 | J17: =H17*I17 -> 541.55 | K17: =G17+J17 -> 62933.408 | M17: =M16+K17-L17 -> 406632.55
A18: 15 | B18: 45792 | E18: 163.58 | F18: 99.7 | G18: =E18*F18 -> 16308.926 | H18: 3 | I18: 111.71 | J18: =H18*I18 -> 335.13 | K18: =G18+J18 -> 16644.056 | L18: 300000 | M18: =M17+K18-L18 -> 123276.61
A19: 16 | B19: 45793 | E19: 763.64 | F19: 99.7 | G19: =E19*F19 -> 76134.908 | H19: 54.23 | I19: 111.71 | J19: =H19*I19 -> 6058.0333 | K19: =G19+J19 -> 82192.941 | M19: =M18+K19-L19 -> 205469.55
A20: 17 | B20: 45794 | E20: 447.36 | F20: 99.7 | G20: =E20*F20 -> 44601.792 | H20: 18 | I20: 111.71 | J20: =H20*I20 -> 2010.78 | K20: =G20+J20 -> 46612.572 | M20: =M19+K20-L20 -> 252082.12
A21: 18 | B21: 45795 | G21: =E21*F21 -> 0 | J21: =H21*I21 -> 0 | K21: =G21+J21 -> 0 | M21: =M20+K21-L21 -> 252082.12
A22: 19 | B22: 45796 | G22: =E22*F22 -> 0 | H22: 10 | I22: 112.69 | J22: =H22*I22 -> 1126.9 | K22: =G22+J22 -> 1126.9 | M22: =M21+K22-L22 -> 253209.02
A23: 20 | B23: 45797 | E23: 133.08 | F23: 100.69 | G23: =E23*F23 -> 13399.825 | J23: =H23*I23 -> 0 | K23: =G23+J23 -> 13399.825 | M23: =M22+K23-L23 -> 266608.85
A24: 21 | B24: 45798 | E24: 845.44 | F24: 100.69 | G24: =E24*F24 -> 85127.354 | H24: 5 | I24: 112.69 | J24: =H24*I24 -> 563.45 | K24: =G24+J24 -> 85690.804 | M24: =M23+K24-L24 -> 352299.65
A25: 22 | B25: 45799 | G25: =E25*F25 -> 0 | H25: 43.39 | I25: 112.69 | J25: =H25*I25 -> 4889.6191 | K25: =G25+J25 -> 4889.6191 | M25: =M24+K25-L25 -> 357189.27
A26: 23 | B26: 45800 | G26: =E26*F26 -> 0 | J26: =H26*I26 -> 0 | K26: =G26+J26 -> 0 | M26: =M25+K26-L26 -> 357189.27
A27: 24 | B27: 45801 | G27: =E27*F27 -> 0 | H27: 10 | I27: 112.69 | J27: =H27*I27 -> 1126.9 | K27: =G27+J27 -> 1126.9 | M27: =M26+K27-L27 -> 358316.17
A28: 25 | B28: 45802 | G28: =E28*F28 -> 0 | J28: 0 | K28: =G28+J28 -> 0 | L28: 250000 | M28: =M27+K28-L28 -> 108316.17
A29: 26 | B29: 45803 | G29: =E29*F29 -> 0 | J29: =H29*I29 -> 0 | K29: =G29+J29 -> 0 | M29: =M28+K29-L29 -> 108316.17
A30: 27 | B30: 45804 | G30: =E30*F30 -> 0 | J30: =H30*I30 -> 0 | K30: =G30+J30 -> 0 | M30: =M29+K30-L30 -> 108316.17
A31: 28 | B31: 45805 | G31: =E31*F31 -> 0 | J31: =H31*I31 -> 0 | K31: =G31+J31 -> 0 | M31: =M30+K31-L31 -> 108316.17
A32: 29 | B32: 45806 | G32: =E32*F32 -> 0 | J32: =H32*I32 -> 0 | K32: =G32+J32 -> 0 | M32: =M31+K32-L32 -> 108316.17
A33: 30 | B33: 45807 | G33: =E33*F33 -> 0 | J33: =H33*I33 -> 0 | K33: =G33+J33 -> 0 | L33: 0 | M33: =M32+K33-L33 -> 108316.17
A34: 31 | B34: 45808 | G34: =E34*F34 -> 0 | J34: =H34*I34 -> 0 | K34: =G34+J34 -> 0 | L34: 0 | M34: =M33+K34-L34 -> 108316.17
E35: =SUM(E4:E34) -> 6343.62 | G35: =SUM(G4:G34) -> 620418.55 | H35: =SUM(H4:H34) -> 261.72 | J35: =SUM(J4:J34) -> 28902.223 | K35: =SUM(K4:K34) -> 649320.78 | L35: =SUM(L4:L34) -> 800000

Sheet  Sangareddy-3
A1: SHIVA PARVATHI FILLING STATION SADASHIVPET
A2: S.No | B2: Date | C2: GRN No | D2: Ind no/Bill No | E2: Diesel (Lts) | F2: Price | G2: Amount | H2: Petrol (Lts) | I2: Price | J2: Amount | K2: Total amount | L2: Amount paid | M2: As on Date | N2: Remarks
A3: Opening Balance | M3: 163539.24
A4: 1 | B4: 45778 | E4: 600 | F4: 96.23 | G4: =E4*F4 -> 57738 | J4: =H4*I4 -> 0 | K4: =G4+J4 -> 57738 | L4: 0 | M4: =M3+K4-L4 -> 221277.24
A5: 2 | B5: 45779 | E5: 690 | F5: 96.23 | G5: =E5*F5 -> 66398.7 | J5: =H5*I5 -> 0 | K5: =G5+J5 -> 66398.7 | L5: 0 | M5: =M4+K5-L5 -> 287675.94
A6: 3 | B6: 45780 | E6: 690 | F6: 96.23 | G6: =E6*F6 -> 66398.7 | J6: =H6*I6 -> 0 | K6: =G6+J6 -> 66398.7 | L6: 0 | M6: =M5+K6-L6 -> 354074.64
A7: 4 | B7: 45781 | E7: 690 | F7: 96.23 | G7: =E7*F7 -> 66398.7 | J7: =H7*I7 -> 0 | K7: =G7+J7 -> 66398.7 | L7: 0 | M7: =M6+K7-L7 -> 420473.34
A8: 5 | B8: 45782 | E8: 0 | F8: 96.23 | G8: =E8*F8 -> 0 | J8: =H8*I8 -> 0 | K8: =G8+J8 -> 0 | L8: 0 | M8: =M7+K8-L8 -> 420473.34
A9: 6 | B9: 45783 | E9: 655 | F9: 96.23 | G9: =E9*F9 -> 63030.65 | J9: =H9*I9 -> 0 | K9: =G9+J9 -> 63030.65 | L9: 0 | M9: =M8+K9-L9 -> 483503.99
A10: 7 | B10: 45784 | E10: 655 | F10: 96.23 | G10: =E10*F10 -> 63030.65 | J10: =H10*I10 -> 0 | K10: =G10+J10 -> 63030.65 | L10: 0 | M10: =M9+K10-L10 -> 546534.64
A11: 8 | B11: 45785 | E11: 690 | F11: 96.23 | G11: =E11*F11 -> 66398.7 | J11: =H11*I11 -> 0 | K11: =G11+J11 -> 66398.7 | L11: 0 | M11: =M10+K11-L11 -> 612933.34
A12: 9 | B12: 45786 | E12: 728.04 | F12: 96.23 | G12: =E12*F12 -> 70059.289 | J12: =H12*I12 -> 0 | K12: =G12+J12 -> 70059.289 | L12: 0 | M12: =M11+K12-L12 -> 682992.63
A13: 10 | B13: 45787 | E13: 670 | F13: 96.23 | G13: =E13*F13 -> 64474.1 | J13: =H13*I13 -> 0 | K13: =G13+J13 -> 64474.1 | L13: 0 | M13: =M12+K13-L13 -> 747466.73
A14: 11 | B14: 45788 | E14: 690 | F14: 96.23 | G14: =E14*F14 -> 66398.7 | J14: =H14*I14 -> 0 | K14: =G14+J14 -> 66398.7 | L14: 500000 | M14: =M13+K14-L14 -> 313865.43 | N14: BT
A15: 12 | B15: 45789 | G15: =E15*F15 -> 0 | J15: =H15*I15 -> 0 | K15: =G15+J15 -> 0 | L15: 0 | M15: =M14+K15-L15 -> 313865.43
A16: 13 | B16: 45790 | G16: =E16*F16 -> 0 | J16: =H16*I16 -> 0 | K16: =G16+J16 -> 0 | L16: 0 | M16: =M15+K16-L16 -> 313865.43
A17: 14 | B17: 45791 | E17: 690 | F17: 96.23 | G17: =E17*F17 -> 66398.7 | J17: =H17*I17 -> 0 | K17: =G17+J17 -> 66398.7 | M17: =M16+K17-L17 -> 380264.13
A18: 15 | B18: 45792 | G18: =E18*F18 -> 0 | J18: =H18*I18 -> 0 | K18: =G18+J18 -> 0 | M18: =M17+K18-L18 -> 380264.13
A19: 16 | B19: 45793 | G19: =E19*F19 -> 0 | J19: =H19*I19 -> 0 | K19: =G19+J19 -> 0 | M19: =M18+K19-L19 -> 380264.13
A20: 17 | B20: 45794 | E20: 690 | F20: 99.49 | G20: =E20*F20 -> 68648.1 | J20: =H20*I20 -> 0 | K20: =G20+J20 -> 68648.1 | M20: =M19+K20-L20 -> 448912.23
A21: 18 | B21: 45795 | E21: 690 | F21: 99.49 | G21: =E21*F21 -> 68648.1 | J21: =H21*I21 -> 0 | K21: =G21+J21 -> 68648.1 | M21: =M20+K21-L21 -> 517560.33
A22: 19 | B22: 45796 | E22: 690 | F22: 100.48 | G22: =E22*F22 -> 69331.2 | J22: =H22*I22 -> 0 | K22: =G22+J22 -> 69331.2 | M22: =M21+K22-L22 -> 586891.53
A23: 20 | B23: 45797 | E23: 690 | F23: 100.48 | G23: =E23*F23 -> 69331.2 | J23: =H23*I23 -> 0 | K23: =G23+J23 -> 69331.2 | M23: =M22+K23-L23 -> 656222.73
A24: 21 | B24: 45798 | E24: 690 | F24: 100.48 | G24: =E24*F24 -> 69331.2 | J24: =H24*I24 -> 0 | K24: =G24+J24 -> 69331.2 | L24: 500000 | M24: =M23+K24-L24 -> 225553.93
A25: 22 | B25: 45799 | G25: =E25*F25 -> 0 | J25: =H25*I25 -> 0 | K25: =G25+J25 -> 0 | M25: =M24+K25-L25 -> 225553.93
A26: 23 | B26: 45800 | E26: 1310.68 | F26: 101.47 | G26: =E26*F26 -> 132994.7 | J26: =H26*I26 -> 0 | K26: =G26+J26 -> 132994.7 | M26: =M25+K26-L26 -> 358548.63
A27: 24 | B27: 45801 | G27: =E27*F27 -> 0 | J27: =H27*I27 -> 0 | K27: =G27+J27 -> 0 | M27: =M26+K27-L27 -> 358548.63
A28: 25 | B28: 45802 | E28: 690.9 | F28: 104.35 | G28: =E28*F28 -> 72095.415 | J28: =H28*I28 -> 0 | K28: =G28+J28 -> 72095.415 | M28: =M27+K28-L28 -> 430644.04
A29: 26 | B29: 45803 | E29: 690 | F29: 104.35 | G29: =E29*F29 -> 72001.5 | J29: =H29*I29 -> 0 | K29: =G29+J29 -> 72001.5 | M29: =M28+K29-L29 -> 502645.54
A30: 27 | B30: 45804 | E30: 1110 | F30: 104.35 | G30: =E30*F30 -> 115828.5 | J30: =H30*I30 -> 0 | K30: =G30+J30 -> 115828.5 | M30: =M29+K30-L30 -> 618474.04
A31: 28 | B31: 45805 | E31: 690 | F31: 104.35 | G31: =E31*F31 -> 72001.5 | H31: 7.36 | I31: 116.25 | J31: =H31*I31 -> 855.6 | K31: =G31+J31 -> 72857.1 | M31: =M30+K31-L31 -> 691331.14
A32: 29 | B32: 45806 | E32: 770 | F32: 104.35 | G32: =E32*F32 -> 80349.5 | J32: =H32*I32 -> 0 | K32: =G32+J32 -> 80349.5 | M32: =M31+K32-L32 -> 771680.64
A33: 30 | B33: 45807 | E33: =690+655 -> 1345 | F33: 104.35 | G33: =E33*F33 -> 140350.75 | H33: 18 | I33: 116.25 | J33: =H33*I33 -> 2092.5 | K33: =G33+J33 -> 142443.25 | M33: =M32+K33-L33 -> 914123.89
A34: 31 | B34: 45808 | E34: 690 | F34: 104.35 | G34: =E34*F34 -> 72001.5 | J34: =H34*I34 -> 0 | K34: =G34+J34 -> 72001.5 | M34: =M33+K34-L34 -> 986125.39
E35: =SUM(E4:E34) -> 18194.62 | G35: =SUM(G4:G34) -> 1819638.1 | H35: =SUM(H4:H34) -> 25.36 | J35: =SUM(J4:J34) -> 2948.1 | K35: =SUM(K4:K34) -> 1822586.2 | L35: =SUM(L4:L34) -> 1000000

Sheet Narayankhed
A2: S.No | B2: Date | C2: GRN No | D2: Ind no/Bill No | E2: Diesel (Lts) | F2: Price | G2: Amount | H2: Petrol (Lts) | I2: Price | J2: Amount | K2: Total amount | L2: Amount paid | M2: As on Date | N2: Remarks
A3: Opening Balance | M3: 0
A4: 1 | B4: 45778 | E4: 100 | F4: 97 | G4: =E4*F4 -> 9700 | J4: =H4*I4 -> 0 | K4: =G4+J4 -> 9700 | L4: =H4+K4 -> 9700 | M4: =M3+K4-L4 -> 0 | N4: BPCL Card
A5: 2 | B5: 45779 | G5: =E5*F5 -> 0 | J5: =H5*I5 -> 0 | K5: =G5+J5 -> 0 | L5: =H5+K5 -> 0 | M5: =M4+K5-L5 -> 0
A6: 3 | B6: 45780 | E6: 200 | F6: 97 | G6: =E6*F6 -> 19400 | J6: =H6*I6 -> 0 | K6: =G6+J6 -> 19400 | L6: =H6+K6 -> 19400 | M6: =M5+K6-L6 -> 0 | N6: BPCL Card
A7: 4 | B7: 45781 | G7: =E7*F7 -> 0 | J7: =H7*I7 -> 0 | K7: =G7+J7 -> 0 | L7: =H7+K7 -> 0 | M7: =M6+K7-L7 -> 0
A8: 5 | B8: 45782 | E8: 200 | F8: 97 | G8: =E8*F8 -> 19400 | J8: =H8*I8 -> 0 | K8: =G8+J8 -> 19400 | L8: =H8+K8 -> 19400 | M8: =M7+K8-L8 -> 0 | N8: BPCL Card
A9: 6 | B9: 45783 | G9: =E9*F9 -> 0 | J9: =H9*I9 -> 0 | K9: =G9+J9 -> 0 | L9: 0 | M9: =M8+K9-L9 -> 0
A10: 7 | B10: 45784 | G10: =E10*F10 -> 0 | J10: =H10*I10 -> 0 | K10: =G10+J10 -> 0 | L10: 0 | M10: =M9+K10-L10 -> 0
A11: 8 | B11: 45785 | G11: =E11*F11 -> 0 | J11: =H11*I11 -> 0 | K11: =G11+J11 -> 0 | L11: 0 | M11: =M10+K11-L11 -> 0
A12: 9 | B12: 45786 | G12: =E12*F12 -> 0 | J12: =H12*I12 -> 0 | K12: =G12+J12 -> 0 | L12: 0 | M12: =M11+K12-L12 -> 0
A13: 10 | B13: 45787 | G13: =E13*F13 -> 0 | J13: =H13*I13 -> 0 | K13: =G13+J13 -> 0 | L13: 0 | M13: =M12+K13-L13 -> 0
A14: 11 | B14: 45788 | E14: 200 | F14: 97 | G14: =E14*F14 -> 19400 | J14: =H14*I14 -> 0 | K14: =G14+J14 -> 19400 | L14: =H14+K14 -> 19400 | M14: =M13+K14-L14 -> 0 | N14: BT
A15: 12 | B15: 45789 | G15: =E15*F15 -> 0 | J15: =H15*I15 -> 0 | K15: =G15+J15 -> 0 | L15: 0 | M15: =M14+K15-L15 -> 0
A16: 13 | B16: 45790 | E16: 200 | F16: 97 | G16: =E16*F16 -> 19400 | J16: =H16*I16 -> 0 | K16: =G16+J16 -> 19400 | L16: =H16+K16 -> 19400 | M16: =M15+K16-L16 -> 0 | N16: BT
A17: 14 | B17: 45791 | G17: =E17*F17 -> 0 | J17: =H17*I17 -> 0 | K17: =G17+J17 -> 0 | L17: =H17+K17 -> 0 | M17: =M16+K17-L17 -> 0
A18: 15 | B18: 45792 | G18: =E18*F18 -> 0 | J18: =H18*I18 -> 0 | K18: =G18+J18 -> 0 | L18: =H18+K18 -> 0 | M18: =M17+K18-L18 -> 0
A19: 16 | B19: 45793 | G19: =E19*F19 -> 0 | J19: =H19*I19 -> 0 | K19: =G19+J19 -> 0 | L19: =H19+K19 -> 0 | M19: =M18+K19-L19 -> 0
A20: 17 | B20: 45794 | G20: =E20*F20 -> 0 | J20: =H20*I20 -> 0 | K20: =G20+J20 -> 0 | L20: =H20+K20 -> 0 | M20: =M19+K20-L20 -> 0
A21: 18 | B21: 45795 | G21: =E21*F21 -> 0 | J21: =H21*I21 -> 0 | K21: =G21+J21 -> 0 | L21: =H21+K21 -> 0 | M21: =M20+K21-L21 -> 0
A22: 19 | B22: 45796 | E22: 400 | F22: 101.25 | G22: =E22*F22 -> 40500 | J22: =H22*I22 -> 0 | K22: =G22+J22 -> 40500 | L22: =H22+K22 -> 40500 | M22: =M21+K22-L22 -> 0 | N22: BT
A23: 20 | B23: 45797 | G23: =E23*F23 -> 0 | J23: =H23*I23 -> 0 | L23: =H23+K23 -> 0 | M23: =M22+K23-L23 -> 0
A24: 21 | B24: 45798 | G24: =E24*F24 -> 0 | J24: =H24*I24 -> 0 | M24: =M23+K24-L24 -> 0
A25: 22 | B25: 45799 | G25: =E25*F25 -> 0 | J25: =H25*I25 -> 0 | K25: =G25+J25 -> 0 | L25: =+K25 -> 0 | M25: =M24+K25-L25 -> 0
A26: 23 | B26: 45800 | G26: =E26*F26 -> 0 | J26: =H26*I26 -> 0 | K26: =G26+J26 -> 0 | L26: =+K26 -> 0 | M26: =M25+K26-L26 -> 0
A27: 24 | B27: 45801 | G27: =E27*F27 -> 0 | J27: =H27*I27 -> 0 | K27: =G27+J27 -> 0 | L27: =+K27 -> 0 | M27: =M26+K27-L27 -> 0
A28: 25 | B28: 45802 | E28: 237.82 | F28: 105.12 | G28: =E28*F28 -> 24999.638 | J28: =H28*I28 -> 0 | K28: =G28+J28 -> 24999.638 | L28: =+K28 -> 24999.638 | M28: =M27+K28-L28 -> 0 | N28: BT
A29: 26 | B29: 45803 | G29: =E29*F29 -> 0 | J29: =H29*I29 -> 0 | K29: =G29+J29 -> 0 | L29: =+K29 -> 0 | M29: =M28+K29-L29 -> 0
A30: 27 | B30: 45804 | G30: =E30*F30 -> 0 | J30: =H30*I30 -> 0 | K30: =G30+J30 -> 0 | L30: =+K30 -> 0 | M30: =M29+K30-L30 -> 0
A31: 28 | B31: 45805 | G31: =E31*F31 -> 0 | J31: =H31*I31 -> 0 | K31: =G31+J31 -> 0 | L31: =+K31 -> 0 | M31: =M30+K31-L31 -> 0
A32: 29 | B32: 45806 | G32: =E32*F32 -> 0 | J32: =H32*I32 -> 0 | K32: =G32+J32 -> 0 | L32: =+K32 -> 0 | M32: =M31+K32-L32 -> 0
A33: 30 | B33: 45807 | G33: =E33*F33 -> 0 | J33: =H33*I33 -> 0 | K33: =G33+J33 -> 0 | L33: =+K33 -> 0 | M33: =M32+K33-L33 -> 0
A34: 31 | G34: =E34*F34 -> 0 | J34: =H34*I34 -> 0 | K34: =G34+J34 -> 0 | L34: =+K34 -> 0 | M34: 0
E35: =SUM(E4:E34) -> 1537.82 | G35: =SUM(G4:G34) -> 152799.64 | H35: =SUM(H4:H34) -> 0 | J35: =SUM(J4:J34) -> 0 | K35: =SUM(K4:K34) -> 152799.64 | L35: =SUM(L4:L34) -> 152799.64

Sheet Dindi
A1: Akarapu Balakistamma Fillling
A2: S.No | B2: Date | C2: GRN No | D2: Ind no/Bill No | E2: Diesel (Lts) | F2: Price | G2: Amount | H2: Petrol (Lts) | I2: Price | J2: Amount | K2: Total amount | L2: Amount paid | M2: As on Date | N2: Remarks
A3: Opening Balance | M3: 0
A4: 1 | B4: 45748 | G4: =E4*F4 -> 0 | H4: 0 | I4: 0 | J4: =H4*I4 -> 0 | K4: =G4+J4 -> 0 | L4: =+K4 -> 0 | M4: 0
A5: 2 | B5: 45749 | G5: =E5*F5 -> 0 | H5: 0 | I5: 0 | J5: =H5*I5 -> 0 | K5: =G5+J5 -> 0 | L5: =+K5 -> 0 | M5: 0
A6: 3 | B6: 45750 | G6: =E6*F6 -> 0 | H6: 0 | I6: 0 | J6: =H6*I6 -> 0 | K6: =G6+J6 -> 0 | L6: =+K6 -> 0 | M6: 0
A7: 4 | B7: 45751 | G7: =E7*F7 -> 0 | H7: 0 | I7: 0 | J7: =H7*I7 -> 0 | K7: =G7+J7 -> 0 | L7: =+K7 -> 0 | M7: 0
A8: 5 | B8: 45752 | G8: =E8*F8 -> 0 | H8: 0 | I8: 0 | J8: =H8*I8 -> 0 | K8: =G8+J8 -> 0 | L8: =+K8 -> 0 | M8: 0
A9: 6 | B9: 45753 | G9: =E9*F9 -> 0 | H9: 0 | I9: 0 | J9: =H9*I9 -> 0 | K9: =G9+J9 -> 0 | L9: =+K9 -> 0 | M9: 0
A10: 7 | B10: 45754 | G10: =E10*F10 -> 0 | H10: 0 | I10: 0 | J10: =H10*I10 -> 0 | K10: =G10+J10 -> 0 | L10: =+K10 -> 0 | M10: 0
A11: 8 | B11: 45755 | G11: =E11*F11 -> 0 | H11: 0 | I11: 0 | J11: =H11*I11 -> 0 | K11: =G11+J11 -> 0 | L11: =+K11 -> 0 | M11: 0
A12: 9 | B12: 45756 | G12: =E12*F12 -> 0 | H12: 0 | I12: 0 | J12: =H12*I12 -> 0 | K12: =G12+J12 -> 0 | L12: =+K12 -> 0 | M12: 0
A13: 10 | B13: 45757 | G13: =E13*F13 -> 0 | H13: 0 | I13: 0 | J13: =H13*I13 -> 0 | K13: =G13+J13 -> 0 | L13: =+K13 -> 0 | M13: 0
A14: 11 | B14: 45758 | G14: =E14*F14 -> 0 | H14: 0 | I14: 0 | J14: =H14*I14 -> 0 | K14: =G14+J14 -> 0 | L14: =+K14 -> 0 | M14: 0
A15: 12 | B15: 45759 | G15: =E15*F15 -> 0 | H15: 0 | I15: 0 | J15: =H15*I15 -> 0 | K15: =G15+J15 -> 0 | L15: =+K15 -> 0 | M15: 0
... A27: 24 | B27: 45771 | G27: =E27*F27 -> 0 | H27: 0 | I27: 0 | J27: =H27*I27 -> 0 | K27: =G27+J27 -> 0 | L27: =+K27 -> 0 | M27: 0
A28: 25 | B28: 45772 | H28: 0 | I28: 0 | J28: =H28*I28 -> 0 | K28: =G28+J28 -> 0 | L28: =+K28 -> 0 | M28: 0
A29: 26 | B29: 45773 | G29: =E29*F29 -> 0 | H29: 0 | I29: 0 | J29: =H29*I29 -> 0 | K29: =G29+J29 -> 0 | L29: =+K29 -> 0 | M29: 0
A30: 27 | B30: 45774 | G30: =E30*F30 -> 0 | H30: 0 | I30: 0 | J30: =H30*I30 -> 0 | K30: =G30+J30 -> 0 | L30: =+K30 -> 0 | M30: 0
A31: 28 | B31: 45775 | G31: =E31*F31 -> 0 | H31: 0 | I31: 0 | J31: =H31*I31 -> 0 | K31: =G31+J31 -> 0 | L31: =+K31 -> 0 | M31: 0
A32: 29 | G32: =E32*F32 -> 0 | H32: 0 | I32: 0 | J32: =H32*I32 -> 0 | K32: =G32+J32 -> 0 | L32: =+K32 -> 0 | M32: 0
A33: 30 | G33: =E33*F33 -> 0 | H33: 0 | I33: 0 | J33: =H33*I33 -> 0 | K33: =G33+J33 -> 0 | L33: =+K33 -> 0 | M33: 0
A34: 31 | G34: =E34*F34 -> 0 | H34: 0 | I34: 0 | J34: =H34*I34 -> 0 | K34: =G34+J34 -> 0 | L34: =+K34 -> 0 | M34: 0
E35: =SUM(E4:E34) -> 0 | G35: =SUM(G4:G34) -> 0 | H35: =SUM(H4:H34) -> 0 | J35: =SUM(J4:J34) -> 0 | K35: =SUM(K4:K34) -> 0 | L35: =SUM(L4:L34) -> 0

Sheet Amalapuram
A2: S.No | B2: Date | C2: GRN No | D2: Ind no/Bill No | E2: Diesel (Lts) | F2: Price | G2: Amount | H2: Petrol (Lts) | I2: Price | J2: Amount | K2: Total amount | L2: Amount paid | M2: As on Date | N2: Remarks
A3: Opening Balance | M3: 0
A4: 1 | B4: 01.05.2026 | C4: CHAKRADWARABANDHAM BHARAT PETROLEUM DEALERS | D4: CHAKRADWARABANDHAM | E4: 50.98 | F4: 96.66 | G4: =E4*F4 -> 4927.7268 | K4: =G4+J4 -> 4927.7268 | L4: =+K4 -> 4927.7268 | M4: =+M3+K4-L4 -> 0 | N4: BPCL
A5: 2 | B5: 02.05.2026 | C5: SRI BALAJI AGENCIES BHARAT PETROLEUM DEALERS | E5: 47.2 | F5: 97.71 | G5: =E5*F5 -> 4611.912 | K5: =G5+J5 -> 4611.912 | L5: =+K5 -> 4611.912 | M5: =+M4+K5-L5 -> 0 | N5: BPCL
A6: 3 | B6: 02.05.2026 | C6: SRILAKSHMI AGENCIES BHARAT PETROLEUM DEALERS | G6: =E6*F6 -> 0 | H6: 5 | I6: 109.71 | J6: =H6*I6 -> 548.55 | K6: =G6+J6 -> 548.55 | L6: =+K6 -> 548.55 | M6: =+M5+K6-L6 -> 0
A7: 4 | B7: 04.05.2026 | C7: SRI BALAJI AGENCIES BHARAT PETROLEUM DEALERS | G7: =E7*F7 -> 0 | H7: 5 | I7: 109.71 | J7: =H7*I7 -> 548.55 | K7: =G7+J7 -> 548.55 | L7: =+K7 -> 548.55 | M7: =+M6+K7-L7 -> 0
A8: 5 | B8: 05.05.2026 | C8: BP Kakinada | D8: Kakinada | E8: 0 | H8: 5 | I8: 109.94 | J8: 549.7 | K8: 549.7 | L8: =+K8 -> 549.7 | M8: =+M7+K8-L8 -> 0
A9: 6 | B9: 05.05.2026 | C9: Sri Balaji Agencies | D9: Kakinada | E9: 43.7 | F9: 97.71 | G9: 4269.93 | H9: 0 | K9: 4269.93 | L9: =+K9 -> 4269.93 | M9: =+M8+K9-L9 -> 0 | N9: BPCL
A10: 7 | B10: 05.05.2026 | C10: BP Chakradwarabhandam | D10: Rajanagaram | E10: 45.64 | F10: 96.66 | G10: 4411.56 | H10: 0 | K10: 4411.56 | L10: =+K10 -> 4411.56 | M10: =+M9+K10-L10 -> 0
A11: 8 | B11: 05.05.2026 | C11: JVVR Filling Station | D11: Pitapuram | E11: 0 | H11: 5 | I11: 109.68 | J11: 548.4 | K11: 548.4 | L11: =+K11 -> 548.4 | M11: =+M10+K11-L11 -> 0 | N11: BPCL
A12: 9 | B12: 06.05.2026 | C12: BP Lalacheruvu | D12: Rajahmundry | E12: 0 | H12: 15 | I12: 108.86 | J12: 1632.9 | K12: 1632.9 | L12: 1632.9 | M12: =+M11+K12-L12 -> 0 | N12: BPCL
A13: 10 | B13: 07.05.2026 | C13: Sardar Singh Sahni&Sons | D13: Gannavaram | E13: 48.23 | F13: 97.34 | G13: 4694.71 | H13: 0 | K13: 4694.71 | L13: 4694.71 | M13: =+M12+K13-L13 -> 0
A14: 11 | B14: 07.05.2026 | C14: Sri Lakshmi Agencies | D14: Samarlkota | E14: 46.87 | F14: 97.49 | G14: 4569.36 | H14: 0 | K14: 4569.36 | L14: 4569.36 | M14: =+M13+K14-L14 -> 0 | N14: BPCL
A15: 12 | B15: 07.05.2026 | C15: BP Lalacheruvu | D15: Rajahmundry | E15: 0 | H15: 5 | I15: 108.86 | J15: 544.3 | K15: 544.3 | L15: 544.3 | M15: =+M14+K15-L15 -> 0 | N15: BPCL
A16: 13 | B16: 08.05.2026 | C16: Sri Balaji Agencies | D16: Kakinada | E16: 101.97 | F16: 97.71 | G16: 9963.49 | H16: 0 | K16: 9963.49 | L16: 9963.49 | M16: =+M15+K16-L16 -> 0
A17: 14 | B17: 08.05.2026 | C17: GSR Vana Durga Filling | D17: Vijayawada | E17: 46.45 | F17: 96.87 | G17: 4499.61 | H17: 0 | K17: 4499.61 | L17: 4499.61 | M17: =+M16+K17-L17 -> 0 | N17: BPCL
A18: 15 | B18: 08.05.2026 | C18: Solasa Krishna Oil Company | D18: Jangareddygudem | E18: 0 | H18: 5 | I18: 109.7 | J18: 550 | K18: 550 | L18: 550 | M18: =+M16+K18-L18 -> 0 | N18: BPCL
A19: 16 | B19: 09.05.2026 | C19: Sri Venkateswara Enterprises | D19: Yanam | E19: 81.76 | F19: 86.75 | G19: 7092.68 | H19: 0 | K19: 7092.68 | L19: 7092.68 | M19: =+M18+K19-L19 -> 0 | N19: BPCL
A20: 17 | B20: 10.05.2026 | C20: BP Kakinada | D20: Kakinada | E20: 0 | H20: 5 | I20: 109.94 | J20: 550 | K20: 550 | L20: 550 | M20: =+M19+K20-L20 -> 0 | N20: BPCL
A21: 18 | B21: 12.05.2026 | C21: BP Kakinada | D21: Kakinada | E21: 51.84 | F21: 97.71 | G21: 5065.29 | H21: 0 | K21: 5065.29 | L21: 5065.29 | M21: =+M20+K21-L21 -> 0 | N21: IOCL
A22: 19 | B22: 13.05.2026 | C22: BP Kakinada | D22: Kakinada | E22: 50 | F22: 97.71 | G22: 4885.5 | H22: 10 | I22: 109.94 | J22: 1099.4 | K22: 5984.9 | L22: 5984.9 | M22: =+M21+K22-L22 -> 0 | N22: BPCL
A23: 20 | B23: 13.05.2026 | C23: Sree SV Agencies | D23: Peddapuram | E23: 50.99 | F23: 96.88 | G23: 4939.91 | H23: 0 | K23: 4939.91 | L23: 4939.91 | M23: =+M22+K23-L23 -> 0
A24: 21 | B24: 14.05.2026 | C24: BPCL Tirumala Agencies | D24: Anathavaram (Mummidivaram) | E24: 45.31 | F24: 97.47 | G24: 4416.36 | H24: 0 | K24: 4416.36 | L24: 4416.36 | M24: =+M23+K24-L24 -> 0
A25: 22 | B25: 15.05.2026 | C25: BP Kakinada | D25: Kakinada | E25: 0 | H25: 5 | I25: 113.22 | J25: =H25*I25 -> 566.1 | K25: 566.1 | L25: 566.1 | M25: =+M24+K25-L25 -> 0
A26: 23 | B26: 15.05.2026 | C26: JVVR Filling Station | D26: Pitapuram | E26: 0 | H26: 5 | I26: 112.96 | J26: =H26*I26 -> 564.8 | K26: 564.8 | L26: 564.8 | M26: =+M25+K26-L26 -> 0 | N26: IOCL
A27: 24 | B27: 15.05.2026 | C27: Sri Venkateswara Enterprises | D27: Yanam | E27: 51.37 | F27: 89.67 | G27: 4606.35 | H27: 0 | I27: 0 | J27: =H27*I27 -> 0 | K27: 4606.35 | L27: 4606.35 | M27: =+M26+K27-L27 -> 0 | N27: BPCL
A28: 25 | B28: 15.05.2026 | C28: Sri Balaji Agencies | D28: Kakinada | E28: 48.42 | F28: 100.85 | G28: 4883.16 | H28: 0 | I28: 0 | J28: =H28*I28 -> 0 | K28: 4883.16 | L28: 4883.16 | M28: =+M27+K28-L28 -> 0
A29: 26 | B29: 16.05.2026 | C29: Sri Lakshmi Agencies | D29: Samarlkota | E29: 46.1 | F29: 100.63 | G29: 4639.04 | H29: 0 | I29: 0 | J29: =H29*I29 -> 0 | K29: 4639.04 | L29: 4639.04 | M29: =+M28+K29-L29 -> 0
A30: 27 | B30: 17.05.2026 | C30: BP Kakinada | D30: Kakinada | E30: 51.87 | F30: 100.85 | G30: 5231.09 | H30: 0 | I30: 0 | J30: =H30*I30 -> 0 | K30: 5231.09 | L30: 5231.09 | M30: =+M29+K30-L30 -> 0
A31: 28 | B31: 17.05.2026 | C31: BP Kovvuru | D31: Kovvuru | E31: 10 | F31: 99.96 | G31: 999.6 | H31: 0 | I31: 0 | J31: =H31*I31 -> 0 | K31: =G31+J31 -> 999.6 | L31: 999.6 | M31: =+M30+K31-L31 -> 0
A32: 29 | B32: 18.05.2026 | C32: Sri Balaji Agencies | D32: Kakinada | E32: 0 | F32: 100.85 | G32: 0 | H32: 5 | I32: 113.22 | J32: =H32*I32 -> 566.1 | K32: =G32+J32 -> 566.1 | L32: 566.1 | M32: =+M31+K32-L32 -> 0
A33: 30 | B33: 18.05.2026 | C33: BP Kovvuru | D33: Kovvuru | E33: 143.5 | F33: 99.96 | G33: =E33*F33 -> 14344.26 | H33: 0 | I33: 0 | J33: =H33*I33 -> 0 | K33: =G33+J33 -> 14344.26 | L33: 14344.26 | M33: =+M32+K33-L33 -> 0
A34: 30 | B34: 18.05.2026 | C34: BP Kakinada | D34: Kakinada | E34: 51.53 | F34: 100.85 | G34: =E34*F34 -> 5196.8005 | H34: 0 | I34: 0 | J34: =H34*I34 -> 0 | K34: =G34+J34 -> 5196.8005 | L34: 5196.8 | M34: =+M33+K34-L34 -> 0.0005
A35: 31 | B35: 18.05.2026 | C35: Sathya Siva Durga Agencies | D35: Chebrolu | E35: 100 | F35: 100.47 | G35: =E35*F35 -> 10047 | H35: 0 | I35: 0 | J35: =H35*I35 -> 0 | K35: =G35+J35 -> 10047 | L35: 10047 | M35: =+M34+K35-L35 -> 0.0005
A36: 32 | B36: 19.05.2026 | C36: SAI LEELA FILLING STATION | D36: MANDADAM | E36: 49.48 | F36: 101.37 | G36: =E36*F36 -> 5015.7876 | I36: 0 | J36: =H36*I36 -> 0 | K36: =G36+J36 -> 5015.7876 | L36: =H36+K36 -> 5015.7876 | M36: =+M35+K36-L36 -> 0.0005
A37: 33 | B37: 19.05.2026 | C37: SOLASA KRISHNA OIL COMPANY BHARAT PETROLEUM | D37: JANGAREDDYGUDEM | G37: =E37*F37 -> 0 | H37: 5 | I37: 113.93 | J37: =H37*I37 -> 569.65 | K37: =G37+J37 -> 569.65 | L37: 569.65 | M37: =+M36+K37-L37 -> 0.0005
B38: 19.05.2026 | C38: SRI BALAJI AGENCIES BHARAT PETROLEUM DEALERS | D38: Kakinada | E38: 36 | F38: 101.79 | G38: =E38*F38 -> 3664.44 | K38: =G38+J38 -> 3664.44 | L38: 3664.44 | M38: =+M37+K38-L38 -> 0.0005
B39: 20.05.2026 | C39: JVVR Filling Station | D39: Pitapuram | E39: 49.04 | F39: 101.55 | G39: 4980.01 | H39: 0 | K39: 4980.01 | L39: 4980.01 | M39: =+M38+K39-L39 -> 0.0005
B40: 20.05.2026 | C40: Sri Balaji Agencies | D40: Kakinada | E40: 0 | H40: 5 | I40: 114.18 | J40: 570.9 | K40: 570.9 | L40: 570.9 | M40: =+M39+K40-L40 -> 0.0005
B41: 20.05.2026 | C41: Sri Balaji Agencies | D41: Kakinada | E41: 51.85 | F41: 100.85 | G41: 5229.07 | H41: 0 | K41: 5229.07 | L41: 5229.07 | M41: =+M40+K41-L41 -> 0.0005
B42: 20.05.2026 | C42: BP Lalacheruvu | D42: Rajahmundry | E42: 0 | H42: 8.11 | I42: 113.1 | J42: 917.24 | K42: 917.24 | L42: 917.24 | M42: =+M41+K42-L42 -> 0.0005
B43: 21.05.2026 | C43: Sri Balaji Agencies | D43: Kakinada | E43: 25.44 | F43: 101.79 | G43: 2589.54 | H43: 0 | J43: 0 | K43: 2589.54 | L43: 2589.54 | M43: =+M42+K43-L43 -> 0.0005
B44: 21.05.2026 | C44: BP Kovvuru | D44: Kovvuru | E44: 95.19 | F44: 100.91 | G44: 9605.62 | H44: 30 | I44: 114.18 | J44: 3425.4 | K44: 13031.02 | L44: 13031.02 | M44: =+M43+K44-L44 -> 0.0005
B45: 21.05.2026 | C45: BP Kakinada | D45: Kakinada | E45: 78.67 | F45: 101.79 | G45: 8007.82 | H45: 5 | I45: 114.18 | J45: 570.9 | K45: 8578.72 | L45: 8578.72 | M45: =+M44+K45-L45 -> 0.0005
B46: 22.05.2026 | C46: BP Kovvuru | D46: Kakinada | H46: 10 | I46: 113.18 | J46: 1131.8 | K46: 1131.8 | L46: 1131.8 | M46: =+M45+K46-L46 -> 0.0005
B47: 22.05.2026 | C47: JVVR Filling Station | D47: Pitapuram | H47: 10 | I47: 113.92 | J47: 1139.2 | K47: 1139.2 | L47: 1139.2 | M47: =+M46+K47-L47 -> 0.0005
B48: 23.05.2026 | C48: BP Kovvuru | D48: Kovvuru | E48: 97.13 | F48: 101.86 | G48: 9893.66 | H48: 0 | K48: 9893.66 | L48: 9893.66 | M48: =+M47+K48-L48 -> 0.0005
B49: 23.05.2026 | C49: BP Kakinada | D49: Kakinada | E49: 0 | H49: 10 | I49: 115.12 | J49: 1151.2 | K49: 1151.2 | L49: 1151.2 | M49: =+M48+K49-L49 -> 0.0005
B50: 23.05.2026 | C50: BP Lalacheruvu | D50: Rajahmundry | E50: 46.28 | F50: 101.78 | G50: 4710.38 | H50: 20 | I50: 114.04 | J50: 2280.8 | K50: 6991.18 | L50: 6991.18 | M50: =+M49+K50-L50 -> 0.0005
B51: 23.05.2026 | C51: Sathya Siva Durga Agencies | D51: Chebrolu | E51: 52.11 | F51: 102.38 | G51: 5335.02 | H51: 0 | K51: 5335.02 | L51: 5335.02 | M51: =+M50+K51-L51 -> 0.0005
B52: 23.05.2026 | C52: Sri Bhimeswara Agencies BPCL | D52: Amalapuram | E52: 46.07 | F52: 102.45 | G52: 4719.87 | H52: 0 | K52: 4719.87 | L52: 4719.87 | M52: =+M51+K52-L52 -> 0.0005
B53: 24.05.2026 | C53: Sri Venkateswara Enterprises | D53: Yanam | E53: 49.8 | F53: 91.44 | G53: 4553.71 | H53: 0 | K53: 4553.71 | L53: 4553.71 | M53: =+M52+K53-L53 -> 0.0005
B54: 24.05.2026 | C54: Sri Balaji Agencies | D54: Kakinada | E54: 46.44 | F54: 102.75 | G54: 4771.71 | H54: 0 | K54: 4771.71 | L54: 4771.71 | M54: =+M53+K54-L54 -> 0.0005
B55: 24.05.2026 | C55: Vishnu filling station | D55: Kakinada | E55: 0 | H55: 5 | I55: 115.12 | J55: 575.6 | K55: 575.6 | L55: 575.6 | M55: =+M54+K55-L55 -> 0.0005
B56: 25.05.2026 | C56: Sathya Siva Durga Agencies | D56: Chebrolu | E56: 82.42 | F56: 105.21 | G56: 8671.41 | H56: 0 | K56: 8671.41 | L56: 8671.41 | M56: =+M55+K56-L56 -> 0.0005
B57: 25.05.2026 | C57: BP Kovvuru | D57: Kovvuru | E57: 173.01 | F57: 104.7 | G57: 18114.15 | H57: 0 | K57: 18114.15 | L57: 18114.15 | M57: =+M56+K57-L57 -> 0.0005
B58: 25.05.2026 | C58: Himagiri Filling Station | D58: Vijayawada | E58: 53.13 | F58: 104.93 | G58: 5574.93 | H58: 0 | K58: 5574.93 | L58: 5574.93 | M58: =+M57+K58-L58 -> 0.0005
B59: 26.05.2026 | C59: JVVR Filling Station | D59: Pitapuram | E59: 46.36 | F59: 105.35 | G59: 4884.03 | H59: 5 | I59: 117.72 | J59: 588.6 | K59: 5472.63 | L59: 5472.63 | M59: =+M58+K59-L59 -> 0.0005
B60: 26.05.2026 | C60: BP Lalacheruvu | D60: Rajahmundry | E60: 68.9 | F60: 104.62 | G60: 7208.32 | H60: 0 | K60: 7208.32 | L60: 7208.32 | M60: =+M59+K60-L60 -> 0.0005
B61: 26.05.2026 | C61: BP Kovvuru | D61: Kovvuru | E61: 10 | F61: 104.7 | G61: 1047 | H61: 0 | K61: 1047 | L61: 1047 | M61: =+M60+K61-L61 -> 0.0005
B62: 26.05.2026 | C62: BP Kakinada | D62: Kakinada | E62: 0 | H62: 5 | I62: 117.98 | J62: 589.9 | K62: 589.9 | L62: 589.9 | M62: =+M61+K62-L62 -> 0.0005
B63: 26.05.2026 | C63: Kilaram Brothers | D63: Denduluru | E63: 44.56 | F63: 105.33 | G63: 4693.5 | H63: 0 | K63: 4693.5 | L63: 4693.5 | M63: =+M62+K63-L63 -> 0.0005
B64: 27.05.2026 | C64: BP Kovvuru | D64: Kovvuru | E64: 97.34 | F64: 104.7 | G64: 10191.5 | H64: 0 | K64: 10191.5 | L64: 10191.5 | M64: =+M63+K64-L64 -> 0.0005
B65: 27.05.2026 | C65: Sathya Siva Durga Agencies | D65: Chebrolu | E65: 50 | F65: 105.21 | G65: 5260.5 | H65: 0 | K65: 5260.5 | L65: 5260.5 | M65: =+M64+K65-L65 -> 0.0005
B66: 27.05.2026 | C66: Sathya Siva Durga Agencies | D66: Chebrolu | E66: 70 | F66: 105.21 | G66: 7364.7 | H66: 0 | K66: 7364.7 | L66: 7364.7 | M66: =+M65+K66-L66 -> 0.0005
B67: 27.05.2026 | C67: BP Lalacheruvu | D67: Rajahmundry | E67: 0 | F67: 0 | G67: 0 | H67: 15 | I67: 116.9 | J67: 1753.5 | K67: 1753.5 | L67: 1753.5 | M67: =+M66+K67-L67 -> 0.0005
B68: 27.05.2026 | C68: BP Kovvuru | D68: Kovvuru | E68: 0 | F68: 0 | G68: 0 | H68: 5 | I68: 116.99 | J68: 584.95 | K68: 584.95 | L68: 584.95 | M68: =+M67+K68-L68 -> 0.0005
B69: 27.05.2026 | C69: Sri Bhimeswara Agencies BPCL | D69: Amalapuram | E69: 48.06 | F69: 105.29 | G69: 5060.24 | H69: 0 | K69: 5060.24 | L69: 5060.24 | M69: =+M68+K69-L69 -> 0.0005
B70: 27.05.2026 | C70: vijaya balaji agencies | D70: Yanam | E70: 55.41 | F70: 94.03 | G70: 5210.2 | H70: 0 | K70: 5210.2 | L70: 5210.2 | M70: =+M69+K70-L70 -> 0.0005
B71: 28.05.2026 | C71: Sathya Siva Durga Agencies | D71: Chebrolu | E71: 50 | F71: 105.21 | G71: 5260.5 | H71: 0 | K71: 5260.5 | L71: 5260.5 | M71: =+M70+K71-L71 -> 0.0005
B72: 29.05.2026 | C72: Sri Balaji Agencies | D72: Kakinada | E72: 37.18 | F72: 105.59 | G72: 3925.84 | H72: 0 | K72: 3925.84 | L72: 3925.84 | M72: =+M71+K72-L72 -> 0.0005
B73: 29.05.2026 | C73: Sri Balaji Agencies | D73: Kakinada | E73: 0 | F73: 0 | G73: 0 | H73: 5 | I73: 117.98 | J73: 589.9 | K73: 589.9 | L73: 589.9 | M73: =+M72+K73-L73 -> 0.0005
B74: 29.05.2026 | C74: Sathya Siva Durga Agencies | D74: Chebrolu | E74: 50 | F74: 105.21 | G74: 5260.5 | H74: 0 | I74: 0 | J74: 0 | K74: 5260.5 | L74: 5260.5 | M74: =+M73+K74-L74 -> 0.0005
B75: 29.05.2026 | C75: Sathya Siva Durga Agencies | D75: Chebrolu | E75: 50 | F75: 105.21 | G75: 5260.5 | H75: 0 | I75: 0 | J75: 0 | K75: 5260.5 | L75: 5260.5 | M75: =+M74+K75-L75 -> 0.0005
B76: 29.05.2026 | C76: BP Kakinada | D76: Kakinada | E76: 45.19 | F76: 105.59 | G76: 4771.61 | H76: 0 | I76: 0 | J76: 0 | K76: 4771.61 | L76: 4771.61 | M76: =+M75+K76-L76 -> 0.0005
B77: 30.05.2026 | C77: BP Kovvuru | D77: Kovvuru | E77: 96 | F77: 104.7 | G77: 10051.2 | H77: 0 | K77: 10051.2 | L77: 10051.2
B78: 30.05.2026 | C78: BP Kovvuru | D78: Kovvuru | E78: 10 | F78: 104.7 | G78: 1047 | H78: 0 | K78: 1047 | L78: 1047 | M78: =+M58+K78-L78 -> 0.0005
B79: 30.05.2026 | C79: MAA PETROLEUM | D79: NAGULAVENIPADU | E79: 0 | G79: 0 | H79: 5 | I79: 118.01 | J79: 590.05 | K79: 590.05 | L79: 590.05
B80: 30.05.2026 | C80: SRI BALAJI AGENCIES | D80: Kakinada | E80: 0 | G80: 0 | H80: 5 | I80: 117.98 | J80: 589.9 | K80: 589.9 | L80: 589.9
B81: 30.05.2026 | C81: Sathya Siva Durga Agencies | D81: Chebrolu | E81: 0 | G81: 0 | H81: 5 | I81: 117.58 | J81: 587.9 | K81: 587.9 | L81: 587.9
B82: 30.05.2026 | C82: Sathya Siva Durga Agencies | D82: Chebrolu | E82: 70 | F82: 105.21 | G82: 7364.7 | H82: 0 | I82: 0 | J82: 0 | K82: 7364.7 | L82: 7364.7
B83: 30.05.2026 | C83: Sathya Siva Durga Agencies | D83: Chebrolu | E83: 20 | F83: 105.21 | G83: 2104.2 | H83: 0 | I83: 0 | J83: 0 | K83: 2104.2 | L83: 2104.2
B84: 31.05.2026 | C84: BP Kovvuru | D84: Kovvuru | E84: 0 | G84: 0 | H84: 5 | I84: 116.99 | J84: 584.95 | K84: 584.95 | L84: 584.95
B85: 31.05.2026 | C85: SRI BALAJI AGENCIES | D85: Kakinada | E85: 49.32 | F85: 105.59 | G85: 5207.7 | H85: 0 | J85: 0 | K85: 5207.7 | L85: 5207.7
B86: 31.05.2026 | C86: BP Kovvuru | D86: Kovvuru | E86: 49.95 | F86: 104.7 | G86: 5229.77 | H86: 0 | J86: 0 | K86: 5229.77 | L86: 5229.77
B87: 31.05.2026 | C87: BP Lalacheruvu | D87: Rajahmundry | E87: 50.31 | F87: 104.62 | G87: 5263.43 | H87: 0 | J87: 0 | K87: 5263.43 | L87: 5263.43
B88: 31.05.2026 | C88: BP Lalacheruvu | D88: Rajahmundry | E88: 0 | G88: 0 | H88: 20 | I88: 116.9 | J88: 2338 | K88: 2338 | L88: 2338
B89: 31.05.2026 | C89: Sathya Siva Durga Agencies | D89: Chebrolu | E89: 48.07 | F89: 105.21 | G89: 5057.44 | H89: 0 | J89: 0 | K89: 5057.44 | L89: 5057.44
E102: =SUM(E4:E101) -> 3362.44 | G102: =SUM(G4:G101) -> 340456.85 | H102: =SUM(H4:H101) -> 258.11 | J102: =SUM(J4:J101) -> 29399.14 | K102: =SUM(K4:K101) -> 369855.99 | L102: =SUM(L4:L101) -> 369855.99

Sheet Madana palli
A2: S.No | B2: Date | C2: GRN No | D2: Ind no/Bill No | E2: Diesel (Lts) | F2: Price | G2: Amount | H2: Petrol (Lts) | I2: Price | J2: Amount | K2: Total amount | L2: Amount paid | M2: As on Date | N2: Remarks
A3: Opening Balance | M3: 0
A4: 1 | B4: 46143 | G4: =E4*F4 -> 0 | J4: =H4*I4 -> 0 | K4: =G4+J4 -> 0 | L4: =+K4 -> 0 | M4: 0
A5: 2 | B5: 46144 | G5: =E5*F5 -> 0 | J5: =H5*I5 -> 0 | K5: =G5+J5 -> 0 | L5: =+K5 -> 0 | M5: 0 | N5: IOCL
A6: 3 | B6: 46145 | G6: =E6*F6 -> 0 | J6: =H6*I6 -> 0 | K6: =G6+J6 -> 0 | L6: =+K6 -> 0 | M6: 0
A7: 4 | B7: 46146 | G7: =E7*F7 -> 0 | J7: =H7*I7 -> 0 | K7: =G7+J7 -> 0 | L7: =+K7 -> 0 | M7: 0
A8: 5 | B8: 46147 | G8: =E8*F8 -> 0 | J8: =H8*I8 -> 0 | K8: =G8+J8 -> 0 | L8: =+K8 -> 0 | M8: 0
A9: 6 | B9: 46148 | G9: =E9*F9 -> 0 | J9: =H9*I9 -> 0 | K9: =G9+J9 -> 0 | L9: =+K9 -> 0 | M9: 0 | N9: HPCL
A10: 7 | B10: 46149 | G10: =E10*F10 -> 0 | J10: =H10*I10 -> 0 | K10: =G10+J10 -> 0 | L10: =+K10 -> 0 | M10: 0 | O10: 169.99
A11: 8 | B11: 46150 | G11: =E11*F11 -> 0 | J11: =H11*I11 -> 0 | K11: =G11+J11 -> 0 | L11: =+K11 -> 0 | M11: 0 | O11: 80
A12: 9 | B12: 46151 | G12: =E12*F12 -> 0 | J12: =H12*I12 -> 0 | K12: =G12+J12 -> 0 | L12: =+K12 -> 0 | M12: 0 | O12: =SUM(O10:O11) -> 249.99 | P12: 97.76 | Q12: =O12*P12 -> 24439.022
A13: 10 | B13: 46152 | G13: =E13*F13 -> 0 | J13: =H13*I13 -> 0 | K13: =G13+J13 -> 0 | L13: =+K13 -> 0 | M13: 0
A14: 11 | B14: 46153 | G14: =E14*F14 -> 0 | J14: =H14*I14 -> 0 | K14: =G14+J14 -> 0 | L14: =+K14 -> 0 | M14: 0
A15: 12 | B15: 46154 | G15: =E15*F15 -> 0 | J15: =H15*I15 -> 0 | K15: =G15+J15 -> 0 | L15: =+K15 -> 0 | M15: 0 | P15: 7820.8
A16: 13 | B16: 46155 | G16: =E16*F16 -> 0 | J16: =H16*I16 -> 0 | K16: =G16+J16 -> 0 | L16: =+K16 -> 0 | M16: 0 | P16: 16619.2
A17: 14 | B17: 46156 | G17: =E17*F17 -> 0 | J17: =H17*I17 -> 0 | K17: =G17+J17 -> 0 | L17: =+K17 -> 0 | M17: 0 | P17: =SUM(P15:P16) -> 24440
A18: 15 | B18: 46157 | G18: =E18*F18 -> 0 | J18: =H18*I18 -> 0 | K18: =G18+J18 -> 0 | L18: =+K18 -> 0 | M18: 0
A19: 16 | B19: 46158 | G19: =E19*F19 -> 0 | J19: =H19*I19 -> 0 | K19: =G19+J19 -> 0 | L19: =+K19 -> 0 | M19: 0
A20: 17 | B20: 46159 | G20: =E20*F20 -> 0 | J20: =H20*I20 -> 0 | K20: =G20+J20 -> 0 | L20: =+K20 -> 0 | M20: 0
A21: 18 | B21: 46160 | G21: =E21*F21 -> 0 | J21: =H21*I21 -> 0 | K21: =G21+J21 -> 0 | L21: =+K21 -> 0 | M21: 0
A22: 19 | B22: 46161 | G22: =E22*F22 -> 0 | J22: =H22*I22 -> 0 | K22: =G22+J22 -> 0 | L22: =+K22 -> 0 | M22: 0
A23: 20 | B23: 46162 | G23: =E23*F23 -> 0 | J23: =H23*I23 -> 0 | K23: =G23+J23 -> 0 | L23: =+K23 -> 0 | M23: 0
A24: 21 | B24: 46163 | G24: =E24*F24 -> 0 | J24: =H24*I24 -> 0 | K24: =G24+J24 -> 0 | L24: =+K24 -> 0 | M24: 0
A25: 22 | B25: 46164 | G25: =E25*F25 -> 0 | J25: =H25*I25 -> 0 | K25: =G25+J25 -> 0 | L25: =+K25 -> 0 | M25: 0
A26: 23 | B26: 46165 | G26: =E26*F26 -> 0 | J26: =H26*I26 -> 0 | K26: =G26+J26 -> 0 | L26: =+K26 -> 0 | M26: 0
A27: 24 | B27: 46166 | G27: =E27*F27 -> 0 | J27: =H27*I27 -> 0 | K27: =G27+J27 -> 0 | L27: =+K27 -> 0 | M27: 0
A28: 25 | B28: 46167 | G28: =E28*F28 -> 0 | J28: =H28*I28 -> 0 | K28: =G28+J28 -> 0 | L28: =+K28 -> 0 | M28: 0
B29: 46168 | J29: =H29*I29 -> 0 | K29: =G29+J29 -> 0 | L29: =+K29 -> 0
A30: 26 | B30: 46169 | G30: =E30*F30 -> 0 | J30: =H30*I30 -> 0 | K30: =G30+J30 -> 0 | L30: =+K30 -> 0 | M30: 0
A31: 27 | B31: 46170 | G31: =E31*F31 -> 0 | J31: =H31*I31 -> 0 | K31: =G31+J31 -> 0 | L31: =+K31 -> 0 | M31: 0
A32: 28 | B32: 46171 | E32: 18.98 | F32: 105.32 | G32: =E32*F32 -> 1998.9736 | H32: 4.25 | I32: 117.66 | J32: =H32*I32 -> 500.055 | K32: =G32+J32 -> 2499.0286 | L32: =+K32 -> 2499.0286 | M32: 0
A33: 29 | B33: 46172 | G33: =E33*F33 -> 0 | J33: =H33*I33 -> 0 | K33: =G33+J33 -> 0 | L33: =+K33 -> 0 | M33: 0
A34: 30 | G34: =E34*F34 -> 0 | J34: =H34*I34 -> 0 | K34: =G34+J34 -> 0 | L34: =+K34 -> 0 | M34: 0
A35: 31 | G35: =E35*F35 -> 0 | J35: =H35*I35 -> 0 | K35: =G35+J35 -> 0 | L35: =+K35 -> 0 | M35: 0
E36: =SUM(E4:E35) -> 18.98 | G36: =SUM(G4:G35) -> 1998.9736 | H36: =SUM(H4:H35) -> 4.25 | J36: =SUM(J4:J35) -> 500.055 | K36: =SUM(K4:K35) -> 2499.0286 | L36: =SUM(L4:L35) -> 2499.0286

Sheet Kadur
A1: Vishal Service Station
A2: S.No | B2: Date | C2: GRN No | D2: Ind No/Bill No | E2: Diesel (Lts) | F2: Price | G2: Amount | H2: Petrol (Lts) | I2: Price | J2: Amount | K2: Total amount | L2: Amount paid | M2: As on Date | N2: Remarks
A3: Opening Balance | K3: 0 | L3: 0 | M3: 0 | O3: 207239.43
A4: 1 | B4: 45778 | F4: 0 | G4: =E4*F4 -> 0 | H4: 0 | I4: 0 | J4: =H4*I4 -> 0 | K4: =G4+J4 -> 0 | M4: =M3+K4-L4 -> 0
A5: 2 | B5: 45779 | E5: 1600 | F5: 95.15 | G5: =E5*F5 -> 152240 | H5: 70 | I5: 109.27 | J5: =H5*I5 -> 7648.9 | K5: =G5+J5 -> 159888.9 | M5: =M4+K5-L5 -> 159888.9
A6: 3 | B6: 45780 | F6: 0 | G6: =E6*F6 -> 0 | H6: 0 | I6: 0 | J6: =H6*I6 -> 0 | K6: =G6+J6 -> 0 | M6: =M5+K6-L6 -> 159888.9
A7: 4 | B7: 45781 | F7: 0 | G7: =E7*F7 -> 0 | H7: 0 | I7: 0 | J7: =H7*I7 -> 0 | K7: =G7+J7 -> 0 | M7: =M6+K7-L7 -> 159888.9
A8: 5 | B8: 45782 | F8: 0 | G8: =E8*F8 -> 0 | H8: 0 | I8: 0 | J8: =H8*I8 -> 0 | K8: =G8+J8 -> 0 | M8: =M7+K8-L8 -> 159888.9
A9: 6 | B9: 45783 | F9: 0 | G9: =E9*F9 -> 0 | H9: 0 | I9: 0 | J9: =H9*I9 -> 0 | K9: =G9+J9 -> 0 | M9: =M8+K9-L9 -> 159888.9
A10: 7 | B10: 45784 | F10: 0 | G10: =E10*F10 -> 0 | H10: 0 | I10: 0 | J10: =H10*I10 -> 0 | K10: =G10+J10 -> 0 | M10: =M9+K10-L10 -> 159888.9
A11: 8 | B11: 45785 | F11: 0 | G11: =E11*F11 -> 0 | H11: 0 | I11: 0 | J11: =H11*I11 -> 0 | K11: =G11+J11 -> 0 | M11: =M10+K11-L11 -> 159888.9
A12: 9 | B12: 45786 | F12: 0 | G12: =E12*F12 -> 0 | H12: 0 | I12: 0 | J12: =H12*I12 -> 0 | K12: =G12+J12 -> 0 | M12: =M11+K12-L12 -> 159888.9
A13: 10 | B13: 45787 | F13: 0 | G13: =E13*F13 -> 0 | H13: 0 | I13: 0 | J13: =H13*I13 -> 0 | K13: =G13+J13 -> 0 | M13: =M12+K13-L13 -> 159888.9
A14: 11 | B14: 45788 | F14: 0 | G14: =E14*F14 -> 0 | H14: 0 | I14: 0 | J14: =H14*I14 -> 0 | K14: =G14+J14 -> 0 | M14: =M13+K14-L14 -> 159888.9
A15: 12 | B15: 45789 | F15: 0 | G15: =E15*F15 -> 0 | H15: 0 | I15: 0 | J15: =H15*I15 -> 0 | K15: =G15+J15 -> 0 | M15: =M14+K15-L15 -> 159888.9
A16: 13 | B16: 45790 | F16: 0 | G16: =E16*F16 -> 0 | H16: 0 | I16: 0 | J16: =H16*I16 -> 0 | K16: =G16+J16 -> 0 | M16: =M15+K16-L16 -> 159888.9
A17: 14 | B17: 45791 | F17: 0 | G17: =E17*F17 -> 0 | H17: 0 | I17: 0 | J17: =H17*I17 -> 0 | K17: =G17+J17 -> 0 | M17: =M16+K17-L17 -> 159888.9
... A21: 18 | B21: 45795 | F21: 0 | G21: =E21*F21 -> 0 | H21: 0 | I21: 0 | J21: =H21*I21 -> 0 | K21: =G21+J21 -> 0 | M21: =M20+K21-L21 -> 159888.9
A22: 19 | B22: 45796 | F22: 0 | H22: 0 | I22: 0 | J22: =H22*I22 -> 0 | K22: =G22+J22 -> 0 | M22: =M21+K22-L22 -> 159888.9
A23: 20 | B23: 45797 | F23: 0 | H23: 0 | I23: 0 | J23: =H23*I23 -> 0 | K23: =G23+J23 -> 0 | M23: =M22+K23-L23 -> 159888.9
A24: 21 | B24: 45798 | F24: 0 | J24: =H24*I24 -> 0 | K24: =G24+J24 -> 0 | M24: =M23+K24-L24 -> 159888.9
A25: 22 | B25: 45799 | F25: 0 | J25: =H25*I25 -> 0 | K25: =G25+J25 -> 0 | M25: =M24+K25-L25 -> 159888.9
A26: 23 | B26: 45800 | F26: 0 | J26: =H26*I26 -> 0 | K26: =G26+J26 -> 0 | M26: =M25+K26-L26 -> 159888.9
A27: 24 | B27: 45801 | F27: 0 | J27: =H27*I27 -> 0 | K27: =G27+J27 -> 0 | M27: =M26+K27-L27 -> 159888.9
A28: 25 | B28: 45802 | F28: 0 | J28: =H28*I28 -> 0 | K28: =G28+J28 -> 0 | M28: =M27+K28-L28 -> 159888.9
A29: 26 | B29: 45803 | F29: 0 | J29: =H29*I29 -> 0 | K29: =G29+J29 -> 0 | M29: =M28+K29-L29 -> 159888.9
A30: 27 | B30: 45804 | F30: 0 | J30: =H30*I30 -> 0 | K30: =G30+J30 -> 0 | M30: =M29+K30-L30 -> 159888.9
A31: 28 | B31: 45805 | F31: 0 | J31: =H31*I31 -> 0 | K31: =G31+J31 -> 0 | M31: =M30+K31-L31 -> 159888.9
A32: 29 | B32: 45806 | F32: 0 | G32: =E32*F32 -> 0 | H32: 0 | I32: 0 | J32: =H32*I32 -> 0 | K32: =G32+J32 -> 0 | M32: =M31+K32-L32 -> 159888.9
A33: 30 | B33: 45807 | F33: 0 | G33: =E33*F33 -> 0 | H33: 0 | I33: 0 | J33: =H33*I33 -> 0 | K33: =G33+J33 -> 0 | M33: =M32+K33-L33 -> 159888.9
A34: 31 | F34: 0 | G34: =E34*F34 -> 0 | J34: =H34*I34 -> 0 | K34: =G34+J34 -> 0
E35: =SUM(E4:E34) -> 1600 | G35: =SUM(G4:G34) -> 152240 | H35: =SUM(H4:H34) -> 70 | J35: =SUM(J4:J34) -> 7648.9 | K35: =SUM(K4:K34) -> 159888.9 | L35: =SUM(L4:L31) -> 0

Sheet YG Gudda-2
A1: Pankaja HP Fuel Center
A2: S.No | B2: Date | C2: GRN No | D2: Ind No/Bill No | E2: Diesel (Lts) | F2: Price | G2: Amount | H2: Petrol (Lts) | I2: Price | J2: Amount | K2: Total amount | L2: Amount paid | M2: As on Date | N2: Remarks
A3: Opening Balance | K3: 194105.96 | M3: 194105.96
A4: 1 | B4: 46143 | E4: 600 | F4: 91.33 | G4: =E4*F4 -> 54798 | H4: 35 | I4: 103.27 | J4: =H4*I4 -> 3614.45 | K4: =G4+J4 -> 58412.45 | M4: =M3+K4-L4 -> 252518.41
A5: 2 | B5: 46144 | G5: =E5*F5 -> 0 | J5: =H5*I5 -> 0 | K5: =G5+J5 -> 0 | M5: =M4+K5-L5 -> 252518.41
A6: 3 | B6: 46145 | G6: =E6*F6 -> 0 | J6: =H6*I6 -> 0 | K6: =G6+J6 -> 0 | M6: =M5+K6-L6 -> 252518.41
A7: 4 | B7: 46146 | G7: =E7*F7 -> 0 | J7: =H7*I7 -> 0 | K7: =G7+J7 -> 0 | L7: 200000 | M7: =M6+K7-L7 -> 52518.41
A8: 5 | B8: 46147 | E8: 600 | F8: 91.33 | G8: =E8*F8 -> 54798 | H8: 70 | I8: 103.27 | J8: =H8*I8 -> 7228.9 | K8: =G8+J8 -> 62026.9 | M8: =M7+K8-L8 -> 114545.31
A9: 6 | B9: 46148 | E9: 600 | F9: 91.33 | G9: =E9*F9 -> 54798 | J9: =H9*I9 -> 0 | K9: =G9+J9 -> 54798 | M9: =M8+K9-L9 -> 169343.31
A10: 7 | B10: 46149 | G10: =E10*F10 -> 0 | J10: =H10*I10 -> 0 | K10: =G10+J10 -> 0 | M10: =M9+K10-L10 -> 169343.31
A11: 8 | B11: 46150 | G11: =E11*F11 -> 0 | J11: =H11*I11 -> 0 | K11: =G11+J11 -> 0 | M11: =M10+K11-L11 -> 169343.31
A12: 9 | B12: 46151 | E12: 600 | F12: 91.33 | G12: =E12*F12 -> 54798 | H12: 35 | I12: 103.27 | J12: =H12*I12 -> 3614.45 | K12: =G12+J12 -> 58412.45 | M12: =M11+K12-L12 -> 227755.76
A13: 10 | B13: 46152 | G13: =E13*F13 -> 0 | J13: =H13*I13 -> 0 | K13: =G13+J13 -> 0 | M13: =M12+K13-L13 -> 227755.76
A14: 11 | B14: 46153 | E14: 300 | F14: 91.39 | G14: =E14*F14 -> 27417 | J14: =H14*I14 -> 0 | K14: =G14+J14 -> 27417 | L14: 27417 | M14: =M13+K14-L14 -> 227755.76
A15: 12 | B15: 46153 | L15: 180000 | M15: =M14+K15-L15 -> 47755.76
A16: 13 | B16: 46154 | G16: =E16*F16 -> 0 | J16: =H16*I16 -> 0 | K16: =G16+J16 -> 0 | L16: 0 | M16: =M15+K16-L16 -> 47755.76
A17: 14 | B17: 46155 | E17: 600 | F17: 91.33 | G17: =E17*F17 -> 54798 | H17: 35 | I17: 103.27 | J17: =H17*I17 -> 3614.45 | K17: =G17+J17 -> 58412.45 | M17: =M16+K17-L17 -> 106168.21
A18: 15 | B18: 46156 | E18: 500 | F18: 91.33 | G18: =E18*F18 -> 45665 | J18: =H18*I18 -> 0 | K18: =G18+J18 -> 45665 | M18: =M17+K18-L18 -> 151833.21
A19: 16 | B19: 46157 | E19: 500 | F19: 94.41 | G19: =E19*F19 -> 47205 | J19: =H19*I19 -> 0 | K19: =G19+J19 -> 47205 | L19: =H19+K19 -> 47205 | M19: =M18+K19-L19 -> 151833.21 | N19: Pallavi IOCL
A20: 17 | B20: 46158 | G20: =E20*F20 -> 0 | J20: =H20*I20 -> 0 | K20: =G20+J20 -> 0 | L20: 150000 | M20: =M19+K20-L20 -> 1833.2099
A21: 18 | B21: 46159 | E21: 800 | F21: 94.44 | G21: =E21*F21 -> 75552 | H21: 35 | I21: 106.53 | J21: =H21*I21 -> 3728.55 | K21: =G21+J21 -> 79280.55 | M21: =M20+K21-L21 -> 81113.76
A22: 19 | B22: 46160 | G22: =E22*F22 -> 0 | J22: =H22*I22 -> 0 | K22: =G22+J22 -> 0 | M22: =M21+K22-L22 -> 81113.76
A23: 20 | B23: 46161 | E23: 400 | F23: 95.44 | G23: =E23*F23 -> 38176 | H23: 0 | I23: 0 | J23: =H23*I23 -> 0 | K23: =G23+J23 -> 38176 | L23: 38176 | M23: =M22+K23-L23 -> 81113.76 | N23: Sri Siddeshwara Fuels HPCL
A24: 21 | B24: 46162 | G24: =E24*F24 -> 0 | J24: =H24*I24 -> 0 | K24: =G24+J24 -> 0 | M24: =M23+K24-L24 -> 81113.76
A25: 22 | B25: 46163 | E25: 800 | F25: 95.48 | G25: =E25*F25 -> 76384 | H25: 35 | I25: 107.48 | J25: =H25*I25 -> 3761.8 | K25: =G25+J25 -> 80145.8 | L25: 140000 | M25: =M24+K25-L25 -> 21259.56
A26: 23 | B26: 46164 | E26: 400 | F26: 95.48 | G26: =E26*F26 -> 38192 | J26: =H26*I26 -> 0 | K26: =G26+J26 -> 38192 | M26: =M25+K26-L26 -> 59451.56
A27: 24 | B27: 46165 | E27: 800 | F27: 96.33 | G27: =E27*F27 -> 77064 | J27: =H27*I27 -> 0 | K27: =G27+J27 -> 77064 | M27: =M26+K27-L27 -> 136515.56
A28: 25 | B28: 46166 | G28: =E28*F28 -> 0 | J28: =H28*I28 -> 0 | K28: =G28+J28 -> 0 | M28: =M27+K28-L28 -> 136515.56
A29: 26 | B29: 46167 | G29: =E29*F29 -> 0 | J29: =H29*I29 -> 0 | K29: =G29+J29 -> 0 | L29: 100000 | M29: =M28+K29-L29 -> 36515.56
A30: 27 | B30: 46168 | G30: =E30*F30 -> 0 | J30: =H30*I30 -> 0 | K30: =G30+J30 -> 0 | M30: =M29+K30-L30 -> 36515.56
A31: 28 | B31: 46169 | E31: 1200 | F31: 99.14 | G31: =E31*F31 -> 118968 | H31: 35 | I31: 111.24 | J31: =H31*I31 -> 3893.4 | K31: =G31+J31 -> 122861.4 | M31: =M30+K31-L31 -> 159376.96
A32: 29 | B32: 46170 | G32: =E32*F32 -> 0 | J32: =H32*I32 -> 0 | K32: =G32+J32 -> 0 | M32: =M31+K32-L32 -> 159376.96
A33: 30 | B33: 46171 | G33: =E33*F33 -> 0 | J33: =H33*I33 -> 0 | K33: =G33+J33 -> 0 | M33: =M32+K33-L33 -> 159376.96
A34: 31 | B34: 46172 | E34: 300 | F34: 99.14 | G34: =E34*F34 -> 29742 | J34: =H34*I34 -> 0 | K34: =G34+J34 -> 29742 | M34: =M33+K34-L34 -> 189118.96
A35: 32 | G35: =E35*F35 -> 0 | J35: =H35*I35 -> 0 | K35: =G35+J35 -> 0 | M35: =M34+K35-L35 -> 189118.96
A36: 33 | G36: =E36*F36 -> 0 | J36: =H36*I36 -> 0 | K36: =G36+J36 -> 0 | M36: =M35+K36-L36 -> 189118.96
A37: 34 | G37: =E37*F37 -> 0 | H37: 0 | I37: 0 | J37: =H37*I37 -> 0 | K37: =G37+J37 -> 0 | M37: =M36+K37-L37 -> 189118.96
E38: =SUM(E4:E37) -> 9000 | G38: =SUM(G4:G37) -> 848355 | H38: =SUM(H4:H37) -> 280 | J38: =SUM(J4:J37) -> 29456 | K38: =SUM(K4:K37) -> 877811 | L38: =SUM(L4:L37) -> 882798

Sheet Hosadurga -2
A1: Shree Veeraprathap Fuel
A2: S.No | B2: Date | C2: GRN No | D2: Ind No/Bill No | E2: Diesel (Lts) | F2: Price | G2: Amount | H2: Petrol (Lts) | I2: Price | J2: Amount | K2: Total amount | L2: Amount paid | M2: As on Date | N2: Remarks
A3: Opening Balance | K3: 248489.28 | M3: 248489.28
A4: 1 | B4: 46143 | C4: 0 | E4: 0 | F4: 0 | G4: =E4*F4 -> 0 | H4: 0 | I4: 0 | J4: =H4*I4 -> 0 | K4: =G4+J4 -> 0 | M4: =M3+K4-L4 -> 248489.28
A5: 2 | B5: 46144 | C5: 0 | G5: =E5*F5 -> 0 | J5: =H5*I5 -> 0 | K5: =G5+J5 -> 0 | M5: =M4+K5-L5 -> 248489.28
A6: 3 | B6: 46145 | C6: 0 | G6: =E6*F6 -> 0 | J6: =H6*I6 -> 0 | K6: =G6+J6 -> 0 | M6: =M5+K6-L6 -> 248489.28
A7: 4 | B7: 46146 | C7: 0 | G7: =E7*F7 -> 0 | J7: =H7*I7 -> 0 | K7: =G7+J7 -> 0 | M7: =M6+K7-L7 -> 248489.28
A8: 5 | B8: 46147 | C8: 0 | G8: =E8*F8 -> 0 | J8: =H8*I8 -> 0 | K8: =G8+J8 -> 0 | M8: =M7+K8-L8 -> 248489.28
A9: 6 | B9: 46148 | C9: 0 | G9: =E9*F9 -> 0 | J9: =H9*I9 -> 0 | K9: =G9+J9 -> 0 | M9: =M8+K9-L9 -> 248489.28
A10: 7 | B10: 46149 | C10: 0 | G10: =E10*F10 -> 0 | J10: =H10*I10 -> 0 | K10: =G10+J10 -> 0 | M10: =M9+K10-L10 -> 248489.28
A11: 8 | B11: 46150 | C11: 0 | G11: =E11*F11 -> 0 | J11: =H11*I11 -> 0 | K11: =G11+J11 -> 0 | M11: =M10+K11-L11 -> 248489.28
A12: 9 | B12: 46151 | C12: 0 | G12: =E12*F12 -> 0 | J12: =H12*I12 -> 0 | K12: =G12+J12 -> 0 | M12: =M11+K12-L12 -> 248489.28
A13: 10 | B13: 46152 | C13: 0 | G13: =E13*F13 -> 0 | J13: =H13*I13 -> 0 | K13: =G13+J13 -> 0 | M13: =M12+K13-L13 -> 248489.28
A14: 11 | B14: 46153 | C14: 0 | G14: =E14*F14 -> 0 | J14: =H14*I14 -> 0 | K14: =G14+J14 -> 0 | M14: =M13+K14-L14 -> 248489.28
A15: 12 | B15: 46154 | C15: 0 | G15: =E15*F15 -> 0 | J15: =H15*I15 -> 0 | K15: =G15+J15 -> 0 | M15: =M14+K15-L15 -> 248489.28
A16: 13 | B16: 46155 | C16: 0 | G16: =E16*F16 -> 0 | J16: =H16*I16 -> 0 | K16: =G16+J16 -> 0 | M16: =M15+K16-L16 -> 248489.28
A17: 14 | B17: 46156 | C17: 0 | G17: =E17*F17 -> 0 | J17: =H17*I17 -> 0 | K17: =G17+J17 -> 0 | M17: =M16+K17-L17 -> 248489.28
A18: 15 | B18: 46157 | C18: 0 | E18: 300 | F18: 94.51 | G18: =E18*F18 -> 28353 | H18: 15.43 | I18: 106.72 | J18: =H18*I18 -> 1646.6896 | K18: =G18+J18 -> 29999.69 | L18: 29999.69 | M18: =M17+K18-L18 -> 248489.28
A19: 16 | B19: 46158 | C19: 0 | E19: 1400 | F19: 94.51 | G19: =E19*F19 -> 132314 | H19: 70 | I19: 106.72 | J19: =H19*I19 -> 7470.4 | K19: =G19+J19 -> 139784.4 | M19: =M18+K19-L19 -> 388273.68
A20: 17 | B20: 46159 | C20: 0 | G20: =E20*F20 -> 0 | J20: =H20*I20 -> 0 | K20: =G20+J20 -> 0 | M20: =M19+K20-L20 -> 388273.68
A21: 18 | B21: 46160 | C21: 0 | G21: =E21*F21 -> 0 | J21: =H21*I21 -> 0 | K21: =G21+J21 -> 0 | L21: 248000 | M21: =M20+K21-L21 -> 140273.68
A22: 19 | B22: 46161 | C22: 0 | G22: =E22*F22 -> 0 | J22: =H22*I22 -> 0 | K22: =G22+J22 -> 0 | M22: =M21+K22-L22 -> 140273.68
A23: 20 | B23: 46162 | C23: 0 | G23: =E23*F23 -> 0 | J23: =H23*I23 -> 0 | K23: =G23+J23 -> 0 | M23: =M22+K23-L23 -> 140273.68
A24: 21 | B24: 46163 | C24: 0 | G24: =E24*F24 -> 0 | J24: =H24*I24 -> 0 | K24: =G24+J24 -> 0 | M24: =M23+K24-L24 -> 140273.68
A25: 22 | B25: 46164 | C25: 0 | G25: =E25*F25 -> 0 | J25: =H25*I25 -> 0 | K25: =G25+J25 -> 0 | M25: =M24+K25-L25 -> 140273.68
A26: 23 | B26: 46165 | C26: 0 | G26: =E26*F26 -> 0 | J26: =H26*I26 -> 0 | K26: =G26+J26 -> 0 | M26: =M25+K26-L26 -> 140273.68
A27: 24 | B27: 46166 | C27: 0 | G27: =E27*F27 -> 0 | J27: =H27*I27 -> 0 | K27: =G27+J27 -> 0 | M27: =M26+K27-L27 -> 140273.68
A28: 25 | B28: 46167 | C28: 0 | G28: =E28*F28 -> 0 | J28: =H28*I28 -> 0 | K28: =G28+J28 -> 0 | L28: 100000 | M28: =M27+K28-L28 -> 40273.676
A29: 26 | B29: 46168 | C29: 0 | E29: 200 | F29: 100.04 | G29: =E29*F29 -> 20008 | J29: =H29*I29 -> 0 | K29: =G29+J29 -> 20008 | M29: =M28+K29-L29 -> 60281.676
A30: 27 | B30: 46169 | C30: 0 | G30: =E30*F30 -> 0 | J30: =H30*I30 -> 0 | K30: =G30+J30 -> 0 | M30: =M29+K30-L30 -> 60281.676
A31: 28 | B31: 46170 | C31: 0 | E31: 800.44 | F31: 100.04 | G31: =E31*F31 -> 80076.018 | H31: 70 | I31: 112.05 | J31: =H31*I31 -> 7843.5 | K31: =G31+J31 -> 87919.518 | M31: =M30+K31-L31 -> 148201.19
A32: 29 | B32: 46171 | C32: 0 | G32: =E32*F32 -> 0 | J32: =H32*I32 -> 0 | K32: =G32+J32 -> 0 | M32: =M31+K32-L32 -> 148201.19
A33: 30 | B33: 46172 | C33: 0 | G33: =E33*F33 -> 0 | J33: =H33*I33 -> 0 | K33: =G33+J33 -> 0 | M33: =M32+K33-L33 -> 148201.19
A34: 31 | K34: =G34+J34 -> 0
E35: =SUM(E4:E34) -> 2700.44 | G35: =SUM(G4:G34) -> 260751.02 | H35: =SUM(H4:H34) -> 155.43 | J35: =SUM(J4:J34) -> 16960.59 | K35: =SUM(K4:K34) -> 277711.61 | L35: =SUM(L4:L34) -> 377999.69

Sheet Hiriyur(VJNL)
A1: Sri Balaji Agencies
A2: S.No | B2: Date | C2: GRN No | D2: Ind No/Bill No | E2: Diesel (Lts) | F2: Price | G2: Amount | H2: Petrol (Lts) | I2: Price | J2: Amount | K2: Total amount | L2: Amount paid | M2: As on Date | N2: Remarks
A3: Opening Balance | K3: 278745.3 | M3: 278745.3
A4: 1 | B4: 46143 | G4: =E4*F4 -> 0 | J4: =H4*I4 -> 0 | K4: =G4+J4 -> 0 | M4: =M3+K4-L4 -> 278745.3
A5: 2 | B5: 46144 | G5: =E5*F5 -> 0 | J5: =H5*I5 -> 0 | K5: =G5+J5 -> 0 | M5: =M4+K5-L5 -> 278745.3
A6: 3 | B6: 46145 | G6: =E6*F6 -> 0 | J6: =H6*I6 -> 0 | K6: =G6+J6 -> 0 | M6: =M5+K6-L6 -> 278745.3
A7: 4 | B7: 46146 | G7: =E7*F7 -> 0 | H7: 70 | I7: 103.86 | J7: =H7*I7 -> 7270.2 | K7: =G7+J7 -> 7270.2 | L7: 250000 | M7: =M6+K7-L7 -> 36015.5
A8: 5 | B8: 46147 | G8: =E8*F8 -> 0 | J8: =H8*I8 -> 0 | K8: =G8+J8 -> 0 | M8: =M7+K8-L8 -> 36015.5
A9: 6 | B9: 46148 | G9: =E9*F9 -> 0 | J9: =H9*I9 -> 0 | K9: =G9+J9 -> 0 | M9: =M8+K9-L9 -> 36015.5
A10: 7 | B10: 46149 | E10: 2000 | F10: 92.1 | G10: =E10*F10 -> 184200 | H10: 35 | I10: 103.86 | J10: =H10*I10 -> 3635.1 | K10: =G10+J10 -> 187835.1 | M10: =M9+K10-L10 -> 223850.6
A11: 8 | B11: 46150 | G11: =E11*F11 -> 0 | J11: =H11*I11 -> 0 | K11: =G11+J11 -> 0 | M11: =M10+K11-L11 -> 223850.6
A12: 9 | B12: 46151 | G12: =E12*F12 -> 0 | J12: =H12*I12 -> 0 | K12: =G12+J12 -> 0 | M12: =M11+K12-L12 -> 223850.6
A13: 10 | B13: 46152 | G13: =E13*F13 -> 0 | J13: =H13*I13 -> 0 | K13: =G13+J13 -> 0 | M13: =M12+K13-L13 -> 223850.6
A14: 11 | B14: 46153 | G14: =E14*F14 -> 0 | J14: =H14*I14 -> 0 | K14: =G14+J14 -> 0 | M14: =M13+K14-L14 -> 223850.6
A15: 12 | B15: 46154 | G15: =E15*F15 -> 0 | J15: =H15*I15 -> 0 | K15: =G15+J15 -> 0 | M15: =M14+K15-L15 -> 223850.6
A16: 13 | B16: 46155 | G16: =E16*F16 -> 0 | H16: 70 | I16: 103.86 | J16: =H16*I16 -> 7270.2 | K16: =G16+J16 -> 7270.2 | M16: =M15+K16-L16 -> 231120.8
A17: 14 | B17: 46156 | G17: =E17*F17 -> 0 | J17: =H17*I17 -> 0 | K17: =G17+J17 -> 0 | M17: =M16+K17-L17 -> 231120.8
A18: 15 | B18: 46157 | G18: =E18*F18 -> 0 | J18: =H18*I18 -> 0 | K18: =G18+J18 -> 0 | M18: =M17+K18-L18 -> 231120.8
A19: 16 | B19: 46158 | G19: =E19*F19 -> 0 | J19: =H19*I19 -> 0 | K19: =G19+J19 -> 0 | M19: =M18+K19-L19 -> 231120.8
A20: 17 | B20: 46159 | G20: =E20*F20 -> 0 | J20: =H20*I20 -> 0 | K20: =G20+J20 -> 0 | M20: =M19+K20-L20 -> 231120.8
A21: 18 | B21: 46160 | G21: =E21*F21 -> 0 | J21: =H21*I21 -> 0 | K21: =G21+J21 -> 0 | M21: =M20+K21-L21 -> 231120.8
A22: 19 | B22: 46161 | G22: =E22*F22 -> 0 | J22: =H22*I22 -> 0 | K22: =G22+J22 -> 0 | M22: =M21+K22-L22 -> 231120.8
A23: 20 | B23: 46162 | G23: =E23*F23 -> 0 | J23: =H23*I23 -> 0 | K23: =G23+J23 -> 0 | M23: =M22+K23-L23 -> 231120.8
A24: 21 | B24: 46163 | E24: 1500 | F24: 96.16 | G24: =E24*F24 -> 144240 | H24: 70 | I24: 108.07 | J24: =H24*I24 -> 7564.9 | K24: =G24+J24 -> 151804.9 | L24: 200000 | M24: =M23+K24-L24 -> 182925.7
A25: 22 | B25: 46164 | G25: =E25*F25 -> 0 | J25: =H25*I25 -> 0 | K25: =G25+J25 -> 0 | M25: =M24+K25-L25 -> 182925.7
A26: 23 | B26: 46165 | G26: =E26*F26 -> 0 | J26: =H26*I26 -> 0 | K26: =G26+J26 -> 0 | M26: =M25+K26-L26 -> 182925.7
A27: 24 | B27: 46166 | G27: =E27*F27 -> 0 | J27: =H27*I27 -> 0 | K27: =G27+J27 -> 0 | M27: =M26+K27-L27 -> 182925.7
A28: 25 | B28: 46167 | G28: =E28*F28 -> 0 | J28: =H28*I28 -> 0 | K28: =G28+J28 -> 0 | M28: =M27+K28-L28 -> 182925.7
A29: 26 | B29: 46168 | G29: =E29*F29 -> 0 | J29: =H29*I29 -> 0 | K29: =G29+J29 -> 0 | M29: =M28+K29-L29 -> 182925.7
A30: 27 | B30: 46169 | G30: =E30*F30 -> 0 | J30: =H30*I30 -> 0 | K30: =G30+J30 -> 0 | M30: =M29+K30-L30 -> 182925.7
A31: 28 | B31: 46170 | G31: =E31*F31 -> 0 | J31: =H31*I31 -> 0 | K31: =G31+J31 -> 0 | M31: =M30+K31-L31 -> 182925.7
A32: 29 | B32: 46171 | G32: =E32*F32 -> 0 | J32: =H32*I32 -> 0 | K32: =G32+J32 -> 0 | M32: =M31+K32-L32 -> 182925.7
A33: 30 | B33: 46172 | G33: =E33*F33 -> 0 | J33: =H33*I33 -> 0 | K33: =G33+J33 -> 0 | M33: =M32+K33-L33 -> 182925.7
A34: 31 | G34: =E34*F34 -> 0 | J34: =H34*I34 -> 0 | K34: =G34+J34 -> 0 | M34: =M33+K34-L34 -> 182925.7
E35: =SUM(E4:E34) -> 3500 | G35: =SUM(G4:G34) -> 328440 | H35: =SUM(H4:H34) -> 245 | J35: =SUM(J4:J34) -> 25740.4 | K35: =SUM(K4:K34) -> 354180.4 | L35: =SUM(L4:L34) -> 450000

Sheet Malebenur(KUWSDB)
A1: Sree Veerabhadreshwara Service Station
A2: S.No | B2: Date | C2: GRN No | D2: Ind No/Bill No | E2: Diesel (Lts) | F2: Price | G2: Amount | H2: Petrol (Lts) | I2: Price | J2: Amount | K2: Total amount | L2: Amount paid | M2: As on Date | N2: Remarks
A3: Opening Balance | K3: 193649.21 | M3: =+K3 -> 193649.21 | O3: 46138.764
A4: 1 | B4: 45778 | E4: 0 | F4: 0 | G4: =E4*F4 -> 0 | H4: 0 | I4: 0 | J4: =H4*I4 -> 0 | K4: =G4+J4 -> 0 | L4: 0 | M4: =M3+K4-L4 -> 193649.21
A5: 2 | B5: 45779 | E5: 0 | F5: 0 | G5: =E5*F5 -> 0 | H5: 0 | I5: 0 | J5: =H5*I5 -> 0 | K5: =G5+J5 -> 0 | L5: 0 | M5: =M4+K5-L5 -> 193649.21
A6: 3 | B6: 45780 | E6: 600 | F6: 92.01 | G6: =E6*F6 -> 55206 | H6: 0 | I6: 0 | J6: =H6*I6 -> 0 | K6: =G6+J6 -> 55206 | L6: 0 | M6: =M5+K6-L6 -> 248855.21
A7: 4 | B7: 45781 | E7: 0 | F7: 0 | G7: =E7*F7 -> 0 | H7: 0 | I7: 0 | J7: =H7*I7 -> 0 | K7: =G7+J7 -> 0 | L7: 198000 | M7: =M6+K7-L7 -> 50855.21
A8: 5 | B8: 45782 | E8: 0 | F8: 0 | G8: =E8*F8 -> 0 | H8: 0 | I8: 0 | J8: =H8*I8 -> 0 | K8: =G8+J8 -> 0 | L8: 0 | M8: =M7+K8-L8 -> 50855.21
A9: 6 | B9: 45783 | E9: 0 | F9: 0 | G9: =E9*F9 -> 0 | H9: 0 | I9: 0 | J9: =H9*I9 -> 0 | K9: =G9+J9 -> 0 | L9: 0 | M9: =M8+K9-L9 -> 50855.21
A10: 7 | B10: 45784 | E10: 0 | F10: 0 | G10: =E10*F10 -> 0 | H10: 35 | I10: 103.76 | J10: =H10*I10 -> 3631.6 | K10: =G10+J10 -> 3631.6 | L10: 0 | M10: =M9+K10-L10 -> 54486.81
A11: 8 | B11: 45785 | E11: 600 | F11: 92.01 | G11: =E11*F11 -> 55206 | H11: 0 | I11: 0 | J11: =H11*I11 -> 0 | K11: =G11+J11 -> 55206 | L11: 0 | M11: =M10+K11-L11 -> 109692.81
A12: 9 | B12: 45786 | E12: 0 | F12: 0 | G12: =E12*F12 -> 0 | H12: 0 | I12: 0 | J12: =H12*I12 -> 0 | K12: =G12+J12 -> 0 | L12: 0 | M12: =M11+K12-L12 -> 109692.81
A13: 10 | B13: 45787 | E13: 0 | F13: 0 | G13: =E13*F13 -> 0 | H13: 0 | I13: 0 | J13: =H13*I13 -> 0 | K13: =G13+J13 -> 0 | L13: 0 | M13: =M12+K13-L13 -> 109692.81
A14: 11 | B14: 45788 | E14: 0 | F14: 0 | G14: =E14*F14 -> 0 | H14: 0 | I14: 0 | J14: =H14*I14 -> 0 | K14: =G14+J14 -> 0 | L14: 0 | M14: =M13+K14-L14 -> 109692.81
A15: 12 | B15: 45789 | E15: 600 | F15: 92.01 | G15: 55206 | H15: 35 | I15: 103.76 | J15: =H15*I15 -> 3631.6 | K15: =G15+J15 -> 58837.6 | L15: 0 | M15: =M14+K15-L15 -> 168530.41
A16: 13 | B16: 45790 | E16: 400 | F16: 92.01 | G16: =E16*F16 -> 36804 | H16: 0 | I16: 0 | J16: =H16*I16 -> 0 | K16: =G16+J16 -> 36804 | L16: 0 | M16: =M15+K16-L16 -> 205334.41
A17: 14 | B17: 45791 | E17: 0 | F17: 0 | G17: =E17*F17 -> 0 | H17: 0 | I17: 0 | J17: =H17*I17 -> 0 | K17: =G17+J17 -> 0 | L17: 0 | M17: =M16+K17-L17 -> 205334.41
A18: 15 | B18: 45792 | E18: 0 | F18: 0 | G18: =E18*F18 -> 0 | H18: 0 | I18: 0 | J18: =H18*I18 -> 0 | K18: =G18+J18 -> 0 | L18: 200000 | M18: =M17+K18-L18 -> 5334.4097 | N18: BT
A19: 16 | B19: 45793 | E19: 600 | F19: 95.12 | G19: =E19*F19 -> 57072 | H19: 0 | I19: 0 | J19: =H19*I19 -> 0 | K19: =G19+J19 -> 57072 | L19: 0 | M19: =M18+K19-L19 -> 62406.41
A20: 17 | B20: 45794 | E20: 0 | F20: 0 | G20: =E20*F20 -> 0 | H20: 0 | I20: 0 | J20: =H20*I20 -> 0 | K20: =G20+J20 -> 0 | L20: 0 | M20: =M19+K20-L20 -> 62406.41
A21: 18 | B21: 45795 | E21: 600 | F21: 95.12 | G21: =E21*F21 -> 57072 | H21: 25 | I21: 107.02 | J21: =H21*I21 -> 2675.5 | K21: =G21+J21 -> 59747.5 | L21: 0 | M21: =M20+K21-L21 -> 122153.91
A22: 19 | B22: 45796 | E22: 0 | F22: 0 | G22: =E22*F22 -> 0 | H22: 0 | I22: 0 | J22: =H22*I22 -> 0 | K22: =G22+J22 -> 0 | L22: 0 | M22: =M21+K22-L22 -> 122153.91
A23: 20 | B23: 45797 | E23: 0 | F23: 0 | G23: =E23*F23 -> 0 | H23: 0 | I23: 0 | J23: =H23*I23 -> 0 | K23: =G23+J23 -> 0 | L23: 0 | M23: =M22+K23-L23 -> 122153.91
A24: 21 | B24: 45798 | E24: 0 | F24: 0 | G24: =E24*F24 -> 0 | H24: 0 | I24: 0 | J24: =H24*I24 -> 0 | K24: =G24+J24 -> 0 | L24: 0 | M24: =M23+K24-L24 -> 122153.91
A25: 22 | B25: 45799 | E25: 0 | F25: 0 | G25: =E25*F25 -> 0 | H25: 0 | I25: 0 | J25: =H25*I25 -> 0 | K25: =G25+J25 -> 0 | L25: 0 | M25: =M24+K25-L25 -> 122153.91
A26: 23 | B26: 45800 | E26: 0 | F26: 0 | G26: =E26*F26 -> 0 | H26: 0 | I26: 0 | J26: =H26*I26 -> 0 | K26: =G26+J26 -> 0 | L26: 0 | M26: =M25+K26-L26 -> 122153.91
A27: 24 | B27: 45801 | E27: 600 | F27: 97.01 | G27: =E27*F27 -> 58206 | H27: 30 | I27: 108.9 | J27: =H27*I27 -> 3267 | K27: =G27+J27 -> 61473 | L27: 0 | M27: =M26+K27-L27 -> 183626.91
A28: 25 | B28: 45802 | E28: 0 | F28: 0 | G28: =E28*F28 -> 0 | H28: 0 | I28: 0 | J28: =H28*I28 -> 0 | K28: =G28+J28 -> 0 | L28: 150000 | M28: =M27+K28-L28 -> 33626.91
A29: 26 | B29: 45803 | E29: 0 | F29: 0 | G29: =E29*F29 -> 0 | H29: 0 | I29: 0 | J29: =H29*I29 -> 0 | K29: =G29+J29 -> 0 | L29: 0 | M29: =M28+K29-L29 -> 33626.91
A30: 27 | B30: 45804 | E30: 0 | F30: 0 | G30: =E30*F30 -> 0 | H30: 0 | I30: 0 | J30: =H30*I30 -> 0 | K30: =G30+J30 -> 0 | L30: 0 | M30: =M29+K30-L30 -> 33626.91
... A34: 31 | B34: 45808 | E34: 0 | F34: 0 | G34: =E34*F34 -> 0 | H34: 0 | I34: 0 | J34: =H34*I34 -> 0 | K34: =G34+J34 -> 0 | L34: 0 | M34: =M33+K34-L34 -> 95753.51
E35: 0 | F35: 0 | G35: =E35*F35 -> 0 | H35: 0 | I35: 0 | J35: =H35*I35 -> 0 | K35: =G35+J35 -> 0 | L35: 0 | M35: =M34+K35-L35 -> 95753.51
E36: 0 | F36: 0 | G36: =E36*F36 -> 0 | H36: 0 | I36: 0 | J36: =H36*I36 -> 0 | K36: =G36+J36 -> 0 | L36: 0 | M36: =M35+K36-L36 -> 95753.51
E37: =SUM(E4:E35) -> 4600 | G37: =SUM(G4:G35) -> 434664 | H37: =SUM(H4:H35) -> 145 | J37: =SUM(J4:J35) -> 15440.3 | K37: =SUM(K4:K35) -> 450104.3 | L37: =SUM(L4:L35) -> 548000
E38: 0 | G38: 0 | H38: 0 | J38: 0 | K38: =G38+J38 -> 0 | L38: 0
S43: 9052944708

Sheet Molakamuru
A1: Molakamuru
A2: S.No | B2: Date | C2: GRN No | D2: Ind No/Bill No | E2: Diesel (Lts) | F2: Price | G2: Amount | H2: Petrol (Lts) | I2: Price | J2: Amount | K2: Total amount | L2: Amount paid | M2: As on Date | N2: Remarks
A3: Opening Balance | K3: 56291.815 | L3: 0 | M3: 56291.815
A4: 1 | B4: 46143 | G4: =E4*F4 -> 0 | J4: =H4*I4 -> 0 | K4: =G4+J4 -> 0 | M4: =M3+K4-L4 -> 56291.815
A5: 2 | B5: 46144 | G5: =E5*F5 -> 0 | J5: =H5*I5 -> 0 | K5: =G5+J5 -> 0 | M5: =M4+K5-L5 -> 56291.815
A6: 3 | B6: 46145 | G6: =E6*F6 -> 0 | J6: =H6*I6 -> 0 | K6: =G6+J6 -> 0 | M6: =M5+K6-L6 -> 56291.815
A7: 4 | B7: 46146 | G7: =E7*F7 -> 0 | J7: =H7*I7 -> 0 | K7: =G7+J7 -> 0 | L7: 56274 | M7: =M6+K7-L7 -> 17.8152
A8: 5 | B8: 46147 | G8: =E8*F8 -> 0 | J8: =H8*I8 -> 0 | K8: =G8+J8 -> 0 | M8: =M7+K8-L8 -> 17.8152
A9: 6 | B9: 46148 | G9: =E9*F9 -> 0 | J9: =H9*I9 -> 0 | K9: =G9+J9 -> 0 | M9: =M8+K9-L9 -> 17.8152
A10: 7 | B10: 46149 | E10: 300 | F10: 92.06 | G10: =E10*F10 -> 27618 | H10: 10 | I10: 103.81 | J10: =H10*I10 -> 1038.1 | K10: =G10+J10 -> 28656.1 | M10: =M9+K10-L10 -> 28673.915
A11: 8 | B11: 46150 | G11: =E11*F11 -> 0 | J11: =H11*I11 -> 0 | K11: =G11+J11 -> 0 | M11: =M10+K11-L11 -> 28673.915
A12: 9 | B12: 46151 | G12: =E12*F12 -> 0 | J12: =H12*I12 -> 0 | K12: =G12+J12 -> 0 | M12: =M11+K12-L12 -> 28673.915
A13: 10 | B13: 46152 | G13: =E13*F13 -> 0 | J13: =H13*I13 -> 0 | K13: =G13+J13 -> 0 | M13: =M12+K13-L13 -> 28673.915
A14: 11 | B14: 46153 | G14: =E14*F14 -> 0 | J14: =H14*I14 -> 0 | K14: =G14+J14 -> 0 | M14: =M13+K14-L14 -> 28673.915
A15: 12 | B15: 46154 | G15: =E15*F15 -> 0 | J15: =H15*I15 -> 0 | K15: =G15+J15 -> 0 | M15: =M14+K15-L15 -> 28673.915
A16: 13 | B16: 46155 | E16: 300 | F16: 92.06 | G16: =E16*F16 -> 27618 | J16: =H16*I16 -> 0 | K16: =G16+J16 -> 27618 | M16: =M15+K16-L16 -> 56291.915
A17: 14 | B17: 46156 | G17: =E17*F17 -> 0 | J17: =H17*I17 -> 0 | K17: =G17+J17 -> 0 | M17: =M16+K17-L17 -> 56291.915
A18: 15 | B18: 46157 | G18: =E18*F18 -> 0 | J18: =H18*I18 -> 0 | K18: =G18+J18 -> 0 | M18: =M17+K18-L18 -> 56291.915
A19: 16 | B19: 46158 | G19: =E19*F19 -> 0 | J19: =H19*I19 -> 0 | K19: =G19+J19 -> 0 | M19: =M18+K19-L19 -> 56291.915
A20: 17 | B20: 46159 | G20: =E20*F20 -> 0 | J20: =H20*I20 -> 0 | K20: =G20+J20 -> 0 | M20: =M19+K20-L20 -> 56291.915
A21: 18 | B21: 46160 | G21: =E21*F21 -> 0 | J21: =H21*I21 -> 0 | K21: =G21+J21 -> 0 | M21: =M20+K21-L21 -> 56291.915
A22: 19 | B22: 46161 | G22: =E22*F22 -> 0 | J22: =H22*I22 -> 0 | K22: =G22+J22 -> 0 | M22: =M21+K22-L22 -> 56291.915
A23: 20 | B23: 46162 | G23: =E23*F23 -> 0 | J23: =H23*I23 -> 0 | K23: =G23+J23 -> 0 | L23: 20952.94 | M23: =M22+K23-L23 -> 35338.975
A24: 21 | B24: 46163 | G24: =E24*F24 -> 0 | J24: =H24*I24 -> 0 | K24: =G24+J24 -> 0 | M24: =M23+K24-L24 -> 35338.975
A25: 22 | B25: 46164 | E25: 300 | F25: 96.11 | G25: =E25*F25 -> 28833 | H25: 20 | I25: 108.1 | J25: =H25*I25 -> 2162 | K25: =G25+J25 -> 30995 | L25: 35151 | M25: =M24+K25-L25 -> 31182.975
A26: 23 | B26: 46165 | G26: =E26*F26 -> 0 | J26: =H26*I26 -> 0 | K26: =G26+J26 -> 0 | M26: =M25+K26-L26 -> 31182.975
A27: 24 | B27: 46166 | G27: =E27*F27 -> 0 | J27: =H27*I27 -> 0 | K27: =G27+J27 -> 0 | M27: =M26+K27-L27 -> 31182.975
A28: 25 | B28: 46167 | G28: =E28*F28 -> 0 | J28: =H28*I28 -> 0 | K28: =G28+J28 -> 0 | M28: =M27+K28-L28 -> 31182.975
A29: 26 | B29: 46168 | G29: =E29*F29 -> 0 | J29: =H29*I29 -> 0 | K29: =G29+J29 -> 0 | M29: =M28+K29-L29 -> 31182.975
A30: 27 | B30: 46169 | E30: 300 | F30: 99.87 | G30: =E30*F30 -> 29961 | H30: 15 | I30: 111.78 | J30: =H30*I30 -> 1676.7 | K30: =G30+J30 -> 31637.7 | M30: =M29+K30-L30 -> 62820.675
A31: 28 | B31: 46170 | G31: =E31*F31 -> 0 | J31: =H31*I31 -> 0 | K31: =G31+J31 -> 0 | M31: =M30+K31-L31 -> 62820.675
A32: 29 | B32: 46171 | G32: =E32*F32 -> 0 | J32: =H32*I32 -> 0 | K32: =G32+J32 -> 0 | M32: =M31+K32-L32 -> 62820.675
A33: 30 | B33: 46172 | G33: =E33*F33 -> 0 | J33: =H33*I33 -> 0 | K33: =G33+J33 -> 0 | M33: =M32+K33-L33 -> 62820.675
A34: 31 | B34: 46173 | G34: =E34*F34 -> 0 | K34: =G34+J34 -> 0 | L34: 0 | M34: =M33+K34-L34 -> 62820.675
E35: =SUM(E4:E34) -> 1200 | G35: =SUM(G4:G34) -> 114030 | H35: =SUM(H4:H34) -> 45 | J35: =SUM(J4:J34) -> 4876.8 | K35: =SUM(K4:K34) -> 118906.8 | L35: =SUM(L4:L34) -> 112377.94

Sheet Chellakere -1
A1: Shivaganga Service Station (BPCL)
A2: S.No | B2: Date | C2: GRN No | D2: Ind No/Bill No | E2: Diesel (Lts) | F2: Price | G2: Amount | H2: Petrol (Lts) | I2: Price | J2: Amount | K2: Total amount | L2: Amount paid | M2: As on Date | N2: Remarks
A3: Opening Balance | K3: 249803.37 | L3: 249803.37 | M3: 249803.37
A4: 1 | B4: 46143 | G4: =E4*F4 -> 0 | J4: =H4*I4 -> 0 | K4: =G4+J4 -> 0 | M4: =M3+K4-L4 -> 249803.37
A5: 2 | B5: 46144 | G5: =E5*F5 -> 0 | J5: =H5*I5 -> 0 | K5: =G5+J5 -> 0 | M5: =M4+K5-L5 -> 249803.37
A6: 3 | B6: 46145 | G6: =E6*F6 -> 0 | J6: =H6*I6 -> 0 | K6: =G6+J6 -> 0 | M6: =M5+K6-L6 -> 249803.37 | R6: =L7+L8 -> 250340.56
A7: 4 | B7: 46146 | G7: =E7*F7 -> 0 | J7: =H7*I7 -> 0 | K7: =G7+J7 -> 0 | L7: 115094.86 | M7: =M6+K7-L7 -> 134708.51
A8: 5 | B8: 46147 | G8: =E8*F8 -> 0 | J8: =H8*I8 -> 0 | K8: =G8+J8 -> 0 | L8: 135245.7 | M8: =M7+K8-L8 -> -537.1856
A9: 6 | B9: 46148 | E9: 600.04 | F9: 92.07 | G9: =E9*F9 -> 55245.683 | H9: 35 | I9: 103.82 | J9: =H9*I9 -> 3633.7 | K9: =G9+J9 -> 58879.383 | M9: =M8+K9-L9 -> 58342.197 | Q9: 54242
A10: 7 | B10: 46149 | G10: =E10*F10 -> 0 | J10: =H10*I10 -> 0 | K10: =G10+J10 -> 0 | M10: =M9+K10-L10 -> 58342.197 | S10: 80000
A11: 8 | B11: 46150 | G11: =E11*F11 -> 0 | J11: =H11*I11 -> 0 | K11: =G11+J11 -> 0 | M11: =M10+K11-L11 -> 58342.197 | S11: 18414
A12: 9 | B12: 46151 | G12: =E12*F12 -> 0 | J12: =H12*I12 -> 0 | K12: =G12+J12 -> 0 | M12: =M11+K12-L12 -> 58342.197 | S12: 18414
A13: 10 | B13: 46152 | G13: =E13*F13 -> 0 | J13: =H13*I13 -> 0 | K13: =G13+J13 -> 0 | M13: =M12+K13-L13 -> 58342.197 | S13: 18417.68
A14: 11 | B14: 46153 | E14: 599.95 | F14: 92.07 | G14: =E14*F14 -> 55237.397 | H14: 35 | I14: 103.82 | J14: =H14*I14 -> 3633.7 | K14: =G14+J14 -> 58871.096 | M14: =M13+K14-L14 -> 117213.29 | S14: =SUM(S10:S13) -> 135245.68
A15: 12 | B15: 46154 | G15: =E15*F15 -> 0 | J15: =H15*I15 -> 0 | K15: =G15+J15 -> 0 | M15: =M14+K15-L15 -> 117213.29
A16: 13 | B16: 46155 | G16: =E16*F16 -> 0 | J16: =H16*I16 -> 0 | K16: =G16+J16 -> 0 | M16: =M15+K16-L16 -> 117213.29
A17: 14 | B17: 46156 | G17: =E17*F17 -> 0 | J17: =H17*I17 -> 0 | K17: =G17+J17 -> 0 | M17: =M16+K17-L17 -> 117213.29
A18: 15 | B18: 46157 | G18: =E18*F18 -> 0 | J18: =H18*I18 -> 0 | K18: =G18+J18 -> 0 | M18: =M17+K18-L18 -> 117213.29
A19: 16 | B19: 46158 | G19: =E19*F19 -> 0 | J19: =H19*I19 -> 0 | K19: =G19+J19 -> 0 | M19: =M18+K19-L19 -> 117213.29
A20: 17 | B20: 46159 | G20: =E20*F20 -> 0 | J20: =H20*I20 -> 0 | K20: =G20+J20 -> 0 | M20: =M19+K20-L20 -> 117213.29
A21: 18 | B21: 46160 | E21: 600 | F21: 95.18 | G21: =E21*F21 -> 57108 | H21: 35 | I21: 107.07 | J21: =H21*I21 -> 3747.45 | K21: =G21+J21 -> 60855.45 | M21: =M20+K21-L21 -> 178068.74
A22: 19 | B22: 46161 | G22: =E22*F22 -> 0 | J22: =H22*I22 -> 0 | K22: =G22+J22 -> 0 | M22: =M21+K22-L22 -> 178068.74
A23: 20 | B23: 46162 | G23: =E23*F23 -> 0 | H23: 35 | I23: 108.02 | J23: =H23*I23 -> 3780.7 | K23: =G23+J23 -> 3780.7 | M23: =M22+K23-L23 -> 181849.44
B24: 46163 | L24: 178000 | M24: =M23+K24-L24 -> 3849.4437
A25: 21 | B25: 46163 | E25: 300 | F25: 96.15 | G25: =E25*F25 -> 28845 | J25: =H25*I25 -> 0 | K25: =G25+J25 -> 28845 | L25: =H25+K25 -> 28845 | M25: =M24+K25-L25 -> 3849.4437 | N25: OCL OTP MLB
A26: 22 | B26: 46164 | E26: 300 | F26: 96.15 | G26: =E26*F26 -> 28845 | J26: =H26*I26 -> 0 | K26: =G26+J26 -> 28845 | L26: =H26+K26 -> 28845 | M26: =M25+K26-L26 -> 3849.4437
A27: 23 | B27: 46165 | G27: =E27*F27 -> 0 | J27: =H27*I27 -> 0 | K27: =G27+J27 -> 0 | M27: =M26+K27-L27 -> 3849.4437
A28: 24 | B28: 46166 | G28: =E28*F28 -> 0 | J28: =H28*I28 -> 0 | K28: =G28+J28 -> 0 | M28: =M27+K28-L28 -> 3849.4437
A29: 25 | B29: 46167 | E29: 600.09 | F29: 99.88 | G29: =E29*F29 -> 59936.989 | H29: 35 | I29: 111.79 | J29: =H29*I29 -> 3912.65 | K29: =G29+J29 -> 63849.639 | M29: =M28+K29-L29 -> 67699.083
A30: 26 | B30: 46168 | G30: =E30*F30 -> 0 | J30: =H30*I30 -> 0 | K30: =G30+J30 -> 0 | M30: =M29+K30-L30 -> 67699.083
A31: 27 | B31: 46169 | G31: =E31*F31 -> 0 | J31: =H31*I31 -> 0 | K31: =G31+J31 -> 0 | M31: =M30+K31-L31 -> 67699.083
A32: 28 | B32: 46170 | G32: =E32*F32 -> 0 | J32: =H32*I32 -> 0 | K32: =G32+J32 -> 0 | M32: =M31+K32-L32 -> 67699.083
A33: 29 | B33: 46171 | G33: =E33*F33 -> 0 | J33: =H33*I33 -> 0 | K33: =G33+J33 -> 0 | M33: =M32+K33-L33 -> 67699.083
A34: 30 | B34: 46172 | E34: 200 | F34: 99.91 | G34: =E34*F34 -> 19982 | J34: =H34*I34 -> 0 | K34: =G34+J34 -> 19982 | L34: =H34+K34 -> 19982 | M34: =M33+K34-L34 -> 67699.083 | N34: Sri Vishnu Baba Petroleum
A35: 31 | B35: 46172 | G35: =E35*F35 -> 0 | H35: 35.03 | I35: 111.79 | J35: =H35*I35 -> 3916.0037 | K35: =G35+J35 -> 3916.0037 | M35: =M34+K35-L35 -> 71615.087
E38: =SUM(E4:E35) -> 3200.08 | G38: =SUM(G4:G35) -> 305200.07 | H38: =SUM(H4:H35) -> 210.03 | J38: =SUM(J4:J35) -> 22624.204 | K38: =SUM(K4:K35) -> 327824.27 | L38: =SUM(L4:L35) -> 506012.56

Sheet  Chellakere-PKG-9
A1: Chellakere-PKG-09
A2: S.No | B2: Date | C2: GRN No | D2: Ind No/Bill No | E2: Diesel (Lts) | F2: Price | G2: Amount | H2: Petrol (Lts) | I2: Price | J2: Amount | K2: Total amount | L2: Amount paid | M2: As on Date | N2: Remarks
A3: Opening Balance | K3: 0 | L3: 0 | M3: 0
A4: 1 | B4: 46143 | E4: 30 | F4: 92.07 | G4: =E4*F4 -> 2762.1 | J4: =H4*I4 -> 0 | K4: =G4+J4 -> 2762.1 | L4: =K4 -> 2762.1 | M4: =M3+K4-L4 -> 0
A5: 2 | B5: 46144 | G5: =E5*F5 -> 0 | H5: 3 | I5: 103.82 | J5: =H5*I5 -> 311.46 | K5: =G5+J5 -> 311.46 | L5: =K5 -> 311.46 | M5: =M4+K5-L5 -> 0
A6: 3 | B6: 46145 | G6: =E6*F6 -> 0 | J6: =H6*I6 -> 0 | K6: =G6+J6 -> 0 | L6: =K6 -> 0 | M6: =M5+K6-L6 -> 0
A7: 4 | B7: 46146 | E7: 30 | F7: 92.07 | G7: =E7*F7 -> 2762.1 | J7: =H7*I7 -> 0 | K7: =G7+J7 -> 2762.1 | L7: =K7 -> 2762.1 | M7: =M6+K7-L7 -> 0
A8: 5 | B8: 46147 | E8: 70 | F8: 92.07 | G8: =E8*F8 -> 6444.9 | H8: 5 | I8: 103.82 | J8: =H8*I8 -> 519.1 | K8: =G8+J8 -> 6964 | L8: =K8 -> 6964 | M8: =M7+K8-L8 -> 0
A9: 6 | B9: 46148 | G9: =E9*F9 -> 0 | J9: =H9*I9 -> 0 | K9: =G9+J9 -> 0 | L9: =K9 -> 0 | M9: =M8+K9-L9 -> 0
A10: 7 | B10: 46149 | G10: =E10*F10 -> 0 | J10: =H10*I10 -> 0 | K10: =G10+J10 -> 0 | L10: =K10 -> 0 | M10: =M9+K10-L10 -> 0
A11: 8 | B11: 46150 | E11: 60 | F11: 92.07 | G11: =E11*F11 -> 5524.2 | J11: =H11*I11 -> 0 | K11: =G11+J11 -> 5524.2 | L11: =K11 -> 5524.2 | M11: =M10+K11-L11 -> 0
A12: 9 | B12: 46151 | G12: =E12*F12 -> 0 | J12: =H12*I12 -> 0 | K12: =G12+J12 -> 0 | L12: =K12 -> 0 | M12: =M11+K12-L12 -> 0
A13: 10 | B13: 46152 | G13: =E13*F13 -> 0 | J13: =H13*I13 -> 0 | K13: =G13+J13 -> 0 | L13: =K13 -> 0 | M13: =M12+K13-L13 -> 0
A14: 11 | B14: 46153 | E14: 30 | F14: 92.07 | G14: =E14*F14 -> 2762.1 | H14: 6 | I14: 103.82 | J14: =H14*I14 -> 622.92 | K14: =G14+J14 -> 3385.02 | L14: =K14 -> 3385.02 | M14: =M13+K14-L14 -> 0
A15: 12 | B15: 46154 | G15: =E15*F15 -> 0 | J15: =H15*I15 -> 0 | K15: =G15+J15 -> 0 | L15: =K15 -> 0 | M15: =M14+K15-L15 -> 0
A16: 13 | B16: 46155 | G16: =E16*F16 -> 0 | J16: =H16*I16 -> 0 | K16: =G16+J16 -> 0 | L16: =K16 -> 0 | M16: =M15+K16-L16 -> 0
A17: 14 | B17: 46156 | E17: 40 | F17: 92.07 | G17: =E17*F17 -> 3682.8 | J17: =H17*I17 -> 0 | K17: =G17+J17 -> 3682.8 | L17: =K17 -> 3682.8 | M17: =M16+K17-L17 -> 0
A18: 15 | B18: 46157 | E18: 37.99 | F18: 95.18 | G18: =E18*F18 -> 3615.8882 | H18: 5 | I18: 107.07 | J18: =H18*I18 -> 535.35 | K18: =G18+J18 -> 4151.2382 | L18: =K18 -> 4151.2382 | M18: =M17+K18-L18 -> 0
A19: 16 | B19: 46158 | E19: 35 | F19: 95.18 | G19: =E19*F19 -> 3331.3 | H19: 5 | I19: 107.07 | J19: =H19*I19 -> 535.35 | K19: =G19+J19 -> 3866.65 | L19: =K19 -> 3866.65 | M19: =M18+K19-L19 -> 0
A20: 17 | B20: 46159 | E20: 25 | F20: 95.18 | G20: =E20*F20 -> 2379.5 | J20: =H20*I20 -> 0 | K20: =G20+J20 -> 2379.5 | L20: =K20 -> 2379.5 | M20: =M19+K20-L20 -> 0 | T20: 54.83
A21: 18 | B21: 46160 | G21: =E21*F21 -> 0 | J21: =H21*I21 -> 0 | K21: =G21+J21 -> 0 | L21: =K21 -> 0 | M21: =M20+K21-L21 -> 0 | T21: 0.55
A22: 19 | B22: 46161 | E22: 30 | F22: 96.11 | G22: =E22*F22 -> 2883.3 | J22: =H22*I22 -> 0 | K22: =G22+J22 -> 2883.3 | L22: =K22 -> 2883.3 | M22: =M21+K22-L22 -> 0
B23: 46161 | E23: 30 | F23: 96.12 | G23: =E23*F23 -> 2883.6 | K23: =G23+J23 -> 2883.6 | L23: =K23 -> 2883.6
A24: 20 | B24: 46162 | G24: =E24*F24 -> 0 | J24: =H24*I24 -> 0 | K24: =G24+J24 -> 0 | L24: =K24 -> 0 | M24: =M22+K24-L24 -> 0
A25: 21 | B25: 46163 | E25: 42 | F25: 96.12 | G25: =E25*F25 -> 4037.04 | H25: 6 | I25: 108.02 | J25: =H25*I25 -> 648.12 | K25: =G25+J25 -> 4685.16 | L25: =K25 -> 4685.16 | M25: =M24+K25-L25 -> 0
A26: 22 | B26: 46164 | G26: =E26*F26 -> 0 | J26: =H26*I26 -> 0 | K26: =G26+J26 -> 0 | L26: =K26 -> 0 | M26: =M25+K26-L26 -> 0
A27: 23 | B27: 46165 | G27: =E27*F27 -> 0 | J27: =H27*I27 -> 0 | K27: =G27+J27 -> 0 | L27: =K27 -> 0 | M27: =M26+K27-L27 -> 0
A28: 24 | B28: 46166 | G28: =E28*F28 -> 0 | J28: =H28*I28 -> 0 | K28: =G28+J28 -> 0 | L28: =K28 -> 0 | M28: =M27+K28-L28 -> 0
A29: 25 | B29: 46167 | E29: 35 | F29: 99.88 | G29: =E29*F29 -> 3495.8 | H29: 5 | I29: 111.79 | J29: =H29*I29 -> 558.95 | K29: =G29+J29 -> 4054.75 | L29: =K29 -> 4054.75 | M29: 0
A30: 26 | B30: 46168 | G30: =E30*F30 -> 0 | J30: =H30*I30 -> 0 | K30: =G30+J30 -> 0 | L30: =K30 -> 0 | M30: 0
A31: 27 | B31: 46169 | E31: 40 | F31: 99.88 | G31: =E31*F31 -> 3995.2 | J31: =H31*I31 -> 0 | K31: =G31+J31 -> 3995.2 | L31: =K31 -> 3995.2 | M31: 0
A32: 28 | B32: 46170 | G32: =E32*F32 -> 0 | J32: =H32*I32 -> 0 | K32: =G32+J32 -> 0 | L32: =K32 -> 0 | M32: 0
A33: 29 | B33: 46171 | E33: 30.66 | F33: 99.88 | G33: 3062.3208 | H33: 5 | I33: 111.79 | J33: 558.95 | K33: =G33+J33 -> 3621.2708 | L33: =K33 -> 3621.2708
A34: 30 | B34: 46172 | G34: =E34*F34 -> 0 | H34: 6 | I34: 111.79 | J34: =H34*I34 -> 670.74 | K34: =G34+J34 -> 670.74 | L34: =K34 -> 670.74
A35: 31 | B35: 46173 | E35: 35 | F35: 99.88 | G35: =E35*F35 -> 3495.8 | J35: =H35*I35 -> 0 | K35: =G35+J35 -> 3495.8 | L35: =K35 -> 3495.8
E36: =SUM(E4:E35) -> 600.65 | G36: =SUM(G4:G35) -> 57117.949 | H36: =SUM(H4:H35) -> 46 | J36: =SUM(J4:J35) -> 4960.94 | K36: =SUM(K4:K35) -> 62078.889 | L36: =SUM(L4:L35) -> 62078.889

Sheet  Chennagiri
A1: Chennagiri
A2: S.No | B2: Date | C2: GRN No | D2: Ind No/Bill No | E2: Diesel (Lts) | F2: Price | G2: Amount | H2: Petrol (Lts) | I2: Price | J2: Amount | K2: Total amount | L2: Amount paid | M2: As on Date | N2: Remarks
A3: Opening Balance | K3: 0 | L3: 0 | M3: =+K3 -> 0
A4: 1 | B4: 46143 | G4: =E4*F4 -> 0 | J4: =H4*I4 -> 0 | K4: =G4+J4 -> 0 | L4: =K4 -> 0 | M4: =M3+K4-L4 -> 0
A5: 2 | B5: 46144 | G5: =E5*F5 -> 0 | J5: =H5*I5 -> 0 | K5: =G5+J5 -> 0 | L5: =K5 -> 0 | M5: =M4+K5-L5 -> 0
A6: 3 | B6: 46145 | G6: =E6*F6 -> 0 | J6: =H6*I6 -> 0 | K6: =G6+J6 -> 0 | L6: =K6 -> 0 | M6: =M5+K6-L6 -> 0
A7: 4 | B7: 46146 | G7: =E7*F7 -> 0 | J7: =H7*I7 -> 0 | K7: =G7+J7 -> 0 | L7: =K7 -> 0 | M7: =M6+K7-L7 -> 0
A8: 5 | B8: 46147 | E8: 200 | F8: 91.89 | G8: =E8*F8 -> 18378 | J8: =H8*I8 -> 0 | K8: =G8+J8 -> 18378 | L8: =K8 -> 18378 | M8: =M7+K8-L8 -> 0
A9: 6 | B9: 46148 | G9: =E9*F9 -> 0 | J9: =H9*I9 -> 0 | K9: =G9+J9 -> 0 | L9: =K9 -> 0 | M9: =M8+K9-L9 -> 0
A10: 7 | B10: 46149 | G10: =E10*F10 -> 0 | J10: =H10*I10 -> 0 | K10: =G10+J10 -> 0 | L10: =K10 -> 0 | M10: =M9+K10-L10 -> 0
A11: 8 | B11: 46150 | G11: =E11*F11 -> 0 | J11: =H11*I11 -> 0 | K11: =G11+J11 -> 0 | L11: =K11 -> 0 | M11: =M10+K11-L11 -> 0
A12: 9 | B12: 46151 | G12: =E12*F12 -> 0 | J12: =H12*I12 -> 0 | K12: =G12+J12 -> 0 | L12: =K12 -> 0 | M12: =M11+K12-L12 -> 0
A13: 10 | B13: 46152 | G13: =E13*F13 -> 0 | J13: =H13*I13 -> 0 | K13: =G13+J13 -> 0 | L13: =K13 -> 0 | M13: =M12+K13-L13 -> 0
A14: 11 | B14: 46153 | G14: =E14*F14 -> 0 | J14: =H14*I14 -> 0 | K14: =G14+J14 -> 0 | L14: =K14 -> 0 | M14: =M13+K14-L14 -> 0
A15: 12 | B15: 46154 | G15: =E15*F15 -> 0 | J15: =H15*I15 -> 0 | K15: =G15+J15 -> 0 | L15: =K15 -> 0 | M15: =M14+K15-L15 -> 0
A16: 13 | B16: 46155 | G16: =E16*F16 -> 0 | J16: =H16*I16 -> 0 | K16: =G16+J16 -> 0 | L16: =K16 -> 0 | M16: =M15+K16-L16 -> 0
A17: 14 | B17: 46156 | G17: =E17*F17 -> 0 | J17: =H17*I17 -> 0 | K17: =G17+J17 -> 0 | L17: =K17 -> 0 | M17: =M16+K17-L17 -> 0
A18: 15 | B18: 46157 | E18: 100 | F18: 91.91 | G18: =E18*F18 -> 9191 | J18: =H18*I18 -> 0 | K18: =G18+J18 -> 9191 | L18: =K18 -> 9191 | M18: =M17+K18-L18 -> 0
A19: 16 | B19: 46158 | G19: =E19*F19 -> 0 | J19: =H19*I19 -> 0 | K19: =G19+J19 -> 0 | L19: =K19 -> 0 | M19: =M18+K19-L19 -> 0
A20: 17 | B20: 46159 | E20: 100 | F20: 95.03 | G20: =E20*F20 -> 9503 | J20: =H20*I20 -> 0 | K20: =G20+J20 -> 9503 | L20: =K20 -> 9503 | M20: =M19+K20-L20 -> 0 | N20: HPCL
A21: 18 | B21: 46160 | E21: 105 | F21: 95 | G21: =E21*F21 -> 9975 | J21: =H21*I21 -> 0 | K21: =G21+J21 -> 9975 | L21: =K21 -> 9975 | M21: =M20+K21-L21 -> 0 | N21: HPCL
A22: 19 | B22: 46161 | G22: =E22*F22 -> 0 | J22: =H22*I22 -> 0 | K22: =G22+J22 -> 0 | L22: =K22 -> 0 | M22: =M21+K22-L22 -> 0
A23: 20 | B23: 46162 | G23: =E23*F23 -> 0 | J23: =H23*I23 -> 0 | K23: =G23+J23 -> 0 | L23: =K23 -> 0 | M23: =M22+K23-L23 -> 0
A24: 21 | B24: 46163 | G24: =E24*F24 -> 0 | J24: =H24*I24 -> 0 | K24: =G24+J24 -> 0 | L24: =K24 -> 0 | M24: =M23+K24-L24 -> 0
A25: 22 | B25: 46164 | G25: =E25*F25 -> 0 | J25: =H25*I25 -> 0 | K25: =G25+J25 -> 0 | L25: =K25 -> 0 | M25: =M24+K25-L25 -> 0
A26: 23 | B26: 46165 | E26: 100 | F26: 96.92 | G26: =E26*F26 -> 9692 | J26: =H26*I26 -> 0 | K26: =G26+J26 -> 9692 | L26: =K26 -> 9692 | M26: =M25+K26-L26 -> 0
A27: 24 | B27: 46166 | G27: =E27*F27 -> 0 | J27: =H27*I27 -> 0 | K27: =G27+J27 -> 0 | L27: =K27 -> 0 | M27: =M26+K27-L27 -> 0
A28: 25 | B28: 46167 | E28: 200 | F28: 99.7 | G28: =E28*F28 -> 19940 | H28: 44.73 | I28: 111.78 | J28: =H28*I28 -> 4999.9194 | K28: =G28+J28 -> 24939.919 | L28: =K28 -> 24939.919 | M28: 0
A29: 26 | B29: 46168 | G29: =E29*F29 -> 0 | J29: =H29*I29 -> 0 | K29: =G29+J29 -> 0 | L29: =K29 -> 0 | M29: 0
A30: 27 | B30: 46169 | G30: =E30*F30 -> 0 | J30: =H30*I30 -> 0 | K30: =G30+J30 -> 0 | L30: =K30 -> 0 | M30: 0 | N30: HPCL
A31: 28 | B31: 46170 | G31: =E31*F31 -> 0 | J31: =H31*I31 -> 0 | K31: =G31+J31 -> 0 | L31: =K31 -> 0 | M31: 0
A32: 29 | B32: 46171 | G32: =E32*F32 -> 0 | J32: =H32*I32 -> 0 | K32: =G32+J32 -> 0 | L32: =K32 -> 0
A33: 30 | B33: 46172 | E33: 160 | F33: 99.73 | G33: =E33*F33 -> 15956.8 | J33: =H33*I33 -> 0 | K33: =G33+J33 -> 15956.8 | L33: =K33 -> 15956.8
A34: 31 | B34: 46173 | G34: =E34*F34 -> 0 | K34: =G34+J34 -> 0 | L34: =K34 -> 0
E35: =SUM(E4:E34) -> 965 | G35: =SUM(G4:G34) -> 92635.8 | H35: =SUM(H4:H34) -> 44.73 | J35: =SUM(J4:J34) -> 4999.9194 | K35: =SUM(K4:K34) -> 97635.719 | L35: =SUM(L4:L34) -> 97635.719

Sheet Khanapur
A1: V.V.Varde
A2: S.No | B2: Date | C2: GRN No | D2: Ind No/Bill No | E2: Diesel (Lts) | F2: Price | G2: Amount | H2: Petrol (Lts) | I2: Price | J2: Amount | K2: Total amount | L2: Date of payment | M2: Amount paid | N2: Remarks
D3: Opening Balance | K3: 114295.13 | M3: 114295.13
A4: 1 | B4: 46143 | E4: 70 | F4: 90.88 | G4: =E4*F4 -> 6361.6 | K4: =G4+J4 -> 6361.6 | M4: =M3+K4-L4 -> 120656.73
A5: 2 | B5: 46144 | G5: =E5*F5 -> 0 | K5: =G5+J5 -> 0 | M5: =M4+K5-L5 -> 120656.73 | S5: 90.88 | T5: 102.77
A6: 3 | B6: 46145 | E6: 100 | F6: 90.88 | G6: =E6*F6 -> 9088 | K6: =G6+J6 -> 9088 | M6: =M5+K6-L6 -> 129744.73
A7: 4 | B7: 46146 | E7: 272.21 | F7: 90.88 | G7: =E7*F7 -> 24738.445 | K7: =G7+J7 -> 24738.445 | M7: =M6+K7-L7 -> 154483.18
A8: 5 | B8: 46147 | G8: =E8*F8 -> 0 | H8: 5 | I8: 102.77 | J8: =H8*I8 -> 513.85 | K8: =G8+J8 -> 513.85 | M8: =M7+K8-L8 -> 154997.03
A9: 6 | B9: 46148 | G9: =E9*F9 -> 0 | H9: 5 | I9: 102.77 | J9: =H9*I9 -> 513.85 | K9: =G9+J9 -> 513.85 | L9: 100000 | M9: =M8+K9-L9 -> 55510.876
A10: 7 | B10: 46149 | E10: 47 | F10: 90.88 | G10: =E10*F10 -> 4271.36 | J10: =H10*I10 -> 0 | K10: =G10+J10 -> 4271.36 | M10: =M9+K10-L10 -> 59782.236
A11: 8 | B11: 46150 | E11: 120 | F11: 90.88 | G11: =E11*F11 -> 10905.6 | J11: =H11*I11 -> 0 | K11: =G11+J11 -> 10905.6 | M11: =M10+K11-L11 -> 70687.836
A12: 9 | B12: 46151 | G12: =E12*F12 -> 0 | H12: 0 | I12: 102.77 | J12: =H12*I12 -> 0 | K12: =G12+J12 -> 0 | M12: =M11+K12-L12 -> 70687.836
A13: 10 | B13: 46152 | G13: =E13*F13 -> 0 | J13: =H13*I13 -> 0 | K13: =G13+J13 -> 0 | M13: =M12+K13-L13 -> 70687.836
A14: 11 | B14: 46153 | E14: 34 | F14: 90.88 | G14: =E14*F14 -> 3089.92 | H14: 10 | I14: 102.77 | J14: =H14*I14 -> 1027.7 | K14: =G14+J14 -> 4117.62 | M14: =M13+K14-L14 -> 74805.456
A15: 12 | B15: 46154 | E15: 48.4 | F15: 90.88 | G15: =E15*F15 -> 4398.592 | J15: =H15*I15 -> 0 | K15: =G15+J15 -> 4398.592 | M15: =M14+K15-L15 -> 79204.048
A16: 13 | B16: 46155 | E16: 123.46 | F16: 90.88 | G16: =E16*F16 -> 11220.045 | H16: 20 | I16: 102.77 | J16: =H16*I16 -> 2055.4 | K16: =G16+J16 -> 13275.445 | M16: =M15+K16-L16 -> 92479.493
A17: 14 | B17: 46156 | E17: 40 | F17: 90.88 | G17: =E17*F17 -> 3635.2 | K17: =G17+J17 -> 3635.2 | M17: =M16+K17-L17 -> 96114.693
A18: 15 | B18: 46157 | K18: =G18+J18 -> 0 | M18: =M17+K18-L18 -> 96114.693
A19: 16 | B19: 46158 | E19: 58 | F19: 94 | G19: =E19*F19 -> 5452 | H19: 5 | I19: 106.02 | J19: =H19*I19 -> 530.1 | K19: =G19+J19 -> 5982.1 | M19: =M18+K19-L19 -> 102096.79
A20: 17 | B20: 46159 | E20: 30 | F20: 94 | G20: =E20*F20 -> 2820 | H20: 5 | I20: 106.02 | J20: =H20*I20 -> 530.1 | K20: =G20+J20 -> 3350.1 | M20: =M19+K20-L20 -> 105446.89 | O20: 16.68
A21: 18 | B21: 46160 | E21: 50 | F21: 94 | G21: =E21*F21 -> 4700 | J21: =H21*I21 -> 0 | K21: =G21+J21 -> 4700 | M21: =M20+K21-L21 -> 110146.89
A22: 19 | B22: 46161 | E22: 20 | F22: 94.94 | G22: =E22*F22 -> 1898.8 | H22: 10 | I22: 106.97 | J22: =H22*I22 -> 1069.7 | K22: =G22+J22 -> 2968.5 | M22: =M21+K22-L22 -> 113115.39
A23: 20 | B23: 46162 | E23: 145.8 | F23: 94.94 | G23: =E23*F23 -> 13842.252 | J23: =H23*I23 -> 0 | K23: =G23+J23 -> 13842.252 | M23: =M22+K23-L23 -> 126957.64 | N23: 0
A24: 21 | B24: 46163 | E24: 21.06 | F24: 94.94 | G24: =E24*F24 -> 1999.4364 | J24: =H24*I24 -> 0 | K24: =G24+J24 -> 1999.4364 | L24: 2000 | M24: =M23+K24-L24 -> 126957.08
A25: 22 | B25: 46164 | E25: 30 | F25: 94.94 | G25: =E25*F25 -> 2848.2 | H25: 10 | I25: 106.97 | J25: =H25*I25 -> 1069.7 | K25: =G25+J25 -> 3917.9 | M25: =M24+K25-L25 -> 130874.98
A26: 23 | B26: 46165 | E26: 314.08 | F26: 95.88 | G26: =E26*F26 -> 30113.99 | J26: =H26*I26 -> 0 | K26: =G26+J26 -> 30113.99 | M26: =M25+K26-L26 -> 160988.97
A27: 24 | B27: 46166 | G27: =E27*F27 -> 0 | J27: =H27*I27 -> 0 | K27: =G27+J27 -> 0 | M27: =M26+K27-L27 -> 160988.97
A28: 25 | B28: 46167 | E28: 35.52 | F28: 98.69 | G28: =E28*F28 -> 3505.4688 | H28: 10 | I28: 110.74 | J28: =H28*I28 -> 1107.4 | K28: =G28+J28 -> 4612.8688 | L28: 120000 | M28: =M27+K28-L28 -> 45601.84
A29: 26 | B29: 46168 | E29: 60.4 | F29: 98.69 | G29: =F29*E29 -> 5960.876 | H29: 5 | I29: 110.74 | J29: =H29*I29 -> 553.7 | K29: =G29+J29 -> 6514.576 | L29: 6514.576 | M29: =M28+K29-L29 -> 45601.84
A30: 27 | B30: 46169 | E30: 106.02 | F30: 98.69 | G30: =F30*E30 -> 10463.114 | J30: =H30*I30 -> 0 | K30: =G30+J30 -> 10463.114 | M30: =M29+K30-L30 -> 56064.954
A31: 28 | B31: 46170 | G31: =F31*E31 -> 0 | J31: =H31*I31 -> 0 | K31: =G31+J31 -> 0 | M31: =M30+K31-L31 -> 56064.954
A32: 29 | B32: 46171 | E32: 30 | F32: 98.69 | G32: =F32*E32 -> 2960.7 | J32: =H32*I32 -> 0 | K32: =G32+J32 -> 2960.7 | M32: =M31+K32-L32 -> 59025.654
A33: 30 | B33: 46172 | G33: =F33*E33 -> 0 | J33: =H33*I33 -> 0 | K33: =G33+J33 -> 0 | M33: =M32+K33-L33 -> 59025.654
A34: 31 | B34: 46173 | G34: =F34*E34 -> 0 | J34: =H34*I34 -> 0 | K34: =G34+J34 -> 0 | M34: =M33+K34-L34 -> 59025.654
E35: =SUM(E4:E34) -> 1755.95 | G35: =SUM(G4:G34) -> 164273.6 | H35: =SUM(H4:H34) -> 85 | J35: =SUM(J4:J34) -> 8971.5 | K35: =SUM(K4:K34) -> 173245.1 | L35: =SUM(L4:L34) -> 228514.58 | M35: =SUM(M4:M34) -> 2964597.6

Sheet Munavali-2
A1: Shiri Shiva Petroluem
A2: S.No | B2: Date | C2: GRN No | D2: Ind No/Bill No | E2: Diesel (Lts) | F2: Price | G2: Amount | H2: Petrol (Lts) | I2: Price | J2: Amount | K2: Total amount | L2: Amount paid | M2: As on date | N2: Remarks
D3: Opening Balance | K3: 567608.01 | M3: 567608.01 | O3: 26506.4
A4: 1 | B4: 46143 | G4: =E4*F4 -> 0 | J4: =H4*I4 -> 0 | K4: =G4+J4 -> 0 | M4: =M3+K4-L4 -> 567608.01
A5: 2 | B5: 46144 | E5: 500 | F5: 91.51 | G5: =E5*F5 -> 45755 | H5: 4.83 | I5: 103.44 | J5: =H5*I5 -> 499.6152 | K5: =G5+J5 -> 46254.615 | L5: 46254.615 | M5: =M4+K5-L5 -> 567608.01 | N5: HPCl
A6: 3 | B6: 46145 | E6: 300 | F6: 91.54 | G6: =E6*F6 -> 27462 | J6: =H6*I6 -> 0 | K6: =G6+J6 -> 27462 | M6: =M5+K6-L6 -> 595070.01
A7: 4 | B7: 46146 | E7: 300 | F7: 91.54 | G7: =E7*F7 -> 27462 | H7: 4.83 | I7: 103.44 | J7: =H7*I7 -> 499.6152 | K7: =G7+J7 -> 27961.615 | L7: 567499 | M7: =M6+K7-L7 -> 55532.62
A8: 5 | B8: 46147 | E8: 300 | F8: 91.54 | G8: =E8*F8 -> 27462 | H8: 4.83 | I8: 103.44 | J8: =H8*I8 -> 499.6152 | K8: =G8+J8 -> 27961.615 | L8: 499.6152 | M8: =M7+K8-L8 -> 82994.62 | R8: SAI SHIVA FILLING STATION
A9: 6 | B9: 46148 | E9: 300 | F9: 91.54 | G9: =E9*F9 -> 27462 | H9: 24.15 | I9: 103.44 | J9: =H9*I9 -> 2498.076 | K9: =G9+J9 -> 29960.076 | L9: 2498.076 | M9: =M8+K9-L9 -> 110456.62
A10: 7 | B10: 46149 | E10: 300 | F10: 91.54 | G10: =E10*F10 -> 27462 | J10: =H10*I10 -> 0 | K10: =G10+J10 -> 27462 | M10: =M9+K10-L10 -> 137918.62 | R10: =PROPER(R8) -> Sai Shiva Filling Station
B11: 46150 | E11: 300 | F11: 91.54 | G11: =E11*F11 -> 27462 | H11: 14.49 | I11: 103.44 | J11: =H11*I11 -> 1498.8456 | K11: =G11+J11 -> 28960.846 | L11: 1498.8456 | M11: =M10+K11-L11 -> 165380.62
A12: 8 | B12: 46151 | E12: 575 | F12: 91.54 | G12: =E12*F12 -> 52635.5 | H12: 4.83 | I12: 103.44 | J12: =H12*I12 -> 499.6152 | K12: =G12+J12 -> 53135.115 | L12: 499.6152 | M12: =M11+K12-L12 -> 218016.12
A13: 9 | B13: 46152 | E13: 300 | F13: 91.54 | G13: =E13*F13 -> 27462 | H13: 4.83 | I13: 103.44 | J13: =H13*I13 -> 499.6152 | K13: =G13+J13 -> 27961.615 | L13: 499.6152 | M13: =M12+K13-L13 -> 245478.12
A14: 10 | B14: 46153 | E14: 375 | F14: 91.54 | G14: =E14*F14 -> 34327.5 | H14: 4.83 | I14: 103.44 | J14: =H14*I14 -> 499.6152 | K14: =G14+J14 -> 34827.115 | L14: 499.6152 | M14: =M13+K14-L14 -> 279805.62
A15: 11 | B15: 46154 | E15: 500 | F15: 91.54 | G15: =E15*F15 -> 45770 | H15: 14.49 | I15: 103.44 | J15: =H15*I15 -> 1498.8456 | K15: =G15+J15 -> 47268.846 | L15: 1498.8456 | M15: =M14+K15-L15 -> 325575.62
A16: 12 | B16: 46155 | E16: 300 | F16: 91.54 | G16: =E16*F16 -> 27462 | H16: 4.83 | I16: 103.44 | J16: =H16*I16 -> 499.6152 | K16: =G16+J16 -> 27961.615 | L16: 499.6152 | M16: =M15+K16-L16 -> 353037.62
B17: 46155 | E17: 100 | F17: 91.19 | G17: =E17*F17 -> 9119 | K17: =G17+J17 -> 9119 | L17: 9119 | M17: =M16+K17-L17 -> 353037.62
A18: 13 | B18: 46156 | D18: 0 | E18: 300 | F18: 91.54 | G18: =E18*F18 -> 27462 | H18: 24.15 | I18: 103.44 | J18: =H18*I18 -> 2498.076 | K18: =G18+J18 -> 29960.076 | L18: 2498.076 | M18: =M17+K18-L18 -> 380499.62
A19: 14 | B19: 46157 | E19: 300 | F19: 94.66 | G19: =E19*F19 -> 28398 | H19: 9.38 | I19: 106.7 | J19: =H19*I19 -> 1000.846 | K19: =G19+J19 -> 29398.846 | L19: 1000.846 | M19: =M18+K19-L19 -> 408897.62
A20: 15 | B20: 46158 | E20: 300 | F20: 94.66 | G20: =E20*F20 -> 28398 | H20: 9.69 | I20: 106.7 | J20: =H20*I20 -> 1033.923 | K20: =G20+J20 -> 29431.923 | L20: 1033.923 | M20: =M19+K20-L20 -> 437295.62
A21: 16 | B21: 46159 | E21: 300 | F21: 94.66 | G21: =E21*F21 -> 28398 | J21: =H21*I21 -> 0 | K21: =G21+J21 -> 28398 | M21: =M20+K21-L21 -> 465693.62
A22: 17 | B22: 46160 | E22: 300 | F22: 94.66 | G22: =E22*F22 -> 28398 | H22: 4.69 | I22: 106.7 | J22: =H22*I22 -> 500.423 | K22: =G22+J22 -> 28898.423 | L22: 500.423 | M22: =M21+K22-L22 -> 494091.62
B23: 46160 | E23: 0 | F23: 0 | G23: 0 | H23: 0 | I23: 0 | J23: 0 | K23: 0 | L23: 300000 | M23: =M22+K23-L23 -> 194091.62
A24: 18 | B24: 46161 | E24: 300 | F24: 95.6 | G24: =E24*F24 -> 28680 | H24: 9.3 | I24: 107.64 | J24: =H24*I24 -> 1001.052 | K24: =G24+J24 -> 29681.052 | L24: 1001.052 | M24: =M23+K24-L24 -> 222771.62
A25: 19 | B25: 46162 | E25: 300 | F25: 95.6 | G25: =E25*F25 -> 28680 | H25: 18.6 | I25: 107.64 | J25: =H25*I25 -> 2002.104 | K25: =G25+J25 -> 30682.104 | L25: 2002.104 | M25: =M24+K25-L25 -> 251451.62
A26: 20 | B26: 46163 | E26: 300 | F26: 95.6 | G26: =E26*F26 -> 28680 | J26: =H26*I26 -> 0 | K26: =G26+J26 -> 28680 | M26: =M25+K26-L26 -> 280131.62
A27: 21 | B27: 46164 | E27: 300 | F27: 95.6 | G27: =E27*F27 -> 28680 | J27: =H27*I27 -> 0 | K27: =G27+J27 -> 28680 | L27: 100000 | M27: =M26+K27-L27 -> 208811.62
A28: 22 | B28: 46165 | E28: 300 | F28: 95.6 | G28: =E28*F28 -> 28680 | J28: =H28*I28 -> 0 | K28: =G28+J28 -> 28680 | M28: =M27+K28-L28 -> 237491.62
A29: 23 | B29: 46166 | E29: 300 | F29: 95.6 | G29: =E29*F29 -> 28680 | J29: =H29*I29 -> 0 | K29: =G29+J29 -> 28680 | M29: =M28+K29-L29 -> 266171.62
A30: 24 | B30: 46167 | E30: 300 | F30: 99.35 | G30: =E30*F30 -> 29805 | J30: =H30*I30 -> 0 | K30: =G30+J30 -> 29805 | M30: =M29+K30-L30 -> 295976.62
A31: 25 | B31: 46168 | E31: 300 | F31: 99.35 | G31: =E31*F31 -> 29805 | J31: =H31*I31 -> 0 | K31: =G31+J31 -> 29805 | M31: =M30+K31-L31 -> 325781.62
A32: 26 | B32: 46169 | E32: 300 | F32: 99.35 | G32: =E32*F32 -> 29805 | J32: =H32*I32 -> 0 | K32: =G32+J32 -> 29805 | M32: =M31+K32-L32 -> 355586.62 | Q32: 166834
A33: 27 | B33: 46170 | E33: 300 | F33: 99.35 | G33: =E33*F33 -> 29805 | J33: =H33*I33 -> 0 | K33: =G33+J33 -> 29805 | M33: =M32+K33-L33 -> 385391.62
A34: 28 | B34: 46171 | E34: 300 | F34: 99.35 | G34: =E34*F34 -> 29805 | J34: =H34*I34 -> 0 | K34: =G34+J34 -> 29805 | M34: =M33+K34-L34 -> 415196.62
A35: 29 | B35: 46172 | G35: =E35*F35 -> 0 | J35: =H35*I35 -> 0 | K35: =G35+J35 -> 0 | M35: =M34+K35-L35 -> 415196.62
A36: 30 | B36: 46173 | E36: 300 | F36: 99.35 | G36: =E36*F36 -> 29805 | J36: =H36*I36 -> 0 | K36: =G36+J36 -> 29805 | M36: =M35+K36-L36 -> 445001.62
A37: 31 | B37: 46174 | G37: =E37*F37 -> 0 | J37: =H37*I37 -> 0 | K37: =G37+J37 -> 0 | M37: =M36+K37-L37 -> 445001.62
A38: 32 | G38: =E38*F38 -> 0 | J38: =H38*I38 -> 0 | K38: =G38+J38 -> 0 | M38: =M37+K38-L38 -> 445001.62
A39: 33 | G39: =E39*F39 -> 0 | J39: =H39*I39 -> 0 | K39: =G39+J39 -> 0 | M39: =M38+K39-L39 -> 445001.62
E40: =SUM(E4:E39) -> 9550 | G40: =SUM(G4:G39) -> 899267 | H40: =SUM(H4:H39) -> 162.75 | J40: =SUM(J4:J39) -> 17029.498 | K40: =SUM(K4:K39) -> 916296.5 | L40: =SUM(L4:L39) -> 1038902.9

Sheet  Munavali
A1: DANESHWARI PETROLIUM(YERRAGATTI)
A2: S.No | B2: Date | C2: GRN No | D2: Ind No/Bill No | E2: Diesel (Lts) | F2: Price | G2: Amount | H2: Petrol (Lts) | I2: Price | J2: Amount | K2: Total amount | L2: Amount paid | M2: As on date | N2: Remarks
D3: Opening Balance | K3: 0 | M3: 0 | O3: 26506.4
A4: 1 | B4: 46143 | G4: =E4*F4 -> 0 | J4: =H4*I4 -> 0 | K4: =G4+J4 -> 0 | M4: =M3+K4-L4 -> 0
A5: 2 | B5: 46144 | G5: =E5*F5 -> 0 | J5: =H5*I5 -> 0 | K5: =G5+J5 -> 0 | M5: =M4+K5-L5 -> 0 | N5: HPCl
A6: 3 | B6: 46145 | G6: =E6*F6 -> 0 | J6: =H6*I6 -> 0 | K6: =G6+J6 -> 0 | M6: =M5+K6-L6 -> 0
A7: 4 | B7: 46146 | G7: =E7*F7 -> 0 | J7: =H7*I7 -> 0 | K7: =G7+J7 -> 0 | M7: =M6+K7-L7 -> 0
A8: 5 | B8: 46147 | G8: =E8*F8 -> 0 | J8: =H8*I8 -> 0 | K8: =G8+J8 -> 0 | M8: =M7+K8-L8 -> 0 | R8: SAI SHIVA FILLING STATION
A9: 6 | B9: 46148 | G9: =E9*F9 -> 0 | J9: =H9*I9 -> 0 | K9: =G9+J9 -> 0 | M9: =M8+K9-L9 -> 0
A10: 7 | B10: 46149 | G10: =E10*F10 -> 0 | J10: =H10*I10 -> 0 | K10: =G10+J10 -> 0 | M10: =M9+K10-L10 -> 0 | R10: =PROPER(R8) -> Sai Shiva Filling Station
A11: 8 | B11: 46150 | G11: =E11*F11 -> 0 | J11: =H11*I11 -> 0 | K11: =G11+J11 -> 0 | M11: =M10+K11-L11 -> 0
A12: 9 | B12: 46151 | G12: =E12*F12 -> 0 | J12: =H12*I12 -> 0 | K12: =G12+J12 -> 0 | M12: =M11+K12-L12 -> 0
A13: 10 | B13: 46152 | G13: =E13*F13 -> 0 | J13: =H13*I13 -> 0 | K13: =G13+J13 -> 0 | M13: =M12+K13-L13 -> 0
A14: 11 | B14: 46153 | G14: =E14*F14 -> 0 | J14: =H14*I14 -> 0 | K14: =G14+J14 -> 0 | M14: =M13+K14-L14 -> 0
A15: 12 | B15: 46154 | G15: =E15*F15 -> 0 | J15: =H15*I15 -> 0 | K15: =G15+J15 -> 0 | M15: =M14+K15-L15 -> 0
A16: 13 | B16: 46155 | G16: =E16*F16 -> 0 | J16: =H16*I16 -> 0 | K16: =G16+J16 -> 0 | M16: =M15+K16-L16 -> 0
A17: 14 | B17: 46155 | G17: =E17*F17 -> 0 | J17: =H17*I17 -> 0 | K17: =G17+J17 -> 0 | M17: =M16+K17-L17 -> 0
A18: 15 | B18: 46156 | D18: 0 | G18: =E18*F18 -> 0 | J18: =H18*I18 -> 0 | K18: =G18+J18 -> 0 | M18: =M17+K18-L18 -> 0
A19: 16 | B19: 46157 | G19: =E19*F19 -> 0 | J19: =H19*I19 -> 0 | K19: =G19+J19 -> 0 | M19: =M18+K19-L19 -> 0
A20: 17 | B20: 46158 | E20: 600 | F20: 94.43 | G20: =E20*F20 -> 56658 | J20: =H20*I20 -> 0 | K20: =G20+J20 -> 56658 | M20: =M19+K20-L20 -> 56658
A21: 18 | B21: 46159 | E21: 400 | F21: 94.43 | G21: =E21*F21 -> 37772 | J21: =H21*I21 -> 0 | K21: =G21+J21 -> 37772 | M21: =M20+K21-L21 -> 94430
A22: 19 | B22: 46160 | E22: 400 | F22: 94.43 | G22: =E22*F22 -> 37772 | J22: =H22*I22 -> 0 | K22: =G22+J22 -> 37772 | M22: =M21+K22-L22 -> 132202
A23: 20 | B23: 46161 | E23: 500 | F23: 95.37 | G23: =E23*F23 -> 47685 | J23: 0 | K23: =G23+J23 -> 47685 | M23: =M22+K23-L23 -> 179887
A24: 22 | B24: 46162 | E24: 300 | F24: 95.37 | G24: =E24*F24 -> 28611 | H24: 20 | I24: 107.44 | J24: =H24*I24 -> 2148.8 | K24: =G24+J24 -> 30759.8 | M24: =M23+K24-L24 -> 210646.8
A25: 23 | B25: 46163 | E25: 200 | F25: 95.37 | G25: =E25*F25 -> 19074 | J25: =H25*I25 -> 0 | K25: =G25+J25 -> 19074 | M25: =M24+K25-L25 -> 229720.8
A26: 24 | B26: 46164 | E26: 600 | F26: 95.37 | G26: =E26*F26 -> 57222 | J26: =H26*I26 -> 0 | K26: =G26+J26 -> 57222 | M26: =M25+K26-L26 -> 286942.8
A27: 25 | B27: 46165 | E27: 500 | F27: 96.32 | G27: =E27*F27 -> 48160 | H27: 20 | I27: 107.44 | J27: =H27*I27 -> 2148.8 | K27: =G27+J27 -> 50308.8 | M27: =M26+K27-L27 -> 337251.6
A28: 26 | B28: 46166 | E28: 200 | F28: 96.32 | G28: =E28*F28 -> 19264 | J28: =H28*I28 -> 0 | K28: =G28+J28 -> 19264 | L28: 0 | M28: =M27+K28-L28 -> 356515.6
A29: 27 | B29: 46167 | E29: 141.67 | F29: 99.13 | G29: =E29*F29 -> 14043.747 | H29: 20 | I29: 111.21 | J29: =H29*I29 -> 2224.2 | K29: =G29+J29 -> 16267.947 | L29: 300000 | M29: =M28+K29-L29 -> 72783.547
A30: 28 | B30: 46168 | G30: =E30*F30 -> 0 | H30: 20 | I30: 111.21 | J30: =H30*I30 -> 2224.2 | K30: =G30+J30 -> 2224.2 | M30: =M29+K30-L30 -> 75007.747
A31: 29 | B31: 46169 | E31: 400 | F31: 99.13 | G31: =E31*F31 -> 39652 | J31: =H31*I31 -> 0 | K31: =G31+J31 -> 39652 | M31: =M30+K31-L31 -> 114659.75 | Q31: 166834
A32: 30 | B32: 46170 | E32: 200 | F32: 99.13 | G32: =E32*F32 -> 19826 | J32: =H32*I32 -> 0 | K32: =G32+J32 -> 19826 | M32: =M31+K32-L32 -> 134485.75
A33: 31 | B33: 46171 | E33: 500 | F33: 99.13 | G33: =E33*F33 -> 49565 | H33: 20 | I33: 111.21 | J33: =H33*I33 -> 2224.2 | K33: =G33+J33 -> 51789.2 | M33: =M32+K33-L33 -> 186274.95
A34: 32 | B34: 46172 | E34: 600 | F34: 99.13 | G34: =E34*F34 -> 59478 | H34: 20 | I34: 111.21 | J34: =H34*I34 -> 2224.2 | K34: =G34+J34 -> 61702.2 | M34: =M33+K34-L34 -> 247977.15
A35: 33 | B35: 46173 | E35: 300 | F35: 99.13 | G35: =E35*F35 -> 29739 | J35: =H35*I35 -> 0 | K35: =G35+J35 -> 29739 | M35: =M34+K35-L35 -> 277716.15
A36: 34 | B36: 46174 | G36: =E36*F36 -> 0 | J36: =H36*I36 -> 0 | K36: =G36+J36 -> 0 | M36: =M35+K36-L36 -> 277716.15
A37: 35 | G37: =E37*F37 -> 0 | J37: =H37*I37 -> 0 | K37: =G37+J37 -> 0 | M37: =M36+K37-L37 -> 277716.15
A38: 36 | G38: =E38*F38 -> 0 | J38: =H38*I38 -> 0 | K38: =G38+J38 -> 0 | M38: =M37+K38-L38 -> 277716.15
E39: =SUM(E4:E38) -> 5841.67 | G39: =SUM(G4:G38) -> 564521.75 | H39: =SUM(H4:H38) -> 120 | J39: =SUM(J4:J38) -> 13194.4 | K39: =SUM(K4:K38) -> 577716.15 | L39: =SUM(L4:L38) -> 300000

Sheet Borgaon
A1: Aadisagar Petrolium
A2: S.No | B2: Date | C2: GRN No | D2: Ind no/Bill No | E2: Diesel (Lts) | F2: Price | G2: Amount | H2: Petrol (Lts) | I2: Price | J2: Amount | K2: Total amount | L2: Amount paid | M2: As on Date | N2: Remarks
A3: Opening Balance | K3: 106655.39 | M3: 106655.39
A4: 1 | B4: 46143 | E4: 70 | F4: 91.77 | G4: =E4*F4 -> 6423.9 | J4: =H4*I4 -> 0 | K4: =G4+J4 -> 6423.9 | M4: =M3+K4-L4 -> 113079.29
A5: 2 | B5: 46144 | E5: 299.06 | F5: 91.77 | G5: =E5*F5 -> 27444.736 | J5: =H5*I5 -> 0 | K5: =G5+J5 -> 27444.736 | M5: =M4+K5-L5 -> 140524.02
A6: 3 | B6: 46145 | E6: 170 | F6: 91.77 | G6: =E6*F6 -> 15600.9 | H6: 10 | I6: 103.73 | J6: =H6*I6 -> 1037.3 | K6: =G6+J6 -> 16638.2 | M6: =M5+K6-L6 -> 157162.22
A7: 4 | B7: 46146 | G7: =E7*F7 -> 0 | J7: =H7*I7 -> 0 | K7: =G7+J7 -> 0 | L7: 150000 | M7: =M6+K7-L7 -> 7162.2246
A8: 5 | B8: 46147 | E8: 187.33 | F8: 91.77 | G8: =E8*F8 -> 17191.274 | J8: =H8*I8 -> 0 | K8: =G8+J8 -> 17191.274 | M8: =M7+K8-L8 -> 24353.499
A9: 6 | B9: 46148 | E9: 105 | F9: 91.77 | G9: =E9*F9 -> 9635.85 | J9: =H9*I9 -> 0 | K9: =G9+J9 -> 9635.85 | M9: =M8+K9-L9 -> 33989.349
A10: 7 | B10: 46149 | E10: 170 | F10: 91.77 | G10: =E10*F10 -> 15600.9 | J10: =H10*I10 -> 0 | K10: =G10+J10 -> 15600.9 | M10: =M9+K10-L10 -> 49590.249
A11: 8 | B11: 46150 | E11: 50 | F11: 91.77 | G11: =E11*F11 -> 4588.5 | J11: =H11*I11 -> 0 | K11: =G11+J11 -> 4588.5 | M11: =M10+K11-L11 -> 54178.749
A12: 9 | B12: 46151 | E12: 140 | F12: 91.77 | G12: =E12*F12 -> 12847.8 | H12: 6 | I12: 103.73 | J12: =H12*I12 -> 622.38 | K12: =G12+J12 -> 13470.18 | M12: =M11+K12-L12 -> 67648.929
A13: 10 | B13: 46152 | E13: 90 | F13: 91.77 | G13: =E13*F13 -> 8259.3 | H13: 10 | I13: 103.73 | J13: =H13*I13 -> 1037.3 | K13: =G13+J13 -> 9296.6 | M13: =M12+K13-L13 -> 76945.529
A14: 11 | B14: 46153 | E14: 125 | F14: 91.77 | G14: =E14*F14 -> 11471.25 | H14: 0 | I14: 103.73 | J14: =H14*I14 -> 0 | K14: =G14+J14 -> 11471.25 | M14: =M13+K14-L14 -> 88416.779
A15: 12 | B15: 46154 | E15: 180 | F15: 91.77 | G15: =E15*F15 -> 16518.6 | J15: =H15*I15 -> 0 | K15: =G15+J15 -> 16518.6 | M15: =M14+K15-L15 -> 104935.38
A16: 13 | B16: 46155 | E16: 140 | F16: 91.77 | G16: =E16*F16 -> 12847.8 | J16: =H16*I16 -> 0 | K16: =G16+J16 -> 12847.8 | L16: 100000 | M16: =M15+K16-L16 -> 17783.179
A17: 14 | B17: 46156 | E17: 230 | F17: 91.77 | G17: =E17*F17 -> 21107.1 | H17: 6 | I17: 103.73 | J17: =H17*I17 -> 622.38 | K17: =G17+J17 -> 21729.48 | M17: =M16+K17-L17 -> 39512.659
A18: 15 | B18: 46157 | E18: 190 | F18: 94.89 | G18: =E18*F18 -> 18029.1 | H18: 10 | I18: 106.99 | J18: =H18*I18 -> 1069.9 | K18: =G18+J18 -> 19099 | M18: =M17+K18-L18 -> 58611.659
A19: 16 | B19: 46158 | E19: 305 | F19: 94.89 | G19: =E19*F19 -> 28941.45 | J19: =H19*I19 -> 0 | K19: =G19+J19 -> 28941.45 | M19: =M18+K19-L19 -> 87553.109
A20: 17 | B20: 46159 | E20: 10 | F20: 94.89 | G20: =E20*F20 -> 948.9 | H20: 5 | I20: 106.99 | J20: =H20*I20 -> 534.95 | K20: =G20+J20 -> 1483.85 | M20: =M19+K20-L20 -> 89036.959
A21: 18 | B21: 46160 | E21: 71.54 | F21: 94.89 | G21: =E21*F21 -> 6788.4306 | J21: =H21*I21 -> 0 | K21: =G21+J21 -> 6788.4306 | M21: =M20+K21-L21 -> 95825.389
A22: 19 | B22: 46161 | E22: 95 | F22: 95.83 | G22: =E22*F22 -> 9103.85 | H22: 6 | I22: 107.93 | J22: =H22*I22 -> 647.58 | K22: =G22+J22 -> 9751.43 | M22: =M21+K22-L22 -> 105576.82
A23: 20 | B23: 46162 | E23: 439.5 | F23: 95.83 | G23: =E23*F23 -> 42117.285 | J23: =H23*I23 -> 0 | K23: =G23+J23 -> 42117.285 | M23: =M22+K23-L23 -> 147694.1
A24: 21 | B24: 46163 | G24: =E24*F24 -> 0 | J24: =H24*I24 -> 0 | K24: =G24+J24 -> 0 | L24: 95000 | M24: =M23+K24-L24 -> 52694.104
A25: 22 | B25: 46164 | E25: 270.8 | F25: 95.83 | G25: =E25*F25 -> 25950.764 | H25: 6 | I25: 107.93 | J25: =H25*I25 -> 647.58 | K25: =G25+J25 -> 26598.344 | M25: =M24+K25-L25 -> 79292.448
A26: 23 | B26: 46165 | E26: 255.72 | F26: 96.77 | G26: =E26*F26 -> 24746.024 | J26: =H26*I26 -> 0 | K26: =G26+J26 -> 24746.024 | M26: =M25+K26-L26 -> 104038.47 | Q26: d
A27: 24 | B27: 46166 | E27: 190 | F27: 96.77 | G27: =E27*F27 -> 18386.3 | H27: 11 | I27: 108.87 | J27: =H27*I27 -> 1197.57 | K27: =G27+J27 -> 19583.87 | M27: =M26+K27-L27 -> 123622.34 | Q27: 30 | R27: 50
A28: 25 | B28: 46167 | E28: 363.75 | F28: 99.58 | G28: =E28*F28 -> 36222.225 | J28: =H28*I28 -> 0 | K28: =G28+J28 -> 36222.225 | L28: 40000 | M28: =M27+K28-L28 -> 119844.57 | Q28: 50 | R28: 4.51
A29: 26 | B29: 46168 | E29: 312.85 | F29: 99.58 | G29: =E29*F29 -> 31153.603 | J29: =H29*I29 -> 0 | K29: =G29+J29 -> 31153.603 | M29: =M28+K29-L29 -> 150998.17
A30: 27 | B30: 46169 | E30: 250 | F30: 99.58 | G30: =E30*F30 -> 24895 | H30: 6 | I30: 108.87 | J30: =H30*I30 -> 653.22 | K30: =G30+J30 -> 25548.22 | M30: =M29+K30-L30 -> 176546.39
A31: 28 | B31: 46170 | E31: 250 | F31: 99.58 | G31: =E31*F31 -> 24895 | J31: =H31*I31 -> 0 | K31: =G31+J31 -> 24895 | M31: =M30+K31-L31 -> 201441.39
A32: 29 | B32: 46171 | E32: 500 | F32: 99.58 | G32: =E32*F32 -> 49790 | J32: =H32*I32 -> 0 | K32: =G32+J32 -> 49790 | M32: =M31+K32-L32 -> 251231.39
A33: 30 | B33: 46172 | E33: 250 | F33: 99.58 | G33: =E33*F33 -> 24895 | J33: =H33*I33 -> 0 | K33: =G33+J33 -> 24895 | M33: =M32+K33-L33 -> 276126.39
A34: 31 | B34: 46173 | G34: =E34*F34 -> 0 | J34: =H34*I34 -> 0 | K34: =G34+J34 -> 0 | M34: =M33+K34-L34 -> 276126.39
E35: =SUM(E4:E34) -> 5710.55 | G35: =SUM(G4:G34) -> 546400.84 | H35: =SUM(H4:H34) -> 76 | J35: =SUM(J4:J34) -> 8070.16 | K35: =SUM(K4:K34) -> 554471 | L35: =SUM(L4:L34) -> 385000

Sheet Ugar,Khagwad,Kudichi
A1: Shiri Bhrhmanath Petrolium
A2: S.No | B2: Date | C2: GRN No | D2: Ind No/Bill No | E2: Diesel (Lts) | F2: Price | G2: Amount | H2: Petrol (Lts) | I2: Price | J2: Amount | K2: Total amount | L2: Amount paid | M2: As on Date | N2: Remarks
A3: Opening Balance | K3: 584214.75 | L3: 0 | M3: 584214.75
A4: 1 | B4: 46143 | E4: 35 | F4: 91.93 | G4: =E4*F4 -> 3217.55 | J4: =H4*I4 -> 0 | K4: =G4+J4 -> 3217.55 | L4: 0 | M4: =M3+K4-L4 -> 587432.3
A5: 2 | B5: 46144 | E5: 440 | F5: 91.93 | G5: =E5*F5 -> 40449.2 | H5: 25 | I5: 103.89 | J5: =H5*I5 -> 2597.25 | K5: =G5+J5 -> 43046.45 | L5: 0 | M5: =M4+K5-L5 -> 630478.75
A6: 3 | B6: 46145 | E6: 310 | F6: 91.93 | G6: =E6*F6 -> 28498.3 | H6: 5 | I6: 103.89 | J6: =H6*I6 -> 519.45 | K6: =G6+J6 -> 29017.75 | L6: 0 | M6: =M5+K6-L6 -> 659496.5
A7: 4 | B7: 46146 | E7: 285 | F7: 91.93 | G7: =E7*F7 -> 26200.05 | J7: =H7*I7 -> 0 | K7: =G7+J7 -> 26200.05 | L7: 573975 | M7: =M6+K7-L7 -> 111721.55
A8: 5 | B8: 46147 | E8: 770 | F8: 91.93 | G8: =E8*F8 -> 70786.1 | H8: 10 | I8: 103.89 | J8: =H8*I8 -> 1038.9 | K8: =G8+J8 -> 71825 | L8: 0 | M8: =M7+K8-L8 -> 183546.55
A9: 6 | B9: 46148 | E9: 305 | F9: 91.93 | G9: =E9*F9 -> 28038.65 | H9: 5 | I9: 103.89 | J9: =H9*I9 -> 519.45 | K9: =G9+J9 -> 28558.1 | L9: 0 | M9: =M8+K9-L9 -> 212104.65
A10: 7 | B10: 46149 | E10: 290 | F10: 91.93 | G10: =E10*F10 -> 26659.7 | J10: =H10*I10 -> 0 | K10: =G10+J10 -> 26659.7 | L10: 0 | M10: =M9+K10-L10 -> 238764.35
A11: 8 | B11: 46150 | E11: 810 | F11: 91.93 | G11: =E11*F11 -> 74463.3 | H11: 40 | I11: 103.89 | J11: =H11*I11 -> 4155.6 | K11: =G11+J11 -> 78618.9 | L11: 0 | M11: =M10+K11-L11 -> 317383.25
A12: 9 | B12: 46151 | E12: 305 | F12: 91.93 | G12: =E12*F12 -> 28038.65 | J12: =H12*I12 -> 0 | K12: =G12+J12 -> 28038.65 | L12: 0 | M12: =M11+K12-L12 -> 345421.9
A13: 10 | B13: 46152 | E13: 679.9 | F13: 91.93 | G13: =E13*F13 -> 62503.207 | J13: =H13*I13 -> 0 | K13: =G13+J13 -> 62503.207 | L13: 0 | M13: =M12+K13-L13 -> 407925.11
A14: 11 | B14: 46153 | E14: 658.5 | F14: 91.93 | G14: =E14*F14 -> 60535.905 | H14: 53 | I14: 103.89 | J14: =H14*I14 -> 5506.17 | K14: =G14+J14 -> 66042.075 | L14: 0 | M14: =M13+K14-L14 -> 473967.18
A15: 12 | B15: 46154 | E15: 960 | F15: 91.93 | G15: =E15*F15 -> 88252.8 | J15: =H15*I15 -> 0 | K15: =G15+J15 -> 88252.8 | L15: 0 | M15: =M14+K15-L15 -> 562219.98
A16: 13 | B16: 46155 | E16: 400 | F16: 91.93 | G16: =E16*F16 -> 36772 | J16: =H16*I16 -> 0 | K16: =G16+J16 -> 36772 | L16: 0 | M16: =M15+K16-L16 -> 598991.98
A17: 14 | B17: 46156 | E17: 504.68 | F17: 91.93 | G17: =E17*F17 -> 46395.232 | J17: =H17*I17 -> 0 | K17: =G17+J17 -> 46395.232 | L17: 0 | M17: =M16+K17-L17 -> 645387.22
A18: 15 | B18: 46157 | E18: 485 | F18: 95.04 | G18: =E18*F18 -> 46094.4 | H18: 2 | I18: 116.55 | J18: =H18*I18 -> 233.1 | K18: =G18+J18 -> 46327.5 | L18: 0 | M18: =M17+K18-L18 -> 691714.72
A19: 16 | B19: 46158 | E19: 705 | F19: 95.04 | G19: =E19*F19 -> 67003.2 | H19: 5 | I19: 107.15 | J19: =H19*I19 -> 535.75 | K19: =G19+J19 -> 67538.95 | L19: 0 | M19: =M18+K19-L19 -> 759253.67
A20: 17 | B20: 46159 | E20: 320 | F20: 95.04 | G20: =E20*F20 -> 30412.8 | H20: 12 | I20: 107.15 | J20: =H20*I20 -> 1285.8 | K20: =G20+J20 -> 31698.6 | L20: 0 | M20: =M19+K20-L20 -> 790952.27
B21: 46159 | H21: 40 | I21: 116.55 | J21: =H21*I21 -> 4662 | K21: =G21+J21 -> 4662 | M21: =M20+K21-L21 -> 795614.27
A22: 18 | B22: 46160 | E22: 410 | F22: 95.04 | G22: =E22*F22 -> 38966.4 | J22: =H22*I22 -> 0 | K22: =G22+J22 -> 38966.4 | L22: 500000 | M22: =M21+K22-L22 -> 334580.67 | N22: BT
A23: 19 | B23: 46161 | G23: =E23*F23 -> 0 | H23: 2 | I23: 107.15 | J23: =H23*I23 -> 214.3 | K23: =G23+J23 -> 214.3 | L23: 0 | M23: =M22+K23-L23 -> 334794.97
A24: 20 | B24: 46162 | E24: 300 | F24: 95.98 | G24: =E24*F24 -> 28794 | J24: =H24*I24 -> 0 | K24: =G24+J24 -> 28794 | L24: 0 | M24: =M23+K24-L24 -> 363588.97
A25: 21 | B25: 46163 | E25: 320 | F25: 95.98 | G25: =E25*F25 -> 30713.6 | J25: =H25*I25 -> 0 | K25: =G25+J25 -> 30713.6 | L25: 191968 | M25: =M24+K25-L25 -> 202334.57
A26: 22 | B26: 46164 | E26: 460 | F26: 95.98 | G26: =E26*F26 -> 44150.8 | H26: 10 | I26: 108.09 | J26: =H26*I26 -> 1080.9 | K26: =G26+J26 -> 45231.7 | L26: 0 | M26: =M25+K26-L26 -> 247566.27
B27: 46164 | H27: 20 | I27: 117.5 | J27: =H27*I27 -> 2350 | K27: =G27+J27 -> 2350 | M27: =M26+K27-L27 -> 249916.27
A28: 23 | B28: 46165 | E28: 445 | F28: 96.93 | G28: =E28*F28 -> 43133.85 | H28: 2 | I28: 118.43 | J28: =H28*I28 -> 236.86 | K28: =G28+J28 -> 43370.71 | L28: 0 | M28: =M27+K28-L28 -> 293286.98
A29: 24 | B29: 46166 | E29: 95 | F29: 96.93 | G29: =E29*F29 -> 9208.35 | J29: =H29*I29 -> 0 | K29: =G29+J29 -> 9208.35 | L29: 0 | M29: =M28+K29-L29 -> 302495.33
A30: 25 | B30: 46167 | E30: 188.76 | F30: 99.74 | G30: =E30*F30 -> 18826.922 | H30: 10 | I30: 121.27 | J30: =H30*I30 -> 1212.7 | K30: =G30+J30 -> 20039.622 | L30: 0 | M30: =M29+K30-L30 -> 322534.95
A31: 26 | B31: 46168 | E31: 230 | F31: 99.74 | G31: =E31*F31 -> 22940.2 | J31: =H31*I31 -> 0 | K31: =G31+J31 -> 22940.2 | L31: 0 | M31: =M30+K31-L31 -> 345475.15
A32: 27 | B32: 46169 | E32: 335 | F32: 99.74 | G32: =E32*F32 -> 33412.9 | J32: =H32*I32 -> 0 | K32: =G32+J32 -> 33412.9 | L32: 0 | M32: =M31+K32-L32 -> 378888.05 | P32: =600*99.73 -> 59838
A33: 28 | B33: 46170 | E33: 150 | F33: 99.74 | G33: =E33*F33 -> 14961 | J33: =H33*I33 -> 0 | K33: =G33+J33 -> 14961 | L33: 0 | M33: =M32+K33-L33 -> 393849.05
A34: 29 | B34: 46171 | E34: 430 | F34: 99.74 | G34: =E34*F34 -> 42888.2 | J34: =H34*I34 -> 0 | K34: =G34+J34 -> 42888.2 | L34: 0 | M34: =M33+K34-L34 -> 436737.25
A35: 30 | B35: 46172 | E35: 400 | F35: 99.74 | G35: =E35*F35 -> 39896 | J35: =H35*I35 -> 0 | K35: =G35+J35 -> 39896 | L35: 0 | M35: =M34+K35-L35 -> 476633.25
A36: 31 | B36: 46173 | G36: =E36*F36 -> 0 | J36: =H36*I36 -> 0 | K36: =G36+J36 -> 0 | L36: 0 | M36: =M35+K36-L36 -> 476633.25
E37: =SUM(E4:E36) -> 12026.84 | G37: =SUM(G4:G36) -> 1132213.3 | H37: =SUM(H4:H36) -> 241 | J37: =SUM(J4:J36) -> 26148.23 | K37: =SUM(K4:K36) -> 1158361.5 | L37: =SUM(L4:L36) -> 1265943

Sheet shedbal
A1: VARAD PETROLEUM SHEDBAL
A2: S.No | B2: Date | C2: GRN No | D2: Ind no/Bill No | E2: Diesel (Lts) | F2: Price | G2: Amount | H2: Petrol (Lts) | I2: Price | J2: Amount | K2: Total amount | L2: Amount paid | M2: As on Date | N2: Remarks
A3: Opening Balance | K3: 0 | M3: 0
A4: 1 | B4: 46143 | G4: =E4*F4 -> 0 | J4: =H4*I4 -> 0 | K4: =G4+J4 -> 0 | M4: =M3+K4-L4 -> 0
A5: 2 | B5: 46144 | G5: =E5*F5 -> 0 | J5: =H5*I5 -> 0 | K5: =G5+J5 -> 0 | M5: =M4+K5-L5 -> 0
A6: 3 | B6: 46145 | G6: =E6*F6 -> 0 | J6: =H6*I6 -> 0 | K6: =G6+J6 -> 0 | M6: =M5+K6-L6 -> 0
A7: 4 | B7: 46146 | G7: =E7*F7 -> 0 | J7: =H7*I7 -> 0 | K7: =G7+J7 -> 0 | M7: =M6+K7-L7 -> 0
A8: 5 | B8: 46147 | G8: =E8*F8 -> 0 | J8: =H8*I8 -> 0 | K8: =G8+J8 -> 0 | M8: =M7+K8-L8 -> 0
A9: 6 | B9: 46148 | G9: =E9*F9 -> 0 | J9: =H9*I9 -> 0 | K9: =G9+J9 -> 0 | M9: =M8+K9-L9 -> 0
A10: 7 | B10: 46149 | G10: =E10*F10 -> 0 | J10: =H10*I10 -> 0 | K10: =G10+J10 -> 0 | M10: =M9+K10-L10 -> 0
A11: 8 | B11: 46150 | G11: =E11*F11 -> 0 | J11: =H11*I11 -> 0 | K11: =G11+J11 -> 0 | M11: =M10+K11-L11 -> 0
A12: 9 | B12: 46151 | G12: =E12*F12 -> 0 | J12: =H12*I12 -> 0 | K12: =G12+J12 -> 0 | M12: =M11+K12-L12 -> 0
A13: 10 | B13: 46152 | G13: =E13*F13 -> 0 | J13: =H13*I13 -> 0 | K13: =G13+J13 -> 0 | M13: =M12+K13-L13 -> 0
A14: 11 | B14: 46153 | G14: =E14*F14 -> 0 | J14: =H14*I14 -> 0 | K14: =G14+J14 -> 0 | M14: =M13+K14-L14 -> 0
A15: 12 | B15: 46154 | G15: =E15*F15 -> 0 | J15: =H15*I15 -> 0 | K15: =G15+J15 -> 0 | M15: =M14+K15-L15 -> 0
... A25: 22 | B25: 46164 | G25: =E25*F25 -> 0 | J25: =H25*I25 -> 0 | K25: =G25+J25 -> 0 | M25: =M24+K25-L25 -> 0
A26: 23 | B26: 46165 | G26: =E26*F26 -> 0 | J26: =H26*I26 -> 0 | K26: =G26+J26 -> 0 | M26: =M25+K26-L26 -> 0 | Q26: d
A27: 24 | B27: 46166 | G27: =E27*F27 -> 0 | J27: =H27*I27 -> 0 | K27: =G27+J27 -> 0 | M27: =M26+K27-L27 -> 0 | Q27: 30 | R27: 50
A28: 25 | B28: 46167 | E28: 600 | F28: 99.73 | G28: =E28*F28 -> 59838 | H28: 35 | I28: 111.85 | J28: =H28*I28 -> 3914.75 | K28: =G28+J28 -> 63752.75 | M28: =M27+K28-L28 -> 63752.75 | Q28: 50 | R28: 4.51
A29: 26 | B29: 46168 | E29: 475 | F29: 99.73 | G29: =E29*F29 -> 47371.75 | H29: 0 | I29: 0 | J29: =H29*I29 -> 0 | K29: =G29+J29 -> 47371.75 | M29: =M28+K29-L29 -> 111124.5
A30: 27 | B30: 46169 | G30: =E30*F30 -> 0 | J30: =H30*I30 -> 0 | K30: =G30+J30 -> 0 | M30: =M29+K30-L30 -> 111124.5
A31: 28 | B31: 46170 | G31: =E31*F31 -> 0 | J31: =H31*I31 -> 0 | K31: =G31+J31 -> 0 | M31: =M30+K31-L31 -> 111124.5
A32: 29 | B32: 46171 | E32: 35 | F32: 99.73 | G32: =E32*F32 -> 3490.55 | H32: 30 | I32: 111.85 | J32: =H32*I32 -> 3355.5 | K32: =G32+J32 -> 6846.05 | M32: =M31+K32-L32 -> 117970.55
A33: 30 | B33: 46172 | E33: 490 | F33: 99.73 | G33: =E33*F33 -> 48867.7 | H33: 10 | I33: 111.85 | J33: =H33*I33 -> 1118.5 | K33: =G33+J33 -> 49986.2 | M33: =M32+K33-L33 -> 167956.75
A34: 31 | B34: 46173 | G34: =E34*F34 -> 0 | J34: =H34*I34 -> 0 | K34: =G34+J34 -> 0 | M34: =M33+K34-L34 -> 167956.75
E35: =SUM(E4:E34) -> 1600 | G35: =SUM(G4:G34) -> 159568 | H35: =SUM(H4:H34) -> 75 | J35: =SUM(J4:J34) -> 8388.75 | K35: =SUM(K4:K34) -> 167956.75 | L35: =SUM(L4:L34) -> 0

Sheet Kabbur
A1: Shri Jai Hanuman Petrolium
A2: S.No | B2: Date | C2: GRN No | D2: Ind no/Bill No | E2: Diesel (Lts) | F2: Price | G2: Amount | H2: Petrol (Lts) | I2: Price | J2: Amount | K2: Total amount | L2: Amount paid | M2: As on Date | N2: Remarks
A3: Opening Balance | K3: 0 | M3: =+K3 -> 0
A4: 1 | B4: 46143 | G4: =E4*F4 -> 0 | J4: =H4*I4 -> 0 | K4: =G4+J4 -> 0 | L4: =+K4 -> 0
A5: 2 | B5: 46144 | G5: =E5*F5 -> 0 | J5: =H5*I5 -> 0 | K5: =G5+J5 -> 0 | L5: =+K5 -> 0
A6: 3 | B6: 46145 | G6: =E6*F6 -> 0 | J6: =H6*I6 -> 0 | K6: =G6+J6 -> 0 | L6: =+K6 -> 0
A7: 4 | B7: 46146 | G7: =E7*F7 -> 0 | J7: =H7*I7 -> 0 | K7: =G7+J7 -> 0 | L7: =+K7 -> 0
A8: 5 | B8: 46147 | G8: =E8*F8 -> 0 | J8: =H8*I8 -> 0 | K8: =G8+J8 -> 0 | L8: =+K8 -> 0
A9: 6 | B9: 46148 | G9: =E9*F9 -> 0 | J9: =H9*I9 -> 0 | K9: =G9+J9 -> 0 | L9: =+K9 -> 0
A10: 7 | B10: 46149 | G10: =E10*F10 -> 0 | J10: =H10*I10 -> 0 | K10: =G10+J10 -> 0 | L10: =+K10 -> 0
A11: 8 | B11: 46150 | G11: =E11*F11 -> 0 | H11: 8.95 | I11: 103.54 | J11: =H11*I11 -> 926.683 | K11: =G11+J11 -> 926.683 | L11: =+K11 -> 926.683
A12: 9 | B12: 46151 | G12: =E12*F12 -> 0 | J12: =H12*I12 -> 0 | K12: =G12+J12 -> 0 | L12: =+K12 -> 0
A13: 10 | B13: 46152 | G13: =E13*F13 -> 0 | J13: =H13*I13 -> 0 | K13: =G13+J13 -> 0 | L13: =+K13 -> 0
A14: 11 | B14: 46153 | G14: =E14*F14 -> 0 | J14: =H14*I14 -> 0 | K14: =G14+J14 -> 0 | L14: =+K14 -> 0
A15: 12 | B15: 46154 | G15: =E15*F15 -> 0 | J15: =H15*I15 -> 0 | K15: =G15+J15 -> 0 | L15: =+K15 -> 0
A16: 13 | B16: 46155 | G16: =E16*F16 -> 0 | J16: =H16*I16 -> 0 | K16: =G16+J16 -> 0 | L16: =+K16 -> 0
A17: 14 | B17: 46156 | G17: =E17*F17 -> 0 | J17: =H17*I17 -> 0 | K17: =G17+J17 -> 0 | L17: =+K17 -> 0
A18: 15 | B18: 46157 | G18: =E18*F18 -> 0 | J18: =H18*I18 -> 0 | K18: =G18+J18 -> 0 | L18: =+K18 -> 0
A19: 16 | B19: 46158 | G19: =E19*F19 -> 0 | J19: =H19*I19 -> 0 | K19: =G19+J19 -> 0 | L19: =+K19 -> 0
A20: 17 | B20: 46159 | G20: =E20*F20 -> 0 | J20: =H20*I20 -> 0 | K20: =G20+J20 -> 0 | L20: =+K20 -> 0
A21: 18 | B21: 46160 | G21: =E21*F21 -> 0 | J21: =H21*I21 -> 0 | K21: =G21+J21 -> 0 | L21: =+K21 -> 0
A22: 19 | B22: 46161 | G22: =E22*F22 -> 0 | J22: =H22*I22 -> 0 | K22: =G22+J22 -> 0 | L22: =+K22 -> 0
A23: 20 | B23: 46162 | G23: =E23*F23 -> 0 | J23: =H23*I23 -> 0 | K23: =G23+J23 -> 0 | L23: =+K23 -> 0
A24: 21 | B24: 46163 | E24: 329.59 | F24: 95.65 | G24: =E24*F24 -> 31525.283 | H24: 8 | I24: 107.74 | J24: =H24*I24 -> 861.92 | K24: =G24+J24 -> 32387.203 | L24: =+K24 -> 32387.203
A25: 22 | B25: 46164 | G25: =E25*F25 -> 0 | J25: =H25*I25 -> 0 | K25: =G25+J25 -> 0 | L25: =+K25 -> 0
A26: 23 | B26: 46165 | E26: 400 | F26: 96.6 | G26: =E26*F26 -> 38640 | J26: =H26*I26 -> 0 | K26: =G26+J26 -> 38640 | L26: =+K26 -> 38640
A27: 24 | B27: 46166 | G27: =E27*F27 -> 0 | J27: =H27*I27 -> 0 | K27: =G27+J27 -> 0 | L27: =+K27 -> 0 | O27: 0
A28: 25 | B28: 46167 | G28: =E28*F28 -> 0 | J28: =H28*I28 -> 0 | K28: =G28+J28 -> 0 | L28: =+K28 -> 0
A29: 26 | B29: 46168 | G29: =E29*F29 -> 0 | J29: =H29*I29 -> 0 | K29: =G29+J29 -> 0 | L29: =+K29 -> 0
A30: 27 | B30: 46169 | E30: 200 | F30: 99.41 | G30: =E30*F30 -> 19882 | H30: 8 | I30: 107.74 | J30: =H30*I30 -> 861.92 | K30: =G30+J30 -> 20743.92 | L30: =+K30 -> 20743.92
A31: 28 | B31: 46170 | G31: =E31*F31 -> 0 | J31: =H31*I31 -> 0 | K31: =G31+J31 -> 0 | L31: =+K31 -> 0
A32: 29 | B32: 46171 | G32: =E32*F32 -> 0 | J32: =H32*I32 -> 0 | K32: =G32+J32 -> 0 | L32: =+K32 -> 0
A33: 30 | B33: 46172 | G33: =E33*F33 -> 0 | J33: =H33*I33 -> 0 | K33: =G33+J33 -> 0 | L33: =+K33 -> 0
A34: 31 | B34: 46173 | E34: 250 | F34: 99.41 | G34: =E34*F34 -> 24852.5 | J34: =H34*I34 -> 0 | K34: =G34+J34 -> 24852.5 | L34: =H34+K34 -> 24852.5
E35: =SUM(E4:E34) -> 1179.59 | G35: =SUM(G4:G34) -> 114899.78 | H35: =SUM(H4:H34) -> 24.95 | J35: =SUM(J4:J34) -> 2650.523 | K35: =SUM(K4:K34) -> 117550.31 | L35: =SUM(L4:L34) -> 117550.31

Sheet kumta
A1: V.M.MIRJANKAR (KUMTA) BHARAT
A2: S.No | B2: Date | C2: GRN No | D2: Ind No/Bill No | E2: Diesel (Lts) | F2: Price | G2: Amount | H2: Petrol (Lts) | I2: Price | J2: Amount | K2: Total amount | L2: Amount paid | M2: As on Date | N2: Remarks
A3: Opening Balance | M3: 2607.22
A4: 1 | B4: 45778 | E4: 50 | F4: 91.97 | G4: =E4*F4 -> 4598.5 | J4: =H4*I4 -> 0 | K4: =G4+J4 -> 4598.5 | M4: =M3+K4-L4 -> 7205.72
A5: 2 | B5: 45779 | E5: 50 | F5: 91.97 | G5: =E5*F5 -> 4598.5 | H5: 5 | I5: 104.01 | J5: =H5*I5 -> 520.05 | K5: =G5+J5 -> 5118.55 | M5: =M4+K5-L5 -> 12324.27
A6: 3 | B6: 45780 | G6: =E6*F6 -> 0 | J6: =H6*I6 -> 0 | K6: =G6+J6 -> 0 | M6: =M5+K6-L6 -> 12324.27
A7: 4 | B7: 45781 | E7: 45 | F7: 91.97 | G7: =E7*F7 -> 4138.65 | H7: 5 | I7: 104.01 | J7: =H7*I7 -> 520.05 | K7: =G7+J7 -> 4658.7 | M7: =M6+K7-L7 -> 16982.97
A8: 5 | B8: 45782 | E8: 50 | F8: 91.97 | G8: =E8*F8 -> 4598.5 | H8: 5 | I8: 104.01 | J8: =H8*I8 -> 520.05 | K8: =G8+J8 -> 5118.55 | M8: =M7+K8-L8 -> 22101.52
A9: 6 | B9: 45783 | E9: 50 | F9: 91.97 | G9: =E9*F9 -> 4598.5 | J9: =H9*I9 -> 0 | K9: =G9+J9 -> 4598.5 | M9: =M8+K9-L9 -> 26700.02
A10: 7 | B10: 45784 | E10: 50 | F10: 91.97 | G10: =E10*F10 -> 4598.5 | H10: 5 | I10: 104.01 | J10: =H10*I10 -> 520.05 | K10: =G10+J10 -> 5118.55 | M10: =M9+K10-L10 -> 31818.57
A11: 8 | B11: 45785 | E11: 40 | F11: 91.97 | G11: =E11*F11 -> 3678.8 | H11: 15 | I11: 104.01 | J11: =H11*I11 -> 1560.15 | K11: =G11+J11 -> 5238.95 | M11: =M10+K11-L11 -> 37057.52
A12: 9 | B12: 45786 | E12: 40 | F12: 91.92 | G12: =E12*F12 -> 3676.8 | H12: 5 | I12: 103.96 | J12: =H12*I12 -> 519.8 | K12: =G12+J12 -> 4196.6 | L12: 4196.6 | M12: =M11+K12-L12 -> 37057.52 | N12: IOCL
B13: 45786 | E13: 100 | F13: 91.97 | G13: =E13*F13 -> 9197 | H13: 10 | I13: 104.01 | J13: =H13*I13 -> 1040.1 | K13: =G13+J13 -> 10237.1 | M13: =M12+K13-L13 -> 47294.62
A14: 10 | B14: 45787 | E14: 50 | F14: 91.97 | G14: =E14*F14 -> 4598.5 | H14: 5 | I14: 104.01 | J14: =H14*I14 -> 520.05 | K14: =G14+J14 -> 5118.55 | M14: =M13+K14-L14 -> 52413.17
A15: 11 | B15: 45788 | E15: 40 | F15: 91.97 | G15: =E15*F15 -> 3678.8 | J15: =H15*I15 -> 0 | K15: =G15+J15 -> 3678.8 | M15: =M14+K15-L15 -> 56091.97
A16: 12 | B16: 45789 | E16: 50 | F16: 91.97 | G16: =E16*F16 -> 4598.5 | H16: 5 | I16: 104.01 | J16: =H16*I16 -> 520.05 | K16: =G16+J16 -> 5118.55 | M16: =M15+K16-L16 -> 61210.52
A17: 13 | B17: 45790 | E17: 50 | F17: 91.97 | G17: =E17*F17 -> 4598.5 | J17: =H17*I17 -> 0 | K17: =G17+J17 -> 4598.5 | L17: 40000 | M17: =M16+K17-L17 -> 25809.02
A18: 14 | B18: 45791 | G18: =E18*F18 -> 0 | J18: =H18*I18 -> 0 | K18: =G18+J18 -> 0 | M18: =M17+K18-L18 -> 25809.02
A19: 15 | B19: 45792 | E19: 40 | F19: 95.03 | G19: =E19*F19 -> 3801.2 | J19: =H19*I19 -> 0 | K19: =G19+J19 -> 3801.2 | L19: =H19+K19 -> 3801.2 | M19: =M18+K19-L19 -> 25809.02 | N19: IOCL
B20: 45792 | E20: 50 | F20: 95.08 | G20: =E20*F20 -> 4754 | H20: 5 | I20: 107.27 | J20: =H20*I20 -> 536.35 | K20: =G20+J20 -> 5290.35 | M20: =M19+K20-L20 -> 31099.37
A21: 16 | B21: 45793 | E21: 50 | F21: 95.08 | G21: =E21*F21 -> 4754 | H21: 5 | I21: 107.27 | J21: =H21*I21 -> 536.35 | K21: =G21+J21 -> 5290.35 | M21: =M20+K21-L21 -> 36389.72
A22: 17 | B22: 45794 | E22: 50 | F22: 95.08 | G22: =E22*F22 -> 4754 | J22: =H22*I22 -> 0 | K22: =G22+J22 -> 4754 | M22: =M21+K22-L22 -> 41143.72
A23: 18 | B23: 45795 | G23: =E23*F23 -> 0 | J23: =H23*I23 -> 0 | K23: =G23+J23 -> 0 | M23: =M22+K23-L23 -> 41143.72
A24: 19 | B24: 45796 | E24: 70 | F24: 96.02 | G24: =E24*F24 -> 6721.4 | H24: 19.62 | I24: 108.21 | J24: =H24*I24 -> 2123.0802 | K24: =G24+J24 -> 8844.4802 | M24: =M23+K24-L24 -> 49988.2 | R24: Kumta | T24: V.M.Mirjankar
A25: 20 | B25: 45797 | G25: =E25*F25 -> 0 | H25: 5 | I25: 108.21 | J25: =H25*I25 -> 541.05 | K25: =G25+J25 -> 541.05 | M25: =M24+K25-L25 -> 50529.25 | R25: Month | S25: Disel In Litters | T25: Petrol In Litters | U25: Amount Paid
A26: 21 | B26: 45798 | E26: 50 | F26: 96.02 | G26: =E26*F26 -> 4801 | H26: 5 | I26: 108.21 | J26: =H26*I26 -> 541.05 | K26: =G26+J26 -> 5342.05 | L26: 36000 | M26: =M25+K26-L26 -> 19871.3 | R26: Feb'-26 | S26: 2040 | T26: 90 | U26: 169925
A27: 22 | B27: 45799 | E27: 50 | F27: 96.02 | G27: =E27*F27 -> 4801 | H27: 15 | I27: 108.21 | J27: =H27*I27 -> 1623.15 | K27: =G27+J27 -> 6424.15 | M27: =M26+K27-L27 -> 26295.45 | R27: March'-26 | S27: 2115 | T27: 185 | U27: 206053
A28: 23 | B28: 45800 | E28: 50 | F28: 96.97 | G28: =E28*F28 -> 4848.5 | H28: 5 | I28: 109.15 | J28: =H28*I28 -> 545.75 | K28: =G28+J28 -> 5394.25 | M28: =M27+K28-L28 -> 31689.7 | R28: April'-26 | S28: 2145 | T28: 177 | U28: 247835
A29: 24 | B29: 45801 | G29: =E29*F29 -> 0 | H29: 5 | I29: 109.15 | J29: =H29*I29 -> 545.75 | K29: =G29+J29 -> 545.75 | M29: =M28+K29-L29 -> 32235.45 | R29: May'-26 | S29: 545 | T29: 50 | U29: 44201
A30: 25 | B30: 45802 | E30: 50 | F30: 99.78 | G30: =E30*F30 -> 4989 | H30: 5 | I30: 111.98 | J30: =H30*I30 -> 559.9 | K30: =G30+J30 -> 5548.9 | M30: =M29+K30-L30 -> 37784.35 | S30: =SUM(S26:S29) -> 6845 | T30: =SUM(T26:T29) -> 502 | U30: =SUM(U26:U29) -> 668014
A31: 26 | B31: 45803 | E31: 80 | F31: 99.78 | G31: =E31*F31 -> 7982.4 | H31: 10 | I31: 111.98 | J31: =H31*I31 -> 1119.8 | K31: =G31+J31 -> 9102.2 | M31: =M30+K31-L31 -> 46886.55
A32: 27 | B32: 45803 | E32: 40 | F32: 99.73 | G32: =E32*F32 -> 3989.2 | K32: =G32+J32 -> 3989.2 | L32: 3989.2 | M32: =M31+K32-L32 -> 46886.55
A33: 28 | B33: 45804 | E33: 50 | F33: 99.78 | G33: =E33*F33 -> 4989 | J33: =H33*I33 -> 0 | K33: =G33+J33 -> 4989 | M33: =M32+K33-L33 -> 51875.55
A34: 29 | B34: 45805 | G34: =E34*F34 -> 0 | H34: 20 | I34: 111.98 | J34: =H34*I34 -> 2239.6 | K34: =G34+J34 -> 2239.6 | M34: =M33+K34-L34 -> 54115.15
A35: 30 | B35: 45806 | E35: 50 | F35: 99.78 | G35: =E35*F35 -> 4989 | J35: =H35*I35 -> 0 | K35: =G35+J35 -> 4989 | M35: =M34+K35-L35 -> 59104.15
A36: 31 | B36: 45807 | E36: 50 | F36: 99.78 | G36: =E36*F36 -> 4989 | H36: 15 | I36: 111.98 | J36: =H36*I36 -> 1679.7 | K36: =G36+J36 -> 6668.7 | M36: =M35+K36-L36 -> 65772.85
A37: 32 | B37: 45808 | E37: 50 | F37: 99.78 | G37: =E37*F37 -> 4989 | H37: 5 | I37: 111.98 | J37: =H37*I37 -> 559.9 | K37: =G37+J37 -> 5548.9 | M37: =M36+K37-L37 -> 71321.75
A38: 33 | B38: 45809 | G38: =E38*F38 -> 0 | J38: =H38*I38 -> 0 | K38: =G38+J38 -> 0 | L38: 0 | M38: =M37+K38-L38 -> 71321.75
E39: =SUM(E4:E38) -> 1445 | G39: =SUM(G4:G38) -> 137309.75 | H39: =SUM(H4:H38) -> 179.62 | J39: =SUM(J4:J38) -> 19391.78 | K39: =SUM(K4:K38) -> 156701.53 | L39: =SUM(L4:L38) -> 87987

Sheet  Jalgaon-1
A1: Jai Bajarang Sarvo Senter Bodwad
A2: S.No | B2: Date | C2: GRN No | D2: Ind No/Bill No | E2: Diesel (Lts) | F2: Price | G2: Amount | H2: Petrol (Lts) | I2: Price | J2: Amount | K2: Total amount | L2: Amount paid | M2: As on Date | N2: Remarks
A3: Opening Balance | K3: 93813.679 | M3: 93813.679
A4: 1 | B4: 46143 | G4: =E4*F4 -> 0 | J4: =H4*I4 -> 0 | K4: =G4+J4 -> 0 | M4: =M3+K4-L4 -> 93813.679
A5: 2 | B5: 46144 | G5: =E5*F5 -> 0 | J5: =H5*I5 -> 0 | K5: =G5+J5 -> 0 | M5: =M4+K5-L5 -> 93813.679
B6: 46145 | G6: =E6*F6 -> 0 | J6: =H6*I6 -> 0 | K6: =G6+J6 -> 0 | M6: =M5+K6-L6 -> 93813.679
A7: 3 | B7: 46146 | G7: =E7*F7 -> 0 | J7: =H7*I7 -> 0 | K7: =G7+J7 -> 0 | M7: =M6+K7-L7 -> 93813.679
A8: 4 | B8: 46147 | G8: =E8*F8 -> 0 | J8: =H8*I8 -> 0 | K8: =G8+J8 -> 0 | M8: =M7+K8-L8 -> 93813.679
A9: 5 | B9: 46148 | G9: =E9*F9 -> 0 | J9: =H9*I9 -> 0 | K9: =G9+J9 -> 0 | M9: =M8+K9-L9 -> 93813.679
A10: 6 | B10: 46149 | G10: =E10*F10 -> 0 | J10: =H10*I10 -> 0 | K10: =G10+J10 -> 0 | M10: =M9+K10-L10 -> 93813.679
A11: 7 | B11: 46150 | G11: =E11*F11 -> 0 | J11: =H11*I11 -> 0 | K11: =G11+J11 -> 0 | M11: =M10+K11-L11 -> 93813.679
A12: 8 | B12: 46151 | G12: =E12*F12 -> 0 | J12: =H12*I12 -> 0 | K12: =G12+J12 -> 0 | M12: =M11+K12-L12 -> 93813.679
A13: 9 | B13: 46152 | G13: =E13*F13 -> 0 | J13: =H13*I13 -> 0 | K13: =G13+J13 -> 0 | M13: =M12+K13-L13 -> 93813.679
A14: 10 | B14: 46153 | G14: =E14*F14 -> 0 | J14: =H14*I14 -> 0 | K14: =G14+J14 -> 0 | M14: =M13+K14-L14 -> 93813.679
A15: 11 | B15: 46154 | G15: =E15*F15 -> 0 | J15: =H15*I15 -> 0 | K15: =G15+J15 -> 0 | M15: =M14+K15-L15 -> 93813.679
A16: 12 | B16: 46155 | G16: =E16*F16 -> 0 | J16: =H16*I16 -> 0 | K16: =G16+J16 -> 0 | M16: =M15+K16-L16 -> 93813.679
A17: 13 | B17: 46156 | G17: =E17*F17 -> 0 | J17: =H17*I17 -> 0 | K17: =G17+J17 -> 0 | M17: =M16+K17-L17 -> 93813.679
A18: 14 | B18: 46157 | G18: =E18*F18 -> 0 | J18: =H18*I18 -> 0 | K18: =G18+J18 -> 0 | M18: =M17+K18-L18 -> 93813.679
A19: 15 | B19: 46158 | G19: =E19*F19 -> 0 | J19: =H19*I19 -> 0 | K19: =G19+J19 -> 0 | L19: 93813 | M19: =M18+K19-L19 -> 0.6791 | N19: BT
A20: 16 | B20: 46159 | G20: =E20*F20 -> 0 | J20: =H20*I20 -> 0 | K20: =G20+J20 -> 0 | M20: =M19+K20-L20 -> 0.6791
A21: 17 | B21: 46160 | G21: =E21*F21 -> 0 | J21: =H21*I21 -> 0 | K21: =G21+J21 -> 0 | M21: =M20+K21-L21 -> 0.6791
A22: 18 | B22: 46161 | G22: =E22*F22 -> 0 | J22: =H22*I22 -> 0 | K22: =G22+J22 -> 0 | M22: =M21+K22-L22 -> 0.6791
A23: 19 | B23: 46162 | G23: =E23*F23 -> 0 | J23: =H23*I23 -> 0 | K23: =G23+J23 -> 0 | M23: =M22+K23-L23 -> 0.6791
A24: 20 | B24: 46163 | G24: =E24*F24 -> 0 | J24: =H24*I24 -> 0 | K24: =G24+J24 -> 0 | M24: =M23+K24-L24 -> 0.6791
A25: 21 | B25: 46164 | G25: =E25*F25 -> 0 | J25: =H25*I25 -> 0 | K25: =G25+J25 -> 0 | M25: =M24+K25-L25 -> 0.6791
A26: 22 | B26: 46165 | G26: =E26*F26 -> 0 | J26: =H26*I26 -> 0 | K26: =G26+J26 -> 0 | M26: =M25+K26-L26 -> 0.6791
A27: 23 | B27: 46166 | G27: =E27*F27 -> 0 | J27: =H27*I27 -> 0 | K27: =G27+J27 -> 0 | M27: =M26+K27-L27 -> 0.6791
A28: 24 | B28: 46167 | G28: =E28*F28 -> 0 | J28: =H28*I28 -> 0 | K28: =G28+J28 -> 0 | M28: =M27+K28-L28 -> 0.6791
A29: 25 | B29: 46168 | G29: =E29*F29 -> 0 | J29: =H29*I29 -> 0 | K29: =G29+J29 -> 0 | M29: =M28+K29-L29 -> 0.6791
A30: 26 | B30: 46169 | G30: =E30*F30 -> 0 | J30: =H30*I30 -> 0 | K30: =G30+J30 -> 0 | M30: =M29+K30-L30 -> 0.6791
A31: 27 | B31: 46170 | G31: =E31*F31 -> 0 | J31: =H31*I31 -> 0 | K31: =G31+J31 -> 0 | M31: =M30+K31-L31 -> 0.6791
... A33: 29 | B33: 46172 | G33: =E33*F33 -> 0 | J33: =H33*I33 -> 0 | K33: =G33+J33 -> 0 | M33: =M32+K33-L33 -> 0.6791
A34: 30 | G34: =E34*F34 -> 0 | J34: =H34*I34 -> 0 | K34: =G34+J34 -> 0 | M34: =M33+K34-L34 -> 0.6791
A35: 31 | G35: =E35*F35 -> 0 | J35: =H35*I35 -> 0 | K35: =G35+J35 -> 0 | M35: =M34+K35-L35 -> 0.6791
A36: 32 | G36: =E36*F36 -> 0 | J36: =H36*I36 -> 0 | K36: =G36+J36 -> 0 | M36: =M35+K36-L36 -> 0.6791
A37: 33 | G37: =E37*F37 -> 0 | J37: =H37*I37 -> 0 | K37: =G37+J37 -> 0 | M37: =M36+K37-L37 -> 0.6791
A38: 34 | G38: =E38*F38 -> 0 | J38: =H38*I38 -> 0 | K38: =G38+J38 -> 0 | M38: =M37+K38-L38 -> 0.6791 | P38: 41
A39: 35 | G39: =E39*F39 -> 0 | J39: =H39*I39 -> 0 | K39: =G39+J39 -> 0 | M39: =M38+K39-L39 -> 0.6791 | P39: 40 | Q39: 5
A40: 36 | G40: =E40*F40 -> 0 | J40: =H40*I40 -> 0 | K40: =G40+J40 -> 0 | M40: =M39+K40-L40 -> 0.6791
A41: 37 | G41: =E41*F41 -> 0 | J41: =H41*I41 -> 0 | K41: =G41+J41 -> 0 | M41: =M40+K41-L41 -> 0.6791
A42: 38 | G42: =E42*F42 -> 0 | J42: =H42*I42 -> 0 | K42: =G42+J42 -> 0 | M42: =M41+K42-L42 -> 0.6791
A43: 39 | G43: =E43*F43 -> 0 | J43: =H43*I43 -> 0 | K43: =G43+J43 -> 0 | M43: =M42+K43-L43 -> 0.6791
A44: 40 | G44: =E44*F44 -> 0 | J44: =H44*I44 -> 0 | K44: =G44+J44 -> 0 | M44: =M43+K44-L44 -> 0.6791
A45: 41 | G45: =E45*F45 -> 0 | J45: =H45*I45 -> 0 | K45: =G45+J45 -> 0 | M45: =M44+K45-L45 -> 0.6791
A46: 42 | G46: =E46*F46 -> 0 | J46: =H46*I46 -> 0 | K46: =G46+J46 -> 0 | M46: =M45+K46-L46 -> 0.6791
A47: 43 | G47: =E47*F47 -> 0 | J47: =H47*I47 -> 0 | K47: =G47+J47 -> 0 | M47: =M46+K47-L47 -> 0.6791
A48: 44 | G48: =E48*F48 -> 0 | J48: =H48*I48 -> 0 | K48: =G48+J48 -> 0 | M48: =M47+K48-L48 -> 0.6791
A49: 45 | G49: =E49*F49 -> 0 | J49: =H49*I49 -> 0 | K49: =G49+J49 -> 0 | M49: =M48+K49-L49 -> 0.6791
A50: 46 | G50: =E50*F50 -> 0 | J50: =H50*I50 -> 0 | K50: =G50+J50 -> 0 | M50: =M49+K50-L50 -> 0.6791
A51: 47 | G51: =E51*F51 -> 0 | J51: =H51*I51 -> 0 | K51: =G51+J51 -> 0 | L51: 0 | M51: =M50+K51-L51 -> 0.6791
A52: 48 | G52: =E52*F52 -> 0 | J52: =H52*I52 -> 0 | K52: =G52+J52 -> 0 | L52: 0 | M52: =M51+K52-L52 -> 0.6791
A53: 49 | G53: =E53*F53 -> 0 | J53: =H53*I53 -> 0 | K53: =G53+J53 -> 0 | L53: 0 | M53: =M52+K53-L53 -> 0.6791
A54: 50 | G54: =E54*F54 -> 0 | J54: =H54*I54 -> 0 | K54: =G54+J54 -> 0 | L54: 0 | M54: =M53+K54-L54 -> 0.6791 | O54: 1109792.3 | P54: =M54-O54 -> -1109791.6
E55: =SUM(E4:E54) -> 0 | G55: =SUM(G4:G54) -> 0 | H55: =SUM(H4:H54) -> 0 | J55: =SUM(J4:J54) -> 0 | K55: =SUM(K4:K54) -> 0 | L55: =SUM(L4:L54) -> 93813

Sheet Jalgoan-2
A1: Nayara
A2: S.No | B2: Date | C2: GRN No | D2: Ind No/Bill No | E2: Diesel (Lts) | F2: Price | G2: Amount | H2: Petrol (Lts) | I2: Price | J2: Amount | K2: Total amount | L2: Amount paid | M2: As on Date | N2: Remarks
A3: Opening Balance | K3: 2665456 | M3: 2665456 | P3: 5472110
A4: 1 | B4: 46143 | E4: 1000 | F4: 94.71 | G4: =E4*F4 -> 94710 | H4: 30 | I4: 110.44 | J4: =H4*I4 -> 3313.2 | K4: =G4+J4 -> 98023.2 | M4: =M3+K4-L4 -> 2763479.2
A5: 2 | B5: 46144 | E5: 1000 | F5: 94.71 | G5: =E5*F5 -> 94710 | H5: 30 | I5: 110.44 | J5: =H5*I5 -> 3313.2 | K5: =G5+J5 -> 98023.2 | M5: =M4+K5-L5 -> 2861502.4
A6: 3 | B6: 46145 | G6: =E6*F6 -> 0 | J6: =H6*I6 -> 0 | K6: =G6+J6 -> 0 | M6: =M5+K6-L6 -> 2861502.4
A7: 4 | B7: 46146 | G7: =E7*F7 -> 0 | J7: =H7*I7 -> 0 | K7: =G7+J7 -> 0 | L7: 1000000 | M7: =M6+K7-L7 -> 1861502.4 | N7: BT
A8: 5 | B8: 46147 | G8: =E8*F8 -> 0 | H8: 50 | I8: 110.44 | J8: =H8*I8 -> 5522 | K8: =G8+J8 -> 5522 | M8: =M7+K8-L8 -> 1867024.4
A9: 6 | B9: 46148 | E9: 3000.42 | F9: 94.71 | G9: =E9*F9 -> 284169.78 | J9: =H9*I9 -> 0 | K9: =G9+J9 -> 284169.78 | M9: =M8+K9-L9 -> 2151194.1
A10: 7 | B10: 46149 | G10: =E10*F10 -> 0 | J10: =H10*I10 -> 0 | K10: =G10+J10 -> 0 | M10: =M9+K10-L10 -> 2151194.1
A11: 8 | B11: 46150 | E11: 4650 | F11: 94.71 | G11: =E11*F11 -> 440401.5 | H11: 30 | I11: 110.44 | J11: =H11*I11 -> 3313.2 | K11: =G11+J11 -> 443714.7 | M11: =M10+K11-L11 -> 2594908.8
A12: 9 | B12: 46151 | E12: 2500 | F12: 94.71 | G12: =E12*F12 -> 236775 | H12: 50 | I12: 110.44 | J12: =H12*I12 -> 5522 | K12: =G12+J12 -> 242297 | M12: =M11+K12-L12 -> 2837205.8
A13: 10 | B13: 46152 | G13: =E13*F13 -> 0 | J13: =H13*I13 -> 0 | K13: =G13+J13 -> 0 | M13: =M12+K13-L13 -> 2837205.8
A14: 11 | B14: 46153 | E14: 1000 | F14: 94.71 | G14: =E14*F14 -> 94710 | J14: =H14*I14 -> 0 | K14: =G14+J14 -> 94710 | L14: 800000 | M14: =M13+K14-L14 -> 2131915.8 | N14: BT
A15: 12 | B15: 46154 | E15: 2500 | F15: 94.71 | G15: =E15*F15 -> 236775 | H15: 20 | I15: 110.44 | J15: =H15*I15 -> 2208.8 | K15: =G15+J15 -> 238983.8 | M15: =M14+K15-L15 -> 2370899.6
A16: 13 | B16: 46155 | G16: =E16*F16 -> 0 | J16: =H16*I16 -> 0 | K16: =G16+J16 -> 0 | M16: =M15+K16-L16 -> 2370899.6
A17: 14 | B17: 46156 | E17: 2000 | F17: 94.71 | G17: =E17*F17 -> 189420 | J17: =H17*I17 -> 0 | K17: =G17+J17 -> 189420 | M17: =M16+K17-L17 -> 2560319.6
A18: 15 | B18: 46157 | G18: =E18*F18 -> 0 | J18: =H18*I18 -> 0 | K18: =G18+J18 -> 0 | M18: =M17+K18-L18 -> 2560319.6
A19: 16 | B19: 46158 | E19: 2000 | F19: 97.84 | G19: =E19*F19 -> 195680 | H19: 30 | I19: 113.58 | J19: =H19*I19 -> 3407.4 | K19: =G19+J19 -> 199087.4 | M19: =M18+K19-L19 -> 2759407
A20: 17 | B20: 46159 | E20: 1000 | F20: 97.84 | G20: =E20*F20 -> 97840 | J20: =H20*I20 -> 0 | K20: =G20+J20 -> 97840 | M20: =M19+K20-L20 -> 2857247
A21: 18 | B21: 46160 | G21: =E21*F21 -> 0 | H21: 30 | I21: 113.58 | J21: =H21*I21 -> 3407.4 | K21: =G21+J21 -> 3407.4 | M21: =M20+K21-L21 -> 2860654.4
A22: 19 | B22: 46161 | G22: =E22*F22 -> 0 | J22: =H22*I22 -> 0 | K22: =G22+J22 -> 0 | M22: =M21+K22-L22 -> 2860654.4
A23: 20 | B23: 46162 | E23: 1000 | F23: 98.77 | G23: =E23*F23 -> 98770 | J23: =H23*I23 -> 0 | K23: =G23+J23 -> 98770 | M23: =M22+K23-L23 -> 2959424.4
B24: 46162 | E24: 253.11 | F24: 98.77 | G24: =E24*F24 -> 24999.675 | H24: 60 | I24: 114.56 | J24: =H24*I24 -> 6873.6 | K24: =G24+J24 -> 31873.275 | L24: 31873.275 | M24: =M23+K24-L24 -> 2959424.4
A25: 21 | B25: 46163 | G25: =E25*F25 -> 0 | J25: =H25*I25 -> 0 | K25: =G25+J25 -> 0 | L25: 500000 | M25: =M24+K25-L25 -> 2459424.4 | N25: BT
A26: 22 | B26: 46164 | G26: =E26*F26 -> 0 | J26: =H26*I26 -> 0 | K26: =G26+J26 -> 0 | M26: =M25+K26-L26 -> 2459424.4
A27: 23 | B27: 46165 | G27: =E27*F27 -> 0 | J27: =H27*I27 -> 0 | K27: =G27+J27 -> 0 | M27: =M26+K27-L27 -> 2459424.4
A28: 24 | B28: 46166 | G28: =E28*F28 -> 0 | J28: =H28*I28 -> 0 | K28: =G28+J28 -> 0 | M28: =M27+K28-L28 -> 2459424.4
A29: 25 | B29: 46167 | G29: =E29*F29 -> 0 | H29: 55 | I29: 118.18 | J29: =H29*I29 -> 6499.9 | K29: =G29+J29 -> 6499.9 | M29: =M28+K29-L29 -> 2465924.3
A30: 26 | B30: 46168 | G30: =E30*F30 -> 0 | J30: =H30*I30 -> 0 | K30: =G30+J30 -> 0 | M30: =M29+K30-L30 -> 2465924.3
A31: 27 | B31: 46169 | G31: =E31*F31 -> 0 | J31: =H31*I31 -> 0 | K31: =G31+J31 -> 0 | L31: 300000 | M31: =M30+K31-L31 -> 2165924.3
A32: 28 | B32: 46170 | G32: =E32*F32 -> 0 | J32: =H32*I32 -> 0 | K32: =G32+J32 -> 0 | M32: =M31+K32-L32 -> 2165924.3
A33: 29 | B33: 46171 | G33: =E33*F33 -> 0 | J33: =H33*I33 -> 0 | K33: =G33+J33 -> 0 | M33: =M32+K33-L33 -> 2165924.3
A34: 30 | B34: 46172 | G34: =E34*F34 -> 0 | H34: 30 | I34: 118.18 | J34: =H34*I34 -> 3545.4 | K34: =G34+J34 -> 3545.4 | M34: =M33+K34-L34 -> 2169469.7
A35: 31 | G35: =E35*F35 -> 0 | J35: =H35*I35 -> 0 | K35: =G35+J35 -> 0 | M35: =M34+K35-L35 -> 2169469.7
A36: 32 | G36: =E36*F36 -> 0 | J36: =H36*I36 -> 0 | K36: =G36+J36 -> 0 | M36: =M35+K36-L36 -> 2169469.7
A37: 33 | G37: =E37*F37 -> 0 | J37: =H37*I37 -> 0 | K37: =G37+J37 -> 0 | M37: =M36+K37-L37 -> 2169469.7
A38: 34 | G38: =E38*F38 -> 0 | J38: =H38*I38 -> 0 | K38: =G38+J38 -> 0 | M38: =M37+K38-L38 -> 2169469.7
A39: 35 | G39: =E39*F39 -> 0 | J39: =H39*I39 -> 0 | K39: =G39+J39 -> 0 | M39: =M38+K39-L39 -> 2169469.7 | P39: 41
A40: 36 | G40: =E40*F40 -> 0 | J40: =H40*I40 -> 0 | K40: =G40+J40 -> 0 | M40: =M39+K40-L40 -> 2169469.7 | P40: 40 | Q40: 5
A41: 37 | G41: =E41*F41 -> 0 | J41: =H41*I41 -> 0 | K41: =G41+J41 -> 0 | M41: =M40+K41-L41 -> 2169469.7
A42: 38 | G42: =E42*F42 -> 0 | J42: =H42*I42 -> 0 | K42: =G42+J42 -> 0 | M42: =M41+K42-L42 -> 2169469.7
A43: 39 | G43: =E43*F43 -> 0 | J43: =H43*I43 -> 0 | K43: =G43+J43 -> 0 | M43: =M42+K43-L43 -> 2169469.7
A44: 40 | G44: =E44*F44 -> 0 | J44: =H44*I44 -> 0 | K44: =G44+J44 -> 0 | M44: =M43+K44-L44 -> 2169469.7
A45: 41 | G45: =E45*F45 -> 0 | J45: =H45*I45 -> 0 | K45: =G45+J45 -> 0 | M45: =M44+K45-L45 -> 2169469.7
A46: 42 | G46: =E46*F46 -> 0 | J46: =H46*I46 -> 0 | K46: =G46+J46 -> 0 | M46: =M45+K46-L46 -> 2169469.7
A47: 43 | G47: =E47*F47 -> 0 | J47: =H47*I47 -> 0 | K47: =G47+J47 -> 0 | M47: =M46+K47-L47 -> 2169469.7
A48: 44 | G48: =E48*F48 -> 0 | J48: =H48*I48 -> 0 | K48: =G48+J48 -> 0 | M48: =M47+K48-L48 -> 2169469.7
A49: 45 | G49: =E49*F49 -> 0 | J49: =H49*I49 -> 0 | K49: =G49+J49 -> 0 | M49: =M48+K49-L49 -> 2169469.7
A50: 46 | G50: =E50*F50 -> 0 | J50: =H50*I50 -> 0 | K50: =G50+J50 -> 0 | M50: =M49+K50-L50 -> 2169469.7
A51: 47 | G51: =E51*F51 -> 0 | J51: =H51*I51 -> 0 | K51: =G51+J51 -> 0 | M51: =M50+K51-L51 -> 2169469.7
A52: 48 | G52: =E52*F52 -> 0 | J52: =H52*I52 -> 0 | K52: =G52+J52 -> 0 | L52: 0 | M52: =M51+K52-L52 -> 2169469.7
A53: 49 | G53: =E53*F53 -> 0 | J53: =H53*I53 -> 0 | K53: =G53+J53 -> 0 | L53: 0 | M53: =M52+K53-L53 -> 2169469.7
A54: 50 | G54: =E54*F54 -> 0 | J54: =H54*I54 -> 0 | K54: =G54+J54 -> 0 | L54: 0 | M54: =M53+K54-L54 -> 2169469.7
A55: 51 | G55: =E55*F55 -> 0 | J55: =H55*I55 -> 0 | K55: =G55+J55 -> 0 | L55: 0 | M55: =M54+K55-L55 -> 2169469.7 | O55: 1109792.3 | P55: =M55-O55 -> 1059677.5
E56: =SUM(E4:E55) -> 21903.53 | G56: =SUM(G4:G55) -> 2088961 | H56: =SUM(H4:H55) -> 415 | J56: =SUM(J4:J55) -> 46926.1 | K56: =SUM(K4:K55) -> 2135887.1 | L56: =SUM(L4:L55) -> 2631873.3

Sheet  Jalgaon-3
A1: Vasudeo
A2: S.No | B2: Date | C2: GRN No | D2: Ind No/Bill No | E2: Diesel (Lts) | F2: Price | G2: Amount | H2: Petrol (Lts) | I2: Price | J2: Amount | K2: Total amount | L2: Amount paid | M2: As on Date | N2: Remarks | O2: RTGS NO.
A3: Opening Balance | M3: 0
A4: 1 | B4: 46143 | E4: 1000 | F4: 91.67 | G4: =E4*F4 -> 91670 | H4: 0 | I4: 0 | J4: =H4*I4 -> 0 | K4: =G4+J4 -> 91670 | L4: 91670 | M4: =M3+K4-L4 -> 0 | O4: BPCL CARD PAYMENT - FC3450676132 | P4: TG 07 V 5356
A5: 2 | B5: 46145 | E5: 500 | F5: 91.67 | G5: =E5*F5 -> 45835 | H5: 0 | I5: 0 | J5: =H5*I5 -> 0 | K5: =G5+J5 -> 45835 | L5: 45835 | M5: =M4+K5-L5 -> 0 | O5: BPCL CARD PAYMENT - FC3450676132 | P5: TG 07 V 5356
A6: 3 | B6: 46145 | E6: 1259.68 | F6: 91.67 | G6: =E6*F6 -> 115474.87 | H6: 0 | I6: 0 | J6: =H6*I6 -> 0 | K6: =G6+J6 -> 115474.87 | L6: 115474.87 | M6: =M5+K6-L6 -> -0.0044 | O6: CNRBH00129325250
A7: 4 | B7: 46148 | E7: 900 | F7: 91.67 | G7: =E7*F7 -> 82503 | H7: 0 | I7: 0 | J7: =H7*I7 -> 0 | K7: =G7+J7 -> 82503 | L7: 228258 | M7: =M6+K7-L7 -> -145755 | N7: BT | O7: CNRBR52026050685101897 | P7: KA 16 AA 8261
A8: 5 | B8: 46151 | E8: 2500 | F8: 91.67 | G8: =E8*F8 -> 229175 | H8: 0 | I8: 0 | J8: =H8*I8 -> 0 | K8: =G8+J8 -> 229175 | L8: 0 | M8: =M7+K8-L8 -> 83419.996 | P8: KA 16 AA 8261
A9: 6 | B9: 46153 | E9: 2500 | F9: 91.67 | G9: =E9*F9 -> 229175 | H9: 91.67 | I9: 0 | J9: =H9*I9 -> 0 | K9: =G9+J9 -> 229175 | L9: 0 | M9: =M8+K9-L9 -> 312595
A10: 7 | B10: 46153 | G10: =E10*F10 -> 0 | H10: 0 | I10: 0 | J10: =H10*I10 -> 0 | K10: =G10+J10 -> 0 | L10: 283420 | M10: =M9+K10-L10 -> 29174.996 | N10: BT
B11: 46155 | E11: 2500 | F11: 91.67 | G11: =E11*F11 -> 229175 | H11: 0 | I11: 0 | J11: =H11*I11 -> 0 | K11: =G11+J11 -> 229175 | L11: 29175 | M11: =M10+K11-L11 -> 229175 | N11: BT
B12: 46157 | E12: 2500 | F12: 94.77 | G12: =E12*F12 -> 236925 | H12: 0 | I12: 0 | J12: =H12*I12 -> 0 | K12: =G12+J12 -> 236925 | L12: 229174 | M12: =M11+K12-L12 -> 236926 | N12: BT
B13: 46158 | E13: 1500 | F13: 94.77 | G13: =E13*F13 -> 142155 | H13: 0 | I13: 0 | J13: =H13*I13 -> 0 | K13: =G13+J13 -> 142155 | L13: 236925 | M13: =M12+K13-L13 -> 142156 | N13: BT
B14: 46159 | G14: =E14*F14 -> 0 | H14: 0 | I14: 0 | J14: =H14*I14 -> 0 | K14: =G14+J14 -> 0 | L14: 142156 | M14: =M13+K14-L14 -> 0 | N14: BT
B15: 46169 | E15: 2173.49 | F15: 99.47 | G15: =E15*F15 -> 216197.05 | H15: 0 | I15: 0 | J15: =H15*I15 -> 0 | K15: =G15+J15 -> 216197.05 | L15: 0 | M15: =M14+K15-L15 -> 216197.05
B16: 46170 | E16: 2800 | F16: 99.47 | G16: =E16*F16 -> 278516 | H16: 0 | I16: 0 | J16: =H16*I16 -> 0 | K16: =G16+J16 -> 278516 | L16: 0 | M16: =M15+K16-L16 -> 494713.05
G17: =E17*F17 -> 0 | H17: 0 | I17: 0 | J17: =H17*I17 -> 0 | K17: =G17+J17 -> 0 | L17: 0
E19: =SUM(E4:E18) -> 20133.17 | G19: =SUM(G4:G18) -> 1896800.9 | K19: =SUM(K4:K18) -> 1896800.9 | L19: =SUM(L4:L18) -> 1402087.9

Sheet Jalgaon-4
A1: Raksha
A2: S.No | B2: Date | C2: GRN No | D2: Ind No/Bill No | E2: Diesel (Lts) | F2: Price | G2: Amount | H2: Petrol (Lts) | I2: Price | J2: Amount | K2: Total amount | L2: Amount paid | M2: As on Date | N2: Remarks | O2: RTGS NO.
A3: Opening Balance | M3: 0
A4: 1 | B4: 46143 | C4: 1477 | E4: 1000 | F4: 91.67 | G4: =E4*F4 -> 91670 | H4: 0 | I4: 0 | J4: =H4*I4 -> 0 | K4: =G4+J4 -> 91670 | L4: 91670 | M4: =M3+K4-L4 -> 0 | N4: RAKSHA AUTO FUELS | O4: BPCL CARD PAYMENT - FC3450676132 | P4: TG 07 V 5356
A5: 2 | B5: 46145 | C5: 1489 | E5: 500 | F5: 91.67 | G5: =E5*F5 -> 45835 | H5: 0 | I5: 0 | J5: =H5*I5 -> 0 | K5: =G5+J5 -> 45835 | L5: 45835 | M5: =M4+K5-L5 -> 0 | N5: RAKSHA AUTO FUELS | O5: BPCL CARD PAYMENT - FC3450676132 | P5: TG 07 V 5356
A6: 3 | B6: 46148 | C6: 1501 | E6: 2500 | F6: 91.67 | G6: =E6*F6 -> 229175 | H6: 0 | I6: 0 | J6: =H6*I6 -> 0 | K6: =G6+J6 -> 229175 | L6: 228258 | M6: =M5+K6-L6 -> 917 | N6: RAKSHA AUTO FUELS | O6: CNRBR5226050685102162 | P6: KA 16 AA 8261 | Q6: HO PAYMENT DONE
A7: 4 | B7: 46149 | C7: 1509 | E7: 2500.01 | F7: 91.67 | G7: =E7*F7 -> 229175.92 | H7: 0 | I7: 0 | J7: =H7*I7 -> 0 | K7: =G7+J7 -> 229175.92 | L7: 0 | M7: =M6+K7-L7 -> 230092.92 | N7: RAKSHA AUTO FUELS | P7: KA 16 AA 8265
A8: 5 | B8: 46150 | E8: 0 | F8: 0 | G8: =E8*F8 -> 0 | H8: 0 | I8: 0 | J8: =H8*I8 -> 0 | K8: =G8+J8 -> 0 | L8: 230092.92 | M8: =M7+K8-L8 -> -0.0033 | N8: RAKSHA AUTO FUELS | O8: CNRBR52026050885329103
A9: 6 | B9: 46152 | C9: 1518 | E9: 2447 | F9: 91.67 | G9: =E9*F9 -> 224316.49 | H9: 0 | I9: 0 | J9: =H9*I9 -> 0 | K9: =G9+J9 -> 224316.49 | L9: 0 | M9: =M8+K9-L9 -> 224316.49 | N9: RAKSHA AUTO FUELS | O9: TG 07 V 5356-2176.53 AND 8261-270.47
A10: 7 | B10: 46153 | G10: =E10*F10 -> 0 | H10: 0 | I10: 0 | J10: =H10*I10 -> 0 | K10: =G10+J10 -> 0 | L10: 224316.49 | M10: =M9+K10-L10 -> -0.0033 | N10: RAKSHA AUTO FUELS
B11: 46154 | E11: 2500 | F11: 91.67 | G11: =E11*F11 -> 229175 | H11: 0 | I11: 0 | J11: =H11*I11 -> 0 | K11: =G11+J11 -> 229175 | L11: 0 | M11: =M10+K11-L11 -> 229175
B12: 46155 | G12: =E12*F12 -> 0 | H12: 0 | I12: 0 | J12: =H12*I12 -> 0 | K12: =G12+J12 -> 0 | L12: 229175 | M12: =M11+K12-L12 -> 0
B13: 46167 | E13: 590.2 | F13: 99.47 | G13: =E13*F13 -> 58707.194 | H13: 0 | I13: 0 | J13: =H13*I13 -> 0 | K13: =G13+J13 -> 58707.194 | L13: =H13+K13 -> 58707.194 | M13: =M12+K13-L13 -> 0
G14: =E14*F14 -> 0 | H14: 0 | I14: 0 | J14: =H14*I14 -> 0 | K14: =G14+J14 -> 0 | L14: 0 | M14: =M13+K14-L14 -> 0
G15: =E15*F15 -> 0 | H15: 0 | I15: 0 | J15: =H15*I15 -> 0 | K15: =G15+J15 -> 0 | L15: 0 | M15: =M14+K15-L15 -> 0
