Workbook

Sheet  MIs
A2: S.No | B2: NAme | C2: Lacation | D2: Card Number | E2: Card Number | F2: Category | G2: 1st Jan | I2: 2nd Jan | J2: 3rd Jan | K2: 4th Jan | L2: 5th Jan | M2: 6th Jan | N2: 7th Jan | O2: 8th Jan | P2: 9th Jan | Q2: 10th Jan | R2: 11th Jan | S2: 12th Jan | T2: 13th Jan | U2: 14th Jan | V2: 15th Jan | W2: 16th Jan | X2: 17th Jan | Y2: 18th Jan | Z2: 19th Jan | AA2: 20th Jan | AB2: 21st Jan | AC2: 22nd Jan | AD2: 23rd Jan | AE2: 24th Jan | AF2: 25th Jan | AG2: 26th Jan | AH2: 27th Jan | AI2: 28th Jan | AJ2: 29th Jan | AK2: 30th Jan | AL2: 31st Jan | AM2: Total
F3: Diesel
A4: 1 | B4: Rambabu | C4: HO(Two Wheeler) | D4: FC3450563999 | E4: Diesel | F4: 0 | G4: 0 | H4: 0 | I4: 0 | J4: 0 | K4: 0 | L4: 0 | M4: 0 | N4: 0 | O4: 0 | P4: 0 | Q4: 0 | R4: 0 | S4: 0 | T4: 0 | U4: 0 | V4: 0 | W4: 0 | X4: 5.22 | Y4: 0 | Z4: 0 | AA4: 0 | AB4: 0 | AC4: 0 | AD4: 60 | AE4: 0 | AF4: 0 | AG4: 0 | AH4: 4.56 | AI4: 0 | AJ4: 0 | AK4: 0 | AL4: 0 | AM4: =SUM(F4:AL4) -> 69.78
E5: Petrol | F5: 0 | G5: 4.69 | H5: 0 | I5: 0 | J5: 0 | K5: 0 | L5: 0 | M5: 0 | N5: 3.91 | O5: 0 | P5: 6.98 | Q5: 0 | R5: 0 | S5: 0 | T5: 0 | U5: 0 | V5: 0 | W5: 0 | X5: 0 | Y5: 0 | Z5: 0 | AB5: 0 | AC5: 0 | AD5: 0 | AE5: 0 | AF5: 0 | AG5: 0 | AH5: 0 | AI5: 0 | AJ5: 0 | AK5: 0 | AL5: 0 | AM5: =SUM(F5:AL5) -> 15.58
A6: 2 | B6: Hanumanth Rao | C6: HO | D6: FC3450676131 | E6: Diesel | F6: 0 | G6: 0 | H6: 0 | I6: 0 | J6: 0 | K6: 0 | L6: 0 | M6: 0 | N6: 0 | O6: 0 | P6: 0 | Q6: 0 | R6: 0 | S6: 0 | T6: 0 | U6: 0 | V6: 0 | W6: 0 | X6: 0 | Y6: 0 | Z6: 0 | AA6: 0 | AB6: 0 | AC6: 0 | AD6: 0 | AE6: 0 | AF6: 0 | AG6: 0 | AH6: 0 | AI6: 0 | AJ6: 0 | AK6: 0 | AL6: 0 | AM6: =SUM(F6:AL6) -> 0
E7: Petrol | F7: 0 | G7: 0 | H7: 0 | I7: 0 | J7: 0 | K7: 0 | L7: 0 | M7: 0 | N7: 0 | O7: 0 | P7: 0 | Q7: 0 | R7: 0 | S7: 0 | T7: 0 | U7: 0 | V7: 0 | W7: 0 | X7: 0 | Y7: 0 | Z7: 0 | AB7: 0 | AC7: 0 | AD7: 0 | AE7: 0 | AF7: 0 | AG7: 0 | AH7: 0 | AI7: 0 | AJ7: 0 | AK7: 0 | AL7: 0 | AM7: =SUM(F7:AL7) -> 0
A8: 3 | B8: Radhakrishna | C8: HO | D8: FC8000207658 | E8: Diesel | F8: 0 | G8: 0 | H8: 0 | I8: 0 | J8: 33.44 | K8: 0 | L8: 0 | M8: 0 | N8: 0 | O8: 0 | P8: 0 | Q8: 0 | R8: 35.53 | S8: 0 | T8: 0 | U8: 0 | V8: 0 | W8: 0 | X8: 0 | Y8: 0 | Z8: 0 | AA8: 0 | AB8: 33.44 | AC8: 0 | AD8: 0 | AE8: 0 | AF8: 0 | AG8: 0 | AH8: 0 | AI8: 0 | AJ8: 0 | AK8: 0 | AL8: 0 | AM8: =SUM(F8:AL8) -> 102.41
E9: Petrol | F9: 0 | G9: 0 | H9: 0 | I9: 0 | J9: 0 | K9: 0 | L9: 0 | M9: 0 | N9: 0 | O9: 0 | P9: 0 | Q9: 0 | R9: 0 | S9: 0 | T9: 0 | U9: 0 | V9: 0 | W9: 0 | X9: 0 | Y9: 0 | Z9: 0 | AB9: 0 | AC9: 0 | AD9: 0 | AE9: 0 | AF9: 0 | AG9: 0 | AH9: 0 | AI9: 0 | AJ9: 0 | AK9: 0 | AL9: 0 | AM9: =SUM(F9:AL9) -> 0
A10: 4 | B10: VIjay | C10: HO | D10: FC3450698859 | E10: Diesel | F10: 0 | G10: 0 | H10: 0 | I10: 0 | J10: 0 | K10: 0 | L10: 0 | M10: 0 | N10: 0 | O10: 0 | P10: 49.22 | Q10: 0 | R10: 0 | S10: 0 | T10: 0 | U10: 54.57 | V10: 0 | W10: 0 | X10: 0 | Y10: 0 | Z10: 0 | AA10: 0 | AB10: 0 | AC10: 0 | AD10: 49.8 | AE10: 0 | AF10: 0 | AG10: 0 | AH10: 0 | AI10: 0 | AJ10: 0 | AK10: 0 | AL10: 0 | AM10: =SUM(F10:AL10) -> 153.59
E11: Petrol | F11: 0 | G11: 0 | H11: 0 | I11: 0 | J11: 0 | K11: 0 | L11: 0 | M11: 0 | N11: 0 | O11: 0 | P11: 0 | Q11: 0 | R11: 0 | S11: 0 | T11: 0 | U11: 0 | V11: 0 | W11: 0 | X11: 0 | Y11: 0 | Z11: 0 | AB11: 0 | AC11: 0 | AD11: 0 | AE11: 0 | AF11: 0 | AG11: 0 | AH11: 0 | AI11: 0 | AJ11: 0 | AK11: 0 | AL11: 0 | AM11: =SUM(F11:AL11) -> 0
A12: 5 | B12: Client | C12: Hiriyur | D12: FC3450698864 | E12: Diesel | F12: 0 | G12: 0 | H12: 0 | I12: 0 | J12: 0 | K12: 0 | L12: 0 | M12: 0 | N12: 86.29 | O12: 0 | P12: 0 | Q12: 0 | R12: 0 | S12: 0 | T12: 0 | U12: 0 | V12: 0 | W12: 0 | X12: 0 | Y12: 0 | Z12: 0 | AA12: 0 | AB12: 0 | AC12: 0 | AD12: 145.61 | AE12: 0 | AF12: 0 | AG12: 0 | AH12: 0 | AI12: 0 | AJ12: 0 | AK12: 0 | AL12: 0 | AM12: =SUM(F12:AL12) -> 231.9
E13: Petrol | F13: 0 | G13: 0 | H13: 0 | I13: 0 | J13: 0 | K13: 0 | L13: 0 | M13: 0 | N13: 0 | O13: 0 | P13: 0 | Q13: 0 | R13: 0 | S13: 0 | T13: 0 | U13: 0 | V13: 0 | W13: 0 | X13: 0 | Y13: 0 | Z13: 0 | AB13: 0 | AC13: 0 | AD13: 0 | AE13: 0 | AF13: 0 | AG13: 0 | AH13: 0 | AI13: 0 | AJ13: 0 | AK13: 0 | AL13: 0 | AM13: =SUM(F13:AL13) -> 0
A14: 6 | B14: Client | C14: Hosadurga | D14: FC3450698865 | E14: Diesel | F14: 0 | G14: 0 | H14: 0 | I14: 0 | J14: 0 | K14: 0 | L14: 40 | M14: 40 | N14: 0 | O14: 36 | P14: 35 | Q14: 0 | R14: 0 | S14: 0 | T14: 0 | U14: 0 | V14: 0 | W14: 45 | X14: 45 | Y14: 43.53 | Z14: 40 | AA14: 43 | AB14: 0 | AC14: 40 | AD14: 0 | AE14: 40 | AF14: 0 | AG14: 0 | AH14: 0 | AI14: 0 | AJ14: 0 | AK14: 0 | AL14: 0 | AM14: =SUM(F14:AL14) -> 447.53
E15: Petrol | F15: 0 | G15: 0 | H15: 0 | I15: 0 | J15: 0 | K15: 0 | L15: 0 | M15: 0 | N15: 0 | O15: 0 | P15: 0 | Q15: 0 | R15: 0 | S15: 0 | T15: 0 | U15: 0 | V15: 0 | W15: 0 | X15: 0 | Y15: 0 | Z15: 0 | AB15: 0 | AC15: 0 | AD15: 0 | AE15: 0 | AF15: 0 | AG15: 0 | AH15: 0 | AI15: 0 | AJ15: 0 | AK15: 0 | AL15: 0 | AM15: =SUM(F15:AL15) -> 0
G18: Diesel Price

Sheet  April-2026
A1: S.no | B1: Site Name | C1: Bunk Name | D1: Diesel(Liters) | E1: Diesel Amount | F1: Petrol(Liters) | G1: Petrol Amount | H1: Total Amount | I1: Opening Blance | J1: Amount Paid | K1: Closing Balances
A2: 1 | B2: Khammam-1 | C2: Divya laxmi ganapathi | D2: =+'Khammam-1'!E38 -> 26600.49 | E2: =+'Khammam-1'!G38 -> 2545134.9 | F2: =+'Khammam-1'!H38 -> 351.49 | G2: =+'Khammam-1'!J38 -> 37771.115 | H2: =E2+G2 -> 2582906 | I2: =+'Khammam-1'!K3 -> 4176411.7 | J2: =+'Khammam-1'!L38 -> 4989687 | K2: =H2+I2-J2 -> 1769630.7
A3: 2 | B3: Khammam-2 | C3: Jayasai union bunk | D3: =+'Khammam-2'!E35 -> 39552.56 | E3: =+'Khammam-2'!G35 -> 3785575.5 | F3: =+'Khammam-2'!H35 -> 561 | G3: =+'Khammam-2'!J35 -> 60301.89 | H3: =E3+G3 -> 3845877.4 | I3: =+'Khammam-2'!K3 -> 8032637.3 | J3: =+'Khammam-2'!L35 -> 8152861.8 | K3: =H3+I3-J3 -> 3725653
A4: 3 | B4: Khammam-3 | C4: JSASFuel Genie India Pvt.Ltd | D4: =+'Khammam-3'!E35 -> 48000 | E4: =+'Khammam-3'!G35 -> 4572600 | F4: =+'Khammam-3'!H35 -> 0 | G4: =+'Khammam-3'!J35 -> 0 | H4: =E4+G4 -> 4572600 | I4: =+'Khammam-3'!M3 -> 8227903.3 | J4: =+'Khammam-3'!L35 -> 10227903 | K4: =H4+I4-J4 -> 2572600.3
A5: 4 | B5: Khammam-4 | C5: Vajra Mahalakshmi filling station | D5: =+'Khammam-4'!E38 -> 0 | E5: =+'Khammam-4'!G38 -> 0 | F5: =+'Khammam-4'!H38 -> 0 | G5: =+'Khammam-4'!J38 -> 0 | H5: =E5+G5 -> 0 | I5: =+'Khammam-4'!M3 -> 330407.08 | J5: =+'Khammam-4'!L38 -> 330407 | K5: =H5+I5-J5 -> 0.08
A6: 5 | B6: Khammam-5 | C6: SR HP Filling Station | D6: =+'Khammam-5'!E38 -> 3135.46 | E6: =+'Khammam-5'!G38 -> 300000.81 | F6: =+'Khammam-5'!H38 -> 0 | G6: =+'Khammam-5'!J38 -> 0 | H6: =E6+G6 -> 300000.81 | I6: =+'Khammam-5'!M3 -> 0 | J6: =+'Khammam-5'!L38 -> 300000.81 | K6: =H6+I6-J6 -> 0
A7: 6 | B7: Khammam-6 | C7: NA | D7: =+' Khammam&Cash'!E46 -> 24857.48 | E7: =+' Khammam&Cash'!G46 -> 2378764.7 | F7: =+' Khammam&Cash'!H46 -> 95 | G7: =+' Khammam&Cash'!J46 -> 10208.7 | H7: =E7+G7 -> 2388973.4 | I7: =+' Khammam&Cash'!M3 -> 0 | J7: =+' Khammam&Cash'!L46 -> 2388973.4 | K7: =H7+I7-J7 -> 0.0020000003
A8: 7 | B8: Jadcherla-1 | C8: JSASFuel Genie India Pvt.Ltd | D8: =+'Jadcherla-3'!E35 -> 13690 | E8: =+'Jadcherla-3'!G35 -> 1313281.7 | F8: =+'Jadcherla-3'!H35 -> 0 | G8: =+'Jadcherla-3'!J35 -> 0 | H8: =E8+G8 -> 1313281.7 | I8: =+'Jadcherla-3'!M3 -> 2453209.4 | J8: =+'Jadcherla-3'!L35 -> 2453209.4 | K8: =H8+I8-J8 -> 1313281.7
A9: 8 | B9: Jadcherla-2 | C9: Shree Poornima F/S | D9: =+'Jadcherla-4'!E35 -> 4020 | E9: =+'Jadcherla-4'!G35 -> 387246 | F9: =+'Jadcherla-4'!H35 -> 80 | G9: =+'Jadcherla-4'!J35 -> 8653.2 | H9: =E9+G9 -> 395899.2 | I9: =+'Jadcherla-4'!M3 -> 9729 | J9: =+'Jadcherla-4'!L35 -> 402105 | K9: =H9+I9-J9 -> 3523.2
A10: 9 | B10: Jadcherla-3 | C10: Sai Baba Filling Station | D10: =+' Jadcherla'!E35 -> 3000 | E10: =+' Jadcherla'!G35 -> 289260 | F10: =+' Jadcherla'!H35 -> 0 | G10: =+' Jadcherla'!J35 -> 0 | H10: =E10+G10 -> 289260 | I10: =+' Jadcherla'!M3 -> 0 | J10: =+' Jadcherla'!L35 -> 244630 | K10: =H10+I10-J10 -> 44630
A11: 10 | B11: Sangareddy-1 | C11: Durga Indhan | D11: =+' Sangareeddy-1'!E35 -> 0 | E11: =+' Sangareeddy-1'!G35 -> 0 | F11: =+' Sangareeddy-1'!H35 -> 0 | G11: =+' Sangareeddy-1'!J35 -> 0 | H11: =E11+G11 -> 0 | I11: =+' Sangareeddy-1'!M3 -> 71161.048 | J11: =+' Sangareeddy-1'!L35 -> 71161.05 | K11: =H11+I11-J11 -> -0.0019999999
A12: 11 | B12: Sangareddy-2 | C12: Durga Bhavani F/S | D12: =+' Sangareddy-2'!E35 -> 18689.16 | E12: =+' Sangareddy-2'!G35 -> 1802382.6 | F12: =+' Sangareddy-2'!H35 -> 315.63 | G12: =+' Sangareddy-2'!J35 -> 34185.885 | H12: =E12+G12 -> 1836568.5 | I12: =+' Sangareddy-2'!M3 -> 324643.92 | J12: =+' Sangareddy-2'!L35 -> 1902217 | K12: =H12+I12-J12 -> 258995.39
A13: 12 | B13: Sangareddy-3 | C13: Shiva Parvathi Filling Station | D13: =+' Sangareddy-3'!E35 -> 5856.17 | E13: =+' Sangareddy-3'!G35 -> 563539.24 | F13: =+' Sangareddy-3'!H35 -> 0 | G13: =+' Sangareddy-3'!J35 -> 0 | H13: =E13+G13 -> 563539.24 | I13: =+' Sangareddy-3'!M3 -> 0 | J13: =+' Sangareddy-3'!L35 -> 400000 | K13: =H13+I13-J13 -> 163539.24
A14: 13 | B14: NarayanKhed | C14: Sai Shiva Filling Station | D14: =+' Narayankhed'!E35 -> 300 | E14: =+' Narayankhed'!G35 -> 29100 | F14: =+' Narayankhed'!H35 -> 0 | G14: =+' Narayankhed'!J35 -> 0 | H14: =E14+G14 -> 29100 | I14: =+' Narayankhed'!M3 -> 0 | J14: =+' Narayankhed'!L35 -> 29100 | K14: =H14+I14-J14 -> 0
A15: 14 | B15: Dindi | C15: Akarapu Balakistamma Fillling | D15: =+Dindi!E35 -> 0 | E15: =+Dindi!G35 -> 0 | F15: =+Dindi!H35 -> 0 | G15: =+Dindi!J35 -> 0 | H15: =E15+G15 -> 0 | I15: =+Dindi!M3 -> 0 | J15: =+Dindi!L35 -> 0 | K15: =H15+I15-J15 -> 0
A16: 15 | B16: Madanapalli | C16: NA | D16: =+'Madana palli'!E36 -> 0 | E16: =+'Madana palli'!G36 -> 0 | F16: =+'Madana palli'!H36 -> 0 | G16: =+'Madana palli'!J36 -> 0 | H16: =E16+G16 -> 0 | I16: =+'Madana palli'!M3 -> 0 | J16: =+'Madana palli'!L36 -> 0 | K16: =H16+I16-J16 -> 0
A17: 16 | B17: Kakinada | C17: NA | D17: =+Amalapuram!E48 -> 1141.65 | E17: =+Amalapuram!G48 -> 110749.41 | F17: =+Amalapuram!H48 -> 105 | G17: =+Amalapuram!J48 -> 11422.35 | H17: =E17+G17 -> 122171.76 | I17: =+Amalapuram!M3 -> 0 | J17: =+Amalapuram!L48 -> 122171.34 | K17: =H17+I17-J17 -> 0.424
A18: 17 | B18: YG Gudda-2 | C18: Pankaja HP Fuel Center | D18: =+'YG Gudda-2'!E37 -> 7200 | E18: =+'YG Gudda-2'!G37 -> 657576 | F18: =+'YG Gudda-2'!H37 -> 315 | G18: =+'YG Gudda-2'!J37 -> 32530.05 | H18: =E18+G18 -> 690106.05 | I18: =+'YG Gudda-2'!M3 -> 250329.91 | J18: =+'YG Gudda-2'!L37 -> 746330 | K18: =H18+I18-J18 -> 194105.96
A19: 18 | B19: Hosadurga-2 | C19: Shree Veeraprathap Fuel | D19: =+'Hosadurga -2'!E35 -> 6599.13 | E19: =+'Hosadurga -2'!G35 -> 603734.35 | F19: =+'Hosadurga -2'!H35 -> 210 | G19: =+'Hosadurga -2'!J35 -> 21754.95 | H19: =+'Hosadurga -2'!K35 -> 625489.3 | I19: =+'Hosadurga -2'!K3 -> 198796.97 | J19: =+'Hosadurga -2'!L35 -> 575797 | K19: =H19+I19-J19 -> 248489.28
A20: 19 | B20: Malebennuru(KUWSDB) | C20: Sri Ramanjuneya Service Station | D20: =+'Malebenur(KUWSDB)'!E37 -> 3600 | E20: =+'Malebenur(KUWSDB)'!G37 -> 331236 | F20: =+'Malebenur(KUWSDB)'!H37 -> 195 | G20: =+'Malebenur(KUWSDB)'!J37 -> 20233.2 | H20: =E20+G20 -> 351469.2 | I20: =+'Malebenur(KUWSDB)'!K3 -> 79478.01 | J20: =+'Malebenur(KUWSDB)'!L37 -> 237298 | K20: =H20+I20-J20 -> 193649.21
A21: 20 | B21: kadur | C21: Vishal Service Station | D21: =+Kadur!E35 -> 1800 | E21: =+Kadur!G35 -> 171270 | F21: =+Kadur!H35 -> 140 | G21: =+Kadur!J35 -> 15297.8 | H21: =E21+G21 -> 186567.8 | I21: =+Kadur!K3 -> 102970.63 | J21: =+Kadur!L35 -> 289538 | K21: =H21+I21-J21 -> 0.431
A22: 21 | B22: Hiriyur(VJNL) | C22: Sri Balaji Agencies | D22: =+'Hiriyur(VJNL)'!E35 -> 5000 | E22: =+'Hiriyur(VJNL)'!G35 -> 460500 | F22: =+'Hiriyur(VJNL)'!H35 -> 175 | G22: =+'Hiriyur(VJNL)'!J35 -> 18175.5 | H22: =E22+G22 -> 478675.5 | I22: =+'Hiriyur(VJNL)'!K3 -> 69.8 | J22: =+'Hiriyur(VJNL)'!L35 -> 200000 | K22: =H22+I22-J22 -> 278745.3
A23: 22 | B23: Chellakere(KUWSDB) | C23: Shivaganga Service Station | D23: =+'Chellakere -1'!E35 -> 4600 | E23: =+'Chellakere -1'!G35 -> 423520.2 | F23: =+'Chellakere -1'!H35 -> 205 | G23: =+'Chellakere -1'!J35 -> 21283.1 | H23: =E23+G23 -> 444803.3 | I23: =+'Chellakere -1'!K3 -> 215562.07 | J23: =+'Chellakere -1'!L35 -> 410562 | K23: =H23+I23-J23 -> 249803.37
A24: 23 | B24: Chellakere(KUWSDB)-09 | C24: Shivaganga Service Station | D24: =+' Chellakere-PKG-9'!E35 -> 325.38 | E24: =+' Chellakere-PKG-9'!G35 -> 29957.387 | F24: =+' Chellakere-PKG-9'!H35 -> 38 | G24: =+' Chellakere-PKG-9'!J35 -> 3945.16 | H24: =E24+G24 -> 33902.547 | I24: =+' Chellakere-PKG-9'!M3 -> 0 | J24: =+' Chellakere-PKG-9'!L35 -> 33902.547 | K24: =H24+I24-J24 -> 0
A25: 24 | B25: Molakalmuru | C25: Sri Lakshmi Venkateshwara Filling Station | D25: =+Molakamuru!E35 -> 1300 | E25: =+Molakamuru!G35 -> 119678 | F25: =+Molakamuru!H35 -> 50 | G25: =+Molakamuru!J35 -> 5190.5 | H25: =E25+G25 -> 124868.5 | I25: =+Molakamuru!K3 -> 4179.7152 | J25: =+Molakamuru!L35 -> 72756.4 | K25: =H25+I25-J25 -> 56291.815
A26: 25 | B26: Chennagiri | C26: NA | D26: =+' Chennagiri'!E35 -> 360 | E26: =+' Chennagiri'!G35 -> 33084.4 | F26: =+' Chennagiri'!H35 -> 49 | G26: =+' Chennagiri'!J35 -> 5087.89 | H26: =E26+G26 -> 38172.29 | I26: =+' Chennagiri'!K3 -> 0 | J26: =+' Chennagiri'!L35 -> 38172.29 | K26: =H26+I26-J26 -> 0
A27: 26 | B27: Khanapur(PKG-3) | C27: V.V.Varde | D27: =+Khanapur!E35 -> 2008.49 | E27: =+Khanapur!G35 -> 182531.57 | F27: =+Khanapur!H35 -> 153 | G27: =+Khanapur!J35 -> 15723.81 | H27: =E27+G27 -> 198255.38 | I27: =+Khanapur!M3 -> 153658.75 | J27: =+Khanapur!L35 -> 237619 | K27: =H27+I27-J27 -> 114295.13
A28: 27 | B28: Munavalli(PKG-3)-2 | C28: Shre Shiva Petroleum | D28: =+'Munavali-2'!E38 -> 12432.9 | E28: =+'Munavali-2'!G38 -> 1138087.2 | F28: =+'Munavali-2'!H38 -> 204.77 | G28: =+'Munavali-2'!J38 -> 21291.852 | H28: =E28+G28 -> 1159379 | I28: =+'Munavali-2'!M3 -> 607059.51 | J28: =+'Munavali-2'!L38 -> 1198830.9 | K28: =H28+I28-J28 -> 567607.62
A29: 28 | B29: Borgaon(PKG-3) | C29: Aadisagar Petrolium | D29: =+Borgaon!E35 -> 4710.57 | E29: =+Borgaon!G35 -> 432289.01 | F29: =+Borgaon!H35 -> 99.81 | G29: =+Borgaon!J35 -> 10353.291 | H29: =E29+G29 -> 442642.3 | I29: =+Borgaon!K3 -> 85513.088 | J29: =+Borgaon!L35 -> 421500 | K29: =H29+I29-J29 -> 106655.39
A30: 29 | B30: Ugar,Kudichi(PKG-3) | C30: Shiri Bhrhmanath Petrolium | D30: =+'Ugar,Khagwad,Kudichi'!E35 -> 10909.45 | E30: =+'Ugar,Khagwad,Kudichi'!G35 -> 1002905.7 | F30: =+'Ugar,Khagwad,Kudichi'!H35 -> 300 | G30: =+'Ugar,Khagwad,Kudichi'!J35 -> 31543.4 | H30: =E30+G30 -> 1034449.1 | I30: =+'Ugar,Khagwad,Kudichi'!M3 -> 434415.61 | J30: =+'Ugar,Khagwad,Kudichi'!L35 -> 884650 | K30: =H30+I30-J30 -> 584214.75
A31: 30 | B31: Kabbur(PKG-3) | C31: Shri Jai Hanuman Petrolium | D31: =+Kabbur!E35 -> 436.01 | E31: =+Kabbur!G35 -> 39938.516 | F31: =+Kabbur!H35 -> 20.83 | G31: =+Kabbur!J35 -> 2156.7382 | H31: =E31+G31 -> 42095.254 | I31: 0 | J31: =+Kabbur!L35 -> 42095.254 | K31: =H31+I31-J31 -> 0
A32: 31 | B32: Kumta (PKG-1) | C32: V.M.MIRJANKAR (KUMTA) BHARAT | D32: =+kumta!E36 -> 2145 | E32: =+kumta!G36 -> 197273.15 | F32: =+kumta!H36 -> 177 | G32: =+kumta!J36 -> 18409.77 | H32: =E32+G32 -> 215682.92 | I32: =kumta!M3 -> 34759.3 | J32: =+kumta!L36 -> 247835 | K32: =H32+I32-J32 -> 2607.22
A33: 32 | B33: Jalgaon | C33: Jai Bajarang Sarvo Senter Bodwad | D33: =+Jalgaon!E55 -> 9000 | E33: =+Jalgaon!G55 -> 825390 | F33: =+Jalgaon!H55 -> 60 | G33: =+Jalgaon!J55 -> 6311.4 | H33: =E33+G33 -> 831701.4 | I33: =+Jalgaon!K3 -> 1651007.9 | J33: =+Jalgaon!L55 -> 2388895.6 | K33: =H33+I33-J33 -> 93813.679
A34: 33 | B34: Jalgaon-2 | C34: Nayara | D34: =+'Jalgoan-2'!E55 -> 64300.61 | E34: ='Jalgoan-2'!G55 -> 6089910.8 | F34: =+'Jalgoan-2'!H55 -> 405 | G34: =+'Jalgoan-2'!J55 -> 44728.2 | H34: =E34+G34 -> 6134639 | I34: =+'Jalgoan-2'!M3 -> 5471845 | J34: =+'Jalgoan-2'!L55 -> 8941028 | K34: =H34+I34-J34 -> 2665456
A35: 34 | B35: Jalgaon-3 | C35: T R KAPOOR AND CO | D35: =+' Jalgoan-3'!E55 -> 2500 | E35: =+' Jalgoan-3'!G55 -> 229925 | F35: =+' Jalgoan-3'!H55 -> 0 | G35: =+' Jalgoan-3'!J55 -> 0 | H35: =E35+G35 -> 229925 | I35: =+' Jalgoan-3'!M3 -> 0 | J35: =+' Jalgoan-3'!L55 -> 229925 | K35: =H35+I35-J35 -> 0
A36: 35 | B36: Jalgaon-4 | C36: NA | D36: =+' Jalgoan-4'!E60 -> 40913.03 | E36: =+' Jalgoan-4'!G60 -> 3753069.7 | F36: =+' Jalgoan-4'!H60 -> 0 | G36: =+' Jalgoan-4'!J60 -> 0 | H36: =E36+G36 -> 3753069.7 | I36: =+' Jalgoan-4'!M3 -> 0 | J36: =+' Jalgoan-4'!L60 -> 3753069.7 | K36: =H36+I36-J36 -> 0
A37: 36 | B37: MKBD | C37: Shree Sai Samarth Petroleum | D37: =+MKBD!E39 -> 27000 | E37: =+MKBD!G39 -> 2460780 | F37: =+MKBD!H39 -> 166 | G37: =+MKBD!J39 -> 18929 | H37: =E37+G37 -> 2479709 | I37: =+MKBD!K3 -> 1463406.5 | J37: =+MKBD!L39 -> 1372840 | K37: =H37+I37-J37 -> 2570275.5
A38: 37 | B38: Haveri | C38: M/s Magavi City Fuels | D38: =' Haveri-2'!E38 -> 2758.19 | E38: =' Haveri-2'!G38 -> 252346.8 | F38: =' Haveri-2'!H38 -> 101.33 | G38: =' Haveri-2'!J38 -> 10480.562 | H38: =E38+G38 -> 262827.36 | I38: =' Haveri-2'!M3 -> 77285.143 | J38: =+' Haveri-2'!L38 -> 280000 | K38: =H38+I38-J38 -> 60112.508
A39: 38 | B39: Guttal-2 | C39: Himagiri Petroleum | D39: =+' Guttal-2'!E35 -> 7724.14 | E39: =+' Guttal-2'!G35 -> 708921.57 | F39: =+' Guttal-2'!H35 -> 180 | G39: =+' Guttal-2'!J35 -> 18673.2 | H39: =E39+G39 -> 727594.77 | I39: =+' Guttal-2'!M3 -> 203929.33 | J39: =+' Guttal-2'!L35 -> 730929 | K39: =H39+I39-J39 -> 200595.1
A40: 39 | B40: Rattihali-2 | C40: Shiva Oil Traders | D40: =+'Rattihali-2'!E37 -> 3860.03 | E40: =+'Rattihali-2'!G37 -> 354698.16 | F40: =+'Rattihali-2'!H37 -> 109 | G40: =+'Rattihali-2'!J37 -> 11319.65 | H40: =E40+G40 -> 366017.81 | I40: =+'Rattihali-2'!M3 -> 263742.1 | J40: =+'Rattihali-2'!L37 -> 363742 | K40: =H40+I40-J40 -> 266017.9
A41: 40 | B41: Gajendragada | C41: Vanasri Petrol Pump | D41: =+Gajendragada!E35 -> 377 | E41: =+Gajendragada!G35 -> 34619.91 | F41: =+Gajendragada!H35 -> 64 | G41: =+Gajendragada!J35 -> 6643.2 | H41: =E41+G41 -> 41263.11 | I41: =+Gajendragada!K3 -> 47365.079 | J41: =+Gajendragada!L35 -> 47365 | K41: =H41+I41-J41 -> 41263.189
A42: 41 | B42: Gokak(PKG-3) | C42: AJ Petrolinks | D42: =+'Gokak Dharwad PKG 3'!E42 -> 11958.26 | E42: =+'Gokak Dharwad PKG 3'!G42 -> 1093941.6 | F42: =+'Gokak Dharwad PKG 3'!H42 -> 399 | G42: =+'Gokak Dharwad PKG 3'!J42 -> 42064.92 | H42: =E42+G42 -> 1136006.5 | I42: =+'Gokak Dharwad PKG 3'!K3 -> 367936.99 | J42: =+'Gokak Dharwad PKG 3'!L42 -> 1177900 | K42: =H42+I42-J42 -> 326043.53
A43: 42 | B43: Hukkere | C43: TR Assocites | D43: =+' TR Associates'!E35 -> 11982.27 | E43: =+' TR Associates'!G35 -> 1094220.9 | F43: =+' TR Associates'!H35 -> 30 | G43: =+' TR Associates'!J35 -> 3096.9 | H43: =E43+G43 -> 1097317.8 | I43: =+' TR Associates'!M3 -> 706575.23 | J43: =+' TR Associates'!L35 -> 1306573 | K43: =H43+I43-J43 -> 497320.03
A44: 43 | B44: Ankaligi | C44: Shivaganga | D44: =+Ankalgi!E35 -> 3023.32 | E44: =+Ankalgi!G35 -> 276089.58 | F44: =+Ankalgi!H35 -> 50 | G44: =+Ankalgi!J35 -> 5162 | H44: =E44+G44 -> 281251.58 | I44: =+Ankalgi!M3 -> 185274.35 | J44: =+Ankalgi!L35 -> 370274 | K44: =H44+I44-J44 -> 96251.927
A45: 44 | B45: ShankeshWAR | C45: SR Patil | D45: =+' Shankeshwar'!E35 -> 510 | E45: =+' Shankeshwar'!G35 -> 46563 | F45: =+' Shankeshwar'!H35 -> 92 | G45: =+' Shankeshwar'!J35 -> 9496.29 | H45: =E45+G45 -> 56059.29 | I45: =' Shankeshwar'!M3 -> 0 | J45: =+' Shankeshwar'!L35 -> 56059.29 | K45: =H45+I45-J45 -> 0
A46: 45 | B46: Talikote(PKG-1) | C46: Raykar Oil Agencies | D46: =+' Talikote'!E46 -> 404.37 | E46: =+' Talikote'!G46 -> 37008.82 | F46: =+' Talikote'!H46 -> 74.65 | G46: =+' Talikote'!J46 -> 7721.796 | H46: =E46+G46 -> 44730.616 | I46: =+' Talikote'!N3 -> 2468.2481 | J46: =+' Talikote'!L46 -> 28730 | K46: =H46+I46-J46 -> 18468.864
A47: 46 | B47: Chadchan(PKG-1) | C47: Khavekar Petrolium | D47: =+Chadchan!E35 -> 1158.48 | E47: =+Chadchan!G35 -> 105688.13 | F47: =+Chadchan!H35 -> 136.27 | G47: =+Chadchan!J35 -> 14057.613 | H47: =E47+G47 -> 119745.74 | I47: =+Chadchan!K3 -> 57209.665 | J47: =+Chadchan!L35 -> 57247 | K47: =H47+I47-J47 -> 119708.41
A48: 47 | B48: Sindagi | C48: G.P.PORWAL | D48: =+Sindagi!E44 -> 318 | E48: =+Sindagi!G44 -> 29017.5 | F48: =+Sindagi!H44 -> 5 | G48: =+Sindagi!J44 -> 515.9 | H48: =E48+G48 -> 29533.4 | I48: =+Sindagi!M3 -> 15584.413 | J48: =+Sindagi!L44 -> 39500 | K48: =H48+I48-J48 -> 5617.8127
A49: 48 | B49: Muddebihal(PKG-1)2 | C49: PS NAGATHAN PETROLIUM | D49: =+'Muddebhihal-2'!E49 -> 1469.31 | E49: =+'Muddebhihal-2'!G49 -> 134324.32 | F49: =+'Muddebhihal-2'!H49 -> 33 | G49: =+'Muddebhihal-2'!J49 -> 3410.55 | H49: =+'Muddebhihal-2'!K49 -> 137734.87 | I49: =+'Muddebhihal-2'!M3 -> 59806.35 | J49: =+'Muddebhihal-2'!L49 -> 59770 | K49: =+'Muddebhihal-2'!M48 -> 137771.22
A50: 49 | B50: Almela(PKG-1) | C50: Shiddeshwar Petroleums | D50: =+Alemela!E43 -> 398.08 | E50: =+Alemela!G43 -> 36408.397 | F50: =+Alemela!H43 -> 52.63 | G50: =+Alemela!J43 -> 5441.942 | H50: =E50+G50 -> 41850.339 | I50: =+Alemela!M3 -> 1291.6359 | J50: =+Alemela!L43 -> 27291.636 | K50: =H50+I50-J50 -> 15850.339
A51: 50 | B51: Nalatwad(PKG-1) | C51: Shri Pawad Basaweshwar Petroleums | D51: =+Nalatwad!E43 -> 868.19 | E51: =+Nalatwad!G43 -> 79543.568 | F51: =+Nalatwad!H43 -> 32.99 | G51: =+Nalatwad!J43 -> 3546.3659 | H51: =E51+G51 -> 83089.934 | I51: =+Nalatwad!M3 -> 53172.942 | J51: =+Nalatwad!L43 -> 53172.942 | K51: =H51+I51-J51 -> 83089.934
A52: 51 | B52: Srirangapatna | C52: Anupama F/S | D52: =+Srirangapatna!E35 -> 0 | E52: =+Srirangapatna!G35 -> 0 | F52: =+Srirangapatna!H35 -> 19.89 | G52: =+Srirangapatna!J35 -> 2038.1283 | H52: =E52+G52 -> 2038.1283 | I52: 0 | J52: =+Srirangapatna!L35 -> 2038.1283 | K52: =H52+I52-J52 -> 0
A53: 52 | B53: HO(DG) | C53: JSASFuel Genie India Pvt.Ltd | D53: =+'HO(DG)'!E43 -> 1583.05 | E53: =+'HO(DG)'!G43 -> 151540.25 | F53: =+'HO(DG)'!H43 -> 0 | G53: =+'HO(DG)'!J43 -> 0 | H53: =E53+G53 -> 151540.25 | I53: =+'HO(DG)'!M3 -> 188521.22 | J53: =+'HO(DG)'!L43 -> 261027.72 | K53: =H53+I53-J53 -> 79033.75
A54: Total | D54: =SUM(D2:D53) -> 444376.23 | E54: =SUM(E2:E53) -> 41695224 | F54: =SUM(F2:F53) -> 5851.29 | G54: =SUM(G2:G53) -> 619157.77 | H54: =SUM(H2:H53) -> 42314382 | I54: =SUM(I2:I53) -> 36609318 | J54: =SUM(J2:J53) -> 59198691 | K54: =H54+I54-J54 -> 19725009 | L54: 19634343 | M54: =K54-L54 -> 90666.585
Q55: =2500*92 -> 230000
A59: S.no | B59: Site Name | C59: Bunk Name | D59: Diesel(Liters) | E59: Diesel Amount | F59: Petrol(Liters) | G59: Petrol Amount | H59: Total Amount | I59: Opening Blance | J59: Amount Paid | K59: Closing Balances
A60: 39 | B60: {=VLOOKUP(A60,A1:K52,{2,3,4,5,6,7,8,9,10,11},FALSE)} -> Rattihali-2 | C60: Shiva Oil Traders | D60: 3860.03 | E60: 354698.16 | F60: 109 | G60: 11319.65 | H60: 366017.81 | I60: 263742.1 | J60: 363742 | K60: 266017.9
B62: Site Name | C62: Bunk Name | D62: Diesel(Liters) | E62: Diesel Amount | F62: Petrol(Liters) | G62: Petrol Amount | H62: Total Amount | I62: Opening Blance | J62: Amount Paid | K62: Closing Balances
B63: Jalgaon-2 | C63: {=VLOOKUP(B63,B1:K52,{2,3,4,5,6,7,8,9,10},FALSE)} -> Nayara | D63: 64300.61 | E63: 6089910.8 | F63: 405 | G63: 44728.2 | H63: 6134639 | I63: 5471845 | J63: 8941028 | K63: 2665456
B70: 60000
B71: 18000
B72: 18000
B73: 75000
B74: 360000

Sheet HO(DG)
A1: JSASFuel Genie India Pvt.Ltd
A2: S.No | B2: Date | C2: GRN No | D2: Ind No/Bill No | E2: Diesel (Lts) | F2: Price | G2: Amount | H2: Petrol (Lts) | I2: Price | J2: Amount | K2: Total amount | L2: Amount paid | M2: As on date | N2: Remarks
A3: Opening Balance | M3: 188521.22 | O3: 2623243.4
A4: 1 | B4: 46113 | G4: =E4*F4 -> 0 | H4: 0 | I4: 0 | J4: =H4*I4 -> 0 | K4: =G4+J4 -> 0 | L4: 0 | M4: =M3+K4-L4 -> 188521.22
A5: 2 | B5: 46114 | G5: =E5*F5 -> 0 | H5: 0 | I5: 0 | J5: =H5*I5 -> 0 | K5: =G5+J5 -> 0 | L5: 0 | M5: =M4+K5-L5 -> 188521.22 | R5: HO | S5: 188521.22
A6: 3 | B6: 46115 | G6: =E6*F6 -> 0 | H6: 0 | I6: 0 | J6: =H6*I6 -> 0 | K6: 0 | L6: 188521.22 | M6: =M5+K6-L6 -> 0 | R6: Khammam | S6: 8227903
B7: 46115 | E7: 20.47 | F7: 95.64 | G7: =E7*F7 -> 1957.7508 | H7: 0 | I7: 0 | J7: =H7*I7 -> 0 | K7: =G7+J7 -> 1957.7508 | L7: =H7+K7 -> 1957.7508 | M7: =M6+K7-L7 -> 0 | R7: Jadcherla | S7: 2453209.4
A8: 4 | B8: 46115 | E8: 35 | F8: 95.64 | G8: =E8*F8 -> 3347.4 | H8: 0 | I8: 0 | J8: =H8*I8 -> 0 | K8: =G8+J8 -> 3347.4 | L8: =H8+K8 -> 3347.4 | M8: =M7+K8-L8 -> 0 | P8: 5679 | R8: Total | S8: =SUM(S5:S7) -> 10869634
A9: 5 | B9: 46116 | E9: 200 | F9: 95.83 | G9: =E9*F9 -> 19166 | H9: 0 | I9: 0 | J9: =H9*I9 -> 0 | K9: =G9+J9 -> 19166 | L9: 0 | M9: =M8+K9-L9 -> 19166 | S9: 10869632
B10: 46116 | E10: 36.59 | F10: 95.64 | G10: =E10*F10 -> 3499.4676 | K10: =G10+J10 -> 3499.4676 | L10: =H10+K10 -> 3499.4676 | M10: =M9+K10-L10 -> 19166 | S10: =S9-S8 -> -1.6105
A11: 6 | B11: 46118 | G11: =E11*F11 -> 0 | H11: 0 | I11: 0 | J11: =H11*I11 -> 0 | K11: =G11+J11 -> 0 | L11: 0 | M11: =M10+K11-L11 -> 19166
A12: 7 | B12: 46119 | G12: =E12*F12 -> 0 | H12: 0 | I12: 0 | J12: =H12*I12 -> 0 | K12: =G12+J12 -> 0 | L12: 0 | M12: =M11+K12-L12 -> 19166
A13: 8 | B13: 46120 | G13: =E13*F13 -> 0 | H13: 0 | I13: 0 | J13: =H13*I13 -> 0 | K13: =G13+J13 -> 0 | L13: 0 | M13: =M12+K13-L13 -> 19166
A14: 9 | B14: 46121 | E14: 205 | F14: 95.83 | G14: =E14*F14 -> 19645.15 | H14: 0 | I14: 0 | J14: =H14*I14 -> 0 | K14: =G14+J14 -> 19645.15 | L14: 0 | M14: =M13+K14-L14 -> 38811.15
A15: 10 | B15: 46122 | G15: =E15*F15 -> 0 | H15: 0 | I15: 0 | J15: =H15*I15 -> 0 | K15: =G15+J15 -> 0 | L15: 0 | M15: =M14+K15-L15 -> 38811.15 | R15: 19166
A16: 11 | B16: 46123 | G16: =E16*F16 -> 0 | H16: 0 | I16: 0 | J16: =H16*I16 -> 0 | K16: =G16+J16 -> 0 | L16: 0 | M16: =M15+K16-L16 -> 38811.15 | R16: 19645
A17: 12 | B17: 46124 | G17: =E17*F17 -> 0 | H17: 0 | I17: 0 | J17: =H17*I17 -> 0 | K17: =G17+J17 -> 0 | L17: 0 | M17: =M16+K17-L17 -> 38811.15 | P17: 1905988 | Q17: =P17-M17 -> 1867176.9 | R17: 21083
A18: 13 | B18: 46125 | G18: =E18*F18 -> 0 | H18: 0 | I18: 0 | J18: =H18*I18 -> 0 | K18: =G18+J18 -> 0 | L18: 0 | M18: =M17+K18-L18 -> 38811.15 | R18: 19140 | S18: 220637
A19: 14 | B19: 46126 | E19: 70 | F19: 95.64 | G19: =E19*F19 -> 6694.8 | H19: 0 | I19: 0 | J19: =H19*I19 -> 0 | K19: =G19+J19 -> 6694.8 | L19: =H19+K19 -> 6694.8 | M19: =M18+K19-L19 -> 38811.15 | N19: HPCL | R19: =SUM(R15:R18) -> 79034 | S19: =S18+R19 -> 299671
A20: 15 | B20: 46127 | E20: 35 | F20: 95.64 | G20: =E20*F20 -> 3347.4 | H20: 0 | I20: 0 | J20: =H20*I20 -> 0 | K20: =G20+J20 -> 3347.4 | L20: =H20+K20 -> 3347.4 | M20: =M19+K20-L20 -> 38811.15 | N20: HPCL
A21: 16 | B21: 46128 | E21: 35 | F21: 95.64 | G21: =E21*F21 -> 3347.4 | H21: 0 | I21: 0 | J21: =H21*I21 -> 0 | K21: =G21+J21 -> 3347.4 | L21: =H21+K21 -> 3347.4 | M21: =M20+K21-L21 -> 38811.15
A22: 16 | B22: 46128 | E22: 220 | F22: 95.83 | G22: =E22*F22 -> 21082.6 | H22: 0 | I22: 0 | J22: =H22*I22 -> 0 | K22: =G22+J22 -> 21082.6 | L22: 0 | M22: =M21+K22-L22 -> 59893.75
A23: 17 | B23: 46129 | G23: =E23*F23 -> 0 | H23: 0 | I23: 0 | J23: =H23*I23 -> 0 | K23: =G23+J23 -> 0 | L23: 0 | M23: =M22+K23-L23 -> 59893.75
A24: 18 | B24: 46130 | G24: =E24*F24 -> 0 | H24: 0 | I24: 0 | J24: =H24*I24 -> 0 | K24: =G24+J24 -> 0 | L24: 0 | M24: =M23+K24-L24 -> 59893.75
A25: 19 | B25: 46131 | G25: =E25*F25 -> 0 | H25: 0 | I25: 0 | J25: =H25*I25 -> 0 | K25: =G25+J25 -> 0 | L25: 0 | M25: =M24+K25-L25 -> 59893.75
A26: 20 | B26: 46132 | G26: =E26*F26 -> 0 | H26: 0 | I26: 0 | J26: =H26*I26 -> 0 | K26: =G26+J26 -> 0 | L26: 0 | M26: =M25+K26-L26 -> 59893.75
A27: 21 | B27: 46133 | E27: 59.08 | F27: 95.64 | G27: =E27*F27 -> 5650.4112 | H27: 0 | I27: 0 | J27: =H27*I27 -> 0 | K27: =G27+J27 -> 5650.4112 | L27: =H27+K27 -> 5650.4112 | M27: =M26+K27-L27 -> 59893.75
A28: 22 | B28: 46134 | E28: 77.73 | F28: 95.64 | G28: =E28*F28 -> 7434.0972 | H28: 0 | I28: 0 | J28: =H28*I28 -> 0 | K28: =G28+J28 -> 7434.0972 | L28: =H28+K28 -> 7434.0972 | M28: =M27+K28-L28 -> 59893.75
A29: 23 | B29: 46135 | E29: 200 | F29: 95.7 | G29: =E29*F29 -> 19140 | H29: 0 | I29: 0 | J29: =H29*I29 -> 0 | K29: =G29+J29 -> 19140 | L29: 0 | M29: =M28+K29-L29 -> 79033.75
A30: 24 | B30: 46136 | G30: =E30*F30 -> 0 | H30: 0 | I30: 0 | J30: =H30*I30 -> 0 | K30: =G30+J30 -> 0 | L30: 0 | M30: =M29+K30-L30 -> 79033.75
B31: 46137 | G31: =E31*F31 -> 0 | H31: 0 | I31: 0 | J31: =H31*I31 -> 0 | K31: =G31+J31 -> 0 | L31: 0 | M31: =M30+K31-L31 -> 79033.75
A32: 25 | B32: 46138 | G32: =E32*F32 -> 0 | H32: 0 | I32: 0 | J32: =H32*I32 -> 0 | K32: =G32+J32 -> 0 | L32: 0 | M32: =M31+K32-L32 -> 79033.75
A33: 26 | B33: 46139 | D33: Ganga Fuel F/S | E33: 114.18 | F33: 95.64 | G33: =E33*F33 -> 10920.175 | H33: 0 | I33: 0 | J33: =H33*I33 -> 0 | K33: =G33+J33 -> 10920.175 | L33: =H33+K33 -> 10920.175 | M33: =M32+K33-L33 -> 79033.75
B34: 46139 | D34: COCO Hitech City IOCL | E34: 110 | F34: 95.7 | G34: =E34*F34 -> 10527 | K34: =G34+J34 -> 10527 | L34: =H34+K34 -> 10527 | M34: =M33+K34-L34 -> 79033.75
A35: 27 | B35: 46140 | G35: =E35*F35 -> 0 | H35: 0 | I35: 0 | J35: =H35*I35 -> 0 | K35: =G35+J35 -> 0 | L35: 0 | M35: =M33+K35-L35 -> 79033.75
A36: 28 | B36: 46141 | G36: =E36*F36 -> 0 | H36: 0 | I36: 0 | J36: =H36*I36 -> 0 | K36: =G36+J36 -> 0 | L36: 0 | M36: =M35+K36-L36 -> 79033.75
A37: 29 | B37: 46142 | D37: Venkatadri Fueles | E37: 165 | F37: 95.64 | G37: =E37*F37 -> 15780.6 | H37: 0 | I37: 0 | J37: =H37*I37 -> 0 | K37: =G37+J37 -> 15780.6 | L37: =H37+K37 -> 15780.6 | M37: =M36+K37-L37 -> 79033.75
A38: 30 | E38: 0 | G38: =E38*F38 -> 0 | H38: 0 | I38: 0 | J38: =H38*I38 -> 0 | K38: =G38+J38 -> 0 | L38: 0 | M38: =M37+K38-L38 -> 79033.75
A39: 31 | G39: =E39*F39 -> 0 | H39: 0 | I39: 0 | J39: =H39*I39 -> 0 | K39: =G39+J39 -> 0 | L39: 0 | M39: =M38+K39-L39 -> 79033.75
A40: 32 | G40: =E40*F40 -> 0 | J40: =H40*I40 -> 0 | K40: =G40+J40 -> 0 | M40: =M39+K40-L40 -> 79033.75
A41: 33 | G41: =E41*F41 -> 0 | J41: =H41*I41 -> 0 | K41: =G41+J41 -> 0 | L41: 0 | M41: =M40+K41-L41 -> 79033.75 | O41: 2669494 | P41: =O41-M41 -> 2590460.2
E42: 0 | F42: 0 | G42: =E42*F42 -> 0 | J42: =H42*I42 -> 0 | K42: =G42+J42 -> 0 | M42: =M41+K42-L42 -> 79033.75
E43: =SUM(E4:E41) -> 1583.05 | G43: =SUM(G4:G41) -> 151540.25 | H43: =SUM(H4:H41) -> 0 | J43: =SUM(J4:J41) -> 0 | K43: =SUM(K4:K41) -> 151540.25 | L43: =SUM(L4:L41) -> 261027.72
M52: 2408309
M53: 5327.86
M54: =M52-M53 -> 2402981.1

Sheet Khammam-1
A1: Divya laxmi ganapathi
A2: S.No | B2: Date | C2: GRN No | D2: Ind No/Bill No | E2: Diesel (Lts) | F2: Price | G2: Amount | H2: Petrol (Lts) | I2: Price | J2: Amount | K2: Total amount | L2: Amount paid | M2: As 0n Date | N2: Remarks
A3: Opening Balance | K3: 4176411.7 | M3: 4176411.7
A4: 1 | B4: 46113 | G4: =E4*F4 -> 0 | K4: =G4+J4 -> 0 | L4: 0 | M4: =M3+K4-L4 -> 4176411.7
A5: 2 | B5: 46114 | G5: =E5*F5 -> 0 | K5: =G5+J5 -> 0 | L5: 4176407 | M5: =M4+K5-L5 -> 4.6869
A6: 3 | B6: 46115 | E6: 2700.49 | F6: 95.68 | G6: =E6*F6 -> 258382.88 | H6: 55 | I6: 107.46 | J6: =H6*I6 -> 5910.3 | K6: =G6+J6 -> 264293.18 | L6: 0 | M6: =M5+K6-L6 -> 264297.87
A7: 4 | B7: 46116 | G7: =E7*F7 -> 0 | J7: =H7*I7 -> 0 | K7: =G7+J7 -> 0 | L7: 0 | M7: =M6+K7-L7 -> 264297.87
A8: 5 | B8: 46117 | E8: 2700 | F8: 95.68 | G8: =E8*F8 -> 258336 | H8: 60 | I8: 107.46 | J8: =H8*I8 -> 6447.6 | K8: =G8+J8 -> 264783.6 | L8: 0 | M8: =M7+K8-L8 -> 529081.47
A9: 6 | B9: 46118 | G9: =E9*F9 -> 0 | J9: =H9*I9 -> 0 | K9: =G9+J9 -> 0 | L9: 0 | M9: =M8+K9-L9 -> 529081.47
A10: 7 | B10: 46119 | E10: 2700 | F10: 95.68 | G10: =E10*F10 -> 258336 | H10: 60 | I10: 107.46 | J10: =H10*I10 -> 6447.6 | K10: =G10+J10 -> 264783.6 | L10: 0 | M10: =M9+K10-L10 -> 793865.07
A11: 8 | B11: 46120 | G11: =E11*F11 -> 0 | J11: =H11*I11 -> 0 | K11: =G11+J11 -> 0 | L11: 0 | M11: =M10+K11-L11 -> 793865.07
A12: 9 | B12: 46121 | G12: =E12*F12 -> 0 | J12: =H12*I12 -> 0 | K12: =G12+J12 -> 0 | L12: 0 | M12: =M11+K12-L12 -> 793865.07
A13: 10 | B13: 46122 | E13: 2500 | F13: 95.68 | G13: =E13*F13 -> 239200 | H13: 95 | I13: 107.46 | J13: =H13*I13 -> 10208.7 | K13: =G13+J13 -> 249408.7 | L13: 0 | M13: =M12+K13-L13 -> 1043273.8
A14: 11 | B14: 46123 | G14: =E14*F14 -> 0 | J14: =H14*I14 -> 0 | K14: =G14+J14 -> 0 | L14: 0 | M14: =M13+K14-L14 -> 1043273.8
A15: 12 | B15: 46124 | G15: =E15*F15 -> 0 | J15: =H15*I15 -> 0 | K15: =G15+J15 -> 0 | L15: 0 | M15: =M14+K15-L15 -> 1043273.8
A16: 13 | B16: 46125 | E16: 2500 | F16: 95.68 | G16: =E16*F16 -> 239200 | H16: 60 | I16: 107.46 | J16: =H16*I16 -> 6447.6 | K16: =G16+J16 -> 245647.6 | L16: 0 | M16: =M15+K16-L16 -> 1288921.4
A17: 14 | B17: 46126 | E17: 1500 | F17: 95.68 | G17: =E17*F17 -> 143520 | H17: 21.49 | I17: 107.46 | J17: =H17*I17 -> 2309.3154 | K17: =G17+J17 -> 145829.32 | L17: 0 | M17: =M16+K17-L17 -> 1434750.7
A18: 15 | B18: 46127 | G18: =E18*F18 -> 0 | K18: =G18+J18 -> 0 | L18: 0 | M18: =M17+K18-L18 -> 1434750.7
A19: 16 | B19: 46128 | G19: =E19*F19 -> 0 | K19: =G19+J19 -> 0 | L19: 0 | M19: =M18+K19-L19 -> 1434750.7
A20: 17 | B20: 46129 | G20: =E20*F20 -> 0 | K20: =G20+J20 -> 0 | L20: 0 | M20: =M19+K20-L20 -> 1434750.7
A21: 18 | B21: 46130 | G21: =E21*F21 -> 0 | K21: =G21+J21 -> 0 | L21: 0 | M21: =M20+K21-L21 -> 1434750.7
A22: 19 | B22: 46131 | G22: =E22*F22 -> 0 | K22: =G22+J22 -> 0 | L22: 0 | M22: =M21+K22-L22 -> 1434750.7
A23: 20 | B23: 46132 | G23: =E23*F23 -> 0 | K23: =G23+J23 -> 0 | L23: 0 | M23: =M22+K23-L23 -> 1434750.7
A24: 21 | B24: 46133 | E24: 2000 | F24: 95.68 | G24: =E24*F24 -> 191360 | K24: =G24+J24 -> 191360 | L24: 0 | M24: =M23+K24-L24 -> 1626110.7
A25: 22 | B25: 46134 | E25: 1500 | F25: 95.68 | G25: =E25*F25 -> 143520 | K25: =G25+J25 -> 143520 | L25: 0 | M25: =M24+K25-L25 -> 1769630.7
A26: 23 | B26: 46135 | G26: =E26*F26 -> 0 | K26: =G26+J26 -> 0 | L26: 0 | M26: =M25+K26-L26 -> 1769630.7
A27: 24 | B27: 46136 | G27: =E27*F27 -> 0 | K27: =G27+J27 -> 0 | L27: 0 | M27: =M26+K27-L27 -> 1769630.7
A28: 25 | B28: 46137 | G28: =E28*F28 -> 0 | K28: =G28+J28 -> 0 | L28: 0 | M28: =M27+K28-L28 -> 1769630.7
A29: 26 | B29: 46138 | G29: =E29*F29 -> 0 | K29: =G29+J29 -> 0 | L29: 0 | M29: =M28+K29-L29 -> 1769630.7
A30: 27 | B30: 46139 | E30: 2000 | F30: 95.68 | G30: =E30*F30 -> 191360 | K30: =G30+J30 -> 191360 | L30: 267904 | M30: =M29+K30-L30 -> 1693086.7
A31: 28 | B31: 46140 | E31: 2000 | F31: 95.68 | G31: =E31*F31 -> 191360 | K31: =G31+J31 -> 191360 | L31: 114816 | M31: =M30+K31-L31 -> 1769630.7
A32: 29 | B32: 46141 | E32: 2000 | F32: 95.68 | G32: =E32*F32 -> 191360 | K32: =G32+J32 -> 191360 | L32: =H32+K32 -> 191360 | M32: =M31+K32-L32 -> 1769630.7
A33: 30 | B33: 46142 | E33: 2500 | F33: 95.68 | G33: =E33*F33 -> 239200 | K33: =G33+J33 -> 239200 | L33: =H33+K33 -> 239200 | M33: =M32+K33-L33 -> 1769630.7
A34: 31 | G34: =E34*F34 -> 0 | K34: =G34+J34 -> 0 | L34: 0 | M34: =M33+K34-L34 -> 1769630.7
A35: 32 | G35: =E35*F35 -> 0 | J35: =H35*I35 -> 0 | K35: =G35+J35 -> 0 | L35: 0 | M35: =M34+K35-L35 -> 1769630.7
A36: 33 | G36: =E36*F36 -> 0 | J36: =H36*I36 -> 0 | K36: =G36+J36 -> 0 | L36: 0
A37: 34 | G37: =E37*F37 -> 0 | J37: =H37*I37 -> 0 | K37: =G37+J37 -> 0
E38: =SUM(E3:E37) -> 26600.49 | G38: =SUM(G3:G37) -> 2545134.9 | H38: =SUM(H3:H37) -> 351.49 | J38: =SUM(J3:J37) -> 37771.115 | K38: =SUM(K4:K37) -> 2582906 | L38: =SUM(L3:L37) -> 4989687

Sheet Khammam-2
A1: Jayasai union bunk
A2: S.No | B2: Date | C2: GRN No | D2: Ind No/Bill No | E2: Diesel (Lts) | F2: Price | G2: Amount | H2: Petrol (Lts) | I2: Price | J2: Amount | K2: Total amount | L2: Amount paid | M2: As 0n Date | N2: Remarks
A3: Opening Balance | K3: 8032637.3 | M3: 8032637.3
A4: 1 | B4: 46113 | G4: =E4*F4 -> 0 | J4: =H4*I4 -> 0 | K4: =G4+J4 -> 0 | M4: =M3+K4-L4 -> 8032637.3 | O4: =O3+M4-N4 -> 8032637.3
A5: 2 | B5: 46114 | E5: 2800 | F5: 95.71 | G5: =E5*F5 -> 267988 | H5: 80 | I5: 107.49 | J5: =H5*I5 -> 8599.2 | K5: =G5+J5 -> 276587.2 | L5: 8032614 | M5: =M4+K5-L5 -> 276610.5
A6: 3 | B6: 46115 | E6: 2800 | F6: 95.71 | G6: =E6*F6 -> 267988 | H6: 20 | I6: 107.49 | J6: =H6*I6 -> 2149.8 | K6: =G6+J6 -> 270137.8 | M6: =M5+K6-L6 -> 546748.3
A7: 4 | B7: 46116 | G7: =E7*F7 -> 0 | J7: =H7*I7 -> 0 | K7: =G7+J7 -> 0 | M7: =M6+K7-L7 -> 546748.3
A8: 5 | B8: 46117 | G8: =E8*F8 -> 0 | J8: =H8*I8 -> 0 | K8: =G8+J8 -> 0 | M8: =M7+K8-L8 -> 546748.3 | O8: 12802499
A9: 6 | B9: 46118 | G9: =E9*F9 -> 0 | J9: =H9*I9 -> 0 | K9: =G9+J9 -> 0 | M9: =M8+K9-L9 -> 546748.3
A10: 7 | B10: 46119 | G10: =E10*F10 -> 0 | J10: =H10*I10 -> 0 | K10: =G10+J10 -> 0 | M10: =M9+K10-L10 -> 546748.3
A11: 8 | B11: 46120 | G11: =E11*F11 -> 0 | J11: =H11*I11 -> 0 | K11: =G11+J11 -> 0 | M11: =M10+K11-L11 -> 546748.3
A12: 9 | B12: 46121 | G12: =E12*F12 -> 0 | J12: =H12*I12 -> 0 | K12: =G12+J12 -> 0 | M12: =M11+K12-L12 -> 546748.3
A13: 10 | B13: 46122 | G13: =E13*F13 -> 0 | J13: =H13*I13 -> 0 | K13: =G13+J13 -> 0 | M13: =M12+K13-L13 -> 546748.3
A14: 11 | B14: 46123 | E14: 4550 | F14: 95.71 | G14: =E14*F14 -> 435480.5 | H14: 40 | I14: 107.49 | J14: =H14*I14 -> 4299.6 | K14: =G14+J14 -> 439780.1 | M14: =M13+K14-L14 -> 986528.4
A15: 12 | B15: 46124 | G15: =E15*F15 -> 0 | J15: =H15*I15 -> 0 | K15: =G15+J15 -> 0 | M15: =M14+K15-L15 -> 986528.4
A16: 13 | B16: 46125 | G16: =E16*F16 -> 0 | J16: =H16*I16 -> 0 | K16: =G16+J16 -> 0 | M16: =M15+K16-L16 -> 986528.4
A17: 14 | B17: 46126 | E17: 2500 | F17: 95.71 | G17: =E17*F17 -> 239275 | H17: 20 | I17: 107.49 | J17: =H17*I17 -> 2149.8 | K17: =G17+J17 -> 241424.8 | M17: =M16+K17-L17 -> 1227953.2
A18: 15 | B18: 46127 | E18: 5500 | F18: 95.71 | G18: =E18*F18 -> 526405 | H18: 40 | I18: 107.49 | J18: =H18*I18 -> 4299.6 | K18: =G18+J18 -> 530704.6 | M18: =M17+K18-L18 -> 1758657.8
A19: 16 | B19: 46128 | E19: 1800 | F19: 95.71 | G19: =E19*F19 -> 172278 | H19: 40 | I19: 107.49 | J19: =H19*I19 -> 4299.6 | K19: =G19+J19 -> 176577.6 | M19: =M18+K19-L19 -> 1935235.4
A20: 17 | B20: 46129 | E20: 5600 | F20: 95.71 | G20: =E20*F20 -> 535976 | H20: 40 | I20: 107.49 | J20: =H20*I20 -> 4299.6 | K20: =G20+J20 -> 540275.6 | M20: =M19+K20-L20 -> 2475511
A21: 18 | B21: 46130 | E21: 2800 | F21: 95.71 | G21: =E21*F21 -> 267988 | I21: 107.49 | J21: =H21*I21 -> 0 | K21: =G21+J21 -> 267988 | M21: =M20+K21-L21 -> 2743499
A22: 19 | B22: 46131 | E22: 3900 | F22: 95.71 | G22: =E22*F22 -> 373269 | H22: 60 | I22: 107.49 | J22: =H22*I22 -> 6449.4 | K22: =G22+J22 -> 379718.4 | M22: =M21+K22-L22 -> 3123217.4
A23: 20 | B23: 46132 | E23: 4000 | F23: 95.71 | G23: =E23*F23 -> 382840 | H23: 20 | I23: 107.49 | J23: =H23*I23 -> 2149.8 | K23: =G23+J23 -> 384989.8 | M23: =M22+K23-L23 -> 3508207.2
A24: 21 | B24: 46133 | G24: =E24*F24 -> 0 | H24: 95 | I24: 107.49 | J24: =H24*I24 -> 10211.55 | K24: =G24+J24 -> 10211.55 | M24: =M23+K24-L24 -> 3518418.7
A25: 22 | B25: 46134 | G25: =E25*F25 -> 0 | J25: =H25*I25 -> 0 | K25: =G25+J25 -> 0 | M25: =M24+K25-L25 -> 3518418.7
A26: 23 | B26: 46135 | G26: =E26*F26 -> 0 | J26: =H26*I26 -> 0 | K26: =G26+J26 -> 0 | M26: =M25+K26-L26 -> 3518418.7
A27: 24 | B27: 46136 | E27: 525 | F27: 95.71 | G27: =E27*F27 -> 50247.75 | J27: =H27*I27 -> 0 | K27: =G27+J27 -> 50247.75 | L27: =H27+K27 -> 50247.75 | M27: =M26+K27-L27 -> 3518418.7
A28: 25 | B28: 46137 | E28: 731.37 | F28: 95.71 | G28: =E28*F28 -> 69999.423 | H28: 106 | I28: 107.49 | J28: =H28*I28 -> 11393.94 | K28: =G28+J28 -> 81393.363 | L28: 70000 | M28: =M27+K28-L28 -> 3529812.1
A29: 26 | B29: 46138 | G29: =E29*F29 -> 0 | J29: =H29*I29 -> 0 | K29: =G29+J29 -> 0 | M29: =M28+K29-L29 -> 3529812.1
A30: 27 | B30: 46139 | E30: 309.38 | F30: 95.71 | G30: =E30*F30 -> 29610.76 | J30: =H30*I30 -> 0 | K30: =G30+J30 -> 29610.76 | M30: =M29+K30-L30 -> 3559422.9
A31: 28 | B31: 46140 | E31: 200 | F31: 95.71 | G31: =E31*F31 -> 19142 | J31: =H31*I31 -> 0 | K31: =G31+J31 -> 19142 | M31: =M30+K31-L31 -> 3578564.9
A32: 29 | B32: 46141 | E32: 1536.81 | F32: 95.71 | G32: =E32*F32 -> 147088.09 | J32: =H32*I32 -> 0 | K32: =G32+J32 -> 147088.09 | M32: =M31+K32-L32 -> 3725653
A33: 30 | B33: 46142 | G33: =E33*F33 -> 0 | J33: =H33*I33 -> 0 | K33: =G33+J33 -> 0 | M33: =M32+K33-L33 -> 3725653
A34: 31 | G34: =E34*F34 -> 0 | J34: =H34*I34 -> 0 | K34: =G34+J34 -> 0 | M34: =M33+K34-L34 -> 3725653
E35: =SUM(E4:E34) -> 39552.56 | G35: =SUM(G4:G34) -> 3785575.5 | H35: =SUM(H4:H34) -> 561 | J35: =SUM(J4:J34) -> 60301.89 | K35: =SUM(K4:K34) -> 3845877.4 | L35: =SUM(L4:L34) -> 8152861.8

Sheet Khammam-3
A1: JSASFuel Genie India Pvt.Ltd
A2: S.No | B2: Date | C2: GRN No | D2: Ind No/Bill No | E2: Diesel (Lts) | F2: Price | G2: Amount | H2: Petrol (Lts) | I2: Price | J2: Amount | K2: Total amount | L2: Amount paid | M2: As 0n Date | N2: Remarks
A3: Opening Balance | K3: 8227903.3 | M3: 8227903.3
A4: 1 | B4: 46113 | E4: 6000 | F4: 95.2 | G4: =E4*F4 -> 571200 | J4: =H4*I4 -> 0 | K4: =G4+J4 -> 571200 | M4: =M3+K4-L4 -> 8799103.3
A5: 2 | B5: 46114 | G5: =E5*F5 -> 0 | J5: =H5*I5 -> 0 | K5: =G5+J5 -> 0 | M5: =M4+K5-L5 -> 8799103.3
A6: 3 | B6: 46115 | G6: =E6*F6 -> 0 | J6: =H6*I6 -> 0 | K6: =G6+J6 -> 0 | L6: 8227903 | M6: =M5+K6-L6 -> 571200.27
A7: 4 | B7: 46116 | E7: 6000 | F7: 95.2 | G7: =E7*F7 -> 571200 | J7: =H7*I7 -> 0 | K7: =G7+J7 -> 571200 | M7: =M6+K7-L7 -> 1142400.3
A8: 5 | B8: 46117 | G8: =E8*F8 -> 0 | J8: =H8*I8 -> 0 | K8: =G8+J8 -> 0 | M8: =M7+K8-L8 -> 1142400.3 | P8: 8227903
A9: 6 | B9: 46118 | E9: 6000 | F9: 95.2 | G9: =E9*F9 -> 571200 | J9: =H9*I9 -> 0 | K9: =G9+J9 -> 571200 | M9: =M8+K9-L9 -> 1713600.3 | P9: 188521.22
A10: 7 | B10: 46119 | E10: 6000 | F10: 95.2 | G10: =E10*F10 -> 571200 | J10: =H10*I10 -> 0 | K10: =G10+J10 -> 571200 | M10: =M9+K10-L10 -> 2284800.3 | P10: 2453209.4
A11: 8 | B11: 46120 | E11: 6000 | F11: 95.2 | G11: =E11*F11 -> 571200 | J11: =H11*I11 -> 0 | K11: =G11+J11 -> 571200 | M11: =M10+K11-L11 -> 2856000.3 | P11: =SUM(P8:P10) -> 10869634
A12: 9 | B12: 46121 | E12: 6000 | F12: 95.2 | G12: =E12*F12 -> 571200 | J12: =H12*I12 -> 0 | K12: =G12+J12 -> 571200 | M12: =M11+K12-L12 -> 3427200.3
A13: 10 | B13: 46122 | G13: =E13*F13 -> 0 | J13: =H13*I13 -> 0 | K13: =G13+J13 -> 0 | M13: =M12+K13-L13 -> 3427200.3
A14: 11 | B14: 46123 | G14: =E14*F14 -> 0 | J14: =H14*I14 -> 0 | K14: =G14+J14 -> 0 | L14: 2000000 | M14: =M13+K14-L14 -> 1427200.3
A15: 12 | B15: 46124 | E15: 6000 | F15: 95.2 | G15: =E15*F15 -> 571200 | J15: =H15*I15 -> 0 | K15: =G15+J15 -> 571200 | M15: =M14+K15-L15 -> 1998400.3
A16: 13 | B16: 46125 | G16: =E16*F16 -> 0 | J16: =H16*I16 -> 0 | K16: =G16+J16 -> 0 | M16: =M15+K16-L16 -> 1998400.3
A17: 14 | B17: 46126 | G17: =E17*F17 -> 0 | J17: =H17*I17 -> 0 | K17: =G17+J17 -> 0 | M17: =M16+K17-L17 -> 1998400.3
A18: 15 | B18: 46127 | G18: =E18*F18 -> 0 | J18: =H18*I18 -> 0 | K18: =G18+J18 -> 0 | M18: =M17+K18-L18 -> 1998400.3
A19: 16 | B19: 46128 | E19: 6000 | F19: 95.7 | G19: =E19*F19 -> 574200 | J19: =H19*I19 -> 0 | K19: =G19+J19 -> 574200 | M19: =M18+K19-L19 -> 2572600.3
A20: 17 | B20: 46129 | G20: =E20*F20 -> 0 | J20: =H20*I20 -> 0 | K20: =G20+J20 -> 0 | M20: =M19+K20-L20 -> 2572600.3
A21: 18 | B21: 46130 | G21: =E21*F21 -> 0 | J21: =H21*I21 -> 0 | K21: =G21+J21 -> 0 | M21: =M20+K21-L21 -> 2572600.3
A22: 19 | B22: 46131 | G22: =E22*F22 -> 0 | J22: =H22*I22 -> 0 | K22: =G22+J22 -> 0 | M22: =M21+K22-L22 -> 2572600.3
A23: 20 | B23: 46132 | G23: =E23*F23 -> 0 | J23: =H23*I23 -> 0 | K23: =G23+J23 -> 0 | M23: =M22+K23-L23 -> 2572600.3
A24: 21 | B24: 46133 | G24: =E24*F24 -> 0 | J24: =H24*I24 -> 0 | K24: =G24+J24 -> 0 | M24: =M23+K24-L24 -> 2572600.3
A25: 22 | B25: 46134 | G25: =E25*F25 -> 0 | J25: =H25*I25 -> 0 | K25: =G25+J25 -> 0 | M25: =M24+K25-L25 -> 2572600.3
A26: 23 | B26: 46135 | G26: =E26*F26 -> 0 | J26: =H26*I26 -> 0 | K26: =G26+J26 -> 0 | M26: =M25+K26-L26 -> 2572600.3
A27: 24 | B27: 46136 | G27: =E27*F27 -> 0 | J27: =H27*I27 -> 0 | K27: =G27+J27 -> 0 | M27: =M26+K27-L27 -> 2572600.3
A28: 25 | B28: 46137 | G28: =E28*F28 -> 0 | J28: =H28*I28 -> 0 | K28: =G28+J28 -> 0 | M28: =M27+K28-L28 -> 2572600.3
A29: 26 | B29: 46138 | G29: =E29*F29 -> 0 | J29: =H29*I29 -> 0 | K29: =G29+J29 -> 0 | M29: =M28+K29-L29 -> 2572600.3
A30: 27 | B30: 46139 | G30: =E30*F30 -> 0 | J30: =H30*I30 -> 0 | K30: =G30+J30 -> 0 | M30: =M29+K30-L30 -> 2572600.3
A31: 28 | B31: 46140 | G31: =E31*F31 -> 0 | J31: =H31*I31 -> 0 | K31: =G31+J31 -> 0 | M31: =M30+K31-L31 -> 2572600.3
... A33: 30 | B33: 46142 | G33: =E33*F33 -> 0 | J33: =H33*I33 -> 0 | K33: =G33+J33 -> 0 | M33: =M32+K33-L33 -> 2572600.3
A34: 31 | G34: =E34*F34 -> 0 | J34: =H34*I34 -> 0 | K34: =G34+J34 -> 0 | M34: =M33+K34-L34 -> 2572600.3
E35: =SUM(E4:E34) -> 48000 | G35: =SUM(G4:G34) -> 4572600 | H35: =SUM(H4:H34) -> 0 | J35: =SUM(J4:J34) -> 0 | K35: =SUM(K4:K34) -> 4572600 | L35: =SUM(L4:L34) -> 10227903

Sheet Khammam-4
A1: Vajra Mahalakshmi filling station
A2: S.No | B2: Date | C2: GRN No | D2: Ind No/Bill No | E2: Diesel (Lts) | F2: Price | G2: Amount | H2: Petrol (Lts) | I2: Price | J2: Amount | K2: Total amount | L2: Amount paid | M2: As 0n Date | N2: Remarks
A3: Opening Balance | K3: 330407.08 | M3: 330407.08
A4: 1 | B4: 46113 | G4: =E4*F4 -> 0 | K4: =G4+J4 -> 0 | L4: 0 | M4: =M3+K4-L4 -> 330407.08
A5: 2 | B5: 46114 | E5: 0 | F5: 0 | G5: =E5*F5 -> 0 | H5: 0 | I5: 0 | J5: =H5*I5 -> 0 | K5: =G5+J5 -> 0 | L5: 0 | M5: =M4+K5-L5 -> 330407.08
A6: 3 | B6: 46115 | E6: 0 | F6: 0 | G6: =E6*F6 -> 0 | H6: 0 | I6: 0 | J6: =H6*I6 -> 0 | K6: =G6+J6 -> 0 | L6: 330407 | M6: =M5+K6-L6 -> 0.08
A7: 4 | B7: 46116 | E7: 0 | F7: 0 | G7: =E7*F7 -> 0 | H7: 0 | I7: 0 | J7: =H7*I7 -> 0 | K7: =G7+J7 -> 0 | L7: 0 | M7: =M6+K7-L7 -> 0.08
A8: 5 | B8: 46117 | E8: 0 | F8: 0 | G8: =E8*F8 -> 0 | H8: 0 | I8: 0 | J8: =H8*I8 -> 0 | K8: =G8+J8 -> 0 | L8: 0 | M8: =M7+K8-L8 -> 0.08
A9: 6 | B9: 46118 | E9: 0 | F9: 0 | G9: =E9*F9 -> 0 | H9: 0 | I9: 0 | J9: =H9*I9 -> 0 | K9: =G9+J9 -> 0 | L9: 0 | M9: =M8+K9-L9 -> 0.08
A10: 7 | B10: 46119 | E10: 0 | F10: 0 | G10: =E10*F10 -> 0 | H10: 0 | I10: 0 | J10: =H10*I10 -> 0 | K10: =G10+J10 -> 0 | L10: 0 | M10: =M9+K10-L10 -> 0.08
A11: 8 | B11: 46120 | E11: 0 | F11: 0 | G11: =E11*F11 -> 0 | H11: 0 | I11: 0 | J11: =H11*I11 -> 0 | K11: =G11+J11 -> 0 | L11: 0 | M11: =M10+K11-L11 -> 0.08
A12: 9 | B12: 46121 | E12: 0 | F12: 0 | G12: =E12*F12 -> 0 | H12: 0 | I12: 0 | J12: =H12*I12 -> 0 | K12: =G12+J12 -> 0 | L12: 0 | M12: =M11+K12-L12 -> 0.08
A13: 10 | B13: 46122 | E13: 0 | F13: 0 | G13: =E13*F13 -> 0 | H13: 0 | I13: 0 | J13: =H13*I13 -> 0 | K13: =G13+J13 -> 0 | L13: 0 | M13: =M12+K13-L13 -> 0.08
A14: 11 | B14: 46123 | E14: 0 | F14: 0 | G14: =E14*F14 -> 0 | H14: 0 | I14: 0 | J14: =H14*I14 -> 0 | K14: =G14+J14 -> 0 | L14: 0 | M14: =M13+K14-L14 -> 0.08
A15: 12 | B15: 46124 | E15: 0 | F15: 0 | G15: =E15*F15 -> 0 | H15: 0 | I15: 0 | J15: =H15*I15 -> 0 | K15: =G15+J15 -> 0 | L15: 0 | M15: =M14+K15-L15 -> 0.08
A16: 13 | B16: 46125 | E16: 0 | F16: 0 | G16: =E16*F16 -> 0 | H16: 0 | I16: 0 | J16: =H16*I16 -> 0 | K16: =G16+J16 -> 0 | L16: 0 | M16: =M15+K16-L16 -> 0.08
... A19: 16 | B19: 46128 | E19: 0 | F19: 0 | G19: =E19*F19 -> 0 | H19: 0 | I19: 0 | J19: =H19*I19 -> 0 | K19: =G19+J19 -> 0 | L19: 0 | M19: =M18+K19-L19 -> 0.08
A20: 17 | B20: 46129 | G20: =E20*F20 -> 0 | J20: =H20*I20 -> 0 | K20: =G20+J20 -> 0 | L20: 0 | M20: =M19+K20-L20 -> 0.08
A21: 18 | B21: 46130 | G21: =E21*F21 -> 0 | J21: =H21*I21 -> 0 | K21: =G21+J21 -> 0 | L21: 0 | M21: =M20+K21-L21 -> 0.08
A22: 19 | B22: 46131 | G22: =E22*F22 -> 0 | J22: =H22*I22 -> 0 | K22: =G22+J22 -> 0 | L22: 0 | M22: =M21+K22-L22 -> 0.08
A23: 20 | B23: 46132 | G23: =E23*F23 -> 0 | J23: =H23*I23 -> 0 | K23: =G23+J23 -> 0 | L23: 0 | M23: =M22+K23-L23 -> 0.08
A24: 21 | B24: 46133 | G24: =E24*F24 -> 0 | J24: =H24*I24 -> 0 | K24: =G24+J24 -> 0 | L24: 0 | M24: =M23+K24-L24 -> 0.08
A25: 22 | B25: 46134 | G25: =E25*F25 -> 0 | J25: =H25*I25 -> 0 | K25: =G25+J25 -> 0 | L25: 0 | M25: =M24+K25-L25 -> 0.08
A26: 23 | B26: 46135 | G26: =E26*F26 -> 0 | J26: =H26*I26 -> 0 | K26: =G26+J26 -> 0 | L26: 0 | M26: =M25+K26-L26 -> 0.08
A27: 24 | B27: 46136 | G27: =E27*F27 -> 0 | J27: =H27*I27 -> 0 | K27: =G27+J27 -> 0 | L27: 0 | M27: =M26+K27-L27 -> 0.08
A28: 25 | B28: 46137 | G28: =E28*F28 -> 0 | J28: =H28*I28 -> 0 | K28: =G28+J28 -> 0 | L28: 0 | M28: =M27+K28-L28 -> 0.08
A29: 26 | B29: 46138 | G29: =E29*F29 -> 0 | J29: =H29*I29 -> 0 | K29: =G29+J29 -> 0 | L29: 0 | M29: =M28+K29-L29 -> 0.08
A30: 27 | B30: 46139 | G30: =E30*F30 -> 0 | J30: =H30*I30 -> 0 | K30: =G30+J30 -> 0 | L30: 0 | M30: =M29+K30-L30 -> 0.08
A31: 28 | B31: 46140 | G31: =E31*F31 -> 0 | J31: =H31*I31 -> 0 | K31: =G31+J31 -> 0 | L31: 0 | M31: =M30+K31-L31 -> 0.08
... A33: 30 | B33: 46142 | G33: =E33*F33 -> 0 | J33: =H33*I33 -> 0 | K33: =G33+J33 -> 0 | L33: 0 | M33: =M32+K33-L33 -> 0.08
A34: 31 | G34: =E34*F34 -> 0 | K34: =G34+J34 -> 0 | L34: 0 | M34: =M33+K34-L34 -> 0.08
A35: 32 | G35: =E35*F35 -> 0 | J35: =H35*I35 -> 0 | K35: =G35+J35 -> 0 | L35: 0 | M35: =M34+K35-L35 -> 0.08
A36: 33 | G36: =E36*F36 -> 0 | J36: =H36*I36 -> 0 | K36: =G36+J36 -> 0 | L36: 0
A37: 34 | G37: =E37*F37 -> 0 | J37: =H37*I37 -> 0 | K37: =G37+J37 -> 0
E38: =SUM(E3:E37) -> 0 | G38: =SUM(G3:G37) -> 0 | H38: =SUM(H3:H37) -> 0 | J38: =SUM(J3:J37) -> 0 | K38: =SUM(K4:K37) -> 0 | L38: =SUM(L3:L37) -> 330407

Sheet Khammam-5
A1: SR HP Filling Station ( Dhamsalapuram)
A2: S.No | B2: Date | C2: GRN No | D2: Ind No/Bill No | E2: Diesel (Lts) | F2: Price | G2: Amount | H2: Petrol (Lts) | I2: Price | J2: Amount | K2: Total amount | L2: Amount paid | M2: As 0n Date | N2: Remarks
A3: Opening Balance | K3: 0 | M3: 0
A4: 1 | B4: 46113 | G4: =E4*F4 -> 0 | K4: =G4+J4 -> 0 | L4: 0 | M4: =M3+K4-L4 -> 0
A5: 2 | B5: 46114 | G5: =E5*F5 -> 0 | J5: =H5*I5 -> 0 | K5: =G5+J5 -> 0 | L5: 0 | M5: =M4+K5-L5 -> 0
A6: 3 | B6: 46115 | G6: =E6*F6 -> 0 | J6: =H6*I6 -> 0 | K6: =G6+J6 -> 0 | L6: 0 | M6: =M5+K6-L6 -> 0
A7: 4 | B7: 46116 | G7: =E7*F7 -> 0 | J7: =H7*I7 -> 0 | K7: =G7+J7 -> 0 | L7: 0 | M7: =M6+K7-L7 -> 0
A8: 5 | B8: 46117 | G8: =E8*F8 -> 0 | J8: =H8*I8 -> 0 | K8: =G8+J8 -> 0 | L8: 0 | M8: =M7+K8-L8 -> 0
A9: 6 | B9: 46118 | G9: =E9*F9 -> 0 | J9: =H9*I9 -> 0 | K9: =G9+J9 -> 0 | L9: 0 | M9: =M8+K9-L9 -> 0
A10: 7 | B10: 46119 | G10: =E10*F10 -> 0 | J10: =H10*I10 -> 0 | K10: =G10+J10 -> 0 | L10: 0 | M10: =M9+K10-L10 -> 0
A11: 8 | B11: 46120 | G11: =E11*F11 -> 0 | J11: =H11*I11 -> 0 | K11: =G11+J11 -> 0 | L11: 0 | M11: =M10+K11-L11 -> 0
A12: 9 | B12: 46121 | G12: =E12*F12 -> 0 | J12: =H12*I12 -> 0 | K12: =G12+J12 -> 0 | L12: 0 | M12: =M11+K12-L12 -> 0
A13: 10 | B13: 46122 | G13: =E13*F13 -> 0 | J13: =H13*I13 -> 0 | K13: =G13+J13 -> 0 | L13: 0 | M13: =M12+K13-L13 -> 0
A14: 11 | B14: 46123 | G14: =E14*F14 -> 0 | J14: =H14*I14 -> 0 | K14: =G14+J14 -> 0 | L14: 0 | M14: =M13+K14-L14 -> 0
A15: 12 | B15: 46124 | G15: =E15*F15 -> 0 | J15: =H15*I15 -> 0 | K15: =G15+J15 -> 0 | L15: 0 | M15: =M14+K15-L15 -> 0
A16: 13 | B16: 46125 | G16: =E16*F16 -> 0 | J16: =H16*I16 -> 0 | K16: =G16+J16 -> 0 | L16: 0 | M16: =M15+K16-L16 -> 0
A17: 14 | B17: 46126 | G17: =E17*F17 -> 0 | J17: =H17*I17 -> 0 | K17: =G17+J17 -> 0 | L17: 0 | M17: =M16+K17-L17 -> 0 | U17: 257315
A18: 15 | B18: 46127 | G18: =E18*F18 -> 0 | J18: =H18*I18 -> 0 | K18: =G18+J18 -> 0 | L18: 0 | M18: =M17+K18-L18 -> 0 | U18: 22996
A19: 16 | B19: 46128 | G19: =E19*F19 -> 0 | J19: =H19*I19 -> 0 | K19: =G19+J19 -> 0 | L19: 0 | M19: =M18+K19-L19 -> 0 | U19: =U17+U18 -> 280311
A20: 17 | B20: 46129 | G20: =E20*F20 -> 0 | J20: =H20*I20 -> 0 | K20: =G20+J20 -> 0 | L20: 0 | M20: =M19+K20-L20 -> 0 | U20: =U19-183340 -> 96971
A21: 18 | B21: 46130 | G21: =E21*F21 -> 0 | J21: =H21*I21 -> 0 | K21: =G21+J21 -> 0 | L21: 0 | M21: =M20+K21-L21 -> 0
A22: 19 | B22: 46131 | G22: =E22*F22 -> 0 | J22: =H22*I22 -> 0 | K22: =G22+J22 -> 0 | L22: 0 | M22: =M21+K22-L22 -> 0 | R22: 91.67
A23: 20 | B23: 46132 | G23: =E23*F23 -> 0 | J23: =H23*I23 -> 0 | K23: =G23+J23 -> 0 | L23: 0 | M23: =M22+K23-L23 -> 0 | R23: 2000 | U23: 197391.46
A24: 21 | B24: 46133 | E24: 3135.46 | F24: 95.68 | G24: =E24*F24 -> 300000.81 | J24: =H24*I24 -> 0 | K24: =G24+J24 -> 300000.81 | L24: =H24+K24 -> 300000.81 | M24: =M23+K24-L24 -> 0 | R24: =R23*R22 -> 183340
A25: 22 | B25: 46134 | G25: =E25*F25 -> 0 | J25: =H25*I25 -> 0 | K25: =G25+J25 -> 0 | L25: 0 | M25: =M24+K25-L25 -> 0
A26: 23 | B26: 46135 | G26: =E26*F26 -> 0 | J26: =H26*I26 -> 0 | K26: =G26+J26 -> 0 | L26: 0 | M26: =M25+K26-L26 -> 0
A27: 24 | B27: 46136 | G27: =E27*F27 -> 0 | J27: =H27*I27 -> 0 | K27: =G27+J27 -> 0 | L27: 0 | M27: =M26+K27-L27 -> 0
A28: 25 | B28: 46137 | G28: =E28*F28 -> 0 | J28: =H28*I28 -> 0 | K28: =G28+J28 -> 0 | L28: 0 | M28: =M27+K28-L28 -> 0
A29: 26 | B29: 46138 | G29: =E29*F29 -> 0 | J29: =H29*I29 -> 0 | K29: =G29+J29 -> 0 | L29: 0 | M29: =M28+K29-L29 -> 0
A30: 27 | B30: 46139 | G30: =E30*F30 -> 0 | J30: =H30*I30 -> 0 | K30: =G30+J30 -> 0 | L30: 0 | M30: =M29+K30-L30 -> 0
A31: 28 | B31: 46140 | G31: =E31*F31 -> 0 | J31: =H31*I31 -> 0 | K31: =G31+J31 -> 0 | L31: 0 | M31: =M30+K31-L31 -> 0
A32: 29 | B32: 46141 | G32: =E32*F32 -> 0 | J32: =H32*I32 -> 0 | K32: =G32+J32 -> 0 | L32: 0 | M32: =M31+K32-L32 -> 0
A33: 30 | B33: 46142 | G33: =E33*F33 -> 0 | J33: =H33*I33 -> 0 | K33: =G33+J33 -> 0 | L33: 0 | M33: =M32+K33-L33 -> 0
A34: 31 | G34: =E34*F34 -> 0 | K34: =G34+J34 -> 0 | L34: 0 | M34: =M33+K34-L34 -> 0
A35: 32 | G35: =E35*F35 -> 0 | J35: =H35*I35 -> 0 | K35: =G35+J35 -> 0 | L35: 0 | M35: =M34+K35-L35 -> 0
A36: 33 | G36: =E36*F36 -> 0 | J36: =H36*I36 -> 0 | K36: =G36+J36 -> 0 | L36: 0
A37: 34 | G37: =E37*F37 -> 0 | J37: =H37*I37 -> 0 | K37: =G37+J37 -> 0
E38: =SUM(E3:E37) -> 3135.46 | G38: =SUM(G3:G37) -> 300000.81 | H38: =SUM(H3:H37) -> 0 | J38: =SUM(J3:J37) -> 0 | K38: =SUM(K4:K37) -> 300000.81 | L38: =SUM(L3:L37) -> 300000.81

Sheet  Khammam&Cash
A1: Cash &Carry
A2: S.No | B2: Date | D2: Ind No/Bill No | E2: Diesel (Lts) | F2: Price | G2: Amount | H2: Petrol (Lts) | I2: Price | J2: Amount | K2: Total amount | L2: Amount paid | M2: As 0n Date | N2: Remarks
A3: Opening Balance | K3: 0 | M3: 0
A4: 1 | G4: =E4*F4 -> 0 | K4: =G4+J4 -> 0 | L4: 0 | M4: =M3+K4-L4 -> 0
A5: 2 | G5: =E5*F5 -> 0 | J5: =H5*I5 -> 0 | K5: =G5+J5 -> 0 | L5: 0 | M5: =M4+K5-L5 -> 0
A6: 3 | G6: =E6*F6 -> 0 | J6: =H6*I6 -> 0 | K6: =G6+J6 -> 0 | L6: 0 | M6: =M5+K6-L6 -> 0
A7: 4 | G7: =E7*F7 -> 0 | J7: =H7*I7 -> 0 | K7: =G7+J7 -> 0 | L7: 0 | M7: =M6+K7-L7 -> 0
A8: 5 | G8: =E8*F8 -> 0 | J8: =H8*I8 -> 0 | K8: =G8+J8 -> 0 | L8: 0 | M8: =M7+K8-L8 -> 0
A9: 6 | G9: =E9*F9 -> 0 | J9: =H9*I9 -> 0 | K9: =G9+J9 -> 0 | L9: 0 | M9: =M8+K9-L9 -> 0
A10: 7 | G10: =E10*F10 -> 0 | J10: =H10*I10 -> 0 | K10: =G10+J10 -> 0 | L10: 0 | M10: =M9+K10-L10 -> 0
A11: 8 | G11: =E11*F11 -> 0 | J11: =H11*I11 -> 0 | K11: =G11+J11 -> 0 | L11: 0 | M11: =M10+K11-L11 -> 0
A12: 9 | G12: =E12*F12 -> 0 | J12: =H12*I12 -> 0 | K12: =G12+J12 -> 0 | L12: 0 | M12: =M11+K12-L12 -> 0
A13: 10 | G13: =E13*F13 -> 0 | J13: =H13*I13 -> 0 | K13: =G13+J13 -> 0 | L13: 0 | M13: =M12+K13-L13 -> 0
A14: 11 | G14: =E14*F14 -> 0 | J14: =H14*I14 -> 0 | K14: =G14+J14 -> 0 | L14: 0 | M14: =M13+K14-L14 -> 0
A15: 12 | G15: =E15*F15 -> 0 | J15: =H15*I15 -> 0 | K15: =G15+J15 -> 0 | L15: 0 | M15: =M14+K15-L15 -> 0
A16: 13 | G16: =E16*F16 -> 0 | J16: =H16*I16 -> 0 | K16: =G16+J16 -> 0 | L16: 0 | M16: =M15+K16-L16 -> 0
... A23: 20 | G23: =E23*F23 -> 0 | J23: =H23*I23 -> 0 | K23: =G23+J23 -> 0 | L23: 0 | M23: =M22+K23-L23 -> 0
A24: 21 | G24: =E24*F24 -> 0 | J24: =H24*I24 -> 0 | K24: =G24+J24 -> 0 | L24: =H24+K24 -> 0 | M24: =M23+K24-L24 -> 0
A25: 22 | B25: 22.04.2026 | C25: My Nation Gas Station (Superintendent) | E25: 2900 | F25: 95.71 | G25: =E25*F25 -> 277559 | J25: =H25*I25 -> 0 | K25: =G25+J25 -> 277559 | L25: =H25+K25 -> 277559 | M25: =M24+K25-L25 -> 0 | N25: Cash
A26: 23 | B26: 23.04.2026 | C26: Perumalla Filling Station | E26: 2800 | F26: 95.68 | G26: =E26*F26 -> 267904 | J26: =H26*I26 -> 0 | K26: =G26+J26 -> 267904 | L26: =H26+K26 -> 267904 | M26: =M25+K26-L26 -> 0 | N26: HPCL
A27: 24 | B27: 23.04.2026 | C27: Jai Sreeram Filling Station | E27: 2200 | F27: 95.72 | G27: =E27*F27 -> 210584 | K27: =G27+J27 -> 210584 | L27: =H27+K27 -> 210584 | M27: =M26+K27-L27 -> 0 | N27: Cash
A28: 25 | B28: 23.04.2026 | C28: Sri Sri Sri Filling Station | E28: =170+170+80+80 -> 500 | F28: 95.68 | G28: =E28*F28 -> 47840 | J28: =H28*I28 -> 0 | K28: =G28+J28 -> 47840 | L28: =H28+K28 -> 47840 | M28: =M26+K28-L28 -> 0 | N28: HPCL
A29: 26 | B29: 24.04.2026 | C29: Perumalla Filling Station | E29: 900 | F29: 95.68 | G29: =E29*F29 -> 86112 | J29: =H29*I29 -> 0 | K29: =G29+J29 -> 86112 | L29: =H29+K29 -> 86112 | M29: =M28+K29-L29 -> 0 | N29: HPCL | O29: 354016 paid to dted 24.04.2026
A30: 27 | B30: 24.04.2026 | C30: SR HP Filling Station | E30: 2700 | F30: 95.68 | G30: =E30*F30 -> 258336 | J30: =H30*I30 -> 0 | K30: =G30+J30 -> 258336 | L30: =H30+K30 -> 258336 | M30: =M29+K30-L30 -> 0 | N30: HPCL
A31: 28 | B31: 25.04.2026 | C31: Perumalla Filling Station | E31: 2200 | F31: 95.68 | G31: =E31*F31 -> 210496 | J31: =H31*I31 -> 0 | K31: =G31+J31 -> 210496 | L31: =H31+K31 -> 210496 | M31: =M30+K31-L31 -> 0 | N31: HPCL
A32: 29 | B32: 27.04.2026 | C32: Perumalla Filling Station | E32: 400 | F32: 95.68 | G32: =E32*F32 -> 38272 | J32: =H32*I32 -> 0 | K32: =G32+J32 -> 38272 | L32: =H32+K32 -> 38272 | M32: =M31+K32-L32 -> 0 | N32: HPCL
A33: 30 | B33: 27.04.2026 | C33: Laxmi manikanta filling station | E33: 229.85 | F33: 95.72 | G33: =E33*F33 -> 22001.242 | J33: =H33*I33 -> 0 | K33: =G33+J33 -> 22001.242 | L33: 22001.24 | M33: =M32+K33-L33 -> 0.002 | N33: Cash
A34: 31 | B34: 28.04.2026 | C34: Sri Sri Sri Filling Station ( HP ) | E34: 200 | F34: 95.68 | G34: =E34*F34 -> 19136 | H34: 95 | I34: 107.46 | J34: =H34*I34 -> 10208.7 | K34: =G34+J34 -> 29344.7 | L34: 29344.7 | M34: =M33+K34-L34 -> 0.002 | N34: HPCL
A35: 32 | B35: 28.04.2026 | C35: Quality Service Station ( IOCL) | E35: 570 | F35: 95.71 | G35: =E35*F35 -> 54554.7 | K35: =G35+J35 -> 54554.7 | L35: =H35+K35 -> 54554.7 | M35: =M34+K35-L35 -> 0.002 | N35: Cash
A36: 33 | B36: 28.04.2026 | C36: Laxmi manikanta filling station (BPCL) | E36: 679.11 | F36: 95.72 | G36: =E36*F36 -> 65004.409 | J36: =H36*I36 -> 0 | K36: =G36+J36 -> 65004.409 | L36: =H36+K36 -> 65004.409 | M36: =M35+K36-L36 -> 0.002 | N36: Cash
A37: 34 | B37: 29.04.2026 | C37: Sri Sri Sri Filling Station ( HP ) | E37: 1000 | F37: 95.68 | G37: =E37*F37 -> 95680 | J37: =H37*I37 -> 0 | K37: =G37+J37 -> 95680 | L37: =H37+K37 -> 95680 | M37: =M36+K37-L37 -> 0.002 | N37: HPCL
A38: 35 | B38: 29.04.2026 | C38: Perumalla Filling Station | E38: 200 | F38: 95.68 | G38: =E38*F38 -> 19136 | K38: =G38+J38 -> 19136 | L38: =H38+K38 -> 19136 | M38: =M37+K38-L38 -> 0.002 | N38: HPCL
A39: 36 | B39: 29.04.2026 | C39: Stambhadri Fuel Park | E39: 1813.56 | F39: 95.68 | G39: =E39*F39 -> 173521.42 | K39: =G39+J39 -> 173521.42 | L39: =H39+K39 -> 173521.42 | M39: =M38+K39-L39 -> 0.002 | N39: HPCL
A40: 37 | B40: 29.04.2026 | C40: Laxmi manikanta filling station (BPCL) | E40: 365.68 | F40: 95.72 | G40: =E40*F40 -> 35002.89 | K40: =G40+J40 -> 35002.89 | L40: =H40+K40 -> 35002.89 | M40: =M39+K40-L40 -> 0.002 | N40: Cash
A41: 38 | G41: =E41*F41 -> 0 | K41: =G41+J41 -> 0 | L41: =H41+K41 -> 0 | M41: =M40+K41-L41 -> 0.002
A42: 39 | B42: 30.04.2026 | C42: Stambhadri Fuel Park | E42: 1250 | F42: 95.68 | G42: =E42*F42 -> 119600 | K42: =G42+J42 -> 119600 | L42: =H42+K42 -> 119600 | M42: =M41+K42-L42 -> 0.002 | N42: HPCL
A43: 40 | B43: 30.04.2026 | C43: Jai Sreeram Filling Station BPCL | E43: 2800 | F43: 95.72 | G43: =E43*F43 -> 268016 | K43: =G43+J43 -> 268016 | L43: =H43+K43 -> 268016 | M43: =M42+K43-L43 -> 0.002 | N43: Cash
A44: 41 | B44: 30.04.2026 | C44: Laxmi manikanta filling station (BPCL) | E44: 1149.28 | F44: 95.72 | G44: =E44*F44 -> 110009.08 | K44: =G44+J44 -> 110009.08 | L44: =H44+K44 -> 110009.08 | M44: =M43+K44-L44 -> 0.002 | N44: Cash
A45: 42 | G45: =E45*F45 -> 0 | J45: =H45*I45 -> 0 | K45: =G45+J45 -> 0
E46: =SUM(E3:E45) -> 24857.48 | G46: =SUM(G3:G45) -> 2378764.7 | H46: =SUM(H3:H45) -> 95 | J46: =SUM(J3:J45) -> 10208.7 | K46: =SUM(K4:K45) -> 2388973.4 | L46: =SUM(L3:L45) -> 2388973.4

Sheet  Jadcherla
A1: Sai baba F/S
A2: S.No | B2: Date | C2: GRN No | D2: Ind No/Bill No | E2: Diesel (Lts) | F2: Price | G2: Amount | H2: Petrol (Lts) | I2: Price | J2: Amount | K2: Total amount | L2: Amount paid | M2: As on date | N2: Remarks
A3: Opening Balance | M3: 0
A4: 1 | B4: 46113 | G4: =E4*F4 -> 0 | J4: =H4*I4 -> 0 | K4: =G4+J4 -> 0 | L4: 0 | M4: =M3+K4-L4 -> 0
A5: 2 | B5: 46114 | G5: =E5*F5 -> 0 | J5: =H5*I5 -> 0 | K5: =G5+J5 -> 0 | L5: 0 | M5: =M4+K5-L5 -> 0
A6: 3 | B6: 46115 | G6: =E6*F6 -> 0 | J6: =H6*I6 -> 0 | K6: =G6+J6 -> 0 | L6: 0 | M6: =M5+K6-L6 -> 0
A7: 4 | B7: 46116 | G7: =E7*F7 -> 0 | J7: =H7*I7 -> 0 | K7: =G7+J7 -> 0 | L7: 0 | M7: =M6+K7-L7 -> 0
A8: 5 | B8: 46117 | G8: =E8*F8 -> 0 | J8: =H8*I8 -> 0 | K8: =G8+J8 -> 0 | L8: 0 | M8: =M7+K8-L8 -> 0
A9: 6 | B9: 46118 | G9: =E9*F9 -> 0 | J9: =H9*I9 -> 0 | K9: =G9+J9 -> 0 | L9: 0 | M9: =M8+K9-L9 -> 0
A10: 7 | B10: 46119 | G10: =E10*F10 -> 0 | J10: =H10*I10 -> 0 | K10: =G10+J10 -> 0 | L10: 0 | M10: =M9+K10-L10 -> 0
A11: 8 | B11: 46120 | G11: =E11*F11 -> 0 | J11: =H11*I11 -> 0 | K11: =G11+J11 -> 0 | L11: 0 | M11: =M10+K11-L11 -> 0
A12: 9 | B12: 46121 | G12: =E12*F12 -> 0 | J12: =H12*I12 -> 0 | K12: =G12+J12 -> 0 | L12: 0 | M12: =M11+K12-L12 -> 0
A13: 10 | B13: 46122 | G13: =E13*F13 -> 0 | J13: =H13*I13 -> 0 | K13: =G13+J13 -> 0 | L13: 0 | M13: =M12+K13-L13 -> 0
A14: 11 | B14: 46123 | G14: =E14*F14 -> 0 | J14: =H14*I14 -> 0 | K14: =G14+J14 -> 0 | L14: 0 | M14: =M13+K14-L14 -> 0
A15: 12 | B15: 46124 | G15: =E15*F15 -> 0 | J15: =H15*I15 -> 0 | K15: =G15+J15 -> 0 | L15: =H15+K15 -> 0 | M15: =M14+K15-L15 -> 0
A16: 13 | B16: 46125 | G16: =E16*F16 -> 0 | J16: =H16*I16 -> 0 | K16: =G16+J16 -> 0 | L16: 0 | M16: =M15+K16-L16 -> 0
A17: 14 | B17: 46126 | G17: =E17*F17 -> 0 | J17: =H17*I17 -> 0 | K17: =G17+J17 -> 0 | L17: 0 | M17: =M16+K17-L17 -> 0
A18: 15 | B18: 46127 | G18: =E18*F18 -> 0 | J18: =H18*I18 -> 0 | K18: =G18+J18 -> 0 | L18: 0 | M18: =M17+K18-L18 -> 0
A19: 16 | B19: 46128 | G19: =E19*F19 -> 0 | J19: =H19*I19 -> 0 | K19: =G19+J19 -> 0 | L19: 0 | M19: =M18+K19-L19 -> 0
A20: 17 | B20: 46129 | G20: =E20*F20 -> 0 | J20: =H20*I20 -> 0 | K20: =G20+J20 -> 0 | L20: 0 | M20: =M19+K20-L20 -> 0
A21: 18 | B21: 46130 | G21: =E21*F21 -> 0 | J21: =H21*I21 -> 0 | K21: =G21+J21 -> 0 | L21: 0 | M21: =M20+K21-L21 -> 0
A22: 19 | B22: 46131 | G22: =E22*F22 -> 0 | J22: =H22*I22 -> 0 | K22: =G22+J22 -> 0 | L22: 0 | M22: =M21+K22-L22 -> 0
A23: 20 | B23: 46132 | G23: =E23*F23 -> 0 | J23: =H23*I23 -> 0 | K23: =G23+J23 -> 0 | L23: 0 | M23: =M22+K23-L23 -> 0
A24: 21 | B24: 46133 | G24: =E24*F24 -> 0 | J24: =H24*I24 -> 0 | K24: =G24+J24 -> 0 | L24: 0 | M24: =M23+K24-L24 -> 0
A25: 22 | B25: 46134 | G25: =E25*F25 -> 0 | J25: =H25*I25 -> 0 | K25: =G25+J25 -> 0 | L25: 0 | M25: =M24+K25-L25 -> 0
A26: 23 | B26: 46135 | E26: 1500 | F26: 96.42 | G26: =E26*F26 -> 144630 | J26: =H26*I26 -> 0 | K26: =G26+J26 -> 144630 | L26: =H26+K26 -> 144630 | M26: =M25+K26-L26 -> 0
A27: 24 | B27: 46136 | G27: =E27*F27 -> 0 | J27: =H27*I27 -> 0 | K27: =G27+J27 -> 0 | L27: 0 | M27: =M26+K27-L27 -> 0
A28: 25 | B28: 46137 | G28: =E28*F28 -> 0 | J28: =H28*I28 -> 0 | K28: =G28+J28 -> 0 | L28: 0 | M28: =M27+K28-L28 -> 0
A29: 26 | B29: 46138 | G29: =E29*F29 -> 0 | J29: =H29*I29 -> 0 | K29: =G29+J29 -> 0 | L29: 0 | M29: =M28+K29-L29 -> 0
A30: 27 | B30: 46139 | G30: =E30*F30 -> 0 | J30: =H30*I30 -> 0 | K30: =G30+J30 -> 0 | L30: 0 | M30: =M29+K30-L30 -> 0
A31: 28 | B31: 46140 | G31: =E31*F31 -> 0 | J31: =H31*I31 -> 0 | K31: =G31+J31 -> 0 | L31: 0 | M31: =M30+K31-L31 -> 0
A32: 29 | B32: 46141 | G32: =E32*F32 -> 0 | J32: =H32*I32 -> 0 | K32: =G32+J32 -> 0 | L32: 0 | M32: =M31+K32-L32 -> 0
A33: 30 | B33: 46142 | E33: 1500 | F33: 96.42 | G33: =E33*F33 -> 144630 | H33: 0 | I33: 0 | J33: =H33*I33 -> 0 | K33: =G33+J33 -> 144630 | L33: 100000 | M33: =M32+K33-L33 -> 44630
A34: 31 | B34: 46143 | G34: =E34*F34 -> 0 | J34: =H34*I34 -> 0 | K34: =G34+J34 -> 0 | M34: =M33+K34-L34 -> 44630
E35: =SUM(E4:E34) -> 3000 | G35: =SUM(G4:G34) -> 289260 | H35: =SUM(H4:H34) -> 0 | J35: =SUM(J4:J34) -> 0 | K35: =SUM(K4:K34) -> 289260 | L35: =SUM(L4:L34) -> 244630

Sheet Jadcherla-3
A1: JSASFuel Genie India Pvt.Ltd
A2: S.No | B2: Date | C2: GRN No | D2: Ind no/Bill No | E2: Diesel (Lts) | F2: Price | G2: Amount | H2: Petrol (Lts) | I2: Price | J2: Amount | K2: Total amount | L2: Amount paid | M2: As on Date | N2: Remarks
A3: Opening Balance | M3: 2453209.4
A4: 1 | B4: 46113 | G4: =E4*F4 -> 0 | J4: =H4*I4 -> 0 | K4: =G4+J4 -> 0 | L4: 0 | M4: =+M3+K4-L4 -> 2453209.4
A5: 2 | B5: 46114 | G5: =E5*F5 -> 0 | J5: =H5*I5 -> 0 | K5: =G5+J5 -> 0 | L5: 0 | M5: =+M4+K5-L5 -> 2453209.4
A6: 3 | B6: 46115 | G6: =E6*F6 -> 0 | J6: =H6*I6 -> 0 | K6: =G6+J6 -> 0 | L6: 2453209.4 | M6: =+M5+K6-L6 -> 0 | O6: 8032614 | P6: 2453209.4 | Q6: =SUM(O6:P6) -> 10485823
A7: 4 | B7: 46116 | E7: 990 | F7: 95.93 | G7: =E7*F7 -> 94970.7 | J7: =H7*I7 -> 0 | K7: =G7+J7 -> 94970.7 | L7: 0 | M7: =+M6+K7-L7 -> 94970.7
A8: 5 | B8: 46117 | G8: =E8*F8 -> 0 | J8: =H8*I8 -> 0 | K8: =G8+J8 -> 0 | L8: 0 | M8: =+M7+K8-L8 -> 94970.7
A9: 6 | B9: 46118 | G9: =E9*F9 -> 0 | J9: =H9*I9 -> 0 | K9: =G9+J9 -> 0 | L9: 0 | M9: =+M8+K9-L9 -> 94970.7
A10: 7 | B10: 46119 | E10: 1400 | F10: 95.93 | G10: =E10*F10 -> 134302 | J10: =H10*I10 -> 0 | K10: =G10+J10 -> 134302 | L10: 0 | M10: =+M9+K10-L10 -> 229272.7 | R10: 700
A11: 8 | B11: 46120 | G11: =E11*F11 -> 0 | J11: =H11*I11 -> 0 | K11: =G11+J11 -> 0 | L11: 0 | M11: =+M10+K11-L11 -> 229272.7 | S11: 5000
A12: 9 | B12: 46121 | G12: =E12*F12 -> 0 | J12: =H12*I12 -> 0 | K12: =G12+J12 -> 0 | L12: 0 | M12: =+M11+K12-L12 -> 229272.7 | S12: 1500
A13: 10 | B13: 46122 | G13: =E13*F13 -> 0 | J13: =H13*I13 -> 0 | K13: =G13+J13 -> 0 | L13: 0 | M13: =+M12+K13-L13 -> 229272.7 | S13: 500
A14: 11 | B14: 46123 | E14: 1800 | F14: 95.93 | G14: =E14*F14 -> 172674 | J14: =H14*I14 -> 0 | K14: =G14+J14 -> 172674 | L14: 0 | M14: =+M13+K14-L14 -> 401946.7
A15: 12 | B15: 46124 | E15: 2000 | F15: 95.93 | G15: =E15*F15 -> 191860 | J15: =H15*I15 -> 0 | K15: =G15+J15 -> 191860 | L15: 0 | M15: =+M14+K15-L15 -> 593806.7
A16: 13 | B16: 46125 | G16: =E16*F16 -> 0 | J16: =H16*I16 -> 0 | K16: =G16+J16 -> 0 | L16: 0 | M16: =+M15+K16-L16 -> 593806.7
A17: 14 | B17: 46126 | G17: =E17*F17 -> 0 | J17: =H17*I17 -> 0 | K17: =G17+J17 -> 0 | L17: 0 | M17: =+M16+K17-L17 -> 593806.7
A18: 15 | B18: 46127 | E18: 2000 | F18: 95.93 | G18: =E18*F18 -> 191860 | J18: =H18*I18 -> 0 | K18: =G18+J18 -> 191860 | L18: 0 | M18: =+M17+K18-L18 -> 785666.7
A19: 16 | B19: 46128 | G19: =E19*F19 -> 0 | J19: =H19*I19 -> 0 | K19: =G19+J19 -> 0 | L19: 0 | M19: =+M18+K19-L19 -> 785666.7
A20: 17 | B20: 46129 | G20: =E20*F20 -> 0 | J20: =H20*I20 -> 0 | K20: =G20+J20 -> 0 | L20: 0 | M20: =+M19+K20-L20 -> 785666.7
A21: 18 | B21: 46130 | E21: 2500 | F21: 95.93 | G21: =E21*F21 -> 239825 | J21: =H21*I21 -> 0 | K21: =G21+J21 -> 239825 | L21: 0 | M21: =+M20+K21-L21 -> 1025491.7
A22: 19 | B22: 46131 | E22: 2000 | F22: 95.93 | G22: =E22*F22 -> 191860 | J22: =H22*I22 -> 0 | K22: =G22+J22 -> 191860 | L22: 0 | M22: =+M21+K22-L22 -> 1217351.7
A23: 20 | B23: 46132 | G23: =E23*F23 -> 0 | J23: =H23*I23 -> 0 | K23: =G23+J23 -> 0 | L23: 0 | M23: =+M22+K23-L23 -> 1217351.7
A24: 21 | B24: 46133 | G24: =E24*F24 -> 0 | J24: =H24*I24 -> 0 | K24: =G24+J24 -> 0 | L24: 0 | M24: =+M23+K24-L24 -> 1217351.7
A25: 22 | B25: 46134 | G25: =E25*F25 -> 0 | J25: =H25*I25 -> 0 | K25: =G25+J25 -> 0 | L25: 0 | M25: =+M24+K25-L25 -> 1217351.7
A26: 23 | B26: 46135 | G26: =E26*F26 -> 0 | J26: =H26*I26 -> 0 | K26: =G26+J26 -> 0 | L26: 0 | M26: =+M25+K26-L26 -> 1217351.7
A27: 24 | B27: 46136 | E27: 1000 | F27: 95.93 | G27: =E27*F27 -> 95930 | J27: =H27*I27 -> 0 | K27: =G27+J27 -> 95930 | L27: 0 | M27: =+M26+K27-L27 -> 1313281.7
A28: 25 | B28: 46137 | G28: =E28*F28 -> 0 | J28: =H28*I28 -> 0 | K28: =G28+J28 -> 0 | L28: 0 | M28: =+M27+K28-L28 -> 1313281.7
A29: 26 | B29: 46138 | G29: =E29*F29 -> 0 | J29: =H29*I29 -> 0 | K29: =G29+J29 -> 0 | L29: 0 | M29: =+M28+K29-L29 -> 1313281.7
A30: 27 | B30: 46139 | G30: =E30*F30 -> 0 | J30: =H30*I30 -> 0 | K30: =G30+J30 -> 0 | L30: 0 | M30: =+M29+K30-L30 -> 1313281.7
A31: 28 | B31: 46140 | G31: =E31*F31 -> 0 | J31: =H31*I31 -> 0 | K31: =G31+J31 -> 0 | L31: 0 | M31: =+M30+K31-L31 -> 1313281.7
A32: 29 | B32: 46141 | G32: =E32*F32 -> 0 | J32: =H32*I32 -> 0 | K32: =G32+J32 -> 0 | M32: =+M31+K32-L32 -> 1313281.7
A33: 30 | B33: 46142 | G33: =E33*F33 -> 0 | J33: =H33*I33 -> 0 | K33: =G33+J33 -> 0 | M33: =+M32+K33-L33 -> 1313281.7
A34: 31 | G34: =E34*F34 -> 0 | H34: 0 | I34: 0 | J34: =H34*I34 -> 0 | K34: =G34+J34 -> 0 | L34: 0 | M34: =+M33+K34-L34 -> 1313281.7
E35: =SUM(E4:E34) -> 13690 | G35: =SUM(G4:G34) -> 1313281.7 | H35: =SUM(H4:H34) -> 0 | J35: =SUM(J4:J34) -> 0 | K35: =SUM(K4:K34) -> 1313281.7 | L35: =SUM(L4:L34) -> 2453209.4

Sheet Jadcherla-4
A1: Shree Poornima F/S
A2: S.No | B2: Date | C2: GRN No | D2: Ind No/Bill No | E2: Diesel (Lts) | F2: Price | G2: Amount | H2: Petrol (Lts) | I2: Price | J2: Amount | K2: Total amount | L2: Amount paid | M2: As on date | N2: Remarks
A3: Opening Balance | M3: 9729
A4: 1 | B4: 46113 | G4: =E4*F4 -> 0 | J4: =H4*I4 -> 0 | K4: =G4+J4 -> 0 | L4: 0 | M4: =M3+K4-L4 -> 9729
A5: 2 | B5: 46114 | G5: =E5*F5 -> 0 | J5: =H5*I5 -> 0 | K5: =G5+J5 -> 0 | L5: 9729 | M5: =M4+K5-L5 -> 0
A6: 3 | B6: 46115 | G6: =E6*F6 -> 0 | J6: =H6*I6 -> 0 | K6: =G6+J6 -> 0 | L6: 0 | M6: =M5+K6-L6 -> 0
A7: 4 | B7: 46116 | G7: =E7*F7 -> 0 | J7: =H7*I7 -> 0 | K7: =G7+J7 -> 0 | L7: 0 | M7: =M6+K7-L7 -> 0
A8: 5 | B8: 46117 | G8: =E8*F8 -> 0 | J8: =H8*I8 -> 0 | K8: =G8+J8 -> 0 | L8: 0 | M8: =M7+K8-L8 -> 0
A9: 6 | B9: 46118 | G9: =E9*F9 -> 0 | J9: =H9*I9 -> 0 | K9: =G9+J9 -> 0 | L9: 0 | M9: =M8+K9-L9 -> 0
A10: 7 | B10: 46119 | G10: =E10*F10 -> 0 | J10: =H10*I10 -> 0 | K10: =G10+J10 -> 0 | L10: 0 | M10: =M9+K10-L10 -> 0
A11: 8 | B11: 46120 | G11: =E11*F11 -> 0 | J11: =H11*I11 -> 0 | K11: =G11+J11 -> 0 | L11: 0 | M11: =M10+K11-L11 -> 0
A12: 9 | B12: 46121 | G12: =E12*F12 -> 0 | J12: =H12*I12 -> 0 | K12: =G12+J12 -> 0 | L12: 0 | M12: =M11+K12-L12 -> 0
A13: 10 | B13: 46122 | G13: =E13*F13 -> 0 | J13: =H13*I13 -> 0 | K13: =G13+J13 -> 0 | L13: 0 | M13: =M12+K13-L13 -> 0
A14: 11 | B14: 46123 | G14: =E14*F14 -> 0 | H14: 40 | I14: 108.1 | J14: =H14*I14 -> 4324 | K14: =G14+J14 -> 4324 | L14: 0 | M14: =M13+K14-L14 -> 4324
A15: 12 | B15: 46124 | E15: 720 | F15: 96.3 | G15: =E15*F15 -> 69336 | J15: =H15*I15 -> 0 | K15: =G15+J15 -> 69336 | L15: =H15+K15 -> 69336 | M15: =M14+K15-L15 -> 4324
A16: 13 | B16: 46125 | G16: =E16*F16 -> 0 | J16: =H16*I16 -> 0 | K16: =G16+J16 -> 0 | L16: 0 | M16: =M15+K16-L16 -> 4324
A17: 14 | B17: 46126 | G17: =E17*F17 -> 0 | J17: =H17*I17 -> 0 | K17: =G17+J17 -> 0 | L17: 0 | M17: =M16+K17-L17 -> 4324
A18: 15 | B18: 46127 | G18: =E18*F18 -> 0 | J18: =H18*I18 -> 0 | K18: =G18+J18 -> 0 | L18: 0 | M18: =M17+K18-L18 -> 4324
A19: 16 | B19: 46128 | G19: =E19*F19 -> 0 | J19: =H19*I19 -> 0 | K19: =G19+J19 -> 0 | L19: 0 | M19: =M18+K19-L19 -> 4324
A20: 17 | B20: 46129 | E20: 800 | F20: 96.3 | G20: =E20*F20 -> 77040 | J20: =H20*I20 -> 0 | K20: =G20+J20 -> 77040 | L20: 0 | M20: =M19+K20-L20 -> 81364
A21: 18 | B21: 46130 | E21: 1000 | F21: 96.42 | G21: =E21*F21 -> 96420 | J21: =H21*I21 -> 0 | K21: =G21+J21 -> 96420 | L21: 77040 | M21: =M20+K21-L21 -> 100744
A22: 19 | B22: 46131 | G22: =E22*F22 -> 0 | J22: =H22*I22 -> 0 | K22: =G22+J22 -> 0 | L22: 0 | M22: =M21+K22-L22 -> 100744
A23: 20 | B23: 46132 | G23: =E23*F23 -> 0 | J23: =H23*I23 -> 0 | K23: =G23+J23 -> 0 | L23: 0 | M23: =M22+K23-L23 -> 100744
A24: 21 | B24: 46133 | E24: 0 | F24: 0 | G24: =E24*F24 -> 0 | H24: 0 | I24: 108.23 | J24: =H24*I24 -> 0 | K24: =G24+J24 -> 0 | L24: 0 | M24: =M23+K24-L24 -> 100744
A25: 22 | B25: 46134 | E25: 0 | F25: 0 | G25: =E25*F25 -> 0 | H25: 40 | I25: 108.23 | J25: =H25*I25 -> 4329.2 | K25: =G25+J25 -> 4329.2 | L25: 96000 | M25: =M24+K25-L25 -> 9073.2
A26: 23 | B26: 46135 | E26: 1500 | F26: 96.3 | G26: =E26*F26 -> 144450 | J26: =H26*I26 -> 0 | K26: =G26+J26 -> 144450 | L26: 100000 | M26: =M25+K26-L26 -> 53523.2
A27: 24 | B27: 46136 | G27: =E27*F27 -> 0 | J27: =H27*I27 -> 0 | K27: =G27+J27 -> 0 | L27: 0 | M27: =M26+K27-L27 -> 53523.2
A28: 25 | B28: 46137 | G28: =E28*F28 -> 0 | J28: =H28*I28 -> 0 | K28: =G28+J28 -> 0 | L28: 0 | M28: =M27+K28-L28 -> 53523.2
A29: 26 | B29: 46138 | G29: =E29*F29 -> 0 | J29: =H29*I29 -> 0 | K29: =G29+J29 -> 0 | L29: 0 | M29: =M28+K29-L29 -> 53523.2
A30: 27 | B30: 46139 | G30: =E30*F30 -> 0 | J30: =H30*I30 -> 0 | K30: =G30+J30 -> 0 | L30: 50000 | M30: =M29+K30-L30 -> 3523.2
A31: 28 | B31: 46140 | G31: =E31*F31 -> 0 | J31: =H31*I31 -> 0 | K31: =G31+J31 -> 0 | L31: 0 | M31: =M30+K31-L31 -> 3523.2
A32: 29 | B32: 46141 | G32: =E32*F32 -> 0 | J32: =H32*I32 -> 0 | K32: =G32+J32 -> 0 | L32: 0 | M32: =M31+K32-L32 -> 3523.2
A33: 30 | B33: 46142 | G33: =E33*F33 -> 0 | H33: 0 | I33: 0 | J33: =H33*I33 -> 0 | K33: =G33+J33 -> 0 | L33: 0 | M33: =M32+K33-L33 -> 3523.2
A34: 31 | B34: 46143 | G34: =E34*F34 -> 0 | J34: =H34*I34 -> 0 | K34: =G34+J34 -> 0 | M34: =M33+K34-L34 -> 3523.2
E35: =SUM(E4:E34) -> 4020 | G35: =SUM(G4:G34) -> 387246 | H35: =SUM(H4:H34) -> 80 | J35: =SUM(J4:J34) -> 8653.2 | K35: =SUM(K4:K34) -> 395899.2 | L35: =SUM(L4:L34) -> 402105

Sheet  Sangareeddy-1
A1: Durga Indhan
A2: S.No | B2: Date | C2: GRN No | D2: Ind no/Bill No | E2: Diesel (Lts) | F2: Price | G2: Amount | H2: Petrol (Lts) | I2: Price | J2: Amount | K2: Total amount | L2: Amount paid | M2: As on Date | N2: Remarks
A3: Opening Balance | M3: 71161.048
A4: 1 | B4: 45748 | G4: =E4*F4 -> 0 | J4: =H4*I4 -> 0 | K4: =G4+J4 -> 0 | L4: 0 | M4: =M3+K4-L4 -> 71161.048
A5: 2 | B5: 45749 | G5: =E5*F5 -> 0 | J5: =H5*I5 -> 0 | K5: =G5+J5 -> 0 | L5: 0 | M5: =M4+K5-L5 -> 71161.048
A6: 3 | B6: 45750 | G6: =E6*F6 -> 0 | J6: =H6*I6 -> 0 | K6: =G6+J6 -> 0 | L6: 0 | M6: =M5+K6-L6 -> 71161.048
A7: 4 | B7: 45751 | G7: =E7*F7 -> 0 | J7: =H7*I7 -> 0 | K7: =G7+J7 -> 0 | L7: 0 | M7: =M6+K7-L7 -> 71161.048
A8: 5 | B8: 45752 | G8: =E8*F8 -> 0 | J8: =H8*I8 -> 0 | K8: =G8+J8 -> 0 | L8: 0 | M8: =M7+K8-L8 -> 71161.048
A9: 6 | B9: 45753 | G9: =E9*F9 -> 0 | J9: =H9*I9 -> 0 | K9: =G9+J9 -> 0 | L9: 0 | M9: =M8+K9-L9 -> 71161.048
A10: 7 | B10: 45754 | G10: =E10*F10 -> 0 | J10: =H10*I10 -> 0 | K10: =G10+J10 -> 0 | L10: 0 | M10: =M9+K10-L10 -> 71161.048
A11: 8 | B11: 45755 | G11: =E11*F11 -> 0 | J11: =H11*I11 -> 0 | K11: =G11+J11 -> 0 | L11: 0 | M11: =M10+K11-L11 -> 71161.048
A12: 9 | B12: 45756 | G12: =E12*F12 -> 0 | J12: =H12*I12 -> 0 | K12: =G12+J12 -> 0 | L12: 0 | M12: =M11+K12-L12 -> 71161.048
A13: 10 | B13: 45757 | G13: =E13*F13 -> 0 | J13: =H13*I13 -> 0 | K13: =G13+J13 -> 0 | L13: 0 | M13: =M12+K13-L13 -> 71161.048
A14: 11 | B14: 45758 | G14: =E14*F14 -> 0 | J14: =H14*I14 -> 0 | K14: =G14+J14 -> 0 | L14: 0 | M14: =M13+K14-L14 -> 71161.048
A15: 12 | B15: 45759 | G15: =E15*F15 -> 0 | J15: =H15*I15 -> 0 | K15: =G15+J15 -> 0 | L15: 0 | M15: =M14+K15-L15 -> 71161.048
A16: 13 | B16: 45760 | G16: =E16*F16 -> 0 | J16: =H16*I16 -> 0 | K16: =G16+J16 -> 0 | L16: 0 | M16: =M15+K16-L16 -> 71161.048
A17: 14 | B17: 45761 | G17: =E17*F17 -> 0 | J17: =H17*I17 -> 0 | K17: =G17+J17 -> 0 | M17: =M16+K17-L17 -> 71161.048
A18: 15 | B18: 45762 | G18: =E18*F18 -> 0 | J18: =H18*I18 -> 0 | K18: =G18+J18 -> 0 | L18: =+K18 -> 0 | M18: =M17+K18-L18 -> 71161.048
A19: 16 | B19: 45763 | G19: =E19*F19 -> 0 | J19: =H19*I19 -> 0 | K19: =G19+J19 -> 0 | M19: =M18+K19-L19 -> 71161.048
A20: 17 | B20: 45764 | G20: =E20*F20 -> 0 | J20: =H20*I20 -> 0 | K20: =G20+J20 -> 0 | M20: =M19+K20-L20 -> 71161.048
A21: 18 | B21: 45765 | G21: =E21*F21 -> 0 | J21: =H21*I21 -> 0 | K21: =G21+J21 -> 0 | L21: 69995 | M21: =M20+K21-L21 -> 1166.048
A22: 19 | B22: 45766 | G22: =E22*F22 -> 0 | J22: =H22*I22 -> 0 | K22: =G22+J22 -> 0 | L22: 1166.05 | M22: =M21+K22-L22 -> -0.0019999999
A23: 20 | B23: 45767 | G23: =E23*F23 -> 0 | J23: =H23*I23 -> 0 | K23: =G23+J23 -> 0 | L23: =+K23 -> 0 | M23: =M22+K23-L23 -> -0.0019999999
A24: 21 | B24: 45768 | G24: =E24*F24 -> 0 | J24: =H24*I24 -> 0 | K24: =G24+J24 -> 0 | L24: =+K24 -> 0 | M24: =M23+K24-L24 -> -0.0019999999
A25: 22 | B25: 45769 | G25: =E25*F25 -> 0 | J25: =H25*I25 -> 0 | K25: =G25+J25 -> 0 | L25: =+K25 -> 0 | M25: =M24+K25-L25 -> -0.0019999999
A26: 23 | B26: 45770 | G26: =E26*F26 -> 0 | J26: =H26*I26 -> 0 | K26: =G26+J26 -> 0 | L26: =+K26 -> 0 | M26: 0
A27: 24 | B27: 45771 | G27: =E27*F27 -> 0 | J27: =H27*I27 -> 0 | K27: =G27+J27 -> 0 | L27: =+K27 -> 0 | M27: 0
A28: 25 | B28: 45772 | G28: =E28*F28 -> 0 | J28: =H28*I28 -> 0 | K28: =G28+J28 -> 0 | L28: =+K28 -> 0 | M28: 0
A29: 26 | B29: 45773 | G29: =E29*F29 -> 0 | J29: =H29*I29 -> 0 | K29: =G29+J29 -> 0 | L29: =+K29 -> 0 | M29: 0
A30: 27 | B30: 45774 | G30: =E30*F30 -> 0 | J30: =H30*I30 -> 0 | K30: =G30+J30 -> 0 | L30: =+K30 -> 0 | M30: 0
A31: 28 | B31: 45775 | G31: =E31*F31 -> 0 | J31: =H31*I31 -> 0 | K31: =G31+J31 -> 0 | L31: =+K31 -> 0 | M31: 0
A32: 29 | B32: 45776 | G32: =E32*F32 -> 0 | J32: =H32*I32 -> 0 | K32: =G32+J32 -> 0 | L32: =+K32 -> 0 | M32: 0
A33: 30 | B33: 45777 | G33: =E33*F33 -> 0 | J33: =H33*I33 -> 0 | K33: =G33+J33 -> 0 | L33: =+K33 -> 0 | M33: 0
A34: 31 | G34: =E34*F34 -> 0 | J34: =H34*I34 -> 0 | K34: =G34+J34 -> 0 | L34: =+K34 -> 0 | M34: 0
E35: =SUM(E4:E34) -> 0 | G35: =SUM(G4:G34) -> 0 | H35: =SUM(H4:H34) -> 0 | J35: =SUM(J4:J34) -> 0 | K35: =SUM(K4:K34) -> 0 | L35: =SUM(L4:L34) -> 71161.05

Sheet  Sangareddy-2
A1: Durga Bhavani F/S
A2: S.No | B2: Date | C2: GRN No | D2: Ind no/Bill No | E2: Diesel (Lts) | F2: Price | G2: Amount | H2: Petrol (Lts) | I2: Price | J2: Amount | K2: Total amount | L2: Amount paid | M2: As on Date | N2: Remarks
A3: Opening Balance | M3: 324643.92
A4: 1 | B4: 45748 | E4: 722.24 | F4: 96.44 | G4: =E4*F4 -> 69652.826 | H4: 5 | I4: 108.31 | J4: =H4*I4 -> 541.55 | K4: =G4+J4 -> 70194.376 | L4: 0 | M4: =M3+K4-L4 -> 394838.29
A5: 2 | B5: 45749 | E5: 631.32 | F5: 96.44 | G5: =E5*F5 -> 60884.501 | J5: =H5*I5 -> 0 | K5: =G5+J5 -> 60884.501 | L5: 324644 | M5: =M4+K5-L5 -> 131078.8
A6: 3 | B6: 45750 | E6: 20 | F6: 96.44 | G6: =E6*F6 -> 1928.8 | H6: 66.58 | I6: 108.31 | J6: =H6*I6 -> 7211.2798 | K6: =G6+J6 -> 9140.0798 | M6: =M5+K6-L6 -> 140218.87
A7: 4 | B7: 45751 | E7: 1728.07 | F7: 96.44 | G7: =E7*F7 -> 166655.07 | H7: 20 | I7: 108.31 | J7: =H7*I7 -> 2166.2 | K7: =G7+J7 -> 168821.27 | M7: =M6+K7-L7 -> 309040.15
A8: 5 | B8: 45752 | E8: 1434.96 | F8: 96.44 | G8: =E8*F8 -> 138387.54 | H8: 5 | I8: 108.31 | J8: =H8*I8 -> 541.55 | K8: =G8+J8 -> 138929.09 | M8: =M7+K8-L8 -> 447969.24
A9: 6 | B9: 45753 | E9: 0 | F9: 96.44 | G9: =E9*F9 -> 0 | H9: 0 | I9: 108.31 | J9: =H9*I9 -> 0 | K9: =G9+J9 -> 0 | M9: =M8+K9-L9 -> 447969.24
A10: 7 | B10: 45754 | E10: 859.83 | F10: 96.44 | G10: =E10*F10 -> 82922.005 | H10: 10 | I10: 108.31 | J10: =H10*I10 -> 1083.1 | K10: =G10+J10 -> 84005.105 | L10: 0 | M10: =M9+K10-L10 -> 531974.34
A11: 8 | B11: 45755 | E11: 2122.2 | F11: 96.44 | G11: =E11*F11 -> 204664.97 | H11: 10 | I11: 108.31 | J11: =H11*I11 -> 1083.1 | K11: =G11+J11 -> 205748.07 | L11: 0 | M11: =M10+K11-L11 -> 737722.41
A12: 9 | B12: 45756 | E12: 558.84 | F12: 96.44 | G12: =E12*F12 -> 53894.53 | H12: 5 | I12: 108.31 | J12: =H12*I12 -> 541.55 | K12: =G12+J12 -> 54436.08 | L12: 0 | M12: =M11+K12-L12 -> 792158.49
A13: 10 | B13: 45757 | G13: =E13*F13 -> 0 | H13: 15 | I13: 108.31 | J13: =H13*I13 -> 1624.65 | K13: =G13+J13 -> 1624.65 | L13: 250000 | M13: =M12+K13-L13 -> 543783.14
A14: 11 | B14: 45758 | E14: 89.3 | F14: 96.44 | G14: =E14*F14 -> 8612.092 | J14: =H14*I14 -> 0 | K14: =G14+J14 -> 8612.092 | L14: 0 | M14: =M13+K14-L14 -> 552395.23
A15: 12 | B15: 45759 | E15: 323.44 | F15: 96.44 | G15: =E15*F15 -> 31192.554 | H15: 5 | I15: 108.31 | J15: =H15*I15 -> 541.55 | K15: =G15+J15 -> 31734.104 | L15: 0 | M15: =M14+K15-L15 -> 584129.34
A16: 13 | B16: 45760 | E16: 648.58 | F16: 96.44 | G16: =E16*F16 -> 62549.055 | H16: 5 | I16: 108.31 | J16: =H16*I16 -> 541.55 | K16: =G16+J16 -> 63090.605 | L16: 300000 | M16: =M15+K16-L16 -> 347219.94
A17: 14 | B17: 45761 | E17: 787.9 | F17: 96.44 | G17: =E17*F17 -> 75985.076 | H17: 5 | I17: 108.31 | J17: =H17*I17 -> 541.55 | K17: =G17+J17 -> 76526.626 | L17: 0 | M17: =M16+K17-L17 -> 423746.57
A18: 15 | B18: 45762 | E18: =158.76+165.28+285.88+25 -> 634.92 | F18: 96.44 | G18: =E18*F18 -> 61231.685 | H18: 5 | I18: 108.31 | J18: =H18*I18 -> 541.55 | K18: =G18+J18 -> 61773.235 | L18: 0 | M18: =M17+K18-L18 -> 485519.8
A19: 16 | B19: 45763 | E19: 1185.49 | F19: 96.44 | G19: =E19*F19 -> 114328.66 | H19: 17 | I19: 108.31 | J19: =H19*I19 -> 1841.27 | K19: =G19+J19 -> 116169.93 | M19: =M18+K19-L19 -> 601689.73
A20: 17 | B20: 45764 | E20: 528.15 | F20: 96.44 | G20: =E20*F20 -> 50934.786 | J20: =H20*I20 -> 0 | K20: =G20+J20 -> 50934.786 | M20: =M19+K20-L20 -> 652624.51
A21: 18 | B21: 45765 | E21: =31.57+77.47+200+45+155.56+148.28+160+153.49 -> 971.37 | F21: 96.44 | G21: =E21*F21 -> 93678.923 | J21: =H21*I21 -> 0 | K21: =G21+J21 -> 93678.923 | L21: 300000 | M21: =M20+K21-L21 -> 446303.44
A22: 19 | B22: 45766 | E22: =18.14+66.71+64 -> 148.85 | F22: 96.44 | G22: =E22*F22 -> 14355.094 | H22: =5+51.05 -> 56.05 | I22: 108.31 | J22: =H22*I22 -> 6070.7755 | K22: =G22+J22 -> 20425.87 | L22: 0 | M22: =M21+K22-L22 -> 466729.31
A23: 20 | B23: 45767 | E23: 675.43 | F23: 96.44 | G23: =E23*F23 -> 65138.469 | H23: 10 | I23: 108.31 | J23: =H23*I23 -> 1083.1 | K23: =G23+J23 -> 66221.569 | L23: 0 | M23: =M22+K23-L23 -> 532950.88 | Q23: 96.44
A24: 21 | B24: 45768 | E24: 748.92 | F24: 96.44 | G24: =E24*F24 -> 72225.845 | H24: 15 | I24: 108.31 | J24: =H24*I24 -> 1624.65 | K24: =G24+J24 -> 73850.495 | L24: 227573 | M24: =M23+K24-L24 -> 379228.37
A25: 22 | B25: 45769 | E25: 291.25 | F25: 96.44 | G25: =E25*F25 -> 28088.15 | H25: 5 | I25: 108.31 | J25: =H25*I25 -> 541.55 | K25: =G25+J25 -> 28629.7 | L25: 0 | M25: =M24+K25-L25 -> 407858.07
A26: 23 | B26: 45770 | G26: =E26*F26 -> 0 | H26: 5 | I26: 108.31 | J26: =H26*I26 -> 541.55 | K26: =G26+J26 -> 541.55 | L26: 0 | M26: =M25+K26-L26 -> 408399.62
A27: 24 | B27: 45771 | E27: 1408.13 | F27: 96.44 | G27: =E27*F27 -> 135800.06 | H27: 15 | I27: 108.31 | J27: =H27*I27 -> 1624.65 | K27: =G27+J27 -> 137424.71 | L27: 0 | M27: =M26+K27-L27 -> 545824.33
A28: 25 | B28: 45772 | E28: 585.33 | F28: 96.44 | G28: =E28*F28 -> 56449.225 | H28: 0 | I28: 0 | J28: 0 | K28: =G28+J28 -> 56449.225 | L28: 0 | M28: =M27+K28-L28 -> 602273.55
A29: 26 | B29: 45773 | E29: 0 | F29: 96.44 | G29: =E29*F29 -> 0 | H29: 5 | I29: 108.31 | J29: =H29*I29 -> 541.55 | K29: =G29+J29 -> 541.55 | L29: 0 | M29: =M28+K29-L29 -> 602815.1
A30: 27 | B30: 45774 | E30: 137.78 | F30: 96.44 | G30: =E30*F30 -> 13287.503 | H30: 5 | I30: 108.31 | J30: =H30*I30 -> 541.55 | K30: =G30+J30 -> 13829.053 | L30: 500000 | M30: =M29+K30-L30 -> 116644.16
A31: 28 | B31: 45775 | G31: =E31*F31 -> 0 | J31: =H31*I31 -> 0 | K31: =G31+J31 -> 0 | L31: 0 | M31: =M30+K31-L31 -> 116644.16
A32: 29 | B32: 45776 | G32: =E32*F32 -> 0 | J32: =H32*I32 -> 0 | K32: =G32+J32 -> 0 | L32: 0 | M32: =M31+K32-L32 -> 116644.16
A33: 30 | B33: 45777 | E33: 1446.86 | F33: 96.44 | G33: =E33*F33 -> 139535.18 | H33: 26 | I33: 108.31 | J33: =H33*I33 -> 2816.06 | K33: =G33+J33 -> 142351.24 | L33: 0 | M33: =M32+K33-L33 -> 258995.39
A34: 31 | B34: 45778 | G34: =E34*F34 -> 0 | J34: =H34*I34 -> 0 | K34: =G34+J34 -> 0 | L34: 0 | M34: =M33+K34-L34 -> 258995.39
E35: =SUM(E4:E34) -> 18689.16 | G35: =SUM(G4:G34) -> 1802382.6 | H35: =SUM(H4:H34) -> 315.63 | J35: =SUM(J4:J34) -> 34185.885 | K35: =SUM(K4:K34) -> 1836568.5 | L35: =SUM(L4:L34) -> 1902217

Sheet  Sangareddy-3
A1: SHIVA PARVATHI FILLING STATION SADASHIVPET
A2: S.No | B2: Date | C2: GRN No | D2: Ind no/Bill No | E2: Diesel (Lts) | F2: Price | G2: Amount | H2: Petrol (Lts) | I2: Price | J2: Amount | K2: Total amount | L2: Amount paid | M2: As on Date | N2: Remarks
A3: Opening Balance | M3: 0
A4: 1 | B4: 45748 | G4: =E4*F4 -> 0 | J4: =H4*I4 -> 0 | K4: =G4+J4 -> 0 | L4: 0 | M4: =M3+K4-L4 -> 0
A5: 2 | B5: 45749 | G5: =E5*F5 -> 0 | J5: =H5*I5 -> 0 | K5: =G5+J5 -> 0 | L5: 0 | M5: =M4+K5-L5 -> 0
A6: 3 | B6: 45750 | G6: =E6*F6 -> 0 | J6: =H6*I6 -> 0 | K6: =G6+J6 -> 0 | L6: 0 | M6: =M5+K6-L6 -> 0
A7: 4 | B7: 45751 | G7: =E7*F7 -> 0 | J7: =H7*I7 -> 0 | K7: =G7+J7 -> 0 | L7: 0 | M7: =M6+K7-L7 -> 0
A8: 5 | B8: 45752 | G8: =E8*F8 -> 0 | J8: =H8*I8 -> 0 | K8: =G8+J8 -> 0 | L8: 0 | M8: =M7+K8-L8 -> 0
A9: 6 | B9: 45753 | G9: =E9*F9 -> 0 | J9: =H9*I9 -> 0 | K9: =G9+J9 -> 0 | L9: 0 | M9: =M8+K9-L9 -> 0
A10: 7 | B10: 45754 | G10: =E10*F10 -> 0 | J10: =H10*I10 -> 0 | K10: =G10+J10 -> 0 | L10: 0 | M10: =M9+K10-L10 -> 0
A11: 8 | B11: 45755 | G11: =E11*F11 -> 0 | J11: =H11*I11 -> 0 | K11: =G11+J11 -> 0 | L11: 0 | M11: =M10+K11-L11 -> 0
A12: 9 | B12: 45756 | G12: =E12*F12 -> 0 | J12: =H12*I12 -> 0 | K12: =G12+J12 -> 0 | L12: 0 | M12: =M11+K12-L12 -> 0
A13: 10 | B13: 45757 | E13: 600 | F13: 96.23 | G13: =E13*F13 -> 57738 | J13: =H13*I13 -> 0 | K13: =G13+J13 -> 57738 | L13: 0 | M13: =M12+K13-L13 -> 57738
A14: 11 | B14: 45758 | G14: =E14*F14 -> 0 | J14: =H14*I14 -> 0 | K14: =G14+J14 -> 0 | L14: 0 | M14: =M13+K14-L14 -> 57738
A15: 12 | B15: 45759 | G15: =E15*F15 -> 0 | J15: =H15*I15 -> 0 | K15: =G15+J15 -> 0 | L15: 0 | M15: =M14+K15-L15 -> 57738
A16: 13 | B16: 45760 | G16: =E16*F16 -> 0 | J16: =H16*I16 -> 0 | K16: =G16+J16 -> 0 | L16: 0 | M16: =M15+K16-L16 -> 57738
A17: 14 | B17: 45761 | G17: =E17*F17 -> 0 | J17: =H17*I17 -> 0 | K17: =G17+J17 -> 0 | M17: =M16+K17-L17 -> 57738
A18: 15 | B18: 45762 | E18: 670 | F18: 96.23 | G18: =E18*F18 -> 64474.1 | J18: =H18*I18 -> 0 | K18: =G18+J18 -> 64474.1 | M18: =M17+K18-L18 -> 122212.1
A19: 16 | B19: 45763 | E19: 0 | F19: 96.23 | G19: =E19*F19 -> 0 | J19: =H19*I19 -> 0 | K19: =G19+J19 -> 0 | M19: =M18+K19-L19 -> 122212.1
A20: 17 | B20: 45764 | G20: =E20*F20 -> 0 | J20: =H20*I20 -> 0 | K20: =G20+J20 -> 0 | M20: =M19+K20-L20 -> 122212.1
A21: 18 | B21: 45765 | G21: =E21*F21 -> 0 | J21: =H21*I21 -> 0 | K21: =G21+J21 -> 0 | L21: 0 | M21: =M20+K21-L21 -> 122212.1
A22: 19 | B22: 45766 | G22: =E22*F22 -> 0 | J22: =H22*I22 -> 0 | K22: =G22+J22 -> 0 | L22: =+K22 -> 0 | M22: =M21+K22-L22 -> 122212.1
A23: 20 | B23: 45767 | E23: 0 | F23: 96.23 | G23: =E23*F23 -> 0 | J23: =H23*I23 -> 0 | K23: =G23+J23 -> 0 | L23: 0 | M23: =M22+K23-L23 -> 122212.1
A24: 21 | B24: 45768 | E24: 635 | F24: 96.23 | G24: =E24*F24 -> 61106.05 | J24: =H24*I24 -> 0 | K24: =G24+J24 -> 61106.05 | L24: 0 | M24: =M23+K24-L24 -> 183318.15
A25: 22 | B25: 45769 | E25: 670 | F25: 96.23 | G25: =E25*F25 -> 64474.1 | J25: =H25*I25 -> 0 | K25: =G25+J25 -> 64474.1 | L25: 0 | M25: =M24+K25-L25 -> 247792.25
A26: 23 | B26: 45770 | E26: 635 | F26: 96.23 | G26: =E26*F26 -> 61106.05 | J26: =H26*I26 -> 0 | K26: =G26+J26 -> 61106.05 | L26: 0 | M26: =M25+K26-L26 -> 308898.3
A27: 24 | B27: 45771 | E27: 0 | F27: 96.23 | G27: =E27*F27 -> 0 | J27: =H27*I27 -> 0 | K27: =G27+J27 -> 0 | L27: =+K27 -> 0 | M27: =M26+K27-L27 -> 308898.3
A28: 25 | B28: 45772 | E28: 1235 | F28: 96.23 | G28: =E28*F28 -> 118844.05 | J28: =H28*I28 -> 0 | K28: =G28+J28 -> 118844.05 | L28: 0 | M28: =M27+K28-L28 -> 427742.35
A29: 26 | B29: 45773 | E29: 0 | F29: 96.23 | G29: =E29*F29 -> 0 | J29: =H29*I29 -> 0 | K29: =G29+J29 -> 0 | L29: =+K29 -> 0 | M29: =M28+K29-L29 -> 427742.35
A30: 27 | B30: 45774 | G30: =E30*F30 -> 0 | J30: =H30*I30 -> 0 | K30: =G30+J30 -> 0 | L30: 400000 | M30: =M29+K30-L30 -> 27742.35
A31: 28 | B31: 45775 | G31: =E31*F31 -> 0 | J31: =H31*I31 -> 0 | K31: =G31+J31 -> 0 | L31: =+K31 -> 0 | M31: =M30+K31-L31 -> 27742.35
A32: 29 | B32: 45776 | E32: 721.17 | F32: 96.23 | G32: =E32*F32 -> 69398.189 | J32: =H32*I32 -> 0 | K32: =G32+J32 -> 69398.189 | L32: 0 | M32: =M31+K32-L32 -> 97140.539
A33: 30 | B33: 45777 | E33: 690 | F33: 96.23 | G33: =E33*F33 -> 66398.7 | J33: =H33*I33 -> 0 | K33: =G33+J33 -> 66398.7 | L33: 0 | M33: =M32+K33-L33 -> 163539.24
A34: 31 | G34: =E34*F34 -> 0 | J34: =H34*I34 -> 0 | K34: =G34+J34 -> 0 | L34: =+K34 -> 0 | M34: =M33+K34-L34 -> 163539.24
E35: =SUM(E4:E34) -> 5856.17 | G35: =SUM(G4:G34) -> 563539.24 | H35: =SUM(H4:H34) -> 0 | J35: =SUM(J4:J34) -> 0 | K35: =SUM(K4:K34) -> 563539.24 | L35: =SUM(L4:L34) -> 400000

Sheet  Narayankhed
A2: S.No | B2: Date | C2: GRN No | D2: Ind no/Bill No | E2: Diesel (Lts) | F2: Price | G2: Amount | H2: Petrol (Lts) | I2: Price | J2: Amount | K2: Total amount | L2: Amount paid | M2: As on Date | N2: Remarks
A3: Opening Balance | M3: 0
A4: 1 | B4: 45748 | G4: =E4*F4 -> 0 | J4: =H4*I4 -> 0 | K4: =G4+J4 -> 0 | L4: 0 | M4: =M3+K4-L4 -> 0
A5: 2 | B5: 45749 | G5: =E5*F5 -> 0 | J5: =H5*I5 -> 0 | K5: =G5+J5 -> 0 | L5: 0 | M5: =M4+K5-L5 -> 0
A6: 3 | B6: 45750 | G6: =E6*F6 -> 0 | J6: =H6*I6 -> 0 | K6: =G6+J6 -> 0 | L6: 0 | M6: =M5+K6-L6 -> 0
A7: 4 | B7: 45751 | G7: =E7*F7 -> 0 | J7: =H7*I7 -> 0 | K7: =G7+J7 -> 0 | L7: 0 | M7: =M6+K7-L7 -> 0
A8: 5 | B8: 45752 | G8: =E8*F8 -> 0 | J8: =H8*I8 -> 0 | K8: =G8+J8 -> 0 | L8: 0 | M8: =M7+K8-L8 -> 0
A9: 6 | B9: 45753 | G9: =E9*F9 -> 0 | J9: =H9*I9 -> 0 | K9: =G9+J9 -> 0 | L9: 0 | M9: =M8+K9-L9 -> 0
A10: 7 | B10: 45754 | E10: 200 | F10: 97 | G10: =E10*F10 -> 19400 | J10: =H10*I10 -> 0 | K10: =G10+J10 -> 19400 | L10: 19400 | M10: =M9+K10-L10 -> 0 | N10: BPCL Card
A11: 8 | B11: 45755 | G11: =E11*F11 -> 0 | J11: =H11*I11 -> 0 | K11: =G11+J11 -> 0 | L11: 0 | M11: =M10+K11-L11 -> 0
A12: 9 | B12: 45756 | G12: =E12*F12 -> 0 | J12: =H12*I12 -> 0 | K12: =G12+J12 -> 0 | L12: 0 | M12: =M11+K12-L12 -> 0
A13: 10 | B13: 45757 | G13: =E13*F13 -> 0 | J13: =H13*I13 -> 0 | K13: =G13+J13 -> 0 | L13: 0 | M13: =M12+K13-L13 -> 0
A14: 11 | B14: 45758 | G14: =E14*F14 -> 0 | J14: =H14*I14 -> 0 | K14: =G14+J14 -> 0 | L14: 0 | M14: =M13+K14-L14 -> 0
A15: 12 | B15: 45759 | G15: =E15*F15 -> 0 | J15: =H15*I15 -> 0 | K15: =G15+J15 -> 0 | L15: 0 | M15: =M14+K15-L15 -> 0
A16: 13 | B16: 45760 | G16: =E16*F16 -> 0 | J16: =H16*I16 -> 0 | K16: =G16+J16 -> 0 | L16: 0 | M16: =M15+K16-L16 -> 0
A17: 14 | B17: 45761 | G17: =E17*F17 -> 0 | J17: =H17*I17 -> 0 | K17: =G17+J17 -> 0 | M17: =M16+K17-L17 -> 0
A18: 15 | B18: 45762 | G18: =E18*F18 -> 0 | J18: =H18*I18 -> 0 | K18: =G18+J18 -> 0 | L18: =+K18 -> 0 | M18: =M17+K18-L18 -> 0
A19: 16 | B19: 45763 | G19: =E19*F19 -> 0 | J19: =H19*I19 -> 0 | K19: =G19+J19 -> 0 | M19: =M18+K19-L19 -> 0
A20: 17 | B20: 45764 | G20: =E20*F20 -> 0 | J20: =H20*I20 -> 0 | M20: =M19+K20-L20 -> 0
A21: 18 | B21: 45765 | G21: =E21*F21 -> 0 | J21: =H21*I21 -> 0 | M21: =M20+K21-L21 -> 0
A22: 19 | B22: 45766 | G22: =E22*F22 -> 0 | J22: =H22*I22 -> 0 | M22: =M21+K22-L22 -> 0
A23: 20 | B23: 45767 | G23: =E23*F23 -> 0 | J23: =H23*I23 -> 0 | M23: =M22+K23-L23 -> 0
A24: 21 | B24: 45768 | G24: =E24*F24 -> 0 | J24: =H24*I24 -> 0 | M24: =M23+K24-L24 -> 0
A25: 22 | B25: 45769 | G25: =E25*F25 -> 0 | J25: =H25*I25 -> 0 | K25: =G25+J25 -> 0 | L25: =+K25 -> 0 | M25: =M24+K25-L25 -> 0
A26: 23 | B26: 45770 | G26: =E26*F26 -> 0 | J26: =H26*I26 -> 0 | K26: =G26+J26 -> 0 | L26: =+K26 -> 0 | M26: =M25+K26-L26 -> 0
A27: 24 | B27: 45771 | G27: =E27*F27 -> 0 | J27: =H27*I27 -> 0 | K27: =G27+J27 -> 0 | L27: =+K27 -> 0 | M27: =M26+K27-L27 -> 0
A28: 25 | B28: 45772 | G28: =E28*F28 -> 0 | J28: =H28*I28 -> 0 | K28: =G28+J28 -> 0 | L28: =+K28 -> 0 | M28: =M27+K28-L28 -> 0
A29: 26 | B29: 45773 | G29: =E29*F29 -> 0 | J29: =H29*I29 -> 0 | K29: =G29+J29 -> 0 | L29: =+K29 -> 0 | M29: =M28+K29-L29 -> 0
A30: 27 | B30: 45774 | G30: =E30*F30 -> 0 | J30: =H30*I30 -> 0 | K30: =G30+J30 -> 0 | L30: =+K30 -> 0 | M30: =M29+K30-L30 -> 0
A31: 28 | B31: 45775 | G31: =E31*F31 -> 0 | J31: =H31*I31 -> 0 | K31: =G31+J31 -> 0 | L31: =+K31 -> 0 | M31: =M30+K31-L31 -> 0
A32: 29 | B32: 45776 | E32: 100 | F32: 97 | G32: =E32*F32 -> 9700 | J32: =H32*I32 -> 0 | K32: =G32+J32 -> 9700 | L32: =+K32 -> 9700 | M32: =M31+K32-L32 -> 0 | N32: BPCL Card
A33: 30 | B33: 45777 | G33: =E33*F33 -> 0 | J33: =H33*I33 -> 0 | K33: =G33+J33 -> 0 | L33: =+K33 -> 0 | M33: =M32+K33-L33 -> 0
A34: 31 | G34: =E34*F34 -> 0 | J34: =H34*I34 -> 0 | K34: =G34+J34 -> 0 | L34: =+K34 -> 0 | M34: 0
E35: =SUM(E4:E34) -> 300 | G35: =SUM(G4:G34) -> 29100 | H35: =SUM(H4:H34) -> 0 | J35: =SUM(J4:J34) -> 0 | K35: =SUM(K4:K34) -> 29100 | L35: =SUM(L4:L34) -> 29100

Sheet Dindi
A1: Akarapu Balakistamma Fillling
A2: S.No | B2: Date | C2: GRN No | D2: Ind no/Bill No | E2: Diesel (Lts) | F2: Price | G2: Amount | H2: Petrol (Lts) | I2: Price | J2: Amount | K2: Total amount | L2: Amount paid | M2: As on Date | N2: Remarks
A3: Opening Balance | M3: 0
A4: 1 | B4: 45748 | G4: =E4*F4 -> 0 | H4: 0 | I4: 0 | J4: =H4*I4 -> 0 | K4: =G4+J4 -> 0 | L4: =+K4 -> 0 | M4: 0
A5: 2 | B5: 45749 | G5: =E5*F5 -> 0 | H5: 0 | I5: 0 | J5: =H5*I5 -> 0 | K5: =G5+J5 -> 0 | L5: =+K5 -> 0 | M5: 0
A6: 3 | B6: 45750 | G6: =E6*F6 -> 0 | H6: 0 | I6: 0 | J6: =H6*I6 -> 0 | K6: =G6+J6 -> 0 | L6: =+K6 -> 0 | M6: 0
A7: 4 | B7: 45751 | G7: =E7*F7 -> 0 | H7: 0 | I7: 0 | J7: =H7*I7 -> 0 | K7: =G7+J7 -> 0 | L7: =+K7 -> 0 | M7: 0
A8: 5 | B8: 45752 | G8: =E8*F8 -> 0 | H8: 0 | I8: 0 | J8: =H8*I8 -> 0 | K8: =G8+J8 -> 0 | L8: =+K8 -> 0 | M8: 0
A9: 6 | B9: 45753 | G9: =E9*F9 -> 0 | H9: 0 | I9: 0 | J9: =H9*I9 -> 0 | K9: =G9+J9 -> 0 | L9: =+K9 -> 0 | M9: 0
A10: 7 | B10: 45754 | G10: =E10*F10 -> 0 | H10: 0 | I10: 0 | J10: =H10*I10 -> 0 | K10: =G10+J10 -> 0 | L10: =+K10 -> 0 | M10: 0
A11: 8 | B11: 45755 | G11: =E11*F11 -> 0 | H11: 0 | I11: 0 | J11: =H11*I11 -> 0 | K11: =G11+J11 -> 0 | L11: =+K11 -> 0 | M11: 0
A12: 9 | B12: 45756 | G12: =E12*F12 -> 0 | H12: 0 | I12: 0 | J12: =H12*I12 -> 0 | K12: =G12+J12 -> 0 | L12: =+K12 -> 0 | M12: 0
A13: 10 | B13: 45757 | G13: =E13*F13 -> 0 | H13: 0 | I13: 0 | J13: =H13*I13 -> 0 | K13: =G13+J13 -> 0 | L13: =+K13 -> 0 | M13: 0
A14: 11 | B14: 45758 | G14: =E14*F14 -> 0 | H14: 0 | I14: 0 | J14: =H14*I14 -> 0 | K14: =G14+J14 -> 0 | L14: =+K14 -> 0 | M14: 0
A15: 12 | B15: 45759 | G15: =E15*F15 -> 0 | H15: 0 | I15: 0 | J15: =H15*I15 -> 0 | K15: =G15+J15 -> 0 | L15: =+K15 -> 0 | M15: 0
... A27: 24 | B27: 45771 | G27: =E27*F27 -> 0 | H27: 0 | I27: 0 | J27: =H27*I27 -> 0 | K27: =G27+J27 -> 0 | L27: =+K27 -> 0 | M27: 0
A28: 25 | B28: 45772 | H28: 0 | I28: 0 | J28: =H28*I28 -> 0 | K28: =G28+J28 -> 0 | L28: =+K28 -> 0 | M28: 0
A29: 26 | B29: 45773 | G29: =E29*F29 -> 0 | H29: 0 | I29: 0 | J29: =H29*I29 -> 0 | K29: =G29+J29 -> 0 | L29: =+K29 -> 0 | M29: 0
A30: 27 | B30: 45774 | G30: =E30*F30 -> 0 | H30: 0 | I30: 0 | J30: =H30*I30 -> 0 | K30: =G30+J30 -> 0 | L30: =+K30 -> 0 | M30: 0
A31: 28 | B31: 45775 | G31: =E31*F31 -> 0 | H31: 0 | I31: 0 | J31: =H31*I31 -> 0 | K31: =G31+J31 -> 0 | L31: =+K31 -> 0 | M31: 0
A32: 29 | G32: =E32*F32 -> 0 | H32: 0 | I32: 0 | J32: =H32*I32 -> 0 | K32: =G32+J32 -> 0 | L32: =+K32 -> 0 | M32: 0
A33: 30 | G33: =E33*F33 -> 0 | H33: 0 | I33: 0 | J33: =H33*I33 -> 0 | K33: =G33+J33 -> 0 | L33: =+K33 -> 0 | M33: 0
A34: 31 | G34: =E34*F34 -> 0 | H34: 0 | I34: 0 | J34: =H34*I34 -> 0 | K34: =G34+J34 -> 0 | L34: =+K34 -> 0 | M34: 0
E35: =SUM(E4:E34) -> 0 | G35: =SUM(G4:G34) -> 0 | H35: =SUM(H4:H34) -> 0 | J35: =SUM(J4:J34) -> 0 | K35: =SUM(K4:K34) -> 0 | L35: =SUM(L4:L34) -> 0

Sheet Amalapuram
A2: S.No | B2: Date | C2: GRN No | D2: Ind no/Bill No | E2: Diesel (Lts) | F2: Price | G2: Amount | H2: Petrol (Lts) | I2: Price | J2: Amount | K2: Total amount | L2: Amount paid | M2: As on Date | N2: Remarks
A3: Opening Balance | M3: 0
A4: 1 | B4: 46113 | C4: BP KakinadaBhanugudi Junction | D4: Kakinada | E4: 0 | H4: 15 | I4: 109.94 | J4: 1649.1 | K4: 1649.1 | L4: 1649.1 | M4: =+M3+K4-L4 -> 0 | N4: BPCL
A5: 2 | B5: 46114 | C5: BP Quarry market BPCL | D5: Rajahmundry | E5: 0 | H5: 5 | I5: 108.86 | J5: 544.3 | K5: 544.3 | L5: 544.3 | M5: =+M4+K5-L5 -> 0 | N5: BPCL
A6: 3 | M6: =+M5+K6-L6 -> 0
A7: 4 | M7: =+M6+K7-L7 -> 0
A8: 5 | M8: =+M7+K8-L8 -> 0
A9: 6 | B9: 46118 | C9: BP Lalacheruvu BPCL | D9: Rajahmundry | E9: 47.51 | F9: 96.74 | G9: 4596.12 | H9: 0 | K9: 4596.12 | L9: 4596.12 | M9: =+M8+K9-L9 -> 0 | N9: BPCL
A10: 7 | M10: =+M9+K10-L10 -> 0
A11: 8 | B11: 46120 | C11: BP Lalacheruvu BPCL | D11: Rajahmundry | E11: 108.08 | F11: 96.74 | G11: 10455.66 | H11: 0 | K11: 10455.66 | L11: 10455.66 | M11: =+M10+K11-L11 -> 0 | N11: BPCL
A12: 9 | B12: 46121 | C12: Sri Sathya Datha Aparna Agencies | D12: Chendurthi(Gollaprolu) | E12: 46.04 | F12: 97.28 | G12: 4478.77 | H12: 10 | I12: 109.47 | J12: 1094.7 | K12: 5573.47 | L12: 5573.47 | M12: =+M11+K12-L12 -> 0 | N12: BPCL
A13: 10 | M13: =+M12+K13-L13 -> 0
A14: 11 | B14: 46123 | C14: Sri Balaji Agencies BPCL | D14: Kakinada | E14: 65.89 | F14: 97.71 | G14: 6438.11 | H14: 0 | K14: 6438.11 | L14: 6438.11 | M14: =+M13+K14-L14 -> 0 | N14: BPCL
A15: 12 | B15: 46123 | C15: BP KakinadaBhanugudi Junction | D15: Kakinada | E15: 0 | H15: 15 | I15: 109.94 | J15: 1649.1 | K15: 1649.1 | L15: 1649.1 | M15: =+M14+K15-L15 -> 0 | N15: BPCL
A16: 13 | M16: =+M15+K16-L16 -> 0
A17: 14 | B17: 46125 | C17: BP Lalacheruvu BPCL | D17: Rajahmundry | E17: 78.51 | F17: 96.74 | G17: =E17*F17 -> 7595.0574 | K17: =G17+J17 -> 7595.0574 | L17: =G17+J17 -> 7595.0574 | M17: =+M16+K17-L17 -> 0 | N17: BPCL
A18: 15 | B18: 46125 | C18: SRI BHIMESWARA AGENCIES BHARAT PETROLEUM | D18: AMALAPURAM | E18: 40 | F18: 97.4 | G18: =E18*F18 -> 3896 | K18: =G18+J18 -> 3896 | L18: =G18+J18 -> 3896 | M18: =+M16+K18-L18 -> 0 | N18: BPCL
A19: 16 | B19: 46127 | C19: BP KakinadaBhanugudi Junction | D19: Kakinada | E19: 40.94 | F19: 97.71 | G19: 4000 | H19: 0 | K19: 4000 | L19: 4000 | M19: =+M18+K19-L19 -> 0 | N19: BPCL
A20: 17 | B20: 46128 | C20: Sri Balaji Agencies BPCL | D20: Kakinada | E20: 46.56 | F20: 97.71 | G20: 4549.38 | H20: 5 | I20: 109.94 | J20: 549.7 | K20: 5099.08 | L20: 5099.08 | M20: =+M19+K20-L20 -> 0 | N20: BPCL
A21: 18 | B21: 46129 | C21: Sri Radha Krishna Agencies | D21: Kakinada | E21: 50.4 | F21: 97.81 | G21: 4929.62 | H21: 0 | K21: 4929.62 | L21: 4929.62 | M21: =+M20+K21-L21 -> 0 | N21: IOCL
A22: 19 | B22: 46129 | C22: BP Lalacheruvu BPCL | D22: Rajahmundry | H22: 5 | I22: 108.86 | J22: 544.3 | K22: 544.3 | L22: 544.3 | M22: =+M21+K22-L22 -> 0 | N22: BPCL
A23: 20 | B23: 46130 | C23: Deepthi Filling Center IOCL | D23: Prathipadu | E23: 46.33 | F23: 97.53 | G23: 4518.56 | H23: 0 | K23: 4518.56 | L23: 4518.56 | M23: =+M22+K23-L23 -> 0
A24: 21 | B24: 46130 | C24: Sri Balaji Agencies BPCL | D24: Kakinada | E24: 0 | H24: 5 | I24: 109.94 | J24: 549.7 | K24: 549.7 | L24: 549.7 | M24: =+M23+K24-L24 -> 0
A25: 22 | B25: 46133 | H25: 5 | I25: 109.94 | J25: 549.7 | K25: 549.7 | L25: 549.7 | M25: =+M24+K25-L25 -> 0
A26: 23 | B26: 46134 | C26: Deepthi Filling Center IOCL | D26: Prathipadu | E26: 50 | F26: 97.53 | G26: 4876.5 | H26: 0 | K26: 4876.5 | L26: 4876.5 | M26: =+M25+K26-L26 -> 0 | N26: IOCL
A27: 24 | B27: 46134 | C27: JVVR Filling Station | D27: Pitapuram | E27: 0 | H27: 5 | I27: 109.68 | J27: 548.4 | K27: 548.4 | L27: 548.4 | M27: =+M26+K27-L27 -> 0 | N27: BPCL
A28: 25 | B28: 46135 | C28: Lamu Filling Station | D28: Dubacherla | E28: 46.24 | F28: 97.31 | G28: 4500 | H28: 0 | K28: 4500 | L28: 4500 | M28: =+M27+K28-L28 -> 0
A29: 26 | B29: 46135 | C29: Sri Ramanjaneya Petrol&Diesel BPCL | D29: Vijayawada | E29: 105.98 | F29: 97.11 | G29: 10291.72 | H29: 0 | K29: 10291.72 | L29: 10291.72 | M29: =+M28+K29-L29 -> 0
A30: 27 | B30: 46136 | C30: Sri Venkateswara Enterorises BPCL | D30: Yanam | E30: 57.64 | F30: 86.75 | G30: 5000 | H30: 10 | I30: 96.91 | J30: 969.1 | K30: 5969.1 | L30: 5969.1 | M30: =+M29+K30-L30 -> 0
A31: 28 | B31: 46137 | C31: BP Lalacheruvu BPCL | D31: Rajahmundry | E31: 10.34 | F31: 96.74 | G31: =E31*F31 -> 1000.2916 | H31: 0 | I31: 0 | J31: 0 | K31: 1000.29 | L31: 1000.29 | M31: =+M30+K31-L31 -> 0
A32: 29 | B32: 46137 | C32: BP Lalacheruvu BPCL | D32: Rajahmundry | E32: 0 | H32: 5 | I32: 118.33 | J32: 591.65 | K32: 591.65 | L32: 591.65 | M32: =+M31+K32-L32 -> 0
A33: 30 | B33: 46137 | C33: BP KakinadaBhanugudi Junction | D33: Kakinada | E33: 0 | H33: 5 | I33: 109.94 | J33: 549.7 | K33: 549.7 | L33: 549.7 | M33: =+M32+K33-L33 -> 0
A34: 30 | B34: 46138 | C34: Sri Sai Datta Dhanalakshmi Agencies | D34: Kakinada | E34: 30.72 | F34: 97.67 | G34: =E34*F34 -> 3000.4224 | H34: 0 | K34: 3000 | L34: 3000 | M34: =+M33+K34-L34 -> 0
A35: 31 | B35: 46138 | C35: Block out side | D35: Tuni | E35: 100 | F35: 100 | G35: 10000 | H35: 0 | K35: 10000 | L35: 10000 | M35: =+M34+K35-L35 -> 0
A36: 32 | B36: 46139 | C36: BP Lalacheruvu BPCL | D36: Rajahmundry | E36: 47.79 | F36: 96.74 | G36: 4623.2 | H36: 15 | I36: 108.86 | J36: 1632.9 | K36: 6256.1 | L36: 6256.1 | M36: =+M35+K36-L36 -> 0 | N36: BPCL
A37: 33 | B37: 46139 | C37: Sri Radha Krishna Agencies IOCL | D37: Kakinada | E37: 122.68 | F37: 97.81 | G37: 12000 | H37: 0 | K37: 12000 | L37: 12000 | M37: =+M36+K37-L37 -> 0 | N37: Hand Cash
B38: 46140 | C38: BP Lalacheruvu BPCL | D38: Rajahmundry | E38: 32.28 | F38: 96.74 | G38: 3122.77 | H38: 0 | K38: 3122.77 | L38: 3122.77 | M38: =+M37+K38-L38 -> 0 | N38: BPCL
B39: 46141 | C39: BP Lalacheruvu BPCL | D39: Rajahmundry | E39: 38.32 | F39: 96.74 | G39: 3707.08 | H39: 0 | K39: 3707.08 | L39: 3707.08 | M39: =+M38+K39-L39 -> 0
B40: 46142 | C40: BP Lalacheruvu BPCL | D40: Rajahmundry | E40: 56.57 | F40: 96.74 | G40: 5472.58 | K40: 5472.58 | L40: 5472.58 | M40: =+M39+K40-L40 -> 0
B41: 46142 | C41: BP KakinadaBhanugudi Junction | D41: Kakinada | E41: 0 | H41: 5 | I41: 109.94 | J41: 549.7 | K41: 549.7 | L41: 549.7 | M41: =+M40+K41-L41 -> 0
M42: =+M41+K42-L42 -> 0
M43: =+M42+K43-L43 -> 0
E48: =SUM(E4:E37) -> 1141.65 | G48: =SUM(G4:G37) -> 110749.41 | H48: =SUM(H4:H37) -> 105 | J48: =SUM(J4:J37) -> 11422.35 | K48: =SUM(K4:K37) -> 122171.34 | L48: =SUM(L4:L37) -> 122171.34

Sheet Madana palli
A2: S.No | B2: Date | C2: GRN No | D2: Ind no/Bill No | E2: Diesel (Lts) | F2: Price | G2: Amount | H2: Petrol (Lts) | I2: Price | J2: Amount | K2: Total amount | L2: Amount paid | M2: As on Date | N2: Remarks
A3: Opening Balance | M3: 0
A4: 1 | B4: 46113 | G4: =E4*F4 -> 0 | J4: =H4*I4 -> 0 | K4: =G4+J4 -> 0 | L4: =+K4 -> 0 | M4: 0
A5: 2 | B5: 46114 | G5: =E5*F5 -> 0 | J5: =H5*I5 -> 0 | K5: =G5+J5 -> 0 | L5: =+K5 -> 0 | M5: 0 | N5: IOCL
A6: 3 | B6: 46115 | G6: =E6*F6 -> 0 | J6: =H6*I6 -> 0 | K6: =G6+J6 -> 0 | L6: =+K6 -> 0 | M6: 0
A7: 4 | B7: 46116 | G7: =E7*F7 -> 0 | J7: =H7*I7 -> 0 | K7: =G7+J7 -> 0 | L7: =+K7 -> 0 | M7: 0
A8: 5 | B8: 46117 | G8: =E8*F8 -> 0 | J8: =H8*I8 -> 0 | K8: =G8+J8 -> 0 | L8: =+K8 -> 0 | M8: 0
A9: 6 | B9: 46118 | G9: =E9*F9 -> 0 | J9: =H9*I9 -> 0 | K9: =G9+J9 -> 0 | L9: =+K9 -> 0 | M9: 0 | N9: HPCL
A10: 7 | B10: 46119 | G10: =E10*F10 -> 0 | J10: =H10*I10 -> 0 | K10: =G10+J10 -> 0 | L10: =+K10 -> 0 | M10: 0 | O10: 169.99
A11: 8 | B11: 46120 | G11: =E11*F11 -> 0 | J11: =H11*I11 -> 0 | K11: =G11+J11 -> 0 | L11: =+K11 -> 0 | M11: 0 | O11: 80
A12: 9 | B12: 46121 | G12: =E12*F12 -> 0 | J12: =H12*I12 -> 0 | K12: =G12+J12 -> 0 | L12: =+K12 -> 0 | M12: 0 | O12: =SUM(O10:O11) -> 249.99 | P12: 97.76 | Q12: =O12*P12 -> 24439.022
A13: 10 | B13: 46122 | G13: =E13*F13 -> 0 | J13: =H13*I13 -> 0 | K13: =G13+J13 -> 0 | L13: =+K13 -> 0 | M13: 0
A14: 11 | B14: 46123 | G14: =E14*F14 -> 0 | J14: =H14*I14 -> 0 | K14: =G14+J14 -> 0 | L14: =+K14 -> 0 | M14: 0
A15: 12 | B15: 46124 | G15: =E15*F15 -> 0 | J15: =H15*I15 -> 0 | K15: =G15+J15 -> 0 | L15: =+K15 -> 0 | M15: 0 | P15: 7820.8
A16: 13 | B16: 46125 | G16: =E16*F16 -> 0 | J16: =H16*I16 -> 0 | K16: =G16+J16 -> 0 | L16: =+K16 -> 0 | M16: 0 | P16: 16619.2
A17: 14 | B17: 46126 | G17: =E17*F17 -> 0 | J17: =H17*I17 -> 0 | K17: =G17+J17 -> 0 | L17: =+K17 -> 0 | M17: 0 | P17: =SUM(P15:P16) -> 24440
A18: 15 | B18: 46127 | G18: =E18*F18 -> 0 | J18: =H18*I18 -> 0 | K18: =G18+J18 -> 0 | L18: =+K18 -> 0 | M18: 0
A19: 16 | B19: 46128 | G19: =E19*F19 -> 0 | J19: =H19*I19 -> 0 | K19: =G19+J19 -> 0 | L19: =+K19 -> 0 | M19: 0
A20: 17 | B20: 46129 | G20: =E20*F20 -> 0 | J20: =H20*I20 -> 0 | K20: =G20+J20 -> 0 | L20: =+K20 -> 0 | M20: 0
A21: 18 | B21: 46130 | G21: =E21*F21 -> 0 | J21: =H21*I21 -> 0 | K21: =G21+J21 -> 0 | L21: =+K21 -> 0 | M21: 0
A22: 19 | B22: 46131 | G22: =E22*F22 -> 0 | J22: =H22*I22 -> 0 | K22: =G22+J22 -> 0 | L22: =+K22 -> 0 | M22: 0
A23: 20 | B23: 46132 | G23: =E23*F23 -> 0 | J23: =H23*I23 -> 0 | K23: =G23+J23 -> 0 | L23: =+K23 -> 0 | M23: 0
A24: 21 | B24: 46133 | G24: =E24*F24 -> 0 | J24: =H24*I24 -> 0 | K24: =G24+J24 -> 0 | L24: =+K24 -> 0 | M24: 0
A25: 22 | B25: 46134 | G25: =E25*F25 -> 0 | J25: =H25*I25 -> 0 | K25: =G25+J25 -> 0 | L25: =+K25 -> 0 | M25: 0
A26: 23 | B26: 46135 | G26: =E26*F26 -> 0 | J26: =H26*I26 -> 0 | K26: =G26+J26 -> 0 | L26: =+K26 -> 0 | M26: 0
A27: 24 | B27: 46136 | G27: =E27*F27 -> 0 | J27: =H27*I27 -> 0 | K27: =G27+J27 -> 0 | L27: =+K27 -> 0 | M27: 0
A28: 25 | B28: 46137 | G28: =E28*F28 -> 0 | J28: =H28*I28 -> 0 | K28: =G28+J28 -> 0 | L28: =+K28 -> 0 | M28: 0
B29: 46138 | J29: =H29*I29 -> 0 | K29: =G29+J29 -> 0 | L29: =+K29 -> 0
A30: 26 | B30: 46139 | G30: =E30*F30 -> 0 | J30: =H30*I30 -> 0 | K30: =G30+J30 -> 0 | L30: =+K30 -> 0 | M30: 0
A31: 27 | B31: 46140 | G31: =E31*F31 -> 0 | J31: =H31*I31 -> 0 | K31: =G31+J31 -> 0 | L31: =+K31 -> 0 | M31: 0
A32: 28 | B32: 46141 | G32: =E32*F32 -> 0 | J32: =H32*I32 -> 0 | K32: =G32+J32 -> 0 | L32: =+K32 -> 0 | M32: 0
A33: 29 | B33: 46142 | G33: =E33*F33 -> 0 | J33: =H33*I33 -> 0 | K33: =G33+J33 -> 0 | L33: =+K33 -> 0 | M33: 0
A34: 30 | G34: =E34*F34 -> 0 | J34: =H34*I34 -> 0 | K34: =G34+J34 -> 0 | L34: =+K34 -> 0 | M34: 0
A35: 31 | G35: =E35*F35 -> 0 | J35: =H35*I35 -> 0 | K35: =G35+J35 -> 0 | L35: =+K35 -> 0 | M35: 0
E36: =SUM(E4:E35) -> 0 | G36: =SUM(G4:G35) -> 0 | H36: =SUM(H4:H35) -> 0 | J36: =SUM(J4:J35) -> 0 | K36: =SUM(K4:K35) -> 0 | L36: =SUM(L4:L35) -> 0

Sheet Kadur
A1: Vishal Service Station
A2: S.No | B2: Date | C2: GRN No | D2: Ind No/Bill No | E2: Diesel (Lts) | F2: Price | G2: Amount | H2: Petrol (Lts) | I2: Price | J2: Amount | K2: Total amount | L2: Amount paid | M2: As on Date | N2: Remarks
A3: Opening Balance | K3: 102970.63 | M3: 102970.63 | O3: 207239.43
A4: 1 | B4: 45748 | F4: 0 | G4: =E4*F4 -> 0 | H4: 0 | I4: 0 | J4: =H4*I4 -> 0 | K4: =G4+J4 -> 0 | M4: =M3+K4-L4 -> 102970.63
A5: 2 | B5: 45749 | F5: 0 | G5: =E5*F5 -> 0 | H5: 0 | I5: 0 | J5: =H5*I5 -> 0 | K5: =G5+J5 -> 0 | M5: =M4+K5-L5 -> 102970.63
A6: 3 | B6: 45750 | F6: 0 | G6: =E6*F6 -> 0 | H6: 0 | I6: 0 | J6: =H6*I6 -> 0 | K6: =G6+J6 -> 0 | L6: 102971 | M6: =M5+K6-L6 -> -0.369
A7: 4 | B7: 45751 | F7: 0 | G7: =E7*F7 -> 0 | H7: 0 | I7: 0 | J7: =H7*I7 -> 0 | K7: =G7+J7 -> 0 | M7: =M6+K7-L7 -> -0.369
A8: 5 | B8: 45752 | F8: 0 | G8: =E8*F8 -> 0 | H8: 0 | I8: 0 | J8: =H8*I8 -> 0 | K8: =G8+J8 -> 0 | M8: =M7+K8-L8 -> -0.369
A9: 6 | B9: 45753 | F9: 0 | G9: =E9*F9 -> 0 | H9: 0 | I9: 0 | J9: =H9*I9 -> 0 | K9: =G9+J9 -> 0 | M9: =M8+K9-L9 -> -0.369
A10: 7 | B10: 45754 | F10: 0 | G10: =E10*F10 -> 0 | H10: 0 | I10: 0 | J10: =H10*I10 -> 0 | K10: =G10+J10 -> 0 | M10: =M9+K10-L10 -> -0.369
A11: 8 | B11: 45755 | E11: 1800 | F11: 95.15 | G11: =E11*F11 -> 171270 | H11: 140 | I11: 109.27 | J11: =H11*I11 -> 15297.8 | K11: =G11+J11 -> 186567.8 | M11: =M10+K11-L11 -> 186567.43
A12: 9 | B12: 45756 | F12: 0 | G12: =E12*F12 -> 0 | H12: 0 | I12: 0 | J12: =H12*I12 -> 0 | K12: =G12+J12 -> 0 | M12: =M11+K12-L12 -> 186567.43
A13: 10 | B13: 45757 | F13: 0 | G13: =E13*F13 -> 0 | H13: 0 | I13: 0 | J13: =H13*I13 -> 0 | K13: =G13+J13 -> 0 | M13: =M12+K13-L13 -> 186567.43
A14: 11 | B14: 45758 | F14: 0 | G14: =E14*F14 -> 0 | H14: 0 | I14: 0 | J14: =H14*I14 -> 0 | K14: =G14+J14 -> 0 | M14: =M13+K14-L14 -> 186567.43
A15: 12 | B15: 45759 | F15: 0 | G15: =E15*F15 -> 0 | H15: 0 | I15: 0 | J15: =H15*I15 -> 0 | K15: =G15+J15 -> 0 | M15: =M14+K15-L15 -> 186567.43
A16: 13 | B16: 45760 | F16: 0 | G16: =E16*F16 -> 0 | H16: 0 | I16: 0 | J16: =H16*I16 -> 0 | K16: =G16+J16 -> 0 | M16: =M15+K16-L16 -> 186567.43
A17: 14 | B17: 45761 | F17: 0 | G17: =E17*F17 -> 0 | H17: 0 | I17: 0 | J17: =H17*I17 -> 0 | K17: =G17+J17 -> 0 | M17: =M16+K17-L17 -> 186567.43
A18: 15 | B18: 45762 | F18: 0 | G18: =E18*F18 -> 0 | H18: 0 | I18: 0 | J18: =H18*I18 -> 0 | K18: =G18+J18 -> 0 | M18: =M17+K18-L18 -> 186567.43
A19: 16 | B19: 45763 | F19: 0 | G19: =E19*F19 -> 0 | H19: 0 | I19: 0 | J19: =H19*I19 -> 0 | K19: =G19+J19 -> 0 | M19: =M18+K19-L19 -> 186567.43
A20: 17 | B20: 45764 | F20: 0 | G20: =E20*F20 -> 0 | H20: 0 | I20: 0 | J20: =H20*I20 -> 0 | K20: =G20+J20 -> 0 | M20: =M19+K20-L20 -> 186567.43
A21: 18 | B21: 45765 | F21: 0 | G21: =E21*F21 -> 0 | H21: 0 | I21: 0 | J21: =H21*I21 -> 0 | K21: =G21+J21 -> 0 | M21: =M20+K21-L21 -> 186567.43
A22: 19 | B22: 45766 | F22: 0 | H22: 0 | I22: 0 | J22: =H22*I22 -> 0 | K22: =G22+J22 -> 0 | M22: =M21+K22-L22 -> 186567.43
A23: 20 | B23: 45767 | F23: 0 | H23: 0 | I23: 0 | J23: =H23*I23 -> 0 | K23: =G23+J23 -> 0 | M23: =M22+K23-L23 -> 186567.43
A24: 21 | B24: 45768 | F24: 0 | J24: =H24*I24 -> 0 | K24: =G24+J24 -> 0 | M24: =M23+K24-L24 -> 186567.43
A25: 22 | B25: 45769 | F25: 0 | J25: =H25*I25 -> 0 | K25: =G25+J25 -> 0 | M25: =M24+K25-L25 -> 186567.43
A26: 23 | B26: 45770 | F26: 0 | J26: =H26*I26 -> 0 | K26: =G26+J26 -> 0 | M26: =M25+K26-L26 -> 186567.43
A27: 24 | B27: 45771 | F27: 0 | J27: =H27*I27 -> 0 | K27: =G27+J27 -> 0 | M27: =M26+K27-L27 -> 186567.43
A28: 25 | B28: 45772 | F28: 0 | J28: =H28*I28 -> 0 | K28: =G28+J28 -> 0 | M28: =M27+K28-L28 -> 186567.43
A29: 26 | B29: 45773 | F29: 0 | J29: =H29*I29 -> 0 | K29: =G29+J29 -> 0 | M29: =M28+K29-L29 -> 186567.43
A30: 27 | B30: 45774 | F30: 0 | J30: =H30*I30 -> 0 | K30: =G30+J30 -> 0 | L30: 186567 | M30: =M29+K30-L30 -> 0.431
A31: 28 | B31: 45775 | F31: 0 | J31: =H31*I31 -> 0 | K31: =G31+J31 -> 0 | M31: =M30+K31-L31 -> 0.431
A32: 29 | B32: 45776 | F32: 0 | G32: =E32*F32 -> 0 | H32: 0 | I32: 0 | J32: =H32*I32 -> 0 | K32: =G32+J32 -> 0 | M32: =M31+K32-L32 -> 0.431
A33: 30 | B33: 45777 | F33: 0 | G33: =E33*F33 -> 0 | H33: 0 | I33: 0 | J33: =H33*I33 -> 0 | K33: =G33+J33 -> 0 | M33: =M32+K33-L33 -> 0.431
A34: 31 | F34: 0 | G34: =E34*F34 -> 0 | J34: =H34*I34 -> 0 | K34: =G34+J34 -> 0
E35: =SUM(E4:E34) -> 1800 | G35: =SUM(G4:G34) -> 171270 | H35: =SUM(H4:H34) -> 140 | J35: =SUM(J4:J34) -> 15297.8 | K35: =SUM(K4:K34) -> 186567.8 | L35: =SUM(L4:L31) -> 289538

Sheet YG Gudda-2
A1: Pankaja HP Fuel Center
A2: S.No | B2: Date | C2: GRN No | D2: Ind No/Bill No | E2: Diesel (Lts) | F2: Price | G2: Amount | H2: Petrol (Lts) | I2: Price | J2: Amount | K2: Total amount | L2: Amount paid | M2: As on Date | N2: Remarks
A3: Opening Balance | K3: 250329.91 | M3: 250329.91
A4: 1 | B4: 46113 | G4: =E4*F4 -> 0 | J4: =H4*I4 -> 0 | K4: =G4+J4 -> 0 | M4: =M3+K4-L4 -> 250329.91
A5: 2 | B5: 46114 | E5: 600 | F5: 91.33 | G5: =E5*F5 -> 54798 | H5: 35 | I5: 103.27 | J5: =H5*I5 -> 3614.45 | K5: =G5+J5 -> 58412.45 | L5: 250330 | M5: =M4+K5-L5 -> 58412.36
A6: 3 | B6: 46115 | G6: =E6*F6 -> 0 | J6: =H6*I6 -> 0 | K6: =G6+J6 -> 0 | M6: =M5+K6-L6 -> 58412.36
A7: 4 | B7: 46116 | E7: 1000 | F7: 91.33 | G7: =E7*F7 -> 91330 | J7: =H7*I7 -> 0 | K7: =G7+J7 -> 91330 | M7: =M6+K7-L7 -> 149742.36
A8: 5 | B8: 46117 | G8: =E8*F8 -> 0 | J8: =H8*I8 -> 0 | K8: =G8+J8 -> 0 | M8: =M7+K8-L8 -> 149742.36
A9: 6 | B9: 46118 | G9: =E9*F9 -> 0 | J9: =H9*I9 -> 0 | K9: =G9+J9 -> 0 | M9: =M8+K9-L9 -> 149742.36
A10: 7 | B10: 46119 | G10: =E10*F10 -> 0 | J10: =H10*I10 -> 0 | K10: =G10+J10 -> 0 | M10: =M9+K10-L10 -> 149742.36
A11: 8 | B11: 46120 | G11: =E11*F11 -> 0 | J11: =H11*I11 -> 0 | K11: =G11+J11 -> 0 | M11: =M10+K11-L11 -> 149742.36
A12: 9 | B12: 46121 | E12: 1000 | F12: 91.33 | G12: =E12*F12 -> 91330 | H12: 35 | I12: 103.27 | J12: =H12*I12 -> 3614.45 | K12: =G12+J12 -> 94944.45 | M12: =M11+K12-L12 -> 244686.81
A13: 10 | B13: 46122 | G13: =E13*F13 -> 0 | J13: =H13*I13 -> 0 | K13: =G13+J13 -> 0 | M13: =M12+K13-L13 -> 244686.81
A14: 11 | B14: 46123 | G14: =E14*F14 -> 0 | J14: =H14*I14 -> 0 | K14: =G14+J14 -> 0 | L14: 150000 | M14: =M13+K14-L14 -> 94686.81
A15: 12 | B15: 46124 | G15: =E15*F15 -> 0 | J15: =H15*I15 -> 0 | K15: =G15+J15 -> 0 | M15: =M14+K15-L15 -> 94686.81
A16: 13 | B16: 46125 | G16: =E16*F16 -> 0 | J16: =H16*I16 -> 0 | K16: =G16+J16 -> 0 | M16: =M15+K16-L16 -> 94686.81
A17: 14 | B17: 46126 | E17: 1000 | F17: 91.33 | G17: =E17*F17 -> 91330 | H17: 70 | I17: 103.27 | J17: =H17*I17 -> 7228.9 | K17: =G17+J17 -> 98558.9 | M17: =M16+K17-L17 -> 193245.71
A18: 15 | B18: 46127 | G18: =E18*F18 -> 0 | J18: =H18*I18 -> 0 | K18: =G18+J18 -> 0 | M18: =M17+K18-L18 -> 193245.71
A19: 16 | B19: 46128 | G19: =E19*F19 -> 0 | J19: =H19*I19 -> 0 | K19: =G19+J19 -> 0 | M19: =M18+K19-L19 -> 193245.71
A20: 17 | B20: 46129 | G20: =E20*F20 -> 0 | J20: =H20*I20 -> 0 | K20: =G20+J20 -> 0 | M20: =M19+K20-L20 -> 193245.71
A21: 18 | B21: 46130 | E21: 1000 | F21: 91.33 | G21: =E21*F21 -> 91330 | H21: 35 | I21: 103.27 | J21: =H21*I21 -> 3614.45 | K21: =G21+J21 -> 94944.45 | L21: 150000 | M21: =M20+K21-L21 -> 138190.16
A22: 19 | B22: 46131 | G22: =E22*F22 -> 0 | J22: =H22*I22 -> 0 | K22: =G22+J22 -> 0 | M22: =M21+K22-L22 -> 138190.16
A23: 20 | B23: 46132 | G23: =E23*F23 -> 0 | J23: =H23*I23 -> 0 | K23: =G23+J23 -> 0 | M23: =M22+K23-L23 -> 138190.16
A24: 21 | B24: 46133 | G24: =E24*F24 -> 0 | J24: =H24*I24 -> 0 | K24: =G24+J24 -> 0 | M24: =M23+K24-L24 -> 138190.16
A25: 22 | B25: 46134 | E25: 600 | F25: 91.33 | G25: =E25*F25 -> 54798 | H25: 35 | I25: 103.27 | J25: =H25*I25 -> 3614.45 | K25: =G25+J25 -> 58412.45 | M25: =M24+K25-L25 -> 196602.61
A26: 23 | B26: 46135 | G26: =E26*F26 -> 0 | J26: =H26*I26 -> 0 | K26: =G26+J26 -> 0 | M26: =M25+K26-L26 -> 196602.61
A27: 24 | B27: 46136 | G27: =E27*F27 -> 0 | J27: =H27*I27 -> 0 | K27: =G27+J27 -> 0 | M27: =M26+K27-L27 -> 196602.61
A28: 25 | B28: 46137 | E28: 1000 | F28: 91.33 | G28: =E28*F28 -> 91330 | H28: 70 | I28: 103.27 | J28: =H28*I28 -> 7228.9 | K28: =G28+J28 -> 98558.9 | L28: 196000 | M28: =M27+K28-L28 -> 99161.51
A29: 26 | B29: 46138 | G29: =E29*F29 -> 0 | J29: =H29*I29 -> 0 | K29: =G29+J29 -> 0 | M29: =M28+K29-L29 -> 99161.51
A30: 27 | B30: 46139 | E30: 1000 | F30: 91.33 | G30: =E30*F30 -> 91330 | H30: 35 | I30: 103.27 | J30: =H30*I30 -> 3614.45 | K30: =G30+J30 -> 94944.45 | M30: =M29+K30-L30 -> 194105.96
A31: 28 | B31: 46140 | G31: =E31*F31 -> 0 | J31: =H31*I31 -> 0 | K31: =G31+J31 -> 0 | M31: =M30+K31-L31 -> 194105.96
A32: 29 | B32: 46141 | G32: =E32*F32 -> 0 | J32: =H32*I32 -> 0 | K32: =G32+J32 -> 0 | M32: =M31+K32-L32 -> 194105.96
A33: 30 | B33: 46142 | G33: =E33*F33 -> 0 | J33: =H33*I33 -> 0 | K33: =G33+J33 -> 0 | M33: =M32+K33-L33 -> 194105.96
A34: 31 | G34: =E34*F34 -> 0 | J34: =H34*I34 -> 0 | K34: =G34+J34 -> 0 | M34: =M33+K34-L34 -> 194105.96
A35: 32 | G35: =E35*F35 -> 0 | J35: =H35*I35 -> 0 | K35: =G35+J35 -> 0 | M35: =M34+K35-L35 -> 194105.96
A36: 33 | G36: =E36*F36 -> 0 | H36: 0 | I36: 0 | J36: =H36*I36 -> 0 | K36: =G36+J36 -> 0 | M36: =M35+K36-L36 -> 194105.96
E37: =SUM(E4:E36) -> 7200 | G37: =SUM(G4:G36) -> 657576 | H37: =SUM(H4:H36) -> 315 | J37: =SUM(J4:J36) -> 32530.05 | K37: =SUM(K4:K36) -> 690106.05 | L37: =SUM(L4:L36) -> 746330

Sheet Hosadurga -2
A1: Shree Veeraprathap Fuel
A2: S.No | B2: Date | C2: GRN No | D2: Ind No/Bill No | E2: Diesel (Lts) | F2: Price | G2: Amount | H2: Petrol (Lts) | I2: Price | J2: Amount | K2: Total amount | L2: Amount paid | M2: As on Date | N2: Remarks
A3: Opening Balance | K3: 198796.97 | M3: 198796.97
A4: 1 | B4: 46113 | C4: 0 | G4: =E4*F4 -> 0 | J4: =H4*I4 -> 0 | K4: =G4+J4 -> 0 | M4: =M3+K4-L4 -> 198796.97
A5: 2 | B5: 46114 | C5: 0 | E5: 2000 | F5: 91.55 | G5: =E5*F5 -> 183100 | H5: 35 | I5: 103.73 | J5: =H5*I5 -> 3630.55 | K5: =G5+J5 -> 186730.55 | L5: 198797 | M5: =M4+K5-L5 -> 186730.52
A6: 3 | B6: 46115 | C6: 0 | G6: =E6*F6 -> 0 | J6: =H6*I6 -> 0 | K6: =G6+J6 -> 0 | M6: =M5+K6-L6 -> 186730.52
A7: 4 | B7: 46116 | C7: 0 | G7: =E7*F7 -> 0 | J7: =H7*I7 -> 0 | K7: =G7+J7 -> 0 | M7: =M6+K7-L7 -> 186730.52
A8: 5 | B8: 46117 | C8: 0 | G8: =E8*F8 -> 0 | J8: =H8*I8 -> 0 | K8: =G8+J8 -> 0 | M8: =M7+K8-L8 -> 186730.52
A9: 6 | B9: 46118 | C9: 0 | G9: =E9*F9 -> 0 | J9: =H9*I9 -> 0 | K9: =G9+J9 -> 0 | M9: =M8+K9-L9 -> 186730.52
A10: 7 | B10: 46119 | C10: 0 | G10: =E10*F10 -> 0 | J10: =H10*I10 -> 0 | K10: =G10+J10 -> 0 | M10: =M9+K10-L10 -> 186730.52
A11: 8 | B11: 46120 | C11: 0 | E11: 1999.13 | F11: 91.55 | G11: =E11*F11 -> 183020.35 | H11: 70 | I11: 103.73 | J11: =H11*I11 -> 7261.1 | K11: =G11+J11 -> 190281.45 | L11: 186000 | M11: =M10+K11-L11 -> 191011.98
A12: 9 | B12: 46121 | C12: 0 | G12: =E12*F12 -> 0 | J12: =H12*I12 -> 0 | K12: =G12+J12 -> 0 | M12: =M11+K12-L12 -> 191011.98
A13: 10 | B13: 46122 | C13: 0 | G13: =E13*F13 -> 0 | J13: =H13*I13 -> 0 | K13: =G13+J13 -> 0 | M13: =M12+K13-L13 -> 191011.98
A14: 11 | B14: 46123 | C14: 0 | G14: =E14*F14 -> 0 | J14: =H14*I14 -> 0 | K14: =G14+J14 -> 0 | M14: =M13+K14-L14 -> 191011.98
A15: 12 | B15: 46124 | C15: 0 | G15: =E15*F15 -> 0 | J15: =H15*I15 -> 0 | K15: =G15+J15 -> 0 | M15: =M14+K15-L15 -> 191011.98
A16: 13 | B16: 46125 | C16: 0 | G16: =E16*F16 -> 0 | J16: =H16*I16 -> 0 | K16: =G16+J16 -> 0 | M16: =M15+K16-L16 -> 191011.98
A17: 14 | B17: 46126 | C17: 0 | G17: =E17*F17 -> 0 | J17: =H17*I17 -> 0 | K17: =G17+J17 -> 0 | M17: =M16+K17-L17 -> 191011.98
A18: 15 | B18: 46127 | C18: 0 | G18: =E18*F18 -> 0 | J18: =H18*I18 -> 0 | K18: =G18+J18 -> 0 | M18: =M17+K18-L18 -> 191011.98
A19: 16 | B19: 46128 | C19: 0 | G19: =E19*F19 -> 0 | J19: =H19*I19 -> 0 | K19: =G19+J19 -> 0 | M19: =M18+K19-L19 -> 191011.98
A20: 17 | B20: 46129 | C20: 0 | G20: =E20*F20 -> 0 | J20: =H20*I20 -> 0 | K20: =G20+J20 -> 0 | M20: =M19+K20-L20 -> 191011.98
A21: 18 | B21: 46130 | C21: 0 | G21: =E21*F21 -> 0 | J21: =H21*I21 -> 0 | K21: =G21+J21 -> 0 | M21: =M20+K21-L21 -> 191011.98
A22: 19 | B22: 46131 | C22: 0 | G22: =E22*F22 -> 0 | J22: =H22*I22 -> 0 | K22: =G22+J22 -> 0 | M22: =M21+K22-L22 -> 191011.98
A23: 20 | B23: 46132 | C23: 0 | G23: =E23*F23 -> 0 | J23: =H23*I23 -> 0 | K23: =G23+J23 -> 0 | M23: =M22+K23-L23 -> 191011.98
... A29: 26 | B29: 46138 | C29: 0 | G29: =E29*F29 -> 0 | J29: =H29*I29 -> 0 | K29: =G29+J29 -> 0 | M29: =M28+K29-L29 -> 191011.98
A30: 27 | B30: 46139 | C30: 0 | E30: 1000 | F30: 91.39 | G30: =E30*F30 -> 91390 | H30: 70 | I30: 103.46 | J30: =H30*I30 -> 7242.2 | K30: =G30+J30 -> 98632.2 | L30: 191000 | M30: =M29+K30-L30 -> 98644.176
A31: 28 | B31: 46140 | C31: 0 | G31: =E31*F31 -> 0 | J31: =H31*I31 -> 0 | K31: =G31+J31 -> 0 | M31: =M30+K31-L31 -> 98644.176
A32: 29 | B32: 46141 | C32: 0 | E32: 1600 | F32: 91.39 | G32: =E32*F32 -> 146224 | H32: 35 | I32: 103.46 | J32: =H32*I32 -> 3621.1 | K32: =G32+J32 -> 149845.1 | M32: =M31+K32-L32 -> 248489.28
A33: 30 | B33: 46142 | C33: 0 | G33: =E33*F33 -> 0 | J33: =H33*I33 -> 0 | K33: =G33+J33 -> 0 | M33: =M32+K33-L33 -> 248489.28
A34: 31
E35: =SUM(E4:E34) -> 6599.13 | G35: =SUM(G4:G34) -> 603734.35 | H35: =SUM(H4:H34) -> 210 | J35: =SUM(J4:J34) -> 21754.95 | K35: =SUM(K4:K34) -> 625489.3 | L35: =SUM(L4:L34) -> 575797

Sheet Hiriyur(VJNL)
A1: Sri Balaji Agencies
A2: S.No | B2: Date | C2: GRN No | D2: Ind No/Bill No | E2: Diesel (Lts) | F2: Price | G2: Amount | H2: Petrol (Lts) | I2: Price | J2: Amount | K2: Total amount | L2: Amount paid | M2: As on Date | N2: Remarks
A3: Opening Balance | K3: 69.8 | M3: 69.8
A4: 1 | B4: 46113 | E4: 2500 | F4: 92.1 | G4: =E4*F4 -> 230250 | J4: =H4*I4 -> 0 | K4: =G4+J4 -> 230250 | M4: =M3+K4-L4 -> 230319.8
A5: 2 | B5: 46114 | G5: =E5*F5 -> 0 | J5: =H5*I5 -> 0 | K5: =G5+J5 -> 0 | M5: =M4+K5-L5 -> 230319.8
A6: 3 | B6: 46115 | G6: =E6*F6 -> 0 | J6: =H6*I6 -> 0 | K6: =G6+J6 -> 0 | M6: =M5+K6-L6 -> 230319.8
A7: 4 | B7: 46116 | G7: =E7*F7 -> 0 | J7: =H7*I7 -> 0 | K7: =G7+J7 -> 0 | M7: =M6+K7-L7 -> 230319.8
A8: 5 | B8: 46117 | G8: =E8*F8 -> 0 | J8: =H8*I8 -> 0 | K8: =G8+J8 -> 0 | M8: =M7+K8-L8 -> 230319.8
A9: 6 | B9: 46118 | G9: =E9*F9 -> 0 | J9: =H9*I9 -> 0 | K9: =G9+J9 -> 0 | M9: =M8+K9-L9 -> 230319.8
A10: 7 | B10: 46119 | G10: =E10*F10 -> 0 | J10: =H10*I10 -> 0 | K10: =G10+J10 -> 0 | M10: =M9+K10-L10 -> 230319.8
A11: 8 | B11: 46120 | G11: =E11*F11 -> 0 | H11: 70 | I11: 103.86 | J11: =H11*I11 -> 7270.2 | K11: =G11+J11 -> 7270.2 | M11: =M10+K11-L11 -> 237590
A12: 9 | B12: 46121 | G12: =E12*F12 -> 0 | J12: =H12*I12 -> 0 | K12: =G12+J12 -> 0 | M12: =M11+K12-L12 -> 237590
A13: 10 | B13: 46122 | G13: =E13*F13 -> 0 | J13: =H13*I13 -> 0 | K13: =G13+J13 -> 0 | M13: =M12+K13-L13 -> 237590
A14: 11 | B14: 46123 | G14: =E14*F14 -> 0 | J14: =H14*I14 -> 0 | K14: =G14+J14 -> 0 | M14: =M13+K14-L14 -> 237590
A15: 12 | B15: 46124 | G15: =E15*F15 -> 0 | J15: =H15*I15 -> 0 | K15: =G15+J15 -> 0 | M15: =M14+K15-L15 -> 237590
A16: 13 | B16: 46125 | G16: =E16*F16 -> 0 | J16: =H16*I16 -> 0 | K16: =G16+J16 -> 0 | M16: =M15+K16-L16 -> 237590
A17: 14 | B17: 46126 | G17: =E17*F17 -> 0 | J17: =H17*I17 -> 0 | K17: =G17+J17 -> 0 | M17: =M16+K17-L17 -> 237590
A18: 15 | B18: 46127 | G18: =E18*F18 -> 0 | J18: =H18*I18 -> 0 | K18: =G18+J18 -> 0 | M18: =M17+K18-L18 -> 237590
A19: 16 | B19: 46128 | G19: =E19*F19 -> 0 | J19: =H19*I19 -> 0 | K19: =G19+J19 -> 0 | M19: =M18+K19-L19 -> 237590
A20: 17 | B20: 46129 | G20: =E20*F20 -> 0 | J20: =H20*I20 -> 0 | K20: =G20+J20 -> 0 | M20: =M19+K20-L20 -> 237590
A21: 18 | B21: 46130 | E21: 1000 | F21: 92.1 | G21: =E21*F21 -> 92100 | H21: 70 | I21: 103.86 | J21: =H21*I21 -> 7270.2 | K21: =G21+J21 -> 99370.2 | M21: =M20+K21-L21 -> 336960.2
A22: 19 | B22: 46131 | G22: =E22*F22 -> 0 | J22: =H22*I22 -> 0 | K22: =G22+J22 -> 0 | L22: 200000 | M22: =M21+K22-L22 -> 136960.2
A23: 20 | B23: 46132 | G23: =E23*F23 -> 0 | J23: =H23*I23 -> 0 | K23: =G23+J23 -> 0 | M23: =M22+K23-L23 -> 136960.2
A24: 21 | B24: 46133 | G24: =E24*F24 -> 0 | J24: =H24*I24 -> 0 | K24: =G24+J24 -> 0 | M24: =M23+K24-L24 -> 136960.2
A25: 22 | B25: 46134 | G25: =E25*F25 -> 0 | J25: =H25*I25 -> 0 | K25: =G25+J25 -> 0 | M25: =M24+K25-L25 -> 136960.2
A26: 23 | B26: 46135 | G26: =E26*F26 -> 0 | J26: =H26*I26 -> 0 | K26: =G26+J26 -> 0 | M26: =M25+K26-L26 -> 136960.2
A27: 24 | B27: 46136 | G27: =E27*F27 -> 0 | J27: =H27*I27 -> 0 | K27: =G27+J27 -> 0 | M27: =M26+K27-L27 -> 136960.2
A28: 25 | B28: 46137 | G28: =E28*F28 -> 0 | J28: =H28*I28 -> 0 | K28: =G28+J28 -> 0 | M28: =M27+K28-L28 -> 136960.2
A29: 26 | B29: 46138 | G29: =E29*F29 -> 0 | J29: =H29*I29 -> 0 | K29: =G29+J29 -> 0 | M29: =M28+K29-L29 -> 136960.2
A30: 27 | B30: 46139 | E30: 1500 | F30: 92.1 | G30: =E30*F30 -> 138150 | H30: 35 | I30: 103.86 | J30: =H30*I30 -> 3635.1 | K30: =G30+J30 -> 141785.1 | M30: =M29+K30-L30 -> 278745.3
A31: 28 | B31: 46140 | G31: =E31*F31 -> 0 | J31: =H31*I31 -> 0 | K31: =G31+J31 -> 0 | M31: =M30+K31-L31 -> 278745.3
A32: 29 | B32: 46141 | G32: =E32*F32 -> 0 | J32: =H32*I32 -> 0 | K32: =G32+J32 -> 0 | M32: =M31+K32-L32 -> 278745.3
A33: 30 | B33: 46142 | G33: =E33*F33 -> 0 | J33: =H33*I33 -> 0 | K33: =G33+J33 -> 0 | M33: =M32+K33-L33 -> 278745.3
A34: 31 | G34: =E34*F34 -> 0 | J34: =H34*I34 -> 0 | K34: =G34+J34 -> 0 | M34: =M33+K34-L34 -> 278745.3
E35: =SUM(E4:E34) -> 5000 | G35: =SUM(G4:G34) -> 460500 | H35: =SUM(H4:H34) -> 175 | J35: =SUM(J4:J34) -> 18175.5 | K35: =SUM(K4:K34) -> 478675.5 | L35: =SUM(L4:L34) -> 200000

Sheet Malebenur(KUWSDB)
A1: Sree Veerabhadreshwara Service Station
A2: S.No | B2: Date | C2: GRN No | D2: Ind No/Bill No | E2: Diesel (Lts) | F2: Price | G2: Amount | H2: Petrol (Lts) | I2: Price | J2: Amount | K2: Total amount | L2: Amount paid | M2: As on Date | N2: Remarks
A3: Opening Balance | K3: 79478.01 | M3: =+K3 -> 79478.01 | O3: 46138.764
A4: 1 | B4: 45748 | E4: 0 | F4: 0 | G4: =E4*F4 -> 0 | H4: 0 | I4: 0 | J4: =H4*I4 -> 0 | K4: =G4+J4 -> 0 | L4: 0 | M4: =M3+K4-L4 -> 79478.01
A5: 2 | B5: 45749 | E5: 0 | F5: 0 | G5: =E5*F5 -> 0 | H5: 0 | I5: 0 | J5: =H5*I5 -> 0 | K5: =G5+J5 -> 0 | L5: 79161 | M5: =M4+K5-L5 -> 317.0097
A6: 3 | B6: 45750 | E6: 0 | F6: 0 | G6: =E6*F6 -> 0 | H6: 0 | I6: 0 | J6: =H6*I6 -> 0 | K6: =G6+J6 -> 0 | L6: 0 | M6: =M5+K6-L6 -> 317.0097
A7: 4 | B7: 45751 | E7: 0 | F7: 0 | G7: =E7*F7 -> 0 | H7: 0 | I7: 0 | J7: =H7*I7 -> 0 | K7: =G7+J7 -> 0 | L7: 0 | M7: =M6+K7-L7 -> 317.0097
A8: 5 | B8: 45752 | E8: 0 | F8: 0 | G8: =E8*F8 -> 0 | H8: 0 | I8: 0 | J8: =H8*I8 -> 0 | K8: =G8+J8 -> 0 | L8: 0 | M8: =M7+K8-L8 -> 317.0097
A9: 6 | B9: 45753 | E9: 600 | F9: 92.01 | G9: =E9*F9 -> 55206 | H9: 35 | I9: 103.76 | J9: =H9*I9 -> 3631.6 | K9: =G9+J9 -> 58837.6 | L9: 0 | M9: =M8+K9-L9 -> 59154.61
A10: 7 | B10: 45754 | E10: 0 | F10: 0 | G10: =E10*F10 -> 0 | H10: 0 | I10: 0 | J10: =H10*I10 -> 0 | K10: =G10+J10 -> 0 | L10: 0 | M10: =M9+K10-L10 -> 59154.61
A11: 8 | B11: 45755 | E11: 0 | F11: 0 | G11: =E11*F11 -> 0 | H11: 0 | I11: 0 | J11: =H11*I11 -> 0 | K11: =G11+J11 -> 0 | L11: 0 | M11: =M10+K11-L11 -> 59154.61
A12: 9 | B12: 45756 | E12: 0 | F12: 0 | G12: =E12*F12 -> 0 | H12: 0 | I12: 0 | J12: =H12*I12 -> 0 | K12: =G12+J12 -> 0 | L12: 0 | M12: =M11+K12-L12 -> 59154.61
A13: 10 | B13: 45757 | E13: 0 | F13: 0 | G13: =E13*F13 -> 0 | H13: 0 | I13: 0 | J13: =H13*I13 -> 0 | K13: =G13+J13 -> 0 | L13: 0 | M13: =M12+K13-L13 -> 59154.61
A14: 11 | B14: 45758 | E14: 0 | F14: 0 | G14: =E14*F14 -> 0 | H14: 35 | I14: 103.76 | J14: =H14*I14 -> 3631.6 | K14: =G14+J14 -> 3631.6 | L14: 0 | M14: =M13+K14-L14 -> 62786.21
A15: 12 | B15: 45759 | E15: 0 | F15: 0 | G15: =E15*F15 -> 0 | H15: 0 | I15: 0 | J15: =H15*I15 -> 0 | K15: =G15+J15 -> 0 | L15: 0 | M15: =M14+K15-L15 -> 62786.21
... A34: 31 | B34: 45778 | E34: 0 | F34: 0 | G34: =E34*F34 -> 0 | H34: 0 | I34: 0 | J34: =H34*I34 -> 0 | K34: =G34+J34 -> 0 | L34: 0 | M34: =M33+K34-L34 -> 193649.21
E35: 0 | F35: 0 | G35: =E35*F35 -> 0 | H35: 0 | I35: 0 | J35: =H35*I35 -> 0 | K35: =G35+J35 -> 0 | L35: 0 | M35: =M34+K35-L35 -> 193649.21
E36: 0 | F36: 0 | G36: =E36*F36 -> 0 | H36: 0 | I36: 0 | J36: =H36*I36 -> 0 | K36: =G36+J36 -> 0 | L36: 0 | M36: =M35+K36-L36 -> 193649.21
E37: =SUM(E4:E35) -> 3600 | G37: =SUM(G4:G35) -> 331236 | H37: =SUM(H4:H35) -> 195 | J37: =SUM(J4:J35) -> 20233.2 | K37: =SUM(K4:K35) -> 351469.2 | L37: =SUM(L4:L35) -> 237298
E38: 0 | G38: 0 | H38: 0 | J38: 0 | K38: =G38+J38 -> 0 | L38: 0
S43: 9052944708

Sheet Molakamuru
A1: Molakamuru
A2: S.No | B2: Date | C2: GRN No | D2: Ind No/Bill No | E2: Diesel (Lts) | F2: Price | G2: Amount | H2: Petrol (Lts) | I2: Price | J2: Amount | K2: Total amount | L2: Amount paid | M2: As on Date | N2: Remarks
A3: Opening Balance | K3: 4179.7152 | L3: 0 | M3: 4179.7152
A4: 1 | B4: 46113 | E4: 400 | F4: 92.06 | G4: =E4*F4 -> 36824 | H4: 20 | I4: 103.81 | J4: =H4*I4 -> 2076.2 | K4: =G4+J4 -> 38900.2 | M4: =M3+K4-L4 -> 43079.915
A5: 2 | B5: 46114 | G5: =E5*F5 -> 0 | J5: =H5*I5 -> 0 | K5: =G5+J5 -> 0 | L5: 4162 | M5: =M4+K5-L5 -> 38917.915
A6: 3 | B6: 46115 | G6: =E6*F6 -> 0 | J6: =H6*I6 -> 0 | K6: =G6+J6 -> 0 | M6: =M5+K6-L6 -> 38917.915
A7: 4 | B7: 46116 | G7: =E7*F7 -> 0 | H7: 20 | I7: 103.81 | J7: =H7*I7 -> 2076.2 | K7: =G7+J7 -> 2076.2 | M7: =M6+K7-L7 -> 40994.115
A8: 5 | B8: 46117 | G8: =E8*F8 -> 0 | J8: =H8*I8 -> 0 | K8: =G8+J8 -> 0 | M8: =M7+K8-L8 -> 40994.115
A9: 6 | B9: 46118 | G9: =E9*F9 -> 0 | J9: =H9*I9 -> 0 | K9: =G9+J9 -> 0 | M9: =M8+K9-L9 -> 40994.115
A10: 7 | B10: 46119 | G10: =E10*F10 -> 0 | J10: =H10*I10 -> 0 | K10: =G10+J10 -> 0 | M10: =M9+K10-L10 -> 40994.115
A11: 8 | B11: 46120 | G11: =E11*F11 -> 0 | J11: =H11*I11 -> 0 | K11: =G11+J11 -> 0 | M11: =M10+K11-L11 -> 40994.115
A12: 9 | B12: 46121 | G12: =E12*F12 -> 0 | J12: =H12*I12 -> 0 | K12: =G12+J12 -> 0 | M12: =M11+K12-L12 -> 40994.115
A13: 10 | B13: 46122 | G13: =E13*F13 -> 0 | J13: =H13*I13 -> 0 | K13: =G13+J13 -> 0 | M13: =M12+K13-L13 -> 40994.115
A14: 11 | B14: 46123 | E14: 300 | F14: 92.06 | G14: =E14*F14 -> 27618 | J14: =H14*I14 -> 0 | K14: =G14+J14 -> 27618 | M14: =M13+K14-L14 -> 68612.115
A15: 12 | B15: 46124 | G15: =E15*F15 -> 0 | J15: =H15*I15 -> 0 | K15: =G15+J15 -> 0 | M15: =M14+K15-L15 -> 68612.115
A16: 13 | B16: 46125 | G16: =E16*F16 -> 0 | J16: =H16*I16 -> 0 | K16: =G16+J16 -> 0 | L16: 68594.4 | M16: =M15+K16-L16 -> 17.7152
A17: 14 | B17: 46126 | G17: =E17*F17 -> 0 | J17: =H17*I17 -> 0 | K17: =G17+J17 -> 0 | M17: =M16+K17-L17 -> 17.7152
A18: 15 | B18: 46127 | G18: =E18*F18 -> 0 | J18: =H18*I18 -> 0 | K18: =G18+J18 -> 0 | M18: =M17+K18-L18 -> 17.7152
A19: 16 | B19: 46128 | G19: =E19*F19 -> 0 | J19: =H19*I19 -> 0 | K19: =G19+J19 -> 0 | M19: =M18+K19-L19 -> 17.7152
A20: 17 | B20: 46129 | G20: =E20*F20 -> 0 | J20: =H20*I20 -> 0 | K20: =G20+J20 -> 0 | M20: =M19+K20-L20 -> 17.7152
A21: 18 | B21: 46130 | G21: =E21*F21 -> 0 | J21: =H21*I21 -> 0 | K21: =G21+J21 -> 0 | M21: =M20+K21-L21 -> 17.7152
A22: 19 | B22: 46131 | G22: =E22*F22 -> 0 | J22: =H22*I22 -> 0 | K22: =G22+J22 -> 0 | M22: =M21+K22-L22 -> 17.7152
A23: 20 | B23: 46132 | G23: =E23*F23 -> 0 | J23: =H23*I23 -> 0 | K23: =G23+J23 -> 0 | M23: =M22+K23-L23 -> 17.7152
A24: 21 | B24: 46133 | E24: 300 | F24: 92.06 | G24: =E24*F24 -> 27618 | J24: =H24*I24 -> 0 | K24: =G24+J24 -> 27618 | M24: =M23+K24-L24 -> 27635.715
A25: 22 | B25: 46134 | G25: =E25*F25 -> 0 | J25: =H25*I25 -> 0 | K25: =G25+J25 -> 0 | M25: =M24+K25-L25 -> 27635.715
A26: 23 | B26: 46135 | G26: =E26*F26 -> 0 | J26: =H26*I26 -> 0 | K26: =G26+J26 -> 0 | M26: =M25+K26-L26 -> 27635.715
A27: 24 | B27: 46136 | E27: 300 | F27: 92.06 | G27: =E27*F27 -> 27618 | H27: 10 | I27: 103.81 | J27: =H27*I27 -> 1038.1 | K27: =G27+J27 -> 28656.1 | M27: =M26+K27-L27 -> 56291.815
A28: 25 | B28: 46137 | G28: =E28*F28 -> 0 | J28: =H28*I28 -> 0 | K28: =G28+J28 -> 0 | M28: =M27+K28-L28 -> 56291.815
A29: 26 | B29: 46138 | G29: =E29*F29 -> 0 | J29: =H29*I29 -> 0 | K29: =G29+J29 -> 0 | M29: =M28+K29-L29 -> 56291.815
A30: 27 | B30: 46139 | G30: =E30*F30 -> 0 | J30: =H30*I30 -> 0 | K30: =G30+J30 -> 0 | M30: =M29+K30-L30 -> 56291.815
A31: 28 | B31: 46140 | G31: =E31*F31 -> 0 | J31: =H31*I31 -> 0 | K31: =G31+J31 -> 0 | M31: =M30+K31-L31 -> 56291.815
A32: 29 | B32: 46141 | G32: =E32*F32 -> 0 | J32: =H32*I32 -> 0 | K32: =G32+J32 -> 0 | M32: =M31+K32-L32 -> 56291.815
A33: 30 | B33: 46142 | G33: =E33*F33 -> 0 | J33: =H33*I33 -> 0 | K33: =G33+J33 -> 0 | M33: =M32+K33-L33 -> 56291.815
A34: 31 | B34: 46143 | G34: =E34*F34 -> 0 | K34: =G34+J34 -> 0 | L34: 0 | M34: =M33+K34-L34 -> 56291.815
E35: =SUM(E4:E34) -> 1300 | G35: =SUM(G4:G34) -> 119678 | H35: =SUM(H4:H34) -> 50 | J35: =SUM(J4:J34) -> 5190.5 | K35: =SUM(K4:K34) -> 124868.5 | L35: =SUM(L4:L34) -> 72756.4

Sheet Chellakere -1
A1: Shivaganga Service Station (BPCL)
A2: S.No | B2: Date | C2: GRN No | D2: Ind No/Bill No | E2: Diesel (Lts) | F2: Price | G2: Amount | H2: Petrol (Lts) | I2: Price | J2: Amount | K2: Total amount | L2: Amount paid | M2: As on Date | N2: Remarks
A3: Opening Balance | K3: 215562.07 | L3: 215562.07 | M3: 215562.07
A4: 1 | B4: 46113 | E4: 600 | F4: 92.07 | G4: =E4*F4 -> 55242 | H4: 35 | I4: 103.82 | J4: =H4*I4 -> 3633.7 | K4: =G4+J4 -> 58875.7 | M4: =M3+K4-L4 -> 274437.77
A5: 2 | B5: 46114 | G5: =E5*F5 -> 0 | H5: 0 | I5: 0 | J5: =H5*I5 -> 0 | K5: =G5+J5 -> 0 | L5: 215562 | M5: =M4+K5-L5 -> 58875.774
A6: 3 | B6: 46115 | G6: =E6*F6 -> 0 | H6: 0 | I6: 0 | J6: =H6*I6 -> 0 | K6: =G6+J6 -> 0 | M6: =M5+K6-L6 -> 58875.774
A7: 4 | B7: 46116 | G7: =E7*F7 -> 0 | H7: 0 | I7: 0 | J7: =H7*I7 -> 0 | K7: =G7+J7 -> 0 | M7: =M6+K7-L7 -> 58875.774
A8: 5 | B8: 46117 | G8: =E8*F8 -> 0 | H8: 0 | I8: 0 | J8: =H8*I8 -> 0 | K8: =G8+J8 -> 0 | M8: =M7+K8-L8 -> 58875.774
A9: 6 | B9: 46118 | G9: =E9*F9 -> 0 | H9: 0 | I9: 0 | J9: =H9*I9 -> 0 | K9: =G9+J9 -> 0 | M9: =M8+K9-L9 -> 58875.774
A10: 7 | B10: 46119 | G10: =E10*F10 -> 0 | H10: 0 | I10: 0 | J10: =H10*I10 -> 0 | K10: =G10+J10 -> 0 | M10: =M9+K10-L10 -> 58875.774
A11: 8 | B11: 46120 | E11: 400 | F11: 92.07 | G11: =E11*F11 -> 36828 | H11: 35 | I11: 103.82 | J11: =H11*I11 -> 3633.7 | K11: =G11+J11 -> 40461.7 | M11: =M10+K11-L11 -> 99337.474
A12: 9 | B12: 46121 | G12: =E12*F12 -> 0 | H12: 0 | I12: 0 | J12: =H12*I12 -> 0 | K12: =G12+J12 -> 0 | M12: =M11+K12-L12 -> 99337.474
A13: 10 | B13: 46122 | G13: =E13*F13 -> 0 | H13: 0 | I13: 0 | J13: =H13*I13 -> 0 | K13: =G13+J13 -> 0 | M13: =M12+K13-L13 -> 99337.474
A14: 11 | B14: 46123 | E14: 400 | F14: 92.07 | G14: =E14*F14 -> 36828 | H14: 35 | I14: 103.82 | J14: =H14*I14 -> 3633.7 | K14: =G14+J14 -> 40461.7 | M14: =M13+K14-L14 -> 139799.17
A15: 12 | B15: 46124 | G15: =E15*F15 -> 0 | H15: 0 | I15: 0 | J15: =H15*I15 -> 0 | K15: =G15+J15 -> 0 | M15: =M14+K15-L15 -> 139799.17
A16: 13 | B16: 46125 | G16: =E16*F16 -> 0 | H16: 0 | I16: 0 | J16: =H16*I16 -> 0 | K16: =G16+J16 -> 0 | M16: =M15+K16-L16 -> 139799.17
A17: 14 | B17: 46126 | E17: 600 | F17: 92.07 | G17: =E17*F17 -> 55242 | H17: 0 | I17: 0 | J17: =H17*I17 -> 0 | K17: =G17+J17 -> 55242 | M17: =M16+K17-L17 -> 195041.17
A18: 15 | B18: 46127 | G18: =E18*F18 -> 0 | H18: 0 | I18: 0 | J18: =H18*I18 -> 0 | K18: =G18+J18 -> 0 | M18: =M17+K18-L18 -> 195041.17
A19: 16 | B19: 46128 | G19: =E19*F19 -> 0 | H19: 0 | I19: 0 | J19: =H19*I19 -> 0 | K19: =G19+J19 -> 0 | M19: =M18+K19-L19 -> 195041.17
A20: 17 | B20: 46129 | G20: =E20*F20 -> 0 | H20: 0 | I20: 0 | J20: =H20*I20 -> 0 | K20: =G20+J20 -> 0 | M20: =M19+K20-L20 -> 195041.17
A21: 18 | B21: 46130 | E21: 600 | F21: 92.067 | G21: =E21*F21 -> 55240.2 | H21: 30 | I21: 103.82 | J21: =H21*I21 -> 3114.6 | K21: =G21+J21 -> 58354.8 | M21: =M20+K21-L21 -> 253395.97
A22: 19 | B22: 46131 | G22: =E22*F22 -> 0 | H22: 0 | I22: 0 | J22: =H22*I22 -> 0 | K22: =G22+J22 -> 0 | L22: 195000 | M22: =M21+K22-L22 -> 58395.974
A23: 20 | B23: 46132 | G23: =E23*F23 -> 0 | H23: 0 | I23: 0 | J23: =H23*I23 -> 0 | K23: =G23+J23 -> 0 | M23: =M22+K23-L23 -> 58395.974
A24: 21 | B24: 46133 | G24: =E24*F24 -> 0 | H24: 0 | I24: 0 | J24: =H24*I24 -> 0 | K24: =G24+J24 -> 0 | M24: =M23+K24-L24 -> 58395.974
A25: 22 | B25: 46134 | E25: 800 | F25: 92.07 | G25: =E25*F25 -> 73656 | H25: 35 | I25: 103.82 | J25: =H25*I25 -> 3633.7 | K25: =G25+J25 -> 77289.7 | M25: =M24+K25-L25 -> 135685.67
A26: 23 | B26: 46135 | G26: =E26*F26 -> 0 | H26: 0 | I26: 0 | J26: =H26*I26 -> 0 | K26: =G26+J26 -> 0 | M26: =M25+K26-L26 -> 135685.67
A27: 24 | B27: 46136 | G27: =E27*F27 -> 0 | H27: 0 | I27: 0 | J27: =H27*I27 -> 0 | K27: =G27+J27 -> 0 | M27: =M26+K27-L27 -> 135685.67
A28: 25 | B28: 46137 | G28: =E28*F28 -> 0 | H28: 0 | I28: 0 | J28: =H28*I28 -> 0 | K28: =G28+J28 -> 0 | M28: =M27+K28-L28 -> 135685.67
A29: 26 | B29: 46138 | G29: =E29*F29 -> 0 | H29: 0 | I29: 0 | J29: =H29*I29 -> 0 | K29: =G29+J29 -> 0 | M29: =M28+K29-L29 -> 135685.67
A30: 27 | B30: 46139 | E30: 600 | F30: 92.07 | G30: =E30*F30 -> 55242 | H30: 0 | I30: 0 | J30: =H30*I30 -> 0 | K30: =G30+J30 -> 55242 | M30: =M29+K30-L30 -> 190927.67
A31: 28 | B31: 46140 | G31: =E31*F31 -> 0 | H31: 0 | I31: 0 | J31: =H31*I31 -> 0 | K31: =G31+J31 -> 0 | M31: =M30+K31-L31 -> 190927.67
A32: 29 | B32: 46141 | G32: =E32*F32 -> 0 | H32: 0 | I32: 0 | J32: =H32*I32 -> 0 | K32: =G32+J32 -> 0 | M32: =M31+K32-L32 -> 190927.67
A33: 30 | B33: 46142 | E33: 600 | F33: 92.07 | G33: =E33*F33 -> 55242 | H33: 35 | I33: 103.82 | J33: =H33*I33 -> 3633.7 | K33: =G33+J33 -> 58875.7 | M33: =M32+K33-L33 -> 249803.37
A34: 31 | G34: =E34*F34 -> 0 | H34: 0 | I34: 0 | J34: =H34*I34 -> 0 | K34: =G34+J34 -> 0
E35: =SUM(E4:E34) -> 4600 | G35: =SUM(G4:G34) -> 423520.2 | H35: =SUM(H4:H34) -> 205 | J35: =SUM(J4:J34) -> 21283.1 | K35: =SUM(K4:K34) -> 444803.3 | L35: =SUM(L4:L34) -> 410562

Sheet  Chellakere-PKG-9
A1: Chellakere-PKG-09
A2: S.No | B2: Date | C2: GRN No | D2: Ind No/Bill No | E2: Diesel (Lts) | F2: Price | G2: Amount | H2: Petrol (Lts) | I2: Price | J2: Amount | K2: Total amount | L2: Amount paid | M2: As on Date | N2: Remarks
A3: Opening Balance | K3: 0 | L3: 0 | M3: 0
A4: 1 | B4: 46113 | E4: 30 | F4: 92.07 | G4: =E4*F4 -> 2762.1 | J4: =H4*I4 -> 0 | K4: =G4+J4 -> 2762.1 | L4: =K4 -> 2762.1 | M4: =M3+K4-L4 -> 0
A5: 2 | B5: 46114 | G5: =E5*F5 -> 0 | J5: =H5*I5 -> 0 | K5: =G5+J5 -> 0 | L5: =K5 -> 0 | M5: =M4+K5-L5 -> 0
A6: 3 | B6: 46115 | G6: =E6*F6 -> 0 | H6: 10 | I6: 103.82 | J6: =H6*I6 -> 1038.2 | K6: =G6+J6 -> 1038.2 | L6: =K6 -> 1038.2 | M6: =M5+K6-L6 -> 0
A7: 4 | B7: 46116 | G7: =E7*F7 -> 0 | J7: =H7*I7 -> 0 | K7: =G7+J7 -> 0 | L7: =K7 -> 0 | M7: =M6+K7-L7 -> 0
A8: 5 | B8: 46117 | G8: =E8*F8 -> 0 | J8: =H8*I8 -> 0 | K8: =G8+J8 -> 0 | L8: =K8 -> 0 | M8: =M7+K8-L8 -> 0
A9: 6 | B9: 46118 | G9: =E9*F9 -> 0 | J9: =H9*I9 -> 0 | K9: =G9+J9 -> 0 | L9: =K9 -> 0 | M9: =M8+K9-L9 -> 0
A10: 7 | B10: 46119 | G10: =E10*F10 -> 0 | J10: =H10*I10 -> 0 | K10: =G10+J10 -> 0 | L10: =K10 -> 0 | M10: =M9+K10-L10 -> 0
A11: 8 | B11: 46120 | G11: =E11*F11 -> 0 | J11: =H11*I11 -> 0 | K11: =G11+J11 -> 0 | L11: =K11 -> 0 | M11: =M10+K11-L11 -> 0
A12: 9 | B12: 46121 | G12: =E12*F12 -> 0 | H12: 6 | I12: 103.82 | J12: =H12*I12 -> 622.92 | K12: =G12+J12 -> 622.92 | L12: =K12 -> 622.92 | M12: =M11+K12-L12 -> 0
A13: 10 | B13: 46122 | G13: =E13*F13 -> 0 | J13: =H13*I13 -> 0 | K13: =G13+J13 -> 0 | L13: =K13 -> 0 | M13: =M12+K13-L13 -> 0
A14: 11 | B14: 46123 | E14: 35 | F14: 92.06 | G14: =E14*F14 -> 3222.1 | J14: =H14*I14 -> 0 | K14: =G14+J14 -> 3222.1 | L14: =K14 -> 3222.1 | M14: =M13+K14-L14 -> 0
A15: 12 | B15: 46124 | E15: 60 | F15: 92.07 | G15: =E15*F15 -> 5524.2 | J15: =H15*I15 -> 0 | K15: =G15+J15 -> 5524.2 | L15: =K15 -> 5524.2 | M15: =M14+K15-L15 -> 0
A16: 13 | B16: 46125 | G16: =E16*F16 -> 0 | J16: =H16*I16 -> 0 | K16: =G16+J16 -> 0 | L16: =K16 -> 0 | M16: =M15+K16-L16 -> 0
A17: 14 | B17: 46126 | G17: =E17*F17 -> 0 | H17: 6 | I17: 103.82 | J17: =H17*I17 -> 622.92 | K17: =G17+J17 -> 622.92 | L17: =K17 -> 622.92 | M17: =M16+K17-L17 -> 0
A18: 15 | B18: 46127 | G18: =E18*F18 -> 0 | J18: =H18*I18 -> 0 | K18: =G18+J18 -> 0 | L18: =K18 -> 0 | M18: =M17+K18-L18 -> 0
A19: 16 | B19: 46128 | G19: =E19*F19 -> 0 | J19: =H19*I19 -> 0 | K19: =G19+J19 -> 0 | L19: =K19 -> 0 | M19: =M18+K19-L19 -> 0
A20: 17 | B20: 46129 | E20: 55.38 | F20: 92.07 | G20: =E20*F20 -> 5098.8366 | H20: 6 | I20: 103.82 | J20: =H20*I20 -> 622.92 | K20: =G20+J20 -> 5721.7566 | L20: =K20 -> 5721.7566 | M20: =M19+K20-L20 -> 0 | T20: 54.83
A21: 18 | B21: 46130 | G21: =E21*F21 -> 0 | J21: =H21*I21 -> 0 | K21: =G21+J21 -> 0 | L21: =K21 -> 0 | M21: =M20+K21-L21 -> 0 | T21: 0.55
A22: 19 | B22: 46131 | G22: =E22*F22 -> 0 | J22: =H22*I22 -> 0 | K22: =G22+J22 -> 0 | L22: =K22 -> 0 | M22: =M21+K22-L22 -> 0
A23: 20 | B23: 46132 | G23: =E23*F23 -> 0 | J23: =H23*I23 -> 0 | K23: =G23+J23 -> 0 | L23: =K23 -> 0 | M23: =M22+K23-L23 -> 0
A24: 21 | B24: 46133 | E24: 40 | F24: 92.07 | G24: =E24*F24 -> 3682.8 | H24: 5 | I24: 103.82 | J24: =H24*I24 -> 519.1 | K24: =G24+J24 -> 4201.9 | L24: =K24 -> 4201.9 | M24: =M23+K24-L24 -> 0
A25: 22 | B25: 46134 | G25: =E25*F25 -> 0 | J25: =H25*I25 -> 0 | K25: =G25+J25 -> 0 | L25: =K25 -> 0 | M25: =M24+K25-L25 -> 0
A26: 23 | B26: 46135 | G26: =E26*F26 -> 0 | J26: =H26*I26 -> 0 | K26: =G26+J26 -> 0 | L26: =K26 -> 0 | M26: =M25+K26-L26 -> 0
A27: 24 | B27: 46136 | E27: 25 | F27: 92.07 | G27: =E27*F27 -> 2301.75 | H27: 5 | I27: 103.82 | J27: =H27*I27 -> 519.1 | K27: =G27+J27 -> 2820.85 | L27: =K27 -> 2820.85 | M27: =M26+K27-L27 -> 0
A28: 25 | B28: 46137 | G28: =E28*F28 -> 0 | J28: =H28*I28 -> 0 | K28: =G28+J28 -> 0 | L28: =K28 -> 0 | M28: 0
A29: 26 | B29: 46138 | E29: 40 | F29: 92.07 | G29: =E29*F29 -> 3682.8 | J29: =H29*I29 -> 0 | K29: =G29+J29 -> 3682.8 | L29: =K29 -> 3682.8 | M29: 0
A30: 27 | B30: 46139 | G30: =E30*F30 -> 0 | J30: =H30*I30 -> 0 | K30: =G30+J30 -> 0 | L30: =K30 -> 0 | M30: 0
A31: 28 | B31: 46140 | E31: 40 | F31: 92.07 | G31: =E31*F31 -> 3682.8 | J31: =H31*I31 -> 0 | K31: =G31+J31 -> 3682.8 | L31: =K31 -> 3682.8 | M31: 0
A32: 29 | B32: 46141 | G32: =E32*F32 -> 0 | J32: =H32*I32 -> 0 | K32: =G32+J32 -> 0 | L32: =K32 -> 0
A33: 30 | B33: 46142 | G33: =E33*F33 -> 0 | J33: =H33*I33 -> 0 | K33: =G33+J33 -> 0 | L33: =K33 -> 0
A34: 31 | G34: =E34*F34 -> 0 | J34: =H34*I34 -> 0 | K34: =G34+J34 -> 0 | L34: =K34 -> 0
E35: =SUM(E4:E34) -> 325.38 | G35: =SUM(G4:G34) -> 29957.387 | H35: =SUM(H4:H34) -> 38 | J35: =SUM(J4:J34) -> 3945.16 | K35: =SUM(K4:K34) -> 33902.547 | L35: =SUM(L4:L34) -> 33902.547

Sheet  Chennagiri
A1: Chennagiri
A2: S.No | B2: Date | C2: GRN No | D2: Ind No/Bill No | E2: Diesel (Lts) | F2: Price | G2: Amount | H2: Petrol (Lts) | I2: Price | J2: Amount | K2: Total amount | L2: Amount paid | M2: As on Date | N2: Remarks
A3: Opening Balance | K3: 0 | L3: 0 | M3: =+K3 -> 0
A4: 1 | B4: 46113 | G4: =E4*F4 -> 0 | J4: =H4*I4 -> 0 | K4: =G4+J4 -> 0 | L4: =K4 -> 0 | M4: =M3+K4-L4 -> 0
A5: 2 | B5: 46114 | G5: =E5*F5 -> 0 | J5: =H5*I5 -> 0 | K5: =G5+J5 -> 0 | L5: =K5 -> 0 | M5: =M4+K5-L5 -> 0
A6: 3 | B6: 46115 | G6: =E6*F6 -> 0 | J6: =H6*I6 -> 0 | K6: =G6+J6 -> 0 | L6: =K6 -> 0 | M6: =M5+K6-L6 -> 0
A7: 4 | B7: 46116 | G7: =E7*F7 -> 0 | J7: =H7*I7 -> 0 | K7: =G7+J7 -> 0 | L7: =K7 -> 0 | M7: =M6+K7-L7 -> 0
A8: 5 | B8: 46117 | G8: =E8*F8 -> 0 | J8: =H8*I8 -> 0 | K8: =G8+J8 -> 0 | L8: =K8 -> 0 | M8: =M7+K8-L8 -> 0
A9: 6 | B9: 46118 | G9: =E9*F9 -> 0 | J9: =H9*I9 -> 0 | K9: =G9+J9 -> 0 | L9: =K9 -> 0 | M9: =M8+K9-L9 -> 0
A10: 7 | B10: 46119 | G10: =E10*F10 -> 0 | H10: 24 | I10: 103.86 | J10: =H10*I10 -> 2492.64 | K10: =G10+J10 -> 2492.64 | L10: =K10 -> 2492.64 | M10: =M9+K10-L10 -> 0
A11: 8 | B11: 46120 | E11: 100 | F11: 91.91 | G11: =E11*F11 -> 9191 | J11: =H11*I11 -> 0 | K11: =G11+J11 -> 9191 | L11: =K11 -> 9191 | M11: =M10+K11-L11 -> 0
A12: 9 | B12: 46121 | G12: =E12*F12 -> 0 | J12: =H12*I12 -> 0 | K12: =G12+J12 -> 0 | L12: =K12 -> 0 | M12: =M11+K12-L12 -> 0
A13: 10 | B13: 46122 | G13: =E13*F13 -> 0 | J13: =H13*I13 -> 0 | K13: =G13+J13 -> 0 | L13: =K13 -> 0 | M13: =M12+K13-L13 -> 0
A14: 11 | B14: 46123 | G14: =E14*F14 -> 0 | J14: =H14*I14 -> 0 | K14: =G14+J14 -> 0 | L14: =K14 -> 0 | M14: =M13+K14-L14 -> 0
A15: 12 | B15: 46124 | G15: =E15*F15 -> 0 | J15: =H15*I15 -> 0 | K15: =G15+J15 -> 0 | L15: =K15 -> 0 | M15: =M14+K15-L15 -> 0
A16: 13 | B16: 46125 | G16: =E16*F16 -> 0 | J16: =H16*I16 -> 0 | K16: =G16+J16 -> 0 | L16: =K16 -> 0 | M16: =M15+K16-L16 -> 0
A17: 14 | B17: 46126 | G17: =E17*F17 -> 0 | J17: =H17*I17 -> 0 | K17: =G17+J17 -> 0 | L17: =K17 -> 0 | M17: =M16+K17-L17 -> 0
A18: 15 | B18: 46127 | G18: =E18*F18 -> 0 | J18: =H18*I18 -> 0 | K18: =G18+J18 -> 0 | L18: =K18 -> 0 | M18: =M17+K18-L18 -> 0
A19: 16 | B19: 46128 | G19: =E19*F19 -> 0 | J19: =H19*I19 -> 0 | K19: =G19+J19 -> 0 | L19: =K19 -> 0 | M19: =M18+K19-L19 -> 0
A20: 17 | B20: 46129 | G20: =E20*F20 -> 0 | J20: =H20*I20 -> 0 | K20: =G20+J20 -> 0 | L20: =K20 -> 0 | M20: =M19+K20-L20 -> 0
A21: 18 | B21: 46130 | G21: =E21*F21 -> 0 | J21: =H21*I21 -> 0 | K21: =G21+J21 -> 0 | L21: =K21 -> 0 | M21: =M20+K21-L21 -> 0
A22: 19 | B22: 46131 | G22: =E22*F22 -> 0 | J22: =H22*I22 -> 0 | K22: =G22+J22 -> 0 | L22: =K22 -> 0 | M22: =M21+K22-L22 -> 0
A23: 20 | B23: 46132 | G23: =E23*F23 -> 0 | J23: =H23*I23 -> 0 | K23: =G23+J23 -> 0 | L23: =K23 -> 0 | M23: =M22+K23-L23 -> 0
A24: 21 | B24: 46133 | G24: =E24*F24 -> 0 | J24: =H24*I24 -> 0 | K24: =G24+J24 -> 0 | L24: =K24 -> 0 | M24: =M23+K24-L24 -> 0
A25: 22 | B25: 46134 | E25: 100 | F25: 91.91 | G25: =E25*F25 -> 9191 | J25: =H25*I25 -> 0 | K25: =G25+J25 -> 9191 | L25: =K25 -> 9191 | M25: =M24+K25-L25 -> 0
A26: 23 | B26: 46135 | G26: =E26*F26 -> 0 | J26: =H26*I26 -> 0 | K26: =G26+J26 -> 0 | L26: =K26 -> 0 | M26: =M25+K26-L26 -> 0
A27: 24 | B27: 46136 | G27: =E27*F27 -> 0 | H27: 25 | I27: 103.81 | J27: =H27*I27 -> 2595.25 | K27: =G27+J27 -> 2595.25 | L27: =K27 -> 2595.25 | M27: =M26+K27-L27 -> 0
A28: 25 | B28: 46137 | G28: =E28*F28 -> 0 | J28: =H28*I28 -> 0 | K28: =G28+J28 -> 0 | L28: =K28 -> 0 | M28: 0
A29: 26 | B29: 46138 | G29: =E29*F29 -> 0 | J29: =H29*I29 -> 0 | K29: =G29+J29 -> 0 | L29: =K29 -> 0 | M29: 0
A30: 27 | B30: 46139 | E30: 160 | F30: 91.89 | G30: =E30*F30 -> 14702.4 | J30: =H30*I30 -> 0 | K30: =G30+J30 -> 14702.4 | L30: =K30 -> 14702.4 | M30: 0 | N30: HPCL
A31: 28 | B31: 46140 | G31: =E31*F31 -> 0 | J31: =H31*I31 -> 0 | K31: =G31+J31 -> 0 | L31: =K31 -> 0 | M31: 0
A32: 29 | B32: 46141 | G32: =E32*F32 -> 0 | J32: =H32*I32 -> 0 | K32: =G32+J32 -> 0 | L32: =K32 -> 0
A33: 30 | B33: 46142 | G33: =E33*F33 -> 0 | J33: =H33*I33 -> 0 | K33: =G33+J33 -> 0 | L33: =K33 -> 0
A34: 31 | B34: 46143 | G34: =E34*F34 -> 0 | K34: =G34+J34 -> 0 | L34: =K34 -> 0
E35: =SUM(E4:E34) -> 360 | G35: =SUM(G4:G34) -> 33084.4 | H35: =SUM(H4:H34) -> 49 | J35: =SUM(J4:J34) -> 5087.89 | K35: =SUM(K4:K34) -> 38172.29 | L35: =SUM(L4:L34) -> 38172.29

Sheet Khanapur
A1: V.V.Varde
A2: S.No | B2: Date | C2: GRN No | D2: Ind No/Bill No | E2: Diesel (Lts) | F2: Price | G2: Amount | H2: Petrol (Lts) | I2: Price | J2: Amount | K2: Total amount | L2: Date of payment | M2: Amount paid | N2: Remarks
D3: Opening Balance | K3: 153658.75 | M3: 153658.75
A4: 1 | B4: 46113 | E4: 111 | F4: 90.88 | G4: 10087.68 | H4: 10 | I4: 102.77 | J4: 1027.7 | K4: =G4+J4 -> 11115.38 | M4: =M3+K4-L4 -> 164774.13
A5: 2 | B5: 46114 | E5: 52 | F5: 90.88 | G5: =F5*E5 -> 4725.76 | H5: 5 | I5: 102.77 | J5: =H5*I5 -> 513.85 | K5: =G5+J5 -> 5239.61 | L5: 153659 | M5: =M4+K5-L5 -> 16354.74 | S5: 90.88 | T5: 102.77
A6: 3 | B6: 46115 | E6: 30 | F6: 90.88 | G6: =F6*E6 -> 2726.4 | J6: =H6*I6 -> 0 | K6: =G6+J6 -> 2726.4 | M6: =M5+K6-L6 -> 19081.14
A7: 4 | B7: 46116 | G7: =F7*E7 -> 0 | J7: =H7*I7 -> 0 | K7: =G7+J7 -> 0 | M7: =M6+K7-L7 -> 19081.14
A8: 5 | B8: 46117 | E8: 100 | F8: 90.88 | G8: =F8*E8 -> 9088 | J8: =H8*I8 -> 0 | K8: =G8+J8 -> 9088 | M8: =M7+K8-L8 -> 28169.14
A9: 6 | B9: 46118 | E9: 35 | F9: 90.88 | G9: 3180.8 | H9: 5 | I9: 102.77 | J9: =H9*I9 -> 513.85 | K9: =G9+J9 -> 3694.65 | M9: =M8+K9-L9 -> 31863.79
A10: 7 | B10: 46119 | E10: 142 | F10: 90.88 | G10: =F10*E10 -> 12904.96 | H10: 10 | I10: 102.77 | J10: =H10*I10 -> 1027.7 | K10: =G10+J10 -> 13932.66 | M10: =M9+K10-L10 -> 45796.45
A11: 8 | B11: 46120 | G11: =F11*E11 -> 0 | H11: 10 | I11: 102.77 | J11: =H11*I11 -> 1027.7 | K11: =G11+J11 -> 1027.7 | M11: =M10+K11-L11 -> 46824.15
A12: 9 | B12: 46121 | E12: 106.41 | F12: 90.88 | G12: =F12*E12 -> 9670.5408 | J12: =H12*I12 -> 0 | K12: =G12+J12 -> 9670.5408 | M12: =M11+K12-L12 -> 56494.691
A13: 10 | B13: 46122 | G13: =F13*E13 -> 0 | H13: 5 | I13: 102.77 | J13: =H13*I13 -> 513.85 | K13: =G13+J13 -> 513.85 | M13: =M12+K13-L13 -> 57008.541
A14: 11 | B14: 46123 | E14: 20 | F14: 90.88 | G14: =F14*E14 -> 1817.6 | J14: =H14*I14 -> 0 | K14: =G14+J14 -> 1817.6 | M14: =M13+K14-L14 -> 58826.141
A15: 12 | B15: 46124 | E15: 61.58 | F15: 90.88 | G15: =F15*E15 -> 5596.3904 | J15: =H15*I15 -> 0 | K15: =G15+J15 -> 5596.3904 | M15: =M14+K15-L15 -> 64422.531
A16: 13 | B16: 46125 | E16: 100 | F16: 90.88 | G16: =F16*E16 -> 9088 | J16: =H16*I16 -> 0 | K16: =G16+J16 -> 9088 | M16: =M15+K16-L16 -> 73510.531
A17: 14 | B17: 46126 | E17: 103.5 | F17: 90.88 | G17: =F17*E17 -> 9406.08 | J17: =H17*I17 -> 0 | K17: =G17+J17 -> 9406.08 | M17: =M16+K17-L17 -> 82916.611
A18: 15 | B18: 46127 | G18: =F18*E18 -> 0 | I18: 102.77 | J18: =H18*I18 -> 0 | K18: =G18+J18 -> 0 | M18: =M17+K18-L18 -> 82916.611
A19: 16 | B19: 46128 | G19: =F19*E19 -> 0 | H19: 10 | I19: 102.77 | J19: =H19*I19 -> 1027.7 | K19: =G19+J19 -> 1027.7 | M19: =M18+K19-L19 -> 83944.311
A20: 17 | B20: 46129 | E20: 125.99 | F20: 90.88 | G20: =F20*E20 -> 11449.971 | H20: 15 | I20: 102.77 | J20: =H20*I20 -> 1541.55 | K20: =G20+J20 -> 12991.521 | M20: =M19+K20-L20 -> 96935.832 | O20: 16.68
A21: 18 | B21: 46130 | E21: 30 | F21: 90.88 | G21: =F21*E21 -> 2726.4 | H21: 13 | I21: 102.77 | J21: =H21*I21 -> 1336.01 | K21: =G21+J21 -> 4062.41 | M21: =M20+K21-L21 -> 100998.24
A22: 19 | B22: 46131 | G22: =F22*E22 -> 0 | J22: =H22*I22 -> 0 | K22: =G22+J22 -> 0 | M22: =M21+K22-L22 -> 100998.24
A23: 20 | B23: 46132 | G23: =F23*E23 -> 0 | J23: =H23*I23 -> 0 | K23: =G23+J23 -> 0 | M23: =M22+K23-L23 -> 100998.24 | N23: 0
A24: 21 | B24: 46133 | E24: 60 | F24: 90.88 | G24: =F24*E24 -> 5452.8 | J24: =H24*I24 -> 0 | K24: =G24+J24 -> 5452.8 | L24: 83960 | M24: =M23+K24-L24 -> 22491.042
A25: 22 | B25: 46134 | G25: =F25*E25 -> 0 | J25: =H25*I25 -> 0 | K25: =G25+J25 -> 0 | M25: =M24+K25-L25 -> 22491.042
A26: 23 | B26: 46135 | E26: 132.85 | F26: 90.88 | G26: =F26*E26 -> 12073.408 | H26: 5 | I26: 102.77 | J26: =H26*I26 -> 513.85 | K26: =G26+J26 -> 12587.258 | M26: =M25+K26-L26 -> 35078.3
A27: 24 | B27: 46136 | G27: =F27*E27 -> 0 | J27: =H27*I27 -> 0 | K27: =G27+J27 -> 0 | M27: =M26+K27-L27 -> 35078.3
A28: 25 | B28: 46137 | G28: =F28*E28 -> 0 | H28: 35 | I28: 102.77 | J28: =H28*I28 -> 3596.95 | K28: =G28+J28 -> 3596.95 | M28: =M27+K28-L28 -> 38675.25
A29: 26 | B29: 46138 | E29: 89.8 | F29: 90.88 | G29: =F29*E29 -> 8161.024 | J29: =H29*I29 -> 0 | K29: =G29+J29 -> 8161.024 | M29: =M28+K29-L29 -> 46836.274
A30: 27 | B30: 46139 | E30: 335.3 | F30: 90.88 | G30: =F30*E30 -> 30472.064 | H30: 15 | I30: 102.77 | J30: =H30*I30 -> 1541.55 | K30: =G30+J30 -> 32013.614 | M30: =M29+K30-L30 -> 78849.888
A31: 28 | B31: 46140 | E31: 20 | F31: 90.88 | G31: =F31*E31 -> 1817.6 | J31: =H31*I31 -> 0 | K31: =G31+J31 -> 1817.6 | M31: =M30+K31-L31 -> 80667.488
A32: 29 | B32: 46141 | E32: 236.45 | F32: 90.88 | G32: =F32*E32 -> 21488.576 | H32: 15 | I32: 102.77 | J32: =H32*I32 -> 1541.55 | K32: =G32+J32 -> 23030.126 | M32: =M31+K32-L32 -> 103697.61
A33: 30 | B33: 46142 | E33: 116.61 | F33: 90.88 | G33: =F33*E33 -> 10597.517 | J33: =H33*I33 -> 0 | K33: =G33+J33 -> 10597.517 | M33: =M32+K33-L33 -> 114295.13
A34: 31 | B34: 46143 | G34: =F34*E34 -> 0 | J34: =H34*I34 -> 0 | K34: =G34+J34 -> 0 | M34: =M33+K34-L34 -> 114295.13
E35: =SUM(E4:E34) -> 2008.49 | G35: =SUM(G4:G34) -> 182531.57 | H35: =SUM(H4:H34) -> 153 | J35: =SUM(J4:J34) -> 15723.81 | K35: =SUM(K4:K34) -> 198255.38 | L35: =SUM(L4:L34) -> 237619 | M35: =SUM(M4:M34) -> 2024370.7

Sheet Munavali-2
A1: Shiri Shva Petroluem
A2: S.No | B2: Date | C2: GRN No | D2: Ind No/Bill No | E2: Diesel (Lts) | F2: Price | G2: Amount | H2: Petrol (Lts) | I2: Price | J2: Amount | K2: Total amount | L2: Amount paid | M2: As on date | N2: Remarks
D3: Opening Balance | K3: 607059.51 | M3: 607059.51 | O3: 26506.4
A4: 1 | B4: 46113 | G4: =E4*F4 -> 0 | J4: =H4*I4 -> 0 | K4: =G4+J4 -> 0 | M4: =M3+K4-L4 -> 607059.51
A5: 2 | B5: 46114 | C5: Start | G5: =E5*F5 -> 0 | H5: 4.83 | I5: 103.44 | J5: =H5*I5 -> 499.6152 | K5: =G5+J5 -> 499.6152 | L5: 607499.62 | M5: =M4+K5-L5 -> 59.50306
A6: 3 | B6: 46115 | E6: 800 | F6: 91.54 | G6: =E6*F6 -> 73232 | H6: 4.83 | I6: 103.44 | J6: =H6*I6 -> 499.6152 | K6: =G6+J6 -> 73731.615 | L6: 499.62 | M6: =M5+K6-L6 -> 73291.498
A7: 4 | B7: 46116 | G7: =E7*F7 -> 0 | J7: =H7*I7 -> 0 | K7: =G7+J7 -> 0 | M7: =M6+K7-L7 -> 73291.498
A8: 5 | B8: 46117 | G8: =E8*F8 -> 0 | J8: =H8*I8 -> 0 | K8: =G8+J8 -> 0 | M8: =M7+K8-L8 -> 73291.498
A9: 6 | B9: 46118 | E9: 1000 | F9: 91.54 | G9: =E9*F9 -> 91540 | H9: 19.32 | I9: 103.44 | J9: =H9*I9 -> 1998.4608 | K9: =G9+J9 -> 93538.461 | L9: 1998.4608 | M9: =M8+K9-L9 -> 164831.5
A10: 7 | B10: 46119 | E10: 800 | F10: 91.54 | G10: =E10*F10 -> 73232 | H10: 11 | I10: 113.41 | J10: =H10*I10 -> 1247.51 | K10: =G10+J10 -> 74479.51 | M10: =M9+K10-L10 -> 239311.01
B11: 46119 | G11: =E11*F11 -> 0 | H11: 4.83 | I11: 103.44 | J11: =H11*I11 -> 499.6152 | K11: =G11+J11 -> 499.6152 | L11: 500 | M11: =M10+K11-L11 -> 239310.62
A12: 8 | B12: 46120 | E12: 1000 | F12: 91.54 | G12: =E12*F12 -> 91540 | J12: =H12*I12 -> 0 | K12: =G12+J12 -> 91540 | M12: =M10+K12-L12 -> 330851.01
A13: 9 | B13: 46121 | E13: 800 | F13: 91.54 | G13: =E13*F13 -> 73232 | H13: 14.55 | I13: 103.44 | J13: =H13*I13 -> 1505.052 | K13: =G13+J13 -> 74737.052 | L13: 1505.052 | M13: =M12+K13-L13 -> 404083.01
A14: 10 | B14: 46122 | G14: =E14*F14 -> 0 | J14: =H14*I14 -> 0 | K14: =G14+J14 -> 0 | M14: =M13+K14-L14 -> 404083.01
A15: 11 | B15: 46123 | E15: 800 | F15: 91.54 | G15: =E15*F15 -> 73232 | H15: 9.66 | I15: 103.44 | J15: =H15*I15 -> 999.2304 | K15: =G15+J15 -> 74231.23 | L15: 999.2304 | M15: =M14+K15-L15 -> 477315.01
A16: 12 | B16: 46124 | E16: 400 | F16: 91.54 | G16: =E16*F16 -> 36616 | J16: =H16*I16 -> 0 | K16: =G16+J16 -> 36616 | M16: =M15+K16-L16 -> 513931.01
A17: 13 | B17: 46125 | D17: 0 | E17: 200 | F17: 91.54 | G17: =E17*F17 -> 18308 | H17: 9.66 | I17: 103.44 | J17: =H17*I17 -> 999.2304 | K17: =G17+J17 -> 19307.23 | L17: 999.2304 | M17: =M16+K17-L17 -> 532239.01
A18: 14 | B18: 46126 | G18: =E18*F18 -> 0 | H18: 4.83 | I18: 103.44 | J18: =H18*I18 -> 499.6152 | K18: =G18+J18 -> 499.6152 | L18: 499.62 | M18: =M17+K18-L18 -> 532239
A19: 15 | B19: 46127 | E19: 100 | F19: 91.54 | G19: =E19*F19 -> 9154 | J19: =H19*I19 -> 0 | K19: =G19+J19 -> 9154 | M19: =M18+K19-L19 -> 541393
A20: 16 | B20: 46127 | E20: 32.9 | F20: 91.19 | G20: =E20*F20 -> 3000.151 | H20: 19.32 | I20: 103.44 | J20: =H20*I20 -> 1998.4608 | K20: =G20+J20 -> 4998.6118 | L20: 4998.61 | M20: =M19+K20-L20 -> 541393.01
A21: 17 | B21: 46128 | E21: 300 | F21: 91.51 | G21: =E21*F21 -> 27453 | J21: =H21*I21 -> 0 | K21: =G21+J21 -> 27453 | L21: 27453 | M21: =M20+K21-L21 -> 541393.01
A22: 18 | B22: 46128 | E22: 500 | F22: 91.54 | G22: =E22*F22 -> 45770 | J22: =H22*I22 -> 0 | K22: =G22+J22 -> 45770 | M22: =M21+K22-L22 -> 587163.01
A23: 19 | B23: 46129 | E23: 500 | F23: 91.54 | G23: =E23*F23 -> 45770 | H23: 9.66 | I23: 103.44 | J23: =H23*I23 -> 999.2304 | K23: =G23+J23 -> 46769.23 | L23: 999.2304 | M23: =M22+K23-L23 -> 632933.01
A24: 20 | B24: 46130 | E24: 500 | F24: 91.54 | G24: =E24*F24 -> 45770 | J24: =H24*I24 -> 0 | K24: =G24+J24 -> 45770 | L24: 300000 | M24: =M23+K24-L24 -> 378703.01
A25: 21 | B25: 46131 | E25: 600 | F25: 91.54 | G25: =E25*F25 -> 54924 | J25: =H25*I25 -> 0 | K25: =G25+J25 -> 54924 | M25: =M24+K25-L25 -> 433627.01
A26: 22 | B26: 46132 | E26: 300 | F26: 91.54 | G26: =E26*F26 -> 27462 | H26: 4.83 | I26: 103.44 | J26: =H26*I26 -> 499.6152 | K26: =G26+J26 -> 27961.615 | L26: 499.6152 | M26: =M25+K26-L26 -> 461089.01
A27: 23 | B27: 46133 | E27: 300 | F27: 91.54 | G27: =E27*F27 -> 27462 | J27: =H27*I27 -> 0 | K27: =G27+J27 -> 27462 | L27: 241333 | M27: =M26+K27-L27 -> 247218.01
A28: 24 | B28: 46134 | G28: =E28*F28 -> 0 | H28: 14.49 | I28: 103.44 | J28: =H28*I28 -> 1498.8456 | K28: =G28+J28 -> 1498.8456 | L28: 1498.8456 | M28: =M27+K28-L28 -> 247218.01
A29: 25 | B29: 46135 | E29: 1000 | F29: 91.54 | G29: =E29*F29 -> 91540 | J29: =H29*I29 -> 0 | K29: =G29+J29 -> 91540 | M29: =M28+K29-L29 -> 338758.01
A30: 26 | B30: 46136 | E30: 300 | F30: 91.54 | G30: =E30*F30 -> 27462 | H30: 19.32 | I30: 103.48 | J30: =H30*I30 -> 1999.2336 | K30: =G30+J30 -> 29461.234 | L30: 1999.2336 | M30: =M29+K30-L30 -> 366220.01 | Q30: 166834
A31: 27 | B31: 46137 | E31: 1000 | F31: 91.54 | G31: =E31*F31 -> 91540 | H31: 9.66 | I31: 103.44 | J31: =H31*I31 -> 999.2304 | K31: =G31+J31 -> 92539.23 | L31: 999.2304 | M31: =M30+K31-L31 -> 457760.01
A32: 28 | B32: 46138 | G32: =E32*F32 -> 0 | J32: =H32*I32 -> 0 | K32: =G32+J32 -> 0 | M32: =M31+K32-L32 -> 457760.01
A33: 29 | B33: 46139 | E33: 300 | F33: 91.54 | G33: =E33*F33 -> 27462 | H33: 4.83 | I33: 103.44 | J33: =H33*I33 -> 499.6152 | K33: =G33+J33 -> 27961.615 | L33: 499.6152 | M33: =M32+K33-L33 -> 485222.01
A34: 30 | B34: 46140 | E34: 300 | F34: 91.54 | G34: =E34*F34 -> 27462 | H34: 19.83 | I34: 103.44 | J34: =H34*I34 -> 2051.2152 | K34: =G34+J34 -> 29513.215 | L34: 2051.2152 | M34: =M33+K34-L34 -> 512684.01
A35: 31 | B35: 46141 | E35: 300 | F35: 91.54 | G35: =E35*F35 -> 27462 | H35: 4.83 | I35: 103.44 | J35: =H35*I35 -> 499.6152 | K35: =G35+J35 -> 27961.615 | L35: 499.6152 | M35: =M34+K35-L35 -> 540146.01
A36: 32 | B36: 46142 | E36: 300 | F36: 91.54 | G36: =E36*F36 -> 27462 | H36: 14.49 | I36: 103.44 | J36: =H36*I36 -> 1498.8456 | K36: =G36+J36 -> 28960.846 | L36: 1498.8456 | M36: =M35+K36-L36 -> 567608.01
A37: 33 | G37: =E37*F37 -> 0 | J37: =H37*I37 -> 0 | K37: =G37+J37 -> 0 | M37: =M36+K37-L37 -> 567608.01
E38: =SUM(E4:E37) -> 12432.9 | G38: =SUM(G4:G37) -> 1138087.2 | H38: =SUM(H4:H37) -> 204.77 | J38: =SUM(J4:J37) -> 21291.852 | K38: =SUM(K4:K37) -> 1159379 | L38: =SUM(L4:L37) -> 1198830.9
M41: =500*91.54 -> 45770

Sheet Borgaon
A1: Aadisagar Petrolium
A2: S.No | B2: Date | C2: GRN No | D2: Ind no/Bill No | E2: Diesel (Lts) | F2: Price | G2: Amount | H2: Petrol (Lts) | I2: Price | J2: Amount | K2: Total amount | L2: Amount paid | M2: As on Date | N2: Remarks
A3: Opening Balance | K3: 85513.088 | M3: 85513.088
A4: 1 | B4: 46113 | E4: 600 | F4: 91.77 | G4: =E4*F4 -> 55062 | J4: =H4*I4 -> 0 | K4: =G4+J4 -> 55062 | M4: =M3+K4-L4 -> 140575.09
A5: 2 | B5: 46114 | G5: =E5*F5 -> 0 | H5: 5 | I5: 103.73 | J5: =H5*I5 -> 518.65 | K5: =G5+J5 -> 518.65 | L5: 85500 | M5: =M4+K5-L5 -> 55593.738
A6: 3 | B6: 46115 | E6: 400 | F6: 91.77 | G6: =E6*F6 -> 36708 | J6: =H6*I6 -> 0 | K6: =G6+J6 -> 36708 | M6: =M5+K6-L6 -> 92301.738
A7: 4 | B7: 46116 | G7: =E7*F7 -> 0 | H7: 12 | I7: 103.73 | J7: =H7*I7 -> 1244.76 | K7: =G7+J7 -> 1244.76 | M7: =M6+K7-L7 -> 93546.498
A8: 5 | B8: 46117 | G8: =E8*F8 -> 0 | J8: =H8*I8 -> 0 | K8: =G8+J8 -> 0 | M8: =M7+K8-L8 -> 93546.498
A9: 6 | B9: 46118 | E9: 635 | F9: 91.77 | G9: =E9*F9 -> 58273.95 | H9: 6 | I9: 103.73 | J9: =H9*I9 -> 622.38 | K9: =G9+J9 -> 58896.33 | M9: =M8+K9-L9 -> 152442.83
A10: 7 | B10: 46119 | G10: =E10*F10 -> 0 | J10: =H10*I10 -> 0 | K10: =G10+J10 -> 0 | M10: =M9+K10-L10 -> 152442.83
A11: 8 | B11: 46120 | G11: =E11*F11 -> 0 | H11: 7 | I11: 103.73 | J11: =H11*I11 -> 726.11 | K11: =G11+J11 -> 726.11 | M11: =M10+K11-L11 -> 153168.94
A12: 9 | B12: 46121 | E12: 600 | F12: 91.77 | G12: =E12*F12 -> 55062 | H12: 5 | I12: 103.73 | J12: =H12*I12 -> 518.65 | K12: =G12+J12 -> 55580.65 | M12: =M11+K12-L12 -> 208749.59
A13: 10 | B13: 46122 | E13: 30 | F13: 91.77 | G13: =E13*F13 -> 2753.1 | J13: =H13*I13 -> 0 | K13: =G13+J13 -> 2753.1 | M13: =M12+K13-L13 -> 211502.69
A14: 11 | B14: 46123 | G14: =E14*F14 -> 0 | H14: 5 | I14: 103.73 | J14: =H14*I14 -> 518.65 | K14: =G14+J14 -> 518.65 | M14: =M13+K14-L14 -> 212021.34
A15: 12 | B15: 46124 | E15: 100 | F15: 91.77 | G15: =E15*F15 -> 9177 | H15: 5 | I15: 103.73 | J15: =H15*I15 -> 518.65 | K15: =G15+J15 -> 9695.65 | M15: =M14+K15-L15 -> 221716.99
A16: 13 | B16: 46125 | G16: =E16*F16 -> 0 | H16: 6 | I16: 103.73 | J16: =H16*I16 -> 622.38 | K16: =G16+J16 -> 622.38 | L16: 150000 | M16: =M15+K16-L16 -> 72339.368
A17: 14 | B17: 46126 | E17: 35 | F17: 91.77 | G17: =E17*F17 -> 3211.95 | J17: =H17*I17 -> 0 | K17: =G17+J17 -> 3211.95 | M17: =M16+K17-L17 -> 75551.318
A18: 15 | B18: 46127 | E18: 430 | F18: 91.77 | G18: =E18*F18 -> 39461.1 | J18: =H18*I18 -> 0 | K18: =G18+J18 -> 39461.1 | M18: =M17+K18-L18 -> 115012.42
A19: 16 | B19: 46128 | E19: 30 | F19: 91.77 | G19: =E19*F19 -> 2753.1 | J19: =H19*I19 -> 0 | K19: =G19+J19 -> 2753.1 | M19: =M18+K19-L19 -> 117765.52
A20: 17 | B20: 46129 | G20: =E20*F20 -> 0 | H20: 5 | I20: 103.73 | J20: =H20*I20 -> 518.65 | K20: =G20+J20 -> 518.65 | M20: =M19+K20-L20 -> 118284.17
A21: 18 | B21: 46130 | E21: 170 | F21: 91.77 | G21: =E21*F21 -> 15600.9 | H21: 4.51 | I21: 103.73 | J21: =H21*I21 -> 467.8223 | K21: =G21+J21 -> 16068.722 | M21: =M20+K21-L21 -> 134352.89
A22: 19 | B22: 46131 | E22: 60 | F22: 91.77 | G22: =E22*F22 -> 5506.2 | J22: =H22*I22 -> 0 | K22: =G22+J22 -> 5506.2 | M22: =M21+K22-L22 -> 139859.09
A23: 20 | B23: 46132 | E23: 222.12 | F23: 91.77 | G23: =E23*F23 -> 20383.952 | J23: =H23*I23 -> 0 | K23: =G23+J23 -> 20383.952 | M23: =M22+K23-L23 -> 160243.04
A24: 21 | B24: 46133 | G24: =E24*F24 -> 0 | H24: 10.3 | I24: 103.73 | J24: =H24*I24 -> 1068.419 | K24: =G24+J24 -> 1068.419 | M24: =M23+K24-L24 -> 161311.46
A25: 22 | B25: 46134 | E25: 275 | F25: 91.77 | G25: =E25*F25 -> 25236.75 | J25: =H25*I25 -> 0 | K25: =G25+J25 -> 25236.75 | M25: =M24+K25-L25 -> 186548.21
A26: 23 | B26: 46135 | E26: 219.73 | F26: 91.77 | G26: =E26*F26 -> 20164.622 | J26: =H26*I26 -> 0 | K26: =G26+J26 -> 20164.622 | L26: 186000 | M26: =M25+K26-L26 -> 20712.834 | Q26: d
A27: 24 | B27: 46136 | E27: 175 | F27: 91.77 | G27: =E27*F27 -> 16059.75 | J27: =H27*I27 -> 0 | K27: =G27+J27 -> 16059.75 | M27: =M26+K27-L27 -> 36772.584 | Q27: 30 | R27: 50
A28: 25 | B28: 46137 | E28: 141.61 | F28: 91.77 | G28: =E28*F28 -> 12995.55 | H28: 12 | I28: 103.73 | J28: =H28*I28 -> 1244.76 | K28: =G28+J28 -> 14240.31 | M28: =M27+K28-L28 -> 51012.894 | Q28: 50 | R28: 4.51
A29: 26 | B29: 46138 | E29: 160 | F29: 91.77 | G29: =E29*F29 -> 14683.2 | J29: =H29*I29 -> 0 | K29: =G29+J29 -> 14683.2 | M29: =M28+K29-L29 -> 65696.094
A30: 27 | B30: 46139 | E30: 153.11 | F30: 91.77 | G30: =E30*F30 -> 14050.905 | J30: =H30*I30 -> 0 | K30: =G30+J30 -> 14050.905 | M30: =M29+K30-L30 -> 79746.998
A31: 28 | B31: 46140 | E31: 94 | F31: 91.77 | G31: =E31*F31 -> 8626.38 | H31: 6 | I31: 103.73 | J31: =H31*I31 -> 622.38 | K31: =G31+J31 -> 9248.76 | M31: =M30+K31-L31 -> 88995.758
A32: 29 | B32: 46141 | E32: 70 | F32: 91.77 | G32: =E32*F32 -> 6423.9 | J32: =H32*I32 -> 0 | K32: =G32+J32 -> 6423.9 | M32: =M31+K32-L32 -> 95419.658
A33: 30 | B33: 46142 | E33: 110 | F33: 91.77 | G33: =E33*F33 -> 10094.7 | H33: 11 | I33: 103.73 | J33: =H33*I33 -> 1141.03 | K33: =G33+J33 -> 11235.73 | M33: =M32+K33-L33 -> 106655.39
A34: 31 | B34: 46143 | G34: =E34*F34 -> 0 | J34: =H34*I34 -> 0 | K34: =G34+J34 -> 0 | M34: =M33+K34-L34 -> 106655.39
E35: =SUM(E4:E34) -> 4710.57 | G35: =SUM(G4:G34) -> 432289.01 | H35: =SUM(H4:H34) -> 99.81 | J35: =SUM(J4:J34) -> 10353.291 | K35: =SUM(K4:K34) -> 442642.3 | L35: =SUM(L4:L34) -> 421500

Sheet Ugar,Khagwad,Kudichi
A1: Shiri Bhrhmanath Petrolium
A2: S.No | B2: Date | C2: GRN No | D2: Ind No/Bill No | E2: Diesel (Lts) | F2: Price | G2: Amount | H2: Petrol (Lts) | I2: Price | J2: Amount | K2: Total amount | L2: Amount paid | M2: As on Date | N2: Remarks
A3: Opening Balance | K3: 434415.61 | L3: 0 | M3: 434415.61
A4: 1 | B4: 46113 | E4: 255 | F4: 91.93 | G4: =E4*F4 -> 23442.15 | J4: =H4*I4 -> 0 | K4: =G4+J4 -> 23442.15 | L4: 0 | M4: =M3+K4-L4 -> 457857.76
A5: 2 | B5: 46114 | E5: 220 | F5: 91.93 | G5: =E5*F5 -> 20224.6 | J5: =H5*I5 -> 0 | K5: =G5+J5 -> 20224.6 | L5: 434650 | M5: =M4+K5-L5 -> 43432.363
A6: 3 | B6: 46115 | E6: 330 | F6: 91.93 | G6: =E6*F6 -> 30336.9 | H6: 10 | I6: 103.89 | J6: =H6*I6 -> 1038.9 | K6: =G6+J6 -> 31375.8 | L6: 0 | M6: =M5+K6-L6 -> 74808.163
A7: 4 | B7: 46116 | E7: 603.83 | F7: 91.93 | G7: =E7*F7 -> 55510.092 | J7: =H7*I7 -> 0 | K7: =G7+J7 -> 55510.092 | L7: 0 | M7: =M6+K7-L7 -> 130318.25
A8: 5 | B8: 46117 | E8: 820 | F8: 91.93 | G8: =E8*F8 -> 75382.6 | H8: 55 | I8: 103.89 | J8: =H8*I8 -> 5713.95 | K8: =G8+J8 -> 81096.55 | L8: 0 | M8: =M7+K8-L8 -> 211414.8
A9: 6 | B9: 46118 | E9: 275 | F9: 91.93 | G9: =E9*F9 -> 25280.75 | J9: =H9*I9 -> 0 | K9: =G9+J9 -> 25280.75 | L9: 0 | M9: =M8+K9-L9 -> 236695.55
A10: 7 | B10: 46119 | E10: 60 | F10: 91.93 | G10: =E10*F10 -> 5515.8 | J10: =H10*I10 -> 0 | K10: =G10+J10 -> 5515.8 | L10: 0 | M10: =M9+K10-L10 -> 242211.35
A11: 8 | B11: 46120 | E11: 361.66 | F11: 91.93 | G11: =E11*F11 -> 33247.404 | J11: =H11*I11 -> 0 | K11: =G11+J11 -> 33247.404 | L11: 0 | M11: =M10+K11-L11 -> 275458.76
A12: 9 | B12: 46121 | E12: 407 | F12: 91.93 | G12: =E12*F12 -> 37415.51 | J12: =H12*I12 -> 0 | K12: =G12+J12 -> 37415.51 | L12: 0 | M12: =M11+K12-L12 -> 312874.27
A13: 10 | B13: 46122 | E13: 925 | F13: 91.93 | G13: =E13*F13 -> 85035.25 | J13: =H13*I13 -> 0 | K13: =G13+J13 -> 85035.25 | L13: 0 | M13: =M12+K13-L13 -> 397909.52
A14: 11 | B14: 46123 | G14: =E14*F14 -> 0 | H14: 10 | I14: 103.89 | J14: =H14*I14 -> 1038.9 | K14: =G14+J14 -> 1038.9 | L14: 0 | M14: =M13+K14-L14 -> 398948.42
A15: 12 | B15: 46124 | E15: 100 | F15: 91.93 | G15: =E15*F15 -> 9193 | J15: =H15*I15 -> 0 | K15: =G15+J15 -> 9193 | L15: 0 | M15: =M14+K15-L15 -> 408141.42
A16: 13 | B16: 46125 | E16: 350 | F16: 91.93 | G16: =E16*F16 -> 32175.5 | H16: 55 | I16: 103.89 | J16: =H16*I16 -> 5713.95 | K16: =G16+J16 -> 37889.45 | L16: 250000 | M16: =M15+K16-L16 -> 196030.87
A17: 14 | B17: 46125 | G17: =E17*F17 -> 0 | H17: 20 | I17: 113.3 | J17: =H17*I17 -> 2266 | K17: =G17+J17 -> 2266 | L17: 0 | M17: =M16+K17-L17 -> 198296.87
A18: 15 | B18: 46126 | E18: 50 | F18: 91.93 | G18: =E18*F18 -> 4596.5 | J18: =H18*I18 -> 0 | K18: =G18+J18 -> 4596.5 | L18: 0 | M18: =M17+K18-L18 -> 202893.37
A19: 16 | B19: 46127 | E19: 80 | F19: 91.93 | G19: =E19*F19 -> 7354.4 | J19: =H19*I19 -> 0 | K19: =G19+J19 -> 7354.4 | L19: 0 | M19: =M18+K19-L19 -> 210247.77
A20: 17 | B20: 46128 | E20: 725 | F20: 91.93 | G20: =E20*F20 -> 66649.25 | J20: =H20*I20 -> 0 | K20: =G20+J20 -> 66649.25 | L20: 0 | M20: =M19+K20-L20 -> 276897.02
A21: 18 | B21: 46129 | E21: 246.96 | F21: 91.93 | G21: =E21*F21 -> 22703.033 | J21: =H21*I21 -> 0 | K21: =G21+J21 -> 22703.033 | L21: 0 | M21: =M20+K21-L21 -> 299600.05
A22: 19 | B22: 46130 | E22: 540 | F22: 91.93 | G22: =E22*F22 -> 49642.2 | J22: =H22*I22 -> 0 | K22: =G22+J22 -> 49642.2 | L22: 200000 | M22: =M21+K22-L22 -> 149242.25
A23: 20 | B23: 46131 | E23: 250 | F23: 91.93 | G23: =E23*F23 -> 22982.5 | J23: =H23*I23 -> 0 | K23: =G23+J23 -> 22982.5 | L23: 0 | M23: =M22+K23-L23 -> 172224.75
A24: 21 | B24: 46132 | E24: 230 | F24: 91.93 | G24: =E24*F24 -> 21143.9 | H24: 30 | I24: 103.89 | J24: =H24*I24 -> 3116.7 | K24: =G24+J24 -> 24260.6 | L24: 0 | M24: =M23+K24-L24 -> 196485.35
A25: 22 | B25: 46133 | E25: 71 | F25: 91.93 | G25: =E25*F25 -> 6527.03 | J25: =H25*I25 -> 0 | K25: =G25+J25 -> 6527.03 | L25: 0 | M25: =M24+K25-L25 -> 203012.38
A26: 23 | B26: 46134 | E26: 755 | F26: 91.93 | G26: =E26*F26 -> 69407.15 | J26: =H26*I26 -> 0 | K26: =G26+J26 -> 69407.15 | L26: 0 | M26: =M25+K26-L26 -> 272419.53
A27: 24 | B27: 46135 | E27: 400 | F27: 91.93 | G27: =E27*F27 -> 36772 | H27: 50 | I27: 103.89 | J27: =H27*I27 -> 5194.5 | K27: =G27+J27 -> 41966.5 | L27: 0 | M27: =M26+K27-L27 -> 314386.03
A28: 25 | B28: 46136 | E28: 560 | F28: 91.93 | G28: =E28*F28 -> 51480.8 | J28: =H28*I28 -> 0 | K28: =G28+J28 -> 51480.8 | L28: 0 | M28: =M27+K28-L28 -> 365866.83
A29: 26 | B29: 46137 | E29: 150 | F29: 91.93 | G29: =E29*F29 -> 13789.5 | J29: =H29*I29 -> 0 | K29: =G29+J29 -> 13789.5 | L29: 0 | M29: =M28+K29-L29 -> 379656.33
A30: 27 | B30: 46138 | E30: 80 | F30: 91.93 | G30: =E30*F30 -> 7354.4 | H30: 20 | I30: 113.3 | J30: =H30*I30 -> 2266 | K30: =G30+J30 -> 9620.4 | L30: 0 | M30: =M29+K30-L30 -> 389276.73
A31: 28 | B31: 46139 | E31: 579 | F31: 91.93 | G31: =E31*F31 -> 53227.47 | H31: 5 | I31: 103.89 | J31: =H31*I31 -> 519.45 | K31: =G31+J31 -> 53746.92 | L31: 0 | M31: =M30+K31-L31 -> 443023.65
A32: 29 | B32: 46140 | E32: 765 | F32: 91.93 | G32: =E32*F32 -> 70326.45 | H32: 45 | I32: 103.89 | J32: =H32*I32 -> 4675.05 | K32: =G32+J32 -> 75001.5 | L32: 0 | M32: =M31+K32-L32 -> 518025.15
A33: 30 | B33: 46141 | E33: 65 | F33: 91.93 | G33: =E33*F33 -> 5975.45 | J33: =H33*I33 -> 0 | K33: =G33+J33 -> 5975.45 | L33: 0 | M33: =M32+K33-L33 -> 524000.6
A34: 31 | B34: 46142 | E34: 655 | F34: 91.93 | G34: =E34*F34 -> 60214.15 | J34: =H34*I34 -> 0 | K34: =G34+J34 -> 60214.15 | L34: 0 | M34: =M33+K34-L34 -> 584214.75
E35: =SUM(E4:E34) -> 10909.45 | G35: =SUM(G4:G34) -> 1002905.7 | H35: =SUM(H4:H34) -> 300 | J35: =SUM(J4:J34) -> 31543.4 | K35: =SUM(K4:K34) -> 1034449.1 | L35: =SUM(L4:L34) -> 884650

Sheet Kabbur
A1: Shri Jai Hanuman Petrolium
A2: S.No | B2: Date | C2: GRN No | D2: Ind no/Bill No | E2: Diesel (Lts) | F2: Price | G2: Amount | H2: Petrol (Lts) | I2: Price | J2: Amount | K2: Total amount | L2: Amount paid | M2: As on Date | N2: Remarks
A3: Opening Balance | K3: 0 | M3: =+K3 -> 0
A4: 1 | B4: 46113 | G4: =E4*F4 -> 0 | J4: =H4*I4 -> 0 | K4: =G4+J4 -> 0 | L4: =+K4 -> 0
A5: 2 | B5: 46114 | E5: 25 | F5: 91.6 | G5: =E5*F5 -> 2290 | J5: =H5*I5 -> 0 | K5: =G5+J5 -> 2290 | L5: =+K5 -> 2290
A6: 3 | B6: 46115 | E6: 50 | F6: 91.6 | G6: =E6*F6 -> 4580 | H6: 6.5 | I6: 103.54 | J6: =H6*I6 -> 673.01 | K6: =G6+J6 -> 5253.01 | L6: =+K6 -> 5253.01
A7: 4 | B7: 46116 | G7: =E7*F7 -> 0 | J7: =H7*I7 -> 0 | K7: =G7+J7 -> 0 | L7: =+K7 -> 0
A8: 5 | B8: 46117 | G8: =E8*F8 -> 0 | J8: =H8*I8 -> 0 | K8: =G8+J8 -> 0 | L8: =+K8 -> 0
A9: 6 | B9: 46118 | G9: =E9*F9 -> 0 | J9: =H9*I9 -> 0 | K9: =G9+J9 -> 0 | L9: =+K9 -> 0
A10: 7 | B10: 46119 | G10: =E10*F10 -> 0 | J10: =H10*I10 -> 0 | K10: =G10+J10 -> 0 | L10: =+K10 -> 0
A11: 8 | B11: 46120 | G11: =E11*F11 -> 0 | J11: =H11*I11 -> 0 | K11: =G11+J11 -> 0 | L11: =+K11 -> 0
A12: 9 | B12: 46121 | G12: =E12*F12 -> 0 | J12: =H12*I12 -> 0 | K12: =G12+J12 -> 0 | L12: =+K12 -> 0
A13: 10 | B13: 46122 | E13: 70 | F13: 91.6 | G13: =E13*F13 -> 6412 | H13: 14.33 | I13: 103.54 | J13: =H13*I13 -> 1483.7282 | K13: =G13+J13 -> 7895.7282 | L13: =+K13 -> 7895.7282
A14: 11 | B14: 46123 | G14: =E14*F14 -> 0 | J14: =H14*I14 -> 0 | K14: =G14+J14 -> 0 | L14: =+K14 -> 0
A15: 12 | B15: 46124 | E15: 20 | F15: 91.6 | G15: =E15*F15 -> 1832 | J15: =H15*I15 -> 0 | K15: =G15+J15 -> 1832 | L15: =+K15 -> 1832
A16: 13 | B16: 46125 | G16: =E16*F16 -> 0 | J16: =H16*I16 -> 0 | K16: =G16+J16 -> 0 | L16: =+K16 -> 0
A17: 14 | B17: 46126 | E17: 20 | F17: 91.6 | G17: =E17*F17 -> 1832 | J17: =H17*I17 -> 0 | K17: =G17+J17 -> 1832 | L17: =+K17 -> 1832
A18: 15 | B18: 46127 | G18: =E18*F18 -> 0 | J18: =H18*I18 -> 0 | K18: =G18+J18 -> 0 | L18: =+K18 -> 0
A19: 16 | B19: 46128 | G19: =E19*F19 -> 0 | J19: =H19*I19 -> 0 | K19: =G19+J19 -> 0 | L19: =+K19 -> 0
A20: 17 | B20: 46129 | G20: =E20*F20 -> 0 | J20: =H20*I20 -> 0 | K20: =G20+J20 -> 0 | L20: =+K20 -> 0
A21: 18 | B21: 46130 | E21: 70 | F21: 91.6 | G21: =E21*F21 -> 6412 | J21: =H21*I21 -> 0 | K21: =G21+J21 -> 6412 | L21: =+K21 -> 6412
A22: 19 | B22: 46131 | G22: =E22*F22 -> 0 | J22: =H22*I22 -> 0 | K22: =G22+J22 -> 0 | L22: =+K22 -> 0
A23: 20 | B23: 46132 | G23: =E23*F23 -> 0 | J23: =H23*I23 -> 0 | K23: =G23+J23 -> 0 | L23: =+K23 -> 0
A24: 21 | B24: 46133 | E24: 25 | F24: 91.6 | G24: =E24*F24 -> 2290 | J24: =H24*I24 -> 0 | K24: =G24+J24 -> 2290 | L24: =+K24 -> 2290
A25: 22 | B25: 46134 | G25: =E25*F25 -> 0 | J25: =H25*I25 -> 0 | K25: =G25+J25 -> 0 | L25: =+K25 -> 0
A26: 23 | B26: 46135 | G26: =E26*F26 -> 0 | J26: =H26*I26 -> 0 | K26: =G26+J26 -> 0 | L26: =+K26 -> 0
A27: 24 | B27: 46136 | G27: =E27*F27 -> 0 | J27: =H27*I27 -> 0 | K27: =G27+J27 -> 0 | L27: =+K27 -> 0 | O27: 0
A28: 25 | B28: 46137 | E28: 70 | F28: 91.6 | G28: =E28*F28 -> 6412 | J28: =H28*I28 -> 0 | K28: =G28+J28 -> 6412 | L28: =+K28 -> 6412
A29: 26 | B29: 46138 | G29: =E29*F29 -> 0 | J29: =H29*I29 -> 0 | K29: =G29+J29 -> 0 | L29: =+K29 -> 0
A30: 27 | B30: 46139 | G30: =E30*F30 -> 0 | J30: =H30*I30 -> 0 | K30: =G30+J30 -> 0 | L30: =+K30 -> 0
A31: 28 | B31: 46140 | G31: =E31*F31 -> 0 | J31: =H31*I31 -> 0 | K31: =G31+J31 -> 0 | L31: =+K31 -> 0
A32: 29 | B32: 46141 | E32: 86.01 | F32: 91.6 | G32: =E32*F32 -> 7878.516 | J32: =H32*I32 -> 0 | K32: =G32+J32 -> 7878.516 | L32: =+K32 -> 7878.516
A33: 30 | B33: 46142 | G33: =E33*F33 -> 0 | J33: =H33*I33 -> 0 | K33: =G33+J33 -> 0 | L33: =+K33 -> 0
A34: 31 | G34: =E34*F34 -> 0 | J34: =H34*I34 -> 0 | K34: =G34+J34 -> 0 | L34: =H34+K34 -> 0
E35: =SUM(E4:E34) -> 436.01 | G35: =SUM(G4:G34) -> 39938.516 | H35: =SUM(H4:H34) -> 20.83 | J35: =SUM(J4:J34) -> 2156.7382 | K35: =SUM(K4:K34) -> 42095.254 | L35: =SUM(L4:L34) -> 42095.254

Sheet kumta
A1: V.M.MIRJANKAR (KUMTA) BHARAT
A2: S.No | B2: Date | C2: GRN No | D2: Ind No/Bill No | E2: Diesel (Lts) | F2: Price | G2: Amount | H2: Petrol (Lts) | I2: Price | J2: Amount | K2: Total amount | L2: Amount paid | M2: As on Date | N2: Remarks
A3: Opening Balance | M3: 34759.3
A4: 1 | B4: 45748 | E4: 100 | F4: 91.97 | G4: =E4*F4 -> 9197 | J4: =H4*I4 -> 0 | K4: =G4+J4 -> 9197 | L4: 0 | M4: =M3+K4-L4 -> 43956.3
A5: 2 | B5: 45749 | E5: 100 | F5: 91.97 | G5: =E5*F5 -> 9197 | H5: 5 | I5: 104.01 | J5: =H5*I5 -> 520.05 | K5: =G5+J5 -> 9717.05 | L5: 34239 | M5: =M4+K5-L5 -> 19434.35
A6: 3 | B6: 45750 | E6: 30 | F6: 91.97 | G6: =E6*F6 -> 2759.1 | H6: 5 | I6: 104.01 | J6: =H6*I6 -> 520.05 | K6: =G6+J6 -> 3279.15 | L6: 0 | M6: =M5+K6-L6 -> 22713.5
A7: 4 | B7: 45751 | E7: 90 | F7: 91.97 | G7: =E7*F7 -> 8277.3 | H7: 10 | I7: 104.01 | J7: =H7*I7 -> 1040.1 | K7: =G7+J7 -> 9317.4 | L7: 0 | M7: =M6+K7-L7 -> 32030.9
A8: 5 | B8: 45752 | E8: 100 | F8: 91.97 | G8: =E8*F8 -> 9197 | H8: 5 | I8: 104.01 | J8: =H8*I8 -> 520.05 | K8: =G8+J8 -> 9717.05 | L8: 0 | M8: =M7+K8-L8 -> 41747.95
A9: 6 | B9: 45753 | E9: 70 | F9: 91.97 | G9: =E9*F9 -> 6437.9 | H9: 15 | I9: 104.01 | J9: =H9*I9 -> 1560.15 | K9: =G9+J9 -> 7998.05 | L9: 0 | M9: =M8+K9-L9 -> 49746
A10: 7 | B10: 45754 | E10: 80 | F10: 91.97 | G10: =E10*F10 -> 7357.6 | H10: 25 | I10: 104.01 | J10: =H10*I10 -> 2600.25 | K10: =G10+J10 -> 9957.85 | L10: 0 | M10: =M9+K10-L10 -> 59703.85
A11: 8 | B11: 45755 | E11: 130 | F11: 91.97 | G11: =E11*F11 -> 11956.1 | H11: 5 | I11: 104.01 | J11: =H11*I11 -> 520.05 | K11: =G11+J11 -> 12476.15 | L11: 0 | M11: =M10+K11-L11 -> 72180
A12: 9 | B12: 45756 | E12: 90 | F12: 91.97 | G12: =E12*F12 -> 8277.3 | H12: 7 | I12: 104.01 | J12: =H12*I12 -> 728.07 | K12: =G12+J12 -> 9005.37 | L12: 0 | M12: =M11+K12-L12 -> 81185.37
A13: 10 | B13: 45757 | E13: 90 | F13: 91.97 | G13: =E13*F13 -> 8277.3 | H13: 10 | I13: 104.01 | J13: =H13*I13 -> 1040.1 | K13: =G13+J13 -> 9317.4 | L13: 0 | M13: =M12+K13-L13 -> 90502.77
A14: 11 | B14: 45758 | E14: 100 | F14: 91.97 | G14: =E14*F14 -> 9197 | H14: 5 | I14: 104.01 | J14: =H14*I14 -> 520.05 | K14: =G14+J14 -> 9717.05 | L14: 89000 | M14: =M13+K14-L14 -> 11219.82
A15: 12 | B15: 45759 | E15: 90 | F15: 91.97 | G15: =E15*F15 -> 8277.3 | J15: =H15*I15 -> 0 | K15: =G15+J15 -> 8277.3 | L15: 0 | M15: =M14+K15-L15 -> 19497.12
A16: 13 | B16: 45760 | E16: 70 | F16: 91.97 | G16: =E16*F16 -> 6437.9 | H16: 15 | I16: 104.01 | J16: =H16*I16 -> 1560.15 | K16: =G16+J16 -> 7998.05 | L16: 0 | M16: =M15+K16-L16 -> 27495.17
A17: 14 | B17: 45761 | E17: 120 | F17: 91.97 | G17: =E17*F17 -> 11036.4 | H17: 10 | I17: 104.01 | J17: =H17*I17 -> 1040.1 | K17: =G17+J17 -> 12076.5 | L17: 0 | M17: =M16+K17-L17 -> 39571.67
A18: 15 | B18: 45762 | E18: 140 | F18: 91.97 | G18: =E18*F18 -> 12875.8 | J18: =H18*I18 -> 0 | K18: =G18+J18 -> 12875.8 | L18: 0 | M18: =M17+K18-L18 -> 52447.47
A19: 16 | B19: 45763 | E19: 110 | F19: 91.97 | G19: =E19*F19 -> 10116.7 | H19: 5 | I19: 104.01 | J19: =H19*I19 -> 520.05 | K19: =G19+J19 -> 10636.75 | L19: 0 | M19: =M18+K19-L19 -> 63084.22
A20: 17 | B20: 45764 | E20: 80 | F20: 91.97 | G20: =E20*F20 -> 7357.6 | H20: 5 | I20: 104.01 | J20: =H20*I20 -> 520.05 | K20: =G20+J20 -> 7877.65 | L20: 0 | M20: =M19+K20-L20 -> 70961.87
A21: 18 | B21: 45765 | G21: =E21*F21 -> 0 | H21: 5 | I21: 104.01 | J21: =H21*I21 -> 520.05 | K21: =G21+J21 -> 520.05 | L21: 70000 | M21: =M20+K21-L21 -> 1481.92
A22: 19 | B22: 45766 | E22: 100 | F22: 91.97 | G22: =E22*F22 -> 9197 | H22: 10 | I22: 104.01 | J22: =H22*I22 -> 1040.1 | K22: =G22+J22 -> 10237.1 | L22: 0 | M22: =M21+K22-L22 -> 11719.02
A23: 20 | B23: 45767 | E23: 55 | F23: 91.97 | G23: =E23*F23 -> 5058.35 | J23: =H23*I23 -> 0 | K23: =G23+J23 -> 5058.35 | L23: 0 | M23: =M22+K23-L23 -> 16777.37
A24: 21 | B24: 45768 | E24: 100 | F24: 91.97 | G24: =E24*F24 -> 9197 | H24: 5 | I24: 104.01 | J24: =H24*I24 -> 520.05 | K24: =G24+J24 -> 9717.05 | L24: 0 | M24: =M23+K24-L24 -> 26494.42
A25: 22 | B25: 45769 | G25: =E25*F25 -> 0 | J25: =H25*I25 -> 0 | K25: =G25+J25 -> 0 | L25: 0 | M25: =M24+K25-L25 -> 26494.42
A26: 23 | B26: 45770 | E26: 100 | F26: 91.97 | G26: =E26*F26 -> 9197 | H26: 5 | I26: 104.01 | J26: =H26*I26 -> 520.05 | K26: =G26+J26 -> 9717.05 | L26: 0 | M26: =M25+K26-L26 -> 36211.47
A27: 24 | B27: 45771 | G27: =E27*F27 -> 0 | H27: 5 | I27: 104.01 | J27: =H27*I27 -> 520.05 | K27: =G27+J27 -> 520.05 | L27: 0 | M27: =M26+K27-L27 -> 36731.52
A28: 25 | B28: 45772 | G28: =E28*F28 -> 0 | H28: 5 | I28: 104.01 | J28: =H28*I28 -> 520.05 | K28: =G28+J28 -> 520.05 | L28: 0 | M28: =M27+K28-L28 -> 37251.57
A29: 26 | B29: 45773 | G29: =E29*F29 -> 0 | J29: =H29*I29 -> 0 | K29: =G29+J29 -> 0 | L29: 0 | M29: =M28+K29-L29 -> 37251.57
A30: 27 | B30: 45774 | G30: =E30*F30 -> 0 | H30: 5 | I30: 104.01 | J30: =H30*I30 -> 520.05 | K30: =G30+J30 -> 520.05 | L30: 0 | M30: =M29+K30-L30 -> 37771.62
A31: 28 | B31: 45775 | E31: 50 | F31: 91.97 | G31: =E31*F31 -> 4598.5 | J31: =H31*I31 -> 0 | K31: =G31+J31 -> 4598.5 | L31: 0 | M31: =M30+K31-L31 -> 42370.12
B32: 45775 | E32: 50 | F32: 91.92 | G32: =E32*F32 -> 4596 | J32: =H32*I32 -> 0 | K32: =G32+J32 -> 4596 | L32: =H32+K32 -> 4596 | M32: =M31+K32-L32 -> 42370.12
A33: 29 | B33: 45776 | E33: 50 | F33: 91.97 | G33: =E33*F33 -> 4598.5 | J33: =H33*I33 -> 0 | K33: =G33+J33 -> 4598.5 | L33: 0 | M33: =M32+K33-L33 -> 46968.62
A34: 30 | B34: 45777 | E34: 50 | F34: 91.97 | G34: =E34*F34 -> 4598.5 | H34: 10 | I34: 104.01 | J34: =H34*I34 -> 1040.1 | K34: =G34+J34 -> 5638.6 | L34: 50000 | M34: =M33+K34-L34 -> 2607.22
A35: 31 | B35: 45778 | G35: =E35*F35 -> 0 | J35: =H35*I35 -> 0 | K35: =G35+J35 -> 0 | L35: 0 | M35: =M34+K35-L35 -> 2607.22 | N35: 2607.07 | O35: =N35-M35 -> -0.15
E36: =SUM(E4:E35) -> 2145 | G36: =SUM(G4:G35) -> 197273.15 | H36: =SUM(H4:H35) -> 177 | J36: =SUM(J4:J35) -> 18409.77 | K36: =SUM(K4:K35) -> 215682.92 | L36: =SUM(L4:L35) -> 247835

Sheet Jalgaon
A1: Jai Bajarang Sarvo Senter Bodwad
A2: S.No | B2: Date | C2: GRN No | D2: Ind No/Bill No | E2: Diesel (Lts) | F2: Price | G2: Amount | H2: Petrol (Lts) | I2: Price | J2: Amount | K2: Total amount | L2: Amount paid | M2: As on Date | N2: Remarks
A3: Opening Balance | K3: 1651007.9 | M3: 1651007.9
A4: 1 | B4: 46113 | G4: =E4*F4 -> 0 | J4: =H4*I4 -> 0 | K4: =G4+J4 -> 0 | M4: =M3+K4-L4 -> 1651007.9
A5: 2 | B5: 46114 | G5: =E5*F5 -> 0 | J5: =H5*I5 -> 0 | K5: =G5+J5 -> 0 | M5: =M4+K5-L5 -> 1651007.9
B6: 46115 | G6: =E6*F6 -> 0 | J6: =H6*I6 -> 0 | K6: =G6+J6 -> 0 | L6: 1651008 | M6: =M5+K6-L6 -> -0.1209
A7: 3 | B7: 46116 | G7: =E7*F7 -> 0 | J7: =H7*I7 -> 0 | K7: =G7+J7 -> 0 | M7: =M6+K7-L7 -> -0.1209
A8: 4 | B8: 46117 | G8: =E8*F8 -> 0 | J8: =H8*I8 -> 0 | K8: =G8+J8 -> 0 | M8: =M7+K8-L8 -> -0.1209 | N8: IOCL
A9: 5 | B9: 46118 | G9: =E9*F9 -> 0 | J9: =H9*I9 -> 0 | K9: =G9+J9 -> 0 | M9: =M8+K9-L9 -> -0.1209 | N9: HPCL
A10: 6 | B10: 46119 | G10: =E10*F10 -> 0 | J10: =H10*I10 -> 0 | K10: =G10+J10 -> 0 | M10: =M9+K10-L10 -> -0.1209
A11: 7 | B11: 46120 | G11: =E11*F11 -> 0 | J11: =H11*I11 -> 0 | K11: =G11+J11 -> 0 | M11: =M10+K11-L11 -> -0.1209
A12: 8 | B12: 46121 | E12: 1000 | F12: 91.71 | G12: =E12*F12 -> 91710 | H12: 20 | I12: 105.19 | J12: =H12*I12 -> 2103.8 | K12: =G12+J12 -> 93813.8 | L12: 93813.8 | M12: =M11+K12-L12 -> -0.1209
A13: 9 | B13: 46122 | E13: 1000 | F13: 91.71 | G13: =E13*F13 -> 91710 | J13: =H13*I13 -> 0 | K13: =G13+J13 -> 91710 | L13: 91710 | M13: =M12+K13-L13 -> -0.1209
A14: 10 | B14: 46123 | E14: 2000 | F14: 91.71 | G14: =E14*F14 -> 183420 | J14: =H14*I14 -> 0 | K14: =G14+J14 -> 183420 | L14: =H14+K14 -> 183420 | M14: =M13+K14-L14 -> -0.1209
A15: 11 | B15: 46124 | E15: 1500 | F15: 91.71 | G15: =E15*F15 -> 137565 | H15: 20 | I15: 105.19 | J15: =H15*I15 -> 2103.8 | K15: =G15+J15 -> 139668.8 | L15: 139668.8 | M15: =M14+K15-L15 -> -0.1209
A16: 12 | B16: 46125 | G16: =E16*F16 -> 0 | J16: =H16*I16 -> 0 | K16: =G16+J16 -> 0 | M16: =M15+K16-L16 -> -0.1209
A17: 13 | B17: 46126 | G17: =E17*F17 -> 0 | J17: =H17*I17 -> 0 | K17: =G17+J17 -> 0 | M17: =M16+K17-L17 -> -0.1209
A18: 14 | B18: 46127 | G18: =E18*F18 -> 0 | J18: =H18*I18 -> 0 | K18: =G18+J18 -> 0 | M18: =M17+K18-L18 -> -0.1209
A19: 15 | B19: 46128 | G19: =E19*F19 -> 0 | J19: =H19*I19 -> 0 | K19: =G19+J19 -> 0 | M19: =M18+K19-L19 -> -0.1209
A20: 16 | B20: 46129 | G20: =E20*F20 -> 0 | J20: =H20*I20 -> 0 | K20: =G20+J20 -> 0 | M20: =M19+K20-L20 -> -0.1209
A21: 17 | B21: 46130 | E21: 1500 | F21: 91.71 | G21: =E21*F21 -> 137565 | J21: =H21*I21 -> 0 | K21: =G21+J21 -> 137565 | L21: =H21+K21 -> 137565 | M21: =M20+K21-L21 -> -0.1209
A22: 18 | B22: 46131 | G22: =E22*F22 -> 0 | J22: =H22*I22 -> 0 | K22: =G22+J22 -> 0 | M22: =M21+K22-L22 -> -0.1209
A23: 19 | B23: 46132 | G23: =E23*F23 -> 0 | J23: =H23*I23 -> 0 | K23: =G23+J23 -> 0 | M23: =M22+K23-L23 -> -0.1209
A24: 20 | B24: 46133 | G24: =E24*F24 -> 0 | J24: =H24*I24 -> 0 | K24: =G24+J24 -> 0 | M24: =M23+K24-L24 -> -0.1209
A25: 21 | B25: 46134 | G25: =E25*F25 -> 0 | J25: =H25*I25 -> 0 | K25: =G25+J25 -> 0 | M25: =M24+K25-L25 -> -0.1209
A26: 22 | B26: 46135 | E26: 2000 | F26: 91.71 | G26: =E26*F26 -> 183420 | H26: 20 | I26: 105.19 | J26: =H26*I26 -> 2103.8 | K26: =G26+J26 -> 185523.8 | L26: 91710 | M26: =M25+K26-L26 -> 93813.679
A27: 23 | B27: 46136 | G27: =E27*F27 -> 0 | J27: =H27*I27 -> 0 | K27: =G27+J27 -> 0 | M27: =M26+K27-L27 -> 93813.679
A28: 24 | B28: 46137 | G28: =E28*F28 -> 0 | J28: =H28*I28 -> 0 | K28: =G28+J28 -> 0 | M28: =M27+K28-L28 -> 93813.679
A29: 25 | B29: 46138 | G29: =E29*F29 -> 0 | J29: =H29*I29 -> 0 | K29: =G29+J29 -> 0 | M29: =M28+K29-L29 -> 93813.679
A30: 26 | B30: 46139 | G30: =E30*F30 -> 0 | J30: =H30*I30 -> 0 | K30: =G30+J30 -> 0 | M30: =M29+K30-L30 -> 93813.679
A31: 27 | B31: 46140 | G31: =E31*F31 -> 0 | J31: =H31*I31 -> 0 | K31: =G31+J31 -> 0 | M31: =M30+K31-L31 -> 93813.679
A32: 28 | B32: 46141 | G32: =E32*F32 -> 0 | J32: =H32*I32 -> 0 | K32: =G32+J32 -> 0 | M32: =M31+K32-L32 -> 93813.679
A33: 29 | B33: 46142 | G33: =E33*F33 -> 0 | J33: =H33*I33 -> 0 | K33: =G33+J33 -> 0 | M33: =M32+K33-L33 -> 93813.679
A34: 30 | G34: =E34*F34 -> 0 | J34: =H34*I34 -> 0 | K34: =G34+J34 -> 0 | M34: =M33+K34-L34 -> 93813.679
A35: 31 | G35: =E35*F35 -> 0 | J35: =H35*I35 -> 0 | K35: =G35+J35 -> 0 | M35: =M34+K35-L35 -> 93813.679
A36: 32 | G36: =E36*F36 -> 0 | J36: =H36*I36 -> 0 | K36: =G36+J36 -> 0 | M36: =M35+K36-L36 -> 93813.679
A37: 33 | G37: =E37*F37 -> 0 | J37: =H37*I37 -> 0 | K37: =G37+J37 -> 0 | M37: =M36+K37-L37 -> 93813.679
A38: 34 | G38: =E38*F38 -> 0 | J38: =H38*I38 -> 0 | K38: =G38+J38 -> 0 | M38: =M37+K38-L38 -> 93813.679 | P38: 41
A39: 35 | G39: =E39*F39 -> 0 | J39: =H39*I39 -> 0 | K39: =G39+J39 -> 0 | M39: =M38+K39-L39 -> 93813.679 | P39: 40 | Q39: 5
A40: 36 | G40: =E40*F40 -> 0 | J40: =H40*I40 -> 0 | K40: =G40+J40 -> 0 | M40: =M39+K40-L40 -> 93813.679
A41: 37 | G41: =E41*F41 -> 0 | J41: =H41*I41 -> 0 | K41: =G41+J41 -> 0 | M41: =M40+K41-L41 -> 93813.679
A42: 38 | G42: =E42*F42 -> 0 | J42: =H42*I42 -> 0 | K42: =G42+J42 -> 0 | M42: =M41+K42-L42 -> 93813.679
A43: 39 | G43: =E43*F43 -> 0 | J43: =H43*I43 -> 0 | K43: =G43+J43 -> 0 | M43: =M42+K43-L43 -> 93813.679
A44: 40 | G44: =E44*F44 -> 0 | J44: =H44*I44 -> 0 | K44: =G44+J44 -> 0 | M44: =M43+K44-L44 -> 93813.679
A45: 41 | G45: =E45*F45 -> 0 | J45: =H45*I45 -> 0 | K45: =G45+J45 -> 0 | M45: =M44+K45-L45 -> 93813.679
A46: 42 | G46: =E46*F46 -> 0 | J46: =H46*I46 -> 0 | K46: =G46+J46 -> 0 | M46: =M45+K46-L46 -> 93813.679
A47: 43 | G47: =E47*F47 -> 0 | J47: =H47*I47 -> 0 | K47: =G47+J47 -> 0 | M47: =M46+K47-L47 -> 93813.679
A48: 44 | G48: =E48*F48 -> 0 | J48: =H48*I48 -> 0 | K48: =G48+J48 -> 0 | M48: =M47+K48-L48 -> 93813.679
A49: 45 | G49: =E49*F49 -> 0 | J49: =H49*I49 -> 0 | K49: =G49+J49 -> 0 | M49: =M48+K49-L49 -> 93813.679
A50: 46 | G50: =E50*F50 -> 0 | J50: =H50*I50 -> 0 | K50: =G50+J50 -> 0 | M50: =M49+K50-L50 -> 93813.679
A51: 47 | G51: =E51*F51 -> 0 | J51: =H51*I51 -> 0 | K51: =G51+J51 -> 0 | L51: 0 | M51: =M50+K51-L51 -> 93813.679
A52: 48 | G52: =E52*F52 -> 0 | J52: =H52*I52 -> 0 | K52: =G52+J52 -> 0 | L52: 0 | M52: =M51+K52-L52 -> 93813.679
A53: 49 | G53: =E53*F53 -> 0 | J53: =H53*I53 -> 0 | K53: =G53+J53 -> 0 | L53: 0 | M53: =M52+K53-L53 -> 93813.679
A54: 50 | G54: =E54*F54 -> 0 | J54: =H54*I54 -> 0 | K54: =G54+J54 -> 0 | L54: 0 | M54: =M53+K54-L54 -> 93813.679 | O54: 1109792.3 | P54: =M54-O54 -> -1015978.6
E55: =SUM(E4:E54) -> 9000 | G55: =SUM(G4:G54) -> 825390 | H55: =SUM(H4:H54) -> 60 | J55: =SUM(J4:J54) -> 6311.4 | K55: =SUM(K4:K54) -> 831701.4 | L55: =SUM(L4:L54) -> 2388895.6

Sheet Jalgoan-2
A1: Nayara
A2: S.No | B2: Date | C2: GRN No | D2: Ind No/Bill No | E2: Diesel (Lts) | F2: Price | G2: Amount | H2: Petrol (Lts) | I2: Price | J2: Amount | K2: Total amount | L2: Amount paid | M2: As on Date | N2: Remarks
A3: Opening Balance | K3: 5471845 | M3: 5471845 | P3: 5472110
A4: 1 | B4: 46113 | E4: 3100 | F4: 94.71 | G4: =E4*F4 -> 293601 | J4: =H4*I4 -> 0 | K4: =G4+J4 -> 293601 | M4: =M3+K4-L4 -> 5765446
A5: 2 | B5: 46114 | E5: 2700 | F5: 94.71 | G5: =E5*F5 -> 255717 | J5: =H5*I5 -> 0 | K5: =G5+J5 -> 255717 | M5: =M4+K5-L5 -> 6021163
A6: 3 | B6: 46115 | E6: 4500 | F6: 94.71 | G6: =E6*F6 -> 426195 | H6: 50 | I6: 110.44 | J6: =H6*I6 -> 5522 | K6: =G6+J6 -> 431717 | M6: =M5+K6-L6 -> 6452880
A7: 4 | B7: 46116 | E7: 1700 | F7: 94.71 | G7: =E7*F7 -> 161007 | J7: =H7*I7 -> 0 | K7: =G7+J7 -> 161007 | L7: 5441028 | M7: =M6+K7-L7 -> 1172859
A8: 5 | B8: 46117 | E8: 1850 | F8: 94.71 | G8: =E8*F8 -> 175213.5 | H8: 5 | I8: 110.44 | J8: =H8*I8 -> 552.2 | K8: =G8+J8 -> 175765.7 | M8: =M7+K8-L8 -> 1348624.7
A9: 6 | B9: 46118 | E9: 4700 | F9: 94.71 | G9: =E9*F9 -> 445137 | H9: 50 | I9: 110.44 | J9: =H9*I9 -> 5522 | K9: =G9+J9 -> 450659 | M9: =M8+K9-L9 -> 1799283.7
A10: 7 | B10: 46119 | E10: 3700 | F10: 94.71 | G10: =E10*F10 -> 350427 | H10: 20 | I10: 110.44 | J10: =H10*I10 -> 2208.8 | K10: =G10+J10 -> 352635.8 | M10: =M9+K10-L10 -> 2151919.5
A11: 8 | B11: 46120 | E11: 3200 | F11: 94.71 | G11: =E11*F11 -> 303072 | H11: 30 | I11: 110.44 | J11: =H11*I11 -> 3313.2 | K11: =G11+J11 -> 306385.2 | M11: =M10+K11-L11 -> 2458304.7
A12: 9 | B12: 46121 | E12: 500 | F12: 94.71 | G12: =E12*F12 -> 47355 | H12: 0 | I12: 110.44 | J12: =H12*I12 -> 0 | K12: =G12+J12 -> 47355 | M12: =M11+K12-L12 -> 2505659.7
A13: 10 | B13: 46122 | E13: 2700 | F13: 94.71 | G13: =E13*F13 -> 255717 | J13: =H13*I13 -> 0 | K13: =G13+J13 -> 255717 | M13: =M12+K13-L13 -> 2761376.7
A14: 11 | B14: 46123 | E14: 2700 | F14: 94.71 | G14: =E14*F14 -> 255717 | J14: =H14*I14 -> 0 | K14: =G14+J14 -> 255717 | L14: 1000000 | M14: =M13+K14-L14 -> 2017093.7
A15: 12 | B15: 46124 | E15: 2700 | F15: 94.71 | G15: =E15*F15 -> 255717 | J15: =H15*I15 -> 0 | K15: =G15+J15 -> 255717 | M15: =M14+K15-L15 -> 2272810.7
A16: 13 | B16: 46125 | E16: 3200.38 | F16: 94.71 | G16: =E16*F16 -> 303107.99 | H16: 35 | I16: 110.44 | J16: =H16*I16 -> 3865.4 | K16: =G16+J16 -> 306973.39 | M16: =M15+K16-L16 -> 2579784.1
A17: 14 | B17: 46126 | E17: 2800 | F17: 94.71 | G17: =E17*F17 -> 265188 | J17: =H17*I17 -> 0 | K17: =G17+J17 -> 265188 | M17: =M16+K17-L17 -> 2844972.1
A18: 15 | B18: 46127 | E18: 2700 | F18: 94.71 | G18: =E18*F18 -> 255717 | J18: =H18*I18 -> 0 | K18: =G18+J18 -> 255717 | M18: =M17+K18-L18 -> 3100689.1
A19: 16 | B19: 46128 | E19: 3100 | F19: 94.71 | G19: =E19*F19 -> 293601 | H19: 30 | I19: 110.44 | J19: =H19*I19 -> 3313.2 | K19: =G19+J19 -> 296914.2 | M19: =M18+K19-L19 -> 3397603.3
A20: 17 | B20: 46129 | E20: 2500 | F20: 94.71 | G20: =E20*F20 -> 236775 | H20: 25 | I20: 110.44 | J20: =H20*I20 -> 2761 | K20: =G20+J20 -> 239536 | M20: =M19+K20-L20 -> 3637139.3
A21: 18 | B21: 46130 | E21: 2000 | F21: 94.71 | G21: =E21*F21 -> 189420 | H21: 30 | I21: 110.44 | J21: =H21*I21 -> 3313.2 | K21: =G21+J21 -> 192733.2 | L21: 500000 | M21: =M20+K21-L21 -> 3329872.5
A22: 19 | B22: 46131 | E22: 1000 | F22: 94.71 | G22: =E22*F22 -> 94710 | J22: =H22*I22 -> 0 | K22: =G22+J22 -> 94710 | M22: =M21+K22-L22 -> 3424582.5
A23: 20 | B23: 46132 | G23: =E23*F23 -> 0 | J23: =H23*I23 -> 0 | K23: =G23+J23 -> 0 | M23: =M22+K23-L23 -> 3424582.5
A24: 21 | B24: 46133 | G24: =E24*F24 -> 0 | H24: 50 | I24: 110.44 | J24: =H24*I24 -> 5522 | K24: =G24+J24 -> 5522 | L24: 1000000 | M24: =M23+K24-L24 -> 2430104.5
A25: 22 | B25: 46134 | E25: 2400 | F25: 94.71 | G25: =E25*F25 -> 227304 | J25: =H25*I25 -> 0 | K25: =G25+J25 -> 227304 | M25: =M24+K25-L25 -> 2657408.5
A26: 23 | B26: 46135 | E26: 2050 | F26: 94.71 | G26: =E26*F26 -> 194155.5 | J26: =H26*I26 -> 0 | K26: =G26+J26 -> 194155.5 | M26: =M25+K26-L26 -> 2851564
A27: 24 | B27: 46136 | E27: 500 | F27: 94.71 | G27: =E27*F27 -> 47355 | H27: 30 | I27: 110.44 | J27: =H27*I27 -> 3313.2 | K27: =G27+J27 -> 50668.2 | M27: =M26+K27-L27 -> 2902232.2
A28: 25 | B28: 46137 | E28: 0 | F28: 0 | G28: =E28*F28 -> 0 | H28: 0 | I28: 0 | J28: =H28*I28 -> 0 | K28: =G28+J28 -> 0 | M28: =M27+K28-L28 -> 2902232.2
A29: 26 | B29: 46138 | E29: 2000.23 | F29: 94.71 | G29: =E29*F29 -> 189441.78 | H29: 20 | I29: 110.44 | J29: =H29*I29 -> 2208.8 | K29: =G29+J29 -> 191650.58 | M29: =M28+K29-L29 -> 3093882.8
A30: 27 | B30: 46139 | E30: 3000 | F30: 94.71 | G30: =E30*F30 -> 284130 | J30: =H30*I30 -> 0 | K30: =G30+J30 -> 284130 | L30: 1000000 | M30: =M29+K30-L30 -> 2378012.8
A31: 28 | B31: 46140 | E31: 1000 | F31: 94.71 | G31: =E31*F31 -> 94710 | H31: 30 | I31: 110.44 | J31: =H31*I31 -> 3313.2 | K31: =G31+J31 -> 98023.2 | M31: =M30+K31-L31 -> 2476036
A32: 29 | B32: 46141 | E32: 2000 | F32: 94.71 | G32: =E32*F32 -> 189420 | J32: =H32*I32 -> 0 | K32: =G32+J32 -> 189420 | M32: =M31+K32-L32 -> 2665456
A33: 30 | B33: 46142 | G33: =E33*F33 -> 0 | J33: =H33*I33 -> 0 | K33: =G33+J33 -> 0 | M33: =M32+K33-L33 -> 2665456
A34: 31 | G34: =E34*F34 -> 0 | J34: =H34*I34 -> 0 | K34: =G34+J34 -> 0 | M34: =M33+K34-L34 -> 2665456
A35: 32 | G35: =E35*F35 -> 0 | J35: =H35*I35 -> 0 | K35: =G35+J35 -> 0 | M35: =M34+K35-L35 -> 2665456
A36: 33 | G36: =E36*F36 -> 0 | J36: =H36*I36 -> 0 | K36: =G36+J36 -> 0 | M36: =M35+K36-L36 -> 2665456
A37: 34 | G37: =E37*F37 -> 0 | J37: =H37*I37 -> 0 | K37: =G37+J37 -> 0 | M37: =M36+K37-L37 -> 2665456
A38: 35 | G38: =E38*F38 -> 0 | J38: =H38*I38 -> 0 | K38: =G38+J38 -> 0 | M38: =M37+K38-L38 -> 2665456 | P38: 41
A39: 36 | G39: =E39*F39 -> 0 | J39: =H39*I39 -> 0 | K39: =G39+J39 -> 0 | M39: =M38+K39-L39 -> 2665456 | P39: 40 | Q39: 5
A40: 37 | G40: =E40*F40 -> 0 | J40: =H40*I40 -> 0 | K40: =G40+J40 -> 0 | M40: =M39+K40-L40 -> 2665456
A41: 38 | G41: =E41*F41 -> 0 | J41: =H41*I41 -> 0 | K41: =G41+J41 -> 0 | M41: =M40+K41-L41 -> 2665456
A42: 39 | G42: =E42*F42 -> 0 | J42: =H42*I42 -> 0 | K42: =G42+J42 -> 0 | M42: =M41+K42-L42 -> 2665456
A43: 40 | G43: =E43*F43 -> 0 | J43: =H43*I43 -> 0 | K43: =G43+J43 -> 0 | M43: =M42+K43-L43 -> 2665456
A44: 41 | G44: =E44*F44 -> 0 | J44: =H44*I44 -> 0 | K44: =G44+J44 -> 0 | M44: =M43+K44-L44 -> 2665456
A45: 42 | G45: =E45*F45 -> 0 | J45: =H45*I45 -> 0 | K45: =G45+J45 -> 0 | M45: =M44+K45-L45 -> 2665456
A46: 43 | G46: =E46*F46 -> 0 | J46: =H46*I46 -> 0 | K46: =G46+J46 -> 0 | M46: =M45+K46-L46 -> 2665456
A47: 44 | G47: =E47*F47 -> 0 | J47: =H47*I47 -> 0 | K47: =G47+J47 -> 0 | M47: =M46+K47-L47 -> 2665456
A48: 45 | G48: =E48*F48 -> 0 | J48: =H48*I48 -> 0 | K48: =G48+J48 -> 0 | M48: =M47+K48-L48 -> 2665456
A49: 46 | G49: =E49*F49 -> 0 | J49: =H49*I49 -> 0 | K49: =G49+J49 -> 0 | M49: =M48+K49-L49 -> 2665456
A50: 47 | G50: =E50*F50 -> 0 | J50: =H50*I50 -> 0 | K50: =G50+J50 -> 0 | M50: =M49+K50-L50 -> 2665456
A51: 48 | G51: =E51*F51 -> 0 | J51: =H51*I51 -> 0 | K51: =G51+J51 -> 0 | L51: 0 | M51: =M50+K51-L51 -> 2665456
A52: 49 | G52: =E52*F52 -> 0 | J52: =H52*I52 -> 0 | K52: =G52+J52 -> 0 | L52: 0 | M52: =M51+K52-L52 -> 2665456
A53: 50 | G53: =E53*F53 -> 0 | J53: =H53*I53 -> 0 | K53: =G53+J53 -> 0 | L53: 0 | M53: =M52+K53-L53 -> 2665456
A54: 51 | G54: =E54*F54 -> 0 | J54: =H54*I54 -> 0 | K54: =G54+J54 -> 0 | L54: 0 | M54: =M53+K54-L54 -> 2665456 | O54: 1109792.3 | P54: =M54-O54 -> 1555663.7
E55: =SUM(E4:E54) -> 64300.61 | G55: =SUM(G4:G54) -> 6089910.8 | H55: =SUM(H4:H54) -> 405 | J55: =SUM(J4:J54) -> 44728.2 | K55: =SUM(K4:K54) -> 6134639 | L55: =SUM(L4:L54) -> 8941028

Sheet  Jalgoan-3
A1: T R KAPOOR AND CO
A2: S.No | B2: Date | C2: GRN No | D2: Ind No/Bill No | E2: Diesel (Lts) | F2: Price | G2: Amount | H2: Petrol (Lts) | I2: Price | J2: Amount | K2: Total amount | L2: Amount paid | M2: As on Date | N2: Remarks
A3: Opening Balance | K3: 0 | M3: =+K3 -> 0
A4: 1 | B4: 46113 | G4: =E4*F4 -> 0 | J4: =H4*I4 -> 0 | K4: =G4+J4 -> 0 | M4: =M3+K4-L4 -> 0
A5: 2 | B5: 46114 | G5: =E5*F5 -> 0 | J5: =H5*I5 -> 0 | K5: =G5+J5 -> 0 | M5: =M4+K5-L5 -> 0
B6: 46115 | G6: =E6*F6 -> 0 | K6: =G6+J6 -> 0 | M6: =M5+K6-L6 -> 0
A7: 3 | B7: 46116 | G7: =E7*F7 -> 0 | J7: =H7*I7 -> 0 | K7: =G7+J7 -> 0 | M7: =M6+K7-L7 -> 0
A8: 4 | B8: 46117 | G8: =E8*F8 -> 0 | J8: =H8*I8 -> 0 | K8: =G8+J8 -> 0 | M8: =M7+K8-L8 -> 0 | N8: IOCL
A9: 5 | B9: 46118 | G9: =E9*F9 -> 0 | J9: =H9*I9 -> 0 | K9: =G9+J9 -> 0 | M9: =M8+K9-L9 -> 0 | N9: HPCL
A10: 6 | B10: 46119 | G10: =E10*F10 -> 0 | J10: =H10*I10 -> 0 | K10: =G10+J10 -> 0 | M10: =M9+K10-L10 -> 0
A11: 7 | B11: 46120 | G11: =E11*F11 -> 0 | J11: =H11*I11 -> 0 | K11: =G11+J11 -> 0 | M11: =M10+K11-L11 -> 0
A12: 8 | B12: 46121 | G12: =E12*F12 -> 0 | J12: =H12*I12 -> 0 | K12: =G12+J12 -> 0 | M12: =M11+K12-L12 -> 0
A13: 9 | B13: 46122 | G13: =E13*F13 -> 0 | J13: =H13*I13 -> 0 | K13: =G13+J13 -> 0 | M13: =M12+K13-L13 -> 0
A14: 10 | B14: 46123 | G14: =E14*F14 -> 0 | J14: =H14*I14 -> 0 | K14: =G14+J14 -> 0 | M14: =M13+K14-L14 -> 0
A15: 11 | B15: 46124 | G15: =E15*F15 -> 0 | J15: =H15*I15 -> 0 | K15: =G15+J15 -> 0 | M15: =M14+K15-L15 -> 0
A16: 12 | B16: 46125 | G16: =E16*F16 -> 0 | J16: =H16*I16 -> 0 | K16: =G16+J16 -> 0 | M16: =M15+K16-L16 -> 0
A17: 13 | B17: 46126 | G17: =E17*F17 -> 0 | J17: =H17*I17 -> 0 | K17: =G17+J17 -> 0 | M17: =M16+K17-L17 -> 0
A18: 14 | B18: 46127 | G18: =E18*F18 -> 0 | J18: =H18*I18 -> 0 | K18: =G18+J18 -> 0 | M18: =M17+K18-L18 -> 0
A19: 15 | B19: 46128 | G19: =E19*F19 -> 0 | J19: =H19*I19 -> 0 | K19: =G19+J19 -> 0 | M19: =M18+K19-L19 -> 0
A20: 16 | B20: 46129 | G20: =E20*F20 -> 0 | J20: =H20*I20 -> 0 | K20: =G20+J20 -> 0 | M20: =M19+K20-L20 -> 0
A21: 17 | B21: 46130 | G21: =E21*F21 -> 0 | J21: =H21*I21 -> 0 | K21: =G21+J21 -> 0 | M21: =M20+K21-L21 -> 0
A22: 18 | B22: 46131 | E22: 2500 | F22: 91.97 | G22: =E22*F22 -> 229925 | J22: =H22*I22 -> 0 | K22: =G22+J22 -> 229925 | M22: =M21+K22-L22 -> 229925
A23: 19 | B23: 46132 | G23: =E23*F23 -> 0 | J23: =H23*I23 -> 0 | K23: =G23+J23 -> 0 | L23: 229925 | M23: =M22+K23-L23 -> 0
A24: 20 | B24: 46133 | G24: =E24*F24 -> 0 | J24: =H24*I24 -> 0 | K24: =G24+J24 -> 0 | M24: =M23+K24-L24 -> 0
A25: 21 | B25: 46134 | G25: =E25*F25 -> 0 | J25: =H25*I25 -> 0 | K25: =G25+J25 -> 0 | M25: =M24+K25-L25 -> 0
A26: 22 | B26: 46135 | G26: =E26*F26 -> 0 | J26: =H26*I26 -> 0 | K26: =G26+J26 -> 0 | M26: =M25+K26-L26 -> 0
A27: 23 | B27: 46136 | G27: =E27*F27 -> 0 | J27: =H27*I27 -> 0 | K27: =G27+J27 -> 0 | M27: =M26+K27-L27 -> 0
A28: 24 | B28: 46137 | G28: =E28*F28 -> 0 | J28: =H28*I28 -> 0 | K28: =G28+J28 -> 0 | M28: =M27+K28-L28 -> 0
A29: 25 | B29: 46138 | G29: =E29*F29 -> 0 | J29: =H29*I29 -> 0 | K29: =G29+J29 -> 0 | M29: =M28+K29-L29 -> 0
A30: 26 | B30: 46139 | G30: =E30*F30 -> 0 | J30: =H30*I30 -> 0 | K30: =G30+J30 -> 0 | M30: =M29+K30-L30 -> 0
A31: 27 | B31: 46140 | G31: =E31*F31 -> 0 | J31: =H31*I31 -> 0 | K31: =G31+J31 -> 0 | M31: =M30+K31-L31 -> 0
A32: 28 | B32: 46141 | G32: =E32*F32 -> 0 | J32: =H32*I32 -> 0 | K32: =G32+J32 -> 0 | M32: =M31+K32-L32 -> 0
A33: 29 | B33: 46142 | G33: =E33*F33 -> 0 | J33: =H33*I33 -> 0 | K33: =G33+J33 -> 0 | M33: =M32+K33-L33 -> 0
A34: 30 | G34: =E34*F34 -> 0 | J34: =H34*I34 -> 0 | K34: =G34+J34 -> 0 | M34: =M33+K34-L34 -> 0
A35: 31 | G35: =E35*F35 -> 0 | J35: =H35*I35 -> 0 | K35: =G35+J35 -> 0 | M35: =M34+K35-L35 -> 0
A36: 32 | G36: =E36*F36 -> 0 | J36: =H36*I36 -> 0 | K36: =G36+J36 -> 0 | M36: =M35+K36-L36 -> 0
A37: 33 | G37: =E37*F37 -> 0 | J37: =H37*I37 -> 0 | K37: =G37+J37 -> 0 | M37: =M36+K37-L37 -> 0
A38: 34 | G38: =E38*F38 -> 0 | J38: =H38*I38 -> 0 | K38: =G38+J38 -> 0 | M38: =M37+K38-L38 -> 0
A39: 35 | G39: =E39*F39 -> 0 | J39: =H39*I39 -> 0 | K39: =G39+J39 -> 0 | M39: =M38+K39-L39 -> 0
A40: 36 | G40: =E40*F40 -> 0 | J40: =H40*I40 -> 0 | K40: =G40+J40 -> 0 | M40: =M39+K40-L40 -> 0
A41: 37 | G41: =E41*F41 -> 0 | J41: =H41*I41 -> 0 | K41: =G41+J41 -> 0 | M41: =M40+K41-L41 -> 0
A42: 38 | G42: =E42*F42 -> 0 | J42: =H42*I42 -> 0 | K42: =G42+J42 -> 0 | M42: =M41+K42-L42 -> 0
A43: 39 | G43: =E43*F43 -> 0 | J43: =H43*I43 -> 0 | K43: =G43+J43 -> 0 | M43: =M42+K43-L43 -> 0
A44: 40 | G44: =E44*F44 -> 0 | J44: =H44*I44 -> 0 | K44: =G44+J44 -> 0 | M44: =M43+K44-L44 -> 0
A45: 41 | G45: =E45*F45 -> 0 | J45: =H45*I45 -> 0 | K45: =G45+J45 -> 0 | M45: =M44+K45-L45 -> 0
... A50: 46 | G50: =E50*F50 -> 0 | J50: =H50*I50 -> 0 | K50: =G50+J50 -> 0 | M50: =M49+K50-L50 -> 0
A51: 47 | G51: =E51*F51 -> 0 | J51: =H51*I51 -> 0 | K51: =G51+J51 -> 0 | L51: 0 | M51: =M50+K51-L51 -> 0
A52: 48 | G52: =E52*F52 -> 0 | J52: =H52*I52 -> 0 | K52: =G52+J52 -> 0 | L52: 0 | M52: =M51+K52-L52 -> 0
A53: 49 | G53: =E53*F53 -> 0 | J53: =H53*I53 -> 0 | K53: =G53+J53 -> 0 | L53: 0 | M53: =M52+K53-L53 -> 0
A54: 50 | G54: =E54*F54 -> 0 | J54: =H54*I54 -> 0 | K54: =G54+J54 -> 0 | L54: 0 | M54: =M53+K54-L54 -> 0
E55: =SUM(E4:E54) -> 2500 | G55: =SUM(G4:G54) -> 229925 | H55: =SUM(H4:H54) -> 0 | J55: =SUM(J4:J54) -> 0 | K55: =SUM(K4:K54) -> 229925 | L55: =SUM(L4:L54) -> 229925

Sheet  Jalgoan-4
A1: Cash &Carry
A2: S.No | B2: Date | C2: GRN No | D2: Ind No/Bill No | E2: Diesel (Lts) | F2: Price | G2: Amount | H2: Petrol (Lts) | I2: Price | J2: Amount | K2: Total amount | L2: Amount paid | M2: As on Date | N2: Remarks
A3: Opening Balance | K3: 0 | M3: =+K3 -> 0
A4: 1 | B4: 46113 | D4: BPCL | E4: 2000 | F4: 91.67 | G4: =E4*F4 -> 183340 | J4: =H4*I4 -> 0 | K4: =G4+J4 -> 183340 | L4: =H4+K4 -> 183340 | M4: =M3+K4-L4 -> 0 | N4: VASUDEO NIVRUTTI MAHAJAN
A5: 2 | B5: 46114 | D5: BPCL | E5: 2000 | F5: 91.67 | G5: =E5*F5 -> 183340 | J5: =H5*I5 -> 0 | K5: =G5+J5 -> 183340 | L5: =H5+K5 -> 183340 | M5: =M4+K5-L5 -> 0 | N5: RAKSHA AUTO FUELS
A6: 3 | B6: 46115 | G6: =E6*F6 -> 0 | K6: =G6+J6 -> 0 | M6: =M5+K6-L6 -> 0 | R6: =2500*91.67 -> 229175
A7: 4 | B7: 46116 | G7: =E7*F7 -> 0 | J7: =H7*I7 -> 0 | K7: =G7+J7 -> 0 | M7: =M6+K7-L7 -> 0
A8: 5 | B8: 46117 | E8: 2000 | F8: 91.67 | G8: =E8*F8 -> 183340 | J8: =H8*I8 -> 0 | K8: =G8+J8 -> 183340 | L8: =H8+K8 -> 183340 | M8: =M7+K8-L8 -> 0 | N8: VASUDEO NIVRUTTI MAHAJAN
A9: 6 | B9: 46118 | G9: =E9*F9 -> 0 | J9: =H9*I9 -> 0 | K9: =G9+J9 -> 0 | M9: =M8+K9-L9 -> 0
A10: 7 | B10: 46119 | G10: =E10*F10 -> 0 | J10: =H10*I10 -> 0 | K10: =G10+J10 -> 0 | M10: =M9+K10-L10 -> 0
A11: 8 | B11: 46120 | G11: =E11*F11 -> 0 | J11: =H11*I11 -> 0 | K11: =G11+J11 -> 0 | M11: =M10+K11-L11 -> 0
A12: 9 | B12: 46121 | G12: =E12*F12 -> 0 | J12: =H12*I12 -> 0 | K12: =G12+J12 -> 0 | M12: =M11+K12-L12 -> 0
A13: 10 | B13: 46122 | G13: =E13*F13 -> 0 | J13: =H13*I13 -> 0 | K13: =G13+J13 -> 0 | M13: =M12+K13-L13 -> 0
A14: 11 | B14: 46123 | G14: =E14*F14 -> 0 | J14: =H14*I14 -> 0 | K14: =G14+J14 -> 0 | M14: =M13+K14-L14 -> 0
A15: 12 | B15: 46124 | G15: =E15*F15 -> 0 | J15: =H15*I15 -> 0 | K15: =G15+J15 -> 0 | M15: =M14+K15-L15 -> 0
A16: 13 | B16: 46125 | E16: 1000 | F16: 91.61 | G16: =E16*F16 -> 91610 | J16: =H16*I16 -> 0 | K16: =G16+J16 -> 91610 | L16: =H16+K16 -> 91610 | M16: =M15+K16-L16 -> 0 | N16: KHANDEWAL PETROLEUM(HP)
A17: 14 | B17: 46126 | G17: =E17*F17 -> 0 | J17: =H17*I17 -> 0 | K17: =G17+J17 -> 0 | M17: =M16+K17-L17 -> 0
A18: 15 | B18: 46127 | G18: =E18*F18 -> 0 | J18: =H18*I18 -> 0 | K18: =G18+J18 -> 0 | M18: =M17+K18-L18 -> 0
A19: 16 | B19: 46128 | G19: =E19*F19 -> 0 | J19: =H19*I19 -> 0 | K19: =G19+J19 -> 0 | M19: =M18+K19-L19 -> 0
A20: 17 | B20: 46129 | E20: 2000 | F20: 91.67 | G20: =E20*F20 -> 183340 | J20: =H20*I20 -> 0 | K20: =G20+J20 -> 183340 | L20: =H20+K20 -> 183340 | M20: =M19+K20-L20 -> 0 | N20: VASUDEO NIVRUTTI MAHAJAN | Q20: =PROPER(N20) -> Vasudeo Nivrutti Mahajan
A21: 18 | B21: 46130 | E21: 2152.84 | F21: 91.67 | G21: =E21*F21 -> 197350.84 | J21: =H21*I21 -> 0 | K21: =G21+J21 -> 197350.84 | L21: =H21+K21 -> 197350.84 | M21: =M20+K21-L21 -> 0 | N21: VASUDEO NIVRUTTI MAHAJAN
A22: 19 | B22: 46132 | G22: =E22*F22 -> 0 | J22: =H22*I22 -> 0 | K22: =G22+J22 -> 0 | M22: =M21+K22-L22 -> 0
A23: 20 | B23: 46133 | E23: 1500 | F23: 91.67 | G23: =E23*F23 -> 137505 | J23: =H23*I23 -> 0 | K23: =G23+J23 -> 137505 | L23: =H23+K23 -> 137505 | M23: =M22+K23-L23 -> 0 | N23: VASUDEO NIVRUTTI MAHAJAN
A24: 21 | B24: 46133 | E24: 1740 | F24: 91.7 | G24: =E24*F24 -> 159558 | J24: =H24*I24 -> 0 | K24: =G24+J24 -> 159558 | L24: =H24+K24 -> 159558 | N24: SAYYED PETROLEUM - IOCL
A25: 22 | B25: 46133 | E25: 2000 | F25: 91.7 | G25: =E25*F25 -> 183400 | J25: =H25*I25 -> 0 | K25: =G25+J25 -> 183400 | L25: =H25+K25 -> 183400 | N25: BOHARDI KHURD - IOCL
A26: 23 | B26: 46134 | E26: 2000 | F26: 91.7 | G26: =E26*F26 -> 183400 | J26: =H26*I26 -> 0 | K26: =G26+J26 -> 183400 | L26: =H26+K26 -> 183400 | M26: =M23+K26-L26 -> 0 | N26: VASUDEO NIVRUTTI MAHAJAN
A27: 24 | B27: 46135 | G27: =E27*F27 -> 0 | J27: =H27*I27 -> 0 | K27: =G27+J27 -> 0 | M27: =M26+K27-L27 -> 0
A28: 25 | B28: 46136 | E28: 2000 | F28: 91.7 | G28: =E28*F28 -> 183400 | J28: =H28*I28 -> 0 | K28: =G28+J28 -> 183400 | L28: =H28+K28 -> 183400 | M28: =M27+K28-L28 -> 0 | N28: BABA FUELS STATION | O28: IOCL
A29: 26 | B29: 46137 | E29: 1000 | F29: 91.98 | G29: =E29*F29 -> 91980 | J29: =H29*I29 -> 0 | K29: =G29+J29 -> 91980 | L29: =H29+K29 -> 91980 | M29: =M28+K29-L29 -> 0 | N29: VASUDEO NIVRUTTI MAHAJAN | O29: BPCL
A30: 27 | B30: 46137 | E30: 2490 | F30: 91.67 | G30: =E30*F30 -> 228258.3 | K30: =G30+J30 -> 228258.3 | L30: =H30+K30 -> 228258.3 | M30: =M29+K30-L30 -> 0 | N30: VASUDEO NIVRUTTI MAHAJAN
A31: 28 | B31: 46137 | E31: 2175 | F31: 91.67 | G31: =E31*F31 -> 199382.25 | K31: =G31+J31 -> 199382.25 | L31: 228258.3 | M31: =M30+K31-L31 -> -28876.05 | N31: RAKSHA AUTO FUELS
A32: 29 | B32: 46138 | E32: 2000 | F32: 91.67 | G32: =E32*F32 -> 183340 | J32: =H32*I32 -> 0 | K32: =G32+J32 -> 183340 | L32: =H32+K32 -> 183340 | M32: =M31+K32-L32 -> -28876.05 | N32: VASUDEO NIVRUTTI MAHAJAN
A33: 30 | B33: 46139 | E33: 315 | F33: 91.67 | G33: =E33*F33 -> 28876.05 | J33: =H33*I33 -> 0 | K33: =G33+J33 -> 28876.05 | M33: =M32+K33-L33 -> 1.0913936e-11 | N33: RAKSHA AUTO FUELS
A34: 31 | B34: 46140 | E34: 1600 | F34: 91.7 | G34: =E34*F34 -> 146720 | J34: =H34*I34 -> 0 | K34: =G34+J34 -> 146720 | L34: =H34+K34 -> 146720 | M34: =M33+K34-L34 -> 0 | N34: BABA FUELS STATION
B35: 46140 | E35: 2000 | F35: 91.98 | G35: =E35*F35 -> 183960 | K35: =G35+J35 -> 183960 | L35: =H35+K35 -> 183960 | M35: =M34+K35-L35 -> 0 | N35: SHRIKRISHNA PETROLEUM
