Workbook

Sheet  MIs
A2: S.No | B2: NAme | C2: Lacation | D2: Card Number | E2: Card Number | F2: Category | G2: 1st Jan | I2: 2nd Jan | J2: 3rd Jan | K2: 4th Jan | L2: 5th Jan | M2: 6th Jan | N2: 7th Jan | O2: 8th Jan | P2: 9th Jan | Q2: 10th Jan | R2: 11th Jan | S2: 12th Jan | T2: 13th Jan | U2: 14th Jan | V2: 15th Jan | W2: 16th Jan | X2: 17th Jan | Y2: 18th Jan | Z2: 19th Jan | AA2: 20th Jan | AB2: 21st Jan | AC2: 22nd Jan | AD2: 23rd Jan | AE2: 24th Jan | AF2: 25th Jan | AG2: 26th Jan | AH2: 27th Jan | AI2: 28th Jan | AJ2: 29th Jan | AK2: 30th Jan | AL2: 31st Jan | AM2: Total
F3: Diesel
A4: 1 | B4: Rambabu | C4: HO(Two Wheeler) | D4: FC3450563999 | E4: Diesel | F4: 0 | G4: 0 | H4: 0 | I4: 0 | J4: 0 | K4: 0 | L4: 0 | M4: 0 | N4: 0 | O4: 0 | P4: 0 | Q4: 0 | R4: 0 | S4: 0 | T4: 0 | U4: 0 | V4: 0 | W4: 0 | X4: 5.22 | Y4: 0 | Z4: 0 | AA4: 0 | AB4: 0 | AC4: 0 | AD4: 60 | AE4: 0 | AF4: 0 | AG4: 0 | AH4: 4.56 | AI4: 0 | AJ4: 0 | AK4: 0 | AL4: 0 | AM4: =SUM(F4:AL4) -> 69.78
E5: Petrol | F5: 0 | G5: 4.69 | H5: 0 | I5: 0 | J5: 0 | K5: 0 | L5: 0 | M5: 0 | N5: 3.91 | O5: 0 | P5: 6.98 | Q5: 0 | R5: 0 | S5: 0 | T5: 0 | U5: 0 | V5: 0 | W5: 0 | X5: 0 | Y5: 0 | Z5: 0 | AB5: 0 | AC5: 0 | AD5: 0 | AE5: 0 | AF5: 0 | AG5: 0 | AH5: 0 | AI5: 0 | AJ5: 0 | AK5: 0 | AL5: 0 | AM5: =SUM(F5:AL5) -> 15.58
A6: 2 | B6: Hanumanth Rao | C6: HO | D6: FC3450676131 | E6: Diesel | F6: 0 | G6: 0 | H6: 0 | I6: 0 | J6: 0 | K6: 0 | L6: 0 | M6: 0 | N6: 0 | O6: 0 | P6: 0 | Q6: 0 | R6: 0 | S6: 0 | T6: 0 | U6: 0 | V6: 0 | W6: 0 | X6: 0 | Y6: 0 | Z6: 0 | AA6: 0 | AB6: 0 | AC6: 0 | AD6: 0 | AE6: 0 | AF6: 0 | AG6: 0 | AH6: 0 | AI6: 0 | AJ6: 0 | AK6: 0 | AL6: 0 | AM6: =SUM(F6:AL6) -> 0
E7: Petrol | F7: 0 | G7: 0 | H7: 0 | I7: 0 | J7: 0 | K7: 0 | L7: 0 | M7: 0 | N7: 0 | O7: 0 | P7: 0 | Q7: 0 | R7: 0 | S7: 0 | T7: 0 | U7: 0 | V7: 0 | W7: 0 | X7: 0 | Y7: 0 | Z7: 0 | AB7: 0 | AC7: 0 | AD7: 0 | AE7: 0 | AF7: 0 | AG7: 0 | AH7: 0 | AI7: 0 | AJ7: 0 | AK7: 0 | AL7: 0 | AM7: =SUM(F7:AL7) -> 0
A8: 3 | B8: Radhakrishna | C8: HO | D8: FC8000207658 | E8: Diesel | F8: 0 | G8: 0 | H8: 0 | I8: 0 | J8: 33.44 | K8: 0 | L8: 0 | M8: 0 | N8: 0 | O8: 0 | P8: 0 | Q8: 0 | R8: 35.53 | S8: 0 | T8: 0 | U8: 0 | V8: 0 | W8: 0 | X8: 0 | Y8: 0 | Z8: 0 | AA8: 0 | AB8: 33.44 | AC8: 0 | AD8: 0 | AE8: 0 | AF8: 0 | AG8: 0 | AH8: 0 | AI8: 0 | AJ8: 0 | AK8: 0 | AL8: 0 | AM8: =SUM(F8:AL8) -> 102.41
E9: Petrol | F9: 0 | G9: 0 | H9: 0 | I9: 0 | J9: 0 | K9: 0 | L9: 0 | M9: 0 | N9: 0 | O9: 0 | P9: 0 | Q9: 0 | R9: 0 | S9: 0 | T9: 0 | U9: 0 | V9: 0 | W9: 0 | X9: 0 | Y9: 0 | Z9: 0 | AB9: 0 | AC9: 0 | AD9: 0 | AE9: 0 | AF9: 0 | AG9: 0 | AH9: 0 | AI9: 0 | AJ9: 0 | AK9: 0 | AL9: 0 | AM9: =SUM(F9:AL9) -> 0
A10: 4 | B10: VIjay | C10: HO | D10: FC3450698859 | E10: Diesel | F10: 0 | G10: 0 | H10: 0 | I10: 0 | J10: 0 | K10: 0 | L10: 0 | M10: 0 | N10: 0 | O10: 0 | P10: 49.22 | Q10: 0 | R10: 0 | S10: 0 | T10: 0 | U10: 54.57 | V10: 0 | W10: 0 | X10: 0 | Y10: 0 | Z10: 0 | AA10: 0 | AB10: 0 | AC10: 0 | AD10: 49.8 | AE10: 0 | AF10: 0 | AG10: 0 | AH10: 0 | AI10: 0 | AJ10: 0 | AK10: 0 | AL10: 0 | AM10: =SUM(F10:AL10) -> 153.59
E11: Petrol | F11: 0 | G11: 0 | H11: 0 | I11: 0 | J11: 0 | K11: 0 | L11: 0 | M11: 0 | N11: 0 | O11: 0 | P11: 0 | Q11: 0 | R11: 0 | S11: 0 | T11: 0 | U11: 0 | V11: 0 | W11: 0 | X11: 0 | Y11: 0 | Z11: 0 | AB11: 0 | AC11: 0 | AD11: 0 | AE11: 0 | AF11: 0 | AG11: 0 | AH11: 0 | AI11: 0 | AJ11: 0 | AK11: 0 | AL11: 0 | AM11: =SUM(F11:AL11) -> 0
A12: 5 | B12: Client | C12: Hiriyur | D12: FC3450698864 | E12: Diesel | F12: 0 | G12: 0 | H12: 0 | I12: 0 | J12: 0 | K12: 0 | L12: 0 | M12: 0 | N12: 86.29 | O12: 0 | P12: 0 | Q12: 0 | R12: 0 | S12: 0 | T12: 0 | U12: 0 | V12: 0 | W12: 0 | X12: 0 | Y12: 0 | Z12: 0 | AA12: 0 | AB12: 0 | AC12: 0 | AD12: 145.61 | AE12: 0 | AF12: 0 | AG12: 0 | AH12: 0 | AI12: 0 | AJ12: 0 | AK12: 0 | AL12: 0 | AM12: =SUM(F12:AL12) -> 231.9
E13: Petrol | F13: 0 | G13: 0 | H13: 0 | I13: 0 | J13: 0 | K13: 0 | L13: 0 | M13: 0 | N13: 0 | O13: 0 | P13: 0 | Q13: 0 | R13: 0 | S13: 0 | T13: 0 | U13: 0 | V13: 0 | W13: 0 | X13: 0 | Y13: 0 | Z13: 0 | AB13: 0 | AC13: 0 | AD13: 0 | AE13: 0 | AF13: 0 | AG13: 0 | AH13: 0 | AI13: 0 | AJ13: 0 | AK13: 0 | AL13: 0 | AM13: =SUM(F13:AL13) -> 0
A14: 6 | B14: Client | C14: Hosadurga | D14: FC3450698865 | E14: Diesel | F14: 0 | G14: 0 | H14: 0 | I14: 0 | J14: 0 | K14: 0 | L14: 40 | M14: 40 | N14: 0 | O14: 36 | P14: 35 | Q14: 0 | R14: 0 | S14: 0 | T14: 0 | U14: 0 | V14: 0 | W14: 45 | X14: 45 | Y14: 43.53 | Z14: 40 | AA14: 43 | AB14: 0 | AC14: 40 | AD14: 0 | AE14: 40 | AF14: 0 | AG14: 0 | AH14: 0 | AI14: 0 | AJ14: 0 | AK14: 0 | AL14: 0 | AM14: =SUM(F14:AL14) -> 447.53
E15: Petrol | F15: 0 | G15: 0 | H15: 0 | I15: 0 | J15: 0 | K15: 0 | L15: 0 | M15: 0 | N15: 0 | O15: 0 | P15: 0 | Q15: 0 | R15: 0 | S15: 0 | T15: 0 | U15: 0 | V15: 0 | W15: 0 | X15: 0 | Y15: 0 | Z15: 0 | AB15: 0 | AC15: 0 | AD15: 0 | AE15: 0 | AF15: 0 | AG15: 0 | AH15: 0 | AI15: 0 | AJ15: 0 | AK15: 0 | AL15: 0 | AM15: =SUM(F15:AL15) -> 0
G18: Diesel Price

Sheet  Aug-26
A1: S.no | B1: Site Name | C1: Bunk Name | D1: Diesel(Liters) | E1: Diesel Amount | F1: Petrol(Liters) | G1: Petrol Amount | H1: Total Amount | I1: Opening Blance | J1: Amount Paid | K1: Closing Balances
A2: 1 | B2: Khammam-1 | C2: Divya laxmi ganapathi | D2: =+'Khammam-1'!E38 -> 26800 | E2: =+'Khammam-1'!G38 -> 2781840 | F2: =+'Khammam-1'!H38 -> 205 | G2: =+'Khammam-1'!J38 -> 23716.45 | H2: =E2+G2 -> 2805556.5 | I2: =+'Khammam-1'!K3 -> 3834148.7 | J2: =+'Khammam-1'!L38 -> 3834140 | K2: =H2+I2-J2 -> 2805565.2
A3: 2 | B3: Khammam-2 | C3: Jayasai union bunk | D3: =+'Khammam-2'!E38 -> 35123.528 | E3: =+'Khammam-2'!G38 -> 3646524.7 | F3: =+'Khammam-2'!H38 -> 515 | G3: =+'Khammam-2'!J38 -> 59595.8 | H3: =E3+G3 -> 3706120.5 | I3: =+'Khammam-2'!K3 -> 18929637 | J3: =+'Khammam-2'!L38 -> 22635758 | K3: =H3+I3-J3 -> 0
A4: 3 | B4: Khammam-3 | C4: JSASFuel Genie India Pvt.Ltd | D4: =+'Khammam-3'!E35 -> 0 | E4: =+'Khammam-3'!G35 -> 0 | F4: =+'Khammam-3'!H35 -> 0 | G4: =+'Khammam-3'!J35 -> 0 | H4: =E4+G4 -> 0 | I4: =+'Khammam-3'!M3 -> 1510680 | J4: =+'Khammam-3'!L35 -> 1510680 | K4: =H4+I4-J4 -> 0
A5: 4 | B5: Khammam | C5: Sai Madeana Filling Station | D5: =+'Khammam-4'!E35 -> 18900 | E5: =+'Khammam-4'!G35 -> 1958418 | F5: =+'Khammam-4'!H35 -> 70 | G5: =+'Khammam-4'!J35 -> 8084.3 | H5: =E5+G5 -> 1966502.3 | I5: =+'Khammam-4'!M3 -> 0 | J5: =+'Khammam-4'!L35 -> 1123138 | K5: =H5+I5-J5 -> 843364.3
A6: 5 | B6: Khammam | C6: Vajra mahalakshmi filling station | D6: =+' Khammam-5'!E35 -> 16260 | E6: =+' Khammam-5'!G35 -> 1684861.2 | F6: =+' Khammam-5'!H35 -> 240 | G6: =+' Khammam-5'!J35 -> 27717.6 | H6: =E6+G6 -> 1712578.8 | I6: =+' Khammam-5'!M3 -> 0 | J6: =+' Khammam-5'!L35 -> 1134007 | K6: =H6+I6-J6 -> 578571.8
A7: 6 | B7: Khammam-Cash&Carry | C7: NA | D7: =+' Khammam&Cash'!E46 -> 7032.753 | E7: =+' Khammam&Cash'!G46 -> 729999.76 | F7: =+' Khammam&Cash'!H46 -> 0 | G7: =+' Khammam&Cash'!J46 -> 0 | H7: =E7+G7 -> 729999.76 | I7: =+' Khammam&Cash'!M3 -> 0 | J7: =+' Khammam&Cash'!L46 -> 729999.76 | K7: =H7+I7-J7 -> 0
A8: 7 | B8: Jadcherla-2 | C8: Shree Poornima F/S | D8: =+'Jadcherla-4'!E35 -> 0 | E8: =+'Jadcherla-4'!G35 -> 0 | F8: =+'Jadcherla-4'!H35 -> 20 | G8: =+'Jadcherla-4'!J35 -> 2326.6 | H8: =E8+G8 -> 2326.6 | I8: =+'Jadcherla-4'!M3 -> 50273.68 | J8: =+'Jadcherla-4'!L35 -> 50000 | K8: =H8+I8-J8 -> 2600.28
A9: 8 | B9: Sangareddy-2 | C9: Durga Bhavani F/S | D9: =+' Sangareddy-2'!E35 -> 38.25 | E9: =+' Sangareddy-2'!G35 -> 3999.42 | F9: =+' Sangareddy-2'!H35 -> 20 | G9: =+' Sangareddy-2'!J35 -> 2330.8 | H9: =E9+G9 -> 6330.22 | I9: =+' Sangareddy-2'!M3 -> 52609.145 | J9: =+' Sangareddy-2'!L35 -> 58939.365 | K9: =H9+I9-J9 -> 0
A10: 9 | B10: Sangareddy-3 | C10: Shiva Parvathi Filling Station | D10: =+' Sangareddy-3'!E36 -> 9474 | E10: =+' Sangareddy-3'!G36 -> 988611.9 | F10: =+' Sangareddy-3'!H36 -> 84 | G10: =+' Sangareddy-3'!J36 -> 9823.68 | H10: =E10+G10 -> 998435.58 | I10: =+' Sangareddy-3'!M3 -> 754936.41 | J10: =+' Sangareddy-3'!L36 -> 1607217 | K10: =H10+I10-J10 -> 146154.99
A11: 10 | B11: NarayanaKhed | C11: Sai Shiva Filling Station | D11: =Narayankhed!E35 -> 1332.8144 | E11: =+Narayankhed!G35 -> 140000.59 | F11: =+Narayankhed!H35 -> 0 | G11: =+Narayankhed!J35 -> 0 | H11: =E11+G11 -> 140000.59 | I11: =+Narayankhed!M3 -> 0 | J11: =+Narayankhed!L35 -> 140000.59 | K11: =H11+I11-J11 -> 0
A12: 11 | B12: Dindi | C12: Akarapu Balakistamma Fillling | D12: =+Dindi!E35 -> 33.78 | E12: =+Dindi!G35 -> 3545.211 | F12: =+Dindi!H35 -> 0 | G12: =+Dindi!J35 -> 0 | H12: =E12+G12 -> 3545.211 | I12: =+Dindi!M3 -> 0 | J12: =+Dindi!L35 -> 3545.211 | K12: =H12+I12-J12 -> 0
A13: 12 | B13: Madanapalli | C13: NA | D13: =+'Madana palli'!E37 -> 0 | E13: =+'Madana palli'!G37 -> 0 | F13: =+'Madana palli'!H37 -> 3.4 | G13: =+'Madana palli'!J37 -> 399.364 | H13: =E13+G13 -> 399.364 | I13: =+'Madana palli'!M3 -> 0 | J13: =+'Madana palli'!L37 -> 399.364 | K13: =H13+I13-J13 -> 0
A14: 13 | B14: Kovvur | C14: Sri Venkateshwara Services | D14: =+'Sri Venkateshwara Services'!E37 -> 879.64 | E14: =+'Sri Venkateshwara Services'!G37 -> 92080.715 | F14: =+'Sri Venkateshwara Services'!H37 -> 70 | G14: =+'Sri Venkateshwara Services'!J37 -> 8187.2 | H14: =E14+G14 -> 100267.92 | I14: =+'Sri Venkateshwara Services'!M3 -> 0 | J14: =+'Sri Venkateshwara Services'!L37 -> 83230 | K14: =H14+I14-J14 -> 17037.915
A15: 14 | B15: Jangareddygudem | C15: Solasa Krishna Oil Company | D15: =+' Solasa Krishna OIl'!E37 -> 2182.97 | E15: =+' Solasa Krishna OIl'!G37 -> 230085.04 | F15: =+' Solasa Krishna OIl'!H37 -> 25.01 | G15: =+' Solasa Krishna OIl'!J37 -> 2944.6774 | H15: =E15+G15 -> 233029.72 | I15: =+' Solasa Krishna OIl'!M3 -> 0 | J15: =+' Solasa Krishna OIl'!L37 -> 186667 | K15: =H15+I15-J15 -> 46362.715
A16: 15 | B16: Amalapuram | C16: Royal Fill 'N' Fly | D16: =+'Amalapuram(KKD)'!E37 -> 7986.03 | E16: =+'Amalapuram(KKD)'!G37 -> 840536.86 | F16: =+'Amalapuram(KKD)'!H37 -> 141 | G16: =+'Amalapuram(KKD)'!J37 -> 16578.78 | H16: =E16+G16 -> 857115.64 | I16: =+'Amalapuram(KKD)'!M3 -> 0 | J16: =+'Amalapuram(KKD)'!L37 -> 430256 | K16: =H16+I16-J16 -> 426859.64
A17: 16 | B17: Yeleshwaram | C17: Sri sathya Filling Station | D17: =+'Yeleshwaram(KKD)'!E37 -> 954.16 | E17: =+'Yeleshwaram(KKD)'!G37 -> 100625.71 | F17: =+'Yeleshwaram(KKD)'!H37 -> 35 | G17: =+'Yeleshwaram(KKD)'!J37 -> 4124.4 | H17: =E17+G17 -> 104750.11 | I17: =+'Yeleshwaram(KKD)'!M3 -> 19106.6 | J17: =+'Yeleshwaram(KKD)'!L37 -> 115358 | K17: =H17+I17-J17 -> 8498.7136
A18: 17 | B18: Pitapuam | C18: Satya Siva Durga Agencies, Chebrolu | D18: =+' Pitapram(KKD)'!E37 -> 5592.86 | E18: =+' Pitapram(KKD)'!G37 -> 588424.8 | F18: =+' Pitapram(KKD)'!H37 -> 188 | G18: =+' Pitapram(KKD)'!J37 -> 22105.04 | H18: =E18+G18 -> 610529.84 | I18: =+' Pitapram(KKD)'!M3 -> 92349.157 | J18: =+' Pitapram(KKD)'!L37 -> 578525 | K18: =H18+I18-J18 -> 124354
A19: 18 | B19: Kakinada | C19: Multiple bunks | D19: =+'Multiple bunks(KKD)'!E289 -> 1535.73 | E19: =+'Multiple bunks(KKD)'!G289 -> 161495.57 | F19: =+'Multiple bunks(KKD)'!H289 -> 184.58 | G19: =+'Multiple bunks(KKD)'!J289 -> 21686.104 | H19: =E19+G19 -> 183181.67 | I19: =+'Multiple bunks(KKD)'!M3 -> 0 | J19: =+'Multiple bunks(KKD)'!L289 -> 183181.67 | K19: =H19+I19-J19 -> 0
A20: 19 | B20: YG Gudda-2 | C20: Pankaja HP Fuel Center | D20: =+'YG Gudda'!E39 -> 9400 | E20: =+'YG Gudda'!G39 -> 931916 | F20: =+'YG Gudda'!H39 -> 245 | G20: =+'YG Gudda'!J39 -> 27253.8 | H20: =E20+G20 -> 959169.8 | I20: =+'YG Gudda'!M3 -> 296621.36 | J20: =+'YG Gudda'!L39 -> 1128000 | K20: =H20+I20-J20 -> 127791.16
A21: 20 | B21: YG Gudda-2 | C21: One stop | D21: =+' YG Gudda-2'!E39 -> 1500 | E21: =+' YG Gudda-2'!G39 -> 148530 | F21: =+' YG Gudda-2'!H39 -> 70 | G21: =+' YG Gudda-2'!J39 -> 7778.4 | H21: =E21+G21 -> 156308.4 | I21: =+' YG Gudda-2'!M3 -> 299.3192 | J21: =+' YG Gudda-2'!L39 -> 0 | K21: =H21+I21-J21 -> 156607.72
A22: 21 | B22: Hosadurga-2 | C22: Shree Veeraprathap Fuel | D22: =+'Hosadurga -2'!E35 -> 2400 | E22: =+'Hosadurga -2'!G35 -> 238512 | F22: =+'Hosadurga -2'!H35 -> 240 | G22: =+'Hosadurga -2'!J35 -> 26812.8 | H22: =+'Hosadurga -2'!K35 -> 265324.8 | I22: =+'Hosadurga -2'!K3 -> 484.7941 | J22: =+'Hosadurga -2'!L35 -> 147000 | K22: =H22+I22-J22 -> 118809.59
A23: 22 | B23: Malebennuru(KUWSDB) | C23: Sri Ramanjuneya Service Station | D23: =+'Malebenur(KUWSDB)'!E37 -> 4150 | E23: =+'Malebenur(KUWSDB)'!G37 -> 414958.5 | F23: =+'Malebenur(KUWSDB)'!H37 -> 200 | G23: =+'Malebenur(KUWSDB)'!J37 -> 22405.2 | H23: =E23+G23 -> 437363.7 | I23: =+'Malebenur(KUWSDB)'!K3 -> 130766.71 | J23: =+'Malebenur(KUWSDB)'!L37 -> 445902 | K23: =H23+I23-J23 -> 122228.41
A24: 23 | B24: kadur | C24: Vishal Service Station | D24: =+Kadur!E35 -> 0 | E24: =+Kadur!G35 -> 0 | F24: =+Kadur!H35 -> 0 | G24: =+Kadur!J35 -> 0 | H24: =E24+G24 -> 0 | I24: =+Kadur!K3 -> 673026.9 | J24: =+Kadur!L35 -> 673026 | K24: =H24+I24-J24 -> 0.9
A25: 24 | B25: Hiriyur(VJNL) | C25: Sri Balaji Agencies | D25: =+'Hiriyur(VJNL)'!E35 -> 4000 | E25: =+'Hiriyur(VJNL)'!G35 -> 400360 | F25: =+'Hiriyur(VJNL)'!H35 -> 315 | G25: =+'Hiriyur(VJNL)'!J35 -> 35317.8 | H25: =E25+G25 -> 435677.8 | I25: =+'Hiriyur(VJNL)'!K3 -> 208267.9 | J25: =+'Hiriyur(VJNL)'!L35 -> 424000 | K25: =H25+I25-J25 -> 219945.7
A26: 25 | B26: Chellakere(KUWSDB) | C26: Shivaganga Service Station | D26: =+'Chellakere -1'!E38 -> 3000 | E26: =+'Chellakere -1'!G38 -> 300150 | F26: =+'Chellakere -1'!H38 -> 175 | G26: =+'Chellakere -1'!J38 -> 19612.25 | H26: =E26+G26 -> 319762.25 | I26: =+'Chellakere -1'!K3 -> 210978.25 | J26: =+'Chellakere -1'!L38 -> 530740 | K26: =H26+I26-J26 -> 0.5014
A27: 26 | B27: Chellakere(KUWSDB)-09 | C27: Shivaganga Service Station | D27: =+' Chellakere-PKG-9'!E36 -> 735.99 | E27: =+' Chellakere-PKG-9'!G36 -> 73532.47 | F27: =+' Chellakere-PKG-9'!H36 -> 41.02 | G27: =+' Chellakere-PKG-9'!J36 -> 4597.1114 | H27: =E27+G27 -> 78129.582 | I27: =+' Chellakere-PKG-9'!M3 -> 0 | J27: =+' Chellakere-PKG-9'!L36 -> 78129.582 | K27: =H27+I27-J27 -> 0
A28: 27 | B28: Molakalmuru | C28: Sri Lakshmi Venkateshwara Filling Station | D28: =+Molakamuru!E35 -> 900 | E28: =+Molakamuru!G35 -> 90036 | F28: =+Molakamuru!H35 -> 85 | G28: =+Molakamuru!J35 -> 9525.1 | H28: =E28+G28 -> 99561.1 | I28: =+Molakamuru!K3 -> 50699.16 | J28: =+Molakamuru!L35 -> 115000 | K28: =H28+I28-J28 -> 35260.26
A29: 28 | B29: Chennagiri | C29: NA | D29: =+' Chennagiri'!E35 -> 860 | E29: =+' Chennagiri'!G35 -> 85894.2 | F29: =+' Chennagiri'!H35 -> 78 | G29: =+' Chennagiri'!J35 -> 8740.68 | H29: =E29+G29 -> 94634.88 | I29: =+' Chennagiri'!K3 -> 0 | J29: =+' Chennagiri'!L35 -> 94634.88 | K29: =H29+I29-J29 -> 0
A30: 29 | B30: Khanapur(PKG-3) | C30: V.V.Varde | D30: =+Khanapur!E35 -> 865.03 | E30: =+Khanapur!G35 -> 85369.611 | F30: =+Khanapur!H35 -> 90 | G30: =+Khanapur!J35 -> 9966.6 | H30: =E30+G30 -> 95336.211 | I30: =+Khanapur!M3 -> 84731.659 | J30: =+Khanapur!L35 -> 138271 | K30: =H30+I30-J30 -> 41796.87
A31: 30 | B31: Munavalli(PKG-3) | C31: Shre Shiva Petroleum | D31: =+'Munavali-2'!E40 -> 5000 | E31: =+'Munavali-2'!G40 -> 496750 | F31: =+'Munavali-2'!H40 -> 30 | G31: =+'Munavali-2'!J40 -> 3343.5 | H31: =E31+G31 -> 500093.5 | I31: =+'Munavali-2'!M3 -> 146708 | J31: =+'Munavali-2'!L40 -> 300000 | K31: =H31+I31-J31 -> 346801.5
A32: 31 | B32: Munavalli(PKG-3) | C32: Daneshwari Petroleum | D32: =+' Munavali'!E39 -> 200 | E32: =+' Munavali'!G39 -> 19826 | F32: =+' Munavali'!H39 -> 217.31 | G32: =+' Munavali'!J39 -> 24167.045 | H32: =E32+G32 -> 43993.045 | I32: =+' Munavali'!M3 -> 274277.22 | J32: =+' Munavali'!L39 -> 317605 | K32: =H32+I32-J32 -> 665.2699
A33: 32 | B33: Borgaon(PKG-3) | C33: Aadisagar Petrolium | D33: =+Borgaon!E35 -> 0 | E33: =+Borgaon!G35 -> 0 | F33: =+Borgaon!H35 -> 0 | G33: =+Borgaon!J35 -> 0 | H33: =E33+G33 -> 0 | I33: =+Borgaon!K3 -> 208.3907 | J33: =+Borgaon!L35 -> 208.39 | K33: =H33+I33-J33 -> 0.00069999999
A34: 33 | B34: Ugar,Kudichi(PKG-3) | C34: Shiri Bhrhmanath Petrolium | D34: =+'Ugar,Khagwad,Kudichi'!E37 -> 7624 | E34: =+'Ugar,Khagwad,Kudichi'!G37 -> 760417.76 | F34: =+'Ugar,Khagwad,Kudichi'!H37 -> 297 | G34: =+'Ugar,Khagwad,Kudichi'!J37 -> 33361.15 | H34: =E34+G34 -> 793778.91 | I34: =+'Ugar,Khagwad,Kudichi'!M3 -> 342020.48 | J34: =+'Ugar,Khagwad,Kudichi'!L37 -> 551965.02 | K34: =H34+I34-J34 -> 583834.37
A35: 34 | B35: Shedbal | C35: Varad Petroluem | D35: =+shedbal!E38 -> 3478.18 | E35: =+shedbal!G38 -> 346853.66 | F35: =+shedbal!H38 -> 192 | G35: =+shedbal!J38 -> 21475.2 | H35: =E35+G35 -> 368328.86 | I35: =+shedbal!M3 -> 506281.15 | J35: =+shedbal!L38 -> 703968.95 | K35: =H35+I35-J35 -> 170641.05
A36: 35 | B36: Kabbur(PKG-3) | C36: Shri Jai Hanuman Petrolium | D36: =+Kabbur!E35 -> 352 | E36: =+Kabbur!G35 -> 34992.32 | F36: =+Kabbur!H35 -> 23.23 | G36: =+Kabbur!J35 -> 2590.3773 | H36: =E36+G36 -> 37582.697 | I36: 0 | J36: =+Kabbur!L35 -> 37582.697 | K36: =H36+I36-J36 -> 0
A37: 36 | B37: Kumta (PKG-1) | C37: V.M.Mirjankar (Kumta) Bharat | D37: =+kumta!E41 -> 1229 | E37: =+kumta!G41 -> 122629.62 | F37: =+kumta!H41 -> 100 | G37: =+kumta!J41 -> 11198 | H37: =E37+G37 -> 133827.62 | I37: =kumta!M3 -> 60343.607 | J37: =+kumta!L41 -> 170079 | K37: =H37+I37-J37 -> 24092.227
A38: 37 | B38: Jalgaon-2 | C38: Nayara | D38: =+'Jalgoan-2'!E56 -> 3826.03 | E38: ='Jalgoan-2'!G56 -> 380734.65 | F38: =+'Jalgoan-2'!H56 -> 160 | G38: =+'Jalgoan-2'!J56 -> 18108.8 | H38: =E38+G38 -> 398843.45 | I38: =+'Jalgoan-2'!M3 -> 4531108.2 | J38: =+'Jalgoan-2'!L56 -> 4879951.6 | K38: =H38+I38-J38 -> 50000.028
A39: 38 | B39: MKBD | C39: Shree Sai Samarth Petroleum | D39: =+MKBD!E42 -> 3000 | E39: =+MKBD!G42 -> 296820 | F39: =+MKBD!H42 -> 50 | G39: =+MKBD!J42 -> 5613.5 | H39: =E39+G39 -> 302433.5 | I39: =+MKBD!K3 -> 929513.51 | J39: =+MKBD!L42 -> 1141380 | K39: =H39+I39-J39 -> 90567.01
A40: 39 | B40: Haveri | C40: M/s Magavi City Fuels | D40: =' Haveri-2'!E42 -> 2755.91 | E40: =' Haveri-2'!G42 -> 273661.86 | F40: =' Haveri-2'!H42 -> 74.5 | G40: =' Haveri-2'!J42 -> 8299.3 | H40: =E40+G40 -> 281961.16 | I40: =' Haveri-2'!M3 -> 119035.39 | J40: =+' Haveri-2'!L42 -> 359944 | K40: =H40+I40-J40 -> 41052.548
A41: 40 | B41: Guttal-2 | C41: Himagiri Petroleum | D41: =+' Guttal-2'!E35 -> 6294 | E41: =+' Guttal-2'!G35 -> 626882.4 | F41: =+' Guttal-2'!H35 -> 207.93 | G41: =+' Guttal-2'!J35 -> 23227.86 | H41: =E41+G41 -> 650110.26 | I41: =+' Guttal-2'!M3 -> 164389.72 | J41: =+' Guttal-2'!L35 -> 406000 | K41: =H41+I41-J41 -> 408499.98
A42: 41 | B42: Rattihali-2 | C42: Shiva Oil Traders | D42: =+'Rattihali-2'!E37 -> 2650.91 | E42: =+'Rattihali-2'!G37 -> 264295.73 | F42: =+'Rattihali-2'!H37 -> 69 | G42: =+'Rattihali-2'!J37 -> 7715.58 | H42: =E42+G42 -> 272011.31 | I42: =+'Rattihali-2'!M3 -> 343880.92 | J42: =+'Rattihali-2'!L37 -> 471000 | K42: =H42+I42-J42 -> 144892.23
A43: 42 | B43: Gajendragada | C43: Vanasri Petrol Pump | D43: =+Gajendragada!E36 -> 979 | E43: =+Gajendragada!G36 -> 97547.56 | F43: =+Gajendragada!H36 -> 84.06 | G43: =+Gajendragada!J36 -> 9395.3862 | H43: =E43+G43 -> 106942.95 | I43: =+Gajendragada!K3 -> 59887.243 | J43: =+Gajendragada!L36 -> 150654 | K43: =H43+I43-J43 -> 16176.189
A44: 43 | B44: Gokak(PKG-3) | C44: AJ Petrolinks | D44: =+'Gokak Dharwad PKG 3'!E42 -> 8436.67 | E44: =+'Gokak Dharwad PKG 3'!G42 -> 837676.96 | F44: =+'Gokak Dharwad PKG 3'!H42 -> 95 | G44: =+'Gokak Dharwad PKG 3'!J42 -> 10630.75 | H44: =E44+G44 -> 848307.71 | I44: =+'Gokak Dharwad PKG 3'!K3 -> 442814.46 | J44: =+'Gokak Dharwad PKG 3'!L42 -> 1109000 | K44: =H44+I44-J44 -> 182122.17
A45: 44 | B45: Hukkere | C45: TR Assocites | D45: =+' TR Associates'!E35 -> 7542.24 | E45: =+' TR Associates'!G35 -> 747662.25 | F45: =+' TR Associates'!H35 -> 0 | G45: =+' TR Associates'!J35 -> 0 | H45: =E45+G45 -> 747662.25 | I45: =+' TR Associates'!M3 -> 1398189.2 | J45: =+' TR Associates'!L35 -> 2009750 | K45: =H45+I45-J45 -> 136101.45
A46: 45 | B46: Ankaligi | C46: Shivaganga | D46: =+Ankalgi!E35 -> 2615.48 | E46: =+Ankalgi!G35 -> 259272.53 | F46: =+Ankalgi!H35 -> 85 | G46: =+Ankalgi!J35 -> 9452.85 | H46: =E46+G46 -> 268725.38 | I46: =+Ankalgi!M3 -> 114274.94 | J46: =+Ankalgi!L35 -> 351157 | K46: =H46+I46-J46 -> 31843.318
A47: 46 | B47: Ghattaprabha | C47: Shri Deshpande | D47: =+'SHRI DESHPANDE'!E35 -> 6753.855 | E47: =+'SHRI DESHPANDE'!G35 -> 671130.57 | F47: =+'SHRI DESHPANDE'!H35 -> 299 | G47: =+'SHRI DESHPANDE'!J35 -> 33326.54 | H47: =E47+G47 -> 704457.11 | I47: =+'SHRI DESHPANDE'!M3 -> 1046236.7 | J47: =+'SHRI DESHPANDE'!L35 -> 1606081 | K47: =H47+I47-J47 -> 144612.81
A48: 47 | B48: ShankeshWAR | C48: SR Patil | D48: =+' Shankeshwar'!E35 -> 160.18 | E48: =+' Shankeshwar'!G35 -> 15877.042 | F48: =+' Shankeshwar'!H35 -> 40 | G48: =+' Shankeshwar'!J35 -> 4448 | H48: =E48+G48 -> 20325.042 | I48: =' Shankeshwar'!M3 -> 0 | J48: =+' Shankeshwar'!L35 -> 20325.042 | K48: =H48+I48-J48 -> 0
A49: 48 | B49: Talikote(PKG-1) | C49: Raykar Oil Agencies | D49: =+' Talikote'!E48 -> 1123.106 | E49: =+' Talikote'!G48 -> 111537.08 | F49: =+' Talikote'!H48 -> 72.66 | G49: =+' Talikote'!J48 -> 8095.7772 | H49: =E49+G49 -> 119632.86 | I49: =+' Talikote'!N3 -> 20180.949 | J49: =+' Talikote'!L48 -> 130000 | K49: =H49+I49-J49 -> 9813.8077
A50: 49 | B50: Chadchan(PKG-1) | C50: Khavekar Petrolium | D50: =+Chadchan!E35 -> 950.98 | E50: =+Chadchan!G35 -> 94261.138 | F50: =+Chadchan!H35 -> 91.82 | G50: =+Chadchan!J35 -> 10209.466 | H50: =E50+G50 -> 104470.6 | I50: =+Chadchan!K3 -> 118310.18 | J50: =+Chadchan!L35 -> 218819 | K50: =H50+I50-J50 -> 3961.7789
A51: 50 | B51: Sindagi | C51: G.P.PORWAL | D51: =+Sindagi!E35 -> 330 | E51: =+Sindagi!G35 -> 32693.1 | F51: =+Sindagi!H35 -> 0 | G51: =+Sindagi!J35 -> 0 | H51: =E51+G51 -> 32693.1 | I51: =+Sindagi!M3 -> 23593.44 | J51: =+Sindagi!L35 -> 46380 | K51: =H51+I51-J51 -> 9906.54
A52: 51 | B52: Muddebihal(PKG-1)2 | C52: PS NAGATHAN PETROLIUM | D52: =+'Muddebhihal-2'!E50 -> 1667.9 | E52: =+'Muddebhihal-2'!G50 -> 165480.86 | F52: =+'Muddebhihal-2'!H50 -> 43 | G52: =+'Muddebhihal-2'!J50 -> 4881.06 | H52: =+'Muddebhihal-2'!K50 -> 170361.92 | I52: =+'Muddebhihal-2'!M3 -> 184308.75 | J52: =+'Muddebhihal-2'!L50 -> 336597 | K52: =+'Muddebhihal-2'!M49 -> 18073.67
A53: 52 | B53: Almela(PKG-1) | C53: Shiddeshwar Petroleums | D53: =+Alemela!E43 -> 360.89 | E53: =+Alemela!G43 -> 35826.587 | F53: =+Alemela!H43 -> 51.04 | G53: =+Alemela!J43 -> 5684.8352 | H53: =E53+G53 -> 41511.422 | I53: =+Alemela!M3 -> 28530.32 | J53: =+Alemela!L43 -> 68954 | K53: =H53+I53-J53 -> 1087.7422
A54: 53 | B54: Nalatwad(PKG-1) | C54: Shri Pawad Basaweshwar Petroleums | D54: =+Nalatwad!E43 -> 431.87 | E54: =+Nalatwad!G43 -> 42945.153 | F54: =+Nalatwad!H43 -> 52.95 | G54: =+Nalatwad!J43 -> 5906.2805 | H54: =E54+G54 -> 48851.433 | I54: =+Nalatwad!M3 -> 121032.21 | J54: =+Nalatwad!L43 -> 154220 | K54: =H54+I54-J54 -> 15663.641
A55: 54 | B55: Srirangapatna | C55: Anupama F/S | D55: =+Srirangapatna!E35 -> 50.82 | E55: =+Srirangapatna!G35 -> 5000.1798 | F55: =+Srirangapatna!H35 -> 27.15 | G55: =+Srirangapatna!J35 -> 2998.446 | H55: =E55+G55 -> 7998.6258 | I55: 0 | J55: =+Srirangapatna!L35 -> 7998.6258 | K55: =H55+I55-J55 -> 0
A56: 55 | B56: HO(DG) | C56: JSASFuel Genie India Pvt.Ltd | D56: =+'HO(DG)'!E47 -> 1160 | E56: =+'HO(DG)'!G47 -> 120361.6 | F56: =+'HO(DG)'!H47 -> 0 | G56: =+'HO(DG)'!J47 -> 0 | H56: =E56+G56 -> 120361.6 | I56: =+'HO(DG)'!M3 -> 265977.75 | J56: =+'HO(DG)'!L47 -> 386339.35 | K56: =H56+I56-J56 -> 0
A57: Total | D57: =SUM(D2:D56) -> 230910.56 | E57: =SUM(E2:E56) -> 23581445 | F57: =SUM(F2:F56) -> 5702.66 | G57: =SUM(G2:G56) -> 645760.24 | H57: =SUM(H2:H56) -> 24227205 | I57: =SUM(I2:I56) -> 38140719 | J57: =SUM(J2:J56) -> 54115705 | K57: =H57+I57-J57 -> 8252219.9
A62: S.no | B62: Site Name | C62: Bunk Name | D62: Diesel(Liters) | E62: Diesel Amount | F62: Petrol(Liters) | G62: Petrol Amount | H62: Total Amount | I62: Opening Blance | J62: Amount Paid | K62: Closing Balances
A63: 39 | B63: {=VLOOKUP(A63,A1:K55,{2,3,4,5,6,7,8,9,10,11},FALSE)} -> Haveri | C63: M/s Magavi City Fuels | D63: 2755.91 | E63: 273661.86 | F63: 74.5 | G63: 8299.3 | H63: 281961.16 | I63: 119035.39 | J63: 359944 | K63: 41052.548
B65: Site Name | C65: Bunk Name | D65: Diesel(Liters) | E65: Diesel Amount | F65: Petrol(Liters) | G65: Petrol Amount | H65: Total Amount | I65: Opening Blance | J65: Amount Paid | K65: Closing Balances
B66: Jalgaon-2 | C66: {=VLOOKUP(B66,B1:K55,{2,3,4,5,6,7,8,9,10},FALSE)} -> Nayara | D66: 3826.03 | E66: 380734.65 | F66: 160 | G66: 18108.8 | H66: 398843.45 | I66: 4531108.2 | J66: 4879951.6 | K66: 50000.028
B73: 60000
B74: 18000
B75: 18000
B76: 75000
B77: 360000

Sheet HO(DG)
A1: JSASFuel Genie India Pvt.Ltd
A2: S.No | B2: Date | C2: GRN No | D2: Ind No/Bill No | E2: Diesel (Lts) | F2: Price | G2: Amount | H2: Petrol (Lts) | I2: Price | J2: Amount | K2: Total amount | L2: Amount paid | M2: As on date | N2: Remarks
A3: Opening Balance | K3: 265977.75 | M3: 265977.75
A4: 1 | B4: 46235 | G4: =E4*F4 -> 0 | H4: 0 | I4: 0 | J4: =H4*I4 -> 0 | K4: =G4+J4 -> 0 | L4: 0 | M4: =M3+K4-L4 -> 265977.75
A5: 2 | B5: 46236 | G5: =E5*F5 -> 0 | K5: =G5+J5 -> 0 | M5: =M4+K5-L5 -> 265977.75
A6: 3 | B6: 46237 | E6: 70 | F6: 103.76 | G6: =E6*F6 -> 7263.2 | K6: =G6+J6 -> 7263.2 | L6: =H6+K6 -> 7263.2 | M6: =M5+K6-L6 -> 265977.75
A7: 4 | B7: 46238 | G7: =E7*F7 -> 0 | K7: =G7+J7 -> 0 | M7: =M6+K7-L7 -> 265977.75
A8: 5 | B8: 46239 | E8: 70 | F8: 103.76 | G8: =E8*F8 -> 7263.2 | K8: =G8+J8 -> 7263.2 | L8: =H8+K8 -> 7263.2 | M8: =M7+K8-L8 -> 265977.75
A9: 6 | B9: 46240 | G9: =E9*F9 -> 0 | K9: =G9+J9 -> 0 | M9: =M8+K9-L9 -> 265977.75
A10: 7 | B10: 46241 | E10: 140 | F10: 103.76 | G10: =E10*F10 -> 14526.4 | K10: =G10+J10 -> 14526.4 | L10: =H10+K10 -> 14526.4 | M10: =M9+K10-L10 -> 265977.75
B11: 46242 | G11: =E11*F11 -> 0 | K11: =G11+J11 -> 0 | L11: =H11+K11 -> 0 | M11: =M10+K11-L11 -> 265977.75
A12: 8 | B12: 46243 | G12: =E12*F12 -> 0 | K12: =G12+J12 -> 0 | M12: =M11+K12-L12 -> 265977.75
A13: 9 | B13: 46244 | E13: 70 | F13: 103.76 | G13: =E13*F13 -> 7263.2 | K13: =G13+J13 -> 7263.2 | L13: =H13+K13 -> 7263.2 | M13: =M12+K13-L13 -> 265977.75
A14: 10 | B14: 46245 | E14: 70 | F14: 103.76 | G14: =E14*F14 -> 7263.2 | K14: =G14+J14 -> 7263.2 | L14: =H14+K14 -> 7263.2 | M14: =M13+K14-L14 -> 265977.75
A15: 11 | B15: 46246 | G15: =E15*F15 -> 0 | K15: =G15+J15 -> 0 | M15: =M14+K15-L15 -> 265977.75
A16: 12 | B16: 46247 | E16: 70 | F16: 103.76 | G16: =E16*F16 -> 7263.2 | K16: =G16+J16 -> 7263.2 | L16: =H16+K16 -> 7263.2 | M16: =M15+K16-L16 -> 265977.75 | N16: Credit Card
A17: 13 | B17: 46248 | G17: =E17*F17 -> 0 | K17: =G17+J17 -> 0 | L17: 265910 | M17: =M16+K17-L17 -> 67.75
B18: 46248 | E18: 70 | F18: 103.76 | G18: =E18*F18 -> 7263.2 | K18: =G18+J18 -> 7263.2 | L18: =H18+K18 -> 7263.2 | M18: =M17+K18-L18 -> 67.75
A19: 14 | B19: 46249 | G19: =E19*F19 -> 0 | K19: =G19+J19 -> 0 | L19: 67.75 | M19: =M18+K19-L19 -> 0 | N19: Roundoff
A20: 15 | B20: 46250 | G20: =E20*F20 -> 0 | K20: =G20+J20 -> 0 | M20: =M19+K20-L20 -> 0
A21: 16 | B21: 46251 | G21: =E21*F21 -> 0 | K21: =G21+J21 -> 0 | M21: =M20+K21-L21 -> 0
A22: 17 | B22: 46252 | G22: =E22*F22 -> 0 | K22: =G22+J22 -> 0 | M22: =M21+K22-L22 -> 0
A23: 18 | B23: 46253 | E23: 140 | F23: 103.76 | G23: =E23*F23 -> 14526.4 | K23: =G23+J23 -> 14526.4 | L23: =H23+K23 -> 14526.4 | M23: =M22+K23-L23 -> 0
A24: 19 | B24: 46254 | E24: 70 | F24: 103.76 | G24: =E24*F24 -> 7263.2 | K24: =G24+J24 -> 7263.2 | L24: =H24+K24 -> 7263.2 | M24: =M23+K24-L24 -> 0
A25: 20 | B25: 46255 | G25: =E25*F25 -> 0 | K25: =G25+J25 -> 0 | M25: =M24+K25-L25 -> 0
A26: 21 | B26: 46256 | E26: 70 | F26: 103.76 | G26: =E26*F26 -> 7263.2 | K26: =G26+J26 -> 7263.2 | L26: =H26+K26 -> 7263.2 | M26: =M25+K26-L26 -> 0
A27: 22 | B27: 46257 | G27: =E27*F27 -> 0 | K27: =G27+J27 -> 0 | M27: =M26+K27-L27 -> 0
A28: 23 | B28: 46258 | E28: 50 | F28: 103.76 | G28: =E28*F28 -> 5188 | K28: =G28+J28 -> 5188 | L28: =H28+K28 -> 5188 | M28: =M27+K28-L28 -> 0
A29: 24 | B29: 46259 | G29: =E29*F29 -> 0 | K29: =G29+J29 -> 0 | M29: =M28+K29-L29 -> 0
A30: 25 | B30: 46260 | E30: 100 | F30: 103.76 | G30: =E30*F30 -> 10376 | K30: =G30+J30 -> 10376 | L30: =H30+K30 -> 10376 | M30: =M29+K30-L30 -> 0
A31: 26 | B31: 46261 | G31: =E31*F31 -> 0 | K31: =G31+J31 -> 0 | M31: =M30+K31-L31 -> 0
A32: 27 | B32: 46262 | E32: 100 | F32: 103.76 | G32: =E32*F32 -> 10376 | K32: =G32+J32 -> 10376 | L32: =H32+K32 -> 10376 | M32: =M31+K32-L32 -> 0
A33: 28 | B33: 46263 | G33: =E33*F33 -> 0 | K33: =G33+J33 -> 0 | M33: =M32+K33-L33 -> 0
B34: 46264 | G34: =E34*F34 -> 0 | M34: =M33+K34-L34 -> 0
A35: 29 | B35: 46265 | E35: 70 | F35: 103.76 | G35: =E35*F35 -> 7263.2 | K35: =G35+J35 -> 7263.2 | L35: =H35+K35 -> 7263.2 | M35: =M34+K35-L35 -> 0
G36: =E36*F36 -> 0 | K36: =G36+J36 -> 0 | M36: =M35+K36-L36 -> 0
A37: 30 | K37: =G37+J37 -> 0 | M37: =M36+K37-L37 -> 0
A38: 31 | M38: =M37+K38-L38 -> 0
A39: 32 | M39: =M38+K39-L39 -> 0
A40: 33
A41: 34
A42: 35
A43: 36
A44: 37
A45: 38 | O45: 2669494 | P45: =O45-M45 -> 2669494
E46: 0 | F46: 0 | G46: =E46*F46 -> 0 | J46: =H46*I46 -> 0 | K46: =G46+J46 -> 0 | M46: =M45+K46-L46 -> 0
E47: =SUM(E4:E45) -> 1160 | G47: =SUM(G4:G45) -> 120361.6 | H47: =SUM(H4:H45) -> 0 | J47: =SUM(J4:J45) -> 0 | K47: =SUM(K4:K45) -> 120361.6 | L47: =SUM(L4:L45) -> 386339.35
M56: 2408309
M57: 5327.86
M58: =M56-M57 -> 2402981.1

Sheet Khammam-1
A1: Divya laxmi ganapathi
A2: S.No | B2: Date | C2: GRN No | D2: Ind No/Bill No | E2: Diesel (Lts) | F2: Price | G2: Amount | H2: Petrol (Lts) | I2: Price | J2: Amount | K2: Total amount | L2: Amount paid | M2: As 0n Date | N2: Remarks
A3: Opening Balance | K3: 3834148.7 | M3: 3834148.7 | O3: =K3-M3 -> 0
A4: 1 | B4: 46235 | G4: =E4*F4 -> 0 | K4: =G4+J4 -> 0 | M4: =M3+K4-L4 -> 3834148.7
A5: 2 | B5: 46236 | G5: =E5*F5 -> 0 | J5: =H5*I5 -> 0 | K5: =G5+J5 -> 0 | M5: =M4+K5-L5 -> 3834148.7
A6: 3 | B6: 46237 | G6: =E6*F6 -> 0 | J6: =H6*I6 -> 0 | K6: =G6+J6 -> 0 | M6: =M5+K6-L6 -> 3834148.7
A7: 4 | B7: 46238 | G7: =E7*F7 -> 0 | J7: =H7*I7 -> 0 | K7: =G7+J7 -> 0 | M7: =M6+K7-L7 -> 3834148.7
A8: 5 | B8: 46239 | G8: =E8*F8 -> 0 | J8: =H8*I8 -> 0 | K8: =G8+J8 -> 0 | M8: =M7+K8-L8 -> 3834148.7
A9: 6 | B9: 46240 | G9: =E9*F9 -> 0 | J9: =H9*I9 -> 0 | K9: =G9+J9 -> 0 | M9: =M8+K9-L9 -> 3834148.7
A10: 7 | B10: 46241 | G10: =E10*F10 -> 0 | J10: =H10*I10 -> 0 | K10: =G10+J10 -> 0 | M10: =M9+K10-L10 -> 3834148.7
A11: 8 | B11: 46242 | G11: =E11*F11 -> 0 | J11: =H11*I11 -> 0 | K11: =G11+J11 -> 0 | M11: =M10+K11-L11 -> 3834148.7
A12: 9 | B12: 46243 | G12: =E12*F12 -> 0 | J12: =H12*I12 -> 0 | K12: =G12+J12 -> 0 | M12: =M11+K12-L12 -> 3834148.7
A13: 10 | B13: 46244 | G13: =E13*F13 -> 0 | J13: =H13*I13 -> 0 | K13: =G13+J13 -> 0 | M13: =M12+K13-L13 -> 3834148.7
A14: 11 | B14: 46245 | G14: =E14*F14 -> 0 | J14: =H14*I14 -> 0 | K14: =G14+J14 -> 0 | M14: =M13+K14-L14 -> 3834148.7
A15: 12 | B15: 46246 | G15: =E15*F15 -> 0 | J15: =H15*I15 -> 0 | K15: =G15+J15 -> 0 | M15: =M14+K15-L15 -> 3834148.7
A16: 13 | B16: 46247 | E16: 2800 | F16: 103.8 | G16: =E16*F16 -> 290640 | J16: =H16*I16 -> 0 | K16: =G16+J16 -> 290640 | L16: 3834140 | M16: =M15+K16-L16 -> 290648.71
A17: 14 | B17: 46248 | G17: =E17*F17 -> 0 | J17: =H17*I17 -> 0 | K17: =G17+J17 -> 0 | M17: =M16+K17-L17 -> 290648.71
A18: 15 | B18: 46249 | E18: 2800 | F18: 103.8 | G18: =E18*F18 -> 290640 | J18: =H18*I18 -> 0 | K18: =G18+J18 -> 290640 | M18: =M17+K18-L18 -> 581288.71
A19: 16 | B19: 46250 | E19: 2700 | F19: 103.8 | G19: =E19*F19 -> 280260 | J19: =H19*I19 -> 0 | K19: =G19+J19 -> 280260 | M19: =M18+K19-L19 -> 861548.71
A20: 17 | B20: 46251 | E20: 4300 | F20: 103.8 | G20: =E20*F20 -> 446340 | H20: 75 | I20: 115.69 | J20: =H20*I20 -> 8676.75 | K20: =G20+J20 -> 455016.75 | M20: =M19+K20-L20 -> 1316565.5
A21: 18 | B21: 46252 | E21: 2800 | F21: 103.8 | G21: =E21*F21 -> 290640 | J21: =H21*I21 -> 0 | K21: =G21+J21 -> 290640 | M21: =M20+K21-L21 -> 1607205.5
A22: 19 | B22: 46253 | E22: 1500 | F22: 103.8 | G22: =E22*F22 -> 155700 | H22: 130 | I22: 115.69 | J22: =H22*I22 -> 15039.7 | K22: =G22+J22 -> 170739.7 | M22: =M21+K22-L22 -> 1777945.2
A23: 20 | B23: 46254 | E23: 1000 | F23: 103.8 | G23: =E23*F23 -> 103800 | J23: =H23*I23 -> 0 | K23: =G23+J23 -> 103800 | M23: =M22+K23-L23 -> 1881745.2
A24: 21 | B24: 46255 | G24: =E24*F24 -> 0 | J24: =H24*I24 -> 0 | K24: =G24+J24 -> 0 | M24: =M23+K24-L24 -> 1881745.2
A25: 22 | B25: 46256 | E25: 1200 | F25: 103.8 | G25: =E25*F25 -> 124560 | J25: =H25*I25 -> 0 | K25: =G25+J25 -> 124560 | M25: =M24+K25-L25 -> 2006305.2
A26: 23 | B26: 46257 | G26: =E26*F26 -> 0 | J26: =H26*I26 -> 0 | K26: =G26+J26 -> 0 | M26: =M25+K26-L26 -> 2006305.2
A27: 24 | B27: 46258 | G27: =E27*F27 -> 0 | J27: =H27*I27 -> 0 | K27: =G27+J27 -> 0 | M27: =M26+K27-L27 -> 2006305.2
A28: 25 | B28: 46259 | E28: 2700 | F28: 103.8 | G28: =E28*F28 -> 280260 | J28: =H28*I28 -> 0 | K28: =G28+J28 -> 280260 | M28: =M27+K28-L28 -> 2286565.2
A29: 26 | B29: 46260 | E29: 1600 | F29: 103.8 | G29: =E29*F29 -> 166080 | J29: =H29*I29 -> 0 | K29: =G29+J29 -> 166080 | M29: =M28+K29-L29 -> 2452645.2
A30: 27 | B30: 46261 | G30: =E30*F30 -> 0 | J30: =H30*I30 -> 0 | K30: =G30+J30 -> 0 | M30: =M29+K30-L30 -> 2452645.2
A31: 28 | B31: 46262 | E31: 800 | F31: 103.8 | G31: =E31*F31 -> 83040 | J31: =H31*I31 -> 0 | K31: =G31+J31 -> 83040 | M31: =M30+K31-L31 -> 2535685.2
A32: 29 | B32: 46263 | E32: 1400 | F32: 103.8 | G32: =E32*F32 -> 145320 | J32: =H32*I32 -> 0 | K32: =G32+J32 -> 145320 | M32: =M31+K32-L32 -> 2681005.2
A33: 30 | B33: 46264 | G33: =E33*F33 -> 0 | J33: =H33*I33 -> 0 | K33: =G33+J33 -> 0 | M33: =M32+K33-L33 -> 2681005.2
A34: 31 | B34: 46265 | E34: 1200 | F34: 103.8 | G34: =E34*F34 -> 124560 | K34: =G34+J34 -> 124560 | M34: =M33+K34-L34 -> 2805565.2
A35: 32 | G35: =E35*F35 -> 0 | J35: =H35*I35 -> 0 | K35: =G35+J35 -> 0 | M35: =M34+K35-L35 -> 2805565.2
A36: 33 | G36: =E36*F36 -> 0 | J36: =H36*I36 -> 0 | K36: =G36+J36 -> 0
A37: 34 | G37: =E37*F37 -> 0 | J37: =H37*I37 -> 0 | K37: =G37+J37 -> 0
E38: =SUM(E3:E37) -> 26800 | G38: =SUM(G3:G37) -> 2781840 | H38: =SUM(H3:H37) -> 205 | J38: =SUM(J3:J37) -> 23716.45 | K38: =SUM(K4:K37) -> 2805556.5 | L38: =SUM(L3:L37) -> 3834140

Sheet Khammam-2
A1: Jayasai union bunk
A2: S.No | B2: Date | C2: GRN No | D2: Ind No/Bill No | E2: Diesel (Lts) | F2: Price | G2: Amount | H2: Petrol (Lts) | I2: Price | J2: Amount | K2: Total amount | L2: Amount paid | M2: As 0n Date | N2: Remarks
A3: Opening Balance | K3: 18929637 | M3: 18929637
A4: 1 | B4: 46235 | E4: 5600 | F4: 103.82 | G4: =E4*F4 -> 581392 | H4: 95 | I4: 115.72 | J4: =H4*I4 -> 10993.4 | K4: =G4+J4 -> 592385.4 | L4: 250000 | M4: =M3+K4-L4 -> 19272022 | N4: 250000-IOCL/40696-DGM Sir | O4: 40696
A5: 2 | B5: 46236 | G5: =E5*F5 -> 0 | J5: =H5*I5 -> 0 | K5: =G5+J5 -> 0 | M5: =M4+K5-L5 -> 19272022
A6: 3 | B6: 46237 | E6: 2215.373 | F6: 103.82 | G6: =E6*F6 -> 230000.02 | J6: =H6*I6 -> 0 | K6: =G6+J6 -> 230000.02 | M6: =M5+K6-L6 -> 19502022 | N6: DGM Sir | O6: 230000
A7: 4 | B7: 46238 | E7: 1300.33 | F7: 103.82 | G7: =E7*F7 -> 135000.26 | J7: =H7*I7 -> 0 | K7: =G7+J7 -> 135000.26 | M7: =M6+K7-L7 -> 19637023 | N7: DGM Sir | O7: 135000.26
A8: 5 | B8: 46239 | G8: =E8*F8 -> 0 | H8: 120 | I8: 115.72 | J8: =H8*I8 -> 13886.4 | K8: =G8+J8 -> 13886.4 | M8: =M7+K8-L8 -> 19650909
A9: 6 | B9: 46240 | E9: 3530 | F9: 103.82 | G9: =E9*F9 -> 366484.6 | J9: =H9*I9 -> 0 | K9: =G9+J9 -> 366484.6 | M9: =M8+K9-L9 -> 20017394 | N9: Devendra | O9: 366485
A10: 7 | B10: 46241 | E10: 2720 | F10: 103.82 | G10: =E10*F10 -> 282390.4 | J10: =H10*I10 -> 0 | K10: =G10+J10 -> 282390.4 | M10: =M9+K10-L10 -> 20299784 | N10: Devendra | O10: 282390.4
A11: 8 | B11: 46242 | E11: 3178.58 | F11: 103.82 | G11: =E11*F11 -> 330000.18 | H11: 95 | I11: 115.72 | J11: =H11*I11 -> 10993.4 | K11: =G11+J11 -> 340993.58 | L11: 70000 | M11: =M10+K11-L11 -> 20570778 | N11: 260000/DGM-70000 IOCL | O11: 260000
A12: 9 | B12: 46243 | G12: =E12*F12 -> 0 | J12: =H12*I12 -> 0 | K12: =G12+J12 -> 0 | M12: =M11+K12-L12 -> 20570778
A13: 10 | B13: 46244 | E13: 722.405 | F13: 103.82 | G13: =E13*F13 -> 75000.087 | J13: =H13*I13 -> 0 | K13: =G13+J13 -> 75000.087 | M13: =M12+K13-L13 -> 20645778 | N13: DGM Sir | O13: 75000 | W13: 250000
A14: 11 | B14: 46245 | E14: 4382.59 | F14: 103.82 | G14: =E14*F14 -> 455000.49 | H14: 130 | I14: 115.72 | J14: =H14*I14 -> 15043.6 | K14: =G14+J14 -> 470044.09 | L14: 300000 | M14: =M13+K14-L14 -> 20815822 | N14: 300000-IOCL/DGM-155000 | O14: 155000 | W14: 70000
A15: 12 | B15: 46246 | E15: 674.25 | F15: 103.82 | G15: =E15*F15 -> 70000.635 | J15: =H15*I15 -> 0 | K15: =G15+J15 -> 70000.635 | M15: =M14+K15-L15 -> 20885823 | N15: DGM Sir | O15: 70000 | S15: 5000000 | W15: 46366
A16: 13 | B16: 46247 | E16: 5400 | F16: 103.82 | G16: =E16*F16 -> 560628 | J16: =H16*I16 -> 0 | K16: =G16+J16 -> 560628 | L16: 15885823 | M16: =M15+K16-L16 -> 5560628 | O16: =SUM(O4:O15) -> 1614571.7 | Q16: 6086287 | S16: 6086287
A17: 14 | B17: 46248 | E17: 5400 | F17: 103.82 | G17: =E17*F17 -> 560628 | H17: 75 | I17: 115.72 | J17: =H17*I17 -> 8679 | K17: =G17+J17 -> 569307 | M17: =M16+K17-L17 -> 6129935 | O17: 1410932 | S17: =SUM(S15:S16) -> 11086287
A18: 15 | B18: 46249 | G18: =E18*F18 -> 0 | J18: =H18*I18 -> 0 | K18: =G18+J18 -> 0 | M18: =M17+K18-L18 -> 6129935 | O18: 600000 | S18: 1162961.4
A19: 16 | B19: 46250 | G19: =E19*F19 -> 0 | J19: =H19*I19 -> 0 | K19: =G19+J19 -> 0 | M19: =M18+K19-L19 -> 6129935 | O19: =SUM(O16:O18) -> 3625503.7 | S19: =S17-S18 -> 9923325.6
A20: 17 | B20: 46251 | G20: =E20*F20 -> 0 | J20: =H20*I20 -> 0 | K20: =G20+J20 -> 0 | M20: =M19+K20-L20 -> 6129935 | S20: 32869.06
A21: 18 | B21: 46252 | G21: =E21*F21 -> 0 | J21: =H21*I21 -> 0 | K21: =G21+J21 -> 0 | M21: =M20+K21-L21 -> 6129935 | S21: =S19+S20 -> 9956194.6
A22: 19 | B22: 46253 | G22: =E22*F22 -> 0 | J22: =H22*I22 -> 0 | K22: =G22+J22 -> 0 | M22: =M21+K22-L22 -> 6129935
A23: 20 | B23: 46254 | G23: =E23*F23 -> 0 | J23: =H23*I23 -> 0 | K23: =G23+J23 -> 0 | M23: =M22+K23-L23 -> 6129935
A24: 21 | B24: 46255 | G24: =E24*F24 -> 0 | J24: =H24*I24 -> 0 | K24: =G24+J24 -> 0 | M24: =M23+K24-L24 -> 6129935
A25: 22 | B25: 46256 | G25: =E25*F25 -> 0 | J25: =H25*I25 -> 0 | K25: =G25+J25 -> 0 | M25: =M24+K25-L25 -> 6129935
A26: 23 | B26: 46257 | G26: =E26*F26 -> 0 | J26: =H26*I26 -> 0 | K26: =G26+J26 -> 0 | M26: =M25+K26-L26 -> 6129935
A27: 24 | B27: 46258 | G27: =E27*F27 -> 0 | J27: =H27*I27 -> 0 | K27: =G27+J27 -> 0 | M27: =M26+K27-L27 -> 6129935
A28: 25 | B28: 46259 | G28: =E28*F28 -> 0 | J28: =H28*I28 -> 0 | K28: =G28+J28 -> 0 | M28: =M27+K28-L28 -> 6129935
A29: 26 | B29: 46260 | G29: =E29*F29 -> 0 | J29: =H29*I29 -> 0 | K29: =G29+J29 -> 0 | M29: =M28+K29-L29 -> 6129935
A30: 27 | B30: 46261 | G30: =E30*F30 -> 0 | J30: =H30*I30 -> 0 | K30: =G30+J30 -> 0 | M30: =M29+K30-L30 -> 6129935
A31: 28 | B31: 46262 | G31: =E31*F31 -> 0 | J31: =H31*I31 -> 0 | K31: =G31+J31 -> 0 | L31: 6129935 | M31: =M30+K31-L31 -> 0
A32: 29 | B32: 46263 | G32: =E32*F32 -> 0 | J32: =H32*I32 -> 0 | K32: =G32+J32 -> 0 | M32: =M31+K32-L32 -> 0
A33: 30 | B33: 46264 | G33: =E33*F33 -> 0 | J33: =H33*I33 -> 0 | K33: =G33+J33 -> 0 | M33: =M32+K33-L33 -> 0
A34: 31 | B34: 46265 | G34: =E34*F34 -> 0 | J34: =H34*I34 -> 0 | K34: =G34+J34 -> 0 | M34: =M33+K34-L34 -> 0
A35: 32 | G35: =E35*F35 -> 0 | J35: =H35*I35 -> 0 | K35: =G35+J35 -> 0 | M35: =M34+K35-L35 -> 0
A36: 33 | G36: =E36*F36 -> 0 | J36: =H36*I36 -> 0 | K36: =G36+J36 -> 0 | M36: =M35+K36-L36 -> 0
E38: =SUM(E4:E36) -> 35123.528 | G38: =SUM(G4:G36) -> 3646524.7 | H38: =SUM(H4:H36) -> 515 | J38: =SUM(J4:J36) -> 59595.8 | K38: =SUM(K4:K36) -> 3706120.5 | L38: =SUM(L4:L36) -> 22635758

Sheet Khammam-3
A1: JSASFuel Genie India Pvt.Ltd
A2: S.No | B2: Date | C2: GRN No | D2: Ind No/Bill No | E2: Diesel (Lts) | F2: Price | G2: Amount | H2: Petrol (Lts) | I2: Price | J2: Amount | K2: Total amount | L2: Amount paid | M2: As 0n Date | N2: Remarks
A3: Opening Balance | K3: 1510680 | M3: 1510680
A4: 1 | B4: 46235 | G4: =E4*F4 -> 0 | J4: =H4*I4 -> 0 | K4: =G4+J4 -> 0 | M4: =M3+K4-L4 -> 1510680
A5: 2 | B5: 46236 | G5: =E5*F5 -> 0 | J5: =H5*I5 -> 0 | K5: =G5+J5 -> 0 | M5: =M4+K5-L5 -> 1510680
A6: 3 | B6: 46237 | G6: =E6*F6 -> 0 | J6: =H6*I6 -> 0 | K6: =G6+J6 -> 0 | M6: =M5+K6-L6 -> 1510680
A7: 4 | B7: 46238 | G7: =E7*F7 -> 0 | J7: =H7*I7 -> 0 | K7: =G7+J7 -> 0 | M7: =M6+K7-L7 -> 1510680
A8: 5 | B8: 46239 | G8: =E8*F8 -> 0 | J8: =H8*I8 -> 0 | K8: =G8+J8 -> 0 | L8: 1200000 | M8: =M7+K8-L8 -> 310680
A9: 6 | B9: 46240 | G9: =E9*F9 -> 0 | J9: =H9*I9 -> 0 | K9: =G9+J9 -> 0 | L9: 310680 | M9: =M8+K9-L9 -> 0
A10: 7 | B10: 46241 | G10: =E10*F10 -> 0 | J10: =H10*I10 -> 0 | K10: =G10+J10 -> 0 | M10: =M9+K10-L10 -> 0
A11: 8 | B11: 46242 | G11: =E11*F11 -> 0 | J11: =H11*I11 -> 0 | K11: =G11+J11 -> 0 | M11: =M10+K11-L11 -> 0
A12: 9 | B12: 46243 | G12: =E12*F12 -> 0 | J12: =H12*I12 -> 0 | K12: =G12+J12 -> 0 | M12: =M11+K12-L12 -> 0
A13: 10 | B13: 46244 | G13: =E13*F13 -> 0 | J13: =H13*I13 -> 0 | K13: =G13+J13 -> 0 | M13: =M12+K13-L13 -> 0
A14: 11 | B14: 46245 | G14: =E14*F14 -> 0 | J14: =H14*I14 -> 0 | K14: =G14+J14 -> 0 | M14: =M13+K14-L14 -> 0
A15: 12 | B15: 46246 | G15: =E15*F15 -> 0 | J15: =H15*I15 -> 0 | K15: =G15+J15 -> 0 | M15: =M14+K15-L15 -> 0
A16: 13 | B16: 46247 | G16: =E16*F16 -> 0 | J16: =H16*I16 -> 0 | K16: =G16+J16 -> 0 | M16: =M15+K16-L16 -> 0
A17: 14 | B17: 46248 | G17: =E17*F17 -> 0 | J17: =H17*I17 -> 0 | K17: =G17+J17 -> 0 | M17: =M16+K17-L17 -> 0
A18: 15 | B18: 46249 | G18: =E18*F18 -> 0 | J18: =H18*I18 -> 0 | K18: =G18+J18 -> 0 | M18: =M17+K18-L18 -> 0
A19: 16 | B19: 46250 | G19: =E19*F19 -> 0 | J19: =H19*I19 -> 0 | K19: =G19+J19 -> 0 | M19: =M18+K19-L19 -> 0
A20: 17 | B20: 46251 | G20: =E20*F20 -> 0 | J20: =H20*I20 -> 0 | K20: =G20+J20 -> 0 | M20: =M19+K20-L20 -> 0
A21: 18 | B21: 46252 | G21: =E21*F21 -> 0 | J21: =H21*I21 -> 0 | K21: =G21+J21 -> 0 | M21: =M20+K21-L21 -> 0
... A33: 30 | B33: 46264 | G33: =E33*F33 -> 0 | J33: =H33*I33 -> 0 | K33: =G33+J33 -> 0 | M33: =M32+K33-L33 -> 0
A34: 31 | G34: =E34*F34 -> 0 | J34: =H34*I34 -> 0 | K34: =G34+J34 -> 0 | M34: =M33+K34-L34 -> 0
E35: =SUM(E4:E34) -> 0 | G35: =SUM(G4:G34) -> 0 | H35: =SUM(H4:H34) -> 0 | J35: =SUM(J4:J34) -> 0 | K35: =SUM(K4:K34) -> 0 | L35: =SUM(L4:L34) -> 1510680

Sheet Khammam-4
A1: Sai Madeana Filling Station
A2: S.No | B2: Date | C2: GRN No | D2: Ind No/Bill No | E2: Diesel (Lts) | F2: Price | G2: Amount | H2: Petrol (Lts) | I2: Price | J2: Amount | K2: Total amount | L2: Amount paid | M2: As 0n Date | N2: Remarks
A3: Opening Balance | K3: 0 | M3: 0
A4: 1 | B4: 46235 | G4: =E4*F4 -> 0 | J4: =H4*I4 -> 0 | K4: =G4+J4 -> 0 | M4: =M3+K4-L4 -> 0
A5: 2 | B5: 46236 | G5: =E5*F5 -> 0 | J5: =H5*I5 -> 0 | K5: =G5+J5 -> 0 | M5: =M4+K5-L5 -> 0
A6: 3 | B6: 46237 | G6: =E6*F6 -> 0 | J6: =H6*I6 -> 0 | K6: =G6+J6 -> 0 | M6: =M5+K6-L6 -> 0
A7: 4 | B7: 46238 | G7: =E7*F7 -> 0 | J7: =H7*I7 -> 0 | K7: =G7+J7 -> 0 | M7: =M6+K7-L7 -> 0
A8: 5 | B8: 46239 | G8: =E8*F8 -> 0 | J8: =H8*I8 -> 0 | K8: =G8+J8 -> 0 | M8: =M7+K8-L8 -> 0
A9: 6 | B9: 46240 | G9: =E9*F9 -> 0 | J9: =H9*I9 -> 0 | K9: =G9+J9 -> 0 | M9: =M8+K9-L9 -> 0
A10: 7 | B10: 46241 | G10: =E10*F10 -> 0 | J10: =H10*I10 -> 0 | K10: =G10+J10 -> 0 | M10: =M9+K10-L10 -> 0
A11: 8 | B11: 46242 | G11: =E11*F11 -> 0 | J11: =H11*I11 -> 0 | K11: =G11+J11 -> 0 | M11: =M10+K11-L11 -> 0
A12: 9 | B12: 46243 | G12: =E12*F12 -> 0 | J12: =H12*I12 -> 0 | K12: =G12+J12 -> 0 | M12: =M11+K12-L12 -> 0
A13: 10 | B13: 46244 | G13: =E13*F13 -> 0 | J13: =H13*I13 -> 0 | K13: =G13+J13 -> 0 | M13: =M12+K13-L13 -> 0
A14: 11 | B14: 46245 | G14: =E14*F14 -> 0 | J14: =H14*I14 -> 0 | K14: =G14+J14 -> 0 | M14: =M13+K14-L14 -> 0
A15: 12 | B15: 46246 | G15: =E15*F15 -> 0 | J15: =H15*I15 -> 0 | K15: =G15+J15 -> 0 | M15: =M14+K15-L15 -> 0
... A21: 18 | B21: 46252 | G21: =E21*F21 -> 0 | J21: =H21*I21 -> 0 | K21: =G21+J21 -> 0 | M21: =M20+K21-L21 -> 0
A22: 19 | B22: 46253 | E22: 2700 | F22: 103.62 | G22: =E22*F22 -> 279774 | J22: =H22*I22 -> 0 | K22: =G22+J22 -> 279774 | M22: =M21+K22-L22 -> 279774
A23: 20 | B23: 46254 | G23: =E23*F23 -> 0 | J23: =H23*I23 -> 0 | K23: =G23+J23 -> 0 | M23: =M22+K23-L23 -> 279774
A24: 21 | B24: 46255 | E24: 2700 | F24: 103.62 | G24: =E24*F24 -> 279774 | J24: =H24*I24 -> 0 | K24: =G24+J24 -> 279774 | M24: =M23+K24-L24 -> 559548
A25: 22 | B25: 46256 | E25: 2700 | F25: 103.62 | G25: =E25*F25 -> 279774 | H25: 35 | I25: 115.49 | J25: =H25*I25 -> 4042.15 | K25: =G25+J25 -> 283816.15 | M25: =M24+K25-L25 -> 843364.15
A26: 23 | B26: 46257 | G26: =E26*F26 -> 0 | J26: =H26*I26 -> 0 | K26: =G26+J26 -> 0 | M26: =M25+K26-L26 -> 843364.15
A27: 24 | B27: 46258 | G27: =E27*F27 -> 0 | J27: =H27*I27 -> 0 | K27: =G27+J27 -> 0 | M27: =M26+K27-L27 -> 843364.15
A28: 25 | B28: 46259 | E28: 2700 | F28: 103.62 | G28: =E28*F28 -> 279774 | J28: =H28*I28 -> 0 | K28: =G28+J28 -> 279774 | M28: =M27+K28-L28 -> 1123138.1
A29: 26 | B29: 46260 | G29: =E29*F29 -> 0 | J29: =H29*I29 -> 0 | K29: =G29+J29 -> 0 | M29: =M28+K29-L29 -> 1123138.1
A30: 27 | B30: 46261 | G30: =E30*F30 -> 0 | J30: =H30*I30 -> 0 | K30: =G30+J30 -> 0 | M30: =M29+K30-L30 -> 1123138.1
A31: 28 | B31: 46262 | E31: 2700 | F31: 103.62 | G31: =E31*F31 -> 279774 | H31: 35 | I31: 115.49 | J31: =H31*I31 -> 4042.15 | K31: =G31+J31 -> 283816.15 | L31: 1123138 | M31: =M30+K31-L31 -> 283816.3
A32: 29 | B32: 46263 | E32: 2700 | F32: 103.62 | G32: =E32*F32 -> 279774 | J32: =H32*I32 -> 0 | K32: =G32+J32 -> 279774 | M32: =M31+K32-L32 -> 563590.3
A33: 30 | B33: 46264 | G33: =E33*F33 -> 0 | J33: =H33*I33 -> 0 | K33: =G33+J33 -> 0 | M33: =M32+K33-L33 -> 563590.3
A34: 31 | B34: 46265 | E34: 2700 | F34: 103.62 | G34: =E34*F34 -> 279774 | J34: =H34*I34 -> 0 | K34: =G34+J34 -> 279774 | M34: =M33+K34-L34 -> 843364.3
E35: =SUM(E4:E34) -> 18900 | G35: =SUM(G4:G34) -> 1958418 | H35: =SUM(H4:H34) -> 70 | J35: =SUM(J4:J34) -> 8084.3 | K35: =SUM(K4:K34) -> 1966502.3 | L35: =SUM(L4:L34) -> 1123138

Sheet  Khammam-5
A1: Vajra mahalakshmi filling station
A2: S.No | B2: Date | C2: GRN No | D2: Ind No/Bill No | E2: Diesel (Lts) | F2: Price | G2: Amount | H2: Petrol (Lts) | I2: Price | J2: Amount | K2: Total amount | L2: Amount paid | M2: As 0n Date | N2: Remarks
A3: Opening Balance | K3: 0 | M3: 0
A4: 1 | B4: 46235 | G4: =E4*F4 -> 0 | J4: =H4*I4 -> 0 | K4: =G4+J4 -> 0 | M4: =M3+K4-L4 -> 0
A5: 2 | B5: 46236 | G5: =E5*F5 -> 0 | J5: =H5*I5 -> 0 | K5: =G5+J5 -> 0 | M5: =M4+K5-L5 -> 0
A6: 3 | B6: 46237 | G6: =E6*F6 -> 0 | J6: =H6*I6 -> 0 | K6: =G6+J6 -> 0 | M6: =M5+K6-L6 -> 0
A7: 4 | B7: 46238 | G7: =E7*F7 -> 0 | J7: =H7*I7 -> 0 | K7: =G7+J7 -> 0 | M7: =M6+K7-L7 -> 0
A8: 5 | B8: 46239 | G8: =E8*F8 -> 0 | J8: =H8*I8 -> 0 | K8: =G8+J8 -> 0 | M8: =M7+K8-L8 -> 0
A9: 6 | B9: 46240 | G9: =E9*F9 -> 0 | J9: =H9*I9 -> 0 | K9: =G9+J9 -> 0 | M9: =M8+K9-L9 -> 0
A10: 7 | B10: 46241 | G10: =E10*F10 -> 0 | J10: =H10*I10 -> 0 | K10: =G10+J10 -> 0 | M10: =M9+K10-L10 -> 0
A11: 8 | B11: 46242 | G11: =E11*F11 -> 0 | J11: =H11*I11 -> 0 | K11: =G11+J11 -> 0 | M11: =M10+K11-L11 -> 0
A12: 9 | B12: 46243 | G12: =E12*F12 -> 0 | J12: =H12*I12 -> 0 | K12: =G12+J12 -> 0 | M12: =M11+K12-L12 -> 0
A13: 10 | B13: 46244 | G13: =E13*F13 -> 0 | J13: =H13*I13 -> 0 | K13: =G13+J13 -> 0 | M13: =M12+K13-L13 -> 0
A14: 11 | B14: 46245 | G14: =E14*F14 -> 0 | J14: =H14*I14 -> 0 | K14: =G14+J14 -> 0 | M14: =M13+K14-L14 -> 0
A15: 12 | B15: 46246 | G15: =E15*F15 -> 0 | J15: =H15*I15 -> 0 | K15: =G15+J15 -> 0 | M15: =M14+K15-L15 -> 0
... A22: 19 | B22: 46253 | G22: =E22*F22 -> 0 | J22: =H22*I22 -> 0 | K22: =G22+J22 -> 0 | M22: =M21+K22-L22 -> 0
A23: 20 | B23: 46254 | E23: 5260 | F23: 103.62 | G23: =E23*F23 -> 545041.2 | J23: =H23*I23 -> 0 | K23: =G23+J23 -> 545041.2 | M23: =M22+K23-L23 -> 545041.2
A24: 21 | B24: 46255 | G24: =E24*F24 -> 0 | J24: =H24*I24 -> 0 | K24: =G24+J24 -> 0 | M24: =M23+K24-L24 -> 545041.2
A25: 22 | B25: 46256 | E25: 2800 | F25: 103.62 | G25: =E25*F25 -> 290136 | H25: 75 | I25: 115.49 | J25: =H25*I25 -> 8661.75 | K25: =G25+J25 -> 298797.75 | M25: =M24+K25-L25 -> 843838.95
A26: 23 | B26: 46257 | G26: =E26*F26 -> 0 | J26: =H26*I26 -> 0 | K26: =G26+J26 -> 0 | M26: =M25+K26-L26 -> 843838.95
A27: 24 | B27: 46258 | G27: =E27*F27 -> 0 | J27: =H27*I27 -> 0 | K27: =G27+J27 -> 0 | M27: =M26+K27-L27 -> 843838.95
A28: 25 | B28: 46259 | G28: =E28*F28 -> 0 | J28: =H28*I28 -> 0 | K28: =G28+J28 -> 0 | M28: =M27+K28-L28 -> 843838.95
A29: 26 | B29: 46260 | E29: 2700 | F29: 103.62 | G29: =E29*F29 -> 279774 | H29: 90 | I29: 115.49 | J29: =H29*I29 -> 10394.1 | K29: =G29+J29 -> 290168.1 | M29: =M28+K29-L29 -> 1134007.1
A30: 27 | B30: 46261 | G30: =E30*F30 -> 0 | J30: =H30*I30 -> 0 | K30: =G30+J30 -> 0 | M30: =M29+K30-L30 -> 1134007.1
A31: 28 | B31: 46262 | G31: =E31*F31 -> 0 | J31: =H31*I31 -> 0 | K31: =G31+J31 -> 0 | L31: 1134007 | M31: =M30+K31-L31 -> 0.05
A32: 29 | B32: 46263 | E32: 2800 | F32: 103.62 | G32: =E32*F32 -> 290136 | H32: 40 | I32: 115.49 | J32: =H32*I32 -> 4619.6 | K32: =G32+J32 -> 294755.6 | M32: =M31+K32-L32 -> 294755.65
A33: 30 | B33: 46264 | E33: 2700 | F33: 103.62 | G33: =E33*F33 -> 279774 | H33: 35 | I33: 115.49 | J33: =H33*I33 -> 4042.15 | K33: =G33+J33 -> 283816.15 | M33: =M32+K33-L33 -> 578571.8
A34: 31 | G34: =E34*F34 -> 0 | J34: =H34*I34 -> 0 | K34: =G34+J34 -> 0 | M34: =M33+K34-L34 -> 578571.8
E35: =SUM(E4:E34) -> 16260 | G35: =SUM(G4:G34) -> 1684861.2 | H35: =SUM(H4:H34) -> 240 | J35: =SUM(J4:J34) -> 27717.6 | K35: =SUM(K4:K34) -> 1712578.8 | L35: =SUM(L4:L34) -> 1134007

Sheet  Khammam&Cash
A1: Cash &Carry
A2: S.No | B2: Date | D2: Ind No/Bill No | E2: Diesel (Lts) | F2: Price | G2: Amount | H2: Petrol (Lts) | I2: Price | J2: Amount | K2: Total amount | L2: Amount paid | M2: As 0n Date | N2: Remarks
A3: Opening Balance | K3: 0 | M3: 0
A4: 1 | B4: 46236 | C4: Stambhadri Fuel Park HPCL | E4: 1734.104 | F4: 103.8 | G4: =E4*F4 -> 180000 | K4: =G4+J4 -> 180000 | L4: =H4+K4 -> 180000 | M4: =M3+K4-L4 -> 0
A5: 2 | B5: 46238 | C5: Stambhadri Fuel Park HPCL | E5: 3853.56 | F5: 103.8 | G5: =E5*F5 -> 399999.53 | J5: =H5*I5 -> 0 | K5: =G5+J5 -> 399999.53 | L5: =H5+K5 -> 399999.53 | M5: =M4+K5-L5 -> 0
A6: 3 | B6: 46242 | C6: Stambhadri Fuel Park HPCL | E6: 1445.089 | F6: 103.8 | G6: =E6*F6 -> 150000.24 | J6: =H6*I6 -> 0 | K6: =G6+J6 -> 150000.24 | L6: =H6+K6 -> 150000.24 | M6: =M5+K6-L6 -> 0
A7: 4 | G7: =E7*F7 -> 0 | J7: =H7*I7 -> 0 | K7: =G7+J7 -> 0 | L7: =H7+K7 -> 0 | M7: =M6+K7-L7 -> 0
A8: 5 | G8: =E8*F8 -> 0 | J8: =H8*I8 -> 0 | K8: =G8+J8 -> 0 | L8: =H8+K8 -> 0 | M8: =M7+K8-L8 -> 0
A9: 6 | G9: =E9*F9 -> 0 | J9: =H9*I9 -> 0 | K9: =G9+J9 -> 0 | L9: =H9+K9 -> 0 | M9: =M8+K9-L9 -> 0
A10: 7 | G10: =E10*F10 -> 0 | J10: =H10*I10 -> 0 | K10: =G10+J10 -> 0 | L10: =H10+K10 -> 0 | M10: =M9+K10-L10 -> 0
A11: 8 | G11: =E11*F11 -> 0 | J11: =H11*I11 -> 0 | K11: =G11+J11 -> 0 | L11: =H11+K11 -> 0 | M11: =M10+K11-L11 -> 0
A12: 9 | G12: =E12*F12 -> 0 | J12: =H12*I12 -> 0 | K12: =G12+J12 -> 0 | L12: =H12+K12 -> 0 | M12: =M11+K12-L12 -> 0
A13: 10 | G13: =E13*F13 -> 0 | J13: =H13*I13 -> 0 | K13: =G13+J13 -> 0 | L13: =H13+K13 -> 0 | M13: =M12+K13-L13 -> 0
A14: 11 | G14: =E14*F14 -> 0 | J14: =H14*I14 -> 0 | K14: =G14+J14 -> 0 | L14: =H14+K14 -> 0 | M14: =M13+K14-L14 -> 0
A15: 12 | G15: =E15*F15 -> 0 | J15: =H15*I15 -> 0 | K15: =G15+J15 -> 0 | L15: =H15+K15 -> 0 | M15: =M14+K15-L15 -> 0
A16: 13 | G16: =E16*F16 -> 0 | J16: =H16*I16 -> 0 | K16: =G16+J16 -> 0 | L16: =H16+K16 -> 0 | M16: =M15+K16-L16 -> 0
A17: 14 | G17: =E17*F17 -> 0 | J17: =H17*I17 -> 0 | K17: =G17+J17 -> 0 | L17: =H17+K17 -> 0 | M17: =M16+K17-L17 -> 0
A18: 15 | G18: =E18*F18 -> 0 | J18: =H18*I18 -> 0 | K18: =G18+J18 -> 0 | L18: =H18+K18 -> 0 | M18: =M17+K18-L18 -> 0
... A22: 19 | G22: =E22*F22 -> 0 | J22: =H22*I22 -> 0 | K22: =G22+J22 -> 0 | L22: =H22+K22 -> 0 | M22: =M21+K22-L22 -> 0
A23: 20 | G23: =E23*F23 -> 0 | J23: =H23*I23 -> 0 | K23: =G23+J23 -> 0 | L23: 0 | M23: =M22+K23-L23 -> 0
A24: 21 | G24: =E24*F24 -> 0 | J24: =H24*I24 -> 0 | K24: =G24+J24 -> 0 | L24: =H24+K24 -> 0 | M24: =M23+K24-L24 -> 0
A25: 22 | G25: =E25*F25 -> 0 | J25: =H25*I25 -> 0 | K25: =G25+J25 -> 0 | L25: =H25+K25 -> 0 | M25: =M24+K25-L25 -> 0
A26: 23 | G26: =E26*F26 -> 0 | J26: =H26*I26 -> 0 | K26: =G26+J26 -> 0 | L26: =H26+K26 -> 0 | M26: =M25+K26-L26 -> 0
A27: 24 | G27: =E27*F27 -> 0 | K27: =G27+J27 -> 0 | L27: =H27+K27 -> 0 | M27: =M26+K27-L27 -> 0
A28: 25 | G28: =E28*F28 -> 0 | J28: =H28*I28 -> 0 | K28: =G28+J28 -> 0 | L28: =H28+K28 -> 0 | M28: =M26+K28-L28 -> 0
A29: 26 | G29: =E29*F29 -> 0 | J29: =H29*I29 -> 0 | K29: =G29+J29 -> 0 | L29: =H29+K29 -> 0 | M29: =M28+K29-L29 -> 0
A30: 27 | G30: =E30*F30 -> 0 | J30: =H30*I30 -> 0 | K30: =G30+J30 -> 0 | L30: =H30+K30 -> 0 | M30: =M29+K30-L30 -> 0
A31: 28 | G31: =E31*F31 -> 0 | J31: =H31*I31 -> 0 | K31: =G31+J31 -> 0 | L31: =H31+K31 -> 0 | M31: =M30+K31-L31 -> 0
A32: 29 | G32: =E32*F32 -> 0 | J32: =H32*I32 -> 0 | K32: =G32+J32 -> 0 | L32: =H32+K32 -> 0 | M32: =M31+K32-L32 -> 0
A33: 30 | G33: =E33*F33 -> 0 | J33: =H33*I33 -> 0 | K33: =G33+J33 -> 0 | L33: =H33+K33 -> 0 | M33: =M32+K33-L33 -> 0
A34: 31 | G34: =E34*F34 -> 0 | J34: =H34*I34 -> 0 | K34: =G34+J34 -> 0 | L34: =H34+K34 -> 0 | M34: =M33+K34-L34 -> 0
A35: 32 | G35: =E35*F35 -> 0 | K35: =G35+J35 -> 0 | L35: =H35+K35 -> 0 | M35: =M34+K35-L35 -> 0
A36: 33 | G36: =E36*F36 -> 0 | J36: =H36*I36 -> 0 | K36: =G36+J36 -> 0 | L36: =H36+K36 -> 0 | M36: =M35+K36-L36 -> 0
A37: 34 | G37: =E37*F37 -> 0 | J37: =H37*I37 -> 0 | K37: =G37+J37 -> 0 | L37: =H37+K37 -> 0 | M37: =M36+K37-L37 -> 0
G38: =E38*F38 -> 0 | K38: =G38+J38 -> 0 | L38: =H38+K38 -> 0 | M38: =M37+K38-L38 -> 0
G39: =E39*F39 -> 0 | K39: =G39+J39 -> 0 | L39: =H39+K39 -> 0 | M39: =M38+K39-L39 -> 0
G40: =E40*F40 -> 0 | K40: =G40+J40 -> 0 | L40: =H40+K40 -> 0 | M40: =M39+K40-L40 -> 0
M41: =M40+K41-L41 -> 0
A45: 35 | G45: =E45*F45 -> 0 | J45: =H45*I45 -> 0 | K45: =G45+J45 -> 0
E46: =SUM(E3:E45) -> 7032.753 | G46: =SUM(G3:G45) -> 729999.76 | H46: =SUM(H3:H45) -> 0 | J46: =SUM(J3:J45) -> 0 | K46: =SUM(K4:K45) -> 729999.76 | L46: =SUM(L3:L45) -> 729999.76

Sheet Jadcherla-4
A1: Shree Poornima F/S
A2: S.No | B2: Date | C2: GRN No | D2: Ind No/Bill No | E2: Diesel (Lts) | F2: Price | G2: Amount | H2: Petrol (Lts) | I2: Price | J2: Amount | K2: Total amount | L2: Amount paid | M2: As on date | N2: Remarks
A3: Opening Balance | M3: 50273.68
A4: 1 | B4: 46235 | G4: =E4*F4 -> 0 | J4: =H4*I4 -> 0 | K4: =G4+J4 -> 0 | L4: 0 | M4: =M3+K4-L4 -> 50273.68
A5: 2 | B5: 46236 | G5: =E5*F5 -> 0 | J5: =H5*I5 -> 0 | K5: =G5+J5 -> 0 | L5: 0 | M5: =M4+K5-L5 -> 50273.68
A6: 3 | B6: 46237 | G6: =E6*F6 -> 0 | J6: =H6*I6 -> 0 | K6: =G6+J6 -> 0 | L6: 0 | M6: =M5+K6-L6 -> 50273.68
A7: 4 | B7: 46238 | G7: =E7*F7 -> 0 | J7: =H7*I7 -> 0 | K7: =G7+J7 -> 0 | L7: 0 | M7: =M6+K7-L7 -> 50273.68
A8: 5 | B8: 46239 | G8: =E8*F8 -> 0 | J8: =H8*I8 -> 0 | K8: =G8+J8 -> 0 | L8: 0 | M8: =M7+K8-L8 -> 50273.68
A9: 6 | B9: 46240 | G9: =E9*F9 -> 0 | J9: =H9*I9 -> 0 | K9: =G9+J9 -> 0 | L9: 0 | M9: =M8+K9-L9 -> 50273.68
A10: 7 | B10: 46241 | G10: =E10*F10 -> 0 | J10: =H10*I10 -> 0 | K10: =G10+J10 -> 0 | L10: 0 | M10: =M9+K10-L10 -> 50273.68
A11: 8 | B11: 46242 | G11: =E11*F11 -> 0 | J11: =H11*I11 -> 0 | K11: =G11+J11 -> 0 | L11: 0 | M11: =M10+K11-L11 -> 50273.68
A12: 9 | B12: 46243 | G12: =E12*F12 -> 0 | J12: =H12*I12 -> 0 | K12: =G12+J12 -> 0 | L12: 0 | M12: =M11+K12-L12 -> 50273.68
A13: 10 | B13: 46244 | G13: =E13*F13 -> 0 | J13: =H13*I13 -> 0 | K13: =G13+J13 -> 0 | L13: 0 | M13: =M12+K13-L13 -> 50273.68
A14: 11 | B14: 46245 | G14: =E14*F14 -> 0 | J14: =H14*I14 -> 0 | K14: =G14+J14 -> 0 | L14: 0 | M14: =M13+K14-L14 -> 50273.68
A15: 12 | B15: 46246 | G15: =E15*F15 -> 0 | J15: =H15*I15 -> 0 | K15: =G15+J15 -> 0 | L15: 0 | M15: =M14+K15-L15 -> 50273.68
A16: 13 | B16: 46247 | G16: =E16*F16 -> 0 | J16: =H16*I16 -> 0 | K16: =G16+J16 -> 0 | L16: 0 | M16: =M15+K16-L16 -> 50273.68
A17: 14 | B17: 46248 | G17: =E17*F17 -> 0 | H17: 20 | I17: 116.33 | J17: =H17*I17 -> 2326.6 | K17: =G17+J17 -> 2326.6 | L17: 50000 | M17: =M16+K17-L17 -> 2600.28
A18: 15 | B18: 46249 | G18: =E18*F18 -> 0 | J18: =H18*I18 -> 0 | K18: =G18+J18 -> 0 | L18: 0 | M18: =M17+K18-L18 -> 2600.28
A19: 16 | B19: 46250 | G19: 0 | J19: 0 | K19: 0 | L19: 0 | M19: =M18+K19-L19 -> 2600.28
A20: 17 | B20: 46251 | G20: =E20*F20 -> 0 | J20: =H20*I20 -> 0 | K20: =G20+J20 -> 0 | L20: 0 | M20: =M19+K20-L20 -> 2600.28
A21: 18 | B21: 46252 | G21: =E21*F21 -> 0 | J21: =H21*I21 -> 0 | K21: =G21+J21 -> 0 | L21: 0 | M21: =M20+K21-L21 -> 2600.28
A22: 19 | B22: 46253 | G22: =E22*F22 -> 0 | J22: =H22*I22 -> 0 | K22: =G22+J22 -> 0 | L22: 0 | M22: =M21+K22-L22 -> 2600.28
A23: 20 | B23: 46254 | G23: =E23*F23 -> 0 | J23: =H23*I23 -> 0 | K23: =G23+J23 -> 0 | L23: 0 | M23: =M22+K23-L23 -> 2600.28
A24: 21 | B24: 46255 | G24: =E24*F24 -> 0 | J24: =H24*I24 -> 0 | K24: =G24+J24 -> 0 | L24: 0 | M24: =M23+K24-L24 -> 2600.28
A25: 22 | B25: 46256 | G25: =E25*F25 -> 0 | J25: =H25*I25 -> 0 | K25: =G25+J25 -> 0 | L25: 0 | M25: =M24+K25-L25 -> 2600.28
A26: 23 | B26: 46257 | G26: =E26*F26 -> 0 | J26: =H26*I26 -> 0 | K26: =G26+J26 -> 0 | L26: 0 | M26: =M25+K26-L26 -> 2600.28
A27: 24 | B27: 46258 | G27: =E27*F27 -> 0 | J27: =H27*I27 -> 0 | K27: =G27+J27 -> 0 | L27: 0 | M27: =M26+K27-L27 -> 2600.28
A28: 25 | B28: 46259 | G28: =E28*F28 -> 0 | J28: =H28*I28 -> 0 | K28: =G28+J28 -> 0 | L28: 0 | M28: =M27+K28-L28 -> 2600.28
A29: 26 | B29: 46260 | G29: =E29*F29 -> 0 | J29: =H29*I29 -> 0 | K29: =G29+J29 -> 0 | L29: 0 | M29: =M28+K29-L29 -> 2600.28
A30: 27 | B30: 46261 | G30: =E30*F30 -> 0 | J30: =H30*I30 -> 0 | K30: =G30+J30 -> 0 | L30: 0 | M30: =M29+K30-L30 -> 2600.28
A31: 28 | B31: 46262 | G31: =E31*F31 -> 0 | J31: =H31*I31 -> 0 | K31: =G31+J31 -> 0 | L31: 0 | M31: =M30+K31-L31 -> 2600.28
... A33: 30 | B33: 46264 | G33: =E33*F33 -> 0 | J33: =H33*I33 -> 0 | K33: =G33+J33 -> 0 | L33: 0 | M33: =M32+K33-L33 -> 2600.28
A34: 31 | G34: =E34*F34 -> 0 | J34: =H34*I34 -> 0 | K34: =G34+J34 -> 0 | M34: =M33+K34-L34 -> 2600.28
E35: =SUM(E4:E34) -> 0 | G35: =SUM(G4:G34) -> 0 | H35: =SUM(H4:H34) -> 20 | J35: =SUM(J4:J34) -> 2326.6 | K35: =SUM(K4:K34) -> 2326.6 | L35: =SUM(L4:L34) -> 50000

Sheet  Sangareddy-2
A1: Durga Bhavani F/S
A2: S.No | B2: Date | C2: GRN No | D2: Ind no/Bill No | E2: Diesel (Lts) | F2: Price | G2: Amount | H2: Petrol (Lts) | I2: Price | J2: Amount | K2: Total amount | L2: Amount paid | M2: As on Date | N2: Remarks
A3: Opening Balance | M3: 52609.145
A4: 1 | B4: 45870 | G4: =E4*F4 -> 0 | H4: 10 | I4: 116.54 | J4: =H4*I4 -> 1165.4 | K4: =G4+J4 -> 1165.4 | M4: =M3+K4-L4 -> 53774.545
A5: 2 | B5: 45871 | E5: 38.25 | F5: 104.56 | G5: =E5*F5 -> 3999.42 | H5: 5 | I5: 116.54 | J5: =H5*I5 -> 582.7 | K5: =G5+J5 -> 4582.12 | M5: =M4+K5-L5 -> 58356.665
A6: 3 | B6: 45872 | G6: =E6*F6 -> 0 | H6: 5 | I6: 116.54 | J6: =H6*I6 -> 582.7 | K6: =G6+J6 -> 582.7 | M6: =M5+K6-L6 -> 58939.365
A7: 4 | B7: 45873 | G7: =E7*F7 -> 0 | J7: =H7*I7 -> 0 | K7: =G7+J7 -> 0 | M7: =M6+K7-L7 -> 58939.365
A8: 5 | B8: 45874 | G8: =E8*F8 -> 0 | J8: =H8*I8 -> 0 | K8: =G8+J8 -> 0 | M8: =M7+K8-L8 -> 58939.365
A9: 6 | B9: 45875 | G9: =E9*F9 -> 0 | J9: =H9*I9 -> 0 | K9: =G9+J9 -> 0 | M9: =M8+K9-L9 -> 58939.365
A10: 7 | B10: 45876 | G10: =E10*F10 -> 0 | J10: =H10*I10 -> 0 | K10: =G10+J10 -> 0 | M10: =M9+K10-L10 -> 58939.365
A11: 8 | B11: 45877 | G11: =E11*F11 -> 0 | J11: =H11*I11 -> 0 | K11: =G11+J11 -> 0 | M11: =M10+K11-L11 -> 58939.365
A12: 9 | B12: 45878 | G12: =E12*F12 -> 0 | J12: =H12*I12 -> 0 | K12: =G12+J12 -> 0 | M12: =M11+K12-L12 -> 58939.365
A13: 10 | B13: 45879 | G13: =E13*F13 -> 0 | J13: =H13*I13 -> 0 | K13: =G13+J13 -> 0 | M13: =M12+K13-L13 -> 58939.365
A14: 11 | B14: 45880 | G14: =E14*F14 -> 0 | J14: =H14*I14 -> 0 | K14: =G14+J14 -> 0 | M14: =M13+K14-L14 -> 58939.365
A15: 12 | B15: 45881 | G15: =E15*F15 -> 0 | J15: =H15*I15 -> 0 | K15: =G15+J15 -> 0 | M15: =M14+K15-L15 -> 58939.365
A16: 13 | B16: 45882 | G16: =E16*F16 -> 0 | J16: =H16*I16 -> 0 | K16: =G16+J16 -> 0 | M16: =M15+K16-L16 -> 58939.365
A17: 14 | B17: 45883 | G17: =E17*F17 -> 0 | J17: =H17*I17 -> 0 | K17: =G17+J17 -> 0 | M17: =M16+K17-L17 -> 58939.365
A18: 15 | B18: 45884 | G18: =E18*F18 -> 0 | J18: =H18*I18 -> 0 | K18: =G18+J18 -> 0 | M18: =M17+K18-L18 -> 58939.365
... A22: 19 | B22: 45888 | G22: =E22*F22 -> 0 | J22: =H22*I22 -> 0 | K22: =G22+J22 -> 0 | M22: =M21+K22-L22 -> 58939.365
A23: 20 | B23: 45889 | G23: =E23*F23 -> 0 | J23: =H23*I23 -> 0 | K23: =G23+J23 -> 0 | L23: 58939.365 | M23: =M22+K23-L23 -> 0 | Q23: 96.44
A24: 21 | B24: 45890 | G24: =E24*F24 -> 0 | J24: =H24*I24 -> 0 | K24: =G24+J24 -> 0 | M24: =M23+K24-L24 -> 0
A25: 22 | B25: 45891 | G25: =E25*F25 -> 0 | J25: =H25*I25 -> 0 | K25: =G25+J25 -> 0 | M25: =M24+K25-L25 -> 0
A26: 23 | B26: 45892 | G26: =E26*F26 -> 0 | J26: =H26*I26 -> 0 | K26: =G26+J26 -> 0 | M26: =M25+K26-L26 -> 0
A27: 24 | B27: 45893 | G27: =E27*F27 -> 0 | J27: =H27*I27 -> 0 | K27: =G27+J27 -> 0 | M27: =M26+K27-L27 -> 0
A28: 25 | B28: 45894 | G28: =E28*F28 -> 0 | J28: =H28*I28 -> 0 | K28: =G28+J28 -> 0 | M28: =M27+K28-L28 -> 0
A29: 26 | B29: 45895 | G29: =E29*F29 -> 0 | J29: =H29*I29 -> 0 | K29: =G29+J29 -> 0 | M29: =M28+K29-L29 -> 0
A30: 27 | B30: 45896 | G30: =E30*F30 -> 0 | J30: =H30*I30 -> 0 | K30: =G30+J30 -> 0 | M30: =M29+K30-L30 -> 0
A31: 28 | B31: 45897 | G31: =E31*F31 -> 0 | J31: =H31*I31 -> 0 | K31: =G31+J31 -> 0 | M31: =M30+K31-L31 -> 0
A32: 29 | B32: 45898 | G32: =E32*F32 -> 0 | J32: =H32*I32 -> 0 | K32: =G32+J32 -> 0 | M32: =M31+K32-L32 -> 0
A33: 30 | B33: 45899 | G33: =E33*F33 -> 0 | J33: =H33*I33 -> 0 | K33: =G33+J33 -> 0 | L33: 0 | M33: =M32+K33-L33 -> 0
A34: 31 | G34: =E34*F34 -> 0 | J34: =H34*I34 -> 0 | K34: =G34+J34 -> 0 | L34: 0 | M34: =M33+K34-L34 -> 0
E35: =SUM(E4:E34) -> 38.25 | G35: =SUM(G4:G34) -> 3999.42 | H35: =SUM(H4:H34) -> 20 | J35: =SUM(J4:J34) -> 2330.8 | K35: =SUM(K4:K34) -> 6330.22 | L35: =SUM(L4:L34) -> 58939.365

Sheet  Sangareddy-3
A1: SHIVA PARVATHI FILLING STATION SADASHIVPET
A2: S.No | B2: Date | C2: GRN No | D2: Ind no/Bill No | E2: Diesel (Lts) | F2: Price | G2: Amount | H2: Petrol (Lts) | I2: Price | J2: Amount | K2: Total amount | L2: Amount paid | M2: As on Date | N2: Remarks
A3: Opening Balance | M3: 754936.41
A4: 1 | B4: 45870 | E4: 600 | F4: 104.35 | G4: =E4*F4 -> 62610 | J4: =H4*I4 -> 0 | K4: =G4+J4 -> 62610 | M4: =M3+K4-L4 -> 817546.41
A5: 2 | B5: 45871 | E5: 690 | F5: 104.35 | G5: =E5*F5 -> 72001.5 | J5: =H5*I5 -> 0 | K5: =G5+J5 -> 72001.5 | M5: =M4+K5-L5 -> 889547.91
A6: 3 | B6: 45872 | G6: =E6*F6 -> 0 | J6: =H6*I6 -> 0 | K6: =G6+J6 -> 0 | M6: =M5+K6-L6 -> 889547.91
A7: 4 | B7: 45873 | G7: =E7*F7 -> 0 | J7: =H7*I7 -> 0 | K7: =G7+J7 -> 0 | M7: =M6+K7-L7 -> 889547.91
A8: 5 | B8: 45874 | G8: =E8*F8 -> 0 | J8: =H8*I8 -> 0 | K8: =G8+J8 -> 0 | M8: =M7+K8-L8 -> 889547.91
A9: 6 | B9: 45875 | E9: 600 | F9: 104.35 | G9: =E9*F9 -> 62610 | J9: =H9*I9 -> 0 | K9: =G9+J9 -> 62610 | M9: =M8+K9-L9 -> 952157.91
A10: 7 | B10: 45876 | E10: 690 | F10: 104.35 | G10: =E10*F10 -> 72001.5 | H10: 6 | I10: 116.25 | J10: =H10*I10 -> 697.5 | K10: =G10+J10 -> 72699 | M10: =M9+K10-L10 -> 1024856.9
A11: 8 | B11: 45877 | G11: =E11*F11 -> 0 | J11: =H11*I11 -> 0 | K11: =G11+J11 -> 0 | M11: =M10+K11-L11 -> 1024856.9
A12: 9 | B12: 45878 | G12: =E12*F12 -> 0 | J12: =H12*I12 -> 0 | K12: =G12+J12 -> 0 | M12: =M11+K12-L12 -> 1024856.9
A13: 10 | B13: 45879 | E13: 690 | F13: 104.35 | G13: =E13*F13 -> 72001.5 | H13: 12 | I13: 116.25 | J13: =H13*I13 -> 1395 | K13: =G13+J13 -> 73396.5 | M13: =M12+K13-L13 -> 1098253.4
A14: 11 | B14: 45880 | E14: 690 | F14: 104.35 | G14: =E14*F14 -> 72001.5 | H14: 6 | I14: 116.25 | J14: =H14*I14 -> 697.5 | K14: =G14+J14 -> 72699 | M14: =M13+K14-L14 -> 1170952.4
A15: 12 | B15: 45881 | G15: =E15*F15 -> 0 | K15: =G15+J15 -> 0 | M15: =M14+K15-L15 -> 1170952.4
A16: 13 | B16: 45882 | E16: 734 | F16: 104.35 | G16: =E16*F16 -> 76592.9 | J16: =H16*I16 -> 0 | K16: =G16+J16 -> 76592.9 | M16: =M15+K16-L16 -> 1247545.3
A17: 14 | B17: 45883 | E17: 690 | F17: 104.35 | G17: =E17*F17 -> 72001.5 | H17: 6 | I17: 116.25 | J17: =H17*I17 -> 697.5 | K17: =G17+J17 -> 72699 | M17: =M16+K17-L17 -> 1320244.3
A18: 15 | B18: 45884 | G18: =E18*F18 -> 0 | J18: =H18*I18 -> 0 | K18: =G18+J18 -> 0 | M18: =M17+K18-L18 -> 1320244.3
A19: 16 | B19: 45885 | G19: =E19*F19 -> 0 | H19: 18 | I19: 116.25 | J19: =H19*I19 -> 2092.5 | K19: =G19+J19 -> 2092.5 | M19: =M18+K19-L19 -> 1322336.8
A20: 17 | B20: 45886 | E20: 690 | F20: 104.35 | G20: =E20*F20 -> 72001.5 | J20: =H20*I20 -> 0 | K20: =G20+J20 -> 72001.5 | M20: =M19+K20-L20 -> 1394338.3
A21: 18 | B21: 45887 | G21: =E21*F21 -> 0 | H21: 6 | I21: 116.25 | J21: =H21*I21 -> 697.5 | K21: =G21+J21 -> 697.5 | M21: =M20+K21-L21 -> 1395035.8
A22: 19 | B22: 45888 | E22: 690 | F22: 104.35 | G22: =E22*F22 -> 72001.5 | J22: =H22*I22 -> 0 | K22: =G22+J22 -> 72001.5 | M22: =M21+K22-L22 -> 1467037.3
A23: 20 | B23: 45889 | G23: =E23*F23 -> 0 | J23: =H23*I23 -> 0 | K23: =G23+J23 -> 0 | L23: 800000 | M23: =M22+K23-L23 -> 667037.31
A24: 21 | B24: 45890 | E24: 730 | F24: 104.35 | G24: =E24*F24 -> 76175.5 | J24: =H24*I24 -> 0 | K24: =G24+J24 -> 76175.5 | M24: =M23+K24-L24 -> 743212.81
A25: 22 | B25: 45891 | E25: 600 | F25: 104.35 | G25: =E25*F25 -> 62610 | J25: =H25*I25 -> 0 | K25: =G25+J25 -> 62610 | M25: =M24+K25-L25 -> 805822.81
A26: 23 | B26: 45892 | G26: =E26*F26 -> 0 | J26: =H26*I26 -> 0 | K26: =G26+J26 -> 0 | M26: =M25+K26-L26 -> 805822.81
A27: 24 | B27: 45893 | G27: =E27*F27 -> 0 | J27: =H27*I27 -> 0 | K27: =G27+J27 -> 0 | M27: =M26+K27-L27 -> 805822.81
A28: 25 | B28: 45894 | G28: =E28*F28 -> 0 | H28: 12 | I28: 116.25 | J28: =H28*I28 -> 1395 | K28: =G28+J28 -> 1395 | M28: =M27+K28-L28 -> 807217.81
A29: 26 | B29: 45895 | G29: =E29*F29 -> 0 | J29: =H29*I29 -> 0 | K29: =G29+J29 -> 0 | M29: =M28+K29-L29 -> 807217.81
A30: 27 | B30: 45896 | G30: =E30*F30 -> 0 | J30: =H30*I30 -> 0 | K30: =G30+J30 -> 0 | M30: =M29+K30-L30 -> 807217.81
A31: 28 | B31: 45897 | G31: =E31*F31 -> 0 | H31: 6 | I31: 126.03 | J31: =H31*I31 -> 756.18 | K31: =G31+J31 -> 756.18 | L31: 807217 | M31: =M30+K31-L31 -> 756.9929
A32: 29 | B32: 45898 | E32: 690 | F32: 104.35 | G32: =E32*F32 -> 72001.5 | H32: 6 | I32: 116.25 | J32: =H32*I32 -> 697.5 | K32: =G32+J32 -> 72699 | M32: =M31+K32-L32 -> 73455.993
A33: 30 | B33: 45899 | G33: =E33*F33 -> 0 | J33: =H33*I33 -> 0 | K33: =G33+J33 -> 0 | M33: =M32+K33-L33 -> 73455.993
A34: 31 | B34: 45900 | E34: 690 | F34: 104.35 | G34: =E34*F34 -> 72001.5 | H34: 6 | I34: 116.25 | J34: =H34*I34 -> 697.5 | K34: =G34+J34 -> 72699 | M34: =M33+K34-L34 -> 146154.99
A35: 32 | G35: =E35*F35 -> 0 | J35: =H35*I35 -> 0 | K35: =G35+J35 -> 0 | M35: =M34+K35-L35 -> 146154.99
E36: =SUM(E4:E35) -> 9474 | G36: =SUM(G4:G35) -> 988611.9 | H36: =SUM(H4:H35) -> 84 | J36: =SUM(J4:J35) -> 9823.68 | K36: =SUM(K4:K35) -> 998435.58 | L36: =SUM(L4:L35) -> 1607217

Sheet Narayankhed
A2: S.No | B2: Date | C2: GRN No | D2: Ind no/Bill No | E2: Diesel (Lts) | F2: Price | G2: Amount | H2: Petrol (Lts) | I2: Price | J2: Amount | K2: Total amount | L2: Amount paid | M2: As on Date | N2: Remarks
A3: Opening Balance | M3: 0
A4: 1 | B4: 45870 | G4: =E4*F4 -> 0 | J4: =H4*I4 -> 0 | K4: =G4+J4 -> 0 | L4: =H4+K4 -> 0 | M4: =M3+K4-L4 -> 0
A5: 2 | B5: 45871 | G5: =E5*F5 -> 0 | J5: =H5*I5 -> 0 | K5: =G5+J5 -> 0 | L5: =H5+K5 -> 0 | M5: =M4+K5-L5 -> 0 | S5: 185.65
A6: 3 | B6: 45872 | G6: =E6*F6 -> 0 | J6: =H6*I6 -> 0 | K6: =G6+J6 -> 0 | L6: =H6+K6 -> 0 | M6: =M5+K6-L6 -> 0 | S6: 5
A7: 4 | B7: 45873 | G7: =E7*F7 -> 0 | J7: =H7*I7 -> 0 | K7: =G7+J7 -> 0 | L7: =H7+K7 -> 0 | M7: =M6+K7-L7 -> 0 | S7: 95.33
A8: 5 | B8: 45874 | G8: =E8*F8 -> 0 | J8: =H8*I8 -> 0 | K8: =G8+J8 -> 0 | L8: =H8+K8 -> 0 | M8: =M7+K8-L8 -> 0
A9: 6 | B9: 45875 | G9: =E9*F9 -> 0 | J9: =H9*I9 -> 0 | K9: =G9+J9 -> 0 | L9: 0 | M9: =M8+K9-L9 -> 0
A10: 7 | B10: 45876 | G10: =E10*F10 -> 0 | J10: =H10*I10 -> 0 | K10: =G10+J10 -> 0 | L10: 0 | M10: =M9+K10-L10 -> 0
A11: 8 | B11: 45877 | G11: =E11*F11 -> 0 | J11: =H11*I11 -> 0 | K11: =G11+J11 -> 0 | L11: =H11+K11 -> 0 | M11: =M10+K11-L11 -> 0
A12: 9 | B12: 45878 | G12: =E12*F12 -> 0 | J12: =H12*I12 -> 0 | K12: =G12+J12 -> 0 | L12: 0 | M12: =M11+K12-L12 -> 0
A13: 10 | B13: 45879 | G13: =E13*F13 -> 0 | J13: =H13*I13 -> 0 | K13: =G13+J13 -> 0 | L13: =H13+K13 -> 0 | M13: =M12+K13-L13 -> 0
A14: 11 | B14: 45880 | G14: =E14*F14 -> 0 | J14: =H14*I14 -> 0 | K14: =G14+J14 -> 0 | L14: =H14+K14 -> 0 | M14: =M13+K14-L14 -> 0
A15: 12 | B15: 45881 | G15: =E15*F15 -> 0 | J15: =H15*I15 -> 0 | K15: =G15+J15 -> 0 | L15: =H15+K15 -> 0 | M15: =M14+K15-L15 -> 0
A16: 13 | B16: 45882 | G16: =E16*F16 -> 0 | J16: =H16*I16 -> 0 | K16: =G16+J16 -> 0 | L16: =H16+K16 -> 0 | M16: =M15+K16-L16 -> 0
A17: 14 | B17: 45883 | E17: 285.39 | F17: 105.12 | G17: =E17*F17 -> 30000.197 | J17: =H17*I17 -> 0 | K17: =G17+J17 -> 30000.197 | L17: =H17+K17 -> 30000.197 | M17: =M16+K17-L17 -> 0 | N17: BT
A18: 15 | B18: 45884 | G18: =E18*F18 -> 0 | J18: =H18*I18 -> 0 | K18: =G18+J18 -> 0 | L18: =H18+K18 -> 0 | M18: =M17+K18-L18 -> 0
A19: 16 | B19: 45885 | G19: =E19*F19 -> 0 | J19: =H19*I19 -> 0 | K19: =G19+J19 -> 0 | L19: =H19+K19 -> 0 | M19: =M18+K19-L19 -> 0
A20: 17 | B20: 45886 | E20: 285.39 | F20: 105.12 | G20: =E20*F20 -> 30000.197 | J20: =H20*I20 -> 0 | K20: =G20+J20 -> 30000.197 | L20: =H20+K20 -> 30000.197 | M20: =M19+K20-L20 -> 0 | N20: BT
A21: 18 | B21: 45887 | G21: =E21*F21 -> 0 | J21: =H21*I21 -> 0 | K21: =G21+J21 -> 0 | L21: =H21+K21 -> 0 | M21: =M20+K21-L21 -> 0
A22: 19 | B22: 45888 | G22: =E22*F22 -> 0 | J22: =H22*I22 -> 0 | K22: =G22+J22 -> 0 | L22: =H22+K22 -> 0 | M22: =M21+K22-L22 -> 0
A23: 20 | B23: 45889 | E23: 285.39 | F23: 105.12 | G23: =E23*F23 -> 30000.197 | J23: =H23*I23 -> 0 | K23: =G23+J23 -> 30000.197 | L23: =H23+K23 -> 30000.197 | M23: =M22+K23-L23 -> 0 | N23: BT
A24: 21 | B24: 45890 | G24: =E24*F24 -> 0 | J24: =H24*I24 -> 0 | K24: =G24+J24 -> 0 | L24: =H24+K24 -> 0 | M24: =M23+K24-L24 -> 0
A25: 22 | B25: 45891 | G25: =E25*F25 -> 0 | J25: =H25*I25 -> 0 | K25: =G25+J25 -> 0 | L25: =H25+K25 -> 0 | M25: =M24+K25-L25 -> 0
A26: 23 | B26: 45892 | G26: =E26*F26 -> 0 | J26: =H26*I26 -> 0 | K26: =G26+J26 -> 0 | L26: =+K26 -> 0 | M26: =M25+K26-L26 -> 0
A27: 24 | B27: 45893 | G27: =E27*F27 -> 0 | J27: =H27*I27 -> 0 | K27: =G27+J27 -> 0 | L27: =+K27 -> 0 | M27: =M26+K27-L27 -> 0
A28: 25 | B28: 45894 | G28: =E28*F28 -> 0 | J28: =H28*I28 -> 0 | K28: =G28+J28 -> 0 | L28: =+K28 -> 0 | M28: =M27+K28-L28 -> 0
A29: 26 | B29: 45895 | G29: =E29*F29 -> 0 | J29: =H29*I29 -> 0 | K29: =G29+J29 -> 0 | L29: =+K29 -> 0 | M29: =M28+K29-L29 -> 0 | U29: =50000/104.9 -> 476.64442
A30: 27 | B30: 45896 | G30: =E30*F30 -> 0 | J30: =H30*I30 -> 0 | K30: =G30+J30 -> 0 | L30: =+K30 -> 0 | M30: =M29+K30-L30 -> 0
A31: 28 | B31: 45897 | G31: =E31*F31 -> 0 | J31: =H31*I31 -> 0 | K31: =G31+J31 -> 0 | L31: =+K31 -> 0 | M31: =M30+K31-L31 -> 0
A32: 29 | B32: 45898 | G32: =E32*F32 -> 0 | J32: =H32*I32 -> 0 | K32: =G32+J32 -> 0 | L32: =+K32 -> 0 | M32: =M31+K32-L32 -> 0
A33: 30 | B33: 45899 | G33: =E33*F33 -> 0 | J33: =H33*I33 -> 0 | K33: =G33+J33 -> 0 | L33: =+K33 -> 0 | M33: =M32+K33-L33 -> 0
A34: 31 | B34: 45900 | E34: 476.64442 | F34: 104.9 | G34: =E34*F34 -> 50000 | J34: =H34*I34 -> 0 | K34: =G34+J34 -> 50000 | L34: =+K34 -> 50000 | M34: 0 | N34: BT
E35: =SUM(E4:E34) -> 1332.8144 | G35: =SUM(G4:G34) -> 140000.59 | H35: =SUM(H4:H34) -> 0 | J35: =SUM(J4:J34) -> 0 | K35: =SUM(K4:K34) -> 140000.59 | L35: =SUM(L4:L34) -> 140000.59

Sheet Dindi
A1: Akarapu Balakistamma Fillling
A2: S.No | B2: Date | C2: GRN No | D2: Ind no/Bill No | E2: Diesel (Lts) | F2: Price | G2: Amount | H2: Petrol (Lts) | I2: Price | J2: Amount | K2: Total amount | L2: Amount paid | M2: As on Date | N2: Remarks
A3: Opening Balance | M3: 0
A4: 1 | B4: 45870 | G4: =E4*F4 -> 0 | H4: 0 | I4: 0 | J4: =H4*I4 -> 0 | K4: =G4+J4 -> 0 | L4: =+K4 -> 0 | M4: 0
A5: 2 | B5: 45871 | G5: =E5*F5 -> 0 | H5: 0 | I5: 0 | J5: =H5*I5 -> 0 | K5: =G5+J5 -> 0 | L5: =+K5 -> 0 | M5: 0
A6: 3 | B6: 45872 | G6: =E6*F6 -> 0 | H6: 0 | I6: 0 | J6: =H6*I6 -> 0 | K6: =G6+J6 -> 0 | L6: =+K6 -> 0 | M6: 0
A7: 4 | B7: 45873 | G7: =E7*F7 -> 0 | H7: 0 | I7: 0 | J7: =H7*I7 -> 0 | K7: =G7+J7 -> 0 | L7: =+K7 -> 0 | M7: 0
A8: 5 | B8: 45874 | G8: =E8*F8 -> 0 | H8: 0 | I8: 0 | J8: =H8*I8 -> 0 | K8: =G8+J8 -> 0 | L8: =+K8 -> 0 | M8: 0
A9: 6 | B9: 45875 | G9: =E9*F9 -> 0 | H9: 0 | I9: 0 | J9: =H9*I9 -> 0 | K9: =G9+J9 -> 0 | L9: =+K9 -> 0 | M9: 0
A10: 7 | B10: 45876 | G10: =E10*F10 -> 0 | H10: 0 | I10: 0 | J10: =H10*I10 -> 0 | K10: =G10+J10 -> 0 | L10: =+K10 -> 0 | M10: 0
A11: 8 | B11: 45877 | G11: =E11*F11 -> 0 | H11: 0 | I11: 0 | J11: =H11*I11 -> 0 | K11: =G11+J11 -> 0 | L11: =+K11 -> 0 | M11: 0
A12: 9 | B12: 45878 | G12: =E12*F12 -> 0 | H12: 0 | I12: 0 | J12: =H12*I12 -> 0 | K12: =G12+J12 -> 0 | L12: =+K12 -> 0 | M12: 0
A13: 10 | B13: 45879 | G13: =E13*F13 -> 0 | H13: 0 | I13: 0 | J13: =H13*I13 -> 0 | K13: =G13+J13 -> 0 | L13: =+K13 -> 0 | M13: 0
A14: 11 | B14: 45880 | G14: =E14*F14 -> 0 | H14: 0 | I14: 0 | J14: =H14*I14 -> 0 | K14: =G14+J14 -> 0 | L14: =+K14 -> 0 | M14: 0
A15: 12 | B15: 45881 | G15: =E15*F15 -> 0 | H15: 0 | I15: 0 | J15: =H15*I15 -> 0 | K15: =G15+J15 -> 0 | L15: =+K15 -> 0 | M15: 0
... A27: 24 | B27: 45893 | G27: =E27*F27 -> 0 | H27: 0 | I27: 0 | J27: =H27*I27 -> 0 | K27: =G27+J27 -> 0 | L27: =+K27 -> 0 | M27: 0
A28: 25 | B28: 45894 | E28: 33.78 | F28: 104.95 | G28: =E28*F28 -> 3545.211 | H28: 0 | I28: 0 | J28: =H28*I28 -> 0 | K28: =G28+J28 -> 3545.211 | L28: =+K28 -> 3545.211 | M28: 0
A29: 26 | B29: 45895 | G29: =E29*F29 -> 0 | H29: 0 | I29: 0 | J29: =H29*I29 -> 0 | K29: =G29+J29 -> 0 | L29: =+K29 -> 0 | M29: 0
A30: 27 | B30: 45896 | G30: =E30*F30 -> 0 | H30: 0 | I30: 0 | J30: =H30*I30 -> 0 | K30: =G30+J30 -> 0 | L30: =+K30 -> 0 | M30: 0
A31: 28 | B31: 45897 | G31: =E31*F31 -> 0 | H31: 0 | I31: 0 | J31: =H31*I31 -> 0 | K31: =G31+J31 -> 0 | L31: =+K31 -> 0 | M31: 0
A32: 29 | B32: 45898 | G32: =E32*F32 -> 0 | H32: 0 | I32: 0 | J32: =H32*I32 -> 0 | K32: =G32+J32 -> 0 | L32: =+K32 -> 0 | M32: 0
A33: 30 | B33: 45899 | G33: =E33*F33 -> 0 | H33: 0 | I33: 0 | J33: =H33*I33 -> 0 | K33: =G33+J33 -> 0 | L33: =+K33 -> 0 | M33: 0
A34: 31 | G34: =E34*F34 -> 0 | H34: 0 | I34: 0 | J34: =H34*I34 -> 0 | K34: =G34+J34 -> 0 | L34: =+K34 -> 0 | M34: 0
E35: =SUM(E4:E34) -> 33.78 | G35: =SUM(G4:G34) -> 3545.211 | H35: =SUM(H4:H34) -> 0 | J35: =SUM(J4:J34) -> 0 | K35: =SUM(K4:K34) -> 3545.211 | L35: =SUM(L4:L34) -> 3545.211

Sheet Multiple bunks(KKD)
A2: S.No | B2: Date | C2: GRN No | D2: Ind no/Bill No | E2: Diesel (Lts) | F2: Price | G2: Amount | H2: Petrol (Lts) | I2: Price | J2: Amount | K2: Total amount | L2: Amount paid | M2: As on Date | N2: Remarks
A3: Opening Balance | M3: 0
A4: 1 | B4: 46235 | C4: DEVI VYSHNAVI FILLING STATION | D4: BALABHADRAPURAM | E4: 30 | F4: =G4/E4 -> 104.67 | G4: 3140.1 | J4: =H4*I4 -> 0 | K4: =G4+J4 -> 3140.1 | L4: =+K4 -> 3140.1 | M4: 0 | N4: 0
A5: 2 | B5: 46235 | C5: BP - KOVVUR | D5: KOVVUR | G5: 0 | H5: 10 | I5: =J5/H5 -> 116.99 | J5: 1169.9 | K5: =G5+J5 -> 1169.9 | L5: =+K5 -> 1169.9 | M5: 0 | N5: 0
A6: 3 | B6: 46235 | C6: SRI BHIMESWARA AGENCIES | D6: AMALAPURAM | G6: 0 | H6: 8.57 | I6: =J6/H6 -> 117.6196 | J6: 1008 | K6: =G6+J6 -> 1008 | L6: =+K6 -> 1008 | M6: 0 | N6: 0
A7: 4 | B7: 46235 | C7: BP - KOVVUR | D7: KOVVUR | E7: 5.76 | F7: =G7/E7 -> 104.69965 | G7: 603.07 | J7: =H7*I7 -> 0 | K7: =G7+J7 -> 603.07 | L7: =+K7 -> 603.07 | M7: 0 | N7: 0
A8: 5 | B8: 46235 | C8: MOTILAL RUPCHAND | D8: KOVVUR | E8: 50 | F8: =G8/E8 -> 104.7 | G8: 5235 | J8: =H8*I8 -> 0 | K8: =G8+J8 -> 5235 | L8: =+K8 -> 5235 | M8: 0 | N8: 0
A9: 6 | B9: 46236 | C9: BP - KOVVUR | D9: KOVVUR | E9: 10 | F9: =G9/E9 -> 104.7 | G9: 1047 | J9: =H9*I9 -> 0 | K9: =G9+J9 -> 1047 | L9: =+K9 -> 1047 | M9: 0 | N9: 0
A10: 7 | B10: 46236 | C10: SRI BHIMESWARA AGENCIES | D10: AMALAPURAM | G10: 0 | H10: 5 | I10: =J10/H10 -> 117.62 | J10: 588.1 | K10: =G10+J10 -> 588.1 | L10: =+K10 -> 588.1 | M10: 0 | N10: 0
A11: 8 | B11: 46237 | C11: SRI BHIMESWARA AGENCIES | D11: AMALAPURAM | E11: 44.13 | F11: =G11/E11 -> 105.29005 | G11: 4646.45 | J11: =H11*I11 -> 0 | K11: =G11+J11 -> 4646.45 | L11: =+K11 -> 4646.45 | M11: 0 | N11: 0
A12: 9 | B12: 46237 | C12: BP - KOVVUR | D12: KOVVUR | G12: 0 | H12: 8 | I12: =J12/H12 -> 116.99 | J12: 935.92 | K12: =G12+J12 -> 935.92 | L12: =+K12 -> 935.92 | M12: 0 | N12: 0
A13: 10 | B13: 46237 | C13: SOLASA KRISHNA OIL COMPANY | D13: JANGAREDDYGUDEM | E13: 30 | F13: =G13/E13 -> 105.4 | G13: 3162 | J13: =H13*I13 -> 0 | K13: =G13+J13 -> 3162 | L13: =+K13 -> 3162 | M13: 0 | N13: 0
A14: 11 | B14: 46237 | C14: BP - CHAKRADWARABANDHAM | D14: RAJHAMUNDRY | E14: 28.7 | F14: =G14/E14 -> 104.52962 | G14: 3000 | J14: =H14*I14 -> 0 | K14: =G14+J14 -> 3000 | L14: =+K14 -> 3000 | M14: 0 | N14: 0
A15: 12 | B15: 46237 | C15: BP - QUARRY MARKET | D15: RAJHAMUNDRY | G15: 0 | H15: 30.01 | I15: =J15/H15 -> 116.90003 | J15: 3508.17 | K15: =G15+J15 -> 3508.17 | L15: =+K15 -> 3508.17 | M15: 0 | N15: 0
A16: 13 | B16: 46238 | C16: SRI BALAJI AGENCIES | D16: KAKINADA | G16: 0 | H16: 4.71 | I16: =J16/H16 -> 117.97877 | J16: 555.68 | K16: =G16+J16 -> 555.68 | L16: =+K16 -> 555.68 | M16: 0 | N16: 0
A17: 14 | B17: 46238 | C17: SRI MALLIDI VENKATA REDDY AGENCIES | D17: MANDAPETA | G17: 0 | H17: 5 | I17: =J17/H17 -> 117.32 | J17: 586.6 | K17: =G17+J17 -> 586.6 | L17: =+K17 -> 586.6 | M17: 0 | N17: 0
A18: 15 | B18: 46238 | C18: TIRUMALA AGENCIES | D18: MUMIDIVARAM | E18: 130 | F18: =G18/E18 -> 105.35 | G18: 13695.5 | J18: =H18*I18 -> 0 | K18: =G18+J18 -> 13695.5 | L18: =+K18 -> 13695.5 | M18: 0 | N18: 0
A19: 16 | B19: 46238 | C19: SRI MALLIDI VENKATA REDDY AGENCIES | D19: MANDAPETA | E19: 50 | F19: =G19/E19 -> 105.01 | G19: 5250.5 | J19: =H19*I19 -> 0 | K19: =G19+J19 -> 5250.5 | L19: =+K19 -> 5250.5 | M19: 0 | N19: 0
A20: 17 | B20: 46238 | C20: SRI BALAJI AGENCIES | D20: KAKINADA | E20: 36.65 | F20: =G20/E20 -> 105.5899 | G20: 3869.87 | J20: =H20*I20 -> 0 | K20: =G20+J20 -> 3869.87 | L20: =+K20 -> 3869.87 | M20: 0 | N20: 0
A21: 18 | B21: 46238 | C21: KILARAM BROTHERS | E21: 30 | F21: =G21/E21 -> 105.33 | G21: 3159.9 | J21: =H21*I21 -> 0 | K21: =G21+J21 -> 3159.9 | L21: =+K21 -> 3159.9 | M21: 0 | N21: 0
A22: 19 | B22: 46238 | C22: SOLASA KRISHNA OIL COMPANY | D22: JANGAREDDYGUDEM | E22: 70 | F22: 105.4 | G22: 7378 | J22: =H22*I22 -> 0 | K22: =G22+J22 -> 7378 | L22: =+K22 -> 7378 | M22: 0 | N22: 0
A23: 20 | B23: 46239 | C23: SRI BALAJI AGENCIES | D23: KAKINADA | E23: 28.41 | F23: 105.4 | G23: 3000 | J23: =H23*I23 -> 0 | K23: =G23+J23 -> 3000 | L23: =+K23 -> 3000 | M23: 0 | N23: 0
A24: 21 | B24: 46239 | C24: SRI MALLIDI VENKATA REDDY AGENCIES | D24: MANDAPETA | E24: 38.09 | F24: 105.4 | G24: 4000 | J24: =H24*I24 -> 0 | K24: =G24+J24 -> 4000 | L24: =+K24 -> 4000 | M24: 0 | N24: 0
A25: 22 | B25: 46239 | C25: SRI BHIMESWARA AGENCIES | D25: AMALAPURAM | G25: 0 | H25: 4 | I25: =J25/H25 -> 117.62 | J25: 470.48 | K25: =G25+J25 -> 470.48 | L25: =+K25 -> 470.48 | M25: 0 | N25: 0
A26: 23 | B26: 46240 | C26: SRI BALAJI AGENCIES | D26: KAKINADA | E26: 45.01 | F26: =G26/E26 -> 105.59009 | G26: 4752.61 | J26: =H26*I26 -> 0 | K26: =G26+J26 -> 4752.61 | L26: =+K26 -> 4752.61 | M26: 0 | N26: 0
A27: 24 | B27: 46240 | C27: SOLASA KRISHNA OIL COMPANY | D27: JANGAREDDYGUDEM | E27: 80 | F27: =G27/E27 -> 105.4 | G27: 8432 | J27: =H27*I27 -> 0 | K27: =G27+J27 -> 8432 | L27: =+K27 -> 8432 | M27: 0 | N27: 0
A28: 25 | B28: 46240 | C28: BP - KOVVUR | D28: KOVVUR | E28: 44.35 | F28: =G28/E28 -> 104.70011 | G28: 4643.45 | J28: =H28*I28 -> 0 | K28: =G28+J28 -> 4643.45 | L28: =+K28 -> 4643.45 | M28: 0 | N28: 0
A29: 26 | B29: 46240 | C29: BP - KOVVUR | D29: KOVVUR | G29: 0 | H29: 5 | I29: =J29/H29 -> 116.99 | J29: 584.95 | K29: =G29+J29 -> 584.95 | L29: =+K29 -> 584.95 | M29: 0 | N29: 0
A30: 27 | B30: 46240 | C30: SRI BALAJI AGENCIES | D30: KAKINADA | G30: 0 | H30: 3 | I30: =J30/H30 -> 117.98 | J30: 353.94 | K30: =G30+J30 -> 353.94 | L30: =+K30 -> 353.94 | M30: 0 | N30: 0
A31: 28 | B31: 46240 | C31: SRI BALAJI AGENCIES | D31: KAKINADA | E31: 50 | F31: =G31/E31 -> 105.59 | G31: 5279.5 | J31: =H31*I31 -> 0 | K31: =G31+J31 -> 5279.5 | L31: =+K31 -> 5279.5 | M31: 0 | N31: 0
A32: 29 | B32: 46240 | C32: SREE SURYAPRAKASH SERVICE STATION | D32: RAJHAMUNDRY | E32: 30 | F32: =G32/E32 -> 104.62 | G32: 3138.6 | J32: =H32*I32 -> 0 | K32: =G32+J32 -> 3138.6 | L32: =+K32 -> 3138.6 | M32: 0 | N32: 0
A33: 30 | B33: 46240 | C33: SOLASA KRISHNA OIL COMPANY | D33: JANGAREDDYGUDEM | G33: 0 | H33: 5.01 | I33: =J33/H33 -> 117.76447 | J33: 590 | K33: =G33+J33 -> 590 | L33: =+K33 -> 590 | M33: 0 | N33: 0
A34: 31 | B34: 46240 | C34: SOLASA KRISHNA OIL COMPANY | D34: JANGAREDDYGUDEM | E34: 50 | F34: =G34/E34 -> 105.4 | G34: 5270 | J34: =H34*I34 -> 0 | K34: =G34+J34 -> 5270 | L34: =+K34 -> 5270 | M34: 0 | N34: 0
A35: 32 | B35: 46241 | C35: SRI MALLIDI VENKATA REDDY AGENCIES | D35: MANDAPETA | E35: 80 | F35: =G35/E35 -> 105.01 | G35: 8400.8 | J35: =H35*I35 -> 0 | K35: =G35+J35 -> 8400.8 | L35: =+K35 -> 8400.8 | M35: 0 | N35: 0
A36: 33 | B36: 46241 | C36: SRI BALAJI AGENCIES | D36: KAKINADA | G36: 0 | H36: 5 | I36: =J36/H36 -> 117.98 | J36: 589.9 | K36: =G36+J36 -> 589.9 | L36: =+K36 -> 589.9 | M36: 0 | N36: 0
A37: 34 | B37: 46241 | C37: SRI MALLIDI VENKATA REDDY AGENCIES | D37: MANDAPETA | G37: 0 | H37: 5 | I37: =J37/H37 -> 117.32 | J37: 586.6 | K37: =G37+J37 -> 586.6 | L37: =+K37 -> 586.6 | M37: 0 | N37: 0
A38: 35 | B38: 46242 | C38: SRI BALAJI AGENCIES | D38: KAKINADA | G38: 0 | H38: 5 | I38: =J38/H38 -> 117.98 | J38: 589.9 | K38: =G38+J38 -> 589.9 | L38: =+K38 -> 589.9 | M38: 0 | N38: 0
A39: 36 | B39: 46242 | C39: BP - KOVVUR | D39: KOVVUR | E39: 4.78 | F39: =G39/E39 -> 104.60251 | G39: 500 | J39: =H39*I39 -> 0 | K39: =G39+J39 -> 500 | L39: =+K39 -> 500 | M39: 0 | N39: 0
A40: 37 | B40: 46242 | C40: BP - KOVVUR | D40: KOVVUR | G40: 0 | H40: 5 | I40: =J40/H40 -> 116.99 | J40: 584.95 | K40: =G40+J40 -> 584.95 | L40: =+K40 -> 584.95 | M40: 0 | N40: 0
A41: 38 | B41: 46242 | C41: SRI BALAJI AGENCIES | D41: KAKINADA | G41: 0 | H41: 4 | I41: =J41/H41 -> 117.98 | J41: 471.92 | K41: =G41+J41 -> 471.92 | L41: =+K41 -> 471.92 | M41: 0 | N41: 0
A42: 39 | B42: 46242 | C42: SOLASA KRISHNA OIL COMPANY | D42: JANGAREDDYGUDEM | E42: 15 | F42: =G42/E42 -> 105.4 | G42: 1581 | J42: =H42*I42 -> 0 | K42: =G42+J42 -> 1581 | L42: =+K42 -> 1581 | M42: 0 | N42: 0
A43: 40 | B43: 46242 | C43: RAJ PETROS | D43: RAVULAPALEM | E43: 150.01 | F43: =G43/E43 -> 104.93 | G43: 15740.55 | J43: =H43*I43 -> 0 | K43: =G43+J43 -> 15740.55 | L43: =+K43 -> 15740.55 | M43: 0 | N43: 0
A44: 41 | B44: 46243 | C44: SRI BALAJI AGENCIES | D44: KAKINADA | H44: 2 | I44: =J44/H44 -> 117.98 | J44: 235.96 | K44: =G44+J44 -> 235.96 | L44: =+K44 -> 235.96 | M44: 0 | N44: 0
A45: 42 | B45: 46244 | C45: SREE SURYAPRAKASH SERVICE STATION | D45: RAJHAMUNDRY | E45: 19.12 | F45: =G45/E45 -> 104.60251 | G45: 2000 | J45: =H45*I45 -> 0 | K45: =G45+J45 -> 2000 | L45: =+K45 -> 2000 | M45: 0 | N45: 0
A46: 43 | B46: 46245 | C46: SRI BALAJI AGENCIES | D46: KAKINADA | E46: 18.94 | F46: =G46/E46 -> 105.58976 | G46: 1999.87 | J46: =H46*I46 -> 0 | K46: =G46+J46 -> 1999.87 | L46: =+K46 -> 1999.87 | M46: 0 | N46: 0
A47: 44 | B47: 46245 | C47: SRI BALAJI AGENCIES | D47: KAKINADA | E47: 9.47 | F47: =G47/E47 -> 105.59662 | G47: 1000 | J47: =H47*I47 -> 0 | K47: =G47+J47 -> 1000 | L47: =+K47 -> 1000 | M47: 0 | N47: 0
A48: 45 | B48: 46245 | C48: SRI BALAJI AGENCIES | D48: KAKINADA | G48: 0 | H48: 2 | I48: =J48/H48 -> 117.98 | J48: 235.96 | K48: =G48+J48 -> 235.96 | L48: =+K48 -> 235.96 | M48: 0 | N48: 0
A49: 46 | B49: 46245 | C49: BP - KOVVUR | D49: KOVVUR | E49: 35 | F49: =G49/E49 -> 104.7 | G49: 3664.5 | J49: =H49*I49 -> 0 | K49: =G49+J49 -> 3664.5 | L49: =+K49 -> 3664.5 | M49: 0 | N49: 0
A50: 47 | B50: 46246 | C50: BP - RAJANAGARAM | D50: RAJHAMUNDRY | E50: 9.57 | F50: =G50/E50 -> 104.49321 | G50: 1000 | J50: =H50*I50 -> 0 | K50: =G50+J50 -> 1000 | L50: =+K50 -> 1000 | M50: 0 | N50: 0 | O50: =+K50+M50-N50 -> 1000
A51: 48 | B51: 46246 | C51: SRI BALAJI AGENCIES | D51: KAKINADA | H51: 3 | I51: =J51/H51 -> 117.98 | J51: 353.94 | K51: =G51+J51 -> 353.94 | L51: =+K51 -> 353.94 | M51: 0 | N51: 0 | O51: =+K51+M51-N51 -> 353.94
A52: 49 | B52: 46246 | C52: BP - KOVVUR | D52: KOVVUR | E52: 30 | F52: =G52/E52 -> 104.7 | G52: 3141 | J52: =H52*I52 -> 0 | K52: =G52+J52 -> 3141 | L52: =+K52 -> 3141 | M52: 0 | N52: 0 | O52: =+K52+M52-N52 -> 3141
A53: 50 | B53: 46246 | C53: SRI MALLIDI VENKATA REDDY AGENCIES | D53: MANDAPETA | H53: 5 | I53: =J53/H53 -> 117.32 | J53: 586.6 | K53: =G53+J53 -> 586.6 | L53: =+K53 -> 586.6 | M53: 0 | N53: 0 | O53: =+K53+M53-N53 -> 586.6
A54: 51 | B54: 46247 | C54: SRI BALAJI AGENCIES | D54: KAKINADA | H54: 5 | I54: =J54/H54 -> 117.98 | J54: 589.9 | K54: =G54+J54 -> 589.9 | L54: =+K54 -> 589.9 | M54: 0 | N54: 0 | O54: =+K54+M54-N54 -> 589.9
A55: 52 | B55: 46247 | C55: SRI BALAJI AGENCIES | D55: KAKINADA | E55: 40 | F55: =G55/E55 -> 105.59 | G55: 4223.6 | J55: =H55*I55 -> 0 | K55: =G55+J55 -> 4223.6 | L55: =+K55 -> 4223.6 | M55: 0 | N55: 0 | O55: =+K55+M55-N55 -> 4223.6
A56: 53 | B56: 46248 | C56: SRI BALAJI AGENCIES | D56: KAKINADA | E56: 30 | F56: =G56/E56 -> 105.59 | G56: 3167.7 | J56: =H56*I56 -> 0 | K56: =G56+J56 -> 3167.7 | L56: =+K56 -> 3167.7 | M56: 0 | N56: 0 | O56: =+K56+M56-N56 -> 3167.7
A57: 54 | B57: 46248 | C57: SRI VIJAYAKRISHNA FILLING STATION | E57: 30 | F57: =G57/E57 -> 104.98 | G57: 3149.4 | J57: =H57*I57 -> 0 | K57: =G57+J57 -> 3149.4 | L57: =+K57 -> 3149.4 | M57: 0 | N57: 0 | O57: =+K57+M57-N57 -> 3149.4
A58: 55 | B58: 46250 | C58: BP - QUARRY MARKET | D58: RAJHAMUNDRY | E58: 14.34 | F58: =G58/E58 -> 104.60251 | G58: 1500 | J58: =H58*I58 -> 0 | K58: =G58+J58 -> 1500 | L58: =+K58 -> 1500 | M58: 0 | N58: 0 | O58: =+K58+M58-N58 -> 1500
A59: 56 | B59: 46250 | C59: BP - QUARRY MARKET | D59: KAKINADA | H59: 2 | I59: 117.98 | J59: =H59*I59 -> 235.96 | K59: =G59+J59 -> 235.96 | L59: =+K59 -> 235.96 | M59: 0 | N59: 0 | O59: =+K59+M59-N59 -> 235.96
A60: 57 | B60: 46250 | C60: BP - QUARRY MARKET | D60: KAKINADA | H60: 2 | I60: 117.98 | J60: =H60*I60 -> 235.96 | K60: =G60+J60 -> 235.96 | L60: =+K60 -> 235.96 | M60: 0 | N60: 0 | O60: =+K60+M60-N60 -> 235.96
A61: 58 | B61: 46251 | C61: SRI BALAJI AGENCIES | D61: KAKINADA | E61: 14.21 | F61: =G61/E61 -> 105.55947 | G61: 1500 | J61: =H61*I61 -> 0 | K61: =G61+J61 -> 1500 | L61: =+K61 -> 1500 | M61: 0 | N61: 0 | O61: =+K61+M61-N61 -> 1500
A62: 59 | B62: 46252 | C62: SRI BALAJI AGENCIES | D62: KAKINADA | E62: 47.35 | F62: 105.59 | G62: 5000 | J62: =H62*I62 -> 0 | K62: =G62+J62 -> 5000 | L62: =+K62 -> 5000 | M62: 0 | N62: 0 | O62: =+K62+M62-N62 -> 5000
A63: 60 | B63: 46252 | C63: SRI MALLIDI VENKATA REDDY AGENCIES | D63: MANDAPETA | H63: 5 | I63: 117.32 | J63: =H63*I63 -> 586.6 | K63: =G63+J63 -> 586.6 | L63: =+K63 -> 586.6 | M63: 0 | N63: 0 | O63: =+K63+M63-N63 -> 586.6
A64: 61 | B64: 46252 | C64: SRI BALAJI AGENCIES | D64: KAKINADA | H64: 4.73 | I64: 117.98 | J64: =H64*I64 -> 558.0454 | K64: =G64+J64 -> 558.0454 | L64: =+K64 -> 558.0454 | M64: 0 | N64: 0 | O64: =+K64+M64-N64 -> 558.0454
A65: 62 | B65: 46252 | C65: SRI BALAJI AGENCIES | D65: KAKINADA | H65: 5 | I65: 117.98 | J65: =H65*I65 -> 589.9 | K65: =G65+J65 -> 589.9 | L65: =+K65 -> 589.9 | M65: 0 | N65: 0 | O65: =+K65+M65-N65 -> 589.9
A66: 63 | B66: 46253 | C66: PSRG FILLING STATION | D66: YERNAGUDEM | E66: 38.14 | F66: 104.88 | G66: 4000 | J66: =H66*I66 -> 0 | K66: =G66+J66 -> 4000 | L66: =+K66 -> 4000 | M66: 0 | N66: 0 | O66: =+K66+M66-N66 -> 4000
A67: 64 | B67: 46255 | C67: SRI BALAJI AGENCIES | D67: KAKINADA | H67: 3 | I67: 117.98 | J67: =H67*I67 -> 353.94 | K67: =G67+J67 -> 353.94 | L67: =+K67 -> 353.94 | M67: 0 | N67: 0 | O67: =+K67+M67-N67 -> 353.94
A68: 65 | B68: 46255 | C68: SRI MALLIDI VENKATA REDDY AGENCIES | D68: MANDAPETA | H68: 5 | I68: 117.32 | J68: =H68*I68 -> 586.6 | K68: =G68+J68 -> 586.6 | L68: =+K68 -> 586.6 | M68: 0 | N68: 0 | O68: =+K68+M68-N68 -> 586.6
A69: 66 | B69: 46258 | C69: SRI BALAJI AGENCIES | D69: KAKINADA | H69: 5 | I69: 117.98 | J69: =H69*I69 -> 589.9 | K69: =G69+J69 -> 589.9 | L69: =+K69 -> 589.9 | M69: 0 | N69: 0 | O69: =+K69+M69-N69 -> 589.9
A70: 67 | B70: 46259 | C70: SRI MALLIDI VENKATA REDDY AGENCIES | D70: MANDAPETA | H70: 5 | I70: 117.32 | J70: =H70*I70 -> 586.6 | K70: =G70+J70 -> 586.6 | L70: =+K70 -> 586.6 | M70: 0 | N70: 0 | O70: =+K70+M70-N70 -> 586.6
A71: 68 | B71: 46260 | C71: SRI BALAJI AGENCIES | D71: KAKINADA | H71: 4.07 | I71: 117.98 | J71: =H71*I71 -> 480.1786 | K71: =G71+J71 -> 480.1786 | L71: =+K71 -> 480.1786 | M71: 0 | N71: 0 | O71: =+K71+M71-N71 -> 480.1786
A72: 69 | B72: 46261 | C72: BP-CHAKRADWARABANDHAM | D72: RAJHAMUNDRY | E72: 28.7 | F72: 104.54 | G72: 3000 | J72: =H72*I72 -> 0 | K72: =G72+J72 -> 3000 | L72: =+K72 -> 3000 | M72: 0 | N72: 0 | O72: =+K72+M72-N72 -> 3000
A73: 70 | B73: 46263 | C73: SRI MALLIDI VENKATA REDDY AGENCIES | D73: MANDAPETA | H73: 5 | I73: 117.32 | J73: =H73*I73 -> 586.6 | K73: =G73+J73 -> 586.6 | L73: =+K73 -> 586.6 | M73: 0 | N73: 0 | O73: =+K73+M73-N73 -> 586.6
A74: 71 | B74: 46263 | C74: SRI BALAJI AGENCIES | D74: KAKINADA | H74: 5 | I74: 117.98 | J74: =H74*I74 -> 589.9 | K74: =G74+J74 -> 589.9 | L74: =+K74 -> 589.9 | M74: 0 | N74: 0 | O74: =+K74+M74-N74 -> 589.9
A75: 72 | B75: 46264 | C75: SRI BALAJI AGENCIES | D75: KAKINADA | H75: 4.48 | I75: 117.98 | J75: =H75*I75 -> 528.5504 | K75: =G75+J75 -> 528.5504 | L75: =+K75 -> 528.5504 | M75: 0 | N75: 0 | O75: =+K75+M75-N75 -> 528.5504
A76: 73 | B76: 46265 | C76: SRI BALAJI AGENCIES | D76: KAKINADA | E76: 40 | F76: 105.59 | G76: 4223.6 | J76: =H76*I76 -> 0 | K76: =G76+J76 -> 4223.6 | L76: =+K76 -> 4223.6 | M76: 0 | N76: 0 | O76: =+K76+M76-N76 -> 4223.6
A77: 74 | J77: =H77*I77 -> 0 | K77: =G77+J77 -> 0 | L77: - | M77: 0 | N77: 0 | O77: =+K77+M77-N77 -> 0
A78: 75 | J78: =H78*I78 -> 0 | K78: =G78+J78 -> 0 | L78: - | M78: 0 | N78: 0 | O78: =+K78+M78-N78 -> 0
A79: 76 | L79: =+K79 -> 0
A80: 77 | L80: =+K80 -> 0
A81: 78 | L81: =+K81 -> 0
A82: 79 | L82: =+K82 -> 0
A83: 80 | L83: =+K83 -> 0
A84: 81 | L84: =+K84 -> 0
A85: 82 | L85: =+K85 -> 0
A86: 83 | L86: =+K86 -> 0
A87: 84 | L87: =+K87 -> 0
A88: 85 | L88: =+K88 -> 0
A89: 86 | L89: =+K89 -> 0
A90: 87 | L90: =+K90 -> 0
... A222: 219 | L222: =+K222 -> 0
L223: =+K223 -> 0
L224: =+K224 -> 0
L225: =+K225 -> 0
L226: =+K226 -> 0
L227: =+K227 -> 0
L228: =+K228 -> 0
L229: =+K229 -> 0
L230: =+K230 -> 0
L231: =+K231 -> 0
L232: =+K232 -> 0
...

Sheet  Pitapram(KKD)
A1: SATYA SIVA DURGA AGENCIES, CHEBROLU (BPCL)
A2: S.No | B2: Date | C2: GRN No | D2: Ind no/Bill No | E2: Diesel (Lts) | F2: Price | G2: Amount | H2: Petrol (Lts) | I2: Price | J2: Amount | K2: Total amount | L2: Amount paid | M2: As on Date | N2: Remarks
A3: Opening Balance | M3: 92349.157
A4: 1 | B4: 46235 | E4: 124.36 | F4: 105.21 | G4: =E4*F4 -> 13083.916 | H4: 5 | I4: 117.58 | J4: =H4*I4 -> 587.9 | K4: =G4+J4 -> 13671.816 | M4: =M3+K4-L4 -> 106020.97
B5: 46236 | E5: 20 | F5: 105.21 | G5: =E5*F5 -> 2104.2 | H5: 5 | I5: 117.58 | J5: =H5*I5 -> 587.9 | K5: =G5+J5 -> 2692.1 | M5: =M4+K5-L5 -> 108713.07
A6: 2 | B6: 46237 | E6: 195.01 | F6: 105.21 | G6: =E6*F6 -> 20517.002 | H6: 5 | I6: 117.58 | J6: =H6*I6 -> 587.9 | K6: =G6+J6 -> 21104.902 | M6: =M5+K6-L6 -> 129817.98
A7: 3 | B7: 46238 | E7: 65 | F7: 105.21 | G7: =E7*F7 -> 6838.65 | H7: 0 | J7: =H7*I7 -> 0 | K7: =G7+J7 -> 6838.65 | M7: =M6+K7-L7 -> 136656.63
A8: 4 | B8: 46239 | E8: 489.5 | F8: 105.21 | G8: =E8*F8 -> 51500.295 | H8: 0 | J8: =H8*I8 -> 0 | K8: =G8+J8 -> 51500.295 | L8: 100000 | M8: =M7+K8-L8 -> 88156.92
A9: 5 | B9: 46240 | E9: 154.7 | F9: 105.21 | G9: =E9*F9 -> 16275.987 | H9: 10 | I9: 117.58 | J9: =H9*I9 -> 1175.8 | K9: =G9+J9 -> 17451.787 | M9: =M8+K9-L9 -> 105608.71
A10: 6 | B10: 46241 | E10: 197.19 | F10: 105.21 | G10: =E10*F10 -> 20746.36 | J10: =H10*I10 -> 0 | K10: =G10+J10 -> 20746.36 | M10: =M9+K10-L10 -> 126355.07
A11: 7 | B11: 46242 | G11: =E11*F11 -> 0 | H11: 5 | I11: 117.58 | J11: =H11*I11 -> 587.9 | K11: =G11+J11 -> 587.9 | M11: =M10+K11-L11 -> 126942.97
A12: 8 | B12: 46243 | E12: 195 | F12: 105.21 | G12: =E12*F12 -> 20515.95 | H12: 10 | I12: 117.58 | J12: =H12*I12 -> 1175.8 | K12: =G12+J12 -> 21691.75 | M12: =M11+K12-L12 -> 148634.72
A13: 9 | B13: 46244 | E13: 212.37 | F13: 105.21 | G13: =E13*F13 -> 22343.448 | H13: 5 | I13: 117.58 | J13: =H13*I13 -> 587.9 | K13: =G13+J13 -> 22931.348 | M13: =M12+K13-L13 -> 171566.06
A14: 10 | B14: 46245 | E14: 217 | F14: 105.21 | G14: =E14*F14 -> 22830.57 | H14: 5 | I14: 117.58 | J14: =H14*I14 -> 587.9 | K14: =G14+J14 -> 23418.47 | L14: 100000 | M14: =M13+K14-L14 -> 94984.535
A15: 11 | B15: 46246 | E15: 180 | F15: 105.21 | G15: =E15*F15 -> 18937.8 | H15: 5 | I15: 117.58 | J15: =H15*I15 -> 587.9 | K15: =G15+J15 -> 19525.7 | M15: =M14+K15-L15 -> 114510.23
A16: 12 | B16: 46247 | E16: 142.61 | F16: 105.21 | G16: =E16*F16 -> 15003.998 | J16: =H16*I16 -> 0 | K16: =G16+J16 -> 15003.998 | M16: =M15+K16-L16 -> 129514.23
A17: 13 | B17: 46248 | E17: 204.04 | F17: 105.21 | G17: =E17*F17 -> 21467.048 | H17: 12 | I17: 117.58 | J17: =H17*I17 -> 1410.96 | K17: =G17+J17 -> 22878.008 | M17: =M16+K17-L17 -> 152392.24
A18: 14 | B18: 46249 | E18: 46 | F18: 105.21 | G18: =E18*F18 -> 4839.66 | H18: 5 | I18: 117.58 | J18: =H18*I18 -> 587.9 | K18: =G18+J18 -> 5427.56 | M18: =M17+K18-L18 -> 157819.8
A19: 15 | B19: 46250 | E19: 20 | F19: 105.21 | G19: =E19*F19 -> 2104.2 | J19: =H19*I19 -> 0 | K19: =G19+J19 -> 2104.2 | M19: =M18+K19-L19 -> 159924
A20: 16 | B20: 46251 | E20: 250.92 | F20: 105.21 | G20: =E20*F20 -> 26399.293 | H20: 15 | I20: 117.58 | J20: =H20*I20 -> 1763.7 | K20: =G20+J20 -> 28162.993 | M20: =M19+K20-L20 -> 188086.99
A21: 17 | B21: 46252 | E21: 200 | F21: 105.21 | G21: =E21*F21 -> 21042 | J21: =H21*I21 -> 0 | K21: =G21+J21 -> 21042 | M21: =M20+K21-L21 -> 209128.99
A22: 18 | B22: 46253 | E22: 5 | F22: 105.21 | G22: =E22*F22 -> 526.05 | H22: 11 | I22: 117.58 | J22: =H22*I22 -> 1293.38 | K22: =G22+J22 -> 1819.43 | M22: =M21+K22-L22 -> 210948.42
A23: 19 | B23: 46254 | E23: 244.62 | F23: 105.21 | G23: =E23*F23 -> 25736.47 | H23: 10 | I23: 117.58 | J23: =H23*I23 -> 1175.8 | K23: =G23+J23 -> 26912.27 | L23: 213661 | M23: =M22+K23-L23 -> 24199.695
A24: 20 | B24: 46255 | E24: 260 | F24: 105.21 | G24: =E24*F24 -> 27354.6 | H24: 15 | I24: 117.58 | J24: =H24*I24 -> 1763.7 | K24: =G24+J24 -> 29118.3 | M24: =M23+K24-L24 -> 53317.995
A25: 21 | B25: 46256 | E25: 97.37 | F25: 105.21 | G25: =E25*F25 -> 10244.298 | H25: 10 | I25: 117.58 | J25: =H25*I25 -> 1175.8 | K25: =G25+J25 -> 11420.098 | M25: =M24+K25-L25 -> 64738.092
A26: 22 | B26: 46257 | E26: 50 | F26: 105.21 | G26: =E26*F26 -> 5260.5 | H26: 10 | I26: 117.58 | J26: =H26*I26 -> 1175.8 | K26: =G26+J26 -> 6436.3 | M26: =M25+K26-L26 -> 71174.392
A27: 23 | B27: 46258 | E27: 415.63 | F27: 105.21 | G27: =E27*F27 -> 43728.432 | H27: 5 | I27: 117.58 | J27: =H27*I27 -> 587.9 | K27: =G27+J27 -> 44316.332 | M27: =M26+K27-L27 -> 115490.72
A28: 24 | B28: 46259 | E28: 333.41 | F28: 105.21 | G28: =E28*F28 -> 35078.066 | J28: =H28*I28 -> 0 | K28: =G28+J28 -> 35078.066 | M28: =M27+K28-L28 -> 150568.79
A29: 25 | B29: 46260 | E29: 113.53 | F29: 105.21 | G29: =E29*F29 -> 11944.491 | H29: 15 | I29: 117.58 | J29: =H29*I29 -> 1763.7 | K29: =G29+J29 -> 13708.191 | M29: =M28+K29-L29 -> 164276.98
B30: 46261 | G30: =E30*F30 -> 0 | H30: 5 | I30: 117.58 | J30: =H30*I30 -> 587.9 | K30: =G30+J30 -> 587.9 | M30: =M29+K30-L30 -> 164864.88
A31: 26 | B31: 46262 | E31: 167.92 | F31: 105.21 | G31: =E31*F31 -> 17666.863 | H31: 10 | I31: 117.58 | J31: =H31*I31 -> 1175.8 | K31: =G31+J31 -> 18842.663 | L31: 164864 | M31: =M30+K31-L31 -> 18843.545
A32: 27 | B32: 46263 | E32: 240 | F32: 105.21 | G32: =E32*F32 -> 25250.4 | J32: =H32*I32 -> 0 | K32: =G32+J32 -> 25250.4 | M32: =M31+K32-L32 -> 44093.945
A33: 28 | B33: 46264 | E33: 343.48 | F33: 105.21 | G33: =E33*F33 -> 36137.531 | H33: 10 | I33: 117.58 | J33: =H33*I33 -> 1175.8 | K33: =G33+J33 -> 37313.331 | M33: =M32+K33-L33 -> 81407.276
A34: 29 | B34: 46265 | E34: 408.2 | F34: 105.21 | G34: =E34*F34 -> 42946.722 | J34: =H34*I34 -> 0 | K34: =G34+J34 -> 42946.722 | M34: =M33+K34-L34 -> 124354
A35: 30 | G35: =E35*F35 -> 0 | J35: =H35*I35 -> 0 | K35: =G35+J35 -> 0 | M35: =M34+K35-L35 -> 124354
A36: 31 | G36: =E36*F36 -> 0 | J36: =H36*I36 -> 0 | K36: =G36+J36 -> 0 | M36: =M35+K36-L36 -> 124354
E37: =SUM(E4:E36) -> 5592.86 | G37: =SUM(G4:G36) -> 588424.8 | H37: =SUM(H4:H36) -> 188 | J37: =SUM(J4:J36) -> 22105.04 | K37: =SUM(K4:K36) -> 610529.84 | L37: =SUM(L4:L36) -> 578525

Sheet Yeleshwaram(KKD)
A1: SRI SATYA FILLING STATION, YELESWARAM (BPCL)
A2: S.No | B2: Date | C2: GRN No | D2: Ind no/Bill No | E2: Diesel (Lts) | F2: Price | G2: Amount | H2: Petrol (Lts) | I2: Price | J2: Amount | K2: Total amount | L2: Amount paid | M2: As on Date | N2: Remarks
A3: Opening Balance | M3: 19106.6
A4: 1 | B4: 46235 | E4: 30 | F4: 105.46 | G4: =E4*F4 -> 3163.8 | H4: 5 | I4: 117.84 | J4: =H4*I4 -> 589.2 | K4: =G4+J4 -> 3753 | L4: 0 | M4: =M3+K4-L4 -> 22859.6
A5: 2 | B5: 46236 | E5: 20 | F5: 105.46 | G5: =E5*F5 -> 2109.2 | J5: =H5*I5 -> 0 | K5: =G5+J5 -> 2109.2 | L5: 0 | M5: =M4+K5-L5 -> 24968.8
A6: 3 | B6: 46237 | G6: =E6*F6 -> 0 | J6: =H6*I6 -> 0 | K6: =G6+J6 -> 0 | L6: 0 | M6: =M5+K6-L6 -> 24968.8
A7: 4 | B7: 46238 | G7: =E7*F7 -> 0 | J7: =H7*I7 -> 0 | K7: =G7+J7 -> 0 | L7: =+K7 -> 0 | M7: =M6+K7-L7 -> 24968.8
A8: 5 | B8: 46239 | E8: 40 | F8: 105.46 | G8: =E8*F8 -> 4218.4 | J8: =H8*I8 -> 0 | K8: =G8+J8 -> 4218.4 | L8: 24000 | M8: =M7+K8-L8 -> 5187.2
A9: 6 | B9: 46240 | G9: =E9*F9 -> 0 | H9: 5 | I9: 117.84 | J9: =H9*I9 -> 589.2 | K9: =G9+J9 -> 589.2 | M9: =M8+K9-L9 -> 5776.4
A10: 7 | B10: 46241 | E10: 10 | F10: 105.46 | G10: =E10*F10 -> 1054.6 | J10: =H10*I10 -> 0 | K10: =G10+J10 -> 1054.6 | M10: =M9+K10-L10 -> 6831
A11: 8 | B11: 46242 | G11: =E11*F11 -> 0 | J11: =H11*I11 -> 0 | K11: =G11+J11 -> 0 | L11: =+K11 -> 0 | M11: =M10+K11-L11 -> 6831
A12: 9 | B12: 46243 | E12: 30 | F12: 105.46 | G12: =E12*F12 -> 3163.8 | J12: =H12*I12 -> 0 | K12: =G12+J12 -> 3163.8 | L12: 0 | M12: =M11+K12-L12 -> 9994.8
A13: 10 | B13: 46244 | G13: =E13*F13 -> 0 | J13: =H13*I13 -> 0 | K13: =G13+J13 -> 0 | M13: =M12+K13-L13 -> 9994.8
A14: 11 | B14: 46245 | G14: =E14*F14 -> 0 | H14: 5 | I14: 117.84 | J14: =H14*I14 -> 589.2 | K14: =G14+J14 -> 589.2 | M14: =M13+K14-L14 -> 10584
A15: 12 | B15: 46246 | E15: 140 | F15: 105.46 | G15: =E15*F15 -> 14764.4 | J15: =H15*I15 -> 0 | K15: =G15+J15 -> 14764.4 | M15: =M14+K15-L15 -> 25348.4
A16: 13 | B16: 46247 | G16: =E16*F16 -> 0 | J16: =H16*I16 -> 0 | K16: =G16+J16 -> 0 | L16: =+K16 -> 0 | M16: =M15+K16-L16 -> 25348.4
A17: 14 | B17: 46248 | E17: 47.7 | F17: 105.46 | G17: =E17*F17 -> 5030.442 | J17: =H17*I17 -> 0 | K17: =G17+J17 -> 5030.442 | M17: =M16+K17-L17 -> 30378.842
A18: 15 | B18: 46249 | G18: =E18*F18 -> 0 | J18: =H18*I18 -> 0 | K18: =G18+J18 -> 0 | M18: =M17+K18-L18 -> 30378.842
A19: 16 | B19: 46250 | E19: 45 | F19: 105.46 | G19: =E19*F19 -> 4745.7 | H19: 5 | I19: 117.84 | J19: =H19*I19 -> 589.2 | K19: =G19+J19 -> 5334.9 | M19: =M18+K19-L19 -> 35713.742
A20: 17 | B20: 46251 | E20: 60 | F20: 105.46 | G20: =E20*F20 -> 6327.6 | J20: =H20*I20 -> 0 | K20: =G20+J20 -> 6327.6 | M20: =M19+K20-L20 -> 42041.342
A21: 18 | B21: 46252 | E21: 100 | F21: 105.46 | G21: =E21*F21 -> 10546 | J21: =H21*I21 -> 0 | K21: =G21+J21 -> 10546 | M21: =M20+K21-L21 -> 52587.342
A22: 19 | B22: 46253 | G22: =E22*F22 -> 0 | J22: =H22*I22 -> 0 | K22: =G22+J22 -> 0 | M22: =M21+K22-L22 -> 52587.342
A23: 20 | B23: 46254 | E23: 40 | F23: 105.46 | G23: =E23*F23 -> 4218.4 | H23: 5 | I23: 117.84 | J23: =H23*I23 -> 589.2 | K23: =G23+J23 -> 4807.6 | M23: =M22+K23-L23 -> 57394.942
A24: 21 | B24: 46255 | G24: =E24*F24 -> 0 | J24: =H24*I24 -> 0 | K24: =G24+J24 -> 0 | L24: 0 | M24: =M23+K24-L24 -> 57394.942
A25: 22 | B25: 46256 | E25: 60 | F25: 105.46 | G25: =E25*F25 -> 6327.6 | J25: =H25*I25 -> 0 | K25: =G25+J25 -> 6327.6 | L25: 0 | M25: =M24+K25-L25 -> 63722.542
A26: 23 | B26: 46257 | G26: =E26*F26 -> 0 | J26: =H26*I26 -> 0 | K26: =G26+J26 -> 0 | L26: 0 | M26: =M25+K26-L26 -> 63722.542
A27: 24 | B27: 46258 | E27: 30 | F27: 105.46 | G27: =E27*F27 -> 3163.8 | J27: =H27*I27 -> 0 | K27: =G27+J27 -> 3163.8 | L27: 0 | M27: =M26+K27-L27 -> 66886.342
A28: 25 | B28: 46259 | E28: 30 | F28: 105.46 | G28: =E28*F28 -> 3163.8 | J28: =H28*I28 -> 0 | K28: =G28+J28 -> 3163.8 | L28: 0 | M28: =M27+K28-L28 -> 70050.142
A29: 26 | B29: 46260 | E29: 196.46 | F29: 105.46 | G29: =E29*F29 -> 20718.672 | H29: 5 | I29: 117.84 | J29: =H29*I29 -> 589.2 | K29: =G29+J29 -> 21307.872 | L29: 0 | M29: =M28+K29-L29 -> 91358.014
A30: 27 | B30: 46261 | J30: =H30*I30 -> 0 | K30: =G30+J30 -> 0 | L30: 0 | M30: =M29+K30-L30 -> 91358.014
A31: 28 | B31: 46262 | E31: 40 | F31: 105.46 | G31: =E31*F31 -> 4218.4 | J31: =H31*I31 -> 0 | K31: =G31+J31 -> 4218.4 | L31: 91358 | M31: =M30+K31-L31 -> 4218.4136
A32: 29 | B32: 46263 | G32: =E32*F32 -> 0 | J32: =H32*I32 -> 0 | K32: =G32+J32 -> 0 | M32: =M31+K32-L32 -> 4218.4136
A33: 30 | B33: 46264 | G33: =E33*F33 -> 0 | J33: =H33*I33 -> 0 | K33: =G33+J33 -> 0 | L33: 0 | M33: =M32+K33-L33 -> 4218.4136
A34: 31 | B34: 46265 | E34: 35 | F34: 105.46 | G34: =E34*F34 -> 3691.1 | H34: 5 | I34: 117.84 | J34: =H34*I34 -> 589.2 | K34: =G34+J34 -> 4280.3 | L34: 0 | M34: =M33+K34-L34 -> 8498.7136
A35: 32 | G35: =E35*F35 -> 0 | J35: =H35*I35 -> 0 | K35: =G35+J35 -> 0 | L35: =+K35 -> 0 | M35: =M34+K35-L35 -> 8498.7136
A36: 33 | G36: =E36*F36 -> 0 | J36: =H36*I36 -> 0 | K36: =G36+J36 -> 0 | L36: =+K36 -> 0 | M36: =M35+K36-L36 -> 8498.7136
E37: =SUM(E4:E36) -> 954.16 | G37: =SUM(G4:G36) -> 100625.71 | H37: =SUM(H4:H36) -> 35 | J37: =SUM(J4:J36) -> 4124.4 | K37: =SUM(K4:K36) -> 104750.11 | L37: =SUM(L4:L36) -> 115358

Sheet Amalapuram(KKD)
A1: ROYAL FILL 'N' FLY, AMALAPURAM(HPCL)
A2: S.No | B2: Date | C2: GRN No | D2: Ind no/Bill No | E2: Diesel (Lts) | F2: Price | G2: Amount | H2: Petrol (Lts) | I2: Price | J2: Amount | K2: Total amount | L2: Amount paid | M2: As on Date | N2: Remarks
A3: Opening Balance | M3: 0
A4: 1 | B4: 46235 | G4: =E4*F4 -> 0 | J4: =H4*I4 -> 0 | K4: =G4+J4 -> 0 | L4: 0 | M4: =M3+K4-L4 -> 0
A5: 2 | B5: 46236 | G5: =E5*F5 -> 0 | J5: =H5*I5 -> 0 | K5: =G5+J5 -> 0 | M5: =M4+K5-L5 -> 0
A6: 3 | B6: 46237 | G6: =E6*F6 -> 0 | J6: =H6*I6 -> 0 | K6: =G6+J6 -> 0 | M6: =M5+K6-L6 -> 0
A7: 4 | B7: 46238 | G7: =E7*F7 -> 0 | J7: =H7*I7 -> 0 | K7: =G7+J7 -> 0 | M7: =M6+K7-L7 -> 0
A8: 5 | B8: 46239 | E8: 230 | F8: 105.25 | G8: =E8*F8 -> 24207.5 | H8: 5 | I8: 117.58 | J8: =H8*I8 -> 587.9 | K8: =G8+J8 -> 24795.4 | M8: =M7+K8-L8 -> 24795.4
A9: 6 | B9: 46240 | E9: 452 | F9: 105.25 | G9: =E9*F9 -> 47573 | H9: 5 | I9: 117.58 | J9: =H9*I9 -> 587.9 | K9: =G9+J9 -> 48160.9 | M9: =M8+K9-L9 -> 72956.3
A10: 7 | B10: 46241 | G10: =E10*F10 -> 0 | H10: 5 | I10: 117.58 | J10: =H10*I10 -> 587.9 | K10: =G10+J10 -> 587.9 | M10: =M9+K10-L10 -> 73544.2
A11: 8 | B11: 46242 | E11: 240 | F11: 105.28 | G11: =E11*F11 -> 25267.2 | H11: 3 | I11: 117.58 | J11: =H11*I11 -> 352.74 | K11: =G11+J11 -> 25619.94 | M11: =M10+K11-L11 -> 99164.14
A12: 9 | B12: 46243 | E12: 230 | F12: 105.25 | G12: =E12*F12 -> 24207.5 | J12: =H12*I12 -> 0 | K12: =G12+J12 -> 24207.5 | M12: =M11+K12-L12 -> 123371.64
A13: 10 | B13: 46244 | E13: 520 | F13: 105.25 | G13: =E13*F13 -> 54730 | H13: 5 | I13: 117.58 | J13: =H13*I13 -> 587.9 | K13: =G13+J13 -> 55317.9 | M13: =M12+K13-L13 -> 178689.54
A14: 11 | B14: 46245 | E14: 165.05 | F14: 105.25 | G14: =E14*F14 -> 17371.513 | H14: 10 | I14: 117.58 | J14: =H14*I14 -> 1175.8 | K14: =G14+J14 -> 18547.312 | L14: 0 | M14: =M13+K14-L14 -> 197236.85
A15: 12 | B15: 46246 | G15: =E15*F15 -> 0 | J15: =H15*I15 -> 0 | K15: =G15+J15 -> 0 | L15: 178689 | M15: =M14+K15-L15 -> 18547.853
A16: 13 | B16: 46247 | E16: 775 | F16: 105.25 | G16: =E16*F16 -> 81568.75 | J16: =H16*I16 -> 0 | K16: =G16+J16 -> 81568.75 | L16: 18547 | M16: =M15+K16-L16 -> 81569.603
A17: 14 | B17: 46248 | E17: 37.74 | F17: 105.25 | G17: =E17*F17 -> 3972.135 | H17: 5 | I17: 117.58 | J17: =H17*I17 -> 587.9 | K17: =G17+J17 -> 4560.035 | M17: =M16+K17-L17 -> 86129.638
A18: 15 | B18: 46249 | G18: =E18*F18 -> 0 | J18: =H18*I18 -> 0 | K18: =G18+J18 -> 0 | M18: =M17+K18-L18 -> 86129.638
A19: 16 | B19: 46250 | E19: 530 | F19: 105.25 | G19: =E19*F19 -> 55782.5 | H19: 5 | I19: 117.58 | J19: =H19*I19 -> 587.9 | K19: =G19+J19 -> 56370.4 | M19: =M18+K19-L19 -> 142500.04
A20: 17 | B20: 46251 | G20: =E20*F20 -> 0 | H20: 5 | I20: 117.58 | J20: =H20*I20 -> 587.9 | K20: =G20+J20 -> 587.9 | M20: =M19+K20-L20 -> 143087.94
A21: 18 | B21: 46252 | E21: 265 | F21: 105.25 | G21: =E21*F21 -> 27891.25 | J21: =H21*I21 -> 0 | K21: =G21+J21 -> 27891.25 | M21: =M20+K21-L21 -> 170979.19
A22: 19 | B22: 46253 | E22: 440 | F22: 105.25 | G22: =E22*F22 -> 46310 | H22: 11 | I22: 117.58 | J22: =H22*I22 -> 1293.38 | K22: =G22+J22 -> 47603.38 | M22: =M21+K22-L22 -> 218582.57
A23: 20 | B23: 46254 | E23: 90.24 | F23: 105.25 | G23: =E23*F23 -> 9497.76 | H23: 37 | I23: 117.58 | J23: =H23*I23 -> 4350.46 | K23: =G23+J23 -> 13848.22 | M23: =M22+K23-L23 -> 232430.79
A24: 21 | B24: 46255 | E24: 440 | F24: 105.25 | G24: =E24*F24 -> 46310 | J24: =H24*I24 -> 0 | K24: =G24+J24 -> 46310 | L24: 0 | M24: =M23+K24-L24 -> 278740.79
A25: 22 | B25: 46256 | G25: =E25*F25 -> 0 | H25: 5 | I25: 117.58 | J25: =H25*I25 -> 587.9 | K25: =G25+J25 -> 587.9 | L25: 0 | M25: =M24+K25-L25 -> 279328.69
A26: 23 | B26: 46257 | E26: 826 | F26: 105.25 | G26: =E26*F26 -> 86936.5 | H26: 11 | I26: 117.58 | J26: =H26*I26 -> 1293.38 | K26: =G26+J26 -> 88229.88 | L26: 0 | M26: =M25+K26-L26 -> 367558.57
A27: 24 | B27: 46258 | G27: =E27*F27 -> 0 | J27: =H27*I27 -> 0 | K27: =G27+J27 -> 0 | L27: 0 | M27: =M26+K27-L27 -> 367558.57
A28: 25 | B28: 46259 | E28: 650 | F28: 105.25 | G28: =E28*F28 -> 68412.5 | J28: =H28*I28 -> 0 | K28: =G28+J28 -> 68412.5 | L28: 0 | M28: =M27+K28-L28 -> 435971.07
A29: 26 | B29: 46260 | E29: 200 | F29: 105.25 | G29: =E29*F29 -> 21050 | H29: 10 | I29: 117.58 | J29: =H29*I29 -> 1175.8 | K29: =G29+J29 -> 22225.8 | L29: 200000 | M29: =M28+K29-L29 -> 258196.87
A30: 27 | B30: 46261 | E30: 870 | F30: 105.25 | G30: =E30*F30 -> 91567.5 | H30: 11 | I30: 117.58 | J30: =H30*I30 -> 1293.38 | K30: =G30+J30 -> 92860.88 | L30: 33020 | M30: =M29+K30-L30 -> 318037.75
A31: 28 | B31: 46262 | E31: 35 | F31: 105.25 | G31: =E31*F31 -> 3683.75 | J31: =H31*I31 -> 0 | K31: =G31+J31 -> 3683.75 | M31: =M30+K31-L31 -> 321721.5
A32: 29 | B32: 46263 | E32: 400 | F32: 105.25 | G32: =E32*F32 -> 42100 | J32: =H32*I32 -> 0 | K32: =G32+J32 -> 42100 | M32: =M31+K32-L32 -> 363821.5
A33: 30 | B33: 46264 | F33: 105.25 | G33: =E33*F33 -> 0 | J33: =H33*I33 -> 0 | K33: =G33+J33 -> 0 | M33: =M32+K33-L33 -> 363821.5
A34: 31 | B34: 46265 | E34: 590 | F34: 105.25 | G34: =E34*F34 -> 62097.5 | H34: 8 | I34: 117.58 | J34: =H34*I34 -> 940.64 | K34: =G34+J34 -> 63038.14 | M34: =M33+K34-L34 -> 426859.64
A35: 32 | G35: =E35*F35 -> 0 | J35: =H35*I35 -> 0 | K35: =G35+J35 -> 0 | L35: =+K35 -> 0 | M35: =M34+K35-L35 -> 426859.64
A36: 33 | G36: =E36*F36 -> 0 | J36: =H36*I36 -> 0 | K36: =G36+J36 -> 0 | L36: =+K36 -> 0 | M36: =M35+K36-L36 -> 426859.64
E37: =SUM(E4:E36) -> 7986.03 | G37: =SUM(G4:G36) -> 840536.86 | H37: =SUM(H4:H36) -> 141 | J37: =SUM(J4:J36) -> 16578.78 | K37: =SUM(K4:K36) -> 857115.64 | L37: =SUM(L4:L36) -> 430256

Sheet  Solasa Krishna OIl
A1: SOLASA KRISHNA OIL COMPANY
A2: S.No | B2: Date | C2: GRN No | D2: Ind no/Bill No | E2: Diesel (Lts) | F2: Price | G2: Amount | H2: Petrol (Lts) | I2: Price | J2: Amount | K2: Total amount | L2: Amount paid | M2: As on Date | N2: Remarks
A3: Opening Balance | M3: 0
A4: 1 | B4: 46235 | G4: =E4*F4 -> 0 | J4: =H4*I4 -> 0 | K4: =G4+J4 -> 0 | L4: 0 | M4: =M3+K4-L4 -> 0
A5: 2 | B5: 46236 | G5: =E5*F5 -> 0 | J5: =H5*I5 -> 0 | K5: =G5+J5 -> 0 | M5: =M4+K5-L5 -> 0
A6: 3 | B6: 46237 | G6: =E6*F6 -> 0 | J6: =H6*I6 -> 0 | K6: =G6+J6 -> 0 | M6: =M5+K6-L6 -> 0
A7: 4 | B7: 46238 | G7: =E7*F7 -> 0 | J7: =H7*I7 -> 0 | K7: =G7+J7 -> 0 | M7: =M6+K7-L7 -> 0
A8: 5 | B8: 46239 | G8: =E8*F8 -> 0 | J8: =H8*I8 -> 0 | K8: =G8+J8 -> 0 | M8: =M7+K8-L8 -> 0
A9: 6 | B9: 46240 | G9: =E9*F9 -> 0 | J9: =H9*I9 -> 0 | K9: =G9+J9 -> 0 | M9: =M8+K9-L9 -> 0
A10: 7 | B10: 46241 | G10: =E10*F10 -> 0 | J10: =H10*I10 -> 0 | K10: =G10+J10 -> 0 | M10: =M9+K10-L10 -> 0
A11: 8 | B11: 46242 | G11: =E11*F11 -> 0 | J11: =H11*I11 -> 0 | K11: =G11+J11 -> 0 | M11: =M10+K11-L11 -> 0
A12: 9 | B12: 46243 | G12: =E12*F12 -> 0 | J12: =H12*I12 -> 0 | K12: =G12+J12 -> 0 | M12: =M11+K12-L12 -> 0
A13: 10 | B13: 46244 | E13: 240.12 | F13: 105.4 | G13: =E13*F13 -> 25308.648 | J13: =H13*I13 -> 0 | K13: =G13+J13 -> 25308.648 | M13: =M12+K13-L13 -> 25308.648
A14: 11 | B14: 46245 | E14: 92.37 | F14: 105.4 | G14: =E14*F14 -> 9735.798 | J14: =H14*I14 -> 0 | K14: =G14+J14 -> 9735.798 | M14: =M13+K14-L14 -> 35044.446
A15: 12 | B15: 46246 | G15: =E15*F15 -> 0 | H15: 5.01 | I15: 117.74 | J15: =H15*I15 -> 589.8774 | K15: =G15+J15 -> 589.8774 | M15: =M14+K15-L15 -> 35634.323
A16: 13 | B16: 46247 | G16: =E16*F16 -> 0 | J16: =H16*I16 -> 0 | K16: =G16+J16 -> 0 | M16: =M15+K16-L16 -> 35634.323
A17: 14 | B17: 46248 | E17: 95.18 | F17: 105.4 | G17: =E17*F17 -> 10031.972 | H17: 5 | I17: 117.74 | J17: =H17*I17 -> 588.7 | K17: =G17+J17 -> 10620.672 | M17: =M16+K17-L17 -> 46254.995
A18: 15 | B18: 46249 | G18: =E18*F18 -> 0 | J18: =H18*I18 -> 0 | K18: =G18+J18 -> 0 | M18: =M17+K18-L18 -> 46254.995
A19: 16 | B19: 46250 | E19: 100 | F19: 105.4 | G19: =E19*F19 -> 10540 | J19: =H19*I19 -> 0 | K19: =G19+J19 -> 10540 | M19: =M18+K19-L19 -> 56794.995
A20: 17 | B20: 46251 | G20: =E20*F20 -> 0 | J20: =H20*I20 -> 0 | K20: =G20+J20 -> 0 | M20: =M19+K20-L20 -> 56794.995
A21: 18 | B21: 46252 | E21: 86.81 | F21: 105.4 | G21: =E21*F21 -> 9149.774 | J21: =H21*I21 -> 0 | K21: =G21+J21 -> 9149.774 | M21: =M20+K21-L21 -> 65944.769
A22: 19 | B22: 46253 | E22: 130.23 | F22: 105.4 | G22: =E22*F22 -> 13726.242 | J22: =H22*I22 -> 0 | K22: =G22+J22 -> 13726.242 | M22: =M21+K22-L22 -> 79671.011
A23: 20 | B23: 46254 | E23: 140 | F23: 105.4 | G23: =E23*F23 -> 14756 | H23: 10 | I23: 117.74 | J23: =H23*I23 -> 1177.4 | K23: =G23+J23 -> 15933.4 | L23: 79000 | M23: =M22+K23-L23 -> 16604.411
A24: 21 | B24: 46255 | E24: 224.66 | F24: 105.4 | G24: =E24*F24 -> 23679.164 | J24: =H24*I24 -> 0 | K24: =G24+J24 -> 23679.164 | L24: 0 | M24: =M23+K24-L24 -> 40283.575
A25: 22 | B25: 46256 | E25: 61.51 | F25: 105.4 | G25: =E25*F25 -> 6483.154 | J25: =H25*I25 -> 0 | K25: =G25+J25 -> 6483.154 | L25: 0 | M25: =M24+K25-L25 -> 46766.729
A26: 23 | B26: 46257 | E26: 160 | F26: 105.4 | G26: =E26*F26 -> 16864 | J26: =H26*I26 -> 0 | K26: =G26+J26 -> 16864 | L26: 0 | M26: =M25+K26-L26 -> 63630.729
A27: 24 | B27: 46258 | E27: 176.85 | F27: 105.4 | G27: =E27*F27 -> 18639.99 | J27: =H27*I27 -> 0 | K27: =G27+J27 -> 18639.99 | L27: 0 | M27: =M26+K27-L27 -> 82270.719
A28: 25 | B28: 46259 | E28: 35.37 | F28: 105.4 | G28: =E28*F28 -> 3727.998 | J28: =H28*I28 -> 0 | K28: =G28+J28 -> 3727.998 | L28: 0 | M28: =M27+K28-L28 -> 85998.717
A29: 26 | B29: 46260 | G29: =E29*F29 -> 0 | J29: =H29*I29 -> 0 | K29: =G29+J29 -> 0 | L29: 0 | M29: =M28+K29-L29 -> 85998.717
A30: 27 | B30: 46261 | E30: 200 | F30: 105.4 | G30: =E30*F30 -> 21080 | H30: 5 | I30: 117.74 | J30: =H30*I30 -> 588.7 | K30: =G30+J30 -> 21668.7 | L30: 0 | M30: =M29+K30-L30 -> 107667.42
A31: 28 | B31: 46262 | E31: 92 | F31: 105.4 | G31: =E31*F31 -> 9696.8 | J31: =H31*I31 -> 0 | K31: =G31+J31 -> 9696.8 | L31: 107667 | M31: =M30+K31-L31 -> 9697.2174
A32: 29 | B32: 46263 | E32: 144.36 | F32: 105.4 | G32: =E32*F32 -> 15215.544 | J32: =H32*I32 -> 0 | K32: =G32+J32 -> 15215.544 | M32: =M31+K32-L32 -> 24912.761
A33: 30 | B33: 46264 | G33: =E33*F33 -> 0 | J33: =H33*I33 -> 0 | K33: =G33+J33 -> 0 | L33: 0 | M33: =M32+K33-L33 -> 24912.761
A34: 31 | B34: 46265 | E34: 203.51 | F34: 105.4 | G34: =E34*F34 -> 21449.954 | J34: =H34*I34 -> 0 | K34: =G34+J34 -> 21449.954 | L34: 0 | M34: =M33+K34-L34 -> 46362.715
A35: 32 | G35: =E35*F35 -> 0 | J35: =H35*I35 -> 0 | K35: =G35+J35 -> 0 | L35: 0 | M35: =M34+K35-L35 -> 46362.715
A36: 33 | G36: =E36*F36 -> 0 | J36: =H36*I36 -> 0 | K36: =G36+J36 -> 0 | L36: =+K36 -> 0 | M36: =M35+K36-L36 -> 46362.715
E37: =SUM(E4:E36) -> 2182.97 | G37: =SUM(G4:G36) -> 230085.04 | H37: =SUM(H4:H36) -> 25.01 | J37: =SUM(J4:J36) -> 2944.6774 | K37: =SUM(K4:K36) -> 233029.72 | L37: =SUM(L4:L36) -> 186667

Sheet Sri Venkateshwara Services
A1: Sri Venkateshwara Services
A2: S.No | B2: Date | C2: GRN No | D2: Ind no/Bill No | E2: Diesel (Lts) | F2: Price | G2: Amount | H2: Petrol (Lts) | I2: Price | J2: Amount | K2: Total amount | L2: Amount paid | M2: As on Date | N2: Remarks
A3: Opening Balance | M3: 0
A4: 1 | B4: 46235 | G4: =E4*F4 -> 0 | J4: =H4*I4 -> 0 | K4: =G4+J4 -> 0 | L4: 0 | M4: =M3+K4-L4 -> 0
A5: 2 | B5: 46236 | G5: =E5*F5 -> 0 | J5: =H5*I5 -> 0 | K5: =G5+J5 -> 0 | M5: =M4+K5-L5 -> 0
A6: 3 | B6: 46237 | G6: =E6*F6 -> 0 | J6: =H6*I6 -> 0 | K6: =G6+J6 -> 0 | M6: =M5+K6-L6 -> 0
A7: 4 | B7: 46238 | G7: =E7*F7 -> 0 | J7: =H7*I7 -> 0 | K7: =G7+J7 -> 0 | M7: =M6+K7-L7 -> 0
A8: 5 | B8: 46239 | G8: =E8*F8 -> 0 | J8: =H8*I8 -> 0 | K8: =G8+J8 -> 0 | M8: =M7+K8-L8 -> 0
A9: 6 | B9: 46240 | G9: =E9*F9 -> 0 | J9: =H9*I9 -> 0 | K9: =G9+J9 -> 0 | M9: =M8+K9-L9 -> 0
A10: 7 | B10: 46241 | G10: =E10*F10 -> 0 | J10: =H10*I10 -> 0 | K10: =G10+J10 -> 0 | M10: =M9+K10-L10 -> 0
A11: 8 | B11: 46242 | G11: =E11*F11 -> 0 | J11: =H11*I11 -> 0 | K11: =G11+J11 -> 0 | M11: =M10+K11-L11 -> 0
A12: 9 | B12: 46243 | G12: =E12*F12 -> 0 | J12: =H12*I12 -> 0 | K12: =G12+J12 -> 0 | M12: =M11+K12-L12 -> 0
A13: 10 | B13: 46244 | G13: =E13*F13 -> 0 | J13: =H13*I13 -> 0 | K13: =G13+J13 -> 0 | M13: =M12+K13-L13 -> 0
A14: 11 | B14: 46245 | G14: =E14*F14 -> 0 | J14: =H14*I14 -> 0 | K14: =G14+J14 -> 0 | M14: =M13+K14-L14 -> 0
A15: 12 | B15: 46246 | G15: =E15*F15 -> 0 | J15: =H15*I15 -> 0 | K15: =G15+J15 -> 0 | M15: =M14+K15-L15 -> 0
A16: 13 | B16: 46247 | E16: 100 | F16: 104.68 | G16: =E16*F16 -> 10468 | H16: 5 | I16: 116.96 | J16: =H16*I16 -> 584.8 | K16: =G16+J16 -> 11052.8 | M16: =M15+K16-L16 -> 11052.8
A17: 14 | B17: 46248 | G17: =E17*F17 -> 0 | J17: =H17*I17 -> 0 | K17: =G17+J17 -> 0 | M17: =M16+K17-L17 -> 11052.8
A18: 15 | B18: 46249 | G18: =E18*F18 -> 0 | J18: =H18*I18 -> 0 | K18: =G18+J18 -> 0 | M18: =M17+K18-L18 -> 11052.8
A19: 16 | B19: 46250 | E19: 5 | F19: 104.68 | G19: =E19*F19 -> 523.4 | H19: 5 | I19: 116.96 | J19: =H19*I19 -> 584.8 | K19: =G19+J19 -> 1108.2 | M19: =M18+K19-L19 -> 12161
A20: 17 | B20: 46251 | E20: 51 | F20: 104.68 | G20: =E20*F20 -> 5338.68 | J20: =H20*I20 -> 0 | K20: =G20+J20 -> 5338.68 | M20: =M19+K20-L20 -> 17499.68
A21: 18 | B21: 46252 | E21: 117 | F21: 104.68 | G21: =E21*F21 -> 12247.56 | H21: 5 | I21: 116.96 | J21: =H21*I21 -> 584.8 | K21: =G21+J21 -> 12832.36 | M21: =M20+K21-L21 -> 30332.04
A22: 19 | B22: 46253 | E22: 28 | F22: 104.68 | G22: =E22*F22 -> 2931.04 | J22: =H22*I22 -> 0 | K22: =G22+J22 -> 2931.04 | M22: =M21+K22-L22 -> 33263.08
A23: 20 | B23: 46254 | G23: =E23*F23 -> 0 | H23: 5 | I23: 116.96 | J23: =H23*I23 -> 584.8 | K23: =G23+J23 -> 584.8 | L23: 33000 | M23: =M22+K23-L23 -> 847.88
A24: 21 | B24: 46255 | G24: =E24*F24 -> 0 | J24: =H24*I24 -> 0 | K24: =G24+J24 -> 0 | L24: 0 | M24: =M23+K24-L24 -> 847.88
A25: 22 | B25: 46256 | E25: 71.84 | F25: 104.68 | G25: =E25*F25 -> 7520.2112 | H25: 25 | I25: 116.96 | J25: =H25*I25 -> 2924 | K25: =G25+J25 -> 10444.211 | L25: 0 | M25: =M24+K25-L25 -> 11292.091
A26: 23 | B26: 46257 | G26: =E26*F26 -> 0 | J26: =H26*I26 -> 0 | K26: =G26+J26 -> 0 | L26: 0 | M26: =M25+K26-L26 -> 11292.091
A27: 24 | B27: 46258 | E27: 41 | F27: 104.68 | G27: =E27*F27 -> 4291.88 | H27: 10 | I27: 116.96 | J27: =H27*I27 -> 1169.6 | K27: =G27+J27 -> 5461.48 | L27: 0 | M27: =M26+K27-L27 -> 16753.571
A28: 25 | B28: 46259 | E28: 98.8 | F28: 104.68 | G28: =E28*F28 -> 10342.384 | J28: =H28*I28 -> 0 | K28: =G28+J28 -> 10342.384 | L28: 0 | M28: =M27+K28-L28 -> 27095.955
A29: 26 | B29: 46260 | E29: 91 | F29: 104.68 | G29: =E29*F29 -> 9525.88 | J29: =H29*I29 -> 0 | K29: =G29+J29 -> 9525.88 | L29: 0 | M29: =M28+K29-L29 -> 36621.835
A30: 27 | B30: 46261 | E30: 130 | F30: 104.68 | G30: =E30*F30 -> 13608.4 | J30: =H30*I30 -> 0 | K30: =G30+J30 -> 13608.4 | L30: 0 | M30: =M29+K30-L30 -> 50230.235
A31: 28 | B31: 46262 | E31: 146 | F31: 104.68 | G31: =E31*F31 -> 15283.28 | H31: 10 | I31: 116.96 | J31: =H31*I31 -> 1169.6 | K31: =G31+J31 -> 16452.88 | L31: 50230 | M31: =M30+K31-L31 -> 16453.115
A32: 29 | B32: 46263 | G32: =E32*F32 -> 0 | H32: 5 | I32: 116.96 | J32: =H32*I32 -> 584.8 | K32: =G32+J32 -> 584.8 | M32: =M31+K32-L32 -> 17037.915
A33: 30 | B33: 46264 | G33: =E33*F33 -> 0 | J33: =H33*I33 -> 0 | K33: =G33+J33 -> 0 | L33: 0 | M33: =M32+K33-L33 -> 17037.915
A34: 31 | B34: 46265 | G34: =E34*F34 -> 0 | J34: =H34*I34 -> 0 | K34: =G34+J34 -> 0 | L34: =+K34 -> 0 | M34: =M33+K34-L34 -> 17037.915
A35: 32 | G35: =E35*F35 -> 0 | J35: =H35*I35 -> 0 | K35: =G35+J35 -> 0 | L35: =+K35 -> 0 | M35: =M34+K35-L35 -> 17037.915
A36: 33 | G36: =E36*F36 -> 0 | J36: =H36*I36 -> 0 | K36: =G36+J36 -> 0 | L36: =+K36 -> 0 | M36: =M35+K36-L36 -> 17037.915
E37: =SUM(E4:E36) -> 879.64 | G37: =SUM(G4:G36) -> 92080.715 | H37: =SUM(H4:H36) -> 70 | J37: =SUM(J4:J36) -> 8187.2 | K37: =SUM(K4:K36) -> 100267.92 | L37: =SUM(L4:L36) -> 83230

Sheet Madana palli
A2: S.No | B2: Date | C2: GRN No | D2: Ind no/Bill No | E2: Diesel (Lts) | F2: Price | G2: Amount | H2: Petrol (Lts) | I2: Price | J2: Amount | K2: Total amount | L2: Amount paid | M2: As on Date | N2: Remarks
A3: Opening Balance | M3: 0
A4: 1 | B4: 46204 | G4: =E4*F4 -> 0 | J4: =H4*I4 -> 0 | K4: =G4+J4 -> 0 | L4: =+K4 -> 0 | M4: 0
B5: 46205 | J5: =H5*I5 -> 0 | K5: =G5+J5 -> 0 | L5: =+K5 -> 0
A6: 2 | B6: 46206 | G6: =E6*F6 -> 0 | J6: =H6*I6 -> 0 | K6: =G6+J6 -> 0 | L6: =+K6 -> 0 | M6: 0 | N6: IOCL
A7: 3 | B7: 46207 | G7: =E7*F7 -> 0 | J7: =H7*I7 -> 0 | K7: =G7+J7 -> 0 | L7: =+K7 -> 0 | M7: 0
A8: 4 | B8: 46208 | G8: =E8*F8 -> 0 | J8: =H8*I8 -> 0 | K8: =G8+J8 -> 0 | L8: =+K8 -> 0 | M8: 0
A9: 5 | B9: 46209 | G9: =E9*F9 -> 0 | J9: =H9*I9 -> 0 | K9: =G9+J9 -> 0 | L9: =+K9 -> 0 | M9: 0
A10: 6 | B10: 46210 | G10: =E10*F10 -> 0 | J10: =H10*I10 -> 0 | K10: =G10+J10 -> 0 | L10: =+K10 -> 0 | M10: 0 | N10: HPCL
A11: 7 | B11: 46211 | G11: =E11*F11 -> 0 | J11: =H11*I11 -> 0 | K11: =G11+J11 -> 0 | L11: =+K11 -> 0 | M11: 0 | O11: 169.99
A12: 8 | B12: 46212 | G12: =E12*F12 -> 0 | J12: =H12*I12 -> 0 | K12: =G12+J12 -> 0 | L12: =+K12 -> 0 | M12: 0 | O12: 80
A13: 9 | B13: 46213 | G13: =E13*F13 -> 0 | J13: =H13*I13 -> 0 | K13: =G13+J13 -> 0 | L13: =+K13 -> 0 | M13: 0 | O13: =SUM(O11:O12) -> 249.99 | P13: 97.76 | Q13: =O13*P13 -> 24439.022
A14: 10 | B14: 46214 | G14: =E14*F14 -> 0 | J14: =H14*I14 -> 0 | K14: =G14+J14 -> 0 | L14: =+K14 -> 0 | M14: 0
A15: 11 | B15: 46215 | G15: =E15*F15 -> 0 | J15: =H15*I15 -> 0 | K15: =G15+J15 -> 0 | L15: =+K15 -> 0 | M15: 0
A16: 12 | B16: 46216 | G16: =E16*F16 -> 0 | J16: =H16*I16 -> 0 | K16: =G16+J16 -> 0 | L16: =+K16 -> 0 | M16: 0 | P16: 7820.8
A17: 13 | B17: 46217 | G17: =E17*F17 -> 0 | H17: 3.4 | I17: 117.46 | J17: =H17*I17 -> 399.364 | K17: =G17+J17 -> 399.364 | L17: =+K17 -> 399.364 | M17: 0 | P17: 16619.2
A18: 14 | B18: 46218 | G18: =E18*F18 -> 0 | J18: =H18*I18 -> 0 | K18: =G18+J18 -> 0 | L18: =+K18 -> 0 | M18: 0 | P18: =SUM(P16:P17) -> 24440
A19: 15 | B19: 46219 | G19: =E19*F19 -> 0 | J19: =H19*I19 -> 0 | K19: =G19+J19 -> 0 | L19: =+K19 -> 0 | M19: 0
A20: 16 | B20: 46220 | G20: =E20*F20 -> 0 | J20: =H20*I20 -> 0 | K20: =G20+J20 -> 0 | L20: =+K20 -> 0 | M20: 0
A21: 17 | B21: 46221 | G21: =E21*F21 -> 0 | J21: =H21*I21 -> 0 | K21: =G21+J21 -> 0 | L21: =+K21 -> 0 | M21: 0
A22: 18 | B22: 46222 | G22: =E22*F22 -> 0 | J22: =H22*I22 -> 0 | K22: =G22+J22 -> 0 | L22: =+K22 -> 0 | M22: 0
A23: 19 | B23: 46223 | G23: =E23*F23 -> 0 | J23: =H23*I23 -> 0 | K23: =G23+J23 -> 0 | L23: =+K23 -> 0 | M23: 0
A24: 20 | B24: 46224 | G24: =E24*F24 -> 0 | J24: =H24*I24 -> 0 | K24: =G24+J24 -> 0 | L24: =+K24 -> 0 | M24: 0
A25: 21 | B25: 46225 | G25: =E25*F25 -> 0 | J25: =H25*I25 -> 0 | K25: =G25+J25 -> 0 | L25: =+K25 -> 0 | M25: 0
A26: 22 | B26: 46226 | G26: =E26*F26 -> 0 | J26: =H26*I26 -> 0 | K26: =G26+J26 -> 0 | L26: =+K26 -> 0 | M26: 0
A27: 23 | B27: 46227 | G27: =E27*F27 -> 0 | J27: =H27*I27 -> 0 | K27: =G27+J27 -> 0 | L27: =+K27 -> 0 | M27: 0
A28: 24 | B28: 46228 | G28: =E28*F28 -> 0 | J28: =H28*I28 -> 0 | K28: =G28+J28 -> 0 | L28: =+K28 -> 0 | M28: 0
A29: 25 | B29: 46229 | G29: =E29*F29 -> 0 | J29: =H29*I29 -> 0 | K29: =G29+J29 -> 0 | L29: =+K29 -> 0 | M29: 0
B30: 46230 | J30: =H30*I30 -> 0 | K30: =G30+J30 -> 0 | L30: =+K30 -> 0
A31: 26 | B31: 46231 | G31: =E31*F31 -> 0 | J31: =H31*I31 -> 0 | K31: =G31+J31 -> 0 | L31: =+K31 -> 0 | M31: 0
A32: 27 | B32: 46232 | G32: =E32*F32 -> 0 | J32: =H32*I32 -> 0 | K32: =G32+J32 -> 0 | L32: =+K32 -> 0 | M32: 0
A33: 28 | B33: 46233 | G33: =E33*F33 -> 0 | J33: =H33*I33 -> 0 | K33: =G33+J33 -> 0 | L33: =+K33 -> 0 | M33: 0
A34: 29 | B34: 46234 | G34: =E34*F34 -> 0 | J34: =H34*I34 -> 0 | K34: =G34+J34 -> 0 | L34: =+K34 -> 0 | M34: 0
A35: 30 | G35: =E35*F35 -> 0 | J35: =H35*I35 -> 0 | K35: =G35+J35 -> 0 | L35: =+K35 -> 0 | M35: 0
A36: 31 | G36: =E36*F36 -> 0 | J36: =H36*I36 -> 0 | K36: =G36+J36 -> 0 | L36: =+K36 -> 0 | M36: 0
E37: =SUM(E4:E36) -> 0 | G37: =SUM(G4:G36) -> 0 | H37: =SUM(H4:H36) -> 3.4 | J37: =SUM(J4:J36) -> 399.364 | K37: =SUM(K4:K36) -> 399.364 | L37: =SUM(L4:L36) -> 399.364

Sheet Kadur
A1: Vishal Service Station
A2: S.No | B2: Date | C2: GRN No | D2: Ind No/Bill No | E2: Diesel (Lts) | F2: Price | G2: Amount | H2: Petrol (Lts) | I2: Price | J2: Amount | K2: Total amount | L2: Amount paid | M2: As on Date | N2: Remarks
A3: Opening Balance | K3: 673026.9 | L3: 0 | M3: 673026.9 | O3: 207239.43
A4: 1 | B4: 45870 | G4: =E4*F4 -> 0 | J4: =H4*I4 -> 0 | K4: =G4+J4 -> 0 | M4: =M3+K4-L4 -> 673026.9
A5: 2 | B5: 45871 | G5: =E5*F5 -> 0 | J5: =H5*I5 -> 0 | K5: =G5+J5 -> 0 | M5: =M4+K5-L5 -> 673026.9
A6: 3 | B6: 45872 | G6: =E6*F6 -> 0 | J6: =H6*I6 -> 0 | K6: =G6+J6 -> 0 | M6: =M5+K6-L6 -> 673026.9
A7: 4 | B7: 45873 | G7: =E7*F7 -> 0 | J7: =H7*I7 -> 0 | K7: =G7+J7 -> 0 | M7: =M6+K7-L7 -> 673026.9
A8: 5 | B8: 45874 | G8: =E8*F8 -> 0 | J8: =H8*I8 -> 0 | K8: =G8+J8 -> 0 | M8: =M7+K8-L8 -> 673026.9
A9: 6 | B9: 45875 | G9: =E9*F9 -> 0 | J9: =H9*I9 -> 0 | K9: =G9+J9 -> 0 | M9: =M8+K9-L9 -> 673026.9
A10: 7 | B10: 45876 | G10: =E10*F10 -> 0 | J10: =H10*I10 -> 0 | K10: =G10+J10 -> 0 | M10: =M9+K10-L10 -> 673026.9
A11: 8 | B11: 45877 | G11: =E11*F11 -> 0 | J11: =H11*I11 -> 0 | K11: =G11+J11 -> 0 | M11: =M10+K11-L11 -> 673026.9
A12: 9 | B12: 45878 | G12: =E12*F12 -> 0 | J12: =H12*I12 -> 0 | K12: =G12+J12 -> 0 | M12: =M11+K12-L12 -> 673026.9
A13: 10 | B13: 45879 | G13: =E13*F13 -> 0 | J13: =H13*I13 -> 0 | K13: =G13+J13 -> 0 | M13: =M12+K13-L13 -> 673026.9
A14: 11 | B14: 45880 | G14: =E14*F14 -> 0 | J14: =H14*I14 -> 0 | K14: =G14+J14 -> 0 | M14: =M13+K14-L14 -> 673026.9
A15: 12 | B15: 45881 | G15: =E15*F15 -> 0 | J15: =H15*I15 -> 0 | K15: =G15+J15 -> 0 | M15: =M14+K15-L15 -> 673026.9
... A21: 18 | B21: 45887 | G21: =E21*F21 -> 0 | J21: =H21*I21 -> 0 | K21: =G21+J21 -> 0 | M21: =M20+K21-L21 -> 673026.9
A22: 19 | B22: 45888 | H22: 0 | I22: 0 | J22: =H22*I22 -> 0 | K22: =G22+J22 -> 0 | M22: =M21+K22-L22 -> 673026.9
A23: 20 | B23: 45889 | H23: 0 | I23: 0 | J23: =H23*I23 -> 0 | K23: =G23+J23 -> 0 | M23: =M22+K23-L23 -> 673026.9
A24: 21 | B24: 45890 | J24: =H24*I24 -> 0 | K24: =G24+J24 -> 0 | M24: =M23+K24-L24 -> 673026.9
A25: 22 | B25: 45891 | J25: =H25*I25 -> 0 | K25: =G25+J25 -> 0 | M25: =M24+K25-L25 -> 673026.9
A26: 23 | B26: 45892 | J26: =H26*I26 -> 0 | K26: =G26+J26 -> 0 | M26: =M25+K26-L26 -> 673026.9
A27: 24 | B27: 45893 | J27: =H27*I27 -> 0 | K27: =G27+J27 -> 0 | M27: =M26+K27-L27 -> 673026.9
A28: 25 | B28: 45894 | J28: =H28*I28 -> 0 | K28: =G28+J28 -> 0 | M28: =M27+K28-L28 -> 673026.9
A29: 26 | B29: 45895 | J29: =H29*I29 -> 0 | K29: =G29+J29 -> 0 | M29: =M28+K29-L29 -> 673026.9
A30: 27 | B30: 45896 | J30: =H30*I30 -> 0 | K30: =G30+J30 -> 0 | M30: =M29+K30-L30 -> 673026.9
A31: 28 | B31: 45897 | J31: =H31*I31 -> 0 | K31: =G31+J31 -> 0 | L31: 673026 | M31: =M30+K31-L31 -> 0.9
A32: 29 | B32: 45898 | G32: =E32*F32 -> 0 | H32: 0 | I32: 0 | J32: =H32*I32 -> 0 | K32: =G32+J32 -> 0 | M32: =M31+K32-L32 -> 0.9
A33: 30 | B33: 45899 | F33: 0 | G33: =E33*F33 -> 0 | H33: 0 | I33: 0 | J33: =H33*I33 -> 0 | K33: =G33+J33 -> 0 | M33: =M32+K33-L33 -> 0.9
A34: 31 | F34: 0 | G34: =E34*F34 -> 0 | J34: =H34*I34 -> 0 | K34: =G34+J34 -> 0
E35: =SUM(E4:E34) -> 0 | G35: =SUM(G4:G34) -> 0 | H35: =SUM(H4:H34) -> 0 | J35: =SUM(J4:J34) -> 0 | K35: =SUM(K4:K34) -> 0 | L35: =SUM(L4:L31) -> 673026

Sheet YG Gudda
A1: Pankaja HP Fuel Center
A2: S.No | B2: Date | C2: GRN No | D2: Ind No/Bill No | E2: Diesel (Lts) | F2: Price | G2: Amount | H2: Petrol (Lts) | I2: Price | J2: Amount | K2: Total amount | L2: Amount paid | M2: As on Date | N2: Remarks
A3: Opening Balance | K3: 296621.36 | M3: 296621.36
A4: 1 | B4: 46235 | G4: =E4*F4 -> 0 | J4: =H4*I4 -> 0 | K4: =G4+J4 -> 0 | M4: =M3+K4-L4 -> 296621.36
B5: 46236 | G5: =E5*F5 -> 0 | K5: =G5+J5 -> 0 | M5: =M4+K5-L5 -> 296621.36
A6: 2 | B6: 46237 | E6: 600 | F6: 99.14 | G6: =E6*F6 -> 59484 | H6: 35 | I6: 111.24 | J6: =H6*I6 -> 3893.4 | K6: =G6+J6 -> 63377.4 | M6: =M5+K6-L6 -> 359998.76
A7: 3 | B7: 46238 | E7: 1000 | F7: 99.14 | G7: =E7*F7 -> 99140 | J7: =H7*I7 -> 0 | K7: =G7+J7 -> 99140 | M7: =M6+K7-L7 -> 459138.76
A8: 4 | B8: 46239 | G8: =E8*F8 -> 0 | J8: =H8*I8 -> 0 | K8: =G8+J8 -> 0 | L8: 300000 | M8: =M7+K8-L8 -> 159138.76
A9: 5 | B9: 46240 | E9: 1000 | F9: 99.14 | G9: =E9*F9 -> 99140 | H9: 35 | I9: 111.24 | J9: =H9*I9 -> 3893.4 | K9: =G9+J9 -> 103033.4 | M9: =M8+K9-L9 -> 262172.16
A10: 6 | B10: 46241 | G10: =E10*F10 -> 0 | J10: =H10*I10 -> 0 | K10: =G10+J10 -> 0 | M10: =M9+K10-L10 -> 262172.16
A11: 7 | B11: 46242 | G11: =E11*F11 -> 0 | J11: =H11*I11 -> 0 | K11: =G11+J11 -> 0 | M11: =M10+K11-L11 -> 262172.16
A12: 8 | B12: 46243 | G12: =E12*F12 -> 0 | J12: =H12*I12 -> 0 | K12: =G12+J12 -> 0 | M12: =M11+K12-L12 -> 262172.16
A13: 9 | B13: 46244 | E13: 600 | F13: 99.14 | G13: =E13*F13 -> 59484 | H13: 35 | I13: 111.24 | J13: =H13*I13 -> 3893.4 | K13: =G13+J13 -> 63377.4 | M13: =M12+K13-L13 -> 325549.56
A14: 10 | B14: 46245 | G14: =E14*F14 -> 0 | J14: =H14*I14 -> 0 | K14: =G14+J14 -> 0 | M14: =M13+K14-L14 -> 325549.56
A15: 11 | B15: 46246 | E15: 1000 | F15: 99.14 | G15: =E15*F15 -> 99140 | H15: 35 | I15: 111.24 | J15: =H15*I15 -> 3893.4 | K15: =G15+J15 -> 103033.4 | M15: =M14+K15-L15 -> 428582.96
A16: 12 | B16: 46247 | G16: =E16*F16 -> 0 | K16: =G16+J16 -> 0 | M16: =M15+K16-L16 -> 428582.96
A17: 13 | B17: 46248 | E17: 1000 | F17: 99.14 | G17: =E17*F17 -> 99140 | J17: =H17*I17 -> 0 | K17: =G17+J17 -> 99140 | L17: 428000 | M17: =M16+K17-L17 -> 99722.96
A18: 14 | B18: 46249 | G18: =E18*F18 -> 0 | J18: =H18*I18 -> 0 | K18: =G18+J18 -> 0 | M18: =M17+K18-L18 -> 99722.96
A19: 15 | B19: 46250 | G19: =E19*F19 -> 0 | J19: =H19*I19 -> 0 | K19: =G19+J19 -> 0 | M19: =M18+K19-L19 -> 99722.96
A20: 16 | B20: 46251 | G20: =E20*F20 -> 0 | J20: =H20*I20 -> 0 | K20: =G20+J20 -> 0 | M20: =M19+K20-L20 -> 99722.96
A21: 17 | B21: 46252 | E21: 1000 | F21: 99.14 | G21: =E21*F21 -> 99140 | H21: 35 | I21: 111.24 | J21: =H21*I21 -> 3893.4 | K21: =G21+J21 -> 103033.4 | M21: =M20+K21-L21 -> 202756.36
A22: 18 | B22: 46253 | G22: =E22*F22 -> 0 | J22: =H22*I22 -> 0 | K22: =G22+J22 -> 0 | M22: =M21+K22-L22 -> 202756.36
A23: 19 | B23: 46254 | E23: 1000 | F23: 99.14 | G23: =E23*F23 -> 99140 | J23: =H23*I23 -> 0 | K23: =G23+J23 -> 99140 | M23: =M22+K23-L23 -> 301896.36
A24: 20 | B24: 46255 | G24: =E24*F24 -> 0 | J24: =H24*I24 -> 0 | K24: =G24+J24 -> 0 | M24: =M23+K24-L24 -> 301896.36
A25: 21 | B25: 46256 | G25: =E25*F25 -> 0 | J25: =H25*I25 -> 0 | K25: =G25+J25 -> 0 | M25: =M24+K25-L25 -> 301896.36
A26: 22 | B26: 46257 | G26: =E26*F26 -> 0 | J26: =H26*I26 -> 0 | K26: =G26+J26 -> 0 | M26: =M25+K26-L26 -> 301896.36
A27: 23 | B27: 46258 | E27: 1200 | F27: 99.14 | G27: =E27*F27 -> 118968 | H27: 70 | I27: 111.24 | J27: =H27*I27 -> 7786.8 | K27: =G27+J27 -> 126754.8 | M27: =M26+K27-L27 -> 428651.16
A28: 24 | B28: 46259 | G28: =E28*F28 -> 0 | J28: =H28*I28 -> 0 | K28: =G28+J28 -> 0 | M28: =M27+K28-L28 -> 428651.16
A29: 25 | B29: 46260 | G29: =E29*F29 -> 0 | J29: =H29*I29 -> 0 | K29: =G29+J29 -> 0 | M29: =M28+K29-L29 -> 428651.16
A30: 26 | B30: 46261 | E30: 1000 | F30: 99.14 | G30: =E30*F30 -> 99140 | J30: =H30*I30 -> 0 | K30: =G30+J30 -> 99140 | M30: =M29+K30-L30 -> 527791.16
A31: 27 | B31: 46262 | G31: =E31*F31 -> 0 | J31: =H31*I31 -> 0 | K31: =G31+J31 -> 0 | L31: 400000 | M31: =M30+K31-L31 -> 127791.16
A32: 28 | B32: 46263 | G32: =E32*F32 -> 0 | J32: =H32*I32 -> 0 | K32: =G32+J32 -> 0 | M32: =M31+K32-L32 -> 127791.16
A33: 29 | B33: 46264 | G33: =E33*F33 -> 0 | J33: =H33*I33 -> 0 | K33: =G33+J33 -> 0 | M33: =M32+K33-L33 -> 127791.16
A34: 30 | B34: 46265 | G34: =E34*F34 -> 0 | J34: =H34*I34 -> 0 | K34: =G34+J34 -> 0 | M34: =M33+K34-L34 -> 127791.16
A35: 31 | G35: =E35*F35 -> 0 | J35: =H35*I35 -> 0 | K35: =G35+J35 -> 0 | M35: =M34+K35-L35 -> 127791.16
A36: 32 | G36: =E36*F36 -> 0 | J36: =H36*I36 -> 0 | K36: =G36+J36 -> 0 | M36: =M35+K36-L36 -> 127791.16
A37: 33 | G37: =E37*F37 -> 0 | J37: =H37*I37 -> 0 | K37: =G37+J37 -> 0 | M37: =M36+K37-L37 -> 127791.16
A38: 34 | G38: =E38*F38 -> 0 | J38: =H38*I38 -> 0 | K38: =G38+J38 -> 0 | M38: =M37+K38-L38 -> 127791.16
E39: =SUM(E4:E38) -> 9400 | G39: =SUM(G4:G38) -> 931916 | H39: =SUM(H4:H38) -> 245 | J39: =SUM(J4:J38) -> 27253.8 | K39: =SUM(K4:K38) -> 959169.8 | L39: =SUM(L4:L38) -> 1128000

Sheet  YG Gudda-2
A1: One Stop
A2: S.No | B2: Date | C2: GRN No | D2: Ind No/Bill No | E2: Diesel (Lts) | F2: Price | G2: Amount | H2: Petrol (Lts) | I2: Price | J2: Amount | K2: Total amount | L2: Amount paid | M2: As on Date | N2: Remarks
A3: Opening Balance | K3: 299.3192 | M3: 299.3192
A4: 1 | B4: 46235 | G4: =E4*F4 -> 0 | K4: =I4*J4 -> 0 | M4: =M3+K4-L4 -> 299.3192
B5: 46236 | G5: =E5*F5 -> 0 | K5: =I5*J5 -> 0 | M5: =M4+K5-L5 -> 299.3192
A6: 2 | B6: 46237 | G6: =E6*F6 -> 0 | K6: =I6*J6 -> 0 | M6: =M4+K6-L6 -> 299.3192
A7: 3 | B7: 46238 | G7: =E7*F7 -> 0 | J7: =H7*I7 -> 0 | K7: =I7*J7 -> 0 | M7: =M6+K7-L7 -> 299.3192
A8: 4 | B8: 46239 | G8: =E8*F8 -> 0 | K8: =I8*J8 -> 0 | M8: =M7+K8-L8 -> 299.3192
A9: 5 | B9: 46240 | G9: =E9*F9 -> 0 | K9: =I9*J9 -> 0 | M9: =M8+K9-L9 -> 299.3192
A10: 6 | B10: 46241 | G10: =E10*F10 -> 0 | K10: =I10*J10 -> 0 | M10: =M9+K10-L10 -> 299.3192
A11: 7 | B11: 46242 | G11: =E11*F11 -> 0 | K11: =I11*J11 -> 0 | M11: =M10+K11-L11 -> 299.3192
A12: 8 | B12: 46243 | G12: =E12*F12 -> 0 | K12: =I12*J12 -> 0 | M12: =M11+K12-L12 -> 299.3192
A13: 9 | B13: 46244 | G13: =E13*F13 -> 0 | K13: =I13*J13 -> 0 | M13: =M12+K13-L13 -> 299.3192
A14: 10 | B14: 46245 | G14: =E14*F14 -> 0 | K14: =I14*J14 -> 0 | M14: =M13+K14-L14 -> 299.3192
A15: 11 | B15: 46246 | G15: =E15*F15 -> 0 | K15: =I15*J15 -> 0 | M15: =M14+K15-L15 -> 299.3192
A16: 12 | B16: 46247 | G16: =E16*F16 -> 0 | J16: =H16*I16 -> 0 | K16: =I16*J16 -> 0 | M16: =M15+K16-L16 -> 299.3192
A17: 13 | B17: 46248 | G17: =E17*F17 -> 0 | J17: =H17*I17 -> 0 | K17: =I17*J17 -> 0 | M17: =M16+K17-L17 -> 299.3192
A18: 14 | B18: 46249 | G18: =E18*F18 -> 0 | J18: =H18*I18 -> 0 | K18: =I18*J18 -> 0 | M18: =M17+K18-L18 -> 299.3192
A19: 15 | B19: 46250 | G19: =E19*F19 -> 0 | J19: =H19*I19 -> 0 | K19: =I19*J19 -> 0 | M19: =M18+K19-L19 -> 299.3192
A20: 16 | B20: 46251 | G20: =E20*F20 -> 0 | J20: =H20*I20 -> 0 | K20: =I20*J20 -> 0 | M20: =M19+K20-L20 -> 299.3192
A21: 17 | B21: 46252 | G21: =E21*F21 -> 0 | J21: =H21*I21 -> 0 | K21: =I21*J21 -> 0 | M21: =M20+K21-L21 -> 299.3192
A22: 18 | B22: 46253 | G22: =E22*F22 -> 0 | J22: =H22*I22 -> 0 | K22: =I22*J22 -> 0 | M22: =M21+K22-L22 -> 299.3192
A23: 19 | B23: 46254 | G23: =E23*F23 -> 0 | J23: =H23*I23 -> 0 | K23: =I23*J23 -> 0 | M23: =M22+K23-L23 -> 299.3192
A24: 20 | B24: 46255 | G24: =E24*F24 -> 0 | J24: =H24*I24 -> 0 | K24: =I24*J24 -> 0 | M24: =M23+K24-L24 -> 299.3192
A25: 21 | B25: 46256 | G25: =E25*F25 -> 0 | J25: =H25*I25 -> 0 | K25: =I25*J25 -> 0 | M25: =M24+K25-L25 -> 299.3192
A26: 22 | B26: 46257 | G26: =E26*F26 -> 0 | J26: =H26*I26 -> 0 | K26: =I26*J26 -> 0 | M26: =M25+K26-L26 -> 299.3192
A27: 23 | B27: 46258 | G27: =E27*F27 -> 0 | J27: =H27*I27 -> 0 | K27: =I27*J27 -> 0 | M27: =M26+K27-L27 -> 299.3192
... A33: 29 | B33: 46264 | G33: =E33*F33 -> 0 | J33: =H33*I33 -> 0 | K33: =I33*J33 -> 0 | M33: =M32+K33-L33 -> 299.3192
A34: 30 | B34: 46265 | E34: 1500 | F34: 99.02 | G34: =E34*F34 -> 148530 | H34: 70 | I34: 111.12 | J34: =H34*I34 -> 7778.4 | K34: =G34+J34 -> 156308.4 | M34: =M33+K34-L34 -> 156607.72
A35: 31 | G35: =E35*F35 -> 0 | J35: =H35*I35 -> 0 | K35: =I35*J35 -> 0 | M35: =M34+K35-L35 -> 156607.72
A36: 32 | G36: =E36*F36 -> 0 | J36: =H36*I36 -> 0 | K36: =I36*J36 -> 0 | M36: =M35+K36-L36 -> 156607.72
A37: 33 | G37: =E37*F37 -> 0 | J37: =H37*I37 -> 0 | K37: =I37*J37 -> 0 | M37: =M36+K37-L37 -> 156607.72
A38: 34 | G38: =E38*F38 -> 0 | J38: =H38*I38 -> 0 | K38: =I38*J38 -> 0 | M38: =M37+K38-L38 -> 156607.72
E39: =SUM(E4:E38) -> 1500 | G39: =SUM(G4:G38) -> 148530 | H39: =SUM(H4:H38) -> 70 | J39: =SUM(J4:J38) -> 7778.4 | K39: =SUM(K4:K38) -> 156308.4 | L39: =SUM(L4:L38) -> 0

Sheet Hosadurga -2
A1: Shree Veeraprathap Fuel
A2: S.No | B2: Date | C2: GRN No | D2: Ind No/Bill No | E2: Diesel (Lts) | F2: Price | G2: Amount | H2: Petrol (Lts) | I2: Price | J2: Amount | K2: Total amount | L2: Amount paid | M2: As on Date | N2: Remarks
A3: Opening Balance | K3: 484.7941 | M3: 484.7941
A4: 1 | B4: 46235 | C4: 0 | E4: 1400 | F4: 99.38 | G4: =E4*F4 -> 139132 | H4: 70 | I4: 111.72 | J4: =H4*I4 -> 7820.4 | K4: =G4+J4 -> 146952.4 | M4: =M3+K4-L4 -> 147437.19
A5: 2 | B5: 46236 | C5: 0 | E5: 0 | F5: 0 | G5: =E5*F5 -> 0 | J5: =H5*I5 -> 0 | K5: =G5+J5 -> 0 | M5: =M4+K5-L5 -> 147437.19
A6: 3 | B6: 46237 | C6: 0 | E6: 0 | F6: 0 | G6: =E6*F6 -> 0 | J6: =H6*I6 -> 0 | K6: =G6+J6 -> 0 | M6: =M5+K6-L6 -> 147437.19
A7: 4 | B7: 46238 | C7: 0 | E7: 0 | F7: 0 | G7: =E7*F7 -> 0 | J7: =H7*I7 -> 0 | K7: =G7+J7 -> 0 | M7: =M6+K7-L7 -> 147437.19
A8: 5 | B8: 46239 | C8: 0 | E8: 0 | F8: 0 | G8: =E8*F8 -> 0 | J8: =H8*I8 -> 0 | K8: =G8+J8 -> 0 | L8: 100000 | M8: =M7+K8-L8 -> 47437.194
A9: 6 | B9: 46240 | C9: 0 | E9: 0 | F9: 0 | G9: =E9*F9 -> 0 | J9: =H9*I9 -> 0 | K9: =G9+J9 -> 0 | M9: =M8+K9-L9 -> 47437.194
A10: 7 | B10: 46241 | C10: 0 | G10: =E10*F10 -> 0 | J10: =H10*I10 -> 0 | K10: =G10+J10 -> 0 | M10: =M9+K10-L10 -> 47437.194
A11: 8 | B11: 46242 | C11: 0 | G11: =E11*F11 -> 0 | J11: =H11*I11 -> 0 | K11: =G11+J11 -> 0 | M11: =M10+K11-L11 -> 47437.194
A12: 9 | B12: 46243 | C12: 0 | G12: =E12*F12 -> 0 | J12: =H12*I12 -> 0 | K12: =G12+J12 -> 0 | M12: =M11+K12-L12 -> 47437.194
A13: 10 | B13: 46244 | C13: 0 | G13: =E13*F13 -> 0 | J13: =H13*I13 -> 0 | K13: =G13+J13 -> 0 | M13: =M12+K13-L13 -> 47437.194
A14: 11 | B14: 46245 | C14: 0 | G14: =E14*F14 -> 0 | J14: =H14*I14 -> 0 | K14: =G14+J14 -> 0 | M14: =M13+K14-L14 -> 47437.194
A15: 12 | B15: 46246 | C15: 0 | G15: =E15*F15 -> 0 | J15: =H15*I15 -> 0 | K15: =G15+J15 -> 0 | M15: =M14+K15-L15 -> 47437.194
A16: 13 | B16: 46247 | C16: 0 | G16: =E16*F16 -> 0 | J16: =H16*I16 -> 0 | K16: =G16+J16 -> 0 | L16: 47000 | M16: =M15+K16-L16 -> 437.1941
A17: 14 | B17: 46248 | C17: 0 | G17: =E17*F17 -> 0 | J17: =H17*I17 -> 0 | K17: =G17+J17 -> 0 | M17: =M16+K17-L17 -> 437.1941
A18: 15 | B18: 46249 | C18: 0 | G18: =E18*F18 -> 0 | J18: =H18*I18 -> 0 | K18: =G18+J18 -> 0 | M18: =M17+K18-L18 -> 437.1941
A19: 16 | B19: 46250 | C19: 0 | G19: =E19*F19 -> 0 | H19: 70 | I19: 111.72 | J19: =H19*I19 -> 7820.4 | K19: =G19+J19 -> 7820.4 | M19: =M18+K19-L19 -> 8257.5941
A20: 17 | B20: 46251 | C20: 0 | G20: =E20*F20 -> 0 | J20: =H20*I20 -> 0 | K20: =G20+J20 -> 0 | M20: =M19+K20-L20 -> 8257.5941
A21: 18 | B21: 46252 | C21: 0 | G21: =E21*F21 -> 0 | J21: =H21*I21 -> 0 | K21: =G21+J21 -> 0 | M21: =M20+K21-L21 -> 8257.5941
A22: 19 | B22: 46253 | C22: 0 | G22: =E22*F22 -> 0 | J22: =H22*I22 -> 0 | K22: =G22+J22 -> 0 | M22: =M21+K22-L22 -> 8257.5941
A23: 20 | B23: 46254 | C23: 0 | G23: =E23*F23 -> 0 | J23: =H23*I23 -> 0 | K23: =G23+J23 -> 0 | M23: =M22+K23-L23 -> 8257.5941
A24: 21 | B24: 46255 | C24: 0 | G24: =E24*F24 -> 0 | J24: =H24*I24 -> 0 | K24: =G24+J24 -> 0 | M24: =M23+K24-L24 -> 8257.5941
A25: 22 | B25: 46256 | C25: 0 | G25: =E25*F25 -> 0 | J25: =H25*I25 -> 0 | K25: =G25+J25 -> 0 | M25: =M24+K25-L25 -> 8257.5941
A26: 23 | B26: 46257 | C26: 0 | G26: =E26*F26 -> 0 | J26: =H26*I26 -> 0 | K26: =G26+J26 -> 0 | M26: =M25+K26-L26 -> 8257.5941
A27: 24 | B27: 46258 | C27: 0 | G27: =E27*F27 -> 0 | J27: =H27*I27 -> 0 | K27: =G27+J27 -> 0 | M27: =M26+K27-L27 -> 8257.5941
A28: 25 | B28: 46259 | C28: 0 | G28: =E28*F28 -> 0 | J28: =H28*I28 -> 0 | K28: =G28+J28 -> 0 | M28: =M27+K28-L28 -> 8257.5941
A29: 26 | B29: 46260 | C29: 0 | G29: =E29*F29 -> 0 | J29: =H29*I29 -> 0 | K29: =G29+J29 -> 0 | M29: =M28+K29-L29 -> 8257.5941
A30: 27 | B30: 46261 | C30: 0 | G30: =E30*F30 -> 0 | J30: =H30*I30 -> 0 | K30: =G30+J30 -> 0 | M30: =M29+K30-L30 -> 8257.5941
A31: 28 | B31: 46262 | C31: 0 | E31: 1000 | F31: 99.38 | G31: =E31*F31 -> 99380 | H31: 100 | I31: 111.72 | J31: =H31*I31 -> 11172 | K31: =G31+J31 -> 110552 | M31: =M30+K31-L31 -> 118809.59
A32: 29 | B32: 46263 | C32: 0 | G32: =E32*F32 -> 0 | J32: =H32*I32 -> 0 | K32: =G32+J32 -> 0 | M32: =M31+K32-L32 -> 118809.59
A33: 30 | B33: 46264 | C33: 0 | G33: =E33*F33 -> 0 | J33: =H33*I33 -> 0 | K33: =G33+J33 -> 0 | M33: =M32+K33-L33 -> 118809.59
A34: 31 | B34: 46265 | K34: =G34+J34 -> 0
E35: =SUM(E4:E34) -> 2400 | G35: =SUM(G4:G34) -> 238512 | H35: =SUM(H4:H34) -> 240 | J35: =SUM(J4:J34) -> 26812.8 | K35: =SUM(K4:K34) -> 265324.8 | L35: =SUM(L4:L34) -> 147000

Sheet Hiriyur(VJNL)
A1: Sri Balaji Agencies
A2: S.No | B2: Date | C2: GRN No | D2: Ind No/Bill No | E2: Diesel (Lts) | F2: Price | G2: Amount | H2: Petrol (Lts) | I2: Price | J2: Amount | K2: Total amount | L2: Amount paid | M2: As on Date | N2: Remarks
A3: Opening Balance | K3: 208267.9 | M3: 208267.9
A4: 1 | B4: 46235 | G4: =E4*F4 -> 0 | J4: =H4*I4 -> 0 | K4: =G4+J4 -> 0 | M4: =M3+K4-L4 -> 208267.9
A5: 2 | B5: 46236 | G5: =E5*F5 -> 0 | J5: =H5*I5 -> 0 | K5: =G5+J5 -> 0 | M5: =M4+K5-L5 -> 208267.9
A6: 3 | B6: 46237 | G6: =E6*F6 -> 0 | H6: 70 | I6: 112.12 | J6: =H6*I6 -> 7848.4 | K6: =G6+J6 -> 7848.4 | M6: =M5+K6-L6 -> 216116.3
A7: 4 | B7: 46238 | G7: =E7*F7 -> 0 | J7: =H7*I7 -> 0 | K7: =G7+J7 -> 0 | M7: =M6+K7-L7 -> 216116.3
A8: 5 | B8: 46239 | E8: 2000 | F8: 100.09 | G8: =E8*F8 -> 200180 | H8: 70 | I8: 112.12 | J8: =H8*I8 -> 7848.4 | K8: =G8+J8 -> 208028.4 | L8: 200000 | M8: =M7+K8-L8 -> 224144.7
A9: 6 | B9: 46240 | G9: =E9*F9 -> 0 | J9: =H9*I9 -> 0 | K9: =G9+J9 -> 0 | M9: =M8+K9-L9 -> 224144.7
A10: 7 | B10: 46241 | G10: =E10*F10 -> 0 | J10: =H10*I10 -> 0 | K10: =G10+J10 -> 0 | M10: =M9+K10-L10 -> 224144.7
A11: 8 | B11: 46242 | G11: =E11*F11 -> 0 | J11: =H11*I11 -> 0 | K11: =G11+J11 -> 0 | M11: =M10+K11-L11 -> 224144.7
A12: 9 | B12: 46243 | G12: =E12*F12 -> 0 | J12: =H12*I12 -> 0 | K12: =G12+J12 -> 0 | M12: =M11+K12-L12 -> 224144.7
A13: 10 | B13: 46244 | G13: =E13*F13 -> 0 | J13: =H13*I13 -> 0 | K13: =G13+J13 -> 0 | M13: =M12+K13-L13 -> 224144.7
A14: 11 | B14: 46245 | G14: =E14*F14 -> 0 | J14: =H14*I14 -> 0 | K14: =G14+J14 -> 0 | M14: =M13+K14-L14 -> 224144.7
A15: 12 | B15: 46246 | G15: =E15*F15 -> 0 | J15: =H15*I15 -> 0 | K15: =G15+J15 -> 0 | M15: =M14+K15-L15 -> 224144.7
A16: 13 | B16: 46247 | G16: =E16*F16 -> 0 | J16: =H16*I16 -> 0 | K16: =G16+J16 -> 0 | M16: =M15+K16-L16 -> 224144.7
A17: 14 | B17: 46248 | E17: 2000 | F17: 100.09 | G17: =E17*F17 -> 200180 | H17: 105 | I17: 112.12 | J17: =H17*I17 -> 11772.6 | K17: =G17+J17 -> 211952.6 | L17: 224000 | M17: =M16+K17-L17 -> 212097.3
A18: 15 | B18: 46249 | G18: =E18*F18 -> 0 | J18: =H18*I18 -> 0 | K18: =G18+J18 -> 0 | M18: =M17+K18-L18 -> 212097.3
A19: 16 | B19: 46250 | G19: =E19*F19 -> 0 | J19: =H19*I19 -> 0 | K19: =G19+J19 -> 0 | M19: =M18+K19-L19 -> 212097.3
A20: 17 | B20: 46251 | G20: =E20*F20 -> 0 | J20: =H20*I20 -> 0 | K20: =G20+J20 -> 0 | M20: =M19+K20-L20 -> 212097.3
A21: 18 | B21: 46252 | G21: =E21*F21 -> 0 | J21: =H21*I21 -> 0 | K21: =G21+J21 -> 0 | M21: =M20+K21-L21 -> 212097.3
A22: 19 | B22: 46253 | G22: =E22*F22 -> 0 | J22: =H22*I22 -> 0 | K22: =G22+J22 -> 0 | M22: =M21+K22-L22 -> 212097.3
A23: 20 | B23: 46254 | G23: =E23*F23 -> 0 | J23: =H23*I23 -> 0 | K23: =G23+J23 -> 0 | M23: =M22+K23-L23 -> 212097.3
A24: 21 | B24: 46255 | G24: =E24*F24 -> 0 | J24: =H24*I24 -> 0 | K24: =G24+J24 -> 0 | M24: =M23+K24-L24 -> 212097.3
A25: 22 | B25: 46256 | G25: =E25*F25 -> 0 | J25: =H25*I25 -> 0 | K25: =G25+J25 -> 0 | M25: =M24+K25-L25 -> 212097.3
A26: 23 | B26: 46257 | G26: =E26*F26 -> 0 | J26: =H26*I26 -> 0 | K26: =G26+J26 -> 0 | M26: =M25+K26-L26 -> 212097.3
A27: 24 | B27: 46258 | G27: =E27*F27 -> 0 | J27: =H27*I27 -> 0 | K27: =G27+J27 -> 0 | M27: =M26+K27-L27 -> 212097.3
A28: 25 | B28: 46259 | G28: =E28*F28 -> 0 | J28: =H28*I28 -> 0 | K28: =G28+J28 -> 0 | M28: =M27+K28-L28 -> 212097.3
A29: 26 | B29: 46260 | G29: =E29*F29 -> 0 | J29: =H29*I29 -> 0 | K29: =G29+J29 -> 0 | M29: =M28+K29-L29 -> 212097.3
A30: 27 | B30: 46261 | G30: =E30*F30 -> 0 | H30: 70 | I30: 112.12 | J30: =H30*I30 -> 7848.4 | K30: =G30+J30 -> 7848.4 | M30: =M29+K30-L30 -> 219945.7
A31: 28 | B31: 46262 | G31: =E31*F31 -> 0 | J31: =H31*I31 -> 0 | K31: =G31+J31 -> 0 | M31: =M30+K31-L31 -> 219945.7
A32: 29 | B32: 46263 | G32: =E32*F32 -> 0 | J32: =H32*I32 -> 0 | K32: =G32+J32 -> 0 | M32: =M31+K32-L32 -> 219945.7
A33: 30 | B33: 46264 | G33: =E33*F33 -> 0 | J33: =H33*I33 -> 0 | K33: =G33+J33 -> 0 | M33: =M32+K33-L33 -> 219945.7
A34: 31 | B34: 46265 | G34: =E34*F34 -> 0 | J34: =H34*I34 -> 0 | K34: =G34+J34 -> 0 | M34: =M33+K34-L34 -> 219945.7
E35: =SUM(E4:E34) -> 4000 | G35: =SUM(G4:G34) -> 400360 | H35: =SUM(H4:H34) -> 315 | J35: =SUM(J4:J34) -> 35317.8 | K35: =SUM(K4:K34) -> 435677.8 | L35: =SUM(L4:L34) -> 424000

Sheet Malebenur(KUWSDB)
A1: Sree Veerabhadreshwara Service Station
A2: S.No | B2: Date | C2: GRN No | D2: Ind No/Bill No | E2: Diesel (Lts) | F2: Price | G2: Amount | H2: Petrol (Lts) | I2: Price | J2: Amount | K2: Total amount | L2: Amount paid | M2: As on Date | N2: Remarks
A3: Opening Balance | K3: 130766.71 | M3: 130766.71 | O3: 46138.764
A4: 1 | B4: 45870 | G4: =E4*F4 -> 0 | J4: =H4*I4 -> 0 | K4: =G4+J4 -> 0 | L4: 0 | M4: =M3+K4-L4 -> 130766.71
A5: 2 | B5: 45871 | G5: =E5*F5 -> 0 | J5: =H5*I5 -> 0 | K5: =G5+J5 -> 0 | L5: 0 | M5: =M4+K5-L5 -> 130766.71
A6: 3 | B6: 45872 | E6: 600 | F6: 99.99 | G6: =E6*F6 -> 59994 | H6: 30 | I6: 112.06 | J6: =H6*I6 -> 3361.8 | K6: =G6+J6 -> 63355.8 | M6: =M5+K6-L6 -> 194122.51
A7: 4 | B7: 45873 | G7: =E7*F7 -> 0 | J7: =H7*I7 -> 0 | K7: =G7+J7 -> 0 | M7: =M6+K7-L7 -> 194122.51
A8: 5 | B8: 45874 | G8: =E8*F8 -> 0 | J8: =H8*I8 -> 0 | K8: =G8+J8 -> 0 | L8: 194000 | M8: =M7+K8-L8 -> 122.5099
A9: 6 | B9: 45875 | G9: =E9*F9 -> 0 | H9: 30 | I9: 112.02 | J9: =H9*I9 -> 3360.6 | K9: =G9+J9 -> 3360.6 | M9: =M8+K9-L9 -> 3483.1099
A10: 7 | B10: 45876 | E10: 400 | F10: 99.99 | G10: =E10*F10 -> 39996 | J10: =H10*I10 -> 0 | K10: =G10+J10 -> 39996 | M10: =M9+K10-L10 -> 43479.11
A11: 8 | B11: 45877 | G11: =E11*F11 -> 0 | J11: =H11*I11 -> 0 | K11: =G11+J11 -> 0 | M11: =M10+K11-L11 -> 43479.11
A12: 9 | B12: 45878 | G12: =E12*F12 -> 0 | J12: =H12*I12 -> 0 | K12: =G12+J12 -> 0 | M12: =M11+K12-L12 -> 43479.11
A13: 10 | B13: 45879 | G13: =E13*F13 -> 0 | J13: =H13*I13 -> 0 | K13: =G13+J13 -> 0 | M13: =M12+K13-L13 -> 43479.11
A14: 11 | B14: 45880 | E14: 600 | F14: 99.99 | G14: =E14*F14 -> 59994 | H14: 30 | I14: 112.02 | J14: =H14*I14 -> 3360.6 | K14: =G14+J14 -> 63354.6 | M14: =M13+K14-L14 -> 106833.71
A15: 12 | B15: 45881 | G15: =E15*F15 -> 0 | J15: =H15*I15 -> 0 | K15: =G15+J15 -> 0 | M15: =M14+K15-L15 -> 106833.71
A16: 13 | B16: 45882 | G16: =E16*F16 -> 0 | J16: =H16*I16 -> 0 | K16: =G16+J16 -> 0 | M16: =M15+K16-L16 -> 106833.71
A17: 14 | B17: 45883 | E17: 150 | F17: 99.99 | G17: =E17*F17 -> 14998.5 | J17: =H17*I17 -> 0 | K17: =G17+J17 -> 14998.5 | M17: =M16+K17-L17 -> 121832.21
A18: 15 | B18: 45884 | E18: 600 | F18: 99.99 | G18: =E18*F18 -> 59994 | J18: =H18*I18 -> 0 | K18: =G18+J18 -> 59994 | M18: =M17+K18-L18 -> 181826.21
A19: 16 | B19: 45885 | G19: =E19*F19 -> 0 | J19: =H19*I19 -> 0 | K19: =G19+J19 -> 0 | M19: =M18+K19-L19 -> 181826.21
A20: 17 | B20: 45886 | G20: =E20*F20 -> 0 | J20: =H20*I20 -> 0 | K20: =G20+J20 -> 0 | M20: =M19+K20-L20 -> 181826.21
A21: 18 | B21: 45887 | G21: =E21*F21 -> 0 | H21: 30 | I21: 112.02 | J21: =H21*I21 -> 3360.6 | K21: =G21+J21 -> 3360.6 | M21: =M20+K21-L21 -> 185186.81
A22: 19 | B22: 45888 | G22: =E22*F22 -> 0 | H22: 30 | I22: 112.02 | J22: =H22*I22 -> 3360.6 | K22: =G22+J22 -> 3360.6 | M22: =M21+K22-L22 -> 188547.41
A23: 20 | B23: 45889 | G23: =E23*F23 -> 0 | J23: =H23*I23 -> 0 | K23: =G23+J23 -> 0 | L23: 188500 | M23: =M22+K23-L23 -> 47.4099
A24: 21 | B24: 45890 | G24: =E24*F24 -> 0 | J24: =H24*I24 -> 0 | K24: =G24+J24 -> 0 | M24: =M23+K24-L24 -> 47.4099
A25: 22 | B25: 45891 | G25: =E25*F25 -> 0 | J25: =H25*I25 -> 0 | K25: =G25+J25 -> 0 | M25: =M24+K25-L25 -> 47.4099
A26: 23 | B26: 45892 | G26: =E26*F26 -> 0 | J26: =H26*I26 -> 0 | K26: =G26+J26 -> 0 | M26: =M25+K26-L26 -> 47.4099
A27: 24 | B27: 45893 | G27: =E27*F27 -> 0 | J27: =H27*I27 -> 0 | K27: =G27+J27 -> 0 | M27: =M26+K27-L27 -> 47.4099
A28: 25 | B28: 45894 | G28: =E28*F28 -> 0 | J28: =H28*I28 -> 0 | K28: =G28+J28 -> 0 | M28: =M27+K28-L28 -> 47.4099
A29: 26 | B29: 45895 | E29: 600 | F29: 99.99 | G29: =E29*F29 -> 59994 | H29: 30 | I29: 112.02 | J29: =H29*I29 -> 3360.6 | K29: =G29+J29 -> 63354.6 | M29: =M28+K29-L29 -> 63402.01
A30: 27 | B30: 45896 | G30: =E30*F30 -> 0 | J30: =H30*I30 -> 0 | K30: =G30+J30 -> 0 | M30: =M29+K30-L30 -> 63402.01
A31: 28 | B31: 45897 | E31: 600 | F31: 99.99 | G31: =E31*F31 -> 59994 | H31: 20 | I31: 112.02 | J31: =H31*I31 -> 2240.4 | K31: =G31+J31 -> 62234.4 | L31: 63402 | M31: =M30+K31-L31 -> 62234.41
A32: 29 | B32: 45898 | G32: =E32*F32 -> 0 | J32: =H32*I32 -> 0 | K32: =G32+J32 -> 0 | M32: =M31+K32-L32 -> 62234.41
A33: 30 | B33: 45899 | G33: =E33*F33 -> 0 | J33: =H33*I33 -> 0 | K33: =G33+J33 -> 0 | M33: =M32+K33-L33 -> 62234.41
A34: 31 | B34: 45900 | E34: 600 | F34: 99.99 | G34: =E34*F34 -> 59994 | J34: =H34*I34 -> 0 | K34: =G34+J34 -> 59994 | M34: =M33+K34-L34 -> 122228.41
G35: =E35*F35 -> 0 | J35: =H35*I35 -> 0 | K35: =G35+J35 -> 0 | L35: 0 | M35: =M34+K35-L35 -> 122228.41
E36: 0 | F36: 0 | G36: =E36*F36 -> 0 | H36: 0 | I36: 0 | J36: =H36*I36 -> 0 | K36: =G36+J36 -> 0 | L36: 0 | M36: =M35+K36-L36 -> 122228.41
E37: =SUM(E4:E35) -> 4150 | G37: =SUM(G4:G35) -> 414958.5 | H37: =SUM(H4:H35) -> 200 | J37: =SUM(J4:J35) -> 22405.2 | K37: =SUM(K4:K35) -> 437363.7 | L37: =SUM(L4:L35) -> 445902
E38: 0 | G38: 0 | H38: 0 | J38: 0 | K38: =G38+J38 -> 0 | L38: 0
S43: 9052944708

Sheet Molakamuru
A1: Molakamuru
A2: S.No | B2: Date | C2: GRN No | D2: Ind No/Bill No | E2: Diesel (Lts) | F2: Price | G2: Amount | H2: Petrol (Lts) | I2: Price | J2: Amount | K2: Total amount | L2: Amount paid | M2: As on Date | N2: Remarks
A3: Opening Balance | K3: 50699.16 | L3: 0 | M3: 50699.16
A4: 1 | B4: 46235 | G4: =E4*F4 -> 0 | J4: =H4*I4 -> 0 | K4: =G4+J4 -> 0 | M4: =M3+K4-L4 -> 50699.16
A5: 2 | B5: 46236 | E5: 400 | F5: 100.04 | G5: =E5*F5 -> 40016 | H5: 20 | I5: 112.06 | J5: =H5*I5 -> 2241.2 | K5: =G5+J5 -> 42257.2 | M5: =M4+K5-L5 -> 92956.36
A6: 3 | B6: 46237 | G6: =E6*F6 -> 0 | J6: =H6*I6 -> 0 | K6: =G6+J6 -> 0 | M6: =M5+K6-L6 -> 92956.36
A7: 4 | B7: 46238 | G7: =E7*F7 -> 0 | J7: =H7*I7 -> 0 | K7: =G7+J7 -> 0 | M7: =M6+K7-L7 -> 92956.36
A8: 5 | B8: 46239 | G8: =E8*F8 -> 0 | J8: =H8*I8 -> 0 | K8: =G8+J8 -> 0 | L8: 92000 | M8: =M7+K8-L8 -> 956.36
A9: 6 | B9: 46240 | G9: =E9*F9 -> 0 | J9: =H9*I9 -> 0 | K9: =G9+J9 -> 0 | M9: =M8+K9-L9 -> 956.36
A10: 7 | B10: 46241 | G10: =E10*F10 -> 0 | J10: =H10*I10 -> 0 | K10: =G10+J10 -> 0 | M10: =M9+K10-L10 -> 956.36
A11: 8 | B11: 46242 | G11: =E11*F11 -> 0 | J11: =H11*I11 -> 0 | K11: =G11+J11 -> 0 | M11: =M10+K11-L11 -> 956.36
A12: 9 | B12: 46243 | G12: =E12*F12 -> 0 | J12: =H12*I12 -> 0 | K12: =G12+J12 -> 0 | M12: =M11+K12-L12 -> 956.36
A13: 10 | B13: 46244 | G13: =E13*F13 -> 0 | J13: =H13*I13 -> 0 | K13: =G13+J13 -> 0 | M13: =M12+K13-L13 -> 956.36
A14: 11 | B14: 46245 | G14: =E14*F14 -> 0 | J14: =H14*I14 -> 0 | K14: =G14+J14 -> 0 | M14: =M13+K14-L14 -> 956.36
A15: 12 | B15: 46246 | G15: =E15*F15 -> 0 | H15: 25 | I15: 112.06 | J15: =H15*I15 -> 2801.5 | K15: =G15+J15 -> 2801.5 | M15: =M14+K15-L15 -> 3757.86
A16: 13 | B16: 46247 | G16: =E16*F16 -> 0 | J16: =H16*I16 -> 0 | K16: =G16+J16 -> 0 | M16: =M15+K16-L16 -> 3757.86
A17: 14 | B17: 46248 | G17: =E17*F17 -> 0 | J17: =H17*I17 -> 0 | K17: =G17+J17 -> 0 | M17: =M16+K17-L17 -> 3757.86
A18: 15 | B18: 46249 | G18: =E18*F18 -> 0 | J18: =H18*I18 -> 0 | K18: =G18+J18 -> 0 | M18: =M17+K18-L18 -> 3757.86
A19: 16 | B19: 46250 | G19: =E19*F19 -> 0 | J19: =H19*I19 -> 0 | K19: =G19+J19 -> 0 | M19: =M18+K19-L19 -> 3757.86
A20: 17 | B20: 46251 | G20: =E20*F20 -> 0 | J20: =H20*I20 -> 0 | K20: =G20+J20 -> 0 | M20: =M19+K20-L20 -> 3757.86
A21: 18 | B21: 46252 | E21: 200 | F21: 100.04 | G21: =E21*F21 -> 20008 | J21: =H21*I21 -> 0 | K21: =G21+J21 -> 20008 | M21: =M20+K21-L21 -> 23765.86
A22: 19 | B22: 46253 | G22: =E22*F22 -> 0 | J22: =H22*I22 -> 0 | K22: =G22+J22 -> 0 | M22: =M21+K22-L22 -> 23765.86
A23: 20 | B23: 46254 | G23: =E23*F23 -> 0 | J23: =H23*I23 -> 0 | K23: =G23+J23 -> 0 | L23: 23000 | M23: =M22+K23-L23 -> 765.86
A24: 21 | B24: 46255 | G24: =E24*F24 -> 0 | J24: =H24*I24 -> 0 | K24: =G24+J24 -> 0 | M24: =M23+K24-L24 -> 765.86
A25: 22 | B25: 46256 | G25: =E25*F25 -> 0 | H25: 20 | I25: 112.06 | J25: =H25*I25 -> 2241.2 | K25: =G25+J25 -> 2241.2 | M25: =M24+K25-L25 -> 3007.06
A26: 23 | B26: 46257 | G26: =E26*F26 -> 0 | J26: =H26*I26 -> 0 | K26: =G26+J26 -> 0 | M26: =M25+K26-L26 -> 3007.06
A27: 24 | B27: 46258 | G27: =E27*F27 -> 0 | J27: =H27*I27 -> 0 | K27: =G27+J27 -> 0 | M27: =M26+K27-L27 -> 3007.06
A28: 25 | B28: 46259 | G28: =E28*F28 -> 0 | J28: =H28*I28 -> 0 | K28: =G28+J28 -> 0 | M28: =M27+K28-L28 -> 3007.06
A29: 26 | B29: 46260 | G29: =E29*F29 -> 0 | J29: =H29*I29 -> 0 | K29: =G29+J29 -> 0 | M29: =M28+K29-L29 -> 3007.06
A30: 27 | B30: 46261 | G30: =E30*F30 -> 0 | J30: =H30*I30 -> 0 | K30: =G30+J30 -> 0 | M30: =M29+K30-L30 -> 3007.06
A31: 28 | B31: 46262 | G31: =E31*F31 -> 0 | J31: =H31*I31 -> 0 | K31: =G31+J31 -> 0 | M31: =M30+K31-L31 -> 3007.06
A32: 29 | B32: 46263 | E32: 300 | F32: 100.04 | G32: =E32*F32 -> 30012 | H32: 20 | I32: 112.06 | J32: =H32*I32 -> 2241.2 | K32: =G32+J32 -> 32253.2 | M32: =M31+K32-L32 -> 35260.26
A33: 30 | B33: 46264 | G33: =E33*F33 -> 0 | J33: =H33*I33 -> 0 | K33: =G33+J33 -> 0 | M33: =M32+K33-L33 -> 35260.26
A34: 31 | B34: 46265 | G34: =E34*F34 -> 0 | K34: =G34+J34 -> 0 | M34: =M33+K34-L34 -> 35260.26
E35: =SUM(E4:E34) -> 900 | G35: =SUM(G4:G34) -> 90036 | H35: =SUM(H4:H34) -> 85 | J35: =SUM(J4:J34) -> 9525.1 | K35: =SUM(K4:K34) -> 99561.1 | L35: =SUM(L4:L34) -> 115000

Sheet Chellakere -1
A1: Shivaganga Service Station (BPCL)
A2: S.No | B2: Date | C2: GRN No | D2: Ind No/Bill No | E2: Diesel (Lts) | F2: Price | G2: Amount | H2: Petrol (Lts) | I2: Price | J2: Amount | K2: Total amount | L2: Amount paid | M2: As on Date | N2: Remarks
A3: Opening Balance | K3: 210978.25 | L3: 210978.25 | M3: 210978.25
A4: 1 | B4: 46235 | G4: =E4*F4 -> 0 | J4: =H4*I4 -> 0 | K4: =G4+J4 -> 0 | M4: =M3+K4-L4 -> 210978.25
A5: 2 | B5: 46236 | G5: =E5*F5 -> 0 | J5: =H5*I5 -> 0 | K5: =G5+J5 -> 0 | M5: =M4+K5-L5 -> 210978.25
A6: 3 | B6: 46237 | G6: =E6*F6 -> 0 | J6: =H6*I6 -> 0 | K6: =G6+J6 -> 0 | M6: =M5+K6-L6 -> 210978.25
A7: 4 | B7: 46238 | G7: =E7*F7 -> 0 | J7: =H7*I7 -> 0 | K7: =G7+J7 -> 0 | M7: =M6+K7-L7 -> 210978.25
A8: 5 | B8: 46239 | G8: =E8*F8 -> 0 | J8: =H8*I8 -> 0 | K8: =G8+J8 -> 0 | L8: 200000 | M8: =M7+K8-L8 -> 10978.251
A9: 6 | B9: 46240 | E9: 600 | F9: 100.05 | G9: =E9*F9 -> 60030 | H9: 35 | I9: 112.07 | J9: =H9*I9 -> 3922.45 | K9: =G9+J9 -> 63952.45 | M9: =M8+K9-L9 -> 74930.701
A10: 7 | B10: 46241 | G10: =E10*F10 -> 0 | J10: =H10*I10 -> 0 | K10: =G10+J10 -> 0 | M10: =M9+K10-L10 -> 74930.701
A11: 8 | B11: 46242 | G11: =E11*F11 -> 0 | J11: =H11*I11 -> 0 | K11: =G11+J11 -> 0 | M11: =M10+K11-L11 -> 74930.701
A12: 9 | B12: 46243 | E12: 600 | F12: 100.05 | G12: =E12*F12 -> 60030 | J12: =H12*I12 -> 0 | K12: =G12+J12 -> 60030 | M12: =M11+K12-L12 -> 134960.7
A13: 10 | B13: 46244 | G13: =E13*F13 -> 0 | J13: =H13*I13 -> 0 | K13: =G13+J13 -> 0 | M13: =M12+K13-L13 -> 134960.7
A14: 11 | B14: 46245 | G14: =E14*F14 -> 0 | J14: =H14*I14 -> 0 | K14: =G14+J14 -> 0 | M14: =M13+K14-L14 -> 134960.7
A15: 12 | B15: 46246 | E15: 600 | F15: 100.05 | G15: =E15*F15 -> 60030 | H15: 35 | I15: 112.07 | J15: =H15*I15 -> 3922.45 | K15: =G15+J15 -> 63952.45 | M15: =M14+K15-L15 -> 198913.15
A16: 13 | B16: 46247 | G16: =E16*F16 -> 0 | J16: =H16*I16 -> 0 | K16: =G16+J16 -> 0 | M16: =M15+K16-L16 -> 198913.15
A17: 14 | B17: 46248 | G17: =E17*F17 -> 0 | J17: =H17*I17 -> 0 | K17: =G17+J17 -> 0 | M17: =M16+K17-L17 -> 198913.15
A18: 15 | B18: 46249 | G18: =E18*F18 -> 0 | J18: =H18*I18 -> 0 | K18: =G18+J18 -> 0 | M18: =M17+K18-L18 -> 198913.15
A19: 16 | B19: 46250 | G19: =E19*F19 -> 0 | J19: =H19*I19 -> 0 | K19: =G19+J19 -> 0 | M19: =M18+K19-L19 -> 198913.15
A20: 17 | B20: 46251 | G20: =E20*F20 -> 0 | J20: =H20*I20 -> 0 | K20: =G20+J20 -> 0 | M20: =M19+K20-L20 -> 198913.15
A21: 18 | B21: 46252 | G21: =E21*F21 -> 0 | J21: =H21*I21 -> 0 | K21: =G21+J21 -> 0 | M21: =M20+K21-L21 -> 198913.15
A22: 19 | B22: 46253 | G22: =E22*F22 -> 0 | J22: =H22*I22 -> 0 | K22: =G22+J22 -> 0 | M22: =M21+K22-L22 -> 198913.15
A23: 20 | B23: 46254 | E23: 600 | F23: 100.05 | G23: =E23*F23 -> 60030 | H23: 70 | I23: 112.07 | J23: =H23*I23 -> 7844.9 | K23: =G23+J23 -> 67874.9 | L23: 198900 | M23: =M22+K23-L23 -> 67888.051
A24: 21 | B24: 46255 | M24: =M23+K24-L24 -> 67888.051
A25: 22 | B25: 46256 | G25: =E25*F25 -> 0 | J25: =H25*I25 -> 0 | K25: =G25+J25 -> 0 | M25: =M24+K25-L25 -> 67888.051
A26: 23 | B26: 46257 | G26: =E26*F26 -> 0 | J26: =H26*I26 -> 0 | K26: =G26+J26 -> 0 | M26: =M25+K26-L26 -> 67888.051
A27: 24 | B27: 46258 | G27: =E27*F27 -> 0 | J27: =H27*I27 -> 0 | K27: =G27+J27 -> 0 | M27: =M26+K27-L27 -> 67888.051
A28: 25 | B28: 46259 | G28: =E28*F28 -> 0 | J28: =H28*I28 -> 0 | K28: =G28+J28 -> 0 | M28: =M27+K28-L28 -> 67888.051
A29: 26 | B29: 46260 | E29: 600 | F29: 100.05 | G29: =E29*F29 -> 60030 | H29: 35 | I29: 112.07 | J29: =H29*I29 -> 3922.45 | K29: =G29+J29 -> 63952.45 | M29: =M28+K29-L29 -> 131840.5
A30: 27 | B30: 46261 | G30: =E30*F30 -> 0 | J30: =H30*I30 -> 0 | K30: =G30+J30 -> 0 | M30: =M29+K30-L30 -> 131840.5
A31: 28 | B31: 46262 | G31: =E31*F31 -> 0 | J31: =H31*I31 -> 0 | K31: =G31+J31 -> 0 | L31: 131840 | M31: =M30+K31-L31 -> 0.5014
A32: 29 | B32: 46263 | G32: =E32*F32 -> 0 | J32: =H32*I32 -> 0 | K32: =G32+J32 -> 0 | M32: =M31+K32-L32 -> 0.5014
A33: 30 | B33: 46264 | G33: =E33*F33 -> 0 | J33: =H33*I33 -> 0 | K33: =G33+J33 -> 0 | M33: =M32+K33-L33 -> 0.5014
A34: 31 | B34: 46265 | G34: =E34*F34 -> 0 | J34: =H34*I34 -> 0 | K34: =G34+J34 -> 0 | M34: =M33+K34-L34 -> 0.5014
A35: 32 | G35: =E35*F35 -> 0 | J35: =H35*I35 -> 0 | K35: =G35+J35 -> 0 | M35: =M34+K35-L35 -> 0.5014
E38: =SUM(E4:E35) -> 3000 | G38: =SUM(G4:G35) -> 300150 | H38: =SUM(H4:H35) -> 175 | J38: =SUM(J4:J35) -> 19612.25 | K38: =SUM(K4:K35) -> 319762.25 | L38: =SUM(L4:L35) -> 530740

Sheet  Chellakere-PKG-9
A1: Chellakere-PKG-09
A2: S.No | B2: Date | C2: GRN No | D2: Ind No/Bill No | E2: Diesel (Lts) | F2: Price | G2: Amount | H2: Petrol (Lts) | I2: Price | J2: Amount | K2: Total amount | L2: Amount paid | M2: As on Date | N2: Remarks
A3: Opening Balance | K3: 0 | L3: 0 | M3: 0
A4: 1 | B4: 46235 | G4: =E4*F4 -> 0 | J4: =H4*I4 -> 0 | K4: =G4+J4 -> 0 | L4: =K4 -> 0 | M4: =M3+K4-L4 -> 0
A5: 2 | B5: 46236 | G5: =E5*F5 -> 0 | J5: =H5*I5 -> 0 | K5: =G5+J5 -> 0 | L5: =K5 -> 0 | M5: =M4+K5-L5 -> 0
A6: 3 | B6: 46237 | E6: 109.95 | F6: 100.05 | G6: =E6*F6 -> 11000.497 | H6: 6.02 | I6: 112.07 | J6: =H6*I6 -> 674.6614 | K6: =G6+J6 -> 11675.159 | L6: =K6 -> 11675.159 | M6: =M5+K6-L6 -> 0
A7: 4 | B7: 46238 | E7: 35 | F7: 100.05 | G7: =E7*F7 -> 3501.75 | J7: =H7*I7 -> 0 | K7: =G7+J7 -> 3501.75 | L7: =K7 -> 3501.75 | M7: =M6+K7-L7 -> 0
A8: 5 | B8: 46239 | E8: 35 | F8: 100.05 | G8: =E8*F8 -> 3501.75 | J8: =H8*I8 -> 0 | K8: =G8+J8 -> 3501.75 | L8: =K8 -> 3501.75 | M8: =M7+K8-L8 -> 0
A9: 6 | B9: 46240 | G9: =E9*F9 -> 0 | J9: =H9*I9 -> 0 | K9: =G9+J9 -> 0 | L9: =K9 -> 0 | M9: =M8+K9-L9 -> 0
A10: 7 | B10: 46241 | E10: 121.98 | F10: 99.202902 | G10: =E10*F10 -> 12100.77 | J10: =H10*I10 -> 0 | K10: =G10+J10 -> 12100.77 | L10: =K10 -> 12100.77 | M10: =M9+K10-L10 -> 0
A11: 8 | B11: 46242 | G11: =E11*F11 -> 0 | H11: 6 | I11: 112.07 | J11: =H11*I11 -> 672.42 | K11: =G11+J11 -> 672.42 | L11: =K11 -> 672.42 | M11: =M10+K11-L11 -> 0
A12: 9 | B12: 46243 | G12: =E12*F12 -> 0 | J12: =H12*I12 -> 0 | K12: =G12+J12 -> 0 | L12: =K12 -> 0 | M12: =M11+K12-L12 -> 0
A13: 10 | B13: 46244 | G13: =E13*F13 -> 0 | J13: =H13*I13 -> 0 | K13: =G13+J13 -> 0 | L13: =K13 -> 0 | M13: =M12+K13-L13 -> 0
A14: 11 | B14: 46245 | G14: =E14*F14 -> 0 | J14: =H14*I14 -> 0 | K14: =G14+J14 -> 0 | L14: =K14 -> 0 | M14: =M13+K14-L14 -> 0
A15: 12 | B15: 46246 | E15: 68.04 | F15: 100.05 | G15: =E15*F15 -> 6807.402 | H15: 10 | I15: 112.07 | J15: =H15*I15 -> 1120.7 | K15: =G15+J15 -> 7928.102 | L15: =K15 -> 7928.102 | M15: =M14+K15-L15 -> 0
A16: 13 | B16: 46247 | G16: =E16*F16 -> 0 | J16: =H16*I16 -> 0 | K16: =G16+J16 -> 0 | L16: =K16 -> 0 | M16: =M15+K16-L16 -> 0
A17: 14 | B17: 46248 | G17: =E17*F17 -> 0 | J17: =H17*I17 -> 0 | K17: =G17+J17 -> 0 | L17: =K17 -> 0 | M17: =M16+K17-L17 -> 0
A18: 15 | B18: 46249 | E18: 31.26 | F18: 100.05 | G18: =E18*F18 -> 3127.563 | J18: =H18*I18 -> 0 | K18: =G18+J18 -> 3127.563 | L18: =K18 -> 3127.563 | M18: =M17+K18-L18 -> 0
A19: 16 | B19: 46250 | G19: =E19*F19 -> 0 | J19: =H19*I19 -> 0 | K19: =G19+J19 -> 0 | L19: =K19 -> 0 | M19: =M18+K19-L19 -> 0
A20: 17 | B20: 46251 | E20: 124.61 | F20: 100.05 | G20: =E20*F20 -> 12467.231 | H20: 12 | I20: 112.07 | J20: =H20*I20 -> 1344.84 | K20: =G20+J20 -> 13812.071 | L20: =K20 -> 13812.071 | M20: =M19+K20-L20 -> 0 | T20: 54.83
A21: 18 | B21: 46252 | G21: =E21*F21 -> 0 | J21: =H21*I21 -> 0 | K21: =G21+J21 -> 0 | L21: =K21 -> 0 | M21: =M20+K21-L21 -> 0 | T21: 0.55
A22: 19 | B22: 46253 | G22: =E22*F22 -> 0 | H22: 7 | I22: 112.07 | J22: =H22*I22 -> 784.49 | K22: =G22+J22 -> 784.49 | L22: =K22 -> 784.49 | M22: =M21+K22-L22 -> 0
B23: 46254 | G23: =E23*F23 -> 0 | K23: =G23+J23 -> 0 | L23: =K23 -> 0
A24: 20 | B24: 46255 | G24: =E24*F24 -> 0 | J24: =H24*I24 -> 0 | K24: =G24+J24 -> 0 | L24: =K24 -> 0 | M24: =M22+K24-L24 -> 0
A25: 21 | B25: 46256 | G25: =E25*F25 -> 0 | J25: =H25*I25 -> 0 | K25: =G25+J25 -> 0 | L25: =K25 -> 0 | M25: =M24+K25-L25 -> 0
A26: 22 | B26: 46257 | G26: =E26*F26 -> 0 | J26: =H26*I26 -> 0 | K26: =G26+J26 -> 0 | L26: =K26 -> 0 | M26: =M25+K26-L26 -> 0
A27: 23 | B27: 46258 | E27: 69 | F27: 100.05 | G27: =E27*F27 -> 6903.45 | J27: =H27*I27 -> 0 | K27: =G27+J27 -> 6903.45 | L27: =K27 -> 6903.45 | M27: =M26+K27-L27 -> 0
A28: 24 | B28: 46259 | G28: =E28*F28 -> 0 | J28: =H28*I28 -> 0 | K28: =G28+J28 -> 0 | L28: =K28 -> 0 | M28: =M27+K28-L28 -> 0
A29: 25 | B29: 46260 | G29: =E29*F29 -> 0 | J29: =H29*I29 -> 0 | K29: =G29+J29 -> 0 | L29: =K29 -> 0 | M29: 0
A30: 26 | B30: 46261 | E30: 138.15 | F30: 100.05 | G30: =E30*F30 -> 13821.907 | J30: =H30*I30 -> 0 | K30: =G30+J30 -> 13821.907 | L30: =K30 -> 13821.907 | M30: 0
A31: 27 | B31: 46262 | G31: =E31*F31 -> 0 | J31: =H31*I31 -> 0 | K31: =G31+J31 -> 0 | L31: =K31 -> 0 | M31: 0
A32: 28 | B32: 46263 | G32: =E32*F32 -> 0 | J32: =H32*I32 -> 0 | K32: =G32+J32 -> 0 | L32: =K32 -> 0 | M32: 0
A33: 29 | B33: 46264 | G33: =E33*F33 -> 0 | J33: =H33*I33 -> 0 | K33: =G33+J33 -> 0 | L33: =K33 -> 0
A34: 30 | B34: 46265 | E34: 3 | F34: 100.05 | G34: =E34*F34 -> 300.15 | J34: =H34*I34 -> 0 | K34: =G34+J34 -> 300.15 | L34: =K34 -> 300.15
A35: 31 | G35: =E35*F35 -> 0 | J35: =H35*I35 -> 0 | K35: =G35+J35 -> 0 | L35: =K35 -> 0
E36: =SUM(E4:E35) -> 735.99 | G36: =SUM(G4:G35) -> 73532.47 | H36: =SUM(H4:H35) -> 41.02 | J36: =SUM(J4:J35) -> 4597.1114 | K36: =SUM(K4:K35) -> 78129.582 | L36: =SUM(L4:L35) -> 78129.582

Sheet  Chennagiri
A1: Chennagiri
A2: S.No | B2: Date | C2: GRN No | D2: Ind No/Bill No | E2: Diesel (Lts) | F2: Price | G2: Amount | H2: Petrol (Lts) | I2: Price | J2: Amount | K2: Total amount | L2: Amount paid | M2: As on Date | N2: Remarks
A3: Opening Balance | K3: 0 | L3: 0 | M3: =+K3 -> 0
A4: 1 | B4: 46235 | G4: =E4*F4 -> 0 | J4: =H4*I4 -> 0 | K4: =G4+J4 -> 0 | L4: =K4 -> 0 | M4: =M3+K4-L4 -> 0
A5: 2 | B5: 46236 | G5: =E5*F5 -> 0 | J5: =H5*I5 -> 0 | K5: =G5+J5 -> 0 | L5: =K5 -> 0 | M5: =M4+K5-L5 -> 0
A6: 3 | B6: 46237 | G6: =E6*F6 -> 0 | J6: =H6*I6 -> 0 | K6: =G6+J6 -> 0 | L6: =K6 -> 0 | M6: =M5+K6-L6 -> 0
A7: 4 | B7: 46238 | E7: 200 | F7: 99.9 | G7: =E7*F7 -> 19980 | J7: =H7*I7 -> 0 | K7: =G7+J7 -> 19980 | L7: =K7 -> 19980 | M7: =M6+K7-L7 -> 0
A8: 5 | B8: 46239 | G8: =E8*F8 -> 0 | J8: =H8*I8 -> 0 | K8: =G8+J8 -> 0 | L8: =K8 -> 0 | M8: =M7+K8-L8 -> 0
A9: 6 | B9: 46240 | G9: =E9*F9 -> 0 | J9: =H9*I9 -> 0 | K9: =G9+J9 -> 0 | L9: =K9 -> 0 | M9: =M8+K9-L9 -> 0
A10: 7 | B10: 46241 | G10: =E10*F10 -> 0 | J10: =H10*I10 -> 0 | K10: =G10+J10 -> 0 | L10: =K10 -> 0 | M10: =M9+K10-L10 -> 0
A11: 8 | B11: 46242 | G11: =E11*F11 -> 0 | J11: =H11*I11 -> 0 | K11: =G11+J11 -> 0 | L11: =K11 -> 0 | M11: =M10+K11-L11 -> 0
A12: 9 | B12: 46243 | G12: =E12*F12 -> 0 | J12: =H12*I12 -> 0 | K12: =G12+J12 -> 0 | L12: =K12 -> 0 | M12: =M11+K12-L12 -> 0
A13: 10 | B13: 46244 | G13: =E13*F13 -> 0 | J13: =H13*I13 -> 0 | K13: =G13+J13 -> 0 | L13: =K13 -> 0 | M13: =M12+K13-L13 -> 0
A14: 11 | B14: 46245 | E14: 100 | F14: 99.87 | G14: =E14*F14 -> 9987 | H14: 17 | I14: 112.06 | J14: =H14*I14 -> 1905.02 | K14: =G14+J14 -> 11892.02 | L14: =K14 -> 11892.02 | M14: =M13+K14-L14 -> 0
A15: 12 | B15: 46246 | G15: =E15*F15 -> 0 | J15: =H15*I15 -> 0 | K15: =G15+J15 -> 0 | L15: =K15 -> 0 | M15: =M14+K15-L15 -> 0
A16: 13 | B16: 46247 | G16: =E16*F16 -> 0 | J16: =H16*I16 -> 0 | K16: =G16+J16 -> 0 | L16: =K16 -> 0 | M16: =M15+K16-L16 -> 0
A17: 14 | B17: 46248 | E17: 200 | F17: 99.87 | G17: =E17*F17 -> 19974 | J17: =H17*I17 -> 0 | K17: =G17+J17 -> 19974 | L17: =K17 -> 19974 | M17: =M16+K17-L17 -> 0
A18: 15 | B18: 46249 | G18: =E18*F18 -> 0 | J18: =H18*I18 -> 0 | K18: =G18+J18 -> 0 | L18: =K18 -> 0 | M18: =M17+K18-L18 -> 0
A19: 16 | B19: 46250 | G19: =E19*F19 -> 0 | J19: =H19*I19 -> 0 | K19: =G19+J19 -> 0 | L19: =K19 -> 0 | M19: =M18+K19-L19 -> 0
A20: 17 | B20: 46251 | G20: =E20*F20 -> 0 | J20: =H20*I20 -> 0 | K20: =G20+J20 -> 0 | L20: =K20 -> 0 | M20: =M19+K20-L20 -> 0
A21: 18 | B21: 46252 | G21: =E21*F21 -> 0 | J21: =H21*I21 -> 0 | K21: =G21+J21 -> 0 | L21: =K21 -> 0 | M21: =M20+K21-L21 -> 0
A22: 19 | B22: 46253 | G22: =E22*F22 -> 0 | H22: 26 | I22: 112.06 | J22: =H22*I22 -> 2913.56 | K22: =G22+J22 -> 2913.56 | L22: =K22 -> 2913.56 | M22: =M21+K22-L22 -> 0
A23: 20 | B23: 46254 | G23: =E23*F23 -> 0 | J23: =H23*I23 -> 0 | K23: =G23+J23 -> 0 | L23: =K23 -> 0 | M23: =M22+K23-L23 -> 0
A24: 21 | B24: 46255 | E24: 200 | F24: 99.87 | G24: =E24*F24 -> 19974 | J24: =H24*I24 -> 0 | K24: =G24+J24 -> 19974 | L24: =K24 -> 19974 | M24: =M23+K24-L24 -> 0
A25: 22 | B25: 46256 | G25: =E25*F25 -> 0 | J25: =H25*I25 -> 0 | K25: =G25+J25 -> 0 | L25: =K25 -> 0 | M25: =M24+K25-L25 -> 0
A26: 23 | B26: 46257 | G26: =E26*F26 -> 0 | J26: =H26*I26 -> 0 | K26: =G26+J26 -> 0 | L26: =K26 -> 0 | M26: =M25+K26-L26 -> 0
A27: 24 | B27: 46258 | G27: =E27*F27 -> 0 | J27: =H27*I27 -> 0 | K27: =G27+J27 -> 0 | L27: =K27 -> 0 | M27: =M26+K27-L27 -> 0
A28: 25 | B28: 46259 | G28: =E28*F28 -> 0 | J28: =H28*I28 -> 0 | K28: =G28+J28 -> 0 | L28: =K28 -> 0 | M28: 0
A29: 26 | B29: 46260 | G29: =E29*F29 -> 0 | J29: =H29*I29 -> 0 | K29: =G29+J29 -> 0 | L29: =K29 -> 0 | M29: 0
A30: 27 | B30: 46261 | G30: =E30*F30 -> 0 | J30: =H30*I30 -> 0 | K30: =G30+J30 -> 0 | L30: =K30 -> 0 | M30: 0
A31: 28 | B31: 46262 | G31: =E31*F31 -> 0 | J31: =H31*I31 -> 0 | K31: =G31+J31 -> 0 | L31: =K31 -> 0 | M31: 0
A32: 29 | B32: 46263 | E32: 160 | F32: 99.87 | G32: =E32*F32 -> 15979.2 | H32: 35 | I32: 112.06 | J32: =H32*I32 -> 3922.1 | K32: =G32+J32 -> 19901.3 | L32: =K32 -> 19901.3
A33: 30 | B33: 46264 | G33: =E33*F33 -> 0 | J33: =H33*I33 -> 0 | K33: =G33+J33 -> 0 | L33: =K33 -> 0
A34: 31 | B34: 46265 | G34: =E34*F34 -> 0 | J34: =H34*I34 -> 0 | K34: =G34+J34 -> 0 | L34: =K34 -> 0
E35: =SUM(E4:E34) -> 860 | G35: =SUM(G4:G34) -> 85894.2 | H35: =SUM(H4:H34) -> 78 | J35: =SUM(J4:J34) -> 8740.68 | K35: =SUM(K4:K34) -> 94634.88 | L35: =SUM(L4:L34) -> 94634.88

Sheet Khanapur
A1: V.V.Varde
A2: S.No | B2: Date | C2: GRN No | D2: Ind No/Bill No | E2: Diesel (Lts) | F2: Price | G2: Amount | H2: Petrol (Lts) | I2: Price | J2: Amount | K2: Total amount | L2: Date of payment | M2: Amount paid | N2: Remarks
D3: Opening Balance | K3: 84731.659 | M3: 84731.659
A4: 1 | B4: 46235 | E4: 42.81 | F4: 98.69 | G4: =E4*F4 -> 4224.9189 | H4: 5 | I4: 110.74 | J4: =H4*I4 -> 553.7 | K4: =G4+J4 -> 4778.6189 | M4: =M3+K4-L4 -> 89510.278
A5: 2 | B5: 46236 | G5: =E5*F5 -> 0 | J5: =H5*I5 -> 0 | K5: =G5+J5 -> 0 | M5: =M4+K5-L5 -> 89510.278 | S5: 90.88 | T5: 102.77
A6: 3 | B6: 46237 | E6: 6 | F6: 98.69 | G6: =E6*F6 -> 592.14 | H6: 10 | I6: 110.74 | J6: =H6*I6 -> 1107.4 | K6: =G6+J6 -> 1699.54 | M6: =M5+K6-L6 -> 91209.818
A7: 4 | B7: 46238 | G7: =E7*F7 -> 0 | J7: =H7*I7 -> 0 | K7: =G7+J7 -> 0 | M7: =M6+K7-L7 -> 91209.818
A8: 5 | B8: 46239 | E8: 34.94 | F8: 98.69 | G8: =E8*F8 -> 3448.2286 | J8: =H8*I8 -> 0 | K8: =G8+J8 -> 3448.2286 | L8: 81000 | M8: =M7+K8-L8 -> 13658.046
A9: 6 | B9: 46240 | G9: =E9*F9 -> 0 | J9: =H9*I9 -> 0 | K9: =G9+J9 -> 0 | M9: =M8+K9-L9 -> 13658.046
A10: 7 | B10: 46241 | G10: =E10*F10 -> 0 | H10: 5 | I10: 110.74 | J10: =H10*I10 -> 553.7 | K10: =G10+J10 -> 553.7 | M10: =M9+K10-L10 -> 14211.746
A11: 8 | B11: 46242 | G11: =E11*F11 -> 0 | H11: 25 | I11: 110.74 | J11: =H11*I11 -> 2768.5 | K11: =G11+J11 -> 2768.5 | M11: =M10+K11-L11 -> 16980.246
A12: 9 | B12: 46243 | E12: 44.13 | F12: 98.69 | G12: =E12*F12 -> 4355.1897 | J12: =H12*I12 -> 0 | K12: =G12+J12 -> 4355.1897 | M12: =M11+K12-L12 -> 21335.436
A13: 10 | B13: 46244 | G13: =E13*F13 -> 0 | J13: =H13*I13 -> 0 | K13: =G13+J13 -> 0 | M13: =M12+K13-L13 -> 21335.436
A14: 11 | B14: 46245 | G14: =E14*F14 -> 0 | H14: 10 | I14: 110.74 | J14: =H14*I14 -> 1107.4 | K14: =G14+J14 -> 1107.4 | M14: =M13+K14-L14 -> 22442.836
A15: 12 | B15: 46246 | G15: =E15*F15 -> 0 | J15: =H15*I15 -> 0 | K15: =G15+J15 -> 0 | M15: =M14+K15-L15 -> 22442.836
A16: 13 | B16: 46247 | G16: =E16*F16 -> 0 | J16: =H16*I16 -> 0 | K16: =G16+J16 -> 0 | M16: =M15+K16-L16 -> 22442.836
A17: 14 | B17: 46248 | E17: 50 | F17: 98.69 | G17: =E17*F17 -> 4934.5 | J17: =H17*I17 -> 0 | K17: =G17+J17 -> 4934.5 | M17: =M16+K17-L17 -> 27377.336
A18: 15 | B18: 46249 | G18: =E18*F18 -> 0 | H18: 5 | I18: 110.74 | J18: =H18*I18 -> 553.7 | K18: =G18+J18 -> 553.7 | M18: =M17+K18-L18 -> 27931.036
A19: 16 | B19: 46250 | G19: =E19*F19 -> 0 | J19: =H19*I19 -> 0 | K19: =G19+J19 -> 0 | M19: =M18+K19-L19 -> 27931.036
A20: 17 | B20: 46251 | G20: =E20*F20 -> 0 | J20: =H20*I20 -> 0 | K20: =G20+J20 -> 0 | M20: =M19+K20-L20 -> 27931.036
A21: 18 | B21: 46252 | E21: 46 | F21: 98.69 | G21: =E21*F21 -> 4539.74 | H21: 5 | I21: 110.74 | J21: =H21*I21 -> 553.7 | K21: =G21+J21 -> 5093.44 | M21: =M20+K21-L21 -> 33024.476
A22: 19 | B22: 46253 | G22: =E22*F22 -> 0 | H22: 5 | I22: 110.74 | J22: =H22*I22 -> 553.7 | K22: =G22+J22 -> 553.7 | M22: =M21+K22-L22 -> 33578.176
A23: 20 | B23: 46254 | G23: =E23*F23 -> 0 | H23: 5 | I23: 110.74 | J23: =H23*I23 -> 553.7 | K23: =G23+J23 -> 553.7 | L23: 33000 | M23: 1123.8772 | N23: 0
A24: 21 | B24: 46255 | E24: 20 | F24: 98.68 | G24: =E24*F24 -> 1973.6 | H24: 5 | I24: 110.74 | J24: =H24*I24 -> 553.7 | K24: =G24+J24 -> 2527.3 | M24: =M23+K24-L24 -> 3651.1772
A25: 22 | B25: 46256 | G25: =E25*F25 -> 0 | J25: =H25*I25 -> 0 | K25: =G25+J25 -> 0 | M25: =M24+K25-L25 -> 3651.1772
A26: 23 | B26: 46257 | G26: =E26*F26 -> 0 | J26: =H26*I26 -> 0 | K26: =G26+J26 -> 0 | M26: =M25+K26-L26 -> 3651.1772
A27: 24 | B27: 46258 | E27: 48.33 | F27: 98.69 | G27: =E27*F27 -> 4769.6877 | J27: =H27*I27 -> 0 | K27: =G27+J27 -> 4769.6877 | M27: =M26+K27-L27 -> 8420.8649
A28: 25 | B28: 46259 | G28: =E28*F28 -> 0 | J28: =H28*I28 -> 0 | K28: =G28+J28 -> 0 | M28: =M27+K28-L28 -> 8420.8649
A29: 26 | B29: 46260 | E29: 150 | F29: 98.69 | G29: =F29*E29 -> 14803.5 | J29: =H29*I29 -> 0 | K29: =G29+J29 -> 14803.5 | M29: =M28+K29-L29 -> 23224.365
A30: 27 | B30: 46261 | E30: 5 | F30: 98.69 | G30: =E30*F30 -> 493.45 | H30: 5 | I30: 110.74 | J30: =H30*I30 -> 553.7 | K30: =G30+J30 -> 1047.15 | M30: =M29+K30-L30 -> 24271.515
A31: 28 | B31: 46262 | E31: 50 | F31: 98.69 | G31: =E31*F31 -> 4934.5 | J31: =H31*I31 -> 0 | K31: =G31+J31 -> 4934.5 | L31: 24271 | M31: =M30+K31-L31 -> 4935.0149
A32: 29 | B32: 46263 | E32: 180 | F32: 98.69 | G32: =F32*E32 -> 17764.2 | H32: 5 | I32: 110.74 | J32: =H32*I32 -> 553.7 | K32: =G32+J32 -> 18317.9 | M32: =M31+K32-L32 -> 23252.915
A33: 30 | B33: 46264 | E33: 140 | F33: 98.69 | G33: =F33*E33 -> 13816.6 | J33: =H33*I33 -> 0 | K33: =G33+J33 -> 13816.6 | M33: =M32+K33-L33 -> 37069.515
A34: 31 | B34: 46265 | E34: 47.82 | F34: 98.69 | G34: =F34*E34 -> 4719.3558 | J34: =H34*I34 -> 0 | K34: =G34+J34 -> 4719.3558 | M34: =M33+K34-L34 -> 41788.871
E35: =SUM(E4:E34) -> 865.03 | G35: =SUM(G4:G34) -> 85369.611 | H35: =SUM(H4:H34) -> 90 | J35: =SUM(J4:J34) -> 9966.6 | K35: =SUM(K4:K34) -> 95336.211 | L35: =SUM(L4:L34) -> 138271 | M35: =SUM(M4:M34) -> 891182.09

Sheet Munavali-2
A1: Shiri Shiva Petroluem
A2: S.No | B2: Date | C2: GRN No | D2: Ind No/Bill No | E2: Diesel (Lts) | F2: Price | G2: Amount | H2: Petrol (Lts) | I2: Price | J2: Amount | K2: Total amount | L2: Amount paid | M2: As on date | N2: Remarks
D3: Opening Balance | K3: 146708 | M3: 146708
A4: 1 | B4: 46235 | G4: =E4*F4 -> 0 | J4: =H4*I4 -> 0 | K4: =G4+J4 -> 0 | M4: =M3+K4-L4 -> 146708
A5: 2 | B5: 46236 | G5: =E5*F5 -> 0 | J5: =H5*I5 -> 0 | K5: =G5+J5 -> 0 | M5: =M4+K5-L5 -> 146708 | N5: HPCl
A6: 3 | B6: 46237 | G6: =E6*F6 -> 0 | J6: =H6*I6 -> 0 | K6: =G6+J6 -> 0 | M6: =M5+K6-L6 -> 146708
A7: 4 | B7: 46238 | E7: 800 | F7: 99.35 | G7: =E7*F7 -> 79480 | J7: =H7*I7 -> 0 | K7: =G7+J7 -> 79480 | M7: =M6+K7-L7 -> 226188
A8: 5 | B8: 46239 | G8: =E8*F8 -> 0 | J8: =H8*I8 -> 0 | K8: =G8+J8 -> 0 | M8: =M7+K8-L8 -> 226188
A9: 6 | B9: 46240 | G9: =E9*F9 -> 0 | J9: =H9*I9 -> 0 | K9: =G9+J9 -> 0 | M9: =M8+K9-L9 -> 226188
A10: 7 | B10: 46241 | G10: =E10*F10 -> 0 | J10: =H10*I10 -> 0 | K10: =G10+J10 -> 0 | M10: =M9+K10-L10 -> 226188
A11: 8 | B11: 46242 | E11: 800 | F11: 99.35 | G11: =E11*F11 -> 79480 | J11: =H11*I11 -> 0 | K11: =G11+J11 -> 79480 | M11: =M10+K11-L11 -> 305668
A12: 9 | B12: 46243 | G12: =E12*F12 -> 0 | J12: =H12*I12 -> 0 | K12: =G12+J12 -> 0 | M12: =M11+K12-L12 -> 305668
A13: 10 | B13: 46244 | G13: =E13*F13 -> 0 | J13: =H13*I13 -> 0 | K13: =G13+J13 -> 0 | M13: =M12+K13-L13 -> 305668
A14: 11 | B14: 46245 | G14: =E14*F14 -> 0 | J14: =H14*I14 -> 0 | K14: =G14+J14 -> 0 | M14: =M13+K14-L14 -> 305668
A15: 12 | B15: 46246 | G15: =E15*F15 -> 0 | J15: =H15*I15 -> 0 | K15: =G15+J15 -> 0 | M15: =M14+K15-L15 -> 305668
A16: 13 | B16: 46247 | E16: 1000 | F16: 99.35 | G16: =E16*F16 -> 99350 | J16: =H16*I16 -> 0 | K16: =G16+J16 -> 99350 | L16: 300000 | M16: =M15+K16-L16 -> 105018
A17: 14 | B17: 46248 | G17: =E17*F17 -> 0 | K17: =G17+J17 -> 0 | M17: =M16+K17-L17 -> 105018
A18: 15 | B18: 46249 | D18: 0 | G18: =E18*F18 -> 0 | J18: =H18*I18 -> 0 | K18: =G18+J18 -> 0 | M18: =M17+K18-L18 -> 105018
A19: 16 | B19: 46250 | G19: =E19*F19 -> 0 | J19: =H19*I19 -> 0 | K19: =G19+J19 -> 0 | M19: =M18+K19-L19 -> 105018
A20: 17 | B20: 46251 | G20: =E20*F20 -> 0 | J20: =H20*I20 -> 0 | K20: =G20+J20 -> 0 | M20: =M19+K20-L20 -> 105018
A21: 18 | B21: 46252 | G21: =E21*F21 -> 0 | J21: =H21*I21 -> 0 | K21: =G21+J21 -> 0 | M21: =M20+K21-L21 -> 105018
A22: 19 | B22: 46253 | G22: =E22*F22 -> 0 | J22: =H22*I22 -> 0 | K22: =G22+J22 -> 0 | M22: =M21+K22-L22 -> 105018
A23: 20 | B23: 46254 | E23: 800 | F23: 99.35 | G23: =E23*F23 -> 79480 | J23: 0 | K23: =G23+J23 -> 79480 | M23: =M22+K23-L23 -> 184498
A24: 21 | B24: 46255 | G24: =E24*F24 -> 0 | J24: =H24*I24 -> 0 | K24: =G24+J24 -> 0 | M24: =M23+K24-L24 -> 184498
A25: 22 | B25: 46256 | G25: =E25*F25 -> 0 | J25: =H25*I25 -> 0 | K25: =G25+J25 -> 0 | M25: =M24+K25-L25 -> 184498
A26: 23 | B26: 46257 | G26: =E26*F26 -> 0 | J26: =H26*I26 -> 0 | K26: =G26+J26 -> 0 | M26: =M25+K26-L26 -> 184498
A27: 24 | B27: 46258 | E27: 800 | F27: 99.35 | G27: =E27*F27 -> 79480 | H27: 30 | I27: 111.45 | J27: =H27*I27 -> 3343.5 | K27: =G27+J27 -> 82823.5 | M27: =M26+K27-L27 -> 267321.5
A28: 25 | B28: 46259 | G28: =E28*F28 -> 0 | J28: =H28*I28 -> 0 | K28: =G28+J28 -> 0 | M28: =M27+K28-L28 -> 267321.5
A29: 26 | B29: 46260 | G29: =E29*F29 -> 0 | J29: =H29*I29 -> 0 | K29: =G29+J29 -> 0 | M29: =M28+K29-L29 -> 267321.5
A30: 27 | B30: 46261 | G30: =E30*F30 -> 0 | J30: =H30*I30 -> 0 | K30: =G30+J30 -> 0 | M30: =M29+K30-L30 -> 267321.5
A31: 28 | B31: 46262 | G31: =E31*F31 -> 0 | J31: =H31*I31 -> 0 | K31: =G31+J31 -> 0 | M31: =M30+K31-L31 -> 267321.5
A32: 29 | B32: 46263 | E32: 800 | F32: 99.35 | G32: =E32*F32 -> 79480 | J32: =H32*I32 -> 0 | K32: =G32+J32 -> 79480 | M32: =M31+K32-L32 -> 346801.5
A33: 30 | B33: 46264 | G33: =E33*F33 -> 0 | J33: =H33*I33 -> 0 | K33: =G33+J33 -> 0 | M33: =M32+K33-L33 -> 346801.5 | S33: =120*111.45 -> 13374
A34: 31 | G34: =E34*F34 -> 0 | J34: =H34*I34 -> 0 | K34: =G34+J34 -> 0 | M34: =M33+K34-L34 -> 346801.5 | S34: 824605
A35: 32 | G35: =E35*F35 -> 0 | J35: =H35*I35 -> 0 | K35: =G35+J35 -> 0 | M35: =M34+K35-L35 -> 346801.5 | S35: =S34+S33 -> 837979
A36: 33 | G36: =E36*F36 -> 0 | J36: =H36*I36 -> 0 | K36: =G36+J36 -> 0 | M36: =M35+K36-L36 -> 346801.5
A37: 34 | G37: =E37*F37 -> 0 | J37: =H37*I37 -> 0 | K37: =G37+J37 -> 0 | M37: =M36+K37-L37 -> 346801.5
A38: 35 | G38: =E38*F38 -> 0 | J38: =H38*I38 -> 0 | K38: =G38+J38 -> 0 | M38: =M37+K38-L38 -> 346801.5
A39: 36 | G39: =E39*F39 -> 0 | J39: =H39*I39 -> 0 | K39: =G39+J39 -> 0 | M39: =M38+K39-L39 -> 346801.5
E40: =SUM(E4:E39) -> 5000 | G40: =SUM(G4:G39) -> 496750 | H40: =SUM(H4:H39) -> 30 | J40: =SUM(J4:J39) -> 3343.5 | K40: =SUM(K4:K39) -> 500093.5 | L40: =SUM(L4:L39) -> 300000

Sheet  Munavali
A1: DANESHWARI PETROLIUM(YERRAGATTI)
A2: S.No | B2: Date | C2: GRN No | D2: Ind No/Bill No | E2: Diesel (Lts) | F2: Price | G2: Amount | H2: Petrol (Lts) | I2: Price | J2: Amount | K2: Total amount | L2: Amount paid | M2: As on date | N2: Remarks
D3: Opening Balance | K3: 274277.22 | M3: 274277.22
A4: 1 | B4: 46235 | G4: =E4*F4 -> 0 | J4: =H4*I4 -> 0 | K4: =G4+J4 -> 0 | M4: =M3+K4-L4 -> 274277.22
A5: 2 | B5: 46236 | G5: =E5*F5 -> 0 | J5: =H5*I5 -> 0 | K5: =G5+J5 -> 0 | M5: =M4+K5-L5 -> 274277.22 | N5: HPCl
A6: 3 | B6: 46237 | G6: =E6*F6 -> 0 | J6: =H6*I6 -> 0 | K6: =G6+J6 -> 0 | M6: =M5+K6-L6 -> 274277.22
A7: 4 | B7: 46238 | G7: =E7*F7 -> 0 | H7: 30 | I7: 111.21 | J7: =H7*I7 -> 3336.3 | K7: =G7+J7 -> 3336.3 | M7: =M6+K7-L7 -> 277613.52
A8: 5 | B8: 46239 | G8: =E8*F8 -> 0 | J8: =H8*I8 -> 0 | K8: =G8+J8 -> 0 | M8: =M7+K8-L8 -> 277613.52
A9: 6 | B9: 46240 | G9: =E9*F9 -> 0 | H9: 30 | I9: 111.21 | J9: =H9*I9 -> 3336.3 | K9: =G9+J9 -> 3336.3 | M9: =M8+K9-L9 -> 280949.82
A10: 7 | B10: 46241 | G10: =E10*F10 -> 0 | J10: =H10*I10 -> 0 | K10: =G10+J10 -> 0 | M10: =M9+K10-L10 -> 280949.82
A11: 8 | B11: 46242 | G11: =E11*F11 -> 0 | H11: 30 | I11: 111.21 | J11: =H11*I11 -> 3336.3 | K11: =G11+J11 -> 3336.3 | M11: =M10+K11-L11 -> 284286.12
A12: 9 | B12: 46243 | G12: =E12*F12 -> 0 | J12: =H12*I12 -> 0 | K12: =G12+J12 -> 0 | M12: =M11+K12-L12 -> 284286.12
A13: 10 | B13: 46244 | G13: =E13*F13 -> 0 | J13: =H13*I13 -> 0 | K13: =G13+J13 -> 0 | M13: =M12+K13-L13 -> 284286.12
A14: 11 | B14: 46245 | G14: =E14*F14 -> 0 | J14: =H14*I14 -> 0 | K14: =G14+J14 -> 0 | M14: =M13+K14-L14 -> 284286.12
A15: 12 | B15: 46246 | G15: =E15*F15 -> 0 | H15: 30 | I15: 111.21 | J15: =H15*I15 -> 3336.3 | K15: =G15+J15 -> 3336.3 | M15: =M14+K15-L15 -> 287622.42
A16: 13 | B16: 46247 | E16: 200 | F16: 99.13 | G16: =E16*F16 -> 19826 | I16: 111.21 | J16: =H16*I16 -> 0 | K16: =G16+J16 -> 19826 | M16: =M15+K16-L16 -> 307448.42
A17: 14 | B17: 46248 | G17: =E17*F17 -> 0 | J17: =H17*I17 -> 0 | K17: =G17+J17 -> 0 | M17: =M16+K17-L17 -> 307448.42
A18: 15 | B18: 46249 | D18: 0 | G18: =E18*F18 -> 0 | J18: =H18*I18 -> 0 | K18: =G18+J18 -> 0 | M18: =M17+K18-L18 -> 307448.42
A19: 16 | B19: 46250 | G19: =E19*F19 -> 0 | J19: =H19*I19 -> 0 | K19: =G19+J19 -> 0 | M19: =M18+K19-L19 -> 307448.42
A20: 17 | B20: 46251 | G20: =E20*F20 -> 0 | H20: 37.31 | I20: 111.21 | J20: =H20*I20 -> 4149.2451 | K20: =G20+J20 -> 4149.2451 | M20: =M19+K20-L20 -> 311597.67
A21: 18 | B21: 46252 | G21: =E21*F21 -> 0 | J21: =H21*I21 -> 0 | K21: =G21+J21 -> 0 | M21: =M20+K21-L21 -> 311597.67
A22: 19 | B22: 46253 | G22: =E22*F22 -> 0 | J22: =H22*I22 -> 0 | K22: =G22+J22 -> 0 | M22: =M21+K22-L22 -> 311597.67
A23: 20 | B23: 46254 | G23: =E23*F23 -> 0 | H23: 30 | I23: 111.21 | J23: =H23*I23 -> 3336.3 | K23: =G23+J23 -> 3336.3 | M23: =M22+K23-L23 -> 314933.97
A24: 22 | B24: 46255 | G24: =E24*F24 -> 0 | J24: =H24*I24 -> 0 | K24: =G24+J24 -> 0 | M24: =M23+K24-L24 -> 314933.97
A25: 23 | B25: 46256 | G25: =E25*F25 -> 0 | J25: =H25*I25 -> 0 | K25: =G25+J25 -> 0 | M25: =M24+K25-L25 -> 314933.97
A26: 24 | B26: 46257 | G26: =E26*F26 -> 0 | J26: =H26*I26 -> 0 | K26: =G26+J26 -> 0 | M26: =M25+K26-L26 -> 314933.97
A27: 25 | B27: 46258 | G27: =E27*F27 -> 0 | J27: =H27*I27 -> 0 | K27: =G27+J27 -> 0 | M27: =M26+K27-L27 -> 314933.97
A28: 26 | B28: 46259 | G28: =E28*F28 -> 0 | J28: =H28*I28 -> 0 | K28: =G28+J28 -> 0 | M28: =M27+K28-L28 -> 314933.97
A29: 27 | B29: 46260 | G29: =E29*F29 -> 0 | J29: =H29*I29 -> 0 | K29: =G29+J29 -> 0 | M29: =M28+K29-L29 -> 314933.97
A30: 28 | B30: 46261 | G30: =E30*F30 -> 0 | H30: 30 | I30: 111.21 | J30: =H30*I30 -> 3336.3 | K30: =G30+J30 -> 3336.3 | M30: =M29+K30-L30 -> 318270.27
A31: 29 | B31: 46262 | G31: =E31*F31 -> 0 | J31: =H31*I31 -> 0 | K31: =G31+J31 -> 0 | L31: 317605 | M31: =M30+K31-L31 -> 665.2699 | Q31: 166834
A32: 30 | B32: 46263 | G32: =E32*F32 -> 0 | J32: =H32*I32 -> 0 | K32: =G32+J32 -> 0 | M32: =M31+K32-L32 -> 665.2699
A33: 31 | B33: 46264 | G33: =E33*F33 -> 0 | J33: =H33*I33 -> 0 | K33: =G33+J33 -> 0 | M33: =M32+K33-L33 -> 665.2699
A34: 32 | B34: 46265 | G34: =E34*F34 -> 0 | J34: =H34*I34 -> 0 | K34: =G34+J34 -> 0 | M34: =M33+K34-L34 -> 665.2699
A35: 33 | G35: =E35*F35 -> 0 | J35: =H35*I35 -> 0 | K35: =G35+J35 -> 0 | M35: =M34+K35-L35 -> 665.2699
A36: 34 | G36: =E36*F36 -> 0 | J36: =H36*I36 -> 0 | K36: =G36+J36 -> 0 | M36: =M35+K36-L36 -> 665.2699
A37: 35 | G37: =E37*F37 -> 0 | J37: =H37*I37 -> 0 | K37: =G37+J37 -> 0 | M37: =M36+K37-L37 -> 665.2699
A38: 36 | G38: =E38*F38 -> 0 | J38: =H38*I38 -> 0 | K38: =G38+J38 -> 0 | M38: =M37+K38-L38 -> 665.2699
E39: =SUM(E4:E38) -> 200 | G39: =SUM(G4:G38) -> 19826 | H39: =SUM(H4:H38) -> 217.31 | J39: =SUM(J4:J38) -> 24167.045 | K39: =SUM(K4:K38) -> 43993.045 | L39: =SUM(L4:L38) -> 317605

Sheet Borgaon
A1: Aadisagar Petrolium
A2: S.No | B2: Date | C2: GRN No | D2: Ind no/Bill No | E2: Diesel (Lts) | F2: Price | G2: Amount | H2: Petrol (Lts) | I2: Price | J2: Amount | K2: Total amount | L2: Amount paid | M2: As on Date | N2: Remarks
A3: Opening Balance | K3: 208.3907 | M3: 208.3907
A4: 1 | B4: 46235 | G4: =E4*F4 -> 0 | J4: =H4*I4 -> 0 | K4: =G4+J4 -> 0 | L4: 208.39 | M4: =M3+K4-L4 -> 0.00069999999 | N4: Roundoff
A5: 2 | B5: 46236 | G5: =E5*F5 -> 0 | J5: =H5*I5 -> 0 | K5: =G5+J5 -> 0 | M5: =M4+K5-L5 -> 0.00069999999
A6: 3 | B6: 46237 | G6: =E6*F6 -> 0 | J6: =H6*I6 -> 0 | K6: =G6+J6 -> 0 | M6: =M5+K6-L6 -> 0.00069999999
A7: 4 | B7: 46238 | G7: =E7*F7 -> 0 | J7: =H7*I7 -> 0 | K7: =G7+J7 -> 0 | M7: =M6+K7-L7 -> 0.00069999999
A8: 5 | B8: 46239 | G8: =E8*F8 -> 0 | J8: =H8*I8 -> 0 | K8: =G8+J8 -> 0 | M8: =M7+K8-L8 -> 0.00069999999
A9: 6 | B9: 46240 | G9: =E9*F9 -> 0 | J9: =H9*I9 -> 0 | K9: =G9+J9 -> 0 | M9: =M8+K9-L9 -> 0.00069999999
A10: 7 | B10: 46241 | G10: =E10*F10 -> 0 | J10: =H10*I10 -> 0 | K10: =G10+J10 -> 0 | M10: =M9+K10-L10 -> 0.00069999999
A11: 8 | B11: 46242 | G11: =E11*F11 -> 0 | J11: =H11*I11 -> 0 | K11: =G11+J11 -> 0 | M11: =M10+K11-L11 -> 0.00069999999
A12: 9 | B12: 46243 | G12: =E12*F12 -> 0 | J12: =H12*I12 -> 0 | K12: =G12+J12 -> 0 | M12: =M11+K12-L12 -> 0.00069999999
A13: 10 | B13: 46244 | G13: =E13*F13 -> 0 | J13: =H13*I13 -> 0 | K13: =G13+J13 -> 0 | M13: =M12+K13-L13 -> 0.00069999999
A14: 11 | B14: 46245 | G14: =E14*F14 -> 0 | J14: =H14*I14 -> 0 | K14: =G14+J14 -> 0 | M14: =M13+K14-L14 -> 0.00069999999
A15: 12 | B15: 46246 | G15: =E15*F15 -> 0 | J15: =H15*I15 -> 0 | K15: =G15+J15 -> 0 | M15: =M14+K15-L15 -> 0.00069999999
A16: 13 | B16: 46247 | G16: =E16*F16 -> 0 | J16: =H16*I16 -> 0 | K16: =G16+J16 -> 0 | M16: =M15+K16-L16 -> 0.00069999999
... A25: 22 | B25: 46256 | G25: =E25*F25 -> 0 | J25: =H25*I25 -> 0 | K25: =G25+J25 -> 0 | M25: =M24+K25-L25 -> 0.00069999999
A26: 23 | B26: 46257 | G26: =E26*F26 -> 0 | J26: =H26*I26 -> 0 | K26: =G26+J26 -> 0 | M26: =M25+K26-L26 -> 0.00069999999 | Q26: d
A27: 24 | B27: 46258 | G27: =E27*F27 -> 0 | J27: =H27*I27 -> 0 | K27: =G27+J27 -> 0 | M27: =M26+K27-L27 -> 0.00069999999 | Q27: 30 | R27: 50
A28: 25 | B28: 46259 | G28: =E28*F28 -> 0 | J28: =H28*I28 -> 0 | K28: =G28+J28 -> 0 | M28: =M27+K28-L28 -> 0.00069999999 | Q28: 50 | R28: 4.51
A29: 26 | B29: 46260 | G29: =E29*F29 -> 0 | J29: =H29*I29 -> 0 | K29: =G29+J29 -> 0 | M29: =M28+K29-L29 -> 0.00069999999
A30: 27 | B30: 46261 | G30: =E30*F30 -> 0 | J30: =H30*I30 -> 0 | K30: =G30+J30 -> 0 | M30: =M29+K30-L30 -> 0.00069999999
A31: 28 | B31: 46262 | G31: =E31*F31 -> 0 | J31: =H31*I31 -> 0 | K31: =G31+J31 -> 0 | M31: =M30+K31-L31 -> 0.00069999999
A32: 29 | B32: 46263 | G32: =E32*F32 -> 0 | J32: =H32*I32 -> 0 | K32: =G32+J32 -> 0 | M32: =M31+K32-L32 -> 0.00069999999
A33: 30 | B33: 46264 | G33: =E33*F33 -> 0 | J33: =H33*I33 -> 0 | K33: =G33+J33 -> 0 | M33: =M32+K33-L33 -> 0.00069999999
A34: 31 | G34: =E34*F34 -> 0 | J34: =H34*I34 -> 0 | K34: =G34+J34 -> 0 | M34: =M33+K34-L34 -> 0.00069999999
E35: =SUM(E4:E34) -> 0 | G35: =SUM(G4:G34) -> 0 | H35: =SUM(H4:H34) -> 0 | J35: =SUM(J4:J34) -> 0 | K35: =SUM(K4:K34) -> 0 | L35: =SUM(L4:L34) -> 208.39

Sheet Ugar,Khagwad,Kudichi
A1: Shiri Bhrhmanath Petrolium
A2: S.No | B2: Date | C2: GRN No | D2: Ind No/Bill No | E2: Diesel (Lts) | F2: Price | G2: Amount | H2: Petrol (Lts) | I2: Price | J2: Amount | K2: Total amount | L2: Amount paid | M2: As on Date | N2: Remarks
A3: Opening Balance | K3: 342020.48 | L3: 0 | M3: 342020.48
A4: 1 | B4: 46235 | G4: =E4*F4 -> 0 | J4: =H4*I4 -> 0 | K4: =G4+J4 -> 0 | L4: 0 | M4: =M3+K4-L4 -> 342020.48
A5: 2 | B5: 46236 | G5: =E5*F5 -> 0 | J5: =H5*I5 -> 0 | K5: =G5+J5 -> 0 | L5: 0 | M5: =M4+K5-L5 -> 342020.48
A6: 3 | B6: 46237 | G6: =E6*F6 -> 0 | J6: =H6*I6 -> 0 | K6: =G6+J6 -> 0 | M6: =M5+K6-L6 -> 342020.48
A7: 4 | B7: 46238 | G7: =E7*F7 -> 0 | J7: =H7*I7 -> 0 | K7: =G7+J7 -> 0 | M7: =M6+K7-L7 -> 342020.48
A8: 5 | B8: 46239 | G8: =E8*F8 -> 0 | J8: =H8*I8 -> 0 | K8: =G8+J8 -> 0 | M8: =M7+K8-L8 -> 342020.48 | R8: 1690
A9: 6 | B9: 46240 | G9: =E9*F9 -> 0 | J9: =H9*I9 -> 0 | K9: =G9+J9 -> 0 | L9: 342000 | M9: =M8+K9-L9 -> 20.4757
A10: 7 | B10: 46241 | E10: 240 | F10: 99.74 | G10: =E10*F10 -> 23937.6 | H10: 40 | I10: 111.86 | J10: =H10*I10 -> 4474.4 | K10: =G10+J10 -> 28412 | L10: 3915.1 | M10: =M9+K10-L10 -> 24517.376 | N10: Card Payment
A11: 8 | B11: 46242 | E11: 500 | F11: 99.74 | G11: =E11*F11 -> 49870 | J11: =H11*I11 -> 0 | K11: =G11+J11 -> 49870 | M11: =M10+K11-L11 -> 74387.376
A12: 9 | B12: 46243 | E12: 60 | F12: 99.74 | G12: =E12*F12 -> 5984.4 | J12: =H12*I12 -> 0 | K12: =G12+J12 -> 5984.4 | M12: =M11+K12-L12 -> 80371.776
A13: 10 | B13: 46244 | E13: 555 | F13: 99.74 | G13: =E13*F13 -> 55355.7 | H13: 41 | I13: 111.85 | J13: =H13*I13 -> 4585.85 | K13: =G13+J13 -> 59941.55 | M13: =M12+K13-L13 -> 140313.33
A14: 11 | B14: 46245 | G14: =E14*F14 -> 0 | J14: =H14*I14 -> 0 | K14: =G14+J14 -> 0 | M14: =M13+K14-L14 -> 140313.33
A15: 12 | B15: 46246 | E15: 620 | F15: 99.74 | G15: =E15*F15 -> 61838.8 | H15: 35 | I15: 111.85 | J15: =H15*I15 -> 3914.75 | K15: =G15+J15 -> 65753.55 | M15: =M14+K15-L15 -> 206066.88
A16: 13 | B16: 46247 | E16: 624 | F16: 99.74 | G16: =E16*F16 -> 62237.76 | J16: =H16*I16 -> 0 | K16: =G16+J16 -> 62237.76 | L16: 206049.92 | M16: =M15+K16-L16 -> 62254.716
A17: 14 | B17: 46248 | E17: 670 | F17: 99.74 | G17: =E17*F17 -> 66825.8 | H17: 35 | I17: 111.85 | J17: =H17*I17 -> 3914.75 | K17: =G17+J17 -> 70740.55 | M17: =M16+K17-L17 -> 132995.27
A18: 15 | B18: 46249 | E18: 65 | F18: 99.74 | G18: =E18*F18 -> 6483.1 | J18: =H18*I18 -> 0 | K18: =G18+J18 -> 6483.1 | M18: =M17+K18-L18 -> 139478.37
A19: 16 | B19: 46250 | G19: =E19*F19 -> 0 | J19: =H19*I19 -> 0 | K19: =G19+J19 -> 0 | M19: =M18+K19-L19 -> 139478.37
A20: 17 | B20: 46251 | E20: 130 | F20: 99.74 | G20: =E20*F20 -> 12966.2 | J20: =H20*I20 -> 0 | K20: =G20+J20 -> 12966.2 | M20: =M19+K20-L20 -> 152444.57
A21: 18 | B21: 46252 | E21: 480 | F21: 99.74 | G21: =E21*F21 -> 47875.2 | H21: 15 | I21: 121.27 | J21: =H21*I21 -> 1819.05 | K21: =G21+J21 -> 49694.25 | M21: =M20+K21-L21 -> 202138.82
A22: 19 | B22: 46253 | E22: 30 | F22: 99.74 | G22: =E22*F22 -> 2992.2 | I22: 111.85 | J22: =H22*I22 -> 0 | K22: =G22+J22 -> 2992.2 | M22: =M21+K22-L22 -> 205131.02
A23: 20 | B23: 46254 | E23: 635 | F23: 99.74 | G23: =E23*F23 -> 63334.9 | J23: =H23*I23 -> 0 | K23: =G23+J23 -> 63334.9 | M23: =M22+K23-L23 -> 268465.92
A24: 21 | B24: 46255 | E24: 70 | F24: 99.74 | G24: =E24*F24 -> 6981.8 | H24: 35 | I24: 111.85 | J24: =H24*I24 -> 3914.75 | K24: =G24+J24 -> 10896.55 | L24: 0 | M24: =M23+K24-L24 -> 279362.47
A25: 22 | B25: 46256 | E25: 200 | F25: 99.74 | G25: =E25*F25 -> 19948 | J25: =H25*I25 -> 0 | K25: =G25+J25 -> 19948 | L25: 0 | M25: =M24+K25-L25 -> 299310.47
A26: 23 | B26: 46257 | E26: 400 | F26: 99.74 | G26: =E26*F26 -> 39896 | J26: =H26*I26 -> 0 | K26: =G26+J26 -> 39896 | L26: 0 | M26: =M25+K26-L26 -> 339206.47
A27: 24 | B27: 46258 | E27: 360 | F27: 99.74 | G27: =E27*F27 -> 35906.4 | H27: 20 | I27: 111.85 | J27: =H27*I27 -> 2237 | K27: =G27+J27 -> 38143.4 | L27: 0 | M27: =M26+K27-L27 -> 377349.87
A28: 25 | B28: 46259 | E28: 200 | F28: 99.74 | G28: =E28*F28 -> 19948 | J28: =H28*I28 -> 0 | K28: =G28+J28 -> 19948 | L28: 0 | M28: =M27+K28-L28 -> 397297.87
A29: 26 | B29: 46260 | E29: 735 | F29: 99.74 | G29: =E29*F29 -> 73308.9 | H29: 35 | I29: 111.85 | J29: =H29*I29 -> 3914.75 | K29: =G29+J29 -> 77223.65 | L29: 0 | M29: =M28+K29-L29 -> 474521.52
A30: 27 | B30: 46261 | E30: 100 | F30: 99.74 | G30: =E30*F30 -> 9974 | J30: =H30*I30 -> 0 | K30: =G30+J30 -> 9974 | L30: 0 | M30: =M29+K30-L30 -> 484495.52
A31: 28 | B31: 46262 | G31: =E31*F31 -> 0 | H31: 6 | I31: 111.85 | J31: =H31*I31 -> 671.1 | K31: =G31+J31 -> 671.1 | L31: 0 | M31: =M30+K31-L31 -> 485166.62
A32: 29 | B32: 46263 | E32: 435 | F32: 99.74 | G32: =E32*F32 -> 43386.9 | J32: =H32*I32 -> 0 | K32: =G32+J32 -> 43386.9 | L32: 0 | M32: =M31+K32-L32 -> 528553.52 | P32: =600*99.73 -> 59838
A33: 30 | B33: 46264 | E33: 475 | F33: 99.74 | G33: =E33*F33 -> 47376.5 | H33: 35 | I33: 111.85 | J33: =H33*I33 -> 3914.75 | K33: =G33+J33 -> 51291.25 | L33: 0 | M33: =M32+K33-L33 -> 579844.77
A34: 31 | B34: 46265 | E34: 40 | F34: 99.74 | G34: =E34*F34 -> 3989.6 | J34: =H34*I34 -> 0 | K34: =G34+J34 -> 3989.6 | L34: 0 | M34: =M33+K34-L34 -> 583834.37
A35: 32 | G35: =E35*F35 -> 0 | J35: =H35*I35 -> 0 | K35: =G35+J35 -> 0 | L35: 0 | M35: =M34+K35-L35 -> 583834.37
A36: 33 | G36: =E36*F36 -> 0 | J36: =H36*I36 -> 0 | K36: =G36+J36 -> 0 | L36: 0 | M36: =M35+K36-L36 -> 583834.37
E37: =SUM(E4:E36) -> 7624 | G37: =SUM(G4:G36) -> 760417.76 | H37: =SUM(H4:H36) -> 297 | J37: =SUM(J4:J36) -> 33361.15 | K37: =SUM(K4:K36) -> 793778.91 | L37: =SUM(L4:L36) -> 551965.02

Sheet shedbal
A1: VARAD PETROLEUM SHEDBAL
A2: S.No | B2: Date | C2: GRN No | D2: Ind no/Bill No | E2: Diesel (Lts) | F2: Price | G2: Amount | H2: Petrol (Lts) | I2: Price | J2: Amount | K2: Total amount | L2: Amount paid | M2: As on Date | N2: Remarks
A3: Opening Balance | K3: 506281.15 | M3: 506281.15
A4: 1 | B4: 46235 | E4: 140.5 | F4: 99.73 | G4: =E4*F4 -> 14012.065 | J4: =H4*I4 -> 0 | K4: =G4+J4 -> 14012.065 | M4: =M3+K4-L4 -> 520293.22
A5: 2 | B5: 46236 | E5: 200 | F5: 99.73 | G5: =E5*F5 -> 19946 | H5: 35 | I5: 111.85 | J5: =H5*I5 -> 3914.75 | K5: =G5+J5 -> 23860.75 | M5: =M4+K5-L5 -> 544153.97
A6: 3 | B6: 46237 | E6: 550 | F6: 99.73 | G6: =E6*F6 -> 54851.5 | H6: 5 | I6: 111.85 | J6: =H6*I6 -> 559.25 | K6: =G6+J6 -> 55410.75 | M6: =M5+K6-L6 -> 599564.72
A7: 4 | B7: 46238 | E7: 100 | F7: 99.73 | G7: =E7*F7 -> 9973 | H7: 12 | I7: 111.85 | J7: =H7*I7 -> 1342.2 | K7: =G7+J7 -> 11315.2 | M7: =M6+K7-L7 -> 610879.92
A8: 5 | B8: 46239 | E8: 710 | F8: 99.73 | G8: =E8*F8 -> 70808.3 | H8: 35 | I8: 111.85 | J8: =H8*I8 -> 3914.75 | K8: =G8+J8 -> 74723.05 | M8: =M7+K8-L8 -> 685602.97
A9: 6 | B9: 46240 | E9: 100 | F9: 99.73 | G9: =E9*F9 -> 9973 | H9: 8 | I9: 111.85 | J9: =H9*I9 -> 894.8 | K9: =G9+J9 -> 10867.8 | M9: =M8+K9-L9 -> 696470.77
A10: 7 | B10: 46241 | E10: 30 | F10: 99.73 | G10: =E10*F10 -> 2991.9 | J10: =H10*I10 -> 0 | K10: =G10+J10 -> 2991.9 | M10: =M9+K10-L10 -> 699462.67
A11: 8 | B11: 46242 | G11: =E11*F11 -> 0 | J11: =H11*I11 -> 0 | K11: =G11+J11 -> 0 | M11: =M10+K11-L11 -> 699462.67
A12: 9 | B12: 46243 | G12: =E12*F12 -> 0 | J12: =H12*I12 -> 0 | K12: =G12+J12 -> 0 | M12: =M11+K12-L12 -> 699462.67
A13: 10 | B13: 46244 | E13: 35 | F13: 99.73 | G13: =E13*F13 -> 3490.55 | J13: =H13*I13 -> 0 | K13: =G13+J13 -> 3490.55 | M13: =M12+K13-L13 -> 702953.22
A14: 11 | B14: 46245 | G14: =E14*F14 -> 0 | J14: =H14*I14 -> 0 | K14: =G14+J14 -> 0 | M14: =M13+K14-L14 -> 702953.22
A15: 12 | B15: 46246 | G15: =E15*F15 -> 0 | J15: =H15*I15 -> 0 | K15: =G15+J15 -> 0 | M15: =M14+K15-L15 -> 702953.22
A16: 13 | B16: 46247 | G16: =E16*F16 -> 0 | J16: =H16*I16 -> 0 | K16: =G16+J16 -> 0 | L16: 700000 | M16: =M15+K16-L16 -> 2953.215
A17: 14 | B17: 46248 | G17: =E17*F17 -> 0 | J17: =H17*I17 -> 0 | K17: =G17+J17 -> 0 | M17: =M16+K17-L17 -> 2953.215
A18: 15 | B18: 46249 | G18: =E18*F18 -> 0 | J18: =H18*I18 -> 0 | K18: =G18+J18 -> 0 | M18: =M17+K18-L18 -> 2953.215
A19: 16 | B19: 46250 | G19: =E19*F19 -> 0 | J19: =H19*I19 -> 0 | K19: =G19+J19 -> 0 | M19: =M18+K19-L19 -> 2953.215
A20: 17 | B20: 46251 | G20: =E20*F20 -> 0 | J20: =H20*I20 -> 0 | K20: =G20+J20 -> 0 | M20: =M19+K20-L20 -> 2953.215
A21: 18 | B21: 46252 | G21: =E21*F21 -> 0 | J21: =H21*I21 -> 0 | K21: =G21+J21 -> 0 | M21: =M20+K21-L21 -> 2953.215
A22: 19 | B22: 46253 | G22: =E22*F22 -> 0 | H22: 40 | I22: 111.85 | J22: =H22*I22 -> 4474 | K22: =G22+J22 -> 4474 | M22: =M21+K22-L22 -> 7427.215
A23: 20 | B23: 46254 | E23: 350 | F23: 99.73 | G23: =E23*F23 -> 34905.5 | J23: =H23*I23 -> 0 | K23: =G23+J23 -> 34905.5 | M23: =M22+K23-L23 -> 42332.715
A24: 21 | B24: 46255 | E24: 100 | F24: 99.73 | G24: =E24*F24 -> 9973 | H24: 12 | I24: 111.85 | J24: =H24*I24 -> 1342.2 | K24: =G24+J24 -> 11315.2 | M24: =M23+K24-L24 -> 53647.915
A25: 22 | B25: 46256 | G25: =E25*F25 -> 0 | J25: =H25*I25 -> 0 | K25: =G25+J25 -> 0 | M25: =M24+K25-L25 -> 53647.915
A26: 23 | B26: 46257 | G26: =E26*F26 -> 0 | J26: =H26*I26 -> 0 | K26: =G26+J26 -> 0 | M26: =M25+K26-L26 -> 53647.915
A27: 24 | B27: 46258 | E27: 100 | F27: 99.73 | G27: =E27*F27 -> 9973 | J27: =H27*I27 -> 0 | K27: =G27+J27 -> 9973 | M27: =M26+K27-L27 -> 63620.915
A28: 25 | B28: 46259 | G28: =E28*F28 -> 0 | H28: 5 | I28: 111.85 | J28: =H28*I28 -> 559.25 | K28: =G28+J28 -> 559.25 | M28: =M27+K28-L28 -> 64180.165 | Q28: d
A29: 26 | B29: 46260 | E29: 540 | F29: 99.73 | G29: =E29*F29 -> 53854.2 | J29: =H29*I29 -> 0 | K29: =G29+J29 -> 53854.2 | M29: =M28+K29-L29 -> 118034.37 | Q29: 30 | R29: 50
A30: 27 | B30: 46261 | E30: 47.63 | F30: 99.73 | G30: =E30*F30 -> 4750.1399 | H30: 0 | I30: 111.85 | J30: =H30*I30 -> 0 | K30: =G30+J30 -> 4750.1399 | M30: =M29+K30-L30 -> 122784.5 | Q30: 50 | R30: 4.51
A31: 28 | B31: 46262 | G31: =E31*F31 -> 0 | H31: 40 | I31: 111.85 | J31: =H31*I31 -> 4474 | K31: =G31+J31 -> 4474 | M31: =M30+K31-L31 -> 127258.5
B32: 46262 | E32: 40.05 | F32: 99.1 | G32: =E32*F32 -> 3968.955 | K32: =G32+J32 -> 3968.955 | L32: 3968.955 | M32: =M31+K32-L32 -> 127258.5
A33: 29 | B33: 46263 | E33: 435 | F33: 99.73 | G33: =E33*F33 -> 43382.55 | J33: =H33*I33 -> 0 | K33: =G33+J33 -> 43382.55 | M33: =M32+K33-L33 -> 170641.05
A34: 30 | B34: 46264 | G34: =E34*F34 -> 0 | J34: =H34*I34 -> 0 | K34: =G34+J34 -> 0 | M34: =M33+K34-L34 -> 170641.05
A35: 31 | B35: 46265 | G35: =E35*F35 -> 0 | J35: =H35*I35 -> 0 | K35: =G35+J35 -> 0 | M35: =M34+K35-L35 -> 170641.05
A36: 32 | B36: 46266 | G36: =E36*F36 -> 0 | J36: =H36*I36 -> 0 | K36: =G36+J36 -> 0 | M36: =M35+K36-L36 -> 170641.05
A37: 33 | B37: 46267 | G37: =E37*F37 -> 0 | J37: =H37*I37 -> 0 | K37: =G37+J37 -> 0 | M37: =M36+K37-L37 -> 170641.05
E38: =SUM(E4:E37) -> 3478.18 | G38: =SUM(G4:G37) -> 346853.66 | H38: =SUM(H4:H37) -> 192 | J38: =SUM(J4:J37) -> 21475.2 | K38: =SUM(K4:K37) -> 368328.86 | L38: =SUM(L4:L37) -> 703968.95

Sheet Kabbur
A1: Shri Jai Hanuman Petrolium
A2: S.No | B2: Date | C2: GRN No | D2: Ind no/Bill No | E2: Diesel (Lts) | F2: Price | G2: Amount | H2: Petrol (Lts) | I2: Price | J2: Amount | K2: Total amount | L2: Amount paid | M2: As on Date | N2: Remarks
A3: Opening Balance | K3: 0 | M3: =+K3 -> 0
A4: 1 | B4: 46235 | G4: =E4*F4 -> 0 | J4: =H4*I4 -> 0 | K4: =G4+J4 -> 0 | L4: =+K4 -> 0
A5: 2 | B5: 46236 | G5: =E5*F5 -> 0 | J5: =H5*I5 -> 0 | K5: =G5+J5 -> 0 | L5: =+K5 -> 0
A6: 3 | B6: 46237 | E6: 50 | F6: 99.41 | G6: =E6*F6 -> 4970.5 | J6: =H6*I6 -> 0 | K6: =G6+J6 -> 4970.5 | L6: =+K6 -> 4970.5
A7: 4 | B7: 46238 | G7: =E7*F7 -> 0 | J7: =H7*I7 -> 0 | K7: =G7+J7 -> 0 | L7: =+K7 -> 0
A8: 5 | B8: 46239 | G8: =E8*F8 -> 0 | J8: =H8*I8 -> 0 | K8: =G8+J8 -> 0 | L8: =+K8 -> 0
A9: 6 | B9: 46240 | E9: 100 | F9: 99.41 | G9: =E9*F9 -> 9941 | J9: =H9*I9 -> 0 | K9: =G9+J9 -> 9941 | L9: =+K9 -> 9941
A10: 7 | B10: 46241 | G10: =E10*F10 -> 0 | J10: =H10*I10 -> 0 | K10: =G10+J10 -> 0 | L10: =+K10 -> 0
A11: 8 | B11: 46242 | E11: 100 | F11: 99.41 | G11: =E11*F11 -> 9941 | H11: 7.53 | I11: 111.51 | J11: =H11*I11 -> 839.6703 | K11: =G11+J11 -> 10780.67 | L11: =+K11 -> 10780.67
A12: 9 | B12: 46243 | E12: 2 | F12: 99.41 | G12: =E12*F12 -> 198.82 | J12: =H12*I12 -> 0 | K12: =G12+J12 -> 198.82 | L12: =+K12 -> 198.82
A13: 10 | B13: 46244 | G13: =E13*F13 -> 0 | J13: =H13*I13 -> 0 | K13: =G13+J13 -> 0 | L13: =+K13 -> 0
A14: 11 | B14: 46245 | E14: 100 | F14: 99.41 | G14: =E14*F14 -> 9941 | J14: =H14*I14 -> 0 | K14: =G14+J14 -> 9941 | L14: =+K14 -> 9941
A15: 12 | B15: 46246 | G15: =E15*F15 -> 0 | J15: =H15*I15 -> 0 | K15: =G15+J15 -> 0 | L15: =+K15 -> 0
A16: 13 | B16: 46247 | G16: =E16*F16 -> 0 | J16: =H16*I16 -> 0 | K16: =G16+J16 -> 0 | L16: =+K16 -> 0
A17: 14 | B17: 46248 | G17: =E17*F17 -> 0 | J17: =H17*I17 -> 0 | K17: =G17+J17 -> 0 | L17: =+K17 -> 0
A18: 15 | B18: 46249 | G18: =E18*F18 -> 0 | J18: =H18*I18 -> 0 | K18: =G18+J18 -> 0 | L18: =+K18 -> 0
A19: 16 | B19: 46250 | G19: =E19*F19 -> 0 | J19: =H19*I19 -> 0 | K19: =G19+J19 -> 0 | L19: =+K19 -> 0
A20: 17 | B20: 46251 | G20: =E20*F20 -> 0 | J20: =H20*I20 -> 0 | K20: =G20+J20 -> 0 | L20: =+K20 -> 0
A21: 18 | B21: 46252 | G21: =E21*F21 -> 0 | J21: =H21*I21 -> 0 | K21: =G21+J21 -> 0 | L21: =+K21 -> 0
A22: 19 | B22: 46253 | G22: =E22*F22 -> 0 | J22: =H22*I22 -> 0 | K22: =G22+J22 -> 0 | L22: =+K22 -> 0
A23: 20 | B23: 46254 | G23: =E23*F23 -> 0 | J23: =H23*I23 -> 0 | K23: =G23+J23 -> 0 | L23: =+K23 -> 0
A24: 21 | B24: 46255 | G24: =E24*F24 -> 0 | H24: 8.52 | I24: 111.51 | J24: =H24*I24 -> 950.0652 | K24: =G24+J24 -> 950.0652 | L24: =+K24 -> 950.0652
A25: 22 | B25: 46256 | G25: =E25*F25 -> 0 | H25: 7.18 | I25: 111.51 | J25: =H25*I25 -> 800.6418 | K25: =G25+J25 -> 800.6418 | L25: =+K25 -> 800.6418
A26: 23 | B26: 46257 | G26: =E26*F26 -> 0 | J26: =H26*I26 -> 0 | K26: =G26+J26 -> 0 | L26: =+K26 -> 0
A27: 24 | B27: 46258 | G27: =E27*F27 -> 0 | J27: =H27*I27 -> 0 | K27: =G27+J27 -> 0 | L27: =+K27 -> 0 | O27: 0
A28: 25 | B28: 46259 | G28: =E28*F28 -> 0 | J28: =H28*I28 -> 0 | K28: =G28+J28 -> 0 | L28: =+K28 -> 0
A29: 26 | B29: 46260 | G29: =E29*F29 -> 0 | J29: =H29*I29 -> 0 | K29: =G29+J29 -> 0 | L29: =+K29 -> 0
A30: 27 | B30: 46261 | G30: =E30*F30 -> 0 | J30: =H30*I30 -> 0 | K30: =G30+J30 -> 0 | L30: =+K30 -> 0
A31: 28 | B31: 46262 | G31: =E31*F31 -> 0 | J31: =H31*I31 -> 0 | K31: =G31+J31 -> 0 | L31: =+K31 -> 0
A32: 29 | B32: 46263 | G32: =E32*F32 -> 0 | J32: =H32*I32 -> 0 | K32: =G32+J32 -> 0 | L32: =+K32 -> 0
A33: 30 | B33: 46264 | G33: =E33*F33 -> 0 | J33: =H33*I33 -> 0 | K33: =G33+J33 -> 0 | L33: =+K33 -> 0
A34: 31 | B34: 46265 | G34: =E34*F34 -> 0 | J34: =H34*I34 -> 0 | K34: =G34+J34 -> 0 | L34: =H34+K34 -> 0
E35: =SUM(E4:E34) -> 352 | G35: =SUM(G4:G34) -> 34992.32 | H35: =SUM(H4:H34) -> 23.23 | J35: =SUM(J4:J34) -> 2590.3773 | K35: =SUM(K4:K34) -> 37582.697 | L35: =SUM(L4:L34) -> 37582.697

Sheet kumta
A1: V.M.MIRJANKAR (KUMTA) BHARAT
A2: S.No | B2: Date | C2: GRN No | D2: Ind No/Bill No | E2: Diesel (Lts) | F2: Price | G2: Amount | H2: Petrol (Lts) | I2: Price | J2: Amount | K2: Total amount | L2: Amount paid | M2: As on Date | N2: Remarks
A3: Opening Balance | M3: 60343.607
A4: 1 | B4: 45870 | E4: 100 | F4: 99.78 | G4: =E4*F4 -> 9978 | J4: =H4*I4 -> 0 | K4: =G4+J4 -> 9978 | M4: =M3+K4-L4 -> 70321.607
A5: 2 | B5: 45871 | E5: 50 | F5: 99.78 | G5: =E5*F5 -> 4989 | H5: 5 | I5: 111.98 | J5: =H5*I5 -> 559.9 | K5: =G5+J5 -> 5548.9 | M5: =M4+K5-L5 -> 75870.507
A6: 3 | B6: 45872 | E6: 80 | F6: 99.78 | G6: =E6*F6 -> 7982.4 | H6: 5 | I6: 111.98 | J6: =H6*I6 -> 559.9 | K6: =G6+J6 -> 8542.3 | M6: =M5+K6-L6 -> 84412.807
A7: 4 | B7: 45873 | G7: =E7*F7 -> 0 | J7: =H7*I7 -> 0 | K7: =G7+J7 -> 0 | M7: =M6+K7-L7 -> 84412.807
A8: 5 | B8: 45874 | E8: 80 | F8: 99.78 | G8: =E8*F8 -> 7982.4 | H8: 10 | I8: 111.98 | J8: =H8*I8 -> 1119.8 | K8: =G8+J8 -> 9102.2 | L8: 84000 | M8: =M7+K8-L8 -> 9515.0068
A9: 6 | B9: 45875 | G9: =E9*F9 -> 0 | J9: =H9*I9 -> 0 | K9: =G9+J9 -> 0 | M9: =M8+K9-L9 -> 9515.0068
A10: 7 | B10: 45876 | E10: 30 | F10: 99.78 | G10: =E10*F10 -> 2993.4 | H10: 10 | I10: 111.98 | J10: =H10*I10 -> 1119.8 | K10: =G10+J10 -> 4113.2 | M10: =M9+K10-L10 -> 13628.207
A11: 8 | B11: 45877 | E11: 40 | F11: 99.78 | G11: =E11*F11 -> 3991.2 | J11: =H11*I11 -> 0 | K11: =G11+J11 -> 3991.2 | M11: =M10+K11-L11 -> 17619.407
A12: 9 | B12: 45878 | E12: 30 | F12: 99.78 | G12: =E12*F12 -> 2993.4 | J12: =H12*I12 -> 0 | K12: =G12+J12 -> 2993.4 | M12: =M11+K12-L12 -> 20612.807
A13: 10 | B13: 45879 | E13: 50 | F13: 99.78 | G13: =E13*F13 -> 4989 | H13: 10 | I13: 111.98 | J13: =H13*I13 -> 1119.8 | K13: =G13+J13 -> 6108.8 | M13: =M12+K13-L13 -> 26721.607
A14: 11 | B14: 45880 | E14: 40 | F14: 99.78 | G14: =E14*F14 -> 3991.2 | H14: 10 | I14: 111.98 | J14: =H14*I14 -> 1119.8 | K14: =G14+J14 -> 5111 | M14: =M13+K14-L14 -> 31832.607
A15: 12 | B15: 45881 | E15: 30 | F15: 99.78 | G15: =E15*F15 -> 2993.4 | J15: =H15*I15 -> 0 | K15: =G15+J15 -> 2993.4 | M15: =M14+K15-L15 -> 34826.007
A16: 13 | B16: 45882 | E16: 40 | F16: 99.78 | G16: =E16*F16 -> 3991.2 | J16: =H16*I16 -> 0 | K16: =G16+J16 -> 3991.2 | M16: =M15+K16-L16 -> 38817.207
A17: 14 | B17: 45883 | G17: =E17*F17 -> 0 | J17: =H17*I17 -> 0 | K17: =G17+J17 -> 0 | M17: =M16+K17-L17 -> 38817.207
A18: 15 | B18: 45884 | G18: =E18*F18 -> 0 | J18: =H18*I18 -> 0 | K18: =G18+J18 -> 0 | M18: =M17+K18-L18 -> 38817.207
A19: 16 | B19: 45885 | G19: =E19*F19 -> 0 | J19: =H19*I19 -> 0 | K19: =G19+J19 -> 0 | M19: =M18+K19-L19 -> 38817.207
A20: 17 | B20: 45886 | G20: =E20*F20 -> 0 | J20: =H20*I20 -> 0 | K20: =G20+J20 -> 0 | M20: =M19+K20-L20 -> 38817.207
A21: 18 | B21: 45887 | E21: 40 | F21: 99.78 | G21: =E21*F21 -> 3991.2 | J21: =H21*I21 -> 0 | K21: =G21+J21 -> 3991.2 | M21: =M20+K21-L21 -> 42808.407
A22: 19 | B22: 45888 | G22: =E22*F22 -> 0 | H22: 5 | I22: 111.98 | J22: =H22*I22 -> 559.9 | K22: =G22+J22 -> 559.9 | M22: =M21+K22-L22 -> 43368.307
A23: 20 | B23: 45889 | E23: 60 | F23: 99.78 | G23: =E23*F23 -> 5986.8 | J23: =H23*I23 -> 0 | K23: =G23+J23 -> 5986.8 | L23: 42000 | M23: =M22+K23-L23 -> 7355.1068
A24: 21 | B24: 45890 | E24: 60 | F24: 99.78 | G24: =E24*F24 -> 5986.8 | H24: 15 | I24: 111.98 | J24: =H24*I24 -> 1679.7 | K24: =G24+J24 -> 7666.5 | M24: =M23+K24-L24 -> 15021.607
A25: 22 | B25: 45891 | G25: =E25*F25 -> 0 | J25: =H25*I25 -> 0 | K25: =G25+J25 -> 0 | M25: =M24+K25-L25 -> 15021.607
A26: 23 | B26: 45892 | E26: 30 | F26: 99.78 | G26: =E26*F26 -> 2993.4 | J26: =H26*I26 -> 0 | K26: =G26+J26 -> 2993.4 | M26: =M25+K26-L26 -> 18015.007 | R26: Kumta | T26: V.M.Mirjankar
A27: 24 | B27: 45893 | E27: 130 | F27: 99.78 | G27: =E27*F27 -> 12971.4 | J27: =H27*I27 -> 0 | K27: =G27+J27 -> 12971.4 | M27: =M26+K27-L27 -> 30986.407 | R27: Month | S27: Disel In Litters | T27: Petrol In Litters | U27: Amount Paid
