Workbook

Sheet  MIs
A2: S.No | B2: NAme | C2: Lacation | D2: Card Number | E2: Card Number | F2: Category | G2: 1st Jan | I2: 2nd Jan | J2: 3rd Jan | K2: 4th Jan | L2: 5th Jan | M2: 6th Jan | N2: 7th Jan | O2: 8th Jan | P2: 9th Jan | Q2: 10th Jan | R2: 11th Jan | S2: 12th Jan | T2: 13th Jan | U2: 14th Jan | V2: 15th Jan | W2: 16th Jan | X2: 17th Jan | Y2: 18th Jan | Z2: 19th Jan | AA2: 20th Jan | AB2: 21st Jan | AC2: 22nd Jan | AD2: 23rd Jan | AE2: 24th Jan | AF2: 25th Jan | AG2: 26th Jan | AH2: 27th Jan | AI2: 28th Jan | AJ2: 29th Jan | AK2: 30th Jan | AL2: 31st Jan | AM2: Total
F3: Diesel
A4: 1 | B4: Rambabu | C4: HO(Two Wheeler) | D4: FC3450563999 | E4: Diesel | F4: 0 | G4: 0 | H4: 0 | I4: 0 | J4: 0 | K4: 0 | L4: 0 | M4: 0 | N4: 0 | O4: 0 | P4: 0 | Q4: 0 | R4: 0 | S4: 0 | T4: 0 | U4: 0 | V4: 0 | W4: 0 | X4: 5.22 | Y4: 0 | Z4: 0 | AA4: 0 | AB4: 0 | AC4: 0 | AD4: 60 | AE4: 0 | AF4: 0 | AG4: 0 | AH4: 4.56 | AI4: 0 | AJ4: 0 | AK4: 0 | AL4: 0 | AM4: =SUM(F4:AL4) -> 69.78
E5: Petrol | F5: 0 | G5: 4.69 | H5: 0 | I5: 0 | J5: 0 | K5: 0 | L5: 0 | M5: 0 | N5: 3.91 | O5: 0 | P5: 6.98 | Q5: 0 | R5: 0 | S5: 0 | T5: 0 | U5: 0 | V5: 0 | W5: 0 | X5: 0 | Y5: 0 | Z5: 0 | AB5: 0 | AC5: 0 | AD5: 0 | AE5: 0 | AF5: 0 | AG5: 0 | AH5: 0 | AI5: 0 | AJ5: 0 | AK5: 0 | AL5: 0 | AM5: =SUM(F5:AL5) -> 15.58
A6: 2 | B6: Hanumanth Rao | C6: HO | D6: FC3450676131 | E6: Diesel | F6: 0 | G6: 0 | H6: 0 | I6: 0 | J6: 0 | K6: 0 | L6: 0 | M6: 0 | N6: 0 | O6: 0 | P6: 0 | Q6: 0 | R6: 0 | S6: 0 | T6: 0 | U6: 0 | V6: 0 | W6: 0 | X6: 0 | Y6: 0 | Z6: 0 | AA6: 0 | AB6: 0 | AC6: 0 | AD6: 0 | AE6: 0 | AF6: 0 | AG6: 0 | AH6: 0 | AI6: 0 | AJ6: 0 | AK6: 0 | AL6: 0 | AM6: =SUM(F6:AL6) -> 0
E7: Petrol | F7: 0 | G7: 0 | H7: 0 | I7: 0 | J7: 0 | K7: 0 | L7: 0 | M7: 0 | N7: 0 | O7: 0 | P7: 0 | Q7: 0 | R7: 0 | S7: 0 | T7: 0 | U7: 0 | V7: 0 | W7: 0 | X7: 0 | Y7: 0 | Z7: 0 | AB7: 0 | AC7: 0 | AD7: 0 | AE7: 0 | AF7: 0 | AG7: 0 | AH7: 0 | AI7: 0 | AJ7: 0 | AK7: 0 | AL7: 0 | AM7: =SUM(F7:AL7) -> 0
A8: 3 | B8: Radhakrishna | C8: HO | D8: FC8000207658 | E8: Diesel | F8: 0 | G8: 0 | H8: 0 | I8: 0 | J8: 33.44 | K8: 0 | L8: 0 | M8: 0 | N8: 0 | O8: 0 | P8: 0 | Q8: 0 | R8: 35.53 | S8: 0 | T8: 0 | U8: 0 | V8: 0 | W8: 0 | X8: 0 | Y8: 0 | Z8: 0 | AA8: 0 | AB8: 33.44 | AC8: 0 | AD8: 0 | AE8: 0 | AF8: 0 | AG8: 0 | AH8: 0 | AI8: 0 | AJ8: 0 | AK8: 0 | AL8: 0 | AM8: =SUM(F8:AL8) -> 102.41
E9: Petrol | F9: 0 | G9: 0 | H9: 0 | I9: 0 | J9: 0 | K9: 0 | L9: 0 | M9: 0 | N9: 0 | O9: 0 | P9: 0 | Q9: 0 | R9: 0 | S9: 0 | T9: 0 | U9: 0 | V9: 0 | W9: 0 | X9: 0 | Y9: 0 | Z9: 0 | AB9: 0 | AC9: 0 | AD9: 0 | AE9: 0 | AF9: 0 | AG9: 0 | AH9: 0 | AI9: 0 | AJ9: 0 | AK9: 0 | AL9: 0 | AM9: =SUM(F9:AL9) -> 0
A10: 4 | B10: VIjay | C10: HO | D10: FC3450698859 | E10: Diesel | F10: 0 | G10: 0 | H10: 0 | I10: 0 | J10: 0 | K10: 0 | L10: 0 | M10: 0 | N10: 0 | O10: 0 | P10: 49.22 | Q10: 0 | R10: 0 | S10: 0 | T10: 0 | U10: 54.57 | V10: 0 | W10: 0 | X10: 0 | Y10: 0 | Z10: 0 | AA10: 0 | AB10: 0 | AC10: 0 | AD10: 49.8 | AE10: 0 | AF10: 0 | AG10: 0 | AH10: 0 | AI10: 0 | AJ10: 0 | AK10: 0 | AL10: 0 | AM10: =SUM(F10:AL10) -> 153.59
E11: Petrol | F11: 0 | G11: 0 | H11: 0 | I11: 0 | J11: 0 | K11: 0 | L11: 0 | M11: 0 | N11: 0 | O11: 0 | P11: 0 | Q11: 0 | R11: 0 | S11: 0 | T11: 0 | U11: 0 | V11: 0 | W11: 0 | X11: 0 | Y11: 0 | Z11: 0 | AB11: 0 | AC11: 0 | AD11: 0 | AE11: 0 | AF11: 0 | AG11: 0 | AH11: 0 | AI11: 0 | AJ11: 0 | AK11: 0 | AL11: 0 | AM11: =SUM(F11:AL11) -> 0
A12: 5 | B12: Client | C12: Hiriyur | D12: FC3450698864 | E12: Diesel | F12: 0 | G12: 0 | H12: 0 | I12: 0 | J12: 0 | K12: 0 | L12: 0 | M12: 0 | N12: 86.29 | O12: 0 | P12: 0 | Q12: 0 | R12: 0 | S12: 0 | T12: 0 | U12: 0 | V12: 0 | W12: 0 | X12: 0 | Y12: 0 | Z12: 0 | AA12: 0 | AB12: 0 | AC12: 0 | AD12: 145.61 | AE12: 0 | AF12: 0 | AG12: 0 | AH12: 0 | AI12: 0 | AJ12: 0 | AK12: 0 | AL12: 0 | AM12: =SUM(F12:AL12) -> 231.9
E13: Petrol | F13: 0 | G13: 0 | H13: 0 | I13: 0 | J13: 0 | K13: 0 | L13: 0 | M13: 0 | N13: 0 | O13: 0 | P13: 0 | Q13: 0 | R13: 0 | S13: 0 | T13: 0 | U13: 0 | V13: 0 | W13: 0 | X13: 0 | Y13: 0 | Z13: 0 | AB13: 0 | AC13: 0 | AD13: 0 | AE13: 0 | AF13: 0 | AG13: 0 | AH13: 0 | AI13: 0 | AJ13: 0 | AK13: 0 | AL13: 0 | AM13: =SUM(F13:AL13) -> 0
A14: 6 | B14: Client | C14: Hosadurga | D14: FC3450698865 | E14: Diesel | F14: 0 | G14: 0 | H14: 0 | I14: 0 | J14: 0 | K14: 0 | L14: 40 | M14: 40 | N14: 0 | O14: 36 | P14: 35 | Q14: 0 | R14: 0 | S14: 0 | T14: 0 | U14: 0 | V14: 0 | W14: 45 | X14: 45 | Y14: 43.53 | Z14: 40 | AA14: 43 | AB14: 0 | AC14: 40 | AD14: 0 | AE14: 40 | AF14: 0 | AG14: 0 | AH14: 0 | AI14: 0 | AJ14: 0 | AK14: 0 | AL14: 0 | AM14: =SUM(F14:AL14) -> 447.53
E15: Petrol | F15: 0 | G15: 0 | H15: 0 | I15: 0 | J15: 0 | K15: 0 | L15: 0 | M15: 0 | N15: 0 | O15: 0 | P15: 0 | Q15: 0 | R15: 0 | S15: 0 | T15: 0 | U15: 0 | V15: 0 | W15: 0 | X15: 0 | Y15: 0 | Z15: 0 | AB15: 0 | AC15: 0 | AD15: 0 | AE15: 0 | AF15: 0 | AG15: 0 | AH15: 0 | AI15: 0 | AJ15: 0 | AK15: 0 | AL15: 0 | AM15: =SUM(F15:AL15) -> 0
G18: Diesel Price

Sheet  Sep-26
A1: S.no | B1: Site Name | C1: Bunk Name | D1: Diesel(Liters) | E1: Diesel Amount | F1: Petrol(Liters) | G1: Petrol Amount | H1: Total Amount | I1: Opening Blance | J1: Amount Paid | K1: Closing Balances
A2: 1 | B2: Khammam-1 | C2: Divya laxmi ganapathi | D2: =+'Khammam-1'!E38 -> 39800 | E2: =+'Khammam-1'!G38 -> 4131240 | F2: =+'Khammam-1'!H38 -> 185 | G2: =+'Khammam-1'!J38 -> 21402.65 | H2: =E2+G2 -> 4152642.6 | I2: =+'Khammam-1'!K3 -> 2805565.2 | J2: =+'Khammam-1'!L38 -> 2826324 | K2: =H2+I2-J2 -> 4131883.8
A3: 2 | B3: Khammam-2 | C3: Jayasai union bunk | D3: =+'Khammam-2'!E39 -> 39546 | E3: =+'Khammam-2'!G39 -> 4230667 | F3: =+'Khammam-2'!H39 -> 155 | G3: =+'Khammam-2'!J39 -> 17936.6 | H3: =E3+G3 -> 4248603.6 | I3: =+'Khammam-2'!K3 -> 0 | J3: =+'Khammam-2'!L39 -> 0 | K3: =H3+I3-J3 -> 4248603.6
A4: 3 | B4: Khammam | C4: Sai Madeana Filling Station | D4: =+'Khammam-4'!E35 -> 27000 | E4: =+'Khammam-4'!G35 -> 2797740 | F4: =+'Khammam-4'!H35 -> 595 | G4: =+'Khammam-4'!J35 -> 68716.55 | H4: =E4+G4 -> 2866456.5 | I4: =+'Khammam-4'!M3 -> 843364.3 | J4: =+'Khammam-4'!L35 -> 568209.75 | K4: =H4+I4-J4 -> 3141611.1
A5: 4 | B5: Khammam | C5: Vajra mahalakshmi filling station | D5: =+' Khammam-5'!E35 -> 8200 | E5: =+' Khammam-5'!G35 -> 849684 | F5: =+' Khammam-5'!H35 -> 145 | G5: =+' Khammam-5'!J35 -> 16746.05 | H5: =E5+G5 -> 866430.05 | I5: =+' Khammam-5'!M3 -> 578571.8 | J5: =+' Khammam-5'!L35 -> 0 | K5: =H5+I5-J5 -> 1445001.9
A6: 5 | B6: Khammam-Cash&Carry | C6: NA | D6: =+' Khammam&Cash'!E46 -> 0 | E6: =+' Khammam&Cash'!G46 -> 0 | F6: =+' Khammam&Cash'!H46 -> 0 | G6: =+' Khammam&Cash'!J46 -> 0 | H6: =E6+G6 -> 0 | I6: =+' Khammam&Cash'!M3 -> 0 | J6: =+' Khammam&Cash'!L46 -> 0 | K6: =H6+I6-J6 -> 0
A7: 6 | B7: Jadcherla-2 | C7: Shree Poornima F/S | D7: =+'Jadcherla-4'!E35 -> 400 | E7: =+'Jadcherla-4'!G35 -> 41768 | F7: =+'Jadcherla-4'!H35 -> 30 | G7: =+'Jadcherla-4'!J35 -> 3489.9 | H7: =E7+G7 -> 45257.9 | I7: =+'Jadcherla-4'!M3 -> 2600.28 | J7: =+'Jadcherla-4'!L35 -> 0 | K7: =H7+I7-J7 -> 47858.18
A8: 7 | B8: Sangareddy-2 | C8: Durga Bhavani F/S | D8: =+' Sangareddy-2'!E35 -> 0 | E8: =+' Sangareddy-2'!G35 -> 0 | F8: =+' Sangareddy-2'!H35 -> 0 | G8: =+' Sangareddy-2'!J35 -> 0 | H8: =E8+G8 -> 0 | I8: =+' Sangareddy-2'!M3 -> 0 | J8: =+' Sangareddy-2'!L35 -> 0 | K8: =H8+I8-J8 -> 0
A9: 8 | B9: Sangareddy-3 | C9: Shiva Parvathi Filling Station | D9: =+' Sangareddy-3'!E36 -> 6120 | E9: =+' Sangareddy-3'!G36 -> 638622 | F9: =+' Sangareddy-3'!H36 -> 82 | G9: =+' Sangareddy-3'!J36 -> 9532.5 | H9: =E9+G9 -> 648154.5 | I9: =+' Sangareddy-3'!M3 -> 146154.99 | J9: =+' Sangareddy-3'!L36 -> 427500 | K9: =H9+I9-J9 -> 366809.49
A10: 9 | B10: NarayanaKhed | C10: Sai Shiva Filling Station | D10: =Narayankhed!E35 -> 2046.27 | E10: =+Narayankhed!G35 -> 214943.35 | F10: =+Narayankhed!H35 -> 0 | G10: =+Narayankhed!J35 -> 0 | H10: =E10+G10 -> 214943.35 | I10: =+Narayankhed!M3 -> 0 | J10: =+Narayankhed!L35 -> 214943.35 | K10: =H10+I10-J10 -> 0
A11: 10 | B11: Dindi | C11: Akarapu Balakistamma Fillling | D11: =+Dindi!E35 -> 91.45 | E11: =+Dindi!G35 -> 9597.6775 | F11: =+Dindi!H35 -> 0 | G11: =+Dindi!J35 -> 0 | H11: =E11+G11 -> 9597.6775 | I11: =+Dindi!M3 -> 0 | J11: =+Dindi!L35 -> 9597.6775 | K11: =H11+I11-J11 -> 0
A12: 11 | B12: Madanapalli | C12: NA | D12: =+'Madana palli'!E37 -> 0 | E12: =+'Madana palli'!G37 -> 0 | F12: =+'Madana palli'!H37 -> 0 | G12: =+'Madana palli'!J37 -> 0 | H12: =E12+G12 -> 0 | I12: =+'Madana palli'!M3 -> 0 | J12: =+'Madana palli'!L37 -> 0 | K12: =H12+I12-J12 -> 0
A13: 12 | B13: Kakinada | C13: Raja Filling Station | D13: =+' Raja Filling Statuion'!E35 -> 119 | E13: =+' Raja Filling Statuion'!G35 -> 12565.21 | F13: =+' Raja Filling Statuion'!H35 -> 14 | G13: =+' Raja Filling Statuion'!J35 -> 1651.72 | H13: =E13+G13 -> 14216.93 | I13: =+' Raja Filling Statuion'!M3 -> 0 | J13: =+' Raja Filling Statuion'!L35 -> 0 | K13: =H13+I13-J13 -> 14216.93
A14: 13 | B14: Kovvur | C14: Sri Venkateshwara Services | D14: =+'Sri Venkateshwara Services'!E37 -> 1621.364 | E14: =+'Sri Venkateshwara Services'!G37 -> 169724.38 | F14: =+'Sri Venkateshwara Services'!H37 -> 245.02 | G14: =+'Sri Venkateshwara Services'!J37 -> 28657.539 | H14: =E14+G14 -> 198381.92 | I14: =+'Sri Venkateshwara Services'!M3 -> 17037.915 | J14: =+'Sri Venkateshwara Services'!L37 -> 100000 | K14: =H14+I14-J14 -> 115419.84
A15: 14 | B15: Jangareddygudem | C15: Solasa Krishna Oil Company | D15: =+' Solasa Krishna OIl'!E37 -> 1795.41 | E15: =+' Solasa Krishna OIl'!G37 -> 189236.21 | F15: =+' Solasa Krishna OIl'!H37 -> 28.05 | G15: =+' Solasa Krishna OIl'!J37 -> 3302.607 | H15: =E15+G15 -> 192538.82 | I15: =+' Solasa Krishna OIl'!M3 -> 46362.715 | J15: =+' Solasa Krishna OIl'!L37 -> 0 | K15: =H15+I15-J15 -> 238901.54
A16: 15 | B16: Amalapuram | C16: Royal Fill 'N' Fly | D16: =+'Amalapuram(KKD)'!E37 -> 10406.79 | E16: =+'Amalapuram(KKD)'!G37 -> 1095314.6 | F16: =+'Amalapuram(KKD)'!H37 -> 106 | G16: =+'Amalapuram(KKD)'!J37 -> 12463.48 | H16: =E16+G16 -> 1107778.1 | I16: =+'Amalapuram(KKD)'!M3 -> 426859.64 | J16: =+'Amalapuram(KKD)'!L37 -> 1015000 | K16: =H16+I16-J16 -> 519637.76
A17: 16 | B17: Yeleshwaram | C17: Sri sathya Filling Station | D17: =+'Yeleshwaram(KKD)'!E37 -> 812.02 | E17: =+'Yeleshwaram(KKD)'!G37 -> 85635.629 | F17: =+'Yeleshwaram(KKD)'!H37 -> 25 | G17: =+'Yeleshwaram(KKD)'!J37 -> 2946 | H17: =E17+G17 -> 88581.629 | I17: =+'Yeleshwaram(KKD)'!M3 -> 8498.7136 | J17: =+'Yeleshwaram(KKD)'!L37 -> 80000 | K17: =H17+I17-J17 -> 17080.343
A18: 17 | B18: Pitapuam | C18: Satya Siva Durga Agencies, Chebrolu | D18: =+' Pitapram(KKD)'!E37 -> 5710.3 | E18: =+' Pitapram(KKD)'!G37 -> 600780.66 | F18: =+' Pitapram(KKD)'!H37 -> 516.23 | G18: =+' Pitapram(KKD)'!J37 -> 60698.323 | H18: =E18+G18 -> 661478.99 | I18: =+' Pitapram(KKD)'!M3 -> 124354 | J18: =+' Pitapram(KKD)'!L37 -> 494000 | K18: =H18+I18-J18 -> 291832.98
A19: 18 | B19: Kakinada | C19: Multiple bunks | D19: =+' Pitapram(KKD)'!E38 -> 0 | E19: =+' Pitapram(KKD)'!G38 -> 0 | F19: =+' Pitapram(KKD)'!H38 -> 0 | G19: =+' Pitapram(KKD)'!J38 -> 0 | H19: =E19+G19 -> 0 | I19: =+'Multiple bunks(KKD)'!M3 -> 0 | J19: =+' Pitapram(KKD)'!L38 -> 0 | K19: =H19+I19-J19 -> 0
A20: 19 | B20: YG Gudda-2 | C20: Pankaja HP Fuel Center | D20: =+'YG Gudda'!E39 -> 8000 | E20: =+'YG Gudda'!G39 -> 793120 | F20: =+'YG Gudda'!H39 -> 315 | G20: =+'YG Gudda'!J39 -> 35040.6 | H20: =E20+G20 -> 828160.6 | I20: =+'YG Gudda'!M3 -> 127791.16 | J20: =+'YG Gudda'!L39 -> 650000 | K20: =H20+I20-J20 -> 305951.76
A21: 20 | B21: YG Gudda-2 | C21: One stop | D21: =+' YG Gudda-2'!E39 -> 2400 | E21: =+' YG Gudda-2'!G39 -> 237648 | F21: =+' YG Gudda-2'!H39 -> 105 | G21: =+' YG Gudda-2'!J39 -> 11667.6 | H21: =E21+G21 -> 249315.6 | I21: =+' YG Gudda-2'!M3 -> 156607.72 | J21: =+' YG Gudda-2'!L39 -> 150000 | K21: =H21+I21-J21 -> 255923.32
A22: 21 | B22: Hosadurga-2 | C22: Shree Veeraprathap Fuel | D22: =+'Hosadurga -2'!E35 -> 1000 | E22: =+'Hosadurga -2'!G35 -> 99380 | F22: =+'Hosadurga -2'!H35 -> 70 | G22: =+'Hosadurga -2'!J35 -> 7820.4 | H22: =+'Hosadurga -2'!K35 -> 107200.4 | I22: =+'Hosadurga -2'!M3 -> 118809.59 | J22: =+'Hosadurga -2'!L35 -> 100000 | K22: =H22+I22-J22 -> 126009.99
A23: 22 | B23: Malebennuru(KUWSDB) | C23: Sri Ramanjuneya Service Station | D23: =+'Malebenur(KUWSDB)'!E38 -> 6099.92 | E23: =+'Malebenur(KUWSDB)'!G38 -> 609939.99 | F23: =+'Malebenur(KUWSDB)'!H38 -> 185 | G23: =+'Malebenur(KUWSDB)'!J38 -> 20723.7 | H23: =E23+G23 -> 630663.69 | I23: =+'Malebenur(KUWSDB)'!M3 -> 122228.41 | J23: =+'Malebenur(KUWSDB)'!L38 -> 461999.99 | K23: =H23+I23-J23 -> 290892.11
A24: 23 | B24: kadur | C24: Vishal Service Station | D24: =+Kadur!E35 -> 1600 | E24: =+Kadur!G35 -> 159936 | F24: =+Kadur!H35 -> 140 | G24: =+Kadur!J35 -> 15722 | H24: =E24+G24 -> 175658 | I24: =+Kadur!K3 -> 0 | J24: =+Kadur!L35 -> 0 | K24: =H24+I24-J24 -> 175658
A25: 24 | B25: Hiriyur(VJNL) | C25: Sri Balaji Agencies | D25: =+'Hiriyur(VJNL)'!E35 -> 4700 | E25: =+'Hiriyur(VJNL)'!G35 -> 470423 | F25: =+'Hiriyur(VJNL)'!H35 -> 295 | G25: =+'Hiriyur(VJNL)'!J35 -> 33075.4 | H25: =E25+G25 -> 503498.4 | I25: =+'Hiriyur(VJNL)'!K3 -> 219945.7 | J25: =+'Hiriyur(VJNL)'!L35 -> 511000 | K25: =H25+I25-J25 -> 212444.1
A26: 25 | B26: Chellakere(KUWSDB) | C26: Shivaganga Service Station | D26: =+'Chellakere -1'!E38 -> 3600 | E26: =+'Chellakere -1'!G38 -> 360180 | F26: =+'Chellakere -1'!H38 -> 175 | G26: =+'Chellakere -1'!J38 -> 19612.25 | H26: =E26+G26 -> 379792.25 | I26: =+'Chellakere -1'!K3 -> 0 | J26: =+'Chellakere -1'!L38 -> 191000 | K26: =H26+I26-J26 -> 188792.25
A27: 26 | B27: Chellakere(KUWSDB)-09 | C27: Shivaganga Service Station | D27: =+' Chellakere-PKG-9'!E38 -> 983.15 | E27: =+' Chellakere-PKG-9'!G38 -> 98364.158 | F27: =+' Chellakere-PKG-9'!H38 -> 48.24 | G27: =+' Chellakere-PKG-9'!J38 -> 5406.2568 | H27: =E27+G27 -> 103770.41 | I27: =+' Chellakere-PKG-9'!M3 -> 0 | J27: =+' Chellakere-PKG-9'!L38 -> 103769.42 | K27: =H27+I27-J27 -> 0.999
A28: 27 | B28: Molakalmuru | C28: Sri Lakshmi Venkateshwara Filling Station | D28: =+Molakamuru!E35 -> 700 | E28: =+Molakamuru!G35 -> 70028 | F28: =+Molakamuru!H35 -> 40 | G28: =+Molakamuru!J35 -> 4482.4 | H28: =E28+G28 -> 74510.4 | I28: =+Molakamuru!K3 -> 35260.26 | J28: =+Molakamuru!L35 -> 65000 | K28: =H28+I28-J28 -> 44770.66
A29: 28 | B29: Chennagiri | C29: NA | D29: =+' Chennagiri'!E35 -> 1290 | E29: =+' Chennagiri'!G35 -> 128858.1 | F29: =+' Chennagiri'!H35 -> 70 | G29: =+' Chennagiri'!J35 -> 7844.2 | H29: =E29+G29 -> 136702.3 | I29: =+' Chennagiri'!K3 -> 0 | J29: =+' Chennagiri'!L35 -> 136702.3 | K29: =H29+I29-J29 -> 0
A30: 29 | B30: Khanapur(PKG-3) | C30: V.V.Varde | D30: =+Khanapur!E35 -> 705.07 | E30: =+Khanapur!G35 -> 69583.358 | F30: =+Khanapur!H35 -> 85 | G30: =+Khanapur!J35 -> 9412.9 | H30: =E30+G30 -> 78996.258 | I30: =+Khanapur!M3 -> 41788.871 | J30: =+Khanapur!L35 -> 0 | K30: =H30+I30-J30 -> 120785.13
A31: 30 | B31: Munavalli(PKG-3) | C31: Shre Shiva Petroleum | D31: =+'Munavali-2'!E40 -> 5200 | E31: =+'Munavali-2'!G40 -> 516620 | F31: =+'Munavali-2'!H40 -> 0 | G31: =+'Munavali-2'!J40 -> 0 | H31: =E31+G31 -> 516620 | I31: =+'Munavali-2'!M3 -> 346801.5 | J31: =+'Munavali-2'!L40 -> 600000 | K31: =H31+I31-J31 -> 263421.5
A32: 31 | B32: Munavalli(PKG-3) | C32: Daneshwari Petroleum | D32: =+' Munavali'!E39 -> 27.13 | E32: =+' Munavali'!G39 -> 2689.3969 | F32: =+' Munavali'!H39 -> 240 | G32: =+' Munavali'!J39 -> 26690.4 | H32: =E32+G32 -> 29379.797 | I32: =+' Munavali'!M3 -> 665.2699 | J32: =+' Munavali'!L39 -> 0 | K32: =H32+I32-J32 -> 30045.067
A33: 32 | B33: Ugar,Kudichi(PKG-3) | C33: Shiri Bhrhmanath Petrolium | D33: =+'Ugar,Khagwad,Kudichi'!E37 -> 7865.62 | E33: =+'Ugar,Khagwad,Kudichi'!G37 -> 784516.94 | F33: =+'Ugar,Khagwad,Kudichi'!H37 -> 411 | G33: =+'Ugar,Khagwad,Kudichi'!J37 -> 45971.2 | H33: =E33+G33 -> 830488.14 | I33: =+'Ugar,Khagwad,Kudichi'!M3 -> 583834.37 | J33: =+'Ugar,Khagwad,Kudichi'!L37 -> 1113666.7 | K33: =H33+I33-J33 -> 300655.8
A34: 33 | B34: Shedbal | C34: Varad Petroluem | D34: =+shedbal!E38 -> 2070.14 | E34: =+shedbal!G38 -> 206443.91 | F34: =+shedbal!H38 -> 112 | G34: =+shedbal!J38 -> 12527.2 | H34: =E34+G34 -> 218971.11 | I34: =+shedbal!M3 -> 170641.05 | J34: =+shedbal!L38 -> 231000.11 | K34: =H34+I34-J34 -> 158612.05
A35: 34 | B35: Kabbur(PKG-3) | C35: Shri Jai Hanuman Petrolium | D35: =+Kabbur!E35 -> 21.58 | E35: =+Kabbur!G35 -> 2145.2678 | F35: =+Kabbur!H35 -> 14.23 | G35: =+Kabbur!J35 -> 1586.7873 | H35: =E35+G35 -> 3732.0551 | I35: 0 | J35: =+Kabbur!L35 -> 3732.0551 | K35: =H35+I35-J35 -> 0
A36: 35 | B36: Kumta (PKG-1) | C36: V.M.Mirjankar (Kumta) Bharat | D36: =+kumta!E41 -> 1518.04 | E36: =+kumta!G41 -> 151470.03 | F36: =+kumta!H41 -> 80 | G36: =+kumta!J41 -> 8958.4 | H36: =E36+G36 -> 160428.43 | I36: =kumta!M3 -> 24092.227 | J36: =+kumta!L41 -> 100000 | K36: =H36+I36-J36 -> 84520.658
A37: 36 | B37: Jalgaon-2 | C37: Nayara | D37: =+'Jalgoan-2'!E56 -> 5431 | E37: ='Jalgoan-2'!G56 -> 540438.81 | F37: =+'Jalgoan-2'!H56 -> 130 | G37: =+'Jalgoan-2'!J56 -> 14713.4 | H37: =E37+G37 -> 555152.21 | I37: =+'Jalgoan-2'!M3 -> 50000.028 | J37: =+'Jalgoan-2'!L56 -> 0 | K37: =H37+I37-J37 -> 605152.24
A38: 37 | B38: MKBD | C38: Shree Sai Samarth Petroleum | D38: =+MKBD!E42 -> 2500 | E38: =+MKBD!G42 -> 247350 | F38: =+MKBD!H42 -> 40 | G38: =+MKBD!J42 -> 4490.8 | H38: =E38+G38 -> 251840.8 | I38: =+MKBD!K3 -> 90567.01 | J38: =+MKBD!L42 -> 0 | K38: =H38+I38-J38 -> 342407.81
A39: 38 | B39: Haveri | C39: M/s Magavi City Fuels | D39: =' Haveri-2'!E42 -> 3322.91 | E39: =' Haveri-2'!G42 -> 329964.96 | F39: =' Haveri-2'!H42 -> 105.81 | G39: =' Haveri-2'!J42 -> 11806.054 | H39: =E39+G39 -> 341771.02 | I39: =' Haveri-2'!M3 -> 41052.548 | J39: =+' Haveri-2'!L42 -> 300000 | K39: =H39+I39-J39 -> 82823.565
A40: 39 | B40: Guttal-2 | C40: Himagiri Petroleum | D40: =+' Guttal-2'!E35 -> 8814 | E40: =+' Guttal-2'!G35 -> 877874.4 | F40: =+' Guttal-2'!H35 -> 208 | G40: =+' Guttal-2'!J35 -> 23235.68 | H40: =E40+G40 -> 901110.08 | I40: =+' Guttal-2'!M3 -> 408499.98 | J40: =+' Guttal-2'!L35 -> 850000 | K40: =H40+I40-J40 -> 459610.06
A41: 40 | B41: Rattihali-2 | C41: Shiva Oil Traders | D41: =+'Rattihali-2'!E37 -> 1471.96 | E41: =+'Rattihali-2'!G37 -> 146754.41 | F41: =+'Rattihali-2'!H37 -> 87 | G41: =+'Rattihali-2'!J37 -> 9728.34 | H41: =E41+G41 -> 156482.75 | I41: =+'Rattihali-2'!M3 -> 144892.23 | J41: =+'Rattihali-2'!L37 -> 140000 | K41: =H41+I41-J41 -> 161374.98
A42: 41 | B42: Gajendragada | C42: Vanasri Petrol Pump | D42: =+Gajendragada!E36 -> 1021.75 | E42: =+Gajendragada!G36 -> 101807.17 | F42: =+Gajendragada!H36 -> 80 | G42: =+Gajendragada!J36 -> 8941.6 | H42: =E42+G42 -> 110748.77 | I42: =+Gajendragada!M3 -> 16176.189 | J42: =+Gajendragada!L36 -> 0 | K42: =H42+I42-J42 -> 126924.96
A43: 42 | B43: Gokak(PKG-3) | C43: AJ Petrolinks | D43: =+'Gokak Dharwad PKG 3'!E42 -> 7783.99 | E43: =+'Gokak Dharwad PKG 3'!G42 -> 772872.37 | F43: =+'Gokak Dharwad PKG 3'!H42 -> 30 | G43: =+'Gokak Dharwad PKG 3'!J42 -> 3341.4 | H43: =E43+G43 -> 776213.77 | I43: =+'Gokak Dharwad PKG 3'!K3 -> 182122.17 | J43: =+'Gokak Dharwad PKG 3'!L42 -> 500000 | K43: =H43+I43-J43 -> 458335.94
A44: 43 | B44: Hukkere | C44: TR Assocites | D44: =+' TR Associates'!E35 -> 12786.71 | E44: =+' TR Associates'!G35 -> 1267546.6 | F44: =+' TR Associates'!H35 -> 0 | G44: =+' TR Associates'!J35 -> 0 | H44: =E44+G44 -> 1267546.6 | I44: =+' TR Associates'!M3 -> 136101.45 | J44: =+' TR Associates'!L35 -> 700000 | K44: =H44+I44-J44 -> 703648.01
A45: 44 | B45: Ankaligi | C45: Shivaganga | D45: =+Ankalgi!E35 -> 2835.63 | E45: =+Ankalgi!G35 -> 281096 | F45: =+Ankalgi!H35 -> 70 | G45: =+Ankalgi!J35 -> 7784.7 | H45: =E45+G45 -> 288880.7 | I45: =+Ankalgi!M3 -> 31843.318 | J45: =+Ankalgi!L35 -> 200000 | K45: =H45+I45-J45 -> 120724.02
A46: 45 | B46: Ghattaprabha | C46: Shri Deshpande | D46: =+'SHRI DESHPANDE'!E35 -> 11558.29 | E46: =+'SHRI DESHPANDE'!G35 -> 1148547.3 | F46: =+'SHRI DESHPANDE'!H35 -> 450 | G46: =+'SHRI DESHPANDE'!J35 -> 50157 | H46: =E46+G46 -> 1198704.3 | I46: =+'SHRI DESHPANDE'!M3 -> 144612.81 | J46: =+'SHRI DESHPANDE'!L35 -> 650000 | K46: =H46+I46-J46 -> 693317.08
A47: 46 | B47: ShankeshWAR | C47: SR Patil | D47: =+' Shankeshwar'!E35 -> 80 | E47: =+' Shankeshwar'!G35 -> 7929.6 | F47: =+' Shankeshwar'!H35 -> 44 | G47: =+' Shankeshwar'!J35 -> 4892.8 | H47: =E47+G47 -> 12822.4 | I47: =' Shankeshwar'!M3 -> 0 | J47: =+' Shankeshwar'!L35 -> 12822.4 | K47: =H47+I47-J47 -> 0
A48: 47 | B48: Talikote(PKG-1) | C48: Raykar Oil Agencies | D48: =+' Talikote'!E48 -> 876.17 | E48: =+' Talikote'!G48 -> 87021.204 | F48: =+' Talikote'!H48 -> 66.6 | G48: =+' Talikote'!J48 -> 7462.8 | H48: =E48+G48 -> 94484.004 | I48: =+' Talikote'!M3 -> 9813.8077 | J48: =+' Talikote'!L48 -> 30000 | K48: =H48+I48-J48 -> 74297.812
A49: 48 | B49: Chadchan(PKG-1) | C49: Khavekar Petrolium | D49: =+Chadchan!E35 -> 1105.91 | E49: =+Chadchan!G35 -> 109617.8 | F49: =+Chadchan!H35 -> 98.85 | G49: =+Chadchan!J35 -> 10991.131 | H49: =E49+G49 -> 120608.93 | I49: =+Chadchan!M3 -> 3961.7789 | J49: =+Chadchan!L35 -> 0 | K49: =H49+I49-J49 -> 124570.71
A50: 49 | B50: Sindagi | C50: G.P.PORWAL | D50: =+Sindagi!E35 -> 179.95 | E50: =+Sindagi!G35 -> 17827.646 | F50: =+Sindagi!H35 -> 0 | G50: =+Sindagi!J35 -> 0 | H50: =E50+G50 -> 17827.646 | I50: =+Sindagi!M3 -> 9906.54 | J50: =+Sindagi!L35 -> 0 | K50: =H50+I50-J50 -> 27734.186
A51: 50 | B51: Muddebihal(PKG-1)2 | C51: PS NAGATHAN PETROLIUM | D51: =+'Muddebhihal-2'!E50 -> 1566.14 | E51: =+'Muddebhihal-2'!G50 -> 155408.07 | F51: =+'Muddebhihal-2'!H50 -> 44 | G51: =+'Muddebhihal-2'!J50 -> 4992.38 | H51: =+'Muddebhihal-2'!K50 -> 160400.45 | I51: =+'Muddebhihal-2'!M3 -> 18073.67 | J51: =+'Muddebhihal-2'!L50 -> 0 | K51: =+'Muddebhihal-2'!M49 -> 178474.12
A52: 51 | B52: Almela(PKG-1) | C52: Shiddeshwar Petroleums | D52: =+Alemela!E43 -> 469.37 | E52: =+Alemela!G43 -> 46599.054 | F52: =+Alemela!H43 -> 48.27 | G52: =+Alemela!J43 -> 5376.3126 | H52: =E52+G52 -> 51975.366 | I52: =+Alemela!M3 -> 1087.9844 | J52: =+Alemela!L43 -> 30000 | K52: =H52+I52-J52 -> 23063.351
A53: 52 | B53: Nalatwad(PKG-1) | C53: Shri Pawad Basaweshwar Petroleums | D53: =+Nalatwad!E43 -> 1116.98 | E53: =+Nalatwad!G43 -> 111072.49 | F53: =+Nalatwad!H43 -> 77.73 | G53: =+Nalatwad!J43 -> 8670.7815 | H53: =E53+G53 -> 119743.27 | I53: =+Nalatwad!M3 -> 15663.641 | J53: =+Nalatwad!L43 -> 0 | K53: =H53+I53-J53 -> 135406.91
A54: 53 | B54: Srirangapatna | C54: Anupama F/S | D54: =+Srirangapatna!E35 -> 0 | E54: =+Srirangapatna!G35 -> 0 | F54: =+Srirangapatna!H35 -> 37.34 | G54: =+Srirangapatna!J35 -> 4197.4014 | H54: =E54+G54 -> 4197.4014 | I54: 0 | J54: =+Srirangapatna!L35 -> 4197.4014 | K54: =H54+I54-J54 -> 0
A55: 54 | B55: HO(DG) | C55: Multiple bunks | D55: =+'HO(DG)'!E48 -> 1263.73 | E55: =+'HO(DG)'!G48 -> 131124.62 | F55: =+'HO(DG)'!H48 -> 0 | G55: =+'HO(DG)'!J48 -> 0 | H55: =E55+G55 -> 131124.62 | I55: =+'HO(DG)'!M3 -> 0 | J55: =+'HO(DG)'!L48 -> 131124.62 | K55: =H55+I55-J55 -> 0
A56: Total | D56: =SUM(D2:D55) -> 255633.74 | E56: =SUM(E2:E55) -> 26209717 | F56: =SUM(F2:F55) -> 6129.37 | G56: =SUM(G2:G55) -> 694868.19 | H56: =SUM(H2:H55) -> 26904586 | I56: =SUM(I2:I55) -> 8252210.8 | J56: =SUM(J2:J55) -> 13701590 | K56: =H56+I56-J56 -> 21455207
I57: 36038811 | K57: 21493063
I58: =I56-I57 -> -27786601 | K58: =K56-K57 -> -37856.16
A61: S.no | B61: Site Name | C61: Bunk Name | D61: Diesel(Liters) | E61: Diesel Amount | F61: Petrol(Liters) | G61: Petrol Amount | H61: Total Amount | I61: Opening Blance | J61: Amount Paid | K61: Closing Balances
A62: 39 | B62: {=VLOOKUP(A62,A1:K54,{2,3,4,5,6,7,8,9,10,11},FALSE)} -> Guttal-2 | C62: Himagiri Petroleum | D62: 8814 | E62: 877874.4 | F62: 208 | G62: 23235.68 | H62: 901110.08 | I62: 408499.98 | J62: 850000 | K62: 459610.06
B64: Site Name | C64: Bunk Name | D64: Diesel(Liters) | E64: Diesel Amount | F64: Petrol(Liters) | G64: Petrol Amount | H64: Total Amount | I64: Opening Blance | J64: Amount Paid | K64: Closing Balances
B65: Jalgaon-2 | C65: {=VLOOKUP(B65,B1:K54,{2,3,4,5,6,7,8,9,10},FALSE)} -> Nayara | D65: 5431 | E65: 540438.81 | F65: 130 | G65: 14713.4 | H65: 555152.21 | I65: 50000.028 | J65: 0 | K65: 605152.24
B72: 60000
B73: 18000
B74: 18000
B75: 75000
B76: 360000

Sheet HO(DG)
A2: S.No | B2: Date | C2: GRN No | D2: Ind No/Bill No | E2: Diesel (Lts) | F2: Price | G2: Amount | H2: Petrol (Lts) | I2: Price | J2: Amount | K2: Total amount | L2: Amount paid | M2: As on date | N2: Remarks
A3: Opening Balance | K3: 0 | M3: 0
A4: 1 | B4: 46266 | G4: =E4*F4 -> 0 | H4: 0 | I4: 0 | J4: =H4*I4 -> 0 | K4: =G4+J4 -> 0 | L4: 0 | M4: =M3+K4-L4 -> 0
A5: 2 | B5: 46267 | E5: 100 | F5: 103.76 | G5: =E5*F5 -> 10376 | K5: =G5+J5 -> 10376 | L5: 10376 | M5: =M4+K5-L5 -> 0
A6: 3 | B6: 46268 | G6: =E6*F6 -> 0 | K6: =G6+J6 -> 0 | M6: =M5+K6-L6 -> 0
A7: 4 | B7: 46269 | E7: 50 | F7: 103.76 | G7: =E7*F7 -> 5188 | K7: =G7+J7 -> 5188 | L7: =H7+K7 -> 5188 | M7: =M6+K7-L7 -> 0
A8: 5 | B8: 46270 | E8: 50 | F8: 103.76 | G8: =E8*F8 -> 5188 | K8: =G8+J8 -> 5188 | L8: 5188 | M8: =M7+K8-L8 -> 0
A9: 6 | B9: 46271 | G9: =E9*F9 -> 0 | K9: =G9+J9 -> 0 | M9: =M8+K9-L9 -> 0
A10: 7 | B10: 46272 | E10: 100 | F10: 103.76 | G10: =E10*F10 -> 10376 | K10: =G10+J10 -> 10376 | L10: =H10+K10 -> 10376 | M10: =M9+K10-L10 -> 0
A11: 8 | B11: 46273 | G11: =E11*F11 -> 0 | K11: =G11+J11 -> 0 | M11: =M10+K11-L11 -> 0
A12: 9 | B12: 46274 | E12: 50 | F12: 103.76 | G12: =E12*F12 -> 5188 | K12: =G12+J12 -> 5188 | L12: 5188 | M12: =M11+K12-L12 -> 0
A13: 10 | B13: 46275 | E13: 100 | F13: 103.76 | G13: =E13*F13 -> 10376 | K13: =G13+J13 -> 10376 | L13: 10376 | M13: =M12+K13-L13 -> 0
A14: 11 | B14: 46276 | G14: =E14*F14 -> 0 | K14: =G14+J14 -> 0 | M14: =M13+K14-L14 -> 0
A15: 12 | B15: 46277 | E15: 50 | F15: 103.76 | G15: =E15*F15 -> 5188 | K15: =G15+J15 -> 5188 | L15: =H15+K15 -> 5188 | M15: =M14+K15-L15 -> 0
A16: 13 | B16: 46278 | G16: =E16*F16 -> 0 | K16: =G16+J16 -> 0 | M16: =M15+K16-L16 -> 0
A17: 14 | B17: 46279 | G17: =E17*F17 -> 0 | K17: =G17+J17 -> 0 | M17: =M16+K17-L17 -> 0
A18: 15 | B18: 46280 | E18: 50 | F18: 103.76 | G18: =E18*F18 -> 5188 | K18: =G18+J18 -> 5188 | L18: 5188 | M18: =M17+K18-L18 -> 0
A19: 16 | B19: 46281 | G19: =E19*F19 -> 0 | K19: =G19+J19 -> 0 | L19: =H19+K19 -> 0 | M19: =M18+K19-L19 -> 0
A20: 17 | B20: 46282 | E20: 100 | F20: 103.76 | G20: =E20*F20 -> 10376 | K20: =G20+J20 -> 10376 | L20: 10376 | M20: =M19+K20-L20 -> 0
A21: 18 | B21: 46283 | G21: =E21*F21 -> 0 | K21: =G21+J21 -> 0 | M21: =M20+K21-L21 -> 0
A22: 19 | B22: 46284 | E22: 90 | F22: 103.76 | G22: =E22*F22 -> 9338.4 | K22: =G22+J22 -> 9338.4 | L22: 9338.4 | M22: =M21+K22-L22 -> 0
A23: 20 | B23: 46285 | G23: =E23*F23 -> 0 | K23: =G23+J23 -> 0 | M23: =M22+K23-L23 -> 0
A24: 21 | B24: 46286 | E24: 40 | F24: 103.76 | G24: =E24*F24 -> 4150.4 | K24: =G24+J24 -> 4150.4 | L24: =H24+K24 -> 4150.4 | M24: =M23+K24-L24 -> 0
A25: 22 | B25: 46287 | E25: 100 | F25: 103.76 | G25: =E25*F25 -> 10376 | K25: =G25+J25 -> 10376 | L25: =H25+K25 -> 10376 | M25: =M24+K25-L25 -> 0
A26: 23 | B26: 46288 | E26: 50 | F26: 103.76 | G26: =E26*F26 -> 5188 | K26: =G26+J26 -> 5188 | L26: =H26+K26 -> 5188 | M26: =M25+K26-L26 -> 0
A27: 24 | B27: 46289 | E27: 33.73 | F27: 103.76 | G27: =E27*F27 -> 3499.8248 | K27: =G27+J27 -> 3499.8248 | L27: =H27+K27 -> 3499.8248 | M27: =M26+K27-L27 -> 0
A28: 25 | B28: 46290 | E28: 50 | F28: 103.76 | G28: =E28*F28 -> 5188 | K28: =G28+J28 -> 5188 | L28: =H28+K28 -> 5188 | M28: =M27+K28-L28 -> 0
A29: 26 | B29: 46291 | E29: 50 | F29: 103.76 | G29: =E29*F29 -> 5188 | K29: =G29+J29 -> 5188 | L29: =H29+K29 -> 5188 | M29: =M28+K29-L29 -> 0
A30: 27 | B30: 46292 | G30: =E30*F30 -> 0 | K30: =G30+J30 -> 0 | L30: =H30+K30 -> 0 | M30: =M29+K30-L30 -> 0
A31: 28 | B31: 46293 | E31: 50 | F31: 103.76 | G31: =E31*F31 -> 5188 | K31: =G31+J31 -> 5188 | L31: =H31+K31 -> 5188 | M31: =M30+K31-L31 -> 0
B32: 46293 | E32: 50 | F32: 103.76 | G32: =E32*F32 -> 5188 | K32: =G32+J32 -> 5188 | L32: =H32+K32 -> 5188
A33: 29 | B33: 46294 | G33: =E33*F33 -> 0 | K33: =G33+J33 -> 0 | L33: =H33+K33 -> 0 | M33: =M31+K33-L33 -> 0
A34: 30 | B34: 46295 | E34: 100 | F34: 103.76 | G34: =E34*F34 -> 10376 | K34: =G34+J34 -> 10376 | L34: =H34+K34 -> 10376 | M34: =M33+K34-L34 -> 0
A35: 31 | B35: 46296 | G35: =E35*F35 -> 0 | K35: =G35+J35 -> 0 | L35: =H35+K35 -> 0 | M35: =M34+K35-L35 -> 0
A36: 32 | B36: 46297 | G36: =E36*F36 -> 0 | K36: =G36+J36 -> 0 | L36: =H36+K36 -> 0 | M36: =M35+K36-L36 -> 0
A37: 33 | G37: =E37*F37 -> 0 | K37: =G37+J37 -> 0 | M37: =M36+K37-L37 -> 0
A38: 34 | K38: =G38+J38 -> 0 | M38: =M37+K38-L38 -> 0
A39: 35 | M39: =M38+K39-L39 -> 0
A40: 36 | M40: =M39+K40-L40 -> 0
A41: 37
A42: 38
A43: 39
A44: 40
A45: 41
A46: 42 | O46: 2669494 | P46: =O46-M46 -> 2669494
E47: 0 | F47: 0 | G47: =E47*F47 -> 0 | J47: =H47*I47 -> 0 | K47: =G47+J47 -> 0 | M47: =M46+K47-L47 -> 0
E48: =SUM(E4:E46) -> 1263.73 | G48: =SUM(G4:G46) -> 131124.62 | H48: =SUM(H4:H46) -> 0 | J48: =SUM(J4:J46) -> 0 | K48: =SUM(K4:K46) -> 131124.62 | L48: =SUM(L4:L46) -> 131124.62
M57: 2408309
M58: 5327.86
M59: =M57-M58 -> 2402981.1

Sheet Khammam-1
A1: Divya laxmi ganapathi
A2: S.No | B2: Date | C2: GRN No | D2: Ind No/Bill No | E2: Diesel (Lts) | F2: Price | G2: Amount | H2: Petrol (Lts) | I2: Price | J2: Amount | K2: Total amount | L2: Amount paid | M2: As 0n Date | N2: Remarks
A3: Opening Balance | K3: 2805565.2 | M3: 2805565.2 | O3: =K3-M3 -> 0
A4: 1 | B4: 46266 | E4: 2700 | F4: 103.8 | G4: =E4*F4 -> 280260 | K4: =G4+J4 -> 280260 | L4: 2826324 | M4: =M3+K4-L4 -> 259501.16
A5: 2 | B5: 46267 | G5: =E5*F5 -> 0 | J5: =H5*I5 -> 0 | K5: =G5+J5 -> 0 | M5: =M4+K5-L5 -> 259501.16
A6: 3 | B6: 46268 | G6: =E6*F6 -> 0 | J6: =H6*I6 -> 0 | K6: =G6+J6 -> 0 | M6: =M5+K6-L6 -> 259501.16
A7: 4 | B7: 46269 | E7: 2700 | F7: 103.8 | G7: =E7*F7 -> 280260 | J7: =H7*I7 -> 0 | K7: =G7+J7 -> 280260 | M7: =M6+K7-L7 -> 539761.16
A8: 5 | B8: 46270 | G8: =E8*F8 -> 0 | J8: =H8*I8 -> 0 | K8: =G8+J8 -> 0 | M8: =M7+K8-L8 -> 539761.16
A9: 6 | B9: 46271 | G9: =E9*F9 -> 0 | J9: =H9*I9 -> 0 | K9: =G9+J9 -> 0 | M9: =M8+K9-L9 -> 539761.16
A10: 7 | B10: 46272 | E10: 2700 | F10: 103.8 | G10: =E10*F10 -> 280260 | H10: 55 | I10: 115.69 | J10: =H10*I10 -> 6362.95 | K10: =G10+J10 -> 286622.95 | M10: =M9+K10-L10 -> 826384.11
A11: 8 | B11: 46273 | E11: 2800 | F11: 103.8 | G11: =E11*F11 -> 290640 | J11: =H11*I11 -> 0 | K11: =G11+J11 -> 290640 | M11: =M10+K11-L11 -> 1117024.1
A12: 9 | B12: 46274 | G12: =E12*F12 -> 0 | J12: =H12*I12 -> 0 | K12: =G12+J12 -> 0 | M12: =M11+K12-L12 -> 1117024.1
A13: 10 | B13: 46275 | E13: 2700 | F13: 103.8 | G13: =E13*F13 -> 280260 | J13: =H13*I13 -> 0 | K13: =G13+J13 -> 280260 | M13: =M12+K13-L13 -> 1397284.1
A14: 11 | B14: 46276 | E14: 2700 | F14: 103.8 | G14: =E14*F14 -> 280260 | J14: =H14*I14 -> 0 | K14: =G14+J14 -> 280260 | M14: =M13+K14-L14 -> 1677544.1
A15: 12 | B15: 46277 | G15: =E15*F15 -> 0 | J15: =H15*I15 -> 0 | K15: =G15+J15 -> 0 | M15: =M14+K15-L15 -> 1677544.1
A16: 13 | B16: 46278 | G16: =E16*F16 -> 0 | H16: 130 | I16: 115.69 | J16: =H16*I16 -> 15039.7 | K16: =G16+J16 -> 15039.7 | M16: =M15+K16-L16 -> 1692583.8
A17: 14 | B17: 46279 | G17: =E17*F17 -> 0 | J17: =H17*I17 -> 0 | K17: =G17+J17 -> 0 | M17: =M16+K17-L17 -> 1692583.8
A18: 15 | B18: 46280 | G18: =E18*F18 -> 0 | J18: =H18*I18 -> 0 | K18: =G18+J18 -> 0 | M18: =M17+K18-L18 -> 1692583.8
A19: 16 | B19: 46281 | E19: 2700 | F19: 103.8 | G19: =E19*F19 -> 280260 | J19: =H19*I19 -> 0 | K19: =G19+J19 -> 280260 | M19: =M18+K19-L19 -> 1972843.8
A20: 17 | B20: 46282 | G20: =E20*F20 -> 0 | J20: =H20*I20 -> 0 | K20: =G20+J20 -> 0 | M20: =M19+K20-L20 -> 1972843.8
A21: 18 | B21: 46283 | E21: 2700 | F21: 103.8 | G21: =E21*F21 -> 280260 | J21: =H21*I21 -> 0 | K21: =G21+J21 -> 280260 | M21: =M20+K21-L21 -> 2253103.8
A22: 19 | B22: 46284 | E22: 3000 | F22: 103.8 | G22: =E22*F22 -> 311400 | J22: =H22*I22 -> 0 | K22: =G22+J22 -> 311400 | M22: =M21+K22-L22 -> 2564503.8
A23: 20 | B23: 46285 | G23: =E23*F23 -> 0 | J23: =H23*I23 -> 0 | K23: =G23+J23 -> 0 | M23: =M22+K23-L23 -> 2564503.8
A24: 21 | B24: 46286 | E24: 2700 | F24: 103.8 | G24: =E24*F24 -> 280260 | J24: =H24*I24 -> 0 | K24: =G24+J24 -> 280260 | M24: =M23+K24-L24 -> 2844763.8
A25: 22 | B25: 46287 | E25: 800 | F25: 103.8 | G25: =E25*F25 -> 83040 | J25: =H25*I25 -> 0 | K25: =G25+J25 -> 83040 | M25: =M24+K25-L25 -> 2927803.8
A26: 23 | B26: 46288 | G26: =E26*F26 -> 0 | J26: =H26*I26 -> 0 | K26: =G26+J26 -> 0 | M26: =M25+K26-L26 -> 2927803.8
A27: 24 | B27: 46289 | E27: 2500 | F27: 103.8 | G27: =E27*F27 -> 259500 | J27: =H27*I27 -> 0 | K27: =G27+J27 -> 259500 | M27: =M26+K27-L27 -> 3187303.8
A28: 25 | B28: 46290 | E28: 3700 | F28: 103.8 | G28: =E28*F28 -> 384060 | J28: =H28*I28 -> 0 | K28: =G28+J28 -> 384060 | M28: =M27+K28-L28 -> 3571363.8
A29: 26 | B29: 46291 | G29: =E29*F29 -> 0 | J29: =H29*I29 -> 0 | K29: =G29+J29 -> 0 | M29: =M28+K29-L29 -> 3571363.8
A30: 27 | B30: 46292 | G30: =E30*F30 -> 0 | J30: =H30*I30 -> 0 | K30: =G30+J30 -> 0 | M30: =M29+K30-L30 -> 3571363.8
A31: 28 | B31: 46293 | G31: =E31*F31 -> 0 | J31: =H31*I31 -> 0 | K31: =G31+J31 -> 0 | M31: =M30+K31-L31 -> 3571363.8
A32: 29 | B32: 46294 | E32: 2700 | F32: 103.8 | G32: =E32*F32 -> 280260 | J32: =H32*I32 -> 0 | K32: =G32+J32 -> 280260 | M32: =M31+K32-L32 -> 3851623.8
A33: 30 | B33: 46295 | E33: 2700 | F33: 103.8 | G33: =E33*F33 -> 280260 | J33: =H33*I33 -> 0 | K33: =G33+J33 -> 280260 | M33: =M32+K33-L33 -> 4131883.8
A34: 31 | B34: 46296 | G34: =E34*F34 -> 0 | K34: =G34+J34 -> 0 | M34: =M33+K34-L34 -> 4131883.8
A35: 32 | G35: =E35*F35 -> 0 | J35: =H35*I35 -> 0 | K35: =G35+J35 -> 0 | M35: =M34+K35-L35 -> 4131883.8
A36: 33 | G36: =E36*F36 -> 0 | J36: =H36*I36 -> 0 | K36: =G36+J36 -> 0
A37: 34 | G37: =E37*F37 -> 0 | J37: =H37*I37 -> 0 | K37: =G37+J37 -> 0
E38: =SUM(E3:E37) -> 39800 | G38: =SUM(G3:G37) -> 4131240 | H38: =SUM(H3:H37) -> 185 | J38: =SUM(J3:J37) -> 21402.65 | K38: =SUM(K4:K37) -> 4152642.6 | L38: =SUM(L3:L37) -> 2826324

Sheet Khammam-2
A1: Jayasai union bunk
A2: S.No | B2: Date | C2: GRN No | D2: Ind No/Bill No | E2: Diesel (Lts) | F2: Price | G2: Amount | H2: Petrol (Lts) | I2: Price | J2: Amount | K2: Total amount | L2: Amount paid | M2: As 0n Date | N2: Remarks
A3: Opening Balance | K3: 0 | M3: 0
A4: 1 | B4: 46266 | G4: =E4*F4 -> 0 | J4: =H4*I4 -> 0 | K4: =G4+J4 -> 0 | M4: =M3+K4-L4 -> 0
A5: 2 | B5: 46267 | E5: 2500 | F5: 103.82 | G5: =E5*F5 -> 259550 | J5: =H5*I5 -> 0 | K5: =G5+J5 -> 259550 | M5: =M4+K5-L5 -> 259550
A6: 3 | B6: 46268 | G6: =E6*F6 -> 0 | J6: =H6*I6 -> 0 | K6: =G6+J6 -> 0 | M6: =M5+K6-L6 -> 259550
A7: 4 | B7: 46269 | G7: =E7*F7 -> 0 | J7: =H7*I7 -> 0 | K7: =G7+J7 -> 0 | M7: =M6+K7-L7 -> 259550
A8: 5 | B8: 46270 | E8: 2800 | F8: 103.82 | G8: =E8*F8 -> 290696 | J8: =H8*I8 -> 0 | K8: =G8+J8 -> 290696 | M8: =M7+K8-L8 -> 550246
A9: 6 | B9: 46271 | G9: =E9*F9 -> 0 | J9: =H9*I9 -> 0 | K9: =G9+J9 -> 0 | M9: =M8+K9-L9 -> 550246
A10: 7 | B10: 46272 | E10: 2700 | F10: 103.82 | G10: =E10*F10 -> 280314 | J10: =H10*I10 -> 0 | K10: =G10+J10 -> 280314 | M10: =M9+K10-L10 -> 830560
A11: 8 | B11: 46273 | E11: 2700 | F11: 103.82 | G11: =E11*F11 -> 280314 | H11: 50 | I11: 115.72 | J11: =H11*I11 -> 5786 | K11: =G11+J11 -> 286100 | M11: =M10+K11-L11 -> 1116660
A12: 9 | B12: 46274 | G12: =E12*F12 -> 0 | J12: =H12*I12 -> 0 | K12: =G12+J12 -> 0 | M12: =M11+K12-L12 -> 1116660
A13: 10 | B13: 46275 | E13: 2700 | F13: 103.82 | G13: =E13*F13 -> 280314 | J13: =H13*I13 -> 0 | K13: =G13+J13 -> 280314 | M13: =M12+K13-L13 -> 1396974 | V13: 250000
A14: 11 | B14: 46276 | E14: 2700 | F14: 103.82 | G14: =E14*F14 -> 280314 | J14: =H14*I14 -> 0 | K14: =G14+J14 -> 280314 | M14: =M13+K14-L14 -> 1677288 | V14: 70000
A15: 12 | B15: 46277 | E15: 3900 | F15: 103.82 | G15: =E15*F15 -> 404898 | J15: =H15*I15 -> 0 | K15: =G15+J15 -> 404898 | M15: =M14+K15-L15 -> 2082186 | V15: 46366
A16: 13 | B16: 46278 | G16: =E16*F16 -> 0 | J16: =H16*I16 -> 0 | K16: =G16+J16 -> 0 | M16: =M15+K16-L16 -> 2082186
A17: 14 | B17: 46279 | E17: 1200 | F17: 103.82 | G17: =E17*F17 -> 124584 | J17: =H17*I17 -> 0 | K17: =G17+J17 -> 124584 | M17: =M16+K17-L17 -> 2206770
A18: 15 | B18: 46280 | G18: =E18*F18 -> 0 | J18: =H18*I18 -> 0 | K18: =G18+J18 -> 0 | M18: =M17+K18-L18 -> 2206770
A19: 16 | B19: 46281 | E19: 2700 | F19: 103.82 | G19: =E19*F19 -> 280314 | J19: =H19*I19 -> 0 | K19: =G19+J19 -> 280314 | M19: =M18+K19-L19 -> 2487084
A20: 17 | B20: 46282 | G20: =E20*F20 -> 0 | J20: =H20*I20 -> 0 | K20: =G20+J20 -> 0 | M20: =M19+K20-L20 -> 2487084
A21: 18 | B21: 46283 | G21: =E21*F21 -> 0 | J21: =H21*I21 -> 0 | K21: =G21+J21 -> 0 | M21: =M20+K21-L21 -> 2487084
A22: 19 | B22: 46284 | G22: =E22*F22 -> 0 | J22: =H22*I22 -> 0 | K22: =G22+J22 -> 0 | M22: =M21+K22-L22 -> 2487084
A23: 20 | B23: 46285 | G23: =E23*F23 -> 0 | J23: =H23*I23 -> 0 | K23: =G23+J23 -> 0 | M23: =M22+K23-L23 -> 2487084
A24: 21 | B24: 46286 | E24: 5400 | F24: 103.82 | G24: =E24*F24 -> 560628 | J24: =H24*I24 -> 0 | K24: =G24+J24 -> 560628 | M24: =M23+K24-L24 -> 3047712
B25: 46286 | D25: 26-27/S1 (MP3 Grease) | E25: 546 | F25: 332.76 | G25: =E25*F25 -> 181686.96 | K25: =G25+J25 -> 181686.96 | M25: =M24+K25-L25 -> 3229399
A26: 22 | B26: 46287 | G26: =E26*F26 -> 0 | J26: =H26*I26 -> 0 | K26: =G26+J26 -> 0 | M26: =M25+K26-L26 -> 3229399
A27: 23 | B27: 46288 | E27: 2700 | F27: 103.82 | G27: =E27*F27 -> 280314 | J27: =H27*I27 -> 0 | K27: =G27+J27 -> 280314 | M27: =M26+K27-L27 -> 3509713
A28: 24 | B28: 46289 | E28: 2700 | F28: 103.82 | G28: =E28*F28 -> 280314 | H28: 55 | I28: 115.72 | J28: =H28*I28 -> 6364.6 | K28: =G28+J28 -> 286678.6 | M28: =M27+K28-L28 -> 3796391.6
A29: 25 | B29: 46290 | G29: =E29*F29 -> 0 | J29: =H29*I29 -> 0 | K29: =G29+J29 -> 0 | M29: =M28+K29-L29 -> 3796391.6
A30: 26 | B30: 46291 | E30: 2700 | F30: 103.82 | G30: =E30*F30 -> 280314 | H30: 50 | I30: 115.72 | J30: =H30*I30 -> 5786 | K30: =G30+J30 -> 286100 | M30: =M29+K30-L30 -> 4082491.6
A31: 27 | B31: 46292 | E31: 800 | F31: 103.82 | G31: =E31*F31 -> 83056 | J31: =H31*I31 -> 0 | K31: =G31+J31 -> 83056 | M31: =M30+K31-L31 -> 4165547.6
A32: 28 | B32: 46293 | E32: 800 | F32: 103.82 | G32: =E32*F32 -> 83056 | J32: =H32*I32 -> 0 | K32: =G32+J32 -> 83056 | M32: =M31+K32-L32 -> 4248603.6
A33: 29 | B33: 46294 | G33: =E33*F33 -> 0 | J33: =H33*I33 -> 0 | K33: =G33+J33 -> 0 | M33: =M32+K33-L33 -> 4248603.6
A34: 30 | B34: 46295 | G34: =E34*F34 -> 0 | J34: =H34*I34 -> 0 | K34: =G34+J34 -> 0 | M34: =M33+K34-L34 -> 4248603.6
A35: 31 | B35: 46296 | G35: =E35*F35 -> 0 | J35: =H35*I35 -> 0 | K35: =G35+J35 -> 0 | M35: =M34+K35-L35 -> 4248603.6
A36: 32 | G36: =E36*F36 -> 0 | J36: =H36*I36 -> 0 | K36: =G36+J36 -> 0 | M36: =M35+K36-L36 -> 4248603.6
A37: 33 | G37: =E37*F37 -> 0 | J37: =H37*I37 -> 0 | K37: =G37+J37 -> 0 | M37: =M36+K37-L37 -> 4248603.6
E39: =SUM(E4:E37) -> 39546 | G39: =SUM(G4:G37) -> 4230667 | H39: =SUM(H4:H37) -> 155 | J39: =SUM(J4:J37) -> 17936.6 | K39: =SUM(K4:K37) -> 4248603.6 | L39: =SUM(L4:L37) -> 0

Sheet Khammam-4
A1: Sai Madeana Filling Station
A2: S.No | B2: Date | C2: GRN No | D2: Ind No/Bill No | E2: Diesel (Lts) | F2: Price | G2: Amount | H2: Petrol (Lts) | I2: Price | J2: Amount | K2: Total amount | L2: Amount paid | M2: As 0n Date | N2: Remarks
A3: Opening Balance | K3: 843364.3 | M3: 843364.3
A4: 1 | B4: 46235 | G4: =E4*F4 -> 0 | J4: =H4*I4 -> 0 | K4: =G4+J4 -> 0 | M4: =M3+K4-L4 -> 843364.3
A5: 2 | B5: 46236 | G5: =E5*F5 -> 0 | J5: =H5*I5 -> 0 | K5: =G5+J5 -> 0 | M5: =M4+K5-L5 -> 843364.3
A6: 3 | B6: 46237 | E6: 2700 | F6: 103.62 | G6: =E6*F6 -> 279774 | H6: 40 | I6: 115.49 | J6: =H6*I6 -> 4619.6 | K6: =G6+J6 -> 284393.6 | M6: =M5+K6-L6 -> 1127757.9
A7: 4 | B7: 46238 | G7: =E7*F7 -> 0 | J7: =H7*I7 -> 0 | K7: =G7+J7 -> 0 | M7: =M6+K7-L7 -> 1127757.9
A8: 5 | B8: 46239 | G8: =E8*F8 -> 0 | J8: =H8*I8 -> 0 | K8: =G8+J8 -> 0 | M8: =M7+K8-L8 -> 1127757.9
A9: 6 | B9: 46240 | E9: 2700 | F9: 103.62 | G9: =E9*F9 -> 279774 | H9: 90 | I9: 115.49 | J9: =H9*I9 -> 10394.1 | K9: =G9+J9 -> 290168.1 | M9: =M8+K9-L9 -> 1417926
A10: 7 | B10: 46241 | G10: =E10*F10 -> 0 | J10: =H10*I10 -> 0 | K10: =G10+J10 -> 0 | M10: =M9+K10-L10 -> 1417926
A11: 8 | B11: 46242 | E11: 2700 | F11: 103.62 | G11: =E11*F11 -> 279774 | H11: 35 | I11: 115.49 | J11: =H11*I11 -> 4042.15 | K11: =G11+J11 -> 283816.15 | M11: =M10+K11-L11 -> 1701742.1
A12: 9 | B12: 46243 | G12: =E12*F12 -> 0 | J12: =H12*I12 -> 0 | K12: =G12+J12 -> 0 | M12: =M11+K12-L12 -> 1701742.1
A13: 10 | B13: 46244 | E13: 2700 | F13: 103.62 | G13: =E13*F13 -> 279774 | H13: 55 | I13: 115.49 | J13: =H13*I13 -> 6351.95 | K13: =G13+J13 -> 286125.95 | M13: =M12+K13-L13 -> 1987868.1
A14: 11 | B14: 46245 | G14: =E14*F14 -> 0 | J14: =H14*I14 -> 0 | K14: =G14+J14 -> 0 | M14: =M13+K14-L14 -> 1987868.1
A15: 12 | B15: 46246 | G15: =E15*F15 -> 0 | J15: =H15*I15 -> 0 | K15: =G15+J15 -> 0 | M15: =M14+K15-L15 -> 1987868.1
A16: 13 | B16: 46247 | G16: =E16*F16 -> 0 | J16: =H16*I16 -> 0 | K16: =G16+J16 -> 0 | M16: =M15+K16-L16 -> 1987868.1
A17: 14 | B17: 46248 | G17: =E17*F17 -> 0 | J17: =H17*I17 -> 0 | K17: =G17+J17 -> 0 | M17: =M16+K17-L17 -> 1987868.1
A18: 15 | B18: 46249 | G18: =E18*F18 -> 0 | J18: =H18*I18 -> 0 | K18: =G18+J18 -> 0 | M18: =M17+K18-L18 -> 1987868.1
A19: 16 | B19: 46250 | G19: =E19*F19 -> 0 | J19: =H19*I19 -> 0 | K19: =G19+J19 -> 0 | M19: =M18+K19-L19 -> 1987868.1
A20: 17 | B20: 46251 | E20: 2700 | F20: 103.62 | G20: =E20*F20 -> 279774 | H20: 75 | I20: 115.49 | J20: =H20*I20 -> 8661.75 | K20: =G20+J20 -> 288435.75 | M20: =M19+K20-L20 -> 2276303.8
A21: 18 | B21: 46252 | G21: =E21*F21 -> 0 | J21: =H21*I21 -> 0 | K21: =G21+J21 -> 0 | M21: =M20+K21-L21 -> 2276303.8
A22: 19 | B22: 46253 | E22: 2700 | F22: 103.62 | G22: =E22*F22 -> 279774 | H22: 75 | I22: 115.49 | J22: =H22*I22 -> 8661.75 | K22: =G22+J22 -> 288435.75 | M22: =M21+K22-L22 -> 2564739.6
A23: 20 | B23: 46254 | G23: =E23*F23 -> 0 | J23: =H23*I23 -> 0 | K23: =G23+J23 -> 0 | M23: =M22+K23-L23 -> 2564739.6
A24: 21 | B24: 46255 | G24: =E24*F24 -> 0 | J24: =H24*I24 -> 0 | K24: =G24+J24 -> 0 | M24: =M23+K24-L24 -> 2564739.6
A25: 22 | B25: 46256 | E25: 2700 | F25: 103.62 | G25: =E25*F25 -> 279774 | H25: 75 | I25: 115.49 | J25: =H25*I25 -> 8661.75 | K25: =G25+J25 -> 288435.75 | M25: =M24+K25-L25 -> 2853175.3
A26: 23 | B26: 46257 | G26: =E26*F26 -> 0 | J26: =H26*I26 -> 0 | K26: =G26+J26 -> 0 | M26: =M25+K26-L26 -> 2853175.3
A27: 24 | B27: 46258 | G27: =E27*F27 -> 0 | J27: =H27*I27 -> 0 | K27: =G27+J27 -> 0 | M27: =M26+K27-L27 -> 2853175.3
A28: 25 | B28: 46259 | G28: =E28*F28 -> 0 | J28: =H28*I28 -> 0 | K28: =G28+J28 -> 0 | M28: =M27+K28-L28 -> 2853175.3
A29: 26 | B29: 46260 | G29: =E29*F29 -> 0 | J29: =H29*I29 -> 0 | K29: =G29+J29 -> 0 | M29: =M28+K29-L29 -> 2853175.3
A30: 27 | B30: 46261 | G30: =E30*F30 -> 0 | J30: =H30*I30 -> 0 | K30: =G30+J30 -> 0 | M30: =M29+K30-L30 -> 2853175.3
A31: 28 | B31: 46262 | E31: 2700 | F31: 103.62 | G31: =E31*F31 -> 279774 | H31: 75 | I31: 115.49 | J31: =H31*I31 -> 8661.75 | K31: =G31+J31 -> 288435.75 | M31: =M30+K31-L31 -> 3141611.1
A32: 29 | B32: 46263 | E32: 2700 | F32: 103.62 | G32: =E32*F32 -> 279774 | H32: 20 | I32: 115.49 | J32: =H32*I32 -> 2309.8 | K32: =G32+J32 -> 282083.8 | L32: 282083.8 | M32: =M31+K32-L32 -> 3141611.1
A33: 30 | B33: 46264 | E33: 2700 | F33: 103.62 | G33: =E33*F33 -> 279774 | H33: 55 | I33: 115.49 | J33: =H33*I33 -> 6351.95 | K33: =G33+J33 -> 286125.95 | L33: 286125.95 | M33: =M32+K33-L33 -> 3141611.1
A34: 31 | B34: 46265 | G34: =E34*F34 -> 0 | J34: =H34*I34 -> 0 | K34: =G34+J34 -> 0 | M34: =M33+K34-L34 -> 3141611.1
E35: =SUM(E4:E34) -> 27000 | G35: =SUM(G4:G34) -> 2797740 | H35: =SUM(H4:H34) -> 595 | J35: =SUM(J4:J34) -> 68716.55 | K35: =SUM(K4:K34) -> 2866456.5 | L35: =SUM(L4:L34) -> 568209.75

Sheet  Khammam-5
A1: Vajra mahalakshmi filling station
A2: S.No | B2: Date | C2: GRN No | D2: Ind No/Bill No | E2: Diesel (Lts) | F2: Price | G2: Amount | H2: Petrol (Lts) | I2: Price | J2: Amount | K2: Total amount | L2: Amount paid | M2: As 0n Date | N2: Remarks
A3: Opening Balance | K3: 578571.8 | M3: 578571.8
A4: 1 | B4: 46266 | E4: 2800 | F4: 103.62 | G4: =E4*F4 -> 290136 | H4: 75 | I4: 115.49 | J4: =H4*I4 -> 8661.75 | K4: =G4+J4 -> 298797.75 | M4: =M3+K4-L4 -> 877369.55
A5: 2 | B5: 46267 | E5: 2700 | F5: 103.62 | G5: =E5*F5 -> 279774 | H5: 35 | I5: 115.49 | J5: =H5*I5 -> 4042.15 | K5: =G5+J5 -> 283816.15 | M5: =M4+K5-L5 -> 1161185.7
A6: 3 | B6: 46268 | G6: =E6*F6 -> 0 | J6: =H6*I6 -> 0 | K6: =G6+J6 -> 0 | M6: =M5+K6-L6 -> 1161185.7
A7: 4 | B7: 46269 | G7: =E7*F7 -> 0 | J7: =H7*I7 -> 0 | K7: =G7+J7 -> 0 | M7: =M6+K7-L7 -> 1161185.7
A8: 5 | B8: 46270 | G8: =E8*F8 -> 0 | J8: =H8*I8 -> 0 | K8: =G8+J8 -> 0 | M8: =M7+K8-L8 -> 1161185.7
A9: 6 | B9: 46271 | G9: =E9*F9 -> 0 | J9: =H9*I9 -> 0 | K9: =G9+J9 -> 0 | M9: =M8+K9-L9 -> 1161185.7
A10: 7 | B10: 46272 | G10: =E10*F10 -> 0 | J10: =H10*I10 -> 0 | K10: =G10+J10 -> 0 | M10: =M9+K10-L10 -> 1161185.7
A11: 8 | B11: 46273 | G11: =E11*F11 -> 0 | J11: =H11*I11 -> 0 | K11: =G11+J11 -> 0 | M11: =M10+K11-L11 -> 1161185.7
A12: 9 | B12: 46274 | G12: =E12*F12 -> 0 | J12: =H12*I12 -> 0 | K12: =G12+J12 -> 0 | M12: =M11+K12-L12 -> 1161185.7
A13: 10 | B13: 46275 | G13: =E13*F13 -> 0 | J13: =H13*I13 -> 0 | K13: =G13+J13 -> 0 | M13: =M12+K13-L13 -> 1161185.7
A14: 11 | B14: 46276 | G14: =E14*F14 -> 0 | J14: =H14*I14 -> 0 | K14: =G14+J14 -> 0 | M14: =M13+K14-L14 -> 1161185.7
A15: 12 | B15: 46277 | G15: =E15*F15 -> 0 | J15: =H15*I15 -> 0 | K15: =G15+J15 -> 0 | M15: =M14+K15-L15 -> 1161185.7
A16: 13 | B16: 46278 | G16: =E16*F16 -> 0 | J16: =H16*I16 -> 0 | K16: =G16+J16 -> 0 | M16: =M15+K16-L16 -> 1161185.7
A17: 14 | B17: 46279 | G17: =E17*F17 -> 0 | J17: =H17*I17 -> 0 | K17: =G17+J17 -> 0 | M17: =M16+K17-L17 -> 1161185.7
A18: 15 | B18: 46280 | E18: 2700 | F18: 103.62 | G18: =E18*F18 -> 279774 | H18: 35 | I18: 115.49 | J18: =H18*I18 -> 4042.15 | K18: =G18+J18 -> 283816.15 | M18: =M17+K18-L18 -> 1445001.9
A19: 16 | B19: 46281 | G19: =E19*F19 -> 0 | J19: =H19*I19 -> 0 | K19: =G19+J19 -> 0 | M19: =M18+K19-L19 -> 1445001.9
A20: 17 | B20: 46282 | G20: =E20*F20 -> 0 | J20: =H20*I20 -> 0 | K20: =G20+J20 -> 0 | M20: =M19+K20-L20 -> 1445001.9
A21: 18 | B21: 46283 | G21: =E21*F21 -> 0 | J21: =H21*I21 -> 0 | K21: =G21+J21 -> 0 | M21: =M20+K21-L21 -> 1445001.9
A22: 19 | B22: 46284 | G22: =E22*F22 -> 0 | J22: =H22*I22 -> 0 | K22: =G22+J22 -> 0 | M22: =M21+K22-L22 -> 1445001.9
A23: 20 | B23: 46285 | G23: =E23*F23 -> 0 | J23: =H23*I23 -> 0 | K23: =G23+J23 -> 0 | M23: =M22+K23-L23 -> 1445001.9
A24: 21 | B24: 46286 | G24: =E24*F24 -> 0 | J24: =H24*I24 -> 0 | K24: =G24+J24 -> 0 | M24: =M23+K24-L24 -> 1445001.9
A25: 22 | B25: 46287 | G25: =E25*F25 -> 0 | J25: =H25*I25 -> 0 | K25: =G25+J25 -> 0 | M25: =M24+K25-L25 -> 1445001.9
A26: 23 | B26: 46288 | G26: =E26*F26 -> 0 | J26: =H26*I26 -> 0 | K26: =G26+J26 -> 0 | M26: =M25+K26-L26 -> 1445001.9
A27: 24 | B27: 46289 | G27: =E27*F27 -> 0 | J27: =H27*I27 -> 0 | K27: =G27+J27 -> 0 | M27: =M26+K27-L27 -> 1445001.9
A28: 25 | B28: 46290 | G28: =E28*F28 -> 0 | J28: =H28*I28 -> 0 | K28: =G28+J28 -> 0 | M28: =M27+K28-L28 -> 1445001.9
A29: 26 | B29: 46291 | G29: =E29*F29 -> 0 | J29: =H29*I29 -> 0 | K29: =G29+J29 -> 0 | M29: =M28+K29-L29 -> 1445001.9
A30: 27 | B30: 46292 | G30: =E30*F30 -> 0 | J30: =H30*I30 -> 0 | K30: =G30+J30 -> 0 | M30: =M29+K30-L30 -> 1445001.9
... A33: 30 | B33: 46295 | G33: =E33*F33 -> 0 | J33: =H33*I33 -> 0 | K33: =G33+J33 -> 0 | M33: =M32+K33-L33 -> 1445001.9
A34: 31 | G34: =E34*F34 -> 0 | J34: =H34*I34 -> 0 | K34: =G34+J34 -> 0 | M34: =M33+K34-L34 -> 1445001.9
E35: =SUM(E4:E34) -> 8200 | G35: =SUM(G4:G34) -> 849684 | H35: =SUM(H4:H34) -> 145 | J35: =SUM(J4:J34) -> 16746.05 | K35: =SUM(K4:K34) -> 866430.05 | L35: =SUM(L4:L34) -> 0

Sheet  Khammam&Cash
A1: Cash &Carry
A2: S.No | B2: Date | D2: Ind No/Bill No | E2: Diesel (Lts) | F2: Price | G2: Amount | H2: Petrol (Lts) | I2: Price | J2: Amount | K2: Total amount | L2: Amount paid | M2: As 0n Date | N2: Remarks
A3: Opening Balance | K3: 0 | M3: 0
A4: 1 | G4: =E4*F4 -> 0 | K4: =G4+J4 -> 0 | L4: =H4+K4 -> 0 | M4: =M3+K4-L4 -> 0
A5: 2 | G5: =E5*F5 -> 0 | J5: =H5*I5 -> 0 | K5: =G5+J5 -> 0 | L5: =H5+K5 -> 0 | M5: =M4+K5-L5 -> 0
A6: 3 | G6: =E6*F6 -> 0 | J6: =H6*I6 -> 0 | K6: =G6+J6 -> 0 | L6: =H6+K6 -> 0 | M6: =M5+K6-L6 -> 0
A7: 4 | G7: =E7*F7 -> 0 | J7: =H7*I7 -> 0 | K7: =G7+J7 -> 0 | L7: =H7+K7 -> 0 | M7: =M6+K7-L7 -> 0
A8: 5 | G8: =E8*F8 -> 0 | J8: =H8*I8 -> 0 | K8: =G8+J8 -> 0 | L8: =H8+K8 -> 0 | M8: =M7+K8-L8 -> 0
A9: 6 | G9: =E9*F9 -> 0 | J9: =H9*I9 -> 0 | K9: =G9+J9 -> 0 | L9: =H9+K9 -> 0 | M9: =M8+K9-L9 -> 0
A10: 7 | G10: =E10*F10 -> 0 | J10: =H10*I10 -> 0 | K10: =G10+J10 -> 0 | L10: =H10+K10 -> 0 | M10: =M9+K10-L10 -> 0
A11: 8 | G11: =E11*F11 -> 0 | J11: =H11*I11 -> 0 | K11: =G11+J11 -> 0 | L11: =H11+K11 -> 0 | M11: =M10+K11-L11 -> 0
A12: 9 | G12: =E12*F12 -> 0 | J12: =H12*I12 -> 0 | K12: =G12+J12 -> 0 | L12: =H12+K12 -> 0 | M12: =M11+K12-L12 -> 0
A13: 10 | G13: =E13*F13 -> 0 | J13: =H13*I13 -> 0 | K13: =G13+J13 -> 0 | L13: =H13+K13 -> 0 | M13: =M12+K13-L13 -> 0
A14: 11 | G14: =E14*F14 -> 0 | J14: =H14*I14 -> 0 | K14: =G14+J14 -> 0 | L14: =H14+K14 -> 0 | M14: =M13+K14-L14 -> 0
A15: 12 | G15: =E15*F15 -> 0 | J15: =H15*I15 -> 0 | K15: =G15+J15 -> 0 | L15: =H15+K15 -> 0 | M15: =M14+K15-L15 -> 0
A16: 13 | G16: =E16*F16 -> 0 | J16: =H16*I16 -> 0 | K16: =G16+J16 -> 0 | L16: =H16+K16 -> 0 | M16: =M15+K16-L16 -> 0
... A22: 19 | G22: =E22*F22 -> 0 | J22: =H22*I22 -> 0 | K22: =G22+J22 -> 0 | L22: =H22+K22 -> 0 | M22: =M21+K22-L22 -> 0
A23: 20 | G23: =E23*F23 -> 0 | J23: =H23*I23 -> 0 | K23: =G23+J23 -> 0 | L23: 0 | M23: =M22+K23-L23 -> 0
A24: 21 | G24: =E24*F24 -> 0 | J24: =H24*I24 -> 0 | K24: =G24+J24 -> 0 | L24: =H24+K24 -> 0 | M24: =M23+K24-L24 -> 0
A25: 22 | G25: =E25*F25 -> 0 | J25: =H25*I25 -> 0 | K25: =G25+J25 -> 0 | L25: =H25+K25 -> 0 | M25: =M24+K25-L25 -> 0
A26: 23 | G26: =E26*F26 -> 0 | J26: =H26*I26 -> 0 | K26: =G26+J26 -> 0 | L26: =H26+K26 -> 0 | M26: =M25+K26-L26 -> 0
A27: 24 | G27: =E27*F27 -> 0 | K27: =G27+J27 -> 0 | L27: =H27+K27 -> 0 | M27: =M26+K27-L27 -> 0
A28: 25 | G28: =E28*F28 -> 0 | J28: =H28*I28 -> 0 | K28: =G28+J28 -> 0 | L28: =H28+K28 -> 0 | M28: =M26+K28-L28 -> 0
A29: 26 | G29: =E29*F29 -> 0 | J29: =H29*I29 -> 0 | K29: =G29+J29 -> 0 | L29: =H29+K29 -> 0 | M29: =M28+K29-L29 -> 0
A30: 27 | G30: =E30*F30 -> 0 | J30: =H30*I30 -> 0 | K30: =G30+J30 -> 0 | L30: =H30+K30 -> 0 | M30: =M29+K30-L30 -> 0
A31: 28 | G31: =E31*F31 -> 0 | J31: =H31*I31 -> 0 | K31: =G31+J31 -> 0 | L31: =H31+K31 -> 0 | M31: =M30+K31-L31 -> 0
A32: 29 | G32: =E32*F32 -> 0 | J32: =H32*I32 -> 0 | K32: =G32+J32 -> 0 | L32: =H32+K32 -> 0 | M32: =M31+K32-L32 -> 0
A33: 30 | G33: =E33*F33 -> 0 | J33: =H33*I33 -> 0 | K33: =G33+J33 -> 0 | L33: =H33+K33 -> 0 | M33: =M32+K33-L33 -> 0
A34: 31 | G34: =E34*F34 -> 0 | J34: =H34*I34 -> 0 | K34: =G34+J34 -> 0 | L34: =H34+K34 -> 0 | M34: =M33+K34-L34 -> 0
A35: 32 | G35: =E35*F35 -> 0 | K35: =G35+J35 -> 0 | L35: =H35+K35 -> 0 | M35: =M34+K35-L35 -> 0
A36: 33 | G36: =E36*F36 -> 0 | J36: =H36*I36 -> 0 | K36: =G36+J36 -> 0 | L36: =H36+K36 -> 0 | M36: =M35+K36-L36 -> 0
A37: 34 | G37: =E37*F37 -> 0 | J37: =H37*I37 -> 0 | K37: =G37+J37 -> 0 | L37: =H37+K37 -> 0 | M37: =M36+K37-L37 -> 0
G38: =E38*F38 -> 0 | K38: =G38+J38 -> 0 | L38: =H38+K38 -> 0 | M38: =M37+K38-L38 -> 0
G39: =E39*F39 -> 0 | K39: =G39+J39 -> 0 | L39: =H39+K39 -> 0 | M39: =M38+K39-L39 -> 0
G40: =E40*F40 -> 0 | K40: =G40+J40 -> 0 | L40: =H40+K40 -> 0 | M40: =M39+K40-L40 -> 0
M41: =M40+K41-L41 -> 0
A45: 35 | G45: =E45*F45 -> 0 | J45: =H45*I45 -> 0 | K45: =G45+J45 -> 0
E46: =SUM(E3:E45) -> 0 | G46: =SUM(G3:G45) -> 0 | H46: =SUM(H3:H45) -> 0 | J46: =SUM(J3:J45) -> 0 | K46: =SUM(K4:K45) -> 0 | L46: =SUM(L3:L45) -> 0

Sheet Jadcherla-4
A1: Shree Poornima F/S
A2: S.No | B2: Date | C2: GRN No | D2: Ind No/Bill No | E2: Diesel (Lts) | F2: Price | G2: Amount | H2: Petrol (Lts) | I2: Price | J2: Amount | K2: Total amount | L2: Amount paid | M2: As on date | N2: Remarks
A3: Opening Balance | M3: 2600.28
A4: 1 | B4: 46266 | G4: =E4*F4 -> 0 | J4: =H4*I4 -> 0 | K4: =G4+J4 -> 0 | L4: 0 | M4: =M3+K4-L4 -> 2600.28
A5: 2 | B5: 46267 | E5: 200 | F5: 104.42 | G5: =E5*F5 -> 20884 | J5: =H5*I5 -> 0 | K5: =G5+J5 -> 20884 | L5: 0 | M5: =M4+K5-L5 -> 23484.28
A6: 3 | B6: 46268 | G6: =E6*F6 -> 0 | J6: =H6*I6 -> 0 | K6: =G6+J6 -> 0 | L6: 0 | M6: =M5+K6-L6 -> 23484.28
A7: 4 | B7: 46269 | G7: =E7*F7 -> 0 | J7: =H7*I7 -> 0 | K7: =G7+J7 -> 0 | L7: 0 | M7: =M6+K7-L7 -> 23484.28
A8: 5 | B8: 46270 | G8: =E8*F8 -> 0 | J8: =H8*I8 -> 0 | K8: =G8+J8 -> 0 | L8: 0 | M8: =M7+K8-L8 -> 23484.28
A9: 6 | B9: 46271 | G9: =E9*F9 -> 0 | J9: =H9*I9 -> 0 | K9: =G9+J9 -> 0 | L9: 0 | M9: =M8+K9-L9 -> 23484.28
A10: 7 | B10: 46272 | G10: =E10*F10 -> 0 | J10: =H10*I10 -> 0 | K10: =G10+J10 -> 0 | L10: 0 | M10: =M9+K10-L10 -> 23484.28
A11: 8 | B11: 46273 | G11: =E11*F11 -> 0 | J11: =H11*I11 -> 0 | K11: =G11+J11 -> 0 | L11: 0 | M11: =M10+K11-L11 -> 23484.28
A12: 9 | B12: 46274 | G12: =E12*F12 -> 0 | J12: =H12*I12 -> 0 | K12: =G12+J12 -> 0 | L12: 0 | M12: =M11+K12-L12 -> 23484.28
A13: 10 | B13: 46275 | G13: =E13*F13 -> 0 | J13: =H13*I13 -> 0 | K13: =G13+J13 -> 0 | L13: 0 | M13: =M12+K13-L13 -> 23484.28
A14: 11 | B14: 46276 | G14: =E14*F14 -> 0 | H14: 10 | I14: 116.33 | J14: =H14*I14 -> 1163.3 | K14: =G14+J14 -> 1163.3 | L14: 0 | M14: =M13+K14-L14 -> 24647.58
A15: 12 | B15: 46277 | G15: =E15*F15 -> 0 | J15: =H15*I15 -> 0 | K15: =G15+J15 -> 0 | L15: 0 | M15: =M14+K15-L15 -> 24647.58
A16: 13 | B16: 46278 | G16: =E16*F16 -> 0 | J16: =H16*I16 -> 0 | K16: =G16+J16 -> 0 | L16: 0 | M16: =M15+K16-L16 -> 24647.58
A17: 14 | B17: 46279 | G17: =E17*F17 -> 0 | J17: =H17*I17 -> 0 | K17: =G17+J17 -> 0 | L17: 0 | M17: =M16+K17-L17 -> 24647.58
A18: 15 | B18: 46280 | G18: =E18*F18 -> 0 | J18: =H18*I18 -> 0 | K18: =G18+J18 -> 0 | L18: 0 | M18: =M17+K18-L18 -> 24647.58
A19: 16 | B19: 46281 | G19: 0 | J19: 0 | K19: 0 | L19: 0 | M19: =M18+K19-L19 -> 24647.58
A20: 17 | B20: 46282 | G20: =E20*F20 -> 0 | J20: =H20*I20 -> 0 | K20: =G20+J20 -> 0 | L20: 0 | M20: =M19+K20-L20 -> 24647.58
A21: 18 | B21: 46283 | G21: =E21*F21 -> 0 | J21: =H21*I21 -> 0 | K21: =G21+J21 -> 0 | L21: 0 | M21: =M20+K21-L21 -> 24647.58
A22: 19 | B22: 46284 | G22: =E22*F22 -> 0 | J22: =H22*I22 -> 0 | K22: =G22+J22 -> 0 | L22: 0 | M22: =M21+K22-L22 -> 24647.58
A23: 20 | B23: 46285 | G23: =E23*F23 -> 0 | J23: =H23*I23 -> 0 | K23: =G23+J23 -> 0 | L23: 0 | M23: =M22+K23-L23 -> 24647.58
A24: 21 | B24: 46286 | G24: =E24*F24 -> 0 | J24: =H24*I24 -> 0 | K24: =G24+J24 -> 0 | L24: 0 | M24: =M23+K24-L24 -> 24647.58
A25: 22 | B25: 46287 | G25: =E25*F25 -> 0 | J25: =H25*I25 -> 0 | K25: =G25+J25 -> 0 | L25: 0 | M25: =M24+K25-L25 -> 24647.58
A26: 23 | B26: 46288 | G26: =E26*F26 -> 0 | J26: =H26*I26 -> 0 | K26: =G26+J26 -> 0 | L26: 0 | M26: =M25+K26-L26 -> 24647.58
A27: 24 | B27: 46289 | G27: =E27*F27 -> 0 | J27: =H27*I27 -> 0 | K27: =G27+J27 -> 0 | L27: 0 | M27: =M26+K27-L27 -> 24647.58
A28: 25 | B28: 46290 | G28: =E28*F28 -> 0 | J28: =H28*I28 -> 0 | K28: =G28+J28 -> 0 | L28: 0 | M28: =M27+K28-L28 -> 24647.58
A29: 26 | B29: 46291 | G29: =E29*F29 -> 0 | J29: =H29*I29 -> 0 | K29: =G29+J29 -> 0 | L29: 0 | M29: =M28+K29-L29 -> 24647.58
A30: 27 | B30: 46292 | G30: =E30*F30 -> 0 | J30: =H30*I30 -> 0 | K30: =G30+J30 -> 0 | L30: 0 | M30: =M29+K30-L30 -> 24647.58
A31: 28 | B31: 46293 | G31: =E31*F31 -> 0 | J31: =H31*I31 -> 0 | K31: =G31+J31 -> 0 | L31: 0 | M31: =M30+K31-L31 -> 24647.58
A32: 29 | B32: 46294 | G32: =E32*F32 -> 0 | J32: =H32*I32 -> 0 | K32: =G32+J32 -> 0 | L32: 0 | M32: =M31+K32-L32 -> 24647.58
A33: 30 | B33: 46295 | E33: 200 | F33: 104.42 | G33: =E33*F33 -> 20884 | H33: 20 | I33: 116.33 | J33: =H33*I33 -> 2326.6 | K33: =G33+J33 -> 23210.6 | L33: 0 | M33: =M32+K33-L33 -> 47858.18
A34: 31 | G34: =E34*F34 -> 0 | J34: =H34*I34 -> 0 | K34: =G34+J34 -> 0 | M34: =M33+K34-L34 -> 47858.18
E35: =SUM(E4:E34) -> 400 | G35: =SUM(G4:G34) -> 41768 | H35: =SUM(H4:H34) -> 30 | J35: =SUM(J4:J34) -> 3489.9 | K35: =SUM(K4:K34) -> 45257.9 | L35: =SUM(L4:L34) -> 0

Sheet  Sangareddy-2
A1: Durga Bhavani F/S
A2: S.No | B2: Date | C2: GRN No | D2: Ind no/Bill No | E2: Diesel (Lts) | F2: Price | G2: Amount | H2: Petrol (Lts) | I2: Price | J2: Amount | K2: Total amount | L2: Amount paid | M2: As on Date | N2: Remarks
A3: Opening Balance | M3: 0
A4: 1 | B4: 46266 | G4: =E4*F4 -> 0 | J4: =H4*I4 -> 0 | K4: =G4+J4 -> 0 | M4: =M3+K4-L4 -> 0
A5: 2 | B5: 46267 | G5: =E5*F5 -> 0 | J5: =H5*I5 -> 0 | K5: =G5+J5 -> 0 | M5: =M4+K5-L5 -> 0
A6: 3 | B6: 46268 | G6: =E6*F6 -> 0 | J6: =H6*I6 -> 0 | K6: =G6+J6 -> 0 | M6: =M5+K6-L6 -> 0
A7: 4 | B7: 46269 | G7: =E7*F7 -> 0 | J7: =H7*I7 -> 0 | K7: =G7+J7 -> 0 | M7: =M6+K7-L7 -> 0
A8: 5 | B8: 46270 | G8: =E8*F8 -> 0 | J8: =H8*I8 -> 0 | K8: =G8+J8 -> 0 | M8: =M7+K8-L8 -> 0
A9: 6 | B9: 46271 | G9: =E9*F9 -> 0 | J9: =H9*I9 -> 0 | K9: =G9+J9 -> 0 | M9: =M8+K9-L9 -> 0
A10: 7 | B10: 46272 | G10: =E10*F10 -> 0 | J10: =H10*I10 -> 0 | K10: =G10+J10 -> 0 | M10: =M9+K10-L10 -> 0
A11: 8 | B11: 46273 | G11: =E11*F11 -> 0 | J11: =H11*I11 -> 0 | K11: =G11+J11 -> 0 | M11: =M10+K11-L11 -> 0
A12: 9 | B12: 46274 | G12: =E12*F12 -> 0 | J12: =H12*I12 -> 0 | K12: =G12+J12 -> 0 | M12: =M11+K12-L12 -> 0
A13: 10 | B13: 46275 | G13: =E13*F13 -> 0 | J13: =H13*I13 -> 0 | K13: =G13+J13 -> 0 | M13: =M12+K13-L13 -> 0
A14: 11 | B14: 46276 | G14: =E14*F14 -> 0 | J14: =H14*I14 -> 0 | K14: =G14+J14 -> 0 | M14: =M13+K14-L14 -> 0
A15: 12 | B15: 46277 | G15: =E15*F15 -> 0 | J15: =H15*I15 -> 0 | K15: =G15+J15 -> 0 | M15: =M14+K15-L15 -> 0
... A32: 29 | B32: 46294 | G32: =E32*F32 -> 0 | J32: =H32*I32 -> 0 | K32: =G32+J32 -> 0 | M32: =M31+K32-L32 -> 0
A33: 30 | B33: 46295 | G33: =E33*F33 -> 0 | J33: =H33*I33 -> 0 | K33: =G33+J33 -> 0 | L33: 0 | M33: =M32+K33-L33 -> 0
A34: 31 | G34: =E34*F34 -> 0 | J34: =H34*I34 -> 0 | K34: =G34+J34 -> 0 | L34: 0 | M34: =M33+K34-L34 -> 0
E35: =SUM(E4:E34) -> 0 | G35: =SUM(G4:G34) -> 0 | H35: =SUM(H4:H34) -> 0 | J35: =SUM(J4:J34) -> 0 | K35: =SUM(K4:K34) -> 0 | L35: =SUM(L4:L34) -> 0

Sheet  Sangareddy-3
A1: SHIVA PARVATHI FILLING STATION SADASHIVPET
A2: S.No | B2: Date | C2: GRN No | D2: Ind no/Bill No | E2: Diesel (Lts) | F2: Price | G2: Amount | H2: Petrol (Lts) | I2: Price | J2: Amount | K2: Total amount | L2: Amount paid | M2: As on Date | N2: Remarks
A3: Opening Balance | M3: 146154.99
A4: 1 | B4: 45901 | G4: =E4*F4 -> 0 | H4: 6 | I4: 116.25 | J4: =H4*I4 -> 697.5 | K4: =G4+J4 -> 697.5 | M4: =M3+K4-L4 -> 146852.49
A5: 2 | B5: 45902 | G5: =E5*F5 -> 0 | J5: =H5*I5 -> 0 | K5: =G5+J5 -> 0 | M5: =M4+K5-L5 -> 146852.49
A6: 3 | B6: 45903 | E6: 690 | F6: 104.35 | G6: =E6*F6 -> 72001.5 | H6: 4 | I6: 116.25 | J6: =H6*I6 -> 465 | K6: =G6+J6 -> 72466.5 | M6: =M5+K6-L6 -> 219318.99
A7: 4 | B7: 45904 | G7: =E7*F7 -> 0 | J7: =H7*I7 -> 0 | K7: =G7+J7 -> 0 | M7: =M6+K7-L7 -> 219318.99
A8: 5 | B8: 45905 | G8: =E8*F8 -> 0 | J8: =H8*I8 -> 0 | K8: =G8+J8 -> 0 | M8: =M7+K8-L8 -> 219318.99
A9: 6 | B9: 45906 | E9: 690 | F9: 104.35 | G9: =E9*F9 -> 72001.5 | J9: =H9*I9 -> 0 | K9: =G9+J9 -> 72001.5 | M9: =M8+K9-L9 -> 291320.49
A10: 7 | B10: 45907 | G10: =E10*F10 -> 0 | J10: =H10*I10 -> 0 | K10: =G10+J10 -> 0 | M10: =M9+K10-L10 -> 291320.49
A11: 8 | B11: 45908 | G11: =E11*F11 -> 0 | H11: 6 | I11: 116.25 | J11: =H11*I11 -> 697.5 | K11: =G11+J11 -> 697.5 | M11: =M10+K11-L11 -> 292017.99
A12: 9 | B12: 45909 | E12: 600 | F12: 104.35 | G12: =E12*F12 -> 62610 | J12: =H12*I12 -> 0 | K12: =G12+J12 -> 62610 | M12: =M11+K12-L12 -> 354627.99
A13: 10 | B13: 45910 | G13: =E13*F13 -> 0 | H13: 6 | I13: 116.25 | J13: =H13*I13 -> 697.5 | K13: =G13+J13 -> 697.5 | M13: =M12+K13-L13 -> 355325.49
A14: 11 | B14: 45911 | E14: 690 | F14: 104.35 | G14: =E14*F14 -> 72001.5 | H14: 20 | I14: 116.25 | J14: =H14*I14 -> 2325 | K14: =G14+J14 -> 74326.5 | M14: =M13+K14-L14 -> 429651.99
A15: 12 | B15: 45912 | G15: =E15*F15 -> 0 | K15: =G15+J15 -> 0 | M15: =M14+K15-L15 -> 429651.99
A16: 13 | B16: 45913 | G16: =E16*F16 -> 0 | J16: =H16*I16 -> 0 | K16: =G16+J16 -> 0 | M16: =M15+K16-L16 -> 429651.99
A17: 14 | B17: 45914 | G17: =E17*F17 -> 0 | J17: =H17*I17 -> 0 | K17: =G17+J17 -> 0 | M17: =M16+K17-L17 -> 429651.99
A18: 15 | B18: 45915 | G18: =E18*F18 -> 0 | J18: =H18*I18 -> 0 | K18: =G18+J18 -> 0 | M18: =M17+K18-L18 -> 429651.99
A19: 16 | B19: 45916 | E19: 690 | F19: 104.35 | G19: =E19*F19 -> 72001.5 | J19: =H19*I19 -> 0 | K19: =G19+J19 -> 72001.5 | M19: =M18+K19-L19 -> 501653.49
A20: 17 | B20: 45917 | G20: =E20*F20 -> 0 | J20: =H20*I20 -> 0 | K20: =G20+J20 -> 0 | M20: =M19+K20-L20 -> 501653.49
A21: 18 | B21: 45918 | G21: =E21*F21 -> 0 | J21: =H21*I21 -> 0 | K21: =G21+J21 -> 0 | M21: =M20+K21-L21 -> 501653.49
A22: 19 | B22: 45919 | G22: =E22*F22 -> 0 | J22: =H22*I22 -> 0 | K22: =G22+J22 -> 0 | M22: =M21+K22-L22 -> 501653.49
A23: 20 | B23: 45920 | G23: =E23*F23 -> 0 | J23: =H23*I23 -> 0 | K23: =G23+J23 -> 0 | M23: =M22+K23-L23 -> 501653.49
A24: 21 | B24: 45921 | E24: 690 | F24: 104.35 | G24: =E24*F24 -> 72001.5 | J24: =H24*I24 -> 0 | K24: =G24+J24 -> 72001.5 | M24: =M23+K24-L24 -> 573654.99
A25: 22 | B25: 45922 | G25: =E25*F25 -> 0 | J25: =H25*I25 -> 0 | K25: =G25+J25 -> 0 | M25: =M24+K25-L25 -> 573654.99
A26: 23 | B26: 45923 | G26: =E26*F26 -> 0 | J26: =H26*I26 -> 0 | K26: =G26+J26 -> 0 | L26: 427500 | M26: =M25+K26-L26 -> 146154.99
A27: 24 | B27: 45924 | E27: 690 | F27: 104.35 | G27: =E27*F27 -> 72001.5 | H27: 20 | I27: 116.25 | J27: =H27*I27 -> 2325 | K27: =G27+J27 -> 74326.5 | M27: =M26+K27-L27 -> 220481.49
A28: 25 | B28: 45925 | G28: =E28*F28 -> 0 | J28: =H28*I28 -> 0 | K28: =G28+J28 -> 0 | M28: =M27+K28-L28 -> 220481.49
A29: 26 | B29: 45926 | E29: 690 | F29: 104.35 | G29: =E29*F29 -> 72001.5 | H29: 20 | I29: 116.25 | J29: =H29*I29 -> 2325 | K29: =G29+J29 -> 74326.5 | M29: =M28+K29-L29 -> 294807.99
A30: 27 | B30: 45927 | G30: =E30*F30 -> 0 | J30: =H30*I30 -> 0 | K30: =G30+J30 -> 0 | M30: =M29+K30-L30 -> 294807.99
A31: 28 | B31: 45928 | G31: =E31*F31 -> 0 | J31: =H31*I31 -> 0 | K31: =G31+J31 -> 0 | M31: =M30+K31-L31 -> 294807.99
A32: 29 | B32: 45929 | E32: 690 | F32: 104.35 | G32: =E32*F32 -> 72001.5 | J32: =H32*I32 -> 0 | K32: =G32+J32 -> 72001.5 | M32: =M31+K32-L32 -> 366809.49
A33: 30 | B33: 45930 | G33: =E33*F33 -> 0 | J33: =H33*I33 -> 0 | K33: =G33+J33 -> 0 | M33: =M32+K33-L33 -> 366809.49
A34: 31 | G34: =E34*F34 -> 0 | J34: =H34*I34 -> 0 | K34: =G34+J34 -> 0 | M34: =M33+K34-L34 -> 366809.49
A35: 32 | G35: =E35*F35 -> 0 | J35: =H35*I35 -> 0 | K35: =G35+J35 -> 0 | M35: =M34+K35-L35 -> 366809.49
E36: =SUM(E4:E35) -> 6120 | G36: =SUM(G4:G35) -> 638622 | H36: =SUM(H4:H35) -> 82 | J36: =SUM(J4:J35) -> 9532.5 | K36: =SUM(K4:K35) -> 648154.5 | L36: =SUM(L4:L35) -> 427500

Sheet Narayankhed
A2: S.No | B2: Date | C2: GRN No | D2: Ind no/Bill No | E2: Diesel (Lts) | F2: Price | G2: Amount | H2: Petrol (Lts) | I2: Price | J2: Amount | K2: Total amount | L2: Amount paid | M2: As on Date | N2: Remarks
A3: Opening Balance | M3: 0
A4: 1 | B4: 46266 | G4: =E4*F4 -> 0 | J4: =H4*I4 -> 0 | K4: =G4+J4 -> 0 | L4: =H4+K4 -> 0 | M4: =M3+K4-L4 -> 0
A5: 2 | B5: 46267 | G5: =E5*F5 -> 0 | J5: =H5*I5 -> 0 | K5: =G5+J5 -> 0 | L5: =H5+K5 -> 0 | M5: =M4+K5-L5 -> 0
A6: 3 | B6: 46268 | G6: =E6*F6 -> 0 | J6: =H6*I6 -> 0 | K6: =G6+J6 -> 0 | L6: =H6+K6 -> 0 | M6: =M5+K6-L6 -> 0
A7: 4 | B7: 46269 | G7: =E7*F7 -> 0 | J7: =H7*I7 -> 0 | K7: =G7+J7 -> 0 | L7: =H7+K7 -> 0 | M7: =M6+K7-L7 -> 0
A8: 5 | B8: 46270 | G8: =E8*F8 -> 0 | J8: =H8*I8 -> 0 | K8: =G8+J8 -> 0 | L8: =H8+K8 -> 0 | M8: =M7+K8-L8 -> 0
A9: 6 | B9: 46271 | E9: 476.64 | F9: 104.9 | G9: =E9*F9 -> 49999.536 | J9: =H9*I9 -> 0 | K9: =G9+J9 -> 49999.536 | L9: 49999.536 | M9: =M8+K9-L9 -> 0 | N9: BT
A10: 7 | B10: 46272 | G10: =E10*F10 -> 0 | J10: =H10*I10 -> 0 | K10: =G10+J10 -> 0 | L10: 0 | M10: =M9+K10-L10 -> 0
A11: 8 | B11: 46273 | G11: =E11*F11 -> 0 | J11: =H11*I11 -> 0 | K11: =G11+J11 -> 0 | L11: =H11+K11 -> 0 | M11: =M10+K11-L11 -> 0
A12: 9 | B12: 46274 | G12: =E12*F12 -> 0 | J12: =H12*I12 -> 0 | K12: =G12+J12 -> 0 | L12: 0 | M12: =M11+K12-L12 -> 0
A13: 10 | B13: 46275 | G13: =E13*F13 -> 0 | J13: =H13*I13 -> 0 | K13: =G13+J13 -> 0 | L13: =H13+K13 -> 0 | M13: =M12+K13-L13 -> 0
A14: 11 | B14: 46276 | G14: =E14*F14 -> 0 | J14: =H14*I14 -> 0 | K14: =G14+J14 -> 0 | L14: =H14+K14 -> 0 | M14: =M13+K14-L14 -> 0
A15: 12 | B15: 46277 | G15: =E15*F15 -> 0 | J15: =H15*I15 -> 0 | K15: =G15+J15 -> 0 | L15: =H15+K15 -> 0 | M15: =M14+K15-L15 -> 0
A16: 13 | B16: 46278 | G16: =E16*F16 -> 0 | J16: =H16*I16 -> 0 | K16: =G16+J16 -> 0 | L16: =H16+K16 -> 0 | M16: =M15+K16-L16 -> 0
A17: 14 | B17: 46279 | G17: =E17*F17 -> 0 | J17: =H17*I17 -> 0 | K17: =G17+J17 -> 0 | L17: =H17+K17 -> 0 | M17: =M16+K17-L17 -> 0
A18: 15 | B18: 46280 | G18: =E18*F18 -> 0 | J18: =H18*I18 -> 0 | K18: =G18+J18 -> 0 | L18: =H18+K18 -> 0 | M18: =M17+K18-L18 -> 0
A19: 16 | B19: 46281 | G19: =E19*F19 -> 0 | J19: =H19*I19 -> 0 | K19: =G19+J19 -> 0 | L19: =H19+K19 -> 0 | M19: =M18+K19-L19 -> 0
A20: 17 | B20: 46282 | E20: 238.03 | F20: 105.03 | G20: =E20*F20 -> 25000.291 | J20: =H20*I20 -> 0 | K20: =G20+J20 -> 25000.291 | L20: =H20+K20 -> 25000.291 | M20: =M19+K20-L20 -> 0 | N20: HPCLCard
A21: 18 | B21: 46283 | G21: =E21*F21 -> 0 | J21: =H21*I21 -> 0 | K21: =G21+J21 -> 0 | L21: =H21+K21 -> 0 | M21: =M20+K21-L21 -> 0
A22: 19 | B22: 46284 | G22: =E22*F22 -> 0 | J22: =H22*I22 -> 0 | K22: =G22+J22 -> 0 | L22: =H22+K22 -> 0 | M22: =M21+K22-L22 -> 0
A23: 20 | B23: 46285 | G23: =E23*F23 -> 0 | J23: =H23*I23 -> 0 | K23: =G23+J23 -> 0 | L23: =H23+K23 -> 0 | M23: =M22+K23-L23 -> 0
A24: 21 | B24: 46286 | E24: 142.82 | F24: 105.03 | G24: =E24*F24 -> 15000.385 | J24: =H24*I24 -> 0 | K24: =G24+J24 -> 15000.385 | L24: =H24+K24 -> 15000.385 | M24: =M23+K24-L24 -> 0 | N24: HPCL Card
A25: 22 | B25: 46287 | G25: =E25*F25 -> 0 | J25: =H25*I25 -> 0 | K25: =G25+J25 -> 0 | L25: =H25+K25 -> 0 | M25: =M24+K25-L25 -> 0
A26: 23 | B26: 46288 | G26: =E26*F26 -> 0 | J26: =H26*I26 -> 0 | K26: =G26+J26 -> 0 | L26: =+K26 -> 0 | M26: =M25+K26-L26 -> 0
A27: 24 | B27: 46289 | E27: 238 | F27: 105.03 | G27: =E27*F27 -> 24997.14 | J27: =H27*I27 -> 0 | K27: =G27+J27 -> 24997.14 | L27: =+K27 -> 24997.14 | M27: =M26+K27-L27 -> 0
A28: 25 | B28: 46290 | G28: =E28*F28 -> 0 | J28: =H28*I28 -> 0 | K28: =G28+J28 -> 0 | L28: =+K28 -> 0 | M28: =M27+K28-L28 -> 0
A29: 26 | B29: 46291 | E29: 380 | F29: 105.12 | G29: =E29*F29 -> 39945.6 | J29: =H29*I29 -> 0 | K29: =G29+J29 -> 39945.6 | L29: =+K29 -> 39945.6 | M29: =M28+K29-L29 -> 0 | N29: BPCL
A30: 27 | B30: 46292 | G30: =E30*F30 -> 0 | J30: =H30*I30 -> 0 | K30: =G30+J30 -> 0 | L30: =+K30 -> 0 | M30: =M29+K30-L30 -> 0
A31: 28 | B31: 46293 | E31: 285.39 | F31: 105.12 | G31: =E31*F31 -> 30000.197 | J31: =H31*I31 -> 0 | K31: =G31+J31 -> 30000.197 | L31: =+K31 -> 30000.197 | M31: =M30+K31-L31 -> 0 | N31: BPCL
A32: 29 | B32: 46294 | G32: =E32*F32 -> 0 | J32: =H32*I32 -> 0 | K32: =G32+J32 -> 0 | L32: =+K32 -> 0 | M32: =M31+K32-L32 -> 0
A33: 30 | B33: 46295 | E33: 285.39 | F33: 105.12 | G33: =E33*F33 -> 30000.197 | J33: =H33*I33 -> 0 | K33: =G33+J33 -> 30000.197 | L33: =+K33 -> 30000.197 | M33: =M32+K33-L33 -> 0 | N33: BPCL
A34: 31 | G34: =E34*F34 -> 0 | J34: =H34*I34 -> 0 | K34: =G34+J34 -> 0 | L34: =+K34 -> 0 | M34: 0
E35: =SUM(E4:E34) -> 2046.27 | G35: =SUM(G4:G34) -> 214943.35 | H35: =SUM(H4:H34) -> 0 | J35: =SUM(J4:J34) -> 0 | K35: =SUM(K4:K34) -> 214943.35 | L35: =SUM(L4:L34) -> 214943.35

Sheet Dindi
A1: Akarapu Balakistamma Fillling
A2: S.No | B2: Date | C2: GRN No | D2: Ind no/Bill No | E2: Diesel (Lts) | F2: Price | G2: Amount | H2: Petrol (Lts) | I2: Price | J2: Amount | K2: Total amount | L2: Amount paid | M2: As on Date | N2: Remarks
A3: Opening Balance | M3: 0
A4: 1 | B4: 45901 | E4: 44.75 | F4: 104.95 | G4: =E4*F4 -> 4696.5125 | J4: =H4*I4 -> 0 | K4: =G4+J4 -> 4696.5125 | L4: =+K4 -> 4696.5125 | M4: 0
A5: 2 | B5: 45902 | G5: =E5*F5 -> 0 | J5: =H5*I5 -> 0 | K5: =G5+J5 -> 0 | L5: =+K5 -> 0 | M5: 0
A6: 3 | B6: 45903 | G6: =E6*F6 -> 0 | J6: =H6*I6 -> 0 | K6: =G6+J6 -> 0 | L6: =+K6 -> 0 | M6: 0
A7: 4 | B7: 45904 | G7: =E7*F7 -> 0 | J7: =H7*I7 -> 0 | K7: =G7+J7 -> 0 | L7: =+K7 -> 0 | M7: 0
A8: 5 | B8: 45905 | G8: =E8*F8 -> 0 | J8: =H8*I8 -> 0 | K8: =G8+J8 -> 0 | L8: =+K8 -> 0 | M8: 0
A9: 6 | B9: 45906 | G9: =E9*F9 -> 0 | J9: =H9*I9 -> 0 | K9: =G9+J9 -> 0 | L9: =+K9 -> 0 | M9: 0
A10: 7 | B10: 45907 | G10: =E10*F10 -> 0 | J10: =H10*I10 -> 0 | K10: =G10+J10 -> 0 | L10: =+K10 -> 0 | M10: 0
A11: 8 | B11: 45908 | G11: =E11*F11 -> 0 | J11: =H11*I11 -> 0 | K11: =G11+J11 -> 0 | L11: =+K11 -> 0 | M11: 0
A12: 9 | B12: 45909 | G12: =E12*F12 -> 0 | J12: =H12*I12 -> 0 | K12: =G12+J12 -> 0 | L12: =+K12 -> 0 | M12: 0
A13: 10 | B13: 45910 | G13: =E13*F13 -> 0 | J13: =H13*I13 -> 0 | K13: =G13+J13 -> 0 | L13: =+K13 -> 0 | M13: 0
A14: 11 | B14: 45911 | G14: =E14*F14 -> 0 | J14: =H14*I14 -> 0 | K14: =G14+J14 -> 0 | L14: =+K14 -> 0 | M14: 0
A15: 12 | B15: 45912 | G15: =E15*F15 -> 0 | J15: =H15*I15 -> 0 | K15: =G15+J15 -> 0 | L15: =+K15 -> 0 | M15: 0
A16: 13 | B16: 45913 | G16: =E16*F16 -> 0 | J16: =H16*I16 -> 0 | K16: =G16+J16 -> 0 | L16: =+K16 -> 0 | M16: 0
... A20: 17 | B20: 45917 | G20: =E20*F20 -> 0 | J20: =H20*I20 -> 0 | K20: =G20+J20 -> 0 | L20: =+K20 -> 0 | M20: 0
A21: 18 | B21: 45918 | E21: 46.7 | F21: 104.95 | G21: =E21*F21 -> 4901.165 | J21: =H21*I21 -> 0 | K21: =G21+J21 -> 4901.165 | L21: =+K21 -> 4901.165 | M21: 0
A22: 19 | B22: 45919 | G22: =E22*F22 -> 0 | J22: =H22*I22 -> 0 | K22: =G22+J22 -> 0 | L22: =+K22 -> 0 | M22: 0
A23: 20 | B23: 45920 | G23: =E23*F23 -> 0 | J23: =H23*I23 -> 0 | K23: =G23+J23 -> 0 | L23: =+K23 -> 0 | M23: 0
A24: 21 | B24: 45921 | G24: =E24*F24 -> 0 | J24: =H24*I24 -> 0 | K24: =G24+J24 -> 0 | L24: =+K24 -> 0 | M24: 0
A25: 22 | B25: 45922 | G25: =E25*F25 -> 0 | J25: =H25*I25 -> 0 | K25: =G25+J25 -> 0 | L25: =+K25 -> 0 | M25: 0
A26: 23 | B26: 45923 | G26: =E26*F26 -> 0 | J26: =H26*I26 -> 0 | K26: =G26+J26 -> 0 | L26: =+K26 -> 0 | M26: 0
A27: 24 | B27: 45924 | G27: =E27*F27 -> 0 | J27: =H27*I27 -> 0 | K27: =G27+J27 -> 0 | L27: =+K27 -> 0 | M27: 0
A28: 25 | B28: 45925 | G28: =E28*F28 -> 0 | J28: =H28*I28 -> 0 | K28: =G28+J28 -> 0 | L28: =+K28 -> 0 | M28: 0
A29: 26 | B29: 45926 | G29: =E29*F29 -> 0 | J29: =H29*I29 -> 0 | K29: =G29+J29 -> 0 | L29: =+K29 -> 0 | M29: 0
A30: 27 | B30: 45927 | G30: =E30*F30 -> 0 | J30: =H30*I30 -> 0 | K30: =G30+J30 -> 0 | L30: =+K30 -> 0 | M30: 0
A31: 28 | B31: 45928 | G31: =E31*F31 -> 0 | J31: =H31*I31 -> 0 | K31: =G31+J31 -> 0 | L31: =+K31 -> 0 | M31: 0
A32: 29 | B32: 45929 | G32: =E32*F32 -> 0 | J32: =H32*I32 -> 0 | K32: =G32+J32 -> 0 | L32: =+K32 -> 0 | M32: 0
A33: 30 | B33: 45930 | G33: =E33*F33 -> 0 | J33: =H33*I33 -> 0 | K33: =G33+J33 -> 0 | L33: =+K33 -> 0 | M33: 0
A34: 31 | G34: =E34*F34 -> 0 | J34: =H34*I34 -> 0 | K34: =G34+J34 -> 0 | L34: =+K34 -> 0 | M34: 0
E35: =SUM(E4:E34) -> 91.45 | G35: =SUM(G4:G34) -> 9597.6775 | H35: =SUM(H4:H34) -> 0 | J35: =SUM(J4:J34) -> 0 | K35: =SUM(K4:K34) -> 9597.6775 | L35: =SUM(L4:L34) -> 9597.6775

Sheet Multiple bunks(KKD)
A2: S.No | B2: Date | C2: GRN No | D2: Ind no/Bill No | E2: Diesel (Lts) | F2: Price | G2: Amount | H2: Petrol (Lts) | I2: Price | J2: Amount | K2: Total amount | L2: Amount paid | M2: As on Date | N2: Remarks
A3: Opening Balance
A4: 1 | B4: 46266 | C4: GJN TRANSLINES | D4: CHITTOOR | E4: 20 | F4: 106.05 | G4: 2121 | J4: =H4*I4 -> 0 | K4: =G4+J4 -> 2121 | L4: =+K4 -> 2121
A5: 2 | B5: 46266 | C5: GJN TRANSLINES | D5: CHITTOOR | E5: 20 | F5: 106.05 | G5: 2121 | K5: =G5+J5 -> 2121 | L5: =+K5 -> 2121
A6: 3 | B6: 46268 | C6: SRI BALAJI AGENCIES | D6: KAKINADA | E6: 47.38 | F6: 105.59 | G6: 5002.85 | K6: =G6+J6 -> 5002.85 | L6: =+K6 -> 5002.85
A7: 4 | B7: 46268 | C7: SRI MALLIDI VENKATA REDDY AGENCIES | D7: MANDAPETA | H7: 5 | I7: 117.32 | J7: 586.6 | K7: =G7+J7 -> 586.6 | L7: =+K7 -> 586.6
A8: 5 | B8: 46269 | C8: SRI BALAJI AGENCIES | D8: KAKINADA | H8: 5 | I8: 117.98 | J8: 589.9 | K8: =G8+J8 -> 589.9 | L8: =+K8 -> 589.9
A9: 6 | B9: 46270 | C9: SRI BALAJI AGENCIES | D9: KAKINADA | H9: 5 | I9: 117.98 | J9: 589.9 | K9: =G9+J9 -> 589.9 | L9: =+K9 -> 589.9
A10: 7 | B10: 46271 | C10: SRI S.V.AGENCIES | D10: SAMARLAKOTA | H10: 5 | I10: 117.06 | J10: 585.3 | K10: =G10+J10 -> 585.3 | L10: =+K10 -> 585.3
A11: 8 | B11: 46273 | C11: SRI BALAJI AGENCIES | D11: KAKINADA | E11: 42.62 | F11: 105.59 | G11: 4500.25 | K11: =G11+J11 -> 4500.25 | L11: =+K11 -> 4500.25
A12: 9 | B12: 46276 | C12: SRI BALAJI AGENCIES | D12: KAKINADA | E12: 37.96 | F12: 105.59 | G12: 4008.2 | K12: =G12+J12 -> 4008.2 | L12: =+K12 -> 4008.2
A13: 10 | B13: 46276 | C13: SRI BALAJI AGENCIES | D13: KAKINADA | H13: 5 | I13: 117.98 | J13: 589.9 | K13: =G13+J13 -> 589.9 | L13: =+K13 -> 589.9
A14: 11 | B14: 46276 | C14: SRI MALLIDI VENKATA REDDY AGENCIES | D14: MANDAPETA | H14: 5 | I14: 117.32 | J14: 586.6 | K14: =G14+J14 -> 586.6 | L14: =+K14 -> 586.6
A15: 12 | B15: 46277 | C15: SRI BALAJI AGENCIES | D15: KAKINADA | E15: 28.41 | F15: 105.59 | G15: 3000 | K15: =G15+J15 -> 3000 | L15: =+K15 -> 3000
A16: 13 | B16: 46280 | C16: BP - KAKINADA | D16: KAKINADA | H16: 7 | I16: 117.98 | J16: 825.86 | K16: =G16+J16 -> 825.86 | L16: =+K16 -> 825.86
A17: 14 | B17: 46282 | C17: BP - KAKINADA | D17: KAKINADA | H17: 5 | I17: 117.98 | J17: 589.9 | K17: =G17+J17 -> 589.9 | L17: =+K17 -> 589.9
A18: 15 | B18: 46284 | C18: BP - KAKINADA | D18: KAKINADA | E18: 37.88 | F18: 105.59 | G18: 4000 | K18: =G18+J18 -> 4000 | L18: =+K18 -> 4000
A19: 16 | B19: 46286 | C19: SRI MALLIDI VENKATA REDDY AGENCIES | D19: MANDAPETA | H19: 4.26 | I19: 117.32 | J19: 500 | K19: =G19+J19 -> 500 | L19: =+K19 -> 500
A20: 17 | B20: 46287 | C20: BP - KAKINADA | D20: KAKINADA | H20: 4.24 | I20: 117.98 | J20: 500 | K20: =G20+J20 -> 500 | L20: =+K20 -> 500
A21: 18 | B21: 46291 | C21: SATYA SIVA DURGA AGENCIES | D21: CHEBROLU | E21: 240 | F21: 105.21 | G21: 25250.4 | K21: =G21+J21 -> 25250.4 | L21: =+K21 -> 25250.4
A22: 19 | B22: 46292 | C22: SRI MALLIDI VENKATA REDDY AGENCIES | D22: MANDAPETA | H22: 5 | I22: 117.32 | J22: 586.6 | K22: =G22+J22 -> 586.6 | L22: =+K22 -> 586.6
A23: 20 | K23: =G23+J23 -> 0 | L23: =+K23 -> 0
A24: 21 | K24: =G24+J24 -> 0 | L24: =+K24 -> 0
A25: 22 | K25: =G25+J25 -> 0 | L25: =+K25 -> 0
A26: 23 | K26: =G26+J26 -> 0 | L26: =+K26 -> 0
A27: 24 | K27: =G27+J27 -> 0 | L27: =+K27 -> 0
A28: 25 | K28: =G28+J28 -> 0 | L28: =+K28 -> 0
A29: 26 | K29: =G29+J29 -> 0 | L29: =+K29 -> 0
A30: 27 | K30: =G30+J30 -> 0 | L30: =+K30 -> 0
A31: 28 | K31: =G31+J31 -> 0 | L31: =+K31 -> 0
A32: 29 | K32: =G32+J32 -> 0 | L32: =+K32 -> 0
A33: 30 | K33: =G33+J33 -> 0 | L33: =+K33 -> 0
A34: 31 | K34: =G34+J34 -> 0 | L34: =+K34 -> 0
A35: 32 | K35: =G35+J35 -> 0 | L35: =+K35 -> 0
A36: 33 | G36: =E36*F36 -> 0 | J36: =H36*I36 -> 0 | K36: =G36+J36 -> 0 | L36: =+K36 -> 0
A37: 34 | G37: =E37*F37 -> 0 | J37: =H37*I37 -> 0 | K37: =G37+J37 -> 0 | L37: =+K37 -> 0
A38: 35 | G38: =E38*F38 -> 0 | J38: =H38*I38 -> 0 | K38: =G38+J38 -> 0 | L38: =+K38 -> 0
A39: 36 | G39: =E39*F39 -> 0 | J39: =H39*I39 -> 0 | K39: =G39+J39 -> 0 | L39: =+K39 -> 0
A40: 37 | G40: =E40*F40 -> 0 | J40: =H40*I40 -> 0 | K40: =G40+J40 -> 0 | L40: =+K40 -> 0
A41: 38 | G41: =E41*F41 -> 0 | J41: =H41*I41 -> 0 | K41: =G41+J41 -> 0 | L41: =+K41 -> 0
A42: 39 | G42: =E42*F42 -> 0 | J42: =H42*I42 -> 0 | K42: =G42+J42 -> 0 | L42: =+K42 -> 0
A43: 40 | G43: =E43*F43 -> 0 | J43: =H43*I43 -> 0 | K43: =G43+J43 -> 0 | L43: =+K43 -> 0
A44: 41 | G44: =E44*F44 -> 0 | J44: =H44*I44 -> 0 | K44: =G44+J44 -> 0 | L44: =+K44 -> 0
A45: 42 | G45: =E45*F45 -> 0 | J45: =H45*I45 -> 0 | K45: =G45+J45 -> 0 | L45: =+K45 -> 0
A46: 43 | G46: =E46*F46 -> 0 | J46: =H46*I46 -> 0 | K46: =G46+J46 -> 0 | L46: =+K46 -> 0
A47: 44 | G47: =E47*F47 -> 0 | J47: =H47*I47 -> 0 | K47: =G47+J47 -> 0 | L47: =+K47 -> 0
... A66: 63 | G66: =E66*F66 -> 0 | J66: =H66*I66 -> 0 | K66: =G66+J66 -> 0 | L66: =+K66 -> 0
A67: 64
E68: =SUM(E4:E67) -> 474.25 | G68: =SUM(G4:G67) -> 50003.7 | H68: =SUM(H4:H67) -> 55.5 | J68: =SUM(J4:J67) -> 6530.56 | K68: =SUM(K4:K67) -> 56534.26

Sheet  Pitapram(KKD)
A1: SATYA SIVA DURGA AGENCIES, CHEBROLU (BPCL)
A2: S.No | B2: Date | C2: GRN No | D2: Ind no/Bill No | E2: Diesel (Lts) | F2: Price | G2: Amount | H2: Petrol (Lts) | I2: Price | J2: Amount | K2: Total amount | L2: Amount paid | M2: As on Date | N2: Remarks
A3: Opening Balance | M3: 124354
A4: 1 | B4: 46266 | E4: 120 | F4: 105.21 | G4: =E4*F4 -> 12625.2 | H4: 10 | I4: 117.58 | J4: =H4*I4 -> 1175.8 | K4: =G4+J4 -> 13801 | M4: =M3+K4-L4 -> 138155
B5: 46267 | E5: 158 | F5: 105.21 | G5: =E5*F5 -> 16623.18 | H5: 5 | I5: 117.58 | J5: =H5*I5 -> 587.9 | K5: =G5+J5 -> 17211.08 | M5: =M4+K5-L5 -> 155366.08
A6: 2 | B6: 46268 | E6: 148 | F6: 105.21 | G6: =E6*F6 -> 15571.08 | H6: 5 | I6: 117.58 | J6: =H6*I6 -> 587.9 | K6: =G6+J6 -> 16158.98 | M6: =M5+K6-L6 -> 171525.06
A7: 3 | B7: 46269 | E7: 344 | F7: 105.21 | G7: =E7*F7 -> 36192.24 | H7: 5 | I7: 117.58 | J7: =H7*I7 -> 587.9 | K7: =G7+J7 -> 36780.14 | M7: =M6+K7-L7 -> 208305.2
A8: 4 | B8: 46270 | E8: 50 | F8: 105.21 | G8: =E8*F8 -> 5260.5 | H8: 5 | I8: 117.58 | J8: =H8*I8 -> 587.9 | K8: =G8+J8 -> 5848.4 | M8: =M7+K8-L8 -> 214153.6
A9: 5 | B9: 46271 | E9: 235 | F9: 105.21 | G9: =E9*F9 -> 24724.35 | H9: 10 | I9: 117.58 | J9: =H9*I9 -> 1175.8 | K9: =G9+J9 -> 25900.15 | M9: =M8+K9-L9 -> 240053.75
A10: 6 | B10: 46272 | E10: 475 | F10: 105.21 | G10: =E10*F10 -> 49974.75 | H10: 55 | I10: 117.58 | J10: =H10*I10 -> 6466.9 | K10: =G10+J10 -> 56441.65 | M10: =M9+K10-L10 -> 296495.4
A11: 7 | B11: 46273 | E11: 157.77 | F11: 105.21 | G11: =E11*F11 -> 16598.982 | H11: 15 | I11: 117.58 | J11: =H11*I11 -> 1763.7 | K11: =G11+J11 -> 18362.682 | M11: =M10+K11-L11 -> 314858.08
A12: 8 | B12: 46274 | E12: 414 | F12: 105.21 | G12: =E12*F12 -> 43556.94 | H12: 5 | I12: 117.58 | J12: =H12*I12 -> 587.9 | K12: =G12+J12 -> 44144.84 | L12: 250000 | M12: =M11+K12-L12 -> 109002.92
A13: 9 | B13: 46275 | E13: 164.79 | F13: 105.21 | G13: =E13*F13 -> 17337.556 | H13: 70 | I13: 117.58 | J13: =H13*I13 -> 8230.6 | K13: =G13+J13 -> 25568.156 | M13: =M12+K13-L13 -> 134571.08
A14: 10 | B14: 46276 | E14: 279.93 | F14: 105.21 | G14: =E14*F14 -> 29451.435 | H14: 15 | I14: 117.58 | J14: =H14*I14 -> 1763.7 | K14: =G14+J14 -> 31215.135 | M14: =M13+K14-L14 -> 165786.21
A15: 11 | B15: 46277 | G15: =E15*F15 -> 0 | H15: 85 | I15: 117.58 | J15: =H15*I15 -> 9994.3 | K15: =G15+J15 -> 9994.3 | M15: =M14+K15-L15 -> 175780.51
A16: 12 | B16: 46278 | G16: =E16*F16 -> 0 | J16: =H16*I16 -> 0 | K16: =G16+J16 -> 0 | M16: =M15+K16-L16 -> 175780.51
A17: 13 | B17: 46279 | G17: =E17*F17 -> 0 | J17: =H17*I17 -> 0 | K17: =G17+J17 -> 0 | M17: =M16+K17-L17 -> 175780.51
A18: 14 | B18: 46280 | E18: 145.11 | F18: 105.21 | G18: =E18*F18 -> 15267.023 | H18: 37 | I18: 117.58 | J18: =H18*I18 -> 4350.46 | K18: =G18+J18 -> 19617.483 | M18: =M17+K18-L18 -> 195397.99
A19: 15 | B19: 46281 | E19: 279.69 | F19: 105.21 | G19: =E19*F19 -> 29426.185 | J19: =H19*I19 -> 0 | K19: =G19+J19 -> 29426.185 | M19: =M18+K19-L19 -> 224824.18
A20: 16 | B20: 46282 | E20: 200 | F20: 105.21 | G20: =E20*F20 -> 21042 | H20: 20 | I20: 117.58 | J20: =H20*I20 -> 2351.6 | K20: =G20+J20 -> 23393.6 | M20: =M19+K20-L20 -> 248217.78
A21: 17 | B21: 46283 | E21: 400 | F21: 105.21 | G21: =E21*F21 -> 42084 | J21: =H21*I21 -> 0 | K21: =G21+J21 -> 42084 | M21: =M20+K21-L21 -> 290301.78
A22: 18 | B22: 46284 | E22: 231.78 | F22: 105.21 | G22: =E22*F22 -> 24385.574 | H22: 25 | I22: 117.58 | J22: =H22*I22 -> 2939.5 | K22: =G22+J22 -> 27325.074 | L22: 244000 | M22: =M21+K22-L22 -> 73626.853
A23: 19 | B23: 46285 | G23: =E23*F23 -> 0 | J23: =H23*I23 -> 0 | K23: =G23+J23 -> 0 | M23: =M22+K23-L23 -> 73626.853
A24: 20 | B24: 46286 | E24: 290.01 | F24: 105.21 | G24: =E24*F24 -> 30511.952 | J24: =H24*I24 -> 0 | K24: =G24+J24 -> 30511.952 | M24: =M23+K24-L24 -> 104138.8
A25: 21 | B25: 46287 | E25: 249.8 | F25: 105.21 | G25: =E25*F25 -> 26281.458 | H25: 10 | I25: 117.58 | J25: =H25*I25 -> 1175.8 | K25: =G25+J25 -> 27457.258 | M25: =M24+K25-L25 -> 131596.06
A26: 22 | B26: 46288 | G26: =E26*F26 -> 0 | H26: 20 | I26: 117.58 | J26: =H26*I26 -> 2351.6 | K26: =G26+J26 -> 2351.6 | M26: =M25+K26-L26 -> 133947.66
A27: 23 | B27: 46289 | G27: =E27*F27 -> 0 | J27: =H27*I27 -> 0 | K27: =G27+J27 -> 0 | M27: =M26+K27-L27 -> 133947.66
A28: 24 | B28: 46290 | G28: =E28*F28 -> 0 | H28: 14.6 | I28: 117.58 | J28: =H28*I28 -> 1716.668 | K28: =G28+J28 -> 1716.668 | M28: =M27+K28-L28 -> 135664.33
A29: 25 | B29: 46291 | E29: 484.35 | F29: 105.21 | G29: =E29*F29 -> 50958.463 | H29: 32 | I29: 117.58 | J29: =H29*I29 -> 3762.56 | K29: =G29+J29 -> 54721.023 | M29: =M28+K29-L29 -> 190385.35
B30: 46292 | E30: 280 | F30: 105.21 | G30: =E30*F30 -> 29458.8 | J30: =H30*I30 -> 0 | K30: =G30+J30 -> 29458.8 | M30: =M29+K30-L30 -> 219844.15
A31: 26 | B31: 46293 | G31: =E31*F31 -> 0 | J31: =H31*I31 -> 0 | K31: =G31+J31 -> 0 | M31: =M30+K31-L31 -> 219844.15
A32: 27 | B32: 46294 | E32: 253.07 | F32: 105.21 | G32: =E32*F32 -> 26625.495 | H32: 52.63 | I32: 117.58 | J32: =H32*I32 -> 6188.2354 | K32: =G32+J32 -> 32813.73 | M32: =M31+K32-L32 -> 252657.88
A33: 28 | B33: 46295 | E33: 350 | F33: 105.21 | G33: =E33*F33 -> 36823.5 | H33: 20 | I33: 117.58 | J33: =H33*I33 -> 2351.6 | K33: =G33+J33 -> 39175.1 | M33: =M32+K33-L33 -> 291832.98
A34: 29 | G34: =E34*F34 -> 0 | J34: =H34*I34 -> 0 | K34: =G34+J34 -> 0 | M34: =M33+K34-L34 -> 291832.98
A35: 30 | G35: =E35*F35 -> 0 | J35: =H35*I35 -> 0 | K35: =G35+J35 -> 0 | M35: =M34+K35-L35 -> 291832.98
A36: 31 | G36: =E36*F36 -> 0 | J36: =H36*I36 -> 0 | K36: =G36+J36 -> 0 | M36: =M35+K36-L36 -> 291832.98
E37: =SUM(E4:E36) -> 5710.3 | G37: =SUM(G4:G36) -> 600780.66 | H37: =SUM(H4:H36) -> 516.23 | J37: =SUM(J4:J36) -> 60698.323 | K37: =SUM(K4:K36) -> 661478.99 | L37: =SUM(L4:L36) -> 494000

Sheet Yeleshwaram(KKD)
A1: SRI SATYA FILLING STATION, YELESWARAM (BPCL)
A2: S.No | B2: Date | C2: GRN No | D2: Ind no/Bill No | E2: Diesel (Lts) | F2: Price | G2: Amount | H2: Petrol (Lts) | I2: Price | J2: Amount | K2: Total amount | L2: Amount paid | M2: As on Date | N2: Remarks
A3: Opening Balance | M3: 8498.7136
A4: 1 | B4: 46266 | E4: 30 | F4: 105.46 | G4: =E4*F4 -> 3163.8 | J4: =H4*I4 -> 0 | K4: =G4+J4 -> 3163.8 | M4: =M3+K4-L4 -> 11662.514
A5: 2 | B5: 46267 | G5: =E5*F5 -> 0 | J5: =H5*I5 -> 0 | K5: =G5+J5 -> 0 | M5: =M4+K5-L5 -> 11662.514
A6: 3 | B6: 46268 | E6: 110 | F6: 105.46 | G6: =E6*F6 -> 11600.6 | J6: =H6*I6 -> 0 | K6: =G6+J6 -> 11600.6 | M6: =M5+K6-L6 -> 23263.114
A7: 4 | B7: 46269 | E7: 100 | F7: 105.46 | G7: =E7*F7 -> 10546 | J7: =H7*I7 -> 0 | K7: =G7+J7 -> 10546 | M7: =M6+K7-L7 -> 33809.114
A8: 5 | B8: 46270 | G8: =E8*F8 -> 0 | J8: =H8*I8 -> 0 | K8: =G8+J8 -> 0 | M8: =M7+K8-L8 -> 33809.114
A9: 6 | B9: 46271 | G9: =E9*F9 -> 0 | J9: =H9*I9 -> 0 | K9: =G9+J9 -> 0 | M9: =M8+K9-L9 -> 33809.114
A10: 7 | B10: 46272 | G10: =E10*F10 -> 0 | J10: =H10*I10 -> 0 | K10: =G10+J10 -> 0 | M10: =M9+K10-L10 -> 33809.114
A11: 8 | B11: 46273 | G11: =E11*F11 -> 0 | J11: =H11*I11 -> 0 | K11: =G11+J11 -> 0 | M11: =M10+K11-L11 -> 33809.114
A12: 9 | B12: 46274 | E12: 140 | F12: 105.46 | G12: =E12*F12 -> 14764.4 | J12: =H12*I12 -> 0 | K12: =G12+J12 -> 14764.4 | M12: =M11+K12-L12 -> 48573.514
A13: 10 | B13: 46275 | E13: 40 | F13: 105.46 | G13: =E13*F13 -> 4218.4 | H13: 5 | I13: 117.84 | J13: =H13*I13 -> 589.2 | K13: =G13+J13 -> 4807.6 | M13: =M12+K13-L13 -> 53381.114
A14: 11 | B14: 46276 | G14: =E14*F14 -> 0 | J14: =H14*I14 -> 0 | K14: =G14+J14 -> 0 | M14: =M13+K14-L14 -> 53381.114
A15: 12 | B15: 46277 | E15: 100 | F15: 105.46 | G15: =E15*F15 -> 10546 | J15: =H15*I15 -> 0 | K15: =G15+J15 -> 10546 | M15: =M14+K15-L15 -> 63927.114
A16: 13 | B16: 46278 | G16: =E16*F16 -> 0 | J16: =H16*I16 -> 0 | K16: =G16+J16 -> 0 | M16: =M15+K16-L16 -> 63927.114
A17: 14 | B17: 46279 | G17: =E17*F17 -> 0 | J17: =H17*I17 -> 0 | K17: =G17+J17 -> 0 | M17: =M16+K17-L17 -> 63927.114
A18: 15 | B18: 46280 | G18: =E18*F18 -> 0 | H18: 5 | I18: 117.84 | J18: =H18*I18 -> 589.2 | K18: =G18+J18 -> 589.2 | M18: =M17+K18-L18 -> 64516.314
A19: 16 | B19: 46281 | G19: =E19*F19 -> 0 | J19: =H19*I19 -> 0 | K19: =G19+J19 -> 0 | M19: =M18+K19-L19 -> 64516.314
A20: 17 | B20: 46282 | G20: =E20*F20 -> 0 | J20: =H20*I20 -> 0 | K20: =G20+J20 -> 0 | M20: =M19+K20-L20 -> 64516.314
A21: 18 | B21: 46283 | E21: 152.02 | F21: 105.46 | G21: =E21*F21 -> 16032.029 | J21: =H21*I21 -> 0 | K21: =G21+J21 -> 16032.029 | M21: =M20+K21-L21 -> 80548.343
A22: 19 | B22: 46284 | G22: =E22*F22 -> 0 | J22: =H22*I22 -> 0 | K22: =G22+J22 -> 0 | M22: =M21+K22-L22 -> 80548.343
A23: 20 | B23: 46285 | G23: =E23*F23 -> 0 | J23: =H23*I23 -> 0 | K23: =G23+J23 -> 0 | M23: =M22+K23-L23 -> 80548.343
A24: 21 | B24: 46286 | G24: =E24*F24 -> 0 | J24: =H24*I24 -> 0 | K24: =G24+J24 -> 0 | M24: =M23+K24-L24 -> 80548.343
A25: 22 | B25: 46287 | G25: =E25*F25 -> 0 | J25: =H25*I25 -> 0 | K25: =G25+J25 -> 0 | M25: =M24+K25-L25 -> 80548.343
A26: 23 | B26: 46288 | E26: 30 | F26: 105.46 | G26: =E26*F26 -> 3163.8 | J26: =H26*I26 -> 0 | K26: =G26+J26 -> 3163.8 | L26: 80000 | M26: =M25+K26-L26 -> 3712.1428
A27: 24 | B27: 46289 | E27: 40 | F27: 105.46 | G27: =E27*F27 -> 4218.4 | H27: 5 | I27: 117.84 | J27: =H27*I27 -> 589.2 | K27: =G27+J27 -> 4807.6 | M27: =M26+K27-L27 -> 8519.7428
A28: 25 | B28: 46290 | G28: =E28*F28 -> 0 | J28: =H28*I28 -> 0 | K28: =G28+J28 -> 0 | M28: =M27+K28-L28 -> 8519.7428
A29: 26 | B29: 46291 | G29: =E29*F29 -> 0 | J29: =H29*I29 -> 0 | K29: =G29+J29 -> 0 | M29: =M28+K29-L29 -> 8519.7428
A30: 27 | B30: 46292 | J30: =H30*I30 -> 0 | K30: =G30+J30 -> 0 | M30: =M29+K30-L30 -> 8519.7428
A31: 28 | B31: 46293 | G31: =E31*F31 -> 0 | J31: =H31*I31 -> 0 | K31: =G31+J31 -> 0 | M31: =M30+K31-L31 -> 8519.7428
A32: 29 | B32: 46294 | G32: =E32*F32 -> 0 | H32: 5 | I32: 117.84 | J32: =H32*I32 -> 589.2 | K32: =G32+J32 -> 589.2 | M32: =M31+K32-L32 -> 9108.9428
A33: 30 | B33: 46295 | E33: 70 | F33: 105.46 | G33: =E33*F33 -> 7382.2 | H33: 5 | I33: 117.84 | J33: =H33*I33 -> 589.2 | K33: =G33+J33 -> 7971.4 | M33: =M32+K33-L33 -> 17080.343
A34: 31 | G34: =E34*F34 -> 0 | J34: =H34*I34 -> 0 | K34: =G34+J34 -> 0 | M34: =M33+K34-L34 -> 17080.343
A35: 32 | G35: =E35*F35 -> 0 | J35: =H35*I35 -> 0 | K35: =G35+J35 -> 0 | M35: =M34+K35-L35 -> 17080.343
A36: 33 | G36: =E36*F36 -> 0 | J36: =H36*I36 -> 0 | K36: =G36+J36 -> 0 | M36: =M35+K36-L36 -> 17080.343
E37: =SUM(E4:E36) -> 812.02 | G37: =SUM(G4:G36) -> 85635.629 | H37: =SUM(H4:H36) -> 25 | J37: =SUM(J4:J36) -> 2946 | K37: =SUM(K4:K36) -> 88581.629 | L37: =SUM(L4:L36) -> 80000

Sheet Amalapuram(KKD)
A1: ROYAL FILL 'N' FLY, AMALAPURAM(HPCL)
A2: S.No | B2: Date | C2: GRN No | D2: Ind no/Bill No | E2: Diesel (Lts) | F2: Price | G2: Amount | H2: Petrol (Lts) | I2: Price | J2: Amount | K2: Total amount | L2: Amount paid | M2: As on Date | N2: Remarks
A3: Opening Balance | M3: 426859.64
A4: 1 | B4: 46266 | E4: 60 | F4: 105.25 | G4: =E4*F4 -> 6315 | H4: 6 | I4: 117.58 | J4: =H4*I4 -> 705.48 | K4: =G4+J4 -> 7020.48 | M4: =M3+K4-L4 -> 433880.12
A5: 2 | B5: 46267 | E5: 500 | F5: 105.25 | G5: =E5*F5 -> 52625 | J5: =H5*I5 -> 0 | K5: =G5+J5 -> 52625 | L5: 326000 | M5: =M4+K5-L5 -> 160505.12
A6: 3 | B6: 46268 | G6: =E6*F6 -> 0 | J6: =H6*I6 -> 0 | K6: =G6+J6 -> 0 | M6: =M5+K6-L6 -> 160505.12
A7: 4 | B7: 46269 | E7: 400 | F7: 105.25 | G7: =E7*F7 -> 42100 | H7: 5 | I7: 117.58 | J7: =H7*I7 -> 587.9 | K7: =G7+J7 -> 42687.9 | M7: =M6+K7-L7 -> 203193.02
A8: 5 | B8: 46270 | E8: 266.67 | F8: 105.25 | G8: =E8*F8 -> 28067.018 | H8: 6 | I8: 117.58 | J8: =H8*I8 -> 705.48 | K8: =G8+J8 -> 28772.498 | M8: =M7+K8-L8 -> 231965.51
A9: 6 | B9: 46271 | E9: 100 | F9: 105.25 | G9: =E9*F9 -> 10525 | J9: =H9*I9 -> 0 | K9: =G9+J9 -> 10525 | M9: =M8+K9-L9 -> 242490.51
A10: 7 | B10: 46272 | E10: 440 | F10: 105.25 | G10: =E10*F10 -> 46310 | H10: 5 | I10: 117.58 | J10: =H10*I10 -> 587.9 | K10: =G10+J10 -> 46897.9 | L10: 99000 | M10: =M9+K10-L10 -> 190388.41
A11: 8 | B11: 46273 | E11: 1159 | F11: 105.25 | G11: =E11*F11 -> 121984.75 | H11: 5 | I11: 117.58 | J11: =H11*I11 -> 587.9 | K11: =G11+J11 -> 122572.65 | M11: =M10+K11-L11 -> 312961.06
A12: 9 | B12: 46274 | E12: 43.1 | F12: 105.25 | G12: =E12*F12 -> 4536.275 | H12: 5 | I12: 117.58 | J12: =H12*I12 -> 587.9 | K12: =G12+J12 -> 5124.175 | M12: =M11+K12-L12 -> 318085.24
A13: 10 | B13: 46275 | E13: 820 | F13: 105.25 | G13: =E13*F13 -> 86305 | H13: 5 | I13: 117.58 | J13: =H13*I13 -> 587.9 | K13: =G13+J13 -> 86892.9 | M13: =M12+K13-L13 -> 404978.14
A14: 11 | B14: 46276 | G14: =E14*F14 -> 0 | J14: =H14*I14 -> 0 | K14: =G14+J14 -> 0 | M14: =M13+K14-L14 -> 404978.14
A15: 12 | B15: 46277 | E15: 786.02 | F15: 105.25 | G15: =E15*F15 -> 82728.605 | J15: =H15*I15 -> 0 | K15: =G15+J15 -> 82728.605 | M15: =M14+K15-L15 -> 487706.74
A16: 13 | B16: 46278 | G16: =E16*F16 -> 0 | J16: =H16*I16 -> 0 | K16: =G16+J16 -> 0 | M16: =M15+K16-L16 -> 487706.74
A17: 14 | B17: 46279 | G17: =E17*F17 -> 0 | J17: =H17*I17 -> 0 | K17: =G17+J17 -> 0 | M17: =M16+K17-L17 -> 487706.74
A18: 15 | B18: 46280 | E18: 330 | F18: 105.25 | G18: =E18*F18 -> 34732.5 | H18: 19 | I18: 117.58 | J18: =H18*I18 -> 2234.02 | K18: =G18+J18 -> 36966.52 | M18: =M17+K18-L18 -> 524673.26
A19: 16 | B19: 46281 | E19: 1020 | F19: 105.25 | G19: =E19*F19 -> 107355 | J19: =H19*I19 -> 0 | K19: =G19+J19 -> 107355 | L19: 490000 | M19: =M18+K19-L19 -> 142028.26
A20: 17 | B20: 46282 | E20: 40 | F20: 105.25 | G20: =E20*F20 -> 4210 | J20: =H20*I20 -> 0 | K20: =G20+J20 -> 4210 | M20: =M19+K20-L20 -> 146238.26
A21: 18 | B21: 46283 | E21: 855 | F21: 105.25 | G21: =E21*F21 -> 89988.75 | H21: 6 | I21: 117.58 | J21: =H21*I21 -> 705.48 | K21: =G21+J21 -> 90694.23 | M21: =M20+K21-L21 -> 236932.49
A22: 19 | B22: 46284 | G22: =E22*F22 -> 0 | H22: 5 | I22: 117.58 | J22: =H22*I22 -> 587.9 | K22: =G22+J22 -> 587.9 | M22: =M21+K22-L22 -> 237520.39
A23: 20 | B23: 46285 | G23: =E23*F23 -> 0 | H23: 5 | I23: 117.58 | J23: =H23*I23 -> 587.9 | K23: =G23+J23 -> 587.9 | M23: =M22+K23-L23 -> 238108.29
A24: 21 | B24: 46286 | E24: 880 | F24: 105.25 | G24: =E24*F24 -> 92620 | J24: =H24*I24 -> 0 | K24: =G24+J24 -> 92620 | M24: =M23+K24-L24 -> 330728.29
A25: 22 | B25: 46287 | E25: 1162 | F25: 105.25 | G25: =E25*F25 -> 122300.5 | H25: 6 | I25: 117.58 | J25: =H25*I25 -> 705.48 | K25: =G25+J25 -> 123005.98 | M25: =M24+K25-L25 -> 453734.27
A26: 23 | B26: 46288 | G26: =E26*F26 -> 0 | J26: =H26*I26 -> 0 | K26: =G26+J26 -> 0 | M26: =M25+K26-L26 -> 453734.27
A27: 24 | B27: 46289 | G27: =E27*F27 -> 0 | J27: =H27*I27 -> 0 | K27: =G27+J27 -> 0 | M27: =M26+K27-L27 -> 453734.27
A28: 25 | B28: 46290 | E28: 225 | F28: 105.25 | G28: =E28*F28 -> 23681.25 | H28: 15 | I28: 117.58 | J28: =H28*I28 -> 1763.7 | K28: =G28+J28 -> 25444.95 | M28: =M27+K28-L28 -> 479179.22
A29: 26 | B29: 46291 | G29: =E29*F29 -> 0 | J29: =H29*I29 -> 0 | K29: =G29+J29 -> 0 | L29: 100000 | M29: =M28+K29-L29 -> 379179.22
A30: 27 | B30: 46292 | G30: =E30*F30 -> 0 | J30: =H30*I30 -> 0 | K30: =G30+J30 -> 0 | M30: =M29+K30-L30 -> 379179.22
A31: 28 | B31: 46293 | E31: 440 | F31: 105.25 | G31: =E31*F31 -> 46310 | H31: 5 | I31: 117.58 | J31: =H31*I31 -> 587.9 | K31: =G31+J31 -> 46897.9 | M31: =M30+K31-L31 -> 426077.12
A32: 29 | B32: 46294 | E32: 40 | F32: 105.25 | G32: =E32*F32 -> 4210 | H32: 5 | I32: 117.58 | J32: =H32*I32 -> 587.9 | K32: =G32+J32 -> 4797.9 | M32: =M31+K32-L32 -> 430875.02
A33: 30 | B33: 46295 | E33: 840 | F33: 105.25 | G33: =E33*F33 -> 88410 | H33: 3 | I33: 117.58 | J33: =H33*I33 -> 352.74 | K33: =G33+J33 -> 88762.74 | M33: =M32+K33-L33 -> 519637.76
A34: 31 | G34: =E34*F34 -> 0 | J34: =H34*I34 -> 0 | K34: =G34+J34 -> 0 | M34: =M33+K34-L34 -> 519637.76
A35: 32 | G35: =E35*F35 -> 0 | J35: =H35*I35 -> 0 | K35: =G35+J35 -> 0 | M35: =M34+K35-L35 -> 519637.76
A36: 33 | G36: =E36*F36 -> 0 | J36: =H36*I36 -> 0 | K36: =G36+J36 -> 0 | M36: =M35+K36-L36 -> 519637.76
E37: =SUM(E4:E36) -> 10406.79 | G37: =SUM(G4:G36) -> 1095314.6 | H37: =SUM(H4:H36) -> 106 | J37: =SUM(J4:J36) -> 12463.48 | K37: =SUM(K4:K36) -> 1107778.1 | L37: =SUM(L4:L36) -> 1015000

Sheet  Solasa Krishna OIl
A1: SOLASA KRISHNA OIL COMPANY
A2: S.No | B2: Date | C2: GRN No | D2: Ind no/Bill No | E2: Diesel (Lts) | F2: Price | G2: Amount | H2: Petrol (Lts) | I2: Price | J2: Amount | K2: Total amount | L2: Amount paid | M2: As on Date | N2: Remarks
A3: Opening Balance | M3: 46362.715
A4: 1 | B4: 46266 | E4: 140 | F4: 105.4 | G4: =E4*F4 -> 14756 | J4: =H4*I4 -> 0 | K4: =G4+J4 -> 14756 | L4: 0 | M4: =M3+K4-L4 -> 61118.715
A5: 2 | B5: 46267 | G5: =E5*F5 -> 0 | H5: 5 | I5: 117.74 | J5: =H5*I5 -> 588.7 | K5: =G5+J5 -> 588.7 | M5: =M4+K5-L5 -> 61707.415
A6: 3 | B6: 46268 | E6: 220 | F6: 105.4 | G6: =E6*F6 -> 23188 | J6: =H6*I6 -> 0 | K6: =G6+J6 -> 23188 | M6: =M5+K6-L6 -> 84895.415
A7: 4 | B7: 46269 | E7: 74.83 | F7: 105.4 | G7: =E7*F7 -> 7887.082 | J7: =H7*I7 -> 0 | K7: =G7+J7 -> 7887.082 | M7: =M6+K7-L7 -> 92782.497
A8: 5 | B8: 46270 | E8: 90 | F8: 105.4 | G8: =E8*F8 -> 9486 | J8: =H8*I8 -> 0 | K8: =G8+J8 -> 9486 | M8: =M7+K8-L8 -> 102268.5
A9: 6 | B9: 46271 | E9: 136.02 | F9: 105.4 | G9: =E9*F9 -> 14336.508 | J9: =H9*I9 -> 0 | K9: =G9+J9 -> 14336.508 | M9: =M8+K9-L9 -> 116605.01
A10: 7 | B10: 46272 | G10: =E10*F10 -> 0 | J10: =H10*I10 -> 0 | K10: =G10+J10 -> 0 | M10: =M9+K10-L10 -> 116605.01
A11: 8 | B11: 46273 | G11: =E11*F11 -> 0 | H11: 5 | I11: 117.74 | J11: =H11*I11 -> 588.7 | K11: =G11+J11 -> 588.7 | M11: =M10+K11-L11 -> 117193.71
A12: 9 | B12: 46274 | G12: =E12*F12 -> 0 | J12: =H12*I12 -> 0 | K12: =G12+J12 -> 0 | M12: =M11+K12-L12 -> 117193.71
A13: 10 | B13: 46275 | G13: =E13*F13 -> 0 | J13: =H13*I13 -> 0 | K13: =G13+J13 -> 0 | M13: =M12+K13-L13 -> 117193.71
A14: 11 | B14: 46276 | G14: =E14*F14 -> 0 | J14: =H14*I14 -> 0 | K14: =G14+J14 -> 0 | M14: =M13+K14-L14 -> 117193.71
A15: 12 | B15: 46277 | G15: =E15*F15 -> 0 | J15: =H15*I15 -> 0 | K15: =G15+J15 -> 0 | M15: =M14+K15-L15 -> 117193.71
A16: 13 | B16: 46278 | G16: =E16*F16 -> 0 | J16: =H16*I16 -> 0 | K16: =G16+J16 -> 0 | M16: =M15+K16-L16 -> 117193.71
A17: 14 | B17: 46279 | G17: =E17*F17 -> 0 | H17: 5.01 | I17: 117.74 | J17: =H17*I17 -> 589.8774 | K17: =G17+J17 -> 589.8774 | M17: =M16+K17-L17 -> 117783.58
A18: 15 | B18: 46280 | E18: 38 | F18: 105.4 | G18: =E18*F18 -> 4005.2 | J18: =H18*I18 -> 0 | K18: =G18+J18 -> 4005.2 | M18: =M17+K18-L18 -> 121788.78
A19: 16 | B19: 46281 | G19: =E19*F19 -> 0 | J19: =H19*I19 -> 0 | K19: =G19+J19 -> 0 | M19: =M18+K19-L19 -> 121788.78
A20: 17 | B20: 46282 | G20: =E20*F20 -> 0 | J20: =H20*I20 -> 0 | K20: =G20+J20 -> 0 | M20: =M19+K20-L20 -> 121788.78
A21: 18 | B21: 46283 | E21: 34.4 | F21: 105.4 | G21: =E21*F21 -> 3625.76 | J21: =H21*I21 -> 0 | K21: =G21+J21 -> 3625.76 | M21: =M20+K21-L21 -> 125414.54
A22: 19 | B22: 46284 | G22: =E22*F22 -> 0 | H22: 5 | I22: 117.74 | J22: =H22*I22 -> 588.7 | K22: =G22+J22 -> 588.7 | M22: =M21+K22-L22 -> 126003.24
A23: 20 | B23: 46285 | G23: =E23*F23 -> 0 | J23: =H23*I23 -> 0 | K23: =G23+J23 -> 0 | M23: =M22+K23-L23 -> 126003.24
A24: 21 | B24: 46286 | E24: 234.64 | F24: 105.4 | G24: =E24*F24 -> 24731.056 | J24: =H24*I24 -> 0 | K24: =G24+J24 -> 24731.056 | M24: =M23+K24-L24 -> 150734.3
A25: 22 | B25: 46287 | E25: 43.01 | F25: 105.4 | G25: =E25*F25 -> 4533.254 | H25: 8.04 | I25: 117.74 | J25: =H25*I25 -> 946.6296 | K25: =G25+J25 -> 5479.8836 | M25: =M24+K25-L25 -> 156214.18
A26: 23 | B26: 46288 | E26: 20 | F26: 105.4 | G26: =E26*F26 -> 2108 | J26: =H26*I26 -> 0 | K26: =G26+J26 -> 2108 | M26: =M25+K26-L26 -> 158322.18
A27: 24 | B27: 46289 | E27: 28.44 | F27: 105.4 | G27: =E27*F27 -> 2997.576 | J27: =H27*I27 -> 0 | K27: =G27+J27 -> 2997.576 | M27: =M26+K27-L27 -> 161319.76
A28: 25 | B28: 46290 | E28: 28.98 | F28: 105.4 | G28: =E28*F28 -> 3054.492 | J28: =H28*I28 -> 0 | K28: =G28+J28 -> 3054.492 | M28: =M27+K28-L28 -> 164374.25
A29: 26 | B29: 46291 | E29: 129.23 | F29: 105.4 | G29: =E29*F29 -> 13620.842 | J29: =H29*I29 -> 0 | K29: =G29+J29 -> 13620.842 | M29: =M28+K29-L29 -> 177995.09
A30: 27 | B30: 46292 | G30: =E30*F30 -> 0 | J30: =H30*I30 -> 0 | K30: =G30+J30 -> 0 | M30: =M29+K30-L30 -> 177995.09
A31: 28 | B31: 46293 | E31: 316.23 | F31: 105.4 | G31: =E31*F31 -> 33330.642 | J31: =H31*I31 -> 0 | K31: =G31+J31 -> 33330.642 | M31: =M30+K31-L31 -> 211325.73
A32: 29 | B32: 46294 | E32: 230 | F32: 105.4 | G32: =E32*F32 -> 24242 | J32: =H32*I32 -> 0 | K32: =G32+J32 -> 24242 | M32: =M31+K32-L32 -> 235567.73
A33: 30 | B33: 46295 | E33: 31.63 | F33: 105.4 | G33: =E33*F33 -> 3333.802 | J33: =H33*I33 -> 0 | K33: =G33+J33 -> 3333.802 | M33: =M32+K33-L33 -> 238901.54
A34: 31 | G34: =E34*F34 -> 0 | J34: =H34*I34 -> 0 | K34: =G34+J34 -> 0 | M34: =M33+K34-L34 -> 238901.54
A35: 32 | G35: =E35*F35 -> 0 | J35: =H35*I35 -> 0 | K35: =G35+J35 -> 0 | M35: =M34+K35-L35 -> 238901.54
A36: 33 | G36: =E36*F36 -> 0 | J36: =H36*I36 -> 0 | K36: =G36+J36 -> 0 | M36: =M35+K36-L36 -> 238901.54
E37: =SUM(E4:E36) -> 1795.41 | G37: =SUM(G4:G36) -> 189236.21 | H37: =SUM(H4:H36) -> 28.05 | J37: =SUM(J4:J36) -> 3302.607 | K37: =SUM(K4:K36) -> 192538.82 | L37: =SUM(L4:L36) -> 0

Sheet Sri Venkateshwara Services
A1: Sri Venkateshwara Services
A2: S.No | B2: Date | C2: GRN No | D2: Ind no/Bill No | E2: Diesel (Lts) | F2: Price | G2: Amount | H2: Petrol (Lts) | I2: Price | J2: Amount | K2: Total amount | L2: Amount paid | M2: As on Date | N2: Remarks
A3: Opening Balance | M3: 17037.915
A4: 1 | B4: 46266 | E4: 104 | F4: 104.68 | G4: =E4*F4 -> 10886.72 | H4: 10 | I4: 116.96 | J4: =H4*I4 -> 1169.6 | K4: =G4+J4 -> 12056.32 | M4: =M3+K4-L4 -> 29094.235
A5: 2 | B5: 46267 | E5: 85 | F5: 104.68 | G5: =E5*F5 -> 8897.8 | H5: 25.01 | I5: 116.96 | J5: =H5*I5 -> 2925.1696 | K5: =G5+J5 -> 11822.97 | M5: =M4+K5-L5 -> 40917.205
A6: 3 | B6: 46268 | G6: =E6*F6 -> 0 | J6: =H6*I6 -> 0 | K6: =G6+J6 -> 0 | M6: =M5+K6-L6 -> 40917.205
A7: 4 | B7: 46269 | E7: 141.12 | F7: 104.68 | G7: =E7*F7 -> 14772.442 | H7: 5 | I7: 116.96 | J7: =H7*I7 -> 584.8 | K7: =G7+J7 -> 15357.242 | M7: =M6+K7-L7 -> 56274.446
A8: 5 | B8: 46270 | E8: 38 | F8: 104.68 | G8: =E8*F8 -> 3977.84 | H8: 10 | I8: 116.96 | J8: =H8*I8 -> 1169.6 | K8: =G8+J8 -> 5147.44 | M8: =M7+K8-L8 -> 61421.886
A9: 6 | B9: 46271 | G9: =E9*F9 -> 0 | J9: =H9*I9 -> 0 | K9: =G9+J9 -> 0 | M9: =M8+K9-L9 -> 61421.886
A10: 7 | B10: 46272 | E10: 86.53 | F10: 104.68 | G10: =E10*F10 -> 9057.9604 | H10: 5 | I10: 116.96 | J10: =H10*I10 -> 584.8 | K10: =G10+J10 -> 9642.7604 | M10: =M9+K10-L10 -> 71064.647
A11: 8 | B11: 46273 | E11: 422 | F11: 104.68 | G11: =E11*F11 -> 44174.96 | J11: =H11*I11 -> 0 | K11: =G11+J11 -> 44174.96 | M11: =M10+K11-L11 -> 115239.61
A12: 9 | B12: 46274 | E12: 50.79 | F12: 104.68 | G12: =E12*F12 -> 5316.6972 | H12: 15 | I12: 116.96 | J12: =H12*I12 -> 1754.4 | K12: =G12+J12 -> 7071.0972 | M12: =M11+K12-L12 -> 122310.7
A13: 10 | B13: 46275 | G13: =E13*F13 -> 0 | H13: 30.01 | I13: 116.96 | J13: =H13*I13 -> 3509.9696 | K13: =G13+J13 -> 3509.9696 | M13: =M12+K13-L13 -> 125820.67
A14: 11 | B14: 46276 | G14: =E14*F14 -> 0 | J14: =H14*I14 -> 0 | K14: =G14+J14 -> 0 | M14: =M13+K14-L14 -> 125820.67
A15: 12 | B15: 46277 | E15: 75 | F15: 104.68 | G15: =E15*F15 -> 7851 | J15: =H15*I15 -> 0 | K15: =G15+J15 -> 7851 | M15: =M14+K15-L15 -> 133671.67
A16: 13 | B16: 46278 | E16: 30 | F16: 104.68 | G16: =E16*F16 -> 3140.4 | H16: 5 | I16: 116.96 | J16: =H16*I16 -> 584.8 | K16: =G16+J16 -> 3725.2 | M16: =M15+K16-L16 -> 137396.87
A17: 14 | B17: 46279 | G17: =E17*F17 -> 0 | J17: =H17*I17 -> 0 | K17: =G17+J17 -> 0 | M17: =M16+K17-L17 -> 137396.87
A18: 15 | B18: 46280 | E18: 143.25 | F18: 104.68 | G18: =E18*F18 -> 14995.41 | H18: 10 | I18: 116.96 | J18: =H18*I18 -> 1169.6 | K18: =G18+J18 -> 16165.01 | M18: =M17+K18-L18 -> 153561.88
A19: 16 | B19: 46281 | E19: 32 | F19: 104.68 | G19: =E19*F19 -> 3349.76 | H19: 10 | I19: 116.96 | J19: =H19*I19 -> 1169.6 | K19: =G19+J19 -> 4519.36 | L19: 100000 | M19: =M18+K19-L19 -> 58081.244
A20: 17 | B20: 46282 | E20: 41 | F20: 104.68 | G20: =E20*F20 -> 4291.88 | J20: =H20*I20 -> 0 | K20: =G20+J20 -> 4291.88 | M20: =M19+K20-L20 -> 62373.124
A21: 18 | B21: 46283 | E21: 70.674 | F21: 104.68 | G21: =E21*F21 -> 7398.1543 | H21: 5 | I21: 116.96 | J21: =H21*I21 -> 584.8 | K21: =G21+J21 -> 7982.9543 | M21: =M20+K21-L21 -> 70356.078
A22: 19 | B22: 46284 | G22: =E22*F22 -> 0 | J22: =H22*I22 -> 0 | K22: =G22+J22 -> 0 | M22: =M21+K22-L22 -> 70356.078
A23: 20 | B23: 46285 | G23: =E23*F23 -> 0 | J23: =H23*I23 -> 0 | K23: =G23+J23 -> 0 | M23: =M22+K23-L23 -> 70356.078
A24: 21 | B24: 46286 | E24: 34 | F24: 104.68 | G24: =E24*F24 -> 3559.12 | H24: 5 | I24: 116.96 | J24: =H24*I24 -> 584.8 | K24: =G24+J24 -> 4143.92 | M24: =M23+K24-L24 -> 74499.998
A25: 22 | B25: 46287 | E25: 79 | F25: 104.68 | G25: =E25*F25 -> 8269.72 | H25: 5 | I25: 116.96 | J25: =H25*I25 -> 584.8 | K25: =G25+J25 -> 8854.52 | M25: =M24+K25-L25 -> 83354.518
A26: 23 | B26: 46288 | E26: 49 | F26: 104.68 | G26: =E26*F26 -> 5129.32 | H26: 5 | I26: 116.96 | J26: =H26*I26 -> 584.8 | K26: =G26+J26 -> 5714.12 | M26: =M25+K26-L26 -> 89068.638
A27: 24 | B27: 46289 | G27: =E27*F27 -> 0 | H27: 5 | I27: 116.96 | J27: =H27*I27 -> 584.8 | K27: =G27+J27 -> 584.8 | M27: =M26+K27-L27 -> 89653.438
A28: 25 | B28: 46290 | G28: =E28*F28 -> 0 | H28: 5 | I28: 116.96 | J28: =H28*I28 -> 584.8 | K28: =G28+J28 -> 584.8 | M28: =M27+K28-L28 -> 90238.238
A29: 26 | B29: 46291 | E29: 40 | F29: 104.68 | G29: =E29*F29 -> 4187.2 | J29: =H29*I29 -> 0 | K29: =G29+J29 -> 4187.2 | M29: =M28+K29-L29 -> 94425.438
A30: 27 | B30: 46292 | G30: =E30*F30 -> 0 | J30: =H30*I30 -> 0 | K30: =G30+J30 -> 0 | M30: =M29+K30-L30 -> 94425.438
A31: 28 | B31: 46293 | E31: 100 | F31: 104.68 | G31: =E31*F31 -> 10468 | H31: 55 | I31: 116.96 | J31: =H31*I31 -> 6432.8 | K31: =G31+J31 -> 16900.8 | M31: =M30+K31-L31 -> 111326.24
A32: 29 | B32: 46294 | G32: =E32*F32 -> 0 | H32: 35 | I32: 116.96 | J32: =H32*I32 -> 4093.6 | K32: =G32+J32 -> 4093.6 | M32: =M31+K32-L32 -> 115419.84
A33: 30 | B33: 46295 | G33: =E33*F33 -> 0 | J33: =H33*I33 -> 0 | K33: =G33+J33 -> 0 | M33: =M32+K33-L33 -> 115419.84
A34: 31 | G34: =E34*F34 -> 0 | J34: =H34*I34 -> 0 | K34: =G34+J34 -> 0 | M34: =M33+K34-L34 -> 115419.84
A35: 32 | G35: =E35*F35 -> 0 | J35: =H35*I35 -> 0 | K35: =G35+J35 -> 0 | M35: =M34+K35-L35 -> 115419.84
A36: 33 | G36: =E36*F36 -> 0 | J36: =H36*I36 -> 0 | K36: =G36+J36 -> 0 | M36: =M35+K36-L36 -> 115419.84
E37: =SUM(E4:E36) -> 1621.364 | G37: =SUM(G4:G36) -> 169724.38 | H37: =SUM(H4:H36) -> 245.02 | J37: =SUM(J4:J36) -> 28657.539 | K37: =SUM(K4:K36) -> 198381.92 | L37: =SUM(L4:L36) -> 100000

Sheet  Raja Filling Statuion
A1: Raja Filling Station
A2: S.No | B2: Date | C2: GRN No | D2: Ind No/Bill No | E2: Diesel (Lts) | F2: Price | G2: Amount | H2: Petrol (Lts) | I2: Price | J2: Amount | K2: Total amount | L2: Amount paid | M2: As on Date | N2: Remarks
A3: Opening Balance
A4: 1 | B4: 45901 | G4: =E4*F4 -> 0 | J4: =H4*I4 -> 0 | K4: =G4+J4 -> 0 | M4: =M3+K4-L4 -> 0
A5: 2 | B5: 45902 | G5: =E5*F5 -> 0 | J5: =H5*I5 -> 0 | K5: =G5+J5 -> 0 | M5: =M4+K5-L5 -> 0
A6: 3 | B6: 45903 | G6: =E6*F6 -> 0 | J6: =H6*I6 -> 0 | K6: =G6+J6 -> 0 | M6: =M5+K6-L6 -> 0
A7: 4 | B7: 45904 | G7: =E7*F7 -> 0 | J7: =H7*I7 -> 0 | K7: =G7+J7 -> 0 | M7: =M6+K7-L7 -> 0
A8: 5 | B8: 45905 | G8: =E8*F8 -> 0 | J8: =H8*I8 -> 0 | K8: =G8+J8 -> 0 | M8: =M7+K8-L8 -> 0
A9: 6 | B9: 45906 | G9: =E9*F9 -> 0 | J9: =H9*I9 -> 0 | K9: =G9+J9 -> 0 | M9: =M8+K9-L9 -> 0
A10: 7 | B10: 45907 | G10: =E10*F10 -> 0 | J10: =H10*I10 -> 0 | K10: =G10+J10 -> 0 | M10: =M9+K10-L10 -> 0
A11: 8 | B11: 45908 | G11: =E11*F11 -> 0 | J11: =H11*I11 -> 0 | K11: =G11+J11 -> 0 | M11: =M10+K11-L11 -> 0
A12: 9 | B12: 45909 | G12: =E12*F12 -> 0 | J12: =H12*I12 -> 0 | K12: =G12+J12 -> 0 | M12: =M11+K12-L12 -> 0
A13: 10 | B13: 45910 | G13: =E13*F13 -> 0 | J13: =H13*I13 -> 0 | K13: =G13+J13 -> 0 | M13: =M12+K13-L13 -> 0
A14: 11 | B14: 45911 | G14: =E14*F14 -> 0 | J14: =H14*I14 -> 0 | K14: =G14+J14 -> 0 | M14: =M13+K14-L14 -> 0
A15: 12 | B15: 45912 | G15: =E15*F15 -> 0 | J15: =H15*I15 -> 0 | K15: =G15+J15 -> 0 | M15: =M14+K15-L15 -> 0
... A21: 18 | B21: 45918 | G21: =E21*F21 -> 0 | J21: =H21*I21 -> 0 | K21: =G21+J21 -> 0 | M21: =M20+K21-L21 -> 0
A22: 19 | B22: 45919 | H22: 0 | I22: 0 | J22: =H22*I22 -> 0 | K22: =G22+J22 -> 0 | M22: =M21+K22-L22 -> 0
A23: 20 | B23: 45920 | H23: 0 | I23: 0 | J23: =H23*I23 -> 0 | K23: =G23+J23 -> 0 | M23: =M22+K23-L23 -> 0
A24: 21 | B24: 45921 | J24: =H24*I24 -> 0 | K24: =G24+J24 -> 0 | M24: =M23+K24-L24 -> 0
A25: 22 | B25: 45922 | J25: =H25*I25 -> 0 | K25: =G25+J25 -> 0 | M25: =M24+K25-L25 -> 0
A26: 23 | B26: 45923 | J26: =H26*I26 -> 0 | K26: =G26+J26 -> 0 | M26: =M25+K26-L26 -> 0
A27: 24 | B27: 45924 | J27: =H27*I27 -> 0 | K27: =G27+J27 -> 0 | M27: =M26+K27-L27 -> 0
A28: 25 | B28: 45925 | J28: =H28*I28 -> 0 | K28: =G28+J28 -> 0 | M28: =M27+K28-L28 -> 0
A29: 26 | B29: 45926 | J29: =H29*I29 -> 0 | K29: =G29+J29 -> 0 | M29: =M28+K29-L29 -> 0
A30: 27 | B30: 45927 | J30: =H30*I30 -> 0 | K30: =G30+J30 -> 0 | M30: =M29+K30-L30 -> 0
A31: 28 | B31: 45928 | J31: =H31*I31 -> 0 | K31: =G31+J31 -> 0 | M31: =M30+K31-L31 -> 0
A32: 29 | B32: 45929 | E32: 44 | F32: 105.59 | G32: =E32*F32 -> 4645.96 | H32: 14 | I32: 117.98 | J32: =H32*I32 -> 1651.72 | K32: =G32+J32 -> 6297.68 | M32: =M31+K32-L32 -> 6297.68
A33: 30 | B33: 45930 | E33: 75 | F33: 105.59 | G33: =E33*F33 -> 7919.25 | H33: 0 | I33: 0 | J33: =H33*I33 -> 0 | K33: =G33+J33 -> 7919.25 | M33: =M32+K33-L33 -> 14216.93
A34: 31 | F34: 0 | G34: =E34*F34 -> 0 | J34: =H34*I34 -> 0 | K34: =G34+J34 -> 0
E35: =SUM(E4:E34) -> 119 | G35: =SUM(G4:G34) -> 12565.21 | H35: =SUM(H4:H34) -> 14 | J35: =SUM(J4:J34) -> 1651.72 | K35: =SUM(K4:K34) -> 14216.93 | L35: =SUM(L4:L31) -> 0

Sheet Madana palli
A2: S.No | B2: Date | C2: GRN No | D2: Ind no/Bill No | E2: Diesel (Lts) | F2: Price | G2: Amount | H2: Petrol (Lts) | I2: Price | J2: Amount | K2: Total amount | L2: Amount paid | M2: As on Date | N2: Remarks
A3: Opening Balance | M3: 0
A4: 1 | B4: 46266 | G4: =E4*F4 -> 0 | J4: =H4*I4 -> 0 | K4: =G4+J4 -> 0 | L4: =+K4 -> 0 | M4: 0
B5: 46267 | J5: =H5*I5 -> 0 | K5: =G5+J5 -> 0 | L5: =+K5 -> 0
A6: 2 | B6: 46268 | G6: =E6*F6 -> 0 | J6: =H6*I6 -> 0 | K6: =G6+J6 -> 0 | L6: =+K6 -> 0 | M6: 0
A7: 3 | B7: 46269 | G7: =E7*F7 -> 0 | J7: =H7*I7 -> 0 | K7: =G7+J7 -> 0 | L7: =+K7 -> 0 | M7: 0
A8: 4 | B8: 46270 | G8: =E8*F8 -> 0 | J8: =H8*I8 -> 0 | K8: =G8+J8 -> 0 | L8: =+K8 -> 0 | M8: 0
A9: 5 | B9: 46271 | G9: =E9*F9 -> 0 | J9: =H9*I9 -> 0 | K9: =G9+J9 -> 0 | L9: =+K9 -> 0 | M9: 0
A10: 6 | B10: 46272 | G10: =E10*F10 -> 0 | J10: =H10*I10 -> 0 | K10: =G10+J10 -> 0 | L10: =+K10 -> 0 | M10: 0
A11: 7 | B11: 46273 | G11: =E11*F11 -> 0 | J11: =H11*I11 -> 0 | K11: =G11+J11 -> 0 | L11: =+K11 -> 0 | M11: 0
A12: 8 | B12: 46274 | G12: =E12*F12 -> 0 | J12: =H12*I12 -> 0 | K12: =G12+J12 -> 0 | L12: =+K12 -> 0 | M12: 0
A13: 9 | B13: 46275 | G13: =E13*F13 -> 0 | J13: =H13*I13 -> 0 | K13: =G13+J13 -> 0 | L13: =+K13 -> 0 | M13: 0
A14: 10 | B14: 46276 | G14: =E14*F14 -> 0 | J14: =H14*I14 -> 0 | K14: =G14+J14 -> 0 | L14: =+K14 -> 0 | M14: 0
A15: 11 | B15: 46277 | G15: =E15*F15 -> 0 | J15: =H15*I15 -> 0 | K15: =G15+J15 -> 0 | L15: =+K15 -> 0 | M15: 0
A16: 12 | B16: 46278 | G16: =E16*F16 -> 0 | J16: =H16*I16 -> 0 | K16: =G16+J16 -> 0 | L16: =+K16 -> 0 | M16: 0
A17: 13 | B17: 46279 | G17: =E17*F17 -> 0 | J17: =H17*I17 -> 0 | K17: =G17+J17 -> 0 | L17: =+K17 -> 0 | M17: 0
... A29: 25 | B29: 46291 | G29: =E29*F29 -> 0 | J29: =H29*I29 -> 0 | K29: =G29+J29 -> 0 | L29: =+K29 -> 0 | M29: 0
B30: 46292 | J30: =H30*I30 -> 0 | K30: =G30+J30 -> 0 | L30: =+K30 -> 0
A31: 26 | B31: 46293 | G31: =E31*F31 -> 0 | J31: =H31*I31 -> 0 | K31: =G31+J31 -> 0 | L31: =+K31 -> 0 | M31: 0
A32: 27 | B32: 46294 | G32: =E32*F32 -> 0 | J32: =H32*I32 -> 0 | K32: =G32+J32 -> 0 | L32: =+K32 -> 0 | M32: 0
A33: 28 | B33: 46295 | G33: =E33*F33 -> 0 | J33: =H33*I33 -> 0 | K33: =G33+J33 -> 0 | L33: =+K33 -> 0 | M33: 0
A34: 29 | G34: =E34*F34 -> 0 | J34: =H34*I34 -> 0 | K34: =G34+J34 -> 0 | L34: =+K34 -> 0 | M34: 0
A35: 30 | G35: =E35*F35 -> 0 | J35: =H35*I35 -> 0 | K35: =G35+J35 -> 0 | L35: =+K35 -> 0 | M35: 0
A36: 31 | G36: =E36*F36 -> 0 | J36: =H36*I36 -> 0 | K36: =G36+J36 -> 0 | L36: =+K36 -> 0 | M36: 0
E37: =SUM(E4:E36) -> 0 | G37: =SUM(G4:G36) -> 0 | H37: =SUM(H4:H36) -> 0 | J37: =SUM(J4:J36) -> 0 | K37: =SUM(K4:K36) -> 0 | L37: =SUM(L4:L36) -> 0

Sheet Kadur
A1: Vishal Service Station
A2: S.No | B2: Date | C2: GRN No | D2: Ind No/Bill No | E2: Diesel (Lts) | F2: Price | G2: Amount | H2: Petrol (Lts) | I2: Price | J2: Amount | K2: Total amount | L2: Amount paid | M2: As on Date | N2: Remarks
A3: Opening Balance
A4: 1 | B4: 45901 | E4: 1600 | F4: 99.96 | G4: =E4*F4 -> 159936 | H4: 140 | I4: 112.3 | J4: =H4*I4 -> 15722 | K4: =G4+J4 -> 175658 | M4: =M3+K4-L4 -> 175658
A5: 2 | B5: 45902 | G5: =E5*F5 -> 0 | J5: =H5*I5 -> 0 | K5: =G5+J5 -> 0 | M5: =M4+K5-L5 -> 175658
A6: 3 | B6: 45903 | G6: =E6*F6 -> 0 | J6: =H6*I6 -> 0 | K6: =G6+J6 -> 0 | M6: =M5+K6-L6 -> 175658
A7: 4 | B7: 45904 | G7: =E7*F7 -> 0 | J7: =H7*I7 -> 0 | K7: =G7+J7 -> 0 | M7: =M6+K7-L7 -> 175658
A8: 5 | B8: 45905 | G8: =E8*F8 -> 0 | J8: =H8*I8 -> 0 | K8: =G8+J8 -> 0 | M8: =M7+K8-L8 -> 175658
A9: 6 | B9: 45906 | G9: =E9*F9 -> 0 | J9: =H9*I9 -> 0 | K9: =G9+J9 -> 0 | M9: =M8+K9-L9 -> 175658
A10: 7 | B10: 45907 | G10: =E10*F10 -> 0 | J10: =H10*I10 -> 0 | K10: =G10+J10 -> 0 | M10: =M9+K10-L10 -> 175658
A11: 8 | B11: 45908 | G11: =E11*F11 -> 0 | J11: =H11*I11 -> 0 | K11: =G11+J11 -> 0 | M11: =M10+K11-L11 -> 175658
A12: 9 | B12: 45909 | G12: =E12*F12 -> 0 | J12: =H12*I12 -> 0 | K12: =G12+J12 -> 0 | M12: =M11+K12-L12 -> 175658
A13: 10 | B13: 45910 | G13: =E13*F13 -> 0 | J13: =H13*I13 -> 0 | K13: =G13+J13 -> 0 | M13: =M12+K13-L13 -> 175658
A14: 11 | B14: 45911 | G14: =E14*F14 -> 0 | J14: =H14*I14 -> 0 | K14: =G14+J14 -> 0 | M14: =M13+K14-L14 -> 175658
A15: 12 | B15: 45912 | G15: =E15*F15 -> 0 | J15: =H15*I15 -> 0 | K15: =G15+J15 -> 0 | M15: =M14+K15-L15 -> 175658
A16: 13 | B16: 45913 | G16: =E16*F16 -> 0 | J16: =H16*I16 -> 0 | K16: =G16+J16 -> 0 | M16: =M15+K16-L16 -> 175658
... A21: 18 | B21: 45918 | G21: =E21*F21 -> 0 | J21: =H21*I21 -> 0 | K21: =G21+J21 -> 0 | M21: =M20+K21-L21 -> 175658
A22: 19 | B22: 45919 | H22: 0 | I22: 0 | J22: =H22*I22 -> 0 | K22: =G22+J22 -> 0 | M22: =M21+K22-L22 -> 175658
A23: 20 | B23: 45920 | H23: 0 | I23: 0 | J23: =H23*I23 -> 0 | K23: =G23+J23 -> 0 | M23: =M22+K23-L23 -> 175658
A24: 21 | B24: 45921 | J24: =H24*I24 -> 0 | K24: =G24+J24 -> 0 | M24: =M23+K24-L24 -> 175658
A25: 22 | B25: 45922 | J25: =H25*I25 -> 0 | K25: =G25+J25 -> 0 | M25: =M24+K25-L25 -> 175658
A26: 23 | B26: 45923 | J26: =H26*I26 -> 0 | K26: =G26+J26 -> 0 | M26: =M25+K26-L26 -> 175658
A27: 24 | B27: 45924 | J27: =H27*I27 -> 0 | K27: =G27+J27 -> 0 | M27: =M26+K27-L27 -> 175658
A28: 25 | B28: 45925 | J28: =H28*I28 -> 0 | K28: =G28+J28 -> 0 | M28: =M27+K28-L28 -> 175658
A29: 26 | B29: 45926 | J29: =H29*I29 -> 0 | K29: =G29+J29 -> 0 | M29: =M28+K29-L29 -> 175658
A30: 27 | B30: 45927 | J30: =H30*I30 -> 0 | K30: =G30+J30 -> 0 | M30: =M29+K30-L30 -> 175658
A31: 28 | B31: 45928 | J31: =H31*I31 -> 0 | K31: =G31+J31 -> 0 | M31: =M30+K31-L31 -> 175658
A32: 29 | B32: 45929 | G32: =E32*F32 -> 0 | H32: 0 | I32: 0 | J32: =H32*I32 -> 0 | K32: =G32+J32 -> 0 | M32: =M31+K32-L32 -> 175658
A33: 30 | B33: 45930 | F33: 0 | G33: =E33*F33 -> 0 | H33: 0 | I33: 0 | J33: =H33*I33 -> 0 | K33: =G33+J33 -> 0 | M33: =M32+K33-L33 -> 175658
A34: 31 | F34: 0 | G34: =E34*F34 -> 0 | J34: =H34*I34 -> 0 | K34: =G34+J34 -> 0
E35: =SUM(E4:E34) -> 1600 | G35: =SUM(G4:G34) -> 159936 | H35: =SUM(H4:H34) -> 140 | J35: =SUM(J4:J34) -> 15722 | K35: =SUM(K4:K34) -> 175658 | L35: =SUM(L4:L31) -> 0

Sheet YG Gudda
A1: Pankaja HP Fuel Center
A2: S.No | B2: Date | C2: GRN No | D2: Ind No/Bill No | E2: Diesel (Lts) | F2: Price | G2: Amount | H2: Petrol (Lts) | I2: Price | J2: Amount | K2: Total amount | L2: Amount paid | M2: As on Date | N2: Remarks
A3: Opening Balance | K3: 127791.16 | M3: 127791.16
A4: 1 | B4: 46266 | G4: =E4*F4 -> 0 | J4: =H4*I4 -> 0 | K4: =G4+J4 -> 0 | M4: =M3+K4-L4 -> 127791.16
B5: 46267 | G5: =E5*F5 -> 0 | K5: =G5+J5 -> 0 | M5: =M4+K5-L5 -> 127791.16
A6: 2 | B6: 46268 | G6: =E6*F6 -> 0 | J6: =H6*I6 -> 0 | K6: =G6+J6 -> 0 | M6: =M5+K6-L6 -> 127791.16
A7: 3 | B7: 46269 | E7: 1200 | F7: 99.14 | G7: =E7*F7 -> 118968 | H7: 70 | I7: 111.24 | J7: =H7*I7 -> 7786.8 | K7: =G7+J7 -> 126754.8 | M7: =M6+K7-L7 -> 254545.96
A8: 4 | B8: 46270 | G8: =E8*F8 -> 0 | J8: =H8*I8 -> 0 | K8: =G8+J8 -> 0 | M8: =M7+K8-L8 -> 254545.96
A9: 5 | B9: 46271 | G9: =E9*F9 -> 0 | J9: =H9*I9 -> 0 | K9: =G9+J9 -> 0 | M9: =M8+K9-L9 -> 254545.96
A10: 6 | B10: 46272 | G10: =E10*F10 -> 0 | J10: =H10*I10 -> 0 | K10: =G10+J10 -> 0 | M10: =M9+K10-L10 -> 254545.96
A11: 7 | B11: 46273 | E11: 1000 | F11: 99.14 | G11: =E11*F11 -> 99140 | H11: 35 | I11: 111.24 | J11: =H11*I11 -> 3893.4 | K11: =G11+J11 -> 103033.4 | M11: =M10+K11-L11 -> 357579.36
A12: 8 | B12: 46274 | G12: =E12*F12 -> 0 | J12: =H12*I12 -> 0 | K12: =G12+J12 -> 0 | M12: =M11+K12-L12 -> 357579.36
A13: 9 | B13: 46275 | E13: 1000 | F13: 99.14 | G13: =E13*F13 -> 99140 | H13: 35 | I13: 111.24 | J13: =H13*I13 -> 3893.4 | K13: =G13+J13 -> 103033.4 | M13: =M12+K13-L13 -> 460612.76
A14: 10 | B14: 46276 | G14: =E14*F14 -> 0 | J14: =H14*I14 -> 0 | K14: =G14+J14 -> 0 | M14: =M13+K14-L14 -> 460612.76
A15: 11 | B15: 46277 | G15: =E15*F15 -> 0 | J15: =H15*I15 -> 0 | K15: =G15+J15 -> 0 | M15: =M14+K15-L15 -> 460612.76
A16: 12 | B16: 46278 | E16: 600 | F16: 99.14 | G16: =E16*F16 -> 59484 | H16: 35 | I16: 111.24 | J16: =H16*I16 -> 3893.4 | K16: =G16+J16 -> 63377.4 | M16: =M15+K16-L16 -> 523990.16
A17: 13 | B17: 46279 | G17: =E17*F17 -> 0 | J17: =H17*I17 -> 0 | K17: =G17+J17 -> 0 | M17: =M16+K17-L17 -> 523990.16
A18: 14 | B18: 46280 | G18: =E18*F18 -> 0 | J18: =H18*I18 -> 0 | K18: =G18+J18 -> 0 | M18: =M17+K18-L18 -> 523990.16
A19: 15 | B19: 46281 | E19: 1000 | F19: 99.14 | G19: =E19*F19 -> 99140 | H19: 70 | I19: 111.24 | J19: =H19*I19 -> 7786.8 | K19: =G19+J19 -> 106926.8 | L19: 350000 | M19: =M18+K19-L19 -> 280916.96
A20: 16 | B20: 46282 | G20: =E20*F20 -> 0 | J20: =H20*I20 -> 0 | K20: =G20+J20 -> 0 | M20: =M19+K20-L20 -> 280916.96
A21: 17 | B21: 46283 | G21: =E21*F21 -> 0 | J21: =H21*I21 -> 0 | K21: =G21+J21 -> 0 | M21: =M20+K21-L21 -> 280916.96
A22: 18 | B22: 46284 | E22: 1000 | F22: 99.14 | G22: =E22*F22 -> 99140 | H22: 35 | I22: 111.24 | J22: =H22*I22 -> 3893.4 | K22: =G22+J22 -> 103033.4 | M22: =M21+K22-L22 -> 383950.36
A23: 19 | B23: 46285 | G23: =E23*F23 -> 0 | J23: =H23*I23 -> 0 | K23: =G23+J23 -> 0 | M23: =M22+K23-L23 -> 383950.36
A24: 20 | B24: 46286 | G24: =E24*F24 -> 0 | J24: =H24*I24 -> 0 | K24: =G24+J24 -> 0 | M24: =M23+K24-L24 -> 383950.36
A25: 21 | B25: 46287 | E25: 1200 | F25: 99.14 | G25: =E25*F25 -> 118968 | H25: 35 | I25: 111.24 | J25: =H25*I25 -> 3893.4 | K25: =G25+J25 -> 122861.4 | M25: =M24+K25-L25 -> 506811.76
A26: 22 | B26: 46288 | G26: =E26*F26 -> 0 | J26: =H26*I26 -> 0 | K26: =G26+J26 -> 0 | L26: 300000 | M26: =M25+K26-L26 -> 206811.76
A27: 23 | B27: 46289 | G27: =E27*F27 -> 0 | J27: =H27*I27 -> 0 | K27: =G27+J27 -> 0 | M27: =M26+K27-L27 -> 206811.76
A28: 24 | B28: 46290 | G28: =E28*F28 -> 0 | I28: 111.24 | J28: =H28*I28 -> 0 | K28: =G28+J28 -> 0 | M28: =M27+K28-L28 -> 206811.76
A29: 25 | B29: 46291 | G29: =E29*F29 -> 0 | J29: =H29*I29 -> 0 | K29: =G29+J29 -> 0 | M29: =M28+K29-L29 -> 206811.76
A30: 26 | B30: 46292 | G30: =E30*F30 -> 0 | J30: =H30*I30 -> 0 | K30: =G30+J30 -> 0 | M30: =M29+K30-L30 -> 206811.76
A31: 27 | B31: 46293 | G31: =E31*F31 -> 0 | J31: =H31*I31 -> 0 | K31: =G31+J31 -> 0 | M31: =M30+K31-L31 -> 206811.76
A32: 28 | B32: 46294 | E32: 1000 | F32: 99.14 | G32: =E32*F32 -> 99140 | J32: =H32*I32 -> 0 | K32: =G32+J32 -> 99140 | M32: =M31+K32-L32 -> 305951.76
A33: 29 | B33: 46295 | G33: =E33*F33 -> 0 | J33: =H33*I33 -> 0 | K33: =G33+J33 -> 0 | M33: =M32+K33-L33 -> 305951.76
A34: 30 | G34: =E34*F34 -> 0 | J34: =H34*I34 -> 0 | K34: =G34+J34 -> 0 | M34: =M33+K34-L34 -> 305951.76
A35: 31 | G35: =E35*F35 -> 0 | J35: =H35*I35 -> 0 | K35: =G35+J35 -> 0 | M35: =M34+K35-L35 -> 305951.76
A36: 32 | G36: =E36*F36 -> 0 | J36: =H36*I36 -> 0 | K36: =G36+J36 -> 0 | M36: =M35+K36-L36 -> 305951.76
A37: 33 | G37: =E37*F37 -> 0 | J37: =H37*I37 -> 0 | K37: =G37+J37 -> 0 | M37: =M36+K37-L37 -> 305951.76
A38: 34 | G38: =E38*F38 -> 0 | J38: =H38*I38 -> 0 | K38: =G38+J38 -> 0 | M38: =M37+K38-L38 -> 305951.76
E39: =SUM(E4:E38) -> 8000 | G39: =SUM(G4:G38) -> 793120 | H39: =SUM(H4:H38) -> 315 | J39: =SUM(J4:J38) -> 35040.6 | K39: =SUM(K4:K38) -> 828160.6 | L39: =SUM(L4:L38) -> 650000

Sheet  YG Gudda-2
A1: One Stop
A2: S.No | B2: Date | C2: GRN No | D2: Ind No/Bill No | E2: Diesel (Lts) | F2: Price | G2: Amount | H2: Petrol (Lts) | I2: Price | J2: Amount | K2: Total amount | L2: Amount paid | M2: As on Date | N2: Remarks
A3: Opening Balance | K3: 156607.72 | M3: 156607.72
A4: 1 | B4: 46266 | G4: =E4*F4 -> 0 | J4: =H4*I4 -> 0 | K4: =I4*J4 -> 0 | M4: =M3+K4-L4 -> 156607.72
B5: 46267 | G5: =E5*F5 -> 0 | J5: =H5*I5 -> 0 | K5: =I5*J5 -> 0 | M5: =M4+K5-L5 -> 156607.72
A6: 2 | B6: 46268 | G6: =E6*F6 -> 0 | J6: =H6*I6 -> 0 | K6: =I6*J6 -> 0 | M6: =M4+K6-L6 -> 156607.72
A7: 3 | B7: 46269 | G7: =E7*F7 -> 0 | J7: =H7*I7 -> 0 | K7: =I7*J7 -> 0 | M7: =M6+K7-L7 -> 156607.72
A8: 4 | B8: 46270 | G8: =E8*F8 -> 0 | J8: =H8*I8 -> 0 | K8: =I8*J8 -> 0 | M8: =M7+K8-L8 -> 156607.72
A9: 5 | B9: 46271 | G9: =E9*F9 -> 0 | J9: =H9*I9 -> 0 | K9: =I9*J9 -> 0 | M9: =M8+K9-L9 -> 156607.72
A10: 6 | B10: 46272 | G10: =E10*F10 -> 0 | J10: =H10*I10 -> 0 | K10: =I10*J10 -> 0 | M10: =M9+K10-L10 -> 156607.72
A11: 7 | B11: 46273 | G11: =E11*F11 -> 0 | J11: =H11*I11 -> 0 | K11: =I11*J11 -> 0 | M11: =M10+K11-L11 -> 156607.72
A12: 8 | B12: 46274 | G12: =E12*F12 -> 0 | J12: =H12*I12 -> 0 | K12: =I12*J12 -> 0 | M12: =M11+K12-L12 -> 156607.72
A13: 9 | B13: 46275 | G13: =E13*F13 -> 0 | J13: =H13*I13 -> 0 | K13: =I13*J13 -> 0 | M13: =M12+K13-L13 -> 156607.72
A14: 10 | B14: 46276 | G14: =E14*F14 -> 0 | J14: =H14*I14 -> 0 | K14: =I14*J14 -> 0 | M14: =M13+K14-L14 -> 156607.72
A15: 11 | B15: 46277 | G15: =E15*F15 -> 0 | J15: =H15*I15 -> 0 | K15: =I15*J15 -> 0 | M15: =M14+K15-L15 -> 156607.72
A16: 12 | B16: 46278 | G16: =E16*F16 -> 0 | J16: =H16*I16 -> 0 | K16: =I16*J16 -> 0 | M16: =M15+K16-L16 -> 156607.72
A17: 13 | B17: 46279 | G17: =E17*F17 -> 0 | J17: =H17*I17 -> 0 | K17: =I17*J17 -> 0 | M17: =M16+K17-L17 -> 156607.72
A18: 14 | B18: 46280 | G18: =E18*F18 -> 0 | J18: =H18*I18 -> 0 | K18: =I18*J18 -> 0 | M18: =M17+K18-L18 -> 156607.72
A19: 15 | B19: 46281 | G19: =E19*F19 -> 0 | J19: =H19*I19 -> 0 | K19: =I19*J19 -> 0 | L19: 150000 | M19: =M18+K19-L19 -> 6607.7192
A20: 16 | B20: 46282 | G20: =E20*F20 -> 0 | J20: =H20*I20 -> 0 | K20: =I20*J20 -> 0 | M20: =M19+K20-L20 -> 6607.7192
A21: 17 | B21: 46283 | G21: =E21*F21 -> 0 | J21: =H21*I21 -> 0 | K21: =I21*J21 -> 0 | M21: =M20+K21-L21 -> 6607.7192
A22: 18 | B22: 46284 | G22: =E22*F22 -> 0 | J22: =H22*I22 -> 0 | K22: =I22*J22 -> 0 | M22: =M21+K22-L22 -> 6607.7192
A23: 19 | B23: 46285 | G23: =E23*F23 -> 0 | J23: =H23*I23 -> 0 | K23: =I23*J23 -> 0 | M23: =M22+K23-L23 -> 6607.7192
A24: 20 | B24: 46286 | G24: =E24*F24 -> 0 | J24: =H24*I24 -> 0 | K24: =I24*J24 -> 0 | M24: =M23+K24-L24 -> 6607.7192
A25: 21 | B25: 46287 | G25: =E25*F25 -> 0 | J25: =H25*I25 -> 0 | K25: =I25*J25 -> 0 | M25: =M24+K25-L25 -> 6607.7192
A26: 22 | B26: 46288 | G26: =E26*F26 -> 0 | J26: =H26*I26 -> 0 | K26: =I26*J26 -> 0 | M26: =M25+K26-L26 -> 6607.7192
A27: 23 | B27: 46289 | G27: =E27*F27 -> 0 | J27: =H27*I27 -> 0 | K27: =I27*J27 -> 0 | M27: =M26+K27-L27 -> 6607.7192
A28: 24 | B28: 46290 | E28: 800 | F28: 99.02 | G28: =E28*F28 -> 79216 | H28: 70 | I28: 111.12 | J28: =H28*I28 -> 7778.4 | K28: =G28+J28 -> 86994.4 | M28: =M27+K28-L28 -> 93602.119
A29: 25 | B29: 46291 | E29: 800 | F29: 99.02 | G29: =E29*F29 -> 79216 | J29: =H29*I29 -> 0 | K29: =G29+J29 -> 79216 | M29: =M28+K29-L29 -> 172818.12
A30: 26 | B30: 46292 | G30: =E30*F30 -> 0 | J30: =H30*I30 -> 0 | K30: =G30+J30 -> 0 | M30: =M29+K30-L30 -> 172818.12
A31: 27 | B31: 46293 | E31: 800 | F31: 99.02 | G31: =E31*F31 -> 79216 | H31: 35 | I31: 111.12 | J31: =H31*I31 -> 3889.2 | K31: =G31+J31 -> 83105.2 | M31: =M30+K31-L31 -> 255923.32
A32: 28 | B32: 46294 | G32: =E32*F32 -> 0 | J32: =H32*I32 -> 0 | K32: =G32+J32 -> 0 | M32: =M31+K32-L32 -> 255923.32
A33: 29 | B33: 46295 | G33: =E33*F33 -> 0 | J33: =H33*I33 -> 0 | K33: =I33*J33 -> 0 | M33: =M32+K33-L33 -> 255923.32
A34: 30 | G34: =E34*F34 -> 0 | J34: =H34*I34 -> 0 | K34: =G34+J34 -> 0 | M34: =M33+K34-L34 -> 255923.32
A35: 31 | G35: =E35*F35 -> 0 | J35: =H35*I35 -> 0 | K35: =I35*J35 -> 0 | M35: =M34+K35-L35 -> 255923.32
A36: 32 | G36: =E36*F36 -> 0 | J36: =H36*I36 -> 0 | K36: =I36*J36 -> 0 | M36: =M35+K36-L36 -> 255923.32
A37: 33 | G37: =E37*F37 -> 0 | J37: =H37*I37 -> 0 | K37: =I37*J37 -> 0 | M37: =M36+K37-L37 -> 255923.32
A38: 34 | G38: =E38*F38 -> 0 | J38: =H38*I38 -> 0 | K38: =I38*J38 -> 0 | M38: =M37+K38-L38 -> 255923.32
E39: =SUM(E4:E38) -> 2400 | G39: =SUM(G4:G38) -> 237648 | H39: =SUM(H4:H38) -> 105 | J39: =SUM(J4:J38) -> 11667.6 | K39: =SUM(K4:K38) -> 249315.6 | L39: =SUM(L4:L38) -> 150000

Sheet Hosadurga -2
A1: Shree Veeraprathap Fuel
A2: S.No | B2: Date | C2: GRN No | D2: Ind No/Bill No | E2: Diesel (Lts) | F2: Price | G2: Amount | H2: Petrol (Lts) | I2: Price | J2: Amount | K2: Total amount | L2: Amount paid | M2: As on Date | N2: Remarks
A3: Opening Balance | K3: 118809.59 | L3: 118809.59 | M3: 118809.59
A4: 1 | B4: 46266 | G4: =E4*F4 -> 0 | J4: =H4*I4 -> 0 | K4: =G4+J4 -> 0 | M4: =M3+K4-L4 -> 118809.59
A5: 2 | B5: 46267 | G5: =E5*F5 -> 0 | J5: =H5*I5 -> 0 | K5: =G5+J5 -> 0 | M5: =M4+K5-L5 -> 118809.59
A6: 3 | B6: 46268 | G6: =E6*F6 -> 0 | J6: =H6*I6 -> 0 | K6: =G6+J6 -> 0 | M6: =M5+K6-L6 -> 118809.59
A7: 4 | B7: 46269 | G7: =E7*F7 -> 0 | J7: =H7*I7 -> 0 | K7: =G7+J7 -> 0 | M7: =M6+K7-L7 -> 118809.59
A8: 5 | B8: 46270 | G8: =E8*F8 -> 0 | J8: =H8*I8 -> 0 | K8: =G8+J8 -> 0 | M8: =M7+K8-L8 -> 118809.59
A9: 6 | B9: 46271 | G9: =E9*F9 -> 0 | J9: =H9*I9 -> 0 | K9: =G9+J9 -> 0 | M9: =M8+K9-L9 -> 118809.59
A10: 7 | B10: 46272 | G10: =E10*F10 -> 0 | J10: =H10*I10 -> 0 | K10: =G10+J10 -> 0 | M10: =M9+K10-L10 -> 118809.59
A11: 8 | B11: 46273 | G11: =E11*F11 -> 0 | J11: =H11*I11 -> 0 | K11: =G11+J11 -> 0 | M11: =M10+K11-L11 -> 118809.59
A12: 9 | B12: 46274 | G12: =E12*F12 -> 0 | J12: =H12*I12 -> 0 | K12: =G12+J12 -> 0 | M12: =M11+K12-L12 -> 118809.59
A13: 10 | B13: 46275 | G13: =E13*F13 -> 0 | J13: =H13*I13 -> 0 | K13: =G13+J13 -> 0 | M13: =M12+K13-L13 -> 118809.59
A14: 11 | B14: 46276 | G14: =E14*F14 -> 0 | J14: =H14*I14 -> 0 | K14: =G14+J14 -> 0 | M14: =M13+K14-L14 -> 118809.59
A15: 12 | B15: 46277 | G15: =E15*F15 -> 0 | J15: =H15*I15 -> 0 | K15: =G15+J15 -> 0 | M15: =M14+K15-L15 -> 118809.59
... A18: 15 | B18: 46280 | G18: =E18*F18 -> 0 | J18: =H18*I18 -> 0 | K18: =G18+J18 -> 0 | M18: =M17+K18-L18 -> 118809.59
A19: 16 | B19: 46281 | G19: =E19*F19 -> 0 | J19: =H19*I19 -> 0 | K19: =G19+J19 -> 0 | L19: 100000 | M19: =M18+K19-L19 -> 18809.594
A20: 17 | B20: 46282 | E20: 1000 | F20: 99.38 | G20: =E20*F20 -> 99380 | H20: 70 | I20: 111.72 | J20: =H20*I20 -> 7820.4 | K20: =G20+J20 -> 107200.4 | M20: =M19+K20-L20 -> 126009.99
A21: 18 | B21: 46283 | G21: =E21*F21 -> 0 | J21: =H21*I21 -> 0 | K21: =G21+J21 -> 0 | M21: =M20+K21-L21 -> 126009.99
A22: 19 | B22: 46284 | G22: =E22*F22 -> 0 | J22: =H22*I22 -> 0 | K22: =G22+J22 -> 0 | M22: =M21+K22-L22 -> 126009.99
A23: 20 | B23: 46285 | G23: =E23*F23 -> 0 | J23: =H23*I23 -> 0 | K23: =G23+J23 -> 0 | M23: =M22+K23-L23 -> 126009.99
A24: 21 | B24: 46286 | G24: =E24*F24 -> 0 | J24: =H24*I24 -> 0 | K24: =G24+J24 -> 0 | M24: =M23+K24-L24 -> 126009.99
A25: 22 | B25: 46287 | G25: =E25*F25 -> 0 | J25: =H25*I25 -> 0 | K25: =G25+J25 -> 0 | M25: =M24+K25-L25 -> 126009.99
A26: 23 | B26: 46288 | G26: =E26*F26 -> 0 | J26: =H26*I26 -> 0 | K26: =G26+J26 -> 0 | M26: =M25+K26-L26 -> 126009.99
A27: 24 | B27: 46289 | G27: =E27*F27 -> 0 | J27: =H27*I27 -> 0 | K27: =G27+J27 -> 0 | M27: =M26+K27-L27 -> 126009.99
A28: 25 | B28: 46290 | G28: =E28*F28 -> 0 | J28: =H28*I28 -> 0 | K28: =G28+J28 -> 0 | M28: =M27+K28-L28 -> 126009.99
A29: 26 | B29: 46291 | G29: =E29*F29 -> 0 | J29: =H29*I29 -> 0 | K29: =G29+J29 -> 0 | M29: =M28+K29-L29 -> 126009.99
A30: 27 | B30: 46292 | G30: =E30*F30 -> 0 | J30: =H30*I30 -> 0 | K30: =G30+J30 -> 0 | M30: =M29+K30-L30 -> 126009.99
A31: 28 | B31: 46293 | G31: =E31*F31 -> 0 | J31: =H31*I31 -> 0 | K31: =G31+J31 -> 0 | M31: =M30+K31-L31 -> 126009.99
A32: 29 | B32: 46294 | G32: =E32*F32 -> 0 | J32: =H32*I32 -> 0 | K32: =G32+J32 -> 0 | M32: =M31+K32-L32 -> 126009.99
A33: 30 | B33: 46295 | G33: =E33*F33 -> 0 | J33: =H33*I33 -> 0 | K33: =G33+J33 -> 0 | M33: =M32+K33-L33 -> 126009.99
A34: 31 | K34: =G34+J34 -> 0
E35: =SUM(E4:E34) -> 1000 | G35: =SUM(G4:G34) -> 99380 | H35: =SUM(H4:H34) -> 70 | J35: =SUM(J4:J34) -> 7820.4 | K35: =SUM(K4:K34) -> 107200.4 | L35: =SUM(L4:L34) -> 100000

Sheet Hiriyur(VJNL)
A1: Sri Balaji Agencies
A2: S.No | B2: Date | C2: GRN No | D2: Ind No/Bill No | E2: Diesel (Lts) | F2: Price | G2: Amount | H2: Petrol (Lts) | I2: Price | J2: Amount | K2: Total amount | L2: Amount paid | M2: As on Date | N2: Remarks
A3: Opening Balance | K3: 219945.7 | M3: 219945.7
A4: 1 | B4: 46266 | G4: =E4*F4 -> 0 | J4: =H4*I4 -> 0 | K4: =G4+J4 -> 0 | L4: 219000 | M4: =M3+K4-L4 -> 945.7
A5: 2 | B5: 46267 | G5: =E5*F5 -> 0 | J5: =H5*I5 -> 0 | K5: =G5+J5 -> 0 | M5: =M4+K5-L5 -> 945.7
A6: 3 | B6: 46268 | E6: 2500 | F6: 100.09 | G6: =E6*F6 -> 250225 | H6: 70 | I6: 112.12 | J6: =H6*I6 -> 7848.4 | K6: =G6+J6 -> 258073.4 | M6: =M5+K6-L6 -> 259019.1
A7: 4 | B7: 46269 | G7: =E7*F7 -> 0 | J7: =H7*I7 -> 0 | K7: =G7+J7 -> 0 | M7: =M6+K7-L7 -> 259019.1
A8: 5 | B8: 46270 | G8: =E8*F8 -> 0 | J8: =H8*I8 -> 0 | K8: =G8+J8 -> 0 | M8: =M7+K8-L8 -> 259019.1
A9: 6 | B9: 46271 | G9: =E9*F9 -> 0 | J9: =H9*I9 -> 0 | K9: =G9+J9 -> 0 | M9: =M8+K9-L9 -> 259019.1
A10: 7 | B10: 46272 | G10: =E10*F10 -> 0 | J10: =H10*I10 -> 0 | K10: =G10+J10 -> 0 | M10: =M9+K10-L10 -> 259019.1
A11: 8 | B11: 46273 | G11: =E11*F11 -> 0 | J11: =H11*I11 -> 0 | K11: =G11+J11 -> 0 | M11: =M10+K11-L11 -> 259019.1
A12: 9 | B12: 46274 | G12: =E12*F12 -> 0 | J12: =H12*I12 -> 0 | K12: =G12+J12 -> 0 | M12: =M11+K12-L12 -> 259019.1
A13: 10 | B13: 46275 | G13: =E13*F13 -> 0 | J13: =H13*I13 -> 0 | K13: =G13+J13 -> 0 | M13: =M12+K13-L13 -> 259019.1
A14: 11 | B14: 46276 | G14: =E14*F14 -> 0 | H14: 70 | I14: 112.12 | J14: =H14*I14 -> 7848.4 | K14: =G14+J14 -> 7848.4 | M14: =M13+K14-L14 -> 266867.5
A15: 12 | B15: 46277 | G15: =E15*F15 -> 0 | J15: =H15*I15 -> 0 | K15: =G15+J15 -> 0 | M15: =M14+K15-L15 -> 266867.5
A16: 13 | B16: 46278 | G16: =E16*F16 -> 0 | J16: =H16*I16 -> 0 | K16: =G16+J16 -> 0 | M16: =M15+K16-L16 -> 266867.5
A17: 14 | B17: 46279 | G17: =E17*F17 -> 0 | J17: =H17*I17 -> 0 | K17: =G17+J17 -> 0 | M17: =M16+K17-L17 -> 266867.5
A18: 15 | B18: 46280 | G18: =E18*F18 -> 0 | J18: =H18*I18 -> 0 | K18: =G18+J18 -> 0 | M18: =M17+K18-L18 -> 266867.5
A19: 16 | B19: 46281 | G19: =E19*F19 -> 0 | J19: =H19*I19 -> 0 | K19: =G19+J19 -> 0 | M19: =M18+K19-L19 -> 266867.5
A20: 17 | B20: 46282 | G20: =E20*F20 -> 0 | J20: =H20*I20 -> 0 | K20: =G20+J20 -> 0 | M20: =M19+K20-L20 -> 266867.5
A21: 18 | B21: 46283 | G21: =E21*F21 -> 0 | J21: =H21*I21 -> 0 | K21: =G21+J21 -> 0 | M21: =M20+K21-L21 -> 266867.5
A22: 19 | B22: 46284 | E22: 200 | F22: 100.09 | G22: =E22*F22 -> 20018 | H22: 50 | I22: 112.12 | J22: =H22*I22 -> 5606 | K22: =G22+J22 -> 25624 | M22: =M21+K22-L22 -> 292491.5
A23: 20 | B23: 46285 | G23: =E23*F23 -> 0 | J23: =H23*I23 -> 0 | K23: =G23+J23 -> 0 | M23: =M22+K23-L23 -> 292491.5
A24: 21 | B24: 46286 | E24: 2000 | F24: 100.09 | G24: =E24*F24 -> 200180 | H24: 35 | I24: 112.12 | J24: =H24*I24 -> 3924.2 | K24: =G24+J24 -> 204104.2 | L24: 292000 | M24: =M23+K24-L24 -> 204595.7
A25: 22 | B25: 46287 | G25: =E25*F25 -> 0 | J25: =H25*I25 -> 0 | K25: =G25+J25 -> 0 | M25: =M24+K25-L25 -> 204595.7
A26: 23 | B26: 46288 | G26: =E26*F26 -> 0 | J26: =H26*I26 -> 0 | K26: =G26+J26 -> 0 | M26: =M25+K26-L26 -> 204595.7
A27: 24 | B27: 46289 | G27: =E27*F27 -> 0 | J27: =H27*I27 -> 0 | K27: =G27+J27 -> 0 | M27: =M26+K27-L27 -> 204595.7
A28: 25 | B28: 46290 | G28: =E28*F28 -> 0 | J28: =H28*I28 -> 0 | K28: =G28+J28 -> 0 | M28: =M27+K28-L28 -> 204595.7
A29: 26 | B29: 46291 | G29: =E29*F29 -> 0 | J29: =H29*I29 -> 0 | K29: =G29+J29 -> 0 | M29: =M28+K29-L29 -> 204595.7
A30: 27 | B30: 46292 | G30: =E30*F30 -> 0 | J30: =H30*I30 -> 0 | K30: =G30+J30 -> 0 | M30: =M29+K30-L30 -> 204595.7
A31: 28 | B31: 46293 | G31: =E31*F31 -> 0 | J31: =H31*I31 -> 0 | K31: =G31+J31 -> 0 | M31: =M30+K31-L31 -> 204595.7
A32: 29 | B32: 46294 | G32: =E32*F32 -> 0 | H32: 70 | I32: 112.12 | J32: =H32*I32 -> 7848.4 | K32: =G32+J32 -> 7848.4 | M32: =M31+K32-L32 -> 212444.1
A33: 30 | B33: 46295 | G33: =E33*F33 -> 0 | J33: =H33*I33 -> 0 | K33: =G33+J33 -> 0 | M33: =M32+K33-L33 -> 212444.1
A34: 31 | G34: =E34*F34 -> 0 | J34: =H34*I34 -> 0 | K34: =G34+J34 -> 0 | M34: =M33+K34-L34 -> 212444.1
E35: =SUM(E4:E34) -> 4700 | G35: =SUM(G4:G34) -> 470423 | H35: =SUM(H4:H34) -> 295 | J35: =SUM(J4:J34) -> 33075.4 | K35: =SUM(K4:K34) -> 503498.4 | L35: =SUM(L4:L34) -> 511000

Sheet Malebenur(KUWSDB)
A1: Sree Veerabhadreshwara Service Station
A2: S.No | B2: Date | C2: GRN No | D2: Ind No/Bill No | E2: Diesel (Lts) | F2: Price | G2: Amount | H2: Petrol (Lts) | I2: Price | J2: Amount | K2: Total amount | L2: Amount paid | M2: As on Date | N2: Remarks
A3: Opening Balance | L3: 122228.41 | M3: 122228.41
A4: 1 | B4: 45901 | G4: =E4*F4 -> 0 | J4: =H4*I4 -> 0 | K4: =G4+J4 -> 0 | M4: =M3+K4-L4 -> 122228.41
A5: 2 | B5: 45902 | E5: 600 | F5: 99.99 | G5: =E5*F5 -> 59994 | H5: 35 | I5: 112.02 | J5: =H5*I5 -> 3920.7 | K5: =G5+J5 -> 63914.7 | M5: =M4+K5-L5 -> 186143.11
A6: 3 | B6: 45903 | G6: =E6*F6 -> 0 | J6: =H6*I6 -> 0 | K6: =G6+J6 -> 0 | M6: =M5+K6-L6 -> 186143.11
A7: 4 | B7: 45904 | G7: =E7*F7 -> 0 | J7: =H7*I7 -> 0 | K7: =G7+J7 -> 0 | M7: =M6+K7-L7 -> 186143.11
A8: 5 | B8: 45905 | E8: 600 | F8: 99.99 | G8: =E8*F8 -> 59994 | J8: =H8*I8 -> 0 | K8: =G8+J8 -> 59994 | M8: =M7+K8-L8 -> 246137.11
A9: 6 | B9: 45906 | G9: =E9*F9 -> 0 | J9: =H9*I9 -> 0 | K9: =G9+J9 -> 0 | M9: =M8+K9-L9 -> 246137.11
A10: 7 | B10: 45907 | E10: 600 | F10: 99.99 | G10: =E10*F10 -> 59994 | H10: 30 | I10: 112.02 | J10: =H10*I10 -> 3360.6 | K10: =G10+J10 -> 63354.6 | M10: =M9+K10-L10 -> 309491.71
A11: 8 | B11: 45908 | G11: =E11*F11 -> 0 | J11: =H11*I11 -> 0 | K11: =G11+J11 -> 0 | M11: =M10+K11-L11 -> 309491.71
A12: 9 | B12: 45909 | G12: =E12*F12 -> 0 | J12: =H12*I12 -> 0 | K12: =G12+J12 -> 0 | L12: 200000 | M12: =M11+K12-L12 -> 109491.71
A13: 10 | B13: 45910 | E13: 800 | F13: 99.99 | G13: =E13*F13 -> 79992 | J13: =H13*I13 -> 0 | K13: =G13+J13 -> 79992 | M13: =M12+K13-L13 -> 189483.71
A14: 11 | B14: 45911 | G14: =E14*F14 -> 0 | J14: =H14*I14 -> 0 | K14: =G14+J14 -> 0 | M14: =M13+K14-L14 -> 189483.71
A15: 12 | B15: 45912 | G15: =E15*F15 -> 0 | J15: =H15*I15 -> 0 | K15: =G15+J15 -> 0 | M15: =M14+K15-L15 -> 189483.71
A16: 13 | B16: 45913 | E16: 600 | F16: 99.99 | G16: =E16*F16 -> 59994 | J16: =H16*I16 -> 0 | K16: =G16+J16 -> 59994 | M16: =M15+K16-L16 -> 249477.71
A17: 14 | B17: 45914 | G17: =E17*F17 -> 0 | J17: =H17*I17 -> 0 | K17: =G17+J17 -> 0 | M17: =M16+K17-L17 -> 249477.71
A18: 15 | B18: 45915 | G18: =E18*F18 -> 0 | J18: =H18*I18 -> 0 | K18: =G18+J18 -> 0 | M18: =M17+K18-L18 -> 249477.71
A19: 16 | B19: 45916 | G19: =E19*F19 -> 0 | H19: 30 | I19: 112.02 | J19: =H19*I19 -> 3360.6 | K19: =G19+J19 -> 3360.6 | M19: =M18+K19-L19 -> 252838.31
A20: 17 | B20: 45917 | G20: =E20*F20 -> 0 | J20: =H20*I20 -> 0 | K20: =G20+J20 -> 0 | M20: =M19+K20-L20 -> 252838.31
A21: 18 | B21: 45918 | G21: =E21*F21 -> 0 | J21: =H21*I21 -> 0 | K21: =G21+J21 -> 0 | M21: =M20+K21-L21 -> 252838.31
A22: 19 | B22: 45919 | E22: 600 | F22: 99.99 | G22: =E22*F22 -> 59994 | H22: 30 | I22: 112.02 | J22: =H22*I22 -> 3360.6 | K22: =G22+J22 -> 63354.6 | M22: =M21+K22-L22 -> 316192.91
A23: 20 | B23: 45920 | G23: =E23*F23 -> 0 | J23: =H23*I23 -> 0 | K23: =G23+J23 -> 0 | M23: =M22+K23-L23 -> 316192.91
A24: 21 | B24: 45921 | G24: =E24*F24 -> 0 | J24: =H24*I24 -> 0 | K24: =G24+J24 -> 0 | M24: =M23+K24-L24 -> 316192.91
A25: 22 | B25: 45922 | G25: =E25*F25 -> 0 | J25: =H25*I25 -> 0 | K25: =G25+J25 -> 0 | M25: =M24+K25-L25 -> 316192.91
A26: 23 | B26: 45923 | E26: 800 | F26: 99.99 | G26: =E26*F26 -> 79992 | J26: =H26*I26 -> 0 | K26: =G26+J26 -> 79992 | L26: 252000 | M26: =M25+K26-L26 -> 144184.91
B27: 45923 | E27: 99.92 | F27: 100.08 | G27: =E27*F27 -> 9999.9936 | K27: =G27+J27 -> 9999.9936 | L27: 9999.9936 | M27: =M26+K27-L27 -> 144184.91
A28: 24 | B28: 45924 | G28: =E28*F28 -> 0 | J28: =H28*I28 -> 0 | K28: =G28+J28 -> 0 | M28: =M27+K28-L28 -> 144184.91
A29: 25 | B29: 45925 | G29: =E29*F29 -> 0 | J29: =H29*I29 -> 0 | K29: =G29+J29 -> 0 | M29: =M28+K29-L29 -> 144184.91
A30: 26 | B30: 45926 | E30: 800 | F30: 99.99 | G30: =E30*F30 -> 79992 | H30: 30 | I30: 112.02 | J30: =H30*I30 -> 3360.6 | K30: =G30+J30 -> 83352.6 | M30: =M29+K30-L30 -> 227537.51
A31: 27 | B31: 45927 | G31: =E31*F31 -> 0 | J31: =H31*I31 -> 0 | K31: =G31+J31 -> 0 | M31: =M30+K31-L31 -> 227537.51
A32: 28 | B32: 45928 | E32: 600 | F32: 99.99 | G32: =E32*F32 -> 59994 | H32: 30 | I32: 112.02 | J32: =H32*I32 -> 3360.6 | K32: =G32+J32 -> 63354.6 | M32: =M31+K32-L32 -> 290892.11
A33: 29 | B33: 45929 | G33: =E33*F33 -> 0 | J33: =H33*I33 -> 0 | K33: =G33+J33 -> 0 | M33: =M32+K33-L33 -> 290892.11
A34: 30 | B34: 45930 | G34: =E34*F34 -> 0 | J34: =H34*I34 -> 0 | K34: =G34+J34 -> 0 | M34: =M33+K34-L34 -> 290892.11
A35: 31 | G35: =E35*F35 -> 0 | J35: =H35*I35 -> 0 | K35: =G35+J35 -> 0 | M35: =M34+K35-L35 -> 290892.11
G36: =E36*F36 -> 0 | J36: =H36*I36 -> 0 | K36: =G36+J36 -> 0 | M36: =M35+K36-L36 -> 290892.11
G37: =E37*F37 -> 0 | J37: =H37*I37 -> 0 | K37: =G37+J37 -> 0 | M37: =M36+K37-L37 -> 290892.11
E38: =SUM(E4:E36) -> 6099.92 | G38: =SUM(G4:G36) -> 609939.99 | H38: =SUM(H4:H36) -> 185 | J38: =SUM(J4:J36) -> 20723.7 | K38: =SUM(K4:K36) -> 630663.69 | L38: =SUM(L4:L36) -> 461999.99
S44: 9052944708

Sheet Molakamuru
A1: Molakamuru
A2: S.No | B2: Date | C2: GRN No | D2: Ind No/Bill No | E2: Diesel (Lts) | F2: Price | G2: Amount | H2: Petrol (Lts) | I2: Price | J2: Amount | K2: Total amount | L2: Amount paid | M2: As on Date | N2: Remarks
A3: Opening Balance | K3: 35260.26 | L3: 35260.26 | M3: 35260.26
A4: 1 | B4: 46266 | G4: =E4*F4 -> 0 | J4: =H4*I4 -> 0 | K4: =G4+J4 -> 0 | M4: =M3+K4-L4 -> 35260.26
A5: 2 | B5: 46267 | G5: =E5*F5 -> 0 | J5: =H5*I5 -> 0 | K5: =G5+J5 -> 0 | M5: =M4+K5-L5 -> 35260.26
A6: 3 | B6: 46268 | G6: =E6*F6 -> 0 | J6: =H6*I6 -> 0 | K6: =G6+J6 -> 0 | M6: =M5+K6-L6 -> 35260.26
A7: 4 | B7: 46269 | G7: =E7*F7 -> 0 | J7: =H7*I7 -> 0 | K7: =G7+J7 -> 0 | M7: =M6+K7-L7 -> 35260.26
A8: 5 | B8: 46270 | G8: =E8*F8 -> 0 | J8: =H8*I8 -> 0 | K8: =G8+J8 -> 0 | M8: =M7+K8-L8 -> 35260.26
A9: 6 | B9: 46271 | G9: =E9*F9 -> 0 | J9: =H9*I9 -> 0 | K9: =G9+J9 -> 0 | M9: =M8+K9-L9 -> 35260.26
A10: 7 | B10: 46272 | G10: =E10*F10 -> 0 | J10: =H10*I10 -> 0 | K10: =G10+J10 -> 0 | M10: =M9+K10-L10 -> 35260.26
A11: 8 | B11: 46273 | G11: =E11*F11 -> 0 | J11: =H11*I11 -> 0 | K11: =G11+J11 -> 0 | M11: =M10+K11-L11 -> 35260.26
A12: 9 | B12: 46274 | E12: 300 | F12: 100.04 | G12: =E12*F12 -> 30012 | H12: 20 | I12: 112.06 | J12: =H12*I12 -> 2241.2 | K12: =G12+J12 -> 32253.2 | M12: =M11+K12-L12 -> 67513.46
A13: 10 | B13: 46275 | G13: =E13*F13 -> 0 | J13: =H13*I13 -> 0 | K13: =G13+J13 -> 0 | M13: =M12+K13-L13 -> 67513.46
A14: 11 | B14: 46276 | G14: =E14*F14 -> 0 | J14: =H14*I14 -> 0 | K14: =G14+J14 -> 0 | M14: =M13+K14-L14 -> 67513.46
A15: 12 | B15: 46277 | G15: =E15*F15 -> 0 | J15: =H15*I15 -> 0 | K15: =G15+J15 -> 0 | M15: =M14+K15-L15 -> 67513.46
A16: 13 | B16: 46278 | G16: =E16*F16 -> 0 | J16: =H16*I16 -> 0 | K16: =G16+J16 -> 0 | M16: =M15+K16-L16 -> 67513.46
A17: 14 | B17: 46279 | G17: =E17*F17 -> 0 | J17: =H17*I17 -> 0 | K17: =G17+J17 -> 0 | M17: =M16+K17-L17 -> 67513.46
A18: 15 | B18: 46280 | G18: =E18*F18 -> 0 | J18: =H18*I18 -> 0 | K18: =G18+J18 -> 0 | M18: =M17+K18-L18 -> 67513.46
A19: 16 | B19: 46281 | G19: =E19*F19 -> 0 | J19: =H19*I19 -> 0 | K19: =G19+J19 -> 0 | M19: =M18+K19-L19 -> 67513.46
A20: 17 | B20: 46282 | G20: =E20*F20 -> 0 | J20: =H20*I20 -> 0 | K20: =G20+J20 -> 0 | M20: =M19+K20-L20 -> 67513.46
A21: 18 | B21: 46283 | G21: =E21*F21 -> 0 | J21: =H21*I21 -> 0 | K21: =G21+J21 -> 0 | M21: =M20+K21-L21 -> 67513.46
A22: 19 | B22: 46284 | G22: =E22*F22 -> 0 | J22: =H22*I22 -> 0 | K22: =G22+J22 -> 0 | L22: 65000 | M22: =M21+K22-L22 -> 2513.46
A23: 20 | B23: 46285 | G23: =E23*F23 -> 0 | J23: =H23*I23 -> 0 | K23: =G23+J23 -> 0 | M23: =M22+K23-L23 -> 2513.46
A24: 21 | B24: 46286 | G24: =E24*F24 -> 0 | J24: =H24*I24 -> 0 | K24: =G24+J24 -> 0 | M24: =M23+K24-L24 -> 2513.46
A25: 22 | B25: 46287 | E25: 400 | F25: 100.04 | G25: =E25*F25 -> 40016 | H25: 20 | I25: 112.06 | J25: =H25*I25 -> 2241.2 | K25: =G25+J25 -> 42257.2 | M25: =M24+K25-L25 -> 44770.66
A26: 23 | B26: 46288 | G26: =E26*F26 -> 0 | J26: =H26*I26 -> 0 | K26: =G26+J26 -> 0 | M26: =M25+K26-L26 -> 44770.66
A27: 24 | B27: 46289 | G27: =E27*F27 -> 0 | J27: =H27*I27 -> 0 | K27: =G27+J27 -> 0 | M27: =M26+K27-L27 -> 44770.66
A28: 25 | B28: 46290 | G28: =E28*F28 -> 0 | J28: =H28*I28 -> 0 | K28: =G28+J28 -> 0 | M28: =M27+K28-L28 -> 44770.66
A29: 26 | B29: 46291 | G29: =E29*F29 -> 0 | J29: =H29*I29 -> 0 | K29: =G29+J29 -> 0 | M29: =M28+K29-L29 -> 44770.66
A30: 27 | B30: 46292 | G30: =E30*F30 -> 0 | J30: =H30*I30 -> 0 | K30: =G30+J30 -> 0 | M30: =M29+K30-L30 -> 44770.66
A31: 28 | B31: 46293 | G31: =E31*F31 -> 0 | J31: =H31*I31 -> 0 | K31: =G31+J31 -> 0 | M31: =M30+K31-L31 -> 44770.66
A32: 29 | B32: 46294 | G32: =E32*F32 -> 0 | J32: =H32*I32 -> 0 | K32: =G32+J32 -> 0 | M32: =M31+K32-L32 -> 44770.66
A33: 30 | B33: 46295 | G33: =E33*F33 -> 0 | J33: =H33*I33 -> 0 | K33: =G33+J33 -> 0 | M33: =M32+K33-L33 -> 44770.66
A34: 31 | G34: =E34*F34 -> 0 | K34: =G34+J34 -> 0 | M34: =M33+K34-L34 -> 44770.66
E35: =SUM(E4:E34) -> 700 | G35: =SUM(G4:G34) -> 70028 | H35: =SUM(H4:H34) -> 40 | J35: =SUM(J4:J34) -> 4482.4 | K35: =SUM(K4:K34) -> 74510.4 | L35: =SUM(L4:L34) -> 65000

Sheet Chellakere -1
A1: Shivaganga Service Station (BPCL)
A2: S.No | B2: Date | C2: GRN No | D2: Ind No/Bill No | E2: Diesel (Lts) | F2: Price | G2: Amount | H2: Petrol (Lts) | I2: Price | J2: Amount | K2: Total amount | L2: Amount paid | M2: As on Date | N2: Remarks
A3: Opening Balance
A4: 1 | B4: 46266 | G4: =E4*F4 -> 0 | J4: =H4*I4 -> 0 | K4: =G4+J4 -> 0 | M4: =M3+K4-L4 -> 0
A5: 2 | B5: 46267 | E5: 600 | F5: 100.05 | G5: =E5*F5 -> 60030 | H5: 35 | I5: 112.07 | J5: =H5*I5 -> 3922.45 | K5: =G5+J5 -> 63952.45 | M5: =M4+K5-L5 -> 63952.45
A6: 3 | B6: 46268 | G6: =E6*F6 -> 0 | J6: =H6*I6 -> 0 | K6: =G6+J6 -> 0 | M6: =M5+K6-L6 -> 63952.45
A7: 4 | B7: 46269 | G7: =E7*F7 -> 0 | J7: =H7*I7 -> 0 | K7: =G7+J7 -> 0 | M7: =M6+K7-L7 -> 63952.45
A8: 5 | B8: 46270 | G8: =E8*F8 -> 0 | J8: =H8*I8 -> 0 | K8: =G8+J8 -> 0 | M8: =M7+K8-L8 -> 63952.45
A9: 6 | B9: 46271 | G9: =E9*F9 -> 0 | J9: =H9*I9 -> 0 | K9: =G9+J9 -> 0 | M9: =M8+K9-L9 -> 63952.45
A10: 7 | B10: 46272 | E10: 600 | F10: 100.05 | G10: =E10*F10 -> 60030 | H10: 35 | I10: 112.07 | J10: =H10*I10 -> 3922.45 | K10: =G10+J10 -> 63952.45 | M10: =M9+K10-L10 -> 127904.9
A11: 8 | B11: 46273 | G11: =E11*F11 -> 0 | J11: =H11*I11 -> 0 | K11: =G11+J11 -> 0 | M11: =M10+K11-L11 -> 127904.9
A12: 9 | B12: 46274 | G12: =E12*F12 -> 0 | J12: =H12*I12 -> 0 | K12: =G12+J12 -> 0 | M12: =M11+K12-L12 -> 127904.9
A13: 10 | B13: 46275 | G13: =E13*F13 -> 0 | J13: =H13*I13 -> 0 | K13: =G13+J13 -> 0 | M13: =M12+K13-L13 -> 127904.9
A14: 11 | B14: 46276 | G14: =E14*F14 -> 0 | J14: =H14*I14 -> 0 | K14: =G14+J14 -> 0 | M14: =M13+K14-L14 -> 127904.9
A15: 12 | B15: 46277 | E15: 600 | F15: 100.05 | G15: =E15*F15 -> 60030 | H15: 35 | I15: 112.07 | J15: =H15*I15 -> 3922.45 | K15: =G15+J15 -> 63952.45 | M15: =M14+K15-L15 -> 191857.35
A16: 13 | B16: 46278 | G16: =E16*F16 -> 0 | J16: =H16*I16 -> 0 | K16: =G16+J16 -> 0 | M16: =M15+K16-L16 -> 191857.35
A17: 14 | B17: 46279 | G17: =E17*F17 -> 0 | J17: =H17*I17 -> 0 | K17: =G17+J17 -> 0 | M17: =M16+K17-L17 -> 191857.35
A18: 15 | B18: 46280 | G18: =E18*F18 -> 0 | J18: =H18*I18 -> 0 | K18: =G18+J18 -> 0 | M18: =M17+K18-L18 -> 191857.35
A19: 16 | B19: 46281 | G19: =E19*F19 -> 0 | J19: =H19*I19 -> 0 | K19: =G19+J19 -> 0 | M19: =M18+K19-L19 -> 191857.35
A20: 17 | B20: 46282 | G20: =E20*F20 -> 0 | J20: =H20*I20 -> 0 | K20: =G20+J20 -> 0 | M20: =M19+K20-L20 -> 191857.35
A21: 18 | B21: 46283 | G21: =E21*F21 -> 0 | J21: =H21*I21 -> 0 | K21: =G21+J21 -> 0 | M21: =M20+K21-L21 -> 191857.35
A22: 19 | B22: 46284 | G22: =E22*F22 -> 0 | J22: =H22*I22 -> 0 | K22: =G22+J22 -> 0 | L22: 191000 | M22: =M21+K22-L22 -> 857.35 | N22: Cash
A23: 20 | B23: 46285 | G23: =E23*F23 -> 0 | J23: =H23*I23 -> 0 | K23: =G23+J23 -> 0 | M23: =M22+K23-L23 -> 857.35
A24: 21 | B24: 46286 | E24: 600 | F24: 100.05 | G24: =E24*F24 -> 60030 | H24: 35 | I24: 112.07 | J24: =H24*I24 -> 3922.45 | K24: =G24+J24 -> 63952.45 | M24: =M23+K24-L24 -> 64809.8
A25: 22 | B25: 46287 | G25: =E25*F25 -> 0 | J25: =H25*I25 -> 0 | K25: =G25+J25 -> 0 | M25: =M24+K25-L25 -> 64809.8
A26: 23 | B26: 46288 | G26: =E26*F26 -> 0 | J26: =H26*I26 -> 0 | K26: =G26+J26 -> 0 | M26: =M25+K26-L26 -> 64809.8
A27: 24 | B27: 46289 | E27: 600 | F27: 100.05 | G27: =E27*F27 -> 60030 | J27: =H27*I27 -> 0 | K27: =G27+J27 -> 60030 | M27: =M26+K27-L27 -> 124839.8
A28: 25 | B28: 46290 | G28: =E28*F28 -> 0 | J28: =H28*I28 -> 0 | K28: =G28+J28 -> 0 | M28: =M27+K28-L28 -> 124839.8
A29: 26 | B29: 46291 | G29: =E29*F29 -> 0 | J29: =H29*I29 -> 0 | K29: =G29+J29 -> 0 | M29: =M28+K29-L29 -> 124839.8
A30: 27 | B30: 46292 | G30: =E30*F30 -> 0 | J30: =H30*I30 -> 0 | K30: =G30+J30 -> 0 | M30: =M29+K30-L30 -> 124839.8
A31: 28 | B31: 46293 | G31: =E31*F31 -> 0 | J31: =H31*I31 -> 0 | K31: =G31+J31 -> 0 | M31: =M30+K31-L31 -> 124839.8
A32: 29 | B32: 46294 | E32: 600 | F32: 100.05 | G32: =E32*F32 -> 60030 | H32: 35 | I32: 112.07 | J32: =H32*I32 -> 3922.45 | K32: =G32+J32 -> 63952.45 | M32: =M31+K32-L32 -> 188792.25
A33: 30 | B33: 46295 | G33: =E33*F33 -> 0 | J33: =H33*I33 -> 0 | K33: =G33+J33 -> 0 | M33: =M32+K33-L33 -> 188792.25
A34: 31 | G34: =E34*F34 -> 0 | J34: =H34*I34 -> 0 | K34: =G34+J34 -> 0 | M34: =M33+K34-L34 -> 188792.25
A35: 32 | G35: =E35*F35 -> 0 | J35: =H35*I35 -> 0 | K35: =G35+J35 -> 0 | M35: =M34+K35-L35 -> 188792.25
E38: =SUM(E4:E35) -> 3600 | G38: =SUM(G4:G35) -> 360180 | H38: =SUM(H4:H35) -> 175 | J38: =SUM(J4:J35) -> 19612.25 | K38: =SUM(K4:K35) -> 379792.25 | L38: =SUM(L4:L35) -> 191000

Sheet  Chellakere-PKG-9
A1: Chellakere-PKG-09
A2: S.No | B2: Date | C2: GRN No | D2: Ind No/Bill No | E2: Diesel (Lts) | F2: Price | G2: Amount | H2: Petrol (Lts) | I2: Price | J2: Amount | K2: Total amount | L2: Amount paid | M2: As on Date | N2: Remarks
A3: Opening Balance
A4: 1 | B4: 46266 | E4: 29.99 | F4: 100.05 | G4: =E4*F4 -> 3000.4995 | J4: =H4*I4 -> 0 | K4: =G4+J4 -> 3000.4995 | L4: =K4 -> 3000.4995 | M4: =M3+K4-L4 -> 0
A5: 2 | B5: 46267 | E5: 8 | F5: 100.05 | G5: =E5*F5 -> 800.4 | J5: =H5*I5 -> 0 | K5: =G5+J5 -> 800.4 | L5: =K5 -> 800.4 | M5: =M4+K5-L5 -> 0
A6: 3 | B6: 46268 | G6: =E6*F6 -> 0 | J6: =H6*I6 -> 0 | K6: =G6+J6 -> 0 | L6: =K6 -> 0 | M6: =M5+K6-L6 -> 0
A7: 4 | B7: 46269 | E7: 139.97 | F7: 100.05 | G7: =E7*F7 -> 14003.998 | J7: =H7*I7 -> 0 | K7: =G7+J7 -> 14003.998 | L7: =K7 -> 14003.998 | M7: =M6+K7-L7 -> 0
A8: 5 | B8: 46270 | G8: =E8*F8 -> 0 | J8: =H8*I8 -> 0 | K8: =G8+J8 -> 0 | L8: =K8 -> 0 | M8: =M7+K8-L8 -> 0
A9: 6 | B9: 46271 | G9: =E9*F9 -> 0 | J9: =H9*I9 -> 0 | K9: =G9+J9 -> 0 | L9: =K9 -> 0 | M9: =M8+K9-L9 -> 0
A10: 7 | B10: 46272 | G10: =E10*F10 -> 0 | J10: =H10*I10 -> 0 | K10: =G10+J10 -> 0 | L10: =K10 -> 0 | M10: =M9+K10-L10 -> 0
A11: 8 | B11: 46273 | E11: 99.95 | F11: 100.05 | G11: =E11*F11 -> 9999.9975 | H11: 5.35 | I11: 112.07 | J11: =H11*I11 -> 599.5745 | K11: =G11+J11 -> 10599.572 | L11: =K11 -> 10599.572 | M11: =M10+K11-L11 -> 0
A12: 9 | B12: 46274 | E12: 75 | F12: 100.05 | G12: =E12*F12 -> 7503.75 | H12: 12 | I12: 112.07 | J12: =H12*I12 -> 1344.84 | K12: =G12+J12 -> 8848.59 | L12: 3001 | M12: =M11+K12-L12 -> 5847.59
A13: 10 | B13: 46275 | E13: 43.69 | F13: 100.05 | G13: =E13*F13 -> 4371.1845 | J13: =H13*I13 -> 0 | K13: =G13+J13 -> 4371.1845 | M13: =M12+K13-L13 -> 10218.774
A14: 11 | B14: 46276 | G14: =E14*F14 -> 0 | J14: =H14*I14 -> 0 | K14: =G14+J14 -> 0 | L14: =K14 -> 0 | M14: =M13+K14-L14 -> 10218.774
A15: 12 | B15: 46277 | G15: =E15*F15 -> 0 | J15: =H15*I15 -> 0 | K15: =G15+J15 -> 0 | L15: =K15 -> 0 | M15: =M14+K15-L15 -> 10218.774
A16: 13 | B16: 46278 | G16: =E16*F16 -> 0 | J16: =H16*I16 -> 0 | K16: =G16+J16 -> 0 | L16: =K16 -> 0 | M16: =M15+K16-L16 -> 10218.774
A17: 14 | B17: 46279 | G17: =E17*F17 -> 0 | J17: =H17*I17 -> 0 | K17: =G17+J17 -> 0 | L17: =K17 -> 0 | M17: =M16+K17-L17 -> 10218.774
A18: 15 | B18: 46280 | E18: 40 | F18: 100.05 | G18: =E18*F18 -> 4002 | J18: =H18*I18 -> 0 | K18: =G18+J18 -> 4002 | M18: =M17+K18-L18 -> 14220.774
A19: 16 | B19: 46281 | E19: 34.98 | F19: 100.05 | G19: =E19*F19 -> 3499.749 | J19: =H19*I19 -> 0 | K19: =G19+J19 -> 3499.749 | L19: =K19 -> 3499.749 | M19: =M18+K19-L19 -> 14220.774
A20: 17 | B20: 46282 | E20: 57.69 | F20: 100.05 | G20: =E20*F20 -> 5771.8845 | J20: =H20*I20 -> 0 | K20: =G20+J20 -> 5771.8845 | L20: 20067 | M20: =M19+K20-L20 -> -74.341
A21: 18 | B21: 46283 | E21: 30 | F21: 100.05 | G21: =E21*F21 -> 3001.5 | J21: =H21*I21 -> 0 | K21: =G21+J21 -> 3001.5 | L21: =K21 -> 3001.5 | M21: =M20+K21-L21 -> -74.341
A22: 19 | B22: 46284 | E22: 20 | F22: 100.05 | G22: =E22*F22 -> 2001 | J22: =H22*I22 -> 0 | K22: =G22+J22 -> 2001 | L22: =K22 -> 2001 | M22: =M21+K22-L22 -> -74.341
B23: 46285 | G23: =E23*F23 -> 0 | K23: =G23+J23 -> 0 | L23: =K23 -> 0 | M23: =M22+K23-L23 -> -74.341
A24: 20 | B24: 46286 | G24: =E24*F24 -> 0 | J24: =H24*I24 -> 0 | K24: =G24+J24 -> 0 | L24: =K24 -> 0 | M24: =M23+K24-L24 -> -74.341
A25: 21 | B25: 46287 | E25: 60 | F25: 100.05 | G25: =E25*F25 -> 6003 | J25: =H25*I25 -> 0 | K25: =G25+J25 -> 6003 | L25: =K25 -> 6003 | M25: =M24+K25-L25 -> -74.341
B26: 46287 | E26: 70 | F26: 100.05 | G26: =E26*F26 -> 7003.5 | J26: =H26*I26 -> 0 | K26: =G26+J26 -> 7003.5 | M26: =M25+K26-L26 -> 6929.159
A27: 22 | B27: 46288 | G27: =E27*F27 -> 0 | J27: =H27*I27 -> 0 | K27: =G27+J27 -> 0 | L27: 7003.5 | M27: =M26+K27-L27 -> -74.341
B28: 46288 | H28: 15 | I28: 112.07 | J28: =H28*I28 -> 1681.05 | K28: =G28+J28 -> 1681.05 | L28: 1681.05 | M28: =M27+K28-L28 -> -74.341
A29: 23 | B29: 46289 | G29: =E29*F29 -> 0 | J29: =H29*I29 -> 0 | K29: =G29+J29 -> 0 | L29: =K29 -> 0 | M29: =M28+K29-L29 -> -74.341
A30: 24 | B30: 46290 | E30: 149.94 | F30: 100.05 | G30: =E30*F30 -> 15001.497 | J30: =H30*I30 -> 0 | K30: =G30+J30 -> 15001.497 | L30: =K30 -> 15001.497 | M30: =M29+K30-L30 -> -74.341
A31: 25 | B31: 46291 | G31: =E31*F31 -> 0 | J31: =H31*I31 -> 0 | K31: =G31+J31 -> 0 | L31: =K31 -> 0 | M31: =M30+K31-L31 -> -74.341
A32: 26 | B32: 46292 | G32: =E32*F32 -> 0 | J32: =H32*I32 -> 0 | K32: =G32+J32 -> 0 | L32: =K32 -> 0 | M32: =M31+K32-L32 -> -74.341
A33: 27 | B33: 46293 | E33: 123.94 | F33: 100.05 | G33: =E33*F33 -> 12400.197 | H33: 15.89 | I33: 112.07 | J33: =H33*I33 -> 1780.7923 | K33: =G33+J33 -> 14180.989 | L33: =K33 -> 14180.989 | M33: =M32+K33-L33 -> -74.341
A34: 28 | B34: 46294 | G34: =E34*F34 -> 0 | J34: =H34*I34 -> 0 | K34: =G34+J34 -> 0 | L34: -75.34 | M34: =M33+K34-L34 -> 0.999
A35: 29 | B35: 46295 | G35: =E35*F35 -> 0 | J35: =H35*I35 -> 0 | K35: =G35+J35 -> 0 | L35: =K35 -> 0 | M35: =M34+K35-L35 -> 0.999
A36: 30 | G36: =E36*F36 -> 0 | J36: =H36*I36 -> 0 | K36: =G36+J36 -> 0 | L36: =K36 -> 0
A37: 31 | G37: =E37*F37 -> 0 | J37: =H37*I37 -> 0 | K37: =G37+J37 -> 0 | L37: =K37 -> 0
E38: =SUM(E4:E37) -> 983.15 | G38: =SUM(G4:G37) -> 98364.158 | H38: =SUM(H4:H37) -> 48.24 | J38: =SUM(J4:J37) -> 5406.2568 | K38: =SUM(K4:K37) -> 103770.41 | L38: =SUM(L4:L37) -> 103769.42

Sheet  Chennagiri
A1: Chennagiri
A2: S.No | B2: Date | C2: GRN No | D2: Ind No/Bill No | E2: Diesel (Lts) | F2: Price | G2: Amount | H2: Petrol (Lts) | I2: Price | J2: Amount | K2: Total amount | L2: Amount paid | M2: As on Date | N2: Remarks
A3: Opening Balance
A4: 1 | B4: 46266 | G4: =E4*F4 -> 0 | J4: =H4*I4 -> 0 | K4: =G4+J4 -> 0 | L4: =K4 -> 0 | M4: =M3+K4-L4 -> 0
A5: 2 | B5: 46267 | E5: 200 | F5: 99.87 | G5: =E5*F5 -> 19974 | J5: =H5*I5 -> 0 | K5: =G5+J5 -> 19974 | L5: =K5 -> 19974 | M5: =M4+K5-L5 -> 0
A6: 3 | B6: 46268 | G6: =E6*F6 -> 0 | J6: =H6*I6 -> 0 | K6: =G6+J6 -> 0 | L6: =K6 -> 0 | M6: =M5+K6-L6 -> 0
A7: 4 | B7: 46269 | G7: =E7*F7 -> 0 | J7: =H7*I7 -> 0 | K7: =G7+J7 -> 0 | L7: =K7 -> 0 | M7: =M6+K7-L7 -> 0
A8: 5 | B8: 46270 | E8: 120 | F8: 99.87 | G8: =E8*F8 -> 11984.4 | J8: =H8*I8 -> 0 | K8: =G8+J8 -> 11984.4 | L8: =K8 -> 11984.4 | M8: =M7+K8-L8 -> 0
A9: 6 | B9: 46271 | G9: =E9*F9 -> 0 | J9: =H9*I9 -> 0 | K9: =G9+J9 -> 0 | L9: =K9 -> 0 | M9: =M8+K9-L9 -> 0
A10: 7 | B10: 46272 | G10: =E10*F10 -> 0 | J10: =H10*I10 -> 0 | K10: =G10+J10 -> 0 | L10: =K10 -> 0 | M10: =M9+K10-L10 -> 0
A11: 8 | B11: 46273 | G11: =E11*F11 -> 0 | J11: =H11*I11 -> 0 | K11: =G11+J11 -> 0 | L11: =K11 -> 0 | M11: =M10+K11-L11 -> 0
A12: 9 | B12: 46274 | G12: =E12*F12 -> 0 | J12: =H12*I12 -> 0 | K12: =G12+J12 -> 0 | L12: =K12 -> 0 | M12: =M11+K12-L12 -> 0
A13: 10 | B13: 46275 | E13: 110 | F13: 99.87 | G13: =E13*F13 -> 10985.7 | H13: 35 | I13: 112.06 | J13: =H13*I13 -> 3922.1 | K13: =G13+J13 -> 14907.8 | L13: =K13 -> 14907.8 | M13: =M12+K13-L13 -> 0
A14: 11 | B14: 46276 | G14: =E14*F14 -> 0 | J14: =H14*I14 -> 0 | K14: =G14+J14 -> 0 | L14: =K14 -> 0 | M14: =M13+K14-L14 -> 0
A15: 12 | B15: 46277 | E15: 200 | F15: 99.9 | G15: =E15*F15 -> 19980 | J15: =H15*I15 -> 0 | K15: =G15+J15 -> 19980 | L15: =K15 -> 19980 | M15: =M14+K15-L15 -> 0 | N15: IOCL
A16: 13 | B16: 46278 | G16: =E16*F16 -> 0 | J16: =H16*I16 -> 0 | K16: =G16+J16 -> 0 | L16: =K16 -> 0 | M16: =M15+K16-L16 -> 0
A17: 14 | B17: 46279 | G17: =E17*F17 -> 0 | J17: =H17*I17 -> 0 | K17: =G17+J17 -> 0 | L17: =K17 -> 0 | M17: =M16+K17-L17 -> 0
A18: 15 | B18: 46280 | G18: =E18*F18 -> 0 | J18: =H18*I18 -> 0 | K18: =G18+J18 -> 0 | L18: =K18 -> 0 | M18: =M17+K18-L18 -> 0
A19: 16 | B19: 46281 | G19: =E19*F19 -> 0 | J19: =H19*I19 -> 0 | K19: =G19+J19 -> 0 | L19: =K19 -> 0 | M19: =M18+K19-L19 -> 0
A20: 17 | B20: 46282 | E20: 200 | F20: 99.9 | G20: =E20*F20 -> 19980 | J20: =H20*I20 -> 0 | K20: =G20+J20 -> 19980 | L20: =K20 -> 19980 | M20: =M19+K20-L20 -> 0
A21: 18 | B21: 46283 | G21: =E21*F21 -> 0 | J21: =H21*I21 -> 0 | K21: =G21+J21 -> 0 | L21: =K21 -> 0 | M21: =M20+K21-L21 -> 0
A22: 19 | B22: 46284 | G22: =E22*F22 -> 0 | J22: =H22*I22 -> 0 | K22: =G22+J22 -> 0 | L22: =K22 -> 0 | M22: =M21+K22-L22 -> 0
A23: 20 | B23: 46285 | G23: =E23*F23 -> 0 | J23: =H23*I23 -> 0 | K23: =G23+J23 -> 0 | L23: =K23 -> 0 | M23: =M22+K23-L23 -> 0
A24: 21 | B24: 46286 | G24: =E24*F24 -> 0 | J24: =H24*I24 -> 0 | K24: =G24+J24 -> 0 | L24: =K24 -> 0 | M24: =M23+K24-L24 -> 0
A25: 22 | B25: 46287 | G25: =E25*F25 -> 0 | J25: =H25*I25 -> 0 | K25: =G25+J25 -> 0 | L25: =K25 -> 0 | M25: =M24+K25-L25 -> 0
A26: 23 | B26: 46288 | E26: 170 | F26: 99.9 | G26: =E26*F26 -> 16983 | J26: =H26*I26 -> 0 | K26: =G26+J26 -> 16983 | L26: =K26 -> 16983 | M26: =M25+K26-L26 -> 0
A27: 24 | B27: 46289 | G27: =E27*F27 -> 0 | H27: 35 | I27: 112.06 | J27: =H27*I27 -> 3922.1 | K27: =G27+J27 -> 3922.1 | L27: =K27 -> 3922.1 | M27: =M26+K27-L27 -> 0
A28: 25 | B28: 46290 | G28: =E28*F28 -> 0 | J28: =H28*I28 -> 0 | K28: =G28+J28 -> 0 | L28: =K28 -> 0 | M28: 0
A29: 26 | B29: 46291 | G29: =E29*F29 -> 0 | J29: =H29*I29 -> 0 | K29: =G29+J29 -> 0 | L29: =K29 -> 0 | M29: 0
A30: 27 | B30: 46292 | E30: 150 | F30: 99.9 | G30: =E30*F30 -> 14985 | J30: =H30*I30 -> 0 | K30: =G30+J30 -> 14985 | L30: =K30 -> 14985 | M30: 0
A31: 28 | B31: 46293 | G31: =E31*F31 -> 0 | J31: =H31*I31 -> 0 | K31: =G31+J31 -> 0 | L31: =K31 -> 0 | M31: 0
A32: 29 | B32: 46294 | E32: 140 | F32: 99.9 | G32: =E32*F32 -> 13986 | J32: =H32*I32 -> 0 | K32: =G32+J32 -> 13986 | L32: =K32 -> 13986
A33: 30 | B33: 46295 | G33: =E33*F33 -> 0 | J33: =H33*I33 -> 0 | K33: =G33+J33 -> 0 | L33: =K33 -> 0
A34: 31 | G34: =E34*F34 -> 0 | J34: =H34*I34 -> 0 | K34: =G34+J34 -> 0 | L34: =K34 -> 0
E35: =SUM(E4:E34) -> 1290 | G35: =SUM(G4:G34) -> 128858.1 | H35: =SUM(H4:H34) -> 70 | J35: =SUM(J4:J34) -> 7844.2 | K35: =SUM(K4:K34) -> 136702.3 | L35: =SUM(L4:L34) -> 136702.3

Sheet Khanapur
A1: V.V.Varde
A2: S.No | B2: Date | C2: GRN No | D2: Ind No/Bill No | E2: Diesel (Lts) | F2: Price | G2: Amount | H2: Petrol (Lts) | I2: Price | J2: Amount | K2: Total amount | L2: Date of payment | M2: Amount paid | N2: Remarks
D3: Opening Balance | L3: 41788.871 | M3: 41788.871
A4: 1 | B4: 46266 | E4: 50 | F4: 98.69 | G4: =E4*F4 -> 4934.5 | J4: =H4*I4 -> 0 | K4: =G4+J4 -> 4934.5 | M4: =M3+K4-L4 -> 46723.371
A5: 2 | B5: 46267 | E5: 33.9 | F5: 98.69 | G5: =E5*F5 -> 3345.591 | J5: =H5*I5 -> 0 | K5: =G5+J5 -> 3345.591 | M5: =M4+K5-L5 -> 50068.962
A6: 3 | B6: 46268 | E6: 89.54 | F6: 98.69 | G6: =E6*F6 -> 8836.7026 | H6: 5 | I6: 110.74 | J6: =H6*I6 -> 553.7 | K6: =G6+J6 -> 9390.4026 | M6: =M5+K6-L6 -> 59459.364
A7: 4 | B7: 46269 | F7: 98.69 | G7: =E7*F7 -> 0 | J7: =H7*I7 -> 0 | K7: =G7+J7 -> 0 | M7: =M6+K7-L7 -> 59459.364
A8: 5 | B8: 46270 | E8: 27.45 | F8: 98.69 | G8: =E8*F8 -> 2709.0405 | H8: 10 | I8: 110.74 | J8: =H8*I8 -> 1107.4 | K8: =G8+J8 -> 3816.4405 | M8: =M7+K8-L8 -> 63275.805 | R8: =30*12 -> 360
A9: 6 | B9: 46271 | F9: 98.69 | G9: =E9*F9 -> 0 | J9: =H9*I9 -> 0 | K9: =G9+J9 -> 0 | M9: =M8+K9-L9 -> 63275.805
A10: 7 | B10: 46272 | E10: 30 | F10: 98.69 | G10: =E10*F10 -> 2960.7 | J10: =H10*I10 -> 0 | K10: =G10+J10 -> 2960.7 | M10: =M9+K10-L10 -> 66236.505
A11: 8 | B11: 46273 | F11: 98.69 | G11: =E11*F11 -> 0 | H11: 15 | I11: 110.74 | J11: =H11*I11 -> 1661.1 | K11: =G11+J11 -> 1661.1 | M11: =M10+K11-L11 -> 67897.605
A12: 9 | B12: 46274 | E12: 30 | F12: 98.69 | G12: =E12*F12 -> 2960.7 | J12: =H12*I12 -> 0 | K12: =G12+J12 -> 2960.7 | M12: =M11+K12-L12 -> 70858.305
A13: 10 | B13: 46275 | E13: 30 | F13: 98.69 | G13: =E13*F13 -> 2960.7 | J13: =H13*I13 -> 0 | K13: =G13+J13 -> 2960.7 | M13: =M12+K13-L13 -> 73819.005
A14: 11 | B14: 46276 | F14: 98.69 | G14: =E14*F14 -> 0 | J14: =H14*I14 -> 0 | K14: =G14+J14 -> 0 | M14: =M13+K14-L14 -> 73819.005
A15: 12 | B15: 46277 | F15: 98.69 | G15: =E15*F15 -> 0 | J15: =H15*I15 -> 0 | K15: =G15+J15 -> 0 | M15: =M14+K15-L15 -> 73819.005
A16: 13 | B16: 46278 | F16: 98.69 | G16: =E16*F16 -> 0 | H16: 5 | I16: 110.74 | J16: =H16*I16 -> 553.7 | K16: =G16+J16 -> 553.7 | M16: =M15+K16-L16 -> 74372.705
A17: 14 | B17: 46279 | F17: 98.69 | G17: =E17*F17 -> 0 | H17: 6 | I17: 110.74 | J17: =H17*I17 -> 664.44 | K17: =G17+J17 -> 664.44 | M17: =M16+K17-L17 -> 75037.145
A18: 15 | B18: 46280 | E18: 50 | F18: 98.69 | G18: =E18*F18 -> 4934.5 | H18: 4 | I18: 110.74 | J18: =H18*I18 -> 442.96 | K18: =G18+J18 -> 5377.46 | M18: =M17+K18-L18 -> 80414.605
A19: 16 | B19: 46281 | E19: 30 | F19: 98.69 | G19: =E19*F19 -> 2960.7 | J19: =H19*I19 -> 0 | K19: =G19+J19 -> 2960.7 | M19: =M18+K19-L19 -> 83375.305
A20: 17 | B20: 46282 | F20: 98.69 | G20: =E20*F20 -> 0 | J20: =H20*I20 -> 0 | K20: =G20+J20 -> 0 | M20: =M19+K20-L20 -> 83375.305
A21: 18 | B21: 46283 | F21: 98.69 | G21: =E21*F21 -> 0 | J21: =H21*I21 -> 0 | K21: =G21+J21 -> 0 | M21: =M20+K21-L21 -> 83375.305
A22: 19 | B22: 46284 | F22: 98.69 | G22: =E22*F22 -> 0 | H22: 10 | I22: 110.74 | J22: =H22*I22 -> 1107.4 | K22: =G22+J22 -> 1107.4 | M22: =M21+K22-L22 -> 84482.705
A23: 20 | B23: 46285 | E23: 188.48 | F23: 98.69 | G23: =E23*F23 -> 18601.091 | J23: =H23*I23 -> 0 | K23: =G23+J23 -> 18601.091 | M23: =M22+K23-L23 -> 103083.8
A24: 21 | B24: 46286 | F24: 98.69 | G24: =E24*F24 -> 0 | H24: 5 | I24: 110.74 | J24: =H24*I24 -> 553.7 | K24: =G24+J24 -> 553.7 | M24: =M23+K24-L24 -> 103637.5
A25: 22 | B25: 46287 | E25: 30 | F25: 98.69 | G25: =E25*F25 -> 2960.7 | H25: 5 | I25: 110.74 | J25: =H25*I25 -> 553.7 | K25: =G25+J25 -> 3514.4 | M25: =M24+K25-L25 -> 107151.9
A26: 23 | B26: 46288 | F26: 98.69 | G26: =E26*F26 -> 0 | H26: 5 | I26: 110.74 | J26: =H26*I26 -> 553.7 | K26: =G26+J26 -> 553.7 | M26: =M25+K26-L26 -> 107705.6
A27: 24 | B27: 46289 | F27: 98.69 | G27: =E27*F27 -> 0 | H27: 5 | I27: 110.74 | J27: =H27*I27 -> 553.7 | K27: =G27+J27 -> 553.7 | M27: =M26+K27-L27 -> 108259.3
A28: 25 | B28: 46290 | F28: 98.69 | G28: =E28*F28 -> 0 | J28: =H28*I28 -> 0 | K28: =G28+J28 -> 0 | M28: =M27+K28-L28 -> 108259.3
A29: 26 | B29: 46291 | E29: 45 | F29: 98.69 | G29: =F29*E29 -> 4441.05 | I29: 110.74 | J29: =H29*I29 -> 0 | K29: =G29+J29 -> 4441.05 | M29: =M28+K29-L29 -> 112700.35
A30: 27 | B30: 46292 | F30: 98.69 | G30: =E30*F30 -> 0 | H30: 5 | I30: 110.74 | J30: =H30*I30 -> 553.7 | K30: =G30+J30 -> 553.7 | M30: =M29+K30-L30 -> 113254.05
A31: 28 | B31: 46293 | E31: 30 | F31: 98.69 | G31: =E31*F31 -> 2960.7 | H31: 5 | I31: 110.74 | J31: =H31*I31 -> 553.7 | K31: =G31+J31 -> 3514.4 | M31: =M30+K31-L31 -> 116768.45
A32: 29 | B32: 46294 | E32: 40.7 | F32: 98.69 | G32: =F32*E32 -> 4016.683 | J32: =H32*I32 -> 0 | K32: =G32+J32 -> 4016.683 | M32: =M31+K32-L32 -> 120785.13
A33: 30 | B33: 46295 | G33: =F33*E33 -> 0 | J33: =H33*I33 -> 0 | K33: =G33+J33 -> 0 | M33: =M32+K33-L33 -> 120785.13
A34: 31 | G34: =F34*E34 -> 0 | J34: =H34*I34 -> 0 | K34: =G34+J34 -> 0 | M34: =M33+K34-L34 -> 120785.13
E35: =SUM(E4:E34) -> 705.07 | G35: =SUM(G4:G34) -> 69583.358 | H35: =SUM(H4:H34) -> 85 | J35: =SUM(J4:J34) -> 9412.9 | K35: =SUM(K4:K34) -> 78996.258 | L35: =SUM(L4:L34) -> 0 | M35: =SUM(M4:M34) -> 2676320.8

Sheet Munavali-2
A1: Shiri Shiva Petroluem
A2: S.No | B2: Date | C2: GRN No | D2: Ind No/Bill No | E2: Diesel (Lts) | F2: Price | G2: Amount | H2: Petrol (Lts) | I2: Price | J2: Amount | K2: Total amount | L2: Amount paid | M2: As on date | N2: Remarks
D3: Opening Balance | M3: 346801.5
A4: 1 | B4: 46266 | G4: =E4*F4 -> 0 | J4: =H4*I4 -> 0 | K4: =G4+J4 -> 0 | L4: 300000 | M4: =M3+K4-L4 -> 46801.5
A5: 2 | B5: 46267 | E5: 800 | F5: 99.35 | G5: =E5*F5 -> 79480 | J5: =H5*I5 -> 0 | K5: =G5+J5 -> 79480 | M5: =M4+K5-L5 -> 126281.5
A6: 3 | B6: 46268 | G6: =E6*F6 -> 0 | J6: =H6*I6 -> 0 | K6: =G6+J6 -> 0 | M6: =M5+K6-L6 -> 126281.5
A7: 4 | B7: 46269 | G7: =E7*F7 -> 0 | J7: =H7*I7 -> 0 | K7: =G7+J7 -> 0 | M7: =M6+K7-L7 -> 126281.5
A8: 5 | B8: 46270 | G8: =E8*F8 -> 0 | J8: =H8*I8 -> 0 | K8: =G8+J8 -> 0 | M8: =M7+K8-L8 -> 126281.5
A9: 6 | B9: 46271 | G9: =E9*F9 -> 0 | J9: =H9*I9 -> 0 | K9: =G9+J9 -> 0 | M9: =M8+K9-L9 -> 126281.5
A10: 7 | B10: 46272 | G10: =E10*F10 -> 0 | J10: =H10*I10 -> 0 | K10: =G10+J10 -> 0 | M10: =M9+K10-L10 -> 126281.5
A11: 8 | B11: 46273 | E11: 800 | F11: 99.35 | G11: =E11*F11 -> 79480 | J11: =H11*I11 -> 0 | K11: =G11+J11 -> 79480 | M11: =M10+K11-L11 -> 205761.5
A12: 9 | B12: 46274 | G12: =E12*F12 -> 0 | J12: =H12*I12 -> 0 | K12: =G12+J12 -> 0 | M12: =M11+K12-L12 -> 205761.5
A13: 10 | B13: 46275 | G13: =E13*F13 -> 0 | J13: =H13*I13 -> 0 | K13: =G13+J13 -> 0 | M13: =M12+K13-L13 -> 205761.5
A14: 11 | B14: 46276 | G14: =E14*F14 -> 0 | J14: =H14*I14 -> 0 | K14: =G14+J14 -> 0 | M14: =M13+K14-L14 -> 205761.5
A15: 12 | B15: 46277 | E15: 800 | F15: 99.35 | G15: =E15*F15 -> 79480 | J15: =H15*I15 -> 0 | K15: =G15+J15 -> 79480 | M15: =M14+K15-L15 -> 285241.5
A16: 13 | B16: 46278 | G16: =E16*F16 -> 0 | J16: =H16*I16 -> 0 | K16: =G16+J16 -> 0 | M16: =M15+K16-L16 -> 285241.5
A17: 14 | B17: 46279 | G17: =E17*F17 -> 0 | J17: =H17*I17 -> 0 | K17: =G17+J17 -> 0 | M17: =M16+K17-L17 -> 285241.5
A18: 15 | B18: 46280 | G18: =E18*F18 -> 0 | J18: =H18*I18 -> 0 | K18: =G18+J18 -> 0 | M18: =M17+K18-L18 -> 285241.5
A19: 16 | B19: 46281 | G19: =E19*F19 -> 0 | J19: =H19*I19 -> 0 | K19: =G19+J19 -> 0 | M19: =M18+K19-L19 -> 285241.5
A20: 17 | B20: 46282 | G20: =E20*F20 -> 0 | J20: =H20*I20 -> 0 | K20: =G20+J20 -> 0 | M20: =M19+K20-L20 -> 285241.5
A21: 18 | B21: 46283 | G21: =E21*F21 -> 0 | J21: =H21*I21 -> 0 | K21: =G21+J21 -> 0 | M21: =M20+K21-L21 -> 285241.5
A22: 19 | B22: 46284 | E22: 1000 | F22: 99.35 | G22: =E22*F22 -> 99350 | J22: =H22*I22 -> 0 | K22: =G22+J22 -> 99350 | M22: =M21+K22-L22 -> 384591.5
A23: 20 | B23: 46285 | G23: =E23*F23 -> 0 | J23: 0 | K23: =G23+J23 -> 0 | M23: =M22+K23-L23 -> 384591.5
A24: 21 | B24: 46286 | G24: =E24*F24 -> 0 | J24: =H24*I24 -> 0 | K24: =G24+J24 -> 0 | M24: =M23+K24-L24 -> 384591.5
A25: 22 | B25: 46287 | G25: =E25*F25 -> 0 | J25: =H25*I25 -> 0 | K25: =G25+J25 -> 0 | M25: =M24+K25-L25 -> 384591.5
A26: 23 | B26: 46288 | G26: =E26*F26 -> 0 | J26: =H26*I26 -> 0 | K26: =G26+J26 -> 0 | L26: 300000 | M26: =M25+K26-L26 -> 84591.5
A27: 24 | B27: 46289 | E27: 800 | F27: 99.35 | G27: =E27*F27 -> 79480 | J27: =H27*I27 -> 0 | K27: =G27+J27 -> 79480 | M27: =M26+K27-L27 -> 164071.5
A28: 25 | B28: 46290 | G28: =E28*F28 -> 0 | J28: =H28*I28 -> 0 | K28: =G28+J28 -> 0 | M28: =M27+K28-L28 -> 164071.5
A29: 26 | B29: 46291 | G29: =E29*F29 -> 0 | J29: =H29*I29 -> 0 | K29: =G29+J29 -> 0 | M29: =M28+K29-L29 -> 164071.5
A30: 27 | B30: 46292 | G30: =E30*F30 -> 0 | J30: =H30*I30 -> 0 | K30: =G30+J30 -> 0 | M30: =M29+K30-L30 -> 164071.5
A31: 28 | B31: 46293 | G31: =E31*F31 -> 0 | J31: =H31*I31 -> 0 | K31: =G31+J31 -> 0 | M31: =M30+K31-L31 -> 164071.5
A32: 29 | B32: 46294 | G32: =E32*F32 -> 0 | J32: =H32*I32 -> 0 | K32: =G32+J32 -> 0 | M32: =M31+K32-L32 -> 164071.5
A33: 30 | B33: 46295 | E33: 1000 | F33: 99.35 | G33: =E33*F33 -> 99350 | J33: =H33*I33 -> 0 | K33: =G33+J33 -> 99350 | M33: =M32+K33-L33 -> 263421.5
A34: 31 | G34: =E34*F34 -> 0 | J34: =H34*I34 -> 0 | K34: =G34+J34 -> 0 | M34: =M33+K34-L34 -> 263421.5
A35: 32 | G35: =E35*F35 -> 0 | J35: =H35*I35 -> 0 | K35: =G35+J35 -> 0 | M35: =M34+K35-L35 -> 263421.5
A36: 33 | G36: =E36*F36 -> 0 | J36: =H36*I36 -> 0 | K36: =G36+J36 -> 0 | M36: =M35+K36-L36 -> 263421.5
A37: 34 | G37: =E37*F37 -> 0 | J37: =H37*I37 -> 0 | K37: =G37+J37 -> 0 | M37: =M36+K37-L37 -> 263421.5
A38: 35 | G38: =E38*F38 -> 0 | J38: =H38*I38 -> 0 | K38: =G38+J38 -> 0 | M38: =M37+K38-L38 -> 263421.5
A39: 36 | G39: =E39*F39 -> 0 | J39: =H39*I39 -> 0 | K39: =G39+J39 -> 0 | M39: =M38+K39-L39 -> 263421.5
E40: =SUM(E4:E39) -> 5200 | G40: =SUM(G4:G39) -> 516620 | H40: =SUM(H4:H39) -> 0 | J40: =SUM(J4:J39) -> 0 | K40: =SUM(K4:K39) -> 516620 | L40: =SUM(L4:L39) -> 600000

Sheet  Munavali
A1: DANESHWARI PETROLIUM(YERRAGATTI)
A2: S.No | B2: Date | C2: GRN No | D2: Ind No/Bill No | E2: Diesel (Lts) | F2: Price | G2: Amount | H2: Petrol (Lts) | I2: Price | J2: Amount | K2: Total amount | L2: Amount paid | M2: As on date | N2: Remarks
D3: Opening Balance | M3: 665.2699
A4: 1 | B4: 46266 | G4: =E4*F4 -> 0 | H4: 30 | I4: 111.21 | J4: =H4*I4 -> 3336.3 | K4: =G4+J4 -> 3336.3 | M4: =M3+K4-L4 -> 4001.5699
A5: 2 | B5: 46267 | E5: 27.13 | F5: 99.13 | G5: =E5*F5 -> 2689.3969 | J5: =H5*I5 -> 0 | K5: =G5+J5 -> 2689.3969 | M5: =M4+K5-L5 -> 6690.9668
A6: 3 | B6: 46268 | G6: =E6*F6 -> 0 | H6: 30 | I6: 111.21 | J6: =H6*I6 -> 3336.3 | K6: =G6+J6 -> 3336.3 | M6: =M5+K6-L6 -> 10027.267
A7: 4 | B7: 46269 | G7: =E7*F7 -> 0 | J7: =H7*I7 -> 0 | K7: =G7+J7 -> 0 | M7: =M6+K7-L7 -> 10027.267
A8: 5 | B8: 46270 | G8: =E8*F8 -> 0 | J8: =H8*I8 -> 0 | K8: =G8+J8 -> 0 | M8: =M7+K8-L8 -> 10027.267
A9: 6 | B9: 46271 | G9: =E9*F9 -> 0 | J9: =H9*I9 -> 0 | K9: =G9+J9 -> 0 | M9: =M8+K9-L9 -> 10027.267
A10: 7 | B10: 46272 | G10: =E10*F10 -> 0 | J10: =H10*I10 -> 0 | K10: =G10+J10 -> 0 | M10: =M9+K10-L10 -> 10027.267
A11: 8 | B11: 46273 | G11: =E11*F11 -> 0 | H11: 30 | I11: 111.21 | J11: =H11*I11 -> 3336.3 | K11: =G11+J11 -> 3336.3 | M11: =M10+K11-L11 -> 13363.567
A12: 9 | B12: 46274 | G12: =E12*F12 -> 0 | J12: =H12*I12 -> 0 | K12: =G12+J12 -> 0 | M12: =M11+K12-L12 -> 13363.567
A13: 10 | B13: 46275 | G13: =E13*F13 -> 0 | J13: =H13*I13 -> 0 | K13: =G13+J13 -> 0 | M13: =M12+K13-L13 -> 13363.567
A14: 11 | B14: 46276 | G14: =E14*F14 -> 0 | H14: 30 | I14: 111.21 | J14: =H14*I14 -> 3336.3 | K14: =G14+J14 -> 3336.3 | M14: =M13+K14-L14 -> 16699.867
A15: 12 | B15: 46277 | G15: =E15*F15 -> 0 | J15: =H15*I15 -> 0 | K15: =G15+J15 -> 0 | M15: =M14+K15-L15 -> 16699.867
A16: 13 | B16: 46278 | G16: =E16*F16 -> 0 | J16: =H16*I16 -> 0 | K16: =G16+J16 -> 0 | M16: =M15+K16-L16 -> 16699.867
A17: 14 | B17: 46279 | G17: =E17*F17 -> 0 | J17: =H17*I17 -> 0 | K17: =G17+J17 -> 0 | M17: =M16+K17-L17 -> 16699.867
A18: 15 | B18: 46280 | G18: =E18*F18 -> 0 | H18: 30 | I18: 111.21 | J18: =H18*I18 -> 3336.3 | K18: =G18+J18 -> 3336.3 | M18: =M17+K18-L18 -> 20036.167
A19: 16 | B19: 46281 | G19: =E19*F19 -> 0 | J19: =H19*I19 -> 0 | K19: =G19+J19 -> 0 | M19: =M18+K19-L19 -> 20036.167
A20: 17 | B20: 46282 | G20: =E20*F20 -> 0 | J20: =H20*I20 -> 0 | K20: =G20+J20 -> 0 | M20: =M19+K20-L20 -> 20036.167
A21: 18 | B21: 46283 | G21: =E21*F21 -> 0 | J21: =H21*I21 -> 0 | K21: =G21+J21 -> 0 | M21: =M20+K21-L21 -> 20036.167
A22: 19 | B22: 46284 | G22: =E22*F22 -> 0 | J22: =H22*I22 -> 0 | K22: =G22+J22 -> 0 | M22: =M21+K22-L22 -> 20036.167
A23: 20 | B23: 46285 | G23: =E23*F23 -> 0 | J23: =H23*I23 -> 0 | K23: =G23+J23 -> 0 | M23: =M22+K23-L23 -> 20036.167
A24: 22 | B24: 46286 | G24: =E24*F24 -> 0 | J24: =H24*I24 -> 0 | K24: =G24+J24 -> 0 | M24: =M23+K24-L24 -> 20036.167
A25: 23 | B25: 46287 | G25: =E25*F25 -> 0 | H25: 30 | I25: 111.21 | J25: =H25*I25 -> 3336.3 | K25: =G25+J25 -> 3336.3 | M25: =M24+K25-L25 -> 23372.467
A26: 24 | B26: 46288 | G26: =E26*F26 -> 0 | J26: =H26*I26 -> 0 | K26: =G26+J26 -> 0 | M26: =M25+K26-L26 -> 23372.467
A27: 25 | B27: 46289 | G27: =E27*F27 -> 0 | J27: =H27*I27 -> 0 | K27: =G27+J27 -> 0 | M27: =M26+K27-L27 -> 23372.467
A28: 26 | B28: 46290 | G28: =E28*F28 -> 0 | H28: 30 | I28: 111.21 | J28: =H28*I28 -> 3336.3 | K28: =G28+J28 -> 3336.3 | M28: =M27+K28-L28 -> 26708.767
A29: 27 | B29: 46291 | G29: =E29*F29 -> 0 | J29: =H29*I29 -> 0 | K29: =G29+J29 -> 0 | M29: =M28+K29-L29 -> 26708.767
A30: 28 | B30: 46292 | G30: =E30*F30 -> 0 | J30: =H30*I30 -> 0 | K30: =G30+J30 -> 0 | M30: =M29+K30-L30 -> 26708.767
A31: 29 | B31: 46293 | G31: =E31*F31 -> 0 | J31: =H31*I31 -> 0 | K31: =G31+J31 -> 0 | M31: =M30+K31-L31 -> 26708.767
A32: 30 | B32: 46294 | G32: =E32*F32 -> 0 | J32: =H32*I32 -> 0 | K32: =G32+J32 -> 0 | M32: =M31+K32-L32 -> 26708.767
A33: 31 | B33: 46295 | G33: =E33*F33 -> 0 | H33: 30 | I33: 111.21 | J33: =H33*I33 -> 3336.3 | K33: =G33+J33 -> 3336.3 | M33: =M32+K33-L33 -> 30045.067
A34: 32 | G34: =E34*F34 -> 0 | J34: =H34*I34 -> 0 | K34: =G34+J34 -> 0 | M34: =M33+K34-L34 -> 30045.067
A35: 33 | G35: =E35*F35 -> 0 | J35: =H35*I35 -> 0 | K35: =G35+J35 -> 0 | M35: =M34+K35-L35 -> 30045.067
A36: 34 | G36: =E36*F36 -> 0 | J36: =H36*I36 -> 0 | K36: =G36+J36 -> 0 | M36: =M35+K36-L36 -> 30045.067
A37: 35 | G37: =E37*F37 -> 0 | J37: =H37*I37 -> 0 | K37: =G37+J37 -> 0 | M37: =M36+K37-L37 -> 30045.067
A38: 36 | G38: =E38*F38 -> 0 | J38: =H38*I38 -> 0 | K38: =G38+J38 -> 0 | M38: =M37+K38-L38 -> 30045.067
E39: =SUM(E4:E38) -> 27.13 | G39: =SUM(G4:G38) -> 2689.3969 | H39: =SUM(H4:H38) -> 240 | J39: =SUM(J4:J38) -> 26690.4 | K39: =SUM(K4:K38) -> 29379.797 | L39: =SUM(L4:L38) -> 0

Sheet Ugar,Khagwad,Kudichi
A1: Shiri Bhrhmanath Petrolium
A2: S.No | B2: Date | C2: GRN No | D2: Ind No/Bill No | E2: Diesel (Lts) | F2: Price | G2: Amount | H2: Petrol (Lts) | I2: Price | J2: Amount | K2: Total amount | L2: Amount paid | M2: As on Date | N2: Remarks
A3: Opening Balance | L3: 583834.37 | M3: 583834.37
A4: 1 | B4: 46266 | E4: 608.23 | F4: 99.74 | G4: =E4*F4 -> 60664.86 | H4: 35 | I4: 111.85 | J4: =H4*I4 -> 3914.75 | K4: =G4+J4 -> 64579.61 | M4: =M3+K4-L4 -> 648413.98
A5: 2 | B5: 46267 | E5: 230 | F5: 99.74 | G5: =E5*F5 -> 22940.2 | H5: 25 | I5: 111.85 | J5: =H5*I5 -> 2796.25 | K5: =G5+J5 -> 25736.45 | L5: 485150.72 | M5: =M4+K5-L5 -> 188999.71
A6: 3 | B6: 46268 | E6: 250 | F6: 99.74 | G6: =E6*F6 -> 24935 | J6: =H6*I6 -> 0 | K6: =G6+J6 -> 24935 | M6: =M5+K6-L6 -> 213934.71
A7: 4 | B7: 46269 | E7: 40 | F7: 99.74 | G7: =E7*F7 -> 3989.6 | H7: 35 | I7: 111.85 | J7: =H7*I7 -> 3914.75 | K7: =G7+J7 -> 7904.35 | M7: =M6+K7-L7 -> 221839.06
A8: 5 | B8: 46270 | E8: 480.24 | F8: 99.74 | G8: =E8*F8 -> 47899.138 | J8: =H8*I8 -> 0 | K8: =G8+J8 -> 47899.138 | M8: =M7+K8-L8 -> 269738.19
A9: 6 | B9: 46271 | E9: 40 | F9: 99.74 | G9: =E9*F9 -> 3989.6 | J9: =H9*I9 -> 0 | K9: =G9+J9 -> 3989.6 | M9: =M8+K9-L9 -> 273727.79
A10: 7 | B10: 46272 | G10: =E10*F10 -> 0 | H10: 5 | I10: 111.86 | J10: =H10*I10 -> 559.3 | K10: =G10+J10 -> 559.3 | M10: =M9+K10-L10 -> 274287.09
A11: 8 | B11: 46273 | E11: 465.29 | F11: 99.74 | G11: =E11*F11 -> 46408.025 | H11: 35 | I11: 111.86 | J11: =H11*I11 -> 3915.1 | K11: =G11+J11 -> 50323.125 | M11: =M10+K11-L11 -> 324610.22
A12: 9 | B12: 46274 | E12: 475 | F12: 99.74 | G12: =E12*F12 -> 47376.5 | H12: 45 | I12: 111.86 | J12: =H12*I12 -> 5033.7 | K12: =G12+J12 -> 52410.2 | M12: =M11+K12-L12 -> 377020.42
A13: 10 | B13: 46275 | E13: 40 | F13: 99.74 | G13: =E13*F13 -> 3989.6 | J13: =H13*I13 -> 0 | K13: =G13+J13 -> 3989.6 | M13: =M12+K13-L13 -> 381010.02
A14: 11 | B14: 46276 | E14: 680 | F14: 99.74 | G14: =E14*F14 -> 67823.2 | H14: 50 | I14: 111.85 | J14: =H14*I14 -> 5592.5 | K14: =G14+J14 -> 73415.7 | M14: =M13+K14-L14 -> 454425.72
A15: 12 | B15: 46277 | E15: 430 | F15: 99.74 | G15: =E15*F15 -> 42888.2 | H15: 6 | I15: 111.85 | J15: =H15*I15 -> 671.1 | K15: =G15+J15 -> 43559.3 | M15: =M14+K15-L15 -> 497985.02
A16: 13 | B16: 46278 | E16: 600 | F16: 99.74 | G16: =E16*F16 -> 59844 | H16: 35 | I16: 111.85 | J16: =H16*I16 -> 3914.75 | K16: =G16+J16 -> 63758.75 | M16: =M15+K16-L16 -> 561743.77
A17: 14 | B17: 46279 | G17: =E17*F17 -> 0 | J17: =H17*I17 -> 0 | K17: =G17+J17 -> 0 | M17: =M16+K17-L17 -> 561743.77
A18: 15 | B18: 46280 | G18: =E18*F18 -> 0 | J18: =H18*I18 -> 0 | K18: =G18+J18 -> 0 | M18: =M17+K18-L18 -> 561743.77
A19: 16 | B19: 46281 | E19: 240 | F19: 99.74 | G19: =E19*F19 -> 23937.6 | J19: =H19*I19 -> 0 | K19: =G19+J19 -> 23937.6 | M19: =M18+K19-L19 -> 585681.37
A20: 17 | B20: 46282 | G20: =E20*F20 -> 0 | J20: =H20*I20 -> 0 | K20: =G20+J20 -> 0 | M20: =M19+K20-L20 -> 585681.37
A21: 18 | B21: 46283 | E21: 475 | F21: 99.74 | G21: =E21*F21 -> 47376.5 | J21: =H21*I21 -> 0 | K21: =G21+J21 -> 47376.5 | M21: =M20+K21-L21 -> 633057.87
A22: 19 | B22: 46284 | E22: 400 | F22: 99.74 | G22: =E22*F22 -> 39896 | H22: 15 | I22: 111.85 | J22: =H22*I22 -> 1677.75 | K22: =G22+J22 -> 41573.75 | M22: =M21+K22-L22 -> 674631.62
A23: 20 | B23: 46285 | E23: 440 | F23: 99.74 | G23: =E23*F23 -> 43885.6 | H23: 40 | I23: 111.85 | J23: =H23*I23 -> 4474 | K23: =G23+J23 -> 48359.6 | M23: =M22+K23-L23 -> 722991.22
A24: 21 | B24: 46286 | G24: =E24*F24 -> 0 | J24: =H24*I24 -> 0 | K24: =G24+J24 -> 0 | L24: 0 | M24: =M23+K24-L24 -> 722991.22
A25: 22 | B25: 46287 | E25: 400 | F25: 99.74 | G25: =E25*F25 -> 39896 | J25: =H25*I25 -> 0 | K25: =G25+J25 -> 39896 | L25: 0 | M25: =M24+K25-L25 -> 762887.22
A26: 23 | B26: 46288 | G26: =E26*F26 -> 0 | J26: =H26*I26 -> 0 | K26: =G26+J26 -> 0 | L26: 628515.98 | M26: =M25+K26-L26 -> 134371.24
A27: 24 | B27: 46289 | E27: 195 | F27: 99.74 | G27: =E27*F27 -> 19449.3 | J27: =H27*I27 -> 0 | K27: =G27+J27 -> 19449.3 | L27: 0 | M27: =M26+K27-L27 -> 153820.54
A28: 25 | B28: 46290 | E28: 472.02 | F28: 99.74 | G28: =E28*F28 -> 47079.275 | H28: 35 | I28: 111.85 | J28: =H28*I28 -> 3914.75 | K28: =G28+J28 -> 50994.025 | L28: 0 | M28: =M27+K28-L28 -> 204814.56
A29: 26 | B29: 46291 | E29: 54.84 | F29: 99.74 | G29: =E29*F29 -> 5469.7416 | H29: 15 | I29: 111.85 | J29: =H29*I29 -> 1677.75 | K29: =G29+J29 -> 7147.4916 | L29: 0 | M29: =M28+K29-L29 -> 211962.05
A30: 27 | B30: 46292 | E30: 35 | F30: 99.74 | G30: =E30*F30 -> 3490.9 | J30: =H30*I30 -> 0 | K30: =G30+J30 -> 3490.9 | L30: 0 | M30: =M29+K30-L30 -> 215452.95
A31: 28 | B31: 46293 | E31: 70 | F31: 99.74 | G31: =E31*F31 -> 6981.8 | J31: =H31*I31 -> 0 | K31: =G31+J31 -> 6981.8 | L31: 0 | M31: =M30+K31-L31 -> 222434.75
A32: 29 | B32: 46294 | E32: 500 | F32: 99.74 | G32: =E32*F32 -> 49870 | H32: 35 | I32: 111.85 | J32: =H32*I32 -> 3914.75 | K32: =G32+J32 -> 53784.75 | L32: 0 | M32: =M31+K32-L32 -> 276219.5
A33: 30 | B33: 46295 | E33: 245 | F33: 99.74 | G33: =E33*F33 -> 24436.3 | J33: =H33*I33 -> 0 | K33: =G33+J33 -> 24436.3 | L33: 0 | M33: =M32+K33-L33 -> 300655.8
A34: 31 | G34: =E34*F34 -> 0 | J34: =H34*I34 -> 0 | K34: =G34+J34 -> 0 | L34: 0 | M34: =M33+K34-L34 -> 300655.8
A35: 32 | G35: =E35*F35 -> 0 | J35: =H35*I35 -> 0 | K35: =G35+J35 -> 0 | L35: 0 | M35: =M34+K35-L35 -> 300655.8
A36: 33 | G36: =E36*F36 -> 0 | J36: =H36*I36 -> 0 | K36: =G36+J36 -> 0 | L36: 0 | M36: =M35+K36-L36 -> 300655.8
E37: =SUM(E4:E36) -> 7865.62 | G37: =SUM(G4:G36) -> 784516.94 | H37: =SUM(H4:H36) -> 411 | J37: =SUM(J4:J36) -> 45971.2 | K37: =SUM(K4:K36) -> 830488.14 | L37: =SUM(L4:L36) -> 1113666.7

Sheet shedbal
A1: VARAD PETROLEUM SHEDBAL
A2: S.No | B2: Date | C2: GRN No | D2: Ind no/Bill No | E2: Diesel (Lts) | F2: Price | G2: Amount | H2: Petrol (Lts) | I2: Price | J2: Amount | K2: Total amount | L2: Amount paid | M2: As on Date | N2: Remarks
A3: Opening Balance | L3: 170641.05 | M3: 170641.05
A4: 1 | B4: 46266 | E4: 85 | F4: 99.73 | G4: =E4*F4 -> 8477.05 | J4: =H4*I4 -> 0 | K4: =G4+J4 -> 8477.05 | L4: 100000 | M4: =M3+K4-L4 -> 79118.105
A5: 2 | B5: 46267 | E5: 400 | F5: 99.73 | G5: =E5*F5 -> 39892 | J5: =H5*I5 -> 0 | K5: =G5+J5 -> 39892 | M5: =M4+K5-L5 -> 119010.1
A6: 3 | B6: 46268 | G6: =E6*F6 -> 0 | J6: =H6*I6 -> 0 | K6: =G6+J6 -> 0 | M6: =M5+K6-L6 -> 119010.1
A7: 4 | B7: 46269 | G7: =E7*F7 -> 0 | J7: =H7*I7 -> 0 | K7: =G7+J7 -> 0 | M7: =M6+K7-L7 -> 119010.1
A8: 5 | B8: 46270 | E8: 400 | F8: 99.73 | G8: =E8*F8 -> 39892 | J8: =H8*I8 -> 0 | K8: =G8+J8 -> 39892 | M8: =M7+K8-L8 -> 158902.1
A9: 6 | B9: 46271 | G9: =E9*F9 -> 0 | J9: =H9*I9 -> 0 | K9: =G9+J9 -> 0 | M9: =M8+K9-L9 -> 158902.1
A10: 7 | B10: 46272 | G10: =E10*F10 -> 0 | J10: =H10*I10 -> 0 | K10: =G10+J10 -> 0 | M10: =M9+K10-L10 -> 158902.1
A11: 8 | B11: 46273 | E11: 280 | F11: 99.73 | G11: =E11*F11 -> 27924.4 | H11: 10 | I11: 111.85 | J11: =H11*I11 -> 1118.5 | K11: =G11+J11 -> 29042.9 | M11: =M10+K11-L11 -> 187945
A12: 9 | B12: 46274 | E12: 10.14 | F12: 98.63 | G12: =E12*F12 -> 1000.1082 | J12: =H12*I12 -> 0 | K12: =G12+J12 -> 1000.1082 | L12: 1000.11 | M12: =M11+K12-L12 -> 187945
A13: 10 | B13: 46275 | G13: =E13*F13 -> 0 | J13: =H13*I13 -> 0 | K13: =G13+J13 -> 0 | M13: =M12+K13-L13 -> 187945
A14: 11 | B14: 46276 | G14: =E14*F14 -> 0 | J14: =H14*I14 -> 0 | K14: =G14+J14 -> 0 | M14: =M13+K14-L14 -> 187945
A15: 12 | B15: 46277 | G15: =E15*F15 -> 0 | J15: =H15*I15 -> 0 | K15: =G15+J15 -> 0 | M15: =M14+K15-L15 -> 187945
A16: 13 | B16: 46278 | G16: =E16*F16 -> 0 | J16: =H16*I16 -> 0 | K16: =G16+J16 -> 0 | M16: =M15+K16-L16 -> 187945
A17: 14 | B17: 46279 | G17: =E17*F17 -> 0 | J17: =H17*I17 -> 0 | K17: =G17+J17 -> 0 | M17: =M16+K17-L17 -> 187945
A18: 15 | B18: 46280 | E18: 320 | F18: 99.73 | G18: =E18*F18 -> 31913.6 | H18: 15 | I18: 111.85 | J18: =H18*I18 -> 1677.75 | K18: =G18+J18 -> 33591.35 | M18: =M17+K18-L18 -> 221536.35
A19: 16 | B19: 46281 | G19: =E19*F19 -> 0 | J19: =H19*I19 -> 0 | K19: =G19+J19 -> 0 | M19: =M18+K19-L19 -> 221536.35
A20: 17 | B20: 46282 | G20: =E20*F20 -> 0 | H20: 42 | I20: 111.85 | J20: =H20*I20 -> 4697.7 | K20: =G20+J20 -> 4697.7 | M20: =M19+K20-L20 -> 226234.05
A21: 18 | B21: 46283 | G21: =E21*F21 -> 0 | J21: =H21*I21 -> 0 | K21: =G21+J21 -> 0 | M21: =M20+K21-L21 -> 226234.05
A22: 19 | B22: 46284 | E22: 40 | F22: 99.73 | G22: =E22*F22 -> 3989.2 | J22: =H22*I22 -> 0 | K22: =G22+J22 -> 3989.2 | M22: =M21+K22-L22 -> 230223.25
A23: 20 | B23: 46285 | G23: =E23*F23 -> 0 | J23: =H23*I23 -> 0 | K23: =G23+J23 -> 0 | M23: =M22+K23-L23 -> 230223.25
A24: 21 | B24: 46286 | E24: 35 | F24: 99.73 | G24: =E24*F24 -> 3490.55 | J24: =H24*I24 -> 0 | K24: =G24+J24 -> 3490.55 | M24: =M23+K24-L24 -> 233713.8
A25: 22 | B25: 46287 | E25: 200 | F25: 99.73 | G25: =E25*F25 -> 19946 | H25: 35 | I25: 111.85 | J25: =H25*I25 -> 3914.75 | K25: =G25+J25 -> 23860.75 | M25: =M24+K25-L25 -> 257574.55
A26: 23 | B26: 46288 | E26: 25 | F26: 99.73 | G26: =E26*F26 -> 2493.25 | J26: =H26*I26 -> 0 | K26: =G26+J26 -> 2493.25 | M26: =M25+K26-L26 -> 260067.8
A27: 24 | B27: 46289 | G27: =E27*F27 -> 0 | J27: =H27*I27 -> 0 | K27: =G27+J27 -> 0 | L27: 130000 | M27: =M26+K27-L27 -> 130067.8
A28: 25 | B28: 46290 | E28: 275 | F28: 99.73 | G28: =E28*F28 -> 27425.75 | H28: 10 | I28: 111.85 | J28: =H28*I28 -> 1118.5 | K28: =G28+J28 -> 28544.25 | M28: =M27+K28-L28 -> 158612.05
A29: 26 | B29: 46291 | G29: =E29*F29 -> 0 | J29: =H29*I29 -> 0 | K29: =G29+J29 -> 0 | M29: =M28+K29-L29 -> 158612.05
A30: 27 | B30: 46292 | G30: =E30*F30 -> 0 | J30: =H30*I30 -> 0 | K30: =G30+J30 -> 0 | M30: =M29+K30-L30 -> 158612.05
A31: 28 | B31: 46293 | G31: =E31*F31 -> 0 | J31: =H31*I31 -> 0 | K31: =G31+J31 -> 0 | M31: =M30+K31-L31 -> 158612.05
B32: 46294 | G32: =E32*F32 -> 0 | K32: =G32+J32 -> 0 | M32: =M31+K32-L32 -> 158612.05
A33: 29 | B33: 46295 | G33: =E33*F33 -> 0 | J33: =H33*I33 -> 0 | K33: =G33+J33 -> 0 | M33: =M32+K33-L33 -> 158612.05
A34: 30 | G34: =E34*F34 -> 0 | J34: =H34*I34 -> 0 | K34: =G34+J34 -> 0 | M34: =M33+K34-L34 -> 158612.05
A35: 31 | G35: =E35*F35 -> 0 | J35: =H35*I35 -> 0 | K35: =G35+J35 -> 0 | M35: =M34+K35-L35 -> 158612.05
A36: 32 | G36: =E36*F36 -> 0 | J36: =H36*I36 -> 0 | K36: =G36+J36 -> 0 | M36: =M35+K36-L36 -> 158612.05
A37: 33 | G37: =E37*F37 -> 0 | J37: =H37*I37 -> 0 | K37: =G37+J37 -> 0 | M37: =M36+K37-L37 -> 158612.05
E38: =SUM(E4:E37) -> 2070.14 | G38: =SUM(G4:G37) -> 206443.91 | H38: =SUM(H4:H37) -> 112 | J38: =SUM(J4:J37) -> 12527.2 | K38: =SUM(K4:K37) -> 218971.11 | L38: =SUM(L4:L37) -> 231000.11

Sheet Kabbur
A1: Shri Jai Hanuman Petrolium
A2: S.No | B2: Date | C2: GRN No | D2: Ind no/Bill No | E2: Diesel (Lts) | F2: Price | G2: Amount | H2: Petrol (Lts) | I2: Price | J2: Amount | K2: Total amount | L2: Amount paid | M2: As on Date | N2: Remarks
A3: Opening Balance | K3: 0 | M3: =+K3 -> 0
A4: 1 | B4: 46266 | G4: =E4*F4 -> 0 | J4: =H4*I4 -> 0 | K4: =G4+J4 -> 0
A5: 2 | B5: 46267 | G5: =E5*F5 -> 0 | J5: =H5*I5 -> 0 | K5: =G5+J5 -> 0
A6: 3 | B6: 46268 | G6: =E6*F6 -> 0 | J6: =H6*I6 -> 0 | K6: =G6+J6 -> 0
A7: 4 | B7: 46269 | G7: =E7*F7 -> 0 | H7: 7.05 | I7: 111.51 | J7: =H7*I7 -> 786.1455 | K7: =G7+J7 -> 786.1455 | L7: =+K7 -> 786.1455
A8: 5 | B8: 46270 | G8: =E8*F8 -> 0 | J8: =H8*I8 -> 0 | K8: =G8+J8 -> 0 | L8: =+K8 -> 0
A9: 6 | B9: 46271 | G9: =E9*F9 -> 0 | J9: =H9*I9 -> 0 | K9: =G9+J9 -> 0 | L9: =+K9 -> 0
A10: 7 | B10: 46272 | G10: =E10*F10 -> 0 | J10: =H10*I10 -> 0 | K10: =G10+J10 -> 0 | L10: =+K10 -> 0
A11: 8 | B11: 46273 | G11: =E11*F11 -> 0 | J11: =H11*I11 -> 0 | K11: =G11+J11 -> 0 | L11: =+K11 -> 0
A12: 9 | B12: 46274 | G12: =E12*F12 -> 0 | J12: =H12*I12 -> 0 | K12: =G12+J12 -> 0 | L12: =+K12 -> 0
A13: 10 | B13: 46275 | G13: =E13*F13 -> 0 | J13: =H13*I13 -> 0 | K13: =G13+J13 -> 0 | L13: =+K13 -> 0
A14: 11 | B14: 46276 | G14: =E14*F14 -> 0 | J14: =H14*I14 -> 0 | K14: =G14+J14 -> 0 | L14: =+K14 -> 0
A15: 12 | B15: 46277 | G15: =E15*F15 -> 0 | J15: =H15*I15 -> 0 | K15: =G15+J15 -> 0 | L15: =+K15 -> 0
A16: 13 | B16: 46278 | G16: =E16*F16 -> 0 | J16: =H16*I16 -> 0 | K16: =G16+J16 -> 0 | L16: =+K16 -> 0
A17: 14 | B17: 46279 | G17: =E17*F17 -> 0 | J17: =H17*I17 -> 0 | K17: =G17+J17 -> 0 | L17: =+K17 -> 0
A18: 15 | B18: 46280 | G18: =E18*F18 -> 0 | J18: =H18*I18 -> 0 | K18: =G18+J18 -> 0 | L18: =+K18 -> 0
A19: 16 | B19: 46281 | G19: =E19*F19 -> 0 | J19: =H19*I19 -> 0 | K19: =G19+J19 -> 0 | L19: =+K19 -> 0
... A21: 18 | B21: 46283 | G21: =E21*F21 -> 0 | J21: =H21*I21 -> 0 | K21: =G21+J21 -> 0 | L21: =+K21 -> 0
A22: 19 | B22: 46284 | E22: 21.58 | F22: 99.41 | G22: =E22*F22 -> 2145.2678 | J22: =H22*I22 -> 0 | K22: =G22+J22 -> 2145.2678 | L22: =+K22 -> 2145.2678
A23: 20 | B23: 46285 | G23: =E23*F23 -> 0 | J23: =H23*I23 -> 0 | K23: =G23+J23 -> 0 | L23: =+K23 -> 0
A24: 21 | B24: 46286 | G24: =E24*F24 -> 0 | J24: =H24*I24 -> 0 | K24: =G24+J24 -> 0 | L24: =+K24 -> 0
A25: 22 | B25: 46287 | G25: =E25*F25 -> 0 | J25: =H25*I25 -> 0 | K25: =G25+J25 -> 0 | L25: =+K25 -> 0
A26: 23 | B26: 46288 | G26: =E26*F26 -> 0 | H26: 7.18 | I26: 111.51 | J26: =H26*I26 -> 800.6418 | K26: =G26+J26 -> 800.6418 | L26: =+K26 -> 800.6418
A27: 24 | B27: 46289 | G27: =E27*F27 -> 0 | J27: =H27*I27 -> 0 | K27: =G27+J27 -> 0 | L27: =+K27 -> 0
A28: 25 | B28: 46290 | G28: =E28*F28 -> 0 | J28: =H28*I28 -> 0 | K28: =G28+J28 -> 0 | L28: =+K28 -> 0
A29: 26 | B29: 46291 | G29: =E29*F29 -> 0 | J29: =H29*I29 -> 0 | K29: =G29+J29 -> 0 | L29: =+K29 -> 0
A30: 27 | B30: 46292 | G30: =E30*F30 -> 0 | J30: =H30*I30 -> 0 | K30: =G30+J30 -> 0 | L30: =+K30 -> 0
A31: 28 | B31: 46293 | G31: =E31*F31 -> 0 | J31: =H31*I31 -> 0 | K31: =G31+J31 -> 0 | L31: =+K31 -> 0
A32: 29 | B32: 46294 | G32: =E32*F32 -> 0 | J32: =H32*I32 -> 0 | K32: =G32+J32 -> 0 | L32: =+K32 -> 0
A33: 30 | B33: 46295 | G33: =E33*F33 -> 0 | J33: =H33*I33 -> 0 | K33: =G33+J33 -> 0 | L33: =+K33 -> 0
A34: 31 | G34: =E34*F34 -> 0 | J34: =H34*I34 -> 0 | K34: =G34+J34 -> 0
E35: =SUM(E4:E34) -> 21.58 | G35: =SUM(G4:G34) -> 2145.2678 | H35: =SUM(H4:H34) -> 14.23 | J35: =SUM(J4:J34) -> 1586.7873 | K35: =SUM(K4:K34) -> 3732.0551 | L35: =SUM(L4:L34) -> 3732.0551

Sheet kumta
A1: V.M.MIRJANKAR (KUMTA) BHARAT
A2: S.No | B2: Date | C2: GRN No | D2: Ind No/Bill No | E2: Diesel (Lts) | F2: Price | G2: Amount | H2: Petrol (Lts) | I2: Price | J2: Amount | K2: Total amount | L2: Amount paid | M2: As on Date | N2: Remarks
A3: Opening Balance | M3: 24092.227
A4: 1 | B4: 46266 | E4: 60 | F4: 99.78 | G4: =E4*F4 -> 5986.8 | J4: =H4*I4 -> 0 | K4: =G4+J4 -> 5986.8 | M4: =M3+K4-L4 -> 30079.027
A5: 2 | B5: 46267 | E5: 60 | F5: 99.78 | G5: =E5*F5 -> 5986.8 | J5: =H5*I5 -> 0 | K5: =G5+J5 -> 5986.8 | M5: =M4+K5-L5 -> 36065.827
A6: 3 | B6: 46268 | E6: 90 | F6: 99.78 | G6: =E6*F6 -> 8980.2 | H6: 5 | I6: 111.98 | J6: =H6*I6 -> 559.9 | K6: =G6+J6 -> 9540.1 | M6: =M5+K6-L6 -> 45605.927
A7: 4 | B7: 46269 | E7: 98 | F7: 99.78 | G7: =E7*F7 -> 9778.44 | J7: =H7*I7 -> 0 | K7: =G7+J7 -> 9778.44 | M7: =M6+K7-L7 -> 55384.367
A8: 5 | B8: 46270 | G8: =E8*F8 -> 0 | H8: 5 | I8: 111.98 | J8: =H8*I8 -> 559.9 | K8: =G8+J8 -> 559.9 | M8: =M7+K8-L8 -> 55944.267
A9: 6 | B9: 46271 | E9: 30 | F9: 99.78 | G9: =E9*F9 -> 2993.4 | H9: 10 | I9: 111.98 | J9: =H9*I9 -> 1119.8 | K9: =G9+J9 -> 4113.2 | M9: =M8+K9-L9 -> 60057.467
A10: 7 | B10: 46272 | G10: =E10*F10 -> 0 | H10: 5 | I10: 111.98 | J10: =H10*I10 -> 559.9 | K10: =G10+J10 -> 559.9 | M10: =M9+K10-L10 -> 60617.367
A11: 8 | B11: 46273 | E11: 60 | F11: 99.78 | G11: =E11*F11 -> 5986.8 | J11: =H11*I11 -> 0 | K11: =G11+J11 -> 5986.8 | M11: =M10+K11-L11 -> 66604.167
A12: 9 | B12: 46274 | G12: =E12*F12 -> 0 | H12: 5 | I12: 111.98 | J12: =H12*I12 -> 559.9 | K12: =G12+J12 -> 559.9 | M12: =M11+K12-L12 -> 67164.067
A13: 10 | B13: 46275 | G13: =E13*F13 -> 0 | J13: =H13*I13 -> 0 | K13: =G13+J13 -> 0 | M13: =M12+K13-L13 -> 67164.067
A14: 11 | B14: 46276 | E14: 100 | F14: 99.78 | G14: =E14*F14 -> 9978 | J14: =H14*I14 -> 0 | K14: =G14+J14 -> 9978 | M14: =M13+K14-L14 -> 77142.067
A15: 12 | B15: 46277 | E15: 80 | F15: 99.78 | G15: =E15*F15 -> 7982.4 | J15: =H15*I15 -> 0 | K15: =G15+J15 -> 7982.4 | M15: =M14+K15-L15 -> 85124.467
A16: 13 | B16: 46278 | E16: 60 | F16: 99.78 | G16: =E16*F16 -> 5986.8 | H16: 5 | I16: 111.98 | J16: =H16*I16 -> 559.9 | K16: =G16+J16 -> 6546.7 | M16: =M15+K16-L16 -> 91671.167
A17: 14 | B17: 46279 | G17: =E17*F17 -> 0 | J17: =H17*I17 -> 0 | K17: =G17+J17 -> 0 | M17: =M16+K17-L17 -> 91671.167
A18: 15 | B18: 46280 | G18: =E18*F18 -> 0 | J18: =H18*I18 -> 0 | K18: =G18+J18 -> 0 | M18: =M17+K18-L18 -> 91671.167
A19: 16 | B19: 46281 | E19: 50 | F19: 99.78 | G19: =E19*F19 -> 4989 | H19: 10 | I19: 111.98 | J19: =H19*I19 -> 1119.8 | K19: =G19+J19 -> 6108.8 | M19: =M18+K19-L19 -> 97779.967
A20: 17 | B20: 46282 | E20: 37 | F20: 99.78 | G20: =E20*F20 -> 3691.86 | J20: =H20*I20 -> 0 | K20: =G20+J20 -> 3691.86 | M20: =M19+K20-L20 -> 101471.83
A21: 18 | B21: 46283 | E21: 60 | F21: 99.78 | G21: =E21*F21 -> 5986.8 | J21: =H21*I21 -> 0 | K21: =G21+J21 -> 5986.8 | M21: =M20+K21-L21 -> 107458.63
A22: 19 | B22: 46284 | E22: 98 | F22: 99.78 | G22: =E22*F22 -> 9778.44 | J22: =H22*I22 -> 0 | K22: =G22+J22 -> 9778.44 | L22: 100000 | M22: =M21+K22-L22 -> 17237.067
A23: 20 | B23: 46285 | E23: 45 | F23: 99.78 | G23: =E23*F23 -> 4490.1 | J23: =H23*I23 -> 0 | K23: =G23+J23 -> 4490.1 | M23: =M22+K23-L23 -> 21727.167
A24: 21 | B24: 46286 | G24: =E24*F24 -> 0 | H24: 5 | I24: 111.98 | J24: =H24*I24 -> 559.9 | K24: =G24+J24 -> 559.9 | M24: =M23+K24-L24 -> 22287.067
A25: 22 | B25: 46287 | E25: 50 | F25: 99.78 | G25: =E25*F25 -> 4989 | H25: 10 | I25: 111.98 | J25: =H25*I25 -> 1119.8 | K25: =G25+J25 -> 6108.8 | M25: =M24+K25-L25 -> 28395.867
A26: 23 | B26: 46288 | E26: 30 | F26: 99.78 | G26: =E26*F26 -> 2993.4 | J26: =H26*I26 -> 0 | K26: =G26+J26 -> 2993.4 | M26: =M25+K26-L26 -> 31389.267 | R26: Kumta | T26: V.M.Mirjankar
A27: 24 | B27: 46289 | E27: 120 | F27: 99.78 | G27: =E27*F27 -> 11973.6 | J27: =H27*I27 -> 0 | K27: =G27+J27 -> 11973.6 | M27: =M26+K27-L27 -> 43362.867 | R27: Month | S27: Disel In Litters | T27: Petrol In Litters | U27: Amount Paid
A28: 25 | B28: 46290 | E28: 60 | F28: 99.78 | G28: =E28*F28 -> 5986.8 | H28: 10 | I28: 111.98 | J28: =H28*I28 -> 1119.8 | K28: =G28+J28 -> 7106.6 | M28: =M27+K28-L28 -> 50469.467 | R28: Feb'-26 | S28: 2040 | T28: 90 | U28: 169925
A29: 26 | B29: 46291 | E29: 75.04 | F29: 99.78 | G29: =E29*F29 -> 7487.4912 | J29: =H29*I29 -> 0 | K29: =G29+J29 -> 7487.4912 | M29: =M28+K29-L29 -> 57956.958 | R29: March'-26 | S29: 2115 | T29: 185 | U29: 206053
A30: 27 | B30: 46292 | E30: 75 | F30: 99.78 | G30: =E30*F30 -> 7483.5 | J30: =H30*I30 -> 0 | K30: =G30+J30 -> 7483.5 | M30: =M29+K30-L30 -> 65440.458 | R30: April'-26 | S30: 2145 | T30: 177 | U30: 247835
A31: 28 | B31: 46293 | E31: 35 | F31: 99.78 | G31: =E31*F31 -> 3492.3 | H31: 5 | I31: 111.98 | J31: =H31*I31 -> 559.9 | K31: =G31+J31 -> 4052.2 | M31: =M30+K31-L31 -> 69492.658 | R31: May'-26 | S31: 545 | T31: 50 | U31: 44201
A32: 29 | B32: 46294 | E32: 55 | F32: 99.78 | G32: =E32*F32 -> 5487.9 | J32: =H32*I32 -> 0 | K32: =G32+J32 -> 5487.9 | M32: =M31+K32-L32 -> 74980.558 | S32: =SUM(S28:S31) -> 6845 | T32: =SUM(T28:T31) -> 502 | U32: =SUM(U28:U31) -> 668014
A33: 30 | B33: 46295 | E33: 90 | F33: 99.78 | G33: =E33*F33 -> 8980.2 | H33: 5 | I33: 111.98 | J33: =H33*I33 -> 559.9 | K33: =G33+J33 -> 9540.1 | M33: =M32+K33-L33 -> 84520.658
A34: 31 | G34: =E34*F34 -> 0 | J34: =H34*I34 -> 0 | K34: =G34+J34 -> 0 | M34: =M33+K34-L34 -> 84520.658
A35: 32 | G35: =E35*F35 -> 0 | J35: =H35*I35 -> 0 | K35: =G35+J35 -> 0 | M35: =M34+K35-L35 -> 84520.658
A36: 33 | G36: =E36*F36 -> 0 | J36: =H36*I36 -> 0 | K36: =G36+J36 -> 0 | M36: =M35+K36-L36 -> 84520.658
A37: 34 | G37: =E37*F37 -> 0 | J37: =H37*I37 -> 0 | K37: =G37+J37 -> 0 | M37: =M36+K37-L37 -> 84520.658
A38: 35 | G38: =E38*F38 -> 0 | J38: =H38*I38 -> 0 | K38: =G38+J38 -> 0 | M38: =M37+K38-L38 -> 84520.658
A39: 36 | G39: =E39*F39 -> 0 | J39: =H39*I39 -> 0 | K39: =G39+J39 -> 0 | M39: =M38+K39-L39 -> 84520.658
A40: 37 | G40: =E40*F40 -> 0 | J40: =H40*I40 -> 0 | K40: =G40+J40 -> 0 | M40: =M39+K40-L40 -> 84520.658
E41: =SUM(E4:E40) -> 1518.04 | G41: =SUM(G4:G40) -> 151470.03 | H41: =SUM(H4:H40) -> 80 | J41: =SUM(J4:J40) -> 8958.4 | K41: =SUM(K4:K40) -> 160428.43 | L41: =SUM(L4:L40) -> 100000

Sheet Jalgoan-2
A1: Nayara
A2: S.No | B2: Date | C2: GRN No | D2: Ind No/Bill No | E2: Diesel (Lts) | F2: Price | G2: Amount | H2: Petrol (Lts) | I2: Price | J2: Amount | K2: Total amount | L2: Amount paid | M2: As on Date | N2: Remarks
A3: Opening Balance | M3: 50000.028
A4: 1 | B4: 46266 | G4: =E4*F4 -> 0 | J4: =H4*I4 -> 0 | K4: =G4+J4 -> 0 | M4: =M3+K4-L4 -> 50000.028
A5: 2 | B5: 46267 | G5: =E5*F5 -> 0 | J5: =H5*I5 -> 0 | K5: =G5+J5 -> 0 | M5: =M4+K5-L5 -> 50000.028
A6: 3 | B6: 46268 | G6: =E6*F6 -> 0 | J6: =H6*I6 -> 0 | K6: =G6+J6 -> 0 | M6: =M5+K6-L6 -> 50000.028
A7: 4 | B7: 46269 | G7: =E7*F7 -> 0 | H7: 35 | I7: 113.18 | J7: =H7*I7 -> 3961.3 | K7: =G7+J7 -> 3961.3 | M7: =M6+K7-L7 -> 53961.328
A8: 5 | B8: 46270 | G8: =E8*F8 -> 0 | J8: =H8*I8 -> 0 | K8: =G8+J8 -> 0 | M8: =M7+K8-L8 -> 53961.328
A9: 6 | B9: 46271 | E9: 2616 | F9: 99.51 | G9: =E9*F9 -> 260318.16 | H9: 35 | I9: 113.18 | J9: =H9*I9 -> 3961.3 | K9: =G9+J9 -> 264279.46 | M9: =M8+K9-L9 -> 318240.79
A10: 7 | B10: 46272 | G10: =E10*F10 -> 0 | J10: =H10*I10 -> 0 | K10: =G10+J10 -> 0 | M10: =M9+K10-L10 -> 318240.79
A11: 8 | B11: 46273 | G11: =E11*F11 -> 0 | J11: =H11*I11 -> 0 | K11: =G11+J11 -> 0 | M11: =M10+K11-L11 -> 318240.79
A12: 9 | B12: 46274 | G12: =E12*F12 -> 0 | J12: =H12*I12 -> 0 | K12: =G12+J12 -> 0 | M12: =M11+K12-L12 -> 318240.79
A13: 10 | B13: 46275 | G13: =E13*F13 -> 0 | J13: =H13*I13 -> 0 | K13: =G13+J13 -> 0 | M13: =M12+K13-L13 -> 318240.79
A14: 11 | B14: 46276 | G14: =E14*F14 -> 0 | J14: =H14*I14 -> 0 | K14: =G14+J14 -> 0 | M14: =M13+K14-L14 -> 318240.79
A15: 12 | B15: 46277 | G15: =E15*F15 -> 0 | J15: =H15*I15 -> 0 | K15: =G15+J15 -> 0 | M15: =M14+K15-L15 -> 318240.79
A16: 13 | B16: 46278 | G16: =E16*F16 -> 0 | J16: =H16*I16 -> 0 | K16: =G16+J16 -> 0 | M16: =M15+K16-L16 -> 318240.79
A17: 14 | B17: 46279 | G17: =E17*F17 -> 0 | J17: =H17*I17 -> 0 | K17: =G17+J17 -> 0 | M17: =M16+K17-L17 -> 318240.79
A18: 15 | B18: 46280 | G18: =E18*F18 -> 0 | J18: =H18*I18 -> 0 | K18: =G18+J18 -> 0 | M18: =M17+K18-L18 -> 318240.79
A19: 16 | B19: 46281 | G19: =E19*F19 -> 0 | J19: =H19*I19 -> 0 | K19: =G19+J19 -> 0 | M19: =M18+K19-L19 -> 318240.79
A20: 17 | B20: 46282 | G20: =E20*F20 -> 0 | J20: =H20*I20 -> 0 | K20: =G20+J20 -> 0 | M20: =M19+K20-L20 -> 318240.79
A21: 18 | B21: 46283 | G21: =E21*F21 -> 0 | J21: =H21*I21 -> 0 | K21: =G21+J21 -> 0 | M21: =M20+K21-L21 -> 318240.79
... A23: 20 | B23: 46285 | G23: =E23*F23 -> 0 | J23: =H23*I23 -> 0 | K23: =G23+J23 -> 0 | M23: =M22+K23-L23 -> 318240.79
A24: 21 | B24: 46286 | E24: 2815 | F24: 99.51 | G24: =E24*F24 -> 280120.65 | H24: 60 | I24: 113.18 | J24: =H24*I24 -> 6790.8 | K24: =G24+J24 -> 286911.45 | M24: =M23+K24-L24 -> 605152.24
A25: 22 | B25: 46287 | G25: =E25*F25 -> 0 | J25: =H25*I25 -> 0 | K25: =G25+J25 -> 0 | M25: =M24+K25-L25 -> 605152.24
A26: 23 | B26: 46288 | G26: =E26*F26 -> 0 | J26: =H26*I26 -> 0 | K26: =G26+J26 -> 0 | M26: =M25+K26-L26 -> 605152.24
A27: 24 | B27: 46289 | G27: =E27*F27 -> 0 | J27: =H27*I27 -> 0 | K27: =G27+J27 -> 0 | M27: =M26+K27-L27 -> 605152.24
A28: 25 | B28: 46290 | G28: =E28*F28 -> 0 | J28: =H28*I28 -> 0 | K28: =G28+J28 -> 0 | M28: =M27+K28-L28 -> 605152.24
A29: 26 | B29: 46291 | G29: =E29*F29 -> 0 | J29: =H29*I29 -> 0 | K29: =G29+J29 -> 0 | M29: =M28+K29-L29 -> 605152.24
A30: 27 | B30: 46292 | G30: =E30*F30 -> 0 | J30: =H30*I30 -> 0 | K30: =G30+J30 -> 0 | M30: =M29+K30-L30 -> 605152.24
A31: 28 | B31: 46293 | G31: =E31*F31 -> 0 | J31: =H31*I31 -> 0 | K31: =G31+J31 -> 0 | M31: =M30+K31-L31 -> 605152.24
A32: 29 | B32: 46294 | G32: =E32*F32 -> 0 | J32: =H32*I32 -> 0 | K32: =G32+J32 -> 0 | M32: =M31+K32-L32 -> 605152.24
A33: 30 | B33: 46295 | G33: =E33*F33 -> 0 | J33: =H33*I33 -> 0 | K33: =G33+J33 -> 0 | M33: =M32+K33-L33 -> 605152.24
A34: 31 | G34: =E34*F34 -> 0 | J34: =H34*I34 -> 0 | K34: =G34+J34 -> 0 | M34: =M33+K34-L34 -> 605152.24
A35: 32 | G35: =E35*F35 -> 0 | J35: =H35*I35 -> 0 | K35: =G35+J35 -> 0 | M35: =M34+K35-L35 -> 605152.24
A36: 33 | G36: =E36*F36 -> 0 | J36: =H36*I36 -> 0 | K36: =G36+J36 -> 0 | M36: =M35+K36-L36 -> 605152.24
A37: 34 | G37: =E37*F37 -> 0 | J37: =H37*I37 -> 0 | K37: =G37+J37 -> 0 | M37: =M36+K37-L37 -> 605152.24
A38: 35 | G38: =E38*F38 -> 0 | J38: =H38*I38 -> 0 | K38: =G38+J38 -> 0 | M38: =M37+K38-L38 -> 605152.24
A39: 36 | G39: =E39*F39 -> 0 | J39: =H39*I39 -> 0 | K39: =G39+J39 -> 0 | M39: =M38+K39-L39 -> 605152.24 | P39: 41
A40: 37 | G40: =E40*F40 -> 0 | J40: =H40*I40 -> 0 | K40: =G40+J40 -> 0 | M40: =M39+K40-L40 -> 605152.24 | P40: 40 | Q40: 5
A41: 38 | G41: =E41*F41 -> 0 | J41: =H41*I41 -> 0 | K41: =G41+J41 -> 0 | M41: =M40+K41-L41 -> 605152.24
A42: 39 | G42: =E42*F42 -> 0 | J42: =H42*I42 -> 0 | K42: =G42+J42 -> 0 | M42: =M41+K42-L42 -> 605152.24
A43: 40 | G43: =E43*F43 -> 0 | J43: =H43*I43 -> 0 | K43: =G43+J43 -> 0 | M43: =M42+K43-L43 -> 605152.24
A44: 41 | G44: =E44*F44 -> 0 | J44: =H44*I44 -> 0 | K44: =G44+J44 -> 0 | M44: =M43+K44-L44 -> 605152.24
A45: 42 | G45: =E45*F45 -> 0 | J45: =H45*I45 -> 0 | K45: =G45+J45 -> 0 | M45: =M44+K45-L45 -> 605152.24
A46: 43 | G46: =E46*F46 -> 0 | J46: =H46*I46 -> 0 | K46: =G46+J46 -> 0 | M46: =M45+K46-L46 -> 605152.24
A47: 44 | G47: =E47*F47 -> 0 | J47: =H47*I47 -> 0 | K47: =G47+J47 -> 0 | M47: =M46+K47-L47 -> 605152.24
A48: 45 | G48: =E48*F48 -> 0 | J48: =H48*I48 -> 0 | K48: =G48+J48 -> 0 | M48: =M47+K48-L48 -> 605152.24
A49: 46 | G49: =E49*F49 -> 0 | J49: =H49*I49 -> 0 | K49: =G49+J49 -> 0 | M49: =M48+K49-L49 -> 605152.24
A50: 47 | G50: =E50*F50 -> 0 | J50: =H50*I50 -> 0 | K50: =G50+J50 -> 0 | M50: =M49+K50-L50 -> 605152.24
A51: 48 | G51: =E51*F51 -> 0 | J51: =H51*I51 -> 0 | K51: =G51+J51 -> 0 | M51: =M50+K51-L51 -> 605152.24
A52: 49 | G52: =E52*F52 -> 0 | J52: =H52*I52 -> 0 | K52: =G52+J52 -> 0 | M52: =M51+K52-L52 -> 605152.24
... A55: 51 | G55: =E55*F55 -> 0 | J55: =H55*I55 -> 0 | K55: =G55+J55 -> 0 | M55: =M54+K55-L55 -> 605152.24
E56: =SUM(E4:E55) -> 5431 | G56: =SUM(G4:G55) -> 540438.81 | H56: =SUM(H4:H55) -> 130 | J56: =SUM(J4:J55) -> 14713.4 | K56: =SUM(K4:K55) -> 555152.21 | L56: =SUM(L4:L55) -> 0

Sheet MKBD
A1: Shree Sai Samarth Petroleum
A2: S.No | B2: Date | C2: GRN No | D2: Ind No/Bill No | E2: Diesel (Lts) | F2: Price | G2: Amount | H2: Petrol (Lts) | I2: Price | J2: Amount | K2: Total amount | L2: Amount paid | M2: As on Date | N2: Remarks
A3: Opening Balance | K3: 90567.01 | M3: 90567.01
A4: 1 | B4: 46266 | G4: =E4*F4 -> 0 | J4: =H4*I4 -> 0 | K4: =G4+J4 -> 0 | M4: =M3+K4-L4 -> 90567.01
A5: 2 | B5: 46267 | G5: =E5*F5 -> 0 | J5: =H5*I5 -> 0 | K5: =G5+J5 -> 0 | M5: =M4+K5-L5 -> 90567.01
A6: 3 | B6: 46268 | G6: =E6*F6 -> 0 | J6: =H6*I6 -> 0 | K6: =G6+J6 -> 0 | M6: =M5+K6-L6 -> 90567.01
A7: 3 | B7: 46269 | G7: =E7*F7 -> 0 | J7: =H7*I7 -> 0 | K7: =G7+J7 -> 0 | M7: =M6+K7-L7 -> 90567.01
A8: 4 | B8: 46270 | G8: =E8*F8 -> 0 | H8: 10 | I8: 112.27 | J8: =H8*I8 -> 1122.7 | K8: =G8+J8 -> 1122.7 | M8: =M7+K8-L8 -> 91689.71
A9: 5 | B9: 46271 | G9: =E9*F9 -> 0 | J9: 0 | K9: =G9+J9 -> 0 | M9: =M8+K9-L9 -> 91689.71
A10: 6 | B10: 46272 | G10: =E10*F10 -> 0 | J10: =H10*I10 -> 0 | K10: =G10+J10 -> 0 | M10: =M9+K10-L10 -> 91689.71
A11: 7 | B11: 46273 | G11: =E11*F11 -> 0 | J11: =H11*I11 -> 0 | K11: =G11+J11 -> 0 | M11: =M10+K11-L11 -> 91689.71
A12: 8 | B12: 46274 | G12: =E12*F12 -> 0 | J12: =H12*I12 -> 0 | K12: =G12+J12 -> 0 | M12: =M11+K12-L12 -> 91689.71
A13: 9 | B13: 46275 | G13: =E13*F13 -> 0 | J13: =H13*I13 -> 0 | K13: =G13+J13 -> 0 | M13: =M12+K13-L13 -> 91689.71
A14: 10 | B14: 46276 | G14: =E14*F14 -> 0 | J14: =H14*I14 -> 0 | K14: =G14+J14 -> 0 | M14: =M13+K14-L14 -> 91689.71
A15: 11 | B15: 46277 | G15: =E15*F15 -> 0 | J15: =H15*I15 -> 0 | K15: =G15+J15 -> 0 | M15: =M14+K15-L15 -> 91689.71
A16: 12 | B16: 46278 | G16: =E16*F16 -> 0 | J16: =H16*I16 -> 0 | K16: =G16+J16 -> 0 | M16: =M15+K16-L16 -> 91689.71
A17: 13 | B17: 46279 | G17: =E17*F17 -> 0 | J17: =H17*I17 -> 0 | K17: =G17+J17 -> 0 | M17: =M16+K17-L17 -> 91689.71
A18: 14 | B18: 46280 | G18: =E18*F18 -> 0 | J18: =H18*I18 -> 0 | K18: =G18+J18 -> 0 | M18: =M17+K18-L18 -> 91689.71
A19: 15 | B19: 46281 | G19: =E19*F19 -> 0 | J19: =H19*I19 -> 0 | K19: =G19+J19 -> 0 | M19: =M18+K19-L19 -> 91689.71
A20: 16 | B20: 46282 | G20: =E20*F20 -> 0 | J20: =H20*I20 -> 0 | K20: =G20+J20 -> 0 | M20: =M19+K20-L20 -> 91689.71
A21: 17 | B21: 46283 | G21: =E21*F21 -> 0 | H21: 20 | I21: 112.27 | J21: =H21*I21 -> 2245.4 | K21: =G21+J21 -> 2245.4 | M21: =M20+K21-L21 -> 93935.11
A22: 18 | B22: 46284 | G22: =E22*F22 -> 0 | J22: =H22*I22 -> 0 | K22: =G22+J22 -> 0 | M22: =M21+K22-L22 -> 93935.11
A23: 19 | B23: 46285 | G23: =E23*F23 -> 0 | J23: =H23*I23 -> 0 | K23: =G23+J23 -> 0 | M23: =M22+K23-L23 -> 93935.11
A24: 20 | B24: 46286 | G24: =E24*F24 -> 0 | J24: =H24*I24 -> 0 | K24: =G24+J24 -> 0 | M24: =M23+K24-L24 -> 93935.11
A25: 21 | B25: 46287 | G25: =E25*F25 -> 0 | J25: =H25*I25 -> 0 | K25: =G25+J25 -> 0 | M25: =M24+K25-L25 -> 93935.11
A26: 22 | B26: 46288 | E26: 500 | F26: 98.94 | G26: =E26*F26 -> 49470 | H26: 10 | I26: 112.27 | J26: =H26*I26 -> 1122.7 | K26: =G26+J26 -> 50592.7 | M26: =M25+K26-L26 -> 144527.81
A27: 23 | B27: 46289 | E27: 2000 | F27: 98.94 | G27: =E27*F27 -> 197880 | J27: =H27*I27 -> 0 | K27: =G27+J27 -> 197880 | M27: =M26+K27-L27 -> 342407.81
A28: 24 | B28: 46290 | G28: =E28*F28 -> 0 | J28: =H28*I28 -> 0 | K28: =G28+J28 -> 0 | M28: =M27+K28-L28 -> 342407.81
A29: 25 | B29: 46291 | G29: =E29*F29 -> 0 | J29: =H29*I29 -> 0 | K29: =G29+J29 -> 0 | M29: =M28+K29-L29 -> 342407.81
A30: 26 | B30: 46292 | G30: =E30*F30 -> 0 | J30: =H30*I30 -> 0 | K30: =G30+J30 -> 0 | M30: =M29+K30-L30 -> 342407.81
A31: 27 | B31: 46293 | G31: =E31*F31 -> 0 | J31: =H31*I31 -> 0 | K31: =G31+J31 -> 0 | M31: =M30+K31-L31 -> 342407.81
A32: 28 | B32: 46294 | G32: =E32*F32 -> 0 | J32: =H32*I32 -> 0 | K32: =G32+J32 -> 0 | M32: =M31+K32-L32 -> 342407.81
A33: 29 | B33: 46295 | G33: =E33*F33 -> 0 | J33: =H33*I33 -> 0 | K33: =G33+J33 -> 0 | M33: =M32+K33-L33 -> 342407.81
A34: 30 | G34: =E34*F34 -> 0 | J34: =H34*I34 -> 0 | K34: =G34+J34 -> 0 | M34: =M33+K34-L34 -> 342407.81
A35: 31 | G35: =E35*F35 -> 0 | J35: =H35*I35 -> 0 | K35: =G35+J35 -> 0 | M35: =M34+K35-L35 -> 342407.81
A36: 32 | G36: =E36*F36 -> 0 | J36: =H36*I36 -> 0 | K36: =G36+J36 -> 0 | M36: =M35+K36-L36 -> 342407.81
A37: 33 | G37: =E37*F37 -> 0 | J37: 0 | K37: =G37+J37 -> 0 | M37: =M36+K37-L37 -> 342407.81
A38: 34 | G38: 0 | J38: 0 | K38: =G38+J38 -> 0 | M38: =M37+K38-L38 -> 342407.81
A39: 35 | G39: =E39*F39 -> 0 | J39: =H39*I39 -> 0 | K39: =G39+J39 -> 0 | M39: =M38+K39-L39 -> 342407.81
A40: 36 | G40: =E40*F40 -> 0 | J40: =H40*I40 -> 0 | K40: =G40+J40 -> 0 | M40: =M39+K40-L40 -> 342407.81
A41: 37 | E41: 0 | F41: 0 | G41: =E41*F41 -> 0 | J41: =H41*I41 -> 0 | K41: =G41+J41 -> 0 | M41: =M40+K41-L41 -> 342407.81
E42: =SUM(E4:E41) -> 2500 | G42: =SUM(G4:G41) -> 247350 | H42: =SUM(H4:H41) -> 40 | J42: =SUM(J4:J41) -> 4490.8 | K42: =SUM(K4:K41) -> 251840.8 | L42: =SUM(L4:L41) -> 0

Sheet  Haveri-2
A1: Magavi fuel F/S
A2: S.No | B2: Date | C2: GRN No | D2: Ind No/Bill No | E2: Diesel (Lts) | F2: Price | G2: Amount | H2: Petrol (Lts) | I2: Price | J2: Amount | K2: Total amount | L2: Amount paid | M2: As on Date | N2: Remarks
D3: Opening Balance | K3: 41052.548 | M3: 41052.548
A4: 1 | B4: 46266 | G4: =E4*F4 -> 0 | H4: 10 | I4: 111.4 | J4: =H4*I4 -> 1114 | K4: =G4+J4 -> 1114 | M4: =M3+K4-L4 -> 42166.548
A5: 2 | B5: 46267 | E5: 179.37 | F5: 99.3 | G5: =E5*F5 -> 17811.441 | J5: =H5*I5 -> 0 | K5: =G5+J5 -> 17811.441 | M5: =M4+K5-L5 -> 59977.989
A6: 3 | B6: 46268 | E6: 35 | F6: 99.3 | G6: =E6*F6 -> 3475.5 | H6: 11.6 | I6: 111.4 | J6: =H6*I6 -> 1292.24 | K6: =G6+J6 -> 4767.74 | M6: =M5+K6-L6 -> 64745.729
A7: 4 | B7: 46269 | E7: 233 | F7: 99.3 | G7: =E7*F7 -> 23136.9 | H7: 11 | I7: 111.4 | J7: =H7*I7 -> 1225.4 | K7: =G7+J7 -> 24362.3 | M7: =M6+K7-L7 -> 89108.029
A8: 5 | B8: 46270 | E8: 415 | F8: 99.3 | G8: =E8*F8 -> 41209.5 | H8: 22 | I8: 111.4 | J8: =H8*I8 -> 2450.8 | K8: =G8+J8 -> 43660.3 | M8: =M7+K8-L8 -> 132768.33
A9: 6 | B9: 46271 | E9: 80 | F9: 99.3 | G9: =E9*F9 -> 7944 | J9: =H9*I9 -> 0 | K9: =G9+J9 -> 7944 | M9: =M8+K9-L9 -> 140712.33
A10: 7 | B10: 46272 | E10: 43.8 | F10: 99.3 | G10: =E10*F10 -> 4349.34 | H10: 7 | I10: 111.4 | J10: =H10*I10 -> 779.8 | K10: =G10+J10 -> 5129.14 | M10: =M9+K10-L10 -> 145841.47
A11: 8 | B11: 46273 | E11: 60 | F11: 99.3 | G11: =E11*F11 -> 5958 | J11: =H11*I11 -> 0 | K11: =G11+J11 -> 5958 | M11: =M10+K11-L11 -> 151799.47
A12: 9 | B12: 46274 | E12: 420 | F12: 99.3 | G12: =E12*F12 -> 41706 | J12: =H12*I12 -> 0 | K12: =G12+J12 -> 41706 | M12: =M11+K12-L12 -> 193505.47 | O12: .
A13: 10 | B13: 46275 | E13: 344 | F13: 99.3 | G13: =E13*F13 -> 34159.2 | H13: 6.7 | I13: 111.4 | J13: =H13*I13 -> 746.38 | K13: =G13+J13 -> 34905.58 | M13: =M12+K13-L13 -> 228411.05
A14: 11 | B14: 46276 | G14: =E14*F14 -> 0 | J14: =H14*I14 -> 0 | K14: =G14+J14 -> 0 | M14: =M13+K14-L14 -> 228411.05
A15: 12 | B15: 46277 | E15: 131.72 | F15: 99.3 | G15: =E15*F15 -> 13079.796 | J15: =H15*I15 -> 0 | K15: =G15+J15 -> 13079.796 | M15: =M14+K15-L15 -> 241490.85
A16: 13 | B16: 46278 | G16: =E16*F16 -> 0 | J16: =H16*I16 -> 0 | K16: =G16+J16 -> 0 | M16: =M15+K16-L16 -> 241490.85
A17: 14 | B17: 46279 | G17: =E17*F17 -> 0 | J17: =H17*I17 -> 0 | K17: =G17+J17 -> 0 | M17: =M16+K17-L17 -> 241490.85
A18: 15 | B18: 46280 | E18: 171 | F18: 99.3 | G18: =E18*F18 -> 16980.3 | H18: 8 | I18: 111.4 | J18: =H18*I18 -> 891.2 | K18: =G18+J18 -> 17871.5 | M18: =M17+K18-L18 -> 259362.35
A19: 16 | B19: 46281 | E19: 246.7 | F19: 99.3 | G19: =E19*F19 -> 24497.31 | J19: =H19*I19 -> 0 | K19: =G19+J19 -> 24497.31 | M19: =M18+K19-L19 -> 283859.66
A20: 17 | B20: 46282 | E20: 100 | F20: 99.3 | G20: =E20*F20 -> 9930 | H20: 6 | I20: 111.4 | J20: =H20*I20 -> 668.4 | K20: =G20+J20 -> 10598.4 | M20: =M19+K20-L20 -> 294458.06
