Workbook

Sheet Jan-26
A1: S.no | B1: Site Name | C1: Bunk Name | D1: Diesel(Liters) | E1: Diesel Amount | F1: Petrol(Liters) | G1: Petrol Amount | H1: Total Amount | I1: Opening Blance | J1: Amount Paid | K1: Closing Balances
A2: 1 | B2: Khammam-1 | C2: Divya laxmi ganapathi | D2: =+'Khammam-1'!E38 -> 55934.28 | E2: =+'Khammam-1'!G38 -> 5351791.9 | F2: =+'Khammam-1'!H38 -> 295 | G2: =+'Khammam-1'!J38 -> 31700.7 | H2: =E2+G2 -> 5383492.6 | I2: =+'Khammam-1'!K3 -> 3956161.3 | J2: =+'Khammam-1'!L38 -> 6503593 | K2: =H2+I2-J2 -> 2836061
A3: 2 | B3: Khammam-2 | C3: Jayasai union bunk | D3: =+'Khammam-2'!E36 -> 62644.369 | E3: =+'Khammam-2'!G36 -> 5995066.1 | F3: =+'Khammam-2'!H36 -> 816.52 | G3: =+'Khammam-2'!J36 -> 87759.57 | H3: =E3+G3 -> 6082825.7 | I3: =+'Khammam-2'!K3 -> 3669815.6 | J3: =+'Khammam-2'!L36 -> 5316864.5 | K3: =H3+I3-J3 -> 4435776.8
A4: 3 | B4: Khammam-3 | C4: JSASFuel Genie India Pvt.Ltd | D4: =+'Khammam-3'!E35 -> 12000 | E4: =+'Khammam-3'!G35 -> 1136400 | F4: =+'Khammam-3'!H35 -> 0 | G4: =+'Khammam-3'!J35 -> 0 | H4: =E4+G4 -> 1136400 | I4: =+'Khammam-3'!M3 -> 0 | J4: =+'Khammam-3'!L35 -> 1016000 | K4: =H4+I4-J4 -> 120400
A5: 4 | B5: Jadcherla-3 | C5: JSASFuel Genie India Pvt.Ltd | D5: =+'Jadcherla-3'!E35 -> 7500 | E5: =+'Jadcherla-3'!G35 -> 715725 | F5: =+'Jadcherla-3'!H35 -> 0 | G5: =+'Jadcherla-3'!J35 -> 0 | H5: =E5+G5 -> 715725 | I5: =+'Jadcherla-3'!M3 -> 1183331.5 | J5: =+'Jadcherla-3'!L35 -> 1600000 | K5: =H5+I5-J5 -> 299056.5
A6: 5 | B6: Jadcherla-4 | C6: Shree Poornima F/S | D6: =+'Jadcherla-4'!E35 -> 0 | E6: =+'Jadcherla-4'!G35 -> 0 | F6: =+'Jadcherla-4'!H35 -> 150 | G6: =+'Jadcherla-4'!J35 -> 16215 | H6: =E6+G6 -> 16215 | I6: =+'Jadcherla-4'!M3 -> 5405 | J6: =+'Jadcherla-4'!L35 -> 16215 | K6: =H6+I6-J6 -> 5405
A7: 6 | B7: Dindi | C7: Akarapu Balakistamma Fillling | D7: =+Dindi!E35 -> 36.13 | E7: =+Dindi!G35 -> 3498.4679 | F7: =+Dindi!H35 -> 0 | G7: =+Dindi!J35 -> 0 | H7: =E7+G7 -> 3498.4679 | I7: =+Dindi!M3 -> 0 | J7: =+Dindi!L35 -> 3498.4679 | K7: =H7+I7-J7 -> 0
A8: 7 | B8: Devarkhadra-1 | C8: Kurumurthy Swami F/S | D8: =+Devarakhadra!E35 -> 90 | E8: =+Devarakhadra!G35 -> 8739 | F8: =+Devarakhadra!H35 -> 42.58 | G8: =+Devarakhadra!J35 -> 4633.9814 | H8: =E8+G8 -> 13372.981 | I8: =+Devarakhadra!M3 -> 5026.311 | J8: =+Devarakhadra!L35 -> 12543 | K8: =H8+I8-J8 -> 5856.2924
A9: 8 | B9: Devarkhadra-3 | C9: JSASFuel Genie India Pvt.Ltd | D9: =+'Devarakhadra-2'!E35 -> 0 | E9: =+'Devarakhadra-2'!G35 -> 0 | F9: =+'Devarakhadra-2'!H35 -> 0 | G9: =+'Devarakhadra-2'!I35 -> 0 | H9: =E9+G9 -> 0 | I9: =+'Devarakhadra-2'!M3 -> 0 | J9: =+'Devarakhadra-2'!L35 -> 0 | K9: =+'Devarakhadra-2'!M34 -> 0
A10: 9 | B10: Madanapalli | D10: =+'Madana palli'!E35 -> 20.52 | E10: =+'Madana palli'!G35 -> 1999.2636 | F10: =+'Madana palli'!H35 -> 16.92 | G10: =+'Madana palli'!J35 -> 1854.6012 | H10: =E10+G10 -> 3853.8648 | I10: =+'Madana palli'!M3 -> 0 | J10: =+'Madana palli'!L35 -> 3853.8648 | K10: =+'Devarakhadra-2'!M35 -> 0
A11: 10 | B11: Amalapuram | C11: Sathya Filling Station | D11: =+Amalapuram!E38 -> 284.37 | E11: =+Amalapuram!G38 -> 26054.425 | F11: =+Amalapuram!H38 -> 67.52 | G11: =+Amalapuram!J38 -> 6736.69 | H11: =E11+G11 -> 32791.115 | I11: =+Amalapuram!M3 -> 0 | J11: =+Amalapuram!L38 -> 32791.44 | K11: =H11+I11-J11 -> -0.325
A12: 11 | B12: YG Gudda-1 | C12: Pallavi Petrolium | D12: =+'YG Gudda '!E36 -> 0 | E12: =+'YG Gudda '!G36 -> 0 | F12: =+'YG Gudda '!H36 -> 0 | G12: =+'YG Gudda '!J36 -> 0 | H12: =E12+G12 -> 0 | I12: ='YG Gudda '!K3 -> 21.541514 | J12: =+'YG Gudda '!L36 -> 21.54 | K12: =H12+I12-J12 -> 0.0015138002
A13: 12 | B13: YG Gudda-2 | C13: Pankaja HP Fuel Center | D13: =+'YG Gudda-2'!E36 -> 9620 | E13: =+'YG Gudda-2'!G36 -> 878594.6 | F13: =+'YG Gudda-2'!H36 -> 365 | G13: =+'YG Gudda-2'!J36 -> 37693.55 | H13: =E13+G13 -> 916288.15 | I13: =+'YG Gudda-2'!M3 -> 713890.2 | J13: =+'YG Gudda-2'!L36 -> 1151841.5 | K13: =H13+I13-J13 -> 478336.85
A14: 13 | B14: Hosadurga-1 | C14: Merchant Petroliums | D14: =+Hosadurga!E35 -> 0 | E14: =+Hosadurga!G35 -> 0 | F14: =+Hosadurga!H35 -> 0 | G14: =+Hosadurga!J35 -> 0 | H14: =E14+G14 -> 0 | I14: =+Hosadurga!K3 -> 2258.6 | J14: =+Hosadurga!L35 -> 0 | K14: =H14+I14-J14 -> 2258.6
A15: 14 | B15: Hosadurga-2 | C15: Shree Veeraprathap Fuel | D15: =+'Hosadurga -2'!E35 -> 6000 | E15: =+'Hosadurga -2'!G35 -> 549300 | F15: =+'Hosadurga -2'!H35 -> 280 | G15: =+'Hosadurga -2'!J35 -> 29044.4 | H15: =+'Hosadurga -2'!K35 -> 578344.4 | I15: =+'Hosadurga -2'!K3 -> 197553.8 | J15: =+'Hosadurga -2'!L35 -> 450000 | K15: =H15+I15-J15 -> 325898.2
A16: 15 | B16: Malebennuru(KUWSDB) | C16: Sri Ramanjuneya Service Station | D16: =+'Malebenur(KUWSDB)'!E37 -> 5549.91 | E16: =+'Malebenur(KUWSDB)'!G37 -> 511543.2 | F16: =+'Malebenur(KUWSDB)'!H37 -> 214 | G16: =+'Malebenur(KUWSDB)'!J37 -> 22263.12 | H16: =E16+G16 -> 533806.32 | I16: =+'Malebenur(KUWSDB)'!K3 -> 202357.36 | J16: =+'Malebenur(KUWSDB)'!L37 -> 522465.12 | K16: =H16+I16-J16 -> 213698.56
A17: 16 | B17: kadur | C17: Vishal Service Station | D17: =+Kadur!E35 -> 0 | E17: =+Kadur!G35 -> 0 | F17: =+Kadur!H35 -> 140 | G17: =+Kadur!J35 -> 14597.8 | H17: =E17+G17 -> 14597.8 | I17: =+Kadur!K3 -> 210029.23 | J17: =+Kadur!L35 -> 210000 | K17: =H17+I17-J17 -> 14627.031
A18: 17 | B18: Hiriyur(VJNL) | C18: Sri Balaji Agencies | D18: =+'Hiriyur(VJNL)'!E35 -> 2300 | E18: =+'Hiriyur(VJNL)'!G35 -> 212198 | F18: =+'Hiriyur(VJNL)'!H35 -> 210 | G18: =+'Hiriyur(VJNL)'!J35 -> 21867.3 | H18: =E18+G18 -> 234065.3 | I18: =+'Hiriyur(VJNL)'!K3 -> 438828.8 | J18: =+'Hiriyur(VJNL)'!L35 -> 453408 | K18: =H18+I18-J18 -> 219486.1
A19: 18 | B19: Chellakere(KUWSDB) | C19: Shivaganga Service Station | D19: =+'Chellakere -1'!E35 -> 3800 | E19: =+'Chellakere -1'!G35 -> 350474 | F19: =+'Chellakere -1'!H35 -> 230.04 | G19: =+'Chellakere -1'!J35 -> 23944.864 | H19: =E19+G19 -> 374418.86 | I19: =+'Chellakere -1'!K3 -> 145403.1 | J19: =+'Chellakere -1'!L35 -> 358717 | K19: =H19+I19-J19 -> 161104.96
A20: 19 | B20: Chellakere(KUWSDB)-09 | D20: =+' Chellakere-PKG-9'!E35 -> 509.99 | E20: =+' Chellakere-PKG-9'!G35 -> 47036.378 | F20: =+' Chellakere-PKG-9'!H35 -> 33.08 | G20: =+' Chellakere-PKG-9'!J35 -> 3442.9972 | H20: =E20+G20 -> 50479.375 | I20: =+' Chellakere-PKG-9'!M3 -> 0 | J20: =+' Chellakere-PKG-9'!L35 -> 50479.375 | K20: =H20+I20-J20 -> 0
A21: 20 | B21: Molakalmuru | C21: Sri Lakshmi Venkateshwara Filling Station | D21: =+Molakamuru!E35 -> 1045 | E21: =+Molakamuru!G35 -> 96369.9 | F21: =+Molakamuru!H35 -> 49.69 | G21: =+Molakamuru!J35 -> 5171.7352 | H21: =E21+G21 -> 101541.64 | I21: =+Molakamuru!K3 -> 53588.5 | J21: =+Molakamuru!L35 -> 127139.54 | K21: =H21+I21-J21 -> 27990.595
A22: 21 | B22: Chennagiri | D22: =+' Chennagiri'!E35 -> 625.92 | E22: =+' Chennagiri'!G35 -> 57616.109 | F22: =+' Chennagiri'!H35 -> 31 | G22: =+' Chennagiri'!J35 -> 3226.48 | H22: =E22+G22 -> 60842.589 | I22: =+' Chennagiri'!K3 -> 0 | J22: =+' Chennagiri'!L35 -> 60842.589 | K22: =H22+I22-J22 -> 0
A23: 22 | B23: Khanapur(PKG-3) | C23: V.V.Varde | D23: =+Khanapur!E35 -> 1989.96 | E23: =+Khanapur!G35 -> 180847.56 | F23: =+Khanapur!H35 -> 84 | G23: =+Khanapur!J35 -> 8632.68 | H23: =E23+G23 -> 189480.24 | I23: =+Khanapur!M3 -> 98982.5 | J23: =+Khanapur!L35 -> 184520 | K23: =H23+I23-J23 -> 103942.75
A24: 23 | B24: Munavalli(PKG-3)-1 | C24: Shri Daneshwari | D24: =+Munavali!E37 -> 135 | E24: =+Munavali!G37 -> 12328.2 | F24: =+Munavali!H37 -> 37 | G24: =+Munavali!J37 -> 3819.88 | H24: =E24+G24 -> 16148.08 | I24: =+Munavali!M3 -> 660530.8 | J24: =+Munavali!L37 -> 676678.88 | K24: =H24+I24-J24 -> 0.0019999997
A25: 24 | B25: Munavalli(PKG-3)-2 | D25: =+'Munavali-2'!E37 -> 6730 | E25: =+'Munavali-2'!G37 -> 616064.2 | F25: =+'Munavali-2'!H37 -> 201 | G25: =+'Munavali-2'!J37 -> 20799.48 | H25: =E25+G25 -> 636863.68 | I25: =+'Munavali-2'!M3 -> 0 | J25: =+'Munavali-2'!L37 -> 293246 | K25: =H25+I25-J25 -> 343617.68
A26: 25 | B26: Borgaon(PKG-3) | C26: Aadisagar Petrolium | D26: =+Borgaon!E35 -> 4415 | E26: =+Borgaon!G35 -> 405164.55 | F26: =+Borgaon!H35 -> 94 | G26: =+Borgaon!J35 -> 9750.62 | H26: =E26+G26 -> 414915.17 | I26: =+Borgaon!K3 -> 120395.81 | J26: =+Borgaon!L35 -> 420000 | K26: =H26+I26-J26 -> 115310.98
A27: 26 | B27: Ugar,Kudichi(PKG-3) | C27: Shiri Bhrhmanath Petrolium | D27: =+'Ugar,Khagwad,Kudichi'!E35 -> 3546.78 | E27: =+'Ugar,Khagwad,Kudichi'!G35 -> 326055.49 | F27: =+'Ugar,Khagwad,Kudichi'!H35 -> 280 | G27: =+'Ugar,Khagwad,Kudichi'!J35 -> 29089.2 | H27: =E27+G27 -> 355144.69 | I27: =+'Ugar,Khagwad,Kudichi'!M3 -> 292365.86 | J27: =+'Ugar,Khagwad,Kudichi'!L35 -> 496000 | K27: =H27+I27-J27 -> 151510.55
A28: 27 | B28: Kabbur(PKG-3) | C28: Shri Jai Hanuman Petrolium | D28: =+Kabbur!E35 -> 103 | E28: =+Kabbur!G35 -> 9433.77 | F28: =+Kabbur!H35 -> 32.8 | G28: =+Kabbur!J35 -> 3395.784 | H28: =E28+G28 -> 12829.554 | I28: 0 | J28: =+Kabbur!L35 -> 12829.554 | K28: =H28+I28-J28 -> 0
A29: 28 | B29: Kumta (PKG-1) | C29: Krishma fuel station | D29: =+kumta!E35 -> 1346.59 | E29: =+kumta!G35 -> 123790.05 | F29: =+kumta!H35 -> 87.41 | G29: =+kumta!J35 -> 9087.1436 | H29: =E29+G29 -> 132877.2 | I29: 0 | J29: =+kumta!L35 -> 132877.2 | K29: =H29+I29-J29 -> 0
A30: 29 | B30: Jalgaon | C30: Sri Sai Petrol Pump | D30: =+Jalgaon!E54 -> 24100 | E30: =+Jalgaon!G54 -> 2209671 | F30: =+Jalgaon!H54 -> 272 | G30: =+Jalgaon!J54 -> 28611.68 | H30: =E30+G30 -> 2238282.7 | I30: =+Jalgaon!K3 -> 730303.78 | J30: =+Jalgaon!L54 -> 1600000 | K30: =H30+I30-J30 -> 1368586.5
A31: 30 | B31: MKBD | C31: Shree Sai Samarth Petroleum | D31: =+MKBD!E38 -> 5600 | E31: =+MKBD!G38 -> 510384 | F31: =+MKBD!H38 -> 103 | G31: =+MKBD!J38 -> 16348.87 | H31: =E31+G31 -> 526732.87 | I31: =+MKBD!K3 -> 362563.78 | J31: =+MKBD!L38 -> 523255 | K31: =H31+I31-J31 -> 366041.65
A32: 31 | B32: Haveri | C32: Shivalingeshwar Petroleum | D32: =+Haveri!E37 -> 0 | E32: =+Haveri!G37 -> 0 | F32: =+Haveri!H37 -> 0 | G32: =+Haveri!J37 -> 0 | H32: =E32+G32 -> 0 | I32: =+Haveri!M3 -> 9461.0769 | J32: =+Haveri!L37 -> 9461.08 | K32: =H32+I32-J32 -> -0.0031000001
A33: 32 | B33: Haveri | C33: M/s Magavi City Fuels | D33: =' Haveri-2'!E37 -> 4555.27 | E33: =' Haveri-2'!G37 -> 416750.85 | F33: =' Haveri-2'!H37 -> 109.93 | G33: =' Haveri-2'!J37 -> 11370.06 | H33: =E33+G33 -> 428120.91 | I33: =' Haveri-2'!M3 -> 164443.72 | J33: =+' Haveri-2'!L37 -> 441733.9 | K33: =H33+I33-J33 -> 150830.73
A34: 33 | B34: Guttal | C34: Taware filling station | D34: =+Guttal!E35 -> 0 | E34: =+Guttal!G35 -> 0 | F34: =+Guttal!H35 -> 0 | G34: =+Guttal!J35 -> 0 | H34: =E34+G34 -> 0 | I34: =+Guttal!M3 -> 336687.37 | J34: =+Guttal!L35 -> 336687.37 | K34: =H34+I34-J34 -> 0.00039999996
A35: 34 | B35: Guttal-2 | C35: Himagiri Petroleum | D35: =+' Guttal-2'!E35 -> 9282.01 | E35: =+' Guttal-2'!G35 -> 851902.88 | F35: =+' Guttal-2'!H35 -> 100 | G35: =+' Guttal-2'!J35 -> 10374 | H35: =E35+G35 -> 862276.88 | I35: =+' Guttal-2'!M3 -> 0 | J35: =+' Guttal-2'!L35 -> 330000 | K35: =H35+I35-J35 -> 532276.88
A36: 35 | B36: Rattihali | C36: Shree Siri Gowari petroliam | D36: =+Rattihali!E35 -> 0 | E36: =+Rattihali!G35 -> 0 | F36: =+Rattihali!H35 -> 0 | G36: =+Rattihali!J35 -> 0 | H36: =E36+G36 -> 0 | I36: =+Rattihali!M3 -> 6442.724 | J36: =+Rattihali!L35 -> 0 | K36: =H36+I36-J36 -> 6442.724
A37: 36 | B37: Rattihali-2 | C37: Shiva Oil Traders | D37: =+'Rattihali-2'!E37 -> 3858.6 | E37: =+'Rattihali-2'!G37 -> 354566.75 | F37: =+'Rattihali-2'!H37 -> 210 | G37: =+'Rattihali-2'!J37 -> 21932.82 | H37: =E37+G37 -> 376499.57 | I37: =+'Rattihali-2'!M3 -> 310880.3 | J37: =+'Rattihali-2'!L37 -> 525000 | K37: =H37+I37-J37 -> 162379.88
A38: 37 | B38: Gajendragada | C38: Vanasri Petrol Pump | D38: =+Gajendragada!E35 -> 40 | E38: =+Gajendragada!G35 -> 3673.2 | F38: =+Gajendragada!H35 -> 20 | G38: =+Gajendragada!J35 -> 2076 | H38: =E38+G38 -> 5749.2 | I38: =+Gajendragada!K3 -> 4500.2015 | J38: =+Gajendragada!L35 -> 0 | K38: =H38+I38-J38 -> 10249.402
A39: 38 | B39: Gokak(PKG-3) | C39: AJ Petrolinks | D39: =+'Gokak Dharwad PKG 3'!E40 -> 11885.35 | E39: =+'Gokak Dharwad PKG 3'!G40 -> 1087271.8 | F39: =+'Gokak Dharwad PKG 3'!H40 -> 339 | G39: =+'Gokak Dharwad PKG 3'!J40 -> 35055.99 | H39: =E39+G39 -> 1122327.8 | I39: =+'Gokak Dharwad PKG 3'!K3 -> 547359.48 | J39: =+'Gokak Dharwad PKG 3'!L40 -> 1231700 | K39: =H39+I39-J39 -> 437987.29
A40: 39 | B40: Hukkere | C40: TR Assocites | D40: =+' TR Associates'!E35 -> 10355.07 | E40: =+' TR Associates'!G35 -> 945624.99 | F40: =+' TR Associates'!H35 -> 20 | G40: =+' TR Associates'!J35 -> 2064.8 | H40: =E40+G40 -> 947689.79 | I40: =+' TR Associates'!M3 -> 0 | J40: =+' TR Associates'!L35 -> 300000 | K40: =H40+I40-J40 -> 647689.79
A41: 40 | B41: Ankaligi | C41: Shivaganga | D41: =+Ankalgi!E35 -> 5235.9 | E41: =+Ankalgi!G35 -> 478090.03 | F41: =+Ankalgi!H35 -> 82 | G41: =+Ankalgi!J35 -> 8464.86 | H41: =E41+G41 -> 486554.89 | I41: =+Ankalgi!M3 -> 180107.62 | J41: =+Ankalgi!L35 -> 360000 | K41: =H41+I41-J41 -> 306662.51
A42: 41 | B42: ShankeshWAR | C42: SR Patil | D42: =+' Shankeshwar'!E35 -> 390 | E42: =+' Shankeshwar'!G35 -> 35607 | F42: =+' Shankeshwar'!H35 -> 159.25 | G42: =+' Shankeshwar'!J35 -> 16437.785 | H42: =E42+G42 -> 52044.785 | J42: =+' Shankeshwar'!L35 -> 52044.785 | K42: =H42+I42-J42 -> 0
A43: 42 | B43: Talikote(PKG-1) | C43: Raykar Oil Agencies | D43: =+' Talikote'!E46 -> 492.26 | E43: =+' Talikote'!G46 -> 45041.79 | F43: =+' Talikote'!H46 -> 82.27 | G43: =+' Talikote'!J46 -> 8510.0088 | H43: =E43+G43 -> 53551.799 | I43: =+' Talikote'!N3 -> 21107.796 | J43: =+' Talikote'!L46 -> 47000 | K43: =H43+I43-J43 -> 27659.595
A44: 43 | B44: Chadchan(PKG-1) | C44: Khavekar Petrolium | D44: =+Chadchan!E35 -> 1897.95 | E44: =+Chadchan!G35 -> 173149.98 | F44: =+Chadchan!H35 -> 80.54 | G44: =+Chadchan!J35 -> 8288.9634 | H44: =E44+G44 -> 181438.94 | I44: =+Chadchan!K3 -> 81512.172 | J44: =+Chadchan!L35 -> 176000 | K44: =H44+I44-J44 -> 86951.114
A45: 44 | B45: Sindagi | C45: G.P.PORWAL | D45: =+Sindagi!E44 -> 0 | E45: =+Sindagi!G44 -> 0 | F45: =+Sindagi!H44 -> 5 | G45: =+Sindagi!J44 -> 515.75 | H45: =E45+G45 -> 515.75 | I45: =+Sindagi!M3 -> 3671.4887 | J45: =+Sindagi!L44 -> 0 | K45: =H45+I45-J45 -> 4187.2387
A46: 45 | B46: Muddebihal(PKG-1)2 | C46: PS NAGATHAN PETROLIUM | D46: =+'Muddebhihal-2'!E48 -> 1946.87 | E46: =+'Muddebhihal-2'!G48 -> 177982.86 | F46: =+'Muddebhihal-2'!H48 -> 62.05 | G46: =+'Muddebhihal-2'!J48 -> 6464.0505 | H46: =+'Muddebhihal-2'!K48 -> 184446.91 | I46: =+'Muddebhihal-2'!M3 -> 106452.54 | J46: =+'Muddebhihal-2'!L48 -> 209000 | K46: =+'Muddebhihal-2'!M47 -> 81899.449
A47: 46 | B47: Almela(PKG-1) | C47: Shiddeshwar Petroleums | D47: =+Alemela!E43 -> 734.49 | E47: =+Alemela!G43 -> 67080.972 | F47: =+Alemela!H43 -> 79.46 | G47: =+Alemela!J43 -> 8205.0396 | H47: =E47+G47 -> 75286.011 | I47: =+Alemela!M3 -> 5104.7894 | J47: =+Alemela!L43 -> 28000 | K47: =H47+I47-J47 -> 52390.801
A48: 47 | B48: Nalatwad(PKG-1) | C48: Shri Pawad Basaweshwar Petroleums | D48: =+Nalatwad!E43 -> 696.06 | E48: =+Nalatwad!G43 -> 63773.017 | F48: =+Nalatwad!H43 -> 52.89 | G48: =+Nalatwad!J43 -> 5477.8173 | H48: =E48+G48 -> 69250.834 | I48: =+Nalatwad!M3 -> 32417.286 | J48: =+Nalatwad!L43 -> 42500 | K48: =H48+I48-J48 -> 59168.12
A49: 48 | B49: Srirangapatna | C49: Anupama F/S | D49: =+Srirangapatna!E35 -> 198.72 | E49: =+Srirangapatna!G35 -> 17998.07 | F49: =+Srirangapatna!H35 -> 18.58 | G49: =+Srirangapatna!J35 -> 1903.7068 | H49: =E49+G49 -> 19901.777 | I49: 0 | J49: =+Srirangapatna!L35 -> 19901.777 | K49: =H49+I49-J49 -> 0
A50: 49 | B50: HO(DG) | C50: JSASFuel Genie India Pvt.Ltd | D50: =+'HO(DG)'!E36 -> 793.68 | E50: =+'HO(DG)'!G36 -> 76050.554 | F50: =+'HO(DG)'!H36 -> 0 | G50: =+'HO(DG)'!J36 -> 0 | H50: =E50+G50 -> 76050.554 | I50: =+'HO(DG)'!M3 -> 16292.058 | J50: =+'HO(DG)'!L36 -> 59742 | K50: =H50+I50-J50 -> 32600.613
A51: Total | D51: =SUM(D2:D50) -> 268289.05 | E51: =SUM(E2:E50) -> 25130710 | F51: =SUM(F2:F50) -> 5553.53 | G51: =SUM(G2:G50) -> 586829.78 | H51: =SUM(H2:H50) -> 25717540 | I51: =SUM(I2:I50) -> 14875254 | J51: =SUM(J2:J50) -> 26398451 | K51: =H51+I51-J51 -> 14194342 | L51: 11794957 | M51: =K51-L51 -> 2399385.7
A56: S.no | B56: Site Name | C56: Bunk Name | D56: Diesel(Liters) | E56: Diesel Amount | F56: Petrol(Liters) | G56: Petrol Amount | H56: Total Amount | I56: Opening Blance | J56: Amount Paid | K56: Closing Balances
A57: 39 | B57: {=VLOOKUP(A57,A1:K49,{2,3,4,5,6,7,8,9,10,11},FALSE)} -> Hukkere | C57: TR Assocites | D57: 10355.07 | E57: 945624.99 | F57: 20 | G57: 2064.8 | H57: 947689.79 | I57: 0 | J57: 300000 | K57: 647689.79
B59: Site Name | C59: Bunk Name | D59: Diesel(Liters) | E59: Diesel Amount | F59: Petrol(Liters) | G59: Petrol Amount | H59: Total Amount | I59: Opening Blance | J59: Amount Paid | K59: Closing Balances
B60: Chellakere(KUWSDB) | C60: {=VLOOKUP(B60,B1:K49,{2,3,4,5,6,7,8,9,10},FALSE)} -> Shivaganga Service Station | D60: 3800 | E60: 350474 | F60: 230.04 | G60: 23944.864 | H60: 374418.86 | I60: 145403.1 | J60: 358717 | K60: 161104.96
B67: 60000
B68: 18000
B69: 18000
B70: 75000
B71: 360000

Sheet Sheet1
B2: S.no | C2: Site Name | D2: Bunk Name | E2: Outstannding | F2: Last Payment | G2: L.P Date | H2: Credit period in Days | I2: Next Payment Date
B3: 1 | C3: Khammam-1 | D3: Divya laxmi ganapathi | E3: =+'Jan-26'!K2 -> 2836061 | F3: 7753305 | G3: 15.12.2025 | H3: 45 | I3: 30.01.2025
B4: 2 | C4: Khammam-2 | D4: Jayasai union bunk | E4: =+'Jan-26'!K3 -> 4435776.8 | F4: 9561886 | G4: 15.12.2025 | H4: 45 | I4: 30.01.2025
B5: 3 | C5: Jadcherla-1 | D5: Sai Baba Fuel Station | E5: =+'Jan-26'!#REF! -> #REF! | F5: 307000 | G5: 15.12.2025 | H5: Close | I5: Close
B6: 4 | C6: Jadcherla-2 | D6: ADHOC FILLING STATION STATION | E6: =+'Jan-26'!#REF! -> #REF! | F6: 1123622.9 | G6: 13.12.2025 | H6: Close | I6: Close
B7: 5 | C7: Jadcherla-3 | D7: JSASFuel Genie India Pvt.Ltd | E7: =+'Jan-26'!K5 -> 299056.5 | F7: 2755171 | G7: 16.12.2025 | H7: 15 | I7: 05.01.2026
B8: 6 | C8: Dindi | D8: Akarapu Balakistamma Fillling | E8: =+'Jan-26'!K7 -> 0 | I8: C&C
B9: 7 | C9: Devarkhadra-1 | D9: Kurumurthy Swami F/S | E9: =+'Jan-26'!K8 -> 5856.2924 | F9: 55563 | G9: 16.12.2025 | H9: 10 | I9: 05.01.2026
B10: 8 | C10: Devarkhadra-3 | D10: JSASFuel Genie India Pvt.Ltd | E10: =+'Jan-26'!K9 -> 0 | F10: 66053.77 | G10: 16.12.2025 | H10: 15 | I10: 05.01.2026
B11: 9 | C11: Madanapalli | E11: =+'Jan-26'!K10 -> 0 | I11: C&C
B12: 10 | C12: Amalapuram | D12: Sathya Filling Station | E12: =+'Jan-26'!K11 -> -0.325 | I12: C&C
B13: 11 | C13: YG Gudda-1 | D13: Pallavi Petrolium | E13: =+'Jan-26'!K12 -> 0.0015138002 | F13: 25000 | G13: 16.12.2025 | H13: 10 | I13: 0
B14: 12 | C14: YG Gudda-2 | D14: Pankaja HP Fuel Center | E14: =+'Jan-26'!K13 -> 478336.85 | F14: 205413 | G14: 15.12.2025 | H14: 15 | I14: 05.01.2026
B15: 13 | C15: Hosadurga-1 | D15: Merchant Petroliums | E15: =+'Jan-26'!K14 -> 2258.6 | I15: 0
B16: 14 | C16: Hosadurga-2 | D16: Shree Veeraprathap Fuel | E16: =+'Jan-26'!K15 -> 325898.2 | F16: 551781.84 | G16: 15.12.2025 | H16: 15 | I16: 05.01.2026
B17: 15 | C17: Malebennuru(KUWSDB) | D17: Sri Ramanjuneya Service Station | E17: =+'Jan-26'!K16 -> 213698.56 | F17: 40495 | G17: 15.12.2025 | H17: 10 | I17: 27.12.2025
B18: 16 | C18: kadur | D18: Vishal Service Station | E18: =+'Jan-26'!K17 -> 14627.031 | F18: 175801 | G18: 15.12.2025 | H18: 30 | I18: 15.01.2026
B19: 17 | C19: Hiriyur(VJNL) | D19: Sri Balaji Agencies | E19: =+'Jan-26'!K18 -> 219486.1 | F19: 135912 | G19: 15.12.2025 | H19: 10 | I19: 30.12.2025
B20: 18 | C20: Chellakere(KUWSDB) | D20: Shivaganga Service Station | E20: =+'Jan-26'!K19 -> 161104.96 | F20: 58955.35 | G20: 15.12.2025 | H20: 15 | I20: 03.01.2025
B21: 19 | C21: Chellakere(KUWSDB)-09 | E21: =+'Jan-26'!K20 -> 0 | I21: C&C
B22: 20 | C22: Molakalmuru | D22: Priyanka Petroleum | E22: =+'Jan-26'!K21 -> 27990.595 | F22: New | I22: 05.01.2026
B23: 21 | C23: Chennagiri | E23: =+'Jan-26'!K22 -> 0
B24: 22 | C24: Khanapur(PKG-3) | D24: V.V.Varde | E24: =+'Jan-26'!K23 -> 103942.75 | F24: 50000 | G24: 13.12.2025 | H24: 15 | I24: 03.01.2025
B25: 23 | C25: Munavalli(PKG-3)-2 | D25: Shri Daneshwari | E25: =+'Jan-26'!K24 -> 0.0019999997 | F25: 107000 | G25: 15.12.2025 | H25: 10 | I25: 30.12.2025
B26: 24 | C26: Borgaon(PKG-3) | D26: Aadisagar Petrolium | E26: =+'Jan-26'!K26 -> 115310.98 | F26: 287043.3 | G26: 16.12.2025 | H26: 30 | I26: 15.01.2026
B27: 25 | C27: Ugar,Kudichi(PKG-3) | D27: Shiri Bhrhmanath Petrolium | E27: =+'Jan-26'!K27 -> 151510.55 | F27: 313314 | G27: 15.12.2025 | H27: 30 | I27: 15.01.2026
B28: 26 | C28: Kabbur(PKG-3) | D28: Shri Jai Hanuman Petrolium | E28: =+'Jan-26'!K28 -> 0
B29: 27 | C29: Kumta (PKG-1) | D29: Krishma fuel station | E29: =+'Jan-26'!K29 -> 0
B30: 28 | C30: Jalgaon | D30: Sri Sai Petrol Pump | E30: =+'Jan-26'!K30 -> 1368586.5 | F30: 1700000 | G30: 15.12.2025 | H30: 30 | I30: 15.01.2026
B31: 29 | C31: MKBD | D31: Shree Sai Samarth Petroleum | E31: =+'Jan-26'!K31 -> 366041.65 | F31: 461912.77 | G31: 15.12.2025 | H31: 30 | I31: 15.01.2026
B32: 30 | C32: Haveri | D32: Shivalingeshwar Petroleum | E32: =+'Jan-26'!K32 -> -0.0031000001 | F32: 224862 | G32: 12.12.2025 | H32: 10
B33: 31 | C33: Haveri | D33: M/s Magavi City Fuels | E33: =+'Jan-26'!K33 -> 150830.73 | F33: 14064 | G33: 16.12.2025 | H33: 13 | I33: 03.01.2025
B34: 32 | C34: Guttal | D34: Taware filling station | E34: =+'Jan-26'!K34 -> 0.00039999996 | F34: 50000 | G34: 24.12.2025 | H34: 7 | I34: 30.12.2025
B35: 33 | C35: Rattihali | D35: Shree Siri Gowari petroliam | E35: =+'Jan-26'!K36 -> 6442.724 | F35: 272393 | G35: 15.12.2025 | H35: 15 | I35: 30.12.2025
B36: 34 | C36: Rattihali-2 | D36: Shiva Oil Traders | E36: =+'Jan-26'!K37 -> 162379.88 | F36: New | H36: 15 | I36: 05.01.2026
B37: 35 | C37: Gajendragada | D37: Vanasri Petrol Pump | E37: =+'Jan-26'!K38 -> 10249.402 | H37: 30 | I37: 05.01.2026
B38: 36 | C38: Gokak(PKG-3) | D38: AJ Petrolinks | E38: =+'Jan-26'!K39 -> 437987.29 | F38: 1000000 | G38: 13.12.2025 | H38: 15 | I38: 05.01.2026
B39: 37 | C39: Ankaligi | D39: Shiv ganga | E39: =+'Jan-26'!K41 -> 306662.51 | F39: 361718.01 | G39: 15.12.2025 | H39: 15 | I39: 03.01.2025
B40: 38 | C40: ShankeshWAR | D40: SR Patil | E40: =+'Jan-26'!K42 -> 0 | I40: C&C
B41: 39 | C41: Talikote(PKG-1) | D41: Raykar Oil Agencies | E41: =+'Jan-26'!K43 -> 27659.595 | F41: 64000 | G41: 15.12.2025 | H41: 10 | I41: 30.12.2025
B42: 40 | C42: Chadchan(PKG-1) | D42: Khavekar Petrolium | E42: =+'Jan-26'!K44 -> 86951.114 | F42: 173004 | G42: 15.12.2025 | H42: 30 | I42: 15.01.2026
B43: 41 | C43: Sindagi | D43: G.P.PORWAL | E43: =+'Jan-26'!K45 -> 4187.2387 | F43: 11016 | G43: 15.12.2025 | H43: 15 | I43: 30.12.2025
B44: 42 | C44: Muddebihal(PKG-1) | D44: Bhosle Service Station | E44: =+'Jan-26'!#REF! -> #REF! | F44: 8500 | G44: 15.12.2025
B45: 43 | C45: Muddebihal(PKG-1)2 | D45: PS NAGATHAN PETROLIUM | E45: =+'Jan-26'!K46 -> 81899.449 | F45: 160000 | G45: 15.12.2025 | H45: 15 | I45: 05.01.2026
B46: 44 | C46: Almela(PKG-1) | D46: Shiddeshwar Petroleums | E46: =+'Jan-26'!K47 -> 52390.801 | F46: 32000 | G46: 15.12.2025 | H46: 10 | I46: 30.12.2025
B47: 45 | C47: Nalatwad(PKG-1) | D47: Shri Pawad Basaweshwar Petroleums | E47: =+'Jan-26'!K48 -> 59168.12 | F47: 66000 | G47: 15.12.2025 | H47: 10 | I47: 30.12.2025
B48: 46 | C48: Srirangapatna | D48: Anupama F/S | E48: =+'Jan-26'!K49 -> 0
B50: Total | E50: =SUM(E3:E48) -> #REF! | F50: =SUM(F3:F48) -> 28172787

Sheet HO(DG)
A1: JSASFuel Genie India Pvt.Ltd
A2: S.No | B2: Date | C2: GRN No | D2: Ind No/Bill No | E2: Diesel (Lts) | F2: Price | G2: Amount | H2: Petrol (Lts) | I2: Price | J2: Amount | K2: Total amount | L2: Amount paid | M2: As on date | N2: Remarks
A3: Opening Balance | M3: 16292.058 | O3: 2623243.4
A4: 1 | B4: 46023 | G4: =E4*F4 -> 0 | H4: 0 | I4: 0 | J4: =H4*I4 -> 0 | K4: =G4+J4 -> 0 | L4: 0 | M4: =M3+K4-L4 -> 16292.058
A5: 2 | B5: 46024 | G5: =E5*F5 -> 0 | H5: 0 | I5: 0 | J5: =H5*I5 -> 0 | K5: =G5+J5 -> 0 | L5: 0 | M5: =M4+K5-L5 -> 16292.058
A6: 3 | B6: 46025 | G6: =E6*F6 -> 0 | H6: 0 | I6: 0 | J6: =H6*I6 -> 0 | K6: =G6+J6 -> 0 | L6: 0 | M6: =M5+K6-L6 -> 16292.058
A7: 4 | B7: 46026 | G7: =E7*F7 -> 0 | H7: 0 | I7: 0 | J7: =H7*I7 -> 0 | K7: =G7+J7 -> 0 | L7: 0 | M7: =M6+K7-L7 -> 16292.058 | P7: 5679
A8: 5 | B8: 46027 | G8: =E8*F8 -> 0 | H8: 0 | I8: 0 | J8: =H8*I8 -> 0 | K8: =G8+J8 -> 0 | L8: 0 | M8: =M7+K8-L8 -> 16292.058
A9: 6 | B9: 46028 | G9: =E9*F9 -> 0 | H9: 0 | I9: 0 | J9: =H9*I9 -> 0 | K9: =G9+J9 -> 0 | L9: 0 | M9: =M8+K9-L9 -> 16292.058
A10: 7 | B10: 46029 | G10: =E10*F10 -> 0 | H10: 0 | I10: 0 | J10: =H10*I10 -> 0 | K10: =G10+J10 -> 0 | L10: 0 | M10: =M9+K10-L10 -> 16292.058
A11: 8 | B11: 46030 | D11: 2 | E11: 200 | F11: 95.83 | G11: =E11*F11 -> 19166 | H11: 0 | I11: 0 | J11: =H11*I11 -> 0 | K11: =G11+J11 -> 19166 | L11: 0 | M11: =M10+K11-L11 -> 35458.058
A12: 9 | B12: 46031 | G12: =E12*F12 -> 0 | H12: 0 | I12: 0 | K12: =G12+J12 -> 0 | L12: 0 | M12: =M11+K12-L12 -> 35458.058
A13: 10 | B13: 46032 | G13: =E13*F13 -> 0 | H13: 0 | I13: 0 | K13: =G13+J13 -> 0 | L13: 0 | M13: =M12+K13-L13 -> 35458.058
A14: 11 | B14: 46033 | G14: =E14*F14 -> 0 | H14: 0 | I14: 0 | K14: =G14+J14 -> 0 | L14: 0 | M14: =M13+K14-L14 -> 35458.058 | P14: 1905988 | Q14: =P14-M14 -> 1870529.9
A15: 12 | B15: 46034 | G15: =E15*F15 -> 0 | H15: 0 | I15: 0 | K15: =G15+J15 -> 0 | L15: 0 | M15: =M14+K15-L15 -> 35458.058
A16: 13 | B16: 46035 | G16: =E16*F16 -> 0 | H16: 0 | I16: 0 | J16: =H16*I16 -> 0 | K16: =G16+J16 -> 0 | L16: 0 | M16: =M15+K16-L16 -> 35458.058
A17: 14 | B17: 46036 | G17: =E17*F17 -> 0 | H17: 0 | I17: 0 | J17: =H17*I17 -> 0 | K17: =G17+J17 -> 0 | L17: 0 | M17: =M16+K17-L17 -> 35458.058
A18: 15 | B18: 46037 | E18: 193.68 | F18: 95.83 | G18: =E18*F18 -> 18560.354 | H18: 0 | I18: 0 | J18: =H18*I18 -> 0 | K18: =G18+J18 -> 18560.354 | L18: 0 | M18: =M17+K18-L18 -> 54018.413
A19: 16 | B19: 46038 | G19: =E19*F19 -> 0 | H19: 0 | I19: 0 | J19: =H19*I19 -> 0 | K19: =G19+J19 -> 0 | L19: 0 | M19: =M18+K19-L19 -> 54018.413
A20: 17 | B20: 46039 | G20: =E20*F20 -> 0 | J20: =H20*I20 -> 0 | K20: =G20+J20 -> 0 | L20: 0 | M20: =M19+K20-L20 -> 54018.413
A21: 18 | B21: 46040 | G21: =E21*F21 -> 0 | J21: =H21*I21 -> 0 | K21: =G21+J21 -> 0 | L21: 0 | M21: =M20+K21-L21 -> 54018.413
A22: 19 | B22: 46041 | G22: =E22*F22 -> 0 | J22: =H22*I22 -> 0 | K22: =G22+J22 -> 0 | L22: 54000 | M22: =M21+K22-L22 -> 18.4127
A23: 20 | B23: 46042 | G23: =E23*F23 -> 0 | J23: =H23*I23 -> 0 | K23: =G23+J23 -> 0 | M23: =M22+K23-L23 -> 18.4127
A24: 21 | B24: 46043 | G24: =E24*F24 -> 0 | J24: =H24*I24 -> 0 | K24: =G24+J24 -> 0 | M24: =M23+K24-L24 -> 18.4127
A25: 22 | B25: 46044 | G25: =E25*F25 -> 0 | J25: =H25*I25 -> 0 | K25: =G25+J25 -> 0 | M25: =M24+K25-L25 -> 18.4127
A26: 23 | B26: 46045 | E26: 60 | F26: 95.7 | G26: =E26*F26 -> 5742 | J26: =H26*I26 -> 0 | K26: =G26+J26 -> 5742 | L26: 5742 | M26: =M25+K26-L26 -> 18.4127
A27: 24 | B27: 46046 | E27: 160 | F27: 95.83 | G27: =E27*F27 -> 15332.8 | J27: =H27*I27 -> 0 | K27: =G27+J27 -> 15332.8 | M27: =M26+K27-L27 -> 15351.213
A28: 25 | B28: 46047 | G28: =E28*F28 -> 0 | J28: =H28*I28 -> 0 | K28: =G28+J28 -> 0 | M28: =M27+K28-L28 -> 15351.213
A29: 26 | B29: 46048 | G29: =E29*F29 -> 0 | J29: =H29*I29 -> 0 | K29: =G29+J29 -> 0 | M29: =M28+K29-L29 -> 15351.213
A30: 27 | B30: 46049 | G30: =E30*F30 -> 0 | J30: =H30*I30 -> 0 | K30: =G30+J30 -> 0 | M30: =M29+K30-L30 -> 15351.213
A31: 28 | B31: 46050 | G31: =E31*F31 -> 0 | J31: =H31*I31 -> 0 | K31: =G31+J31 -> 0 | M31: =M30+K31-L31 -> 15351.213
A32: 29 | B32: 46051 | G32: =E32*F32 -> 0 | J32: =H32*I32 -> 0 | K32: =G32+J32 -> 0 | M32: =M31+K32-L32 -> 15351.213
A33: 30 | B33: 46052 | G33: =E33*F33 -> 0 | J33: =H33*I33 -> 0 | K33: =G33+J33 -> 0 | M33: =M32+K33-L33 -> 15351.213
A34: 31 | B34: 46053 | E34: 180 | F34: 95.83 | G34: =E34*F34 -> 17249.4 | J34: =H34*I34 -> 0 | K34: =G34+J34 -> 17249.4 | L34: 0 | M34: =M33+K34-L34 -> 32600.613 | O34: 2669494 | P34: =O34-M34 -> 2636893.4
E35: 0 | F35: 0 | G35: =E35*F35 -> 0 | J35: =H35*I35 -> 0 | K35: =G35+J35 -> 0 | M35: =M34+K35-L35 -> 32600.613
E36: =SUM(E4:E34) -> 793.68 | G36: =SUM(G4:G34) -> 76050.554 | H36: =SUM(H4:H34) -> 0 | J36: =SUM(J4:J34) -> 0 | K36: =SUM(K4:K34) -> 76050.554 | L36: =SUM(L4:L34) -> 59742
M45: 2408309
M46: 5327.86
M47: =M45-M46 -> 2402981.1

Sheet Sheet2
A2: S.No | B2: NAme | C2: Lacation | D2: Card Number | E2: Card Number | F2: Category | G2: 1st Jan | I2: 2nd Jan | J2: 3rd Jan | K2: 4th Jan | L2: 5th Jan | M2: 6th Jan | N2: 7th Jan | O2: 8th Jan | P2: 9th Jan | Q2: 10th Jan | R2: 11th Jan | S2: 12th Jan | T2: 13th Jan | U2: 14th Jan | V2: 15th Jan | W2: 16th Jan | X2: 17th Jan | Y2: 18th Jan | Z2: 19th Jan | AA2: 20th Jan | AB2: 21st Jan | AC2: 22nd Jan | AD2: 23rd Jan | AE2: 24th Jan | AF2: 25th Jan | AG2: 26th Jan | AH2: 27th Jan | AI2: 28th Jan | AJ2: 29th Jan | AK2: 30th Jan | AL2: 31st Jan | AM2: Total
F3: Diesel
A4: 1 | B4: Rambabu | C4: HO(Two Wheeler) | D4: FC3450563999 | E4: Diesel | F4: 0 | G4: 0 | H4: 0 | I4: 0 | J4: 0 | K4: 0 | L4: 0 | M4: 0 | N4: 0 | O4: 0 | P4: 0 | Q4: 0 | R4: 0 | S4: 0 | T4: 0 | U4: 0 | V4: 0 | W4: 0 | X4: 5.22 | Y4: 0 | Z4: 0 | AA4: 0 | AB4: 0 | AC4: 0 | AD4: 60 | AE4: 0 | AF4: 0 | AG4: 0 | AH4: 4.56 | AI4: 0 | AJ4: 0 | AK4: 0 | AL4: 0 | AM4: =SUM(F4:AL4) -> 69.78
E5: Petrol | F5: 0 | G5: 4.69 | H5: 0 | I5: 0 | J5: 0 | K5: 0 | L5: 0 | M5: 0 | N5: 3.91 | O5: 0 | P5: 6.98 | Q5: 0 | R5: 0 | S5: 0 | T5: 0 | U5: 0 | V5: 0 | W5: 0 | X5: 0 | Y5: 0 | Z5: 0 | AB5: 0 | AC5: 0 | AD5: 0 | AE5: 0 | AF5: 0 | AG5: 0 | AH5: 0 | AI5: 0 | AJ5: 0 | AK5: 0 | AL5: 0 | AM5: =SUM(F5:AL5) -> 15.58
A6: 2 | B6: Hanumanth Rao | C6: HO | D6: FC3450676131 | E6: Diesel | F6: 0 | G6: 0 | H6: 0 | I6: 0 | J6: 0 | K6: 0 | L6: 0 | M6: 0 | N6: 0 | O6: 0 | P6: 0 | Q6: 0 | R6: 0 | S6: 0 | T6: 0 | U6: 0 | V6: 0 | W6: 0 | X6: 0 | Y6: 0 | Z6: 0 | AA6: 0 | AB6: 0 | AC6: 0 | AD6: 0 | AE6: 0 | AF6: 0 | AG6: 0 | AH6: 0 | AI6: 0 | AJ6: 0 | AK6: 0 | AL6: 0 | AM6: =SUM(F6:AL6) -> 0
E7: Petrol | F7: 0 | G7: 0 | H7: 0 | I7: 0 | J7: 0 | K7: 0 | L7: 0 | M7: 0 | N7: 0 | O7: 0 | P7: 0 | Q7: 0 | R7: 0 | S7: 0 | T7: 0 | U7: 0 | V7: 0 | W7: 0 | X7: 0 | Y7: 0 | Z7: 0 | AB7: 0 | AC7: 0 | AD7: 0 | AE7: 0 | AF7: 0 | AG7: 0 | AH7: 0 | AI7: 0 | AJ7: 0 | AK7: 0 | AL7: 0 | AM7: =SUM(F7:AL7) -> 0
A8: 3 | B8: Radhakrishna | C8: HO | D8: FC8000207658 | E8: Diesel | F8: 0 | G8: 0 | H8: 0 | I8: 0 | J8: 33.44 | K8: 0 | L8: 0 | M8: 0 | N8: 0 | O8: 0 | P8: 0 | Q8: 0 | R8: 35.53 | S8: 0 | T8: 0 | U8: 0 | V8: 0 | W8: 0 | X8: 0 | Y8: 0 | Z8: 0 | AA8: 0 | AB8: 33.44 | AC8: 0 | AD8: 0 | AE8: 0 | AF8: 0 | AG8: 0 | AH8: 0 | AI8: 0 | AJ8: 0 | AK8: 0 | AL8: 0 | AM8: =SUM(F8:AL8) -> 102.41
E9: Petrol | F9: 0 | G9: 0 | H9: 0 | I9: 0 | J9: 0 | K9: 0 | L9: 0 | M9: 0 | N9: 0 | O9: 0 | P9: 0 | Q9: 0 | R9: 0 | S9: 0 | T9: 0 | U9: 0 | V9: 0 | W9: 0 | X9: 0 | Y9: 0 | Z9: 0 | AB9: 0 | AC9: 0 | AD9: 0 | AE9: 0 | AF9: 0 | AG9: 0 | AH9: 0 | AI9: 0 | AJ9: 0 | AK9: 0 | AL9: 0 | AM9: =SUM(F9:AL9) -> 0
A10: 4 | B10: VIjay | C10: HO | D10: FC3450698859 | E10: Diesel | F10: 0 | G10: 0 | H10: 0 | I10: 0 | J10: 0 | K10: 0 | L10: 0 | M10: 0 | N10: 0 | O10: 0 | P10: 49.22 | Q10: 0 | R10: 0 | S10: 0 | T10: 0 | U10: 54.57 | V10: 0 | W10: 0 | X10: 0 | Y10: 0 | Z10: 0 | AA10: 0 | AB10: 0 | AC10: 0 | AD10: 49.8 | AE10: 0 | AF10: 0 | AG10: 0 | AH10: 0 | AI10: 0 | AJ10: 0 | AK10: 0 | AL10: 0 | AM10: =SUM(F10:AL10) -> 153.59
E11: Petrol | F11: 0 | G11: 0 | H11: 0 | I11: 0 | J11: 0 | K11: 0 | L11: 0 | M11: 0 | N11: 0 | O11: 0 | P11: 0 | Q11: 0 | R11: 0 | S11: 0 | T11: 0 | U11: 0 | V11: 0 | W11: 0 | X11: 0 | Y11: 0 | Z11: 0 | AB11: 0 | AC11: 0 | AD11: 0 | AE11: 0 | AF11: 0 | AG11: 0 | AH11: 0 | AI11: 0 | AJ11: 0 | AK11: 0 | AL11: 0 | AM11: =SUM(F11:AL11) -> 0
A12: 5 | B12: Client | C12: Hiriyur | D12: FC3450698864 | E12: Diesel | F12: 0 | G12: 0 | H12: 0 | I12: 0 | J12: 0 | K12: 0 | L12: 0 | M12: 0 | N12: 86.29 | O12: 0 | P12: 0 | Q12: 0 | R12: 0 | S12: 0 | T12: 0 | U12: 0 | V12: 0 | W12: 0 | X12: 0 | Y12: 0 | Z12: 0 | AA12: 0 | AB12: 0 | AC12: 0 | AD12: 145.61 | AE12: 0 | AF12: 0 | AG12: 0 | AH12: 0 | AI12: 0 | AJ12: 0 | AK12: 0 | AL12: 0 | AM12: =SUM(F12:AL12) -> 231.9
E13: Petrol | F13: 0 | G13: 0 | H13: 0 | I13: 0 | J13: 0 | K13: 0 | L13: 0 | M13: 0 | N13: 0 | O13: 0 | P13: 0 | Q13: 0 | R13: 0 | S13: 0 | T13: 0 | U13: 0 | V13: 0 | W13: 0 | X13: 0 | Y13: 0 | Z13: 0 | AB13: 0 | AC13: 0 | AD13: 0 | AE13: 0 | AF13: 0 | AG13: 0 | AH13: 0 | AI13: 0 | AJ13: 0 | AK13: 0 | AL13: 0 | AM13: =SUM(F13:AL13) -> 0
A14: 6 | B14: Client | C14: Hosadurga | D14: FC3450698865 | E14: Diesel | F14: 0 | G14: 0 | H14: 0 | I14: 0 | J14: 0 | K14: 0 | L14: 40 | M14: 40 | N14: 0 | O14: 36 | P14: 35 | Q14: 0 | R14: 0 | S14: 0 | T14: 0 | U14: 0 | V14: 0 | W14: 45 | X14: 45 | Y14: 43.53 | Z14: 40 | AA14: 43 | AB14: 0 | AC14: 40 | AD14: 0 | AE14: 40 | AF14: 0 | AG14: 0 | AH14: 0 | AI14: 0 | AJ14: 0 | AK14: 0 | AL14: 0 | AM14: =SUM(F14:AL14) -> 447.53
E15: Petrol | F15: 0 | G15: 0 | H15: 0 | I15: 0 | J15: 0 | K15: 0 | L15: 0 | M15: 0 | N15: 0 | O15: 0 | P15: 0 | Q15: 0 | R15: 0 | S15: 0 | T15: 0 | U15: 0 | V15: 0 | W15: 0 | X15: 0 | Y15: 0 | Z15: 0 | AB15: 0 | AC15: 0 | AD15: 0 | AE15: 0 | AF15: 0 | AG15: 0 | AH15: 0 | AI15: 0 | AJ15: 0 | AK15: 0 | AL15: 0 | AM15: =SUM(F15:AL15) -> 0
G18: Diesel Price

Sheet Khammam-1
A1: Divya laxmi ganapathi
A2: S.No | B2: Date | C2: GRN No | D2: Ind No/Bill No | E2: Diesel (Lts) | F2: Price | G2: Amount | H2: Petrol (Lts) | I2: Price | J2: Amount | K2: Total amount | L2: Amount paid | M2: As 0n Date | N2: Remarks
A3: Opening Balance | K3: 3956161.3 | M3: =+K3 -> 3956161.3 | O3: 11178224
A4: 1 | B4: 46023 | G4: =E4*F4 -> 0 | K4: =G4+J4 -> 0 | L4: 0 | M4: =M3+K4-L4 -> 3956161.3
A5: 2 | B5: 46024 | E5: 2000 | F5: 95.68 | G5: =E5*F5 -> 191360 | J5: =H5*I5 -> 0 | K5: =G5+J5 -> 191360 | L5: 0 | M5: =M4+K5-L5 -> 4147521.3
A6: 3 | B6: 46025 | E6: 2000 | F6: 95.68 | G6: =E6*F6 -> 191360 | J6: =H6*I6 -> 0 | K6: =G6+J6 -> 191360 | L6: 0 | M6: =M5+K6-L6 -> 4338881.3
A7: 4 | B7: 46026 | E7: 2000 | F7: 95.68 | G7: =E7*F7 -> 191360 | J7: =H7*I7 -> 0 | K7: =G7+J7 -> 191360 | L7: 0 | M7: =M6+K7-L7 -> 4530241.3
A8: 5 | B8: 46027 | E8: 1891.06 | F8: 95.68 | G8: =E8*F8 -> 180936.62 | J8: =H8*I8 -> 0 | K8: =G8+J8 -> 180936.62 | L8: 0 | M8: =M7+K8-L8 -> 4711178
A9: 6 | B9: 46028 | E9: 4534.98 | F9: 95.68 | G9: =E9*F9 -> 433906.89 | H9: 40 | I9: 107.46 | J9: =H9*I9 -> 4298.4 | K9: =G9+J9 -> 438205.29 | L9: 0 | M9: =M8+K9-L9 -> 5149383.2
A10: 7 | B10: 46029 | E10: 6508.24 | F10: 95.68 | G10: =E10*F10 -> 622708.4 | H10: 40 | I10: 107.46 | J10: =H10*I10 -> 4298.4 | K10: =G10+J10 -> 627006.8 | L10: 0 | M10: =M9+K10-L10 -> 5776390.1
A11: 8 | B11: 46030 | E11: 3700 | F11: 95.68 | G11: =E11*F11 -> 354016 | H11: 40 | I11: 107.46 | J11: =H11*I11 -> 4298.4 | K11: =G11+J11 -> 358314.4 | L11: 0 | M11: =M10+K11-L11 -> 6134704.5
A12: 9 | B12: 46031 | E12: 2000 | F12: 95.68 | G12: =E12*F12 -> 191360 | H12: 20 | I12: 107.46 | J12: =H12*I12 -> 2149.2 | K12: =G12+J12 -> 193509.2 | L12: 0 | M12: =M11+K12-L12 -> 6328213.7
A13: 10 | B13: 46032 | E13: 4500 | F13: 95.68 | G13: =E13*F13 -> 430560 | H13: 40 | I13: 107.46 | J13: =H13*I13 -> 4298.4 | K13: =G13+J13 -> 434858.4 | L13: 0 | M13: =M12+K13-L13 -> 6763072.1
A14: 11 | B14: 46033 | G14: =E14*F14 -> 0 | J14: =H14*I14 -> 0 | K14: =G14+J14 -> 0 | L14: 0 | M14: =M13+K14-L14 -> 6763072.1
A15: 12 | B15: 46034 | G15: =E15*F15 -> 0 | J15: =H15*I15 -> 0 | K15: =G15+J15 -> 0 | L15: 0 | M15: =M14+K15-L15 -> 6763072.1
A16: 13 | B16: 46035 | G16: =E16*F16 -> 0 | J16: =H16*I16 -> 0 | K16: =G16+J16 -> 0 | L16: 0 | M16: =M15+K16-L16 -> 6763072.1
A17: 14 | B17: 46036 | G17: =E17*F17 -> 0 | J17: =H17*I17 -> 0 | K17: =G17+J17 -> 0 | L17: 0 | M17: =M16+K17-L17 -> 6763072.1
A18: 15 | B18: 46037 | G18: =E18*F18 -> 0 | J18: =H18*I18 -> 0 | K18: =G18+J18 -> 0 | L18: 0 | M18: =M17+K18-L18 -> 6763072.1
A19: 16 | B19: 46038 | G19: =E19*F19 -> 0 | J19: =H19*I19 -> 0 | K19: =G19+J19 -> 0 | L19: 0 | M19: =M18+K19-L19 -> 6763072.1
A20: 17 | B20: 46039 | G20: =E20*F20 -> 0 | J20: =H20*I20 -> 0 | K20: =G20+J20 -> 0 | L20: 0 | M20: =M19+K20-L20 -> 6763072.1
A21: 18 | B21: 46040 | G21: =E21*F21 -> 0 | J21: =H21*I21 -> 0 | K21: =G21+J21 -> 0 | L21: 0 | M21: =M20+K21-L21 -> 6763072.1
A22: 19 | B22: 46041 | E22: 5500 | F22: 95.68 | G22: =E22*F22 -> 526240 | H22: 95 | I22: 107.46 | J22: =H22*I22 -> 10208.7 | K22: =G22+J22 -> 536448.7 | L22: 6503593 | M22: =M21+K22-L22 -> 795927.75
A23: 20 | B23: 46042 | G23: =E23*F23 -> 0 | J23: =H23*I23 -> 0 | K23: =G23+J23 -> 0 | L23: 0 | M23: =M22+K23-L23 -> 795927.75
A24: 21 | B24: 46043 | E24: 1500 | F24: 95.68 | G24: =E24*F24 -> 143520 | J24: =H24*I24 -> 0 | K24: =G24+J24 -> 143520 | L24: 0 | M24: =M23+K24-L24 -> 939447.75
A25: 22 | B25: 46044 | E25: 1500 | F25: 95.68 | G25: =E25*F25 -> 143520 | J25: =H25*I25 -> 0 | K25: =G25+J25 -> 143520 | L25: 0 | M25: =M24+K25-L25 -> 1082967.8
A26: 23 | B26: 46045 | E26: 4300 | F26: 95.68 | G26: =E26*F26 -> 411424 | H26: 20 | I26: 107.46 | J26: =H26*I26 -> 2149.2 | K26: =G26+J26 -> 413573.2 | L26: 0 | M26: =M25+K26-L26 -> 1496541
A27: 24 | B27: 46046 | E27: 1500 | F27: 95.68 | G27: =E27*F27 -> 143520 | J27: =H27*I27 -> 0 | K27: =G27+J27 -> 143520 | L27: 0 | M27: =M26+K27-L27 -> 1640061
A28: 25 | B28: 46047 | E28: 1500 | F28: 95.68 | G28: =E28*F28 -> 143520 | J28: =H28*I28 -> 0 | K28: =G28+J28 -> 143520 | L28: 0 | M28: =M27+K28-L28 -> 1783581
A29: 26 | B29: 46048 | E29: 1500 | F29: 95.68 | G29: =E29*F29 -> 143520 | J29: =H29*I29 -> 0 | K29: =G29+J29 -> 143520 | L29: 0 | M29: =M28+K29-L29 -> 1927101
A30: 27 | B30: 46049 | E30: 1500 | F30: 95.68 | G30: =E30*F30 -> 143520 | J30: =H30*I30 -> 0 | K30: =G30+J30 -> 143520 | L30: 0 | M30: =M29+K30-L30 -> 2070621
A31: 28 | B31: 46050 | E31: 1500 | F31: 95.68 | G31: =E31*F31 -> 143520 | J31: =H31*I31 -> 0 | K31: =G31+J31 -> 143520 | L31: 0 | M31: =M30+K31-L31 -> 2214141
A32: 29 | B32: 46051 | E32: 2500 | F32: 95.68 | G32: =E32*F32 -> 239200 | J32: =H32*I32 -> 0 | K32: =G32+J32 -> 239200 | L32: 0 | M32: =M31+K32-L32 -> 2453341
A33: 30 | B33: 46052 | E33: 1500 | F33: 95.68 | G33: =E33*F33 -> 143520 | J33: =H33*I33 -> 0 | K33: =G33+J33 -> 143520 | L33: 0 | M33: =M32+K33-L33 -> 2596861
A34: 31 | B34: 46053 | E34: 2500 | F34: 95.68 | G34: =E34*F34 -> 239200 | K34: =G34+J34 -> 239200 | L34: 0 | M34: =M33+K34-L34 -> 2836061
A35: 32 | G35: =E35*F35 -> 0 | J35: =H35*I35 -> 0 | K35: =G35+J35 -> 0 | L35: 0 | M35: =M34+K35-L35 -> 2836061
A36: 33 | G36: =E36*F36 -> 0 | J36: =H36*I36 -> 0 | K36: =G36+J36 -> 0 | L36: 0
A37: 34 | G37: =E37*F37 -> 0 | J37: =H37*I37 -> 0 | K37: =G37+J37 -> 0
E38: =SUM(E3:E37) -> 55934.28 | G38: =SUM(G3:G37) -> 5351791.9 | H38: =SUM(H3:H37) -> 295 | J38: =SUM(J3:J37) -> 31700.7 | K38: =SUM(K4:K37) -> 5383492.6 | L38: =SUM(L3:L37) -> 6503593
E39: 62644.369
E40: 12000

Sheet Khammam-2
A1: Jayasai union bunk
A2: S.No | B2: Date | C2: GRN No | D2: Ind No/Bill No | E2: Diesel (Lts) | F2: Price | G2: Amount | H2: Petrol (Lts) | I2: Price | J2: Amount | K2: Total amount | L2: Amount paid | M2: As 0n Date | N2: Remarks
A3: Opening Balance | K3: 3669815.6 | M3: 3669815.6
A4: 1 | B4: 46023 | G4: =E4*F4 -> 0 | J4: =H4*I4 -> 0 | K4: =G4+J4 -> 0 | M4: =M3+K4-L4 -> 3669815.6 | O4: =O3+M4-N4 -> 3669815.6
A5: 2 | B5: 46024 | E5: 2700 | F5: 95.7 | G5: =E5*F5 -> 258390 | H5: 75 | I5: 107.48 | J5: =H5*I5 -> 8061 | K5: =G5+J5 -> 266451 | M5: =M4+K5-L5 -> 3936266.6
A6: 3 | B6: 46025 | E6: 5500 | F6: 95.7 | G6: =E6*F6 -> 526350 | H6: 60 | I6: 107.48 | J6: =H6*I6 -> 6448.8 | K6: =G6+J6 -> 532798.8 | M6: =M5+K6-L6 -> 4469065.4
A7: 4 | B7: 46026 | G7: =E7*F7 -> 0 | J7: =H7*I7 -> 0 | K7: =G7+J7 -> 0 | M7: =M6+K7-L7 -> 4469065.4
A8: 5 | B8: 46027 | E8: 2700 | F8: 95.7 | G8: =E8*F8 -> 258390 | H8: 60 | I8: 107.48 | J8: =H8*I8 -> 6448.8 | K8: =G8+J8 -> 264838.8 | M8: =M7+K8-L8 -> 4733904.2 | O8: 12802499
A9: 6 | B9: 46028 | E9: 2800 | F9: 95.7 | G9: =E9*F9 -> 267960 | J9: =H9*I9 -> 0 | K9: =G9+J9 -> 267960 | M9: =M8+K9-L9 -> 5001864.2
A10: 7 | B10: 46029 | G10: =E10*F10 -> 0 | J10: =H10*I10 -> 0 | K10: =G10+J10 -> 0 | M10: =M9+K10-L10 -> 5001864.2
A11: 8 | B11: 46030 | G11: =E11*F11 -> 0 | J11: =H11*I11 -> 0 | K11: =G11+J11 -> 0 | M11: =M10+K11-L11 -> 5001864.2
A12: 9 | B12: 46031 | G12: =E12*F12 -> 0 | J12: =H12*I12 -> 0 | K12: =G12+J12 -> 0 | M12: =M11+K12-L12 -> 5001864.2
A13: 10 | B13: 46032 | G13: =E13*F13 -> 0 | J13: =H13*I13 -> 0 | K13: =G13+J13 -> 0 | M13: =M12+K13-L13 -> 5001864.2
A14: 11 | B14: 46033 | G14: =E14*F14 -> 0 | J14: =H14*I14 -> 0 | K14: =G14+J14 -> 0 | M14: =M13+K14-L14 -> 5001864.2
A15: 12 | B15: 46034 | E15: 3194.369 | F15: 95.7 | G15: =E15*F15 -> 305701.11 | H15: 40 | I15: 107.48 | J15: =H15*I15 -> 4299.2 | K15: =G15+J15 -> 310000.31 | M15: =M14+K15-L15 -> 5311864.5
A16: 13 | B16: 46035 | G16: =E16*F16 -> 0 | J16: =H16*I16 -> 0 | K16: =G16+J16 -> 0 | M16: =M15+K16-L16 -> 5311864.5
A17: 14 | B17: 46036 | G17: =E17*F17 -> 0 | J17: =H17*I17 -> 0 | K17: =G17+J17 -> 0 | M17: =M16+K17-L17 -> 5311864.5
A18: 15 | B18: 46037 | G18: =E18*F18 -> 0 | J18: =H18*I18 -> 0 | K18: =G18+J18 -> 0 | M18: =M17+K18-L18 -> 5311864.5
A19: 16 | B19: 46038 | G19: =E19*F19 -> 0 | H19: 46.52 | I19: 107.48 | J19: =H19*I19 -> 4999.9696 | K19: =G19+J19 -> 4999.9696 | M19: =M18+K19-L19 -> 5316864.5
A20: 17 | B20: 46039 | D20: Round Off | G20: =E20*F20 -> 0 | J20: =H20*I20 -> 0 | K20: =G20+J20 -> 0 | M20: =M19+K20-L20 -> 5316864.5
A21: 18 | B21: 46040 | G21: =E21*F21 -> 0 | J21: =H21*I21 -> 0 | K21: =G21+J21 -> 0 | M21: =M20+K21-L21 -> 5316864.5
A22: 19 | B22: 46041 | G22: =E22*F22 -> 0 | J22: =H22*I22 -> 0 | K22: =G22+J22 -> 0 | L22: 5316861 | M22: =M21+K22-L22 -> 3.4829
B23: 46041 | L23: 3.48 | M23: =M22+K23-L23 -> 0.0029000002
A24: 20 | B24: 46042 | E24: 5000 | F24: 95.7 | G24: =E24*F24 -> 478500 | H24: 40 | I24: 107.48 | J24: =H24*I24 -> 4299.2 | K24: =G24+J24 -> 482799.2 | M24: =M23+K24-L24 -> 482799.2
A25: 21 | B25: 46043 | E25: 2700 | F25: 95.7 | G25: =E25*F25 -> 258390 | H25: 60 | I25: 107.48 | J25: =H25*I25 -> 6448.8 | K25: =G25+J25 -> 264838.8 | M25: =M24+K25-L25 -> 747638
A26: 22 | B26: 46044 | E26: =2800+2700 -> 5500 | F26: 95.7 | G26: =E26*F26 -> 526350 | H26: 60 | I26: 107.48 | J26: =H26*I26 -> 6448.8 | K26: =G26+J26 -> 532798.8 | M26: =M25+K26-L26 -> 1280436.8
A27: 23 | B27: 46045 | E27: 2850 | F27: 95.7 | G27: =E27*F27 -> 272745 | H27: 55 | I27: 107.48 | J27: =H27*I27 -> 5911.4 | K27: =G27+J27 -> 278656.4 | M27: =M26+K27-L27 -> 1559093.2
A28: 24 | B28: 46046 | E28: 5400 | F28: 95.7 | G28: =E28*F28 -> 516780 | H28: 40 | I28: 107.48 | J28: =H28*I28 -> 4299.2 | K28: =G28+J28 -> 521079.2 | M28: =M27+K28-L28 -> 2080172.4
A29: 25 | B29: 46047 | E29: 2800 | F29: 95.7 | G29: =E29*F29 -> 267960 | H29: 60 | I29: 107.48 | J29: =H29*I29 -> 6448.8 | K29: =G29+J29 -> 274408.8 | M29: =M28+K29-L29 -> 2354581.2
A30: 26 | B30: 46048 | F30: 95.7 | G30: =E30*F30 -> 0 | I30: 107.48 | J30: =H30*I30 -> 0 | K30: =G30+J30 -> 0 | M30: =M29+K30-L30 -> 2354581.2
A31: 27 | B31: 46049 | E31: 5300 | F31: 95.7 | G31: =E31*F31 -> 507210 | H31: 40 | I31: 107.48 | J31: =H31*I31 -> 4299.2 | K31: =G31+J31 -> 511509.2 | M31: =M30+K31-L31 -> 2866090.4
A32: 28 | B32: 46050 | E32: 2700 | F32: 95.7 | G32: =E32*F32 -> 258390 | H32: 60 | I32: 107.48 | J32: =H32*I32 -> 6448.8 | K32: =G32+J32 -> 264838.8 | M32: =M31+K32-L32 -> 3130929.2
A33: 29 | B33: 46051 | E33: 5500 | F33: 95.7 | G33: =E33*F33 -> 526350 | H33: 20 | I33: 107.48 | J33: =H33*I33 -> 2149.6 | K33: =G33+J33 -> 528499.6 | M33: =M32+K33-L33 -> 3659428.8
A34: 30 | B34: 46052 | E34: 5500 | F34: 95.7 | G34: =E34*F34 -> 526350 | H34: 40 | I34: 107.48 | J34: =H34*I34 -> 4299.2 | K34: =G34+J34 -> 530649.2 | M34: =M33+K34-L34 -> 4190078
A35: 31 | B35: 46053 | E35: 2500 | F35: 95.7 | G35: =E35*F35 -> 239250 | H35: 60 | I35: 107.48 | J35: =H35*I35 -> 6448.8 | K35: =G35+J35 -> 245698.8 | M35: =M34+K35-L35 -> 4435776.8
E36: =SUM(E4:E35) -> 62644.369 | G36: =SUM(G4:G35) -> 5995066.1 | H36: =SUM(H4:H35) -> 816.52 | J36: =SUM(J4:J35) -> 87759.57 | K36: =SUM(K4:K35) -> 6082825.7 | L36: =SUM(L4:L35) -> 5316864.5
K37: 5383492.6
K38: 1133100
K39: 6082825.7
K40: =SUM(K37:K39) -> 12599418

Sheet Khammam-3
A1: JSASFuel Genie India Pvt.Ltd
A2: S.No | B2: Date | C2: GRN No | D2: Ind No/Bill No | E2: Diesel (Lts) | F2: Price | G2: Amount | H2: Petrol (Lts) | I2: Price | J2: Amount | K2: Total amount | L2: Amount paid | M2: As 0n Date | N2: Remarks
A3: Opening Balance | K3: 0 | M3: 0
A4: 1 | B4: 46023 | G4: =E4*F4 -> 0 | J4: =H4*I4 -> 0 | K4: =G4+J4 -> 0 | M4: =M3+K4-L4 -> 0 | O4: =O3+M4-N4 -> 0
A5: 2 | B5: 46024 | G5: =E5*F5 -> 0 | J5: =H5*I5 -> 0 | K5: =G5+J5 -> 0 | M5: =M4+K5-L5 -> 0
A6: 3 | B6: 46025 | G6: =E6*F6 -> 0 | J6: =H6*I6 -> 0 | K6: =G6+J6 -> 0 | M6: =M5+K6-L6 -> 0
A7: 4 | B7: 46026 | G7: =E7*F7 -> 0 | J7: =H7*I7 -> 0 | K7: =G7+J7 -> 0 | M7: =M6+K7-L7 -> 0
A8: 5 | B8: 46027 | G8: =E8*F8 -> 0 | J8: =H8*I8 -> 0 | K8: =G8+J8 -> 0 | M8: =M7+K8-L8 -> 0
A9: 6 | B9: 46028 | G9: =E9*F9 -> 0 | J9: =H9*I9 -> 0 | K9: =G9+J9 -> 0 | M9: =M8+K9-L9 -> 0
A10: 7 | B10: 46029 | G10: =E10*F10 -> 0 | J10: =H10*I10 -> 0 | K10: =G10+J10 -> 0 | M10: =M9+K10-L10 -> 0
A11: 8 | B11: 46030 | G11: =E11*F11 -> 0 | J11: =H11*I11 -> 0 | K11: =G11+J11 -> 0 | M11: =M10+K11-L11 -> 0
A12: 9 | B12: 46031 | G12: =E12*F12 -> 0 | J12: =H12*I12 -> 0 | K12: =G12+J12 -> 0 | M12: =M11+K12-L12 -> 0
A13: 10 | B13: 46032 | G13: =E13*F13 -> 0 | J13: =H13*I13 -> 0 | K13: =G13+J13 -> 0 | M13: =M12+K13-L13 -> 0
A14: 11 | B14: 46033 | G14: =E14*F14 -> 0 | J14: =H14*I14 -> 0 | K14: =G14+J14 -> 0 | M14: =M13+K14-L14 -> 0
A15: 12 | B15: 46034 | G15: =E15*F15 -> 0 | J15: =H15*I15 -> 0 | K15: =G15+J15 -> 0 | M15: =M14+K15-L15 -> 0
A16: 13 | B16: 46035 | E16: 6000 | F16: 94.7 | G16: =E16*F16 -> 568200 | J16: =H16*I16 -> 0 | K16: =G16+J16 -> 568200 | M16: =M15+K16-L16 -> 568200
A17: 14 | B17: 46036 | E17: 6000 | F17: 94.7 | G17: =E17*F17 -> 568200 | J17: =H17*I17 -> 0 | K17: =G17+J17 -> 568200 | M17: =M16+K17-L17 -> 1136400
A18: 15 | B18: 46037 | G18: =E18*F18 -> 0 | J18: =H18*I18 -> 0 | K18: =G18+J18 -> 0 | M18: =M17+K18-L18 -> 1136400
A19: 16 | B19: 46038 | G19: =E19*F19 -> 0 | J19: =H19*I19 -> 0 | K19: =G19+J19 -> 0 | M19: =M18+K19-L19 -> 1136400
A20: 17 | B20: 46039 | G20: =E20*F20 -> 0 | J20: =H20*I20 -> 0 | K20: =G20+J20 -> 0 | M20: =M19+K20-L20 -> 1136400
A21: 18 | B21: 46040 | G21: =E21*F21 -> 0 | J21: =H21*I21 -> 0 | K21: =G21+J21 -> 0 | M21: =M20+K21-L21 -> 1136400
A22: 19 | B22: 46041 | G22: =E22*F22 -> 0 | J22: =H22*I22 -> 0 | K22: =G22+J22 -> 0 | L22: 1016000 | M22: =M21+K22-L22 -> 120400
A23: 20 | B23: 46042 | G23: =E23*F23 -> 0 | J23: =H23*I23 -> 0 | K23: =G23+J23 -> 0 | M23: =M22+K23-L23 -> 120400
A24: 21 | B24: 46043 | G24: =E24*F24 -> 0 | J24: =H24*I24 -> 0 | K24: =G24+J24 -> 0 | M24: =M23+K24-L24 -> 120400
A25: 22 | B25: 46044 | G25: =E25*F25 -> 0 | J25: =H25*I25 -> 0 | K25: =G25+J25 -> 0 | M25: =M24+K25-L25 -> 120400
A26: 23 | B26: 46045 | G26: =E26*F26 -> 0 | J26: =H26*I26 -> 0 | K26: =G26+J26 -> 0 | M26: =M25+K26-L26 -> 120400
A27: 24 | B27: 46046 | G27: =E27*F27 -> 0 | J27: =H27*I27 -> 0 | K27: =G27+J27 -> 0 | M27: =M26+K27-L27 -> 120400
A28: 25 | B28: 46047 | G28: =E28*F28 -> 0 | J28: =H28*I28 -> 0 | K28: =G28+J28 -> 0 | M28: =M27+K28-L28 -> 120400
A29: 26 | B29: 46048 | G29: =E29*F29 -> 0 | J29: =H29*I29 -> 0 | K29: =G29+J29 -> 0 | M29: =M28+K29-L29 -> 120400
A30: 27 | B30: 46049 | G30: =E30*F30 -> 0 | J30: =H30*I30 -> 0 | K30: =G30+J30 -> 0 | M30: =M29+K30-L30 -> 120400
A31: 28 | B31: 46050 | G31: =E31*F31 -> 0 | J31: =H31*I31 -> 0 | K31: =G31+J31 -> 0 | M31: =M30+K31-L31 -> 120400
A32: 29 | B32: 46051 | G32: =E32*F32 -> 0 | J32: =H32*I32 -> 0 | K32: =G32+J32 -> 0 | M32: =M31+K32-L32 -> 120400
A33: 30 | B33: 46052 | G33: =E33*F33 -> 0 | J33: =H33*I33 -> 0 | K33: =G33+J33 -> 0 | M33: =M32+K33-L33 -> 120400
A34: 31 | B34: 46053 | G34: =E34*F34 -> 0 | J34: =H34*I34 -> 0 | K34: =G34+J34 -> 0 | M34: =M33+K34-L34 -> 120400
E35: =SUM(E4:E34) -> 12000 | G35: =SUM(G4:G34) -> 1136400 | H35: =SUM(H4:H34) -> 0 | J35: =SUM(J4:J34) -> 0 | K35: =SUM(K4:K34) -> 1136400 | L35: =SUM(L4:L34) -> 1016000

Sheet Jadcherla-3
A1: JSASFuel Genie India Pvt.Ltd
A2: S.No | B2: Date | C2: GRN No | D2: Ind no/Bill No | E2: Diesel (Lts) | F2: Price | G2: Amount | H2: Petrol (Lts) | I2: Price | J2: Amount | K2: Total amount | L2: Amount paid | M2: As on Date | N2: Remarks
A3: Opening Balance | M3: 1183331.5
A4: 1 | B4: 46023 | E4: 1500 | F4: 95.43 | G4: =E4*F4 -> 143145 | H4: 0 | I4: 0 | J4: =H4*I4 -> 0 | K4: =G4+J4 -> 143145 | L4: 0 | M4: =+M3+K4-L4 -> 1326476.5
A5: 2 | B5: 46024 | G5: =E5*F5 -> 0 | H5: 0 | I5: 0 | J5: =H5*I5 -> 0 | K5: =G5+J5 -> 0 | L5: 0 | M5: =+M4+K5-L5 -> 1326476.5
A6: 3 | B6: 46025 | E6: 1000 | F6: 95.43 | G6: =E6*F6 -> 95430 | H6: 0 | I6: 0 | J6: =H6*I6 -> 0 | K6: =G6+J6 -> 95430 | M6: =+M5+K6-L6 -> 1421906.5
A7: 4 | B7: 46026 | G7: =E7*F7 -> 0 | H7: 0 | I7: 0 | J7: =H7*I7 -> 0 | K7: =G7+J7 -> 0 | M7: =+M6+K7-L7 -> 1421906.5
A8: 5 | B8: 46027 | G8: =E8*F8 -> 0 | H8: 0 | I8: 0 | J8: =H8*I8 -> 0 | K8: =G8+J8 -> 0 | M8: =+M7+K8-L8 -> 1421906.5
A9: 6 | B9: 46028 | G9: =E9*F9 -> 0 | H9: 0 | I9: 0 | J9: =H9*I9 -> 0 | K9: =G9+J9 -> 0 | M9: =+M8+K9-L9 -> 1421906.5
A10: 7 | B10: 46029 | G10: =E10*F10 -> 0 | H10: 0 | I10: 0 | J10: =H10*I10 -> 0 | K10: =G10+J10 -> 0 | M10: =+M9+K10-L10 -> 1421906.5
A11: 8 | B11: 46030 | E11: 1000 | F11: 95.43 | G11: =E11*F11 -> 95430 | H11: 0 | I11: 0 | J11: =H11*I11 -> 0 | K11: =G11+J11 -> 95430 | M11: =+M10+K11-L11 -> 1517336.5
A12: 9 | B12: 46031 | G12: =E12*F12 -> 0 | H12: 0 | I12: 0 | J12: =H12*I12 -> 0 | K12: =G12+J12 -> 0 | M12: =+M11+K12-L12 -> 1517336.5
A13: 10 | B13: 46032 | G13: =E13*F13 -> 0 | H13: 0 | I13: 0 | J13: =H13*I13 -> 0 | K13: =G13+J13 -> 0 | M13: =+M12+K13-L13 -> 1517336.5
A14: 11 | B14: 46033 | G14: =E14*F14 -> 0 | H14: 0 | I14: 0 | J14: =H14*I14 -> 0 | K14: =G14+J14 -> 0 | M14: =+M13+K14-L14 -> 1517336.5
A15: 12 | B15: 46034 | G15: =E15*F15 -> 0 | H15: 0 | I15: 0 | J15: =H15*I15 -> 0 | K15: =G15+J15 -> 0 | M15: =+M14+K15-L15 -> 1517336.5
A16: 13 | B16: 46035 | G16: =E16*F16 -> 0 | H16: 0 | I16: 0 | J16: =H16*I16 -> 0 | K16: =G16+J16 -> 0 | L16: 1000000 | M16: =+M15+K16-L16 -> 517336.5
A17: 14 | B17: 46036 | E17: 1000 | F17: 95.43 | G17: =E17*F17 -> 95430 | H17: 0 | I17: 0 | J17: =H17*I17 -> 0 | K17: =G17+J17 -> 95430 | M17: =+M16+K17-L17 -> 612766.5
A18: 15 | B18: 46037 | G18: =E18*F18 -> 0 | H18: 0 | I18: 0 | J18: =H18*I18 -> 0 | K18: =G18+J18 -> 0 | M18: =+M17+K18-L18 -> 612766.5
A19: 16 | B19: 46038 | G19: =E19*F19 -> 0 | H19: 0 | I19: 0 | J19: =H19*I19 -> 0 | K19: =G19+J19 -> 0 | M19: =+M18+K19-L19 -> 612766.5
A20: 17 | B20: 46039 | G20: =E20*F20 -> 0 | H20: 0 | I20: 0 | J20: =H20*I20 -> 0 | K20: =G20+J20 -> 0 | M20: =+M19+K20-L20 -> 612766.5
A21: 18 | B21: 46040 | G21: =E21*F21 -> 0 | H21: 0 | I21: 0 | J21: =H21*I21 -> 0 | K21: =G21+J21 -> 0 | M21: =+M20+K21-L21 -> 612766.5
A22: 19 | B22: 46041 | G22: =E22*F22 -> 0 | H22: 0 | I22: 0 | J22: =H22*I22 -> 0 | K22: =G22+J22 -> 0 | L22: 600000 | M22: =+M21+K22-L22 -> 12766.5
A23: 20 | B23: 46042 | G23: =E23*F23 -> 0 | H23: 0 | I23: 0 | J23: =H23*I23 -> 0 | K23: =G23+J23 -> 0 | M23: =+M22+K23-L23 -> 12766.5
A24: 21 | B24: 46043 | G24: =E24*F24 -> 0 | H24: 0 | I24: 0 | J24: =H24*I24 -> 0 | K24: =G24+J24 -> 0 | M24: =+M23+K24-L24 -> 12766.5
A25: 22 | B25: 46044 | G25: =E25*F25 -> 0 | H25: 0 | I25: 0 | J25: =H25*I25 -> 0 | K25: =G25+J25 -> 0 | M25: =+M24+K25-L25 -> 12766.5
A26: 23 | B26: 46045 | G26: =E26*F26 -> 0 | H26: 0 | I26: 0 | J26: =H26*I26 -> 0 | K26: =G26+J26 -> 0 | M26: =+M25+K26-L26 -> 12766.5
A27: 24 | B27: 46046 | E27: 1000 | F27: 95.43 | G27: =E27*F27 -> 95430 | H27: 0 | I27: 0 | J27: =H27*I27 -> 0 | K27: =G27+J27 -> 95430 | M27: =+M26+K27-L27 -> 108196.5
A28: 25 | B28: 46047 | G28: =E28*F28 -> 0 | H28: 0 | I28: 0 | J28: =H28*I28 -> 0 | K28: =G28+J28 -> 0 | M28: =+M27+K28-L28 -> 108196.5
A29: 26 | B29: 46048 | G29: =E29*F29 -> 0 | H29: 0 | I29: 0 | J29: =H29*I29 -> 0 | K29: =G29+J29 -> 0 | M29: =+M28+K29-L29 -> 108196.5
A30: 27 | B30: 46049 | G30: =E30*F30 -> 0 | H30: 0 | I30: 0 | J30: =H30*I30 -> 0 | K30: =G30+J30 -> 0 | M30: =+M29+K30-L30 -> 108196.5
A31: 28 | B31: 46050 | G31: =E31*F31 -> 0 | H31: 0 | I31: 0 | J31: =H31*I31 -> 0 | K31: =G31+J31 -> 0 | M31: =+M30+K31-L31 -> 108196.5
A32: 29 | B32: 46051 | G32: =E32*F32 -> 0 | H32: 0 | I32: 0 | J32: =H32*I32 -> 0 | K32: =G32+J32 -> 0 | M32: =+M31+K32-L32 -> 108196.5
A33: 30 | B33: 46052 | E33: 2000 | F33: 95.43 | G33: =E33*F33 -> 190860 | H33: 0 | I33: 0 | J33: =H33*I33 -> 0 | K33: =G33+J33 -> 190860 | M33: =+M32+K33-L33 -> 299056.5
A34: 31 | B34: 46053 | G34: =E34*F34 -> 0 | H34: 0 | I34: 0 | J34: =H34*I34 -> 0 | K34: =G34+J34 -> 0 | L34: 0 | M34: =+M33+K34-L34 -> 299056.5
E35: =SUM(E4:E34) -> 7500 | G35: =SUM(G4:G34) -> 715725 | H35: =SUM(H4:H34) -> 0 | J35: =SUM(J4:J34) -> 0 | K35: =SUM(K4:K34) -> 715725 | L35: =SUM(L4:L34) -> 1600000
F38: /

Sheet Jadcherla-4
A1: Shree Poornima F/S
A2: S.No | B2: Date | C2: GRN No | D2: Ind No/Bill No | E2: Diesel (Lts) | F2: Price | G2: Amount | H2: Petrol (Lts) | I2: Price | J2: Amount | K2: Total amount | L2: Amount paid | M2: As on date | N2: Remarks
A3: Opening Balance | M3: 5405
A4: 1 | B4: 46023 | G4: =E4*F4 -> 0 | H4: 0 | I4: 0 | J4: =H4*I4 -> 0 | K4: =G4+J4 -> 0 | L4: 0 | M4: =M3+K4-L4 -> 5405
A5: 2 | B5: 46024 | G5: =E5*F5 -> 0 | H5: 50 | I5: 108.1 | J5: =H5*I5 -> 5405 | K5: =G5+J5 -> 5405 | L5: 0 | M5: =M4+K5-L5 -> 10810
A6: 3 | B6: 46025 | G6: =E6*F6 -> 0 | H6: 0 | I6: 0 | J6: =H6*I6 -> 0 | K6: =G6+J6 -> 0 | L6: 0 | M6: =M5+K6-L6 -> 10810
A7: 4 | B7: 46026 | G7: =E7*F7 -> 0 | H7: 0 | I7: 0 | J7: =H7*I7 -> 0 | K7: =G7+J7 -> 0 | L7: 0 | M7: =M6+K7-L7 -> 10810
A8: 5 | B8: 46027 | G8: =E8*F8 -> 0 | H8: 0 | I8: 0 | J8: =H8*I8 -> 0 | K8: =G8+J8 -> 0 | L8: 0 | M8: =M7+K8-L8 -> 10810
A9: 6 | B9: 46028 | G9: =E9*F9 -> 0 | H9: 0 | I9: 0 | J9: =H9*I9 -> 0 | K9: =G9+J9 -> 0 | L9: 0 | M9: =M8+K9-L9 -> 10810
A10: 7 | B10: 46029 | G10: =E10*F10 -> 0 | H10: 0 | I10: 0 | J10: =H10*I10 -> 0 | K10: =G10+J10 -> 0 | L10: 0 | M10: =M9+K10-L10 -> 10810
A11: 8 | B11: 46030 | G11: =E11*F11 -> 0 | H11: 0 | I11: 0 | J11: =H11*I11 -> 0 | K11: =G11+J11 -> 0 | L11: 0 | M11: =M10+K11-L11 -> 10810
A12: 9 | B12: 46031 | G12: =E12*F12 -> 0 | H12: 0 | I12: 0 | K12: =G12+J12 -> 0 | L12: 0 | M12: =M11+K12-L12 -> 10810
A13: 10 | B13: 46032 | G13: =E13*F13 -> 0 | H13: 0 | I13: 0 | K13: =G13+J13 -> 0 | L13: 0 | M13: =M12+K13-L13 -> 10810
A14: 11 | B14: 46033 | G14: =E14*F14 -> 0 | H14: 0 | I14: 0 | K14: =G14+J14 -> 0 | L14: 0 | M14: =M13+K14-L14 -> 10810
A15: 12 | B15: 46034 | G15: =E15*F15 -> 0 | H15: 0 | I15: 0 | K15: =G15+J15 -> 0 | L15: 0 | M15: =M14+K15-L15 -> 10810
A16: 13 | B16: 46035 | G16: =E16*F16 -> 0 | H16: 0 | I16: 0 | J16: =H16*I16 -> 0 | K16: =G16+J16 -> 0 | L16: 0 | M16: =M15+K16-L16 -> 10810
A17: 14 | B17: 46036 | G17: =E17*F17 -> 0 | H17: 0 | I17: 0 | J17: =H17*I17 -> 0 | K17: =G17+J17 -> 0 | L17: 0 | M17: =M16+K17-L17 -> 10810
A18: 15 | B18: 46037 | G18: =E18*F18 -> 0 | H18: 0 | I18: 0 | J18: =H18*I18 -> 0 | K18: =G18+J18 -> 0 | L18: 0 | M18: =M17+K18-L18 -> 10810
A19: 16 | B19: 46038 | G19: =E19*F19 -> 0 | H19: 0 | I19: 0 | J19: =H19*I19 -> 0 | K19: =G19+J19 -> 0 | L19: 0 | M19: =M18+K19-L19 -> 10810
A20: 17 | B20: 46039 | G20: =E20*F20 -> 0 | H20: 50 | I20: 108.1 | J20: =H20*I20 -> 5405 | K20: =G20+J20 -> 5405 | L20: 16215 | M20: =M19+K20-L20 -> 0
A21: 18 | B21: 46040 | G21: =E21*F21 -> 0 | H21: 0 | I21: 0 | J21: =H21*I21 -> 0 | K21: =G21+J21 -> 0 | L21: 0 | M21: =M20+K21-L21 -> 0
A22: 19 | B22: 46041 | G22: =E22*F22 -> 0 | H22: 0 | I22: 0 | J22: =H22*I22 -> 0 | K22: =G22+J22 -> 0 | L22: 0 | M22: =M21+K22-L22 -> 0
A23: 20 | B23: 46042 | G23: =E23*F23 -> 0 | H23: 0 | I23: 0 | J23: =H23*I23 -> 0 | K23: =G23+J23 -> 0 | L23: 0 | M23: =M22+K23-L23 -> 0
A24: 21 | B24: 46043 | G24: =E24*F24 -> 0 | H24: 0 | I24: 0 | J24: =H24*I24 -> 0 | K24: =G24+J24 -> 0 | L24: 0 | M24: =M23+K24-L24 -> 0
A25: 22 | B25: 46044 | G25: =E25*F25 -> 0 | H25: 0 | I25: 0 | J25: =H25*I25 -> 0 | K25: =G25+J25 -> 0 | L25: 0 | M25: =M24+K25-L25 -> 0
A26: 23 | B26: 46045 | E26: 0 | F26: 0 | G26: =E26*F26 -> 0 | H26: 0 | I26: 0 | J26: =H26*I26 -> 0 | K26: =G26+J26 -> 0 | L26: 0 | M26: =M25+K26-L26 -> 0
A27: 24 | B27: 46046 | G27: =E27*F27 -> 0 | H27: 0 | I27: 0 | J27: =H27*I27 -> 0 | K27: =G27+J27 -> 0 | L27: 0 | M27: =M26+K27-L27 -> 0
A28: 25 | B28: 46047 | G28: =E28*F28 -> 0 | H28: 0 | I28: 0 | J28: =H28*I28 -> 0 | K28: =G28+J28 -> 0 | L28: 0 | M28: =M27+K28-L28 -> 0
A29: 26 | B29: 46048 | G29: =E29*F29 -> 0 | H29: 0 | I29: 0 | J29: =H29*I29 -> 0 | K29: =G29+J29 -> 0 | L29: 0 | M29: =M28+K29-L29 -> 0
A30: 27 | B30: 46049 | G30: =E30*F30 -> 0 | H30: 0 | I30: 0 | J30: =H30*I30 -> 0 | K30: =G30+J30 -> 0 | L30: 0 | M30: =M29+K30-L30 -> 0
A31: 28 | B31: 46050 | G31: =E31*F31 -> 0 | H31: 50 | I31: 108.1 | J31: =H31*I31 -> 5405 | K31: =G31+J31 -> 5405 | M31: =M30+K31-L31 -> 5405
A32: 28 | B32: 46051 | G32: =E32*F32 -> 0 | J32: =H32*I32 -> 0 | K32: =G32+J32 -> 0 | M32: =M31+K32-L32 -> 5405
A33: 28 | B33: 46052 | G33: =E33*F33 -> 0 | J33: =H33*I33 -> 0 | K33: =G33+J33 -> 0 | M33: =M32+K33-L33 -> 5405
A34: 28 | B34: 46053 | G34: =E34*F34 -> 0 | J34: =H34*I34 -> 0 | K34: =G34+J34 -> 0 | M34: =M33+K34-L34 -> 5405
E35: =SUM(E4:E34) -> 0 | G35: =SUM(G4:G34) -> 0 | H35: =SUM(H4:H34) -> 150 | J35: =SUM(J4:J34) -> 16215 | K35: =SUM(K4:K34) -> 16215 | L35: =SUM(L4:L34) -> 16215

Sheet Devarakhadra
A1: Kurumurthy Swami F/S
A2: S.No | B2: Date | C2: GRN No | D2: Ind no/Bill No | E2: Diesel (Lts) | F2: Price | G2: Amount | H2: Petrol (Lts) | I2: Price | J2: Amount | K2: Total amount | L2: Amount paid | M2: As on Date | N2: Remarks
A3: Opening Balance | M3: 5026.311 | O3: 121213.37
A4: 1 | B4: 46023 | E4: 35 | F4: 97.1 | G4: =E4*F4 -> 3398.5 | J4: =H4*I4 -> 0 | K4: =G4+J4 -> 3398.5 | M4: =+M3+K4-L4 -> 8424.811
A5: 2 | B5: 46024 | E5: 0 | F5: 0 | G5: =E5*F5 -> 0 | H5: 5 | I5: 108.83 | J5: =H5*I5 -> 544.15 | K5: =G5+J5 -> 544.15 | M5: =+M4+K5-L5 -> 8968.961
A6: 3 | B6: 46025 | E6: 0 | F6: 0 | G6: =E6*F6 -> 0 | J6: =H6*I6 -> 0 | K6: =G6+J6 -> 0 | M6: =+M5+K6-L6 -> 8968.961
A7: 4 | B7: 46026 | E7: 0 | F7: 0 | G7: =E7*F7 -> 0 | H7: 5 | I7: 108.83 | J7: =H7*I7 -> 544.15 | K7: =G7+J7 -> 544.15 | M7: =+M6+K7-L7 -> 9513.111
A8: 5 | B8: 46027 | E8: 0 | F8: 0 | G8: =E8*F8 -> 0 | J8: =H8*I8 -> 0 | K8: =G8+J8 -> 0 | M8: =+M7+K8-L8 -> 9513.111
A9: 6 | B9: 46028 | E9: 0 | F9: 0 | G9: =E9*F9 -> 0 | J9: =H9*I9 -> 0 | K9: =G9+J9 -> 0 | M9: =+M8+K9-L9 -> 9513.111
A10: 7 | B10: 46029 | E10: 0 | F10: 0 | G10: =E10*F10 -> 0 | J10: =H10*I10 -> 0 | K10: =G10+J10 -> 0 | M10: =+M9+K10-L10 -> 9513.111
A11: 8 | B11: 46030 | E11: 20 | F11: 97.1 | G11: =E11*F11 -> 1942 | J11: =H11*I11 -> 0 | K11: =G11+J11 -> 1942 | M11: =+M10+K11-L11 -> 11455.111
A12: 9 | B12: 46031 | E12: 0 | F12: 0 | G12: =E12*F12 -> 0 | H12: 5 | I12: 108.83 | J12: =H12*I12 -> 544.15 | K12: =G12+J12 -> 544.15 | M12: =+M11+K12-L12 -> 11999.261
A13: 10 | B13: 46032 | E13: 0 | F13: 0 | G13: =E13*F13 -> 0 | J13: =H13*I13 -> 0 | K13: =G13+J13 -> 0 | M13: =+M12+K13-L13 -> 11999.261
A14: 11 | B14: 46033 | E14: 0 | F14: 0 | G14: =E14*F14 -> 0 | J14: =H14*I14 -> 0 | K14: =G14+J14 -> 0 | M14: =+M13+K14-L14 -> 11999.261
A15: 12 | B15: 46034 | E15: 0 | F15: 0 | G15: =E15*F15 -> 0 | J15: =H15*I15 -> 0 | K15: =G15+J15 -> 0 | M15: =+M14+K15-L15 -> 11999.261
A16: 13 | B16: 46035 | E16: 0 | F16: 0 | G16: =E16*F16 -> 0 | J16: =H16*I16 -> 0 | K16: =G16+J16 -> 0 | M16: =+M15+K16-L16 -> 11999.261
A17: 14 | B17: 46036 | E17: 0 | F17: 0 | G17: =E17*F17 -> 0 | J17: =H17*I17 -> 0 | K17: =G17+J17 -> 0 | M17: =+M16+K17-L17 -> 11999.261
A18: 15 | B18: 46037 | E18: 0 | F18: 0 | G18: =E18*F18 -> 0 | H18: 5 | I18: 108.83 | J18: =H18*I18 -> 544.15 | K18: =G18+J18 -> 544.15 | M18: =+M17+K18-L18 -> 12543.411
A19: 16 | B19: 46038 | E19: 0 | F19: 0 | G19: =E19*F19 -> 0 | J19: =H19*I19 -> 0 | K19: =G19+J19 -> 0 | M19: =+M18+K19-L19 -> 12543.411 | N19: Fuel bills
A20: 17 | B20: 46039 | E20: 35 | F20: 97.1 | G20: =E20*F20 -> 3398.5 | J20: =H20*I20 -> 0 | K20: =G20+J20 -> 3398.5 | L20: 12543 | M20: =+M19+K20-L20 -> 3398.911
A21: 18 | B21: 46040 | E21: 0 | F21: 0 | G21: =E21*F21 -> 0 | J21: =H21*I21 -> 0 | K21: =G21+J21 -> 0 | M21: =+M20+K21-L21 -> 3398.911
A22: 19 | B22: 46041 | E22: 0 | F22: 0 | G22: =E22*F22 -> 0 | J22: =H22*I22 -> 0 | K22: =G22+J22 -> 0 | M22: =+M21+K22-L22 -> 3398.911
A23: 20 | B23: 46042 | E23: 0 | F23: 0 | G23: =E23*F23 -> 0 | J23: =H23*I23 -> 0 | K23: =G23+J23 -> 0 | M23: =+M22+K23-L23 -> 3398.911
A24: 21 | B24: 46043 | E24: 0 | F24: 0 | G24: =E24*F24 -> 0 | J24: =H24*I24 -> 0 | K24: =G24+J24 -> 0 | M24: =+M23+K24-L24 -> 3398.911
A25: 22 | B25: 46044 | E25: 0 | F25: 0 | G25: =E25*F25 -> 0 | J25: =H25*I25 -> 0 | K25: =G25+J25 -> 0 | M25: =+M24+K25-L25 -> 3398.911
A26: 23 | B26: 46045 | E26: 0 | F26: 0 | G26: =E26*F26 -> 0 | H26: 5 | I26: 108.83 | J26: =H26*I26 -> 544.15 | K26: =G26+J26 -> 544.15 | M26: =+M25+K26-L26 -> 3943.061
A27: 24 | B27: 46046 | E27: 0 | F27: 0 | G27: =E27*F27 -> 0 | J27: =H27*I27 -> 0 | K27: =G27+J27 -> 0 | M27: =+M26+K27-L27 -> 3943.061
A28: 25 | B28: 46047 | E28: 0 | F28: 0 | G28: =E28*F28 -> 0 | J28: =H28*I28 -> 0 | K28: =G28+J28 -> 0 | M28: =+M27+K28-L28 -> 3943.061
A29: 26 | B29: 46048 | E29: 0 | F29: 0 | G29: =E29*F29 -> 0 | J29: =H29*I29 -> 0 | K29: =G29+J29 -> 0 | M29: =+M28+K29-L29 -> 3943.061
A30: 27 | B30: 46049 | E30: 0 | F30: 0 | G30: =E30*F30 -> 0 | J30: =H30*I30 -> 0 | K30: =G30+J30 -> 0 | M30: =+M29+K30-L30 -> 3943.061
A31: 28 | B31: 46050 | E31: 0 | F31: 0 | G31: =E31*F31 -> 0 | J31: =H31*I31 -> 0 | K31: =G31+J31 -> 0 | M31: =+M30+K31-L31 -> 3943.061
A32: 29 | B32: 46051 | E32: 0 | F32: 0 | G32: =E32*F32 -> 0 | H32: 10 | I32: 108.83 | J32: =H32*I32 -> 1088.3 | K32: =G32+J32 -> 1088.3 | M32: =+M31+K32-L32 -> 5031.361
A33: 30 | B33: 46052 | E33: 0 | F33: 0 | G33: =E33*F33 -> 0 | H33: 5 | I33: 108.83 | J33: =H33*I33 -> 544.15 | K33: =G33+J33 -> 544.15 | M33: =+M32+K33-L33 -> 5575.511
A34: 31 | B34: 46053 | G34: =E34*F34 -> 0 | H34: 2.58 | I34: 108.83 | J34: =H34*I34 -> 280.7814 | K34: =G34+J34 -> 280.7814 | M34: =+M33+K34-L34 -> 5856.2924 | O34: 5921.25 | P34: =O34-M34 -> 64.9576
E35: =SUM(E4:E34) -> 90 | G35: =SUM(G4:G34) -> 8739 | H35: =SUM(H4:H34) -> 42.58 | J35: =SUM(J4:J34) -> 4633.9814 | K35: =SUM(K4:K34) -> 13372.981 | L35: =SUM(L4:L34) -> 12543

Sheet Devarakhadra-2
A1: JSASFuel Genie India Pvt.Ltd
A2: S.No | B2: Date | C2: GRN No | D2: Ind no/Bill No | E2: Diesel (Lts) | F2: Price | G2: Amount | H2: Petrol (Lts) | I2: Price | J2: Amount | K2: Total amount | L2: Amount paid | M2: As on Date | N2: Remarks
A3: Opening Balance | M3: 0
A4: 1 | B4: 46023 | G4: =E4*F4 -> 0 | H4: 0 | I4: 0 | J4: =H4*I4 -> 0 | K4: =G4+J4 -> 0 | L4: 0 | M4: =+M3+K4-L4 -> 0
A5: 2 | B5: 46024 | G5: =E5*F5 -> 0 | H5: 0 | I5: 0 | J5: =H5*I5 -> 0 | K5: =G5+J5 -> 0 | L5: 0 | M5: =+M4+K5-L5 -> 0
A6: 3 | B6: 46025 | G6: =E6*F6 -> 0 | H6: 0 | I6: 0 | J6: =H6*I6 -> 0 | K6: =G6+J6 -> 0 | L6: 0 | M6: =+M5+K6-L6 -> 0
A7: 4 | B7: 46026 | G7: =E7*F7 -> 0 | H7: 0 | I7: 0 | J7: =H7*I7 -> 0 | K7: =G7+J7 -> 0 | L7: 0 | M7: =+M6+K7-L7 -> 0
A8: 5 | B8: 46027 | G8: =E8*F8 -> 0 | H8: 0 | I8: 0 | J8: =H8*I8 -> 0 | K8: =G8+J8 -> 0 | L8: 0 | M8: =+M7+K8-L8 -> 0
A9: 6 | B9: 46028 | G9: =E9*F9 -> 0 | H9: 0 | I9: 0 | J9: =H9*I9 -> 0 | K9: =G9+J9 -> 0 | L9: 0 | M9: =+M8+K9-L9 -> 0
A10: 7 | B10: 46029 | G10: =E10*F10 -> 0 | H10: 0 | I10: 0 | J10: =H10*I10 -> 0 | K10: =G10+J10 -> 0 | L10: 0 | M10: =+M9+K10-L10 -> 0
A11: 8 | B11: 46030 | G11: =E11*F11 -> 0 | H11: 0 | I11: 0 | J11: =H11*I11 -> 0 | K11: =G11+J11 -> 0 | L11: 0 | M11: =+M10+K11-L11 -> 0
A12: 9 | B12: 46031 | G12: =E12*F12 -> 0 | H12: 0 | I12: 0 | J12: =H12*I12 -> 0 | K12: =G12+J12 -> 0 | L12: 0 | M12: =+M11+K12-L12 -> 0
A13: 10 | B13: 46032 | G13: =E13*F13 -> 0 | H13: 0 | I13: 0 | J13: =H13*I13 -> 0 | K13: =G13+J13 -> 0 | L13: 0 | M13: =+M12+K13-L13 -> 0
A14: 11 | B14: 46033 | G14: =E14*F14 -> 0 | H14: 0 | I14: 0 | J14: =H14*I14 -> 0 | K14: =G14+J14 -> 0 | L14: 0 | M14: =+M13+K14-L14 -> 0
A15: 12 | B15: 46034 | G15: =E15*F15 -> 0 | H15: 0 | I15: 0 | J15: =H15*I15 -> 0 | K15: =G15+J15 -> 0 | L15: 0 | M15: =+M14+K15-L15 -> 0
A16: 13 | B16: 46035 | G16: =E16*F16 -> 0 | H16: 0 | I16: 0 | J16: =H16*I16 -> 0 | K16: =G16+J16 -> 0 | L16: 0 | M16: =+M15+K16-L16 -> 0
A17: 14 | B17: 46036 | H17: 0 | I17: 0 | J17: =H17*I17 -> 0 | K17: =G17+J17 -> 0 | L17: 0 | M17: =+M16+K17-L17 -> 0
A18: 15 | B18: 46037 | H18: 0 | I18: 0 | J18: =H18*I18 -> 0 | K18: =G18+J18 -> 0 | L18: 0 | M18: =+M17+K18-L18 -> 0
A19: 16 | B19: 46038 | H19: 0 | I19: 0 | J19: =H19*I19 -> 0 | K19: =G19+J19 -> 0 | L19: 0 | M19: =+M18+K19-L19 -> 0
A20: 17 | B20: 46039 | G20: =E20*F20 -> 0 | H20: 0 | I20: 0 | J20: =H20*I20 -> 0 | K20: =G20+J20 -> 0 | L20: 0 | M20: =+M19+K20-L20 -> 0
A21: 18 | B21: 46040 | G21: =E21*F21 -> 0 | H21: 0 | I21: 0 | J21: =H21*I21 -> 0 | K21: =G21+J21 -> 0 | L21: 0 | M21: =+M20+K21-L21 -> 0
A22: 19 | B22: 46041 | G22: =E22*F22 -> 0 | H22: 0 | I22: 0 | J22: =H22*I22 -> 0 | K22: =G22+J22 -> 0 | L22: 0 | M22: =+M21+K22-L22 -> 0
A23: 20 | B23: 46042 | G23: =E23*F23 -> 0 | H23: 0 | I23: 0 | J23: =H23*I23 -> 0 | K23: =G23+J23 -> 0 | L23: 0 | M23: =+M22+K23-L23 -> 0
A24: 21 | B24: 46043 | G24: =E24*F24 -> 0 | H24: 0 | I24: 0 | J24: =H24*I24 -> 0 | K24: =G24+J24 -> 0 | L24: 0 | M24: =+M23+K24-L24 -> 0
A25: 22 | B25: 46044 | G25: =E25*F25 -> 0 | H25: 0 | I25: 0 | J25: =H25*I25 -> 0 | K25: =G25+J25 -> 0 | L25: 0 | M25: =+M24+K25-L25 -> 0
A26: 23 | B26: 46045 | G26: =E26*F26 -> 0 | H26: 0 | I26: 0 | J26: =H26*I26 -> 0 | K26: =G26+J26 -> 0 | L26: 0 | M26: =+M25+K26-L26 -> 0
A27: 24 | B27: 46046 | G27: =E27*F27 -> 0 | H27: 0 | I27: 0 | J27: =H27*I27 -> 0 | K27: =G27+J27 -> 0 | L27: 0 | M27: =+M26+K27-L27 -> 0
A28: 25 | B28: 46047 | G28: =E28*F28 -> 0 | H28: 0 | I28: 0 | J28: =H28*I28 -> 0 | K28: =G28+J28 -> 0 | L28: 0 | M28: =+M27+K28-L28 -> 0
A29: 26 | B29: 46048 | G29: =E29*F29 -> 0 | H29: 0 | I29: 0 | J29: =H29*I29 -> 0 | K29: =G29+J29 -> 0 | L29: 0 | M29: =+M28+K29-L29 -> 0
A30: 27 | B30: 46049 | G30: =E30*F30 -> 0 | H30: 0 | I30: 0 | J30: =H30*I30 -> 0 | K30: =G30+J30 -> 0 | L30: 0 | M30: =+M29+K30-L30 -> 0
A31: 28 | B31: 46050 | G31: =E31*F31 -> 0 | H31: 0 | I31: 0 | J31: =H31*I31 -> 0 | K31: =G31+J31 -> 0 | L31: 0 | M31: =+M30+K31-L31 -> 0
... A34: 31 | B34: 46053 | G34: =E34*F34 -> 0 | H34: 0 | I34: 0 | J34: =H34*I34 -> 0 | K34: =G34+J34 -> 0 | L34: 0 | M34: =+M33+K34-L34 -> 0
E35: =SUM(E4:E34) -> 0 | G35: =SUM(G4:G34) -> 0 | H35: =SUM(H4:H34) -> 0 | J35: =SUM(J4:J34) -> 0 | K35: =SUM(K4:K34) -> 0 | L35: =SUM(L4:L34) -> 0
F38: /

Sheet Dindi
A1: Akarapu Balakistamma Fillling
A2: S.No | B2: Date | C2: GRN No | D2: Ind no/Bill No | E2: Diesel (Lts) | F2: Price | G2: Amount | H2: Petrol (Lts) | I2: Price | J2: Amount | K2: Total amount | L2: Amount paid | M2: As on Date | N2: Remarks
A3: Opening Balance | M3: 0
A4: 1 | B4: 45658 | G4: =E4*F4 -> 0 | H4: 0 | I4: 0 | J4: =H4*I4 -> 0 | K4: =G4+J4 -> 0 | L4: =+K4 -> 0 | M4: 0
A5: 2 | B5: 45659 | G5: =E5*F5 -> 0 | H5: 0 | I5: 0 | J5: =H5*I5 -> 0 | K5: =G5+J5 -> 0 | L5: =+K5 -> 0 | M5: 0
A6: 3 | B6: 45660 | G6: =E6*F6 -> 0 | H6: 0 | I6: 0 | J6: =H6*I6 -> 0 | K6: =G6+J6 -> 0 | L6: =+K6 -> 0 | M6: 0
A7: 4 | B7: 45661 | G7: =E7*F7 -> 0 | H7: 0 | I7: 0 | J7: =H7*I7 -> 0 | K7: =G7+J7 -> 0 | L7: =+K7 -> 0 | M7: 0
A8: 5 | B8: 45662 | G8: =E8*F8 -> 0 | H8: 0 | I8: 0 | J8: =H8*I8 -> 0 | K8: =G8+J8 -> 0 | L8: =+K8 -> 0 | M8: 0
A9: 6 | B9: 45663 | G9: =E9*F9 -> 0 | H9: 0 | I9: 0 | J9: =H9*I9 -> 0 | K9: =G9+J9 -> 0 | L9: =+K9 -> 0 | M9: 0
A10: 7 | B10: 45664 | G10: =E10*F10 -> 0 | H10: 0 | I10: 0 | J10: =H10*I10 -> 0 | K10: =G10+J10 -> 0 | L10: =+K10 -> 0 | M10: 0
A11: 8 | B11: 45665 | G11: =E11*F11 -> 0 | H11: 0 | I11: 0 | J11: =H11*I11 -> 0 | K11: =G11+J11 -> 0 | L11: =+K11 -> 0 | M11: 0
A12: 9 | B12: 45666 | G12: =E12*F12 -> 0 | H12: 0 | I12: 0 | J12: =H12*I12 -> 0 | K12: =G12+J12 -> 0 | L12: =+K12 -> 0 | M12: 0
A13: 10 | B13: 45667 | G13: =E13*F13 -> 0 | H13: 0 | I13: 0 | J13: =H13*I13 -> 0 | K13: =G13+J13 -> 0 | L13: =+K13 -> 0 | M13: 0
A14: 11 | B14: 45668 | G14: =E14*F14 -> 0 | H14: 0 | I14: 0 | J14: =H14*I14 -> 0 | K14: =G14+J14 -> 0 | L14: =+K14 -> 0 | M14: 0
A15: 12 | B15: 45669 | G15: =E15*F15 -> 0 | H15: 0 | I15: 0 | J15: =H15*I15 -> 0 | K15: =G15+J15 -> 0 | L15: =+K15 -> 0 | M15: 0
... A27: 24 | B27: 45681 | G27: =E27*F27 -> 0 | H27: 0 | I27: 0 | J27: =H27*I27 -> 0 | K27: =G27+J27 -> 0 | L27: =+K27 -> 0 | M27: 0
A28: 25 | B28: 45682 | H28: 0 | I28: 0 | J28: =H28*I28 -> 0 | K28: =G28+J28 -> 0 | L28: =+K28 -> 0 | M28: 0
A29: 26 | B29: 45683 | G29: =E29*F29 -> 0 | H29: 0 | I29: 0 | J29: =H29*I29 -> 0 | K29: =G29+J29 -> 0 | L29: =+K29 -> 0 | M29: 0
A30: 27 | B30: 45684 | G30: =E30*F30 -> 0 | H30: 0 | I30: 0 | J30: =H30*I30 -> 0 | K30: =G30+J30 -> 0 | L30: =+K30 -> 0 | M30: 0
A31: 28 | B31: 45685 | G31: =E31*F31 -> 0 | H31: 0 | I31: 0 | J31: =H31*I31 -> 0 | K31: =G31+J31 -> 0 | L31: =+K31 -> 0 | M31: 0
A32: 29 | B32: 45686 | G32: =E32*F32 -> 0 | H32: 0 | I32: 0 | J32: =H32*I32 -> 0 | K32: =G32+J32 -> 0 | L32: =+K32 -> 0 | M32: 0
A33: 30 | B33: 45687 | E33: 36.13 | F33: 96.83 | G33: =E33*F33 -> 3498.4679 | H33: 0 | I33: 0 | J33: =H33*I33 -> 0 | K33: =G33+J33 -> 3498.4679 | L33: =+K33 -> 3498.4679 | M33: 0
A34: 31 | B34: 45688 | G34: =E34*F34 -> 0 | H34: 0 | I34: 0 | J34: =H34*I34 -> 0 | K34: =G34+J34 -> 0 | L34: =+K34 -> 0 | M34: 0
E35: =SUM(E4:E34) -> 36.13 | G35: =SUM(G4:G34) -> 3498.4679 | H35: =SUM(H4:H34) -> 0 | J35: =SUM(J4:J34) -> 0 | K35: =SUM(K4:K34) -> 3498.4679 | L35: =SUM(L4:L34) -> 3498.4679

Sheet Amalapuram
A1: Sri venkateswara Enterprises | B1: Yanam | C1: 42.18 | D1: 86.75 | E1: 3659.12 | F1: 5 | G1: 96.91 | H1: 484.55 | I1: 4143.67
A2: S.No | B2: Date | C2: GRN No | D2: Ind no/Bill No | E2: Diesel (Lts) | F2: Price | G2: Amount | H2: Petrol (Lts) | I2: Price | J2: Amount | K2: Total amount | L2: Amount paid | M2: As on Date | N2: Remarks
A3: Opening Balance | M3: 0
A4: 1 | C4: Sri venkateswara Enterprises | D4: Yanam | E4: 67.3 | F4: 86.75 | G4: =E4*F4 -> 5838.275 | H4: 5 | I4: 96.91 | J4: =H4*I4 -> 484.55 | K4: =G4+J4 -> 6322.825 | L4: 6322.83 | M4: =+M3+K4-L4 -> -0.005
A5: 2 | G5: =E5*F5 -> 0 | H5: 0 | I5: 0 | J5: =H5*I5 -> 0 | K5: =G5+J5 -> 0 | M5: =+M4+K5-L5 -> -0.005
A6: 3 | G6: =E6*F6 -> 0 | H6: 0 | I6: 0 | J6: =H6*I6 -> 0 | K6: =G6+J6 -> 0 | M6: =+M5+K6-L6 -> -0.005
A7: 4 | G7: =E7*F7 -> 0 | H7: 0 | I7: 0 | J7: =H7*I7 -> 0 | K7: =G7+J7 -> 0 | M7: =+M6+K7-L7 -> -0.005
A8: 5 | G8: =E8*F8 -> 0 | H8: 0 | I8: 0 | J8: =H8*I8 -> 0 | K8: =G8+J8 -> 0 | M8: =+M7+K8-L8 -> -0.005
A9: 6 | C9: Sri venkateswara Enterprises | D9: Yanam | E9: 42.18 | F9: 86.75 | G9: 3659.12 | H9: 5 | I9: 96.91 | J9: 484.55 | K9: 4143.67 | L9: 4143.67 | M9: =+M8+K9-L9 -> -0.005
A10: 7 | G10: =E10*F10 -> 0 | H10: 0 | I10: 0 | J10: =H10*I10 -> 0 | K10: =G10+J10 -> 0 | M10: =+M9+K10-L10 -> -0.005
A11: 8 | C11: BP Kakinada (coco) | D11: Kakinada | E11: 0 | H11: 5 | I11: 109.94 | J11: 550 | K11: 550 | L11: 550 | M11: =+M10+K11-L11 -> -0.005
A12: 9 | G12: =E12*F12 -> 0 | H12: 0 | I12: 0 | J12: =H12*I12 -> 0 | K12: =G12+J12 -> 0 | M12: =+M11+K12-L12 -> -0.005
A13: 10 | G13: =E13*F13 -> 0 | H13: 0 | I13: 0 | J13: =H13*I13 -> 0 | K13: =G13+J13 -> 0 | M13: =+M12+K13-L13 -> -0.005
A14: 11 | G14: =E14*F14 -> 0 | H14: 0 | I14: 0 | J14: =H14*I14 -> 0 | K14: =G14+J14 -> 0 | M14: =+M13+K14-L14 -> -0.005
A15: 12 | G15: =E15*F15 -> 0 | H15: 0 | I15: 0 | J15: =H15*I15 -> 0 | K15: =G15+J15 -> 0 | M15: =+M14+K15-L15 -> -0.005
A16: 13 | G16: =E16*F16 -> 0 | H16: 0 | I16: 0 | J16: =H16*I16 -> 0 | K16: =G16+J16 -> 0 | M16: =+M15+K16-L16 -> -0.005
A17: 14 | G17: =E17*F17 -> 0 | H17: 0 | I17: 0 | J17: =H17*I17 -> 0 | K17: =G17+J17 -> 0 | M17: =+M16+K17-L17 -> -0.005
A18: 15 | G18: =E18*F18 -> 0 | H18: 0 | I18: 0 | J18: =H18*I18 -> 0 | K18: =G18+J18 -> 0 | M18: =+M16+K18-L18 -> -0.005
A19: 16 | G19: =E19*F19 -> 0 | H19: 0 | I19: 0 | J19: =H19*I19 -> 0 | K19: =G19+J19 -> 0 | M19: =+M18+K19-L19 -> -0.005
A20: 17 | G20: =E20*F20 -> 0 | H20: 0 | I20: 0 | J20: =H20*I20 -> 0 | K20: =G20+J20 -> 0 | M20: =+M19+K20-L20 -> -0.005
A21: 18 | G21: =E21*F21 -> 0 | H21: 0 | I21: 0 | J21: =H21*I21 -> 0 | K21: =G21+J21 -> 0 | M21: =+M20+K21-L21 -> -0.005
A22: 19 | C22: Sree Suryaprakash Service Station | D22: Rajahmundry | E22: 42.38 | F22: 96.74 | G22: =E22*F22 -> 4099.8412 | H22: 5 | I22: 108.86 | J22: =H22*I22 -> 544.3 | K22: =G22+J22 -> 4644.1412 | L22: 4644.14 | M22: =+M21+K22-L22 -> -0.0038
A23: 20 | C23: BP Lalacheruvu,BPCL | D23: Rajahmundry | G23: =E23*F23 -> 0 | H23: 0 | I23: 0 | J23: =H23*I23 -> 0 | K23: =G23+J23 -> 0 | M23: =+M22+K23-L23 -> -0.0038
A24: 21 | G24: =E24*F24 -> 0 | H24: 0 | I24: 0 | J24: =H24*I24 -> 0 | K24: =G24+J24 -> 0 | M24: =+M23+K24-L24 -> -0.0038
A25: 22 | C25: BP Lalacheruvu,BPCL | D25: Rajahmundry | E25: 45.62 | F25: 96.74 | G25: =E25*F25 -> 4413.2788 | H25: 0 | I25: 0 | J25: =H25*I25 -> 0 | K25: =G25+J25 -> 4413.2788 | L25: 4413.28 | M25: =+M24+K25-L25 -> -0.005
A26: 23 | C26: BP Lalacheruvu,BPCL | D26: Rajahmundry | H26: 5 | I26: 108.86 | J26: =H26*I26 -> 544.3 | K26: =G26+J26 -> 544.3 | L26: 544.3 | M26: =+M25+K26-L26 -> -0.005
A27: 24 | C27: Sri venkateswara Enterprises | D27: Yanam | E27: 36.87 | F27: 86.75 | G27: 3198.47 | H27: 21 | I27: 96.91 | J27: 2035.11 | K27: 5233.58 | L27: 5233.58 | M27: =+M26+K27-L27 -> -0.005
A28: 25 | G28: =E28*F28 -> 0 | H28: 0 | I28: 0 | J28: =H28*I28 -> 0 | K28: =G28+J28 -> 0 | M28: =+M27+K28-L28 -> -0.005
A29: 26 | G29: =E29*F29 -> 0 | H29: 0 | I29: 0 | J29: =H29*I29 -> 0 | K29: =G29+J29 -> 0 | M29: =+M28+K29-L29 -> -0.005
A30: 27 | C30: Padma Highway Filling Station | D30: Yanam | E30: 0 | H30: 5.76 | I30: 86.75 | J30: 499.68 | K30: 500 | L30: 500 | M30: =+M29+K30-L30 -> -0.005
A31: 28 | C31: APSRTC Petrol Bunk | D31: Rangampeta | E31: 0 | H31: 5 | I31: 108.79 | J31: 543.95 | K31: 543.95 | L31: 543.95 | M31: =+M30+K31-L31 -> -0.005
A32: 29 | G32: =E32*F32 -> 0 | H32: 0 | I32: 0 | J32: =H32*I32 -> 0 | K32: =G32+J32 -> 0 | M32: =+M31+K32-L32 -> -0.005
A33: 30 | C33: CSR VANA Durga Filling Station | D33: Vijayawada | E33: 50.02 | F33: 96.87 | G33: 4845.44 | K33: 4845.44 | L33: 4845.44 | M33: =+M32+K33-L33 -> -0.005
A34: 30 | C34: Indian Oil | D34: Yanam | E34: 0 | H34: 5.76 | I34: 86.75 | J34: 500 | K34: 500 | L34: 500 | M34: =+M33+K34-L34 -> -0.005
A35: 31 | G35: =E35*F35 -> 0 | H35: 5 | I35: 110.05 | J35: =H35*I35 -> 550.25 | K35: =G35+J35 -> 550.25 | L35: 550.25 | M35: =+M34+K35-L35 -> -0.005
A36: 32 | G36: =E36*F36 -> 0 | H36: 0 | I36: 0 | J36: =H36*I36 -> 0 | K36: =G36+J36 -> 0 | M36: =+M35+K36-L36 -> -0.005
A37: 33 | G37: =E37*F37 -> 0 | H37: 0 | I37: 0 | J37: =H37*I37 -> 0 | K37: =G37+J37 -> 0 | M37: =+M36+K37-L37 -> -0.005
E38: =SUM(E4:E37) -> 284.37 | G38: =SUM(G4:G37) -> 26054.425 | H38: =SUM(H4:H37) -> 67.52 | J38: =SUM(J4:J37) -> 6736.69 | K38: =SUM(K4:K37) -> 32791.435 | L38: =SUM(L4:L37) -> 32791.44

Sheet Madana palli
A2: S.No | B2: Date | C2: GRN No | D2: Ind no/Bill No | E2: Diesel (Lts) | F2: Price | G2: Amount | H2: Petrol (Lts) | I2: Price | J2: Amount | K2: Total amount | L2: Amount paid | M2: As on Date | N2: Remarks
A3: Opening Balance | M3: 0
A4: 1 | B4: 46023 | G4: =E4*F4 -> 0 | H4: 0 | I4: 0 | J4: =H4*I4 -> 0 | K4: =G4+J4 -> 0 | L4: =+K4 -> 0 | M4: 0
A5: 2 | B5: 46024 | G5: =E5*F5 -> 0 | H5: 2.74 | I5: 109.61 | J5: =H5*I5 -> 300.3314 | K5: =G5+J5 -> 300.3314 | L5: =+K5 -> 300.3314 | M5: 0
A6: 3 | B6: 46025 | G6: =E6*F6 -> 0 | H6: 0 | I6: 0 | J6: =H6*I6 -> 0 | K6: =G6+J6 -> 0 | L6: =+K6 -> 0 | M6: 0
A7: 4 | B7: 46026 | G7: =E7*F7 -> 0 | H7: 0 | I7: 0 | J7: =H7*I7 -> 0 | K7: =G7+J7 -> 0 | L7: =+K7 -> 0 | M7: 0
A8: 5 | B8: 46027 | G8: =E8*F8 -> 0 | H8: 0 | I8: 0 | J8: =H8*I8 -> 0 | K8: =G8+J8 -> 0 | L8: =+K8 -> 0 | M8: 0
A9: 6 | B9: 46028 | G9: =E9*F9 -> 0 | H9: 0 | I9: 0 | J9: =H9*I9 -> 0 | K9: =G9+J9 -> 0 | L9: =+K9 -> 0 | M9: 0
A10: 7 | B10: 46029 | G10: =E10*F10 -> 0 | H10: 2.73 | I10: 109.61 | J10: =H10*I10 -> 299.2353 | K10: =G10+J10 -> 299.2353 | L10: =+K10 -> 299.2353 | M10: 0 | O10: 169.99
A11: 8 | B11: 46030 | G11: =E11*F11 -> 0 | H11: 0 | I11: 0 | J11: =H11*I11 -> 0 | K11: =G11+J11 -> 0 | L11: =+K11 -> 0 | M11: 0 | O11: 80
A12: 9 | B12: 46031 | G12: =E12*F12 -> 0 | H12: 0 | I12: 0 | J12: =H12*I12 -> 0 | K12: =G12+J12 -> 0 | L12: =+K12 -> 0 | M12: 0 | O12: =SUM(O10:O11) -> 249.99 | P12: 97.76 | Q12: =O12*P12 -> 24439.022
A13: 10 | B13: 46032 | G13: =E13*F13 -> 0 | H13: 0 | I13: 0 | J13: =H13*I13 -> 0 | K13: =G13+J13 -> 0 | L13: =+K13 -> 0 | M13: 0
A14: 11 | B14: 46033 | G14: =E14*F14 -> 0 | H14: 0 | I14: 0 | J14: =H14*I14 -> 0 | K14: =G14+J14 -> 0 | L14: =+K14 -> 0 | M14: 0
A15: 12 | B15: 46034 | G15: =E15*F15 -> 0 | H15: 0 | I15: 0 | J15: =H15*I15 -> 0 | K15: =G15+J15 -> 0 | L15: =+K15 -> 0 | M15: 0 | P15: 7820.8
A16: 13 | B16: 46035 | G16: =E16*F16 -> 0 | H16: 0 | I16: 109.61 | J16: =H16*I16 -> 0 | K16: =G16+J16 -> 0 | L16: =+K16 -> 0 | M16: 0 | P16: 16619.2
A17: 14 | B17: 46036 | G17: =E17*F17 -> 0 | H17: 0 | I17: 0 | J17: =H17*I17 -> 0 | K17: =G17+J17 -> 0 | L17: =+K17 -> 0 | M17: 0 | P17: =SUM(P15:P16) -> 24440
A18: 15 | B18: 46037 | G18: =E18*F18 -> 0 | H18: 0 | I18: 0 | J18: =H18*I18 -> 0 | K18: =G18+J18 -> 0 | L18: =+K18 -> 0 | M18: 0
A19: 16 | B19: 46038 | G19: =E19*F19 -> 0 | H19: 0 | I19: 0 | J19: =H19*I19 -> 0 | K19: =G19+J19 -> 0 | L19: =+K19 -> 0 | M19: 0
A20: 17 | B20: 46039 | G20: =E20*F20 -> 0 | H20: 0 | I20: 0 | J20: =H20*I20 -> 0 | K20: =G20+J20 -> 0 | L20: =+K20 -> 0 | M20: 0
A21: 18 | B21: 46040 | G21: =E21*F21 -> 0 | H21: 0 | I21: 0 | J21: =H21*I21 -> 0 | K21: =G21+J21 -> 0 | L21: =+K21 -> 0 | M21: 0
A22: 19 | B22: 46041 | G22: =E22*F22 -> 0 | H22: 0 | I22: 0 | J22: =H22*I22 -> 0 | K22: =G22+J22 -> 0 | L22: =+K22 -> 0 | M22: 0
A23: 20 | B23: 46042 | G23: =E23*F23 -> 0 | H23: 5.79 | I23: 109.61 | J23: =H23*I23 -> 634.6419 | K23: =G23+J23 -> 634.6419 | L23: =+K23 -> 634.6419 | M23: 0
A24: 21 | B24: 46043 | G24: =E24*F24 -> 0 | H24: 0 | I24: 0 | J24: =H24*I24 -> 0 | K24: =G24+J24 -> 0 | L24: =+K24 -> 0 | M24: 0
A25: 22 | B25: 46044 | G25: =E25*F25 -> 0 | H25: 0 | I25: 0 | J25: =H25*I25 -> 0 | K25: =G25+J25 -> 0 | L25: =+K25 -> 0 | M25: 0
A26: 23 | B26: 46045 | G26: =E26*F26 -> 0 | H26: 0 | I26: 0 | J26: =H26*I26 -> 0 | K26: =G26+J26 -> 0 | L26: =+K26 -> 0 | M26: 0
A27: 24 | B27: 46046 | G27: =E27*F27 -> 0 | H27: 0 | I27: 0 | J27: =H27*I27 -> 0 | K27: =G27+J27 -> 0 | L27: =+K27 -> 0 | M27: 0
A28: 25 | B28: 46047 | E28: 20.52 | F28: 97.43 | G28: =E28*F28 -> 1999.2636 | H28: 5.66 | I28: 109.61 | J28: =H28*I28 -> 620.3926 | K28: =G28+J28 -> 2619.6562 | L28: =+K28 -> 2619.6562 | M28: 0
A29: 26 | B29: 46048 | G29: =E29*F29 -> 0 | H29: 0 | I29: 0 | J29: =H29*I29 -> 0 | K29: =G29+J29 -> 0 | L29: =+K29 -> 0 | M29: 0
A30: 27 | B30: 46049 | G30: =E30*F30 -> 0 | H30: 0 | I30: 0 | J30: =H30*I30 -> 0 | K30: =G30+J30 -> 0 | L30: =+K30 -> 0 | M30: 0
A31: 28 | B31: 46050 | G31: =E31*F31 -> 0 | H31: 0 | I31: 0 | J31: =H31*I31 -> 0 | K31: =G31+J31 -> 0 | L31: =+K31 -> 0 | M31: 0
A32: 29 | B32: 46051 | G32: =E32*F32 -> 0 | H32: 0 | I32: 0 | J32: =H32*I32 -> 0 | K32: =G32+J32 -> 0 | L32: =+K32 -> 0 | M32: 0
A33: 30 | B33: 46052 | G33: =E33*F33 -> 0 | H33: 0 | I33: 0 | J33: =H33*I33 -> 0 | K33: =G33+J33 -> 0 | L33: =+K33 -> 0 | M33: 0
A34: 31 | B34: 46053 | G34: =E34*F34 -> 0 | H34: 0 | I34: 0 | J34: =H34*I34 -> 0 | K34: =G34+J34 -> 0 | L34: =+K34 -> 0 | M34: 0
E35: =SUM(E4:E34) -> 20.52 | G35: =SUM(G4:G34) -> 1999.2636 | H35: =SUM(H4:H34) -> 16.92 | J35: =SUM(J4:J34) -> 1854.6012 | K35: =SUM(K4:K34) -> 3853.8648 | L35: =SUM(L4:L34) -> 3853.8648

Sheet Kadur
A1: Vishal Service Station
A2: S.No | B2: Date | C2: GRN No | D2: Ind No/Bill No | E2: Diesel (Lts) | F2: Price | G2: Amount | H2: Petrol (Lts) | I2: Price | J2: Amount | K2: Total amount | L2: Amount paid | M2: As on Date | N2: Remarks
A3: Opening Balance | K3: 210029.23 | M3: 210029.23 | O3: 207239.43
A4: 1 | B4: 45992 | F4: 0 | G4: =E4*F4 -> 0 | H4: 0 | I4: 0 | J4: =H4*I4 -> 0 | K4: =G4+J4 -> 0 | M4: =M3+K4-L4 -> 210029.23
A5: 2 | B5: 45993 | F5: 0 | G5: =E5*F5 -> 0 | H5: 0 | I5: 0 | J5: =H5*I5 -> 0 | K5: =G5+J5 -> 0 | M5: =M4+K5-L5 -> 210029.23
A6: 3 | B6: 45994 | F6: 0 | G6: =E6*F6 -> 0 | H6: 0 | I6: 0 | J6: =H6*I6 -> 0 | K6: =G6+J6 -> 0 | M6: =M5+K6-L6 -> 210029.23
A7: 4 | B7: 45995 | F7: 0 | G7: =E7*F7 -> 0 | H7: 0 | I7: 0 | J7: =H7*I7 -> 0 | K7: =G7+J7 -> 0 | M7: =M6+K7-L7 -> 210029.23
A8: 5 | B8: 45996 | F8: 0 | G8: =E8*F8 -> 0 | H8: 0 | I8: 0 | J8: =H8*I8 -> 0 | K8: =G8+J8 -> 0 | M8: =M7+K8-L8 -> 210029.23
A9: 6 | B9: 45997 | F9: 0 | G9: =E9*F9 -> 0 | H9: 0 | I9: 0 | J9: =H9*I9 -> 0 | K9: =G9+J9 -> 0 | M9: =M8+K9-L9 -> 210029.23
A10: 7 | B10: 45998 | F10: 0 | G10: =E10*F10 -> 0 | H10: 0 | I10: 0 | J10: =H10*I10 -> 0 | K10: =G10+J10 -> 0 | M10: =M9+K10-L10 -> 210029.23
A11: 8 | B11: 45999 | F11: 0 | G11: =E11*F11 -> 0 | H11: 0 | I11: 0 | J11: =H11*I11 -> 0 | K11: =G11+J11 -> 0 | M11: =M10+K11-L11 -> 210029.23
A12: 9 | B12: 46000 | F12: 0 | G12: =E12*F12 -> 0 | H12: 0 | I12: 0 | J12: =H12*I12 -> 0 | K12: =G12+J12 -> 0 | M12: =M11+K12-L12 -> 210029.23
A13: 10 | B13: 46001 | F13: 0 | G13: =E13*F13 -> 0 | H13: 0 | I13: 0 | J13: =H13*I13 -> 0 | K13: =G13+J13 -> 0 | M13: =M12+K13-L13 -> 210029.23
A14: 11 | B14: 46002 | F14: 0 | G14: =E14*F14 -> 0 | H14: 0 | I14: 0 | J14: =H14*I14 -> 0 | K14: =G14+J14 -> 0 | M14: =M13+K14-L14 -> 210029.23
A15: 12 | B15: 46003 | F15: 0 | G15: =E15*F15 -> 0 | H15: 0 | I15: 0 | J15: =H15*I15 -> 0 | K15: =G15+J15 -> 0 | M15: =M14+K15-L15 -> 210029.23
... A19: 16 | B19: 46007 | F19: 0 | G19: =E19*F19 -> 0 | H19: 0 | I19: 0 | J19: =H19*I19 -> 0 | K19: =G19+J19 -> 0 | M19: =M18+K19-L19 -> 210029.23
A20: 17 | B20: 46008 | F20: 0 | G20: =E20*F20 -> 0 | H20: 140 | I20: 104.27 | J20: =H20*I20 -> 14597.8 | K20: =G20+J20 -> 14597.8 | L20: 210000 | M20: =M19+K20-L20 -> 14627.031 | N20: 14492 | O20: =M20-N20 -> 135.031
A21: 18 | B21: 46009 | F21: 0 | G21: =E21*F21 -> 0 | H21: 0 | I21: 0 | J21: =H21*I21 -> 0 | K21: =G21+J21 -> 0 | M21: =M20+K21-L21 -> 14627.031
A22: 19 | B22: 46010 | F22: 0 | H22: 0 | I22: 0 | J22: =H22*I22 -> 0 | K22: =G22+J22 -> 0 | M22: =M21+K22-L22 -> 14627.031
A23: 20 | B23: 46011 | F23: 0 | J23: =H23*I23 -> 0 | K23: =G23+J23 -> 0 | M23: =M22+K23-L23 -> 14627.031
A24: 21 | B24: 46012 | F24: 0 | J24: =H24*I24 -> 0 | K24: =G24+J24 -> 0 | M24: =M23+K24-L24 -> 14627.031
A25: 22 | B25: 46013 | F25: 0 | J25: =H25*I25 -> 0 | K25: =G25+J25 -> 0 | M25: =M24+K25-L25 -> 14627.031
A26: 23 | B26: 46014 | F26: 0 | J26: =H26*I26 -> 0 | K26: =G26+J26 -> 0 | M26: =M25+K26-L26 -> 14627.031
A27: 24 | B27: 46015 | F27: 0 | J27: =H27*I27 -> 0 | K27: =G27+J27 -> 0 | M27: =M26+K27-L27 -> 14627.031
A28: 25 | B28: 46016 | F28: 0 | J28: =H28*I28 -> 0 | K28: =G28+J28 -> 0 | M28: =M27+K28-L28 -> 14627.031
A29: 26 | B29: 46017 | F29: 0 | J29: =H29*I29 -> 0 | K29: =G29+J29 -> 0 | M29: =M28+K29-L29 -> 14627.031
A30: 27 | B30: 46018 | F30: 0 | J30: =H30*I30 -> 0 | K30: =G30+J30 -> 0 | M30: =M29+K30-L30 -> 14627.031
A31: 28 | B31: 46019 | F31: 0 | J31: =H31*I31 -> 0 | K31: =G31+J31 -> 0 | M31: =M30+K31-L31 -> 14627.031
A32: 29 | B32: 46020 | F32: 0 | G32: =E32*F32 -> 0 | H32: 0 | I32: 0 | J32: =H32*I32 -> 0 | K32: =G32+J32 -> 0 | M32: =M31+K32-L32 -> 14627.031
A33: 30 | B33: 46021 | F33: 0 | G33: =E33*F33 -> 0 | H33: 0 | I33: 0 | J33: =H33*I33 -> 0 | K33: =G33+J33 -> 0 | M33: =M32+K33-L33 -> 14627.031
A34: 31 | F34: 0 | G34: =E34*F34 -> 0 | J34: =H34*I34 -> 0 | K34: =G34+J34 -> 0
E35: =SUM(E4:E34) -> 0 | G35: =SUM(G4:G34) -> 0 | H35: =SUM(H4:H34) -> 140 | J35: =SUM(J4:J34) -> 14597.8 | K35: =SUM(K4:K34) -> 14597.8 | L35: =SUM(L4:L31) -> 210000

Sheet YG Gudda 
A1: Pallavi Petrolium
A2: S.No | B2: Date | C2: GRN No | D2: Ind No/Bill No | E2: Diesel (Lts) | F2: Price | G2: Amount | H2: Petrol (Lts) | I2: Price | J2: Amount | K2: Total amount | L2: Amount paid | M2: As on Date | N2: Remarks
A3: Opening Balance | K3: 21.541514 | M3: 21.541514
A4: 1 | B4: 46023 | G4: =E4*F4 -> 0 | J4: =H4*I4 -> 0 | K4: =G4+J4 -> 0 | M4: =M3+K4-L4 -> 21.541514
A5: 2 | B5: 46024 | G5: =E5*F5 -> 0 | J5: =H5*I5 -> 0 | K5: =G5+J5 -> 0 | L5: 21.54 | M5: =M4+K5-L5 -> 0.0015138002 | N5: Rounoff
A6: 3 | B6: 46025 | G6: =E6*F6 -> 0 | J6: =H6*I6 -> 0 | K6: =G6+J6 -> 0 | M6: =M5+K6-L6 -> 0.0015138002
A7: 4 | B7: 46026 | G7: =E7*F7 -> 0 | J7: =H7*I7 -> 0 | K7: =G7+J7 -> 0 | M7: =M6+K7-L7 -> 0.0015138002
A8: 5 | B8: 46027 | G8: =E8*F8 -> 0 | J8: =H8*I8 -> 0 | K8: =G8+J8 -> 0 | M8: =M7+K8-L8 -> 0.0015138002
A9: 6 | B9: 46028 | G9: =E9*F9 -> 0 | J9: =H9*I9 -> 0 | K9: =G9+J9 -> 0 | M9: =M8+K9-L9 -> 0.0015138002
A10: 7 | B10: 46029 | G10: =E10*F10 -> 0 | J10: =H10*I10 -> 0 | K10: =G10+J10 -> 0 | M10: =M9+K10-L10 -> 0.0015138002
A11: 8 | B11: 46030 | G11: =E11*F11 -> 0 | J11: =H11*I11 -> 0 | K11: =G11+J11 -> 0 | M11: =M10+K11-L11 -> 0.0015138002
A12: 9 | B12: 46031 | G12: =E12*F12 -> 0 | J12: =H12*I12 -> 0 | K12: =G12+J12 -> 0 | M12: =M11+K12-L12 -> 0.0015138002
A13: 10 | B13: 46032 | G13: =E13*F13 -> 0 | J13: =H13*I13 -> 0 | K13: =G13+J13 -> 0 | M13: =M12+K13-L13 -> 0.0015138002
A14: 11 | B14: 46033 | G14: =E14*F14 -> 0 | J14: =H14*I14 -> 0 | K14: =G14+J14 -> 0 | M14: =M13+K14-L14 -> 0.0015138002
A15: 12 | B15: 46034 | G15: =E15*F15 -> 0 | J15: =H15*I15 -> 0 | K15: =G15+J15 -> 0 | M15: =M14+K15-L15 -> 0.0015138002
A16: 13 | B16: 46035 | G16: =E16*F16 -> 0 | J16: =H16*I16 -> 0 | K16: =G16+J16 -> 0 | M16: =M15+K16-L16 -> 0.0015138002
A17: 14 | B17: 46036 | G17: =E17*F17 -> 0 | J17: =H17*I17 -> 0 | K17: =G17+J17 -> 0 | M17: =M16+K17-L17 -> 0.0015138002
... A34: 31 | B34: 46053 | G34: =E34*F34 -> 0 | J34: =H34*I34 -> 0 | K34: =G34+J34 -> 0 | M34: =M33+K34-L34 -> 0.0015138002
A35: 32 | E35: 0 | F35: 0 | G35: =E35*F35 -> 0 | J35: =H35*I35 -> 0 | K35: =G35+J35 -> 0 | M35: =M34+K35-L35 -> 0.0015138002
E36: =SUM(E4:E35) -> 0 | G36: =SUM(G4:G35) -> 0 | H36: =SUM(H4:H35) -> 0 | J36: =SUM(J4:J35) -> 0 | K36: =SUM(K4:K35) -> 0 | L36: =SUM(L4:L35) -> 21.54

Sheet YG Gudda-2
A1: Pankaja HP Fuel Center
A2: S.No | B2: Date | C2: GRN No | D2: Ind No/Bill No | E2: Diesel (Lts) | F2: Price | G2: Amount | H2: Petrol (Lts) | I2: Price | J2: Amount | K2: Total amount | L2: Amount paid | M2: As on Date | N2: Remarks
A3: Opening Balance | K3: 713890.2 | M3: =+K3 -> 713890.2 | O3: 99992.615
A4: 1 | B4: 46023 | G4: =E4*F4 -> 0 | J4: =H4*I4 -> 0 | K4: =G4+J4 -> 0 | M4: =M3+K4-L4 -> 713890.2
A5: 2 | B5: 46024 | G5: =E5*F5 -> 0 | J5: =H5*I5 -> 0 | K5: =G5+J5 -> 0 | M5: =M4+K5-L5 -> 713890.2
A6: 3 | B6: 46025 | G6: =E6*F6 -> 0 | J6: =H6*I6 -> 0 | K6: =G6+J6 -> 0 | M6: =M5+K6-L6 -> 713890.2
A7: 4 | B7: 46026 | G7: =E7*F7 -> 0 | J7: =H7*I7 -> 0 | K7: =G7+J7 -> 0 | M7: =M6+K7-L7 -> 713890.2 | O7: 1 | P7: Bill No
A8: 5 | B8: 46027 | G8: =E8*F8 -> 0 | J8: =H8*I8 -> 0 | K8: =G8+J8 -> 0 | M8: =M7+K8-L8 -> 713890.2
A9: 6 | B9: 46028 | E9: 600 | F9: 91.33 | G9: =E9*F9 -> 54798 | H9: 50 | I9: 103.27 | J9: =H9*I9 -> 5163.5 | K9: =G9+J9 -> 59961.5 | L9: 59961.5 | M9: =M8+K9-L9 -> 713890.2
A10: 7 | B10: 46029 | G10: =E10*F10 -> 0 | J10: =H10*I10 -> 0 | K10: =G10+J10 -> 0 | M10: =M9+K10-L10 -> 713890.2
A11: 8 | B11: 46030 | G11: =E11*F11 -> 0 | J11: =H11*I11 -> 0 | K11: =G11+J11 -> 0 | L11: 400000 | M11: =M10+K11-L11 -> 313890.2
A12: 9 | B12: 46031 | E12: 1000 | F12: 91.33 | G12: =E12*F12 -> 91330 | H12: 35 | I12: 103.27 | J12: =H12*I12 -> 3614.45 | K12: =G12+J12 -> 94944.45 | M12: =M11+K12-L12 -> 408834.65 | O12: 2 | P12: Bill No
A13: 10 | B13: 46032 | G13: =E13*F13 -> 0 | J13: =H13*I13 -> 0 | K13: =G13+J13 -> 0 | M13: =M12+K13-L13 -> 408834.65
A14: 11 | B14: 46033 | G14: =E14*F14 -> 0 | J14: =H14*I14 -> 0 | K14: =G14+J14 -> 0 | M14: =M13+K14-L14 -> 408834.65
A15: 12 | B15: 46034 | E15: 1020 | F15: 91.33 | G15: =E15*F15 -> 93156.6 | J15: =H15*I15 -> 0 | K15: =G15+J15 -> 93156.6 | M15: =M14+K15-L15 -> 501991.25
A16: 13 | B16: 46035 | G16: =E16*F16 -> 0 | J16: =H16*I16 -> 0 | K16: =G16+J16 -> 0 | L16: 300000 | M16: =M15+K16-L16 -> 201991.25 | O16: 3 | P16: Bill No
A17: 14 | B17: 46036 | G17: =E17*F17 -> 0 | J17: =H17*I17 -> 0 | K17: =G17+J17 -> 0 | M17: =M16+K17-L17 -> 201991.25
A18: 15 | B18: 46037 | G18: =E18*F18 -> 0 | J18: =H18*I18 -> 0 | K18: =G18+J18 -> 0 | M18: =M17+K18-L18 -> 201991.25
A19: 16 | B19: 46038 | E19: 2000 | F19: 91.33 | G19: =E19*F19 -> 182660 | H19: 70 | I19: 103.27 | J19: =H19*I19 -> 7228.9 | K19: =G19+J19 -> 189888.9 | M19: =M18+K19-L19 -> 391880.15
A20: 17 | B20: 46039 | G20: =E20*F20 -> 0 | J20: =H20*I20 -> 0 | K20: =G20+J20 -> 0 | L20: 391880 | M20: =M19+K20-L20 -> 0.152903
A21: 18 | B21: 46040 | G21: =E21*F21 -> 0 | J21: =H21*I21 -> 0 | K21: =G21+J21 -> 0 | M21: =M20+K21-L21 -> 0.152903
A22: 19 | B22: 46041 | G22: =E22*F22 -> 0 | J22: =H22*I22 -> 0 | K22: =G22+J22 -> 0 | M22: =M21+K22-L22 -> 0.152903
A23: 20 | B23: 46042 | G23: =E23*F23 -> 0 | J23: =H23*I23 -> 0 | K23: =G23+J23 -> 0 | M23: =M22+K23-L23 -> 0.152903
A24: 21 | B24: 46043 | E24: 2000 | F24: 91.33 | G24: =E24*F24 -> 182660 | H24: 70 | I24: 103.27 | J24: =H24*I24 -> 7228.9 | K24: =G24+J24 -> 189888.9 | M24: =M23+K24-L24 -> 189889.05 | O24: 4 | P24: Bill No
A25: 22 | B25: 46044 | G25: =E25*F25 -> 0 | J25: =H25*I25 -> 0 | K25: =G25+J25 -> 0 | M25: =M24+K25-L25 -> 189889.05
A26: 23 | B26: 46045 | G26: =E26*F26 -> 0 | J26: =H26*I26 -> 0 | K26: =G26+J26 -> 0 | M26: =M25+K26-L26 -> 189889.05
A27: 24 | B27: 46046 | G27: =E27*F27 -> 0 | J27: =H27*I27 -> 0 | K27: =G27+J27 -> 0 | M27: =M26+K27-L27 -> 189889.05
A28: 25 | B28: 46047 | G28: =E28*F28 -> 0 | J28: =H28*I28 -> 0 | K28: =G28+J28 -> 0 | M28: =M27+K28-L28 -> 189889.05
A29: 26 | B29: 46048 | G29: =E29*F29 -> 0 | J29: =H29*I29 -> 0 | K29: =G29+J29 -> 0 | M29: =M28+K29-L29 -> 189889.05
A30: 27 | B30: 46049 | G30: =E30*F30 -> 0 | J30: =H30*I30 -> 0 | K30: =G30+J30 -> 0 | M30: =M29+K30-L30 -> 189889.05
A31: 28 | B31: 46050 | E31: 1000 | F31: 91.33 | G31: =E31*F31 -> 91330 | H31: 70 | I31: 103.27 | J31: =H31*I31 -> 7228.9 | K31: =G31+J31 -> 98558.9 | M31: =M30+K31-L31 -> 288447.95
A32: 29 | B32: 46051 | G32: =E32*F32 -> 0 | J32: =H32*I32 -> 0 | K32: =G32+J32 -> 0 | M32: =M31+K32-L32 -> 288447.95
A33: 30 | B33: 46052 | E33: 2000 | F33: 91.33 | G33: =E33*F33 -> 182660 | H33: 70 | I33: 103.27 | J33: =H33*I33 -> 7228.9 | K33: =G33+J33 -> 189888.9 | M33: =M32+K33-L33 -> 478336.85
A34: 31 | B34: 46053 | G34: =E34*F34 -> 0 | J34: =H34*I34 -> 0 | K34: =G34+J34 -> 0 | M34: =M33+K34-L34 -> 478336.85
A35: 32 | G35: =E35*F35 -> 0 | H35: 0 | I35: 0 | J35: =H35*I35 -> 0 | K35: =G35+J35 -> 0 | M35: =M34+K35-L35 -> 478336.85
E36: =SUM(E4:E35) -> 9620 | G36: =SUM(G4:G35) -> 878594.6 | H36: =SUM(H4:H35) -> 365 | J36: =SUM(J4:J35) -> 37693.55 | K36: =SUM(K4:K35) -> 916288.15 | L36: =SUM(L4:L35) -> 1151841.5

Sheet Hosadurga
A1: Merchant Petroliums
A2: S.No | B2: Date | C2: GRN No | D2: Ind No/Bill No | E2: Diesel (Lts) | F2: Price | G2: Amount | H2: Petrol (Lts) | I2: Price | J2: Amount | K2: Total amount | L2: Amount paid | M2: As on Date | N2: Remarks
A3: Opening Balance | K3: 2258.6 | M3: =+K3 -> 2258.6
A4: 1 | B4: 46023 | G4: =E4*F4 -> 0 | H4: 0 | J4: =H4*I4 -> 0 | K4: =G4+J4 -> 0 | L4: 0 | M4: =M3+K4-L4 -> 2258.6
A5: 2 | B5: 46024 | G5: =E5*F5 -> 0 | H5: 0 | I5: 0 | J5: =H5*I5 -> 0 | K5: =G5+J5 -> 0 | L5: 0 | M5: =M4+K5-L5 -> 2258.6
A6: 3 | B6: 46025 | G6: =E6*F6 -> 0 | H6: 0 | I6: 0 | J6: =H6*I6 -> 0 | K6: =G6+J6 -> 0 | L6: 0 | M6: =M5+K6-L6 -> 2258.6
A7: 4 | B7: 46026 | G7: =E7*F7 -> 0 | H7: 0 | I7: 0 | J7: =H7*I7 -> 0 | K7: =G7+J7 -> 0 | L7: 0 | M7: =M6+K7-L7 -> 2258.6
A8: 5 | B8: 46027 | G8: =E8*F8 -> 0 | H8: 0 | I8: 0 | J8: =H8*I8 -> 0 | K8: =G8+J8 -> 0 | L8: 0 | M8: =M7+K8-L8 -> 2258.6
A9: 6 | B9: 46028 | G9: =E9*F9 -> 0 | H9: 0 | I9: 0 | J9: =H9*I9 -> 0 | K9: =G9+J9 -> 0 | L9: 0 | M9: =M8+K9-L9 -> 2258.6
A10: 7 | B10: 46029 | G10: =E10*F10 -> 0 | J10: =H10*I10 -> 0 | K10: =G10+J10 -> 0 | L10: 0 | M10: =M9+K10-L10 -> 2258.6
A11: 8 | B11: 46030 | G11: =E11*F11 -> 0 | H11: 0 | I11: 0 | J11: =H11*I11 -> 0 | K11: =G11+J11 -> 0 | L11: 0 | M11: =M10+K11-L11 -> 2258.6
A12: 9 | B12: 46031 | G12: =E12*F12 -> 0 | H12: 0 | I12: 0 | J12: =H12*I12 -> 0 | K12: =G12+J12 -> 0 | L12: 0 | M12: =M11+K12-L12 -> 2258.6
A13: 10 | B13: 46032 | G13: =E13*F13 -> 0 | H13: 0 | I13: 0 | J13: =H13*I13 -> 0 | K13: =G13+J13 -> 0 | L13: 0 | M13: =M12+K13-L13 -> 2258.6
A14: 11 | B14: 46033 | G14: =E14*F14 -> 0 | H14: 0 | I14: 0 | J14: =H14*I14 -> 0 | K14: =G14+J14 -> 0 | L14: 0 | M14: =M13+K14-L14 -> 2258.6
A15: 12 | B15: 46034 | G15: =E15*F15 -> 0 | H15: 0 | I15: 0 | J15: =H15*I15 -> 0 | K15: =G15+J15 -> 0 | L15: 0 | M15: =M14+K15-L15 -> 2258.6
A16: 13 | B16: 46035 | G16: =E16*F16 -> 0 | H16: 0 | I16: 0 | J16: =H16*I16 -> 0 | K16: =G16+J16 -> 0 | L16: 0 | M16: =M15+K16-L16 -> 2258.6 | X16: =100*104 -> 10400
A17: 14 | B17: 46036 | G17: =E17*F17 -> 0 | H17: 0 | I17: 0 | J17: =H17*I17 -> 0 | K17: =G17+J17 -> 0 | L17: 0 | M17: =M16+K17-L17 -> 2258.6
A18: 15 | B18: 46037 | G18: =E18*F18 -> 0 | H18: 0 | I18: 0 | J18: =H18*I18 -> 0 | K18: =G18+J18 -> 0 | M18: =M17+K18-L18 -> 2258.6
A19: 16 | B19: 46038 | G19: =E19*F19 -> 0 | H19: 0 | I19: 0 | J19: =H19*I19 -> 0 | K19: =G19+J19 -> 0 | M19: =M18+K19-L19 -> 2258.6
A20: 17 | B20: 46039 | G20: =E20*F20 -> 0 | H20: 0 | I20: 0 | J20: =H20*I20 -> 0 | K20: =G20+J20 -> 0 | M20: =M19+K20-L20 -> 2258.6
A21: 18 | B21: 46040 | G21: =E21*F21 -> 0 | H21: 0 | I21: 0 | J21: =H21*I21 -> 0 | K21: =G21+J21 -> 0 | M21: =M20+K21-L21 -> 2258.6
A22: 19 | B22: 46041 | G22: =E22*F22 -> 0 | H22: 0 | I22: 0 | J22: =H22*I22 -> 0 | K22: =G22+J22 -> 0 | M22: =M21+K22-L22 -> 2258.6
A23: 20 | B23: 46042 | G23: =E23*F23 -> 0 | H23: 0 | I23: 0 | J23: =H23*I23 -> 0 | K23: =G23+J23 -> 0 | M23: =M22+K23-L23 -> 2258.6
A24: 21 | B24: 46043 | G24: =E24*F24 -> 0 | H24: 0 | I24: 0 | J24: =H24*I24 -> 0 | K24: =G24+J24 -> 0 | M24: =M23+K24-L24 -> 2258.6
A25: 22 | B25: 46044 | G25: =E25*F25 -> 0 | H25: 0 | I25: 0 | J25: =H25*I25 -> 0 | K25: =G25+J25 -> 0 | M25: =M24+K25-L25 -> 2258.6
A26: 23 | B26: 46045 | G26: =E26*F26 -> 0 | H26: 0 | I26: 0 | J26: =H26*I26 -> 0 | K26: =G26+J26 -> 0 | M26: =M25+K26-L26 -> 2258.6
A27: 24 | B27: 46046 | G27: =E27*F27 -> 0 | H27: 0 | I27: 0 | J27: =H27*I27 -> 0 | K27: =G27+J27 -> 0 | M27: =M26+K27-L27 -> 2258.6
A28: 25 | B28: 46047 | G28: =E28*F28 -> 0 | H28: 0 | I28: 0 | J28: =H28*I28 -> 0 | K28: =G28+J28 -> 0 | M28: =M27+K28-L28 -> 2258.6
A29: 26 | B29: 46048 | G29: =E29*F29 -> 0 | H29: 0 | I29: 0 | J29: =H29*I29 -> 0 | K29: =G29+J29 -> 0 | M29: =M28+K29-L29 -> 2258.6
... A33: 30 | B33: 46052 | G33: =E33*F33 -> 0 | H33: 0 | I33: 0 | J33: =H33*I33 -> 0 | K33: =G33+J33 -> 0 | M33: =M32+K33-L33 -> 2258.6
A34: 31 | G34: =E34*F34 -> 0 | H34: 0 | I34: 0 | J34: =H34*I34 -> 0 | K34: =G34+J34 -> 0 | L34: 0 | M34: =M33+K34-L34 -> 2258.6
E35: =SUM(E4:E34) -> 0 | G35: =SUM(G4:G34) -> 0 | H35: =SUM(H4:H34) -> 0 | J35: =SUM(J4:J34) -> 0 | K35: =SUM(K4:K34) -> 0 | L35: =SUM(L4:L34) -> 0

Sheet Hosadurga -2
A1: Shree Veeraprathap Fuel
A2: S.No | B2: Date | C2: GRN No | D2: Ind No/Bill No | E2: Diesel (Lts) | F2: Price | G2: Amount | H2: Petrol (Lts) | I2: Price | J2: Amount | K2: Total amount | L2: Amount paid | M2: As on Date | N2: Remarks
A3: Opening Balance | K3: 197553.8 | M3: =+K3 -> 197553.8
A4: 1 | B4: 46023 | C4: 0 | G4: =E4*F4 -> 0 | J4: =H4*I4 -> 0 | K4: =G4+J4 -> 0 | M4: =M3+K4-L4 -> 197553.8
A5: 2 | B5: 46024 | C5: 0 | E5: 2000 | F5: 91.55 | G5: =E5*F5 -> 183100 | H5: 70 | I5: 103.73 | J5: =H5*I5 -> 7261.1 | K5: =G5+J5 -> 190361.1 | M5: =M4+K5-L5 -> 387914.9
A6: 3 | B6: 46025 | C6: 0 | G6: =E6*F6 -> 0 | J6: =H6*I6 -> 0 | K6: =G6+J6 -> 0 | M6: =M5+K6-L6 -> 387914.9
A7: 4 | B7: 46026 | C7: 0 | G7: =E7*F7 -> 0 | J7: =H7*I7 -> 0 | K7: =G7+J7 -> 0 | M7: =M6+K7-L7 -> 387914.9
A8: 5 | B8: 46027 | C8: 0 | G8: =E8*F8 -> 0 | J8: =H8*I8 -> 0 | K8: =G8+J8 -> 0 | M8: =M7+K8-L8 -> 387914.9
A9: 6 | B9: 46028 | C9: 0 | G9: =E9*F9 -> 0 | J9: =H9*I9 -> 0 | K9: =G9+J9 -> 0 | M9: =M8+K9-L9 -> 387914.9
A10: 7 | B10: 46029 | C10: 0 | G10: =E10*F10 -> 0 | J10: =H10*I10 -> 0 | K10: =G10+J10 -> 0 | M10: =M9+K10-L10 -> 387914.9
A11: 8 | B11: 46030 | C11: 0 | G11: =E11*F11 -> 0 | J11: =H11*I11 -> 0 | K11: =G11+J11 -> 0 | M11: =M10+K11-L11 -> 387914.9
A12: 9 | B12: 46031 | C12: 0 | G12: =E12*F12 -> 0 | J12: =H12*I12 -> 0 | K12: =G12+J12 -> 0 | M12: =M11+K12-L12 -> 387914.9
A13: 10 | B13: 46032 | C13: 0 | G13: =E13*F13 -> 0 | J13: =H13*I13 -> 0 | K13: =G13+J13 -> 0 | M13: =M12+K13-L13 -> 387914.9
A14: 11 | B14: 46033 | C14: 0 | G14: =E14*F14 -> 0 | H14: 105 | I14: 103.73 | J14: =H14*I14 -> 10891.65 | K14: =G14+J14 -> 10891.65 | M14: =M13+K14-L14 -> 398806.55
A15: 12 | B15: 46034 | C15: 0 | G15: =E15*F15 -> 0 | J15: =H15*I15 -> 0 | K15: =G15+J15 -> 0 | M15: =M14+K15-L15 -> 398806.55
A16: 13 | B16: 46035 | C16: 0 | E16: 1000 | F16: 91.55 | G16: =E16*F16 -> 91550 | J16: =H16*I16 -> 0 | K16: =G16+J16 -> 91550 | L16: 250000 | M16: =M15+K16-L16 -> 240356.55
A17: 14 | B17: 46036 | C17: 0 | G17: =E17*F17 -> 0 | J17: =H17*I17 -> 0 | K17: =G17+J17 -> 0 | M17: =M16+K17-L17 -> 240356.55
A18: 15 | B18: 46037 | C18: 0 | G18: =E18*F18 -> 0 | J18: =H18*I18 -> 0 | K18: =G18+J18 -> 0 | M18: =M17+K18-L18 -> 240356.55
A19: 16 | B19: 46038 | C19: 0 | G19: =E19*F19 -> 0 | J19: =H19*I19 -> 0 | K19: =G19+J19 -> 0 | M19: =M18+K19-L19 -> 240356.55
A20: 17 | B20: 46039 | C20: 0 | G20: =E20*F20 -> 0 | J20: =H20*I20 -> 0 | K20: =G20+J20 -> 0 | M20: =M19+K20-L20 -> 240356.55
A21: 18 | B21: 46040 | C21: 0 | G21: =E21*F21 -> 0 | J21: =H21*I21 -> 0 | K21: =G21+J21 -> 0 | M21: =M20+K21-L21 -> 240356.55
A22: 19 | B22: 46041 | C22: 0 | E22: 1000 | F22: 91.55 | G22: =E22*F22 -> 91550 | H22: 35 | I22: 103.73 | J22: =H22*I22 -> 3630.55 | K22: =G22+J22 -> 95180.55 | L22: 200000 | M22: =M21+K22-L22 -> 135537.1
A23: 20 | B23: 46042 | C23: 0 | G23: =E23*F23 -> 0 | J23: =H23*I23 -> 0 | K23: =G23+J23 -> 0 | M23: =M22+K23-L23 -> 135537.1
A24: 21 | B24: 46043 | C24: 0 | G24: =E24*F24 -> 0 | J24: =H24*I24 -> 0 | K24: =G24+J24 -> 0 | M24: =M23+K24-L24 -> 135537.1
A25: 22 | B25: 46044 | C25: 0 | G25: =E25*F25 -> 0 | J25: =H25*I25 -> 0 | K25: =G25+J25 -> 0 | M25: =M24+K25-L25 -> 135537.1
A26: 23 | B26: 46045 | C26: 0 | G26: =E26*F26 -> 0 | J26: =H26*I26 -> 0 | K26: =G26+J26 -> 0 | M26: =M25+K26-L26 -> 135537.1
A27: 24 | B27: 46046 | C27: 0 | G27: =E27*F27 -> 0 | J27: =H27*I27 -> 0 | K27: =G27+J27 -> 0 | M27: =M26+K27-L27 -> 135537.1
A28: 25 | B28: 46047 | C28: 0 | E28: 2000 | F28: 91.55 | G28: =E28*F28 -> 183100 | H28: 70 | I28: 103.73 | J28: =H28*I28 -> 7261.1 | K28: =G28+J28 -> 190361.1 | M28: =M27+K28-L28 -> 325898.2
A29: 26 | B29: 46048 | C29: 0 | G29: =E29*F29 -> 0 | J29: =H29*I29 -> 0 | K29: =G29+J29 -> 0 | M29: =M28+K29-L29 -> 325898.2
A30: 27 | B30: 46049 | C30: 0 | G30: =E30*F30 -> 0 | J30: =H30*I30 -> 0 | K30: =G30+J30 -> 0 | M30: =M29+K30-L30 -> 325898.2
A31: 28 | B31: 46050 | C31: 0 | G31: =E31*F31 -> 0 | J31: =H31*I31 -> 0 | K31: =G31+J31 -> 0 | M31: =M30+K31-L31 -> 325898.2
A32: 29 | B32: 46051 | C32: 0 | G32: =E32*F32 -> 0 | J32: =H32*I32 -> 0 | K32: =G32+J32 -> 0 | M32: =M31+K32-L32 -> 325898.2
A33: 30 | B33: 46052 | C33: 0 | G33: =E33*F33 -> 0 | J33: =H33*I33 -> 0 | K33: =G33+J33 -> 0 | L33: 0 | M33: =M32+K33-L33 -> 325898.2
A34: 31 | B34: 46053
E35: =SUM(E4:E34) -> 6000 | G35: =SUM(G4:G34) -> 549300 | H35: =SUM(H4:H34) -> 280 | J35: =SUM(J4:J34) -> 29044.4 | K35: =SUM(K4:K34) -> 578344.4 | L35: =SUM(L4:L34) -> 450000

Sheet Hiriyur(VJNL)
A1: Sri Balaji Agencies
A2: S.No | B2: Date | C2: GRN No | D2: Ind No/Bill No | E2: Diesel (Lts) | F2: Price | G2: Amount | H2: Petrol (Lts) | I2: Price | J2: Amount | K2: Total amount | L2: Amount paid | M2: As on Date | N2: Remarks
A3: Opening Balance | K3: 438828.8 | M3: =+K3 -> 438828.8
A4: 1 | B4: 46023 | G4: =E4*F4 -> 0 | J4: =H4*I4 -> 0 | K4: =G4+J4 -> 0 | M4: =M3+K4-L4 -> 438828.8
A5: 2 | B5: 46024 | G5: =E5*F5 -> 0 | J5: =H5*I5 -> 0 | K5: =G5+J5 -> 0 | M5: =M4+K5-L5 -> 438828.8
A6: 3 | B6: 46025 | G6: =E6*F6 -> 0 | J6: =H6*I6 -> 0 | K6: =G6+J6 -> 0 | M6: =M5+K6-L6 -> 438828.8
A7: 4 | B7: 46026 | G7: =E7*F7 -> 0 | J7: =H7*I7 -> 0 | K7: =G7+J7 -> 0 | M7: =M6+K7-L7 -> 438828.8
A8: 5 | B8: 46027 | G8: =E8*F8 -> 0 | J8: =H8*I8 -> 0 | K8: =G8+J8 -> 0 | M8: =M7+K8-L8 -> 438828.8
A9: 6 | B9: 46028 | G9: =E9*F9 -> 0 | H9: 70 | I9: 104.13 | J9: =H9*I9 -> 7289.1 | K9: =G9+J9 -> 7289.1 | M9: =M8+K9-L9 -> 446117.9
A10: 7 | B10: 46029 | G10: =E10*F10 -> 0 | J10: =H10*I10 -> 0 | K10: =G10+J10 -> 0 | M10: =M9+K10-L10 -> 446117.9
A11: 8 | B11: 46030 | G11: =E11*F11 -> 0 | J11: =H11*I11 -> 0 | K11: =G11+J11 -> 0 | L11: 200000 | M11: =M10+K11-L11 -> 246117.9
A12: 9 | B12: 46031 | G12: =E12*F12 -> 0 | J12: =H12*I12 -> 0 | K12: =G12+J12 -> 0 | M12: =M11+K12-L12 -> 246117.9
A13: 10 | B13: 46032 | G13: =E13*F13 -> 0 | J13: =H13*I13 -> 0 | K13: =G13+J13 -> 0 | M13: =M12+K13-L13 -> 246117.9
A14: 11 | B14: 46033 | G14: =E14*F14 -> 0 | J14: =H14*I14 -> 0 | K14: =G14+J14 -> 0 | M14: =M13+K14-L14 -> 246117.9
A15: 12 | B15: 46034 | G15: =E15*F15 -> 0 | J15: =H15*I15 -> 0 | K15: =G15+J15 -> 0 | M15: =M14+K15-L15 -> 246117.9
A16: 13 | B16: 46035 | G16: =E16*F16 -> 0 | J16: =H16*I16 -> 0 | K16: =G16+J16 -> 0 | L16: 200000 | M16: =M15+K16-L16 -> 46117.9
A17: 14 | B17: 46036 | G17: =E17*F17 -> 0 | H17: 70 | I17: 104.13 | J17: =H17*I17 -> 7289.1 | K17: =G17+J17 -> 7289.1 | M17: =M16+K17-L17 -> 53407
A18: 15 | B18: 46037 | G18: =E18*F18 -> 0 | J18: =H18*I18 -> 0 | K18: =G18+J18 -> 0 | M18: =M17+K18-L18 -> 53407
A19: 16 | B19: 46038 | G19: =E19*F19 -> 0 | J19: =H19*I19 -> 0 | K19: =G19+J19 -> 0 | M19: =M18+K19-L19 -> 53407
A20: 17 | B20: 46039 | E20: 2300 | F20: 92.26 | G20: =E20*F20 -> 212198 | J20: =H20*I20 -> 0 | K20: =G20+J20 -> 212198 | L20: 53408 | M20: =M19+K20-L20 -> 212197
A21: 18 | B21: 46040 | G21: =E21*F21 -> 0 | J21: =H21*I21 -> 0 | K21: =G21+J21 -> 0 | M21: =M20+K21-L21 -> 212197
A22: 19 | B22: 46041 | G22: =E22*F22 -> 0 | J22: =H22*I22 -> 0 | K22: =G22+J22 -> 0 | M22: =M21+K22-L22 -> 212197
A23: 20 | B23: 46042 | G23: =E23*F23 -> 0 | J23: =H23*I23 -> 0 | K23: =G23+J23 -> 0 | M23: =M22+K23-L23 -> 212197
A24: 21 | B24: 46043 | G24: =E24*F24 -> 0 | J24: =H24*I24 -> 0 | K24: =G24+J24 -> 0 | M24: =M23+K24-L24 -> 212197
A25: 22 | B25: 46044 | G25: =E25*F25 -> 0 | J25: =H25*I25 -> 0 | K25: =G25+J25 -> 0 | M25: =M24+K25-L25 -> 212197
A26: 23 | B26: 46045 | G26: =E26*F26 -> 0 | H26: 70 | I26: 104.13 | J26: =H26*I26 -> 7289.1 | K26: =G26+J26 -> 7289.1 | M26: =M25+K26-L26 -> 219486.1
A27: 24 | B27: 46046 | G27: =E27*F27 -> 0 | J27: =H27*I27 -> 0 | K27: =G27+J27 -> 0 | M27: =M26+K27-L27 -> 219486.1
A28: 25 | B28: 46047 | G28: =E28*F28 -> 0 | J28: =H28*I28 -> 0 | K28: =G28+J28 -> 0 | M28: =M27+K28-L28 -> 219486.1
A29: 26 | B29: 46048 | G29: =E29*F29 -> 0 | J29: =H29*I29 -> 0 | K29: =G29+J29 -> 0 | M29: =M28+K29-L29 -> 219486.1
A30: 27 | B30: 46049 | G30: =E30*F30 -> 0 | J30: =H30*I30 -> 0 | K30: =G30+J30 -> 0 | M30: =M29+K30-L30 -> 219486.1
A31: 28 | B31: 46050 | G31: =E31*F31 -> 0 | J31: =H31*I31 -> 0 | K31: =G31+J31 -> 0 | M31: =M30+K31-L31 -> 219486.1
A32: 29 | B32: 46051 | G32: =E32*F32 -> 0 | J32: =H32*I32 -> 0 | K32: =G32+J32 -> 0 | M32: =M31+K32-L32 -> 219486.1
A33: 30 | B33: 46052 | G33: =E33*F33 -> 0 | J33: =H33*I33 -> 0 | K33: =G33+J33 -> 0 | M33: =M32+K33-L33 -> 219486.1
A34: 31 | B34: 46053 | G34: =E34*F34 -> 0 | J34: =H34*I34 -> 0 | K34: =G34+J34 -> 0 | M34: =M33+K34-L34 -> 219486.1
E35: =SUM(E4:E34) -> 2300 | G35: =SUM(G4:G34) -> 212198 | H35: =SUM(H4:H34) -> 210 | J35: =SUM(J4:J34) -> 21867.3 | K35: =SUM(K4:K34) -> 234065.3 | L35: =SUM(L4:L34) -> 453408

Sheet Malebenur(KUWSDB)
A1: Sree Veerabhadreshwara Service Station
A2: S.No | B2: Date | C2: GRN No | D2: Ind No/Bill No | E2: Diesel (Lts) | F2: Price | G2: Amount | H2: Petrol (Lts) | I2: Price | J2: Amount | K2: Total amount | L2: Amount paid | M2: As on Date | N2: Remarks
A3: Opening Balance | K3: 202357.36 | M3: =+K3 -> 202357.36 | O3: 46138.764
A4: 1 | B4: 45658 | E4: 600 | F4: 92.17 | G4: =E4*F4 -> 55302 | H4: 25 | I4: 104.03 | J4: =H4*I4 -> 2600.75 | K4: =G4+J4 -> 57902.75 | L4: 0 | M4: =M3+K4-L4 -> 260260.11
A5: 2 | B5: 45659 | E5: 0 | F5: 0 | G5: =E5*F5 -> 0 | H5: 0 | I5: 0 | J5: =H5*I5 -> 0 | K5: =G5+J5 -> 0 | L5: 0 | M5: =M4+K5-L5 -> 260260.11
A6: 3 | B6: 45660 | E6: 0 | F6: 0 | G6: =E6*F6 -> 0 | H6: 0 | I6: 0 | J6: =H6*I6 -> 0 | K6: =G6+J6 -> 0 | M6: =M5+K6-L6 -> 260260.11
A7: 4 | B7: 45661 | E7: 0 | F7: 0 | G7: =E7*F7 -> 0 | H7: 0 | I7: 0 | J7: =H7*I7 -> 0 | K7: =G7+J7 -> 0 | M7: =M6+K7-L7 -> 260260.11
A8: 5 | B8: 45662 | E8: 600 | F8: 92.17 | G8: =E8*F8 -> 55302 | H8: 0 | I8: 0 | J8: =H8*I8 -> 0 | K8: =G8+J8 -> 55302 | M8: =M7+K8-L8 -> 315562.1
A9: 6 | B9: 45663 | E9: 0 | F9: 0 | G9: =E9*F9 -> 0 | H9: 0 | I9: 0 | J9: =H9*I9 -> 0 | K9: =G9+J9 -> 0 | M9: =M8+K9-L9 -> 315562.1
A10: 7 | B10: 45664 | E10: 0 | F10: 0 | G10: =E10*F10 -> 0 | H10: 0 | I10: 0 | J10: =H10*I10 -> 0 | K10: =G10+J10 -> 0 | M10: =M9+K10-L10 -> 315562.1
A11: 8 | B11: 45665 | E11: 750 | F11: 92.17 | G11: =E11*F11 -> 69127.5 | H11: 35 | I11: 104.03 | J11: =H11*I11 -> 3641.05 | K11: =G11+J11 -> 72768.55 | L11: 260250 | M11: =M10+K11-L11 -> 128080.65
B12: 45665 | E12: 200 | F12: 92.21 | G12: =E12*F12 -> 18442 | H12: 14 | I12: 104.08 | J12: =H12*I12 -> 1457.12 | K12: =G12+J12 -> 19899.12 | L12: =G12+J12 -> 19899.12 | M12: =M11+K12-L12 -> 128080.65 | N12: laxmi ranganath(HP)
A13: 9 | B13: 45666 | E13: 0 | F13: 0 | G13: =E13*F13 -> 0 | H13: 0 | I13: 0 | J13: =H13*I13 -> 0 | K13: =G13+J13 -> 0 | M13: =M12+K13-L13 -> 128080.65
A14: 10 | B14: 45667 | E14: 0 | F14: 0 | G14: =E14*F14 -> 0 | H14: 0 | I14: 0 | J14: =H14*I14 -> 0 | K14: =G14+J14 -> 0 | M14: =M13+K14-L14 -> 128080.65
A15: 11 | B15: 45668 | E15: 0 | F15: 0 | G15: =E15*F15 -> 0 | H15: 0 | I15: 0 | J15: =H15*I15 -> 0 | K15: =G15+J15 -> 0 | M15: =M14+K15-L15 -> 128080.65
A16: 12 | B16: 45669 | E16: 600 | F16: 92.17 | G16: =E16*F16 -> 55302 | H16: 0 | I16: 0 | J16: =H16*I16 -> 0 | K16: =G16+J16 -> 55302 | M16: =M15+K16-L16 -> 183382.65
A17: 13 | B17: 45670 | E17: 0 | F17: 0 | G17: =E17*F17 -> 0 | H17: 0 | I17: 0 | J17: =H17*I17 -> 0 | K17: =G17+J17 -> 0 | M17: =M16+K17-L17 -> 183382.65
A18: 14 | B18: 45671 | E18: 0 | F18: 0 | G18: =E18*F18 -> 0 | H18: 0 | I18: 0 | J18: =H18*I18 -> 0 | K18: =G18+J18 -> 0 | M18: =M17+K18-L18 -> 183382.65 | Q18: 2767.8 | S18: =Q18-M19 -> -180614.85
A19: 15 | B19: 45672 | E19: 0 | F19: 0 | G19: =E19*F19 -> 0 | H19: 0 | I19: 0 | J19: =H19*I19 -> 0 | K19: =G19+J19 -> 0 | M19: =M18+K19-L19 -> 183382.65
A20: 16 | B20: 45673 | E20: 600 | F20: 92.17 | G20: =E20*F20 -> 55302 | H20: 35 | I20: 104.03 | J20: =H20*I20 -> 3641.05 | K20: =G20+J20 -> 58943.05 | M20: =M19+K20-L20 -> 242325.7
A21: 17 | B21: 45674 | E21: 0 | F21: 0 | G21: =E21*F21 -> 0 | H21: 0 | I21: 0 | J21: =H21*I21 -> 0 | K21: =G21+J21 -> 0 | M21: =M20+K21-L21 -> 242325.7 | V21: =400*90.23 -> 36092
A22: 18 | B22: 45675 | E22: 0 | F22: 0 | G22: =E22*F22 -> 0 | H22: 0 | I22: 0 | J22: =H22*I22 -> 0 | K22: =G22+J22 -> 0 | M22: =M21+K22-L22 -> 242325.7 | V22: =35*104.14 -> 3644.9
A23: 19 | B23: 45676 | E23: 600 | F23: 92.17 | G23: =E23*F23 -> 55302 | H23: 20 | I23: 104.03 | J23: =H23*I23 -> 2080.6 | K23: =G23+J23 -> 57382.6 | L23: 242316 | M23: =M22+K23-L23 -> 57392.305
A24: 20 | B24: 45677 | E24: 0 | F24: 0 | G24: =E24*F24 -> 0 | H24: 0 | I24: 0 | J24: =H24*I24 -> 0 | K24: =G24+J24 -> 0 | M24: =M23+K24-L24 -> 57392.305
A25: 21 | B25: 45678 | E25: 0 | F25: 0 | G25: =E25*F25 -> 0 | H25: 0 | I25: 0 | J25: =H25*I25 -> 0 | K25: =G25+J25 -> 0 | M25: =M24+K25-L25 -> 57392.305
A26: 22 | B26: 45679 | E26: 0 | F26: 0 | G26: =E26*F26 -> 0 | H26: 0 | I26: 0 | J26: =H26*I26 -> 0 | K26: =G26+J26 -> 0 | M26: =M25+K26-L26 -> 57392.305
A27: 23 | B27: 45680 | E27: 599.91 | F27: 92.17 | G27: =E27*F27 -> 55293.705 | H27: 35 | I27: 104.03 | J27: =H27*I27 -> 3641.05 | K27: =G27+J27 -> 58934.755 | M27: =M26+K27-L27 -> 116327.06
A28: 24 | B28: 45681 | E28: 0 | F28: 0 | G28: =E28*F28 -> 0 | H28: 0 | I28: 0 | J28: =H28*I28 -> 0 | K28: =G28+J28 -> 0 | M28: =M27+K28-L28 -> 116327.06
A29: 25 | B29: 45682 | E29: 0 | F29: 0 | G29: =E29*F29 -> 0 | H29: 0 | I29: 0 | J29: =H29*I29 -> 0 | K29: =G29+J29 -> 0 | M29: =M28+K29-L29 -> 116327.06
A30: 26 | B30: 45683 | E30: 0 | F30: 0 | G30: =E30*F30 -> 0 | H30: 0 | I30: 0 | J30: =H30*I30 -> 0 | K30: =G30+J30 -> 0 | M30: =M29+K30-L30 -> 116327.06
A31: 27 | B31: 45684 | E31: 600 | F31: 92.17 | G31: =E31*F31 -> 55302 | H31: 30 | I31: 104.03 | J31: =H31*I31 -> 3120.9 | K31: =G31+J31 -> 58422.9 | M31: =M30+K31-L31 -> 174749.96 | P31: 29774.14
A32: 28 | B32: 45685 | E32: 0 | F32: 0 | G32: =E32*F32 -> 0 | H32: 0 | I32: 0 | J32: =H32*I32 -> 0 | K32: =G32+J32 -> 0 | M32: =M31+K32-L32 -> 174749.96 | P32: 50000
A33: 29 | B33: 45686 | E33: 400 | F33: 92.17 | G33: =E33*F33 -> 36868 | H33: 20 | I33: 104.03 | J33: =H33*I33 -> 2080.6 | K33: =G33+J33 -> 38948.6 | M33: =M32+K33-L33 -> 213698.56 | P33: =SUM(P31:P32) -> 79774.14
A34: 30 | B34: 45687 | E34: 0 | F34: 0 | G34: =E34*F34 -> 0 | H34: 0 | I34: 0 | J34: =H34*I34 -> 0 | K34: =G34+J34 -> 0 | M34: =M33+K34-L34 -> 213698.56
A35: 31 | G35: =E35*F35 -> 0 | J35: =H35*I35 -> 0 | K35: =G35+J35 -> 0 | M35: =M34+K35-L35 -> 213698.56
E36: 0 | F36: 0 | G36: =E36*F36 -> 0 | H36: 0 | J36: =H36*I36 -> 0 | K36: =G36+J36 -> 0 | L36: 0 | M36: =M35+K36-L36 -> 213698.56
E37: =SUM(E4:E35) -> 5549.91 | G37: =SUM(G4:G35) -> 511543.2 | H37: =SUM(H4:H35) -> 214 | J37: =SUM(J4:J35) -> 22263.12 | K37: =SUM(K4:K35) -> 533806.32 | L37: =SUM(L4:L35) -> 522465.12
E38: 0 | G38: 0 | H38: 0 | J38: 0 | K38: =G38+J38 -> 0 | L38: 0
S43: 9052944708

Sheet Molakamuru
A1: Molakamuru
A2: S.No | B2: Date | C2: GRN No | D2: Ind No/Bill No | E2: Diesel (Lts) | F2: Price | G2: Amount | H2: Petrol (Lts) | I2: Price | J2: Amount | K2: Total amount | L2: Amount paid | M2: As on Date | N2: Remarks
A3: Opening Balance | K3: 53588.5 | L3: 53588.5 | M3: 53588.5
A4: 1 | B4: 46023 | G4: =E4*F4 -> 0 | J4: =H4*I4 -> 0 | K4: =G4+J4 -> 0 | L4: =K4 -> 0 | M4: =M3+K4-L4 -> 53588.5
A5: 2 | B5: 46024 | E5: 270 | F5: 92.22 | G5: =E5*F5 -> 24899.4 | H5: 10 | I5: 104.08 | J5: =H5*I5 -> 1040.8 | K5: =G5+J5 -> 25940.2 | L5: 53588.5 | M5: =M4+K5-L5 -> 25940.2
A6: 3 | B6: 46025 | G6: =E6*F6 -> 0 | H6: 0 | I6: 0 | J6: =H6*I6 -> 0 | K6: 0 | L6: 1040 | M6: =M5+K6-L6 -> 24900.2
A7: 4 | B7: 46026 | G7: =E7*F7 -> 0 | J7: =H7*I7 -> 0 | K7: =G7+J7 -> 0 | L7: =K7 -> 0 | M7: =M6+K7-L7 -> 24900.2
A8: 5 | B8: 46027 | G8: =E8*F8 -> 0 | J8: =H8*I8 -> 0 | K8: =G8+J8 -> 0 | L8: =K8 -> 0 | M8: =M7+K8-L8 -> 24900.2
A9: 6 | B9: 46028 | G9: =E9*F9 -> 0 | J9: =H9*I9 -> 0 | K9: =G9+J9 -> 0 | L9: =K9 -> 0 | M9: =M8+K9-L9 -> 24900.2
A10: 7 | B10: 46029 | G10: =E10*F10 -> 0 | J10: =H10*I10 -> 0 | K10: =G10+J10 -> 0 | L10: =K10 -> 0 | M10: =M9+K10-L10 -> 24900.2
A11: 8 | B11: 46030 | E11: 235 | F11: 92.22 | G11: =E11*F11 -> 21671.7 | H11: 9.99 | I11: 104.08 | J11: =H11*I11 -> 1039.7592 | K11: =G11+J11 -> 22711.459 | L11: 0 | M11: =M10+K11-L11 -> 47611.659
A12: 9 | B12: 46031 | G12: =E12*F12 -> 0 | J12: =H12*I12 -> 0 | K12: =G12+J12 -> 0 | L12: =K12 -> 0 | M12: =M11+K12-L12 -> 47611.659
A13: 10 | B13: 46032 | G13: =E13*F13 -> 0 | J13: =H13*I13 -> 0 | K13: =G13+J13 -> 0 | L13: =K13 -> 0 | M13: =M12+K13-L13 -> 47611.659 | P13: 412365
A14: 11 | B14: 46033 | G14: =E14*F14 -> 0 | J14: =H14*I14 -> 0 | K14: =G14+J14 -> 0 | L14: =K14 -> 0 | M14: =M13+K14-L14 -> 47611.659
A15: 12 | B15: 46034 | G15: =E15*F15 -> 0 | J15: =H15*I15 -> 0 | K15: =G15+J15 -> 0 | L15: =K15 -> 0 | M15: =M14+K15-L15 -> 47611.659
A16: 13 | B16: 46035 | E16: 270 | F16: 92.22 | G16: =E16*F16 -> 24899.4 | J16: =H16*I16 -> 0 | K16: =G16+J16 -> 24899.4 | L16: 47611.9 | M16: =M15+K16-L16 -> 24899.159
A17: 14 | B17: 46036 | G17: =E17*F17 -> 0 | J17: =H17*I17 -> 0 | K17: =G17+J17 -> 0 | L17: =K17 -> 0 | M17: =M16+K17-L17 -> 24899.159
A18: 15 | B18: 46037 | G18: =E18*F18 -> 0 | J18: =H18*I18 -> 0 | K18: =G18+J18 -> 0 | L18: =K18 -> 0 | M18: =M17+K18-L18 -> 24899.159
A19: 16 | B19: 46038 | G19: =E19*F19 -> 0 | J19: =H19*I19 -> 0 | K19: =G19+J19 -> 0 | L19: =K19 -> 0 | M19: =M18+K19-L19 -> 24899.159
A20: 17 | B20: 46039 | G20: =E20*F20 -> 0 | J20: =H20*I20 -> 0 | K20: =G20+J20 -> 0 | L20: 24899.14 | M20: =M19+K20-L20 -> 0.0192
A21: 18 | B21: 46040 | G21: =E21*F21 -> 0 | J21: =H21*I21 -> 0 | K21: =G21+J21 -> 0 | L21: =K21 -> 0 | M21: =M20+K21-L21 -> 0.0192
A22: 19 | B22: 46041 | G22: =E22*F22 -> 0 | J22: =H22*I22 -> 0 | K22: =G22+J22 -> 0 | L22: =K22 -> 0 | M22: =M21+K22-L22 -> 0.0192
A23: 20 | B23: 46042 | G23: =E23*F23 -> 0 | J23: =H23*I23 -> 0 | K23: =G23+J23 -> 0 | L23: =K23 -> 0 | M23: =M22+K23-L23 -> 0.0192
A24: 21 | B24: 46043 | E24: 270 | F24: 92.22 | G24: =E24*F24 -> 24899.4 | J24: =H24*I24 -> 0 | K24: =G24+J24 -> 24899.4 | L24: 0 | M24: =M23+K24-L24 -> 24899.419
A25: 22 | B25: 46044 | G25: =E25*F25 -> 0 | J25: =H25*I25 -> 0 | K25: =G25+J25 -> 0 | L25: 0 | M25: =M24+K25-L25 -> 24899.419
A26: 23 | B26: 46045 | G26: =E26*F26 -> 0 | J26: =H26*I26 -> 0 | K26: =G26+J26 -> 0 | L26: 0 | M26: =M25+K26-L26 -> 24899.419
A27: 24 | B27: 46046 | D27: Priyanka Petroleum (BPCL) | G27: =E27*F27 -> 0 | J27: =H27*I27 -> 0 | K27: =G27+J27 -> 0 | L27: 0 | M27: =M26+K27-L27 -> 24899.419
A28: 25 | B28: 46047 | G28: =E28*F28 -> 0 | J28: =H28*I28 -> 0 | K28: =G28+J28 -> 0 | L28: 0 | M28: =M27+K28-L28 -> 24899.419
A29: 26 | B29: 46048 | G29: =E29*F29 -> 0 | J29: =H29*I29 -> 0 | K29: =G29+J29 -> 0 | L29: 0 | M29: =M28+K29-L29 -> 24899.419
A30: 27 | B30: 46049 | G30: =E30*F30 -> 0 | H30: 10 | I30: 104.08 | J30: =H30*I30 -> 1040.8 | K30: =G30+J30 -> 1040.8 | L30: 0 | M30: =M29+K30-L30 -> 25940.219
A31: 28 | B31: 46050 | G31: =E31*F31 -> 0 | H31: 19.7 | I31: 104.08 | J31: =H31*I31 -> 2050.376 | K31: =G31+J31 -> 2050.376 | L31: 0 | M31: =M30+K31-L31 -> 27990.595
A32: 29 | B32: 46051 | G32: =E32*F32 -> 0 | J32: =H32*I32 -> 0 | K32: =G32+J32 -> 0 | L32: 0 | M32: =M31+K32-L32 -> 27990.595
A33: 30 | B33: 46052 | G33: =E33*F33 -> 0 | J33: =H33*I33 -> 0 | K33: =G33+J33 -> 0 | L33: =K33 -> 0 | M33: =M32+K33-L33 -> 27990.595
A34: 31 | B34: 46053 | G34: =E34*F34 -> 0 | K34: =G34+J34 -> 0 | L34: 0 | M34: =M33+K34-L34 -> 27990.595
E35: =SUM(E4:E34) -> 1045 | G35: =SUM(G4:G34) -> 96369.9 | H35: =SUM(H4:H34) -> 49.69 | J35: =SUM(J4:J34) -> 5171.7352 | K35: =SUM(K4:K34) -> 101541.64 | L35: =SUM(L4:L34) -> 127139.54

Sheet Chellakere -1
A1: Shivaganga Service Station (BPCL)
A2: S.No | B2: Date | C2: GRN No | D2: Ind No/Bill No | E2: Diesel (Lts) | F2: Price | G2: Amount | H2: Petrol (Lts) | I2: Price | J2: Amount | K2: Total amount | L2: Amount paid | M2: As on Date | N2: Remarks
A3: Opening Balance | K3: 145403.1 | L3: 0 | M3: =+K3 -> 145403.1
A4: 1 | B4: 46023 | E4: 600 | F4: 92.23 | G4: =E4*F4 -> 55338 | H4: 35 | I4: 104.09 | J4: =H4*I4 -> 3643.15 | K4: =G4+J4 -> 58981.15 | M4: =M3+K4-L4 -> 204384.25
A5: 2 | B5: 46024 | M5: =M4+K5-L5 -> 204384.25
A6: 3 | B6: 46025 | G6: =E6*F6 -> 0 | J6: =H6*I6 -> 0 | K6: =G6+J6 -> 0 | L6: 145402 | M6: =M5+K6-L6 -> 58982.25
A7: 4 | B7: 46026 | E7: 600 | F7: 92.23 | G7: =E7*F7 -> 55338 | H7: 30 | I7: 104.09 | J7: =H7*I7 -> 3122.7 | K7: =G7+J7 -> 58460.7 | M7: =M6+K7-L7 -> 117442.95
A8: 5 | B8: 46027 | G8: =E8*F8 -> 0 | J8: =H8*I8 -> 0 | K8: =G8+J8 -> 0 | M8: =M7+K8-L8 -> 117442.95
A9: 6 | B9: 46028 | G9: =E9*F9 -> 0 | J9: =H9*I9 -> 0 | K9: =G9+J9 -> 0 | M9: =M8+K9-L9 -> 117442.95
A10: 7 | B10: 46029 | G10: =E10*F10 -> 0 | J10: =H10*I10 -> 0 | K10: =G10+J10 -> 0 | M10: =M9+K10-L10 -> 117442.95
A11: 8 | B11: 46030 | G11: =E11*F11 -> 0 | J11: =H11*I11 -> 0 | K11: =G11+J11 -> 0 | M11: =M10+K11-L11 -> 117442.95
A12: 9 | B12: 46031 | E12: 600 | F12: 92.23 | G12: =E12*F12 -> 55338 | H12: 35 | I12: 104.09 | J12: =H12*I12 -> 3643.15 | K12: =G12+J12 -> 58981.15 | M12: =M11+K12-L12 -> 176424.1
A13: 10 | B13: 46032 | G13: =E13*F13 -> 0 | J13: =H13*I13 -> 0 | K13: =G13+J13 -> 0 | M13: =M12+K13-L13 -> 176424.1
A14: 11 | B14: 46033 | G14: =E14*F14 -> 0 | J14: =H14*I14 -> 0 | K14: =G14+J14 -> 0 | M14: =M13+K14-L14 -> 176424.1
A15: 12 | B15: 46034 | G15: =E15*F15 -> 0 | J15: =H15*I15 -> 0 | K15: =G15+J15 -> 0 | M15: =M14+K15-L15 -> 176424.1
A16: 13 | B16: 46035 | G16: =E16*F16 -> 0 | J16: =H16*I16 -> 0 | K16: =G16+J16 -> 0 | M16: =M15+K16-L16 -> 176424.1
A17: 14 | B17: 46036 | E17: 400 | F17: 92.23 | G17: =E17*F17 -> 36892 | J17: =H17*I17 -> 0 | K17: =G17+J17 -> 36892 | M17: =M16+K17-L17 -> 213316.1
A18: 15 | B18: 46037 | G18: =E18*F18 -> 0 | J18: =H18*I18 -> 0 | K18: =G18+J18 -> 0 | M18: =M17+K18-L18 -> 213316.1
A19: 16 | B19: 46038 | G19: =E19*F19 -> 0 | J19: =H19*I19 -> 0 | K19: =G19+J19 -> 0 | M19: =M18+K19-L19 -> 213316.1
A20: 17 | B20: 46039 | G20: =E20*F20 -> 0 | J20: =H20*I20 -> 0 | K20: =G20+J20 -> 0 | L20: 213315 | M20: =M19+K20-L20 -> 1.1
A21: 18 | B21: 46040 | G21: =E21*F21 -> 0 | J21: =H21*I21 -> 0 | K21: =G21+J21 -> 0 | M21: =M20+K21-L21 -> 1.1
A22: 19 | B22: 46041 | E22: 200 | F22: 92.23 | G22: =E22*F22 -> 18446 | H22: 35 | I22: 104.09 | J22: =H22*I22 -> 3643.15 | K22: =G22+J22 -> 22089.15 | M22: =M21+K22-L22 -> 22090.25
A23: 20 | B23: 46042 | G23: =E23*F23 -> 0 | J23: =H23*I23 -> 0 | K23: =G23+J23 -> 0 | M23: =M22+K23-L23 -> 22090.25
A24: 21 | B24: 46043 | E24: 400 | F24: 92.23 | G24: =E24*F24 -> 36892 | H24: 25.01 | I24: 104.09 | J24: =H24*I24 -> 2603.2909 | K24: =G24+J24 -> 39495.291 | M24: =M23+K24-L24 -> 61585.541
A25: 22 | B25: 46044 | G25: =E25*F25 -> 0 | J25: =H25*I25 -> 0 | K25: =G25+J25 -> 0 | M25: =M24+K25-L25 -> 61585.541
A26: 23 | B26: 46045 | G26: =E26*F26 -> 0 | J26: =H26*I26 -> 0 | K26: =G26+J26 -> 0 | M26: =M25+K26-L26 -> 61585.541
A27: 24 | B27: 46046 | G27: =E27*F27 -> 0 | J27: =H27*I27 -> 0 | K27: =G27+J27 -> 0 | M27: =M26+K27-L27 -> 61585.541
A28: 25 | B28: 46047 | G28: =E28*F28 -> 0 | J28: =H28*I28 -> 0 | K28: =G28+J28 -> 0 | M28: =M27+K28-L28 -> 61585.541
A29: 26 | B29: 46048 | G29: =E29*F29 -> 0 | J29: =H29*I29 -> 0 | K29: =G29+J29 -> 0 | M29: =M28+K29-L29 -> 61585.541
A30: 27 | B30: 46049 | G30: =E30*F30 -> 0 | J30: =H30*I30 -> 0 | K30: =G30+J30 -> 0 | M30: =M29+K30-L30 -> 61585.541
A31: 28 | B31: 46050 | E31: 400 | F31: 92.23 | G31: =E31*F31 -> 36892 | H31: 35 | I31: 104.09 | J31: =H31*I31 -> 3643.15 | K31: =G31+J31 -> 40535.15 | M31: =M30+K31-L31 -> 102120.69
A32: 29 | B32: 46051 | G32: =E32*F32 -> 0 | J32: =H32*I32 -> 0 | K32: =G32+J32 -> 0 | M32: =M31+K32-L32 -> 102120.69
A33: 30 | B33: 46052 | G33: =E33*F33 -> 0 | J33: =H33*I33 -> 0 | K33: =G33+J33 -> 0 | M33: =M32+K33-L33 -> 102120.69
A34: 31 | B34: 46053 | E34: 600 | F34: 92.23 | G34: =E34*F34 -> 55338 | H34: 35.03 | I34: 104.09 | J34: =H34*I34 -> 3646.2727 | K34: =G34+J34 -> 58984.273 | M34: =M33+K34-L34 -> 161104.96
E35: =SUM(E4:E34) -> 3800 | G35: =SUM(G4:G34) -> 350474 | H35: =SUM(H4:H34) -> 230.04 | J35: =SUM(J4:J34) -> 23944.864 | K35: =SUM(K4:K34) -> 374418.86 | L35: =SUM(L4:L34) -> 358717

Sheet  Chellakere-PKG-9
A1: Chellakere-PKG-09
A2: S.No | B2: Date | C2: GRN No | D2: Ind No/Bill No | E2: Diesel (Lts) | F2: Price | G2: Amount | H2: Petrol (Lts) | I2: Price | J2: Amount | K2: Total amount | L2: Amount paid | M2: As on Date | N2: Remarks
A3: Opening Balance | K3: 0 | L3: 0 | M3: =+K3 -> 0
A4: 1 | B4: 46023 | G4: =E4*F4 -> 0 | J4: =H4*I4 -> 0 | K4: =G4+J4 -> 0 | L4: =K4 -> 0 | M4: =M3+K4-L4 -> 0
A5: 2 | B5: 46024 | G5: =E5*F5 -> 0 | J5: =H5*I5 -> 0 | K5: =G5+J5 -> 0 | L5: =K5 -> 0 | M5: =M4+K5-L5 -> 0
A6: 3 | B6: 46025 | G6: =E6*F6 -> 0 | J6: =H6*I6 -> 0 | K6: =G6+J6 -> 0 | L6: =K6 -> 0 | M6: =M5+K6-L6 -> 0
A7: 4 | B7: 46026 | G7: =E7*F7 -> 0 | J7: =H7*I7 -> 0 | K7: =G7+J7 -> 0 | L7: =K7 -> 0 | M7: =M6+K7-L7 -> 0
A8: 5 | B8: 46027 | E8: 70 | F8: 92.23 | G8: =E8*F8 -> 6456.1 | H8: 5 | I8: 104.03 | J8: =H8*I8 -> 520.15 | K8: =G8+J8 -> 6976.25 | L8: =K8 -> 6976.25 | M8: =M7+K8-L8 -> 0
A9: 6 | B9: 46028 | G9: =E9*F9 -> 0 | J9: =H9*I9 -> 0 | K9: =G9+J9 -> 0 | L9: =K9 -> 0 | M9: =M8+K9-L9 -> 0
A10: 7 | B10: 46029 | G10: =E10*F10 -> 0 | J10: =H10*I10 -> 0 | K10: =G10+J10 -> 0 | L10: =K10 -> 0 | M10: =M9+K10-L10 -> 0
A11: 8 | B11: 46030 | G11: =E11*F11 -> 0 | J11: =H11*I11 -> 0 | K11: =G11+J11 -> 0 | L11: =K11 -> 0 | M11: =M10+K11-L11 -> 0
A12: 9 | B12: 46031 | E12: 80 | F12: 92.23 | G12: =E12*F12 -> 7378.4 | H12: 5.01 | I12: 104.09 | J12: =H12*I12 -> 521.4909 | K12: =G12+J12 -> 7899.8909 | L12: =K12 -> 7899.8909 | M12: =M11+K12-L12 -> 0
A13: 10 | B13: 46032 | G13: =E13*F13 -> 0 | J13: =H13*I13 -> 0 | K13: =G13+J13 -> 0 | L13: =K13 -> 0 | M13: =M12+K13-L13 -> 0
A14: 11 | B14: 46033 | G14: =E14*F14 -> 0 | J14: =H14*I14 -> 0 | K14: =G14+J14 -> 0 | L14: =K14 -> 0 | M14: =M13+K14-L14 -> 0
A15: 12 | B15: 46034 | E15: 60 | F15: 92.23 | G15: =E15*F15 -> 5533.8 | H15: 5 | I15: 104.09 | J15: =H15*I15 -> 520.45 | K15: =G15+J15 -> 6054.25 | L15: =K15 -> 6054.25 | M15: =M14+K15-L15 -> 0
A16: 13 | B16: 46035 | G16: =E16*F16 -> 0 | J16: =H16*I16 -> 0 | K16: =G16+J16 -> 0 | L16: =K16 -> 0 | M16: =M15+K16-L16 -> 0
A17: 14 | B17: 46036 | G17: =E17*F17 -> 0 | J17: =H17*I17 -> 0 | K17: =G17+J17 -> 0 | L17: =K17 -> 0 | M17: =M16+K17-L17 -> 0
A18: 15 | B18: 46037 | G18: =E18*F18 -> 0 | J18: =H18*I18 -> 0 | K18: =G18+J18 -> 0 | L18: =K18 -> 0 | M18: =M17+K18-L18 -> 0
A19: 16 | B19: 46038 | E19: 59.99 | F19: 92.23 | G19: =E19*F19 -> 5532.8777 | H19: 5 | I19: 104.09 | J19: =H19*I19 -> 520.45 | K19: =G19+J19 -> 6053.3277 | L19: =K19 -> 6053.3277 | M19: =M18+K19-L19 -> 0
A20: 17 | B20: 46039 | G20: =E20*F20 -> 0 | J20: =H20*I20 -> 0 | K20: =G20+J20 -> 0 | L20: =K20 -> 0 | M20: =M19+K20-L20 -> 0
A21: 18 | B21: 46040 | G21: =E21*F21 -> 0 | J21: =H21*I21 -> 0 | K21: =G21+J21 -> 0 | L21: =K21 -> 0 | M21: =M20+K21-L21 -> 0
A22: 19 | B22: 46041 | E22: 60 | F22: 92.23 | G22: =E22*F22 -> 5533.8 | H22: 5 | I22: 104.09 | J22: =H22*I22 -> 520.45 | K22: =G22+J22 -> 6054.25 | L22: =K22 -> 6054.25 | M22: =M21+K22-L22 -> 0
A23: 20 | B23: 46042 | G23: =E23*F23 -> 0 | J23: =H23*I23 -> 0 | K23: =G23+J23 -> 0 | L23: =K23 -> 0 | M23: =M22+K23-L23 -> 0
A24: 21 | B24: 46043 | G24: =E24*F24 -> 0 | J24: =H24*I24 -> 0 | K24: =G24+J24 -> 0 | L24: =K24 -> 0 | M24: =M23+K24-L24 -> 0
A25: 22 | B25: 46044 | G25: =E25*F25 -> 0 | J25: =H25*I25 -> 0 | K25: =G25+J25 -> 0 | L25: =K25 -> 0 | M25: =M24+K25-L25 -> 0
A26: 23 | B26: 46045 | E26: 55 | F26: 92.23 | G26: =E26*F26 -> 5072.65 | J26: =H26*I26 -> 0 | K26: =G26+J26 -> 5072.65 | L26: =K26 -> 5072.65 | M26: =M25+K26-L26 -> 0
A27: 24 | B27: 46046 | G27: =E27*F27 -> 0 | J27: =H27*I27 -> 0 | K27: =G27+J27 -> 0 | L27: =K27 -> 0 | M27: =M26+K27-L27 -> 0
A28: 25 | B28: 46047 | G28: =E28*F28 -> 0 | J28: =H28*I28 -> 0 | K28: =G28+J28 -> 0 | L28: =K28 -> 0 | M28: 0
A29: 26 | B29: 46048 | G29: =E29*F29 -> 0 | J29: =H29*I29 -> 0 | K29: =G29+J29 -> 0 | L29: =K29 -> 0 | M29: 0
A30: 27 | B30: 46049 | E30: 60 | F30: 92.23 | G30: =E30*F30 -> 5533.8 | H30: 8.07 | I30: 104.09 | J30: =H30*I30 -> 840.0063 | K30: =G30+J30 -> 6373.8063 | L30: =K30 -> 6373.8063 | M30: 0
A31: 28 | B31: 46050 | G31: =E31*F31 -> 0 | J31: =H31*I31 -> 0 | K31: =G31+J31 -> 0 | L31: =K31 -> 0 | M31: 0
A32: 29 | B32: 46051 | E32: 65 | F32: 92.23 | G32: =E32*F32 -> 5994.95 | J32: =H32*I32 -> 0 | K32: =G32+J32 -> 5994.95 | L32: =K32 -> 5994.95
A33: 30 | B33: 46052 | G33: =E33*F33 -> 0 | J33: =H33*I33 -> 0 | K33: =G33+J33 -> 0 | L33: =K33 -> 0
A34: 31 | B34: 46053 | G34: =E34*F34 -> 0 | J34: =H34*I34 -> 0 | K34: =G34+J34 -> 0 | L34: =K34 -> 0
E35: =SUM(E4:E34) -> 509.99 | G35: =SUM(G4:G34) -> 47036.378 | H35: =SUM(H4:H34) -> 33.08 | J35: =SUM(J4:J34) -> 3442.9972 | K35: =SUM(K4:K34) -> 50479.375 | L35: =SUM(L4:L34) -> 50479.375

Sheet  Chennagiri
A1: Chennagiri
A2: S.No | B2: Date | C2: GRN No | D2: Ind No/Bill No | E2: Diesel (Lts) | F2: Price | G2: Amount | H2: Petrol (Lts) | I2: Price | J2: Amount | K2: Total amount | L2: Amount paid | M2: As on Date | N2: Remarks
A3: Opening Balance | K3: 0 | L3: 0 | M3: =+K3 -> 0
A4: 1 | B4: 46023 | G4: =E4*F4 -> 0 | J4: =H4*I4 -> 0 | K4: =G4+J4 -> 0 | L4: =K4 -> 0 | M4: =M3+K4-L4 -> 0
A5: 2 | B5: 46024 | G5: =E5*F5 -> 0 | J5: =H5*I5 -> 0 | K5: =G5+J5 -> 0 | L5: =K5 -> 0 | M5: =M4+K5-L5 -> 0 | N5: HPCL
A6: 3 | B6: 46025 | G6: =E6*F6 -> 0 | H6: 10 | I6: 104.08 | J6: =H6*I6 -> 1040.8 | K6: =G6+J6 -> 1040.8 | L6: =K6 -> 1040.8 | M6: =M5+K6-L6 -> 0
A7: 4 | B7: 46026 | G7: =E7*F7 -> 0 | J7: =H7*I7 -> 0 | K7: =G7+J7 -> 0 | L7: =K7 -> 0 | M7: =M6+K7-L7 -> 0
A8: 5 | B8: 46027 | G8: =E8*F8 -> 0 | J8: =H8*I8 -> 0 | K8: =G8+J8 -> 0 | L8: =K8 -> 0 | M8: =M7+K8-L8 -> 0 | N8: HPCL
A9: 6 | B9: 46028 | G9: =E9*F9 -> 0 | J9: =H9*I9 -> 0 | K9: =G9+J9 -> 0 | L9: =K9 -> 0 | M9: =M8+K9-L9 -> 0
A10: 7 | B10: 46029 | G10: =E10*F10 -> 0 | J10: =H10*I10 -> 0 | K10: =G10+J10 -> 0 | L10: =K10 -> 0 | M10: =M9+K10-L10 -> 0
A11: 8 | B11: 46030 | E11: 100 | F11: 92.05 | G11: =E11*F11 -> 9205 | J11: =H11*I11 -> 0 | K11: =G11+J11 -> 9205 | L11: =K11 -> 9205 | M11: =M10+K11-L11 -> 0
A12: 9 | B12: 46031 | G12: =E12*F12 -> 0 | J12: =H12*I12 -> 0 | K12: =G12+J12 -> 0 | L12: =K12 -> 0 | M12: =M11+K12-L12 -> 0
A13: 10 | B13: 46032 | G13: =E13*F13 -> 0 | J13: =H13*I13 -> 0 | K13: =G13+J13 -> 0 | L13: =K13 -> 0 | M13: =M12+K13-L13 -> 0
A14: 11 | B14: 46033 | G14: =E14*F14 -> 0 | H14: 21 | I14: 104.08 | J14: =H14*I14 -> 2185.68 | K14: =G14+J14 -> 2185.68 | L14: =K14 -> 2185.68 | M14: =M13+K14-L14 -> 0
A15: 12 | B15: 46034 | E15: 108.65 | F15: 92.07 | G15: =E15*F15 -> 10003.405 | J15: =H15*I15 -> 0 | K15: =G15+J15 -> 10003.405 | L15: =K15 -> 10003.405 | M15: =M14+K15-L15 -> 0
A16: 13 | B16: 46035 | G16: =E16*F16 -> 0 | J16: =H16*I16 -> 0 | K16: =G16+J16 -> 0 | L16: =K16 -> 0 | M16: =M15+K16-L16 -> 0
A17: 14 | B17: 46036 | E17: 200 | F17: 92.04 | G17: =E17*F17 -> 18408 | J17: =H17*I17 -> 0 | K17: =G17+J17 -> 18408 | L17: =K17 -> 18408 | M17: =M16+K17-L17 -> 0
A18: 15 | B18: 46037 | G18: =E18*F18 -> 0 | J18: =H18*I18 -> 0 | K18: =G18+J18 -> 0 | L18: =K18 -> 0 | M18: =M17+K18-L18 -> 0
A19: 16 | B19: 46038 | G19: =E19*F19 -> 0 | J19: =H19*I19 -> 0 | K19: =G19+J19 -> 0 | L19: =K19 -> 0 | M19: =M18+K19-L19 -> 0
A20: 17 | B20: 46039 | G20: =E20*F20 -> 0 | J20: =H20*I20 -> 0 | K20: =G20+J20 -> 0 | L20: =K20 -> 0 | M20: =M19+K20-L20 -> 0
A21: 18 | B21: 46040 | G21: =E21*F21 -> 0 | J21: =H21*I21 -> 0 | K21: =G21+J21 -> 0 | L21: =K21 -> 0 | M21: =M20+K21-L21 -> 0
A22: 19 | B22: 46041 | G22: =E22*F22 -> 0 | J22: =H22*I22 -> 0 | K22: =G22+J22 -> 0 | L22: =K22 -> 0 | M22: =M21+K22-L22 -> 0
A23: 20 | B23: 46042 | G23: =E23*F23 -> 0 | J23: =H23*I23 -> 0 | K23: =G23+J23 -> 0 | L23: =K23 -> 0 | M23: =M22+K23-L23 -> 0
A24: 21 | B24: 46043 | G24: =E24*F24 -> 0 | J24: =H24*I24 -> 0 | K24: =G24+J24 -> 0 | L24: =K24 -> 0 | M24: =M23+K24-L24 -> 0
A25: 22 | B25: 46044 | G25: =E25*F25 -> 0 | J25: =H25*I25 -> 0 | K25: =G25+J25 -> 0 | L25: =K25 -> 0 | M25: =M24+K25-L25 -> 0
A26: 23 | B26: 46045 | G26: =E26*F26 -> 0 | J26: =H26*I26 -> 0 | K26: =G26+J26 -> 0 | L26: =K26 -> 0 | M26: =M25+K26-L26 -> 0
A27: 24 | B27: 46046 | E27: 217.27 | F27: 92.05 | G27: =E27*F27 -> 19999.703 | J27: =H27*I27 -> 0 | K27: =G27+J27 -> 19999.703 | L27: =K27 -> 19999.703 | M27: =M26+K27-L27 -> 0
A28: 25 | B28: 46047 | G28: =E28*F28 -> 0 | J28: =H28*I28 -> 0 | K28: =G28+J28 -> 0 | L28: =K28 -> 0 | M28: 0
A29: 26 | B29: 46048 | G29: =E29*F29 -> 0 | J29: =H29*I29 -> 0 | K29: =G29+J29 -> 0 | L29: =K29 -> 0 | M29: 0
A30: 27 | B30: 46049 | G30: =E30*F30 -> 0 | J30: =H30*I30 -> 0 | K30: =G30+J30 -> 0 | L30: =K30 -> 0 | M30: 0
A31: 28 | B31: 46050 | G31: =E31*F31 -> 0 | J31: =H31*I31 -> 0 | K31: =G31+J31 -> 0 | L31: =K31 -> 0 | M31: 0
A32: 29 | B32: 46051 | G32: =E32*F32 -> 0 | J32: =H32*I32 -> 0 | K32: =G32+J32 -> 0 | L32: =K32 -> 0
A33: 30 | B33: 46052 | G33: =E33*F33 -> 0 | J33: =H33*I33 -> 0 | K33: =G33+J33 -> 0 | L33: =K33 -> 0
A34: 31 | B34: 46053 | G34: =E34*F34 -> 0 | K34: =G34+J34 -> 0 | L34: =K34 -> 0
E35: =SUM(E4:E34) -> 625.92 | G35: =SUM(G4:G34) -> 57616.109 | H35: =SUM(H4:H34) -> 31 | J35: =SUM(J4:J34) -> 3226.48 | K35: =SUM(K4:K34) -> 60842.589 | L35: =SUM(L4:L34) -> 60842.589

Sheet Khanapur
A1: V.V.Varde
A2: S.No | B2: Date | C2: GRN No | D2: Ind No/Bill No | E2: Diesel (Lts) | F2: Price | G2: Amount | H2: Petrol (Lts) | I2: Price | J2: Amount | K2: Total amount | L2: Date of payment | M2: Amount paid | N2: Remarks
D3: Opening Balance | K3: 98982.5 | M3: 98982.5
A4: 1 | B4: 46023 | E4: 60 | F4: 90.88 | G4: =F4*E4 -> 5452.8 | H4: 5 | I4: 102.77 | J4: =H4*I4 -> 513.85 | K4: =G4+J4 -> 5966.65 | M4: =M3+K4-L4 -> 104949.15
A5: 2 | B5: 46024 | E5: 0 | F5: 0 | G5: =F5*E5 -> 0 | H5: 0 | I5: 0 | J5: =H5*I5 -> 0 | K5: =G5+J5 -> 0 | M5: =M4+K5-L5 -> 104949.15 | S5: 90.88 | T5: 102.77
A6: 3 | B6: 46025 | E6: 65 | F6: 90.88 | G6: =F6*E6 -> 5907.2 | H6: 4 | I6: 102.77 | J6: =H6*I6 -> 411.08 | K6: =G6+J6 -> 6318.28 | L6: 98000 | M6: =M5+K6-L6 -> 13267.43
A7: 4 | B7: 46026 | E7: 60 | F7: 90.88 | G7: =F7*E7 -> 5452.8 | H7: 0 | I7: 0 | J7: =H7*I7 -> 0 | K7: =G7+J7 -> 5452.8 | M7: =M6+K7-L7 -> 18720.23
A8: 5 | B8: 46027 | E8: 110 | F8: 90.88 | G8: =F8*E8 -> 9996.8 | H8: 0 | I8: 0 | J8: =H8*I8 -> 0 | K8: =G8+J8 -> 9996.8 | M8: =M7+K8-L8 -> 28717.03
A9: 6 | B9: 46028 | E9: 77 | F9: 90.88 | G9: =F9*E9 -> 6997.76 | H9: 5 | I9: 102.77 | J9: =H9*I9 -> 513.85 | K9: =G9+J9 -> 7511.61 | M9: =M8+K9-L9 -> 36228.64
A10: 7 | B10: 46029 | E10: 40 | F10: 90.88 | G10: =F10*E10 -> 3635.2 | H10: 5 | I10: 102.77 | J10: =H10*I10 -> 513.85 | K10: =G10+J10 -> 4149.05 | M10: =M9+K10-L10 -> 40377.69
A11: 8 | B11: 46030 | E11: 35 | F11: 90.88 | G11: =F11*E11 -> 3180.8 | H11: 0 | I11: 0 | J11: =H11*I11 -> 0 | K11: =G11+J11 -> 3180.8 | M11: =M10+K11-L11 -> 43558.49
A12: 9 | B12: 46031 | E12: 50 | F12: 90.88 | G12: =F12*E12 -> 4544 | H12: 0 | I12: 0 | J12: =H12*I12 -> 0 | K12: =G12+J12 -> 4544 | M12: =M11+K12-L12 -> 48102.49
A13: 10 | B13: 46032 | E13: 120 | F13: 90.88 | G13: =F13*E13 -> 10905.6 | H13: 0 | I13: 0 | J13: =H13*I13 -> 0 | K13: =G13+J13 -> 10905.6 | M13: =M12+K13-L13 -> 59008.09
A14: 11 | B14: 46033 | E14: 10 | F14: 90.88 | G14: =F14*E14 -> 908.8 | H14: 0 | I14: 0 | J14: =H14*I14 -> 0 | K14: =G14+J14 -> 908.8 | M14: =M13+K14-L14 -> 59916.89
A15: 12 | B15: 46034 | E15: 145.24 | F15: 90.88 | G15: =F15*E15 -> 13199.411 | H15: 10 | I15: 102.77 | J15: =H15*I15 -> 1027.7 | K15: =G15+J15 -> 14227.111 | M15: =M14+K15-L15 -> 74144.002
A16: 13 | B16: 46035 | E16: 0 | F16: 0 | G16: =F16*E16 -> 0 | H16: 5 | I16: 102.77 | J16: =H16*I16 -> 513.85 | K16: =G16+J16 -> 513.85 | M16: =M15+K16-L16 -> 74657.852
A17: 14 | B17: 46036 | E17: 35 | F17: 90.88 | G17: =F17*E17 -> 3180.8 | H17: 0 | I17: 0 | J17: =H17*I17 -> 0 | K17: =G17+J17 -> 3180.8 | M17: =M16+K17-L17 -> 77838.652
A18: 15 | B18: 46037 | E18: 0 | F18: 90.88 | G18: =F18*E18 -> 0 | H18: 0 | I18: 0 | J18: =H18*I18 -> 0 | K18: =G18+J18 -> 0 | M18: =M17+K18-L18 -> 77838.652
A19: 16 | B19: 46038 | E19: 100 | F19: 90.88 | G19: =F19*E19 -> 9088 | H19: 0 | I19: 0 | J19: =H19*I19 -> 0 | K19: =G19+J19 -> 9088 | M19: =M18+K19-L19 -> 86926.652
A20: 17 | B20: 46039 | E20: 80 | F20: 90.88 | G20: =F20*E20 -> 7270.4 | H20: 0 | I20: 0 | J20: =H20*I20 -> 0 | K20: =G20+J20 -> 7270.4 | M20: =M19+K20-L20 -> 94197.052 | O20: 16.68
A21: 18 | B21: 46040 | E21: 55 | F21: 90.88 | G21: =F21*E21 -> 4998.4 | H21: 5 | I21: 102.77 | J21: =H21*I21 -> 513.85 | K21: =G21+J21 -> 5512.25 | M21: =M20+K21-L21 -> 99709.302
A22: 19 | B22: 46041 | E22: 110 | F22: 90.88 | G22: =F22*E22 -> 9996.8 | H22: 10 | I22: 102.77 | J22: =H22*I22 -> 1027.7 | K22: =G22+J22 -> 11024.5 | L22: 86520 | M22: =M21+K22-L22 -> 24213.802
A23: 20 | B23: 46042 | E23: 50 | F23: 90.88 | G23: =F23*E23 -> 4544 | H23: 5 | I23: 102.77 | J23: =H23*I23 -> 513.85 | K23: =G23+J23 -> 5057.85 | M23: =M22+K23-L23 -> 29271.652 | N23: 0
A24: 21 | B24: 46043 | E24: 0 | F24: 0 | G24: =F24*E24 -> 0 | H24: 0 | I24: 0 | J24: =H24*I24 -> 0 | K24: =G24+J24 -> 0 | M24: =M23+K24-L24 -> 29271.652
A25: 22 | B25: 46044 | E25: 121 | F25: 90.88 | G25: =F25*E25 -> 10996.48 | H25: 0 | I25: 0 | J25: =H25*I25 -> 0 | K25: =G25+J25 -> 10996.48 | M25: =M24+K25-L25 -> 40268.132
A26: 23 | B26: 46045 | E26: 0 | F26: 0 | G26: =F26*E26 -> 0 | H26: 0 | I26: 0 | J26: =H26*I26 -> 0 | K26: =G26+J26 -> 0 | M26: =M25+K26-L26 -> 40268.132
A27: 24 | B27: 46046 | E27: 128 | F27: 90.88 | G27: =F27*E27 -> 11632.64 | H27: 0 | I27: 0 | J27: =H27*I27 -> 0 | K27: =G27+J27 -> 11632.64 | M27: =M26+K27-L27 -> 51900.772
A28: 25 | B28: 46047 | E28: 30 | F28: 90.88 | G28: =F28*E28 -> 2726.4 | H28: 5 | I28: 102.77 | J28: =H28*I28 -> 513.85 | K28: =G28+J28 -> 3240.25 | M28: =M27+K28-L28 -> 55141.022
A29: 26 | B29: 46048 | E29: 155 | F29: 90.88 | G29: =F29*E29 -> 14086.4 | H29: 0 | I29: 0 | J29: =H29*I29 -> 0 | K29: =G29+J29 -> 14086.4 | M29: =M28+K29-L29 -> 69227.422
A30: 27 | B30: 46049 | E30: 0 | F30: 0 | G30: =F30*E30 -> 0 | H30: 0 | I30: 0 | J30: =H30*I30 -> 0 | K30: =G30+J30 -> 0 | M30: =M29+K30-L30 -> 69227.422
A31: 28 | B31: 46050 | E31: 35 | F31: 90.88 | G31: =F31*E31 -> 3180.8 | H31: 5 | I31: 102.77 | J31: =H31*I31 -> 513.85 | K31: =G31+J31 -> 3694.65 | M31: =M30+K31-L31 -> 72922.072
A32: 29 | B32: 46051 | E32: 80 | F32: 90.88 | G32: =F32*E32 -> 7270.4 | H32: 10 | I32: 102.77 | J32: =H32*I32 -> 1027.7 | K32: =G32+J32 -> 8298.1 | M32: =M31+K32-L32 -> 81220.172
A33: 30 | B33: 46052 | E33: 210 | F33: 90.88 | G33: =F33*E33 -> 19084.8 | H33: 10 | I33: 102.77 | J33: =H33*I33 -> 1027.7 | K33: =G33+J33 -> 20112.5 | M33: =M32+K33-L33 -> 101332.67
A34: 31 | B34: 46053 | E34: 28.72 | F34: 90.88 | G34: =F34*E34 -> 2610.0736 | H34: 0 | I34: 0 | J34: =H34*I34 -> 0 | K34: =G34+J34 -> 2610.0736 | M34: =M33+K34-L34 -> 103942.75
E35: =SUM(E4:E34) -> 1989.96 | G35: =SUM(G4:G34) -> 180847.56 | H35: =SUM(H4:H34) -> 84 | J35: =SUM(J4:J34) -> 8632.68 | K35: =SUM(K4:K34) -> 189480.24 | L35: =SUM(L4:L34) -> 184520 | M35: =SUM(M4:M34) -> 1911315.1
E36: 1541.87
E37: 1661 | H37: 43.92
E38: =E37-E36 -> 119.13

Sheet Munavali
A1: Shri Daneshwari
A2: S.No | B2: Date | C2: GRN No | D2: Ind No/Bill No | E2: Diesel (Lts) | F2: Price | G2: Amount | H2: Petrol (Lts) | I2: Price | J2: Amount | K2: Total amount | L2: Amount paid | M2: As on date | N2: Remarks
D3: Opening Balance | K3: 660530.8 | M3: 660530.8 | O3: 26506.4
A4: 1 | B4: 46023 | E4: 40 | F4: 91.32 | G4: =E4*F4 -> 3652.8 | J4: =H4*I4 -> 0 | K4: =G4+J4 -> 3652.8 | M4: =M3+K4-L4 -> 664183.6
A5: 2 | B5: 46024 | E5: 35 | F5: 91.32 | G5: =E5*F5 -> 3196.2 | H5: 10 | I5: 103.24 | J5: =H5*I5 -> 1032.4 | K5: =G5+J5 -> 4228.6 | M5: =M4+K5-L5 -> 668412.2
A6: 3 | B6: 46025 | E6: 0 | F6: 91.32 | G6: =E6*F6 -> 0 | H6: 3 | I6: 103.24 | J6: =H6*I6 -> 309.72 | K6: =G6+J6 -> 309.72 | M6: =M5+K6-L6 -> 668721.92
A7: 4 | B7: 46026 | E7: 30 | F7: 91.32 | G7: =E7*F7 -> 2739.6 | H7: 18 | I7: 103.24 | J7: =H7*I7 -> 1858.32 | K7: =G7+J7 -> 4597.92 | M7: =M6+K7-L7 -> 673319.84
A8: 5 | B8: 46027 | E8: 30 | F8: 91.32 | G8: =E8*F8 -> 2739.6 | H8: 6 | I8: 103.24 | J8: =H8*I8 -> 619.44 | K8: =G8+J8 -> 3359.04 | M8: =M7+K8-L8 -> 676678.88
A9: 6 | B9: 46028 | G9: =E9*F9 -> 0 | J9: =H9*I9 -> 0 | K9: =G9+J9 -> 0 | M9: =M8+K9-L9 -> 676678.88
A10: 7 | B10: 46029 | G10: =E10*F10 -> 0 | J10: =H10*I10 -> 0 | K10: =G10+J10 -> 0 | M10: =M9+K10-L10 -> 676678.88
A11: 8 | B11: 46030 | G11: =E11*F11 -> 0 | J11: =H11*I11 -> 0 | K11: =G11+J11 -> 0 | L11: 400000 | M11: =M10+K11-L11 -> 276678.88
A12: 9 | B12: 46031 | G12: =E12*F12 -> 0 | J12: =H12*I12 -> 0 | K12: =G12+J12 -> 0 | L12: 271620 | M12: =M11+K12-L12 -> 5058.882
A13: 10 | B13: 46032 | G13: =E13*F13 -> 0 | J13: =H13*I13 -> 0 | K13: =G13+J13 -> 0 | L13: 5058.88 | M13: =M12+K13-L13 -> 0.0019999999 | O13: 4782
A14: 11 | B14: 46033 | G14: =E14*F14 -> 0 | J14: =H14*I14 -> 0 | K14: =G14+J14 -> 0 | M14: =M13+K14-L14 -> 0.0019999999
A15: 12 | B15: 46034 | G15: =E15*F15 -> 0 | J15: =H15*I15 -> 0 | K15: =G15+J15 -> 0 | M15: =M14+K15-L15 -> 0.0019999999
A16: 13 | B16: 46035 | D16: 0 | G16: =E16*F16 -> 0 | J16: =H16*I16 -> 0 | K16: =G16+J16 -> 0 | M16: =M15+K16-L16 -> 0.0019999999
A17: 14 | B17: 46036 | G17: =E17*F17 -> 0 | J17: =H17*I17 -> 0 | K17: =G17+J17 -> 0 | M17: =M16+K17-L17 -> 0.0019999999
A18: 15 | B18: 46037 | G18: =E18*F18 -> 0 | J18: =H18*I18 -> 0 | K18: =G18+J18 -> 0 | M18: =M17+K18-L18 -> 0.0019999999
A19: 16 | B19: 46038 | G19: =E19*F19 -> 0 | J19: =H19*I19 -> 0 | K19: =G19+J19 -> 0 | M19: =M18+K19-L19 -> 0.0019999999
A20: 17 | B20: 46039 | G20: =E20*F20 -> 0 | J20: =H20*I20 -> 0 | K20: =G20+J20 -> 0 | M20: =M19+K20-L20 -> 0.0019999999
A21: 18 | B21: 46040 | G21: =E21*F21 -> 0 | J21: =H21*I21 -> 0 | K21: =G21+J21 -> 0 | M21: =M20+K21-L21 -> 0.0019999999
A22: 19 | B22: 46041 | G22: =E22*F22 -> 0 | J22: =H22*I22 -> 0 | K22: =G22+J22 -> 0 | M22: =M21+K22-L22 -> 0.0019999999
A23: 20 | B23: 46042 | G23: =E23*F23 -> 0 | J23: =H23*I23 -> 0 | K23: =G23+J23 -> 0 | M23: =M22+K23-L23 -> 0.0019999999
A24: 21 | B24: 46043 | G24: =E24*F24 -> 0 | J24: =H24*I24 -> 0 | K24: =G24+J24 -> 0 | M24: =M23+K24-L24 -> 0.0019999999
A25: 22 | B25: 46044 | G25: =E25*F25 -> 0 | J25: =H25*I25 -> 0 | K25: =G25+J25 -> 0 | M25: =M24+K25-L25 -> 0.0019999999
A26: 23 | B26: 46045 | G26: =E26*F26 -> 0 | J26: =H26*I26 -> 0 | K26: =G26+J26 -> 0 | M26: =M25+K26-L26 -> 0.0019999999
A27: 24 | B27: 46046 | G27: =E27*F27 -> 0 | J27: =H27*I27 -> 0 | K27: =G27+J27 -> 0 | M27: =M26+K27-L27 -> 0.0019999999
A28: 25 | B28: 46047 | G28: =E28*F28 -> 0 | J28: =H28*I28 -> 0 | K28: =G28+J28 -> 0 | M28: =M27+K28-L28 -> 0.0019999999
... A32: 29 | B32: 46051 | G32: =E32*F32 -> 0 | J32: =H32*I32 -> 0 | K32: =G32+J32 -> 0 | M32: =M31+K32-L32 -> 0.0019999999
A33: 30 | B33: 46052 | G33: =E33*F33 -> 0 | J33: =H33*I33 -> 0 | K33: =G33+J33 -> 0 | L33: 0 | M33: =M32+K33-L33 -> 0.0019999999
A34: 31 | G34: =E34*F34 -> 0 | J34: =H34*I34 -> 0 | K34: =G34+J34 -> 0 | L34: 0 | M34: =M33+K34-L34 -> 0.0019999999
A35: 32 | G35: =E35*F35 -> 0 | J35: =H35*I35 -> 0 | K35: =G35+J35 -> 0 | L35: 0 | M35: =M34+K35-L35 -> 0.0019999999
A36: 33 | G36: =E36*F36 -> 0 | J36: =H36*I36 -> 0 | K36: =G36+J36 -> 0 | L36: 0 | M36: =M35+K36-L36 -> 0.0019999999
E37: =SUM(E4:E36) -> 135 | G37: =SUM(G4:G36) -> 12328.2 | H37: =SUM(H4:H36) -> 37 | J37: =SUM(J4:J36) -> 3819.88 | K37: =SUM(K4:K36) -> 16148.08 | L37: =SUM(L4:L36) -> 676678.88

Sheet Munavali-2
A1: Shiri Shva Petroluem
A2: S.No | B2: Date | C2: GRN No | D2: Ind No/Bill No | E2: Diesel (Lts) | F2: Price | G2: Amount | H2: Petrol (Lts) | I2: Price | J2: Amount | K2: Total amount | L2: Amount paid | M2: As on date | N2: Remarks
D3: Opening Balance | K3: 0 | M3: 0 | O3: 26506.4
A4: 1 | B4: 46023 | J4: =H4*I4 -> 0 | K4: =G4+J4 -> 0 | M4: =M3+K4-L4 -> 0
A5: 2 | B5: 46024 | C5: Start | E5: 500 | F5: 91.54 | G5: =E5*F5 -> 45770 | I5: 103.48 | J5: =H5*I5 -> 0 | K5: =G5+J5 -> 45770 | M5: =M4+K5-L5 -> 45770
A6: 3 | B6: 46025 | G6: =E6*F6 -> 0 | J6: =H6*I6 -> 0 | K6: =G6+J6 -> 0 | M6: =M5+K6-L6 -> 45770
A7: 4 | B7: 46026 | G7: =E7*F7 -> 0 | J7: =H7*I7 -> 0 | K7: =G7+J7 -> 0 | M7: =M6+K7-L7 -> 45770
A8: 5 | B8: 46027 | E8: 400 | F8: 91.54 | G8: =E8*F8 -> 36616 | J8: =H8*I8 -> 0 | K8: =G8+J8 -> 36616 | M8: =M7+K8-L8 -> 82386
A9: 6 | B9: 46028 | G9: =E9*F9 -> 0 | J9: =H9*I9 -> 0 | K9: =G9+J9 -> 0 | M9: =M8+K9-L9 -> 82386
A10: 7 | B10: 46029 | E10: 400 | F10: 91.54 | G10: =E10*F10 -> 36616 | H10: 20 | I10: 103.48 | J10: =H10*I10 -> 2069.6 | K10: =G10+J10 -> 38685.6 | M10: =M9+K10-L10 -> 121071.6
A11: 8 | B11: 46030 | G11: =E11*F11 -> 0 | J11: =H11*I11 -> 0 | K11: =G11+J11 -> 0 | M11: =M10+K11-L11 -> 121071.6
A12: 9 | B12: 46031 | G12: =E12*F12 -> 0 | J12: =H12*I12 -> 0 | K12: =G12+J12 -> 0 | M12: =M11+K12-L12 -> 121071.6
A13: 10 | B13: 46032 | E13: 400 | F13: 91.54 | G13: =E13*F13 -> 36616 | H13: 20 | I13: 103.48 | J13: =H13*I13 -> 2069.6 | K13: =G13+J13 -> 38685.6 | M13: =M12+K13-L13 -> 159757.2
A14: 11 | B14: 46033 | G14: =E14*F14 -> 0 | J14: =H14*I14 -> 0 | K14: =G14+J14 -> 0 | M14: =M13+K14-L14 -> 159757.2
A15: 12 | B15: 46034 | E15: 500 | F15: 91.54 | G15: =E15*F15 -> 45770 | H15: 20 | I15: 103.48 | J15: =H15*I15 -> 2069.6 | K15: =G15+J15 -> 47839.6 | M15: =M14+K15-L15 -> 207596.8
A16: 13 | B16: 46035 | D16: 0 | G16: =E16*F16 -> 0 | J16: =H16*I16 -> 0 | K16: =G16+J16 -> 0 | M16: =M15+K16-L16 -> 207596.8
A17: 14 | B17: 46036 | E17: 400 | F17: 91.54 | G17: =E17*F17 -> 36616 | J17: =H17*I17 -> 0 | K17: =G17+J17 -> 36616 | M17: =M16+K17-L17 -> 244212.8
A18: 15 | B18: 46037 | G18: =E18*F18 -> 0 | J18: =H18*I18 -> 0 | K18: =G18+J18 -> 0 | M18: =M17+K18-L18 -> 244212.8
A19: 16 | B19: 46038 | E19: 530 | F19: 91.54 | G19: =E19*F19 -> 48516.2 | H19: 5 | I19: 103.48 | J19: =H19*I19 -> 517.4 | K19: =G19+J19 -> 49033.6 | M19: =M18+K19-L19 -> 293246.4
A20: 17 | B20: 46039 | G20: =E20*F20 -> 0 | J20: =H20*I20 -> 0 | K20: =G20+J20 -> 0 | M20: =M19+K20-L20 -> 293246.4
A21: 18 | B21: 46040 | E21: 400 | F21: 91.54 | G21: =E21*F21 -> 36616 | H21: 30 | I21: 103.48 | J21: =H21*I21 -> 3104.4 | K21: =G21+J21 -> 39720.4 | M21: =M20+K21-L21 -> 332966.8
A22: 19 | B22: 46041 | G22: =E22*F22 -> 0 | H22: 20 | I22: 103.48 | J22: =H22*I22 -> 2069.6 | K22: =G22+J22 -> 2069.6 | L22: 293246 | M22: =M21+K22-L22 -> 41790.4
A23: 20 | B23: 46042 | G23: =E23*F23 -> 0 | J23: =H23*I23 -> 0 | K23: =G23+J23 -> 0 | M23: =M22+K23-L23 -> 41790.4
A24: 21 | B24: 46043 | G24: =E24*F24 -> 0 | J24: =H24*I24 -> 0 | K24: =G24+J24 -> 0 | M24: =M23+K24-L24 -> 41790.4
A25: 22 | B25: 46044 | E25: 500 | F25: 91.54 | G25: =E25*F25 -> 45770 | J25: =H25*I25 -> 0 | K25: =G25+J25 -> 45770 | M25: =M24+K25-L25 -> 87560.4
A26: 23 | B26: 46045 | E26: 500 | F26: 91.54 | G26: =E26*F26 -> 45770 | H26: 20 | I26: 103.48 | J26: =H26*I26 -> 2069.6 | K26: =G26+J26 -> 47839.6 | M26: =M25+K26-L26 -> 135400
A27: 24 | B27: 46046 | G27: =E27*F27 -> 0 | J27: =H27*I27 -> 0 | K27: =G27+J27 -> 0 | M27: =M26+K27-L27 -> 135400
A28: 25 | B28: 46047 | E28: 600 | F28: 91.54 | G28: =E28*F28 -> 54924 | J28: =H28*I28 -> 0 | K28: =G28+J28 -> 54924 | M28: =M27+K28-L28 -> 190324
A29: 26 | B29: 46048 | G29: =E29*F29 -> 0 | J29: =H29*I29 -> 0 | K29: =G29+J29 -> 0 | M29: =M28+K29-L29 -> 190324
A30: 27 | B30: 46049 | G30: =E30*F30 -> 0 | H30: 15 | I30: 103.48 | J30: =H30*I30 -> 1552.2 | K30: =G30+J30 -> 1552.2 | M30: =M29+K30-L30 -> 191876.2
A31: 28 | B31: 46050 | E31: 600 | F31: 91.54 | G31: =E31*F31 -> 54924 | H31: 26 | I31: 103.48 | J31: =H31*I31 -> 2690.48 | K31: =G31+J31 -> 57614.48 | M31: =M30+K31-L31 -> 249490.68
A32: 29 | B32: 46051 | E32: 600 | F32: 91.54 | G32: =E32*F32 -> 54924 | H32: 20 | I32: 103.48 | J32: =H32*I32 -> 2069.6 | K32: =G32+J32 -> 56993.6 | M32: =M31+K32-L32 -> 306484.28
A33: 30 | B33: 46052 | E33: 400 | F33: 91.54 | G33: =E33*F33 -> 36616 | J33: =H33*I33 -> 0 | K33: =G33+J33 -> 36616 | L33: 0 | M33: =M32+K33-L33 -> 343100.28
A34: 31 | B34: 46053 | G34: =E34*F34 -> 0 | H34: 5 | I34: 103.48 | J34: =H34*I34 -> 517.4 | K34: =G34+J34 -> 517.4 | L34: 0 | M34: =M33+K34-L34 -> 343617.68
A35: 32 | G35: =E35*F35 -> 0 | J35: =H35*I35 -> 0 | K35: =G35+J35 -> 0 | L35: 0 | M35: =M34+K35-L35 -> 343617.68
A36: 33 | G36: =E36*F36 -> 0 | J36: =H36*I36 -> 0 | K36: =G36+J36 -> 0 | L36: 0 | M36: =M35+K36-L36 -> 343617.68
E37: =SUM(E4:E36) -> 6730 | G37: =SUM(G4:G36) -> 616064.2 | H37: =SUM(H4:H36) -> 201 | J37: =SUM(J4:J36) -> 20799.48 | K37: =SUM(K4:K36) -> 636863.68 | L37: =SUM(L4:L36) -> 293246

Sheet Borgaon
A1: Aadisagar Petrolium
A2: S.No | B2: Date | C2: GRN No | D2: Ind no/Bill No | E2: Diesel (Lts) | F2: Price | G2: Amount | H2: Petrol (Lts) | I2: Price | J2: Amount | K2: Total amount | L2: Amount paid | M2: As on Date | N2: Remarks
A3: Opening Balance | K3: 120395.81 | M3: 120395.81
A4: 1 | B4: 46023 | E4: 70 | F4: 91.77 | G4: =E4*F4 -> 6423.9 | J4: =H4*I4 -> 0 | K4: =G4+J4 -> 6423.9 | M4: =M3+K4-L4 -> 126819.71
A5: 2 | B5: 46024 | E5: 1010 | F5: 91.77 | G5: =E5*F5 -> 92687.7 | H5: 10 | I5: 103.73 | J5: =H5*I5 -> 1037.3 | K5: =G5+J5 -> 93725 | M5: =M4+K5-L5 -> 220544.71
A6: 3 | B6: 46025 | E6: 0 | F6: 0 | G6: =E6*F6 -> 0 | J6: =H6*I6 -> 0 | K6: =G6+J6 -> 0 | M6: =M5+K6-L6 -> 220544.71
A7: 4 | B7: 46026 | E7: 0 | F7: 0 | G7: =E7*F7 -> 0 | J7: =H7*I7 -> 0 | K7: =G7+J7 -> 0 | M7: =M6+K7-L7 -> 220544.71
A8: 5 | B8: 46027 | E8: 800 | F8: 91.77 | G8: =E8*F8 -> 73416 | J8: =H8*I8 -> 0 | K8: =G8+J8 -> 73416 | M8: =M7+K8-L8 -> 293960.71
A9: 6 | B9: 46028 | E9: 0 | F9: 0 | G9: =E9*F9 -> 0 | H9: 5 | I9: 103.73 | J9: =H9*I9 -> 518.65 | K9: =G9+J9 -> 518.65 | M9: =M8+K9-L9 -> 294479.36
A10: 7 | B10: 46029 | E10: 820 | F10: 91.77 | G10: =E10*F10 -> 75251.4 | J10: =H10*I10 -> 0 | K10: =G10+J10 -> 75251.4 | M10: =M9+K10-L10 -> 369730.76
A11: 8 | B11: 46030 | E11: 420 | F11: 91.77 | G11: =E11*F11 -> 38543.4 | H11: 11 | I11: 103.73 | J11: =H11*I11 -> 1141.03 | K11: =G11+J11 -> 39684.43 | L11: 100000 | M11: =M10+K11-L11 -> 309415.19
A12: 9 | B12: 46031 | E12: 0 | F12: 0 | G12: =E12*F12 -> 0 | H12: 5 | I12: 103.73 | J12: =H12*I12 -> 518.65 | K12: =G12+J12 -> 518.65 | M12: =M11+K12-L12 -> 309933.84
A13: 10 | B13: 46032 | E13: 30 | F13: 91.77 | G13: =E13*F13 -> 2753.1 | H13: 15 | I13: 103.73 | J13: =H13*I13 -> 1555.95 | K13: =G13+J13 -> 4309.05 | M13: =M12+K13-L13 -> 314242.89
A14: 11 | B14: 46033 | E14: 0 | F14: 0 | G14: =E14*F14 -> 0 | J14: =H14*I14 -> 0 | K14: =G14+J14 -> 0 | M14: =M13+K14-L14 -> 314242.89
A15: 12 | B15: 46034 | E15: 20 | F15: 91.77 | G15: =E15*F15 -> 1835.4 | H15: 10 | I15: 103.73 | J15: =H15*I15 -> 1037.3 | K15: =G15+J15 -> 2872.7 | M15: =M14+K15-L15 -> 317115.59
A16: 13 | B16: 46035 | E16: 0 | F16: 91.77 | G16: =E16*F16 -> 0 | J16: =H16*I16 -> 0 | K16: =G16+J16 -> 0 | L16: 200000 | M16: =M15+K16-L16 -> 117115.59
A17: 14 | B17: 46036 | E17: 25 | F17: 91.77 | G17: =E17*F17 -> 2294.25 | H17: 5 | I17: 103.73 | J17: =H17*I17 -> 518.65 | K17: =G17+J17 -> 2812.9 | M17: =M16+K17-L17 -> 119928.49
A18: 15 | B18: 46037 | E18: 0 | F18: 0 | G18: =E18*F18 -> 0 | I18: 103.73 | J18: =H18*I18 -> 0 | K18: =G18+J18 -> 0 | M18: =M17+K18-L18 -> 119928.49
A19: 16 | B19: 46038 | E19: 0 | F19: 0 | G19: =E19*F19 -> 0 | I19: 103.73 | J19: =H19*I19 -> 0 | K19: =G19+J19 -> 0 | M19: =M18+K19-L19 -> 119928.49
A20: 17 | B20: 46039 | E20: 0 | F20: 0 | G20: =E20*F20 -> 0 | H20: 5 | I20: 103.73 | J20: =H20*I20 -> 518.65 | K20: =G20+J20 -> 518.65 | M20: =M19+K20-L20 -> 120447.14
A21: 18 | B21: 46040 | E21: 0 | F21: 0 | G21: =E21*F21 -> 0 | H21: 6 | I21: 103.73 | J21: =H21*I21 -> 622.38 | K21: =G21+J21 -> 622.38 | M21: =M20+K21-L21 -> 121069.52
A22: 19 | B22: 46041 | E22: 0 | F22: 0 | G22: =E22*F22 -> 0 | J22: =H22*I22 -> 0 | K22: =G22+J22 -> 0 | L22: 120000 | M22: =M21+K22-L22 -> 1069.5231
A23: 20 | B23: 46042 | E23: 0 | F23: 0 | G23: =E23*F23 -> 0 | J23: =H23*I23 -> 0 | K23: =G23+J23 -> 0 | M23: =M22+K23-L23 -> 1069.5231
A24: 21 | B24: 46043 | E24: 0 | F24: 0 | G24: =E24*F24 -> 0 | H24: 6 | I24: 103.73 | J24: =H24*I24 -> 622.38 | K24: =G24+J24 -> 622.38 | M24: =M23+K24-L24 -> 1691.9031
A25: 22 | B25: 46044 | E25: 70 | F25: 91.77 | G25: =E25*F25 -> 6423.9 | J25: =H25*I25 -> 0 | K25: =G25+J25 -> 6423.9 | M25: =M24+K25-L25 -> 8115.8031
A26: 23 | B26: 46045 | E26: 70 | F26: 91.77 | G26: =E26*F26 -> 6423.9 | J26: =H26*I26 -> 0 | K26: =G26+J26 -> 6423.9 | M26: =M25+K26-L26 -> 14539.703 | Q26: d
A27: 24 | B27: 46046 | E27: 120 | F27: 91.77 | G27: =E27*F27 -> 11012.4 | H27: 5 | I27: 103.73 | J27: =H27*I27 -> 518.65 | K27: =G27+J27 -> 11531.05 | M27: =M26+K27-L27 -> 26070.753 | Q27: 30 | R27: 50
A28: 25 | B28: 46047 | E28: 0 | F28: 0 | G28: =E28*F28 -> 0 | H28: 5 | I28: 103.73 | J28: =H28*I28 -> 518.65 | K28: =G28+J28 -> 518.65 | M28: =M27+K28-L28 -> 26589.403 | Q28: 50 | R28: 4.51
A29: 26 | B29: 46048 | E29: 0 | F29: 0 | G29: =E29*F29 -> 0 | J29: =H29*I29 -> 0 | K29: =G29+J29 -> 0 | M29: =M28+K29-L29 -> 26589.403
A30: 27 | B30: 46049 | E30: 800 | F30: 91.77 | G30: =E30*F30 -> 73416 | J30: =H30*I30 -> 0 | K30: =G30+J30 -> 73416 | M30: =M29+K30-L30 -> 100005.4
A31: 28 | B31: 46050 | E31: 0 | F31: 0 | G31: =E31*F31 -> 0 | H31: 6 | I31: 103.73 | J31: =H31*I31 -> 622.38 | K31: =G31+J31 -> 622.38 | M31: =M30+K31-L31 -> 100627.78
A32: 29 | B32: 46051 | E32: 0 | F32: 0 | G32: =E32*F32 -> 0 | J32: =H32*I32 -> 0 | K32: =G32+J32 -> 0 | M32: =M31+K32-L32 -> 100627.78
A33: 30 | B33: 46052 | E33: 125 | F33: 91.77 | G33: =E33*F33 -> 11471.25 | J33: =H33*I33 -> 0 | K33: =G33+J33 -> 11471.25 | M33: =M32+K33-L33 -> 112099.03
A34: 31 | B34: 46053 | E34: 35 | F34: 91.77 | G34: =E34*F34 -> 3211.95 | J34: =H34*I34 -> 0 | K34: =G34+J34 -> 3211.95 | M34: =M33+K34-L34 -> 115310.98
E35: =SUM(E4:E34) -> 4415 | G35: =SUM(G4:G34) -> 405164.55 | H35: =SUM(H4:H34) -> 94 | J35: =SUM(J4:J34) -> 9750.62 | K35: =SUM(K4:K34) -> 414915.17 | L35: =SUM(L4:L34) -> 420000

Sheet Ugar,Khagwad,Kudichi
A1: Shiri Bhrhmanath Petrolium
A2: S.No | B2: Date | C2: GRN No | D2: Ind No/Bill No | E2: Diesel (Lts) | F2: Price | G2: Amount | H2: Petrol (Lts) | I2: Price | J2: Amount | K2: Total amount | L2: Amount paid | M2: As on Date | N2: Remarks
A3: Opening Balance | K3: 292365.86 | M3: 292365.86 | O3: 235015.76 | P3: =O3-M3 -> -57350.102
A4: 1 | B4: 46023 | E4: 0 | F4: 0 | G4: =E4*F4 -> 0 | H4: 0 | I4: 0 | J4: =H4*I4 -> 0 | K4: =G4+J4 -> 0 | L4: 0 | M4: =M3+K4-L4 -> 292365.86 | Q4: 235410
A5: 2 | B5: 46024 | E5: 335 | F5: 91.93 | G5: =E5*F5 -> 30796.55 | H5: 40 | I5: 103.89 | J5: =H5*I5 -> 4155.6 | K5: =G5+J5 -> 34952.15 | L5: 0 | M5: =M4+K5-L5 -> 327318.01
A6: 3 | B6: 46025 | E6: 265 | F6: 91.93 | G6: =E6*F6 -> 24361.45 | H6: 0 | I6: 0 | J6: =H6*I6 -> 0 | K6: =G6+J6 -> 24361.45 | L6: 0 | M6: =M5+K6-L6 -> 351679.46
A7: 4 | B7: 46026 | E7: 35 | F7: 91.93 | G7: =E7*F7 -> 3217.55 | H7: 0 | I7: 0 | J7: =H7*I7 -> 0 | K7: =G7+J7 -> 3217.55 | L7: 0 | M7: =M6+K7-L7 -> 354897.01
A8: 5 | B8: 46027 | E8: 90 | F8: 91.93 | G8: =E8*F8 -> 8273.7 | H8: 40 | I8: 103.89 | J8: =H8*I8 -> 4155.6 | K8: =G8+J8 -> 12429.3 | L8: 0 | M8: =M7+K8-L8 -> 367326.31
A9: 6 | B9: 46028 | E9: 200 | F9: 91.93 | G9: =E9*F9 -> 18386 | H9: 0 | I9: 0 | J9: =H9*I9 -> 0 | K9: =G9+J9 -> 18386 | L9: 0 | M9: =M8+K9-L9 -> 385712.31
A10: 7 | B10: 46029 | E10: 0 | F10: 0 | G10: =E10*F10 -> 0 | H10: 0 | I10: 0 | J10: =H10*I10 -> 0 | K10: =G10+J10 -> 0 | L10: 0 | M10: =M9+K10-L10 -> 385712.31
A11: 8 | B11: 46030 | E11: 470 | F11: 91.93 | G11: =E11*F11 -> 43207.1 | H11: 30 | I11: 103.89 | J11: =H11*I11 -> 3116.7 | K11: =G11+J11 -> 46323.8 | L11: 0 | M11: =M10+K11-L11 -> 432036.11
A12: 9 | B12: 46031 | E12: 274.91 | F12: 91.93 | G12: =E12*F12 -> 25272.476 | H12: 0 | I12: 0 | J12: =H12*I12 -> 0 | K12: =G12+J12 -> 25272.476 | L12: 0 | M12: =M11+K12-L12 -> 457308.59
A13: 10 | B13: 46032 | E13: 0 | F13: 0 | G13: =E13*F13 -> 0 | H13: 0 | I13: 0 | J13: =H13*I13 -> 0 | K13: =G13+J13 -> 0 | L13: 0 | M13: =M12+K13-L13 -> 457308.59
A14: 11 | B14: 46033 | E14: 0 | F14: 0 | G14: =E14*F14 -> 0 | H14: 0 | I14: 0 | J14: =H14*I14 -> 0 | K14: =G14+J14 -> 0 | L14: 0 | M14: =M13+K14-L14 -> 457308.59
A15: 12 | B15: 46034 | E15: 0 | F15: 0 | G15: =E15*F15 -> 0 | H15: 0 | I15: 0 | J15: =H15*I15 -> 0 | K15: =G15+J15 -> 0 | L15: 0 | M15: =M14+K15-L15 -> 457308.59
A16: 13 | B16: 46035 | E16: 255 | F16: 91.93 | G16: =E16*F16 -> 23442.15 | H16: 30 | I16: 103.89 | J16: =H16*I16 -> 3116.7 | K16: =G16+J16 -> 26558.85 | L16: 300000 | M16: =M15+K16-L16 -> 183867.44
... A22: 19 | B22: 46041 | E22: 0 | F22: 0 | G22: =E22*F22 -> 0 | H22: 0 | I22: 0 | J22: =H22*I22 -> 0 | K22: =G22+J22 -> 0 | L22: 196000 | M22: =M21+K22-L22 -> 46661.588
A23: 20 | B23: 46042 | E23: 145 | F23: 91.93 | G23: =E23*F23 -> 13329.85 | H23: 0 | I23: 0 | J23: =H23*I23 -> 0 | K23: =G23+J23 -> 13329.85 | M23: =M22+K23-L23 -> 59991.438
A24: 21 | B24: 46043 | E24: 100 | F24: 91.93 | G24: =E24*F24 -> 9193 | H24: 0 | I24: 0 | J24: =H24*I24 -> 0 | K24: =G24+J24 -> 9193 | L24: 0 | M24: =M23+K24-L24 -> 69184.438
A25: 22 | B25: 46044 | E25: 265 | F25: 91.93 | G25: =E25*F25 -> 24361.45 | H25: 50 | I25: 103.89 | J25: =H25*I25 -> 5194.5 | K25: =G25+J25 -> 29555.95 | L25: 0 | M25: =M24+K25-L25 -> 98740.388
A26: 23 | B26: 46045 | E26: 95 | F26: 91.93 | G26: =E26*F26 -> 8733.35 | H26: 0 | I26: 0 | J26: =H26*I26 -> 0 | K26: =G26+J26 -> 8733.35 | L26: 0 | M26: =M25+K26-L26 -> 107473.74
A27: 24 | B27: 46046 | E27: 105 | F27: 91.93 | G27: =E27*F27 -> 9652.65 | H27: 0 | I27: 0 | J27: =H27*I27 -> 0 | K27: =G27+J27 -> 9652.65 | L27: 0 | M27: =M26+K27-L27 -> 117126.39
A28: 25 | B28: 46047 | E28: 0 | F28: 0 | G28: =E28*F28 -> 0 | H28: 0 | I28: 0 | J28: =H28*I28 -> 0 | K28: =G28+J28 -> 0 | L28: 0 | M28: =M27+K28-L28 -> 117126.39
A29: 26 | B29: 46048 | E29: 0 | F29: 0 | G29: =E29*F29 -> 0 | H29: 0 | I29: 0 | J29: =H29*I29 -> 0 | K29: =G29+J29 -> 0 | L29: 0 | M29: =M28+K29-L29 -> 117126.39
A30: 27 | B30: 46049 | E30: 56.87 | F30: 91.93 | G30: =E30*F30 -> 5228.0591 | H30: 55 | I30: 103.89 | J30: =H30*I30 -> 5713.95 | K30: =G30+J30 -> 10942.009 | L30: 0 | M30: =M29+K30-L30 -> 128068.4
A31: 28 | B31: 46050 | E31: 200 | F31: 91.93 | G31: =E31*F31 -> 18386 | H31: 0 | I31: 0 | J31: =H31*I31 -> 0 | K31: =G31+J31 -> 18386 | L31: 0 | M31: =M30+K31-L31 -> 146454.4
A32: 29 | B32: 46051 | E32: 55 | F32: 91.93 | G32: =E32*F32 -> 5056.15 | H32: 0 | I32: 0 | J32: =H32*I32 -> 0 | K32: =G32+J32 -> 5056.15 | L32: 0 | M32: =M31+K32-L32 -> 151510.55
A33: 30 | B33: 46052 | E33: 0 | F33: 0 | G33: =E33*F33 -> 0 | H33: 0 | I33: 0 | J33: =H33*I33 -> 0 | K33: =G33+J33 -> 0 | L33: 0 | M33: =M32+K33-L33 -> 151510.55
A34: 31 | B34: 46053 | E34: 0 | F34: 0 | G34: =E34*F34 -> 0 | H34: 0 | I34: 0 | J34: =H34*I34 -> 0 | K34: =G34+J34 -> 0 | L34: 0 | M34: =M33+K34-L34 -> 151510.55
E35: =SUM(E4:E34) -> 3546.78 | G35: =SUM(G4:G34) -> 326055.49 | H35: =SUM(H4:H34) -> 280 | J35: =SUM(J4:J34) -> 29089.2 | K35: =SUM(K4:K34) -> 355144.69 | L35: =SUM(L4:L34) -> 496000

Sheet Kabbur
A1: Shri Jai Hanuman Petrolium
A2: S.No | B2: Date | C2: GRN No | D2: Ind no/Bill No | E2: Diesel (Lts) | F2: Price | G2: Amount | H2: Petrol (Lts) | I2: Price | J2: Amount | K2: Total amount | L2: Amount paid | M2: As on Date | N2: Remarks
A3: Opening Balance | K3: 0 | M3: =+K3 -> 0
A4: 1 | B4: 46023 | G4: =E4*F4 -> 0 | J4: =H4*I4 -> 0 | K4: =G4+J4 -> 0 | L4: =+K4 -> 0
A5: 2 | B5: 46024 | G5: =E5*F5 -> 0 | H5: 13.8 | I5: 103.53 | J5: =H5*I5 -> 1428.714 | K5: =G5+J5 -> 1428.714 | L5: =+K5 -> 1428.714
A6: 3 | B6: 46025 | G6: =E6*F6 -> 0 | J6: =H6*I6 -> 0 | K6: =G6+J6 -> 0 | L6: =+K6 -> 0
A7: 4 | B7: 46026 | G7: =E7*F7 -> 0 | J7: =H7*I7 -> 0 | K7: =G7+J7 -> 0 | L7: =+K7 -> 0
A8: 5 | B8: 46027 | E8: 25 | F8: 91.59 | G8: =E8*F8 -> 2289.75 | H8: 5 | I8: 103.53 | J8: =H8*I8 -> 517.65 | K8: =G8+J8 -> 2807.4 | L8: =+K8 -> 2807.4
A9: 6 | B9: 46028 | G9: =E9*F9 -> 0 | H9: 5 | I9: 103.53 | J9: =H9*I9 -> 517.65 | K9: =G9+J9 -> 517.65 | L9: =+K9 -> 517.65
A10: 7 | B10: 46029 | G10: =E10*F10 -> 0 | H10: 7 | I10: 103.53 | J10: =H10*I10 -> 724.71 | K10: =G10+J10 -> 724.71 | L10: =+K10 -> 724.71
A11: 8 | B11: 46030 | E11: 25 | F11: 91.59 | G11: =E11*F11 -> 2289.75 | J11: =H11*I11 -> 0 | K11: =G11+J11 -> 2289.75 | L11: =+K11 -> 2289.75
A12: 9 | B12: 46031 | E12: 40 | F12: 91.59 | G12: =E12*F12 -> 3663.6 | J12: =H12*I12 -> 0 | K12: =G12+J12 -> 3663.6 | L12: =+K12 -> 3663.6
A13: 10 | B13: 46032 | G13: =E13*F13 -> 0 | J13: =H13*I13 -> 0 | K13: =G13+J13 -> 0 | L13: =+K13 -> 0
A14: 11 | B14: 46033 | G14: =E14*F14 -> 0 | J14: =H14*I14 -> 0 | K14: =G14+J14 -> 0 | L14: =+K14 -> 0
A15: 12 | B15: 46034 | G15: =E15*F15 -> 0 | J15: =H15*I15 -> 0 | K15: =G15+J15 -> 0 | L15: =+K15 -> 0
A16: 13 | B16: 46035 | G16: =E16*F16 -> 0 | J16: =H16*I16 -> 0 | K16: =G16+J16 -> 0 | L16: =+K16 -> 0
A17: 14 | B17: 46036 | G17: =E17*F17 -> 0 | J17: =H17*I17 -> 0 | K17: =G17+J17 -> 0 | L17: =+K17 -> 0
A18: 15 | B18: 46037 | G18: =E18*F18 -> 0 | J18: =H18*I18 -> 0 | K18: =G18+J18 -> 0 | L18: =+K18 -> 0
A19: 16 | B19: 46038 | G19: =E19*F19 -> 0 | J19: =H19*I19 -> 0 | K19: =G19+J19 -> 0 | L19: =+K19 -> 0
A20: 17 | B20: 46039 | G20: =E20*F20 -> 0 | J20: =H20*I20 -> 0 | K20: =G20+J20 -> 0 | L20: =+K20 -> 0
A21: 18 | B21: 46040 | G21: =E21*F21 -> 0 | J21: =H21*I21 -> 0 | K21: =G21+J21 -> 0 | L21: =+K21 -> 0
A22: 19 | B22: 46041 | G22: =E22*F22 -> 0 | J22: =H22*I22 -> 0 | K22: =G22+J22 -> 0 | L22: =+K22 -> 0
A23: 20 | B23: 46042 | E23: 13 | F23: 91.59 | G23: =E23*F23 -> 1190.67 | J23: =H23*I23 -> 0 | K23: =G23+J23 -> 1190.67 | L23: =+K23 -> 1190.67
A24: 21 | B24: 46043 | G24: =E24*F24 -> 0 | J24: =H24*I24 -> 0 | K24: =G24+J24 -> 0 | L24: =+K24 -> 0
A25: 22 | B25: 46044 | G25: =E25*F25 -> 0 | J25: =H25*I25 -> 0 | K25: =G25+J25 -> 0 | L25: =+K25 -> 0
A26: 23 | B26: 46045 | G26: =E26*F26 -> 0 | H26: 2 | I26: 103.53 | J26: =H26*I26 -> 207.06 | K26: =G26+J26 -> 207.06 | L26: =+K26 -> 207.06
A27: 24 | B27: 46046 | G27: =E27*F27 -> 0 | J27: =H27*I27 -> 0 | K27: =G27+J27 -> 0 | L27: =+K27 -> 0 | O27: 0
A28: 25 | B28: 46047 | G28: =E28*F28 -> 0 | J28: =H28*I28 -> 0 | K28: =G28+J28 -> 0 | L28: =+K28 -> 0
A29: 26 | B29: 46048 | G29: =E29*F29 -> 0 | J29: =H29*I29 -> 0 | K29: =G29+J29 -> 0 | L29: =+K29 -> 0
A30: 27 | B30: 46049 | G30: =E30*F30 -> 0 | J30: =H30*I30 -> 0 | K30: =G30+J30 -> 0 | L30: =+K30 -> 0
A31: 28 | B31: 46050 | G31: =E31*F31 -> 0 | J31: =H31*I31 -> 0 | K31: =G31+J31 -> 0 | L31: =+K31 -> 0
A32: 29 | B32: 46051 | G32: =E32*F32 -> 0 | J32: =H32*I32 -> 0 | K32: =G32+J32 -> 0 | L32: =+K32 -> 0
A33: 30 | B33: 46052 | G33: =E33*F33 -> 0 | J33: =H33*I33 -> 0 | K33: =G33+J33 -> 0 | L33: =+K33 -> 0
A34: 31 | G34: =E34*F34 -> 0 | J34: =H34*I34 -> 0 | K34: =G34+J34 -> 0
E35: =SUM(E4:E34) -> 103 | G35: =SUM(G4:G34) -> 9433.77 | H35: =SUM(H4:H34) -> 32.8 | J35: =SUM(J4:J34) -> 3395.784 | K35: =SUM(K4:K34) -> 12829.554 | L35: =SUM(L4:L34) -> 12829.554

Sheet kumta
A1: Krishma fuel station
A2: S.No | B2: Date | C2: GRN No | D2: Ind No/Bill No | E2: Diesel (Lts) | F2: Price | G2: Amount | H2: Petrol (Lts) | I2: Price | J2: Amount | K2: Total amount | L2: Amount paid | M2: As on Date | N2: Remarks
A3: Opening Balance | K3: 0 | M3: =+K3 -> 0
A4: 1 | B4: 46023 | E4: 0 | F4: 91.92 | G4: =E4*F4 -> 0 | H4: 0 | I4: 103.96 | J4: =H4*I4 -> 0 | K4: =G4+J4 -> 0 | L4: =+K4 -> 0 | M4: =M3+K4-L4 -> 0 | N4: IOCL Card
A5: 2 | B5: 46024 | E5: 80 | F5: 91.92 | G5: =E5*F5 -> 7353.6 | J5: =H5*I5 -> 0 | K5: =G5+J5 -> 7353.6 | L5: =+K5 -> 7353.6 | M5: =M4+K5-L5 -> 0
A6: 3 | B6: 46025 | E6: 0 | G6: =E6*F6 -> 0 | H6: 5 | I6: 103.96 | J6: =H6*I6 -> 519.8 | K6: =G6+J6 -> 519.8 | L6: =+K6 -> 519.8 | M6: =M5+K6-L6 -> 0
A7: 4 | B7: 46026 | E7: 98 | F7: 91.92 | G7: =E7*F7 -> 9008.16 | H7: 5 | I7: 103.96 | J7: =H7*I7 -> 519.8 | K7: =G7+J7 -> 9527.96 | L7: =+K7 -> 9527.96 | M7: =M6+K7-L7 -> 0
A8: 5 | B8: 46027 | E8: 27.99 | F8: 91.92 | G8: =E8*F8 -> 2572.8408 | J8: =H8*I8 -> 0 | K8: =G8+J8 -> 2572.8408 | L8: =+K8 -> 2572.8408 | M8: =M7+K8-L8 -> 0
A9: 6 | B9: 46028 | E9: 50 | F9: 91.92 | G9: =E9*F9 -> 4596 | J9: =H9*I9 -> 0 | K9: =G9+J9 -> 4596 | L9: =+K9 -> 4596 | M9: =M8+K9-L9 -> 0 | R9: 91.92
A10: 7 | B10: 46029 | E10: 80 | F10: 91.92 | G10: =E10*F10 -> 7353.6 | H10: 5 | I10: 103.96 | J10: =H10*I10 -> 519.8 | K10: =G10+J10 -> 7873.4 | L10: =+K10 -> 7873.4 | M10: =M9+K10-L10 -> 0
A11: 8 | B11: 46030 | E11: 90 | F11: 91.92 | G11: =E11*F11 -> 8272.8 | J11: =H11*I11 -> 0 | K11: =G11+J11 -> 8272.8 | L11: =+K11 -> 8272.8 | M11: =M10+K11-L11 -> 0 | R11: =6.5/675.74 -> 0.0096190843
A12: 9 | B12: 46031 | E12: 65 | F12: 91.92 | G12: =E12*F12 -> 5974.8 | J12: =H12*I12 -> 0 | K12: =G12+J12 -> 5974.8 | L12: =+K12 -> 5974.8 | M12: =M11+K12-L12 -> 0
A13: 10 | B13: 46032 | E13: 26 | F13: 91.92 | G13: =E13*F13 -> 2389.92 | H13: 5 | I13: 103.96 | J13: =H13*I13 -> 519.8 | K13: =G13+J13 -> 2909.72 | L13: =+K13 -> 2909.72 | M13: =M12+K13-L13 -> 0 | R13: =675.74/6.5 -> 103.96
A14: 11 | B14: 46033 | E14: 0 | G14: =E14*F14 -> 0 | J14: =H14*I14 -> 0 | K14: =G14+J14 -> 0 | L14: =+K14 -> 0 | M14: =M13+K14-L14 -> 0
A15: 12 | B15: 46034 | E15: 0 | G15: =E15*F15 -> 0 | J15: =H15*I15 -> 0 | K15: =G15+J15 -> 0 | L15: =+K15 -> 0 | M15: =M14+K15-L15 -> 0
A16: 13 | B16: 46035 | E16: 110 | F16: 91.92 | G16: =E16*F16 -> 10111.2 | H16: 15 | I16: 103.96 | J16: =H16*I16 -> 1559.4 | K16: =G16+J16 -> 11670.6 | L16: =+K16 -> 11670.6 | M16: =M15+K16-L16 -> 0
A17: 14 | B17: 46036 | E17: 100 | F17: 91.92 | G17: =E17*F17 -> 9192 | H17: 5 | I17: 103.96 | J17: =H17*I17 -> 519.8 | K17: =G17+J17 -> 9711.8 | L17: =+K17 -> 9711.8 | M17: =M16+K17-L17 -> 0
A18: 15 | B18: 46037 | E18: 120 | F18: 91.92 | G18: =E18*F18 -> 11030.4 | J18: =H18*I18 -> 0 | K18: =G18+J18 -> 11030.4 | L18: =+K18 -> 11030.4 | M18: =M17+K18-L18 -> 0
A19: 16 | B19: 46038 | E19: 0 | G19: =E19*F19 -> 0 | J19: =H19*I19 -> 0 | K19: =G19+J19 -> 0 | L19: =+K19 -> 0 | M19: =M18+K19-L19 -> 0
A20: 17 | B20: 46039 | E20: 0 | G20: =E20*F20 -> 0 | J20: =H20*I20 -> 0 | K20: =G20+J20 -> 0 | L20: =+K20 -> 0 | M20: =M19+K20-L20 -> 0
A21: 18 | B21: 46040 | E21: 0 | G21: =E21*F21 -> 0 | J21: =H21*I21 -> 0 | K21: =G21+J21 -> 0 | L21: =+K21 -> 0 | M21: =M20+K21-L21 -> 0
A22: 19 | B22: 46041 | E22: 70 | F22: 91.92 | G22: =E22*F22 -> 6434.4 | H22: 6.84 | I22: 103.96 | J22: =H22*I22 -> 711.0864 | K22: =G22+J22 -> 7145.4864 | L22: =+K22 -> 7145.4864 | M22: =M21+K22-L22 -> 0
A23: 20 | B23: 46042 | E23: 0 | G23: =E23*F23 -> 0 | H23: 5 | I23: 103.96 | J23: =H23*I23 -> 519.8 | K23: =G23+J23 -> 519.8 | L23: =+K23 -> 519.8 | M23: =M22+K23-L23 -> 0
A24: 21 | B24: 46043 | E24: 100 | F24: 91.92 | G24: =E24*F24 -> 9192 | J24: =H24*I24 -> 0 | K24: =G24+J24 -> 9192 | L24: =+K24 -> 9192 | M24: =M23+K24-L24 -> 0
A25: 22 | B25: 46044 | E25: 0 | G25: =E25*F25 -> 0 | J25: =H25*I25 -> 0 | K25: =G25+J25 -> 0 | L25: =+K25 -> 0 | M25: =M24+K25-L25 -> 0
A26: 23 | B26: 46045 | E26: 49.6 | F26: 91.92 | G26: =E26*F26 -> 4559.232 | J26: =H26*I26 -> 0 | K26: =G26+J26 -> 4559.232 | L26: =+K26 -> 4559.232 | M26: =M25+K26-L26 -> 0
A27: 24 | B27: 46046 | E27: 0 | G27: =E27*F27 -> 0 | J27: =H27*I27 -> 0 | K27: =G27+J27 -> 0 | L27: =+K27 -> 0 | M27: =M26+K27-L27 -> 0
A28: 25 | B28: 46047 | E28: 0 | G28: =E28*F28 -> 0 | J28: =H28*I28 -> 0 | K28: =G28+J28 -> 0 | L28: =+K28 -> 0 | M28: =M27+K28-L28 -> 0
A29: 26 | B29: 46048 | E29: 0 | G29: =E29*F29 -> 0 | J29: =H29*I29 -> 0 | K29: =G29+J29 -> 0 | L29: =+K29 -> 0 | M29: =M28+K29-L29 -> 0
A30: 27 | B30: 46049 | E30: 50 | F30: 91.92 | G30: =E30*F30 -> 4596 | H30: 19.57 | I30: 103.96 | J30: =H30*I30 -> 2034.4972 | K30: =G30+J30 -> 6630.4972 | L30: =+K30 -> 6630.4972 | M30: =M29+K30-L30 -> 0
A31: 28 | B31: 46050 | D31: Bpcl | E31: 100 | F31: 91.97 | G31: =E31*F31 -> 9197 | H31: 6 | I31: 103.96 | J31: =H31*I31 -> 623.76 | K31: =G31+J31 -> 9820.76 | L31: =+K31 -> 9820.76 | M31: =M30+K31-L31 -> 0
A32: 29 | B32: 46051 | D32: Bpcl | E32: 0 | G32: =E32*F32 -> 0 | J32: =H32*I32 -> 0 | K32: =G32+J32 -> 0 | L32: =+K32 -> 0 | M32: =M31+K32-L32 -> 0
A33: 30 | B33: 46052 | D33: Bpcl | E33: 30 | F33: 91.97 | G33: =E33*F33 -> 2759.1 | H33: 10 | I33: 103.96 | J33: =H33*I33 -> 1039.6 | K33: =G33+J33 -> 3798.7 | L33: =+K33 -> 3798.7 | M33: =M32+K33-L33 -> 0
A34: 31 | B34: 46053 | D34: Bpcl | E34: 100 | F34: 91.97 | G34: =E34*F34 -> 9197 | J34: =H34*I34 -> 0 | K34: =G34+J34 -> 9197 | L34: =+K34 -> 9197 | M34: =M33+K34-L34 -> 0
E35: =SUM(E4:E34) -> 1346.59 | G35: =SUM(G4:G34) -> 123790.05 | H35: =SUM(H4:H34) -> 87.41 | J35: =SUM(J4:J34) -> 9087.1436 | K35: =SUM(K4:K34) -> 132877.2 | L35: =SUM(L4:L34) -> 132877.2

Sheet Jalgaon
A1: Sri Sai Petrol Pump
A2: S.No | B2: Date | C2: GRN No | D2: Ind No/Bill No | E2: Diesel (Lts) | F2: Price | G2: Amount | H2: Petrol (Lts) | I2: Price | J2: Amount | K2: Total amount | L2: Amount paid | M2: As on Date | N2: Remarks
A3: Opening Balance | K3: 730303.78 | M3: =+K3 -> 730303.78
A4: 1 | B4: 01.1.2026 | E4: 400 | F4: 91.71 | G4: =E4*F4 -> 36684 | J4: =H4*I4 -> 0 | K4: =G4+J4 -> 36684 | M4: =M3+K4-L4 -> 766987.78
A5: 2 | B5: 02.1.2026 | E5: 0 | F5: 0 | G5: =E5*F5 -> 0 | J5: =H5*I5 -> 0 | K5: =G5+J5 -> 0 | M5: =M4+K5-L5 -> 766987.78
A6: 3 | B6: 03.1.2026 | E6: 0 | F6: 0 | G6: =E6*F6 -> 0 | H6: 30 | I6: 105.19 | J6: =H6*I6 -> 3155.7 | K6: =G6+J6 -> 3155.7 | M6: =M5+K6-L6 -> 770143.48
A7: 4 | B7: 04.1.2026 | E7: 400 | F7: 91.71 | G7: =E7*F7 -> 36684 | J7: =H7*I7 -> 0 | K7: =G7+J7 -> 36684 | M7: =M6+K7-L7 -> 806827.48
A8: 5 | B8: 05.1.2026 | E8: 0 | F8: 0 | G8: =E8*F8 -> 0 | J8: =H8*I8 -> 0 | K8: =G8+J8 -> 0 | M8: =M7+K8-L8 -> 806827.48
A9: 6 | B9: 07.1.2026 | E9: 2500 | F9: 91.71 | G9: =E9*F9 -> 229275 | H9: 25 | I9: 105.19 | J9: =H9*I9 -> 2629.75 | K9: =G9+J9 -> 231904.75 | M9: =M8+K9-L9 -> 1038732.2
A10: 7 | B10: 08.1.2026 | E10: 600 | F10: 91.71 | G10: =E10*F10 -> 55026 | J10: =H10*I10 -> 0 | K10: =G10+J10 -> 55026 | M10: =M9+K10-L10 -> 1093758.2
A11: 8 | B11: 09.01.2025 | E11: 400 | F11: 91.71 | G11: =E11*F11 -> 36684 | J11: =H11*I11 -> 0 | K11: =G11+J11 -> 36684 | M11: =M10+K11-L11 -> 1130442.2
A12: 9 | B12: 10.01.2025 | E12: 500 | F12: 91.71 | G12: =E12*F12 -> 45855 | J12: =H12*I12 -> 0 | K12: =G12+J12 -> 45855 | M12: =M11+K12-L12 -> 1176297.2
A13: 10 | B13: 11.01.2025 | E13: 3500 | F13: 91.71 | G13: =E13*F13 -> 320985 | H13: 30 | I13: 105.19 | J13: =H13*I13 -> 3155.7 | K13: =G13+J13 -> 324140.7 | M13: =M12+K13-L13 -> 1500437.9
A14: 11 | B14: 12.01.2025 | E14: 500 | F14: 91.71 | G14: =E14*F14 -> 45855 | J14: =H14*I14 -> 0 | K14: =G14+J14 -> 45855 | M14: =M13+K14-L14 -> 1546292.9
A15: 12 | B15: 13.01.2025 | E15: 500 | F15: 91.71 | G15: =E15*F15 -> 45855 | J15: =H15*I15 -> 0 | K15: =G15+J15 -> 45855 | M15: =M14+K15-L15 -> 1592147.9
A16: 13 | B16: 14.01.2025 | E16: 700 | F16: 91.71 | G16: =E16*F16 -> 64197 | J16: =H16*I16 -> 0 | K16: =G16+J16 -> 64197 | M16: =M15+K16-L16 -> 1656344.9
A17: 14 | B17: 15.01.2025 | E17: 0 | F17: 0 | G17: =E17*F17 -> 0 | J17: =H17*I17 -> 0 | K17: =G17+J17 -> 0 | M17: =M16+K17-L17 -> 1656344.9
A18: 15 | B18: 16.01.2025 | E18: 500 | F18: 91.71 | G18: =E18*F18 -> 45855 | H18: 35 | I18: 105.19 | J18: =H18*I18 -> 3681.65 | K18: =G18+J18 -> 49536.65 | M18: =M17+K18-L18 -> 1705881.6
A19: 16 | B19: 17.01.2025 | E19: 500 | F19: 91.71 | G19: =E19*F19 -> 45855 | J19: =H19*I19 -> 0 | K19: =G19+J19 -> 45855 | L19: 1600000 | M19: =M18+K19-L19 -> 151736.58
A20: 17 | B20: 18.01.2025 | E20: 0 | F20: 0 | G20: =E20*F20 -> 0 | J20: =H20*I20 -> 0 | K20: =G20+J20 -> 0 | M20: =M19+K20-L20 -> 151736.58
A21: 18 | B21: 19.01.2025 | E21: 500 | F21: 91.71 | G21: =E21*F21 -> 45855 | J21: =H21*I21 -> 0 | K21: =G21+J21 -> 45855 | M21: =M20+K21-L21 -> 197591.58
A22: 19 | B22: 20.01.2026 | E22: 4000 | F22: 91.71 | G22: =E22*F22 -> 366840 | H22: 42 | I22: 105.19 | J22: =H22*I22 -> 4417.98 | K22: =G22+J22 -> 371257.98 | M22: =M21+K22-L22 -> 568849.56
A23: 20 | B23: 21.01.2026 | E23: 500 | F23: 91.71 | G23: =E23*F23 -> 45855 | J23: =H23*I23 -> 0 | K23: =G23+J23 -> 45855 | M23: =M22+K23-L23 -> 614704.56
A24: 21 | B24: 22.01.2026 | E24: 500 | F24: 91.71 | G24: =E24*F24 -> 45855 | J24: =H24*I24 -> 0 | K24: =G24+J24 -> 45855 | M24: =M23+K24-L24 -> 660559.56
A25: 22 | B25: 23.01.2026 | E25: 400 | F25: 91.71 | G25: =E25*F25 -> 36684 | J25: =H25*I25 -> 0 | K25: =G25+J25 -> 36684 | M25: =M24+K25-L25 -> 697243.56
A26: 23 | B26: 24.01.2026 | E26: 0 | F26: 0 | G26: =E26*F26 -> 0 | H26: 40 | I26: 105.19 | J26: =H26*I26 -> 4207.6 | K26: =G26+J26 -> 4207.6 | M26: =M25+K26-L26 -> 701451.16
A27: 24 | B27: 25.01.2026 | E27: 500 | F27: 91.71 | G27: =E27*F27 -> 45855 | J27: =H27*I27 -> 0 | K27: =G27+J27 -> 45855 | M27: =M26+K27-L27 -> 747306.16
A28: 25 | B28: 26.01.2026 | E28: 2900 | F28: 91.61 | G28: =E28*F28 -> 265669 | J28: =H28*I28 -> 0 | K28: =G28+J28 -> 265669 | M28: =M27+K28-L28 -> 1012975.2
A29: 26 | B29: 27.01.2026 | E29: 0 | F29: 91.71 | G29: =E29*F29 -> 0 | H29: 30 | I29: 105.19 | J29: =H29*I29 -> 3155.7 | K29: =G29+J29 -> 3155.7 | M29: =M28+K29-L29 -> 1016130.9
A30: 27 | B30: 28.01.2026 | E30: 2500 | F30: 91.61 | G30: =E30*F30 -> 229025 | J30: =H30*I30 -> 0 | K30: =G30+J30 -> 229025 | M30: =M29+K30-L30 -> 1245155.9
A31: 28 | B31: 29.01.2026 | E31: 400 | F31: 91.71 | G31: =E31*F31 -> 36684 | J31: =H31*I31 -> 0 | K31: =G31+J31 -> 36684 | M31: =M30+K31-L31 -> 1281839.9
A32: 29 | B32: 30.01.2026 | E32: 0 | F32: 91.71 | G32: =E32*F32 -> 0 | H32: 40 | I32: 105.19 | J32: =H32*I32 -> 4207.6 | K32: =G32+J32 -> 4207.6 | M32: =M31+K32-L32 -> 1286047.5
A33: 30 | B33: 31.01.2026 | E33: 900 | F33: 91.71 | G33: =E33*F33 -> 82539 | J33: =H33*I33 -> 0 | K33: =G33+J33 -> 82539 | M33: =M32+K33-L33 -> 1368586.5
A34: 31 | E34: 0 | F34: 0 | G34: =E34*F34 -> 0 | J34: =H34*I34 -> 0 | K34: =G34+J34 -> 0 | M34: =M33+K34-L34 -> 1368586.5
A35: 32 | E35: 0 | F35: 0 | G35: =E35*F35 -> 0 | J35: =H35*I35 -> 0 | K35: =G35+J35 -> 0 | M35: =M34+K35-L35 -> 1368586.5
A36: 33 | E36: 0 | F36: 0 | G36: =E36*F36 -> 0 | J36: =H36*I36 -> 0 | K36: =G36+J36 -> 0 | M36: =M35+K36-L36 -> 1368586.5
A37: 34 | E37: 0 | F37: 0 | G37: =E37*F37 -> 0 | J37: =H37*I37 -> 0 | K37: =G37+J37 -> 0 | M37: =M36+K37-L37 -> 1368586.5 | P37: 41
A38: 35 | E38: 0 | F38: 0 | G38: =E38*F38 -> 0 | J38: =H38*I38 -> 0 | K38: =G38+J38 -> 0 | M38: =M37+K38-L38 -> 1368586.5 | P38: 40 | Q38: 5
A39: 36 | G39: =E39*F39 -> 0 | J39: =H39*I39 -> 0 | K39: =G39+J39 -> 0 | M39: =M38+K39-L39 -> 1368586.5
A40: 37 | G40: =E40*F40 -> 0 | J40: =H40*I40 -> 0 | K40: =G40+J40 -> 0 | M40: =M39+K40-L40 -> 1368586.5
A41: 38 | G41: =E41*F41 -> 0 | J41: =H41*I41 -> 0 | K41: =G41+J41 -> 0 | M41: =M40+K41-L41 -> 1368586.5
A42: 39 | G42: =E42*F42 -> 0 | J42: =H42*I42 -> 0 | K42: =G42+J42 -> 0 | M42: =M41+K42-L42 -> 1368586.5
A43: 40 | G43: =E43*F43 -> 0 | J43: =H43*I43 -> 0 | K43: =G43+J43 -> 0 | M43: =M42+K43-L43 -> 1368586.5
A44: 41 | G44: =E44*F44 -> 0 | J44: =H44*I44 -> 0 | K44: =G44+J44 -> 0 | M44: =M43+K44-L44 -> 1368586.5
A45: 42 | G45: =E45*F45 -> 0 | J45: =H45*I45 -> 0 | K45: =G45+J45 -> 0 | M45: =M44+K45-L45 -> 1368586.5
A46: 43 | G46: =E46*F46 -> 0 | J46: =H46*I46 -> 0 | K46: =G46+J46 -> 0 | M46: =M45+K46-L46 -> 1368586.5
A47: 44 | G47: =E47*F47 -> 0 | J47: =H47*I47 -> 0 | K47: =G47+J47 -> 0 | M47: =M46+K47-L47 -> 1368586.5
A48: 45 | G48: =E48*F48 -> 0 | J48: =H48*I48 -> 0 | K48: =G48+J48 -> 0 | M48: =M47+K48-L48 -> 1368586.5
A49: 46 | G49: =E49*F49 -> 0 | J49: =H49*I49 -> 0 | K49: =G49+J49 -> 0 | M49: =M48+K49-L49 -> 1368586.5
A50: 47 | G50: =E50*F50 -> 0 | J50: =H50*I50 -> 0 | K50: =G50+J50 -> 0 | L50: 0 | M50: =M49+K50-L50 -> 1368586.5
A51: 48 | G51: =E51*F51 -> 0 | J51: =H51*I51 -> 0 | K51: =G51+J51 -> 0 | L51: 0 | M51: =M50+K51-L51 -> 1368586.5
A52: 49 | G52: =E52*F52 -> 0 | J52: =H52*I52 -> 0 | K52: =G52+J52 -> 0 | L52: 0 | M52: =M51+K52-L52 -> 1368586.5
A53: 50 | G53: =E53*F53 -> 0 | J53: =H53*I53 -> 0 | K53: =G53+J53 -> 0 | L53: 0 | M53: =M52+K53-L53 -> 1368586.5 | O53: 1109792.3 | P53: =M53-O53 -> 258794.18
E54: =SUM(E4:E53) -> 24100 | G54: =SUM(G4:G53) -> 2209671 | H54: =SUM(H4:H53) -> 272 | J54: =SUM(J4:J53) -> 28611.68 | K54: =SUM(K4:K53) -> 2238282.7 | L54: =SUM(L4:L53) -> 1600000

Sheet MKBD
A1: Shree Sai Samarth Petroleum
A2: S.No | B2: Date | C2: GRN No | D2: Ind No/Bill No | E2: Diesel (Lts) | F2: Price | G2: Amount | H2: Petrol (Lts) | I2: Price | J2: Amount | K2: Total amount | L2: Amount paid | M2: As on Date | N2: Remarks
A3: Opening Balance | K3: 362563.78 | M3: =+K3 -> 362563.78 | O3: 1194597
A4: 1 | B4: 46023 | C4: 0 | G4: =E4*F4 -> 0 | J4: =H4*I4 -> 0 | K4: =G4+J4 -> 0 | M4: =M3+K4-L4 -> 362563.78
A5: 2 | B5: 46024 | C5: 0 | G5: =E5*F5 -> 0 | J5: =H5*I5 -> 0 | K5: =G5+J5 -> 0 | M5: =M4+K5-L5 -> 362563.78
A6: 3 | B6: 46025 | C6: 0 | E6: 600 | F6: 91.14 | G6: =E6*F6 -> 54684 | J6: =H6*I6 -> 0 | K6: =G6+J6 -> 54684 | M6: =M5+K6-L6 -> 417247.78
A7: 4 | B7: 46026 | C7: 0 | G7: 0 | J7: 0 | K7: 0 | M7: =M6+K7-L7 -> 417247.78
A8: 5 | B8: 46027 | C8: 0 | G8: =E8*F8 -> 0 | J8: =H8*I8 -> 0 | K8: =G8+J8 -> 0 | M8: =M7+K8-L8 -> 417247.78
A9: 6 | B9: 46028 | C9: 0 | E9: 800 | F9: 91.14 | G9: =E9*F9 -> 72912 | H9: 10 | I9: 104.6 | J9: =H9*I9 -> 1046 | K9: =G9+J9 -> 73958 | M9: =M8+K9-L9 -> 491205.78
A10: 7 | B10: 46029 | C10: 0 | G10: =E10*F10 -> 0 | J10: =H10*I10 -> 0 | K10: =G10+J10 -> 0 | M10: =M9+K10-L10 -> 491205.78
A11: 8 | B11: 46030 | C11: 0 | G11: =E11*F11 -> 0 | J11: =H11*I11 -> 0 | K11: =G11+J11 -> 0 | M11: =M10+K11-L11 -> 491205.78
A12: 9 | B12: 46031 | C12: 0 | G12: =E12*F12 -> 0 | J12: =H12*I12 -> 0 | K12: =G12+J12 -> 0 | M12: =M11+K12-L12 -> 491205.78
A13: 10 | B13: 46032 | C13: 0 | G13: =E13*F13 -> 0 | J13: =H13*I13 -> 0 | K13: =G13+J13 -> 0 | M13: =M12+K13-L13 -> 491205.78
A14: 11 | B14: 46033 | C14: 0 | G14: =E14*F14 -> 0 | J14: =H14*I14 -> 0 | K14: =G14+J14 -> 0 | M14: =M13+K14-L14 -> 491205.78
A15: 12 | B15: 46034 | C15: 0 | E15: 800 | F15: 91.14 | G15: =E15*F15 -> 72912 | H15: 10 | I15: 104.6 | J15: =H15*I15 -> 1046 | K15: =G15+J15 -> 73958 | M15: =M14+K15-L15 -> 565163.78
A16: 13 | B16: 46035 | C16: 0 | G16: =E16*F16 -> 0 | J16: =H16*I16 -> 0 | K16: =G16+J16 -> 0 | M16: =M15+K16-L16 -> 565163.78
A17: 14 | B17: 46036 | C17: 0 | G17: =E17*F17 -> 0 | J17: =H17*I17 -> 0 | K17: =G17+J17 -> 0 | M17: =M16+K17-L17 -> 565163.78
A18: 15 | B18: 46037 | C18: 0 | E18: 600 | F18: 91.14 | G18: =E18*F18 -> 54684 | J18: =H18*I18 -> 0 | K18: =G18+J18 -> 54684 | M18: =M17+K18-L18 -> 619847.78
A19: 16 | B19: 46038 | C19: 0 | G19: =E19*F19 -> 0 | J19: =H19*I19 -> 0 | K19: =G19+J19 -> 0 | M19: =M18+K19-L19 -> 619847.78
A20: 17 | B20: 46039 | C20: 0 | E20: 800 | F20: 91.14 | G20: =E20*F20 -> 72912 | H20: 20 | I20: 104.6 | J20: =H20*I20 -> 2092 | K20: =G20+J20 -> 75004 | M20: =M19+K20-L20 -> 694851.78
A21: 18 | B21: 46040 | C21: 0 | G21: =E21*F21 -> 0 | J21: =H21*I21 -> 0 | K21: =G21+J21 -> 0 | M21: =M20+K21-L21 -> 694851.78
A22: 19 | B22: 46041 | C22: 0 | G22: =E22*F22 -> 0 | J22: =H22*I22 -> 0 | K22: =G22+J22 -> 0 | L22: 523255 | M22: =M21+K22-L22 -> 171596.78 | Q22: =3800/26 -> 146.15385
A23: 20 | B23: 46042 | H23: 53 | I23: 209.79 | J23: =H23*I23 -> 11118.87 | K23: =G23+J23 -> 11118.87 | M23: =M22+K23-L23 -> 182715.65 | O23: Lubricant Purchaged
A24: 21 | B24: 46043 | C24: 0 | G24: =E24*F24 -> 0 | J24: =H24*I24 -> 0 | K24: =G24+J24 -> 0 | M24: =M23+K24-L24 -> 182715.65
A25: 22 | B25: 46044 | C25: 0 | G25: =E25*F25 -> 0 | J25: =H25*I25 -> 0 | K25: =G25+J25 -> 0 | M25: =M24+K25-L25 -> 182715.65
A26: 23 | B26: 46045 | C26: 0 | G26: =E26*F26 -> 0 | J26: =H26*I26 -> 0 | K26: =G26+J26 -> 0 | M26: =M25+K26-L26 -> 182715.65
A27: 24 | B27: 46046 | C27: 0 | G27: =E27*F27 -> 0 | J27: =H27*I27 -> 0 | K27: =G27+J27 -> 0 | M27: =M26+K27-L27 -> 182715.65
A28: 25 | B28: 46047 | C28: 0 | G28: =E28*F28 -> 0 | J28: =H28*I28 -> 0 | K28: =G28+J28 -> 0 | M28: =M27+K28-L28 -> 182715.65
A29: 26 | B29: 46048 | J29: =H29*I29 -> 0 | K29: =G29+J29 -> 0 | M29: =M28+K29-L29 -> 182715.65
A30: 27 | B30: 46049 | C30: 0 | E30: 1000 | F30: 91.14 | G30: =E30*F30 -> 91140 | J30: =H30*I30 -> 0 | K30: =G30+J30 -> 91140 | M30: =M29+K30-L30 -> 273855.65
A31: 28 | B31: 46050 | C31: 0 | G31: =E31*F31 -> 0 | J31: =H31*I31 -> 0 | K31: =G31+J31 -> 0 | M31: =M30+K31-L31 -> 273855.65
A32: 29 | B32: 46051 | C32: 0 | G32: =E32*F32 -> 0 | J32: =H32*I32 -> 0 | K32: =G32+J32 -> 0 | M32: =M31+K32-L32 -> 273855.65
A33: 30 | B33: 46052 | C33: 0 | G33: =E33*F33 -> 0 | J33: =H33*I33 -> 0 | K33: =G33+J33 -> 0 | M33: =M32+K33-L33 -> 273855.65
A34: 31 | B34: 46053 | C34: 0 | E34: 1000 | F34: 91.14 | G34: =E34*F34 -> 91140 | H34: 10 | I34: 104.6 | J34: =H34*I34 -> 1046 | K34: =G34+J34 -> 92186 | M34: =M33+K34-L34 -> 366041.65
A35: 32 | C35: 0 | G35: =E35*F35 -> 0 | J35: =H35*I35 -> 0 | K35: =G35+J35 -> 0 | M35: =M34+K35-L35 -> 366041.65
A36: 31 | C36: 0 | G36: =E36*F36 -> 0 | J36: =H36*I36 -> 0 | K36: =G36+J36 -> 0 | M36: =M35+K36-L36 -> 366041.65
A37: 32 | E37: 0 | F37: 0 | G37: =E37*F37 -> 0 | J37: =H37*I37 -> 0 | K37: =G37+J37 -> 0 | M37: =M36+K37-L37 -> 366041.65 | P37: 1194597.7 | Q37: =P37-M37 -> 828556.06
E38: =SUM(E4:E37) -> 5600 | G38: =SUM(G4:G37) -> 510384 | H38: =SUM(H4:H37) -> 103 | J38: =SUM(J4:J37) -> 16348.87 | K38: =SUM(K4:K37) -> 526732.87 | L38: =SUM(L4:L37) -> 523255

Sheet Haveri
A1: Shivalingeshwar Petroleum
A2: S.No | B2: Date | C2: GRN No | D2: Ind No/Bill No | E2: Diesel (Lts) | F2: Price | G2: Amount | H2: Petrol (Lts) | I2: Price | J2: Amount | K2: Total amount | L2: Amount paid | M2: As on Date | N2: Remarks
D3: Opening Balance | L3: 9461.0769 | M3: 9461.0769
A4: 1 | B4: 45658 | E4: 0 | F4: 0 | G4: 0 | H4: 0 | I4: 0 | J4: =H4*I4 -> 0 | K4: =G4+J4 -> 0 | L4: 0 | M4: =M3+K4-L4 -> 9461.0769
A5: 2 | B5: 45659 | E5: 0 | F5: 0 | G5: =E5*F5 -> 0 | H5: 0 | I5: 0 | J5: =H5*I5 -> 0 | K5: =G5+J5 -> 0 | L5: 0 | M5: =M4+K5-L5 -> 9461.0769
A6: 3 | B6: 45660 | E6: 0 | F6: 0 | G6: =E6*F6 -> 0 | H6: 0 | I6: 0 | J6: =H6*I6 -> 0 | K6: =G6+J6 -> 0 | L6: 0 | M6: =M5+K6-L6 -> 9461.0769
A7: 4 | B7: 45661 | E7: 0 | F7: 0 | G7: =E7*F7 -> 0 | H7: 0 | I7: 0 | J7: =H7*I7 -> 0 | K7: =G7+J7 -> 0 | L7: 0 | M7: =M6+K7-L7 -> 9461.0769
A8: 5 | B8: 45662 | E8: 0 | F8: 0 | G8: =E8*F8 -> 0 | H8: 0 | I8: 0 | J8: =H8*I8 -> 0 | K8: =G8+J8 -> 0 | L8: 0 | M8: =M7+K8-L8 -> 9461.0769
A9: 6 | B9: 45663 | E9: 0 | F9: 0 | G9: =E9*F9 -> 0 | H9: 0 | I9: 0 | J9: =H9*I9 -> 0 | K9: =G9+J9 -> 0 | L9: 9147 | M9: =M8+K9-L9 -> 314.0769
A10: 7 | B10: 45664 | E10: 0 | F10: 0 | G10: =E10*F10 -> 0 | H10: 0 | I10: 0 | J10: =H10*I10 -> 0 | K10: =G10+J10 -> 0 | L10: 314.08 | M10: =M9+K10-L10 -> -0.0031000001 | N10: Roud off
A11: 8 | B11: 45665 | E11: 0 | F11: 0 | G11: =E11*F11 -> 0 | H11: 0 | I11: 0 | J11: =H11*I11 -> 0 | K11: =G11+J11 -> 0 | L11: 0 | M11: =M10+K11-L11 -> -0.0031000001
A12: 9 | B12: 45666 | E12: 0 | F12: 0 | G12: =E12*F12 -> 0 | H12: 0 | I12: 0 | J12: =H12*I12 -> 0 | K12: =G12+J12 -> 0 | L12: 0 | M12: =M11+K12-L12 -> -0.0031000001 | O12: .
A13: 10 | B13: 45667 | E13: 0 | F13: 0 | G13: =E13*F13 -> 0 | H13: 0 | I13: 0 | J13: =H13*I13 -> 0 | K13: =G13+J13 -> 0 | L13: 0 | M13: =M12+K13-L13 -> -0.0031000001
A14: 11 | B14: 45668 | E14: 0 | F14: 0 | G14: =E14*F14 -> 0 | H14: 0 | I14: 0 | J14: =H14*I14 -> 0 | K14: =G14+J14 -> 0 | L14: 0 | M14: =M13+K14-L14 -> -0.0031000001
A15: 12 | B15: 45669 | E15: 0 | F15: 0 | G15: =E15*F15 -> 0 | H15: 0 | I15: 0 | J15: =H15*I15 -> 0 | K15: =G15+J15 -> 0 | L15: 0 | M15: =M14+K15-L15 -> -0.0031000001
A16: 13 | B16: 45670 | E16: 0 | F16: 0 | G16: =E16*F16 -> 0 | H16: 0 | I16: 0 | J16: =H16*I16 -> 0 | K16: =G16+J16 -> 0 | L16: 0 | M16: =M15+K16-L16 -> -0.0031000001
A17: 14 | B17: 45671 | E17: 0 | F17: 0 | G17: =E17*F17 -> 0 | H17: 0 | I17: 0 | K17: =G17+J17 -> 0 | L17: 0 | M17: =M16+K17-L17 -> -0.0031000001
A18: 15 | B18: 45672 | E18: 0 | F18: 0 | G18: =E18*F18 -> 0 | H18: 0 | I18: 0 | J18: =H18*I18 -> 0 | K18: =G18+J18 -> 0 | L18: 0 | M18: =M17+K18-L18 -> -0.0031000001
A19: 16 | B19: 45673 | E19: 0 | F19: 0 | G19: =E19*F19 -> 0 | H19: 0 | I19: 0 | J19: =H19*I19 -> 0 | K19: =G19+J19 -> 0 | L19: 0 | M19: =M18+K19-L19 -> -0.0031000001
A20: 17 | B20: 45674 | E20: 0 | F20: 0 | G20: =E20*F20 -> 0 | H20: 0 | I20: 0 | J20: =H20*I20 -> 0 | K20: =G20+J20 -> 0 | L20: 0 | M20: =M19+K20-L20 -> -0.0031000001
A21: 18 | B21: 45675 | E21: 0 | F21: 0 | G21: =E21*F21 -> 0 | H21: 0 | I21: 0 | J21: =H21*I21 -> 0 | K21: =G21+J21 -> 0 | L21: 0 | M21: =M20+K21-L21 -> -0.0031000001
A22: 19 | B22: 45676 | E22: 0 | F22: 0 | G22: =E22*F22 -> 0 | H22: 0 | I22: 0 | J22: =H22*I22 -> 0 | K22: =G22+J22 -> 0 | L22: 0 | M22: =M21+K22-L22 -> -0.0031000001
A23: 20 | B23: 45677 | E23: 0 | F23: 0 | G23: =E23*F23 -> 0 | H23: 0 | I23: 0 | J23: =H23*I23 -> 0 | K23: =G23+J23 -> 0 | L23: 0 | M23: =M22+K23-L23 -> -0.0031000001
A24: 21 | B24: 45678 | E24: 0 | F24: 0 | G24: =E24*F24 -> 0 | H24: 0 | I24: 0 | J24: =H24*I24 -> 0 | K24: =G24+J24 -> 0 | L24: 0 | M24: =M23+K24-L24 -> -0.0031000001
A25: 22 | B25: 45679 | E25: 0 | F25: 0 | G25: =E25*F25 -> 0 | H25: 0 | I25: 0 | J25: =H25*I25 -> 0 | K25: =G25+J25 -> 0 | L25: 0 | M25: =M24+K25-L25 -> -0.0031000001
A26: 23 | B26: 45680 | E26: 0 | F26: 0 | G26: =E26*F26 -> 0 | H26: 0 | I26: 0 | J26: =H26*I26 -> 0 | K26: =G26+J26 -> 0 | L26: 0 | M26: =M25+K26-L26 -> -0.0031000001
A27: 24 | B27: 45681 | E27: 0 | F27: 0 | G27: =E27*F27 -> 0 | H27: 0 | I27: 0 | J27: =H27*I27 -> 0 | K27: =G27+J27 -> 0 | L27: 0 | M27: =M26+K27-L27 -> -0.0031000001
A28: 25 | B28: 45682 | E28: 0 | F28: 0 | G28: =E28*F28 -> 0 | H28: 0 | I28: 0 | J28: =H28*I28 -> 0 | K28: =G28+J28 -> 0 | L28: 0 | M28: =M27+K28-L28 -> -0.0031000001
A29: 26 | B29: 45683 | E29: 0 | F29: 0 | G29: =E29*F29 -> 0 | H29: 0 | I29: 0 | J29: =H29*I29 -> 0 | K29: =G29+J29 -> 0 | L29: 0 | M29: =M28+K29-L29 -> -0.0031000001
A30: 27 | B30: 45684 | E30: 0 | F30: 0 | G30: =E30*F30 -> 0 | H30: 0 | I30: 0 | J30: =H30*I30 -> 0 | K30: =G30+J30 -> 0 | L30: 0 | M30: =M29+K30-L30 -> -0.0031000001
A31: 28 | B31: 45685 | E31: 0 | F31: 0 | G31: =E31*F31 -> 0 | H31: 0 | I31: 0 | J31: =H31*I31 -> 0 | K31: =G31+J31 -> 0 | L31: 0 | M31: =M30+K31-L31 -> -0.0031000001 | R31: 46.61
A32: 29 | B32: 45686 | E32: 0 | F32: 0 | G32: =E32*F32 -> 0 | H32: 0 | I32: 0 | J32: =H32*I32 -> 0 | K32: =G32+J32 -> 0 | L32: 0 | M32: =M31+K32-L32 -> -0.0031000001 | R32: 100
A33: 30 | B33: 45687 | E33: 0 | F33: 0 | G33: =E33*F33 -> 0 | H33: 0 | I33: 0 | J33: =H33*I33 -> 0 | K33: =G33+J33 -> 0 | L33: 0 | M33: =M32+K33-L33 -> -0.0031000001 | R33: 35
A34: 31 | B34: 45688 | E34: 0 | F34: 0 | G34: =E34*F34 -> 0 | H34: 0 | I34: 0 | J34: =H34*I34 -> 0 | K34: =G34+J34 -> 0 | L34: 0 | M34: =M33+K34-L34 -> -0.0031000001 | N34: BPCL OTP
A35: 32 | B35: 45689 | E35: 0 | F35: 0 | G35: =E35*F35 -> 0 | H35: 0 | I35: 0 | J35: =H35*I35 -> 0 | K35: =G35+J35 -> 0 | L35: 0 | M35: =M34+K35-L35 -> -0.0031000001
H36: 0 | I36: 0 | M36: =M35+K36-L36 -> -0.0031000001
E37: =SUM(E4:E35) -> 0 | G37: =SUM(G4:G35) -> 0 | H37: =SUM(H4:H35) -> 0 | J37: =SUM(J4:J35) -> 0 | K37: =SUM(K4:K35) -> 0 | L37: =SUM(L4:L35) -> 9461.08
I40: =K25+L25 -> 0

Sheet  Haveri-2
A1: Magavi fuel F/S
A2: S.No | B2: Date | C2: GRN No | D2: Ind No/Bill No | E2: Diesel (Lts) | F2: Price | G2: Amount | H2: Petrol (Lts) | I2: Price | J2: Amount | K2: Total amount | L2: Amount paid | M2: As on Date | N2: Remarks
D3: Opening Balance | L3: 164443.72 | M3: 164443.72
A4: 1 | B4: 46023 | E4: 300 | F4: 91.49 | G4: =E4*F4 -> 27447 | H4: 10 | I4: 103.43 | J4: =H4*I4 -> 1034.3 | K4: =G4+J4 -> 28481.3 | L4: 0 | M4: =M3+K4-L4 -> 192925.02
A5: 2 | B5: 46024 | E5: 92.08 | F5: 91.49 | G5: =E5*F5 -> 8424.3992 | H5: 0 | I5: 0 | J5: =H5*I5 -> 0 | K5: =G5+J5 -> 8424.3992 | L5: 0 | M5: =M4+K5-L5 -> 201349.42
A6: 3 | B6: 46025 | E6: 125 | F6: 91.49 | G6: =E6*F6 -> 11436.25 | H6: 0 | I6: 0 | J6: =H6*I6 -> 0 | K6: =G6+J6 -> 11436.25 | L6: 165000 | M6: =M5+K6-L6 -> 47785.67
A7: 4 | B7: 46026 | E7: 71 | F7: 91.49 | G7: =E7*F7 -> 6495.79 | H7: 6 | I7: 103.43 | J7: =H7*I7 -> 620.58 | K7: =G7+J7 -> 7116.37 | L7: 0 | M7: =M6+K7-L7 -> 54902.04
A8: 5 | B8: 46027 | E8: 350 | F8: 91.49 | G8: =E8*F8 -> 32021.5 | H8: 0 | I8: 0 | J8: =H8*I8 -> 0 | K8: =G8+J8 -> 32021.5 | L8: 0 | M8: =M7+K8-L8 -> 86923.54
A9: 6 | B9: 46028 | E9: 155.5 | F9: 91.49 | G9: =E9*F9 -> 14226.695 | H9: 0 | I9: 0 | J9: =H9*I9 -> 0 | K9: =G9+J9 -> 14226.695 | L9: 0 | M9: =M8+K9-L9 -> 101150.24
A10: 7 | B10: 46029 | E10: 305 | F10: 91.49 | G10: =E10*F10 -> 27904.45 | H10: 0 | I10: 0 | J10: =H10*I10 -> 0 | K10: =G10+J10 -> 27904.45 | L10: 0 | M10: =M9+K10-L10 -> 129054.69
A11: 8 | B11: 46030 | E11: 120 | F11: 91.49 | G11: =E11*F11 -> 10978.8 | H11: 6 | I11: 103.43 | J11: =H11*I11 -> 620.58 | K11: =G11+J11 -> 11599.38 | L11: 0 | M11: =M10+K11-L11 -> 140654.07
A12: 9 | B12: 46031 | E12: 409 | F12: 91.49 | G12: =E12*F12 -> 37419.41 | H12: 5 | I12: 103.43 | J12: =H12*I12 -> 517.15 | K12: =G12+J12 -> 37936.56 | L12: 0 | M12: =M11+K12-L12 -> 178590.63 | O12: .
A13: 10 | B13: 46032 | E13: 515.08 | F13: 91.49 | G13: =E13*F13 -> 47124.669 | H13: 14.6 | I13: 103.43 | J13: =H13*I13 -> 1510.078 | K13: =G13+J13 -> 48634.747 | L13: 0 | M13: =M12+K13-L13 -> 227225.37
A14: 11 | B14: 46033 | E14: 100 | F14: 91.49 | G14: =E14*F14 -> 9149 | H14: 0 | I14: 0 | J14: =H14*I14 -> 0 | K14: =G14+J14 -> 9149 | L14: 0 | M14: =M13+K14-L14 -> 236374.37
A15: 12 | B15: 46034 | E15: 0 | F15: 0 | G15: =E15*F15 -> 0 | H15: 0 | I15: 0 | J15: =H15*I15 -> 0 | K15: =G15+J15 -> 0 | L15: 0 | M15: =M14+K15-L15 -> 236374.37
A16: 13 | B16: 46035 | E16: 358 | F16: 91.49 | G16: =E16*F16 -> 32753.42 | H16: 5 | I16: 103.43 | J16: =H16*I16 -> 517.15 | K16: =G16+J16 -> 33270.57 | L16: 0 | M16: =M15+K16-L16 -> 269644.94
A17: 14 | B17: 46036 | E17: 43.72 | F17: 91.49 | G17: =E17*F17 -> 3999.9428 | H17: 5 | I17: 103.43 | J17: =H17*I17 -> 517.15 | K17: =G17+J17 -> 4517.0928 | L17: 0 | M17: =M16+K17-L17 -> 274162.04
A18: 15 | B18: 46037 | E18: 0 | F18: 0 | G18: =E18*F18 -> 0 | H18: 0 | I18: 0 | J18: =H18*I18 -> 0 | K18: =G18+J18 -> 0 | L18: 0 | M18: =M17+K18-L18 -> 274162.04
A19: 16 | B19: 46038 | E19: 0 | F19: 0 | G19: =E19*F19 -> 0 | H19: 0 | I19: 0 | J19: =H19*I19 -> 0 | K19: =G19+J19 -> 0 | L19: 0 | M19: =M18+K19-L19 -> 274162.04
A20: 17 | B20: 46039 | E20: 95 | F20: 91.49 | G20: =E20*F20 -> 8691.55 | H20: 0 | I20: 0 | J20: =H20*I20 -> 0 | K20: =G20+J20 -> 8691.55 | L20: 0 | M20: =M19+K20-L20 -> 282853.59 | R20: 141649
A21: 18 | B21: 46040 | E21: 220 | F21: 91.49 | G21: =E21*F21 -> 20127.8 | H21: 0 | I21: 0 | J21: =H21*I21 -> 0 | K21: =G21+J21 -> 20127.8 | L21: 0 | M21: =M20+K21-L21 -> 302981.39
A22: 19 | B22: 46041 | E22: 32 | F22: 91.49 | G22: =E22*F22 -> 2927.68 | H22: 0 | I22: 0 | J22: =H22*I22 -> 0 | K22: =G22+J22 -> 2927.68 | L22: 274000 | M22: =M21+K22-L22 -> 31909.065
A23: 20 | B23: 46042 | E23: 200 | F23: 91.49 | G23: =E23*F23 -> 18298 | H23: 12.83 | I23: 103.43 | J23: =H23*I23 -> 1327.0069 | K23: =G23+J23 -> 19625.007 | L23: 0 | M23: =M22+K23-L23 -> 51534.072
A24: 21 | B24: 46043 | E24: 30 | F24: 91.49 | G24: =E24*F24 -> 2744.7 | H24: 5 | I24: 103.43 | J24: =H24*I24 -> 517.15 | K24: =G24+J24 -> 3261.85 | L24: 0 | M24: =M23+K24-L24 -> 54795.922
A25: 22 | B25: 46044 | E25: 245.03 | F25: 91.49 | G25: =E25*F25 -> 22417.795 | H25: 5 | I25: 103.43 | J25: =H25*I25 -> 517.15 | K25: =G25+J25 -> 22934.945 | L25: 0 | M25: =M24+K25-L25 -> 77730.867
A26: 23 | B26: 46045 | E26: 160.42 | F26: 91.49 | G26: =E26*F26 -> 14676.826 | H26: 0 | I26: 0 | J26: =H26*I26 -> 0 | K26: =G26+J26 -> 14676.826 | L26: 0 | M26: =M25+K26-L26 -> 92407.693
A27: 24 | B27: 46046 | E27: 0 | F27: 0 | G27: =E27*F27 -> 0 | H27: 5 | I27: 103.43 | J27: =H27*I27 -> 517.15 | K27: =G27+J27 -> 517.15 | L27: 0 | M27: =M26+K27-L27 -> 92924.843
A28: 25 | B28: 46047 | E28: 182 | F28: 91.49 | G28: =E28*F28 -> 16651.18 | H28: 7.5 | I28: 103.43 | J28: =H28*I28 -> 775.725 | K28: =G28+J28 -> 17426.905 | L28: 0 | M28: =M27+K28-L28 -> 110351.75
A29: 26 | B29: 46048 | E29: 0 | F29: 0 | G29: =E29*F29 -> 0 | H29: 6 | I29: 103.43 | J29: =H29*I29 -> 620.58 | K29: =G29+J29 -> 620.58 | L29: 0 | M29: =M28+K29-L29 -> 110972.33
A30: 27 | B30: 46049 | E30: 63.43 | F30: 91.49 | G30: =E30*F30 -> 5803.2107 | H30: 0 | I30: 0 | J30: =H30*I30 -> 0 | K30: =G30+J30 -> 5803.2107 | L30: 0 | M30: =M29+K30-L30 -> 116775.54
A31: 28 | B31: 46050 | E31: 145 | F31: 91.49 | G31: =E31*F31 -> 13266.05 | H31: 12 | I31: 103.43 | J31: =H31*I31 -> 1241.16 | K31: =G31+J31 -> 14507.21 | L31: 0 | M31: =M30+K31-L31 -> 131282.75 | R31: 46.61
A32: 29 | B32: 46051 | E32: 96 | F32: 91.49 | G32: =E32*F32 -> 8783.04 | H32: 5 | I32: 103.43 | J32: =H32*I32 -> 517.15 | K32: =G32+J32 -> 9300.19 | L32: 0 | M32: =M31+K32-L32 -> 140582.94 | R32: 100
A33: 30 | B33: 46052 | E33: 25 | F33: 91.49 | G33: =E33*F33 -> 2287.25 | H33: 0 | I33: 0 | J33: =H33*I33 -> 0 | K33: =G33+J33 -> 2287.25 | L33: 0 | M33: =M32+K33-L33 -> 142870.19 | R33: 35
A34: 31 | B34: 46053 | E34: 87.01 | F34: 91.49 | G34: =E34*F34 -> 7960.5449 | H34: 0 | I34: 0 | J34: =H34*I34 -> 0 | K34: =G34+J34 -> 7960.5449 | L34: 0 | M34: =M33+K34-L34 -> 150830.73 | N34: BPCL OTP
A35: 32 | B35: 46053 | E35: 30 | F35: 91.13 | G35: =E35*F35 -> 2733.9 | H35: 0 | I35: 0 | J35: =H35*I35 -> 0 | K35: =G35+J35 -> 2733.9 | L35: 2733.9 | M35: =M34+K35-L35 -> 150830.73
H36: 0 | I36: 0 | M36: =M35+K36-L36 -> 150830.73
E37: =SUM(E4:E35) -> 4555.27 | G37: =SUM(G4:G35) -> 416750.85 | H37: =SUM(H4:H35) -> 109.93 | J37: =SUM(J4:J35) -> 11370.06 | K37: =SUM(K4:K35) -> 428120.91 | L37: =SUM(L4:L35) -> 441733.9
I40: =K25+L25 -> 22934.945

Sheet Guttal
A1: Taware filling station
A2: S.No | B2: Date | C2: GRN No | D2: Ind No/Bill No | E2: Diesel (Lts) | F2: Price | G2: Amount | H2: Petrol (Lts) | I2: Price | J2: Amount | K2: Total amount | L2: Amount paid | M2: As on Date | N2: Remarks
D3: Opening Balance | K3: 336687.37 | L3: 0 | M3: =+K3 -> 336687.37
A4: 1 | B4: 45658 | E4: 0 | F4: 0 | G4: =E4*F4 -> 0 | H4: 0 | I4: 0 | J4: =H4*I4 -> 0 | K4: =G4+J4 -> 0 | L4: 0 | M4: =M3+K4-L4 -> 336687.37
A5: 2 | B5: 45659 | E5: 0 | F5: 0 | G5: =E5*F5 -> 0 | H5: 0 | I5: 0 | J5: =H5*I5 -> 0 | K5: =G5+J5 -> 0 | M5: =M4+K5-L5 -> 336687.37
A6: 3 | B6: 45660 | E6: 0 | F6: 0 | G6: =E6*F6 -> 0 | H6: 0 | I6: 0 | J6: =H6*I6 -> 0 | K6: =G6+J6 -> 0 | M6: =M5+K6-L6 -> 336687.37
A7: 4 | B7: 45661 | E7: 0 | F7: 0 | G7: =E7*F7 -> 0 | H7: 0 | I7: 0 | J7: =H7*I7 -> 0 | K7: =G7+J7 -> 0 | M7: =M6+K7-L7 -> 336687.37
A8: 5 | B8: 45662 | E8: 0 | F8: 0 | G8: =E8*F8 -> 0 | H8: 0 | I8: 0 | J8: =H8*I8 -> 0 | K8: =G8+J8 -> 0 | M8: =M7+K8-L8 -> 336687.37
A9: 6 | B9: 45663 | E9: 0 | F9: 0 | G9: =E9*F9 -> 0 | H9: 0 | I9: 0 | J9: =H9*I9 -> 0 | K9: =G9+J9 -> 0 | M9: =M8+K9-L9 -> 336687.37
A10: 7 | B10: 45664 | E10: 0 | F10: 0 | G10: =E10*F10 -> 0 | H10: 0 | I10: 0 | J10: =H10*I10 -> 0 | K10: =G10+J10 -> 0 | M10: =M9+K10-L10 -> 336687.37
A11: 8 | B11: 45665 | E11: 0 | F11: 0 | G11: =E11*F11 -> 0 | H11: 0 | I11: 0 | J11: =H11*I11 -> 0 | K11: =G11+J11 -> 0 | L11: 200000 | M11: =M10+K11-L11 -> 136687.37
A12: 9 | B12: 45666 | E12: 0 | F12: 0 | G12: =E12*F12 -> 0 | H12: 0 | I12: 0 | J12: =H12*I12 -> 0 | K12: =G12+J12 -> 0 | M12: =M11+K12-L12 -> 136687.37 | O12: .
A13: 10 | B13: 45667 | E13: 0 | F13: 0 | G13: =E13*F13 -> 0 | H13: 0 | I13: 0 | J13: =H13*I13 -> 0 | K13: =G13+J13 -> 0 | M13: =M12+K13-L13 -> 136687.37
A14: 11 | B14: 45668 | E14: 0 | F14: 0 | G14: =E14*F14 -> 0 | H14: 0 | I14: 0 | J14: =H14*I14 -> 0 | K14: =G14+J14 -> 0 | M14: =M13+K14-L14 -> 136687.37
A15: 12 | B15: 45669 | E15: 0 | F15: 0 | G15: =E15*F15 -> 0 | H15: 0 | I15: 0 | J15: =H15*I15 -> 0 | K15: =G15+J15 -> 0 | M15: =M14+K15-L15 -> 136687.37
A16: 13 | B16: 45670 | E16: 0 | F16: 0 | G16: =E16*F16 -> 0 | H16: 0 | I16: 0 | J16: =H16*I16 -> 0 | K16: =G16+J16 -> 0 | M16: =M15+K16-L16 -> 136687.37
A17: 14 | B17: 45671 | E17: 0 | F17: 0 | G17: =E17*F17 -> 0 | H17: 0 | I17: 0 | J17: =H17*I17 -> 0 | K17: =G17+J17 -> 0 | M17: =M16+K17-L17 -> 136687.37
A18: 15 | B18: 45672 | E18: 0 | F18: 0 | G18: =E18*F18 -> 0 | H18: 0 | I18: 0 | J18: =H18*I18 -> 0 | K18: =G18+J18 -> 0 | M18: =M17+K18-L18 -> 136687.37
A19: 16 | B19: 45673 | E19: 0 | F19: 0 | G19: =E19*F19 -> 0 | H19: 0 | I19: 0 | J19: =H19*I19 -> 0 | K19: =G19+J19 -> 0 | M19: =M18+K19-L19 -> 136687.37
A20: 17 | B20: 45674 | E20: 0 | F20: 0 | G20: =E20*F20 -> 0 | H20: 0 | I20: 0 | J20: =H20*I20 -> 0 | K20: =G20+J20 -> 0 | L20: 136687.37 | M20: =M19+K20-L20 -> 0.00039999996
A21: 18 | B21: 45675 | E21: 0 | F21: 0 | G21: =E21*F21 -> 0 | H21: 0 | I21: 0 | J21: =H21*I21 -> 0 | K21: =G21+J21 -> 0 | M21: =M20+K21-L21 -> 0.00039999996
A22: 19 | B22: 45676 | E22: 0 | F22: 0 | G22: =E22*F22 -> 0 | H22: 0 | I22: 0 | J22: =H22*I22 -> 0 | K22: =G22+J22 -> 0 | M22: =M21+K22-L22 -> 0.00039999996
A23: 20 | B23: 45677 | E23: 0 | F23: 0 | G23: =E23*F23 -> 0 | H23: 0 | I23: 0 | J23: =H23*I23 -> 0 | K23: =G23+J23 -> 0 | M23: =M22+K23-L23 -> 0.00039999996
A24: 21 | B24: 45678 | E24: 0 | F24: 0 | G24: =E24*F24 -> 0 | H24: 0 | I24: 0 | J24: =H24*I24 -> 0 | K24: =G24+J24 -> 0 | M24: =M23+K24-L24 -> 0.00039999996
A25: 22 | B25: 45679 | E25: 0 | F25: 0 | G25: =E25*F25 -> 0 | H25: 0 | I25: 0 | J25: =H25*I25 -> 0 | K25: =G25+J25 -> 0 | M25: =M24+K25-L25 -> 0.00039999996
A26: 23 | B26: 45680 | E26: 0 | F26: 0 | G26: =E26*F26 -> 0 | H26: 0 | I26: 0 | J26: =H26*I26 -> 0 | K26: =G26+J26 -> 0 | M26: =M25+K26-L26 -> 0.00039999996
A27: 24 | B27: 45681 | E27: 0 | F27: 0 | G27: =E27*F27 -> 0 | H27: 0 | I27: 0 | J27: =H27*I27 -> 0 | K27: =G27+J27 -> 0 | M27: =M26+K27-L27 -> 0.00039999996
A28: 25 | B28: 45682 | E28: 0 | F28: 0 | G28: =E28*F28 -> 0 | H28: 0 | I28: 0 | J28: =H28*I28 -> 0 | K28: =G28+J28 -> 0 | M28: =M27+K28-L28 -> 0.00039999996
A29: 26 | B29: 45683 | E29: 0 | F29: 0 | G29: =E29*F29 -> 0 | H29: 0 | I29: 0 | J29: =H29*I29 -> 0 | K29: =G29+J29 -> 0 | M29: =M28+K29-L29 -> 0.00039999996 | Q29: 30
A30: 27 | B30: 45684 | E30: 0 | F30: 0 | G30: =E30*F30 -> 0 | H30: 0 | I30: 0 | J30: =H30*I30 -> 0 | K30: =G30+J30 -> 0 | M30: =M29+K30-L30 -> 0.00039999996 | Q30: 20.02
A31: 28 | B31: 45685 | E31: 0 | F31: 0 | G31: =E31*F31 -> 0 | H31: 0 | I31: 0 | J31: =H31*I31 -> 0 | K31: =G31+J31 -> 0 | M31: =M30+K31-L31 -> 0.00039999996
A32: 29 | B32: 45686 | E32: 0 | F32: 0 | G32: =E32*F32 -> 0 | H32: 0 | I32: 0 | J32: =H32*I32 -> 0 | K32: =G32+J32 -> 0 | M32: =M31+K32-L32 -> 0.00039999996
A33: 30 | B33: 45687 | E33: 0 | F33: 0 | G33: =E33*F33 -> 0 | H33: 0 | I33: 0 | J33: =H33*I33 -> 0 | K33: =G33+J33 -> 0 | M33: =M32+K33-L33 -> 0.00039999996
A34: 31 | B34: 45688 | E34: 0 | F34: 0 | G34: =E34*F34 -> 0 | H34: 0 | I34: 0 | J34: =H34*I34 -> 0 | K34: =G34+J34 -> 0 | L34: 0 | M34: =M33+K34-L34 -> 0.00039999996
E35: =SUM(E4:E34) -> 0 | G35: =SUM(G4:G34) -> 0 | H35: =SUM(H4:H34) -> 0 | J35: =SUM(J4:J34) -> 0 | K35: =SUM(K4:K34) -> 0 | L35: =SUM(L4:L34) -> 336687.37
I38: =K24+L24 -> 0

Sheet  Guttal-2
A1: Himagiri Petroleum
A2: S.No | B2: Date | C2: GRN No | D2: Ind No/Bill No | E2: Diesel (Lts) | F2: Price | G2: Amount | H2: Petrol (Lts) | I2: Price | J2: Amount | K2: Total amount | L2: Amount paid | M2: As on Date | N2: Remarks
D3: Opening Balance | K3: 0 | L3: 0 | M3: =+K3 -> 0
A4: 1 | B4: 45658 | E4: 0 | F4: 0 | G4: =E4*F4 -> 0 | H4: 0 | I4: 0 | J4: =H4*I4 -> 0 | K4: =G4+J4 -> 0 | L4: 0 | M4: =M3+K4-L4 -> 0
A5: 2 | B5: 45659 | E5: 419 | F5: 91.78 | G5: =E5*F5 -> 38455.82 | H5: 5 | I5: 103.74 | J5: =H5*I5 -> 518.7 | K5: =G5+J5 -> 38974.52 | M5: =M4+K5-L5 -> 38974.52
A6: 3 | B6: 45660 | E6: 210 | F6: 91.78 | G6: =E6*F6 -> 19273.8 | H6: 0 | I6: 103.74 | J6: =H6*I6 -> 0 | K6: =G6+J6 -> 19273.8 | M6: =M5+K6-L6 -> 58248.32
A7: 4 | B7: 45661 | E7: 330 | F7: 91.78 | G7: =E7*F7 -> 30287.4 | H7: 5 | I7: 103.74 | J7: =H7*I7 -> 518.7 | K7: =G7+J7 -> 30806.1 | M7: =M6+K7-L7 -> 89054.42
A8: 5 | B8: 45662 | E8: 230 | F8: 91.78 | G8: =E8*F8 -> 21109.4 | H8: 5 | I8: 103.74 | J8: =H8*I8 -> 518.7 | K8: =G8+J8 -> 21628.1 | M8: =M7+K8-L8 -> 110682.52
A9: 6 | B9: 45663 | E9: 145 | F9: 91.78 | G9: =E9*F9 -> 13308.1 | H9: 5 | I9: 103.74 | J9: =H9*I9 -> 518.7 | K9: =G9+J9 -> 13826.8 | M9: =M8+K9-L9 -> 124509.32
A10: 7 | B10: 45664 | E10: 230 | F10: 91.78 | G10: =E10*F10 -> 21109.4 | H10: 0 | I10: 0 | J10: =H10*I10 -> 0 | K10: =G10+J10 -> 21109.4 | M10: =M9+K10-L10 -> 145618.72
A11: 8 | B11: 45665 | E11: 250 | F11: 91.78 | G11: =E11*F11 -> 22945 | H11: 0 | I11: 0 | J11: =H11*I11 -> 0 | K11: =G11+J11 -> 22945 | M11: =M10+K11-L11 -> 168563.72
A12: 9 | B12: 45666 | E12: 0 | F12: 0 | G12: =E12*F12 -> 0 | H12: 10 | I12: 103.74 | J12: =H12*I12 -> 1037.4 | K12: =G12+J12 -> 1037.4 | M12: =M11+K12-L12 -> 169601.12 | O12: .
A13: 10 | B13: 45667 | E13: 170 | F13: 91.78 | G13: =E13*F13 -> 15602.6 | H13: 0 | I13: 0 | J13: =H13*I13 -> 0 | K13: =G13+J13 -> 15602.6 | M13: =M12+K13-L13 -> 185203.72
A14: 11 | B14: 45668 | E14: 486 | F14: 91.78 | G14: =E14*F14 -> 44605.08 | H14: 0 | I14: 0 | J14: =H14*I14 -> 0 | K14: =G14+J14 -> 44605.08 | M14: =M13+K14-L14 -> 229808.8
A15: 12 | B15: 45669 | E15: 355 | F15: 91.78 | G15: =E15*F15 -> 32581.9 | H15: 0 | I15: 0 | J15: =H15*I15 -> 0 | K15: =G15+J15 -> 32581.9 | M15: =M14+K15-L15 -> 262390.7
A16: 13 | B16: 45670 | E16: 180 | F16: 91.78 | G16: =E16*F16 -> 16520.4 | H16: 5 | I16: 103.74 | J16: =H16*I16 -> 518.7 | K16: =G16+J16 -> 17039.1 | M16: =M15+K16-L16 -> 279429.8
A17: 14 | B17: 45671 | E17: 455 | F17: 91.78 | G17: =E17*F17 -> 41759.9 | H17: 0 | I17: 0 | J17: =H17*I17 -> 0 | K17: =G17+J17 -> 41759.9 | L17: 150000 | M17: =M16+K17-L17 -> 171189.7
A18: 15 | B18: 45672 | E18: 0 | F18: 0 | G18: =E18*F18 -> 0 | H18: 0 | I18: 0 | J18: =H18*I18 -> 0 | K18: =G18+J18 -> 0 | M18: =M17+K18-L18 -> 171189.7
A19: 16 | B19: 45673 | E19: 386 | F19: 91.78 | G19: =E19*F19 -> 35427.08 | H19: 10 | I19: 103.74 | J19: =H19*I19 -> 1037.4 | K19: =G19+J19 -> 36464.48 | M19: =M18+K19-L19 -> 207654.18
A20: 17 | B20: 45674 | E20: 584.01 | F20: 91.78 | G20: =E20*F20 -> 53600.438 | H20: 0 | I20: 0 | J20: =H20*I20 -> 0 | K20: =G20+J20 -> 53600.438 | M20: =M19+K20-L20 -> 261254.62
A21: 18 | B21: 45675 | E21: 0 | F21: 0 | G21: =E21*F21 -> 0 | H21: 0 | I21: 0 | J21: =H21*I21 -> 0 | K21: =G21+J21 -> 0 | M21: =M20+K21-L21 -> 261254.62
A22: 19 | B22: 45676 | E22: 515 | F22: 91.78 | G22: =E22*F22 -> 47266.7 | H22: 5 | I22: 103.74 | J22: =H22*I22 -> 518.7 | K22: =G22+J22 -> 47785.4 | L22: 180000 | M22: =M21+K22-L22 -> 129040.02
A23: 20 | B23: 45677 | E23: 430 | F23: 91.78 | G23: =E23*F23 -> 39465.4 | H23: 0 | I23: 0 | J23: =H23*I23 -> 0 | K23: =G23+J23 -> 39465.4 | M23: =M22+K23-L23 -> 168505.42
A24: 21 | B24: 45678 | E24: 460 | F24: 91.78 | G24: =E24*F24 -> 42218.8 | H24: 5 | I24: 103.74 | J24: =H24*I24 -> 518.7 | K24: =G24+J24 -> 42737.5 | M24: =M23+K24-L24 -> 211242.92
A25: 22 | B25: 45679 | E25: 360 | F25: 91.78 | G25: =E25*F25 -> 33040.8 | H25: 10 | I25: 103.74 | J25: =H25*I25 -> 1037.4 | K25: =G25+J25 -> 34078.2 | M25: =M24+K25-L25 -> 245321.12
A26: 23 | B26: 45680 | E26: 470 | F26: 91.78 | G26: =E26*F26 -> 43136.6 | H26: 5 | I26: 103.74 | J26: =H26*I26 -> 518.7 | K26: =G26+J26 -> 43655.3 | M26: =M25+K26-L26 -> 288976.42
A27: 24 | B27: 45681 | E27: 455 | F27: 91.78 | G27: =E27*F27 -> 41759.9 | H27: 0 | I27: 0 | J27: =H27*I27 -> 0 | K27: =G27+J27 -> 41759.9 | M27: =M26+K27-L27 -> 330736.32
A28: 25 | B28: 45682 | E28: 280 | F28: 91.78 | G28: =E28*F28 -> 25698.4 | H28: 0 | I28: 0 | J28: =H28*I28 -> 0 | K28: =G28+J28 -> 25698.4 | M28: =M27+K28-L28 -> 356434.72
A29: 26 | B29: 45683 | E29: 0 | F29: 0 | G29: =E29*F29 -> 0 | H29: 0 | I29: 0 | J29: =H29*I29 -> 0 | K29: =G29+J29 -> 0 | M29: =M28+K29-L29 -> 356434.72 | Q29: 30
A30: 27 | B30: 45684 | E30: 495 | F30: 91.78 | G30: =E30*F30 -> 45431.1 | H30: 10 | I30: 103.74 | J30: =H30*I30 -> 1037.4 | K30: =G30+J30 -> 46468.5 | M30: =M29+K30-L30 -> 402903.22 | Q30: 20.02
A31: 28 | B31: 45685 | E31: 40 | F31: 91.78 | G31: =E31*F31 -> 3671.2 | H31: 5 | I31: 103.74 | J31: =H31*I31 -> 518.7 | K31: =G31+J31 -> 4189.9 | M31: =M30+K31-L31 -> 407093.12
A32: 29 | B32: 45686 | E32: 340 | F32: 91.78 | G32: =E32*F32 -> 31205.2 | H32: 5 | I32: 103.74 | J32: =H32*I32 -> 518.7 | K32: =G32+J32 -> 31723.9 | M32: =M31+K32-L32 -> 438817.02
A33: 30 | B33: 45687 | E33: 472 | F33: 91.78 | G33: =E33*F33 -> 43320.16 | H33: 5 | I33: 103.74 | J33: =H33*I33 -> 518.7 | K33: =G33+J33 -> 43838.86 | M33: =M32+K33-L33 -> 482655.88
A34: 31 | B34: 45688 | E34: 535 | F34: 91.78 | G34: =E34*F34 -> 49102.3 | H34: 5 | I34: 103.74 | J34: =H34*I34 -> 518.7 | K34: =G34+J34 -> 49621 | L34: 0 | M34: =M33+K34-L34 -> 532276.88
E35: =SUM(E4:E34) -> 9282.01 | G35: =SUM(G4:G34) -> 851902.88 | H35: =SUM(H4:H34) -> 100 | J35: =SUM(J4:J34) -> 10374 | K35: =SUM(K4:K34) -> 862276.88 | L35: =SUM(L4:L34) -> 330000
I38: =K24+L24 -> 42737.5

Sheet Rattihali
A1: Shree Siri Gowari petroliam
A2: S.No | B2: Date | C2: GRN No | D2: Ind No/Bill No | E2: Diesel (Lts) | F2: Price | G2: Amount | H2: Petrol (Lts) | I2: Price | J2: Amount | K2: Total amount | L2: Amount paid | M2: As on Date | N2: Remarks
D3: Opening Balance | K3: 6442.724 | M3: 6442.724
A4: 1 | B4: 45658 | F4: 0 | G4: =E4*F4 -> 0 | H4: 0 | I4: 0 | J4: =H4*I4 -> 0 | K4: =G4+J4 -> 0 | L4: 0 | M4: =M3+K4-L4 -> 6442.724
A5: 2 | B5: 45659 | F5: 0 | G5: =E5*F5 -> 0 | H5: 0 | I5: 0 | J5: =H5*I5 -> 0 | K5: =G5+J5 -> 0 | L5: 0 | M5: =M4+K5-L5 -> 6442.724
A6: 3 | B6: 45660 | F6: 0 | G6: =E6*F6 -> 0 | H6: 0 | I6: 0 | J6: =H6*I6 -> 0 | K6: =G6+J6 -> 0 | L6: 0 | M6: =M5+K6-L6 -> 6442.724
A7: 4 | B7: 45661 | F7: 0 | G7: =E7*F7 -> 0 | H7: 0 | I7: 0 | J7: =H7*I7 -> 0 | K7: =G7+J7 -> 0 | L7: 0 | M7: =M6+K7-L7 -> 6442.724
A8: 5 | B8: 45662 | F8: 0 | G8: =E8*F8 -> 0 | H8: 0 | I8: 0 | J8: =H8*I8 -> 0 | K8: =G8+J8 -> 0 | L8: 0 | M8: =M7+K8-L8 -> 6442.724
A9: 6 | B9: 45663 | F9: 0 | G9: =E9*F9 -> 0 | H9: 0 | I9: 0 | J9: =H9*I9 -> 0 | K9: =G9+J9 -> 0 | L9: 0 | M9: =M8+K9-L9 -> 6442.724
A10: 7 | B10: 45664 | F10: 0 | G10: =E10*F10 -> 0 | H10: 0 | I10: 0 | J10: =H10*I10 -> 0 | K10: =G10+J10 -> 0 | L10: 0 | M10: =M9+K10-L10 -> 6442.724
A11: 8 | B11: 45665 | F11: 0 | G11: =E11*F11 -> 0 | H11: 0 | I11: 0 | J11: =H11*I11 -> 0 | K11: =G11+J11 -> 0 | L11: 0 | M11: =M10+K11-L11 -> 6442.724
A12: 9 | B12: 45666 | F12: 0 | G12: =E12*F12 -> 0 | H12: 0 | I12: 0 | J12: =H12*I12 -> 0 | K12: =G12+J12 -> 0 | L12: 0 | M12: =M11+K12-L12 -> 6442.724 | O12: .
A13: 10 | B13: 45667 | F13: 0 | G13: =E13*F13 -> 0 | H13: 0 | I13: 0 | J13: =H13*I13 -> 0 | K13: =G13+J13 -> 0 | L13: 0 | M13: =M12+K13-L13 -> 6442.724
A14: 11 | B14: 45668 | F14: 0 | G14: =E14*F14 -> 0 | H14: 0 | I14: 0 | J14: =H14*I14 -> 0 | K14: =G14+J14 -> 0 | L14: 0 | M14: =M13+K14-L14 -> 6442.724
A15: 12 | B15: 45669 | F15: 0 | G15: =E15*F15 -> 0 | H15: 0 | I15: 0 | J15: =H15*I15 -> 0 | K15: =G15+J15 -> 0 | L15: 0 | M15: =M14+K15-L15 -> 6442.724
