Workbook

Sheet Oct-25 
A1: S.no | B1: Site Name | C1: Bunk Name | D1: Diesel(Liters) | E1: Diesel Amount | F1: Petrol(Liters) | G1: Petrol Amount | H1: Total Amount | I1: Opening Blance | J1: Amount Paid | K1: Closing Balances
A2: 1 | B2: Khammam-1 | C2: Divya laxmi ganapathi | D2: =+'Khammam-1'!E38 -> 56900 | E2: =+'Khammam-1'!G38 -> 5444192 | F2: =+'Khammam-1'!H38 -> 235 | G2: =+'Khammam-1'!J38 -> 25253.1 | H2: =E2+G2 -> 5469445.1 | I2: =+'Khammam-1'!K3 -> 11177697 | J2: =+'Khammam-1'!L38 -> 7500000 | K2: =H2+I2-J2 -> 9147141.7
A3: 2 | B3: Khammam-2 | C3: Jayasai union bunk | D3: =+'Khammam-2'!E38 -> 111000 | E3: =+'Khammam-2'!G38 -> 10622700 | F3: =+'Khammam-2'!H38 -> 900 | G3: =+'Khammam-2'!J38 -> 96732 | H3: =E3+G3 -> 10719432 | I3: =+'Khammam-2'!K3 -> 13443331 | J3: =+'Khammam-2'!L38 -> 0 | K3: =H3+I3-J3 -> 24162763
A4: 3 | B4: Jadcherla-1 | C4: Sai Baba Fuel Station | D4: =+'Jedcherla -1'!E36 -> 12153.6 | E4: =+'Jedcherla -1'!G36 -> 1171850.1 | F4: =+'Jedcherla -1'!H36 -> 693.13 | G4: =+'Jedcherla -1'!J36 -> 75018.46 | H4: =E4+G4 -> 1246868.6 | I4: =+'Jedcherla -1'!M3 -> 2639914.6 | J4: =+'Jedcherla -1'!L36 -> 2175000 | K4: =H4+I4-J4 -> 1711783.1
A5: 4 | B5: Jadcherla-2 | C5: ADHOC FILLING STATION STATION | D5: =+'Jedcharla-2'!E35 -> 51700 | E5: =+'Jedcharla-2'!G35 -> 4985431 | F5: 0 | G5: 0 | H5: =E5+G5 -> 4985431 | I5: =+'Jedcharla-2'!K3 -> 238933 | J5: =+'Jedcharla-2'!L35 -> 2900000 | K5: =H5+I5-J5 -> 2324364
A6: 5 | B6: Dindi | C6: Akarapu Balakistamma Fillling | D6: =+Dindi!E35 -> 85.88 | E6: =+Dindi!G35 -> 8315.7604 | F6: =+Dindi!H35 -> 0 | G6: =+Dindi!J35 -> 0 | H6: =E6+G6 -> 8315.7604 | J6: =+Dindi!L35 -> 8315.7604 | K6: =H6+I6-J6 -> 0
A7: 6 | B7: Devarkhadra-1 | C7: Kurumurthy Swami F/S | D7: =+Devarakhadra!E35 -> 7811.71 | E7: =+Devarakhadra!G35 -> 758517.04 | F7: =+Devarakhadra!H35 -> 129 | G7: =+Devarakhadra!J35 -> 14039.07 | H7: =E7+G7 -> 772556.11 | I7: =+Devarakhadra!M3 -> 121213.37 | J7: =+Devarakhadra!L35 -> 700000 | K7: =H7+I7-J7 -> 193769.48
A8: 7 | B8: Devarkhadra-2 | C8: M/S. Sri Rama Filling Station | D8: =+'Devarakhadra-2'!E35 -> 0 | E8: =+'Devarakhadra-2'!G35 -> 0 | F8: =+'Devarakhadra-2'!H35 -> 0 | G8: =+'Devarakhadra-2'!I35 -> 0 | H8: =E8+G8 -> 0 | I8: =+'Devarakhadra-2'!M3 -> 132273.54 | J8: =+'Devarakhadra-2'!L35 -> 132200 | K8: =H8+I8-J8 -> 73.536
A9: 8 | B9: Devarkhadra-3 | C9: JSASFuel Genie India Pvt.Ltd | D9: =+'Devarakhadra-3'!E35 -> 1743.87 | E9: =+'Devarakhadra-3'!G35 -> 167115.06 | F9: =+'Devarakhadra-3'!H35 -> 0 | G9: =+'Devarakhadra-3'!I35 -> 0 | H9: =E9+G9 -> 167115.06 | I9: =+'Devarakhadra-3'!M3 -> 0 | J9: =+'Devarakhadra-3'!L35 -> 0 | K9: =+'Devarakhadra-3'!M34 -> 167115.06
A10: 9 | B10: MAdanapalli | C10: Sri Mallikarjuna Traders | D10: =+'Madana palli'!E35 -> 1126.73 | E10: =+'Madana palli'!G35 -> 109975.3 | F10: =+'Madana palli'!H35 -> 15.93 | G10: =+'Madana palli'!J35 -> 1748.1757 | H10: =E10+G10 -> 111723.48 | I10: =+'Madana palli'!M3 -> 0 | J10: =+'Madana palli'!L35 -> 111723.48 | K10: =+'Devarakhadra-3'!M35 -> 0
A11: 10 | B11: Amalapuram | C11: Sathya Filling Station | D11: =+Amalapuram!E37 -> 340.68 | E11: =+Amalapuram!G37 -> 32321.64 | F11: =+Amalapuram!H37 -> 175 | G11: =+Amalapuram!J37 -> 19169.45 | H11: =E11+G11 -> 51491.09 | I11: =+Amalapuram!M3 -> 0 | J11: =+Amalapuram!L37 -> 51491.095 | K11: =H11+I11-J11 -> -0.0045
A12: 11 | B12: YG Gudda-1 | C12: Pallavi Petrolium | D12: =+'YG Gudda '!E36 -> 1000 | E12: =+'YG Gudda '!G36 -> 91300 | F12: =+'YG Gudda '!H36 -> 210 | G12: =+'YG Gudda '!J36 -> 21680.4 | H12: =E12+G12 -> 112980.4 | I12: ='YG Gudda '!K3 -> 109814.66 | J12: =+'YG Gudda '!L36 -> 120000 | K12: =H12+I12-J12 -> 102795.06
A13: 12 | B13: YG Gudda-2 | C13: Pankaja HP Fuel Center | D13: =+'YG Gudda-2'!E36 -> 8100 | E13: =+'YG Gudda-2'!G36 -> 739773 | F13: =+'YG Gudda-2'!H36 -> 280 | G13: =+'YG Gudda-2'!J36 -> 28915.6 | H13: =E13+G13 -> 768688.6 | I13: =+'YG Gudda-2'!M3 -> 306111 | J13: =+'YG Gudda-2'!L36 -> 750000 | K13: =H13+I13-J13 -> 324799.6
A14: 13 | B14: Hosadurga-1 | C14: Merchant Petroliums | D14: =+Hosadurga!E35 -> 0 | E14: =+Hosadurga!G35 -> 0 | F14: =+Hosadurga!H35 -> 0 | G14: =+Hosadurga!J35 -> 0 | H14: =E14+G14 -> 0 | I14: =+Hosadurga!K3 -> 2258.6 | J14: =+Hosadurga!L35 -> 0 | K14: =H14+I14-J14 -> 2258.6
A15: 14 | B15: Hosadurga-2 | C15: Shree Veeraprathap Fuel | D15: =+'Hosadurga -2'!E35 -> 7100 | E15: =+'Hosadurga -2'!G35 -> 649792 | F15: =+'Hosadurga -2'!H35 -> 310 | G15: =+'Hosadurga -2'!J35 -> 32137.7 | H15: =+'Hosadurga -2'!K35 -> 681929.7 | I15: =+'Hosadurga -2'!K3 -> 277709.09 | J15: =+'Hosadurga -2'!L35 -> 500000 | K15: =H15+I15-J15 -> 459638.79
A16: 15 | B16: Malebennuru(KUWSDB) | C16: Sri Ramanjuneya Service Station | D16: =+'Malebenur(KUWSDB)'!E36 -> 3928.62 | E16: =+'Malebenur(KUWSDB)'!G36 -> 362013.42 | F16: =+'Malebenur(KUWSDB)'!H36 -> 164.86 | G16: =+'Malebenur(KUWSDB)'!J36 -> 17140.494 | H16: =E16+G16 -> 379153.91 | I16: =+'Malebenur(KUWSDB)'!K3 -> 2634.8284 | J16: =+'Malebenur(KUWSDB)'!L36 -> 342853.33 | K16: =H16+I16-J16 -> 38935.405
A17: 16 | B17: kadur | C17: Vishal Service Station | D17: =+Kadur!E35 -> 1500 | E17: =+Kadur!G35 -> 138225 | F17: =+Kadur!H35 -> 140 | G17: =+Kadur!J35 -> 14597.8 | H17: =E17+G17 -> 152822.8 | I17: =+Kadur!K3 -> 11508.831 | J17: =+Kadur!L35 -> 0 | K17: =H17+I17-J17 -> 164331.63
A18: 17 | B18: Hiriyur(VJNL) | C18: Sri Balaji Agencies | D18: =+'Hiriyur(VJNL)'!E35 -> 6800 | E18: =+'Hiriyur(VJNL)'!G35 -> 627164 | F18: =+'Hiriyur(VJNL)'!H35 -> 280 | G18: =+'Hiriyur(VJNL)'!J35 -> 29142.4 | H18: =E18+G18 -> 656306.4 | I18: =+'Hiriyur(VJNL)'!K3 -> 74841.4 | J18: =+'Hiriyur(VJNL)'!L35 -> 409797 | K18: =H18+I18-J18 -> 321350.8
A19: 18 | B19: Chellakere(KUWSDB) | C19: Sri Vishnu Baba Petroleum | D19: =+'Chellakere (KUWSDB)'!E35 -> 3055 | E19: =+'Chellakere (KUWSDB)'!G35 -> 281665.35 | F19: =+'Chellakere (KUWSDB)'!H35 -> 145 | G19: =+'Chellakere (KUWSDB)'!J35 -> 15084.35 | H19: =E19+G19 -> 296749.7 | I19: 0 | J19: =+'Chellakere (KUWSDB)'!L35 -> 296749.75 | K19: =H19+I19-J19 -> -0.05
A20: 19 | B20: Molakalmuru | C20: Sri Lakshmi Venkateshwara Filling Station | D20: =+Molakamuru!E36 -> 1199.996 | E20: =+Molakamuru!G36 -> 110652.63 | F20: =+Molakamuru!H36 -> 45 | G20: =+Molakamuru!J36 -> 4682.4 | H20: =E20+G20 -> 115335.03 | I20: =+Molakamuru!K3 -> 0 | J20: =+Molakamuru!L36 -> 115335.03 | K20: =H20+I20-J20 -> 0
A21: 20 | B21: Khanapur(PKG-3) | C21: V.V.Varde | D21: =+Khanapur!E35 -> 1063.75 | E21: =+Khanapur!G35 -> 96666 | F21: =+Khanapur!H35 -> 81 | G21: =+Khanapur!J35 -> 8324.37 | H21: =E21+G21 -> 104990.37 | I21: =+Khanapur!M3 -> 10170.75 | J21: =+Khanapur!L35 -> 65000 | K21: =H21+I21-J21 -> 50161.12
A22: 21 | B22: Munavalli(PKG-3)-2 | C22: Shri Daneshwari | D22: =+'Munavali-2'!E37 -> 9723.27 | E22: =+'Munavali-2'!G37 -> 887929.02 | F22: =+'Munavali-2'!H37 -> 159 | G22: =+'Munavali-2'!J37 -> 16415.16 | H22: =E22+G22 -> 904344.18 | I22: =+'Munavali-2'!M3 -> 204851.03 | J22: =+'Munavali-2'!L37 -> 450000 | K22: =H22+I22-J22 -> 659195.2
A23: 22 | B23: Borgaon(PKG-3) | C23: Aadisagar Petrolium | D23: =+Borgaon!E37 -> 1049.33 | E23: =+Borgaon!G37 -> 96297.014 | F23: =+Borgaon!H37 -> 61 | G23: =+Borgaon!J37 -> 6364.08 | H23: =E23+G23 -> 102661.09 | I23: =+Borgaon!K3 -> 41597.607 | J23: =+Borgaon!L37 -> 82597 | K23: =H23+I23-J23 -> 61661.701
A24: 23 | B24: Ugar,Kudichi(PKG-3) | C24: Shiri Bhrhmanath Petrolium | D24: =+'Ugar,Khagwad,Kudichi'!E35 -> 2204.24 | E24: =+'Ugar,Khagwad,Kudichi'!G35 -> 202635.78 | F24: =+'Ugar,Khagwad,Kudichi'!H35 -> 301 | G24: =+'Ugar,Khagwad,Kudichi'!J35 -> 32501.74 | H24: =E24+G24 -> 235137.52 | I24: =+'Ugar,Khagwad,Kudichi'!M3 -> 230919.24 | J24: =+'Ugar,Khagwad,Kudichi'!L35 -> 231041 | K24: =H24+I24-J24 -> 235015.76
A25: 24 | B25: Kabbur(PKG-3) | C25: Shri Jai Hanuman Petrolium | D25: =+Kabbur!E35 -> 550.65 | E25: =+Kabbur!G35 -> 50434.034 | F25: =+Kabbur!H35 -> 41.33 | G25: =+Kabbur!J35 -> 4278.8949 | H25: =E25+G25 -> 54712.928 | I25: 0 | J25: =+Kabbur!L35 -> 54712.928 | K25: =H25+I25-J25 -> 0
A26: 25 | B26: Kumta (PKG-1) | C26: Krishma fuel station | D26: =+kumta!E35 -> 1364.5 | E26: =+kumta!G35 -> 125424.84 | F26: =+kumta!H35 -> 49.68 | G26: =+kumta!J35 -> 5162.9346 | H26: =E26+G26 -> 130587.77 | I26: 0 | J26: =+kumta!L35 -> 130587.77 | K26: =H26+I26-J26 -> 0
A27: 26 | B27: Jalgaon | C27: Sri Sai Petrol Pump | D27: =+Jalgaon!E48 -> 9772.69 | E27: =+Jalgaon!G48 -> 896212.92 | F27: =+Jalgaon!H48 -> 97 | G27: =+Jalgaon!J48 -> 10203.43 | H27: =E27+G27 -> 906416.35 | I27: =+Jalgaon!K3 -> 509588.32 | J27: =+Jalgaon!L48 -> 710403.36 | K27: =H27+I27-J27 -> 705601.31
A28: 27 | B28: MKBD | C28: Shree Sai Samarth Petroleum | D28: =+MKBD!E36 -> 1800 | E28: =+MKBD!G36 -> 164052 | F28: =+MKBD!H36 -> 40 | G28: =+MKBD!J36 -> 4184 | H28: =E28+G28 -> 168236 | I28: =+MKBD!K3 -> 108480.65 | J28: =+MKBD!L36 -> 0 | K28: =H28+I28-J28 -> 276716.65
A29: 28 | B29: Haveri | C29: Shivalingeshwar Petroleum | D29: =+Haveri!E36 -> 4650 | E29: =+Haveri!G36 -> 425345.26 | F29: =+Haveri!H36 -> 115.98 | G29: =+Haveri!J36 -> 11992.332 | H29: =E29+G29 -> 437337.59 | I29: =+Haveri!M3 -> 100388.61 | J29: =+Haveri!L36 -> 410000 | K29: =H29+I29-J29 -> 127726.19
A30: 29 | B30: Guttal | C30: Taware filling station | D30: =+Guttal!E35 -> 1039.61 | E30: =+Guttal!G35 -> 95436.198 | F30: =+Guttal!H35 -> 83 | G30: =+Guttal!J35 -> 8613.74 | H30: =E30+G30 -> 104049.94 | I30: 0 | J30: =+Guttal!L35 -> 67093.874 | K30: =H30+I30-J30 -> 36956.064
A31: 30 | B31: Rattihali | C31: Shree Siri Gowari petroliam | D31: =+Rattihali!E35 -> 1736.13 | E31: =+Rattihali!G35 -> 159793.41 | F31: =+Rattihali!H35 -> 63.75 | G31: =+Rattihali!J35 -> 6631.275 | H31: =E31+G31 -> 166424.68 | I31: =+Rattihali!M3 -> 173876.23 | J31: =+Rattihali!L35 -> 150000 | K31: =H31+I31-J31 -> 190300.91
A32: 31 | B32: Gajendragada | C32: Vanasri Petrol Pump | D32: =+Gajendragada!E35 -> 675 | E32: =+Gajendragada!G35 -> 61985.25 | F32: =+Gajendragada!H35 -> 25 | G32: =+Gajendragada!J35 -> 2595 | H32: =E32+G32 -> 64580.25 | I32: =+Gajendragada!K3 -> 133672.01 | J32: =+Gajendragada!L35 -> 100000 | K32: =H32+I32-J32 -> 98252.262
A33: 32 | B33: Gokak(PKG-3) | C33: AJ Petrolinks | D33: =+'Gokak Dharwad PKG 3'!E40 -> 13672.48 | E33: =+'Gokak Dharwad PKG 3'!G40 -> 1250758.5 | F33: =+'Gokak Dharwad PKG 3'!H40 -> 280.67 | G33: =+'Gokak Dharwad PKG 3'!J40 -> 29062.885 | H33: =E33+G33 -> 1279821.4 | I33: =+'Gokak Dharwad PKG 3'!K3 -> 1036892.1 | J33: =+'Gokak Dharwad PKG 3'!L40 -> 1000000 | K33: =H33+I33-J33 -> 1316713.4
A34: 33 | B34: Ankaligi | C34: Shiv ganga | D34: =+Ankalgi!E35 -> 2105.29 | E34: =+Ankalgi!G35 -> 192234.03 | F34: =+Ankalgi!H35 -> 128 | G34: =+Ankalgi!J35 -> 13213.44 | H34: =E34+G34 -> 205447.47 | I34: =+Ankalgi!M3 -> 105996.1 | J34: =+Ankalgi!L35 -> 270000 | K34: =H34+I34-J34 -> 41443.572
A35: 34 | B35: ShankeshWAR | C35: SR Patil | D35: =+' Shankeshwar'!E35 -> 485.68 | E35: =+' Shankeshwar'!G35 -> 44342.584 | F35: =+' Shankeshwar'!H35 -> 51.01 | G35: =+' Shankeshwar'!J35 -> 4644.9 | H35: =E35+G35 -> 48987.484 | J35: =+' Shankeshwar'!L35 -> 48987.484 | K35: =H35+I35-J35 -> 0
A36: 35 | B36: Talikote(PKG-1) | C36: Raykar Oil Agencies | D36: =+' Talikote'!E46 -> 1173.55 | E36: =+' Talikote'!G46 -> 107372.12 | F36: =+' Talikote'!H46 -> 127.01 | G36: =+' Talikote'!J46 -> 13137.914 | H36: =E36+G36 -> 120510.03 | I36: =+' Talikote'!N3 -> 20613.942 | J36: =+' Talikote'!L46 -> 97999.71 | K36: =H36+I36-J36 -> 43124.265
A37: 36 | B37: Chadchan(PKG-1) | C37: Khavekar Petrolium | D37: =+Chadchan!E35 -> 1424.68 | E37: =+Chadchan!G35 -> 129973.56 | F37: =+Chadchan!H35 -> 102.18 | G37: =+Chadchan!J35 -> 10540.889 | H37: =E37+G37 -> 140514.45 | I37: =+Chadchan!K3 -> 92882.428 | J37: =+Chadchan!L35 -> 90000 | K37: =H37+I37-J37 -> 143396.87
A38: 37 | B38: Sindagi | C38: G.P.PORWAL | D38: =+Sindagi!E44 -> 0 | E38: =+Sindagi!G44 -> 0 | F38: =+Sindagi!H44 -> 0 | G38: =+Sindagi!J44 -> 0 | H38: =E38+G38 -> 0 | I38: =+Sindagi!M3 -> 0 | J38: =+Sindagi!L44 -> 0 | K38: =H38+I38-J38 -> 0
A39: 38 | B39: Muddebihal(PKG-1) | C39: Bhosle Service Station | D39: =+Muddebihal!E47 -> 652.34 | E39: =+Muddebihal!G47 -> 59656.493 | F39: =+Muddebihal!H47 -> 14.84 | G39: =+Muddebihal!J47 -> 1534.3076 | H39: =E39+G39 -> 61190.801 | I39: =+Muddebihal!M3 -> 30403.024 | J39: =+Muddebihal!L47 -> 88000 | K39: =H39+I39-J39 -> 3593.8248
A40: 39 | B40: Muddebihal(PKG-1)2 | C40: PS NAGATHAN PETROLIUM | D40: =+'Muddebhihal-2'!E47 -> 481 | E40: =+'Muddebhihal-2'!G47 -> 43973.02 | F40: =+'Muddebhihal-2'!H47 -> 25 | G40: =+'Muddebhihal-2'!J47 -> 2583.75 | H40: =+'Muddebhihal-2'!K47 -> 46556.77 | I40: =+'Muddebhihal-2'!M3 -> 0 | J40: =+'Muddebhihal-2'!L47 -> 0 | K40: =+'Muddebhihal-2'!M46 -> 46556.77
A41: 40 | B41: Almela(PKG-1) | C41: Shiddeshwar Petroleums | D41: =+Alemela!E43 -> 1044.66 | E41: =+Alemela!G43 -> 95408.798 | F41: =+Alemela!H43 -> 82.87 | G41: =+Alemela!J43 -> 8557.1562 | H41: =E41+G41 -> 103965.95 | I41: =+Alemela!M3 -> 4396.8207 | J41: =+Alemela!L43 -> 52000 | K41: =H41+I41-J41 -> 56362.775
A42: 41 | B42: Nalatwad(PKG-1) | C42: Shri Pawad Basaweshwar Petroleums | D42: =+Nalatwad!E43 -> 541.55 | E42: =+Nalatwad!G43 -> 49616.811 | F42: =+Nalatwad!H43 -> 42.17 | G42: =+Nalatwad!J43 -> 4364.9529 | H42: =E42+G42 -> 53981.764 | I42: =+Nalatwad!M3 -> 19544.637 | J42: =+Nalatwad!L43 -> 50000 | K42: =H42+I42-J42 -> 23526.401
A43: 42 | B43: Srirangapatna | C43: Sri Chakra Fuel Station | D43: =+Srirangapatna!E35 -> 110.41 | E43: =+Srirangapatna!G35 -> 9999.8337 | F43: =+Srirangapatna!H35 -> 67.94 | G43: =+Srirangapatna!J35 -> 6961.1324 | H43: =E43+G43 -> 16960.966 | I43: 0 | J43: =+Srirangapatna!L35 -> 16960.966 | K43: =H43+I43-J43 -> 0
A44: Total | D44: =SUM(D2:D43) -> 332866.9 | E44: =SUM(E2:E43) -> 31546551 | F44: =SUM(F2:F43) -> 5762.35 | G44: =SUM(G2:G43) -> 607209.68 | H44: =SUM(H2:H43) -> 32153760 | I44: =SUM(I2:I43) -> 31362514 | J44: =SUM(J2:J43) -> 20278850 | K44: =H44+I44-J44 -> 43237425 | L44: 43108772 | M44: =L44-K44 -> -128652.72
A49: S.no | B49: Site Name | C49: Bunk Name | D49: Diesel(Liters) | E49: Diesel Amount | F49: Petrol(Liters) | G49: Petrol Amount | H49: Total Amount | I49: Opening Blance | J49: Amount Paid | K49: Closing Balances
A50: 30 | B50: {=VLOOKUP(A50,A1:K43,{2,3,4,5,6,7,8,9,10,11},FALSE)} -> Rattihali | C50: Shree Siri Gowari petroliam | D50: 1736.13 | E50: 159793.41 | F50: 63.75 | G50: 6631.275 | H50: 166424.68 | I50: 173876.23 | J50: 150000 | K50: 190300.91
B52: Site Name | C52: Bunk Name | D52: Diesel(Liters) | E52: Diesel Amount | F52: Petrol(Liters) | G52: Petrol Amount | H52: Total Amount | I52: Opening Blance | J52: Amount Paid | K52: Closing Balances
B53: Haveri | C53: {=VLOOKUP(B53,B1:K43,{2,3,4,5,6,7,8,9,10},FALSE)} -> Shivalingeshwar Petroleum | D53: 4650 | E53: 425345.26 | F53: 115.98 | G53: 11992.332 | H53: 437337.59 | I53: 100388.61 | J53: 410000 | K53: 127726.19

Sheet Sheet2

Sheet Khammam-1
A1: Divya laxmi ganapathi
A2: S.No | B2: Date | C2: GRN No | D2: Ind No/Bill No | E2: Diesel (Lts) | F2: Price | G2: Amount | H2: Petrol (Lts) | I2: Price | J2: Amount | K2: Total amount | L2: Amount paid | M2: As 0n Date | N2: Remarks
A3: Opening Balance | K3: 11177697 | M3: =+K3 -> 11177697 | O3: 11178224
A4: 1 | B4: 45931 | G4: =E4*F4 -> 0 | J4: =H4*I4 -> 0 | K4: =G4+J4 -> 0 | L4: 0 | M4: =M3+K4-L4 -> 11177697
A5: 2 | B5: 45932 | G5: =E5*F5 -> 0 | J5: =H5*I5 -> 0 | K5: =G5+J5 -> 0 | M5: =M4+K5-L5 -> 11177697
A6: 3 | B6: 45933 | G6: =E6*F6 -> 0 | J6: =H6*I6 -> 0 | K6: =G6+J6 -> 0 | M6: =M5+K6-L6 -> 11177697
A7: 4 | B7: 45934 | G7: =E7*F7 -> 0 | J7: =H7*I7 -> 0 | K7: =G7+J7 -> 0 | M7: =M6+K7-L7 -> 11177697
A8: 5 | B8: 45935 | G8: =E8*F8 -> 0 | J8: =H8*I8 -> 0 | K8: =G8+J8 -> 0 | M8: =M7+K8-L8 -> 11177697
A9: 6 | B9: 45936 | G9: =E9*F9 -> 0 | J9: =H9*I9 -> 0 | K9: =G9+J9 -> 0 | M9: =M8+K9-L9 -> 11177697
A10: 7 | B10: 45937 | D10: 1 | E10: 2800 | F10: 95.68 | G10: =E10*F10 -> 267904 | H10: 20 | I10: 107.46 | J10: =H10*I10 -> 2149.2 | K10: =G10+J10 -> 270053.2 | M10: =M9+K10-L10 -> 11447750
A11: 8 | B11: 45938 | G11: =E11*F11 -> 0 | J11: =H11*I11 -> 0 | K11: =G11+J11 -> 0 | M11: =M10+K11-L11 -> 11447750
A12: 9 | B12: 45939 | D12: 2 | E12: 4000 | F12: 95.68 | G12: =E12*F12 -> 382720 | J12: =H12*I12 -> 0 | K12: =G12+J12 -> 382720 | M12: =M11+K12-L12 -> 11830470
A13: 10 | B13: 45940 | G13: =E13*F13 -> 0 | J13: =H13*I13 -> 0 | K13: =G13+J13 -> 0 | M13: =M12+K13-L13 -> 11830470
A14: 11 | B14: 45941 | D14: 3 | E14: 6500 | F14: 95.68 | G14: =E14*F14 -> 621920 | H14: 20 | I14: 107.46 | J14: =H14*I14 -> 2149.2 | K14: =G14+J14 -> 624069.2 | M14: =M13+K14-L14 -> 12454539
A15: 12 | B15: 45942 | G15: =E15*F15 -> 0 | J15: =H15*I15 -> 0 | K15: =G15+J15 -> 0 | M15: =M14+K15-L15 -> 12454539
A16: 13 | B16: 45943 | G16: =E16*F16 -> 0 | J16: =H16*I16 -> 0 | K16: =G16+J16 -> 0 | M16: =M15+K16-L16 -> 12454539
A17: 14 | B17: 45944 | G17: =E17*F17 -> 0 | J17: =H17*I17 -> 0 | K17: =G17+J17 -> 0 | L17: 5000000 | M17: =M16+K17-L17 -> 7454539
A18: 15 | B18: 45945 | G18: =E18*F18 -> 0 | J18: =H18*I18 -> 0 | K18: =G18+J18 -> 0 | M18: =M17+K18-L18 -> 7454539
A19: 16 | B19: 45946 | D19: 4 | E19: 4200 | F19: 95.68 | G19: =E19*F19 -> 401856 | H19: 20 | I19: 107.46 | J19: =H19*I19 -> 2149.2 | K19: =G19+J19 -> 404005.2 | M19: =M18+K19-L19 -> 7858544.2
A20: 17 | B20: 45947 | D20: 5 | E20: 4300 | F20: 95.68 | G20: =E20*F20 -> 411424 | H20: 20 | I20: 107.46 | J20: =H20*I20 -> 2149.2 | K20: =G20+J20 -> 413573.2 | M20: =M19+K20-L20 -> 8272117.4
A21: 18 | B21: 45948 | D21: 6 | E21: 5300 | F21: 95.68 | G21: =E21*F21 -> 507104 | H21: 20 | I21: 107.46 | J21: =H21*I21 -> 2149.2 | K21: =G21+J21 -> 509253.2 | M21: =M20+K21-L21 -> 8781370.6
A22: 19 | B22: 45949 | D22: 7 | E22: 1500 | F22: 95.68 | G22: =E22*F22 -> 143520 | J22: =H22*I22 -> 0 | K22: =G22+J22 -> 143520 | M22: =M21+K22-L22 -> 8924890.6
A23: 20 | B23: 45950 | G23: =E23*F23 -> 0 | J23: =H23*I23 -> 0 | K23: =G23+J23 -> 0 | M23: =M22+K23-L23 -> 8924890.6
A24: 21 | B24: 45951 | D24: 8 | E24: 4700 | F24: 95.68 | G24: =E24*F24 -> 449696 | H24: 60 | I24: 107.46 | J24: =H24*I24 -> 6447.6 | K24: =G24+J24 -> 456143.6 | M24: =M23+K24-L24 -> 9381034.2
A25: 22 | B25: 45952 | D25: 9 | E25: 3000 | F25: 95.68 | G25: =E25*F25 -> 287040 | J25: =H25*I25 -> 0 | K25: =G25+J25 -> 287040 | L25: 2500000 | M25: =M24+K25-L25 -> 7168074.2
A26: 23 | B26: 45953 | D26: 10 | E26: 1000 | F26: 95.68 | G26: =E26*F26 -> 95680 | J26: =H26*I26 -> 0 | K26: =G26+J26 -> 95680 | M26: =M25+K26-L26 -> 7263754.2
A27: 24 | B27: 45954 | D27: 11 | E27: 2700 | F27: 95.68 | G27: =E27*F27 -> 258336 | J27: =H27*I27 -> 0 | K27: =G27+J27 -> 258336 | M27: =M26+K27-L27 -> 7522090.2
A28: 25 | B28: 45955 | D28: 12 | E28: 2700 | F28: 95.68 | G28: =E28*F28 -> 258336 | H28: 20 | I28: 107.46 | J28: =H28*I28 -> 2149.2 | K28: =G28+J28 -> 260485.2 | M28: =M27+K28-L28 -> 7782575.4
A29: 26 | B29: 45956 | G29: =E29*F29 -> 0 | J29: =H29*I29 -> 0 | K29: =G29+J29 -> 0 | M29: =M28+K29-L29 -> 7782575.4
A30: 27 | B30: 45957 | D30: 13 | E30: 3700 | F30: 95.68 | G30: =E30*F30 -> 354016 | J30: =H30*I30 -> 0 | K30: =G30+J30 -> 354016 | M30: =M29+K30-L30 -> 8136591.4
A31: 28 | B31: 45958 | D31: 14 | E31: 2700 | F31: 95.68 | G31: =E31*F31 -> 258336 | H31: 20 | I31: 107.46 | J31: =H31*I31 -> 2149.2 | K31: =G31+J31 -> 260485.2 | M31: =M30+K31-L31 -> 8397076.6
A32: 29 | B32: 45959 | D32: 15 | E32: 2800 | F32: 95.68 | G32: =E32*F32 -> 267904 | J32: =H32*I32 -> 0 | K32: =G32+J32 -> 267904 | M32: =M31+K32-L32 -> 8664980.6 | O32: 11177692 | P32: =M32-O32 -> -2512710.9
A33: 30 | B33: 45960 | D33: 16 | E33: 2300 | F33: 95.68 | G33: =E33*F33 -> 220064 | H33: 35 | I33: 107.46 | J33: =H33*I33 -> 3761.1 | K33: =G33+J33 -> 223825.1 | M33: =M32+K33-L33 -> 8888805.7
A34: 31 | B34: 45961 | D34: 17 | E34: 2700 | F34: 95.68 | G34: =E34*F34 -> 258336 | J34: =H34*I34 -> 0 | K34: =G34+J34 -> 258336 | M34: =M33+K34-L34 -> 9147141.7
A35: 32 | G35: =E35*F35 -> 0 | J35: =H35*I35 -> 0 | K35: =G35+J35 -> 0 | M35: =M34+K35-L35 -> 9147141.7
A36: 33 | E36: 0 | G36: =E36*F36 -> 0 | J36: =H36*I36 -> 0 | K36: =G36+J36 -> 0
A37: 34 | E37: 0 | F37: 0 | G37: =E37*F37 -> 0 | H37: 0 | I37: 0 | J37: =H37*I37 -> 0 | K37: =G37+J37 -> 0
E38: =SUM(E3:E37) -> 56900 | G38: =SUM(G3:G37) -> 5444192 | H38: =SUM(H3:H37) -> 235 | J38: =SUM(J3:J37) -> 25253.1 | K38: =SUM(K4:K37) -> 5469445.1 | L38: =SUM(L3:L37) -> 7500000

Sheet Khammam-2
A1: Jayasai union bunk
A2: S.No | B2: Date | C2: GRN No | D2: Ind No/Bill No | E2: Diesel (Lts) | F2: Price | G2: Amount | H2: Petrol (Lts) | I2: Price | J2: Amount | K2: Total amount | L2: Amount paid | M2: As 0n Date | N2: Remarks
A3: Opening Balance | K3: 13443331 | M3: 13443331
A4: 1 | B4: 45931 | D4: 1 | E4: 5500 | F4: 95.7 | G4: =E4*F4 -> 526350 | H4: 40 | I4: 107.48 | J4: =H4*I4 -> 4299.2 | K4: =G4+J4 -> 530649.2 | M4: =M3+K4-L4 -> 13973980 | O4: =O3+M4-N4 -> 13973980
A5: 2 | B5: 45932 | G5: =E5*F5 -> 0 | J5: =H5*I5 -> 0 | K5: =G5+J5 -> 0 | M5: =M4+K5-L5 -> 13973980
A6: 3 | B6: 45933 | D6: 2 | E6: 5500 | F6: 95.7 | G6: =E6*F6 -> 526350 | H6: 75 | I6: 107.48 | J6: =H6*I6 -> 8061 | K6: =G6+J6 -> 534411 | M6: =M5+K6-L6 -> 14508391
A7: 4 | B7: 45934 | D7: 3 | E7: 6600 | F7: 95.7 | G7: =E7*F7 -> 631620 | H7: 40 | I7: 107.48 | J7: =H7*I7 -> 4299.2 | K7: =G7+J7 -> 635919.2 | M7: =M6+K7-L7 -> 15144310
A8: 5 | B8: 45935 | D8: 4 | E8: 3800 | F8: 95.7 | G8: =E8*F8 -> 363660 | J8: =H8*I8 -> 0 | K8: =G8+J8 -> 363660 | M8: =M7+K8-L8 -> 15507970 | O8: 12802499
A9: 6 | B9: 45936 | D9: 5 | E9: 2200 | F9: 95.7 | G9: =E9*F9 -> 210540 | J9: =H9*I9 -> 0 | K9: =G9+J9 -> 210540 | M9: =M8+K9-L9 -> 15718510
A10: 7 | B10: 45937 | D10: 6 | E10: 5200 | F10: 95.7 | G10: =E10*F10 -> 497640 | H10: 60 | I10: 107.48 | J10: =H10*I10 -> 6448.8 | K10: =G10+J10 -> 504088.8 | M10: =M9+K10-L10 -> 16222599
A11: 8 | B11: 45938 | D11: 7 | E11: 8500 | F11: 95.7 | G11: =E11*F11 -> 813450 | H11: 35 | I11: 107.48 | J11: =H11*I11 -> 3761.8 | K11: =G11+J11 -> 817211.8 | M11: =M10+K11-L11 -> 17039811
A12: 9 | B12: 45939 | D12: 8 | E12: 5400 | F12: 95.7 | G12: =E12*F12 -> 516780 | H12: 60 | I12: 107.48 | J12: =H12*I12 -> 6448.8 | K12: =G12+J12 -> 523228.8 | M12: =M11+K12-L12 -> 17563040
A13: 10 | B13: 45940 | D13: 9 | E13: 6500 | F13: 95.7 | G13: =E13*F13 -> 622050 | H13: 60 | I13: 107.48 | J13: =H13*I13 -> 6448.8 | K13: =G13+J13 -> 628498.8 | M13: =M12+K13-L13 -> 18191538
A14: 11 | B14: 45941 | D14: 10 | E14: 2700 | F14: 95.7 | G14: =E14*F14 -> 258390 | H14: 20 | I14: 107.48 | J14: =H14*I14 -> 2149.6 | K14: =G14+J14 -> 260539.6 | M14: =M13+K14-L14 -> 18452078 | P14: 24162284
A15: 12 | B15: 45942 | D15: 11 | E15: 2700 | F15: 95.7 | G15: =E15*F15 -> 258390 | H15: 20 | I15: 107.48 | J15: =H15*I15 -> 2149.6 | K15: =G15+J15 -> 260539.6 | M15: =M14+K15-L15 -> 18712618
A16: 13 | B16: 45943 | D16: 12 | E16: 4800 | F16: 95.7 | G16: =E16*F16 -> 459360 | H16: 40 | I16: 107.48 | J16: =H16*I16 -> 4299.2 | K16: =G16+J16 -> 463659.2 | M16: =M15+K16-L16 -> 19176277
A17: 14 | B17: 45944 | D17: 13 | E17: 5500 | F17: 95.7 | G17: =E17*F17 -> 526350 | H17: 55 | I17: 107.48 | J17: =H17*I17 -> 5911.4 | K17: =G17+J17 -> 532261.4 | M17: =M16+K17-L17 -> 19708538
A18: 15 | B18: 45945 | D18: 14 | E18: 5400 | F18: 95.7 | G18: =E18*F18 -> 516780 | H18: 60 | I18: 107.48 | J18: =H18*I18 -> 6448.8 | K18: =G18+J18 -> 523228.8 | M18: =M17+K18-L18 -> 20231767
A19: 16 | B19: 45946 | D19: 15 | E19: 2700 | F19: 95.7 | G19: =E19*F19 -> 258390 | H19: 20 | I19: 107.48 | J19: =H19*I19 -> 2149.6 | K19: =G19+J19 -> 260539.6 | M19: =M18+K19-L19 -> 20492307
A20: 17 | B20: 45947 | D20: 16 | E20: 2700 | F20: 95.7 | G20: =E20*F20 -> 258390 | H20: 20 | I20: 107.48 | J20: =H20*I20 -> 2149.6 | K20: =G20+J20 -> 260539.6 | M20: =M19+K20-L20 -> 20752846
A21: 18 | B21: 45948 | D21: 17 | E21: 5400 | F21: 95.7 | G21: =E21*F21 -> 516780 | H21: 40 | I21: 107.48 | J21: =H21*I21 -> 4299.2 | K21: =G21+J21 -> 521079.2 | M21: =M20+K21-L21 -> 21273925
A22: 19 | B22: 45949 | G22: =E22*F22 -> 0 | J22: =H22*I22 -> 0 | K22: =G22+J22 -> 0 | M22: =M21+K22-L22 -> 21273925
A23: 20 | B23: 45950 | G23: =E23*F23 -> 0 | J23: =H23*I23 -> 0 | K23: =G23+J23 -> 0 | M23: =M22+K23-L23 -> 21273925
A24: 21 | B24: 45951 | D24: 18 | E24: 2700 | F24: 95.7 | G24: =E24*F24 -> 258390 | H24: 20 | I24: 107.48 | J24: =H24*I24 -> 2149.6 | K24: =G24+J24 -> 260539.6 | M24: =M23+K24-L24 -> 21534465
A25: 22 | B25: 45952 | D25: 19 | E25: 7000 | F25: 95.7 | G25: =E25*F25 -> 669900 | H25: 40 | I25: 107.48 | J25: =H25*I25 -> 4299.2 | K25: =G25+J25 -> 674199.2 | M25: =M24+K25-L25 -> 22208664
A26: 23 | B26: 45953 | D26: 20 | E26: 2700 | F26: 95.7 | G26: =E26*F26 -> 258390 | H26: 20 | I26: 107.48 | J26: =H26*I26 -> 2149.6 | K26: =G26+J26 -> 260539.6 | M26: =M25+K26-L26 -> 22469204
A27: 24 | B27: 45954 | D27: 21 | E27: 2800 | F27: 95.7 | G27: =E27*F27 -> 267960 | H27: 40 | I27: 107.48 | J27: =H27*I27 -> 4299.2 | K27: =G27+J27 -> 272259.2 | M27: =M26+K27-L27 -> 22741463
A28: 25 | B28: 45955 | D28: 22 | E28: 2700 | F28: 95.7 | G28: =E28*F28 -> 258390 | H28: 40 | I28: 107.48 | J28: =H28*I28 -> 4299.2 | K28: =G28+J28 -> 262689.2 | M28: =M27+K28-L28 -> 23004152
A29: 26 | B29: 45956 | D29: 23 | E29: 6500 | F29: 95.7 | G29: =E29*F29 -> 622050 | H29: 20 | I29: 107.48 | J29: =H29*I29 -> 2149.6 | K29: =G29+J29 -> 624199.6 | M29: =M28+K29-L29 -> 23628352
A30: 27 | B30: 45957 | D30: 24 | E30: 2700 | F30: 95.7 | G30: =E30*F30 -> 258390 | H30: 40 | I30: 107.48 | J30: =H30*I30 -> 4299.2 | K30: =G30+J30 -> 262689.2 | M30: =M29+K30-L30 -> 23891041
A31: 28 | B31: 45958 | D31: 25 | E31: 2800 | F31: 95.7 | G31: =E31*F31 -> 267960 | H31: 35 | I31: 107.48 | J31: =H31*I31 -> 3761.8 | K31: =G31+J31 -> 271721.8 | M31: =M30+K31-L31 -> 24162763
A32: 29 | B32: 45959 | G32: =E32*F32 -> 0 | J32: =H32*I32 -> 0 | K32: =G32+J32 -> 0 | M32: =M31+K32-L32 -> 24162763
A33: 30 | B33: 45960 | G33: =E33*F33 -> 0 | J33: =H33*I33 -> 0 | K33: =G33+J33 -> 0 | M33: =M32+K33-L33 -> 24162763
A34: 31 | B34: 45961 | G34: =E34*F34 -> 0 | J34: =H34*I34 -> 0 | K34: =G34+J34 -> 0 | M34: =M33+K34-L34 -> 24162763
E38: =SUM(E4:E34) -> 111000 | G38: =SUM(G4:G34) -> 10622700 | H38: =SUM(H4:H34) -> 900 | J38: =SUM(J4:J34) -> 96732 | K38: =SUM(K4:K34) -> 10719432 | L38: =SUM(L4:L34) -> 0

Sheet Jedcherla -1
A1: Sai Baba Fuel Station
A2: S.No | B2: Date | C2: GRN No | D2: Ind No/Bill No | E2: Diesel (Lts) | F2: Price | G2: Amount | H2: Petrol (Lts) | I2: Price | J2: Amount | K2: Total amount | L2: Amount paid | M2: As on date | N2: Remarks
A3: Opening Balance | M3: 2639914.6 | O3: 2623243.4
A4: 1 | B4: 45931 | F4: 0 | G4: 0 | H4: 15 | I4: 108.23 | J4: =H4*I4 -> 1623.45 | K4: =G4+J4 -> 1623.45 | M4: =M3+K4-L4 -> 2641538
A5: 2 | B5: 45932 | G5: =E5*F5 -> 0 | J5: =H5*I5 -> 0 | K5: =G5+J5 -> 0 | M5: =M4+K5-L5 -> 2641538
A6: 3 | B6: 45933 | E6: 2400 | F6: 96.42 | G6: =E6*F6 -> 231408 | H6: 15 | I6: 108.28 | J6: =H6*I6 -> 1624.2 | K6: =G6+J6 -> 233032.2 | M6: =M5+K6-L6 -> 2874570.2
A7: 4 | B7: 45934 | G7: =E7*F7 -> 0 | H7: 5 | I7: 108.28 | J7: =H7*I7 -> 541.4 | K7: =G7+J7 -> 541.4 | M7: =M6+K7-L7 -> 2875111.6 | P7: 5679
A8: 5 | B8: 45935 | E8: 500 | F8: 96.42 | G8: =E8*F8 -> 48210 | H8: 5 | I8: 108.23 | J8: =H8*I8 -> 541.15 | K8: =G8+J8 -> 48751.15 | M8: =M7+K8-L8 -> 2923862.8
A9: 6 | B9: 45936 | E9: 1500 | F9: 96.42 | G9: =E9*F9 -> 144630 | H9: 35 | I9: 108.23 | J9: =H9*I9 -> 3788.05 | K9: =G9+J9 -> 148418.05 | M9: =M8+K9-L9 -> 3072280.8
A10: 7 | B10: 45937 | D10: 34.94 | E10: 1634.94 | F10: 96.42 | G10: =E10*F10 -> 157640.91 | H10: 10 | I10: 108.23 | J10: =H10*I10 -> 1082.3 | K10: =G10+J10 -> 158723.21 | L10: 975000 | M10: =M9+K10-L10 -> 2256004
A11: 8 | B11: 45938 | E11: 2000 | F11: 96.42 | G11: =E11*F11 -> 192840 | H11: 55 | I11: 108.23 | J11: =H11*I11 -> 5952.65 | K11: =G11+J11 -> 198792.65 | M11: =M10+K11-L11 -> 2454796.7
A12: 9 | B12: 45939 | E12: 2400 | F12: 96.42 | G12: =E12*F12 -> 231408 | H12: 5 | I12: 108.23 | J12: =H12*I12 -> 541.15 | K12: =G12+J12 -> 231949.15 | M12: =M11+K12-L12 -> 2686745.8
A13: 10 | B13: 45940 | G13: =E13*F13 -> 0 | H13: 35 | I13: 108.23 | J13: =H13*I13 -> 3788.05 | K13: =G13+J13 -> 3788.05 | M13: =M12+K13-L13 -> 2690533.9
A14: 11 | B14: 45941 | E14: 1500 | F14: 96.42 | G14: =E14*F14 -> 144630 | H14: 20 | I14: 108.23 | J14: =H14*I14 -> 2164.6 | K14: =G14+J14 -> 146794.6 | M14: =M13+K14-L14 -> 2837328.5
A15: 12 | B15: 45942 | E15: 37.96 | F15: 96.42 | G15: =E15*F15 -> 3660.1032 | H15: 15 | I15: 108.23 | J15: =H15*I15 -> 1623.45 | K15: =G15+J15 -> 5283.5532 | M15: =M14+K15-L15 -> 2842612
A16: 13 | B16: 45943 | G16: =E16*F16 -> 0 | H16: 15 | I16: 108.23 | J16: =H16*I16 -> 1623.45 | K16: =G16+J16 -> 1623.45 | M16: =M15+K16-L16 -> 2844235.5
A17: 14 | B17: 45944 | G17: =E17*F17 -> 0 | H17: 15 | I17: 108.23 | J17: =H17*I17 -> 1623.45 | K17: =G17+J17 -> 1623.45 | M17: =M16+K17-L17 -> 2845858.9
A18: 15 | B18: 45945 | G18: =E18*F18 -> 0 | H18: 20 | I18: 108.23 | J18: =H18*I18 -> 2164.6 | K18: =G18+J18 -> 2164.6 | L18: 500000 | M18: =M17+K18-L18 -> 2348023.5
A19: 16 | B19: 45946 | E19: 33.7 | F19: 96.42 | G19: =E19*F19 -> 3249.354 | H19: 25 | I19: 108.23 | J19: =H19*I19 -> 2705.75 | K19: =G19+J19 -> 5955.104 | M19: =M18+K19-L19 -> 2353978.6
A20: 17 | B20: 45947 | E20: 0 | G20: =E20*F20 -> 0 | H20: 20 | I20: 108.23 | J20: =H20*I20 -> 2164.6 | K20: =G20+J20 -> 2164.6 | M20: =M19+K20-L20 -> 2356143.2
A21: 18 | B21: 45948 | E21: 60 | F21: 96.42 | G21: =E21*F21 -> 5785.2 | H21: 25 | I21: 108.23 | J21: =H21*I21 -> 2705.75 | K21: =G21+J21 -> 8490.95 | M21: =M20+K21-L21 -> 2364634.2
A22: 19 | B22: 45949 | G22: =E22*F22 -> 0 | H22: 10 | I22: 108.23 | J22: =H22*I22 -> 1082.3 | K22: =G22+J22 -> 1082.3 | M22: =M21+K22-L22 -> 2365716.5
A23: 20 | B23: 45950 | G23: =E23*F23 -> 0 | H23: 5 | I23: 108.23 | J23: =H23*I23 -> 541.15 | K23: =G23+J23 -> 541.15 | M23: =M22+K23-L23 -> 2366257.6
A24: 21 | B24: 45951 | G24: =E24*F24 -> 0 | H24: 73.42 | I24: 108.23 | J24: =H24*I24 -> 7946.2466 | K24: =G24+J24 -> 7946.2466 | M24: =M23+K24-L24 -> 2374203.9
A25: 22 | B25: 45952 | G25: =E25*F25 -> 0 | H25: 22 | I25: 108.23 | J25: =H25*I25 -> 2381.06 | K25: =G25+J25 -> 2381.06 | M25: =M24+K25-L25 -> 2376584.9
A26: 23 | B26: 45953 | G26: =E26*F26 -> 0 | H26: 97.71 | I26: 108.23 | J26: =H26*I26 -> 10575.153 | K26: =G26+J26 -> 10575.153 | M26: =M25+K26-L26 -> 2387160.1
A27: 24 | B27: 45954 | G27: =E27*F27 -> 0 | J27: =H27*I27 -> 0 | K27: =G27+J27 -> 0 | M27: =M26+K27-L27 -> 2387160.1
A28: 25 | B28: 45955 | G28: =E28*F28 -> 0 | J28: =H28*I28 -> 0 | K28: =G28+J28 -> 0 | M28: =M27+K28-L28 -> 2387160.1
A29: 26 | B29: 45956 | G29: =E29*F29 -> 0 | H29: 100 | I29: 108.23 | J29: =H29*I29 -> 10823 | K29: =G29+J29 -> 10823 | M29: =M28+K29-L29 -> 2397983.1
A30: 27 | B30: 45957 | G30: =E30*F30 -> 0 | J30: =H30*I30 -> 0 | K30: =G30+J30 -> 0 | M30: =M29+K30-L30 -> 2397983.1
A31: 28 | B31: 45958 | G31: =E31*F31 -> 0 | J31: =H31*I31 -> 0 | K31: =G31+J31 -> 0 | M31: =M30+K31-L31 -> 2397983.1
A32: 29 | B32: 45959 | E32: 35 | F32: 96.42 | G32: =E32*F32 -> 3374.7 | H32: 50 | I32: 108.23 | J32: =H32*I32 -> 5411.5 | K32: =G32+J32 -> 8786.2 | M32: =M31+K32-L32 -> 2406769.3
A33: 30 | B33: 45960 | G33: =E33*F33 -> 0 | J33: =H33*I33 -> 0 | K33: =G33+J33 -> 0 | L33: 700000 | M33: =M32+K33-L33 -> 1706769.3
A34: 31 | B34: 45961 | E34: 52 | F34: 96.42 | G34: =E34*F34 -> 5013.84 | J34: =H34*I34 -> 0 | K34: =G34+J34 -> 5013.84 | L34: 0 | M34: =M33+K34-L34 -> 1711783.1 | O34: 2669494 | P34: =O34-M34 -> 957710.87
E35: 0 | F35: 0 | G35: =E35*F35 -> 0 | J35: =H35*I35 -> 0 | K35: =G35+J35 -> 0 | M35: =M34+K35-L35 -> 1711783.1
E36: =SUM(E4:E34) -> 12153.6 | G36: =SUM(G4:G34) -> 1171850.1 | H36: =SUM(H4:H34) -> 693.13 | J36: =SUM(J4:J34) -> 75018.46 | K36: =SUM(K4:K34) -> 1246868.6 | L36: =SUM(L4:L34) -> 2175000
M45: 2408309
M46: 5327.86
M47: =M45-M46 -> 2402981.1

Sheet Jedcharla-2
A1: ADHOC FILLING STATION STATION
A2: S.No | B2: Date | C2: GRN No | D2: Ind No/Bill No | E2: Diesel (Lts) | F2: Price | G2: Amount | H2: Petrol (Lts) | I2: Price | J2: Amount | K2: Total amount | L2: Amount paid | M2: As on Date | N2: Remarks
A3: Opening Balance | K3: 238933 | M3: =+K3 -> 238933 | O3: 238933
A4: 1 | B4: 45931 | G4: =E4*F4 -> 0 | J4: =H4*I4 -> 0 | K4: =G4+J4 -> 0 | M4: =M3+K4-L4 -> 238933
A5: 2 | B5: 45932 | G5: =E5*F5 -> 0 | J5: =H5*I5 -> 0 | K5: =G5+J5 -> 0 | M5: =M4+K5-L5 -> 238933
A6: 3 | B6: 45933 | G6: =E6*F6 -> 0 | J6: =H6*I6 -> 0 | K6: =G6+J6 -> 0 | M6: =M5+K6-L6 -> 238933 | R6: 541.08
A7: 4 | B7: 45934 | G7: =E7*F7 -> 0 | J7: =H7*I7 -> 0 | K7: =G7+J7 -> 0 | M7: =M6+K7-L7 -> 238933
A8: 5 | B8: 45935 | G8: =E8*F8 -> 0 | J8: =H8*I8 -> 0 | K8: =G8+J8 -> 0 | M8: =M7+K8-L8 -> 238933
A9: 6 | B9: 45936 | G9: =E9*F9 -> 0 | J9: =H9*I9 -> 0 | K9: =G9+J9 -> 0 | M9: =M8+K9-L9 -> 238933
A10: 7 | B10: 45937 | D10: 1 | E10: 2500 | F10: 96.43 | G10: =E10*F10 -> 241075 | J10: =H10*I10 -> 0 | K10: =G10+J10 -> 241075 | M10: =M9+K10-L10 -> 480008
A11: 8 | B11: 45938 | G11: =E11*F11 -> 0 | J11: =H11*I11 -> 0 | K11: =G11+J11 -> 0 | M11: =M10+K11-L11 -> 480008
A12: 9 | B12: 45939 | G12: =E12*F12 -> 0 | J12: =H12*I12 -> 0 | K12: =G12+J12 -> 0 | M12: =M11+K12-L12 -> 480008
A13: 10 | B13: 45940 | G13: =E13*F13 -> 0 | J13: =H13*I13 -> 0 | K13: =G13+J13 -> 0 | L13: 200000 | M13: =M12+K13-L13 -> 280008
A14: 11 | B14: 45941 | D14: 2 | E14: 2400 | F14: 96.43 | G14: =E14*F14 -> 231432 | J14: =H14*I14 -> 0 | K14: =G14+J14 -> 231432 | M14: =M13+K14-L14 -> 511440
A15: 12 | B15: 45942 | D15: 3 | E15: 2000 | F15: 96.43 | G15: =E15*F15 -> 192860 | H15: 0 | I15: 0 | J15: =H15*I15 -> 0 | K15: =G15+J15 -> 192860 | M15: =M14+K15-L15 -> 704300
A16: 13 | B16: 45943 | D16: 4 | E16: 2000 | F16: 96.43 | G16: =E16*F16 -> 192860 | J16: =H16*I16 -> 0 | K16: =G16+J16 -> 192860 | M16: =M15+K16-L16 -> 897160
A17: 14 | B17: 45944 | D17: 5 | E17: 4800 | F17: 96.43 | G17: =E17*F17 -> 462864 | J17: =H17*I17 -> 0 | K17: =G17+J17 -> 462864 | M17: =M16+K17-L17 -> 1360024
A18: 15 | B18: 45945 | D18: 6 | E18: 4400 | F18: 96.43 | G18: =E18*F18 -> 424292 | J18: =H18*I18 -> 0 | K18: =G18+J18 -> 424292 | L18: 800000 | M18: =M17+K18-L18 -> 984316
A19: 16 | B19: 45946 | D19: 7 | E19: 2400 | F19: 96.43 | G19: =E19*F19 -> 231432 | J19: =H19*I19 -> 0 | K19: =G19+J19 -> 231432 | M19: =M18+K19-L19 -> 1215748
A20: 17 | B20: 45947 | D20: 8 | E20: 2400 | F20: 96.43 | G20: =E20*F20 -> 231432 | J20: =H20*I20 -> 0 | K20: =G20+J20 -> 231432 | M20: =M19+K20-L20 -> 1447180
A21: 18 | B21: 45948 | D21: 9 | E21: 4300 | F21: 96.43 | G21: =E21*F21 -> 414649 | J21: =H21*I21 -> 0 | K21: =G21+J21 -> 414649 | M21: =M20+K21-L21 -> 1861829
A22: 19 | B22: 45949 | D22: 10 | E22: 4400 | F22: 96.43 | G22: =E22*F22 -> 424292 | J22: =H22*I22 -> 0 | K22: =G22+J22 -> 424292 | M22: =M21+K22-L22 -> 2286121
A23: 20 | B23: 45950 | G23: =E23*F23 -> 0 | J23: =H23*I23 -> 0 | K23: =G23+J23 -> 0 | M23: =M22+K23-L23 -> 2286121
A24: 21 | B24: 45951 | D24: 11 | E24: 1500 | F24: 96.43 | G24: =E24*F24 -> 144645 | J24: =H24*I24 -> 0 | K24: =G24+J24 -> 144645 | M24: =M23+K24-L24 -> 2430766
A25: 22 | B25: 45952 | D25: 12 | E25: 2400 | F25: 96.43 | G25: =E25*F25 -> 231432 | J25: =H25*I25 -> 0 | K25: =G25+J25 -> 231432 | M25: =M24+K25-L25 -> 2662198
A26: 23 | B26: 45953 | D26: 13 | E26: 1400 | F26: 96.43 | G26: =E26*F26 -> 135002 | J26: =H26*I26 -> 0 | K26: =G26+J26 -> 135002 | M26: =M25+K26-L26 -> 2797200
A27: 24 | B27: 45954 | D27: 14 | E27: 2400 | F27: 96.43 | G27: =E27*F27 -> 231432 | J27: =H27*I27 -> 0 | K27: =G27+J27 -> 231432 | M27: =M26+K27-L27 -> 3028632
A28: 25 | B28: 45955 | D28: 15 | E28: 1600 | F28: 96.43 | G28: =E28*F28 -> 154288 | J28: =H28*I28 -> 0 | K28: =G28+J28 -> 154288 | M28: =M27+K28-L28 -> 3182920
A29: 26 | B29: 45956 | D29: 16 | E29: 2400 | F29: 96.43 | G29: =E29*F29 -> 231432 | J29: =H29*I29 -> 0 | K29: =G29+J29 -> 231432 | M29: =M28+K29-L29 -> 3414352
A30: 27 | B30: 45957 | D30: 17 | E30: 2400 | F30: 96.43 | G30: =E30*F30 -> 231432 | J30: =H30*I30 -> 0 | K30: =G30+J30 -> 231432 | M30: =M29+K30-L30 -> 3645784
A31: 28 | B31: 45958 | D31: 18 | E31: 1800 | F31: 96.43 | G31: =E31*F31 -> 173574 | J31: =H31*I31 -> 0 | K31: =G31+J31 -> 173574 | M31: =M30+K31-L31 -> 3819358
A32: 29 | B32: 45959 | D32: 19 | E32: 1000 | F32: 96.43 | G32: =E32*F32 -> 96430 | J32: =H32*I32 -> 0 | K32: =G32+J32 -> 96430 | M32: =M31+K32-L32 -> 3915788
A33: 30 | B33: 45960 | D33: 20 | E33: 1200 | F33: 96.43 | G33: =E33*F33 -> 115716 | J33: =H33*I33 -> 0 | K33: =G33+J33 -> 115716 | L33: 1900000 | M33: =M32+K33-L33 -> 2131504
A34: 31 | B34: 45961 | D34: 21 | E34: 2000 | F34: 96.43 | G34: =E34*F34 -> 192860 | J34: =H34*I34 -> 0 | K34: =G34+J34 -> 192860 | M34: =M33+K34-L34 -> 2324364 | O34: 1688453.6 | P34: 1900671 | Q34: =P34-O34 -> 212217.42
E35: =SUM(E4:E34) -> 51700 | G35: =SUM(G4:G34) -> 4985431 | H35: =SUM(H4:H34) -> 0 | J35: =SUM(J4:J34) -> 0 | K35: =SUM(K4:K34) -> 4985431 | L35: =SUM(L4:L34) -> 2900000

Sheet Devarakhadra
A1: Kurumurthy Swami F/S
A2: S.No | B2: Date | C2: GRN No | D2: Ind no/Bill No | E2: Diesel (Lts) | F2: Price | G2: Amount | H2: Petrol (Lts) | I2: Price | J2: Amount | K2: Total amount | L2: Amount paid | M2: As on Date | N2: Remarks
A3: Opening Balance | M3: 121213.37 | O3: 121213.37
A4: 1 | B4: 45931 | D4: 1 | E4: 441 | F4: 97.1 | G4: =E4*F4 -> 42821.1 | H4: 5 | I4: 108.83 | J4: =H4*I4 -> 544.15 | K4: =G4+J4 -> 43365.25 | M4: =+M3+K4-L4 -> 164578.62
A5: 2 | B5: 45932 | D5: 2 | E5: 33.8 | F5: 97.1 | G5: =E5*F5 -> 3281.98 | H5: 5 | I5: 108.83 | J5: =H5*I5 -> 544.15 | K5: =G5+J5 -> 3826.13 | M5: =+M4+K5-L5 -> 168404.75
A6: 3 | B6: 45933 | D6: 3 | E6: 270.6 | F6: 97.1 | G6: =E6*F6 -> 26275.26 | H6: 10 | I6: 108.83 | J6: =H6*I6 -> 1088.3 | K6: =G6+J6 -> 27363.56 | M6: =+M5+K6-L6 -> 195768.31
A7: 4 | B7: 45934 | D7: 4 | E7: 683.4 | F7: 97.1 | G7: =E7*F7 -> 66358.14 | H7: 7 | I7: 108.83 | J7: =H7*I7 -> 761.81 | K7: =G7+J7 -> 67119.95 | M7: =+M6+K7-L7 -> 262888.26
A8: 5 | B8: 45935 | D8: 5 | E8: 160 | F8: 97.1 | G8: =E8*F8 -> 15536 | J8: =H8*I8 -> 0 | K8: =G8+J8 -> 15536 | M8: =+M7+K8-L8 -> 278424.26
A9: 6 | B9: 45936 | D9: 6 | E9: 809.25 | F9: 97.1 | G9: =E9*F9 -> 78578.175 | J9: =H9*I9 -> 0 | K9: =G9+J9 -> 78578.175 | M9: =+M8+K9-L9 -> 357002.43
A10: 7 | B10: 45937 | D10: 7 | E10: 647.67 | F10: 97.1 | G10: =E10*F10 -> 62888.757 | H10: 6 | I10: 108.83 | J10: =H10*I10 -> 652.98 | K10: =G10+J10 -> 63541.737 | M10: =+M9+K10-L10 -> 420544.17
A11: 8 | B11: 45938 | D11: 8 | E11: 466.71 | F11: 97.1 | G11: =E11*F11 -> 45317.541 | H11: 5 | I11: 108.83 | J11: =H11*I11 -> 544.15 | K11: =G11+J11 -> 45861.691 | M11: =+M10+K11-L11 -> 466405.86
A12: 9 | B12: 45939 | D12: 9 | E12: 712.49 | F12: 97.1 | G12: =E12*F12 -> 69182.779 | J12: =H12*I12 -> 0 | K12: =G12+J12 -> 69182.779 | M12: =+M11+K12-L12 -> 535588.64
A13: 10 | B13: 45940 | D13: 10 | E13: 284 | F13: 97.1 | G13: =E13*F13 -> 27576.4 | J13: =H13*I13 -> 0 | K13: =G13+J13 -> 27576.4 | L13: 150000 | M13: =+M12+K13-L13 -> 413165.04
A14: 11 | B14: 45941 | D14: 11 | E14: 511.11 | F14: 97.1 | G14: =E14*F14 -> 49628.781 | H14: 0 | I14: 108.83 | J14: =H14*I14 -> 0 | K14: =G14+J14 -> 49628.781 | M14: =+M13+K14-L14 -> 462793.82
A15: 12 | B15: 45942 | D15: 12 | G15: =E15*F15 -> 0 | H15: 28 | I15: 108.83 | J15: =H15*I15 -> 3047.24 | K15: =G15+J15 -> 3047.24 | M15: =+M14+K15-L15 -> 465841.06
A16: 13 | B16: 45943 | D16: 13 | E16: 575.43 | F16: 97.1 | G16: =E16*F16 -> 55874.253 | H16: 5 | I16: 108.83 | J16: =H16*I16 -> 544.15 | K16: =G16+J16 -> 56418.403 | M16: =+M15+K16-L16 -> 522259.46
A17: 14 | B17: 45944 | D17: 14 | E17: 118 | F17: 97.1 | G17: =E17*F17 -> 11457.8 | H17: 3 | I17: 108.83 | J17: =H17*I17 -> 326.49 | K17: =G17+J17 -> 11784.29 | M17: =+M16+K17-L17 -> 534043.75
A18: 15 | B18: 45945 | D18: 15 | E18: 18 | F18: 97.1 | G18: =E18*F18 -> 1747.8 | J18: =H18*I18 -> 0 | K18: =G18+J18 -> 1747.8 | L18: 200000 | M18: =+M17+K18-L18 -> 335791.55
A19: 16 | B19: 45946 | D19: 16 | E19: 12 | F19: 97.1 | G19: =E19*F19 -> 1165.2 | H19: 5 | I19: 108.83 | J19: =H19*I19 -> 544.15 | K19: =G19+J19 -> 1709.35 | M19: =+M18+K19-L19 -> 337500.9 | N19: Fuel bills
A20: 17 | B20: 45947 | D20: 17 | E20: 50 | F20: 97.1 | G20: =E20*F20 -> 4855 | J20: =H20*I20 -> 0 | K20: =G20+J20 -> 4855 | M20: =+M19+K20-L20 -> 342355.9
A21: 18 | B21: 45948 | D21: 18 | E21: 111 | F21: 97.1 | G21: =E21*F21 -> 10778.1 | H21: 5 | I21: 108.83 | J21: =H21*I21 -> 544.15 | K21: =G21+J21 -> 11322.25 | M21: =+M20+K21-L21 -> 353678.15
A22: 19 | B22: 45949 | D22: 19 | E22: =35+20 -> 55 | F22: 97.1 | G22: =E22*F22 -> 5340.5 | J22: =H22*I22 -> 0 | K22: =G22+J22 -> 5340.5 | M22: =+M21+K22-L22 -> 359018.65
A23: 20 | B23: 45950 | D23: 20 | E23: 0 | F23: 97.1 | G23: =E23*F23 -> 0 | H23: 5 | I23: 108.83 | J23: =H23*I23 -> 544.15 | K23: =G23+J23 -> 544.15 | M23: =+M22+K23-L23 -> 359562.8
A24: 21 | B24: 45951 | D24: 21 | G24: =E24*F24 -> 0 | H24: 10 | I24: 108.83 | J24: =H24*I24 -> 1088.3 | K24: =G24+J24 -> 1088.3 | M24: =+M23+K24-L24 -> 360651.1
A25: 22 | B25: 45952 | D25: 22 | E25: 373 | F25: 97.1 | G25: =E25*F25 -> 36218.3 | H25: 5 | I25: 108.83 | J25: =H25*I25 -> 544.15 | K25: =G25+J25 -> 36762.45 | M25: =+M24+K25-L25 -> 397413.55
A26: 23 | B26: 45953 | D26: 23 | E26: 238 | F26: 97.1 | G26: =E26*F26 -> 23109.8 | H26: 5 | I26: 108.83 | J26: =H26*I26 -> 544.15 | K26: =G26+J26 -> 23653.95 | M26: =+M25+K26-L26 -> 421067.5
A27: 24 | B27: 45954 | D27: 24 | E27: 710.25 | F27: 97.1 | G27: =E27*F27 -> 68965.275 | J27: =H27*I27 -> 0 | K27: =G27+J27 -> 68965.275 | M27: =+M26+K27-L27 -> 490032.78
A28: 25 | B28: 45955 | F28: 97.1 | G28: =E28*F28 -> 0 | J28: =H28*I28 -> 0 | K28: =G28+J28 -> 0 | M28: =+M27+K28-L28 -> 490032.78
A29: 26 | B29: 45956 | D29: 25 | E29: 20 | F29: 97.1 | G29: =E29*F29 -> 1942 | H29: 5 | I29: 108.83 | J29: =H29*I29 -> 544.15 | K29: =G29+J29 -> 2486.15 | M29: =+M28+K29-L29 -> 492518.93
A30: 27 | B30: 45957 | D30: 26 | E30: 135 | F30: 97.1 | G30: =E30*F30 -> 13108.5 | J30: =H30*I30 -> 0 | K30: =G30+J30 -> 13108.5 | M30: =+M29+K30-L30 -> 505627.43
A31: 28 | B31: 45958 | D31: 27 | E31: 176 | F31: 97.1 | G31: =E31*F31 -> 17089.6 | H31: 5 | I31: 108.83 | J31: =H31*I31 -> 544.15 | K31: =G31+J31 -> 17633.75 | M31: =+M30+K31-L31 -> 523261.18
A32: 29 | B32: 45959 | D32: 28 | E32: 200 | F32: 97.1 | G32: =E32*F32 -> 19420 | H32: 10 | I32: 108.83 | J32: =H32*I32 -> 1088.3 | K32: =G32+J32 -> 20508.3 | M32: =+M31+K32-L32 -> 543769.48
A33: 30 | B33: 45960 | G33: =E33*F33 -> 0 | J33: =H33*I33 -> 0 | K33: =G33+J33 -> 0 | L33: 350000 | M33: =+M32+K33-L33 -> 193769.48
A34: 31 | B34: 45961 | G34: =E34*F34 -> 0 | J34: =H34*I34 -> 0 | K34: =G34+J34 -> 0 | M34: =+M33+K34-L34 -> 193769.48
E35: =SUM(E4:E34) -> 7811.71 | G35: =SUM(G4:G34) -> 758517.04 | H35: =SUM(H4:H34) -> 129 | J35: =SUM(J4:J34) -> 14039.07 | K35: =SUM(K4:K34) -> 772556.11 | L35: =SUM(L4:L34) -> 700000

Sheet Devarakhadra-2
A1: Sri rama F/S
A2: S.No | B2: Date | C2: GRN No | D2: Ind no/Bill No | E2: Diesel (Lts) | F2: Price | G2: Amount | H2: Petrol (Lts) | I2: Price | J2: Amount | K2: Total amount | L2: Amount paid | M2: As on Date | N2: Remarks
A3: Opening Balance | M3: 132273.54
A4: 1 | B4: 45931 | G4: =E4*F4 -> 0 | H4: 0 | I4: 0 | J4: =H4*I4 -> 0 | K4: =G4+J4 -> 0 | L4: 0 | M4: =+M3+K4-L4 -> 132273.54
A5: 2 | B5: 45932 | G5: =E5*F5 -> 0 | H5: 0 | I5: 0 | J5: =H5*I5 -> 0 | K5: =G5+J5 -> 0 | L5: 0 | M5: =+M4+K5-L5 -> 132273.54
A6: 3 | B6: 45933 | G6: =E6*F6 -> 0 | H6: 0 | I6: 0 | J6: =H6*I6 -> 0 | K6: =G6+J6 -> 0 | L6: 0 | M6: =+M5+K6-L6 -> 132273.54
A7: 4 | B7: 45934 | G7: =E7*F7 -> 0 | H7: 0 | I7: 0 | J7: =H7*I7 -> 0 | K7: =G7+J7 -> 0 | L7: 0 | M7: =+M6+K7-L7 -> 132273.54
A8: 5 | B8: 45935 | G8: =E8*F8 -> 0 | H8: 0 | I8: 0 | J8: =H8*I8 -> 0 | K8: =G8+J8 -> 0 | L8: 0 | M8: =+M7+K8-L8 -> 132273.54
A9: 6 | B9: 45936 | G9: =E9*F9 -> 0 | H9: 0 | I9: 0 | J9: =H9*I9 -> 0 | K9: =G9+J9 -> 0 | L9: 0 | M9: =+M8+K9-L9 -> 132273.54
A10: 7 | B10: 45937 | G10: =E10*F10 -> 0 | H10: 0 | I10: 0 | J10: =H10*I10 -> 0 | K10: =G10+J10 -> 0 | L10: 132200 | M10: =+M9+K10-L10 -> 73.536
A11: 8 | B11: 45938 | G11: =E11*F11 -> 0 | H11: 0 | I11: 0 | J11: =H11*I11 -> 0 | K11: =G11+J11 -> 0 | L11: 0 | M11: =+M10+K11-L11 -> 73.536
A12: 9 | B12: 45939 | G12: =E12*F12 -> 0 | H12: 0 | I12: 0 | J12: =H12*I12 -> 0 | K12: =G12+J12 -> 0 | L12: 0 | M12: =+M11+K12-L12 -> 73.536
A13: 10 | B13: 45940 | G13: =E13*F13 -> 0 | H13: 0 | I13: 0 | J13: =H13*I13 -> 0 | K13: =G13+J13 -> 0 | L13: 0 | M13: =+M12+K13-L13 -> 73.536
A14: 11 | B14: 45941 | G14: =E14*F14 -> 0 | H14: 0 | I14: 0 | J14: =H14*I14 -> 0 | K14: =G14+J14 -> 0 | L14: 0 | M14: =+M13+K14-L14 -> 73.536
A15: 12 | B15: 45942 | G15: =E15*F15 -> 0 | H15: 0 | I15: 0 | J15: =H15*I15 -> 0 | K15: =G15+J15 -> 0 | L15: 0 | M15: =+M14+K15-L15 -> 73.536
... A33: 30 | B33: 45960 | G33: =E33*F33 -> 0 | H33: 0 | I33: 0 | J33: =H33*I33 -> 0 | K33: =G33+J33 -> 0 | L33: 0 | M33: =+M32+K33-L33 -> 73.536
A34: 31 | G34: =E34*F34 -> 0 | H34: 0 | I34: 0 | J34: =H34*I34 -> 0 | K34: =G34+J34 -> 0 | L34: 0 | M34: =+M33+K34-L34 -> 73.536
E35: =SUM(E4:E34) -> 0 | G35: =SUM(G4:G34) -> 0 | H35: =SUM(H4:H34) -> 0 | J35: =SUM(J4:J34) -> 0 | K35: =SUM(K4:K34) -> 0 | L35: =SUM(L4:L34) -> 132200
F38: /

Sheet Devarakhadra-3
A1: JSASFuel Genie India Pvt.Ltd
A2: S.No | B2: Date | C2: GRN No | D2: Ind no/Bill No | E2: Diesel (Lts) | F2: Price | G2: Amount | H2: Petrol (Lts) | I2: Price | J2: Amount | K2: Total amount | L2: Amount paid | M2: As on Date | N2: Remarks
A3: Opening Balance | M3: 0
A4: 1 | B4: 45931 | G4: =E4*F4 -> 0 | H4: 0 | I4: 0 | J4: =H4*I4 -> 0 | K4: =G4+J4 -> 0 | L4: 0 | M4: =+M3+K4-L4 -> 0
A5: 2 | B5: 45932 | G5: =E5*F5 -> 0 | H5: 0 | I5: 0 | J5: =H5*I5 -> 0 | K5: =G5+J5 -> 0 | L5: 0 | M5: =+M4+K5-L5 -> 0
A6: 3 | B6: 45933 | G6: =E6*F6 -> 0 | H6: 0 | I6: 0 | J6: =H6*I6 -> 0 | K6: =G6+J6 -> 0 | L6: 0 | M6: =+M5+K6-L6 -> 0
A7: 4 | B7: 45934 | G7: =E7*F7 -> 0 | H7: 0 | I7: 0 | J7: =H7*I7 -> 0 | K7: =G7+J7 -> 0 | L7: 0 | M7: =+M6+K7-L7 -> 0
A8: 5 | B8: 45935 | G8: =E8*F8 -> 0 | H8: 0 | I8: 0 | J8: =H8*I8 -> 0 | K8: =G8+J8 -> 0 | L8: 0 | M8: =+M7+K8-L8 -> 0
A9: 6 | B9: 45936 | G9: =E9*F9 -> 0 | H9: 0 | I9: 0 | J9: =H9*I9 -> 0 | K9: =G9+J9 -> 0 | L9: 0 | M9: =+M8+K9-L9 -> 0
A10: 7 | B10: 45937 | G10: =E10*F10 -> 0 | H10: 0 | I10: 0 | J10: =H10*I10 -> 0 | K10: =G10+J10 -> 0 | L10: 0 | M10: =+M9+K10-L10 -> 0
A11: 8 | B11: 45938 | G11: =E11*F11 -> 0 | H11: 0 | I11: 0 | J11: =H11*I11 -> 0 | K11: =G11+J11 -> 0 | L11: 0 | M11: =+M10+K11-L11 -> 0
A12: 9 | B12: 45939 | G12: =E12*F12 -> 0 | H12: 0 | I12: 0 | J12: =H12*I12 -> 0 | K12: =G12+J12 -> 0 | L12: 0 | M12: =+M11+K12-L12 -> 0
A13: 10 | B13: 45940 | G13: =E13*F13 -> 0 | H13: 0 | I13: 0 | J13: =H13*I13 -> 0 | K13: =G13+J13 -> 0 | L13: 0 | M13: =+M12+K13-L13 -> 0
A14: 11 | B14: 45941 | G14: =E14*F14 -> 0 | H14: 0 | I14: 0 | J14: =H14*I14 -> 0 | K14: =G14+J14 -> 0 | L14: 0 | M14: =+M13+K14-L14 -> 0
A15: 12 | B15: 45942 | G15: =E15*F15 -> 0 | H15: 0 | I15: 0 | J15: =H15*I15 -> 0 | K15: =G15+J15 -> 0 | L15: 0 | M15: =+M14+K15-L15 -> 0
A16: 13 | B16: 45943 | G16: =E16*F16 -> 0 | H16: 0 | I16: 0 | J16: =H16*I16 -> 0 | K16: =G16+J16 -> 0 | L16: 0 | M16: =+M15+K16-L16 -> 0
A17: 14 | B17: 45944 | E17: 1743.87 | F17: 95.83 | G17: =E17*F17 -> 167115.06 | H17: 0 | I17: 0 | J17: =H17*I17 -> 0 | K17: =G17+J17 -> 167115.06 | L17: 0 | M17: =+M16+K17-L17 -> 167115.06
A18: 15 | B18: 45945 | G18: =E18*F18 -> 0 | H18: 0 | I18: 0 | J18: =H18*I18 -> 0 | K18: =G18+J18 -> 0 | L18: 0 | M18: =+M17+K18-L18 -> 167115.06
A19: 16 | B19: 45946 | G19: =E19*F19 -> 0 | H19: 0 | I19: 0 | J19: =H19*I19 -> 0 | K19: =G19+J19 -> 0 | L19: 0 | M19: =+M18+K19-L19 -> 167115.06
A20: 17 | B20: 45947 | G20: =E20*F20 -> 0 | H20: 0 | I20: 0 | J20: =H20*I20 -> 0 | K20: =G20+J20 -> 0 | L20: 0 | M20: =+M19+K20-L20 -> 167115.06
A21: 18 | B21: 45948 | G21: =E21*F21 -> 0 | H21: 0 | I21: 0 | J21: =H21*I21 -> 0 | K21: =G21+J21 -> 0 | L21: 0 | M21: =+M20+K21-L21 -> 167115.06
A22: 19 | B22: 45949 | G22: =E22*F22 -> 0 | H22: 0 | I22: 0 | J22: =H22*I22 -> 0 | K22: =G22+J22 -> 0 | L22: 0 | M22: =+M21+K22-L22 -> 167115.06
A23: 20 | B23: 45950 | G23: =E23*F23 -> 0 | H23: 0 | I23: 0 | J23: =H23*I23 -> 0 | K23: =G23+J23 -> 0 | L23: 0 | M23: =+M22+K23-L23 -> 167115.06
A24: 21 | B24: 45951 | G24: =E24*F24 -> 0 | H24: 0 | I24: 0 | J24: =H24*I24 -> 0 | K24: =G24+J24 -> 0 | L24: 0 | M24: =+M23+K24-L24 -> 167115.06
A25: 22 | B25: 45952 | G25: =E25*F25 -> 0 | H25: 0 | I25: 0 | J25: =H25*I25 -> 0 | K25: =G25+J25 -> 0 | L25: 0 | M25: =+M24+K25-L25 -> 167115.06
A26: 23 | B26: 45953 | G26: =E26*F26 -> 0 | H26: 0 | I26: 0 | J26: =H26*I26 -> 0 | K26: =G26+J26 -> 0 | L26: 0 | M26: =+M25+K26-L26 -> 167115.06
A27: 24 | B27: 45954 | G27: =E27*F27 -> 0 | H27: 0 | I27: 0 | J27: =H27*I27 -> 0 | K27: =G27+J27 -> 0 | L27: 0 | M27: =+M26+K27-L27 -> 167115.06
A28: 25 | B28: 45955 | G28: =E28*F28 -> 0 | H28: 0 | I28: 0 | J28: =H28*I28 -> 0 | K28: =G28+J28 -> 0 | L28: 0 | M28: =+M27+K28-L28 -> 167115.06
A29: 26 | B29: 45956 | G29: =E29*F29 -> 0 | H29: 0 | I29: 0 | J29: =H29*I29 -> 0 | K29: =G29+J29 -> 0 | L29: 0 | M29: =+M28+K29-L29 -> 167115.06
... A33: 30 | B33: 45960 | G33: =E33*F33 -> 0 | H33: 0 | I33: 0 | J33: =H33*I33 -> 0 | K33: =G33+J33 -> 0 | L33: 0 | M33: =+M32+K33-L33 -> 167115.06
A34: 31 | G34: =E34*F34 -> 0 | H34: 0 | I34: 0 | J34: =H34*I34 -> 0 | K34: =G34+J34 -> 0 | L34: 0 | M34: =+M33+K34-L34 -> 167115.06
E35: =SUM(E4:E34) -> 1743.87 | G35: =SUM(G4:G34) -> 167115.06 | H35: =SUM(H4:H34) -> 0 | J35: =SUM(J4:J34) -> 0 | K35: =SUM(K4:K34) -> 167115.06 | L35: =SUM(L4:L34) -> 0

Sheet Dindi
A1: Akarapu Balakistamma Fillling
A2: S.No | B2: Date | C2: GRN No | D2: Ind no/Bill No | E2: Diesel (Lts) | F2: Price | G2: Amount | H2: Petrol (Lts) | I2: Price | J2: Amount | K2: Total amount | L2: Amount paid | M2: As on Date | N2: Remarks
A3: Opening Balance | M3: 0
A4: 1 | B4: 45931 | G4: =E4*F4 -> 0 | H4: 0 | I4: 0 | J4: =H4*I4 -> 0 | K4: =G4+J4 -> 0 | L4: =+K4 -> 0 | M4: 0
A5: 2 | B5: 45932 | G5: =E5*F5 -> 0 | H5: 0 | I5: 0 | J5: =H5*I5 -> 0 | K5: =G5+J5 -> 0 | L5: =+K5 -> 0 | M5: 0
A6: 3 | B6: 45933 | G6: =E6*F6 -> 0 | H6: 0 | I6: 0 | J6: =H6*I6 -> 0 | K6: =G6+J6 -> 0 | L6: =+K6 -> 0 | M6: 0
A7: 4 | B7: 45934 | G7: =E7*F7 -> 0 | H7: 0 | I7: 0 | J7: =H7*I7 -> 0 | K7: =G7+J7 -> 0 | L7: =+K7 -> 0 | M7: 0
A8: 5 | B8: 45935 | G8: =E8*F8 -> 0 | H8: 0 | I8: 0 | J8: =H8*I8 -> 0 | K8: =G8+J8 -> 0 | L8: =+K8 -> 0 | M8: 0
A9: 6 | B9: 45936 | G9: =E9*F9 -> 0 | H9: 0 | I9: 0 | J9: =H9*I9 -> 0 | K9: =G9+J9 -> 0 | L9: =+K9 -> 0 | M9: 0
A10: 7 | B10: 45937 | E10: 43.61 | F10: 96.83 | G10: =E10*F10 -> 4222.7563 | H10: 0 | I10: 0 | J10: =H10*I10 -> 0 | K10: =G10+J10 -> 4222.7563 | L10: =+K10 -> 4222.7563 | M10: 0
A11: 8 | B11: 45938 | G11: =E11*F11 -> 0 | H11: 0 | I11: 0 | J11: =H11*I11 -> 0 | K11: =G11+J11 -> 0 | L11: =+K11 -> 0 | M11: 0
A12: 9 | B12: 45939 | G12: =E12*F12 -> 0 | H12: 0 | I12: 0 | J12: =H12*I12 -> 0 | K12: =G12+J12 -> 0 | L12: =+K12 -> 0 | M12: 0
A13: 10 | B13: 45940 | G13: =E13*F13 -> 0 | H13: 0 | I13: 0 | J13: =H13*I13 -> 0 | K13: =G13+J13 -> 0 | L13: =+K13 -> 0 | M13: 0
A14: 11 | B14: 45941 | G14: =E14*F14 -> 0 | H14: 0 | I14: 0 | J14: =H14*I14 -> 0 | K14: =G14+J14 -> 0 | L14: =+K14 -> 0 | M14: 0
A15: 12 | B15: 45942 | G15: =E15*F15 -> 0 | H15: 0 | I15: 0 | J15: =H15*I15 -> 0 | K15: =G15+J15 -> 0 | L15: =+K15 -> 0 | M15: 0
A16: 13 | B16: 45943 | G16: =E16*F16 -> 0 | H16: 0 | I16: 0 | J16: =H16*I16 -> 0 | K16: =G16+J16 -> 0 | L16: =+K16 -> 0 | M16: 0
A17: 14 | B17: 45944 | G17: =E17*F17 -> 0 | H17: 0 | I17: 0 | J17: =H17*I17 -> 0 | K17: =G17+J17 -> 0 | L17: =+K17 -> 0 | M17: 0
A18: 15 | B18: 45945 | G18: =E18*F18 -> 0 | H18: 0 | I18: 0 | J18: =H18*I18 -> 0 | K18: =G18+J18 -> 0 | L18: =+K18 -> 0 | M18: 0
A19: 16 | B19: 45946 | G19: =E19*F19 -> 0 | H19: 0 | I19: 0 | J19: =H19*I19 -> 0 | K19: =G19+J19 -> 0 | L19: =+K19 -> 0 | M19: 0
A20: 17 | B20: 45947 | G20: =E20*F20 -> 0 | H20: 0 | I20: 0 | J20: =H20*I20 -> 0 | K20: =G20+J20 -> 0 | L20: =+K20 -> 0 | M20: 0
A21: 18 | B21: 45948 | G21: =E21*F21 -> 0 | H21: 0 | I21: 0 | J21: =H21*I21 -> 0 | K21: =G21+J21 -> 0 | L21: =+K21 -> 0 | M21: 0
A22: 19 | B22: 45949 | G22: =E22*F22 -> 0 | H22: 0 | I22: 0 | J22: =H22*I22 -> 0 | K22: =G22+J22 -> 0 | L22: =+K22 -> 0 | M22: 0
... A25: 22 | B25: 45952 | G25: =E25*F25 -> 0 | H25: 0 | I25: 0 | J25: =H25*I25 -> 0 | K25: =G25+J25 -> 0 | L25: =+K25 -> 0 | M25: 0
A26: 23 | B26: 45953 | E26: 0 | F26: 0 | G26: =E26*F26 -> 0 | H26: 0 | I26: 0 | J26: =H26*I26 -> 0 | K26: =G26+J26 -> 0 | L26: =+K26 -> 0 | M26: 0
A27: 24 | B27: 45954 | E27: 42.27 | F27: 96.83 | G27: =E27*F27 -> 4093.0041 | H27: 0 | I27: 0 | J27: =H27*I27 -> 0 | K27: =G27+J27 -> 4093.0041 | L27: =+K27 -> 4093.0041 | M27: 0
A28: 25 | B28: 45955 | G28: =E28*F28 -> 0 | H28: 0 | I28: 0 | J28: =H28*I28 -> 0 | K28: =G28+J28 -> 0 | L28: =+K28 -> 0 | M28: 0
A29: 26 | B29: 45956 | G29: =E29*F29 -> 0 | H29: 0 | I29: 0 | J29: =H29*I29 -> 0 | K29: =G29+J29 -> 0 | L29: =+K29 -> 0 | M29: 0
A30: 27 | B30: 45957 | G30: =E30*F30 -> 0 | H30: 0 | I30: 0 | J30: =H30*I30 -> 0 | K30: =G30+J30 -> 0 | L30: =+K30 -> 0 | M30: 0
A31: 28 | B31: 45958 | G31: =E31*F31 -> 0 | H31: 0 | I31: 0 | J31: =H31*I31 -> 0 | K31: =G31+J31 -> 0 | L31: =+K31 -> 0 | M31: 0
A32: 29 | B32: 45959 | G32: =E32*F32 -> 0 | H32: 0 | I32: 0 | J32: =H32*I32 -> 0 | K32: =G32+J32 -> 0 | L32: =+K32 -> 0 | M32: 0
A33: 30 | B33: 45960 | G33: =E33*F33 -> 0 | H33: 0 | I33: 0 | J33: =H33*I33 -> 0 | K33: =G33+J33 -> 0 | L33: =+K33 -> 0 | M33: 0
A34: 31 | G34: =E34*F34 -> 0 | H34: 0 | I34: 0 | J34: =H34*I34 -> 0 | K34: =G34+J34 -> 0 | L34: =+K34 -> 0 | M34: 0
E35: =SUM(E4:E34) -> 85.88 | G35: =SUM(G4:G34) -> 8315.7604 | H35: =SUM(H4:H34) -> 0 | J35: =SUM(J4:J34) -> 0 | K35: =SUM(K4:K34) -> 8315.7604 | L35: =SUM(L4:L34) -> 8315.7604

Sheet Amalapuram
A1: Sathya Filling Station
A2: S.No | B2: Date | C2: GRN No | D2: Ind no/Bill No | E2: Diesel (Lts) | F2: Price | G2: Amount | H2: Petrol (Lts) | I2: Price | J2: Amount | K2: Total amount | L2: Amount paid | M2: As on Date | N2: Remarks
A3: Opening Balance | M3: 0
A4: 1 | B4: 45931 | G4: =E4*F4 -> 0 | J4: =H4*I4 -> 0 | K4: =G4+J4 -> 0 | M4: =+M3+K4-L4 -> 0
A5: 2 | B5: 45932 | G5: =E5*F5 -> 0 | J5: =H5*I5 -> 0 | K5: =G5+J5 -> 0 | M5: =+M4+K5-L5 -> 0
A6: 3 | B6: 45933 | G6: =E6*F6 -> 0 | J6: =H6*I6 -> 0 | K6: =G6+J6 -> 0 | M6: =+M5+K6-L6 -> 0
A7: 4 | B7: 45934 | G7: =E7*F7 -> 0 | J7: =H7*I7 -> 0 | K7: =G7+J7 -> 0 | M7: =+M6+K7-L7 -> 0
A8: 5 | B8: 45935 | C8: Bhaskara Agencies Morampudi | D8: Rajahmundry | G8: =E8*F8 -> 0 | H8: 25 | I8: 108.83 | J8: =H8*I8 -> 2720.75 | K8: =G8+J8 -> 2720.75 | L8: 2720.75 | M8: =+M7+K8-L8 -> 0
A9: 6 | B9: 45936 | C9: Padma Filling Station | D9: Rajahmundry | E9: 20.68 | F9: 96.71 | G9: =E9*F9 -> 1999.9628 | J9: =H9*I9 -> 0 | K9: =G9+J9 -> 1999.9628 | L9: 1999.96 | M9: =+M8+K9-L9 -> 0.0028
A10: 7 | B10: 45937 | C10: Bhaskara Agencies Morampudi | D10: Rajahmundry | E10: 44.45 | F10: 96.71 | G10: =E10*F10 -> 4298.7595 | J10: =H10*I10 -> 0 | K10: =G10+J10 -> 4298.7595 | L10: 4298.76 | M10: =+M9+K10-L10 -> 0.0023
A11: 8 | B11: 45938 | G11: =E11*F11 -> 0 | J11: =H11*I11 -> 0 | K11: =G11+J11 -> 0 | M11: =+M10+K11-L11 -> 0.0023
A12: 9 | B12: 45939 | C12: Sri Venkata Ganesh Enterprises-Venkatapuram | D12: Eluru | E12: 48.53 | F12: 97.66 | G12: =E12*F12 -> 4739.4398 | J12: =H12*I12 -> 0 | K12: =G12+J12 -> 4739.4398 | L12: 4739.4398 | M12: =+M11+K12-L12 -> 0.0023
A13: 10 | B13: 45940 | C13: Sri Venkata Ganesh Enterprises-Venkatapuram | D13: Eluru | G13: =E13*F13 -> 0 | H13: 20 | I13: 109.86 | J13: =H13*I13 -> 2197.2 | K13: =G13+J13 -> 2197.2 | L13: 2197.2 | M13: =+M12+K13-L13 -> 0.0023
A14: 11 | B14: 45941 | G14: =E14*F14 -> 0 | J14: =H14*I14 -> 0 | K14: =G14+J14 -> 0 | M14: =+M13+K14-L14 -> 0.0023
A15: 12 | B15: 45942 | G15: =E15*F15 -> 0 | J15: =H15*I15 -> 0 | K15: =G15+J15 -> 0 | M15: =+M14+K15-L15 -> 0.0023
A16: 13 | B16: 45943 | C16: Sri Venkateswara Enterprises Bharat Petroleum | D16: Yanam | E16: 38.9 | F16: 86.75 | G16: =E16*F16 -> 3374.575 | J16: =H16*I16 -> 0 | K16: =G16+J16 -> 3374.575 | L16: =H16+K16 -> 3374.575 | M16: =+M15+K16-L16 -> 0.0023
B17: 45943 | C17: Sri Lakshmi Filling Station-Nadipalli | D17: Chinthalapudi | H17: 25 | I17: 109.97 | J17: =H17*I17 -> 2749.25 | K17: =G17+J17 -> 2749.25 | L17: 2749.25
A18: 14 | B18: 45944 | G18: =E18*F18 -> 0 | J18: =H18*I18 -> 0 | K18: =G18+J18 -> 0 | M18: =+M16+K18-L18 -> 0.0023
A19: 15 | B19: 45945 | C19: Padma Highway Filling Station | D19: Yanam | E19: 38.04 | F19: 86.75 | G19: =E19*F19 -> 3299.97 | J19: =H19*I19 -> 0 | K19: =G19+J19 -> 3299.97 | L19: 3299.97 | M19: =+M18+K19-L19 -> 0.0023
A20: 16 | B20: 45946 | G20: =E20*F20 -> 0 | J20: =H20*I20 -> 0 | K20: =G20+J20 -> 0 | M20: =+M19+K20-L20 -> 0.0023
A21: 17 | B21: 45947 | C21: Buchibabu Filling Center Bharat Petroleum | D21: Ethakota | E21: 45.44 | F21: 97.06 | G21: =E21*F21 -> 4410.4064 | J21: =H21*I21 -> 0 | K21: =G21+J21 -> 4410.4064 | L21: 4410.41 | M21: =+M20+K21-L21 -> -0.0013
A22: 18 | B22: 45948 | C22: GR Filling Station Bharath Petrolium | D22: Tanuku | G22: =E22*F22 -> 0 | H22: 25 | I22: 109.51 | J22: =H22*I22 -> 2737.75 | K22: =G22+J22 -> 2737.75 | L22: 2737.75 | M22: =+M21+K22-L22 -> -0.0013
A23: 19 | B23: 45949 | C23: GR Filling Station Bharath Petrolium | D23: Tanuku | G23: =E23*F23 -> 0 | H23: 20 | I23: 109.51 | J23: =H23*I23 -> 2190.2 | K23: =G23+J23 -> 2190.2 | L23: 2190.2 | M23: =+M22+K23-L23 -> -0.0013
A24: 20 | B24: 45950 | G24: =E24*F24 -> 0 | J24: =H24*I24 -> 0 | K24: =G24+J24 -> 0 | M24: =+M23+K24-L24 -> -0.0013
A25: 21 | B25: 45951 | G25: =E25*F25 -> 0 | J25: =H25*I25 -> 0 | K25: =G25+J25 -> 0 | M25: =+M24+K25-L25 -> -0.0013
A26: 22 | B26: 45952 | G26: =E26*F26 -> 0 | J26: =H26*I26 -> 0 | K26: =G26+J26 -> 0 | M26: =+M25+K26-L26 -> -0.0013
A27: 23 | B27: 45953 | C27: BHARAT FILLING STATION | D27: Nuziveedu | E27: 30.89 | F27: 97.12 | G27: =E27*F27 -> 3000.0368 | J27: =H27*I27 -> 0 | K27: =G27+J27 -> 3000.0368 | L27: 3000.04 | M27: =+M26+K27-L27 -> -0.0045
A28: 24 | B28: 45954 | C28: Pulla Fuels Bharat Petrolium | D28: Pulla(Bhimadolu) | E28: 30.75 | F28: 97.56 | G28: =E28*F28 -> 2999.97 | J28: =H28*I28 -> 0 | K28: =G28+J28 -> 2999.97 | L28: 2999.97 | M28: =+M27+K28-L28 -> -0.0045
A29: 25 | B29: 45955 | C29: R Ammiraju&Brothers Bharat Petrolium | D29: Nidadavolu | G29: =E29*F29 -> 0 | H29: 25 | I29: 109.21 | J29: =H29*I29 -> 2730.25 | K29: =G29+J29 -> 2730.25 | L29: 2730.25 | M29: =+M28+K29-L29 -> -0.0045
A30: 26 | B30: 45956 | G30: =E30*F30 -> 0 | J30: =H30*I30 -> 0 | K30: =G30+J30 -> 0 | M30: =+M29+K30-L30 -> -0.0045
A31: 27 | B31: 45957 | G31: =E31*F31 -> 0 | J31: =H31*I31 -> 0 | K31: =G31+J31 -> 0 | M31: =+M30+K31-L31 -> -0.0045
A32: 28 | B32: 45958 | G32: =E32*F32 -> 0 | J32: =H32*I32 -> 0 | K32: =G32+J32 -> 0 | M32: =+M31+K32-L32 -> -0.0045
A33: 29 | B33: 45959 | G33: =E33*F33 -> 0 | J33: =H33*I33 -> 0 | K33: =G33+J33 -> 0 | M33: =+M32+K33-L33 -> -0.0045
B34: 45960 | C34: Sri Venkata Sitarama Filling Station | D34: Bhimavaram | G34: =E34*F34 -> 0 | H34: 15 | I34: 109.83 | J34: =H34*I34 -> 1647.45 | K34: =G34+J34 -> 1647.45 | L34: 1647.45 | M34: 0
A35: 30 | B35: 45961 | C35: Sri Venkata Sitarama Filling Station | D35: Bhimavaram | E35: 43 | F35: 97.64 | G35: =E35*F35 -> 4198.52 | H35: 20 | I35: 109.83 | J35: =H35*I35 -> 2196.6 | K35: =G35+J35 -> 6395.12 | L35: 6395.12 | M35: =+M33+K35-L35 -> -0.0045
A36: 31 | E36: 0 | F36: 0 | G36: =E36*F36 -> 0 | J36: =H36*I36 -> 0 | K36: =G36+J36 -> 0 | L36: 0 | M36: =+M35+K36-L36 -> -0.0045
E37: =SUM(E4:E36) -> 340.68 | G37: =SUM(G4:G36) -> 32321.64 | H37: =SUM(H4:H36) -> 175 | J37: =SUM(J4:J36) -> 19169.45 | K37: =SUM(K4:K36) -> 51491.09 | L37: =SUM(L4:L36) -> 51491.095

Sheet Madana palli
A2: S.No | B2: Date | C2: GRN No | D2: Ind no/Bill No | E2: Diesel (Lts) | F2: Price | G2: Amount | H2: Petrol (Lts) | I2: Price | J2: Amount | K2: Total amount | L2: Amount paid | M2: As on Date | N2: Remarks
A3: Opening Balance | M3: 0
A4: 1 | B4: 45931 | G4: =E4*F4 -> 0 | H4: 0 | I4: 0 | J4: =H4*I4 -> 0 | K4: =G4+J4 -> 0 | L4: =+K4 -> 0 | M4: 0
A5: 2 | B5: 45932 | G5: =E5*F5 -> 0 | H5: 0 | I5: 0 | J5: =H5*I5 -> 0 | K5: =G5+J5 -> 0 | L5: =+K5 -> 0 | M5: 0
A6: 3 | B6: 45933 | G6: =E6*F6 -> 0 | H6: 0 | I6: 0 | J6: =H6*I6 -> 0 | K6: =G6+J6 -> 0 | L6: =+K6 -> 0 | M6: 0
A7: 4 | B7: 45934 | G7: =E7*F7 -> 0 | H7: 0 | I7: 0 | J7: =H7*I7 -> 0 | K7: =G7+J7 -> 0 | L7: =+K7 -> 0 | M7: 0
A8: 5 | B8: 45935 | G8: =E8*F8 -> 0 | H8: 0 | I8: 0 | J8: =H8*I8 -> 0 | K8: =G8+J8 -> 0 | L8: =+K8 -> 0 | M8: 0
A9: 6 | B9: 45936 | G9: =E9*F9 -> 0 | H9: 0 | I9: 0 | J9: =H9*I9 -> 0 | K9: =G9+J9 -> 0 | L9: =+K9 -> 0 | M9: 0
A10: 7 | B10: 45937 | G10: =E10*F10 -> 0 | H10: 0 | I10: 0 | J10: =H10*I10 -> 0 | K10: =G10+J10 -> 0 | L10: =+K10 -> 0 | M10: 0
A11: 8 | B11: 45938 | G11: =E11*F11 -> 0 | H11: 0 | I11: 0 | J11: =H11*I11 -> 0 | K11: =G11+J11 -> 0 | L11: =+K11 -> 0 | M11: 0
A12: 9 | B12: 45939 | G12: =E12*F12 -> 0 | H12: 0 | I12: 0 | J12: =H12*I12 -> 0 | K12: =G12+J12 -> 0 | L12: =+K12 -> 0 | M12: 0
A13: 10 | B13: 45940 | G13: =E13*F13 -> 0 | H13: 0 | I13: 0 | J13: =H13*I13 -> 0 | K13: =G13+J13 -> 0 | L13: =+K13 -> 0 | M13: 0
A14: 11 | B14: 45941 | G14: =E14*F14 -> 0 | H14: 0 | I14: 0 | J14: =H14*I14 -> 0 | K14: =G14+J14 -> 0 | L14: =+K14 -> 0 | M14: 0
A15: 12 | B15: 45942 | G15: =E15*F15 -> 0 | H15: 0 | I15: 0 | J15: =H15*I15 -> 0 | K15: =G15+J15 -> 0 | L15: =+K15 -> 0 | M15: 0
... A20: 17 | B20: 45947 | G20: =E20*F20 -> 0 | H20: 0 | I20: 0 | J20: =H20*I20 -> 0 | K20: =G20+J20 -> 0 | L20: =+K20 -> 0 | M20: 0
A21: 18 | B21: 45948 | E21: 335.74 | F21: 97.43 | G21: =E21*F21 -> 32711.148 | H21: 5.56 | I21: 109.61 | J21: =H21*I21 -> 609.4316 | K21: =G21+J21 -> 33320.58 | L21: =+K21 -> 33320.58 | M21: 0 | N21: IOCL
A22: 19 | B22: 45949 | G22: =E22*F22 -> 0 | H22: 0 | I22: 0 | J22: =H22*I22 -> 0 | K22: =G22+J22 -> 0 | L22: =+K22 -> 0 | M22: 0
A23: 20 | B23: 45950 | E23: 61.58 | F23: 97.43 | G23: =E23*F23 -> 5999.7394 | H23: 0 | I23: 0 | J23: =H23*I23 -> 0 | K23: =G23+J23 -> 5999.7394 | L23: =+K23 -> 5999.7394 | M23: 0 | N23: IOCL
A24: 21 | B24: 45951 | G24: =E24*F24 -> 0 | H24: 0 | I24: 0 | J24: =H24*I24 -> 0 | K24: =G24+J24 -> 0 | L24: =+K24 -> 0 | M24: 0
A25: 22 | B25: 45952 | G25: =E25*F25 -> 0 | H25: 0 | I25: 0 | J25: =H25*I25 -> 0 | K25: =G25+J25 -> 0 | L25: =+K25 -> 0 | M25: 0
A26: 23 | B26: 45953 | E26: 200 | F26: 97.76 | G26: =E26*F26 -> 19552 | H26: 0 | I26: 0 | J26: =H26*I26 -> 0 | K26: =G26+J26 -> 19552 | L26: =+K26 -> 19552 | M26: 0 | N26: HPCL
A27: 24 | B27: 45954 | E27: 98.62 | F27: 97.43 | G27: =E27*F27 -> 9608.5466 | H27: 5.83 | I27: 109.61 | J27: =H27*I27 -> 639.0263 | K27: =G27+J27 -> 10247.573 | L27: =+K27 -> 10247.573 | M27: 0 | N27: IOCL
A28: 25 | B28: 45955 | G28: =E28*F28 -> 0 | H28: 0 | I28: 0 | J28: =H28*I28 -> 0 | K28: =G28+J28 -> 0 | L28: =+K28 -> 0 | M28: 0
A29: 26 | B29: 45956 | G29: =E29*F29 -> 0 | H29: 0 | I29: 0 | J29: =H29*I29 -> 0 | K29: =G29+J29 -> 0 | L29: =+K29 -> 0 | M29: 0
A30: 27 | B30: 45957 | G30: =E30*F30 -> 0 | H30: 0 | I30: 0 | J30: =H30*I30 -> 0 | K30: =G30+J30 -> 0 | L30: =+K30 -> 0 | M30: 0
A31: 28 | B31: 45958 | G31: =E31*F31 -> 0 | H31: 0 | I31: 0 | J31: =H31*I31 -> 0 | K31: =G31+J31 -> 0 | L31: =+K31 -> 0 | M31: 0
A32: 29 | B32: 45959 | G32: =E32*F32 -> 0 | H32: 0 | I32: 0 | J32: =H32*I32 -> 0 | K32: =G32+J32 -> 0 | L32: =+K32 -> 0 | M32: 0
A33: 30 | B33: 45960 | E33: 400 | F33: 97.76 | G33: =E33*F33 -> 39104 | H33: 4.54 | I33: 110.07 | J33: =H33*I33 -> 499.7178 | K33: =G33+J33 -> 39603.718 | L33: =+K33 -> 39603.718 | M33: 0 | N33: HPCL
A34: 31 | E34: 30.79 | F34: 97.43 | G34: =E34*F34 -> 2999.8697 | H34: 0 | I34: 0 | J34: =H34*I34 -> 0 | K34: =G34+J34 -> 2999.8697 | L34: =+K34 -> 2999.8697 | M34: 0
E35: =SUM(E4:E34) -> 1126.73 | G35: =SUM(G4:G34) -> 109975.3 | H35: =SUM(H4:H34) -> 15.93 | J35: =SUM(J4:J34) -> 1748.1757 | K35: =SUM(K4:K34) -> 111723.48 | L35: =SUM(L4:L34) -> 111723.48

Sheet Kadur
A1: Vishal Service Station
A2: S.No | B2: Date | C2: GRN No | D2: Ind No/Bill No | E2: Diesel (Lts) | F2: Price | G2: Amount | H2: Petrol (Lts) | I2: Price | J2: Amount | K2: Total amount | L2: Amount paid | M2: As on Date | N2: Remarks
A3: Opening Balance | K3: 11508.831 | M3: 11508.831 | O3: 207239.43
A4: 1 | B4: 45931 | F4: 0 | G4: =E4*F4 -> 0 | H4: 0 | I4: 0 | J4: =H4*I4 -> 0 | K4: =G4+J4 -> 0 | M4: =M3+K4-L4 -> 11508.831
A5: 2 | B5: 45932 | F5: 0 | G5: =E5*F5 -> 0 | H5: 0 | I5: 0 | J5: =H5*I5 -> 0 | K5: =G5+J5 -> 0 | M5: =M4+K5-L5 -> 11508.831
A6: 3 | B6: 45933 | F6: 0 | G6: =E6*F6 -> 0 | H6: 0 | I6: 0 | J6: =H6*I6 -> 0 | K6: =G6+J6 -> 0 | M6: =M5+K6-L6 -> 11508.831
A7: 4 | B7: 45934 | F7: 0 | G7: =E7*F7 -> 0 | H7: 0 | I7: 0 | J7: =H7*I7 -> 0 | K7: =G7+J7 -> 0 | M7: =M6+K7-L7 -> 11508.831
A8: 5 | B8: 45935 | F8: 0 | G8: =E8*F8 -> 0 | H8: 0 | I8: 0 | J8: =H8*I8 -> 0 | K8: =G8+J8 -> 0 | M8: =M7+K8-L8 -> 11508.831
A9: 6 | B9: 45936 | F9: 0 | G9: =E9*F9 -> 0 | H9: 0 | I9: 0 | J9: =H9*I9 -> 0 | K9: =G9+J9 -> 0 | M9: =M8+K9-L9 -> 11508.831
A10: 7 | B10: 45937 | E10: 1500 | F10: 92.15 | G10: =E10*F10 -> 138225 | H10: 70 | I10: 104.27 | J10: =H10*I10 -> 7298.9 | K10: =G10+J10 -> 145523.9 | M10: =M9+K10-L10 -> 157032.73
A11: 8 | B11: 45938 | F11: 0 | G11: =E11*F11 -> 0 | H11: 0 | I11: 0 | J11: =H11*I11 -> 0 | K11: =G11+J11 -> 0 | M11: =M10+K11-L11 -> 157032.73
A12: 9 | B12: 45939 | F12: 0 | G12: =E12*F12 -> 0 | H12: 0 | I12: 0 | J12: =H12*I12 -> 0 | K12: =G12+J12 -> 0 | M12: =M11+K12-L12 -> 157032.73
A13: 10 | B13: 45940 | F13: 0 | G13: =E13*F13 -> 0 | H13: 0 | I13: 0 | J13: =H13*I13 -> 0 | K13: =G13+J13 -> 0 | M13: =M12+K13-L13 -> 157032.73
A14: 11 | B14: 45941 | F14: 0 | G14: =E14*F14 -> 0 | H14: 0 | I14: 0 | J14: =H14*I14 -> 0 | K14: =G14+J14 -> 0 | M14: =M13+K14-L14 -> 157032.73
A15: 12 | B15: 45942 | F15: 0 | G15: =E15*F15 -> 0 | H15: 0 | I15: 0 | J15: =H15*I15 -> 0 | K15: =G15+J15 -> 0 | M15: =M14+K15-L15 -> 157032.73
A16: 13 | B16: 45943 | F16: 0 | G16: =E16*F16 -> 0 | H16: 0 | I16: 0 | J16: =H16*I16 -> 0 | K16: =G16+J16 -> 0 | M16: =M15+K16-L16 -> 157032.73
A17: 14 | B17: 45944 | F17: 0 | G17: =E17*F17 -> 0 | H17: 0 | I17: 0 | J17: =H17*I17 -> 0 | K17: =G17+J17 -> 0 | M17: =M16+K17-L17 -> 157032.73
A18: 15 | B18: 45945 | F18: 0 | G18: =E18*F18 -> 0 | H18: 0 | I18: 0 | J18: =H18*I18 -> 0 | K18: =G18+J18 -> 0 | M18: =M17+K18-L18 -> 157032.73
A19: 16 | B19: 45946 | F19: 0 | G19: =E19*F19 -> 0 | H19: 0 | I19: 0 | J19: =H19*I19 -> 0 | K19: =G19+J19 -> 0 | M19: =M18+K19-L19 -> 157032.73
A20: 17 | B20: 45947 | F20: 0 | G20: =E20*F20 -> 0 | H20: 0 | I20: 0 | J20: =H20*I20 -> 0 | K20: =G20+J20 -> 0 | M20: =M19+K20-L20 -> 157032.73
A21: 18 | B21: 45948 | F21: 0 | J21: =H21*I21 -> 0 | K21: =G21+J21 -> 0 | M21: =M20+K21-L21 -> 157032.73
A22: 19 | B22: 45949 | F22: 0 | J22: =H22*I22 -> 0 | K22: =G22+J22 -> 0 | M22: =M21+K22-L22 -> 157032.73
A23: 20 | B23: 45950 | F23: 0 | J23: =H23*I23 -> 0 | K23: =G23+J23 -> 0 | M23: =M22+K23-L23 -> 157032.73
A24: 21 | B24: 45951 | F24: 0 | J24: =H24*I24 -> 0 | K24: =G24+J24 -> 0 | M24: =M23+K24-L24 -> 157032.73
A25: 22 | B25: 45952 | F25: 0 | J25: =H25*I25 -> 0 | K25: =G25+J25 -> 0 | M25: =M24+K25-L25 -> 157032.73
A26: 23 | B26: 45953 | F26: 0 | J26: =H26*I26 -> 0 | K26: =G26+J26 -> 0 | M26: =M25+K26-L26 -> 157032.73
A27: 24 | B27: 45954 | F27: 0 | J27: =H27*I27 -> 0 | K27: =G27+J27 -> 0 | M27: =M26+K27-L27 -> 157032.73
A28: 25 | B28: 45955 | F28: 0 | J28: =H28*I28 -> 0 | K28: =G28+J28 -> 0 | M28: =M27+K28-L28 -> 157032.73
A29: 26 | B29: 45956 | F29: 0 | J29: =H29*I29 -> 0 | K29: =G29+J29 -> 0 | M29: =M28+K29-L29 -> 157032.73
A30: 27 | B30: 45957 | F30: 0 | J30: =H30*I30 -> 0 | K30: =G30+J30 -> 0 | M30: =M29+K30-L30 -> 157032.73
A31: 28 | B31: 45958 | F31: 0 | J31: =H31*I31 -> 0 | K31: =G31+J31 -> 0 | M31: =M30+K31-L31 -> 157032.73
A32: 29 | B32: 45959 | F32: 0 | G32: =E32*F32 -> 0 | H32: 0 | I32: 0 | J32: =H32*I32 -> 0 | K32: =G32+J32 -> 0 | M32: =M31+K32-L32 -> 157032.73
A33: 30 | B33: 45960 | F33: 0 | G33: =E33*F33 -> 0 | H33: 70 | I33: 104.27 | J33: =H33*I33 -> 7298.9 | K33: =G33+J33 -> 7298.9 | M33: =M32+K33-L33 -> 164331.63
A34: 31 | F34: 0 | G34: =E34*F34 -> 0 | J34: =H34*I34 -> 0 | K34: =G34+J34 -> 0
E35: =SUM(E4:E34) -> 1500 | G35: =SUM(G4:G34) -> 138225 | H35: =SUM(H4:H34) -> 140 | J35: =SUM(J4:J34) -> 14597.8 | K35: =SUM(K4:K34) -> 152822.8 | L35: =SUM(L4:L31) -> 0

Sheet Hosadurga
A1: Merchant Petroliums
A2: S.No | B2: Date | C2: GRN No | D2: Ind No/Bill No | E2: Diesel (Lts) | F2: Price | G2: Amount | H2: Petrol (Lts) | I2: Price | J2: Amount | K2: Total amount | L2: Amount paid | M2: As on Date | N2: Remarks
A3: Opening Balance | K3: 2258.6 | M3: =+K3 -> 2258.6
A4: 1 | B4: 45931 | G4: =E4*F4 -> 0 | H4: 0 | J4: =H4*I4 -> 0 | K4: =G4+J4 -> 0 | L4: 0 | M4: =M3+K4-L4 -> 2258.6
A5: 2 | B5: 45932 | G5: =E5*F5 -> 0 | H5: 0 | I5: 0 | J5: =H5*I5 -> 0 | K5: =G5+J5 -> 0 | L5: 0 | M5: =M4+K5-L5 -> 2258.6
A6: 3 | B6: 45933 | G6: =E6*F6 -> 0 | H6: 0 | I6: 0 | J6: =H6*I6 -> 0 | K6: =G6+J6 -> 0 | L6: 0 | M6: =M5+K6-L6 -> 2258.6
A7: 4 | B7: 45934 | G7: =E7*F7 -> 0 | H7: 0 | I7: 0 | J7: =H7*I7 -> 0 | K7: =G7+J7 -> 0 | L7: 0 | M7: =M6+K7-L7 -> 2258.6
A8: 5 | B8: 45935 | G8: =E8*F8 -> 0 | H8: 0 | I8: 0 | J8: =H8*I8 -> 0 | K8: =G8+J8 -> 0 | L8: 0 | M8: =M7+K8-L8 -> 2258.6
A9: 6 | B9: 45936 | G9: =E9*F9 -> 0 | H9: 0 | I9: 0 | J9: =H9*I9 -> 0 | K9: =G9+J9 -> 0 | L9: 0 | M9: =M8+K9-L9 -> 2258.6
A10: 7 | B10: 45937 | G10: =E10*F10 -> 0 | J10: =H10*I10 -> 0 | K10: =G10+J10 -> 0 | L10: 0 | M10: =M9+K10-L10 -> 2258.6
A11: 8 | B11: 45938 | G11: =E11*F11 -> 0 | H11: 0 | I11: 0 | J11: =H11*I11 -> 0 | K11: =G11+J11 -> 0 | L11: 0 | M11: =M10+K11-L11 -> 2258.6
A12: 9 | B12: 45939 | G12: =E12*F12 -> 0 | H12: 0 | I12: 0 | J12: =H12*I12 -> 0 | K12: =G12+J12 -> 0 | L12: 0 | M12: =M11+K12-L12 -> 2258.6
A13: 10 | B13: 45940 | G13: =E13*F13 -> 0 | H13: 0 | I13: 0 | J13: =H13*I13 -> 0 | K13: =G13+J13 -> 0 | L13: 0 | M13: =M12+K13-L13 -> 2258.6
A14: 11 | B14: 45941 | G14: =E14*F14 -> 0 | H14: 0 | I14: 0 | J14: =H14*I14 -> 0 | K14: =G14+J14 -> 0 | L14: 0 | M14: =M13+K14-L14 -> 2258.6
A15: 12 | B15: 45942 | G15: =E15*F15 -> 0 | H15: 0 | I15: 0 | J15: =H15*I15 -> 0 | K15: =G15+J15 -> 0 | L15: 0 | M15: =M14+K15-L15 -> 2258.6
A16: 13 | B16: 45943 | G16: =E16*F16 -> 0 | H16: 0 | I16: 0 | J16: =H16*I16 -> 0 | K16: =G16+J16 -> 0 | L16: 0 | M16: =M15+K16-L16 -> 2258.6 | X16: =100*104 -> 10400
A17: 14 | B17: 45944 | G17: =E17*F17 -> 0 | H17: 0 | I17: 0 | J17: =H17*I17 -> 0 | K17: =G17+J17 -> 0 | L17: 0 | M17: =M16+K17-L17 -> 2258.6
A18: 15 | B18: 45945 | G18: =E18*F18 -> 0 | H18: 0 | I18: 0 | J18: =H18*I18 -> 0 | K18: =G18+J18 -> 0 | M18: =M17+K18-L18 -> 2258.6
A19: 16 | B19: 45946 | G19: =E19*F19 -> 0 | H19: 0 | I19: 0 | J19: =H19*I19 -> 0 | K19: =G19+J19 -> 0 | M19: =M18+K19-L19 -> 2258.6
A20: 17 | B20: 45947 | G20: =E20*F20 -> 0 | H20: 0 | I20: 0 | J20: =H20*I20 -> 0 | K20: =G20+J20 -> 0 | M20: =M19+K20-L20 -> 2258.6
A21: 18 | B21: 45948 | G21: =E21*F21 -> 0 | H21: 0 | I21: 0 | J21: =H21*I21 -> 0 | K21: =G21+J21 -> 0 | M21: =M20+K21-L21 -> 2258.6
A22: 19 | B22: 45949 | G22: =E22*F22 -> 0 | H22: 0 | I22: 0 | J22: =H22*I22 -> 0 | K22: =G22+J22 -> 0 | M22: =M21+K22-L22 -> 2258.6
A23: 20 | B23: 45950 | G23: =E23*F23 -> 0 | H23: 0 | I23: 0 | J23: =H23*I23 -> 0 | K23: =G23+J23 -> 0 | M23: =M22+K23-L23 -> 2258.6
A24: 21 | B24: 45951 | G24: =E24*F24 -> 0 | H24: 0 | I24: 0 | J24: =H24*I24 -> 0 | K24: =G24+J24 -> 0 | M24: =M23+K24-L24 -> 2258.6
A25: 22 | B25: 45952 | G25: =E25*F25 -> 0 | H25: 0 | I25: 0 | J25: =H25*I25 -> 0 | K25: =G25+J25 -> 0 | M25: =M24+K25-L25 -> 2258.6
A26: 23 | B26: 45953 | G26: =E26*F26 -> 0 | H26: 0 | I26: 0 | J26: =H26*I26 -> 0 | K26: =G26+J26 -> 0 | M26: =M25+K26-L26 -> 2258.6
A27: 24 | B27: 45954 | G27: =E27*F27 -> 0 | H27: 0 | I27: 0 | J27: =H27*I27 -> 0 | K27: =G27+J27 -> 0 | M27: =M26+K27-L27 -> 2258.6
A28: 25 | B28: 45955 | G28: =E28*F28 -> 0 | H28: 0 | I28: 0 | J28: =H28*I28 -> 0 | K28: =G28+J28 -> 0 | M28: =M27+K28-L28 -> 2258.6
A29: 26 | B29: 45956 | G29: =E29*F29 -> 0 | H29: 0 | I29: 0 | J29: =H29*I29 -> 0 | K29: =G29+J29 -> 0 | M29: =M28+K29-L29 -> 2258.6
... A33: 30 | B33: 45960 | G33: =E33*F33 -> 0 | H33: 0 | I33: 0 | J33: =H33*I33 -> 0 | K33: =G33+J33 -> 0 | M33: =M32+K33-L33 -> 2258.6
A34: 31 | G34: =E34*F34 -> 0 | H34: 0 | I34: 0 | J34: =H34*I34 -> 0 | K34: =G34+J34 -> 0 | L34: 0 | M34: =M33+K34-L34 -> 2258.6
E35: =SUM(E4:E34) -> 0 | G35: =SUM(G4:G34) -> 0 | H35: =SUM(H4:H34) -> 0 | J35: =SUM(J4:J34) -> 0 | K35: =SUM(K4:K34) -> 0 | L35: =SUM(L4:L34) -> 0

Sheet Hosadurga -2
A1: Shree Veeraprathap Fuel
A2: S.No | B2: Date | C2: GRN No | D2: Ind No/Bill No | E2: Diesel (Lts) | F2: Price | G2: Amount | H2: Petrol (Lts) | I2: Price | J2: Amount | K2: Total amount | L2: Amount paid | M2: As on Date | N2: Remarks
A3: Opening Balance | K3: 277709.09 | M3: =+K3 -> 277709.09 | O3: 618231.25
A4: 1 | B4: 45931 | C4: 0 | G4: =E4*F4 -> 0 | J4: =H4*I4 -> 0 | K4: =G4+J4 -> 0 | M4: =M3+K4-L4 -> 277709.09
A5: 2 | B5: 45932 | C5: 0 | G5: =E5*F5 -> 0 | J5: =H5*I5 -> 0 | K5: =G5+J5 -> 0 | M5: =M4+K5-L5 -> 277709.09
A6: 3 | B6: 45933 | C6: 0 | G6: =E6*F6 -> 0 | J6: =H6*I6 -> 0 | K6: =G6+J6 -> 0 | M6: =M5+K6-L6 -> 277709.09
A7: 4 | B7: 45934 | C7: 0 | D7: 1 | E7: 1800 | F7: 91.52 | G7: =E7*F7 -> 164736 | H7: 70 | I7: 103.67 | J7: =H7*I7 -> 7256.9 | K7: =G7+J7 -> 171992.9 | M7: =M6+K7-L7 -> 449701.99
A8: 5 | B8: 45935 | C8: 0 | G8: =E8*F8 -> 0 | J8: =H8*I8 -> 0 | K8: =G8+J8 -> 0 | M8: =M7+K8-L8 -> 449701.99
A9: 6 | B9: 45936 | C9: 0 | G9: =E9*F9 -> 0 | J9: =H9*I9 -> 0 | K9: =G9+J9 -> 0 | M9: =M8+K9-L9 -> 449701.99
A10: 7 | B10: 45937 | C10: 0 | G10: =E10*F10 -> 0 | J10: =H10*I10 -> 0 | K10: =G10+J10 -> 0 | M10: =M9+K10-L10 -> 449701.99
A11: 8 | B11: 45938 | C11: 0 | G11: =E11*F11 -> 0 | J11: =H11*I11 -> 0 | K11: =G11+J11 -> 0 | L11: 100000 | M11: =M10+K11-L11 -> 349701.99
A12: 9 | B12: 45939 | C12: 0 | G12: =E12*F12 -> 0 | J12: =H12*I12 -> 0 | K12: =G12+J12 -> 0 | M12: =M11+K12-L12 -> 349701.99
A13: 10 | B13: 45940 | C13: 0 | G13: =E13*F13 -> 0 | J13: =H13*I13 -> 0 | K13: =G13+J13 -> 0 | M13: =M12+K13-L13 -> 349701.99
A14: 11 | B14: 45941 | C14: 0 | D14: 2 | E14: 2000 | F14: 91.52 | G14: =E14*F14 -> 183040 | H14: 70 | I14: 103.67 | J14: =H14*I14 -> 7256.9 | K14: =G14+J14 -> 190296.9 | M14: =M13+K14-L14 -> 539998.89 | O14: 2 | P14: Bill No
A15: 12 | B15: 45942 | C15: 0 | G15: =E15*F15 -> 0 | J15: =H15*I15 -> 0 | K15: =G15+J15 -> 0 | M15: =M14+K15-L15 -> 539998.89
A16: 13 | B16: 45943 | C16: 0 | G16: =E16*F16 -> 0 | J16: =H16*I16 -> 0 | K16: =G16+J16 -> 0 | L16: 100000 | M16: =M15+K16-L16 -> 439998.89
A17: 14 | B17: 45944 | C17: 0 | G17: =E17*F17 -> 0 | J17: =H17*I17 -> 0 | K17: =G17+J17 -> 0 | M17: =M16+K17-L17 -> 439998.89
A18: 15 | B18: 45945 | C18: 0 | G18: =E18*F18 -> 0 | J18: =H18*I18 -> 0 | K18: =G18+J18 -> 0 | M18: =M17+K18-L18 -> 439998.89
A19: 16 | B19: 45946 | C19: 0 | G19: =E19*F19 -> 0 | J19: =H19*I19 -> 0 | K19: =G19+J19 -> 0 | L19: 100000 | M19: =M18+K19-L19 -> 339998.89
A20: 17 | B20: 45947 | C20: 0 | D20: 3 | G20: =E20*F20 -> 0 | H20: 100 | I20: 103.67 | J20: =H20*I20 -> 10367 | K20: =G20+J20 -> 10367 | M20: =M19+K20-L20 -> 350365.89 | O20: 3 | P20: Bill No
A21: 18 | B21: 45948 | C21: 0 | E21: 1800 | F21: 91.52 | G21: =E21*F21 -> 164736 | J21: =H21*I21 -> 0 | K21: =G21+J21 -> 164736 | M21: =M20+K21-L21 -> 515101.89
A22: 19 | B22: 45949 | C22: 0 | G22: =E22*F22 -> 0 | J22: =H22*I22 -> 0 | K22: =G22+J22 -> 0 | M22: =M21+K22-L22 -> 515101.89
A23: 20 | B23: 45950 | C23: 0 | G23: =E23*F23 -> 0 | J23: =H23*I23 -> 0 | K23: =G23+J23 -> 0 | M23: =M22+K23-L23 -> 515101.89
A24: 21 | B24: 45951 | C24: 0 | G24: =E24*F24 -> 0 | J24: =H24*I24 -> 0 | K24: =G24+J24 -> 0 | M24: =M23+K24-L24 -> 515101.89
A25: 22 | B25: 45952 | C25: 0 | G25: =E25*F25 -> 0 | J25: =H25*I25 -> 0 | K25: =G25+J25 -> 0 | M25: =M24+K25-L25 -> 515101.89
A26: 23 | B26: 45953 | C26: 0 | G26: =E26*F26 -> 0 | J26: =H26*I26 -> 0 | K26: =G26+J26 -> 0 | M26: =M25+K26-L26 -> 515101.89
A27: 24 | B27: 45954 | C27: 0 | G27: =E27*F27 -> 0 | J27: =H27*I27 -> 0 | K27: =G27+J27 -> 0 | M27: =M26+K27-L27 -> 515101.89
A28: 25 | B28: 45955 | C28: 0 | G28: =E28*F28 -> 0 | J28: =H28*I28 -> 0 | K28: =G28+J28 -> 0 | M28: =M27+K28-L28 -> 515101.89
A29: 26 | B29: 45956 | C29: 0 | G29: =E29*F29 -> 0 | J29: =H29*I29 -> 0 | K29: =G29+J29 -> 0 | M29: =M28+K29-L29 -> 515101.89
A30: 27 | B30: 45957 | C30: 0 | G30: =E30*F30 -> 0 | J30: =H30*I30 -> 0 | K30: =G30+J30 -> 0 | M30: =M29+K30-L30 -> 515101.89
A31: 28 | B31: 45958 | C31: 0 | G31: =E31*F31 -> 0 | J31: =H31*I31 -> 0 | K31: =G31+J31 -> 0 | M31: =M30+K31-L31 -> 515101.89
A32: 29 | B32: 45959 | C32: 0 | E32: 1500 | F32: 91.52 | G32: =E32*F32 -> 137280 | H32: 70 | I32: 103.67 | J32: =H32*I32 -> 7256.9 | K32: =G32+J32 -> 144536.9 | M32: =M31+K32-L32 -> 659638.79
A33: 30 | B33: 45960 | C33: 0 | G33: =E33*F33 -> 0 | J33: =H33*I33 -> 0 | K33: =G33+J33 -> 0 | L33: 200000 | M33: =M32+K33-L33 -> 459638.79
A34: 31 | B34: 45961
E35: =SUM(E4:E34) -> 7100 | G35: =SUM(G4:G34) -> 649792 | H35: =SUM(H4:H34) -> 310 | J35: =SUM(J4:J34) -> 32137.7 | K35: =SUM(K4:K34) -> 681929.7 | L35: =SUM(L4:L34) -> 500000

Sheet YG Gudda 
A1: Pallavi Petrolium
A2: S.No | B2: Date | C2: GRN No | D2: Ind No/Bill No | E2: Diesel (Lts) | F2: Price | G2: Amount | H2: Petrol (Lts) | I2: Price | J2: Amount | K2: Total amount | L2: Amount paid | M2: As on Date | N2: Remarks
A3: Opening Balance | K3: 109814.66 | M3: =+K3 -> 109814.66
A4: 1 | B4: 45931 | G4: =E4*F4 -> 0 | J4: =H4*I4 -> 0 | K4: =G4+J4 -> 0 | M4: =M3+K4-L4 -> 109814.66
A5: 2 | B5: 45932 | G5: =E5*F5 -> 0 | J5: =H5*I5 -> 0 | K5: =G5+J5 -> 0 | M5: =M4+K5-L5 -> 109814.66
A6: 3 | B6: 45933 | G6: =E6*F6 -> 0 | J6: =H6*I6 -> 0 | K6: =G6+J6 -> 0 | M6: =M5+K6-L6 -> 109814.66
A7: 4 | B7: 45934 | G7: =E7*F7 -> 0 | J7: =H7*I7 -> 0 | K7: =G7+J7 -> 0 | M7: =M6+K7-L7 -> 109814.66
A8: 5 | B8: 45935 | G8: =E8*F8 -> 0 | J8: =H8*I8 -> 0 | K8: =G8+J8 -> 0 | M8: =M7+K8-L8 -> 109814.66
A9: 6 | B9: 45936 | G9: =E9*F9 -> 0 | J9: =H9*I9 -> 0 | K9: =G9+J9 -> 0 | M9: =M8+K9-L9 -> 109814.66
A10: 7 | B10: 45937 | G10: =E10*F10 -> 0 | J10: =H10*I10 -> 0 | K10: =G10+J10 -> 0 | L10: 80000 | M10: =M9+K10-L10 -> 29814.665
A11: 8 | B11: 45938 | G11: =E11*F11 -> 0 | H11: 105 | I11: 103.24 | J11: =H11*I11 -> 10840.2 | K11: =G11+J11 -> 10840.2 | M11: =M10+K11-L11 -> 40654.865 | O11: 1 | P11: Bill No
A12: 9 | B12: 45939 | G12: =E12*F12 -> 0 | J12: =H12*I12 -> 0 | K12: =G12+J12 -> 0 | M12: =M11+K12-L12 -> 40654.865
A13: 10 | B13: 45940 | G13: =E13*F13 -> 0 | J13: =H13*I13 -> 0 | K13: =G13+J13 -> 0 | M13: =M12+K13-L13 -> 40654.865
A14: 11 | B14: 45941 | G14: =E14*F14 -> 0 | J14: =H14*I14 -> 0 | K14: =G14+J14 -> 0 | M14: =M13+K14-L14 -> 40654.865
A15: 12 | B15: 45942 | G15: =E15*F15 -> 0 | J15: =H15*I15 -> 0 | K15: =G15+J15 -> 0 | M15: =M14+K15-L15 -> 40654.865
A16: 13 | B16: 45943 | G16: =E16*F16 -> 0 | J16: =H16*I16 -> 0 | K16: =G16+J16 -> 0 | M16: =M15+K16-L16 -> 40654.865
A17: 14 | B17: 45944 | G17: =E17*F17 -> 0 | J17: =H17*I17 -> 0 | K17: =G17+J17 -> 0 | M17: =M16+K17-L17 -> 40654.865
A18: 15 | B18: 45945 | G18: =E18*F18 -> 0 | J18: =H18*I18 -> 0 | K18: =G18+J18 -> 0 | M18: =M17+K18-L18 -> 40654.865
A19: 16 | B19: 45946 | E19: 1000 | F19: 91.3 | G19: =E19*F19 -> 91300 | H19: 105 | I19: 103.24 | J19: =H19*I19 -> 10840.2 | K19: =G19+J19 -> 102140.2 | L19: 40000 | M19: =M18+K19-L19 -> 102795.06 | O19: 2 | P19: Bill No
A20: 17 | B20: 45947 | G20: =E20*F20 -> 0 | J20: =H20*I20 -> 0 | K20: =G20+J20 -> 0 | M20: =M19+K20-L20 -> 102795.06
A21: 18 | B21: 45948 | G21: =E21*F21 -> 0 | J21: =H21*I21 -> 0 | K21: =G21+J21 -> 0 | M21: =M20+K21-L21 -> 102795.06
A22: 19 | B22: 45949 | G22: =E22*F22 -> 0 | J22: =H22*I22 -> 0 | K22: =G22+J22 -> 0 | M22: =M21+K22-L22 -> 102795.06
A23: 20 | B23: 45950 | G23: =E23*F23 -> 0 | J23: =H23*I23 -> 0 | K23: =G23+J23 -> 0 | M23: =M22+K23-L23 -> 102795.06
A24: 21 | B24: 45951 | G24: =E24*F24 -> 0 | J24: =H24*I24 -> 0 | K24: =G24+J24 -> 0 | M24: =M23+K24-L24 -> 102795.06
A25: 22 | B25: 45952 | G25: =E25*F25 -> 0 | J25: =H25*I25 -> 0 | K25: =G25+J25 -> 0 | M25: =M24+K25-L25 -> 102795.06
A26: 23 | B26: 45953 | G26: =E26*F26 -> 0 | J26: =H26*I26 -> 0 | K26: =G26+J26 -> 0 | M26: =M25+K26-L26 -> 102795.06
A27: 24 | B27: 45954 | G27: =E27*F27 -> 0 | J27: =H27*I27 -> 0 | K27: =G27+J27 -> 0 | M27: =M26+K27-L27 -> 102795.06
A28: 25 | B28: 45955 | G28: =E28*F28 -> 0 | J28: =H28*I28 -> 0 | K28: =G28+J28 -> 0 | M28: =M27+K28-L28 -> 102795.06
A29: 26 | B29: 45956 | G29: =E29*F29 -> 0 | J29: =H29*I29 -> 0 | K29: =G29+J29 -> 0 | M29: =M28+K29-L29 -> 102795.06
A30: 27 | B30: 45957 | G30: =E30*F30 -> 0 | J30: =H30*I30 -> 0 | K30: =G30+J30 -> 0 | M30: =M29+K30-L30 -> 102795.06
A31: 28 | B31: 45958 | G31: =E31*F31 -> 0 | J31: =H31*I31 -> 0 | K31: =G31+J31 -> 0 | M31: =M30+K31-L31 -> 102795.06
... A34: 31 | B34: 45961 | G34: =E34*F34 -> 0 | J34: =H34*I34 -> 0 | K34: =G34+J34 -> 0 | M34: =M33+K34-L34 -> 102795.06
A35: 32 | E35: 0 | F35: 0 | G35: =E35*F35 -> 0 | J35: =H35*I35 -> 0 | K35: =G35+J35 -> 0 | M35: =M34+K35-L35 -> 102795.06
E36: =SUM(E4:E35) -> 1000 | G36: =SUM(G4:G35) -> 91300 | H36: =SUM(H4:H35) -> 210 | J36: =SUM(J4:J35) -> 21680.4 | K36: =SUM(K4:K35) -> 112980.4 | L36: =SUM(L4:L35) -> 120000

Sheet YG Gudda-2
A1: Pankaja HP Fuel Center
A2: S.No | B2: Date | C2: GRN No | D2: Ind No/Bill No | E2: Diesel (Lts) | F2: Price | G2: Amount | H2: Petrol (Lts) | I2: Price | J2: Amount | K2: Total amount | L2: Amount paid | M2: As on Date | N2: Remarks
A3: Opening Balance | K3: 306111 | M3: =+K3 -> 306111 | O3: 99992.615
A4: 1 | B4: 45931 | G4: =E4*F4 -> 0 | H4: 0 | I4: 0 | J4: =H4*I4 -> 0 | K4: =G4+J4 -> 0 | M4: =M3+K4-L4 -> 306111
A5: 2 | B5: 45932 | G5: =E5*F5 -> 0 | J5: =H5*I5 -> 0 | K5: =G5+J5 -> 0 | M5: =M4+K5-L5 -> 306111
A6: 3 | B6: 45933 | G6: =E6*F6 -> 0 | J6: =H6*I6 -> 0 | K6: =G6+J6 -> 0 | M6: =M5+K6-L6 -> 306111
A7: 4 | B7: 45934 | E7: 1500 | F7: 91.33 | G7: =E7*F7 -> 136995 | H7: 70 | I7: 103.27 | J7: =H7*I7 -> 7228.9 | K7: =G7+J7 -> 144223.9 | M7: =M6+K7-L7 -> 450334.9 | O7: 1 | P7: Bill No
A8: 5 | B8: 45935 | G8: =E8*F8 -> 0 | J8: =H8*I8 -> 0 | K8: =G8+J8 -> 0 | M8: =M7+K8-L8 -> 450334.9
A9: 6 | B9: 45936 | G9: =E9*F9 -> 0 | J9: =H9*I9 -> 0 | K9: =G9+J9 -> 0 | M9: =M8+K9-L9 -> 450334.9
A10: 7 | B10: 45937 | G10: =E10*F10 -> 0 | J10: =H10*I10 -> 0 | K10: =G10+J10 -> 0 | M10: =M9+K10-L10 -> 450334.9
A11: 8 | B11: 45938 | G11: =E11*F11 -> 0 | J11: =H11*I11 -> 0 | K11: =G11+J11 -> 0 | L11: 250000 | M11: =M10+K11-L11 -> 200334.9
A12: 9 | B12: 45939 | E12: 1500 | F12: 91.33 | G12: =E12*F12 -> 136995 | J12: =H12*I12 -> 0 | K12: =G12+J12 -> 136995 | M12: =M11+K12-L12 -> 337329.9 | O12: 2 | P12: Bill No
A13: 10 | B13: 45940 | G13: =E13*F13 -> 0 | J13: =H13*I13 -> 0 | K13: =G13+J13 -> 0 | M13: =M12+K13-L13 -> 337329.9
A14: 11 | B14: 45941 | G14: =E14*F14 -> 0 | J14: =H14*I14 -> 0 | K14: =G14+J14 -> 0 | M14: =M13+K14-L14 -> 337329.9
A15: 12 | B15: 45942 | G15: =E15*F15 -> 0 | J15: =H15*I15 -> 0 | K15: =G15+J15 -> 0 | M15: =M14+K15-L15 -> 337329.9
A16: 13 | B16: 45943 | E16: 1500 | F16: 91.33 | G16: =E16*F16 -> 136995 | H16: 70 | I16: 103.27 | J16: =H16*I16 -> 7228.9 | K16: =G16+J16 -> 144223.9 | M16: =M15+K16-L16 -> 481553.8 | O16: 3 | P16: Bill No
A17: 14 | B17: 45944 | G17: =E17*F17 -> 0 | J17: =H17*I17 -> 0 | K17: =G17+J17 -> 0 | M17: =M16+K17-L17 -> 481553.8
A18: 15 | B18: 45945 | G18: =E18*F18 -> 0 | J18: =H18*I18 -> 0 | K18: =G18+J18 -> 0 | L18: 300000 | M18: =M17+K18-L18 -> 181553.8
A19: 16 | B19: 45946 | G19: =E19*F19 -> 0 | J19: =H19*I19 -> 0 | K19: =G19+J19 -> 0 | M19: =M18+K19-L19 -> 181553.8
A20: 17 | B20: 45947 | G20: =E20*F20 -> 0 | J20: =H20*I20 -> 0 | K20: =G20+J20 -> 0 | M20: =M19+K20-L20 -> 181553.8
A21: 18 | B21: 45948 | G21: =E21*F21 -> 0 | J21: =H21*I21 -> 0 | K21: =G21+J21 -> 0 | M21: =M20+K21-L21 -> 181553.8
A22: 19 | B22: 45949 | G22: =E22*F22 -> 0 | J22: =H22*I22 -> 0 | K22: =G22+J22 -> 0 | M22: =M21+K22-L22 -> 181553.8
A23: 20 | B23: 45950 | G23: =E23*F23 -> 0 | J23: =H23*I23 -> 0 | K23: =G23+J23 -> 0 | M23: =M22+K23-L23 -> 181553.8
A24: 21 | B24: 45951 | E24: 600 | F24: 91.33 | G24: =E24*F24 -> 54798 | H24: 70 | I24: 103.27 | J24: =H24*I24 -> 7228.9 | K24: =G24+J24 -> 62026.9 | M24: =M23+K24-L24 -> 243580.7 | O24: 4 | P24: Bill No
A25: 22 | B25: 45952 | G25: =E25*F25 -> 0 | J25: =H25*I25 -> 0 | K25: =G25+J25 -> 0 | M25: =M24+K25-L25 -> 243580.7
A26: 23 | B26: 45953 | G26: =E26*F26 -> 0 | J26: =H26*I26 -> 0 | K26: =G26+J26 -> 0 | M26: =M25+K26-L26 -> 243580.7
A27: 24 | B27: 45954 | E27: 1500 | F27: 91.33 | G27: =E27*F27 -> 136995 | J27: =H27*I27 -> 0 | K27: =G27+J27 -> 136995 | M27: =M26+K27-L27 -> 380575.7
A28: 25 | B28: 45955 | G28: =E28*F28 -> 0 | J28: =H28*I28 -> 0 | K28: =G28+J28 -> 0 | M28: =M27+K28-L28 -> 380575.7
A29: 26 | B29: 45956 | G29: =E29*F29 -> 0 | J29: =H29*I29 -> 0 | K29: =G29+J29 -> 0 | M29: =M28+K29-L29 -> 380575.7
A30: 27 | B30: 45957 | E30: 1500 | F30: 91.33 | G30: =E30*F30 -> 136995 | H30: 70 | I30: 103.27 | J30: =H30*I30 -> 7228.9 | K30: =G30+J30 -> 144223.9 | M30: =M29+K30-L30 -> 524799.6
A31: 28 | B31: 45958 | G31: =E31*F31 -> 0 | J31: =H31*I31 -> 0 | K31: =G31+J31 -> 0 | M31: =M30+K31-L31 -> 524799.6
A32: 29 | B32: 45959 | G32: =E32*F32 -> 0 | J32: =H32*I32 -> 0 | K32: =G32+J32 -> 0 | M32: =M31+K32-L32 -> 524799.6
A33: 30 | B33: 45960 | G33: =E33*F33 -> 0 | J33: =H33*I33 -> 0 | K33: =G33+J33 -> 0 | L33: 200000 | M33: =M32+K33-L33 -> 324799.6
A34: 31 | B34: 45961 | G34: =E34*F34 -> 0 | J34: =H34*I34 -> 0 | K34: =G34+J34 -> 0 | M34: =M33+K34-L34 -> 324799.6
A35: 32 | G35: =E35*F35 -> 0 | H35: 0 | I35: 0 | J35: =H35*I35 -> 0 | K35: =G35+J35 -> 0 | M35: =M34+K35-L35 -> 324799.6
E36: =SUM(E4:E35) -> 8100 | G36: =SUM(G4:G35) -> 739773 | H36: =SUM(H4:H35) -> 280 | J36: =SUM(J4:J35) -> 28915.6 | K36: =SUM(K4:K35) -> 768688.6 | L36: =SUM(L4:L35) -> 750000

Sheet Hiriyur(VJNL)
A1: Sri Balaji Agencies
A2: S.No | B2: Date | C2: GRN No | D2: Ind No/Bill No | E2: Diesel (Lts) | F2: Price | G2: Amount | H2: Petrol (Lts) | I2: Price | J2: Amount | K2: Total amount | L2: Amount paid | M2: As on Date | N2: Remarks
A3: Opening Balance | K3: 74841.4 | M3: =+K3 -> 74841.4
A4: 1 | B4: 45931 | E4: 0 | G4: =E4*F4 -> 0 | J4: =H4*I4 -> 0 | K4: =G4+J4 -> 0 | M4: =M3+K4-L4 -> 74841.4
A5: 2 | B5: 45932 | E5: 0 | G5: =E5*F5 -> 0 | J5: =H5*I5 -> 0 | K5: =G5+J5 -> 0 | M5: =M4+K5-L5 -> 74841.4
A6: 3 | B6: 45933 | E6: 0 | G6: =E6*F6 -> 0 | J6: =H6*I6 -> 0 | K6: =G6+J6 -> 0 | M6: =M5+K6-L6 -> 74841.4
A7: 4 | B7: 45934 | E7: 2200 | F7: 92.23 | G7: =E7*F7 -> 202906 | H7: 70 | I7: 104.08 | J7: =H7*I7 -> 7285.6 | K7: =G7+J7 -> 210191.6 | M7: =M6+K7-L7 -> 285033
A8: 5 | B8: 45935 | E8: 0 | G8: =E8*F8 -> 0 | J8: =H8*I8 -> 0 | K8: =G8+J8 -> 0 | M8: =M7+K8-L8 -> 285033
A9: 6 | B9: 45936 | E9: 0 | G9: =E9*F9 -> 0 | J9: =H9*I9 -> 0 | K9: =G9+J9 -> 0 | M9: =M8+K9-L9 -> 285033
A10: 7 | B10: 45937 | E10: 0 | G10: =E10*F10 -> 0 | J10: =H10*I10 -> 0 | K10: =G10+J10 -> 0 | M10: =M9+K10-L10 -> 285033
A11: 8 | B11: 45938 | E11: 0 | G11: =E11*F11 -> 0 | J11: =H11*I11 -> 0 | K11: =G11+J11 -> 0 | M11: =M10+K11-L11 -> 285033
A12: 9 | B12: 45939 | E12: 0 | G12: =E12*F12 -> 0 | J12: =H12*I12 -> 0 | K12: =G12+J12 -> 0 | M12: =M11+K12-L12 -> 285033
A13: 10 | B13: 45940 | E13: 0 | G13: =E13*F13 -> 0 | J13: =H13*I13 -> 0 | K13: =G13+J13 -> 0 | L13: 100000 | M13: =M12+K13-L13 -> 185033
A14: 11 | B14: 45941 | E14: 0 | G14: =E14*F14 -> 0 | J14: =H14*I14 -> 0 | K14: =G14+J14 -> 0 | M14: =M13+K14-L14 -> 185033
A15: 12 | B15: 45942 | E15: 0 | G15: =E15*F15 -> 0 | H15: 70 | I15: 104.08 | J15: =H15*I15 -> 7285.6 | K15: =G15+J15 -> 7285.6 | M15: =M14+K15-L15 -> 192318.6
A16: 13 | B16: 45943 | E16: 0 | G16: =E16*F16 -> 0 | J16: =H16*I16 -> 0 | K16: =G16+J16 -> 0 | M16: =M15+K16-L16 -> 192318.6
A17: 14 | B17: 45944 | E17: 0 | G17: =E17*F17 -> 0 | H17: 0 | I17: 0 | J17: =H17*I17 -> 0 | K17: =G17+J17 -> 0 | M17: =M16+K17-L17 -> 192318.6
A18: 15 | B18: 45945 | E18: 0 | G18: =E18*F18 -> 0 | H18: 0 | I18: 0 | J18: =H18*I18 -> 0 | K18: =G18+J18 -> 0 | L18: 192000 | M18: =M17+K18-L18 -> 318.6
A19: 16 | B19: 45946 | E19: 0 | F19: 0 | G19: =E19*F19 -> 0 | H19: 0 | I19: 0 | J19: =H19*I19 -> 0 | K19: =G19+J19 -> 0 | M19: =M18+K19-L19 -> 318.6
A20: 17 | B20: 45947 | E20: 2200 | F20: 92.23 | G20: =E20*F20 -> 202906 | H20: 70 | I20: 104.08 | J20: =H20*I20 -> 7285.6 | K20: =G20+J20 -> 210191.6 | M20: =M19+K20-L20 -> 210510.2
A21: 18 | B21: 45948 | E21: 0 | G21: =E21*F21 -> 0 | H21: 0 | I21: 0 | J21: =H21*I21 -> 0 | K21: =G21+J21 -> 0 | M21: =M20+K21-L21 -> 210510.2
A22: 19 | B22: 45949 | E22: 0 | G22: =E22*F22 -> 0 | H22: 0 | I22: 0 | J22: =H22*I22 -> 0 | K22: =G22+J22 -> 0 | M22: =M21+K22-L22 -> 210510.2
A23: 20 | B23: 45950 | E23: 0 | G23: =E23*F23 -> 0 | H23: 0 | I23: 0 | J23: =H23*I23 -> 0 | K23: =G23+J23 -> 0 | M23: =M22+K23-L23 -> 210510.2
A24: 21 | B24: 45951 | E24: 0 | G24: =E24*F24 -> 0 | H24: 0 | I24: 0 | J24: =H24*I24 -> 0 | K24: =G24+J24 -> 0 | M24: =M23+K24-L24 -> 210510.2
A25: 22 | B25: 45952 | E25: 0 | G25: =E25*F25 -> 0 | H25: 0 | I25: 0 | J25: =H25*I25 -> 0 | K25: =G25+J25 -> 0 | M25: =M24+K25-L25 -> 210510.2
A26: 23 | B26: 45953 | E26: 0 | G26: =E26*F26 -> 0 | H26: 0 | I26: 0 | J26: =H26*I26 -> 0 | K26: =G26+J26 -> 0 | M26: =M25+K26-L26 -> 210510.2
A27: 24 | B27: 45954 | E27: 0 | G27: =E27*F27 -> 0 | H27: 0 | I27: 0 | J27: =H27*I27 -> 0 | K27: =G27+J27 -> 0 | M27: =M26+K27-L27 -> 210510.2
A28: 25 | B28: 45955 | E28: 0 | G28: =E28*F28 -> 0 | H28: 0 | I28: 0 | J28: =H28*I28 -> 0 | K28: =G28+J28 -> 0 | M28: =M27+K28-L28 -> 210510.2
A29: 26 | B29: 45956 | E29: 0 | G29: =E29*F29 -> 0 | H29: 0 | I29: 0 | J29: =H29*I29 -> 0 | K29: =G29+J29 -> 0 | M29: =M28+K29-L29 -> 210510.2
A30: 27 | B30: 45957 | E30: 0 | G30: =E30*F30 -> 0 | H30: 70 | I30: 104.08 | J30: =H30*I30 -> 7285.6 | K30: =G30+J30 -> 7285.6 | M30: =M29+K30-L30 -> 217795.8
A31: 28 | B31: 45958 | E31: 0 | G31: =E31*F31 -> 0 | H31: 0 | I31: 0 | J31: =H31*I31 -> 0 | K31: =G31+J31 -> 0 | M31: =M30+K31-L31 -> 217795.8
A32: 29 | B32: 45959 | E32: 0 | G32: =E32*F32 -> 0 | H32: 0 | I32: 0 | J32: =H32*I32 -> 0 | K32: =G32+J32 -> 0 | M32: =M31+K32-L32 -> 217795.8
A33: 30 | B33: 45960 | E33: 0 | G33: =E33*F33 -> 0 | H33: 0 | I33: 0 | J33: =H33*I33 -> 0 | K33: =G33+J33 -> 0 | L33: 117797 | M33: =M32+K33-L33 -> 99998.8
A34: 31 | B34: 45961 | E34: 2400 | F34: 92.23 | G34: =E34*F34 -> 221352 | H34: 0 | I34: 0 | J34: =H34*I34 -> 0 | K34: =G34+J34 -> 221352 | M34: =M33+K34-L34 -> 321350.8
E35: =SUM(E4:E34) -> 6800 | G35: =SUM(G4:G34) -> 627164 | H35: =SUM(H4:H34) -> 280 | J35: =SUM(J4:J34) -> 29142.4 | K35: =SUM(K4:K34) -> 656306.4 | L35: =SUM(L4:L34) -> 409797

Sheet Chellakere (KUWSDB)
A1: Sri Vishnu Baba Petroleum
A2: S.No | B2: Date | C2: GRN No | D2: Ind No/Bill No | E2: Diesel (Lts) | F2: Price | G2: Amount | H2: Petrol (Lts) | I2: Price | J2: Amount | K2: Total amount | L2: Amount paid | M2: As on Date | N2: Remarks
A3: Opening Balance | K3: 0 | L3: 0 | M3: =+K3 -> 0
A4: 1 | B4: 45931 | E4: 0 | F4: 0 | G4: =E4*F4 -> 0 | H4: 0 | I4: 0 | J4: =H4*I4 -> 0 | K4: =G4+J4 -> 0 | L4: =K4 -> 0 | M4: =M3+K4-L4 -> 0
A5: 2 | B5: 45932 | E5: 0 | F5: 0 | G5: =E5*F5 -> 0 | H5: 0 | I5: 0 | J5: =H5*I5 -> 0 | K5: =G5+J5 -> 0 | L5: =K5 -> 0 | M5: =M4+K5-L5 -> 0
A6: 3 | B6: 45933 | E6: 430 | F6: 92.22 | G6: =E6*F6 -> 39654.6 | H6: 0 | I6: 0 | J6: =H6*I6 -> 0 | K6: =G6+J6 -> 39654.6 | L6: =K6 -> 39654.6 | M6: =M5+K6-L6 -> 0
A7: 4 | B7: 45934 | E7: 0 | F7: 0 | G7: =E7*F7 -> 0 | H7: 0 | I7: 0 | J7: =H7*I7 -> 0 | K7: =G7+J7 -> 0 | L7: =K7 -> 0 | M7: =M6+K7-L7 -> 0
A8: 5 | B8: 45935 | E8: 0 | F8: 0 | G8: =E8*F8 -> 0 | H8: 0 | I8: 0 | J8: =H8*I8 -> 0 | K8: =G8+J8 -> 0 | L8: =K8 -> 0 | M8: =M7+K8-L8 -> 0
A9: 6 | B9: 45936 | E9: 185 | F9: 92.19 | G9: =E9*F9 -> 17055.15 | H9: 25 | I9: 104.03 | J9: =H9*I9 -> 2600.75 | K9: =G9+J9 -> 19655.9 | L9: =K9 -> 19655.9 | M9: =M8+K9-L9 -> 0
A10: 7 | B10: 45937 | E10: 0 | F10: 0 | G10: =E10*F10 -> 0 | H10: 0 | I10: 0 | J10: =H10*I10 -> 0 | K10: =G10+J10 -> 0 | L10: =K10 -> 0 | M10: =M9+K10-L10 -> 0
A11: 8 | B11: 45938 | E11: 400 | F11: 92.22 | G11: =E11*F11 -> 36888 | H11: 25 | I11: 104.03 | J11: =H11*I11 -> 2600.75 | K11: =G11+J11 -> 39488.75 | L11: =K11 -> 39488.75 | M11: =M10+K11-L11 -> 0
A12: 9 | B12: 45939 | E12: 0 | F12: 0 | G12: =E12*F12 -> 0 | H12: 0 | I12: 0 | J12: =H12*I12 -> 0 | K12: =G12+J12 -> 0 | L12: =K12 -> 0 | M12: =M11+K12-L12 -> 0
A13: 10 | B13: 45940 | E13: 0 | F13: 0 | G13: =E13*F13 -> 0 | H13: 0 | I13: 0 | J13: =H13*I13 -> 0 | K13: =G13+J13 -> 0 | L13: =K13 -> 0 | M13: =M12+K13-L13 -> 0
A14: 11 | B14: 45941 | D14: Credit start | E14: 400 | F14: 92.19 | G14: =E14*F14 -> 36876 | H14: 0 | I14: 0 | J14: =H14*I14 -> 0 | K14: =G14+J14 -> 36876 | L14: 0 | M14: =M13+K14-L14 -> 36876
A15: 12 | B15: 45942 | E15: 0 | F15: 0 | G15: =E15*F15 -> 0 | H15: 0 | I15: 0 | J15: =H15*I15 -> 0 | K15: =G15+J15 -> 0 | L15: =K15 -> 0 | M15: =M14+K15-L15 -> 36876
A16: 13 | B16: 45943 | E16: 0 | F16: 0 | G16: =E16*F16 -> 0 | H16: 0 | I16: 0 | J16: =H16*I16 -> 0 | K16: =G16+J16 -> 0 | L16: =K16 -> 0 | M16: =M15+K16-L16 -> 36876
A17: 14 | B17: 45944 | E17: 500 | F17: 92.19 | G17: =E17*F17 -> 46095 | H17: 30 | I17: 104.03 | J17: =H17*I17 -> 3120.9 | K17: =G17+J17 -> 49215.9 | L17: 0 | M17: =M16+K17-L17 -> 86091.9
A18: 15 | B18: 45945 | E18: 0 | F18: 0 | G18: =E18*F18 -> 0 | H18: 0 | I18: 0 | J18: =H18*I18 -> 0 | K18: =G18+J18 -> 0 | L18: 86091.9 | M18: =M17+K18-L18 -> 0
A19: 16 | B19: 45946 | E19: 0 | F19: 0 | G19: =E19*F19 -> 0 | H19: 0 | I19: 0 | J19: =H19*I19 -> 0 | K19: =G19+J19 -> 0 | L19: =K19 -> 0 | M19: =M18+K19-L19 -> 0
A20: 17 | B20: 45947 | E20: 270 | F20: 92.19 | G20: =E20*F20 -> 24891.3 | H20: 0 | I20: 0 | J20: =H20*I20 -> 0 | K20: =G20+J20 -> 24891.3 | L20: 0 | M20: =M19+K20-L20 -> 24891.3
A21: 18 | B21: 45948 | E21: 0 | F21: 0 | G21: =E21*F21 -> 0 | H21: 0 | I21: 0 | J21: =H21*I21 -> 0 | K21: =G21+J21 -> 0 | L21: =K21 -> 0 | M21: =M20+K21-L21 -> 24891.3
A22: 19 | B22: 45949 | E22: 0 | F22: 0 | G22: =E22*F22 -> 0 | H22: 0 | I22: 0 | J22: =H22*I22 -> 0 | K22: =G22+J22 -> 0 | L22: =K22 -> 0 | M22: =M21+K22-L22 -> 24891.3
A23: 20 | B23: 45950 | E23: 0 | F23: 0 | G23: =E23*F23 -> 0 | H23: 0 | I23: 0 | J23: =H23*I23 -> 0 | K23: =G23+J23 -> 0 | L23: =K23 -> 0 | M23: =M22+K23-L23 -> 24891.3
A24: 21 | B24: 45951 | E24: 0 | F24: 0 | G24: =E24*F24 -> 0 | H24: 0 | I24: 0 | J24: =H24*I24 -> 0 | K24: =G24+J24 -> 0 | L24: =K24 -> 0 | M24: =M23+K24-L24 -> 24891.3
A25: 22 | B25: 45952 | E25: 0 | F25: 0 | G25: =E25*F25 -> 0 | H25: 0 | I25: 0 | J25: =H25*I25 -> 0 | K25: =G25+J25 -> 0 | L25: =K25 -> 0 | M25: =M24+K25-L25 -> 24891.3
A26: 23 | B26: 45953 | E26: 400 | F26: 92.19 | G26: =E26*F26 -> 36876 | H26: 35 | I26: 104.03 | J26: =H26*I26 -> 3641.05 | K26: =G26+J26 -> 40517.05 | L26: 0 | M26: =M25+K26-L26 -> 65408.35
A27: 24 | B27: 45954 | E27: 0 | F27: 0 | G27: =E27*F27 -> 0 | H27: 0 | I27: 0 | J27: =H27*I27 -> 0 | K27: =G27+J27 -> 0 | L27: =K27 -> 0 | M27: =M26+K27-L27 -> 65408.35
A28: 25 | B28: 45955 | E28: 0 | F28: 0 | G28: =E28*F28 -> 0 | H28: 0 | I28: 0 | J28: =H28*I28 -> 0 | K28: =G28+J28 -> 0 | L28: =K28 -> 0 | M28: =M27+K28-L28 -> 65408.35
A29: 26 | B29: 45956 | E29: 0 | F29: 0 | G29: =E29*F29 -> 0 | H29: 0 | I29: 0 | J29: =H29*I29 -> 0 | K29: =G29+J29 -> 0 | L29: =K29 -> 0 | M29: =M28+K29-L29 -> 65408.35
A30: 27 | B30: 45957 | E30: 470 | F30: 92.19 | G30: =E30*F30 -> 43329.3 | H30: 30 | I30: 104.03 | J30: =H30*I30 -> 3120.9 | K30: =G30+J30 -> 46450.2 | L30: 0 | M30: =M29+K30-L30 -> 111858.55
A31: 28 | B31: 45958 | E31: 0 | F31: 0 | G31: =E31*F31 -> 0 | H31: 0 | I31: 0 | J31: =H31*I31 -> 0 | K31: =G31+J31 -> 0 | L31: =K31 -> 0 | M31: =M30+K31-L31 -> 111858.55
A32: 29 | B32: 45959 | E32: 0 | F32: 0 | G32: =E32*F32 -> 0 | H32: 0 | I32: 0 | J32: =H32*I32 -> 0 | K32: =G32+J32 -> 0 | L32: =K32 -> 0 | M32: =M31+K32-L32 -> 111858.55
A33: 30 | B33: 45960 | E33: 0 | F33: 0 | G33: =E33*F33 -> 0 | H33: 0 | I33: 0 | J33: =H33*I33 -> 0 | K33: =G33+J33 -> 0 | L33: 111858.6 | M33: =M32+K33-L33 -> -0.05
A34: 31
E35: =SUM(E4:E34) -> 3055 | G35: =SUM(G4:G34) -> 281665.35 | H35: =SUM(H4:H34) -> 145 | J35: =SUM(J4:J34) -> 15084.35 | K35: =SUM(K4:K34) -> 296749.7 | L35: =SUM(L4:L34) -> 296749.75

Sheet Chellakere -2
A1: Shivaganga Service Station (BPCL)
A2: S.No | B2: Date | C2: GRN No | D2: Ind No/Bill No | E2: Diesel (Lts) | F2: Price | G2: Amount | H2: Petrol (Lts) | I2: Price | J2: Amount | K2: Total amount | L2: Amount paid | M2: As on Date | N2: Remarks
A3: Opening Balance | K3: 0 | L3: 0 | M3: =+K3 -> 0
A4: 1 | B4: 45931 | M4: =M3+K4-L4 -> 0
A5: 2 | B5: 45932 | M5: =M4+K5-L5 -> 0
A6: 3 | B6: 45933 | M6: =M5+K6-L6 -> 0
A7: 4 | B7: 45934 | M7: =M6+K7-L7 -> 0
A8: 5 | B8: 45935 | M8: =M7+K8-L8 -> 0
A9: 6 | B9: 45936 | M9: =M8+K9-L9 -> 0
A10: 7 | B10: 45937 | M10: =M9+K10-L10 -> 0
A11: 8 | B11: 45938 | M11: =M10+K11-L11 -> 0
A12: 9 | B12: 45939 | M12: =M11+K12-L12 -> 0
A13: 10 | B13: 45940 | M13: =M12+K13-L13 -> 0
A14: 11 | B14: 45941 | D14: Credit start | E14: 400 | F14: 92.19 | G14: =E14*F14 -> 36876 | H14: 0 | I14: 0 | J14: =H14*I14 -> 0 | K14: =G14+J14 -> 36876 | L14: 0 | M14: =M13+K14-L14 -> 36876
A15: 12 | B15: 45942 | E15: 0 | F15: 0 | G15: =E15*F15 -> 0 | H15: 0 | I15: 0 | J15: =H15*I15 -> 0 | K15: =G15+J15 -> 0 | L15: =K15 -> 0 | M15: =M14+K15-L15 -> 36876
A16: 13 | B16: 45943 | E16: 0 | F16: 0 | G16: =E16*F16 -> 0 | H16: 0 | I16: 0 | J16: =H16*I16 -> 0 | K16: =G16+J16 -> 0 | L16: =K16 -> 0 | M16: =M15+K16-L16 -> 36876
A17: 14 | B17: 45944 | E17: 500 | F17: 92.19 | G17: =E17*F17 -> 46095 | H17: 30 | I17: 104.03 | J17: =H17*I17 -> 3120.9 | K17: =G17+J17 -> 49215.9 | L17: 0 | M17: =M16+K17-L17 -> 86091.9
A18: 15 | B18: 45945 | E18: 0 | F18: 0 | G18: =E18*F18 -> 0 | H18: 0 | I18: 0 | J18: =H18*I18 -> 0 | K18: =G18+J18 -> 0 | L18: 86091.9 | M18: =M17+K18-L18 -> 0
A19: 16 | B19: 45946 | E19: 0 | F19: 0 | G19: =E19*F19 -> 0 | H19: 0 | I19: 0 | J19: =H19*I19 -> 0 | K19: =G19+J19 -> 0 | L19: =K19 -> 0 | M19: =M18+K19-L19 -> 0
A20: 17 | B20: 45947 | E20: 0 | F20: 0 | G20: =E20*F20 -> 0 | H20: 0 | I20: 0 | J20: =H20*I20 -> 0 | K20: =G20+J20 -> 0 | L20: =K20 -> 0 | M20: =M19+K20-L20 -> 0
A21: 18 | B21: 45948 | E21: 0 | F21: 0 | G21: =E21*F21 -> 0 | H21: 0 | I21: 0 | J21: =H21*I21 -> 0 | K21: =G21+J21 -> 0 | L21: =K21 -> 0 | M21: =M20+K21-L21 -> 0
A22: 19 | B22: 45949 | E22: 0 | F22: 0 | G22: =E22*F22 -> 0 | H22: 0 | I22: 0 | J22: =H22*I22 -> 0 | K22: =G22+J22 -> 0 | L22: =K22 -> 0 | M22: =M21+K22-L22 -> 0
A23: 20 | B23: 45950 | E23: 0 | F23: 0 | G23: =E23*F23 -> 0 | H23: 0 | I23: 0 | J23: =H23*I23 -> 0 | K23: =G23+J23 -> 0 | L23: =K23 -> 0 | M23: =M22+K23-L23 -> 0
A24: 21 | B24: 45951 | E24: 0 | F24: 0 | G24: =E24*F24 -> 0 | H24: 0 | I24: 0 | J24: =H24*I24 -> 0 | K24: =G24+J24 -> 0 | L24: =K24 -> 0 | M24: =M23+K24-L24 -> 0
A25: 22 | B25: 45952 | E25: 0 | F25: 0 | G25: =E25*F25 -> 0 | H25: 0 | I25: 0 | J25: =H25*I25 -> 0 | K25: =G25+J25 -> 0 | L25: =K25 -> 0 | M25: =M24+K25-L25 -> 0
A26: 23 | B26: 45953 | E26: 0 | F26: 0 | G26: =E26*F26 -> 0 | H26: 0 | I26: 0 | J26: =H26*I26 -> 0 | K26: =G26+J26 -> 0 | L26: =K26 -> 0 | M26: =M25+K26-L26 -> 0
A27: 24 | B27: 45954 | E27: 0 | F27: 0 | G27: =E27*F27 -> 0 | H27: 0 | I27: 0 | J27: =H27*I27 -> 0 | K27: =G27+J27 -> 0 | L27: =K27 -> 0 | M27: =M26+K27-L27 -> 0
A28: 25 | B28: 45955 | E28: 0 | F28: 0 | G28: =E28*F28 -> 0 | H28: 0 | I28: 0 | J28: =H28*I28 -> 0 | K28: =G28+J28 -> 0 | L28: =K28 -> 0 | M28: 0
A29: 26 | B29: 45956 | E29: 0 | F29: 0 | G29: =E29*F29 -> 0 | H29: 0 | I29: 0 | J29: =H29*I29 -> 0 | K29: =G29+J29 -> 0 | L29: =K29 -> 0 | M29: 0
A30: 27 | B30: 45957 | E30: 0 | F30: 0 | G30: =E30*F30 -> 0 | H30: 0 | I30: 0 | J30: =H30*I30 -> 0 | K30: =G30+J30 -> 0 | L30: =K30 -> 0 | M30: 0
A31: 28 | B31: 45958 | E31: 0 | F31: 0 | G31: =E31*F31 -> 0 | H31: 0 | I31: 0 | J31: =H31*I31 -> 0 | K31: =G31+J31 -> 0 | L31: =K31 -> 0 | M31: 0
A32: 29 | B32: 45959 | E32: 0 | F32: 0 | G32: =E32*F32 -> 0 | H32: 0 | I32: 0 | J32: =H32*I32 -> 0 | K32: =G32+J32 -> 0 | L32: =K32 -> 0
A33: 30 | B33: 45960 | E33: 0 | F33: 0 | G33: =E33*F33 -> 0 | H33: 0 | I33: 0 | J33: =H33*I33 -> 0 | K33: =G33+J33 -> 0 | L33: =K33 -> 0
A34: 31
E35: =SUM(E4:E34) -> 900 | G35: =SUM(G4:G34) -> 82971 | H35: =SUM(H4:H34) -> 30 | J35: =SUM(J4:J34) -> 3120.9 | K35: =SUM(K4:K34) -> 86091.9 | L35: =SUM(L4:L34) -> 86091.9

Sheet Malebenur(KUWSDB)
A1: Sree Veerabhadreshwara Service Station
A2: S.No | B2: Date | C2: GRN No | D2: Ind No/Bill No | E2: Diesel (Lts) | F2: Price | G2: Amount | H2: Petrol (Lts) | I2: Price | J2: Amount | K2: Total amount | L2: Amount paid | M2: As on Date | N2: Remarks
A3: Opening Balance | K3: 2634.8284 | M3: =+K3 -> 2634.8284 | O3: 46138.764
A4: 1 | B4: 45931 | E4: 0 | F4: 0 | G4: =E4*F4 -> 0 | H4: 0 | J4: =H4*I4 -> 0 | K4: =G4+J4 -> 0 | L4: 0 | M4: =M3+K4-L4 -> 2634.8284
A5: 2 | B5: 45932 | E5: 0 | F5: 0 | G5: =E5*F5 -> 0 | H5: 0 | J5: =H5*I5 -> 0 | K5: =G5+J5 -> 0 | L5: 0 | M5: =M4+K5-L5 -> 2634.8284
A6: 3 | B6: 45933 | E6: 400.27 | F6: 92.14 | G6: =E6*F6 -> 36880.878 | H6: 30 | I6: 103.97 | J6: =H6*I6 -> 3119.1 | K6: =G6+J6 -> 39999.978 | L6: 39999.98 | M6: =M5+K6-L6 -> 2634.8262
A7: 4 | B7: 45934 | E7: 0 | F7: 0 | G7: =E7*F7 -> 0 | H7: 0 | J7: =H7*I7 -> 0 | K7: =G7+J7 -> 0 | L7: 0 | M7: =M6+K7-L7 -> 2634.8262
A8: 5 | B8: 45935 | E8: 0 | F8: 0 | G8: =E8*F8 -> 0 | H8: 0 | J8: =H8*I8 -> 0 | K8: =G8+J8 -> 0 | L8: 0 | M8: =M7+K8-L8 -> 2634.8262
A9: 6 | B9: 45936 | E9: 0 | F9: 0 | G9: =E9*F9 -> 0 | H9: 0 | J9: =H9*I9 -> 0 | K9: =G9+J9 -> 0 | L9: 0 | M9: =M8+K9-L9 -> 2634.8262
A10: 7 | B10: 45937 | E10: 0 | F10: 0 | G10: =E10*F10 -> 0 | H10: 0 | J10: =H10*I10 -> 0 | K10: =G10+J10 -> 0 | L10: 0 | M10: =M9+K10-L10 -> 2634.8262
A11: 8 | B11: 45938 | E11: 243.11 | F11: 92.14 | G11: =E11*F11 -> 22400.155 | H11: 25.01 | I11: 103.97 | J11: =H11*I11 -> 2600.2897 | K11: =G11+J11 -> 25000.445 | L11: 25000.45 | M11: =M10+K11-L11 -> 2634.8213
A12: 9 | B12: 45939 | E12: 0 | F12: 0 | G12: =E12*F12 -> 0 | H12: 0 | J12: =H12*I12 -> 0 | K12: =G12+J12 -> 0 | L12: 0 | M12: =M11+K12-L12 -> 2634.8213
A13: 10 | B13: 45940 | E13: 216.87 | F13: 92.22 | G13: =E13*F13 -> 19999.751 | H13: 0 | J13: =H13*I13 -> 0 | K13: =G13+J13 -> 19999.751 | L13: 19999.75 | M13: =M12+K13-L13 -> 2634.8227
A14: 11 | B14: 45941 | E14: 434.12 | F14: 92.14 | G14: =E14*F14 -> 39999.817 | H14: 0 | J14: =H14*I14 -> 0 | K14: =G14+J14 -> 39999.817 | L14: =H14+K14 -> 39999.817 | M14: =M13+K14-L14 -> 2634.8227
A15: 12 | B15: 45942 | E15: 0 | F15: 0 | G15: =E15*F15 -> 0 | H15: 0 | J15: =H15*I15 -> 0 | K15: =G15+J15 -> 0 | L15: 0 | M15: =M14+K15-L15 -> 2634.8227
A16: 13 | B16: 45943 | E16: 400.27 | F16: 92.14 | G16: =E16*F16 -> 36880.878 | H16: 30 | I16: 103.97 | J16: =H16*I16 -> 3119.1 | K16: =G16+J16 -> 39999.978 | L16: 39999.98 | M16: =M15+K16-L16 -> 2634.8205
A17: 14 | B17: 45944 | E17: 433.98 | F17: 92.17 | G17: =E17*F17 -> 39999.937 | H17: 0 | J17: =H17*I17 -> 0 | K17: =G17+J17 -> 39999.937 | L17: =H17+K17 -> 39999.937 | M17: =M16+K17-L17 -> 2634.8205 | Q17: 2767.8 | S17: =Q17-M18 -> 132.9795
A18: 15 | B18: 45945 | E18: 0 | F18: 0 | G18: =E18*F18 -> 0 | H18: 0 | J18: =H18*I18 -> 0 | K18: =G18+J18 -> 0 | L18: 0 | M18: =M17+K18-L18 -> 2634.8205
A19: 16 | B19: 45946 | E19: 400 | F19: 92.14 | G19: =E19*F19 -> 36856 | H19: 25 | I19: 103.97 | J19: =H19*I19 -> 2599.25 | K19: =G19+J19 -> 39455.25 | L19: 0 | M19: =M18+K19-L19 -> 42090.07
A20: 17 | B20: 45947 | E20: 0 | F20: 0 | G20: =E20*F20 -> 0 | H20: 0 | J20: =H20*I20 -> 0 | K20: =G20+J20 -> 0 | L20: 0 | M20: =M19+K20-L20 -> 42090.07 | V20: =400*90.23 -> 36092
A21: 18 | B21: 45948 | E21: 0 | F21: 0 | G21: =E21*F21 -> 0 | H21: 0 | J21: =H21*I21 -> 0 | K21: =G21+J21 -> 0 | L21: 0 | M21: =M20+K21-L21 -> 42090.07 | V21: =35*104.14 -> 3644.9
A22: 19 | B22: 45949 | E22: 0 | F22: 0 | G22: =E22*F22 -> 0 | H22: 0 | J22: =H22*I22 -> 0 | K22: =G22+J22 -> 0 | L22: 2634.82 | M22: =M21+K22-L22 -> 39455.25
A23: 20 | B23: 45950 | E23: 500 | F23: 92.14 | G23: =E23*F23 -> 46070 | H23: 0 | J23: =H23*I23 -> 0 | K23: =G23+J23 -> 46070 | L23: 0 | M23: =M22+K23-L23 -> 85525.25
A24: 21 | B24: 45951 | E24: 0 | F24: 0 | G24: =E24*F24 -> 0 | H24: 0 | J24: =H24*I24 -> 0 | K24: =G24+J24 -> 0 | L24: 0 | M24: =M23+K24-L24 -> 85525.25
A25: 22 | B25: 45952 | E25: 0 | F25: 0 | G25: =E25*F25 -> 0 | H25: 0 | J25: =H25*I25 -> 0 | K25: =G25+J25 -> 0 | L25: 0 | M25: =M24+K25-L25 -> 85525.25
A26: 23 | B26: 45953 | E26: 0 | F26: 0 | G26: =E26*F26 -> 0 | H26: 0 | J26: =H26*I26 -> 0 | K26: =G26+J26 -> 0 | L26: 0 | M26: =M25+K26-L26 -> 85525.25
A27: 24 | B27: 45954 | E27: 500 | F27: 92.14 | G27: =E27*F27 -> 46070 | H27: 34.85 | I27: 103.97 | J27: =H27*I27 -> 3623.3545 | K27: =G27+J27 -> 49693.355 | L27: 0 | M27: =M26+K27-L27 -> 135218.6
A28: 25 | B28: 45955 | E28: 0 | F28: 0 | G28: =E28*F28 -> 0 | H28: 0 | J28: =H28*I28 -> 0 | K28: =G28+J28 -> 0 | L28: 0 | M28: =M27+K28-L28 -> 135218.6
A29: 26 | B29: 45956 | E29: 0 | F29: 0 | G29: =E29*F29 -> 0 | H29: 0 | J29: =H29*I29 -> 0 | K29: =G29+J29 -> 0 | L29: 0 | M29: =M28+K29-L29 -> 135218.6
A30: 27 | B30: 45957 | E30: 0 | F30: 0 | G30: =E30*F30 -> 0 | H30: 0 | J30: =H30*I30 -> 0 | K30: =G30+J30 -> 0 | L30: 135218.6 | M30: =M29+K30-L30 -> 0.005 | P30: 29774.14
A31: 28 | B31: 45958 | E31: 0 | F31: 0 | G31: =E31*F31 -> 0 | H31: 0 | J31: =H31*I31 -> 0 | K31: =G31+J31 -> 0 | L31: 0 | M31: =M30+K31-L31 -> 0.005 | P31: 50000
A32: 29 | B32: 45959 | E32: 0 | F32: 0 | G32: =E32*F32 -> 0 | H32: 0 | J32: =H32*I32 -> 0 | K32: =G32+J32 -> 0 | L32: 0 | M32: =M31+K32-L32 -> 0.005 | P32: =SUM(P30:P31) -> 79774.14
A33: 30 | B33: 45960 | E33: 400 | F33: 92.14 | G33: =E33*F33 -> 36856 | H33: 20 | I33: 103.97 | J33: =H33*I33 -> 2079.4 | K33: =G33+J33 -> 38935.4 | L33: 0 | M33: =M32+K33-L33 -> 38935.405
A34: 31 | E34: 0 | F34: 0 | G34: =E34*F34 -> 0 | H34: 0 | J34: =H34*I34 -> 0 | K34: =G34+J34 -> 0 | L34: 0 | M34: =M33+K34-L34 -> 38935.405
E35: 0 | F35: 0 | G35: =E35*F35 -> 0 | H35: 0 | J35: =H35*I35 -> 0 | K35: =G35+J35 -> 0 | L35: 0 | M35: =M34+K35-L35 -> 38935.405
E36: =SUM(E4:E34) -> 3928.62 | G36: =SUM(G4:G34) -> 362013.42 | H36: =SUM(H4:H34) -> 164.86 | J36: =SUM(J4:J34) -> 17140.494 | K36: =SUM(K4:K34) -> 379153.91 | L36: =SUM(L4:L34) -> 342853.33
E37: 0 | G37: 0 | H37: 0 | J37: 0 | K37: =G37+J37 -> 0 | L37: 0
S42: 9052944708

Sheet Molakamuru
A1: Molakamuru
A2: S.No | B2: Date | C2: GRN No | D2: Ind No/Bill No | E2: Diesel (Lts) | F2: Price | G2: Amount | H2: Petrol (Lts) | I2: Price | J2: Amount | K2: Total amount | L2: Amount paid | M2: As on Date | N2: Remarks
A3: Opening Balance | K3: 0 | L3: 0 | M3: =+K3 -> 0
A4: 1 | B4: 45931 | G4: =E4*F4 -> 0 | J4: =H4*I4 -> 0 | K4: =G4+J4 -> 0 | L4: =K4 -> 0 | M4: =M3+K4-L4 -> 0
A5: 2 | B5: 45932 | G5: =E5*F5 -> 0 | J5: =H5*I5 -> 0 | K5: =G5+J5 -> 0 | L5: =K5 -> 0 | M5: =M4+K5-L5 -> 0
A6: 3 | B6: 45933 | G6: =E6*F6 -> 0 | J6: =H6*I6 -> 0 | K6: =G6+J6 -> 0 | L6: =K6 -> 0 | M6: =M5+K6-L6 -> 0
A7: 4 | B7: 45934 | E7: 255 | F7: 92.22 | G7: =E7*F7 -> 23516.1 | H7: 10 | I7: 104.07 | J7: =H7*I7 -> 1040.7 | K7: =G7+J7 -> 24556.8 | L7: =K7 -> 24556.8 | M7: =M6+K7-L7 -> 0
A8: 5 | B8: 45935 | G8: =E8*F8 -> 0 | J8: =H8*I8 -> 0 | K8: =G8+J8 -> 0 | L8: =K8 -> 0 | M8: =M7+K8-L8 -> 0
A9: 6 | B9: 45936 | G9: =E9*F9 -> 0 | J9: =H9*I9 -> 0 | K9: =G9+J9 -> 0 | L9: =K9 -> 0 | M9: =M8+K9-L9 -> 0
A10: 7 | B10: 45937 | G10: =E10*F10 -> 0 | J10: =H10*I10 -> 0 | K10: =G10+J10 -> 0 | L10: =K10 -> 0 | M10: =M9+K10-L10 -> 0
A11: 8 | B11: 45938 | E11: 210 | F11: 92.22 | G11: =E11*F11 -> 19366.2 | J11: =H11*I11 -> 0 | K11: =G11+J11 -> 19366.2 | L11: =K11 -> 19366.2 | M11: =M10+K11-L11 -> 0
A12: 9 | B12: 45939 | G12: =E12*F12 -> 0 | J12: =H12*I12 -> 0 | K12: =G12+J12 -> 0 | L12: =K12 -> 0 | M12: =M11+K12-L12 -> 0
A13: 10 | B13: 45940 | G13: =E13*F13 -> 0 | J13: =H13*I13 -> 0 | K13: =G13+J13 -> 0 | L13: =K13 -> 0 | M13: =M12+K13-L13 -> 0
A14: 11 | B14: 45941 | G14: =E14*F14 -> 0 | J14: =H14*I14 -> 0 | K14: =G14+J14 -> 0 | L14: =K14 -> 0 | M14: =M13+K14-L14 -> 0
A15: 12 | B15: 45942 | G15: =E15*F15 -> 0 | J15: =H15*I15 -> 0 | K15: =G15+J15 -> 0 | L15: =K15 -> 0 | M15: =M14+K15-L15 -> 0
A16: 13 | B16: 45943 | E16: 245 | F16: 92.22 | G16: =E16*F16 -> 22593.9 | H16: 20 | I16: 104.07 | J16: =H16*I16 -> 2081.4 | K16: =G16+J16 -> 24675.3 | L16: =K16 -> 24675.3 | M16: =M15+K16-L16 -> 0
A17: 14 | B17: 45944 | G17: =E17*F17 -> 0 | J17: =H17*I17 -> 0 | K17: =G17+J17 -> 0 | L17: =K17 -> 0 | M17: =M16+K17-L17 -> 0
A18: 15 | B18: 45945 | G18: =E18*F18 -> 0 | J18: =H18*I18 -> 0 | K18: =G18+J18 -> 0 | L18: =K18 -> 0 | M18: =M17+K18-L18 -> 0
A19: 16 | B19: 45946 | G19: =E19*F19 -> 0 | J19: =H19*I19 -> 0 | K19: =G19+J19 -> 0 | L19: =K19 -> 0 | M19: =M18+K19-L19 -> 0
A20: 17 | B20: 45947 | G20: =E20*F20 -> 0 | J20: =H20*I20 -> 0 | K20: =G20+J20 -> 0 | L20: =K20 -> 0 | M20: =M19+K20-L20 -> 0
A21: 18 | B21: 45948 | E21: 270 | F21: 92.22 | G21: =E21*F21 -> 24899.4 | J21: =H21*I21 -> 0 | K21: =G21+J21 -> 24899.4 | L21: =K21 -> 24899.4 | M21: =M20+K21-L21 -> 0
A22: 19 | B22: 45949 | G22: =E22*F22 -> 0 | J22: =H22*I22 -> 0 | K22: =G22+J22 -> 0 | L22: =K22 -> 0 | M22: =M21+K22-L22 -> 0
A23: 20 | B23: 45950 | G23: =E23*F23 -> 0 | J23: =H23*I23 -> 0 | K23: =G23+J23 -> 0 | L23: =K23 -> 0 | M23: =M22+K23-L23 -> 0
A24: 21 | B24: 45951 | G24: =E24*F24 -> 0 | J24: =H24*I24 -> 0 | K24: =G24+J24 -> 0 | L24: =K24 -> 0 | M24: =M23+K24-L24 -> 0
A25: 22 | B25: 45952 | G25: =E25*F25 -> 0 | J25: =H25*I25 -> 0 | K25: =G25+J25 -> 0 | L25: =K25 -> 0 | M25: =M24+K25-L25 -> 0
A26: 23 | B26: 45953 | G26: =E26*F26 -> 0 | J26: =H26*I26 -> 0 | K26: =G26+J26 -> 0 | L26: =K26 -> 0 | M26: =M25+K26-L26 -> 0
A27: 24 | B27: 45954 | G27: =E27*F27 -> 0 | J27: =H27*I27 -> 0 | K27: =G27+J27 -> 0 | L27: =K27 -> 0 | M27: =M26+K27-L27 -> 0
A28: 25 | B28: 45955 | E28: 219.996 | F28: 92.17 | G28: =E28*F28 -> 20277.031 | H28: 15 | I28: 104.02 | J28: =H28*I28 -> 1560.3 | K28: =G28+J28 -> 21837.331 | L28: =K28 -> 21837.331 | M28: 0
A29: 26 | B29: 45956 | G29: =E29*F29 -> 0 | J29: =H29*I29 -> 0 | K29: =G29+J29 -> 0 | L29: =K29 -> 0 | M29: 0
A30: 27 | B30: 45957 | G30: =E30*F30 -> 0 | J30: =H30*I30 -> 0 | K30: =G30+J30 -> 0 | L30: =K30 -> 0 | M30: 0
A31: 28 | B31: 45958 | G31: =E31*F31 -> 0 | J31: =H31*I31 -> 0 | K31: =G31+J31 -> 0 | L31: =K31 -> 0 | M31: 0
A32: 29 | B32: 45959 | G32: =E32*F32 -> 0 | J32: =H32*I32 -> 0 | K32: =G32+J32 -> 0 | L32: =K32 -> 0
A33: 30 | B33: 45960 | G33: =E33*F33 -> 0 | J33: =H33*I33 -> 0 | K33: =G33+J33 -> 0 | L33: =K33 -> 0
A35: 31 | L35: =H35+K35 -> 0
E36: =SUM(E4:E35) -> 1199.996 | G36: =SUM(G4:G35) -> 110652.63 | H36: =SUM(H4:H35) -> 45 | J36: =SUM(J4:J35) -> 4682.4 | K36: =SUM(K4:K35) -> 115335.03 | L36: =SUM(L4:L35) -> 115335.03

Sheet Haveri
A1: Shivalingeshwar Petroleum
A2: S.No | B2: Date | C2: GRN No | D2: Ind No/Bill No | E2: Diesel (Lts) | F2: Price | G2: Amount | H2: Petrol (Lts) | I2: Price | J2: Amount | K2: Total amount | L2: Amount paid | M2: As on Date | N2: Remarks
D3: Opening Balance | L3: 100388.61 | M3: 100388.61
A4: 1 | B4: 45931 | E4: 50 | F4: 91.47 | G4: =E4*F4 -> 4573.5 | H4: 0 | I4: 0 | J4: =H4*I4 -> 0 | K4: =G4+J4 -> 4573.5 | L4: 0 | M4: =M3+K4-L4 -> 104962.11
A5: 2 | B5: 45932 | E5: 0 | F5: 0 | G5: =E5*F5 -> 0 | H5: 0 | I5: 0 | J5: =H5*I5 -> 0 | K5: =G5+J5 -> 0 | L5: 0 | M5: =M4+K5-L5 -> 104962.11
A6: 3 | B6: 45933 | E6: 0 | F6: 0 | G6: =E6*F6 -> 0 | H6: 0 | I6: 0 | J6: =H6*I6 -> 0 | K6: =G6+J6 -> 0 | L6: 0 | M6: =M5+K6-L6 -> 104962.11
A7: 4 | B7: 45934 | E7: 159 | F7: 91.47 | G7: =E7*F7 -> 14543.73 | H7: 15 | I7: 103.4 | J7: =H7*I7 -> 1551 | K7: =G7+J7 -> 16094.73 | L7: 0 | M7: =M6+K7-L7 -> 121056.84
A8: 5 | B8: 45935 | E8: 131.01 | F8: 91.47 | G8: =E8*F8 -> 11983.485 | H8: 0 | I8: 0 | J8: =H8*I8 -> 0 | K8: =G8+J8 -> 11983.485 | L8: 0 | M8: =M7+K8-L8 -> 133040.32
A9: 6 | B9: 45936 | E9: 230 | F9: 91.47 | G9: =E9*F9 -> 21038.1 | H9: 0 | I9: 0 | J9: =H9*I9 -> 0 | K9: =G9+J9 -> 21038.1 | L9: 0 | M9: =M8+K9-L9 -> 154078.42
A10: 7 | B10: 45937 | E10: 156.49 | F10: 91.47 | G10: =E10*F10 -> 14314.14 | H10: 0 | I10: 0 | J10: =H10*I10 -> 0 | K10: =G10+J10 -> 14314.14 | L10: 100000 | M10: =M9+K10-L10 -> 68392.56
A11: 8 | B11: 45938 | E11: 100.01 | F11: 91.47 | G11: =E11*F11 -> 9147.9147 | H11: 11.12 | I11: 103.4 | J11: =H11*I11 -> 1149.808 | K11: =G11+J11 -> 10297.723 | L11: 0 | M11: =M10+K11-L11 -> 78690.283
A12: 9 | B12: 45939 | E12: 111 | F12: 91.47 | G12: =E12*F12 -> 10153.17 | H12: 7.84 | I12: 103.4 | J12: =H12*I12 -> 810.656 | K12: =G12+J12 -> 10963.826 | L12: 0 | M12: =M11+K12-L12 -> 89654.109 | O12: .
A13: 10 | B13: 45940 | E13: 200.01 | F13: 91.47 | G13: =E13*F13 -> 18294.915 | H13: 6.5 | I13: 103.4 | J13: =H13*I13 -> 672.1 | K13: =G13+J13 -> 18967.015 | L13: 0 | M13: =M12+K13-L13 -> 108621.12
A14: 11 | B14: 45941 | E14: 180 | F14: 91.47 | G14: =E14*F14 -> 16464.6 | H14: 0 | I14: 0 | J14: =H14*I14 -> 0 | K14: =G14+J14 -> 16464.6 | L14: 0 | M14: =M13+K14-L14 -> 125085.72
A15: 12 | B15: 45942 | E15: 130 | F15: 91.47 | G15: =E15*F15 -> 11891.1 | H15: 0 | I15: 0 | J15: =H15*I15 -> 0 | K15: =G15+J15 -> 11891.1 | L15: 0 | M15: =M14+K15-L15 -> 136976.82
A16: 13 | B16: 45943 | E16: 179.3 | F16: 91.47 | G16: =E16*F16 -> 16400.571 | H16: 5 | I16: 103.4 | J16: =H16*I16 -> 517 | K16: =G16+J16 -> 16917.571 | L16: 0 | M16: =M15+K16-L16 -> 153894.39
A17: 14 | B17: 45944 | E17: 215.01 | F17: 91.47 | G17: =E17*F17 -> 19666.965 | H17: 0 | I17: 0 | J17: =H17*I17 -> 0 | K17: =G17+J17 -> 19666.965 | L17: 0 | M17: =M16+K17-L17 -> 173561.36
A18: 15 | B18: 45945 | E18: 385 | F18: 91.47 | G18: =E18*F18 -> 35215.95 | H18: 7 | I18: 103.4 | J18: =H18*I18 -> 723.8 | K18: =G18+J18 -> 35939.75 | L18: 100000 | M18: =M17+K18-L18 -> 109501.11
A19: 16 | B19: 45946 | E19: 220.68 | F19: 91.47 | G19: =E19*F19 -> 20185.6 | H19: 0 | I19: 0 | J19: =H19*I19 -> 0 | K19: =G19+J19 -> 20185.6 | L19: 0 | M19: =M18+K19-L19 -> 129686.71
A20: 17 | B20: 45947 | E20: 521.89 | F20: 91.47 | G20: =E20*F20 -> 47737.278 | H20: 13.02 | I20: 103.4 | J20: =H20*I20 -> 1346.268 | K20: =G20+J20 -> 49083.546 | L20: 0 | M20: =M19+K20-L20 -> 178770.26
A21: 18 | B21: 45948 | E21: 100 | F21: 91.47 | G21: =E21*F21 -> 9147 | H21: 0 | I21: 0 | J21: =H21*I21 -> 0 | K21: =G21+J21 -> 9147 | L21: 0 | M21: =M20+K21-L21 -> 187917.26
A22: 19 | B22: 45949 | E22: 55 | F22: 91.47 | G22: =E22*F22 -> 5030.85 | H22: 0 | I22: 0 | J22: =H22*I22 -> 0 | K22: =G22+J22 -> 5030.85 | L22: 0 | M22: =M21+K22-L22 -> 192948.11
A23: 20 | B23: 45950 | E23: 0 | F23: 0 | G23: =E23*F23 -> 0 | H23: 0 | I23: 0 | J23: =H23*I23 -> 0 | K23: =G23+J23 -> 0 | L23: 0 | M23: =M22+K23-L23 -> 192948.11
A24: 21 | B24: 45951 | E24: 253 | F24: 91.47 | G24: =E24*F24 -> 23141.91 | H24: 5 | I24: 103.4 | J24: =H24*I24 -> 517 | K24: =G24+J24 -> 23658.91 | L24: 0 | M24: =M23+K24-L24 -> 216607.02
... A29: 26 | B29: 45956 | E29: 35 | F29: 91.47 | G29: =E29*F29 -> 3201.45 | H29: 0 | I29: 0 | J29: =H29*I29 -> 0 | K29: =G29+J29 -> 3201.45 | L29: 0 | M29: =M28+K29-L29 -> 265052.4
A30: 27 | B30: 45957 | E30: 183.61 | F30: 91.47 | G30: =E30*F30 -> 16794.807 | H30: 0 | I30: 0 | J30: =H30*I30 -> 0 | K30: =G30+J30 -> 16794.807 | L30: 0 | M30: =M29+K30-L30 -> 281847.2 | R30: 46.61
A31: 28 | B31: 45958 | E31: 90 | F31: 91.47 | G31: =E31*F31 -> 8232.3 | H31: 0 | I31: 0 | J31: =H31*I31 -> 0 | K31: =G31+J31 -> 8232.3 | L31: 0 | M31: =M30+K31-L31 -> 290079.5 | R31: 100
A32: 29 | B32: 45959 | E32: 25 | F32: 91.47 | G32: =E32*F32 -> 2286.75 | H32: 0 | I32: 0 | J32: =H32*I32 -> 0 | K32: =G32+J32 -> 2286.75 | L32: 0 | M32: =M31+K32-L32 -> 292366.25 | R32: 35
A33: 30 | B33: 45960 | E33: 109.3 | F33: 91.49 | G33: =E33*F33 -> 9999.857 | H33: 0 | I33: 0 | J33: =H33*I33 -> 0 | K33: =G33+J33 -> 9999.857 | L33: 10000 | M33: =M32+K33-L33 -> 292366.11 | N33: BPCL OTP
A34: 31 | B34: 45960 | E34: 0 | F34: 0 | G34: =E34*F34 -> 0 | H34: 0 | I34: 0 | J34: =H34*I34 -> 0 | K34: =G34+J34 -> 0 | L34: 200000 | M34: =M33+K34-L34 -> 92366.11
B35: 45961 | E35: 378.58 | F35: 91.49 | G35: =E35*F35 -> 34636.284 | H35: 7 | I35: 103.4 | J35: =H35*I35 -> 723.8 | K35: =G35+J35 -> 35360.084 | M35: =M34+K35-L35 -> 127726.19
E36: =SUM(E4:E35) -> 4650 | G36: =SUM(G4:G35) -> 425345.26 | H36: =SUM(H4:H35) -> 115.98 | J36: =SUM(J4:J35) -> 11992.332 | K36: =SUM(K4:K35) -> 437337.59 | L36: =SUM(L4:L35) -> 410000
I39: =K24+L24 -> 23658.91

Sheet Guttal
A1: Taware filling station
A2: S.No | B2: Date | C2: GRN No | D2: Ind No/Bill No | E2: Diesel (Lts) | F2: Price | G2: Amount | H2: Petrol (Lts) | I2: Price | J2: Amount | K2: Total amount | L2: Amount paid | M2: As on Date | N2: Remarks
D3: Opening Balance | K3: 0 | L3: 0 | M3: =+K3 -> 0
A4: 1 | B4: 45931 | E4: 0 | F4: 0 | G4: =E4*F4 -> 0 | H4: 0 | I4: 0 | J4: =H4*I4 -> 0 | K4: =G4+J4 -> 0 | L4: 0 | M4: =M3+K4-L4 -> 0
A5: 2 | B5: 45932 | E5: 0 | F5: 0 | G5: =E5*F5 -> 0 | H5: 0 | I5: 0 | J5: =H5*I5 -> 0 | K5: =G5+J5 -> 0 | L5: 0 | M5: =M4+K5-L5 -> 0
A6: 3 | B6: 45933 | E6: 41.79 | F6: 91.8 | G6: =E6*F6 -> 3836.322 | H6: 5 | I6: 103.78 | J6: =H6*I6 -> 518.9 | K6: =G6+J6 -> 4355.222 | L6: 4355.22 | M6: =M5+K6-L6 -> 0.002
A7: 4 | B7: 45934 | E7: 32.23 | F7: 91.8 | G7: =E7*F7 -> 2958.714 | H7: 0 | I7: 0 | J7: =H7*I7 -> 0 | K7: =G7+J7 -> 2958.714 | L7: =H7+K7 -> 2958.714 | M7: =M6+K7-L7 -> 0.002
A8: 5 | B8: 45935 | E8: 0 | F8: 0 | G8: =E8*F8 -> 0 | H8: 0 | I8: 0 | J8: =H8*I8 -> 0 | K8: =G8+J8 -> 0 | L8: 0 | M8: =M7+K8-L8 -> 0.002
A9: 6 | B9: 45936 | E9: 0 | F9: 0 | G9: =E9*F9 -> 0 | H9: 6 | I9: 103.78 | J9: =H9*I9 -> 622.68 | K9: =G9+J9 -> 622.68 | L9: 622.68 | M9: =M8+K9-L9 -> 0.002
A10: 7 | B10: 45937 | E10: 30 | F10: 91.8 | G10: =E10*F10 -> 2754 | H10: 17 | I10: 103.78 | J10: =H10*I10 -> 1764.26 | K10: =G10+J10 -> 4518.26 | L10: 4518.26 | M10: =M9+K10-L10 -> 0.002
A11: 8 | B11: 45938 | E11: 60 | F11: 91.8 | G11: =E11*F11 -> 5508 | H11: 0 | I11: 0 | J11: =H11*I11 -> 0 | K11: =G11+J11 -> 5508 | L11: 0 | M11: =M10+K11-L11 -> 5508.002
A12: 9 | B12: 45939 | E12: 45 | F12: 91.8 | G12: =E12*F12 -> 4131 | H12: 0 | I12: 0 | J12: =H12*I12 -> 0 | K12: =G12+J12 -> 4131 | L12: 0 | M12: =M11+K12-L12 -> 9639.002 | O12: .
A13: 10 | B13: 45940 | E13: 111.01 | F13: 91.8 | G13: =E13*F13 -> 10190.718 | H13: 10 | I13: 103.78 | J13: =H13*I13 -> 1037.8 | K13: =G13+J13 -> 11228.518 | L13: 0 | M13: =M12+K13-L13 -> 20867.52
A14: 11 | B14: 45941 | E14: 50 | F14: 91.8 | G14: =E14*F14 -> 4590 | H14: 5 | I14: 103.78 | J14: =H14*I14 -> 518.9 | K14: =G14+J14 -> 5108.9 | L14: 9639 | M14: =M13+K14-L14 -> 16337.42
A15: 12 | B15: 45942 | E15: 0 | F15: 0 | G15: =E15*F15 -> 0 | H15: 0 | I15: 0 | J15: =H15*I15 -> 0 | K15: =G15+J15 -> 0 | L15: 0 | M15: =M14+K15-L15 -> 16337.42
A16: 13 | B16: 45943 | E16: 90 | F16: 91.8 | G16: =E16*F16 -> 8262 | H16: 5 | I16: 103.78 | J16: =H16*I16 -> 518.9 | K16: =G16+J16 -> 8780.9 | L16: 0 | M16: =M15+K16-L16 -> 25118.32
A17: 14 | B17: 45944 | E17: 20 | F17: 91.8 | G17: =E17*F17 -> 1836 | H17: 0 | I17: 0 | J17: =H17*I17 -> 0 | K17: =G17+J17 -> 1836 | L17: 20000 | M17: =M16+K17-L17 -> 6954.32
A18: 15 | B18: 45945 | E18: 15 | F18: 91.8 | G18: =E18*F18 -> 1377 | H18: 5 | I18: 103.78 | J18: =H18*I18 -> 518.9 | K18: =G18+J18 -> 1895.9 | L18: 0 | M18: =M17+K18-L18 -> 8850.22
A19: 16 | B19: 45946 | E19: 0 | F19: 0 | G19: =E19*F19 -> 0 | H19: 5 | I19: 103.78 | J19: =H19*I19 -> 518.9 | K19: =G19+J19 -> 518.9 | L19: 0 | M19: =M18+K19-L19 -> 9369.12
A20: 17 | B20: 45947 | E20: 134.56 | F20: 91.8 | G20: =E20*F20 -> 12352.608 | H20: 0 | I20: 0 | J20: =H20*I20 -> 0 | K20: =G20+J20 -> 12352.608 | L20: 0 | M20: =M19+K20-L20 -> 21721.728
A21: 18 | B21: 45948 | E21: 60 | F21: 91.8 | G21: =E21*F21 -> 5508 | H21: 0 | I21: 0 | J21: =H21*I21 -> 0 | K21: =G21+J21 -> 5508 | L21: 0 | M21: =M20+K21-L21 -> 27229.728
A22: 19 | B22: 45949 | E22: 0 | F22: 0 | G22: =E22*F22 -> 0 | H22: 0 | I22: 0 | J22: =H22*I22 -> 0 | K22: =G22+J22 -> 0 | L22: 0 | M22: =M21+K22-L22 -> 27229.728
A23: 20 | B23: 45950 | E23: 0 | F23: 0 | G23: =E23*F23 -> 0 | H23: 0 | I23: 0 | J23: =H23*I23 -> 0 | K23: =G23+J23 -> 0 | L23: 0 | M23: =M22+K23-L23 -> 27229.728
A24: 21 | B24: 45951 | E24: 0 | F24: 0 | G24: =E24*F24 -> 0 | H24: 0 | I24: 0 | J24: =H24*I24 -> 0 | K24: =G24+J24 -> 0 | L24: 0 | M24: =M23+K24-L24 -> 27229.728
... A28: 25 | B28: 45955 | E28: 90 | F28: 91.8 | G28: =E28*F28 -> 8262 | H28: 5 | I28: 103.78 | J28: =H28*I28 -> 518.9 | K28: =G28+J28 -> 8780.9 | L28: 0 | M28: =M27+K28-L28 -> 36010.628
A29: 26 | B29: 45956 | E29: 0 | F29: 0 | G29: =E29*F29 -> 0 | H29: 0 | I29: 0 | J29: =H29*I29 -> 0 | K29: =G29+J29 -> 0 | L29: 0 | M29: =M28+K29-L29 -> 36010.628 | Q29: 30
A30: 27 | B30: 45957 | E30: 50.02 | F30: 91.8 | G30: =E30*F30 -> 4591.836 | H30: 10 | I30: 103.78 | J30: =H30*I30 -> 1037.8 | K30: =G30+J30 -> 5629.636 | L30: 0 | M30: =M29+K30-L30 -> 41640.264 | Q30: 20.02
A31: 28 | B31: 45958 | E31: 20 | F31: 91.8 | G31: =E31*F31 -> 1836 | H31: 10 | I31: 103.78 | J31: =H31*I31 -> 1037.8 | K31: =G31+J31 -> 2873.8 | L31: 0 | M31: =M30+K31-L31 -> 44514.064
A32: 29 | B32: 45959 | E32: 120 | F32: 91.8 | G32: =E32*F32 -> 11016 | H32: 0 | I32: 0 | J32: =H32*I32 -> 0 | K32: =G32+J32 -> 11016 | L32: 0 | M32: =M31+K32-L32 -> 55530.064
A33: 30 | B33: 45960 | E33: 20 | F33: 91.8 | G33: =E33*F33 -> 1836 | H33: 0 | I33: 0 | J33: =H33*I33 -> 0 | K33: =G33+J33 -> 1836 | L33: 0 | M33: =M32+K33-L33 -> 57366.064
A34: 31 | B34: 45961 | E34: 50 | F34: 91.8 | G34: =E34*F34 -> 4590 | H34: 0 | I34: 0 | J34: =H34*I34 -> 0 | K34: =G34+J34 -> 4590 | L34: 25000 | M34: =M33+K34-L34 -> 36956.064
E35: =SUM(E4:E34) -> 1039.61 | G35: =SUM(G4:G34) -> 95436.198 | H35: =SUM(H4:H34) -> 83 | J35: =SUM(J4:J34) -> 8613.74 | K35: =SUM(K4:K34) -> 104049.94 | L35: =SUM(L4:L34) -> 67093.874
I38: =K24+L24 -> 0

Sheet Rattihali
A1: Shree Siri Gowari petroliam
A2: S.No | B2: Date | C2: GRN No | D2: Ind No/Bill No | E2: Diesel (Lts) | F2: Price | G2: Amount | H2: Petrol (Lts) | I2: Price | J2: Amount | K2: Total amount | L2: Amount paid | M2: As on Date | N2: Remarks
D3: Opening Balance | K3: 173876.23 | M3: 173876.23
A4: 1 | B4: 45931 | E4: 0 | F4: 0 | G4: =E4*F4 -> 0 | H4: 0 | I4: 0 | J4: =H4*I4 -> 0 | K4: =G4+J4 -> 0 | L4: 0 | M4: =M3+K4-L4 -> 173876.23
A5: 2 | B5: 45932 | E5: 0 | F5: 0 | G5: =E5*F5 -> 0 | H5: 0 | I5: 0 | J5: =H5*I5 -> 0 | K5: =G5+J5 -> 0 | L5: 0 | M5: =M4+K5-L5 -> 173876.23
A6: 3 | B6: 45933 | E6: 116.88 | F6: 92.04 | G6: =E6*F6 -> 10757.635 | H6: 11 | I6: 104.02 | J6: =H6*I6 -> 1144.22 | K6: =G6+J6 -> 11901.855 | L6: 0 | M6: =M5+K6-L6 -> 185778.09
A7: 4 | B7: 45934 | E7: 0 | F7: 0 | G7: =E7*F7 -> 0 | H7: 0 | I7: 0 | J7: =H7*I7 -> 0 | K7: =G7+J7 -> 0 | L7: 0 | M7: =M6+K7-L7 -> 185778.09
A8: 5 | B8: 45935 | E8: 150 | F8: 92.04 | G8: =E8*F8 -> 13806 | H8: 0 | I8: 0 | J8: =H8*I8 -> 0 | K8: =G8+J8 -> 13806 | L8: 0 | M8: =M7+K8-L8 -> 199584.09
A9: 6 | B9: 45936 | E9: 130 | F9: 92.04 | G9: =E9*F9 -> 11965.2 | H9: 5 | I9: 104.02 | J9: =H9*I9 -> 520.1 | K9: =G9+J9 -> 12485.3 | L9: 0 | M9: =M8+K9-L9 -> 212069.39
A10: 7 | B10: 45937 | E10: 0 | F10: 0 | G10: =E10*F10 -> 0 | H10: 0 | I10: 0 | J10: =H10*I10 -> 0 | K10: =G10+J10 -> 0 | L10: 150000 | M10: =M9+K10-L10 -> 62069.389
A11: 8 | B11: 45938 | E11: 0 | F11: 0 | G11: =E11*F11 -> 0 | H11: 0 | I11: 0 | J11: =H11*I11 -> 0 | K11: =G11+J11 -> 0 | L11: 0 | M11: =M10+K11-L11 -> 62069.389
A12: 9 | B12: 45939 | E12: 20 | F12: 92.04 | G12: =E12*F12 -> 1840.8 | H12: 6.63 | I12: 104.02 | J12: =H12*I12 -> 689.6526 | K12: =G12+J12 -> 2530.4526 | L12: 0 | M12: =M11+K12-L12 -> 64599.842
A13: 10 | B13: 45940 | E13: 97.01 | F13: 92.04 | G13: =E13*F13 -> 8928.8004 | H13: 11.16 | I13: 104.02 | J13: =H13*I13 -> 1160.8632 | K13: =G13+J13 -> 10089.664 | L13: 0 | M13: =M12+K13-L13 -> 74689.505 | Q13: =+K13 -> 10089.664
A14: 11 | B14: 45941 | E14: 105 | F14: 92.04 | G14: =E14*F14 -> 9664.2 | H14: 0 | I14: 0 | J14: =H14*I14 -> 0 | K14: =G14+J14 -> 9664.2 | L14: 0 | M14: =M13+K14-L14 -> 84353.705
A15: 12 | B15: 45942 | E15: 100 | F15: 92.04 | G15: =E15*F15 -> 9204 | H15: 0 | I15: 0 | J15: =H15*I15 -> 0 | K15: =G15+J15 -> 9204 | L15: 0 | M15: =M14+K15-L15 -> 93557.705
A16: 13 | B16: 45943 | E16: 133.06 | F16: 92.04 | G16: =E16*F16 -> 12246.842 | H16: 0 | I16: 0 | J16: =H16*I16 -> 0 | K16: =G16+J16 -> 12246.842 | L16: 0 | M16: =M15+K16-L16 -> 105804.55
A17: 14 | B17: 45944 | E17: 20 | F17: 92.04 | G17: =E17*F17 -> 1840.8 | H17: 0 | I17: 0 | J17: =H17*I17 -> 0 | K17: =G17+J17 -> 1840.8 | L17: 0 | M17: =M16+K17-L17 -> 107645.35
A18: 15 | B18: 45945 | E18: 120 | F18: 92.04 | G18: =E18*F18 -> 11044.8 | H18: 0 | I18: 0 | J18: =H18*I18 -> 0 | K18: =G18+J18 -> 11044.8 | L18: 0 | M18: =M17+K18-L18 -> 118690.15
A19: 16 | B19: 45946 | E19: 0 | F19: 0 | G19: =E19*F19 -> 0 | H19: 0 | I19: 0 | J19: =H19*I19 -> 0 | K19: =G19+J19 -> 0 | L19: 0 | M19: =M18+K19-L19 -> 118690.15
A20: 17 | B20: 45947 | E20: 65.79 | F20: 92.04 | G20: =E20*F20 -> 6055.3116 | H20: 11.96 | I20: 104.02 | J20: =H20*I20 -> 1244.0792 | K20: =G20+J20 -> 7299.3908 | L20: 0 | M20: =M19+K20-L20 -> 125989.54
A21: 18 | B21: 45948 | E21: 0 | F21: 0 | G21: =E21*F21 -> 0 | H21: 0 | I21: 0 | J21: =H21*I21 -> 0 | K21: =G21+J21 -> 0 | L21: 0 | M21: =M20+K21-L21 -> 125989.54
A22: 19 | B22: 45949 | E22: 0 | F22: 0 | G22: =E22*F22 -> 0 | H22: 0 | I22: 0 | J22: =H22*I22 -> 0 | K22: =G22+J22 -> 0 | L22: 0 | M22: =M21+K22-L22 -> 125989.54
A23: 20 | B23: 45950 | E23: 0 | F23: 0 | G23: =E23*F23 -> 0 | H23: 0 | I23: 0 | J23: =H23*I23 -> 0 | K23: =G23+J23 -> 0 | L23: 0 | M23: =M22+K23-L23 -> 125989.54
A24: 21 | B24: 45951 | E24: 0 | F24: 0 | G24: =E24*F24 -> 0 | H24: 0 | I24: 0 | J24: =H24*I24 -> 0 | K24: =G24+J24 -> 0 | L24: 0 | M24: =M23+K24-L24 -> 125989.54
A25: 22 | B25: 45952 | E25: 0 | F25: 0 | G25: =E25*F25 -> 0 | H25: 0 | I25: 0 | J25: =H25*I25 -> 0 | K25: =G25+J25 -> 0 | L25: 0 | M25: =M24+K25-L25 -> 125989.54
... A32: 29 | B32: 45959 | E32: 111.01 | F32: 92.04 | G32: =E32*F32 -> 10217.36 | H32: 0 | I32: 0 | J32: =H32*I32 -> 0 | K32: =G32+J32 -> 10217.36 | L32: 0 | M32: =M31+K32-L32 -> 181096.91
A33: 30 | B33: 45960 | E33: 100 | F33: 92.04 | G33: =E33*F33 -> 9204 | H33: 0 | I33: 0 | J33: =H33*I33 -> 0 | K33: =G33+J33 -> 9204 | L33: 0 | M33: =M32+K33-L33 -> 190300.91 | Q33: 30
A34: 31 | E34: 0 | F34: 0 | G34: =E34*F34 -> 0 | H34: 0 | I34: 0 | J34: =H34*I34 -> 0 | K34: =G34+J34 -> 0 | L34: =+K34 -> 0 | M34: =M33+K34-L34 -> 190300.91
E35: =SUM(E4:E34) -> 1736.13 | G35: =SUM(G4:G34) -> 159793.41 | H35: =SUM(H4:H34) -> 63.75 | J35: =SUM(J4:J34) -> 6631.275 | K35: =SUM(K4:K34) -> 166424.68 | L35: =SUM(L4:L34) -> 150000
I38: =K24+L24 -> 0

Sheet Gajendragada
A1: Vanasri Petrol Pump
A2: S.No | B2: Date | C2: GRN No | D2: Ind no/Bill No | E2: Diesel (Lts) | F2: Price | G2: Amount | H2: Petrol (Lts) | I2: Price | J2: Amount | K2: Total amount | L2: Amount paid | M2: As on Date | N2: Remarks
A3: Opening Balance | K3: 133672.01 | M3: 133672.01
A4: 1 | B4: 45931 | E4: 0 | F4: 0 | G4: =E4*F4 -> 0 | H4: 0 | I4: 0 | J4: =H4*I4 -> 0 | K4: =G4+J4 -> 0 | M4: =M3+K4-L4 -> 133672.01
A5: 2 | B5: 45932 | E5: 0 | F5: 0 | G5: =E5*F5 -> 0 | H5: 0 | I5: 0 | J5: =H5*I5 -> 0 | K5: =G5+J5 -> 0 | M5: =M4+K5-L5 -> 133672.01
A6: 3 | B6: 45933 | E6: 75 | F6: 91.83 | G6: =E6*F6 -> 6887.25 | H6: 10 | I6: 103.8 | J6: =H6*I6 -> 1038 | K6: =G6+J6 -> 7925.25 | M6: =M5+K6-L6 -> 141597.26
A7: 4 | B7: 45934 | E7: 100 | F7: 91.83 | G7: =E7*F7 -> 9183 | H7: 0 | I7: 0 | J7: =H7*I7 -> 0 | K7: =G7+J7 -> 9183 | M7: =M6+K7-L7 -> 150780.26
A8: 5 | B8: 45935 | E8: 30 | F8: 91.83 | G8: =E8*F8 -> 2754.9 | H8: 0 | I8: 0 | J8: =H8*I8 -> 0 | K8: =G8+J8 -> 2754.9 | M8: =M7+K8-L8 -> 153535.16 | O8: 8497892194 | P8: raja bhakshi
A9: 6 | B9: 45936 | E9: 60 | F9: 91.83 | G9: =E9*F9 -> 5509.8 | H9: 0 | I9: 0 | J9: =H9*I9 -> 0 | K9: =G9+J9 -> 5509.8 | M9: =M8+K9-L9 -> 159044.96
A10: 7 | B10: 45937 | E10: 0 | F10: 0 | G10: =E10*F10 -> 0 | H10: 0 | I10: 0 | J10: =H10*I10 -> 0 | K10: =G10+J10 -> 0 | L10: 100000 | M10: =M9+K10-L10 -> 59044.962
A11: 8 | B11: 45938 | E11: 60 | F11: 91.83 | G11: =E11*F11 -> 5509.8 | H11: 0 | I11: 0 | J11: =H11*I11 -> 0 | K11: =G11+J11 -> 5509.8 | M11: =M10+K11-L11 -> 64554.762
A12: 9 | B12: 45939 | E12: 70 | F12: 91.83 | G12: =E12*F12 -> 6428.1 | H12: 0 | I12: 0 | J12: =H12*I12 -> 0 | K12: =G12+J12 -> 6428.1 | M12: =M11+K12-L12 -> 70982.862
A13: 10 | B13: 45940 | E13: 50 | F13: 91.83 | G13: =E13*F13 -> 4591.5 | H13: 5 | I13: 103.8 | J13: =H13*I13 -> 519 | K13: =G13+J13 -> 5110.5 | M13: =M12+K13-L13 -> 76093.362
A14: 11 | B14: 45941 | E14: 0 | F14: 0 | G14: =E14*F14 -> 0 | H14: 0 | I14: 0 | J14: =H14*I14 -> 0 | K14: =G14+J14 -> 0 | M14: =M13+K14-L14 -> 76093.362
A15: 12 | B15: 45942 | E15: 200 | F15: 91.83 | G15: =E15*F15 -> 18366 | H15: 0 | I15: 0 | J15: =H15*I15 -> 0 | K15: =G15+J15 -> 18366 | M15: =M14+K15-L15 -> 94459.362
A16: 13 | B16: 45943 | E16: 30 | F16: 91.83 | G16: =E16*F16 -> 2754.9 | H16: 0 | I16: 0 | J16: =H16*I16 -> 0 | K16: =G16+J16 -> 2754.9 | M16: =M15+K16-L16 -> 97214.262
A17: 14 | B17: 45944 | E17: 0 | F17: 0 | G17: =E17*F17 -> 0 | H17: 0 | I17: 0 | J17: =H17*I17 -> 0 | K17: =G17+J17 -> 0 | M17: =M16+K17-L17 -> 97214.262
A18: 15 | B18: 45945 | E18: 0 | F18: 0 | G18: =E18*F18 -> 0 | H18: 0 | I18: 0 | J18: =H18*I18 -> 0 | K18: =G18+J18 -> 0 | M18: =M17+K18-L18 -> 97214.262
A19: 16 | B19: 45946 | E19: 0 | F19: 0 | G19: =E19*F19 -> 0 | H19: 0 | I19: 0 | J19: =H19*I19 -> 0 | K19: =G19+J19 -> 0 | M19: =M18+K19-L19 -> 97214.262
A20: 17 | B20: 45947 | E20: 0 | F20: 0 | G20: =E20*F20 -> 0 | H20: 5 | I20: 103.8 | J20: =H20*I20 -> 519 | K20: =G20+J20 -> 519 | M20: =M19+K20-L20 -> 97733.262
A21: 18 | B21: 45948 | E21: 0 | F21: 0 | G21: =E21*F21 -> 0 | H21: 0 | I21: 0 | J21: =H21*I21 -> 0 | K21: =G21+J21 -> 0 | M21: =M20+K21-L21 -> 97733.262
A22: 19 | B22: 45949 | E22: 0 | F22: 0 | G22: =E22*F22 -> 0 | H22: 0 | I22: 0 | J22: =H22*I22 -> 0 | K22: =G22+J22 -> 0 | M22: =M21+K22-L22 -> 97733.262
... A26: 23 | B26: 45953 | E26: 0 | F26: 0 | G26: =E26*F26 -> 0 | H26: 0 | I26: 0 | J26: =H26*I26 -> 0 | K26: =G26+J26 -> 0 | M26: =M25+K26-L26 -> 97733.262
A27: 24 | B27: 45954 | E27: 0 | F27: 0 | G27: =E27*F27 -> 0 | H27: 0 | I27: 0 | J27: =H27*I27 -> 0 | K27: =G27+J27 -> 0 | M27: =M26+K27-L27 -> 97733.262 | R27: 66742
A28: 25 | B28: 45955 | E28: 0 | F28: 0 | G28: =E28*F28 -> 0 | H28: 0 | I28: 0 | J28: =H28*I28 -> 0 | K28: =G28+J28 -> 0 | M28: =M27+K28-L28 -> 97733.262
A29: 26 | B29: 45956 | E29: 0 | F29: 0 | G29: =E29*F29 -> 0 | H29: 0 | I29: 0 | J29: =H29*I29 -> 0 | K29: =G29+J29 -> 0 | M29: =M28+K29-L29 -> 97733.262
A30: 27 | B30: 45957 | E30: 0 | F30: 0 | G30: =E30*F30 -> 0 | H30: 5 | I30: 103.8 | J30: =H30*I30 -> 519 | K30: =G30+J30 -> 519 | M30: =M29+K30-L30 -> 98252.262
A31: 28 | B31: 45958 | E31: 0 | F31: 0 | G31: =E31*F31 -> 0 | H31: 0 | I31: 0 | J31: =H31*I31 -> 0 | K31: =G31+J31 -> 0 | M31: =M30+K31-L31 -> 98252.262
A32: 29 | B32: 45959 | E32: 0 | F32: 0 | G32: =E32*F32 -> 0 | H32: 0 | I32: 0 | J32: =H32*I32 -> 0 | K32: =G32+J32 -> 0 | M32: =M31+K32-L32 -> 98252.262
A33: 30 | B33: 45960 | E33: 0 | F33: 0 | G33: =E33*F33 -> 0 | H33: 0 | I33: 0 | J33: =H33*I33 -> 0 | K33: =G33+J33 -> 0 | M33: =M32+K33-L33 -> 98252.262
A34: 31 | E34: 0 | F34: 0 | G34: =E34*F34 -> 0 | H34: 0 | I34: 0 | J34: =H34*I34 -> 0 | K34: =G34+J34 -> 0 | M34: =M33+K34-L34 -> 98252.262
E35: =SUM(E4:E34) -> 675 | G35: =SUM(G4:G34) -> 61985.25 | H35: =SUM(H4:H34) -> 25 | J35: =SUM(J4:J34) -> 2595 | K35: =SUM(K4:K34) -> 64580.25 | L35: =SUM(L4:L34) -> 100000

Sheet  Talikote
A1: Talikote
A2: S.No | B2: Date | C2: GRN No | D2: Ind no/Bill No | E2: Diesel (Lts) | F2: Price | G2: Amount | H2: Petrol (Lts) | I2: Price | J2: Amount | K2: Total amount | L2: Amount paid | M2: As on Date | N2: Remarks
A3: Opening Balance | N3: 20613.942
A4: 1 | B4: 1.10.2025 | E4: 25.57 | F4: 91.5 | G4: =E4*F4 -> 2339.655 | H4: 0 | I4: 0 | J4: =H4*I4 -> 0 | K4: =G4+J4 -> 2339.655 | L4: 0 | M4: =N3+K4-L4 -> 22953.597 | N4: IOCL Card
A5: 2 | B5: 2.10.2025 | E5: 0 | F5: 0 | G5: =E5*F5 -> 0 | H5: 0 | I5: 0 | J5: =H5*I5 -> 0 | K5: =G5+J5 -> 0 | L5: 0 | M5: =M4+K5-L5 -> 22953.597 | N5: IOCL Card
A6: 3 | B6: 3.10.2025 | E6: 0 | F6: 0 | G6: =E6*F6 -> 0 | H6: 0 | I6: 0 | J6: =H6*I6 -> 0 | K6: =G6+J6 -> 0 | L6: 0 | M6: =M5+K6-L6 -> 22953.597 | N6: IOCL Card
B7: 04.10.2025 | E7: 0 | F7: 0 | G7: =E7*F7 -> 0 | H7: 6.79 | I7: 103.44 | J7: =H7*I7 -> 702.3576 | K7: =G7+J7 -> 702.3576 | L7: 0 | M7: =M6+K7-L7 -> 23655.955 | N7: IOCL Card
A8: 4 | B8: 05.10.2025 | E8: 110.21 | F8: 91.5 | G8: =E8*F8 -> 10084.215 | H8: 0 | I8: 0 | J8: =H8*I8 -> 0 | K8: =G8+J8 -> 10084.215 | L8: 0 | M8: =M7+K8-L8 -> 33740.17 | N8: IOCL Card
A9: 5 | B9: 06.10.2025 | E9: 60 | F9: 91.5 | G9: =E9*F9 -> 5490 | H9: 15 | I9: 103.44 | J9: =H9*I9 -> 1551.6 | K9: =G9+J9 -> 7041.6 | L9: 0 | M9: =M8+K9-L9 -> 40781.77 | N9: IOCL Card
A10: 6 | B10: 07.10.2025 | E10: 0 | F10: 0 | G10: =E10*F10 -> 0 | H10: 0 | I10: 0 | J10: =H10*I10 -> 0 | K10: =G10+J10 -> 0 | L10: 0 | M10: =M9+K10-L10 -> 40781.77 | N10: IOCL Card
A11: 7 | B11: 08.10.2025 | E11: 80 | F11: 91.5 | G11: =E11*F11 -> 7320 | H11: 6.77 | I11: 103.44 | J11: =H11*I11 -> 700.2888 | K11: =G11+J11 -> 8020.2888 | L11: 40000 | M11: =M10+K11-L11 -> 8802.0588 | N11: IOCL Card
A12: 8 | B12: 09.10.2025 | E12: 0 | F12: 0 | G12: =E12*F12 -> 0 | H12: 7.2 | I12: 103.44 | J12: =H12*I12 -> 744.768 | K12: =G12+J12 -> 744.768 | L12: 0 | M12: =M11+K12-L12 -> 9546.8268 | N12: IOCL Card
A13: 9 | B13: 10.10.2025 | E13: 118.42 | F13: 91.5 | G13: =E13*F13 -> 10835.43 | H13: 5 | I13: 103.44 | J13: =H13*I13 -> 517.2 | K13: =G13+J13 -> 11352.63 | L13: 0 | M13: =M12+K13-L13 -> 20899.457 | N13: IOCL Card
A14: 10 | B14: 11.10.2025 | E14: 37.59 | F14: 91.5 | G14: =E14*F14 -> 3439.485 | H14: 0 | I14: 0 | J14: =H14*I14 -> 0 | K14: =G14+J14 -> 3439.485 | L14: 0 | M14: =M13+K14-L14 -> 24338.942 | N14: IOCL Card
A15: 11 | B15: 12.10.2025 | E15: =29.92+30+12 -> 71.92 | F15: 91.5 | G15: =E15*F15 -> 6580.68 | H15: 4.83 | I15: 103.44 | J15: =H15*I15 -> 499.6152 | K15: =G15+J15 -> 7080.2952 | L15: 0 | M15: =M14+K15-L15 -> 31419.237 | N15: IOCL Card
A16: 12 | B16: 13.10.2025 | E16: 66.75 | F16: 91.5 | G16: =E16*F16 -> 6107.625 | H16: 0 | I16: 0 | J16: =H16*I16 -> 0 | K16: =G16+J16 -> 6107.625 | L16: 0 | M16: =M15+K16-L16 -> 37526.862 | N16: IOCL Card
A17: 13 | B17: 15.10.2025 | E17: 43.53 | F17: 91.5 | G17: =E17*F17 -> 3982.995 | H17: 4.83 | I17: 103.44 | J17: =H17*I17 -> 499.6152 | K17: =G17+J17 -> 4482.6102 | L17: 0 | M17: =M16+K17-L17 -> 42009.472 | N17: IOCL Card
A18: 14 | B18: 16.10.2025 | E18: 79.76 | F18: 91.5 | G18: =E18*F18 -> 7298.04 | H18: 6.28 | I18: 103.44 | J18: =H18*I18 -> 649.6032 | K18: =G18+J18 -> 7947.6432 | L18: 37000 | M18: =M17+K18-L18 -> 12957.115 | N18: IOCL Card
A19: 15 | B19: 17.10.2025 | E19: =10+3.83+2.96+39.92 -> 56.71 | F19: 91.5 | G19: =E19*F19 -> 5188.965 | H19: 6 | I19: 103.44 | J19: =H19*I19 -> 620.64 | K19: =G19+J19 -> 5809.605 | L19: 0 | M19: =M18+K19-L19 -> 18766.72 | N19: IOCL Card
A20: 16 | B20: 17.10.2025 | E20: 11.01 | F20: 90.8 | G20: =E20*F20 -> 999.708 | H20: 0 | I20: 0 | J20: =H20*I20 -> 0 | K20: =G20+J20 -> 999.708 | L20: 999.71 | M20: =M19+K20-L20 -> 18766.718 | N20: IOCL Card
A21: 17 | B21: 22.10.2025 | E21: 44.75 | F21: 91.5 | G21: =E21*F21 -> 4094.625 | H21: 9.66 | I21: 103.44 | J21: =H21*I21 -> 999.2304 | K21: =G21+J21 -> 5093.8554 | L21: 0 | M21: =M20+K21-L21 -> 23860.574 | N21: IOCL Card
A22: 18 | B22: 23.10.2025 | E22: 20 | F22: 91.5 | G22: =E22*F22 -> 1830 | H22: 0 | I22: 0 | J22: =H22*I22 -> 0 | K22: =G22+J22 -> 1830 | L22: 0 | M22: =M21+K22-L22 -> 25690.574 | N22: IOCL Card
A23: 19 | B23: 24.10.2025 | E23: 39.29 | F23: 91.5 | G23: =E23*F23 -> 3595.035 | H23: 6 | I23: 103.44 | J23: =H23*I23 -> 620.64 | K23: =G23+J23 -> 4215.675 | L23: 0 | M23: =M22+K23-L23 -> 29906.249 | N23: IOCL Card
A24: 21 | B24: 25.10.2025 | E24: 55.16 | F24: 91.5 | G24: =E24*F24 -> 5047.14 | H24: 0 | I24: 0 | J24: =H24*I24 -> 0 | K24: =G24+J24 -> 5047.14 | L24: 0 | M24: =M23+K24-L24 -> 34953.389 | N24: IOCL Card
A25: 22 | B25: 26.10.2025 | E25: 60 | F25: 91.5 | G25: =E25*F25 -> 5490 | H25: 10 | I25: 103.44 | J25: =H25*I25 -> 1034.4 | K25: =G25+J25 -> 6524.4 | L25: 0 | M25: =M24+K25-L25 -> 41477.789 | N25: IOCL Card
A26: 23 | B26: 27.10.2025 | E26: 0 | F26: 0 | G26: =E26*F26 -> 0 | H26: 0 | I26: 0 | J26: =H26*I26 -> 0 | K26: =G26+J26 -> 0 | L26: 0 | M26: =M25+K26-L26 -> 41477.789 | N26: IOCL Card
A27: 24 | B27: 28.10.2025 | E27: 101.56 | F27: 91.5 | G27: =E27*F27 -> 9292.74 | H27: 10 | I27: 103.44 | J27: =H27*I27 -> 1034.4 | K27: =G27+J27 -> 10327.14 | L27: 20000 | M27: =M26+K27-L27 -> 31804.929 | N27: IOCL Card
A28: 25 | B28: 29.10.2025 | E28: 0 | F28: 0 | G28: =E28*F28 -> 0 | H28: 7.83 | I28: 103.44 | J28: =H28*I28 -> 809.9352 | K28: =G28+J28 -> 809.9352 | L28: 0 | M28: =M27+K28-L28 -> 32614.864 | N28: IOCL Card
A29: 26 | B29: 30.10.2025 | E29: 31.32 | F29: 91.5 | G29: =E29*F29 -> 2865.78 | H29: 20.82 | I29: 103.44 | J29: =H29*I29 -> 2153.6208 | K29: =G29+J29 -> 5019.4008 | L29: 0 | M29: =M28+K29-L29 -> 37634.265 | N29: IOCL Card
A30: 27 | B30: 31.10.2025 | E30: 60 | F30: 91.5 | G30: =E30*F30 -> 5490 | H30: 0 | I30: 0 | J30: =H30*I30 -> 0 | K30: =G30+J30 -> 5490 | L30: 0 | M30: =M29+K30-L30 -> 43124.265 | N30: IOCL Card
A31: 28 | E31: 0 | F31: 0 | G31: =E31*F31 -> 0 | H31: 0 | I31: 0 | J31: =H31*I31 -> 0 | K31: =G31+J31 -> 0 | L31: 0 | M31: =M30+K31-L31 -> 43124.265 | N31: IOCL Card
A32: 29 | E32: 0 | F32: 0 | G32: =E32*F32 -> 0 | H32: 0 | I32: 0 | J32: =H32*I32 -> 0 | K32: =G32+J32 -> 0 | L32: 0 | M32: =M31+K32-L32 -> 43124.265 | N32: IOCL Card
A33: 30 | E33: 0 | F33: 0 | G33: =E33*F33 -> 0 | H33: 0 | I33: 0 | J33: =H33*I33 -> 0 | K33: =G33+J33 -> 0 | L33: 0 | M33: =M32+K33-L33 -> 43124.265 | N33: IOCL Card
A34: 31 | E34: 0 | F34: 0 | G34: =E34*F34 -> 0 | H34: 0 | I34: 0 | J34: =H34*I34 -> 0 | K34: =G34+J34 -> 0 | L34: 0 | M34: =M33+K34-L34 -> 43124.265 | N34: IOCL Card
A35: 32 | E35: 0 | F35: 0 | G35: =E35*F35 -> 0 | H35: 0 | I35: 0 | J35: =H35*I35 -> 0 | K35: =G35+J35 -> 0 | L35: 0 | M35: =M34+K35-L35 -> 43124.265 | N35: IOCL Card
A36: 33 | E36: 0 | F36: 0 | G36: =E36*F36 -> 0 | H36: 0 | I36: 0 | J36: =H36*I36 -> 0 | K36: =G36+J36 -> 0 | L36: 0 | M36: =M35+K36-L36 -> 43124.265 | N36: IOCL Card
A37: 34 | E37: 0 | F37: 0 | G37: =E37*F37 -> 0 | H37: 0 | I37: 0 | J37: =H37*I37 -> 0 | K37: =G37+J37 -> 0 | L37: 0 | M37: =M36+K37-L37 -> 43124.265 | N37: IOCL Card
A38: 35 | E38: 0 | F38: 0 | G38: =E38*F38 -> 0 | H38: 0 | I38: 0 | J38: =H38*I38 -> 0 | K38: =G38+J38 -> 0 | L38: 0 | M38: =M37+K38-L38 -> 43124.265 | N38: IOCL Card
A39: 36 | E39: 0 | F39: 0 | G39: =E39*F39 -> 0 | H39: 0 | I39: 0 | J39: =H39*I39 -> 0 | K39: =G39+J39 -> 0 | L39: 0 | M39: =M38+K39-L39 -> 43124.265 | N39: IOCL Card
A40: 37 | E40: 0 | F40: 0 | G40: =E40*F40 -> 0 | H40: 0 | I40: 0 | J40: =H40*I40 -> 0 | K40: =G40+J40 -> 0 | L40: 0 | M40: =M39+K40-L40 -> 43124.265 | N40: IOCL Card
A41: 38 | E41: 0 | F41: 0 | G41: =E41*F41 -> 0 | H41: 0 | I41: 0 | J41: =H41*I41 -> 0 | K41: =G41+J41 -> 0 | L41: 0 | M41: =M40+K41-L41 -> 43124.265 | N41: IOCL Card
A42: 39 | E42: 0 | F42: 0 | G42: =E42*F42 -> 0 | H42: 0 | I42: 0 | J42: =H42*I42 -> 0 | K42: =G42+J42 -> 0 | L42: 0 | M42: =M41+K42-L42 -> 43124.265 | N42: IOCL Card
... A44: 41 | E44: 0 | F44: 0 | G44: =E44*F44 -> 0 | H44: 0 | I44: 0 | J44: =H44*I44 -> 0 | K44: =G44+J44 -> 0 | L44: 0 | M44: =M43+K44-L44 -> 43124.265 | N44: IOCL Card
A45: 42 | E45: 0 | F45: 0 | G45: =E45*F45 -> 0 | H45: 0 | I45: 0 | J45: =H45*I45 -> 0 | K45: =G45+J45 -> 0 | L45: =+K45 -> 0 | M45: =M44+K45-L45 -> 43124.265 | N45: IOCL Card
E46: =SUM(E4:E45) -> 1173.55 | G46: =SUM(G4:G45) -> 107372.12 | H46: =SUM(H4:H45) -> 127.01 | J46: =SUM(J4:J45) -> 13137.914 | K46: =SUM(K4:K45) -> 120510.03 | L46: =SUM(L4:L45) -> 97999.71

Sheet Chadchan
A1: Khavekar Petrolium
A2: S.No | B2: Date | C2: GRN No | D2: Ind no/Bill No | E2: Diesel (Lts) | F2: Price | G2: Amount | H2: Petrol (Lts) | I2: Price | J2: Amount | K2: Total amount | L2: Amount paid | M2: As on Date | N2: Remarks
B3: Opening Balance | K3: 92882.428 | M3: =+K3 -> 92882.428 | O3: 86559.567
A4: 1 | B4: 45931 | E4: 0 | F4: 0 | G4: =E4*F4 -> 0 | H4: 0 | I4: 0 | J4: =H4*I4 -> 0 | K4: =G4+J4 -> 0 | M4: =M3+K4-L4 -> 92882.428
A5: 2 | B5: 45932 | E5: 45.06 | F5: 91.23 | G5: =E5*F5 -> 4110.8238 | H5: 5 | I5: 103.16 | J5: =H5*I5 -> 515.8 | K5: =G5+J5 -> 4626.6238 | M5: =M4+K5-L5 -> 97509.052
A6: 3 | B6: 45933 | E6: 0 | F6: 0 | G6: =E6*F6 -> 0 | H6: 0 | I6: 0 | J6: =H6*I6 -> 0 | K6: =G6+J6 -> 0 | M6: =M5+K6-L6 -> 97509.052
A7: 4 | B7: 45934 | E7: 0 | F7: 0 | G7: =E7*F7 -> 0 | H7: 0 | I7: 0 | J7: =H7*I7 -> 0 | K7: =G7+J7 -> 0 | M7: =M6+K7-L7 -> 97509.052
A8: 5 | B8: 45935 | E8: 0 | F8: 0 | G8: =E8*F8 -> 0 | H8: 7.03 | I8: 103.16 | J8: =H8*I8 -> 725.2148 | K8: =G8+J8 -> 725.2148 | M8: =M7+K8-L8 -> 98234.267
A9: 6 | B9: 45936 | E9: 0 | F9: 0 | G9: =E9*F9 -> 0 | H9: 0 | I9: 0 | J9: =H9*I9 -> 0 | K9: =G9+J9 -> 0 | M9: =M8+K9-L9 -> 98234.267
A10: 7 | B10: 45937 | E10: 0 | F10: 0 | G10: =E10*F10 -> 0 | H10: 5 | I10: 103.16 | J10: =H10*I10 -> 515.8 | K10: =G10+J10 -> 515.8 | L10: 90000 | M10: =M9+K10-L10 -> 8750.0668
A11: 8 | B11: 45938 | E11: 0 | F11: 0 | G11: =E11*F11 -> 0 | H11: 0 | I11: 0 | J11: =H11*I11 -> 0 | K11: =G11+J11 -> 0 | M11: =M10+K11-L11 -> 8750.0668
A12: 9 | B12: 45939 | E12: 143.9 | F12: 91.23 | G12: =E12*F12 -> 13127.997 | H12: 0 | I12: 0 | J12: =H12*I12 -> 0 | K12: =G12+J12 -> 13127.997 | M12: =M11+K12-L12 -> 21878.064
A13: 10 | B13: 45940 | E13: 35 | F13: 91.23 | G13: =E13*F13 -> 3193.05 | H13: 5 | I13: 103.16 | J13: =H13*I13 -> 515.8 | K13: =G13+J13 -> 3708.85 | M13: =M12+K13-L13 -> 25586.914
A14: 11 | B14: 45941 | E14: 0 | F14: 0 | G14: =E14*F14 -> 0 | H14: 0 | I14: 0 | J14: =H14*I14 -> 0 | K14: =G14+J14 -> 0 | M14: =M13+K14-L14 -> 25586.914
A15: 12 | B15: 45942 | E15: 174.69 | F15: 91.23 | G15: =E15*F15 -> 15936.969 | H15: 0 | I15: 0 | J15: =H15*I15 -> 0 | K15: =G15+J15 -> 15936.969 | M15: =M14+K15-L15 -> 41523.883
A16: 13 | B16: 45943 | E16: 0 | F16: 0 | G16: =E16*F16 -> 0 | H16: 9.12 | I16: 103.16 | J16: =H16*I16 -> 940.8192 | K16: =G16+J16 -> 940.8192 | M16: =M15+K16-L16 -> 42464.702
A17: 14 | B17: 45944 | E17: 126.27 | F17: 91.23 | G17: =E17*F17 -> 11519.612 | H17: 18 | I17: 103.16 | J17: =H17*I17 -> 1856.88 | K17: =G17+J17 -> 13376.492 | M17: =M16+K17-L17 -> 55841.194
A18: 15 | B18: 45945 | E18: 0 | F18: 0 | G18: =E18*F18 -> 0 | H18: 0 | I18: 0 | J18: =H18*I18 -> 0 | K18: =G18+J18 -> 0 | M18: =M17+K18-L18 -> 55841.194
A19: 16 | B19: 45946 | E19: 35 | F19: 91.23 | G19: =E19*F19 -> 3193.05 | H19: 0 | I19: 0 | J19: =H19*I19 -> 0 | K19: =G19+J19 -> 3193.05 | M19: =M18+K19-L19 -> 59034.244
A20: 17 | B20: 45947 | E20: 122.16 | F20: 91.23 | G20: =E20*F20 -> 11144.657 | H20: 0 | I20: 0 | J20: =H20*I20 -> 0 | K20: =G20+J20 -> 11144.657 | M20: =M19+K20-L20 -> 70178.901
A21: 18 | B21: 45948 | E21: 0 | F21: 0 | G21: =E21*F21 -> 0 | H21: 0 | I21: 0 | J21: =H21*I21 -> 0 | K21: =G21+J21 -> 0 | M21: =M20+K21-L21 -> 70178.901
A22: 19 | B22: 45949 | E22: 0 | F22: 0 | G22: =E22*F22 -> 0 | H22: 0 | I22: 0 | J22: =H22*I22 -> 0 | K22: =G22+J22 -> 0 | M22: =M21+K22-L22 -> 70178.901
... A25: 22 | B25: 45952 | E25: 42.89 | F25: 91.23 | G25: =E25*F25 -> 3912.8547 | H25: 5 | I25: 103.16 | J25: =H25*I25 -> 515.8 | K25: =G25+J25 -> 4428.6547 | M25: =M24+K25-L25 -> 83293.64
A26: 23 | B26: 45953 | E26: 59.34 | F26: 91.23 | G26: =E26*F26 -> 5413.5882 | H26: 5 | I26: 103.16 | J26: =H26*I26 -> 515.8 | K26: =G26+J26 -> 5929.3882 | M26: =M25+K26-L26 -> 89223.028 | O26: 51702
A27: 24 | B27: 45954 | E27: 0 | F27: 0 | G27: =E27*F27 -> 0 | H27: 0 | I27: 0 | J27: =H27*I27 -> 0 | K27: =G27+J27 -> 0 | M27: =M26+K27-L27 -> 89223.028
A28: 25 | B28: 45955 | E28: 219.94 | F28: 91.23 | G28: =E28*F28 -> 20065.126 | H28: 0 | I28: 0 | J28: =H28*I28 -> 0 | K28: =G28+J28 -> 20065.126 | M28: =M27+K28-L28 -> 109288.15
A29: 26 | B29: 45956 | E29: 0 | F29: 0 | G29: =E29*F29 -> 0 | H29: 10 | I29: 103.16 | J29: =H29*I29 -> 1031.6 | K29: =G29+J29 -> 1031.6 | M29: =M28+K29-L29 -> 110319.75
A30: 27 | B30: 45957 | E30: 75.51 | F30: 91.23 | G30: =E30*F30 -> 6888.7773 | H30: 12 | I30: 103.16 | J30: =H30*I30 -> 1237.92 | K30: =G30+J30 -> 8126.6973 | M30: =M29+K30-L30 -> 118446.45
A31: 28 | B31: 45958 | E31: 136.22 | F31: 91.23 | G31: =E31*F31 -> 12427.351 | H31: 5 | I31: 103.16 | J31: =H31*I31 -> 515.8 | K31: =G31+J31 -> 12943.151 | M31: =M30+K31-L31 -> 131389.6
A32: 29 | B32: 45959 | E32: 0 | F32: 0 | G32: =E32*F32 -> 0 | H32: 0 | I32: 0 | J32: =H32*I32 -> 0 | K32: =G32+J32 -> 0 | M32: =M31+K32-L32 -> 131389.6
A33: 30 | B33: 45960 | E33: 7 | F33: 91.23 | G33: =E33*F33 -> 638.61 | H33: 7 | I33: 103.16 | J33: =H33*I33 -> 722.12 | K33: =G33+J33 -> 1360.73 | M33: =M32+K33-L33 -> 132750.33
A34: 31 | B34: 45961 | E34: 116.7 | F34: 91.23 | G34: =E34*F34 -> 10646.541 | H34: 0 | I34: 0 | J34: =H34*I34 -> 0 | K34: =G34+J34 -> 10646.541 | M34: =M33+K34-L34 -> 143396.87
E35: =SUM(E4:E34) -> 1424.68 | G35: =SUM(G4:G34) -> 129973.56 | H35: =SUM(H4:H34) -> 102.18 | J35: =SUM(J4:J34) -> 10540.889 | K35: =SUM(K4:K34) -> 140514.45 | L35: =SUM(L4:L31) -> 90000

Sheet Sindagi
A1: G.P.PORWAL
A2: S.No | B2: Date | C2: GRN No | D2: Ind no/Bill No | E2: Diesel (Lts) | F2: Price | G2: Amount | H2: Petrol (Lts) | I2: Price | J2: Amount | K2: Total amount | L2: Amount paid | M2: As on Date | N2: Remarks
A3: Opening Balance | M3: 0
A4: 1 | E4: 0 | F4: 0 | G4: =E4*F4 -> 0 | H4: 0 | I4: 0 | J4: =H4*I4 -> 0 | K4: =G4+J4 -> 0 | L4: 0 | M4: =M3+K4-L4 -> 0 | O4: 908.2041
A5: 2 | E5: 0 | F5: 0 | G5: =E5*F5 -> 0 | H5: 0 | I5: 0 | J5: =H5*I5 -> 0 | K5: =G5+J5 -> 0 | L5: 0 | M5: =M4+K5-L5 -> 0
A6: 3 | E6: 0 | F6: 0 | G6: =E6*F6 -> 0 | H6: 0 | I6: 0 | J6: =H6*I6 -> 0 | K6: =G6+J6 -> 0 | L6: 0 | M6: =M5+K6-L6 -> 0
A7: 4 | E7: 0 | F7: 0 | G7: =E7*F7 -> 0 | H7: 0 | I7: 0 | J7: =H7*I7 -> 0 | K7: =G7+J7 -> 0 | L7: 0 | M7: =M6+K7-L7 -> 0
A8: 5 | E8: 0 | F8: 0 | G8: =E8*F8 -> 0 | H8: 0 | I8: 0 | J8: =H8*I8 -> 0 | K8: =G8+J8 -> 0 | L8: 0 | M8: =M7+K8-L8 -> 0
A9: 6 | E9: 0 | F9: 0 | G9: =E9*F9 -> 0 | H9: 0 | I9: 0 | J9: =H9*I9 -> 0 | K9: =G9+J9 -> 0 | L9: 0 | M9: =M8+K9-L9 -> 0
A10: 7 | E10: 0 | F10: 0 | G10: =E10*F10 -> 0 | H10: 0 | I10: 0 | J10: =H10*I10 -> 0 | K10: =G10+J10 -> 0 | L10: 0 | M10: =M9+K10-L10 -> 0
A11: 8 | E11: 0 | F11: 0 | G11: =E11*F11 -> 0 | H11: 0 | I11: 0 | J11: =H11*I11 -> 0 | K11: =G11+J11 -> 0 | L11: 0 | M11: =M10+K11-L11 -> 0 | P11: =P10+N11-O11 -> 0
A12: 9 | E12: 0 | F12: 0 | G12: =E12*F12 -> 0 | H12: 0 | I12: 0 | J12: =H12*I12 -> 0 | K12: =G12+J12 -> 0 | L12: 0 | M12: =M11+K12-L12 -> 0
A13: 10 | E13: 0 | F13: 0 | G13: =E13*F13 -> 0 | H13: 0 | I13: 0 | J13: =H13*I13 -> 0 | K13: =G13+J13 -> 0 | L13: 0 | M13: =M12+K13-L13 -> 0
A14: 11 | E14: 0 | F14: 0 | G14: =E14*F14 -> 0 | H14: 0 | I14: 0 | J14: =H14*I14 -> 0 | K14: =G14+J14 -> 0 | L14: 0 | M14: =M13+K14-L14 -> 0
A15: 12 | E15: 0 | F15: 0 | G15: =E15*F15 -> 0 | H15: 0 | I15: 0 | J15: =H15*I15 -> 0 | K15: =G15+J15 -> 0 | L15: 0 | M15: =M14+K15-L15 -> 0
A16: 13 | E16: 0 | F16: 0 | G16: =E16*F16 -> 0 | H16: 0 | I16: 0 | J16: =H16*I16 -> 0 | K16: =G16+J16 -> 0 | L16: 0 | M16: =M15+K16-L16 -> 0
A17: 14 | E17: 0 | F17: 0 | G17: =E17*F17 -> 0 | H17: 0 | I17: 0 | J17: =H17*I17 -> 0 | K17: =G17+J17 -> 0 | L17: 0 | M17: =M16+K17-L17 -> 0
A18: 15 | E18: 0 | F18: 0 | G18: =E18*F18 -> 0 | H18: 0 | I18: 0 | J18: =H18*I18 -> 0 | K18: =G18+J18 -> 0 | L18: 0 | M18: =M17+K18-L18 -> 0
A19: 16 | E19: 0 | F19: 0 | G19: =E19*F19 -> 0 | H19: 0 | I19: 0 | J19: =H19*I19 -> 0 | K19: =G19+J19 -> 0 | L19: 0 | M19: =M18+K19-L19 -> 0
A20: 17 | E20: 0 | F20: 0 | G20: =E20*F20 -> 0 | H20: 0 | I20: 0 | J20: =H20*I20 -> 0 | K20: =G20+J20 -> 0 | L20: 0 | M20: =M19+K20-L20 -> 0
A21: 18 | E21: 0 | F21: 0 | G21: =E21*F21 -> 0 | H21: 0 | I21: 0 | J21: =H21*I21 -> 0 | K21: =G21+J21 -> 0 | L21: 0 | M21: =M20+K21-L21 -> 0
A22: 19 | E22: 0 | F22: 0 | G22: =E22*F22 -> 0 | H22: 0 | I22: 0 | J22: =H22*I22 -> 0 | K22: =G22+J22 -> 0 | L22: 0 | M22: =M21+K22-L22 -> 0
A23: 20 | E23: 0 | F23: 0 | G23: =E23*F23 -> 0 | H23: 0 | I23: 0 | J23: =H23*I23 -> 0 | K23: =G23+J23 -> 0 | L23: 0 | M23: =M22+K23-L23 -> 0
... A43: 42 | E43: 0 | F43: 0 | G43: =E43*F43 -> 0 | H43: 0 | I43: 0 | J43: =H43*I43 -> 0 | K43: =G43+J43 -> 0 | L43: 0 | M43: =M42+K43-L43 -> 0
E44: =SUM(E4:E43) -> 0 | G44: =SUM(G4:G43) -> 0 | H44: =SUM(H4:H43) -> 0 | J44: =SUM(J4:J43) -> 0 | K44: =SUM(K4:K43) -> 0 | L44: =SUM(L4:L43) -> 0 | M44: =SUM(M4:M43) -> 0

Sheet Alemela
A1: Shiddeshwar Petroleums
A2: S.No | B2: Date | C2: GRN No | D2: Ind no/Bill No | E2: Diesel (Lts) | F2: Price | G2: Amount | H2: Petrol (Lts) | I2: Price | J2: Amount | K2: Total amount | L2: Amount paid | M2: As on Date | N2: Remarks
A3: Opening Balance | M3: 4396.8207
A4: 1 | B4: 03.10.2025 | E4: 0 | F4: 0 | G4: 0 | H4: 13 | I4: 103.26 | J4: =H4*I4 -> 1342.38 | K4: =G4+J4 -> 1342.38 | L4: 0 | M4: =M3+K4-L4 -> 5739.2007 | N4: IOCL Card
A5: 2 | B5: 04.10.2025 | E5: 100 | F5: 91.33 | G5: =E5*F5 -> 9133 | H5: 0 | I5: 0 | J5: =H5*I5 -> 0 | K5: =G5+J5 -> 9133 | L5: 0 | M5: =M4+K5-L5 -> 14872.201 | N5: IOCL Card
A6: 3 | B6: 05.10.2025 | E6: 43.8 | F6: 91.33 | G6: =E6*F6 -> 4000.254 | H6: 5 | I6: 103.26 | J6: =H6*I6 -> 516.3 | K6: =G6+J6 -> 4516.554 | L6: 0 | M6: =M5+K6-L6 -> 19388.755 | N6: IOCL Card
A7: 4 | B7: 07.10.2025 | E7: 0 | F7: 0 | G7: =E7*F7 -> 0 | H7: 8 | I7: 103.26 | J7: =H7*I7 -> 826.08 | K7: =G7+J7 -> 826.08 | L7: 0 | M7: =M6+K7-L7 -> 20214.835 | N7: IOCL Card
A8: 5 | B8: 08.10.2025 | E8: 0 | F8: 0 | G8: =E8*F8 -> 0 | H8: 9.06 | I8: 103.26 | J8: =H8*I8 -> 935.5356 | K8: =G8+J8 -> 935.5356 | L8: 0 | M8: =M7+K8-L8 -> 21150.37 | N8: IOCL Card
A9: 6 | B9: 09.10.2025 | E9: 200 | F9: 91.33 | G9: =E9*F9 -> 18266 | H9: 3 | I9: 103.26 | J9: =H9*I9 -> 309.78 | K9: =G9+J9 -> 18575.78 | L9: 0 | M9: =M8+K9-L9 -> 39726.15 | N9: IOCL Card
A10: 7 | B10: 10.10.2025 | E10: 100 | F10: 91.33 | G10: =E10*F10 -> 9133 | H10: 4 | I10: 103.26 | J10: =H10*I10 -> 413.04 | K10: =G10+J10 -> 9546.04 | L10: 0 | M10: =M9+K10-L10 -> 49272.19 | N10: IOCL Card
A11: 8 | B11: 13.10.2025 | E11: 40 | F11: 91.33 | G11: =E11*F11 -> 3653.2 | H11: 0 | I11: 0 | J11: =H11*I11 -> 0 | K11: =G11+J11 -> 3653.2 | L11: 0 | M11: =M10+K11-L11 -> 52925.39 | N11: IOCL Card
A12: 9 | B12: 15.10.2025 | E12: 31.9 | F12: 91.33 | G12: =E12*F12 -> 2913.427 | H12: 0 | I12: 0 | J12: =H12*I12 -> 0 | K12: =G12+J12 -> 2913.427 | L12: 0 | M12: =M11+K12-L12 -> 55838.817 | N12: IOCL Card
A13: 10 | B13: 16.10.2025 | E13: 411.29 | F13: 91.33 | G13: =E13*F13 -> 37563.116 | H13: 22.81 | I13: 103.26 | J13: =H13*I13 -> 2355.3606 | K13: =G13+J13 -> 39918.476 | L13: 52000 | M13: =M12+K13-L13 -> 43757.294 | N13: IOCL Card
A14: 11 | B14: 17.10.2025 | E14: 0 | F14: 0 | G14: =E14*F14 -> 0 | H14: 0 | I14: 0 | J14: =H14*I14 -> 0 | K14: =G14+J14 -> 0 | L14: 0 | M14: =M13+K14-L14 -> 43757.294 | N14: IOCL Card
A15: 12 | B15: 26.10.2025 | E15: 80 | F15: 91.33 | G15: =E15*F15 -> 7306.4 | H15: 0 | I15: 0 | J15: =H15*I15 -> 0 | K15: =G15+J15 -> 7306.4 | L15: 0 | M15: =M14+K15-L15 -> 51063.694 | N15: IOCL Card
A16: 13 | B16: 27.10.2025 | E16: 0 | F16: 0 | G16: =E16*F16 -> 0 | H16: 2 | I16: 103.26 | J16: =H16*I16 -> 206.52 | K16: =G16+J16 -> 206.52 | L16: 0 | M16: =M15+K16-L16 -> 51270.214 | N16: IOCL Card
A17: 14 | B17: 28.10.2025 | E17: 37.67 | F17: 91.33 | G17: =E17*F17 -> 3440.4011 | H17: 0 | I17: 0 | J17: =H17*I17 -> 0 | K17: =G17+J17 -> 3440.4011 | L17: 0 | M17: =M16+K17-L17 -> 54710.615 | N17: IOCL Card
A18: 15 | B18: 30.10.2025 | E18: 0 | F18: 0 | G18: 0 | H18: 5 | I18: 103.26 | J18: =H18*I18 -> 516.3 | K18: =G18+J18 -> 516.3 | L18: 0 | M18: =M17+K18-L18 -> 55226.915 | N18: IOCL Card
A19: 16 | B19: 31.10.2025 | E19: 0 | F19: 0 | G19: 0 | H19: 11 | I19: 103.26 | J19: =H19*I19 -> 1135.86 | K19: =G19+J19 -> 1135.86 | L19: 0 | M19: =M18+K19-L19 -> 56362.775 | N19: IOCL Card
A20: 17 | E20: 0 | F20: 0 | G20: 0 | H20: 0 | I20: 0 | J20: =H20*I20 -> 0 | K20: =G20+J20 -> 0 | L20: 0 | M20: =M19+K20-L20 -> 56362.775 | N20: IOCL Card
A21: 18 | E21: 0 | F21: 0 | G21: 0 | H21: 0 | I21: 0 | J21: =H21*I21 -> 0 | K21: =G21+J21 -> 0 | L21: 0 | M21: =M20+K21-L21 -> 56362.775 | N21: IOCL Card
A22: 19 | E22: 0 | F22: 0 | G22: 0 | H22: 0 | I22: 0 | J22: =H22*I22 -> 0 | K22: =G22+J22 -> 0 | L22: 0 | M22: =M21+K22-L22 -> 56362.775 | N22: IOCL Card
A23: 20 | E23: 0 | F23: 0 | G23: 0 | H23: 0 | I23: 0 | J23: =H23*I23 -> 0 | K23: =G23+J23 -> 0 | L23: 0 | M23: =M22+K23-L23 -> 56362.775
A24: 21 | E24: 0 | F24: 0 | G24: 0 | H24: 0 | I24: 0 | J24: =H24*I24 -> 0 | K24: =G24+J24 -> 0 | L24: 0 | M24: =M23+K24-L24 -> 56362.775
A25: 22 | E25: 0 | F25: 0 | G25: 0 | H25: 0 | I25: 0 | J25: =H25*I25 -> 0 | K25: =G25+J25 -> 0 | L25: 0 | M25: =M24+K25-L25 -> 56362.775
A26: 23 | E26: 0 | F26: 0 | G26: 0 | H26: 0 | I26: 0 | J26: =H26*I26 -> 0 | K26: =G26+J26 -> 0 | L26: 0 | M26: =M25+K26-L26 -> 56362.775
A27: 24 | E27: 0 | F27: 0 | G27: 0 | H27: 0 | I27: 0 | J27: =H27*I27 -> 0 | K27: =G27+J27 -> 0 | L27: 0 | M27: =M26+K27-L27 -> 56362.775
A28: 25 | E28: 0 | F28: 0 | G28: 0 | H28: 0 | I28: 0 | J28: =H28*I28 -> 0 | K28: =G28+J28 -> 0 | L28: 0 | M28: =M27+K28-L28 -> 56362.775
A29: 26 | E29: 0 | F29: 0 | G29: 0 | H29: 0 | I29: 0 | J29: =H29*I29 -> 0 | K29: =G29+J29 -> 0 | L29: 0 | M29: =M28+K29-L29 -> 56362.775
A30: 27 | E30: 0 | F30: 0 | G30: 0 | H30: 0 | I30: 0 | J30: =H30*I30 -> 0 | K30: =G30+J30 -> 0 | L30: 0 | M30: =M29+K30-L30 -> 56362.775
A31: 28 | E31: 0 | F31: 0 | G31: 0 | H31: 0 | I31: 0 | J31: =H31*I31 -> 0 | K31: =G31+J31 -> 0 | L31: 0 | M31: =M30+K31-L31 -> 56362.775
A32: 29 | E32: 0 | F32: 0 | G32: 0 | H32: 0 | I32: 0 | J32: =H32*I32 -> 0 | K32: =G32+J32 -> 0 | L32: 0 | M32: =M31+K32-L32 -> 56362.775
A33: 30 | E33: 0 | F33: 0 | G33: 0 | H33: 0 | I33: 0 | J33: =H33*I33 -> 0 | K33: =G33+J33 -> 0 | L33: 0 | M33: =M32+K33-L33 -> 56362.775
A34: 31 | E34: 0 | F34: 0 | G34: 0 | H34: 0 | I34: 0 | J34: =H34*I34 -> 0 | K34: =G34+J34 -> 0 | L34: 0 | M34: =M33+K34-L34 -> 56362.775
... A41: 41 | E41: 0 | F41: 0 | G41: 0 | H41: 0 | I41: 0 | J41: =H41*I41 -> 0 | K41: =G41+J41 -> 0 | L41: 0 | M41: =M40+K41-L41 -> 56362.775
A42: 42 | E42: 0 | F42: 0 | G42: =E42*F42 -> 0 | J42: =H42*I42 -> 0 | K42: =G42+J42 -> 0 | L42: =+K42 -> 0 | M42: =M41+K42-L42 -> 56362.775
E43: =SUM(E4:E42) -> 1044.66 | G43: =SUM(G4:G42) -> 95408.798 | H43: =SUM(H4:H42) -> 82.87 | J43: =SUM(J4:J42) -> 8557.1562 | K43: =SUM(K4:K42) -> 103965.95 | L43: =SUM(L4:L42) -> 52000
L46: 41648.541
L47: =L43+L46 -> 93648.541

Sheet Nalatwad
A1: Shri Pawad Basaweshwar Petroleums
A2: S.No | B2: Date | C2: GRN No | D2: Ind no/Bill No | E2: Diesel (Lts) | F2: Price | G2: Amount | H2: Petrol (Lts) | I2: Price | J2: Amount | K2: Total amount | L2: Amount paid | M2: As on Date | N2: Remarks
A3: Opening Balance | M3: 19544.637
A4: 1 | B4: 45931 | E4: 0 | F4: 0 | G4: =E4*F4 -> 0 | H4: 0 | I4: 0 | J4: =H4*I4 -> 0 | K4: =G4+J4 -> 0 | L4: 0 | M4: =M3+K4-L4 -> 19544.637 | N4: IOCL Card
A5: 2 | B5: 45932 | E5: 0 | F5: 0 | G5: =E5*F5 -> 0 | H5: 0 | I5: 0 | J5: =H5*I5 -> 0 | K5: =G5+J5 -> 0 | L5: 0 | M5: =M4+K5-L5 -> 19544.637 | N5: IOCL Card
A6: 3 | B6: 45933 | E6: 0 | F6: 0 | G6: =E6*F6 -> 0 | H6: 5.98 | I6: 103.57 | J6: =H6*I6 -> 619.3486 | K6: =G6+J6 -> 619.3486 | L6: 0 | M6: =M5+K6-L6 -> 20163.986 | N6: IOCL Card
A7: 4 | B7: 45934 | E7: 0 | F7: 0 | G7: =E7*F7 -> 0 | H7: 0 | I7: 0 | J7: =H7*I7 -> 0 | K7: =G7+J7 -> 0 | L7: 0 | M7: =M6+K7-L7 -> 20163.986 | N7: IOCL Card
A8: 5 | B8: 45935 | E8: 43.66 | F8: 91.62 | G8: =E8*F8 -> 4000.1292 | H8: 0 | I8: 0 | J8: =H8*I8 -> 0 | K8: =G8+J8 -> 4000.1292 | L8: 0 | M8: =M7+K8-L8 -> 24164.115 | N8: IOCL Card
A9: 6 | B9: 45936 | E9: 0 | F9: 0 | G9: =E9*F9 -> 0 | H9: 0 | I9: 0 | J9: =H9*I9 -> 0 | K9: =G9+J9 -> 0 | L9: 0 | M9: =M8+K9-L9 -> 24164.115 | N9: IOCL Card
A10: 7 | B10: 45937 | E10: 70.95 | F10: 91.62 | G10: =E10*F10 -> 6500.439 | H10: 5 | I10: 103.57 | J10: =H10*I10 -> 517.85 | K10: =G10+J10 -> 7018.289 | L10: 0 | M10: =M9+K10-L10 -> 31182.404 | N10: IOCL Card
A11: 8 | B11: 45938 | E11: 0 | F11: 0 | G11: =E11*F11 -> 0 | H11: 0 | I11: 0 | J11: =H11*I11 -> 0 | K11: =G11+J11 -> 0 | L11: 0 | M11: =M10+K11-L11 -> 31182.404 | N11: IOCL Card
A12: 9 | B12: 45939 | E12: 21.83 | F12: 91.62 | G12: =E12*F12 -> 2000.0646 | H12: 0 | I12: 0 | J12: =H12*I12 -> 0 | K12: =G12+J12 -> 2000.0646 | L12: 0 | M12: =M11+K12-L12 -> 33182.469 | N12: IOCL Card
A13: 10 | B13: 45940 | E13: 49.11 | F13: 91.62 | G13: =E13*F13 -> 4499.4582 | H13: 5.25 | I13: 103.57 | J13: =H13*I13 -> 543.7425 | K13: =G13+J13 -> 5043.2007 | L13: 0 | M13: =M12+K13-L13 -> 38225.67 | N13: IOCL Card
A14: 11 | B14: 45941 | E14: 0 | F14: 0 | G14: =E14*F14 -> 0 | H14: 0 | I14: 0 | J14: =H14*I14 -> 0 | K14: =G14+J14 -> 0 | L14: 0 | M14: =M13+K14-L14 -> 38225.67 | N14: IOCL Card
A15: 12 | B15: 45942 | E15: 49.11 | F15: 91.62 | G15: =E15*F15 -> 4499.4582 | H15: 0 | I15: 0 | J15: =H15*I15 -> 0 | K15: =G15+J15 -> 4499.4582 | L15: 0 | M15: =M14+K15-L15 -> 42725.128 | N15: IOCL Card
... A22: 19 | B22: 45949 | E22: 0 | F22: 0 | G22: =E22*F22 -> 0 | H22: 0 | I22: 0 | J22: =H22*I22 -> 0 | K22: =G22+J22 -> 0 | L22: 0 | M22: =M21+K22-L22 -> 17551.83 | N22: IOCL Card
A23: 20 | B23: 45950 | E23: 0 | F23: 0 | G23: =E23*F23 -> 0 | H23: 0 | I23: 0 | J23: =H23*I23 -> 0 | K23: =G23+J23 -> 0 | L23: 0 | M23: =M22+K23-L23 -> 17551.83
A24: 21 | B24: 45951 | E24: 0 | F24: 0 | G24: =E24*F24 -> 0 | H24: 9.66 | I24: 103.47 | J24: =H24*I24 -> 999.5202 | K24: =G24+J24 -> 999.5202 | L24: 0 | M24: =M23+K24-L24 -> 18551.35
A25: 22 | B25: 45952 | E25: 0 | F25: 0 | G25: =E25*F25 -> 0 | H25: 0 | I25: 0 | J25: =H25*I25 -> 0 | K25: =G25+J25 -> 0 | L25: 0 | M25: =M24+K25-L25 -> 18551.35
A26: 23 | B26: 45953 | E26: 0 | F26: 0 | G26: =E26*F26 -> 0 | H26: 0 | I26: 0 | J26: =H26*I26 -> 0 | K26: =G26+J26 -> 0 | L26: 0 | M26: =M25+K26-L26 -> 18551.35
A27: 24 | B27: 45954 | E27: 25 | F27: 91.62 | G27: =E27*F27 -> 2290.5 | H27: 0 | I27: 0 | J27: =H27*I27 -> 0 | K27: =G27+J27 -> 2290.5 | L27: 0 | M27: =M26+K27-L27 -> 20841.85
A28: 25 | B28: 45955 | E28: 0 | F28: 0 | G28: =E28*F28 -> 0 | H28: 0 | I28: 0 | J28: =H28*I28 -> 0 | K28: =G28+J28 -> 0 | L28: 0 | M28: =M27+K28-L28 -> 20841.85
A29: 26 | B29: 45956 | E29: 0 | F29: 0 | G29: =E29*F29 -> 0 | H29: 0 | I29: 0 | J29: =H29*I29 -> 0 | K29: =G29+J29 -> 0 | L29: 0 | M29: =M28+K29-L29 -> 20841.85
A30: 27 | B30: 45957 | E30: 16.37 | F30: 91.62 | G30: =E30*F30 -> 1499.8194 | H30: 0 | I30: 0 | J30: =H30*I30 -> 0 | K30: =G30+J30 -> 1499.8194 | L30: 0 | M30: =M29+K30-L30 -> 22341.67
A31: 28 | B31: 45958 | E31: 0 | F31: 0 | G31: =E31*F31 -> 0 | H31: 4.83 | I31: 103.47 | J31: =H31*I31 -> 499.7601 | K31: =G31+J31 -> 499.7601 | L31: 0 | M31: =M30+K31-L31 -> 22841.43
A32: 29 | B32: 45959 | E32: 0 | F32: 0 | G32: =E32*F32 -> 0 | H32: 0 | I32: 0 | J32: =H32*I32 -> 0 | K32: =G32+J32 -> 0 | L32: 0 | M32: =M31+K32-L32 -> 22841.43
A33: 30 | B33: 45960 | E33: 0 | F33: 0 | G33: =E33*F33 -> 0 | H33: 6.62 | I33: 103.47 | J33: =H33*I33 -> 684.9714 | K33: =G33+J33 -> 684.9714 | L33: 0 | M33: =M32+K33-L33 -> 23526.401
A34: 31 | E34: 0 | F34: 0 | G34: =E34*F34 -> 0 | H34: 0 | I34: 0 | J34: =H34*I34 -> 0 | K34: =G34+J34 -> 0 | L34: 0 | M34: =M33+K34-L34 -> 23526.401
A35: 35 | E35: 0 | F35: 0 | G35: =E35*F35 -> 0 | H35: 0 | I35: 0 | J35: =H35*I35 -> 0 | K35: =G35+J35 -> 0 | L35: 0 | M35: =M34+K35-L35 -> 23526.401
A36: 36 | E36: 0 | F36: 0 | G36: =E36*F36 -> 0 | H36: 0 | I36: 0 | J36: =H36*I36 -> 0 | K36: =G36+J36 -> 0 | L36: 0 | M36: =M35+K36-L36 -> 23526.401
A37: 37 | E37: 0 | F37: 0 | G37: =E37*F37 -> 0 | H37: 0 | I37: 0 | J37: =H37*I37 -> 0 | K37: =G37+J37 -> 0 | L37: 0 | M37: =M36+K37-L37 -> 23526.401
A38: 38 | E38: 0 | F38: 0 | G38: =E38*F38 -> 0 | H38: 0 | I38: 0 | J38: =H38*I38 -> 0 | K38: =G38+J38 -> 0 | L38: 0 | M38: =M37+K38-L38 -> 23526.401
A39: 39 | E39: 0 | F39: 0 | G39: =E39*F39 -> 0 | H39: 0 | I39: 0 | J39: =H39*I39 -> 0 | K39: =G39+J39 -> 0 | L39: 0 | M39: =M38+K39-L39 -> 23526.401
A40: 40 | E40: 0 | F40: 0 | G40: =E40*F40 -> 0 | H40: 0 | I40: 0 | J40: =H40*I40 -> 0 | K40: =G40+J40 -> 0 | L40: 0 | M40: 0
A41: 41 | E41: 0 | F41: 0 | G41: =E41*F41 -> 0 | H41: 0 | I41: 0 | J41: =H41*I41 -> 0 | K41: =G41+J41 -> 0 | L41: 0 | M41: 0
A42: 42 | E42: 0 | F42: 0 | G42: =E42*F42 -> 0 | J42: =H42*I42 -> 0 | K42: =G42+J42 -> 0 | L42: =+K42 -> 0 | M42: 0
E43: =SUM(E4:E42) -> 541.55 | G43: =SUM(G4:G42) -> 49616.811 | H43: =SUM(H4:H42) -> 42.17 | J43: =SUM(J4:J42) -> 4364.9529 | K43: =SUM(K4:K42) -> 53981.764 | L43: =SUM(L4:L42) -> 50000
Q47: 9542400867

Sheet Muddebihal
A1: Bhosle Service Station
A2: S.No | B2: Date | C2: GRN No | D2: Ind no/Bill No | E2: Diesel (Lts) | F2: Price | G2: Amount | H2: Petrol (Lts) | I2: Price | J2: Amount | K2: Total amount | L2: Amount paid | M2: As on Date | N2: Remarks
A3: Opening Balance | M3: 30403.024
A4: 1 | B4: 01.10.2025 | E4: 0 | F4: 0 | G4: =E4*F4 -> 0 | H4: 5 | I4: 103.39 | J4: =H4*I4 -> 516.95 | K4: =G4+J4 -> 516.95 | L4: 0 | M4: =M3+K4-L4 -> 30919.974 | N4: IOCL Card
A5: 2 | B5: 03.10.2025 | E5: 35 | F5: 91.45 | G5: =E5*F5 -> 3200.75 | H5: 0 | I5: 0 | J5: =H5*I5 -> 0 | K5: =G5+J5 -> 3200.75 | L5: 0 | M5: =M4+K5-L5 -> 34120.724 | N5: IOCL Card
A6: 3 | B6: 06.10.2025 | E6: 54.67 | F6: 91.45 | G6: =E6*F6 -> 4999.5715 | H6: 0 | I6: 0 | J6: =H6*I6 -> 0 | K6: =G6+J6 -> 4999.5715 | L6: 0 | M6: =M5+K6-L6 -> 39120.296 | N6: IOCL Card
A7: 4 | B7: 07.10.2025 | E7: 113 | F7: 91.45 | G7: =E7*F7 -> 10333.85 | H7: 0 | I7: 0 | J7: =H7*I7 -> 0 | K7: =G7+J7 -> 10333.85 | L7: 40000 | M7: =M6+K7-L7 -> 9454.1457 | N7: IOCL Card
A8: 5 | B8: 08.10.2025 | E8: 15 | F8: 91.45 | G8: =E8*F8 -> 1371.75 | H8: 9.84 | I8: 103.39 | J8: =H8*I8 -> 1017.3576 | K8: =G8+J8 -> 2389.1076 | L8: 0 | M8: =M7+K8-L8 -> 11843.253 | N8: IOCL Card
A9: 6 | B9: 09.10.2025 | E9: 70 | F9: 91.45 | G9: =E9*F9 -> 6401.5 | H9: 0 | I9: 0 | J9: =H9*I9 -> 0 | K9: =G9+J9 -> 6401.5 | L9: 0 | M9: =M8+K9-L9 -> 18244.753 | N9: IOCL Card
A10: 7 | B10: 10.10.2025 | E10: 110 | F10: 91.45 | G10: =E10*F10 -> 10059.5 | H10: 0 | I10: 0 | J10: =H10*I10 -> 0 | K10: =G10+J10 -> 10059.5 | L10: 0 | M10: =M9+K10-L10 -> 28304.253 | N10: IOCL Card
A11: 8 | B11: 11.10.2025 | E11: =35+35+54.67 -> 124.67 | F11: 91.45 | G11: =E11*F11 -> 11401.072 | H11: 0 | I11: 0 | J11: =H11*I11 -> 0 | K11: =G11+J11 -> 11401.072 | L11: 0 | M11: =M10+K11-L11 -> 39705.325 | N11: IOCL Card
A12: 9 | B12: 12.10.2025 | E12: 25 | F12: 91.45 | G12: =E12*F12 -> 2286.25 | H12: 0 | I12: 0 | J12: =H12*I12 -> 0 | K12: =G12+J12 -> 2286.25 | L12: 0 | M12: =M11+K12-L12 -> 41991.575 | N12: IOCL Card
A13: 10 | B13: 13.10.2025 | E13: 70 | F13: 91.45 | G13: =E13*F13 -> 6401.5 | H13: 0 | I13: 0 | J13: =H13*I13 -> 0 | K13: =G13+J13 -> 6401.5 | L13: 0 | M13: =M12+K13-L13 -> 48393.075 | N13: IOCL Card
A14: 11 | B14: 14.10.2025 | E14: 0 | F14: 0 | G14: =E14*F14 -> 0 | H14: 0 | I14: 103.35 | J14: =H14*I14 -> 0 | K14: =G14+J14 -> 0 | L14: 0 | M14: =M13+K14-L14 -> 48393.075 | N14: IOCL Card
A15: 12 | B15: 16.10.2025 | E15: 0 | F15: 0 | G15: =E15*F15 -> 0 | H15: 0 | I15: 0 | J15: =H15*I15 -> 0 | K15: =G15+J15 -> 0 | L15: 48000 | M15: =M14+K15-L15 -> 393.0748 | N15: IOCL Card
A16: 13 | B16: 31.10.2025 | E16: 35 | F16: 91.45 | G16: =E16*F16 -> 3200.75 | H16: 0 | I16: 0 | J16: =H16*I16 -> 0 | K16: =G16+J16 -> 3200.75 | L16: 0 | M16: =M15+K16-L16 -> 3593.8248 | N16: IOCL Card
A17: 14 | E17: 0 | F17: 0 | G17: =E17*F17 -> 0 | H17: 0 | I17: 103.35 | J17: =H17*I17 -> 0 | K17: =G17+J17 -> 0 | L17: 0 | M17: =M16+K17-L17 -> 3593.8248 | N17: IOCL Card
A18: 15 | E18: 0 | F18: 0 | G18: =E18*F18 -> 0 | H18: 0 | I18: 0 | J18: =H18*I18 -> 0 | K18: =G18+J18 -> 0 | L18: 0 | M18: =M17+K18-L18 -> 3593.8248 | N18: IOCL Card
A19: 16 | E19: 0 | F19: 0 | G19: =E19*F19 -> 0 | H19: 0 | I19: 0 | J19: =H19*I19 -> 0 | K19: =G19+J19 -> 0 | L19: 0 | M19: =M18+K19-L19 -> 3593.8248 | N19: IOCL Card
A20: 17 | E20: 0 | F20: 0 | G20: =E20*F20 -> 0 | H20: 0 | I20: 0 | J20: =H20*I20 -> 0 | K20: =G20+J20 -> 0 | L20: 0 | M20: =M19+K20-L20 -> 3593.8248 | N20: IOCL Card
A21: 18 | E21: 0 | F21: 0 | G21: =E21*F21 -> 0 | H21: 0 | I21: 0 | J21: =H21*I21 -> 0 | K21: =G21+J21 -> 0 | L21: 0 | M21: =M20+K21-L21 -> 3593.8248 | N21: IOCL Card | Q21: =76.54*91.45 -> 6999.583 | T21: =25*600 -> 15000 | U21: =T21*2 -> 30000 | V21: =250*600 -> 150000
A22: 19 | E22: 0 | F22: 0 | G22: =E22*F22 -> 0 | H22: 0 | I22: 0 | J22: =H22*I22 -> 0 | K22: =G22+J22 -> 0 | L22: 0 | M22: =M21+K22-L22 -> 3593.8248 | N22: IOCL Card | T22: =25*480 -> 12000 | U22: =T22*2 -> 24000 | V22: =250*480 -> 120000
A23: 20 | E23: 0 | F23: 0 | G23: =E23*F23 -> 0 | H23: 0 | I23: 0 | J23: =H23*I23 -> 0 | K23: =G23+J23 -> 0 | L23: 0 | M23: =M22+K23-L23 -> 3593.8248 | N23: IOCL Card
A24: 21 | E24: 0 | F24: 0 | G24: =E24*F24 -> 0 | H24: 0 | I24: 0 | J24: =H24*I24 -> 0 | K24: =G24+J24 -> 0 | L24: 0 | M24: =M23+K24-L24 -> 3593.8248 | N24: IOCL Card
A25: 22 | E25: 0 | F25: 0 | G25: =E25*F25 -> 0 | H25: 0 | I25: 0 | J25: =H25*I25 -> 0 | K25: =G25+J25 -> 0 | L25: 0 | M25: =M24+K25-L25 -> 3593.8248 | N25: IOCL Card
A26: 23 | E26: 0 | F26: 0 | G26: =E26*F26 -> 0 | H26: 0 | I26: 0 | J26: =H26*I26 -> 0 | K26: =G26+J26 -> 0 | L26: 0 | M26: =M25+K26-L26 -> 3593.8248 | N26: IOCL Card | O26: 14616
A27: 24 | E27: 0 | F27: 0 | G27: =E27*F27 -> 0 | H27: 0 | I27: 0 | J27: =H27*I27 -> 0 | K27: =G27+J27 -> 0 | L27: 0 | M27: =M26+K27-L27 -> 3593.8248 | N27: IOCL Card
A28: 25 | E28: 0 | F28: 0 | G28: =E28*F28 -> 0 | H28: 0 | I28: 0 | J28: =H28*I28 -> 0 | K28: =G28+J28 -> 0 | L28: 0 | M28: =M27+K28-L28 -> 3593.8248 | N28: IOCL Card
A29: 26 | E29: 0 | F29: 0 | G29: =E29*F29 -> 0 | H29: 0 | I29: 0 | J29: =H29*I29 -> 0 | K29: =G29+J29 -> 0 | L29: 0 | M29: =M28+K29-L29 -> 3593.8248 | N29: IOCL Card
A30: 27 | E30: 0 | F30: 0 | G30: =E30*F30 -> 0 | H30: 0 | I30: 0 | J30: =H30*I30 -> 0 | K30: =G30+J30 -> 0 | L30: 0 | M30: =M29+K30-L30 -> 3593.8248 | N30: IOCL Card
A31: 28 | E31: 0 | F31: 0 | G31: =E31*F31 -> 0 | H31: 0 | I31: 0 | J31: =H31*I31 -> 0 | K31: =G31+J31 -> 0 | L31: 0 | M31: =M30+K31-L31 -> 3593.8248 | N31: IOCL Card
A32: 29 | E32: 0 | F32: 0 | G32: =E32*F32 -> 0 | H32: 0 | I32: 0 | J32: =H32*I32 -> 0 | K32: =G32+J32 -> 0 | L32: 0 | M32: =M31+K32-L32 -> 3593.8248 | N32: IOCL Card
A33: 30 | E33: 0 | F33: 0 | G33: =E33*F33 -> 0 | H33: 0 | I33: 0 | J33: =H33*I33 -> 0 | K33: =G33+J33 -> 0 | L33: 0 | M33: =M32+K33-L33 -> 3593.8248 | N33: IOCL Card
A34: 31 | E34: 0 | F34: 0 | G34: =E34*F34 -> 0 | H34: 0 | I34: 0 | J34: =H34*I34 -> 0 | K34: =G34+J34 -> 0 | L34: 0 | M34: =M33+K34-L34 -> 3593.8248 | N34: IOCL Card
A35: 32 | E35: 0 | F35: 0 | G35: =E35*F35 -> 0 | H35: 0 | I35: 0 | J35: =H35*I35 -> 0 | K35: =G35+J35 -> 0 | L35: 0 | M35: =M34+K35-L35 -> 3593.8248 | N35: IOCL Card
A36: 33 | E36: 0 | F36: 0 | G36: =E36*F36 -> 0 | H36: 0 | I36: 0 | J36: =H36*I36 -> 0 | K36: =G36+J36 -> 0 | L36: 0 | M36: =M35+K36-L36 -> 3593.8248 | N36: IOCL Card
A37: 34 | E37: 0 | F37: 0 | G37: =E37*F37 -> 0 | H37: 0 | I37: 0 | J37: =H37*I37 -> 0 | K37: =G37+J37 -> 0 | L37: 0 | M37: =M36+K37-L37 -> 3593.8248 | N37: IOCL Card
A38: 35 | E38: 0 | F38: 0 | G38: =E38*F38 -> 0 | H38: 0 | I38: 0 | J38: =H38*I38 -> 0 | K38: =G38+J38 -> 0 | L38: 0 | M38: =M37+K38-L38 -> 3593.8248
A39: 36 | E39: 0 | F39: 0 | G39: =E39*F39 -> 0 | H39: 0 | I39: 0 | J39: =H39*I39 -> 0 | K39: =G39+J39 -> 0 | L39: 0 | M39: =M38+K39-L39 -> 3593.8248
A40: 37 | E40: 0 | F40: 0 | G40: =E40*F40 -> 0 | H40: 0 | I40: 0 | J40: =H40*I40 -> 0 | K40: =G40+J40 -> 0 | L40: 0 | M40: =M39+K40-L40 -> 3593.8248
A41: 38 | E41: 0 | F41: 0 | G41: =E41*F41 -> 0 | H41: 0 | I41: 0 | J41: =H41*I41 -> 0 | K41: =G41+J41 -> 0 | L41: 0 | M41: =M40+K41-L41 -> 3593.8248
A42: 39 | E42: 0 | F42: 0 | G42: =E42*F42 -> 0 | H42: 0 | I42: 0 | J42: =H42*I42 -> 0 | K42: =G42+J42 -> 0 | L42: 0 | M42: =M41+K42-L42 -> 3593.8248
A43: 40 | E43: 0 | F43: 0 | G43: =E43*F43 -> 0 | H43: 0 | I43: 0 | J43: =H43*I43 -> 0 | K43: =G43+J43 -> 0 | L43: 0 | M43: =M42+K43-L43 -> 3593.8248
A44: 41 | E44: 0 | F44: 0 | G44: =E44*F44 -> 0 | H44: 0 | I44: 0 | J44: =H44*I44 -> 0 | K44: =G44+J44 -> 0 | L44: 0 | M44: =M43+K44-L44 -> 3593.8248
A45: 42 | E45: 0 | F45: 0 | G45: =E45*F45 -> 0 | J45: =H45*I45 -> 0 | K45: =G45+J45 -> 0 | L45: =+K45 -> 0 | M45: =M44+K45-L45 -> 3593.8248
E46: 0 | F46: 0 | G46: =E46*F46 -> 0 | J46: =H46*I46 -> 0 | K46: =G46+J46 -> 0 | L46: =+K46 -> 0 | M46: =M45+K46-L46 -> 3593.8248
E47: =SUM(E4:E46) -> 652.34 | G47: =SUM(G4:G46) -> 59656.493 | H47: =SUM(H4:H46) -> 14.84 | J47: =SUM(J4:J46) -> 1534.3076 | K47: =SUM(K4:K46) -> 61190.801 | L47: =SUM(L4:L46) -> 88000

Sheet Muddebhihal-2
A1: PS NAGATHAN PETROLIUM
A2: S.No | B2: Date | C2: GRN No | D2: Ind no/Bill No | E2: Diesel (Lts) | F2: Price | G2: Amount | H2: Petrol (Lts) | I2: Price | J2: Amount | K2: Total amount | L2: Amount paid | M2: As on Date | N2: Remarks
A3: Opening Balance
A4: 1 | B4: 01.10.2025 | E4: 0 | F4: 0 | G4: =E4*F4 -> 0 | H4: 0 | I4: 0 | J4: =H4*I4 -> 0 | K4: =G4+J4 -> 0 | L4: 0 | M4: =M3+K4-L4 -> 0
A5: 2 | B5: 03.10.2025 | E5: 0 | F5: 0 | G5: =E5*F5 -> 0 | H5: 0 | I5: 0 | J5: =H5*I5 -> 0 | K5: =G5+J5 -> 0 | L5: 0 | M5: =M4+K5-L5 -> 0
A6: 3 | B6: 06.10.2025 | E6: 0 | F6: 0 | G6: =E6*F6 -> 0 | H6: 0 | I6: 0 | J6: =H6*I6 -> 0 | K6: =G6+J6 -> 0 | L6: 0 | M6: =M5+K6-L6 -> 0
A7: 4 | B7: 07.10.2025 | E7: 0 | F7: 0 | G7: =E7*F7 -> 0 | H7: 0 | I7: 0 | J7: =H7*I7 -> 0 | K7: =G7+J7 -> 0 | L7: 0 | M7: =M6+K7-L7 -> 0
A8: 5 | B8: 08.10.2025 | E8: 0 | F8: 0 | G8: =E8*F8 -> 0 | H8: 0 | I8: 0 | J8: =H8*I8 -> 0 | K8: =G8+J8 -> 0 | L8: 0 | M8: =M7+K8-L8 -> 0
A9: 6 | B9: 09.10.2025 | E9: 0 | F9: 0 | G9: =E9*F9 -> 0 | H9: 0 | I9: 0 | J9: =H9*I9 -> 0 | K9: =G9+J9 -> 0 | L9: 0 | M9: =M8+K9-L9 -> 0
A10: 7 | B10: 10.10.2025 | E10: 0 | F10: 0 | G10: =E10*F10 -> 0 | H10: 0 | I10: 0 | J10: =H10*I10 -> 0 | K10: =G10+J10 -> 0 | L10: 0 | M10: =M9+K10-L10 -> 0
A11: 8 | B11: 11.10.2025 | E11: 0 | F11: 0 | G11: =E11*F11 -> 0 | H11: 0 | I11: 0 | J11: =H11*I11 -> 0 | K11: =G11+J11 -> 0 | L11: 0 | M11: =M10+K11-L11 -> 0
A12: 9 | B12: 12.10.2025 | E12: 0 | F12: 0 | G12: =E12*F12 -> 0 | H12: 0 | I12: 0 | J12: =H12*I12 -> 0 | K12: =G12+J12 -> 0 | L12: 0 | M12: =M11+K12-L12 -> 0
A13: 10 | B13: 13.10.2025 | E13: 0 | F13: 0 | G13: =E13*F13 -> 0 | H13: 0 | I13: 0 | J13: =H13*I13 -> 0 | K13: =G13+J13 -> 0 | L13: 0 | M13: =M12+K13-L13 -> 0
A14: 11 | B14: 14.10.2025 | E14: =35+35 -> 70 | F14: 91.42 | G14: =E14*F14 -> 6399.4 | H14: 5 | I14: 103.35 | J14: =H14*I14 -> 516.75 | K14: =G14+J14 -> 6916.15 | L14: 0 | M14: =M13+K14-L14 -> 6916.15
A15: 12 | B15: 15.10.2025 | E15: =8+37+130 -> 175 | F15: 91.42 | G15: =E15*F15 -> 15998.5 | H15: 5 | I15: 103.35 | J15: =H15*I15 -> 516.75 | K15: =G15+J15 -> 16515.25 | L15: 0 | M15: =M14+K15-L15 -> 23431.4
A16: 13 | B16: 18.10.2025 | E16: 120 | F16: 91.42 | G16: =E16*F16 -> 10970.4 | H16: 0 | I16: 0 | J16: =H16*I16 -> 0 | K16: =G16+J16 -> 10970.4 | L16: 0 | M16: =M15+K16-L16 -> 34401.8
A17: 14 | B17: 19.10.2025 | E17: 25 | F17: 91.42 | G17: =E17*F17 -> 2285.5 | H17: 5 | I17: 103.35 | J17: =H17*I17 -> 516.75 | K17: =G17+J17 -> 2802.25 | L17: 0 | M17: =M16+K17-L17 -> 37204.05
A18: 15 | B18: 28.10.2025 | E18: 0 | F18: 0 | G18: =E18*F18 -> 0 | H18: 10 | I18: 103.35 | J18: =H18*I18 -> 1033.5 | K18: =G18+J18 -> 1033.5 | L18: 0 | M18: =M17+K18-L18 -> 38237.55
A19: 16 | B19: 29.10.2025 | E19: 50 | F19: 91.42 | G19: =E19*F19 -> 4571 | H19: 0 | I19: 0 | J19: =H19*I19 -> 0 | K19: =G19+J19 -> 4571 | L19: 0 | M19: =M18+K19-L19 -> 42808.55
A20: 17 | B20: 30.10.2025 | E20: 8 | F20: 91.42 | G20: =E20*F20 -> 731.36 | H20: 0 | I20: 0 | J20: =H20*I20 -> 0 | K20: =G20+J20 -> 731.36 | L20: 0 | M20: =M19+K20-L20 -> 43539.91
A21: 18 | B21: 31.10.2025 | E21: 33 | F21: 91.42 | G21: =E21*F21 -> 3016.86 | H21: 0 | I21: 0 | J21: =H21*I21 -> 0 | K21: =G21+J21 -> 3016.86 | L21: 0 | M21: =M20+K21-L21 -> 46556.77 | Q21: =76.54*91.45 -> 6999.583
A22: 19 | E22: 0 | F22: 0 | G22: =E22*F22 -> 0 | H22: 0 | I22: 0 | J22: =H22*I22 -> 0 | K22: =G22+J22 -> 0 | L22: 0 | M22: =M21+K22-L22 -> 46556.77
A23: 20 | E23: 0 | F23: 0 | G23: =E23*F23 -> 0 | H23: 0 | I23: 0 | J23: =H23*I23 -> 0 | K23: =G23+J23 -> 0 | L23: 0 | M23: =M22+K23-L23 -> 46556.77
A24: 21 | E24: 0 | F24: 0 | G24: =E24*F24 -> 0 | H24: 0 | I24: 0 | J24: =H24*I24 -> 0 | K24: =G24+J24 -> 0 | L24: 0 | M24: =M23+K24-L24 -> 46556.77
A25: 22 | E25: 0 | F25: 0 | G25: =E25*F25 -> 0 | H25: 0 | I25: 0 | J25: =H25*I25 -> 0 | K25: =G25+J25 -> 0 | L25: 0 | M25: =M24+K25-L25 -> 46556.77
A26: 23 | E26: 0 | F26: 0 | G26: =E26*F26 -> 0 | H26: 0 | I26: 0 | J26: =H26*I26 -> 0 | K26: =G26+J26 -> 0 | L26: 0 | M26: =M25+K26-L26 -> 46556.77 | O26: 14616
A27: 24 | E27: 0 | F27: 0 | G27: =E27*F27 -> 0 | H27: 0 | I27: 0 | J27: =H27*I27 -> 0 | K27: =G27+J27 -> 0 | L27: 0 | M27: =M26+K27-L27 -> 46556.77
A28: 25 | E28: 0 | F28: 0 | G28: =E28*F28 -> 0 | H28: 0 | I28: 0 | J28: =H28*I28 -> 0 | K28: =G28+J28 -> 0 | L28: 0 | M28: =M27+K28-L28 -> 46556.77
A29: 26 | E29: 0 | F29: 0 | G29: =E29*F29 -> 0 | H29: 0 | I29: 0 | J29: =H29*I29 -> 0 | K29: =G29+J29 -> 0 | L29: 0 | M29: =M28+K29-L29 -> 46556.77
A30: 27 | E30: 0 | F30: 0 | G30: =E30*F30 -> 0 | H30: 0 | I30: 0 | J30: =H30*I30 -> 0 | K30: =G30+J30 -> 0 | L30: 0 | M30: =M29+K30-L30 -> 46556.77
A31: 28 | E31: 0 | F31: 0 | G31: =E31*F31 -> 0 | H31: 0 | I31: 0 | J31: =H31*I31 -> 0 | K31: =G31+J31 -> 0 | L31: 0 | M31: =M30+K31-L31 -> 46556.77
A32: 29 | E32: 0 | F32: 0 | G32: =E32*F32 -> 0 | H32: 0 | I32: 0 | J32: =H32*I32 -> 0 | K32: =G32+J32 -> 0 | L32: 0 | M32: =M31+K32-L32 -> 46556.77
A33: 30 | E33: 0 | F33: 0 | G33: =E33*F33 -> 0 | H33: 0 | I33: 0 | J33: =H33*I33 -> 0 | K33: =G33+J33 -> 0 | L33: 0 | M33: =M32+K33-L33 -> 46556.77
A34: 31 | E34: 0 | F34: 0 | G34: =E34*F34 -> 0 | H34: 0 | I34: 0 | J34: =H34*I34 -> 0 | K34: =G34+J34 -> 0 | L34: 0 | M34: =M33+K34-L34 -> 46556.77
A35: 32 | E35: 0 | F35: 0 | G35: =E35*F35 -> 0 | H35: 0 | I35: 0 | J35: =H35*I35 -> 0 | K35: =G35+J35 -> 0 | L35: 0 | M35: =M34+K35-L35 -> 46556.77
A36: 33 | E36: 0 | F36: 0 | G36: =E36*F36 -> 0 | H36: 0 | I36: 0 | J36: =H36*I36 -> 0 | K36: =G36+J36 -> 0 | L36: 0 | M36: =M35+K36-L36 -> 46556.77
A37: 34 | E37: 0 | F37: 0 | G37: =E37*F37 -> 0 | H37: 0 | I37: 0 | J37: =H37*I37 -> 0 | K37: =G37+J37 -> 0 | L37: 0 | M37: =M36+K37-L37 -> 46556.77
A38: 35 | E38: 0 | F38: 0 | G38: =E38*F38 -> 0 | H38: 0 | I38: 0 | J38: =H38*I38 -> 0 | K38: =G38+J38 -> 0 | L38: 0 | M38: =M37+K38-L38 -> 46556.77
... A44: 41 | E44: 0 | F44: 0 | G44: =E44*F44 -> 0 | H44: 0 | I44: 0 | J44: =H44*I44 -> 0 | K44: =G44+J44 -> 0 | L44: 0 | M44: =M43+K44-L44 -> 46556.77
A45: 42 | E45: 0 | F45: 0 | G45: =E45*F45 -> 0 | J45: =H45*I45 -> 0 | K45: =G45+J45 -> 0 | L45: =+K45 -> 0 | M45: =M44+K45-L45 -> 46556.77
E46: 0 | F46: 0 | G46: =E46*F46 -> 0 | J46: =H46*I46 -> 0 | K46: =G46+J46 -> 0 | L46: =+K46 -> 0 | M46: =M45+K46-L46 -> 46556.77
E47: =SUM(E4:E46) -> 481 | G47: =SUM(G4:G46) -> 43973.02 | H47: =SUM(H4:H46) -> 25 | J47: =SUM(J4:J46) -> 2583.75 | K47: =SUM(K4:K46) -> 46556.77 | L47: =SUM(L4:L46) -> 0

Sheet Khanapur
A1: V.V.Varde
A2: S.No | B2: Date | C2: GRN No | D2: Ind No/Bill No | E2: Diesel (Lts) | F2: Price | G2: Amount | H2: Petrol (Lts) | I2: Price | J2: Amount | K2: Total amount | L2: Date of payment | M2: Amount paid | N2: Remarks
D3: Opening Balance | K3: 10170.75 | M3: 10170.75
A4: 1 | B4: 45931 | E4: 0 | F4: 0 | G4: =F4*E4 -> 0 | H4: 5 | I4: 102.77 | J4: =H4*I4 -> 513.85 | K4: =G4+J4 -> 513.85 | L4: 0 | M4: =M3+K4-L4 -> 10684.6
A5: 2 | B5: 45932 | E5: 40 | F5: 90.88 | G5: =F5*E5 -> 3635.2 | H5: 0 | I5: 0 | J5: =H5*I5 -> 0 | K5: =G5+J5 -> 3635.2 | L5: 0 | M5: =M4+K5-L5 -> 14319.8 | S5: 90.88 | T5: 102.77
A6: 3 | B6: 45933 | E6: 170 | F6: 90.88 | G6: =F6*E6 -> 15449.6 | H6: 0 | I6: 0 | J6: =H6*I6 -> 0 | K6: =G6+J6 -> 15449.6 | L6: 0 | M6: =M5+K6-L6 -> 29769.4
A7: 4 | B7: 45934 | E7: 160 | F7: 90.88 | G7: =F7*E7 -> 14540.8 | H7: 0 | I7: 0 | J7: =H7*I7 -> 0 | K7: =G7+J7 -> 14540.8 | L7: 0 | M7: =M6+K7-L7 -> 44310.2
A8: 5 | B8: 45935 | E8: 100 | F8: 90.88 | G8: =F8*E8 -> 9088 | H8: 0 | I8: 0 | J8: =H8*I8 -> 0 | K8: =G8+J8 -> 9088 | L8: 0 | M8: =M7+K8-L8 -> 53398.2
A9: 6 | B9: 45936 | E9: 0 | F9: 0 | G9: =F9*E9 -> 0 | H9: 5 | I9: 102.77 | J9: =H9*I9 -> 513.85 | K9: =G9+J9 -> 513.85 | L9: 0 | M9: =M8+K9-L9 -> 53912.05
A10: 7 | B10: 45937 | E10: 88 | F10: 90.88 | G10: =F10*E10 -> 7997.44 | H10: 5 | I10: 102.77 | J10: =H10*I10 -> 513.85 | K10: =G10+J10 -> 8511.29 | L10: 0 | M10: =M9+K10-L10 -> 62423.34
A11: 8 | B11: 45938 | E11: 35.14 | F11: 90.88 | G11: =F11*E11 -> 3193.5232 | H11: 5 | I11: 102.77 | J11: =H11*I11 -> 513.85 | K11: =G11+J11 -> 3707.3732 | L11: 0 | M11: =M10+K11-L11 -> 66130.713
A12: 9 | B12: 45939 | E12: 40 | F12: 90.88 | G12: =F12*E12 -> 3635.2 | H12: 0 | I12: 0 | J12: =H12*I12 -> 0 | K12: =G12+J12 -> 3635.2 | L12: 0 | M12: =M11+K12-L12 -> 69765.913
A13: 10 | B13: 45940 | E13: 159.6 | F13: 90.88 | G13: =F13*E13 -> 14504.448 | H13: 0 | I13: 0 | J13: =H13*I13 -> 0 | K13: =G13+J13 -> 14504.448 | L13: 65000 | M13: =M12+K13-L13 -> 19270.361
A14: 11 | B14: 45941 | E14: 0 | F14: 0 | G14: =F14*E14 -> 0 | H14: 0 | I14: 0 | J14: =H14*I14 -> 0 | K14: =G14+J14 -> 0 | L14: =+K14 -> 0 | M14: =M13+K14-L14 -> 19270.361
A15: 12 | B15: 45942 | E15: 0 | F15: 0 | G15: =F15*E15 -> 0 | H15: 0 | I15: 0 | J15: =H15*I15 -> 0 | K15: =G15+J15 -> 0 | L15: =+K15 -> 0 | M15: =M14+K15-L15 -> 19270.361
A16: 13 | B16: 45943 | E16: 86.01 | F16: 90.88 | G16: =F16*E16 -> 7816.5888 | H16: 10 | I16: 102.77 | J16: =H16*I16 -> 1027.7 | K16: =G16+J16 -> 8844.2888 | L16: 0 | M16: =M15+K16-L16 -> 28114.65
A17: 14 | B17: 45944 | E17: 0 | F17: 0 | G17: =F17*E17 -> 0 | H17: 5 | I17: 102.77 | J17: =H17*I17 -> 513.85 | K17: =G17+J17 -> 513.85 | L17: 0 | M17: =M16+K17-L17 -> 28628.5
A18: 15 | B18: 45945 | E18: 90 | F18: 90.88 | G18: =F18*E18 -> 8179.2 | H18: 10 | I18: 102.77 | J18: =H18*I18 -> 1027.7 | K18: =G18+J18 -> 9206.9 | L18: 0 | M18: =M17+K18-L18 -> 37835.4
A19: 16 | B19: 45946 | E19: 0 | F19: 0 | G19: =F19*E19 -> 0 | H19: 0 | I19: 0 | J19: =H19*I19 -> 0 | K19: =G19+J19 -> 0 | L19: =+K19 -> 0 | M19: =M18+K19-L19 -> 37835.4
A20: 17 | B20: 45947 | E20: 0 | F20: 0 | G20: =F20*E20 -> 0 | H20: 0 | I20: 0 | J20: =H20*I20 -> 0 | K20: =G20+J20 -> 0 | L20: =+K20 -> 0 | M20: =M19+K20-L20 -> 37835.4 | O20: 16.68
A21: 18 | B21: 45948 | E21: 0 | F21: 0 | G21: =F21*E21 -> 0 | H21: 5 | I21: 102.77 | J21: =H21*I21 -> 513.85 | K21: =G21+J21 -> 513.85 | L21: 0 | M21: =M20+K21-L21 -> 38349.25
A22: 19 | B22: 45949 | E22: 0 | F22: 0 | G22: =F22*E22 -> 0 | H22: 0 | I22: 0 | J22: =H22*I22 -> 0 | K22: =G22+J22 -> 0 | L22: =+K22 -> 0 | M22: =M21+K22-L22 -> 38349.25
A23: 20 | B23: 45950 | E23: 0 | F23: 0 | G23: =F23*E23 -> 0 | H23: 0 | I23: 0 | J23: =H23*I23 -> 0 | K23: =G23+J23 -> 0 | L23: =+K23 -> 0 | M23: =M22+K23-L23 -> 38349.25 | N23: 0
A24: 21 | B24: 45951 | E24: 0 | F24: 0 | G24: =F24*E24 -> 0 | H24: 5 | I24: 102.77 | J24: =H24*I24 -> 513.85 | K24: =G24+J24 -> 513.85 | L24: 0 | M24: =M23+K24-L24 -> 38863.1
A25: 22 | B25: 45952 | E25: 0 | F25: 0 | G25: =F25*E25 -> 0 | H25: 0 | I25: 0 | J25: =H25*I25 -> 0 | K25: =G25+J25 -> 0 | L25: =+K25 -> 0 | M25: =M24+K25-L25 -> 38863.1
A26: 23 | B26: 45953 | E26: 0 | F26: 0 | G26: =F26*E26 -> 0 | H26: 5 | I26: 102.77 | J26: =H26*I26 -> 513.85 | K26: =G26+J26 -> 513.85 | L26: 0 | M26: =M25+K26-L26 -> 39376.95
A27: 24 | B27: 45954 | E27: 0 | F27: 0 | G27: =F27*E27 -> 0 | H27: 5 | I27: 102.77 | J27: =H27*I27 -> 513.85 | K27: =G27+J27 -> 513.85 | L27: 0 | M27: =M26+K27-L27 -> 39890.8
A28: 25 | B28: 45955 | E28: 0 | F28: 0 | G28: =F28*E28 -> 0 | H28: 5 | I28: 102.77 | J28: =H28*I28 -> 513.85 | K28: =G28+J28 -> 513.85 | L28: 0 | M28: =M27+K28-L28 -> 40404.65
A29: 26 | B29: 45956 | E29: 0 | F29: 0 | G29: =F29*E29 -> 0 | H29: 0 | I29: 0 | J29: =H29*I29 -> 0 | K29: =G29+J29 -> 0 | L29: =+K29 -> 0 | M29: =M28+K29-L29 -> 40404.65
A30: 27 | B30: 45957 | E30: 0 | F30: 0 | G30: =F30*E30 -> 0 | H30: 0 | I30: 0 | J30: =H30*I30 -> 0 | K30: =G30+J30 -> 0 | L30: =+K30 -> 0 | M30: =M29+K30-L30 -> 40404.65
A31: 28 | B31: 45958 | E31: 0 | F31: 0 | G31: =F31*E31 -> 0 | H31: 5 | I31: 102.77 | J31: =H31*I31 -> 513.85 | K31: =G31+J31 -> 513.85 | L31: 0 | M31: =M30+K31-L31 -> 40918.5
A32: 29 | B32: 45959 | E32: 0 | F32: 0 | G32: =F32*E32 -> 0 | H32: 0 | I32: 0 | J32: =H32*I32 -> 0 | K32: =G32+J32 -> 0 | L32: =+K32 -> 0 | M32: =M31+K32-L32 -> 40918.5
A33: 30 | B33: 45960 | E33: 95 | F33: 90.8 | G33: =F33*E33 -> 8626 | H33: 6 | I33: 102.77 | J33: =H33*I33 -> 616.62 | K33: =G33+J33 -> 9242.62 | L33: 0 | M33: =M32+K33-L33 -> 50161.12
A34: 31
E35: =SUM(E4:E34) -> 1063.75 | G35: =SUM(G4:G34) -> 96666 | H35: =SUM(H4:H34) -> 81 | J35: =SUM(J4:J34) -> 8324.37 | K35: =SUM(K4:K34) -> 104990.37 | L35: =SUM(L4:L34) -> 65000 | M35: =SUM(M4:M34) -> 1158028.4
E36: 1541.87
E37: 1661 | H37: 43.92
E38: =E37-E36 -> 119.13

Sheet Munavali-2
A1: Shri Daneshwari
A2: S.No | B2: Date | C2: GRN No | D2: Ind No/Bill No | E2: Diesel (Lts) | F2: Price | G2: Amount | H2: Petrol (Lts) | I2: Price | J2: Amount | K2: Total amount | L2: Amount paid | M2: As on date | N2: Remarks
D3: Opening Balance | K3: 204851.03 | M3: 204851.03 | O3: 26506.4
A4: 1 | B4: 45931 | E4: 0 | F4: 0 | G4: =E4*F4 -> 0 | H4: 0 | I4: 0 | J4: =H4*I4 -> 0 | K4: =G4+J4 -> 0 | L4: 0 | M4: =M3+K4-L4 -> 204851.03
A5: 2 | B5: 45932 | E5: 0 | F5: 0 | G5: =E5*F5 -> 0 | H5: 0 | I5: 0 | J5: =H5*I5 -> 0 | K5: =G5+J5 -> 0 | L5: 0 | M5: =M4+K5-L5 -> 204851.03
A6: 3 | B6: 45933 | E6: 530 | F6: 91.32 | G6: =E6*F6 -> 48399.6 | H6: 16 | I6: 103.24 | J6: =H6*I6 -> 1651.84 | K6: =G6+J6 -> 50051.44 | L6: 0 | M6: =M5+K6-L6 -> 254902.47
A7: 4 | B7: 45934 | E7: 400 | F7: 91.32 | G7: =E7*F7 -> 36528 | H7: 10 | I7: 103.24 | J7: =H7*I7 -> 1032.4 | K7: =G7+J7 -> 37560.4 | L7: 0 | M7: =M6+K7-L7 -> 292462.87
A8: 5 | B8: 45935 | E8: 200 | F8: 91.32 | G8: =E8*F8 -> 18264 | H8: 0 | I8: 0 | J8: =H8*I8 -> 0 | K8: =G8+J8 -> 18264 | L8: 0 | M8: =M7+K8-L8 -> 310726.87
A9: 6 | B9: 45936 | E9: 400 | F9: 91.32 | G9: =E9*F9 -> 36528 | H9: 0 | I9: 0 | J9: =H9*I9 -> 0 | K9: =G9+J9 -> 36528 | L9: 0 | M9: =M8+K9-L9 -> 347254.87
A10: 7 | B10: 45937 | E10: 20 | F10: 91.32 | G10: =E10*F10 -> 1826.4 | H10: 0 | I10: 0 | J10: =H10*I10 -> 0 | K10: =G10+J10 -> 1826.4 | L10: 0 | M10: =M9+K10-L10 -> 349081.27
A11: 8 | B11: 45938 | E11: 643 | F11: 91.32 | G11: =E11*F11 -> 58718.76 | H11: 20 | I11: 103.24 | J11: =H11*I11 -> 2064.8 | K11: =G11+J11 -> 60783.56 | L11: 0 | M11: =M10+K11-L11 -> 409864.83
A12: 9 | B12: 45939 | E12: 0 | F12: 0 | G12: =E12*F12 -> 0 | H12: 0 | I12: 0 | J12: =H12*I12 -> 0 | K12: =G12+J12 -> 0 | L12: 0 | M12: =M11+K12-L12 -> 409864.83
A13: 10 | B13: 45940 | E13: 0 | F13: 0 | G13: =E13*F13 -> 0 | H13: 0 | I13: 0 | J13: =H13*I13 -> 0 | K13: =G13+J13 -> 0 | L13: 300000 | M13: =M12+K13-L13 -> 109864.83
A14: 11 | B14: 45941 | E14: 592.04 | F14: 91.32 | G14: =E14*F14 -> 54065.093 | H14: 5 | I14: 103.24 | J14: =H14*I14 -> 516.2 | K14: =G14+J14 -> 54581.293 | L14: 0 | M14: =M13+K14-L14 -> 164446.12
A15: 12 | B15: 45942 | E15: 0 | F15: 0 | G15: =E15*F15 -> 0 | H15: 5 | I15: 103.24 | J15: =H15*I15 -> 516.2 | K15: =G15+J15 -> 516.2 | L15: 0 | M15: =M14+K15-L15 -> 164962.32
A16: 13 | B16: 45943 | D16: 0 | E16: 532.8 | F16: 91.32 | G16: =E16*F16 -> 48655.296 | H16: 10 | I16: 103.24 | J16: =H16*I16 -> 1032.4 | K16: =G16+J16 -> 49687.696 | L16: 0 | M16: =M15+K16-L16 -> 214650.02
A17: 14 | B17: 45944 | E17: 515 | F17: 91.32 | G17: =E17*F17 -> 47029.8 | H17: 10 | I17: 103.24 | J17: =H17*I17 -> 1032.4 | K17: =G17+J17 -> 48062.2 | L17: 0 | M17: =M16+K17-L17 -> 262712.22
A18: 15 | B18: 45945 | E18: 35.52 | F18: 91.32 | G18: =E18*F18 -> 3243.6864 | H18: 0 | I18: 0 | J18: =H18*I18 -> 0 | K18: =G18+J18 -> 3243.6864 | L18: 150000 | M18: =M17+K18-L18 -> 115955.9
A19: 16 | B19: 45946 | E19: 539.99 | F19: 91.32 | G19: =E19*F19 -> 49311.887 | H19: 8 | I19: 103.24 | J19: =H19*I19 -> 825.92 | K19: =G19+J19 -> 50137.807 | L19: 0 | M19: =M18+K19-L19 -> 166093.71
A20: 17 | B20: 45947 | E20: 0 | F20: 0 | G20: =E20*F20 -> 0 | H20: 5 | I20: 103.24 | J20: =H20*I20 -> 516.2 | K20: =G20+J20 -> 516.2 | L20: 0 | M20: =M19+K20-L20 -> 166609.91
A21: 18 | B21: 45948 | E21: 598.25 | F21: 91.32 | G21: =E21*F21 -> 54632.19 | H21: 10 | I21: 103.24 | J21: =H21*I21 -> 1032.4 | K21: =G21+J21 -> 55664.59 | L21: 0 | M21: =M20+K21-L21 -> 222274.5
A22: 19 | B22: 45949 | E22: 550 | F22: 91.32 | G22: =E22*F22 -> 50226 | H22: 0 | I22: 0 | J22: =H22*I22 -> 0 | K22: =G22+J22 -> 50226 | L22: 0 | M22: =M21+K22-L22 -> 272500.5
A23: 20 | B23: 45950 | E23: 0 | F23: 0 | G23: =E23*F23 -> 0 | H23: 0 | I23: 0 | J23: =H23*I23 -> 0 | K23: =G23+J23 -> 0 | L23: 0 | M23: =M22+K23-L23 -> 272500.5
A24: 21 | B24: 45951 | E24: 600 | F24: 91.32 | G24: =E24*F24 -> 54792 | H24: 0 | I24: 0 | J24: =H24*I24 -> 0 | K24: =G24+J24 -> 54792 | L24: 0 | M24: =M23+K24-L24 -> 327292.5
A25: 22 | B25: 45952 | E25: 435.26 | F25: 91.32 | G25: =E25*F25 -> 39747.943 | H25: 16 | I25: 103.24 | J25: =H25*I25 -> 1651.84 | K25: =G25+J25 -> 41399.783 | L25: 0 | M25: =M24+K25-L25 -> 368692.28
A26: 23 | B26: 45953 | E26: 533.13 | F26: 91.32 | G26: =E26*F26 -> 48685.432 | H26: 0 | I26: 0 | J26: =H26*I26 -> 0 | K26: =G26+J26 -> 48685.432 | L26: 0 | M26: =M25+K26-L26 -> 417377.71
A27: 24 | B27: 45954 | E27: 400 | F27: 91.32 | G27: =E27*F27 -> 36528 | H27: 0 | I27: 0 | J27: =H27*I27 -> 0 | K27: =G27+J27 -> 36528 | L27: 0 | M27: =M26+K27-L27 -> 453905.71
A28: 25 | B28: 45955 | E28: 455 | F28: 91.32 | G28: =E28*F28 -> 41550.6 | H28: 6 | I28: 103.24 | J28: =H28*I28 -> 619.44 | K28: =G28+J28 -> 42170.04 | L28: 0 | M28: =M27+K28-L28 -> 496075.75
... A31: 28 | B31: 45958 | E31: 0 | F31: 0 | G31: =E31*F31 -> 0 | H31: 0 | I31: 0 | J31: =H31*I31 -> 0 | K31: =G31+J31 -> 0 | L31: 0 | M31: =M30+K31-L31 -> 590167.27
A32: 29 | B32: 45959 | D32: BPCL | E32: 30 | F32: 91.32 | G32: =E32*F32 -> 2739.6 | H32: 15 | I32: 103.24 | J32: =H32*I32 -> 1548.6 | K32: =G32+J32 -> 4288.2 | L32: 0 | M32: =M31+K32-L32 -> 594455.47
A33: 30 | B33: 45960 | E33: 703.28 | F33: 91.32 | G33: =E33*F33 -> 64223.53 | H33: 5 | I33: 103.24 | J33: =H33*I33 -> 516.2 | K33: =G33+J33 -> 64739.73 | L33: 0 | M33: =M32+K33-L33 -> 659195.2
A34: 31 | E34: 0 | F34: 0 | G34: =E34*F34 -> 0 | H34: 0 | I34: 0 | J34: =H34*I34 -> 0 | K34: =G34+J34 -> 0 | L34: 0 | M34: =M33+K34-L34 -> 659195.2
A35: 32 | E35: 0 | F35: 0 | G35: =E35*F35 -> 0 | H35: 0 | I35: 0 | J35: =H35*I35 -> 0 | K35: =G35+J35 -> 0 | L35: 0 | M35: =M34+K35-L35 -> 659195.2
A36: 33 | E36: 0 | F36: 0 | G36: =E36*F36 -> 0 | H36: 0 | I36: 0 | J36: =H36*I36 -> 0 | K36: =G36+J36 -> 0 | L36: 0 | M36: =M35+K36-L36 -> 659195.2
E37: =SUM(E4:E36) -> 9723.27 | G37: =SUM(G4:G36) -> 887929.02 | H37: =SUM(H4:H36) -> 159 | J37: =SUM(J4:J36) -> 16415.16 | K37: =SUM(K4:K36) -> 904344.18 | L37: =SUM(L4:L36) -> 450000

Sheet Ugar,Khagwad,Kudichi
A1: Shiri Bhrhmanath Petrolium
A2: S.No | B2: Date | C2: GRN No | D2: Ind No/Bill No | E2: Diesel (Lts) | F2: Price | G2: Amount | H2: Petrol (Lts) | I2: Price | J2: Amount | K2: Total amount | L2: Amount paid | M2: As on Date | N2: Remarks
A3: Opening Balance | K3: 230919.24 | M3: 230919.24
A4: 1 | B4: 45931 | G4: =E4*F4 -> 0 | J4: =H4*I4 -> 0 | K4: =G4+J4 -> 0 | L4: 0 | M4: =M3+K4-L4 -> 230919.24
A5: 2 | B5: 45932 | G5: =E5*F5 -> 0 | J5: =H5*I5 -> 0 | K5: =G5+J5 -> 0 | L5: 0 | M5: =M4+K5-L5 -> 230919.24
A6: 3 | B6: 45933 | G6: =E6*F6 -> 0 | J6: =H6*I6 -> 0 | K6: =G6+J6 -> 0 | L6: 0 | M6: =M5+K6-L6 -> 230919.24
A7: 4 | B7: 45934 | E7: 300.24 | F7: 91.93 | G7: =E7*F7 -> 27601.063 | H7: 30 | I7: 103.89 | J7: =H7*I7 -> 3116.7 | K7: =G7+J7 -> 30717.763 | L7: 0 | M7: =M6+K7-L7 -> 261637
A8: 5 | B8: 45935 | G8: =E8*F8 -> 0 | H8: 6 | I8: 103.89 | J8: =H8*I8 -> 623.34 | K8: =G8+J8 -> 623.34 | L8: 0 | M8: =M7+K8-L8 -> 262260.34
A9: 6 | B9: 45936 | E9: 30 | F9: 91.93 | G9: =E9*F9 -> 2757.9 | H9: 5 | I9: 103.89 | J9: =H9*I9 -> 519.45 | K9: =G9+J9 -> 3277.35 | L9: 0 | M9: =M8+K9-L9 -> 265537.69
A10: 7 | B10: 45937 | E10: 75 | F10: 91.93 | G10: =E10*F10 -> 6894.75 | H10: 40 | I10: 103.89 | J10: =H10*I10 -> 4155.6 | K10: =G10+J10 -> 11050.35 | M10: =M9+K10-L10 -> 276588.04
A11: 8 | B11: 45938 | G11: =E11*F11 -> 0 | J11: =H11*I11 -> 0 | K11: =G11+J11 -> 0 | L11: 200000 | M11: =M10+K11-L11 -> 76588.04
A12: 9 | B12: 45939 | E12: 30 | F12: 91.93 | G12: =E12*F12 -> 2757.9 | J12: =H12*I12 -> 0 | K12: =G12+J12 -> 2757.9 | M12: =M11+K12-L12 -> 79345.94
A13: 10 | B13: 45940 | E13: 35 | F13: 91.93 | G13: =E13*F13 -> 3217.55 | J13: =H13*I13 -> 0 | K13: =G13+J13 -> 3217.55 | M13: =M12+K13-L13 -> 82563.49
A14: 11 | B14: 45941 | E14: 70 | F14: 91.93 | G14: =E14*F14 -> 6435.1 | J14: =H14*I14 -> 0 | K14: =G14+J14 -> 6435.1 | M14: =M13+K14-L14 -> 88998.59
A15: 12 | B15: 45942 | G15: =E15*F15 -> 0 | J15: =H15*I15 -> 0 | K15: =G15+J15 -> 0 | L15: 0 | M15: =M14+K15-L15 -> 88998.59
A16: 13 | B16: 45943 | E16: 305 | F16: 91.93 | G16: =E16*F16 -> 28038.65 | H16: 60 | I16: 111.13 | J16: =H16*I16 -> 6667.8 | K16: =G16+J16 -> 34706.45 | L16: 0 | M16: =M15+K16-L16 -> 123705.04
A17: 14 | B17: 45944 | E17: 50 | F17: 91.93 | G17: =E17*F17 -> 4596.5 | H17: 5 | I17: 111.13 | J17: =H17*I17 -> 555.65 | K17: =G17+J17 -> 5152.15 | L17: 0 | M17: =M16+K17-L17 -> 128857.19
A18: 15 | B18: 45945 | G18: =E18*F18 -> 0 | J18: =H18*I18 -> 0 | K18: =G18+J18 -> 0 | L18: 0 | M18: =M17+K18-L18 -> 128857.19
A19: 16 | B19: 45946 | E19: 35 | F19: 91.93 | G19: =E19*F19 -> 3217.55 | J19: =H19*I19 -> 0 | K19: =G19+J19 -> 3217.55 | L19: 31041 | M19: =M18+K19-L19 -> 101033.74
A20: 17 | B20: 45947 | E20: 81 | F20: 91.93 | G20: =E20*F20 -> 7446.33 | J20: =H20*I20 -> 0 | K20: =G20+J20 -> 7446.33 | L20: 0 | M20: =M19+K20-L20 -> 108480.07
A21: 18 | B21: 45948 | E21: 233 | F21: 91.93 | G21: =E21*F21 -> 21419.69 | H21: 45 | I21: 103.89 | J21: =H21*I21 -> 4675.05 | K21: =G21+J21 -> 26094.74 | L21: 0 | M21: =M20+K21-L21 -> 134574.81
A22: 19 | B22: 45949 | G22: =E22*F22 -> 0 | J22: =H22*I22 -> 0 | K22: =G22+J22 -> 0 | L22: 0 | M22: =M21+K22-L22 -> 134574.81
A23: 20 | B23: 45950 | G23: =E23*F23 -> 0 | J23: =H23*I23 -> 0 | K23: =G23+J23 -> 0 | L23: 0 | M23: =M22+K23-L23 -> 134574.81
A24: 21 | B24: 45951 | G24: =E24*F24 -> 0 | J24: =H24*I24 -> 0 | K24: =G24+J24 -> 0 | L24: 0 | M24: =M23+K24-L24 -> 134574.81
A25: 22 | B25: 45952 | G25: =E25*F25 -> 0 | J25: =H25*I25 -> 0 | K25: =G25+J25 -> 0 | L25: 0 | M25: =M24+K25-L25 -> 134574.81
A26: 23 | B26: 45953 | E26: 0 | F26: 0 | G26: =E26*F26 -> 0 | H26: 55 | I26: 111.13 | J26: =H26*I26 -> 6112.15 | K26: =G26+J26 -> 6112.15 | L26: 0 | M26: =M25+K26-L26 -> 140686.96
A27: 24 | B27: 45954 | G27: =E27*F27 -> 0 | J27: =H27*I27 -> 0 | K27: =G27+J27 -> 0 | L27: 0 | M27: =M26+K27-L27 -> 140686.96
A28: 25 | B28: 45955 | G28: =E28*F28 -> 0 | J28: =H28*I28 -> 0 | K28: =G28+J28 -> 0 | L28: 0 | M28: =M27+K28-L28 -> 140686.96
A29: 26 | B29: 45956 | G29: =E29*F29 -> 0 | J29: =H29*I29 -> 0 | K29: =G29+J29 -> 0 | L29: 0 | M29: =M28+K29-L29 -> 140686.96
A30: 27 | B30: 45957 | E30: 40 | F30: 91.93 | G30: =E30*F30 -> 3677.2 | J30: =H30*I30 -> 0 | K30: =G30+J30 -> 3677.2 | L30: 0 | M30: =M29+K30-L30 -> 144364.16
A31: 28 | B31: 45958 | G31: =E31*F31 -> 0 | J31: =H31*I31 -> 0 | K31: =G31+J31 -> 0 | L31: 0 | M31: =M30+K31-L31 -> 144364.16
A32: 29 | B32: 45959 | E32: 685 | F32: 91.93 | G32: =E32*F32 -> 62972.05 | H32: 5 | I32: 103.9 | J32: =H32*I32 -> 519.5 | K32: =G32+J32 -> 63491.55 | L32: 0 | M32: =M31+K32-L32 -> 207855.71
A33: 30 | B33: 45960 | E33: 235 | F33: 91.93 | G33: =E33*F33 -> 21603.55 | H33: 50 | I33: 111.13 | J33: =H33*I33 -> 5556.5 | K33: =G33+J33 -> 27160.05 | L33: 0 | M33: =M32+K33-L33 -> 235015.76
A34: 31 | F34: 0 | G34: =E34*F34 -> 0 | J34: =H34*I34 -> 0 | K34: =G34+J34 -> 0 | L34: 0 | M34: =M33+K34-L34 -> 235015.76
E35: =SUM(E4:E34) -> 2204.24 | G35: =SUM(G4:G34) -> 202635.78 | H35: =SUM(H4:H34) -> 301 | J35: =SUM(J4:J34) -> 32501.74 | K35: =SUM(K4:K34) -> 235137.52 | L35: =SUM(L4:L34) -> 231041

Sheet Borgaon
A1: Aadisagar Petrolium
A2: S.No | B2: Date | C2: GRN No | D2: Ind no/Bill No | E2: Diesel (Lts) | F2: Price | G2: Amount | H2: Petrol (Lts) | I2: Price | J2: Amount | K2: Total amount | L2: Amount paid | M2: As on Date | N2: Remarks
A3: Opening Balance | K3: 41597.607 | M3: 41597.607
A4: 1 | B4: 45931 | E4: 0 | F4: 0 | G4: =E4*F4 -> 0 | H4: 0 | I4: 0 | J4: =H4*I4 -> 0 | K4: =G4+J4 -> 0 | L4: 0 | M4: =M3+K4-L4 -> 41597.607
A5: 2 | B5: 45932 | E5: 0 | F5: 0 | G5: =E5*F5 -> 0 | H5: 0 | I5: 0 | J5: =H5*I5 -> 0 | K5: =G5+J5 -> 0 | L5: 0 | M5: =M4+K5-L5 -> 41597.607
A6: 3 | B6: 45933 | E6: 5 | F6: 91.77 | G6: =E6*F6 -> 458.85 | H6: 5 | I6: 103.73 | J6: =H6*I6 -> 518.65 | K6: =G6+J6 -> 977.5 | L6: 0 | M6: =M5+K6-L6 -> 42575.107
A7: 4 | B7: 45934 | E7: 0 | F7: 0 | G7: =E7*F7 -> 0 | H7: 5 | I7: 103.73 | J7: =H7*I7 -> 518.65 | K7: =G7+J7 -> 518.65 | L7: 0 | M7: =M6+K7-L7 -> 43093.757
A8: 5 | B8: 45935 | E8: 0 | F8: 0 | G8: =E8*F8 -> 0 | H8: 0 | I8: 0 | J8: =H8*I8 -> 0 | K8: =G8+J8 -> 0 | L8: 0 | M8: =M7+K8-L8 -> 43093.757
A9: 6 | B9: 45936 | E9: 50 | F9: 91.77 | G9: =E9*F9 -> 4588.5 | H9: 5 | I9: 103.73 | J9: =H9*I9 -> 518.65 | K9: =G9+J9 -> 5107.15 | L9: 0 | M9: =M8+K9-L9 -> 48200.907
A10: 7 | B10: 45937 | E10: 0 | F10: 0 | G10: =E10*F10 -> 0 | H10: 0 | I10: 0 | J10: =H10*I10 -> 0 | K10: =G10+J10 -> 0 | L10: 0 | M10: =M9+K10-L10 -> 48200.907
A11: 8 | B11: 45938 | E11: 20 | F11: 91.77 | G11: =E11*F11 -> 1835.4 | H11: 11 | I11: 103.73 | J11: =H11*I11 -> 1141.03 | K11: =G11+J11 -> 2976.43 | L11: 43000 | M11: =M10+K11-L11 -> 8177.3374
A12: 9 | B12: 45939 | E12: 0 | F12: 0 | G12: =E12*F12 -> 0 | H12: 0 | I12: 0 | J12: =H12*I12 -> 0 | K12: =G12+J12 -> 0 | L12: 0 | M12: =M11+K12-L12 -> 8177.3374
A13: 10 | B13: 45940 | E13: 50 | F13: 91.77 | G13: =E13*F13 -> 4588.5 | H13: 0 | I13: 0 | J13: =H13*I13 -> 0 | K13: =G13+J13 -> 4588.5 | L13: 0 | M13: =M12+K13-L13 -> 12765.837
A14: 11 | B14: 45941 | E14: 100 | F14: 91.77 | G14: =E14*F14 -> 9177 | H14: 0 | I14: 0 | J14: =H14*I14 -> 0 | K14: =G14+J14 -> 9177 | L14: 0 | M14: =M13+K14-L14 -> 21942.837
A15: 12 | B15: 45942 | E15: 0 | F15: 0 | G15: =E15*F15 -> 0 | H15: 0 | I15: 0 | J15: =H15*I15 -> 0 | K15: =G15+J15 -> 0 | L15: 0 | M15: =M14+K15-L15 -> 21942.837
... A25: 22 | B25: 45952 | E25: 75 | F25: 91.77 | G25: =E25*F25 -> 6882.75 | H25: 0 | I25: 0 | J25: =H25*I25 -> 0 | K25: =G25+J25 -> 6882.75 | L25: 0 | M25: =M24+K25-L25 -> 35389.337
A26: 23 | B26: 45953 | E26: 4.33 | F26: 91.77 | G26: =E26*F26 -> 397.3641 | H26: 0 | I26: 103.73 | J26: =H26*I26 -> 0 | K26: =G26+J26 -> 397.3641 | L26: 0 | M26: =M25+K26-L26 -> 35786.701 | Q26: d
A27: 24 | B27: 45954 | E27: 120 | F27: 91.77 | G27: =E27*F27 -> 11012.4 | H27: 0 | I27: 0 | J27: =H27*I27 -> 0 | K27: =G27+J27 -> 11012.4 | L27: 0 | M27: =M26+K27-L27 -> 46799.101 | Q27: 30 | R27: 50
A28: 25 | B28: 45955 | E28: 55 | F28: 91.77 | G28: =E28*F28 -> 5047.35 | H28: 0 | I28: 103.73 | J28: =H28*I28 -> 0 | K28: =G28+J28 -> 5047.35 | L28: 0 | M28: =M27+K28-L28 -> 51846.451 | Q28: 50 | R28: 4.51
A29: 26 | B29: 45956 | E29: 70 | F29: 91.77 | G29: =E29*F29 -> 6423.9 | H29: 0 | I29: 0 | J29: =H29*I29 -> 0 | K29: =G29+J29 -> 6423.9 | L29: 0 | M29: =M28+K29-L29 -> 58270.351
A30: 27 | B30: 45957 | E30: 0 | F30: 0 | G30: =E30*F30 -> 0 | H30: 5 | I30: 103.73 | J30: =H30*I30 -> 518.65 | K30: =G30+J30 -> 518.65 | L30: 0 | M30: =M29+K30-L30 -> 58789.001
A31: 28 | B31: 45958 | E31: 0 | F31: 0 | G31: =E31*F31 -> 0 | H31: 0 | I31: 0 | J31: =H31*I31 -> 0 | K31: =G31+J31 -> 0 | L31: 0 | M31: =M30+K31-L31 -> 58789.001
A32: 29 | B32: 45959 | E32: 20 | F32: 91.77 | G32: =E32*F32 -> 1835.4 | H32: 10 | I32: 103.73 | J32: =H32*I32 -> 1037.3 | K32: =G32+J32 -> 2872.7 | L32: 0 | M32: =M31+K32-L32 -> 61661.701
A33: 30 | B33: 45960 | E33: 0 | F33: 0 | G33: =E33*F33 -> 0 | H33: 0 | I33: 0 | J33: =H33*I33 -> 0 | K33: =G33+J33 -> 0 | L33: 0 | M33: =M32+K33-L33 -> 61661.701
A34: 31 | B34: 45961 | E34: 0 | F34: 0 | G34: =E34*F34 -> 0 | H34: 0 | I34: 0 | J34: =H34*I34 -> 0 | K34: =G34+J34 -> 0 | L34: 0 | M34: =M33+K34-L34 -> 61661.701
G35: =E35*F35 -> 0 | M35: =M34+K35-L35 -> 61661.701
B36: 02.11.2025 | E36: 50 | F36: 91.77 | G36: =E36*F36 -> 4588.5 | M36: =M35+K36-L36 -> 61661.701
E37: =SUM(E4:E34) -> 1049.33 | G37: =SUM(G4:G34) -> 96297.014 | H37: =SUM(H4:H34) -> 61 | J37: =SUM(J4:J34) -> 6364.08 | K37: =SUM(K4:K34) -> 102661.09 | L37: =SUM(L4:L34) -> 82597

Sheet Kabbur
A1: Shri Jai Hanuman Petrolium
A2: S.No | B2: Date | C2: GRN No | D2: Ind no/Bill No | E2: Diesel (Lts) | F2: Price | G2: Amount | H2: Petrol (Lts) | I2: Price | J2: Amount | K2: Total amount | L2: Amount paid | M2: As on Date | N2: Remarks
A3: Opening Balance | K3: 0 | M3: =+K3 -> 0
A4: 1 | B4: 45931 | E4: 0 | F4: 0 | G4: =E4*F4 -> 0 | K4: =G4+J4 -> 0 | L4: =+K4 -> 0
A5: 2 | B5: 45932 | E5: 0 | F5: 0 | G5: =E5*F5 -> 0 | K5: =G5+J5 -> 0 | L5: =+K5 -> 0
A6: 3 | B6: 45933 | E6: 0 | F6: 0 | G6: =E6*F6 -> 0 | K6: =G6+J6 -> 0 | L6: =+K6 -> 0
A7: 4 | B7: 45934 | E7: 0 | F7: 0 | G7: =E7*F7 -> 0 | K7: =G7+J7 -> 0 | L7: =+K7 -> 0
A8: 5 | B8: 45935 | E8: 0 | F8: 0 | G8: =E8*F8 -> 0 | K8: =G8+J8 -> 0 | L8: =+K8 -> 0
A9: 6 | B9: 45936 | E9: 0 | F9: 0 | G9: =E9*F9 -> 0 | K9: =G9+J9 -> 0 | L9: =+K9 -> 0
A10: 7 | B10: 45937 | E10: 120 | F10: 91.59 | G10: =E10*F10 -> 10990.8 | H10: 15.76 | I10: 103.53 | J10: =H10*I10 -> 1631.6328 | K10: =G10+J10 -> 12622.433 | L10: =+K10 -> 12622.433
A11: 8 | B11: 45938 | E11: 0 | F11: 0 | G11: =E11*F11 -> 0 | K11: =G11+J11 -> 0 | L11: =+K11 -> 0
A12: 9 | B12: 45939 | E12: 0 | F12: 0 | G12: =E12*F12 -> 0 | J12: =H12*I12 -> 0 | K12: =G12+J12 -> 0 | L12: =+K12 -> 0
A13: 10 | B13: 45940 | E13: 100 | F13: 91.59 | G13: =E13*F13 -> 9159 | J13: =H13*I13 -> 0 | K13: =G13+J13 -> 9159 | L13: =+K13 -> 9159
A14: 11 | B14: 45941 | E14: 0 | F14: 0 | G14: =E14*F14 -> 0 | J14: =H14*I14 -> 0 | K14: =G14+J14 -> 0 | L14: =+K14 -> 0
A15: 12 | B15: 45942 | E15: 0 | F15: 0 | G15: =E15*F15 -> 0 | J15: =H15*I15 -> 0 | K15: =G15+J15 -> 0 | L15: =+K15 -> 0
A16: 13 | B16: 45943 | E16: 100 | F16: 91.59 | G16: =E16*F16 -> 9159 | J16: =H16*I16 -> 0 | K16: =G16+J16 -> 9159 | L16: =+K16 -> 9159
A17: 14 | B17: 45944 | E17: 0 | F17: 0 | G17: =E17*F17 -> 0 | H17: 5 | I17: 103.53 | J17: =H17*I17 -> 517.65 | K17: =G17+J17 -> 517.65 | L17: =+K17 -> 517.65
A18: 15 | B18: 45945 | E18: 100 | F18: 91.59 | G18: =E18*F18 -> 9159 | J18: =H18*I18 -> 0 | K18: =G18+J18 -> 9159 | L18: =+K18 -> 9159
A19: 16 | B19: 45946 | E19: 5.65 | F19: 91.59 | G19: =E19*F19 -> 517.4835 | J19: =H19*I19 -> 0 | K19: =G19+J19 -> 517.4835 | L19: =+K19 -> 517.4835
A20: 17 | B20: 45947 | E20: 0 | F20: 0 | G20: =E20*F20 -> 0 | H20: 5 | I20: 103.53 | J20: =H20*I20 -> 517.65 | K20: =G20+J20 -> 517.65 | L20: =+K20 -> 517.65
A21: 18 | B21: 45948 | E21: 0 | F21: 0 | G21: =E21*F21 -> 0 | J21: =H21*I21 -> 0 | K21: =G21+J21 -> 0 | L21: =+K21 -> 0
A22: 19 | B22: 45949 | E22: 0 | F22: 0 | G22: =E22*F22 -> 0 | J22: =H22*I22 -> 0 | K22: =G22+J22 -> 0 | L22: =+K22 -> 0
A23: 20 | B23: 45950 | E23: 0 | F23: 0 | G23: =E23*F23 -> 0 | J23: =H23*I23 -> 0 | K23: =G23+J23 -> 0 | L23: =+K23 -> 0
A24: 21 | B24: 45951 | E24: 100 | F24: 91.59 | G24: =E24*F24 -> 9159 | H24: 7 | I24: 103.53 | J24: =H24*I24 -> 724.71 | K24: =G24+J24 -> 9883.71 | L24: =+K24 -> 9883.71
A25: 22 | B25: 45952 | E25: 0 | F25: 0 | G25: =E25*F25 -> 0 | H25: 6.57 | I25: 103.53 | J25: =H25*I25 -> 680.1921 | K25: =G25+J25 -> 680.1921 | L25: =+K25 -> 680.1921
A26: 23 | B26: 45953 | E26: 0 | F26: 0 | G26: =E26*F26 -> 0 | J26: =H26*I26 -> 0 | K26: =G26+J26 -> 0 | L26: =+K26 -> 0
A27: 24 | B27: 45954 | E27: 0 | F27: 0 | G27: =E27*F27 -> 0 | J27: =H27*I27 -> 0 | K27: =G27+J27 -> 0 | L27: =+K27 -> 0 | O27: 0
A28: 25 | B28: 45955 | E28: 0 | F28: 0 | G28: =E28*F28 -> 0 | J28: =H28*I28 -> 0 | K28: =G28+J28 -> 0 | L28: =+K28 -> 0
A29: 26 | B29: 45956 | E29: 0 | F29: 0 | G29: =E29*F29 -> 0 | J29: =H29*I29 -> 0 | K29: =G29+J29 -> 0 | L29: =+K29 -> 0
A30: 27 | B30: 45957 | E30: 25 | F30: 91.59 | G30: =E30*F30 -> 2289.75 | J30: =H30*I30 -> 0 | K30: =G30+J30 -> 2289.75 | L30: =+K30 -> 2289.75
A31: 28 | B31: 45958 | E31: 0 | F31: 0 | G31: =E31*F31 -> 0 | J31: =H31*I31 -> 0 | K31: =G31+J31 -> 0 | L31: =+K31 -> 0
A32: 29 | B32: 45959 | E32: 0 | F32: 0 | G32: =E32*F32 -> 0 | J32: =H32*I32 -> 0 | K32: =G32+J32 -> 0 | L32: =+K32 -> 0
A33: 30 | B33: 45960 | E33: 0 | F33: 0 | G33: =E33*F33 -> 0 | H33: 2 | I33: 103.53 | J33: =H33*I33 -> 207.06 | K33: =G33+J33 -> 207.06 | L33: =+K33 -> 207.06
A34: 31 | E34: 0 | F34: 0 | G34: =E34*F34 -> 0 | K34: =G34+J34 -> 0
E35: =SUM(E4:E34) -> 550.65 | G35: =SUM(G4:G34) -> 50434.034 | H35: =SUM(H4:H34) -> 41.33 | J35: =SUM(J4:J34) -> 4278.8949 | K35: =SUM(K4:K34) -> 54712.928 | L35: =SUM(L4:L34) -> 54712.928

Sheet kumta
A1: Krishma fuel station
A2: S.No | B2: Date | C2: GRN No | D2: Ind No/Bill No | E2: Diesel (Lts) | F2: Price | G2: Amount | H2: Petrol (Lts) | I2: Price | J2: Amount | K2: Total amount | L2: Amount paid | M2: As on Date | N2: Remarks
A3: Opening Balance | K3: 0 | M3: =+K3 -> 0
A4: 1 | B4: 45931 | E4: 0 | F4: 0 | G4: =E4*F4 -> 0 | H4: 0 | I4: 0 | J4: =H4*I4 -> 0 | K4: =G4+J4 -> 0 | L4: =+K4 -> 0 | M4: =M3+K4-L4 -> 0 | N4: IOCL Card
A5: 2 | B5: 45932 | E5: 0 | F5: 0 | G5: =E5*F5 -> 0 | H5: 0 | I5: 0 | J5: =H5*I5 -> 0 | K5: =G5+J5 -> 0 | L5: =+K5 -> 0 | M5: =M4+K5-L5 -> 0
A6: 3 | B6: 45933 | E6: 100 | F6: 91.92 | G6: =E6*F6 -> 9192 | H6: 0 | I6: 0 | J6: =H6*I6 -> 0 | K6: =G6+J6 -> 9192 | L6: =+K6 -> 9192 | M6: =M5+K6-L6 -> 0
