Workbook

Sheet Sheet1
A1: S.no | B1: Site Name | C1: Bunk Name | D1: Diesel(Liters) | E1: Diesel Amount | F1: Petrol(Liters) | G1: Petrol Amount | H1: Total Amount | I1: Opening Blance | J1: Amount Paid | K1: Closing Balances
A2: 1 | B2: Khammam-1 | C2: Sri Ramakotaiah Fuel Point | D2: 11984.26 | E2: 1146654 | F2: 130 | G2: 13969.8 | H2: =E2+G2 -> 1160623.8 | I2: 5140597 | J2: 2500000 | K2: =I2+H2-J2 -> 3801220.8
A3: 2 | B3: Khammam-2 | C3: Divya laxmi ganapathi | D3: 118512.26 | E3: 11339228 | F3: 535 | G3: 57491.1 | H3: =E3+G3 -> 11396719 | I3: 3730421 | J3: 1500000 | K3: =I3+H3-J3 -> 13627140
A4: 3 | B4: Khammam-3 | C4: Jayasai union bunk | D4: 33155.09 | E4: 3172942.1 | F4: 70 | G4: 7523.6 | H4: =E4+G4 -> 3180465.7 | I4: 8891075.4 | J4: 2000000 | K4: =I4+H4-J4 -> 10071541
A5: 4 | B5: Jadcherla-1 | C5: Sai Baba Fuel Station | D5: 6550.84 | E5: 631631.99 | F5: 305.75 | G5: 33091.323 | H5: =E5+G5 -> 664723.32 | I5: 1966837 | J5: 0 | K5: =I5+H5-J5 -> 2631560.3
A6: 5 | B6: Jadcherla-2 | C6: Uttara Enterprises | D6: 0 | E6: 0 | F6: 0 | G6: 0 | H6: =E6+G6 -> 0 | I6: 1832240.6 | J6: 0 | K6: =I6+H6-J6 -> 1832240.6
A7: 6 | B7: Jadcherla-3 | C7: Bhavani KSK Fuel Station-Nawabpet | D7: 4040 | E7: 389092.4 | F7: 0 | G7: 0 | H7: =E7+G7 -> 389092.4 | I7: 0 | J7: 0 | K7: =I7+H7-J7 -> 389092.4
A8: 7 | B8: Jadcherla-4 | C8: ADHOC FILLING STATION STATION | D8: 11600 | E8: 1118588 | F8: 0 | G8: 0 | H8: =E8+G8 -> 1118588 | I8: 0 | J8: 0 | K8: =I8+H8-J8 -> 1118588
A9: 8 | B9: Sangareddy-1 | C9: Shree lakshmi ganapathi F/S | D9: 4185.96 | E9: 403359.11 | F9: 62 | G9: 6706.54 | H9: =E9+G9 -> 410065.65 | I9: 1004532 | J9: 1414699.8 | K9: 0
A10: 9 | B10: Sangareddy-2 | C10: Sri Durgabhavani Filling Station | D10: 165 | E10: 15912 | F10: 16 | G10: 1732.96 | H10: =E10+G10 -> 17644.96 | I10: 0 | J10: 17644.96 | K10: =I10+H10-J10 -> 0
A11: 10 | B11: Sangareddy-3 | C11: Laxmi Narasimha Enterprises F/S | D11: 40 | E11: 3849 | F11: 0 | G11: 0 | H11: =E11+G11 -> 3849 | I11: 0 | J11: 3849 | K11: =I11+H11-J11 -> 0
A12: 11 | B12: Sangareddy-4 | C12: Sree Shiva Parvathi Filling Station | D12: 1459.79 | E12: 140476 | F12: 16 | G12: 1732.96 | H12: =E12+G12 -> 142208.96 | I12: 0 | J12: 142208.96 | K12: =I12+H12-J12 -> 0
A13: 12 | B13: YG Gudda | C13: Pallavi Petrolium | D13: 3800 | E13: 346940 | F13: 385 | G13: 39747.4 | H13: =E13+G13 -> 386687.4 | I13: 244365 | J13: 299920 | K13: =I13+H13-J13 -> 331132.4
A14: 13 | B14: Hosadurga-1 | C14: Merchant Petroliums | D14: 4500 | E14: 412380 | F14: 140 | G14: 14777 | H14: =E14+G14 -> 427157 | I14: 0 | J14: 150000 | K14: =I14+H14-J14 -> 277157
A15: 14 | B15: Hosadurga-2 | C15: Shree Veeraprathap Fuel | D15: 2000 | E15: 182780 | F15: 135 | G15: 13967.1 | H15: =E15+G15 -> 196747.1 | I15: 151569.4 | J15: 150000 | K15: =I15+H15-J15 -> 198316.5
A16: 15 | B16: Malebennuru(KUWSDB) | C16: Sri Ramanjuneya Service Station | D16: 3277.82 | E16: 301888 | F16: 138 | G16: 14332 | H16: =E16+G16 -> 316220 | I16: 96655 | J16: 385490 | K16: =I16+H16-J16 -> 27385
A17: 16 | B17: kadur | C17: Vishal Service Station | D17: 2000 | E17: 182300 | F17: 145 | G17: 15119.15 | H17: =E17+G17 -> 197419.15 | I17: 578097.65 | J17: 0 | K17: =I17+H17-J17 -> 775516.8
A18: 17 | B18: Hiriyur(VJNL) | C18: Sri Balaji Agencies | D18: 2400 | E18: 221040 | F18: 210 | G18: 21810.6 | H18: =E18+G18 -> 242850.6 | I18: 237520 | J18: 250000 | K18: =I18+H18-J18 -> 230370.6
A19: 18 | B19: Chellakere(KUWSDB) | C19: Sri Vishnu Baba Petroleum | D19: 2045 | E19: 188324.05 | F19: 125 | G19: 12982.5 | H19: =E19+G19 -> 201306.55 | I19: 0 | J19: 201306.55 | K19: =I19+H19-J19 -> 0
A20: 19 | B20: Khanapur(PKG-3) | C20: J K Makavi | D20: 169 | E20: 15411.11 | F20: 16.25 | G20: 1669.23 | H20: =E20+G20 -> 17080.34 | I20: 0 | J20: 17080.34 | K20: =I20+H20-J20 -> 0
A21: 20 | B21: Munavalli(PKG-3) | C21: Shahapur Petroleum | D21: 14283.35 | E21: 1303412.1 | F21: 127 | G21: 13103.86 | H21: =E21+G21 -> 1316516 | I21: 58857 | J21: 1134279.9 | K21: =I21+H21-J21 -> 241093.08
... A24: 23 | B24: Kabbur(PKG-3) | C24: Shri Jai Hanuman Petrolium | D24: 509.02 | E24: 46621.142 | F24: 11.56 | G24: 1196.8068 | H24: =E24+G24 -> 47817.949 | I24: 0 | J24: 47817.949 | K24: =I24+H24-J24 -> 0
A25: 24 | B25: Kumta (PKG-1) | C25: Krishma fuel station | D25: 760.33 | E25: 69889.534 | F25: 47.46 | G25: 4933.9416 | H25: =E25+G25 -> 74823.475 | J25: 74823.475 | K25: =I25+H25-J25 -> 0
A26: 25 | B26: Jalgaon | C26: Sri Sai Petrol Pump | D26: 597.14 | E26: 54712.182 | F26: 13.52 | G26: 1419.4272 | H26: =E26+G26 -> 56131.609 | I26: 4528.49 | J26: 49930.511 | K26: =I26+H26-J26 -> 10729.588
A27: 26 | B27: MKBD | C27: Shree Sai Samarth Petroleum | D27: 25450 | E27: 2319513 | F27: 75 | G27: 7845 | H27: =E27+G27 -> 2327358 | I27: 1668531 | J27: 2000000 | K27: =I27+H27-J27 -> 1995889
A28: 27 | B28: Haveri | C28: Shivalingeshwar Petroleum | D28: 944.46 | E28: 86389.756 | F28: 63.01 | G28: 6517.1243 | H28: =E28+G28 -> 92906.88 | I28: 90058 | J28: 115444 | K28: =I28+H28-J28 -> 67520.88
A29: 28 | B29: Guttal | C29: Taware filling station | D29: 935.89 | E29: 85914.702 | F29: 40 | G29: 4150.4 | H29: =E29+G29 -> 90065.102 | J29: 90065.102 | K29: =I29+H29-J29 -> 0
A30: 29 | B30: Rattihali | C30: Shree Siri Gowari petroliam | D30: 1032.57 | E30: 95037.743 | F30: 45 | G30: 4680.9 | H30: =E30+G30 -> 99718.643 | J30: 99718.643 | K30: =I30+H30-J30 -> 0
A31: 30 | B31: Gajendragada | C31: Vanasri Petrol Pump | D31: 60 | E31: 5509.8 | F31: 18 | G31: 1868.4 | H31: =E31+G31 -> 7378.2 | I31: 30323 | J31: 7378.2 | K31: =I31+H31-J31 -> 30323
A32: 31 | B32: Ghattaprabha(PKG-3) | C32: Vivek Petrol Pump | D32: 0 | E32: 0 | F32: 0 | G32: 0 | H32: =E32+G32 -> 0 | I32: 1036347.3 | J32: 400000 | K32: =I32+H32-J32 -> 636347.32
A33: 32 | B33: Gokak(PKG-3) | C33: AJ Petrolinks | D33: 11163.57 | E33: 1021243.4 | F33: 271 | G33: 28024.11 | H33: =E33+G33 -> 1049267.5 | I33: 473791 | J33: 300000 | K33: =I33+H33-J33 -> 1223058.5
A34: 33 | B34: Ghattaprabha-2(PKG-3) | C34: Manikeri Petroleums | D34: 0 | E34: 0 | F34: 4.82 | G34: 499.98 | H34: =E34+G34 -> 499.98 | I34: 0 | J34: 499.98 | K34: =I34+H34-J34 -> 0
A35: 34 | B35: Ankalgi(PKG-3) | C35: Nirwani Petroleums | D35: 152.92 | E35: 13949.929 | F35: 37.28 | G35: 3857.5144 | H35: =E35+G35 -> 17807.443 | I35: 0 | J35: 17807.443 | K35: =I35+H35-J35 -> 0
A36: 35 | B36: Talikote(PKG-1) | C36: Raykar Oil Agencies | D36: 637.8 | E36: 58358.7 | F36: 61.99 | G36: 5912.6304 | H36: =E36+G36 -> 64271.33 | I36: 0 | J36: 64271.33 | K36: =I36+H36-J36 -> 0
A37: 36 | B37: Chadchan(PKG-1) | C37: Khavekar Petrolium | D37: 577.29 | E37: 52088.877 | F37: 43.88 | G37: 4482.7808 | H37: =E37+G37 -> 56571.658 | I37: 192780 | J37: 192780 | K37: =I37+H37-J37 -> 56571.658
A38: 37 | B38: Sindagi | C38: G.P.PORWAL | D38: 138 | E38: 12589.74 | F38: 0 | G38: 0 | H38: =E38+G38 -> 12589.74 | I38: 0 | J38: 12589.74 | K38: =I38+H38-J38 -> 0
A39: 38 | B39: Muddebihal(PKG-1) | C39: Bhosle Service Station | D39: 98.41 | E39: 8999.5945 | F39: 33.81 | G39: 3495.6159 | H39: =E39+G39 -> 12495.21 | I39: 0 | J39: 12495.21 | K39: =I39+H39-J39 -> 0
A40: 39 | B40: Almela(PKG-1) | C40: Shiddeshwar Petroleums | D40: 35.03 | E40: 3199.2899 | F40: 30.92 | G40: 3192.7992 | H40: =E40+G40 -> 6392.0891 | I40: 0 | J40: 6392.0891 | K40: =I40+H40-J40 -> 0
A41: 40 | B41: Srirangapatna | C41: Sri Chakra Fuel Station | D41: 71.77 | E41: 6500.2089 | F41: 35.13 | G41: 3599.4198 | H41: =E41+G41 -> 10099.629 | I41: 0 | J41: 10099.629 | K41: =I41+H41-J41 -> 0
A42: 41 | B42: Nalatwad(PKG-1) | C42: Shri Pawad Basaweshwar Petroleums | D42: 436.89 | E42: 40027.862 | F42: 21.25 | G42: 2200.8625 | H42: =E42+G42 -> 42228.724 | I42: 48315 | J42: 90535.84 | K42: =I42+H42-J42 -> 7.8843
A43: Total | D43: =SUM(D2:D42) -> 272571.36 | E43: =SUM(E2:E42) -> 25754294 | F43: =SUM(F2:F42) -> 3563.63 | G43: =SUM(G2:G42) -> 373628.94 | H43: =SUM(H2:H42) -> 26127923 | I43: =SUM(I2:I42) -> 27985140 | J43: =SUM(J2:J42) -> 14320973 | K43: =SUM(K2:K42) -> 39792192
D49: =PROPER(C49)

Sheet May-25
A1: S.no | B1: Site Name | C1: Bunk Name | D1: Diesel(Liters) | E1: Diesel Amount | F1: Petrol(Liters) | G1: Petrol Amount | H1: Total Amount | I1: Opening Blance | J1: Amount Paid | K1: Closing Balances
A2: 1 | B2: Khammam-1 | C2: Sri Ramakotaiah Fuel Point | D2: =+'Khammam-1'!E36 -> 11984.26 | E2: =+'Khammam-1'!G36 -> 1146654 | F2: =+'Khammam-1'!H36 -> 130 | G2: =+'Khammam-1'!J36 -> 13969.8 | H2: =E2+G2 -> 1160623.8 | I2: =+'Khammam-1'!K3 -> 5140597 | J2: =+'Khammam-1'!L36 -> 4000000 | K2: =H2+I2-J2 -> 2301220.8
A3: 2 | B3: Khammam-2 | C3: Divya laxmi ganapathi | D3: =+'Khammam-2'!E37 -> 146362.52 | E3: =+'Khammam-2'!G37 -> 14003941 | F3: =+'Khammam-2'!H37 -> 680 | G3: =+'Khammam-2'!J37 -> 73072.8 | H3: =E3+G3 -> 14077014 | I3: =+'Khammam-2'!K3 -> 3730421 | J3: =+'Khammam-2'!L37 -> 8500000 | K3: =H3+I3-J3 -> 9307434.7
A4: 3 | B4: Khammam-3 | C4: Jayasai union bunk | D4: =+'Khammam-3'!E35 -> 57904.99 | E4: =+'Khammam-3'!G35 -> 5541507.5 | F4: =+'Khammam-3'!H35 -> 230 | G4: =+'Khammam-3'!J35 -> 24720.4 | H4: =E4+G4 -> 5566227.9 | I4: =+'Khammam-3'!K3 -> 8891075.4 | J4: =+'Khammam-3'!L35 -> 7000000 | K4: =H4+I4-J4 -> 7457303.4
A5: 4 | B5: Jadcherla-1 | C5: Sai Baba Fuel Station | D5: =+'Jedcherla -1'!E35 -> 6568.06 | E5: =+'Jedcherla -1'!G35 -> 633292.35 | F5: =+'Jedcherla -1'!H35 -> 459.59 | G5: =+'Jedcherla -1'!J35 -> 49741.426 | H5: =E5+G5 -> 683033.77 | I5: =+'Jedcherla -1'!K3 -> 1966837 | J5: =+'Jedcherla -1'!L35 -> 1500000 | K5: =H5+I5-J5 -> 1149870.8
A6: 5 | B6: Jadcherla-2 | C6: Uttara Enterprises | D6: 0 | E6: 0 | F6: 0 | G6: 0 | H6: =E6+G6 -> 0 | I6: 1832240.6 | J6: 1500000 | K6: =H6+I6-J6 -> 332240.61
A7: 6 | B7: Jadcherla-3 | C7: Bhavani KSK Fuel Station-Nawabpet | D7: ='Jadcharla-3'!E35 -> 4040 | E7: =+'Jadcharla-3'!G35 -> 389092.4 | F7: 0 | G7: 0 | H7: =E7+G7 -> 389092.4 | I7: 0 | J7: 389092.4 | K7: =H7+I7-J7 -> 0
A8: 7 | B8: Jadcherla-4 | C8: ADHOC FILLING STATION STATION | D8: =+'Jedcharla-4'!E35 -> 18600 | E8: =+'Jedcharla-4'!G35 -> 1793598 | F8: 0 | G8: 0 | H8: =E8+G8 -> 1793598 | I8: 0 | J8: =+'Jedcharla-4'!L35 -> 1793598 | K8: =H8+I8-J8 -> 0
A9: 8 | B9: Sangareddy-1 | C9: Shree lakshmi ganapathi F/S | D9: 4186 | E9: 403359 | F9: 62 | G9: 6707 | H9: =E9+G9 -> 410066 | I9: 1004532 | J9: 1414700 | K9: =H9+I9-J9 -> -102
A10: 9 | B10: Sangareddy-2 | C10: Sri Durgabhavani Filling Station | D10: 165 | E10: 15912 | F10: 16 | G10: 1733 | H10: 17645 | I10: 0 | J10: 17645 | K10: =H10+I10-J10 -> 0
A11: 10 | B11: Sangareddy-3 | C11: Laxmi Narasimha Enterprises F/S | D11: 40 | E11: 3849 | F11: 0 | G11: 0 | H11: 3849 | J11: 3849 | K11: =H11+I11-J11 -> 0
A12: 11 | B12: Sangareddy-4 | C12: Sree Shiva Parvathi Filling Station | D12: 4154.79 | E12: 399815.85 | F12: 56.92 | G12: 6149.07 | H12: =E12+G12 -> 405964.92 | I12: 0 | J12: 405965 | K12: =H12+I12-J12 -> -0.08
A13: 12 | B13: Dindi | D13: =+Dindi!E35 -> 160.67 | E13: =+Dindi!G35 -> 15529.94 | F13: =+Dindi!H35 -> 0 | G13: =+Dindi!J35 -> 0 | H13: =E13+G13 -> 15529.94 | J13: =+Dindi!L35 -> 15529.94 | K13: =H13+I13-J13 -> 0
A14: 12 | B14: YG Gudda | C14: Pallavi Petrolium | D14: =+'YG Gudda '!E36 -> 6528.47 | E14: =+'YG Gudda '!G36 -> 596059.17 | F14: =+'YG Gudda '!H36 -> 595 | G14: =+'YG Gudda '!J36 -> 61427.8 | H14: =E14+G14 -> 657486.97 | I14: ='YG Gudda '!K3 -> 244365 | J14: =+'YG Gudda '!L36 -> 829920 | K14: =H14+I14-J14 -> 71931.965
A15: 13 | B15: Hosadurga-1 | C15: Merchant Petroliums | D15: =+Hosadurga!E35 -> 4500 | E15: =+Hosadurga!G35 -> 412380 | F15: =+Hosadurga!H35 -> 140 | G15: =+Hosadurga!J35 -> 14777 | H15: =E15+G15 -> 427157 | I15: 0 | J15: 427157 | K15: =H15+I15-J15 -> 0
A16: 14 | B16: Hosadurga-2 | C16: Shree Veeraprathap Fuel | D16: =+'Hosadurga -2'!E35 -> 3999.21 | E16: =+'Hosadurga -2'!G35 -> 365487.8 | F16: =+'Hosadurga -2'!H35 -> 205 | G16: =+'Hosadurga -2'!J35 -> 21209.3 | H16: =E16+G16 -> 386697.1 | I16: 151569.4 | J16: 150000 | K16: =H16+I16-J16 -> 388266.5
A17: 15 | B17: Malebennuru(KUWSDB) | C17: Sri Ramanjuneya Service Station | D17: =+'Malebenur(KUWSDB)'!E38 -> 4752.84 | E17: =+'Malebenur(KUWSDB)'!G38 -> 437736.26 | F17: =+'Malebenur(KUWSDB)'!H38 -> 193 | G17: =+'Malebenur(KUWSDB)'!J38 -> 20044.9 | H17: =E17+G17 -> 457781.16 | I17: 96655 | J17: =+'Malebenur(KUWSDB)'!L38 -> 517820.15 | K17: =H17+I17-J17 -> 36616.014
A18: 16 | B18: kadur | C18: Vishal Service Station | D18: =+Kadur!E35 -> 4011.04 | E18: =+Kadur!G35 -> 365606.3 | F18: =+Kadur!H35 -> 250 | G18: =+Kadur!J35 -> 26067.5 | H18: =E18+G18 -> 391673.8 | I18: 578097.65 | J18: 1006.3 | K18: =H18+I18-J18 -> 968765.15
A19: 17 | B19: Hiriyur(VJNL) | C19: Sri Balaji Agencies | D19: =+'Hiriyur(VJNL)'!E35 -> 2400 | E19: =+'Hiriyur(VJNL)'!G35 -> 221040 | F19: =+'Hiriyur(VJNL)'!H35 -> 280 | G19: =+'Hiriyur(VJNL)'!J35 -> 29080.8 | H19: =E19+G19 -> 250120.8 | I19: 237520 | J19: =+'Hiriyur(VJNL)'!L35 -> 400000 | K19: =H19+I19-J19 -> 87640.8
A20: 18 | B20: Chellakere(KUWSDB) | C20: Sri Vishnu Baba Petroleum | D20: =+'Chellakere (KUWSDB)'!E35 -> 2970 | E20: =+'Chellakere (KUWSDB)'!G35 -> 273507.3 | F20: =+'Chellakere (KUWSDB)'!H35 -> 165 | G20: =+'Chellakere (KUWSDB)'!J35 -> 17136.9 | H20: =E20+G20 -> 290644.2 | I20: 0 | J20: =+'Chellakere (KUWSDB)'!L35 -> 290644.2 | K20: =H20+I20-J20 -> 0
A21: 19 | B21: Khanapur(PKG-3) | C21: J K Makavi | D21: =+Khanapur!E35 -> 402.01 | E21: =+Khanapur!G35 -> 36587.059 | F21: =+Khanapur!H35 -> 21.25 | G21: =+Khanapur!J35 -> 2183.1814 | H21: =E21+G21 -> 38770.24 | I21: 0 | J21: =+Khanapur!M35 -> 38770.24 | K21: =H21+I21-J21 -> 0
A22: 20 | B22: Munavalli(PKG-3) | C22: Shahapur Petroleum | D22: =+'Munavalli(KUWSDB)'!E39 -> 16582.17 | E22: =+'Munavalli(KUWSDB)'!G39 -> 1513202.4 | F22: =+'Munavalli(KUWSDB)'!H39 -> 186.32 | G22: =+'Munavalli(KUWSDB)'!J39 -> 19224.498 | H22: =E22+G22 -> 1532426.9 | I22: 58857 | J22: =+'Munavalli(KUWSDB)'!L39 -> 1484279.9 | K22: =H22+I22-J22 -> 107004.03
A23: 21 | B23: Borgaon(PKG-3) | C23: Aadisagar Petrolium | D23: =+Borgaon!E35 -> 445.45 | E23: =+Borgaon!G35 -> 40880.476 | F23: =+Borgaon!H35 -> 46 | G23: =+Borgaon!J35 -> 4771.58 | H23: =E23+G23 -> 45652.056 | I23: 234525.22 | J23: =+Borgaon!L35 -> 257350.95 | K23: =H23+I23-J23 -> 22826.33
A24: 22 | B24: Ugar,Kudichi(PKG-3) | C24: Shiri Bhrhmanath Petrolium | D24: =+'Ugar,Khagwad,Kudichi'!E35 -> 2836.99 | E24: =+'Ugar,Khagwad,Kudichi'!G35 -> 260804.49 | F24: =+'Ugar,Khagwad,Kudichi'!H35 -> 168 | G24: =+'Ugar,Khagwad,Kudichi'!J35 -> 17453.52 | H24: =E24+G24 -> 278258.01 | I24: 273174.22 | J24: =+'Ugar,Khagwad,Kudichi'!L35 -> 310000 | K24: =H24+I24-J24 -> 241432.23
A25: 23 | B25: Kabbur(PKG-3) | C25: Shri Jai Hanuman Petrolium | D25: =+Kabbur!E35 -> 609.02 | E25: =+Kabbur!G35 -> 55780.142 | F25: =+Kabbur!H35 -> 11.56 | G25: =+Kabbur!J35 -> 1196.8068 | H25: =E25+G25 -> 56976.949 | I25: 0 | J25: =+Kabbur!L35 -> 56976.949 | K25: =H25+I25-J25 -> 0
A26: 24 | B26: Kumta (PKG-1) | C26: Krishma fuel station | D26: =+kumta!E35 -> 1080.33 | E26: =+kumta!G35 -> 99303.934 | F26: =+kumta!H35 -> 76.24 | G26: =+kumta!J35 -> 7925.6554 | H26: =E26+G26 -> 107229.59 | I26: 0 | J26: =+kumta!L35 -> 107229.59 | K26: =H26+I26-J26 -> 0
A27: 25 | B27: Jalgaon | C27: Sri Sai Petrol Pump | D27: =+Jalgaon!E39 -> 856.74 | E27: =+Jalgaon!G39 -> 78520.441 | F27: =+Jalgaon!H39 -> 13.52 | G27: =+Jalgaon!J39 -> 1419.4272 | H27: =E27+G27 -> 79939.868 | I27: 4528.49 | J27: =+Jalgaon!L39 -> 70742.446 | K27: =H27+I27-J27 -> 13725.912
A28: 26 | B28: MKBD | C28: Shree Sai Samarth Petroleum | D28: =+MKBD!E36 -> 34366.54 | E28: =+MKBD!G36 -> 3132158.8 | F28: =+MKBD!H36 -> 95 | G28: =+MKBD!J36 -> 9937 | H28: =E28+G28 -> 3142095.8 | I28: 1668531 | J28: =+MKBD!L36 -> 4361948.8 | K28: =H28+I28-J28 -> 448678
A29: 27 | B29: Haveri | C29: Shivalingeshwar Petroleum | D29: =+Haveri!E35 -> 1327.13 | E29: =+Haveri!G35 -> 121392.58 | F29: =+Haveri!H35 -> 74.68 | G29: =+Haveri!J35 -> 7723.8023 | H29: =E29+G29 -> 129116.38 | I29: 90058 | J29: =+Haveri!L35 -> 182855.23 | K29: =H29+I29-J29 -> 36319.153
A30: 28 | B30: Guttal | C30: Taware filling station | D30: =+Guttal!E35 -> 1295.79 | E30: =+Guttal!G35 -> 118953.52 | F30: =+Guttal!H35 -> 67 | G30: =+Guttal!J35 -> 6951.92 | H30: =E30+G30 -> 125905.44 | I30: 0 | J30: =+Guttal!L35 -> 125905.44 | K30: =H30+I30-J30 -> 0.002
A31: 29 | B31: Rattihali | C31: Shree Siri Gowari petroliam | D31: =+Rattihali!E35 -> 1382.42 | E31: =+Rattihali!G35 -> 127237.94 | F31: =+Rattihali!H35 -> 55 | G31: =+Rattihali!J35 -> 5722.9 | H31: =E31+G31 -> 132960.84 | I31: 0 | J31: =+Rattihali!L35 -> 132960.84 | K31: =H31+I31-J31 -> 0
A32: 30 | B32: Gajendragada | C32: Vanasri Petrol Pump | D32: =+Gajendragada!E35 -> 280 | E32: =+Gajendragada!G35 -> 25712.4 | F32: =+Gajendragada!H35 -> 33 | G32: =+Gajendragada!J35 -> 3425.4 | H32: =E32+G32 -> 29137.8 | I32: 30323 | J32: =+Gajendragada!L35 -> 0 | K32: =H32+I32-J32 -> 59460.8
A33: 31 | B33: Ghattaprabha(PKG-3) | C33: Vivek Petrol Pump | D33: =+Ghattaprabha!E35 -> 0 | E33: =+Ghattaprabha!G35 -> 0 | F33: =+Ghattaprabha!H35 -> 0 | G33: =+Ghattaprabha!J35 -> 0 | H33: =E33+G33 -> 0 | I33: 1036347.3 | J33: =+Ghattaprabha!L35 -> 1036347 | K33: =H33+I33-J33 -> 0.3179
A34: 32 | B34: Gokak(PKG-3) | C34: AJ Petrolinks | D34: =+'Gokak Dharwad PKG 3'!E35 -> 16586.07 | E34: =+'Gokak Dharwad PKG 3'!G35 -> 1517293.7 | F34: =+'Gokak Dharwad PKG 3'!H35 -> 452 | G34: =+'Gokak Dharwad PKG 3'!J35 -> 46904.28 | H34: =E34+G34 -> 1564198 | I34: 473791 | J34: =+'Gokak Dharwad PKG 3'!L35 -> 500000 | K34: =H34+I34-J34 -> 1537989
A35: 33 | B35: Ghattaprabha-2(PKG-3) | C35: Manikeri Petroleums | D35: 0 | E35: 0 | F35: 4.82 | G35: 499.98 | H35: =E35+G35 -> 499.98 | I35: 0 | J35: 499.98 | K35: =H35+I35-J35 -> 0
A36: 34 | B36: Ankalgi(PKG-3) | C36: Nirwani Petroleums | D36: 152.92 | E36: 13949.929 | F36: 37.28 | G36: 3857.5144 | H36: =E36+G36 -> 17807.443 | I36: 0 | J36: 17807.443 | K36: =H36+I36-J36 -> 0
A37: 35 | B37: ShankeshWAR | C37: SR Patil | D37: =+' Shankeshwar'!F35 -> 317 | E37: =+' Shankeshwar'!H35 -> 28942.1 | F37: =+' Shankeshwar'!I35 -> 9.68 | G37: =+' Shankeshwar'!K35 -> 999.1696 | H37: =E37+G37 -> 29941.27 | J37: 18442 | K37: =H37+I37-J37 -> 11499.27
A38: 36 | B38: Talikote(PKG-1) | C38: Raykar Oil Agencies | D38: =+' Talikote'!E44 -> 1084.75 | E38: =+' Talikote'!G44 -> 99250.544 | F38: =+' Talikote'!H44 -> 90.52 | G38: =+' Talikote'!J44 -> 9363.3888 | H38: =E38+G38 -> 108613.93 | I38: 0 | J38: =+' Talikote'!L44 -> 106125.19 | K38: =H38+I38-J38 -> 2488.7434
A39: 37 | B39: Chadchan(PKG-1) | C39: Khavekar Petrolium | D39: =+Chadchan!E35 -> 795.91 | E39: =+Chadchan!G35 -> 71814.959 | F39: =+Chadchan!H35 -> 60.36 | G39: =+Chadchan!J35 -> 6166.3776 | H39: =E39+G39 -> 77981.337 | I39: 192780 | J39: =+Chadchan!L35 -> 192780 | K39: =H39+I39-J39 -> 77981.337
A40: 38 | B40: Sindagi | C40: G.P.PORWAL | D40: =+Sindagi!E44 -> 607.7 | E40: =+Sindagi!G44 -> 55440.471 | F40: =+Sindagi!H44 -> 0 | G40: =+Sindagi!J44 -> 0 | H40: =E40+G40 -> 55440.471 | I40: 0 | J40: =+Sindagi!L44 -> 55440.471 | K40: =H40+I40-J40 -> 0
A41: 39 | B41: Muddebihal(PKG-1) | C41: Bhosle Service Station | D41: =+Muddebihal!E46 -> 146.71 | E41: =+Muddebihal!G46 -> 13416.629 | F41: =+Muddebihal!H46 -> 38.64 | G41: =+Muddebihal!J46 -> 3994.9896 | H41: =E41+G41 -> 17411.619 | I41: 0 | J41: =+Muddebihal!L46 -> 17411.619 | K41: =H41+I41-J41 -> 0
A42: 40 | B42: Almela(PKG-1) | C42: Shiddeshwar Petroleums | D42: =+Alemela!E43 -> 295.22 | E42: =+Alemela!G43 -> 26962.443 | F42: =+Alemela!H43 -> 50.62 | G42: =+Alemela!J43 -> 5227.0212 | H42: =E42+G42 -> 32189.464 | I42: 0 | J42: =+Alemela!L43 -> 32189.464 | K42: =H42+I42-J42 -> 0
A43: 42 | B43: Nalatwad(PKG-1) | C43: Shri Pawad Basaweshwar Petroleums | D43: =+Nalatwad!E43 -> 646.89 | E43: =+Nalatwad!G43 -> 59268.062 | F43: =+Nalatwad!H43 -> 30.91 | G43: =+Nalatwad!J43 -> 3201.3487 | H43: =E43+G43 -> 62469.41 | I43: 48315 | J43: =+Nalatwad!L43 -> 90535.84 | K43: =H43+I43-J43 -> 20248.571
A44: 41 | B44: Srirangapatna | C44: Sri Chakra Fuel Station | D44: =+Srirangapatna!E35 -> 259.47 | E44: =+Srirangapatna!G35 -> 23500.198 | F44: =+Srirangapatna!H35 -> 49.16 | G44: =+Srirangapatna!J35 -> 5036.9336 | H44: =E44+G44 -> 28537.131 | I44: 0 | J44: =+Srirangapatna!L35 -> 28537.131 | K44: =H44+I44-J44 -> 0
A45: Total | D45: =SUM(D2:D44) -> 365685.08 | E45: =SUM(E2:E44) -> 34538741 | F45: =SUM(F2:F44) -> 5134.07 | G45: =SUM(G2:G44) -> 539024.39 | H45: =SUM(H2:H44) -> 35077765 | I45: =SUM(I2:I44) -> 27985140 | J45: =SUM(J2:J44) -> 38382064 | K45: =H45+I45-J45 -> 24680842
K46: 24419621
K47: =K45-K46 -> 261221.31

Sheet  May -2025 revised
A1: S.no | B1: Site Name | C1: Bunk Name | D1: Diesel(Liters) | E1: Diesel Amount | F1: Petrol(Liters) | G1: Petrol Amount | H1: Total Amount | I1: Opening Blance | J1: Amount Paid | K1: Closing Balances
A2: 1 | B2: Khammam-1 | C2: Sri Ramakotaiah Fuel Point | D2: ='Khammam-1'!E36 -> 11984.26 | E2: ='Khammam-1'!G36 -> 1146654 | F2: ='Khammam-1'!H36 -> 130 | G2: ='Khammam-1'!J36 -> 13969.8 | H2: =E2+G2 -> 1160623.8 | I2: ='Khammam-1'!K3 -> 5140597 | J2: =+'Khammam-1'!L36 -> 4000000 | K2: =I2+H2-J2 -> 2301220.8
A3: 2 | B3: Khammam-2 | C3: Divya laxmi ganapathi | D3: =+'Khammam-2'!E37 -> 146362.52 | E3: =+'Khammam-2'!G37 -> 14003941 | F3: =+'Khammam-2'!H37 -> 680 | G3: =+'Khammam-2'!J37 -> 73072.8 | H3: =E3+G3 -> 14077014 | I3: =+'Khammam-2'!K3 -> 3730421 | J3: =+'Khammam-2'!L37 -> 8500000 | K3: =I3+H3-J3 -> 9307434.7
A4: 3 | B4: Khammam-3 | C4: Jayasai union bunk | D4: =+'Khammam-3'!E35 -> 57904.99 | E4: =+'Khammam-3'!G35 -> 5541507.5 | F4: =+'Khammam-3'!H35 -> 230 | G4: =+'Khammam-3'!J35 -> 24720.4 | H4: =E4+G4 -> 5566227.9 | I4: =+'Khammam-3'!K3 -> 8891075.4 | J4: =+'Khammam-3'!L35 -> 7000000 | K4: =I4+H4-J4 -> 7457303.4
A5: 4 | B5: Jadcherla-1 | C5: Sai Baba Fuel Station | D5: =+'Jedcherla -1'!E35 -> 6568.06 | E5: =+'Jedcherla -1'!G35 -> 633292.35 | F5: =+'Jedcherla -1'!H35 -> 459.59 | G5: =+'Jedcherla -1'!J35 -> 49741.426 | H5: =E5+G5 -> 683033.77 | I5: =+'Jedcherla -1'!K3 -> 1966837 | J5: =+'Jedcherla -1'!L35 -> 1500000 | K5: =I5+H5-J5 -> 1149870.8
A6: 5 | B6: Jadcherla-2 | C6: Uttara Enterprises | D6: =+'Jedcherla-2'!E35 -> 0 | E6: =+'Jedcherla-2'!G35 -> 0 | F6: =+'Jedcherla-2'!H35 -> 0 | G6: =+'Jedcherla-2'!J35 -> 0 | H6: =E6+G6 -> 0 | I6: =+'Jedcherla-2'!K3 -> 1831699.5 | J6: =+'Jedcherla-2'!L35 -> 1500000 | K6: =I6+H6-J6 -> 331699.53
A7: 6 | B7: Jadcherla-3 | C7: Bhavani KSK Fuel Station-Nawabpet | D7: =+'Jadcharla-3'!E35 -> 4040 | E7: =+'Jadcharla-3'!G35 -> 389092.4 | F7: =+'Jadcharla-3'!H35 -> 0 | G7: =+'Jadcharla-3'!J35 -> 0 | H7: =E7+G7 -> 389092.4 | I7: =+'Jadcharla-3'!M3 -> 0 | J7: =+'Jadcharla-3'!L35 -> 389092.4 | K7: =I7+H7-J7 -> 0
A8: 7 | B8: Jadcherla-4 | C8: ADHOC FILLING STATION STATION | D8: =+'Jedcharla-4'!E35 -> 18600 | E8: =+'Jedcharla-4'!G35 -> 1793598 | F8: =+'Jedcharla-4'!H35 -> 0 | G8: =+'Jedcharla-4'!J35 -> 0 | H8: =E8+G8 -> 1793598 | I8: =+'Jedcharla-4'!M3 -> 0 | J8: =+'Jedcharla-4'!L35 -> 1793598 | K8: =I8+H8-J8 -> 0
A9: 8 | B9: Sangareddy-1 | C9: Shree lakshmi ganapathi F/S | D9: 4186 | E9: 403359 | F9: 62 | G9: 6707 | H9: 410066 | I9: 1004532 | J9: 1414700 | K9: =I9+H9-J9 -> -102
A10: 9 | B10: Sangareddy-2 | C10: Sri Durgabhavani Filling Station | D10: 165 | E10: 15912 | F10: 16 | G10: 1733 | H10: 17645 | I10: 0 | J10: 17645 | K10: =I10+H10-J10 -> 0
A11: 10 | B11: Sangareddy-3 | C11: Laxmi Narasimha Enterprises F/S | D11: 40 | E11: 3849 | F11: 0 | G11: 0 | H11: 3849 | I11: 0 | J11: 3849 | K11: =I11+H11-J11 -> 0
A12: 11 | B12: Sangareddy-4 | C12: Sree Shiva Parvathi Filling Station | D12: 4155 | E12: 399816 | F12: 57 | G12: 6149 | H12: 405965 | I12: 0 | J12: 405965 | K12: =I12+H12-J12 -> 0
A13: 12 | B13: Dindi | D13: =+Dindi!E35 -> 160.67 | E13: =+Dindi!G35 -> 15529.94 | F13: =+Dindi!H35 -> 0 | G13: =+Dindi!J35 -> 0 | H13: =E13+G13 -> 15529.94 | I13: =+Dindi!M3 -> 0 | J13: =+Dindi!L35 -> 15529.94 | K13: =I13+H13-J13 -> 0
A14: 12 | B14: YG Gudda | C14: Pallavi Petrolium | D14: =+'YG Gudda '!E36 -> 6528.47 | E14: =+'YG Gudda '!G36 -> 596059.17 | F14: =+'YG Gudda '!H36 -> 595 | G14: =+'YG Gudda '!J36 -> 61427.8 | H14: =E14+G14 -> 657486.97 | I14: =+'YG Gudda '!M3 -> 244365 | J14: =+'YG Gudda '!L36 -> 829920 | K14: =I14+H14-J14 -> 71931.965
A15: 13 | B15: Hosadurga-1 | C15: Merchant Petroliums | D15: =+Hosadurga!E35 -> 4500 | E15: =+Hosadurga!G35 -> 412380 | F15: =+Hosadurga!H35 -> 140 | G15: =+Hosadurga!J35 -> 14777 | H15: =E15+G15 -> 427157 | I15: =+Hosadurga!M3 -> 0 | J15: =+Hosadurga!L35 -> 427157 | K15: =I15+H15-J15 -> 0
A16: 14 | B16: Hosadurga-2 | C16: Shree Veeraprathap Fuel | D16: =+'Hosadurga -2'!E35 -> 3999.21 | E16: =+'Hosadurga -2'!G35 -> 365487.8 | F16: =+'Hosadurga -2'!H35 -> 205 | G16: =+'Hosadurga -2'!J35 -> 21209.3 | H16: =E16+G16 -> 386697.1 | I16: =+'Hosadurga -2'!M3 -> 151569.4 | J16: =+'Hosadurga -2'!L35 -> 150000 | K16: =I16+H16-J16 -> 388266.5
A17: 15 | B17: Malebennuru(KUWSDB) | C17: Sri Ramanjuneya Service Station | D17: =+'Malebenur(KUWSDB)'!E38 -> 4752.84 | E17: =+'Malebenur(KUWSDB)'!G38 -> 437736.26 | F17: =+'Malebenur(KUWSDB)'!H38 -> 193 | G17: =+'Malebenur(KUWSDB)'!J38 -> 20044.9 | H17: =E17+G17 -> 457781.16 | I17: =+'Malebenur(KUWSDB)'!M3 -> 96655 | J17: =+'Malebenur(KUWSDB)'!L38 -> 517820.15 | K17: =I17+H17-J17 -> 36616.014
A18: 16 | B18: kadur | C18: Vishal Service Station | D18: =+Kadur!E35 -> 4011.04 | E18: =+Kadur!G35 -> 365606.3 | F18: =+Kadur!H35 -> 250 | G18: =+Kadur!J35 -> 26067.5 | H18: =E18+G18 -> 391673.8 | I18: =+Kadur!K3 -> 776427.65 | J18: =+Kadur!L35 -> 1006.3 | K18: =I18+H18-J18 -> 1167095.1
A19: 17 | B19: Hiriyur(VJNL) | C19: Sri Balaji Agencies | D19: =+'Hiriyur(VJNL)'!E35 -> 2400 | E19: =+'Hiriyur(VJNL)'!G35 -> 221040 | F19: =+'Hiriyur(VJNL)'!H35 -> 280 | G19: =+'Hiriyur(VJNL)'!J35 -> 29080.8 | H19: =E19+G19 -> 250120.8 | I19: =+'Hiriyur(VJNL)'!M3 -> 237520 | J19: =+'Hiriyur(VJNL)'!L35 -> 400000 | K19: =I19+H19-J19 -> 87640.8
A20: 18 | B20: Chellakere(KUWSDB) | C20: Sri Vishnu Baba Petroleum | D20: =+'Chellakere (KUWSDB)'!E35 -> 2970 | E20: =+'Chellakere (KUWSDB)'!G35 -> 273507.3 | F20: =+'Chellakere (KUWSDB)'!H35 -> 165 | G20: =+'Chellakere (KUWSDB)'!J35 -> 17136.9 | H20: =E20+G20 -> 290644.2 | I20: =+'Chellakere (KUWSDB)'!L3 -> 0 | J20: =+'Chellakere (KUWSDB)'!L35 -> 290644.2 | K20: =I20+H20-J20 -> 0
A21: 19 | B21: Khanapur(PKG-3) | C21: J K Makavi | D21: =+Khanapur!E35 -> 402.01 | E21: =+Khanapur!G35 -> 36587.059 | F21: =+Khanapur!H35 -> 21.25 | G21: =+Khanapur!J35 -> 2183.1814 | H21: =E21+G21 -> 38770.24 | I21: =+Khanapur!M3 -> 0 | J21: =+Khanapur!M35 -> 38770.24 | K21: =I21+H21-J21 -> 0
A22: 20 | B22: Munavalli(PKG-3) | C22: Shahapur Petroleum | D22: ='Munavalli(KUWSDB)'!E39 -> 16582.17 | E22: ='Munavalli(KUWSDB)'!G39 -> 1513202.4 | F22: ='Munavalli(KUWSDB)'!H39 -> 186.32 | G22: ='Munavalli(KUWSDB)'!J39 -> 19224.498 | H22: =E22+G22 -> 1532426.9 | I22: ='Munavalli(KUWSDB)'!M3 -> 58857 | J22: ='Munavalli(KUWSDB)'!L39 -> 1484279.9 | K22: =I22+H22-J22 -> 107004.03
A23: 21 | B23: Borgaon(PKG-3) | C23: Aadisagar Petrolium | D23: =Borgaon!E35 -> 445.45 | E23: =Borgaon!G35 -> 40880.476 | F23: =Borgaon!H35 -> 46 | G23: =Borgaon!J35 -> 4771.58 | H23: =E23+G23 -> 45652.056 | I23: =Borgaon!M3 -> 234525.22 | J23: =Borgaon!L35 -> 257350.95 | K23: =I23+H23-J23 -> 22826.33
A24: 22 | B24: Ugar,Kudichi(PKG-3) | C24: Shiri Bhrhmanath Petrolium | D24: ='Ugar,Khagwad,Kudichi'!E35 -> 2836.99 | E24: ='Ugar,Khagwad,Kudichi'!G35 -> 260804.49 | F24: ='Ugar,Khagwad,Kudichi'!H35 -> 168 | G24: ='Ugar,Khagwad,Kudichi'!J35 -> 17453.52 | H24: =E24+G24 -> 278258.01 | I24: ='Ugar,Khagwad,Kudichi'!M3 -> 273179.62 | J24: ='Ugar,Khagwad,Kudichi'!L35 -> 310000 | K24: =I24+H24-J24 -> 241437.63
A25: 23 | B25: Kabbur(PKG-3) | C25: Shri Jai Hanuman Petrolium | D25: =Kabbur!E35 -> 609.02 | E25: =Kabbur!G35 -> 55780.142 | F25: =Kabbur!H35 -> 11.56 | G25: =Kabbur!J35 -> 1196.8068 | H25: =E25+G25 -> 56976.949 | I25: =Kabbur!K3 -> 0 | J25: =Kabbur!L35 -> 56976.949 | K25: =I25+H25-J25 -> 0
A26: 24 | B26: Kumta (PKG-1) | C26: Krishma fuel station | D26: =kumta!E35 -> 1080.33 | E26: =kumta!G35 -> 99303.934 | F26: =kumta!H35 -> 76.24 | G26: =kumta!J35 -> 7925.6554 | H26: =E26+G26 -> 107229.59 | I26: =kumta!M3 -> 0 | J26: =kumta!L35 -> 107229.59 | K26: =I26+H26-J26 -> 0
A27: 25 | B27: Jalgaon | C27: Sri Sai Petrol Pump | D27: =Jalgaon!E39 -> 856.74 | E27: =Jalgaon!G39 -> 78520.441 | F27: =Jalgaon!H39 -> 13.52 | G27: =Jalgaon!J39 -> 1419.4272 | H27: =E27+G27 -> 79939.868 | I27: =Jalgaon!M3 -> 4528.49 | J27: =Jalgaon!L39 -> 70742.446 | K27: =I27+H27-J27 -> 13725.912
A28: 26 | B28: MKBD | C28: Shree Sai Samarth Petroleum | D28: =MKBD!E36 -> 34366.54 | E28: =MKBD!G36 -> 3132158.8 | F28: =MKBD!H36 -> 95 | G28: =MKBD!J36 -> 9937 | H28: =E28+G28 -> 3142095.8 | I28: =MKBD!M3 -> 1670481.7 | J28: =MKBD!L36 -> 4361948.8 | K28: =I28+H28-J28 -> 450628.67
A29: 27 | B29: Haveri | C29: Shivalingeshwar Petroleum | D29: =Haveri!E35 -> 1327.13 | E29: =Haveri!G35 -> 121392.58 | F29: =Haveri!H35 -> 74.68 | G29: =Haveri!J35 -> 7723.8023 | H29: =E29+G29 -> 129116.38 | I29: =Haveri!M3 -> 90058 | J29: =Haveri!L35 -> 182855.23 | K29: =I29+H29-J29 -> 36319.153
A30: 28 | B30: Guttal | C30: Taware filling station | D30: =Guttal!E35 -> 1295.79 | E30: =Guttal!G35 -> 118953.52 | F30: =Guttal!H35 -> 67 | G30: =Guttal!J35 -> 6951.92 | H30: =E30+G30 -> 125905.44 | I30: =Guttal!M3 -> 0 | J30: =Guttal!L35 -> 125905.44 | K30: =I30+H30-J30 -> 0.002
A31: 29 | B31: Rattihali | C31: Shree Siri Gowari petroliam | D31: =Rattihali!E35 -> 1382.42 | E31: =Rattihali!G35 -> 127237.94 | F31: =Rattihali!H35 -> 55 | G31: =Rattihali!J35 -> 5722.9 | H31: =E31+G31 -> 132960.84 | I31: =Rattihali!M3 -> 0 | J31: =Rattihali!L35 -> 132960.84 | K31: =I31+H31-J31 -> 0
A32: 30 | B32: Gajendragada | C32: Vanasri Petrol Pump | D32: =Gajendragada!E35 -> 280 | E32: =Gajendragada!G35 -> 25712.4 | F32: =Gajendragada!H35 -> 33 | G32: =Gajendragada!J35 -> 3425.4 | H32: =E32+G32 -> 29137.8 | I32: =Gajendragada!M3 -> 30323 | J32: =Gajendragada!L35 -> 0 | K32: =I32+H32-J32 -> 59460.8
A33: 31 | B33: Ghattaprabha(PKG-3) | C33: Vivek Petrol Pump | D33: =Ghattaprabha!E35 -> 0 | E33: =Ghattaprabha!G35 -> 0 | F33: =Ghattaprabha!H35 -> 0 | G33: =Ghattaprabha!J35 -> 0 | H33: =E33+G33 -> 0 | I33: =Ghattaprabha!M3 -> 1036347.3 | J33: =Ghattaprabha!L35 -> 1036347 | K33: =I33+H33-J33 -> 0.3179
A34: 32 | B34: Gokak(PKG-3) | C34: AJ Petrolinks | D34: ='Gokak Dharwad PKG 3'!E35 -> 16586.07 | E34: ='Gokak Dharwad PKG 3'!G35 -> 1517293.7 | F34: ='Gokak Dharwad PKG 3'!H35 -> 452 | G34: ='Gokak Dharwad PKG 3'!J35 -> 46904.28 | H34: =E34+G34 -> 1564198 | I34: ='Gokak Dharwad PKG 3'!M3 -> 473791 | J34: ='Gokak Dharwad PKG 3'!L35 -> 500000 | K34: =I34+H34-J34 -> 1537989
A35: 33 | B35: Ghattaprabha-2(PKG-3) | C35: Manikeri Petroleums | D35: =+' Gokak'!F35 -> 0 | E35: =+' Gokak'!H35 -> 0 | F35: =+' Gokak'!I35 -> 4.82 | G35: =+' Gokak'!K35 -> 499.9786 | H35: =E35+G35 -> 499.9786 | I35: =+' Gokak'!M4 -> 0 | J35: =+' Gokak'!M35 -> 499.9786 | K35: =I35+H35-J35 -> 0
A36: 34 | B36: Ankalgi(PKG-3) | C36: Nirwani Petroleums | D36: =Ankalgi!E35 -> 132.92 | E36: =Ankalgi!G35 -> 12114.329 | F36: =Ankalgi!H35 -> 18 | G36: =Ankalgi!J35 -> 1857.6 | H36: =E36+G36 -> 13971.929 | I36: =Ankalgi!M3 -> 0 | J36: =Ankalgi!L35 -> 13971.929 | K36: =I36+H36-J36 -> 0
A37: 35 | B37: ShankeshWAR | C37: SR Patil | D37: =' Shankeshwar'!F35 -> 317 | E37: =' Shankeshwar'!H35 -> 28942.1 | F37: =' Shankeshwar'!I35 -> 9.68 | G37: =' Shankeshwar'!K35 -> 999.1696 | H37: =E37+G37 -> 29941.27 | I37: =' Shankeshwar'!M3 -> 0 | J37: =' Shankeshwar'!L35 -> 29941.27 | K37: =I37+H37-J37 -> 0
A38: 36 | B38: Talikote(PKG-1) | C38: Raykar Oil Agencies | D38: =' Talikote'!E44 -> 1084.75 | E38: =' Talikote'!G44 -> 99250.544 | F38: =' Talikote'!H44 -> 90.52 | G38: =' Talikote'!J44 -> 9363.3888 | H38: =E38+G38 -> 108613.93 | I38: =' Talikote'!M3 -> 0 | J38: =' Talikote'!L44 -> 106125.19 | K38: =I38+H38-J38 -> 2488.7434
A39: 37 | B39: Chadchan(PKG-1) | C39: Khavekar Petrolium | D39: =Chadchan!E35 -> 795.91 | E39: =Chadchan!G35 -> 71814.959 | F39: =Chadchan!H35 -> 60.36 | G39: =Chadchan!J35 -> 6166.3776 | H39: =E39+G39 -> 77981.337 | I39: =Chadchan!M3 -> 192780 | J39: =Chadchan!L35 -> 192780 | K39: =I39+H39-J39 -> 77981.337
A40: 38 | B40: Sindagi | C40: G.P.PORWAL | D40: =Sindagi!E44 -> 607.7 | E40: =Sindagi!G44 -> 55440.471 | F40: =Sindagi!H44 -> 0 | G40: =Sindagi!J44 -> 0 | H40: =E40+G40 -> 55440.471 | I40: 0 | J40: =Sindagi!L44 -> 55440.471 | K40: =I40+H40-J40 -> 0
A41: 39 | B41: Muddebihal(PKG-1) | C41: Bhosle Service Station | D41: =Muddebihal!E46 -> 146.71 | E41: =Muddebihal!G46 -> 13416.629 | F41: =Muddebihal!H46 -> 38.64 | G41: =Muddebihal!J46 -> 3994.9896 | H41: =E41+G41 -> 17411.619 | I41: 0 | J41: =Muddebihal!L46 -> 17411.619 | K41: =I41+H41-J41 -> 0
A42: 40 | B42: Almela(PKG-1) | C42: Shiddeshwar Petroleums | D42: =Alemela!E43 -> 295.22 | E42: =Alemela!G43 -> 26962.443 | F42: =Alemela!H43 -> 50.62 | G42: =Alemela!J43 -> 5227.0212 | H42: =E42+G42 -> 32189.464 | I42: =Alemela!M3 -> 0 | J42: =Alemela!L43 -> 32189.464 | K42: =I42+H42-J42 -> 0
A43: 42 | B43: Nalatwad(PKG-1) | C43: Shri Pawad Basaweshwar Petroleums | D43: =Nalatwad!E43 -> 646.89 | E43: =Nalatwad!G43 -> 59268.062 | F43: =Nalatwad!H43 -> 30.91 | G43: =Nalatwad!J43 -> 3201.3487 | H43: =E43+G43 -> 62469.41 | I43: =Nalatwad!M3 -> 48315 | J43: =Nalatwad!L43 -> 90535.84 | K43: =I43+H43-J43 -> 20248.571
A44: 41 | B44: Srirangapatna | C44: Sri Chakra Fuel Station | D44: =Srirangapatna!E35 -> 259.47 | E44: =Srirangapatna!G35 -> 23500.198 | F44: =Srirangapatna!H35 -> 49.16 | G44: =Srirangapatna!J35 -> 5036.9336 | H44: =E44+G44 -> 28537.131 | I44: =Srirangapatna!M3 -> 0 | J44: =Srirangapatna!L35 -> 28537.131 | K44: =I44+H44-J44 -> 0
A45: Total | D45: =SUM(D2:D44) -> 365665.29 | E45: =SUM(E2:E44) -> 34536906 | F45: =SUM(F2:F44) -> 5114.87 | G45: =SUM(G2:G44) -> 537024.4 | H45: =SUM(H2:H44) -> 35073930 | I45: =SUM(I2:I44) -> 28184885 | J45: =SUM(J2:J44) -> 38389727 | K45: =SUM(K2:K44) -> 24869088

Sheet Khammam-1
A1: Sri Ramakotaiah Fuel Point
A2: S.No | B2: Date | C2: GRN No | D2: Ind No/Bill No | E2: Diesel (Lts) | F2: Price | G2: Amount | H2: Petrol (Lts) | I2: Price | J2: Amount | K2: Total amount | L2: Amount paid | M2: As 0n Date | N2: Remarks
A3: Opening Balance | K3: 5140597 | M3: =+K3 -> 5140597 | P3: 220299.06
A4: 1 | B4: 45778 | E4: 2600 | F4: 95.68 | G4: =E4*F4 -> 248768 | H4: 20 | I4: 107.46 | J4: =H4*I4 -> 2149.2 | K4: =G4+J4 -> 250917.2 | L4: 0 | M4: =M3+K4-L4 -> 5391514.2
A5: 2 | B5: 45779 | E5: 0 | F5: 0 | G5: =E5*F5 -> 0 | H5: 0 | I5: 0 | J5: =H5*I5 -> 0 | K5: =G5+J5 -> 0 | L5: 0 | M5: =M4+K5-L5 -> 5391514.2
A6: 3 | B6: 45780 | E6: 0 | F6: 0 | G6: =E6*F6 -> 0 | H6: 0 | I6: 0 | J6: =H6*I6 -> 0 | K6: =G6+J6 -> 0 | L6: 0 | M6: =M5+K6-L6 -> 5391514.2
A7: 4 | B7: 45781 | E7: 2800 | F7: 95.68 | G7: =E7*F7 -> 267904 | H7: 35 | I7: 107.46 | J7: =H7*I7 -> 3761.1 | K7: =G7+J7 -> 271665.1 | L7: 0 | M7: =M6+K7-L7 -> 5663179.3
A8: 5 | B8: 45782 | E8: 2000 | F8: 95.68 | G8: =E8*F8 -> 191360 | H8: 20 | I8: 107.46 | J8: =H8*I8 -> 2149.2 | K8: =G8+J8 -> 193509.2 | L8: 0 | M8: =M7+K8-L8 -> 5856688.5
A9: 6 | B9: 45783 | E9: 0 | F9: 0 | G9: =E9*F9 -> 0 | H9: 0 | I9: 0 | J9: =H9*I9 -> 0 | K9: =G9+J9 -> 0 | L9: 0 | M9: =M8+K9-L9 -> 5856688.5
A10: 7 | B10: 45784 | E10: 2013.7 | F10: 95.68 | G10: =E10*F10 -> 192670.82 | H10: 55 | I10: 107.46 | J10: =H10*I10 -> 5910.3 | K10: =G10+J10 -> 198581.12 | L10: 0 | M10: =M9+K10-L10 -> 6055269.6
A11: 8 | B11: 45785 | E11: 0 | F11: 0 | G11: =E11*F11 -> 0 | H11: 0 | I11: 0 | J11: =H11*I11 -> 0 | K11: =G11+J11 -> 0 | L11: 0 | M11: =M10+K11-L11 -> 6055269.6
A12: 9 | B12: 45786 | E12: 0 | F12: 0 | G12: =E12*F12 -> 0 | H12: 0 | I12: 0 | J12: =H12*I12 -> 0 | K12: =G12+J12 -> 0 | L12: 0 | M12: =M11+K12-L12 -> 6055269.6
A13: 10 | B13: 45787 | E13: 0 | F13: 0 | G13: =E13*F13 -> 0 | H13: 0 | I13: 0 | J13: =H13*I13 -> 0 | K13: =G13+J13 -> 0 | L13: 1500000 | M13: =M12+K13-L13 -> 4555269.6
A14: 11 | B14: 45788 | E14: 0 | F14: 0 | G14: =E14*F14 -> 0 | H14: 0 | I14: 0 | J14: =H14*I14 -> 0 | K14: =G14+J14 -> 0 | L14: 0 | M14: =M13+K14-L14 -> 4555269.6
A15: 12 | B15: 45789 | E15: 0 | F15: 0 | G15: =E15*F15 -> 0 | H15: 0 | I15: 0 | J15: =H15*I15 -> 0 | K15: =G15+J15 -> 0 | L15: 0 | M15: =M14+K15-L15 -> 4555269.6
... A18: 15 | B18: 45792 | E18: 0 | F18: 0 | G18: =E18*F18 -> 0 | H18: 0 | I18: 0 | J18: =H18*I18 -> 0 | K18: =G18+J18 -> 0 | L18: 1000000 | M18: =M17+K18-L18 -> 3801220.8
A19: 16 | B19: 45793 | E19: 0 | F19: 0 | G19: =E19*F19 -> 0 | H19: 0 | I19: 0 | J19: =H19*I19 -> 0 | K19: =G19+J19 -> 0 | L19: 0 | M19: =M18+K19-L19 -> 3801220.8 | O19: .
A20: 17 | B20: 45794 | E20: 0 | F20: 0 | G20: =E20*F20 -> 0 | H20: 0 | I20: 0 | J20: =H20*I20 -> 0 | K20: =G20+J20 -> 0 | L20: 0 | M20: =M19+K20-L20 -> 3801220.8
A21: 18 | B21: 45795 | E21: 0 | F21: 0 | G21: =E21*F21 -> 0 | H21: 0 | I21: 0 | J21: =H21*I21 -> 0 | K21: =G21+J21 -> 0 | L21: 0 | M21: =M20+K21-L21 -> 3801220.8
A22: 19 | B22: 45796 | E22: 0 | F22: 0 | G22: =E22*F22 -> 0 | H22: 0 | I22: 0 | J22: =H22*I22 -> 0 | K22: =G22+J22 -> 0 | L22: 0 | M22: =M21+K22-L22 -> 3801220.8
A23: 20 | B23: 45797 | E23: 0 | F23: 0 | G23: =E23*F23 -> 0 | H23: 0 | I23: 0 | J23: =H23*I23 -> 0 | K23: =G23+J23 -> 0 | L23: 0 | M23: =M22+K23-L23 -> 3801220.8
A24: 21 | B24: 45798 | E24: 0 | F24: 0 | G24: =E24*F24 -> 0 | H24: 0 | I24: 0 | J24: =H24*I24 -> 0 | K24: =G24+J24 -> 0 | L24: 0 | M24: =M23+K24-L24 -> 3801220.8
A25: 22 | B25: 45799 | E25: 0 | F25: 0 | G25: =E25*F25 -> 0 | H25: 0 | I25: 0 | J25: =H25*I25 -> 0 | K25: =G25+J25 -> 0 | L25: 0 | M25: =M24+K25-L25 -> 3801220.8
A26: 23 | B26: 45800 | E26: 0 | F26: 0 | G26: =E26*F26 -> 0 | H26: 0 | I26: 0 | J26: =H26*I26 -> 0 | K26: =G26+J26 -> 0 | L26: 0 | M26: =M25+K26-L26 -> 3801220.8
A27: 24 | B27: 45801 | E27: 0 | F27: 0 | G27: =E27*F27 -> 0 | H27: 0 | I27: 0 | J27: =H27*I27 -> 0 | K27: =G27+J27 -> 0 | L27: 0 | M27: =M26+K27-L27 -> 3801220.8
A28: 25 | B28: 45802 | E28: 0 | F28: 0 | G28: =E28*F28 -> 0 | H28: 0 | I28: 0 | J28: =H28*I28 -> 0 | K28: =G28+J28 -> 0 | L28: 0 | M28: =M27+K28-L28 -> 3801220.8
A29: 26 | B29: 45803 | E29: 0 | F29: 0 | G29: =E29*F29 -> 0 | H29: 0 | I29: 0 | J29: =H29*I29 -> 0 | K29: =G29+J29 -> 0 | L29: 0 | M29: =M28+K29-L29 -> 3801220.8
A30: 27 | B30: 45804 | E30: 0 | F30: 0 | G30: =E30*F30 -> 0 | H30: 0 | I30: 0 | J30: =H30*I30 -> 0 | K30: =G30+J30 -> 0 | L30: 0 | M30: =M29+K30-L30 -> 3801220.8
A31: 28 | B31: 45805 | E31: 0 | F31: 0 | G31: =E31*F31 -> 0 | H31: 0 | I31: 0 | J31: =H31*I31 -> 0 | K31: =G31+J31 -> 0 | L31: 1500000 | M31: =M30+K31-L31 -> 2301220.8
A32: 29 | B32: 45806 | E32: 0 | F32: 0 | G32: =E32*F32 -> 0 | H32: 0 | I32: 0 | J32: =H32*I32 -> 0 | K32: =G32+J32 -> 0 | L32: 0 | M32: =M31+K32-L32 -> 2301220.8
A33: 30 | B33: 45807 | E33: 0 | F33: 0 | G33: =E33*F33 -> 0 | H33: 0 | I33: 0 | J33: =H33*I33 -> 0 | K33: =G33+J33 -> 0 | L33: 0 | M33: =M32+K33-L33 -> 2301220.8 | R33: 2584221.7
A34: 31 | B34: 45808 | E34: 0 | F34: 0 | G34: =E34*F34 -> 0 | H34: 0 | I34: 0 | J34: =H34*I34 -> 0 | K34: =G34+J34 -> 0 | L34: 0 | M34: =M33+K34-L34 -> 2301220.8
E35: 0 | F35: 0 | G35: =E35*F35 -> 0 | H35: 0 | I35: 0 | J35: =H35*I35 -> 0 | K35: =G35+J35 -> 0
E36: =SUM(E4:E35) -> 11984.26 | G36: =SUM(G4:G35) -> 1146654 | H36: =SUM(H4:H35) -> 130 | J36: =SUM(J3:J35) -> 13969.8 | K36: =SUM(K4:K35) -> 1160623.8 | L36: =SUM(L4:L35) -> 4000000
E42: =E36+H36 -> 12114.26

Sheet Khammam-2
A1: Divya laxmi ganapathi
A2: S.No | B2: Date | C2: GRN No | D2: Ind No/Bill No | E2: Diesel (Lts) | F2: Price | G2: Amount | H2: Petrol (Lts) | I2: Price | J2: Amount | K2: Total amount | L2: Amount paid | M2: As 0n Date | N2: Remarks
A3: Opening Balance | K3: 3730421 | M3: =+K3 -> 3730421
A4: 1 | B4: 45778 | E4: 5000 | F4: 95.68 | G4: =E4*F4 -> 478400 | H4: 0 | I4: 0 | J4: =H4*I4 -> 0 | K4: =G4+J4 -> 478400 | M4: =M3+K4-L4 -> 4208821
A5: 2 | B5: 45779 | E5: 6529.67 | F5: 95.68 | G5: =E5*F5 -> 624758.83 | H5: 35 | I5: 107.46 | J5: =H5*I5 -> 3761.1 | K5: =G5+J5 -> 628519.93 | M5: =M4+K5-L5 -> 4837340.9
A6: 3 | B6: 45780 | E6: 7183.16 | F6: 95.68 | G6: =E6*F6 -> 687284.75 | H6: 40 | I6: 107.46 | J6: =H6*I6 -> 4298.4 | K6: =G6+J6 -> 691583.15 | M6: =M5+K6-L6 -> 5528924.1
A7: 4 | B7: 45781 | E7: 2500.41 | F7: 95.68 | G7: =E7*F7 -> 239239.23 | H7: 0 | I7: 0 | J7: =H7*I7 -> 0 | K7: =G7+J7 -> 239239.23 | M7: =M6+K7-L7 -> 5768163.3
A8: 5 | B8: 45782 | E8: 5348.86 | F8: 95.68 | G8: =E8*F8 -> 511778.92 | H8: 35 | I8: 107.46 | J8: =H8*I8 -> 3761.1 | K8: =G8+J8 -> 515540.02 | M8: =M7+K8-L8 -> 6283703.3
A9: 6 | B9: 45783 | E9: 5000 | F9: 95.68 | G9: =E9*F9 -> 478400 | H9: 0 | I9: 0 | J9: 0 | K9: =G9+J9 -> 478400 | M9: =M8+K9-L9 -> 6762103.3
A10: 7 | B10: 45784 | E10: 9365.22 | F10: 95.68 | G10: =E10*F10 -> 896064.25 | H10: 0 | I10: 0 | J10: =H10*I10 -> 0 | K10: =G10+J10 -> 896064.25 | M10: =M9+K10-L10 -> 7658167.6
A11: 8 | B11: 45785 | E11: 6000 | F11: 95.68 | G11: =E11*F11 -> 574080 | H11: 20 | I11: 107.46 | J11: =H11*I11 -> 2149.2 | K11: =G11+J11 -> 576229.2 | M11: =M10+K11-L11 -> 8234396.8
A12: 9 | B12: 45786 | D12: 14016.8 | E12: 14016.8 | F12: 95.68 | G12: =E12*F12 -> 1341127.4 | H12: 55 | I12: 107.46 | J12: =H12*I12 -> 5910.3 | K12: =G12+J12 -> 1347037.7 | M12: =M11+K12-L12 -> 9581434.5
A13: 10 | B13: 45787 | E13: 2500 | F13: 95.68 | G13: =E13*F13 -> 239200 | H13: 0 | I13: 0 | J13: =H13*I13 -> 0 | K13: =G13+J13 -> 239200 | L13: 1500000 | M13: =M12+K13-L13 -> 8320634.5
A14: 11 | B14: 45787 | E14: 2500 | F14: 95.67 | G14: =E14*F14 -> 239175 | K14: =G14+J14 -> 239175 | M14: =M13+K14-L14 -> 8559809.5
A15: 12 | B15: 45788 | E15: 2500 | F15: 95.68 | G15: =E15*F15 -> 239200 | H15: 35 | I15: 107.46 | J15: =H15*I15 -> 3761.1 | K15: =G15+J15 -> 242961.1 | M15: =M14+K15-L15 -> 8802770.6
A16: 13 | B16: 45789 | E16: 6200 | F16: 95.68 | G16: =E16*F16 -> 593216 | H16: 20 | I16: 107.46 | J16: =H16*I16 -> 2149.2 | K16: =G16+J16 -> 595365.2 | M16: =M15+K16-L16 -> 9398135.8
A17: 14 | B17: 45790 | E17: 7500 | F17: 95.68 | G17: =E17*F17 -> 717600 | H17: 55 | I17: 107.46 | J17: =H17*I17 -> 5910.3 | K17: =G17+J17 -> 723510.3 | M17: =M16+K17-L17 -> 10121646
A18: 15 | B18: 45791 | E18: 4300 | F18: 95.68 | G18: =E18*F18 -> 411424 | H18: 20 | I18: 107.46 | J18: =H18*I18 -> 2149.2 | K18: =G18+J18 -> 413573.2 | M18: =M17+K18-L18 -> 10535219
A19: 16 | B19: 45792 | E19: 7210.93 | F19: 95.68 | G19: =E19*F19 -> 689941.78 | H19: 55 | I19: 107.46 | J19: =H19*I19 -> 5910.3 | K19: =G19+J19 -> 695852.08 | L19: 0 | M19: =M18+K19-L19 -> 11231071
A20: 17 | B20: 45793 | E20: 0 | F20: 0 | G20: =E20*F20 -> 0 | H20: 35 | I20: 107.46 | J20: =H20*I20 -> 3761.1 | K20: =G20+J20 -> 3761.1 | M20: =M19+K20-L20 -> 11234832
A21: 18 | B21: 45794 | E21: 9445.01 | F21: 95.68 | G21: =E21*F21 -> 903698.56 | H21: 20 | I21: 107.46 | J21: =H21*I21 -> 2149.2 | K21: =G21+J21 -> 905847.76 | M21: =M20+K21-L21 -> 12140680
A22: 19 | B22: 45795 | E22: 5000 | F22: 95.68 | G22: =E22*F22 -> 478400 | H22: 35 | I22: 107.46 | J22: =H22*I22 -> 3761.1 | K22: =G22+J22 -> 482161.1 | M22: =M21+K22-L22 -> 12622841
A23: 20 | B23: 45796 | E23: 1400 | F23: 95.68 | G23: =E23*F23 -> 133952 | H23: 0 | I23: 0 | J23: =H23*I23 -> 0 | K23: =G23+J23 -> 133952 | M23: =M22+K23-L23 -> 12756793
A24: 21 | B24: 45797 | E24: 5000 | F24: 95.68 | G24: =E24*F24 -> 478400 | H24: 55 | I24: 107.46 | J24: =H24*I24 -> 5910.3 | K24: =G24+J24 -> 484310.3 | M24: =M23+K24-L24 -> 13241104
A25: 22 | B25: 45798 | E25: 6529 | F25: 95.68 | G25: =E25*F25 -> 624694.72 | H25: 20 | I25: 107.46 | J25: =H25*I25 -> 2149.2 | K25: =G25+J25 -> 626843.92 | M25: =M24+K25-L25 -> 13867948
A26: 23 | B26: 45799 | E26: 6727 | F26: 95.68 | G26: =E26*F26 -> 643639.36 | H26: 0 | I26: 0 | J26: =H26*I26 -> 0 | K26: =G26+J26 -> 643639.36 | M26: =M25+K26-L26 -> 14511587
A27: 24 | B27: 45800 | E27: 1506 | F27: 95.68 | G27: =E27*F27 -> 144094.08 | H27: 55 | I27: 107.46 | J27: =H27*I27 -> 5910.3 | K27: =G27+J27 -> 150004.38 | M27: =M26+K27-L27 -> 14661591
A28: 25 | B28: 45801 | E28: 4100 | F28: 95.68 | G28: =E28*F28 -> 392288 | H28: 35 | I28: 107.46 | J28: =H28*I28 -> 3761.1 | K28: =G28+J28 -> 396049.1 | M28: =M27+K28-L28 -> 15057640
A29: 26 | B29: 45802 | E29: 2500 | F29: 95.68 | G29: =E29*F29 -> 239200 | H29: 0 | I29: 0 | J29: =H29*I29 -> 0 | K29: =G29+J29 -> 239200 | M29: =M28+K29-L29 -> 15296840
A30: 27 | B30: 45803 | E30: 6600.19 | F30: 95.68 | G30: =E30*F30 -> 631506.18 | H30: 55 | I30: 107.46 | J30: =H30*I30 -> 5910.3 | K30: =G30+J30 -> 637416.48 | L30: 7000000 | M30: =M29+K30-L30 -> 8934256.9
A31: 28 | B31: 45804 | E31: 2500 | F31: 95.68 | G31: =E31*F31 -> 239200 | H31: 0 | I31: 0 | J31: =H31*I31 -> 0 | K31: =G31+J31 -> 239200 | M31: =M30+K31-L31 -> 9173456.9
A32: 29 | B32: 45805 | E32: 0 | F32: 0 | G32: =E32*F32 -> 0 | H32: 0 | I32: 0 | J32: =H32*I32 -> 0 | K32: =G32+J32 -> 0 | M32: =M31+K32-L32 -> 9173456.9
A33: 30 | B33: 45806 | E33: 1400.27 | F33: 95.68 | G33: =E33*F33 -> 133977.83 | H33: 0 | I33: 0 | J33: =H33*I33 -> 0 | K33: =G33+J33 -> 133977.83 | M33: =M32+K33-L33 -> 9307434.7
A34: 31 | B34: 45807 | E34: 0 | F34: 0 | G34: =E34*F34 -> 0 | H34: 0 | I34: 0 | J34: =H34*I34 -> 0 | K34: =G34+J34 -> 0 | M34: =M33+K34-L34 -> 9307434.7
A35: 32 | B35: 45808 | E35: 0 | F35: 0 | G35: =E35*F35 -> 0 | H35: 0 | I35: 0 | J35: =H35*I35 -> 0 | K35: =G35+J35 -> 0
A36: 33
E37: =SUM(E3:E36) -> 146362.52 | G37: =SUM(G3:G36) -> 14003941 | H37: =SUM(H3:H36) -> 680 | J37: =SUM(J3:J36) -> 73072.8 | K37: =SUM(K4:K36) -> 14077014 | L37: =SUM(L3:L36) -> 8500000

Sheet Khammam-3
A1: Jayasai union bunk
A2: S.No | B2: Date | C2: GRN No | D2: Ind No/Bill No | E2: Diesel (Lts) | F2: Price | G2: Amount | H2: Petrol (Lts) | I2: Price | J2: Amount | K2: Total amount | L2: Amount paid | M2: As 0n Date | N2: Remarks
A3: Opening Balance | K3: 8891075.4 | M3: =+K3 -> 8891075.4
A4: 1 | B4: 45778 | E4: 4844.88 | F4: 95.7 | G4: =E4*F4 -> 463655.02 | H4: 0 | I4: 0 | J4: 0 | K4: =G4+J4 -> 463655.02 | M4: =M3+K4-L4 -> 9354730.5
A5: 2 | B5: 45779 | E5: 2871.69 | F5: 95.7 | G5: =E5*F5 -> 274820.73 | H5: 0 | I5: 0 | J5: 0 | K5: =G5+J5 -> 274820.73 | M5: =M4+K5-L5 -> 9629551.2
A6: 3 | B6: 45780 | E6: 7544.95 | F6: 95.7 | G6: =E6*F6 -> 722051.71 | H6: 0 | I6: 0 | J6: 0 | K6: =G6+J6 -> 722051.71 | M6: =M5+K6-L6 -> 10351603
A7: 4 | B7: 45781 | E7: 5393.57 | F7: 95.7 | G7: =E7*F7 -> 516164.65 | H7: 0 | I7: 0 | J7: 0 | K7: =G7+J7 -> 516164.65 | M7: =M6+K7-L7 -> 10867768
A8: 5 | B8: 45782 | E8: 0 | F8: 0 | G8: =E8*F8 -> 0 | H8: 0 | I8: 0 | J8: 0 | K8: =G8+J8 -> 0 | M8: =M7+K8-L8 -> 10867768
A9: 6 | B9: 45783 | E9: 2500 | F9: 95.7 | G9: =E9*F9 -> 239250 | H9: 35 | I9: 107.48 | J9: =H9*I9 -> 3761.8 | K9: =G9+J9 -> 243011.8 | M9: =M8+K9-L9 -> 11110779
A10: 7 | B10: 45784 | E10: 0 | F10: 0 | G10: =E10*F10 -> 0 | H10: 0 | I10: 0 | J10: =H10*I10 -> 0 | K10: =G10+J10 -> 0 | M10: =M9+K10-L10 -> 11110779
A11: 8 | B11: 45785 | E11: 2500 | F11: 95.7 | G11: =E11*F11 -> 239250 | H11: 0 | I11: 0 | J11: =H11*I11 -> 0 | K11: =G11+J11 -> 239250 | M11: =M10+K11-L11 -> 11350029
A12: 9 | B12: 45786 | E12: 0 | F12: 0 | G12: =E12*F12 -> 0 | H12: 0 | I12: 0 | J12: =H12*I12 -> 0 | K12: =G12+J12 -> 0 | M12: =M11+K12-L12 -> 11350029
A13: 10 | B13: 45787 | E13: 0 | F13: 0 | G13: =E13*F13 -> 0 | H13: 0 | I13: 0 | J13: =H13*I13 -> 0 | K13: =G13+J13 -> 0 | M13: =M12+K13-L13 -> 11350029
A14: 11 | B14: 45788 | E14: 0 | F14: 0 | G14: =E14*F14 -> 0 | H14: 0 | I14: 0 | J14: =H14*I14 -> 0 | K14: =G14+J14 -> 0 | M14: =M13+K14-L14 -> 11350029
A15: 12 | B15: 45789 | E15: 0 | F15: 0 | G15: =E15*F15 -> 0 | H15: 0 | I15: 0 | J15: =H15*I15 -> 0 | K15: =G15+J15 -> 0 | M15: =M14+K15-L15 -> 11350029
A16: 13 | B16: 45790 | E16: 0 | F16: 0 | G16: =E16*F16 -> 0 | H16: 0 | I16: 0 | J16: =H16*I16 -> 0 | K16: =G16+J16 -> 0 | M16: =M15+K16-L16 -> 11350029
A17: 14 | B17: 45791 | E17: 0 | F17: 0 | G17: =E17*F17 -> 0 | H17: 0 | I17: 0 | J17: =H17*I17 -> 0 | K17: =G17+J17 -> 0 | M17: =M16+K17-L17 -> 11350029
A18: 15 | B18: 45792 | E18: 0 | F18: 0 | G18: =E18*F18 -> 0 | H18: 0 | I18: 0 | J18: =H18*I18 -> 0 | K18: =G18+J18 -> 0 | M18: =M17+K18-L18 -> 11350029
A19: 16 | B19: 45793 | E19: 0 | F19: 0 | G19: =E19*F19 -> 0 | H19: 0 | I19: 0 | J19: =H19*I19 -> 0 | K19: =G19+J19 -> 0 | L19: 2000000 | M19: =M18+K19-L19 -> 9350029.4
A20: 17 | B20: 45794 | E20: 0 | F20: 0 | G20: =E20*F20 -> 0 | H20: 0 | I20: 0 | J20: =H20*I20 -> 0 | K20: =G20+J20 -> 0 | M20: =M19+K20-L20 -> 9350029.4
A21: 18 | B21: 45795 | E21: 0 | F21: 0 | G21: =E21*F21 -> 0 | H21: 0 | I21: 0 | J21: =H21*I21 -> 0 | K21: =G21+J21 -> 0 | M21: =M20+K21-L21 -> 9350029.4
A22: 19 | B22: 45796 | E22: 2500 | F22: 95.7 | G22: =E22*F22 -> 239250 | H22: 0 | I22: 0 | J22: =H22*I22 -> 0 | K22: =G22+J22 -> 239250 | M22: =M21+K22-L22 -> 9589279.4
A23: 20 | B23: 45797 | E23: 2500 | F23: 95.7 | G23: =E23*F23 -> 239250 | H23: 35 | I23: 107.48 | J23: =H23*I23 -> 3761.8 | K23: =G23+J23 -> 243011.8 | M23: =M22+K23-L23 -> 9832291.2 | O23: x
A24: 21 | B24: 45798 | E24: 2500 | F24: 95.7 | G24: =E24*F24 -> 239250 | H24: 0 | I24: 0 | J24: =H24*I24 -> 0 | K24: =G24+J24 -> 239250 | M24: =M23+K24-L24 -> 10071541
A25: 22 | B25: 45799 | E25: 0 | F25: 0 | G25: =E25*F25 -> 0 | H25: 0 | I25: 0 | J25: =H25*I25 -> 0 | K25: =G25+J25 -> 0 | M25: =M24+K25-L25 -> 10071541
A26: 23 | B26: 45800 | E26: 4750 | F26: 95.7 | G26: =E26*F26 -> 454575 | H26: 0 | I26: 0 | J26: =H26*I26 -> 0 | K26: =G26+J26 -> 454575 | M26: =M25+K26-L26 -> 10526116
A27: 24 | B27: 45801 | E27: 0 | F27: 0 | G27: =E27*F27 -> 0 | H27: 0 | I27: 0 | J27: =H27*I27 -> 0 | K27: =G27+J27 -> 0 | M27: =M26+K27-L27 -> 10526116
A28: 25 | B28: 45802 | E28: 0 | F28: 0 | G28: =E28*F28 -> 0 | H28: 0 | I28: 0 | J28: =H28*I28 -> 0 | K28: =G28+J28 -> 0 | M28: =M27+K28-L28 -> 10526116
A29: 26 | B29: 45803 | E29: 0 | F29: 0 | G29: =E29*F29 -> 0 | H29: 0 | I29: 0 | J29: =H29*I29 -> 0 | K29: =G29+J29 -> 0 | L29: 5000000 | M29: =M28+K29-L29 -> 5526116.2
A30: 27 | B30: 45804 | E30: 2500 | F30: 95.7 | G30: =E30*F30 -> 239250 | H30: 35 | I30: 107.48 | J30: =H30*I30 -> 3761.8 | K30: =G30+J30 -> 243011.8 | M30: =M29+K30-L30 -> 5769128
A31: 28 | B31: 45805 | E31: 2500 | F31: 95.7 | G31: =E31*F31 -> 239250 | H31: 35 | I31: 107.48 | J31: =H31*I31 -> 3761.8 | K31: =G31+J31 -> 243011.8 | M31: =M30+K31-L31 -> 6012139.8
A32: 29 | B32: 45806 | E32: 4999.9 | F32: 95.7 | G32: =E32*F32 -> 478490.43 | H32: 20 | I32: 107.48 | J32: =H32*I32 -> 2149.6 | K32: =G32+J32 -> 480640.03 | M32: =M31+K32-L32 -> 6492779.8
A33: 30 | B33: 45807 | E33: 5000 | F33: 95.7 | G33: =E33*F33 -> 478500 | H33: 35 | I33: 107.48 | J33: =H33*I33 -> 3761.8 | K33: =G33+J33 -> 482261.8 | M33: =M32+K33-L33 -> 6975041.6
A34: 31 | B34: 45808 | E34: 5000 | F34: 95.7 | G34: =E34*F34 -> 478500 | H34: 35 | I34: 107.48 | J34: =H34*I34 -> 3761.8 | K34: =G34+J34 -> 482261.8 | M34: =M33+K34-L34 -> 7457303.4
E35: =SUM(E4:E34) -> 57904.99 | G35: =SUM(G4:G34) -> 5541507.5 | H35: =SUM(H4:H34) -> 230 | J35: =SUM(J4:J34) -> 24720.4 | K35: =SUM(K4:K34) -> 5566227.9 | L35: =SUM(L4:L34) -> 7000000

Sheet Jedcherla -1
A1: Sai Baba Fuel Station
A2: S.No | B2: Date | C2: GRN No | D2: Ind No/Bill No | E2: Diesel (Lts) | F2: Price | G2: Amount | H2: Petrol (Lts) | I2: Price | J2: Amount | K2: Total amount | L2: Amount paid | M2: As on date | N2: Remarks
A3: Opening Balance | K3: 1966837 | M3: =+K3 -> 1966837
A4: 1 | B4: 45778 | E4: 1500 | F4: 96.42 | G4: =E4*F4 -> 144630 | H4: 0 | I4: 0 | J4: =H4*I4 -> 0 | K4: =G4+J4 -> 144630 | L4: 0 | M4: =M3+K4-L4 -> 2111467 | P4: 2259050
A5: 2 | B5: 45779 | E5: 1500 | F5: 96.42 | G5: =E5*F5 -> 144630 | H5: 20 | I5: 108.23 | J5: =H5*I5 -> 2164.6 | K5: =G5+J5 -> 146794.6 | L5: 0 | M5: =M4+K5-L5 -> 2258261.6
A6: 3 | B6: 45780 | E6: 1700 | F6: 96.42 | G6: =E6*F6 -> 163914 | H6: 20 | I6: 108.23 | J6: =H6*I6 -> 2164.6 | K6: =G6+J6 -> 166078.6 | L6: 0 | M6: =M5+K6-L6 -> 2424340.2
A7: 4 | B7: 45781 | E7: 0 | F7: 0 | G7: =E7*F7 -> 0 | H7: 20 | I7: 108.23 | J7: =H7*I7 -> 2164.6 | K7: =G7+J7 -> 2164.6 | L7: 0 | M7: =M6+K7-L7 -> 2426504.8
A8: 5 | B8: 45782 | E8: 1500 | F8: 96.42 | G8: =E8*F8 -> 144630 | H8: 20 | I8: 108.23 | J8: =H8*I8 -> 2164.6 | K8: =G8+J8 -> 146794.6 | L8: 0 | M8: =M7+K8-L8 -> 2573299.4
A9: 6 | B9: 45783 | E9: 0 | F9: 0 | G9: =E9*F9 -> 0 | H9: 15 | I9: 108.23 | J9: =H9*I9 -> 1623.45 | K9: =G9+J9 -> 1623.45 | L9: 0 | M9: =M8+K9-L9 -> 2574922.9
A10: 7 | B10: 45784 | E10: 93.69 | F10: 96.42 | G10: =E10*F10 -> 9033.5898 | H10: 10 | I10: 108.23 | J10: =H10*I10 -> 1082.3 | K10: =G10+J10 -> 10115.89 | L10: 0 | M10: =M9+K10-L10 -> 2585038.8
A11: 8 | B11: 45785 | E11: 33 | F11: 96.42 | G11: =E11*F11 -> 3181.86 | H11: 23 | I11: 108.23 | J11: =H11*I11 -> 2489.29 | K11: =G11+J11 -> 5671.15 | L11: 0 | M11: =M10+K11-L11 -> 2590709.9
A12: 9 | B12: 45786 | E12: 81.38 | F12: 96.42 | G12: =E12*F12 -> 7846.6596 | H12: 10 | I12: 108.23 | J12: =H12*I12 -> 1082.3 | K12: =G12+J12 -> 8928.9596 | L12: 0 | M12: =M11+K12-L12 -> 2599638.9
A13: 10 | B13: 45787 | E13: 33.06 | F13: 96.42 | G13: =E13*F13 -> 3187.6452 | H13: 15 | I13: 108.23 | J13: =H13*I13 -> 1623.45 | K13: =G13+J13 -> 4811.0952 | L13: 0 | M13: =M12+K13-L13 -> 2604450
A14: 11 | B14: 45788 | E14: 0 | F14: 0 | G14: =E14*F14 -> 0 | H14: 0 | I14: 0 | J14: =H14*I14 -> 0 | K14: =G14+J14 -> 0 | L14: 0 | M14: =M13+K14-L14 -> 2604450
A15: 12 | B15: 45789 | E15: 0 | F15: 0 | G15: =E15*F15 -> 0 | H15: 20 | I15: 108.23 | J15: =H15*I15 -> 2164.6 | K15: =G15+J15 -> 2164.6 | L15: 0 | M15: =M14+K15-L15 -> 2606614.6
A16: 13 | B16: 45790 | E16: 0 | F16: 0 | G16: =E16*F16 -> 0 | H16: 15 | I16: 108.23 | J16: =H16*I16 -> 1623.45 | K16: =G16+J16 -> 1623.45 | L16: 0 | M16: =M15+K16-L16 -> 2608238
... A21: 18 | B21: 45795 | E21: 0 | F21: 0 | G21: =E21*F21 -> 0 | H21: 5 | I21: 108.23 | J21: =H21*I21 -> 541.15 | K21: =G21+J21 -> 541.15 | L21: 0 | M21: =M20+K21-L21 -> 2624274.2
A22: 19 | B22: 45796 | E22: 0 | F22: 0 | G22: =E22*F22 -> 0 | H22: 5 | I22: 108.23 | J22: =H22*I22 -> 541.15 | K22: =G22+J22 -> 541.15 | L22: 0 | M22: =M21+K22-L22 -> 2624815.4 | P22: 2422641
A23: 20 | B23: 45797 | E23: 0 | F23: 0 | G23: =E23*F23 -> 0 | H23: 17.75 | I23: 108.23 | J23: =H23*I23 -> 1921.0825 | K23: =G23+J23 -> 1921.0825 | L23: 0 | M23: =M22+K23-L23 -> 2626736.5 | P23: 2419549
A24: 21 | B24: 45798 | E24: 27.58 | F24: 96.42 | G24: =E24*F24 -> 2659.2636 | H24: 20 | I24: 108.23 | J24: =H24*I24 -> 2164.6 | K24: =G24+J24 -> 4823.8636 | L24: 0 | M24: =M23+K24-L24 -> 2631560.3 | P24: =P23-P22 -> -3092
A25: 22 | B25: 45799 | E25: 0 | F25: 0 | G25: =E25*F25 -> 0 | H25: 10 | I25: 108.23 | J25: =H25*I25 -> 1082.3 | K25: =G25+J25 -> 1082.3 | L25: 0 | M25: =M24+K25-L25 -> 2632642.6
A26: 23 | B26: 45800 | E26: 0 | F26: 0 | G26: =E26*F26 -> 0 | H26: 27.84 | I26: 108.23 | J26: =H26*I26 -> 3013.1232 | K26: =G26+J26 -> 3013.1232 | L26: 0 | M26: =M25+K26-L26 -> 2635655.8
A27: 24 | B27: 45801 | E27: 0 | F27: 0 | G27: =E27*F27 -> 0 | H27: 25 | I27: 108.23 | J27: =H27*I27 -> 2705.75 | K27: =G27+J27 -> 2705.75 | L27: 0 | M27: =M26+K27-L27 -> 2638361.5
A28: 25 | B28: 45802 | E28: 0 | F28: 0 | G28: =E28*F28 -> 0 | H28: 10 | I28: 108.23 | J28: =H28*I28 -> 1082.3 | K28: =G28+J28 -> 1082.3 | L28: 0 | M28: =M27+K28-L28 -> 2639443.8
A29: 26 | B29: 45803 | E29: 17.22 | F29: 96.42 | G29: =E29*F29 -> 1660.3524 | H29: 5 | I29: 108.23 | J29: =H29*I29 -> 541.15 | K29: =G29+J29 -> 2201.5024 | L29: 0 | M29: =M28+K29-L29 -> 2641645.3
A30: 27 | B30: 45804 | E30: 0 | F30: 0 | G30: =E30*F30 -> 0 | H30: 7 | I30: 108.23 | J30: =H30*I30 -> 757.61 | K30: =G30+J30 -> 757.61 | L30: 0 | M30: =M29+K30-L30 -> 2642402.9
A31: 28 | B31: 45805 | E31: 0 | F31: 0 | G31: =E31*F31 -> 0 | H31: 24 | I31: 108.23 | J31: =H31*I31 -> 2597.52 | K31: =G31+J31 -> 2597.52 | L31: 1500000 | M31: =M30+K31-L31 -> 1145000.4
A32: 29 | B32: 45806 | E32: 0 | F32: 0 | G32: =E32*F32 -> 0 | H32: 20 | I32: 108.23 | J32: =H32*I32 -> 2164.6 | K32: =G32+J32 -> 2164.6 | L32: 0 | M32: =M31+K32-L32 -> 1147165
A33: 30 | B33: 45807 | E33: 0 | F33: 0 | G33: =E33*F33 -> 0 | H33: 20 | I33: 108.23 | J33: =H33*I33 -> 2164.6 | K33: =G33+J33 -> 2164.6 | L33: 0 | M33: =M32+K33-L33 -> 1149329.6
A34: 31 | B34: 45808 | E34: 0 | F34: 0 | G34: =E34*F34 -> 0 | H34: 5 | I34: 108.23 | J34: =H34*I34 -> 541.15 | K34: =G34+J34 -> 541.15 | L34: 0 | M34: =M33+K34-L34 -> 1149870.8
E35: =SUM(E4:E34) -> 6568.06 | G35: =SUM(G4:G34) -> 633292.35 | H35: =SUM(H4:H34) -> 459.59 | J35: =SUM(J4:J34) -> 49741.426 | K35: =SUM(K4:K34) -> 683033.77 | L35: =SUM(L4:L34) -> 1500000
H37: 3

Sheet Jedcherla-2
A1: Uttara Enterprises
A2: S.No | B2: Date | C2: GRN No | D2: Ind No/Bill No | E2: Diesel (Lts) | F2: Price | G2: Amount | H2: Petrol (Lts) | I2: Price | J2: Amount | K2: Total amount | L2: Amount paid | M2: As on Date | N2: Remarks
A3: Opening Balance | K3: 1831699.5 | M3: =+K3 -> 1831699.5
A4: 1 | B4: 45778 | G4: =E4*F4 -> 0 | J4: =H4*I4 -> 0 | K4: =G4+J4 -> 0 | M4: =M3+K4-L4 -> 1831699.5
A5: 2 | B5: 45779 | E5: 0 | F5: 0 | G5: =E5*F5 -> 0 | J5: =H5*I5 -> 0 | K5: =G5+J5 -> 0 | M5: =M4+K5-L5 -> 1831699.5
A6: 3 | B6: 45780 | E6: 0 | F6: 0 | G6: =E6*F6 -> 0 | J6: =H6*I6 -> 0 | K6: =G6+J6 -> 0 | M6: =M5+K6-L6 -> 1831699.5 | R6: 541.08
A7: 4 | B7: 45781 | E7: 0 | F7: 0 | G7: =E7*F7 -> 0 | J7: =H7*I7 -> 0 | K7: =G7+J7 -> 0 | M7: =M6+K7-L7 -> 1831699.5
A8: 5 | B8: 45782 | E8: 0 | F8: 0 | G8: =E8*F8 -> 0 | J8: =H8*I8 -> 0 | K8: =G8+J8 -> 0 | M8: =M7+K8-L8 -> 1831699.5
A9: 6 | B9: 45783 | E9: 0 | F9: 0 | G9: =E9*F9 -> 0 | J9: =H9*I9 -> 0 | K9: =G9+J9 -> 0 | M9: =M8+K9-L9 -> 1831699.5
A10: 7 | B10: 45784 | E10: 0 | F10: 0 | G10: =E10*F10 -> 0 | J10: =H10*I10 -> 0 | K10: =G10+J10 -> 0 | M10: =M9+K10-L10 -> 1831699.5
A11: 8 | B11: 45785 | E11: 0 | F11: 0 | G11: =E11*F11 -> 0 | J11: =H11*I11 -> 0 | K11: =G11+J11 -> 0 | M11: =M10+K11-L11 -> 1831699.5
A12: 9 | B12: 45786 | E12: 0 | F12: 0 | G12: =E12*F12 -> 0 | J12: =H12*I12 -> 0 | K12: =G12+J12 -> 0 | M12: =M11+K12-L12 -> 1831699.5
A13: 10 | B13: 45787 | E13: 0 | F13: 0 | G13: =E13*F13 -> 0 | J13: =H13*I13 -> 0 | K13: =G13+J13 -> 0 | M13: =M12+K13-L13 -> 1831699.5
A14: 11 | B14: 45788 | E14: 0 | F14: 0 | G14: =E14*F14 -> 0 | J14: =H14*I14 -> 0 | K14: =G14+J14 -> 0 | M14: =M13+K14-L14 -> 1831699.5
A15: 12 | B15: 45789 | E15: 0 | F15: 0 | G15: =E15*F15 -> 0 | J15: =H15*I15 -> 0 | K15: =G15+J15 -> 0 | M15: =M14+K15-L15 -> 1831699.5
A16: 13 | B16: 45790 | E16: 0 | F16: 0 | G16: =E16*F16 -> 0 | J16: =H16*I16 -> 0 | K16: =G16+J16 -> 0 | M16: =M15+K16-L16 -> 1831699.5
A17: 14 | B17: 45791 | E17: 0 | F17: 0 | G17: =E17*F17 -> 0 | J17: =H17*I17 -> 0 | K17: =G17+J17 -> 0 | M17: =M16+K17-L17 -> 1831699.5
A18: 15 | B18: 45792 | E18: 0 | F18: 0 | G18: =E18*F18 -> 0 | J18: =H18*I18 -> 0 | K18: =G18+J18 -> 0 | M18: =M17+K18-L18 -> 1831699.5
... A29: 26 | B29: 45803 | E29: 0 | F29: 0 | G29: =E29*F29 -> 0 | J29: =H29*I29 -> 0 | K29: =G29+J29 -> 0 | M29: =M28+K29-L29 -> 1831699.5
A30: 27 | B30: 45804 | E30: 0 | F30: 0 | G30: =E30*F30 -> 0 | J30: =H30*I30 -> 0 | K30: =G30+J30 -> 0 | M30: =M29+K30-L30 -> 1831699.5 | P30: =2939612.08-2939070.93 -> 541.15
A31: 28 | B31: 45805 | E31: 0 | F31: 0 | G31: =E31*F31 -> 0 | J31: =H31*I31 -> 0 | K31: =G31+J31 -> 0 | L31: 1500000 | M31: =M30+K31-L31 -> 331699.53
A32: 29 | B32: 45806 | E32: 0 | F32: 0 | G32: =E32*F32 -> 0 | J32: =H32*I32 -> 0 | K32: =G32+J32 -> 0
A33: 30 | B33: 45807 | E33: 0 | F33: 0 | G33: =E33*F33 -> 0 | J33: =H33*I33 -> 0 | K33: =G33+J33 -> 0
A34: 31 | B34: 45808 | E34: 0 | F34: 0 | G34: =E34*F34 -> 0 | J34: =H34*I34 -> 0 | K34: =G34+J34 -> 0
E35: =SUM(E4:E34) -> 0 | G35: =SUM(G4:G34) -> 0 | H35: =SUM(H4:H34) -> 0 | J35: =SUM(J4:J34) -> 0 | K35: =SUM(K4:K34) -> 0 | L35: =SUM(L4:L34) -> 1500000
P36: =170+165 -> 335

Sheet Jadcharla-3
A1: Bhavani KSK Fuel Station-Nawabpet
A2: S.No | B2: Date | C2: GRN No | D2: Ind No/Bill No | E2: Diesel (Lts) | F2: Price | G2: Amount | H2: Petrol (Lts) | I2: Price | J2: Amount | K2: Total amount | L2: Amount paid | M2: As on Date | N2: Remarks
A3: Opening Balance | K3: 0 | M3: =+K3 -> 0
A4: 1 | B4: 45778 | G4: 0 | J4: 0 | K4: 0 | L4: 0 | M4: =M3+K4-L4 -> 0
A5: 2 | B5: 45779 | E5: 0 | F5: 0 | G5: 0 | J5: 0 | K5: 0 | L5: 0 | M5: =M4+K5-L5 -> 0
A6: 3 | B6: 45780 | E6: 0 | F6: 0 | G6: 0 | J6: 0 | K6: 0 | L6: 0 | M6: =M5+K6-L6 -> 0 | R6: 541.08
A7: 4 | B7: 45781 | E7: 0 | F7: 0 | G7: 0 | J7: 0 | K7: 0 | L7: 0 | M7: =M6+K7-L7 -> 0
A8: 5 | B8: 45782 | E8: 20 | F8: 96.31 | G8: 1926.2 | J8: 0 | K8: 1926.2 | L8: 0 | M8: =M7+K8-L8 -> 1926.2
A9: 6 | B9: 45783 | E9: 3000 | F9: 96.31 | G9: 288930 | J9: 0 | K9: 288930 | L9: 0 | M9: =M8+K9-L9 -> 290856.2
A10: 7 | B10: 45784 | E10: 0 | F10: 0 | G10: 0 | J10: 0 | K10: 0 | L10: 0 | M10: =M9+K10-L10 -> 290856.2
A11: 8 | B11: 45785 | E11: 1020 | F11: 96.31 | G11: 98236.2 | J11: 0 | K11: 98236.2 | L11: 0 | M11: =M10+K11-L11 -> 389092.4
A12: 9 | B12: 45786 | E12: 0 | F12: 0 | G12: 0 | J12: 0 | K12: 0 | L12: 0 | M12: =M11+K12-L12 -> 389092.4
A13: 10 | B13: 45787 | E13: 0 | F13: 0 | G13: 0 | J13: 0 | K13: 0 | L13: 0 | M13: =M12+K13-L13 -> 389092.4
A14: 11 | B14: 45788 | E14: 0 | F14: 0 | G14: 0 | J14: 0 | K14: 0 | L14: 0 | M14: =M13+K14-L14 -> 389092.4
A15: 12 | B15: 45789 | E15: 0 | F15: 0 | G15: 0 | J15: 0 | K15: 0 | L15: 0 | M15: =M14+K15-L15 -> 389092.4
A16: 13 | B16: 45790 | E16: 0 | F16: 0 | G16: 0 | J16: 0 | K16: 0 | L16: 0 | M16: =M15+K16-L16 -> 389092.4
A17: 14 | B17: 45791 | E17: 0 | F17: 0 | G17: 0 | J17: 0 | K17: 0 | L17: 0 | M17: =M16+K17-L17 -> 389092.4
A18: 15 | B18: 45792 | E18: 0 | F18: 0 | G18: 0 | J18: 0 | K18: 0 | L18: 0 | M18: =M17+K18-L18 -> 389092.4
... A29: 26 | B29: 45803 | E29: 0 | F29: 0 | G29: 0 | J29: 0 | K29: 0 | L29: 389092.4 | M29: =M28+K29-L29 -> 0
A30: 27 | B30: 45804 | E30: 0 | F30: 0 | G30: 0 | J30: 0 | K30: 0 | L30: 0 | M30: =M29+K30-L30 -> 0 | P30: =2939612.08-2939070.93 -> 541.15
A31: 28 | B31: 45805 | E31: 0 | F31: 0 | G31: 0 | J31: 0 | K31: 0 | L31: 0 | M31: =M30+K31-L31 -> 0
A32: 29 | B32: 45806 | E32: 0 | F32: 0 | G32: 0 | J32: 0 | K32: 0
A33: 30 | B33: 45807 | E33: 0 | F33: 0 | G33: 0 | J33: 0 | K33: 0
A34: 31 | B34: 45808 | E34: 0 | F34: 0 | G34: 0 | J34: 0 | K34: 0
E35: =SUM(E4:E34) -> 4040 | G35: =SUM(G4:G34) -> 389092.4 | H35: =SUM(H4:H34) -> 0 | J35: =SUM(J4:J34) -> 0 | K35: =SUM(K4:K34) -> 389092.4 | L35: =SUM(L4:L34) -> 389092.4

Sheet Jedcharla-4
A1: ADHOC FILLING STATION STATION
A2: S.No | B2: Date | C2: GRN No | D2: Ind No/Bill No | E2: Diesel (Lts) | F2: Price | G2: Amount | H2: Petrol (Lts) | I2: Price | J2: Amount | K2: Total amount | L2: Amount paid | M2: As on Date | N2: Remarks
A3: Opening Balance | K3: 0 | M3: =+K3 -> 0
A4: 1 | B4: 45778 | G4: =E4*F4 -> 0 | J4: =H4*I4 -> 0 | K4: =G4+J4 -> 0 | M4: =M3+K4-L4 -> 0
A5: 2 | B5: 45779 | E5: 0 | F5: 0 | G5: =E5*F5 -> 0 | J5: =H5*I5 -> 0 | K5: =G5+J5 -> 0 | M5: =M4+K5-L5 -> 0
A6: 3 | B6: 45780 | E6: 0 | F6: 0 | G6: =E6*F6 -> 0 | J6: =H6*I6 -> 0 | K6: =G6+J6 -> 0 | M6: =M5+K6-L6 -> 0 | R6: 541.08
A7: 4 | B7: 45781 | E7: 0 | F7: 0 | G7: =E7*F7 -> 0 | J7: =H7*I7 -> 0 | K7: =G7+J7 -> 0 | M7: =M6+K7-L7 -> 0
A8: 5 | B8: 45782 | E8: 0 | F8: 0 | G8: =E8*F8 -> 0 | J8: =H8*I8 -> 0 | K8: =G8+J8 -> 0 | M8: =M7+K8-L8 -> 0
A9: 6 | B9: 45783 | E9: 0 | F9: 0 | G9: =E9*F9 -> 0 | J9: =H9*I9 -> 0 | K9: =G9+J9 -> 0 | M9: =M8+K9-L9 -> 0
A10: 7 | B10: 45784 | E10: 0 | F10: 0 | G10: =E10*F10 -> 0 | J10: =H10*I10 -> 0 | K10: =G10+J10 -> 0 | M10: =M9+K10-L10 -> 0
A11: 8 | B11: 45785 | E11: 0 | F11: 0 | G11: =E11*F11 -> 0 | J11: =H11*I11 -> 0 | K11: =G11+J11 -> 0 | M11: =M10+K11-L11 -> 0
A12: 9 | B12: 45786 | E12: 0 | F12: 0 | G12: =E12*F12 -> 0 | J12: =H12*I12 -> 0 | K12: =G12+J12 -> 0 | M12: =M11+K12-L12 -> 0
A13: 10 | B13: 45787 | E13: 2400 | F13: 96.43 | G13: =E13*F13 -> 231432 | J13: =H13*I13 -> 0 | K13: =G13+J13 -> 231432 | M13: =M12+K13-L13 -> 231432
A14: 11 | B14: 45788 | E14: 0 | F14: 0 | G14: =E14*F14 -> 0 | J14: =H14*I14 -> 0 | K14: =G14+J14 -> 0 | M14: =M13+K14-L14 -> 231432
A15: 12 | B15: 45789 | E15: 2400 | F15: 96.43 | G15: =E15*F15 -> 231432 | J15: =H15*I15 -> 0 | K15: =G15+J15 -> 231432 | M15: =M14+K15-L15 -> 462864
A16: 13 | B16: 45790 | E16: 2000 | F16: 96.43 | G16: =E16*F16 -> 192860 | J16: =H16*I16 -> 0 | K16: =G16+J16 -> 192860 | M16: =M15+K16-L16 -> 655724
A17: 14 | B17: 45791 | E17: 0 | F17: 0 | G17: =E17*F17 -> 0 | J17: =H17*I17 -> 0 | K17: =G17+J17 -> 0 | M17: =M16+K17-L17 -> 655724
A18: 15 | B18: 45792 | E18: 0 | F18: 0 | G18: =E18*F18 -> 0 | J18: =H18*I18 -> 0 | K18: =G18+J18 -> 0 | M18: =M17+K18-L18 -> 655724
... A29: 26 | B29: 45803 | E29: 2200 | F29: 96.43 | G29: =E29*F29 -> 212146 | J29: =H29*I29 -> 0 | K29: =G29+J29 -> 212146 | M29: =M28+K29-L29 -> 1562166
A30: 27 | B30: 45804 | E30: 0 | F30: 0 | G30: =E30*F30 -> 0 | J30: =H30*I30 -> 0 | K30: =G30+J30 -> 0 | L30: 500000 | M30: =M29+K30-L30 -> 1062166 | P30: =2939612.08-2939070.93 -> 541.15
A31: 28 | B31: 45805 | E31: 0 | F31: 0 | G31: =E31*F31 -> 0 | J31: =H31*I31 -> 0 | K31: =G31+J31 -> 0 | L31: 0 | M31: =M30+K31-L31 -> 1062166
A32: 29 | B32: 45806 | E32: 2400 | F32: 96.43 | G32: =E32*F32 -> 231432 | J32: =H32*I32 -> 0 | K32: =G32+J32 -> 231432 | M32: =M31+K32-L32 -> 1293598
A33: 30 | B33: 45807 | E33: 0 | F33: 0 | G33: =E33*F33 -> 0 | J33: =H33*I33 -> 0 | K33: =G33+J33 -> 0 | L33: 1293600 | M33: =M32+K33-L33 -> -2
A34: 31 | E34: 0 | F34: 0 | G34: =E34*F34 -> 0 | J34: =H34*I34 -> 0 | K34: =G34+J34 -> 0 | L34: -2 | M34: =M33+K34-L34 -> 0
E35: =SUM(E4:E34) -> 18600 | G35: =SUM(G4:G34) -> 1793598 | H35: =SUM(H4:H34) -> 0 | J35: =SUM(J4:J34) -> 0 | K35: =SUM(K4:K34) -> 1793598 | L35: =SUM(L4:L34) -> 1793598

Sheet Sangareddy
A1: Sangareddy
A2: S.No | B2: Date | C2: GRN No | D2: Ind No/Bill No | E2: Diesel (Lts) | F2: Price | G2: Amount | H2: Petrol (Lts) | I2: Price | J2: Amount | K2: Total amount | L2: Amount paid | M2: As on Date | N2: Remarks
A3: Opening Balance | K3: 1004532 | M3: =+K3 -> 1004532
A4: 1 | B4: 45778 | E4: 200 | F4: 96.36 | G4: =E4*F4 -> 19272 | H4: 10 | I4: 108.17 | J4: =H4*I4 -> 1081.7 | K4: =G4+J4 -> 20353.7 | M4: =M3+K4-L4 -> 1024885.7
A5: 2 | B5: 45779 | E5: 1787.9 | F5: 96.36 | G5: =E5*F5 -> 172282.04 | H5: 5 | I5: 108.17 | J5: =H5*I5 -> 540.85 | K5: =G5+J5 -> 172822.89 | M5: =M4+K5-L5 -> 1197708.6
A6: 3 | B6: 45780 | E6: 340 | F6: 96.36 | G6: =E6*F6 -> 32762.4 | H6: 0 | I6: 0 | J6: =H6*I6 -> 0 | K6: =G6+J6 -> 32762.4 | M6: =M5+K6-L6 -> 1230471
A7: 4 | B7: 45781 | E7: 1001.23 | F7: 96.36 | G7: =E7*F7 -> 96478.523 | H7: 2 | I7: 108.17 | J7: =H7*I7 -> 216.34 | K7: =G7+J7 -> 96694.863 | M7: =M6+K7-L7 -> 1327165.8
A8: 5 | B8: 45782 | E8: 586.83 | F8: 96.36 | G8: =E8*F8 -> 56546.939 | H8: 10 | I8: 108.17 | J8: =H8*I8 -> 1081.7 | K8: =G8+J8 -> 57628.639 | M8: =M7+K8-L8 -> 1384794.5
A9: 6 | B9: 45783 | E9: 0 | F9: 0 | G9: =E9*F9 -> 0 | H9: 0 | I9: 0 | J9: =H9*I9 -> 0 | K9: =G9+J9 -> 0 | M9: =M8+K9-L9 -> 1384794.5
A10: 7 | B10: 45784 | E10: 0 | F10: 0 | G10: =E10*F10 -> 0 | H10: 0 | I10: 0 | J10: =H10*I10 -> 0 | K10: =G10+J10 -> 0 | M10: =M9+K10-L10 -> 1384794.5
A11: 8 | B11: 45785 | E11: 100 | F11: 96.36 | G11: =E11*F11 -> 9636 | H11: 19 | I11: 108.17 | J11: =H11*I11 -> 2055.23 | K11: =G11+J11 -> 11691.23 | L11: 11691.23 | M11: =M10+K11-L11 -> 1384794.5
A12: 9 | B12: 45786 | E12: 170 | F12: 96.36 | G12: =E12*F12 -> 16381.2 | H12: 0 | I12: 0 | J12: =H12*I12 -> 0 | K12: =G12+J12 -> 16381.2 | L12: 16381.2 | M12: =M11+K12-L12 -> 1384794.5
A13: 10 | B13: 45787 | E13: 170 | F13: 96.36 | G13: =E13*F13 -> 16381.2 | H13: 0 | I13: 0 | J13: =H13*I13 -> 0 | K13: =G13+J13 -> 16381.2 | L13: 16381.2 | M13: =M12+K13-L13 -> 1384794.5
A14: 11 | B14: 45788 | E14: 0 | F14: 0 | G14: =E14*F14 -> 0 | H14: 0 | I14: 0 | J14: =H14*I14 -> 0 | K14: =G14+J14 -> 0 | M14: =M13+K14-L14 -> 1384794.5
A15: 12 | B15: 45789 | E15: 0 | F15: 0 | G15: =E15*F15 -> 0 | H15: 16 | I15: 108.17 | J15: =H15*I15 -> 1730.72 | K15: =G15+J15 -> 1730.72 | L15: 1730.72 | M15: =M14+K15-L15 -> 1384794.5
A16: 13 | B16: 45790 | E16: 100 | F16: 96.36 | G16: =E16*F16 -> 9636 | H16: 0 | I16: 0 | J16: =H16*I16 -> 0 | K16: =G16+J16 -> 9636 | L16: 9636 | M16: =M15+K16-L16 -> 1384794.5
A17: 14 | B17: 45791 | E17: 20 | F17: 96.36 | G17: =E17*F17 -> 1927.2 | H17: 0 | I17: 0 | J17: =H17*I17 -> 0 | K17: =G17+J17 -> 1927.2 | L17: =H17+K17 -> 1927.2 | M17: =M16+K17-L17 -> 1384794.5
A18: 15 | B18: 45792 | E18: 50 | F18: 96.36 | G18: =E18*F18 -> 4818 | H18: 0 | I18: 0 | J18: =H18*I18 -> 0 | K18: =G18+J18 -> 4818 | L18: 4818 | M18: =M17+K18-L18 -> 1384794.5
A19: 16 | B19: 45793 | E19: 30 | F19: 96.36 | G19: =E19*F19 -> 2890.8 | H19: 0 | I19: 0 | J19: =H19*I19 -> 0 | K19: =G19+J19 -> 2890.8 | L19: 2890.8 | M19: =M18+K19-L19 -> 1384794.5
B20: 45793 | E20: 0 | F20: 0 | G20: =E20*F20 -> 0 | H20: 0 | I20: 0 | J20: =H20*I20 -> 0 | K20: =G20+J20 -> 0 | L20: 1384896.7 | M20: =M19+K20-L20 -> -102.1798
B21: 45793 | D21: SRI DURGABHAVANI FILLING STATION BPCL | E21: 10 | F21: 96.44 | G21: =E21*F21 -> 964.4 | H21: 16 | I21: 108.31 | J21: =H21*I21 -> 1732.96 | K21: =G21+J21 -> 2697.36 | L21: =+K21 -> 2697.36 | M21: =M20+K21-L21 -> -102.1798 | N21: BPCL
A22: 17 | B22: 45794 | D22: SRI DURGABHAVANI FILLING STATION BPCL | E22: 90 | F22: 96.44 | G22: =E22*F22 -> 8679.6 | H22: 0 | I22: 0 | J22: =H22*I22 -> 0 | K22: =G22+J22 -> 8679.6 | L22: =+K22 -> 8679.6 | M22: =M21+K22-L22 -> -102.1798 | N22: BPCL
B23: 45794 | D23: LAXMI NARASIMHA ENTERPRISES | E23: 40 | F23: 96.24 | G23: =E23*F23 -> 3849.6 | H23: 0 | I23: 0 | J23: =H23*I23 -> 0 | K23: =G23+J23 -> 3849.6 | L23: =+K23 -> 3849.6 | M23: =M22+K23-L23 -> -102.1798 | N23: IOCL
A24: 18 | B24: 45795 | D24: SRI DURGABHAVANI FILLING STATION BPCL | E24: 10 | F24: 96.24 | G24: =E24*F24 -> 962.4 | H24: 0 | I24: 0 | J24: =H24*I24 -> 0 | K24: =G24+J24 -> 962.4 | L24: =+K24 -> 962.4 | M24: =M23+K24-L24 -> -102.1798 | N24: BPCL
B25: 45795 | D25: Sree Shiva Parvathi Filling Station F/S BPCL | E25: 259.79 | F25: 96.23 | G25: =E25*F25 -> 24999.592 | H25: 0 | I25: 0 | J25: =H25*I25 -> 0 | K25: =G25+J25 -> 24999.592 | L25: =+K25 -> 24999.592 | M25: =M24+K25-L25 -> -102.1798 | N25: BPCL
A26: 19 | B26: 45796 | D26: SRI DURGABHAVANI FILLING STATION BPCL | E26: 55 | F26: 96.44 | G26: =E26*F26 -> 5304.2 | H26: 0 | I26: 0 | J26: =H26*I26 -> 0 | K26: =G26+J26 -> 5304.2 | L26: =+K26 -> 5304.2 | M26: =M25+K26-L26 -> -102.1798 | N26: BPCL
A27: 20 | B27: 45797 | D27: Sree Shiva Parvathi Filling Station F/S BPCL | E27: 600 | F27: 96.23 | G27: =E27*F27 -> 57738 | H27: 16 | I27: 0 | J27: =H27*I27 -> 0 | K27: =G27+J27 -> 57738 | L27: =+K27 -> 57738 | M27: =M26+K27-L27 -> -102.1798
A28: 21 | B28: 45798 | D28: Sree Shiva Parvathi Filling Station F/S BPCL | E28: 600 | F28: 96.23 | G28: =E28*F28 -> 57738 | H28: 0 | I28: 0 | J28: =H28*I28 -> 0 | K28: =G28+J28 -> 57738 | L28: =+K28 -> 57738 | M28: =M27+K28-L28 -> -102.1798
A29: 22 | B29: 45799 | E29: 0 | F29: 0 | G29: =E29*F29 -> 0 | H29: 0 | I29: 0 | J29: =H29*I29 -> 0 | K29: =G29+J29 -> 0 | L29: =+K29 -> 0 | M29: =M28+K29-L29 -> -102.1798
A30: 23 | B30: 45800 | D30: Sree Shiva Parvathi Filling Station F/S BPCL | E30: 600 | F30: 96.23 | G30: =E30*F30 -> 57738 | H30: 10 | I30: 108.31 | J30: =H30*I30 -> 1083.1 | K30: =G30+J30 -> 58821.1 | L30: =+K30 -> 58821.1 | M30: =M29+K30-L30 -> -102.1798
A31: 24 | B31: 45801 | E31: 0 | F31: 0 | G31: =E31*F31 -> 0 | H31: 0 | I31: 0 | J31: =H31*I31 -> 0 | K31: =G31+J31 -> 0 | L31: =+K31 -> 0 | M31: =M30+K31-L31 -> -102.1798
A32: 25 | B32: 45802 | D32: Sree Shiva Parvathi Filling Station F/S BPCL | E32: 0 | F32: 0 | G32: =E32*F32 -> 0 | H32: 0 | I32: 0 | J32: =H32*I32 -> 0 | K32: =G32+J32 -> 0 | L32: =+K32 -> 0 | M32: =M31+K32-L32 -> -102.1798
A33: 26 | B33: 45803 | D33: Sree Shiva Parvathi Filling Station F/S BPCL | E33: 295 | F33: 96.23 | G33: =E33*F33 -> 28387.85 | H33: 14.92 | I33: 108.31 | J33: =H33*I33 -> 1615.9852 | K33: =G33+J33 -> 30003.835 | L33: =+K33 -> 30003.835 | M33: =M32+K33-L33 -> -102.1798
A34: 27 | B34: 45804 | D34: Sree Shiva Parvathi Filling Station F/S BPCL | E34: 600 | F34: 96.23 | G34: =E34*F34 -> 57738 | H34: 0 | I34: 0 | J34: =H34*I34 -> 0 | K34: =G34+J34 -> 57738 | L34: =+K34 -> 57738 | M34: =M33+K34-L34 -> -102.1798
A35: 28 | B35: 45805 | E35: 0 | F35: 0 | G35: =E35*F35 -> 0 | H35: 0 | I35: 0 | J35: =H35*I35 -> 0 | K35: =G35+J35 -> 0 | L35: =+K35 -> 0 | M35: =M34+K35-L35 -> -102.1798
A36: 29 | B36: 45806 | D36: Sree Shiva Parvathi Filling Station F/S BPCL | E36: 600 | F36: 96.23 | G36: =E36*F36 -> 57738 | H36: 0 | I36: 0 | J36: =H36*I36 -> 0 | K36: =G36+J36 -> 57738 | L36: =+K36 -> 57738 | M36: =M35+K36-L36 -> -102.1798
A37: 30 | B37: 45807 | D37: Sree Shiva Parvathi Filling Station F/S BPCL | E37: 0 | F37: 0 | G37: =E37*F37 -> 0 | H37: 0 | I37: 0 | J37: =H37*I37 -> 0 | K37: =G37+J37 -> 0 | L37: =+K37 -> 0 | M37: =M36+K37-L37 -> -102.1798
A38: 31 | B38: 45808 | D38: Sree Shiva Parvathi Filling Station F/S BPCL | E38: 600 | F38: 96.23 | G38: =E38*F38 -> 57738 | H38: 16 | I38: 108.31 | J38: =H38*I38 -> 1732.96 | K38: =G38+J38 -> 59470.96 | L38: =+K38 -> 59470.96 | M38: =M37+K38-L38 -> -102.1798
E39: =SUM(E4:E38) -> 8915.75 | G39: =SUM(G4:G38) -> 858587.95 | H39: =SUM(H4:H38) -> 134.92 | J39: =SUM(J4:J38) -> 12871.545 | K39: =SUM(K4:K38) -> 871459.49 | L39: =SUM(L4:L38) -> 1876093.7
M45: 236703.21
M46: 236635.16
M47: =M45-M46 -> 68.0548

Sheet Dindi
A2: S.No | B2: Date | C2: GRN No | D2: Ind no/Bill No | E2: Diesel (Lts) | F2: Price | G2: Amount | H2: Petrol (Lts) | I2: Price | J2: Amount | K2: Total amount | L2: Amount paid | M2: As on Date | N2: Remarks
A3: Opening Balance | M3: 0
A4: 1 | B4: 45778 | E4: 0 | F4: 0 | G4: =E4*F4 -> 0 | H4: 0 | I4: 0 | J4: =H4*I4 -> 0 | K4: =G4+J4 -> 0 | L4: =+K4 -> 0 | M4: 0
A5: 2 | B5: 45779 | E5: 0 | F5: 0 | G5: =E5*F5 -> 0 | H5: 0 | I5: 0 | J5: =H5*I5 -> 0 | K5: =G5+J5 -> 0 | L5: =+K5 -> 0 | M5: 0
A6: 3 | B6: 45780 | E6: 0 | F6: 0 | G6: =E6*F6 -> 0 | H6: 0 | I6: 0 | J6: =H6*I6 -> 0 | K6: =G6+J6 -> 0 | L6: =+K6 -> 0 | M6: 0
A7: 4 | B7: 45781 | E7: 0 | F7: 0 | G7: =E7*F7 -> 0 | H7: 0 | I7: 0 | J7: =H7*I7 -> 0 | K7: =G7+J7 -> 0 | L7: =+K7 -> 0 | M7: 0
A8: 5 | B8: 45782 | E8: 0 | F8: 0 | G8: =E8*F8 -> 0 | H8: 0 | I8: 0 | J8: =H8*I8 -> 0 | K8: =G8+J8 -> 0 | L8: =+K8 -> 0 | M8: 0
A9: 6 | B9: 45783 | E9: 0 | F9: 0 | G9: =E9*F9 -> 0 | H9: 0 | I9: 0 | J9: =H9*I9 -> 0 | K9: =G9+J9 -> 0 | L9: =+K9 -> 0 | M9: 0
A10: 7 | B10: 45784 | E10: 0 | F10: 0 | G10: =E10*F10 -> 0 | H10: 0 | I10: 0 | J10: =H10*I10 -> 0 | K10: =G10+J10 -> 0 | L10: =+K10 -> 0 | M10: 0
A11: 8 | B11: 45785 | E11: 0 | F11: 0 | G11: =E11*F11 -> 0 | H11: 0 | I11: 0 | J11: =H11*I11 -> 0 | K11: =G11+J11 -> 0 | L11: =+K11 -> 0 | M11: 0
A12: 9 | B12: 45786 | E12: 0 | F12: 0 | G12: =E12*F12 -> 0 | H12: 0 | I12: 0 | J12: =H12*I12 -> 0 | K12: =G12+J12 -> 0 | L12: =+K12 -> 0 | M12: 0
A13: 10 | B13: 45787 | E13: 0 | F13: 0 | G13: =E13*F13 -> 0 | H13: 0 | I13: 0 | J13: =H13*I13 -> 0 | K13: =G13+J13 -> 0 | L13: =+K13 -> 0 | M13: 0
A14: 11 | B14: 45788 | E14: 0 | F14: 0 | G14: =E14*F14 -> 0 | H14: 0 | I14: 0 | J14: =H14*I14 -> 0 | K14: =G14+J14 -> 0 | L14: =+K14 -> 0 | M14: 0
A15: 12 | B15: 45789 | E15: 0 | F15: 0 | G15: =E15*F15 -> 0 | H15: 0 | I15: 0 | J15: =H15*I15 -> 0 | K15: =G15+J15 -> 0 | L15: =+K15 -> 0 | M15: 0
... A34: 31 | B34: 45808 | E34: 0 | F34: 0 | G34: =E34*F34 -> 0 | H34: 0 | I34: 0 | J34: =H34*I34 -> 0 | K34: =G34+J34 -> 0 | L34: =+K34 -> 0 | M34: 0
E35: =SUM(E4:E34) -> 160.67 | G35: =SUM(G4:G34) -> 15529.94 | H35: =SUM(H4:H34) -> 0 | J35: =SUM(J4:J34) -> 0 | K35: =SUM(K4:K34) -> 15529.94 | L35: =SUM(L4:L34) -> 15529.94

Sheet Hiriyur(VJNL)
A1: Sri Balaji Agencies
A2: S.No | B2: Date | C2: GRN No | D2: Ind No/Bill No | E2: Diesel (Lts) | F2: Price | G2: Amount | H2: Petrol (Lts) | I2: Price | J2: Amount | K2: Total amount | L2: Amount paid | M2: As on Date | N2: Remarks
A3: Opening Balance | K3: 0 | M3: 237520
A4: 1 | B4: 45778 | E4: 0 | G4: =E4*F4 -> 0 | H4: 0 | I4: 0 | J4: =H4*I4 -> 0 | K4: =G4+J4 -> 0 | M4: =M3+K4-L4 -> 237520
A5: 2 | B5: 45779 | E5: 0 | G5: =E5*F5 -> 0 | H5: 70 | I5: 103.86 | J5: =H5*I5 -> 7270.2 | K5: =G5+J5 -> 7270.2 | M5: =M4+K5-L5 -> 244790.2
A6: 3 | B6: 45780 | E6: 0 | G6: =E6*F6 -> 0 | H6: 0 | I6: 0 | J6: =H6*I6 -> 0 | K6: =G6+J6 -> 0 | M6: =M5+K6-L6 -> 244790.2
A7: 4 | B7: 45781 | E7: 0 | G7: =E7*F7 -> 0 | H7: 0 | I7: 0 | J7: =H7*I7 -> 0 | K7: =G7+J7 -> 0 | M7: =M6+K7-L7 -> 244790.2
A8: 5 | B8: 45782 | E8: 0 | G8: =E8*F8 -> 0 | H8: 0 | I8: 0 | J8: =H8*I8 -> 0 | K8: =G8+J8 -> 0 | M8: =M7+K8-L8 -> 244790.2
A9: 6 | B9: 45783 | E9: 0 | G9: =E9*F9 -> 0 | H9: 0 | I9: 0 | J9: =H9*I9 -> 0 | K9: =G9+J9 -> 0 | L9: 150000 | M9: =M8+K9-L9 -> 94790.2
A10: 7 | B10: 45784 | E10: 0 | G10: =E10*F10 -> 0 | H10: 0 | I10: 0 | J10: =H10*I10 -> 0 | K10: =G10+J10 -> 0 | M10: =M9+K10-L10 -> 94790.2
A11: 8 | B11: 45785 | E11: 0 | G11: =E11*F11 -> 0 | H11: 0 | I11: 0 | J11: =H11*I11 -> 0 | K11: =G11+J11 -> 0 | M11: =M10+K11-L11 -> 94790.2
A12: 9 | B12: 45786 | E12: 0 | G12: =E12*F12 -> 0 | H12: 0 | I12: 0 | J12: =H12*I12 -> 0 | K12: =G12+J12 -> 0 | M12: =M11+K12-L12 -> 94790.2
A13: 10 | B13: 45787 | E13: 0 | G13: =E13*F13 -> 0 | H13: 70 | I13: 103.86 | J13: =H13*I13 -> 7270.2 | K13: =G13+J13 -> 7270.2 | M13: =M12+K13-L13 -> 102060.4
A14: 11 | B14: 45788 | E14: 0 | G14: =E14*F14 -> 0 | H14: 0 | I14: 0 | J14: =H14*I14 -> 0 | K14: =G14+J14 -> 0 | M14: =M13+K14-L14 -> 102060.4
A15: 12 | B15: 45789 | E15: 0 | G15: =E15*F15 -> 0 | H15: 0 | I15: 0 | J15: =H15*I15 -> 0 | K15: =G15+J15 -> 0 | L15: 100000 | M15: =M14+K15-L15 -> 2060.4
A16: 13 | B16: 45790 | E16: 0 | G16: =E16*F16 -> 0 | H16: 0 | I16: 0 | J16: =H16*I16 -> 0 | K16: =G16+J16 -> 0 | M16: =M15+K16-L16 -> 2060.4
A17: 14 | B17: 45791 | E17: 0 | G17: =E17*F17 -> 0 | H17: 0 | I17: 0 | J17: =H17*I17 -> 0 | K17: =G17+J17 -> 0 | M17: =M16+K17-L17 -> 2060.4
A18: 15 | B18: 45792 | E18: 0 | G18: =E18*F18 -> 0 | H18: 0 | I18: 0 | J18: =H18*I18 -> 0 | K18: =G18+J18 -> 0 | M18: =M17+K18-L18 -> 2060.4
A19: 16 | B19: 45793 | E19: 2400 | F19: 92.1 | G19: =E19*F19 -> 221040 | H19: 70 | I19: 103.86 | J19: =H19*I19 -> 7270.2 | K19: =G19+J19 -> 228310.2 | M19: =M18+K19-L19 -> 230370.6
A20: 17 | B20: 45794 | E20: 0 | G20: =E20*F20 -> 0 | H20: 0 | I20: 0 | J20: =H20*I20 -> 0 | K20: =G20+J20 -> 0 | M20: =M19+K20-L20 -> 230370.6
A21: 18 | B21: 45795 | E21: 0 | G21: =E21*F21 -> 0 | H21: 0 | I21: 0 | J21: =H21*I21 -> 0 | K21: =G21+J21 -> 0 | M21: =M20+K21-L21 -> 230370.6
A22: 19 | B22: 45796 | E22: 0 | G22: =E22*F22 -> 0 | H22: 0 | I22: 0 | J22: =H22*I22 -> 0 | K22: =G22+J22 -> 0 | M22: =M21+K22-L22 -> 230370.6
A23: 20 | B23: 45797 | E23: 0 | G23: =E23*F23 -> 0 | H23: 0 | I23: 0 | J23: =H23*I23 -> 0 | K23: =G23+J23 -> 0 | M23: =M22+K23-L23 -> 230370.6
A24: 21 | B24: 45798 | E24: 0 | G24: =E24*F24 -> 0 | H24: 0 | I24: 0 | J24: =H24*I24 -> 0 | K24: =G24+J24 -> 0 | M24: =M23+K24-L24 -> 230370.6
A25: 22 | B25: 45799 | E25: 0 | G25: =E25*F25 -> 0 | H25: 0 | I25: 0 | J25: =H25*I25 -> 0 | K25: =G25+J25 -> 0 | M25: =M24+K25-L25 -> 230370.6
A26: 23 | B26: 45800 | E26: 0 | G26: =E26*F26 -> 0 | H26: 0 | I26: 0 | J26: =H26*I26 -> 0 | K26: =G26+J26 -> 0 | M26: =M25+K26-L26 -> 230370.6
A27: 24 | B27: 45801 | E27: 0 | G27: =E27*F27 -> 0 | H27: 0 | I27: 0 | J27: =H27*I27 -> 0 | K27: =G27+J27 -> 0 | M27: =M26+K27-L27 -> 230370.6
A28: 25 | B28: 45802 | E28: 0 | G28: =E28*F28 -> 0 | H28: 0 | I28: 0 | J28: =H28*I28 -> 0 | K28: =G28+J28 -> 0 | M28: =M27+K28-L28 -> 230370.6
A29: 26 | B29: 45803 | E29: 0 | G29: =E29*F29 -> 0 | H29: 0 | I29: 0 | J29: =H29*I29 -> 0 | K29: =G29+J29 -> 0 | M29: =M28+K29-L29 -> 230370.6
A30: 27 | B30: 45804 | E30: 0 | G30: =E30*F30 -> 0 | H30: 0 | I30: 0 | J30: =H30*I30 -> 0 | K30: =G30+J30 -> 0 | L30: 150000 | M30: =M29+K30-L30 -> 80370.6
A31: 28 | B31: 45805 | E31: 0 | G31: =E31*F31 -> 0 | H31: 0 | I31: 0 | J31: =H31*I31 -> 0 | K31: =G31+J31 -> 0 | M31: =M30+K31-L31 -> 80370.6
A32: 29 | B32: 45806 | E32: 0 | G32: =E32*F32 -> 0 | H32: 0 | I32: 0 | J32: =H32*I32 -> 0 | K32: =G32+J32 -> 0 | M32: =M31+K32-L32 -> 80370.6
A33: 30 | B33: 45807 | E33: 0 | G33: =E33*F33 -> 0 | H33: 70 | I33: 103.86 | J33: =H33*I33 -> 7270.2 | K33: =G33+J33 -> 7270.2 | M33: =M32+K33-L33 -> 87640.8
A34: 31 | B34: 45808 | E34: 0 | G34: =E34*F34 -> 0 | H34: 0 | I34: 0 | J34: =H34*I34 -> 0 | K34: =G34+J34 -> 0 | M34: =M33+K34-L34 -> 87640.8
E35: =SUM(E4:E34) -> 2400 | G35: =SUM(G4:G34) -> 221040 | H35: =SUM(H4:H34) -> 280 | J35: =SUM(J4:J34) -> 29080.8 | K35: =SUM(K4:K34) -> 250120.8 | L35: =SUM(L4:L34) -> 400000

Sheet Hosadurga
A1: Merchant Petroliums
A2: S.No | B2: Date | C2: GRN No | D2: Ind No/Bill No | E2: Diesel (Lts) | F2: Price | G2: Amount | H2: Petrol (Lts) | I2: Price | J2: Amount | K2: Total amount | L2: Amount paid | M2: As on Date | N2: Remarks
A3: Opening Balance | K3: 0 | M3: =+K3 -> 0
A4: 1 | B4: 45778 | E4: 0 | F4: 0 | G4: 0 | H4: 0 | I4: 0 | J4: =H4*I4 -> 0 | K4: =G4+J4 -> 0 | L4: 0 | M4: =M3+K4-L4 -> 0
A5: 2 | B5: 45779 | E5: 0 | F5: 0 | G5: 0 | H5: 0 | I5: 0 | J5: =H5*I5 -> 0 | K5: =G5+J5 -> 0 | L5: 0 | M5: =M4+K5-L5 -> 0
A6: 3 | B6: 45780 | E6: 0 | F6: 0 | G6: 0 | H6: 0 | I6: 0 | J6: =H6*I6 -> 0 | K6: =G6+J6 -> 0 | L6: 0 | M6: =M5+K6-L6 -> 0
A7: 4 | B7: 45781 | E7: 0 | F7: 0 | G7: 0 | H7: 0 | I7: 0 | J7: =H7*I7 -> 0 | K7: =G7+J7 -> 0 | L7: 0 | M7: =M6+K7-L7 -> 0
A8: 5 | B8: 45782 | E8: 0 | F8: 0 | G8: 0 | H8: 0 | I8: 0 | J8: =H8*I8 -> 0 | K8: =G8+J8 -> 0 | L8: 0 | M8: =M7+K8-L8 -> 0
A9: 6 | B9: 45783 | E9: 0 | F9: 0 | G9: 0 | H9: 0 | I9: 0 | J9: =H9*I9 -> 0 | K9: =G9+J9 -> 0 | L9: 0 | M9: =M8+K9-L9 -> 0
A10: 7 | B10: 45784 | E10: 0 | F10: 0 | G10: 0 | H10: 0 | I10: 0 | J10: =H10*I10 -> 0 | K10: =G10+J10 -> 0 | L10: 0 | M10: =M9+K10-L10 -> 0
A11: 8 | B11: 45785 | E11: 500 | F11: 91.64 | G11: =E11*F11 -> 45820 | H11: 70 | I11: 103.72 | J11: =H11*I11 -> 7260.4 | K11: =G11+J11 -> 53080.4 | L11: 0 | M11: =M10+K11-L11 -> 53080.4
A12: 9 | B12: 45786 | E12: 0 | F12: 0 | G12: =E12*F12 -> 0 | H12: 0 | I12: 0 | J12: =H12*I12 -> 0 | K12: =G12+J12 -> 0 | L12: 0 | M12: =M11+K12-L12 -> 53080.4
A13: 10 | B13: 45787 | E13: 0 | F13: 0 | G13: =E13*F13 -> 0 | H13: 0 | I13: 0 | J13: =H13*I13 -> 0 | K13: =G13+J13 -> 0 | L13: 0 | M13: =M12+K13-L13 -> 53080.4
A14: 11 | B14: 45788 | E14: 1000 | F14: 91.64 | G14: =E14*F14 -> 91640 | H14: 35 | I14: 111.04 | J14: =H14*I14 -> 3886.4 | K14: =G14+J14 -> 95526.4 | L14: 0 | M14: =M13+K14-L14 -> 148606.8
A15: 12 | B15: 45789 | E15: 0 | F15: 0 | G15: =E15*F15 -> 0 | H15: 0 | I15: 0 | J15: =H15*I15 -> 0 | K15: =G15+J15 -> 0 | L15: 0 | M15: =M14+K15-L15 -> 148606.8
A16: 13 | B16: 45790 | E16: 0 | F16: 0 | G16: =E16*F16 -> 0 | H16: 0 | I16: 0 | J16: =H16*I16 -> 0 | K16: =G16+J16 -> 0 | L16: 0 | M16: =M15+K16-L16 -> 148606.8 | X16: =100*104 -> 10400
A17: 14 | B17: 45791 | E17: 1500 | F17: 91.64 | G17: =E17*F17 -> 137460 | H17: 0 | I17: 0 | J17: =H17*I17 -> 0 | K17: =G17+J17 -> 137460 | L17: 0 | M17: =M16+K17-L17 -> 286066.8
A18: 15 | B18: 45792 | E18: 0 | F18: 0 | G18: =E18*F18 -> 0 | H18: 0 | I18: 0 | J18: =H18*I18 -> 0 | K18: =G18+J18 -> 0 | L18: 0 | M18: =M17+K18-L18 -> 286066.8
A19: 16 | B19: 45793 | E19: 0 | F19: 0 | G19: =E19*F19 -> 0 | H19: 35 | I19: 103.72 | J19: =H19*I19 -> 3630.2 | K19: =G19+J19 -> 3630.2 | L19: 0 | M19: =M18+K19-L19 -> 289697
A20: 17 | B20: 45794 | E20: 0 | F20: 0 | G20: =E20*F20 -> 0 | H20: 0 | I20: 0 | J20: =H20*I20 -> 0 | K20: =G20+J20 -> 0 | L20: 0 | M20: =M19+K20-L20 -> 289697
A21: 18 | B21: 45795 | E21: 0 | F21: 0 | G21: =E21*F21 -> 0 | H21: 0 | I21: 0 | J21: =H21*I21 -> 0 | K21: =G21+J21 -> 0 | L21: 0 | M21: =M20+K21-L21 -> 289697
A22: 19 | B22: 45796 | E22: 0 | F22: 0 | G22: =E22*F22 -> 0 | H22: 0 | I22: 0 | J22: =H22*I22 -> 0 | K22: =G22+J22 -> 0 | L22: 0 | M22: =M21+K22-L22 -> 289697
A23: 20 | B23: 45797 | E23: 0 | F23: 0 | G23: =E23*F23 -> 0 | H23: 0 | I23: 0 | J23: =H23*I23 -> 0 | K23: =G23+J23 -> 0 | L23: 0 | M23: =M22+K23-L23 -> 289697
A24: 21 | B24: 45798 | E24: 1500 | F24: 91.64 | G24: =E24*F24 -> 137460 | H24: 0 | I24: 0 | J24: =H24*I24 -> 0 | K24: =G24+J24 -> 137460 | L24: 150000 | M24: =M23+K24-L24 -> 277157
A25: 22 | B25: 45799 | E25: 0 | F25: 0 | G25: 0 | H25: 0 | I25: 0 | J25: =H25*I25 -> 0 | K25: =G25+J25 -> 0 | L25: 0 | M25: =M24+K25-L25 -> 277157
A26: 23 | B26: 45800 | E26: 0 | F26: 0 | G26: 0 | H26: 0 | I26: 0 | J26: =H26*I26 -> 0 | K26: =G26+J26 -> 0 | L26: 0 | M26: =M25+K26-L26 -> 277157
A27: 24 | B27: 45801 | E27: 0 | F27: 0 | G27: 0 | H27: 0 | I27: 0 | J27: =H27*I27 -> 0 | K27: =G27+J27 -> 0 | L27: 0 | M27: =M26+K27-L27 -> 277157
A28: 25 | B28: 45802 | E28: 0 | F28: 0 | G28: 0 | H28: 0 | I28: 0 | J28: =H28*I28 -> 0 | K28: =G28+J28 -> 0 | L28: 0 | M28: =M27+K28-L28 -> 277157
A29: 26 | B29: 45803 | E29: 0 | F29: 0 | G29: 0 | H29: 0 | I29: 0 | J29: =H29*I29 -> 0 | K29: =G29+J29 -> 0 | L29: 275530 | M29: =M28+K29-L29 -> 1627
A30: 27 | B30: 45804 | E30: 0 | F30: 0 | G30: 0 | H30: 0 | I30: 0 | J30: =H30*I30 -> 0 | K30: =G30+J30 -> 0 | L30: 1627 | M30: =M29+K30-L30 -> 0
A31: 28 | B31: 45805 | E31: 0 | F31: 0 | G31: 0 | H31: 0 | I31: 0 | J31: =H31*I31 -> 0 | K31: =G31+J31 -> 0 | L31: 0 | M31: =M30+K31-L31 -> 0
A32: 29 | B32: 45806 | E32: 0 | F32: 0 | G32: =E32*F32 -> 0 | H32: 0 | I32: 0 | J32: =H32*I32 -> 0 | K32: =G32+J32 -> 0 | L32: 0
A33: 30 | B33: 45807 | E33: 0 | F33: 0 | G33: =E33*F33 -> 0 | H33: 0 | I33: 0 | J33: =H33*I33 -> 0 | K33: =G33+J33 -> 0 | L33: 0
A34: 31 | B34: 45808
E35: =SUM(E4:E34) -> 4500 | G35: =SUM(G4:G34) -> 412380 | H35: =SUM(H4:H34) -> 140 | J35: =SUM(J4:J34) -> 14777 | K35: =SUM(K4:K34) -> 427157 | L35: =SUM(L4:L34) -> 427157

Sheet Hosadurga -2
A1: Shree Veeraprathap Fuel
A2: S.No | B2: Date | C2: GRN No | D2: Ind No/Bill No | E2: Diesel (Lts) | F2: Price | G2: Amount | H2: Petrol (Lts) | I2: Price | J2: Amount | K2: Total amount | L2: Amount paid | M2: As on Date | N2: Remarks
A3: Opening Balance | K3: 151569.4 | M3: =+K3 -> 151569.4
A4: 1 | B4: 45778 | C4: 1569/1570 | E4: 2000 | F4: 91.39 | G4: =E4*F4 -> 182780 | H4: 35 | I4: 103.46 | J4: =H4*I4 -> 3621.1 | K4: =G4+J4 -> 186401.1 | L4: 0 | M4: =M3+K4-L4 -> 337970.5
A5: 2 | B5: 45779 | E5: 0 | F5: 0 | G5: =E5*F5 -> 0 | H5: 0 | I5: 0 | J5: =H5*I5 -> 0 | K5: =G5+J5 -> 0 | L5: 0 | M5: =M4+K5-L5 -> 337970.5
A6: 3 | B6: 45780 | E6: 0 | F6: 0 | G6: =E6*F6 -> 0 | H6: 0 | I6: 0 | J6: =H6*I6 -> 0 | K6: =G6+J6 -> 0 | L6: 0 | M6: =M5+K6-L6 -> 337970.5
A7: 4 | B7: 45781 | C7: ` | E7: 0 | F7: 0 | G7: =E7*F7 -> 0 | H7: 0 | I7: 0 | J7: =H7*I7 -> 0 | K7: =G7+J7 -> 0 | L7: 0 | M7: =M6+K7-L7 -> 337970.5
A8: 5 | B8: 45782 | E8: 0 | F8: 0 | G8: =E8*F8 -> 0 | H8: 0 | I8: 0 | J8: =H8*I8 -> 0 | K8: =G8+J8 -> 0 | L8: 0 | M8: =M7+K8-L8 -> 337970.5
A9: 6 | B9: 45783 | E9: 0 | F9: 0 | G9: =E9*F9 -> 0 | H9: 0 | I9: 0 | J9: =H9*I9 -> 0 | K9: =G9+J9 -> 0 | L9: 0 | M9: =M8+K9-L9 -> 337970.5
A10: 7 | B10: 45784 | E10: 0 | F10: 0 | G10: =E10*F10 -> 0 | H10: 0 | I10: 0 | J10: =H10*I10 -> 0 | K10: =G10+J10 -> 0 | L10: 0 | M10: =M9+K10-L10 -> 337970.5
A11: 8 | B11: 45785 | E11: 0 | F11: 0 | G11: =E11*F11 -> 0 | H11: 0 | I11: 0 | J11: =H11*I11 -> 0 | K11: =G11+J11 -> 0 | L11: 150000 | M11: =M10+K11-L11 -> 187970.5
A12: 9 | B12: 45786 | E12: 0 | F12: 0 | G12: =E12*F12 -> 0 | H12: 0 | I12: 0 | J12: =H12*I12 -> 0 | K12: =G12+J12 -> 0 | L12: 0 | M12: =M11+K12-L12 -> 187970.5
A13: 10 | B13: 45787 | E13: 0 | F13: 0 | G13: =E13*F13 -> 0 | H13: 0 | I13: 0 | J13: =H13*I13 -> 0 | K13: =G13+J13 -> 0 | L13: 0 | M13: =M12+K13-L13 -> 187970.5
A14: 11 | B14: 45788 | E14: 0 | F14: 0 | G14: =E14*F14 -> 0 | H14: 0 | I14: 0 | J14: =H14*I14 -> 0 | K14: =G14+J14 -> 0 | L14: 0 | M14: =M13+K14-L14 -> 187970.5
A15: 12 | B15: 45789 | E15: 0 | F15: 0 | G15: =E15*F15 -> 0 | H15: 0 | I15: 0 | J15: =H15*I15 -> 0 | K15: =G15+J15 -> 0 | L15: 0 | M15: =M14+K15-L15 -> 187970.5
A16: 13 | B16: 45790 | E16: 0 | F16: 0 | G16: =E16*F16 -> 0 | H16: 0 | I16: 0 | J16: =H16*I16 -> 0 | K16: =G16+J16 -> 0 | L16: 0 | M16: =M15+K16-L16 -> 187970.5
A17: 14 | B17: 45791 | E17: 0 | F17: 0 | G17: =E17*F17 -> 0 | H17: 0 | I17: 0 | J17: =H17*I17 -> 0 | K17: =G17+J17 -> 0 | L17: 0 | M17: =M16+K17-L17 -> 187970.5
A18: 15 | B18: 45792 | E18: 0 | F18: 0 | G18: =E18*F18 -> 0 | H18: 0 | I18: 0 | J18: =H18*I18 -> 0 | K18: =G18+J18 -> 0 | L18: 0 | M18: =M17+K18-L18 -> 187970.5
A19: 16 | B19: 45793 | E19: 0 | F19: 0 | G19: =E19*F19 -> 0 | H19: 0 | I19: 0 | J19: =H19*I19 -> 0 | K19: =G19+J19 -> 0 | L19: 0 | M19: =M18+K19-L19 -> 187970.5
... A31: 28 | B31: 45805 | E31: 0 | F31: 0 | G31: =E31*F31 -> 0 | H31: 0 | I31: 0 | J31: =H31*I31 -> 0 | K31: =G31+J31 -> 0 | L31: 0 | M31: =M30+K31-L31 -> 388266.5
A32: 29 | B32: 45806 | E32: 0 | F32: 0 | G32: =E32*F32 -> 0 | H32: 0 | I32: 0 | J32: =H32*I32 -> 0 | K32: =G32+J32 -> 0 | L32: 0
A33: 30 | B33: 45807 | E33: 0 | F33: 0 | G33: =E33*F33 -> 0 | H33: 0 | I33: 0 | J33: =H33*I33 -> 0 | K33: =G33+J33 -> 0 | L33: 0
A34: 31 | B34: 45808
E35: =SUM(E4:E34) -> 3999.21 | G35: =SUM(G4:G34) -> 365487.8 | H35: =SUM(H4:H34) -> 205 | J35: =SUM(J4:J34) -> 21209.3 | K35: =SUM(K4:K34) -> 386697.1 | L35: =SUM(L4:L34) -> 150000

Sheet Srirangapatna
A1: Sri Chakra Fuel Station
A2: S.No | B2: Date | C2: GRN No | D2: Ind no/Bill No | E2: Diesel (Lts) | F2: Price | G2: Amount | H2: Petrol (Lts) | I2: Price | J2: Amount | K2: Total amount | L2: Amount paid | M2: As on Date | N2: Remarks
A3: Opening Balance | M3: 0
A4: 1 | B4: 45778 | G4: =E4*F4 -> 0 | H4: 0 | I4: 0 | J4: =H4*I4 -> 0 | K4: =G4+J4 -> 0 | L4: =+K4 -> 0 | M4: 0
A5: 2 | B5: 45779 | G5: =E5*F5 -> 0 | H5: 0 | I5: 0 | J5: =H5*I5 -> 0 | K5: =G5+J5 -> 0 | L5: =+K5 -> 0 | M5: 0
A6: 3 | B6: 45780 | G6: =E6*F6 -> 0 | H6: 0 | I6: 0 | J6: =H6*I6 -> 0 | K6: =G6+J6 -> 0 | L6: =+K6 -> 0 | M6: 0
A7: 4 | B7: 45781 | G7: =E7*F7 -> 0 | H7: 8.3 | I7: 102.46 | J7: =H7*I7 -> 850.418 | K7: =G7+J7 -> 850.418 | L7: =+K7 -> 850.418 | M7: 0
A8: 5 | B8: 45782 | G8: =E8*F8 -> 0 | H8: 0 | I8: 0 | J8: =H8*I8 -> 0 | K8: =G8+J8 -> 0 | L8: =+K8 -> 0 | M8: 0
A9: 6 | B9: 45783 | G9: =E9*F9 -> 0 | H9: 0 | I9: 0 | J9: =H9*I9 -> 0 | K9: =G9+J9 -> 0 | L9: =+K9 -> 0 | M9: 0
A10: 7 | B10: 45784 | G10: =E10*F10 -> 0 | H10: 6.05 | I10: 102.46 | J10: =H10*I10 -> 619.883 | K10: =G10+J10 -> 619.883 | L10: =+K10 -> 619.883 | M10: 0
A11: 8 | B11: 45785 | G11: =E11*F11 -> 0 | H11: 0 | I11: 0 | J11: =H11*I11 -> 0 | K11: =G11+J11 -> 0 | L11: =+K11 -> 0 | M11: 0
A12: 9 | B12: 45786 | G12: =E12*F12 -> 0 | H12: 0 | I12: 0 | J12: =H12*I12 -> 0 | K12: =G12+J12 -> 0 | L12: =+K12 -> 0 | M12: 0
A13: 10 | B13: 45787 | G13: =E13*F13 -> 0 | H13: 0 | I13: 0 | J13: =H13*I13 -> 0 | K13: =G13+J13 -> 0 | L13: =+K13 -> 0 | M13: 0
A14: 11 | B14: 45788 | G14: =E14*F14 -> 0 | H14: 0 | I14: 0 | J14: =H14*I14 -> 0 | K14: =G14+J14 -> 0 | L14: =+K14 -> 0 | M14: 0
A15: 12 | B15: 45789 | G15: =E15*F15 -> 0 | H15: 0 | I15: 0 | J15: =H15*I15 -> 0 | K15: =G15+J15 -> 0 | L15: =+K15 -> 0 | M15: 0
... A23: 20 | B23: 45797 | G23: =E23*F23 -> 0 | H23: 0 | I23: 0 | J23: =H23*I23 -> 0 | K23: =G23+J23 -> 0 | L23: =+K23 -> 0 | M23: 0
A24: 21 | B24: 45798 | E24: 71.77 | F24: 90.57 | G24: =E24*F24 -> 6500.2089 | H24: 9.08 | I24: 102.46 | J24: =H24*I24 -> 930.3368 | K24: =G24+J24 -> 7430.5457 | L24: =+K24 -> 7430.5457 | M24: 0
A25: 22 | B25: 45799 | G25: =E25*F25 -> 0 | H25: 0 | I25: 0 | J25: =H25*I25 -> 0 | K25: =G25+J25 -> 0 | L25: =+K25 -> 0 | M25: 0
A26: 23 | B26: 45800 | G26: =E26*F26 -> 0 | H26: 0 | I26: 0 | J26: =H26*I26 -> 0 | K26: =G26+J26 -> 0 | L26: =+K26 -> 0 | M26: 0
A27: 24 | B27: 45801 | G27: =E27*F27 -> 0 | H27: 0 | I27: 0 | J27: =H27*I27 -> 0 | K27: =G27+J27 -> 0 | L27: =+K27 -> 0 | M27: 0
A28: 25 | B28: 45802 | G28: =E28*F28 -> 0 | H28: 0 | I28: 0 | J28: =H28*I28 -> 0 | K28: =G28+J28 -> 0 | L28: =+K28 -> 0 | M28: 0
A29: 26 | B29: 45803 | G29: =E29*F29 -> 0 | H29: 0 | I29: 0 | J29: =H29*I29 -> 0 | K29: =G29+J29 -> 0 | L29: =+K29 -> 0 | M29: 0
A30: 27 | B30: 45804 | E30: 0 | F30: 0 | G30: =E30*F30 -> 0 | H30: 4.88 | I30: 102.46 | J30: =H30*I30 -> 500.0048 | K30: =G30+J30 -> 500.0048 | L30: =+K30 -> 500.0048 | M30: 0
A31: 28 | B31: 45805 | E31: 77.29 | F31: 90.57 | G31: =E31*F31 -> 7000.1553 | H31: 0 | I31: 0 | J31: =H31*I31 -> 0 | K31: =G31+J31 -> 7000.1553 | L31: =+K31 -> 7000.1553 | M31: 0
A32: 29 | B32: 45806 | G32: =E32*F32 -> 0 | H32: 9.15 | I32: 102.46 | J32: =H32*I32 -> 937.509 | K32: =G32+J32 -> 937.509 | L32: =+K32 -> 937.509 | M32: 0
A33: 30 | B33: 45807 | G33: =E33*F33 -> 0 | H33: 0 | I33: 0 | J33: =H33*I33 -> 0 | K33: =G33+J33 -> 0 | L33: =+K33 -> 0 | M33: 0
A34: 31 | B34: 45808 | E34: 110.41 | F34: 90.57 | G34: =E34*F34 -> 9999.8337 | H34: 0 | I34: 0 | J34: =H34*I34 -> 0 | K34: =G34+J34 -> 9999.8337 | L34: =+K34 -> 9999.8337 | M34: 0
E35: =SUM(E4:E34) -> 259.47 | G35: =SUM(G4:G34) -> 23500.198 | H35: =SUM(H4:H34) -> 49.16 | J35: =SUM(J4:J34) -> 5036.9336 | K35: =SUM(K4:K34) -> 28537.131 | L35: =SUM(L4:L34) -> 28537.131

Sheet YG Gudda 
A1: Pallavi Petrolium
A2: S.No | B2: Date | C2: GRN No | D2: Ind No/Bill No | E2: Diesel (Lts) | F2: Price | G2: Amount | H2: Petrol (Lts) | I2: Price | J2: Amount | K2: Total amount | L2: Amount paid | M2: As on Date | N2: Remarks
A3: Opening Balance | K3: 244365 | M3: =+K3 -> 244365
A4: 1 | B4: 45778 | E4: 0 | G4: =E4*F4 -> 0 | H4: 0 | J4: =H4*I4 -> 0 | K4: =G4+J4 -> 0 | M4: =M3+K4-L4 -> 244365
A5: 2 | B5: 45779 | E5: 0 | G5: =E5*F5 -> 0 | H5: 0 | J5: =H5*I5 -> 0 | K5: =G5+J5 -> 0 | M5: =M4+K5-L5 -> 244365
A6: 3 | B6: 45780 | E6: 0 | G6: =E6*F6 -> 0 | H6: 105 | I6: 103.24 | J6: =H6*I6 -> 10840.2 | K6: =G6+J6 -> 10840.2 | M6: =M5+K6-L6 -> 255205.2
A7: 4 | B7: 45781 | E7: 400 | F7: 91.3 | G7: =E7*F7 -> 36520 | H7: 0 | J7: =H7*I7 -> 0 | K7: =G7+J7 -> 36520 | M7: =M6+K7-L7 -> 291725.2
A8: 5 | B8: 45782 | E8: 0 | G8: =E8*F8 -> 0 | H8: 0 | J8: =H8*I8 -> 0 | K8: =G8+J8 -> 0 | M8: =M7+K8-L8 -> 291725.2
A9: 6 | B9: 45783 | E9: 0 | G9: =E9*F9 -> 0 | H9: 0 | J9: =H9*I9 -> 0 | K9: =G9+J9 -> 0 | M9: =M8+K9-L9 -> 291725.2
A10: 7 | B10: 45784 | E10: 2400 | F10: 91.3 | G10: =E10*F10 -> 219120 | H10: 70 | I10: 103.24 | J10: =H10*I10 -> 7226.8 | K10: =G10+J10 -> 226346.8 | L10: 199947 | M10: =M9+K10-L10 -> 318125
A11: 8 | B11: 45785 | E11: 0 | G11: =E11*F11 -> 0 | H11: 0 | J11: =H11*I11 -> 0 | K11: =G11+J11 -> 0 | M11: =M10+K11-L11 -> 318125
A12: 9 | B12: 45786 | E12: 0 | G12: =E12*F12 -> 0 | H12: 0 | J12: =H12*I12 -> 0 | K12: =G12+J12 -> 0 | M12: =M11+K12-L12 -> 318125
A13: 10 | B13: 45787 | E13: 0 | G13: =E13*F13 -> 0 | H13: 0 | J13: =H13*I13 -> 0 | K13: =G13+J13 -> 0 | M13: =M12+K13-L13 -> 318125
A14: 11 | B14: 45788 | E14: 0 | G14: =E14*F14 -> 0 | H14: 0 | J14: =H14*I14 -> 0 | K14: =G14+J14 -> 0 | M14: =M13+K14-L14 -> 318125
A15: 12 | B15: 45789 | E15: 0 | G15: =E15*F15 -> 0 | H15: 0 | J15: =H15*I15 -> 0 | K15: =G15+J15 -> 0 | M15: =M14+K15-L15 -> 318125
A16: 13 | B16: 45790 | E16: 0 | G16: =E16*F16 -> 0 | H16: 105 | I16: 103.24 | J16: =H16*I16 -> 10840.2 | K16: =G16+J16 -> 10840.2 | L16: 99973 | M16: =M15+K16-L16 -> 228992.2
A17: 14 | B17: 45791 | E17: 0 | G17: =E17*F17 -> 0 | H17: 0 | J17: =H17*I17 -> 0 | K17: =G17+J17 -> 0 | M17: =M16+K17-L17 -> 228992.2
A18: 15 | B18: 45792 | E18: 0 | G18: =E18*F18 -> 0 | H18: 0 | J18: =H18*I18 -> 0 | K18: =G18+J18 -> 0 | M18: =M17+K18-L18 -> 228992.2
A19: 16 | B19: 45793 | E19: 0 | G19: =E19*F19 -> 0 | H19: 0 | J19: =H19*I19 -> 0 | K19: =G19+J19 -> 0 | M19: =M18+K19-L19 -> 228992.2
A20: 17 | B20: 45794 | E20: 1000 | F20: 91.3 | G20: =E20*F20 -> 91300 | H20: 105 | I20: 103.24 | J20: =H20*I20 -> 10840.2 | K20: =G20+J20 -> 102140.2 | M20: =M19+K20-L20 -> 331132.4
A21: 18 | B21: 45795 | E21: 0 | G21: =E21*F21 -> 0 | H21: 0 | J21: =H21*I21 -> 0 | K21: =G21+J21 -> 0 | M21: =M20+K21-L21 -> 331132.4
A22: 19 | B22: 45796 | E22: 0 | G22: =E22*F22 -> 0 | H22: 0 | J22: =H22*I22 -> 0 | K22: =G22+J22 -> 0 | M22: =M21+K22-L22 -> 331132.4
A23: 20 | B23: 45797 | E23: 0 | G23: =E23*F23 -> 0 | H23: 0 | J23: =H23*I23 -> 0 | K23: =G23+J23 -> 0 | M23: =M22+K23-L23 -> 331132.4
A24: 21 | B24: 45798 | E24: 0 | G24: =E24*F24 -> 0 | H24: 0 | J24: =H24*I24 -> 0 | K24: =G24+J24 -> 0 | M24: =M23+K24-L24 -> 331132.4
A25: 22 | B25: 45799 | E25: 0 | G25: =E25*F25 -> 0 | H25: 0 | J25: =H25*I25 -> 0 | K25: =G25+J25 -> 0 | M25: =M24+K25-L25 -> 331132.4
A26: 23 | B26: 45800 | E26: 0 | G26: =E26*F26 -> 0 | H26: 0 | J26: =H26*I26 -> 0 | K26: =G26+J26 -> 0 | M26: =M25+K26-L26 -> 331132.4
A27: 24 | B27: 45801 | E27: 328.47 | F27: 91.33 | G27: =E27*F27 -> 29999.165 | H27: 0 | J27: =H27*I27 -> 0 | K27: =G27+J27 -> 29999.165 | L27: 30000 | M27: =M26+K27-L27 -> 331131.57
A28: 25 | B28: 45801 | E28: 2400 | F28: 91.3 | G28: =E28*F28 -> 219120 | H28: 105 | I28: 103.24 | J28: =H28*I28 -> 10840.2 | K28: =G28+J28 -> 229960.2 | M28: =M27+K28-L28 -> 561091.77
A29: 26 | B29: 45802 | E29: 0 | G29: =E29*F29 -> 0 | H29: 0 | J29: =H29*I29 -> 0 | K29: =G29+J29 -> 0 | M29: =M28+K29-L29 -> 561091.77
A30: 27 | B30: 45803 | E30: 0 | G30: =E30*F30 -> 0 | H30: 0 | J30: =H30*I30 -> 0 | K30: =G30+J30 -> 0 | L30: 250000 | M30: =M29+K30-L30 -> 311091.77
A31: 28 | B31: 45804 | E31: 0 | G31: =E31*F31 -> 0 | H31: 105 | I31: 103.24 | J31: =H31*I31 -> 10840.2 | K31: =G31+J31 -> 10840.2 | M31: =M30+K31-L31 -> 321931.97
A32: 29 | B32: 45805 | E32: 0 | G32: =E32*F32 -> 0 | H32: 0 | J32: =H32*I32 -> 0 | K32: =G32+J32 -> 0 | M32: =M31+K32-L32 -> 321931.97
A33: 30 | B33: 45806 | E33: 0 | G33: =E33*F33 -> 0 | H33: 0 | J33: =H33*I33 -> 0 | K33: =G33+J33 -> 0 | L33: 250000 | M33: =M32+K33-L33 -> 71931.965
A34: 31 | B34: 45807 | E34: 0 | G34: =E34*F34 -> 0 | H34: 0 | J34: =H34*I34 -> 0 | K34: =G34+J34 -> 0 | M34: =M33+K34-L34 -> 71931.965
A35: 32 | B35: 45808 | E35: 0 | G35: =E35*F35 -> 0 | H35: 0 | J35: =H35*I35 -> 0 | K35: =G35+J35 -> 0 | M35: =M34+K35-L35 -> 71931.965
E36: =SUM(E4:E35) -> 6528.47 | G36: =SUM(G4:G35) -> 596059.17 | H36: =SUM(H4:H35) -> 595 | J36: =SUM(J4:J35) -> 61427.8 | K36: =SUM(K4:K35) -> 657486.97 | L36: =SUM(L4:L35) -> 829920

Sheet Kadur
A1: Vishal Service Station
A2: S.No | B2: Date | C2: GRN No | D2: Ind No/Bill No | E2: Diesel (Lts) | F2: Price | G2: Amount | H2: Petrol (Lts) | I2: Price | J2: Amount | K2: Total amount | L2: Amount paid | M2: As on Date | N2: Remarks
A3: Opening Balance | K3: 776427.65 | M3: =+K3 -> 776427.65 | P3: 1142944.1
A4: 1 | B4: 45778 | F4: 0 | G4: =E4*F4 -> 0 | H4: 0 | I4: 0 | J4: =H4*I4 -> 0 | K4: =G4+J4 -> 0 | M4: =M3+K4-L4 -> 776427.65
A5: 2 | B5: 45779 | F5: 0 | G5: =E5*F5 -> 0 | H5: 110 | I5: 104.27 | J5: =H5*I5 -> 11469.7 | K5: =G5+J5 -> 11469.7 | M5: =M4+K5-L5 -> 787897.35
A6: 3 | B6: 45780 | F6: 0 | G6: =E6*F6 -> 0 | H6: 0 | I6: 0 | J6: =H6*I6 -> 0 | K6: =G6+J6 -> 0 | M6: =M5+K6-L6 -> 787897.35
A7: 4 | B7: 45781 | F7: 0 | G7: =E7*F7 -> 0 | H7: 0 | I7: 0 | J7: =H7*I7 -> 0 | K7: =G7+J7 -> 0 | M7: =M6+K7-L7 -> 787897.35
A8: 5 | B8: 45782 | F8: 0 | G8: =E8*F8 -> 0 | H8: 0 | I8: 0 | J8: =H8*I8 -> 0 | K8: =G8+J8 -> 0 | M8: =M7+K8-L8 -> 787897.35
A9: 6 | B9: 45783 | F9: 0 | G9: =E9*F9 -> 0 | H9: 0 | I9: 0 | J9: =H9*I9 -> 0 | K9: =G9+J9 -> 0 | M9: =M8+K9-L9 -> 787897.35
A10: 7 | B10: 45784 | F10: 0 | G10: =E10*F10 -> 0 | H10: 0 | I10: 0 | J10: =H10*I10 -> 0 | K10: =G10+J10 -> 0 | M10: =M9+K10-L10 -> 787897.35
A11: 8 | B11: 45785 | F11: 0 | G11: =E11*F11 -> 0 | H11: 0 | I11: 0 | J11: =H11*I11 -> 0 | K11: =G11+J11 -> 0 | M11: =M10+K11-L11 -> 787897.35
A12: 9 | B12: 45786 | E12: 2000 | F12: 91.15 | G12: =E12*F12 -> 182300 | H12: 35 | I12: 104.27 | J12: =H12*I12 -> 3649.45 | K12: =G12+J12 -> 185949.45 | M12: =M11+K12-L12 -> 973846.8
A13: 10 | B13: 45787 | F13: 0 | G13: =E13*F13 -> 0 | H13: 0 | I13: 0 | J13: =H13*I13 -> 0 | K13: =G13+J13 -> 0 | M13: =M12+K13-L13 -> 973846.8
A14: 11 | B14: 45788 | F14: 0 | G14: =E14*F14 -> 0 | H14: 0 | I14: 0 | J14: =H14*I14 -> 0 | K14: =G14+J14 -> 0 | M14: =M13+K14-L14 -> 973846.8
A15: 12 | B15: 45789 | F15: 0 | G15: =E15*F15 -> 0 | H15: 0 | I15: 0 | J15: =H15*I15 -> 0 | K15: =G15+J15 -> 0 | M15: =M14+K15-L15 -> 973846.8
A16: 13 | B16: 45790 | F16: 0 | G16: =E16*F16 -> 0 | H16: 0 | I16: 0 | J16: =H16*I16 -> 0 | K16: =G16+J16 -> 0 | M16: =M15+K16-L16 -> 973846.8
A17: 14 | B17: 45791 | F17: 0 | G17: =E17*F17 -> 0 | H17: 0 | I17: 0 | J17: =H17*I17 -> 0 | K17: =G17+J17 -> 0 | M17: =M16+K17-L17 -> 973846.8
A18: 15 | B18: 45792 | F18: 0 | G18: =E18*F18 -> 0 | H18: 0 | I18: 0 | J18: =H18*I18 -> 0 | K18: =G18+J18 -> 0 | M18: =M17+K18-L18 -> 973846.8
A19: 16 | B19: 45793 | F19: 0 | G19: =E19*F19 -> 0 | H19: 0 | I19: 0 | J19: =H19*I19 -> 0 | K19: =G19+J19 -> 0 | M19: =M18+K19-L19 -> 973846.8
A20: 17 | B20: 45794 | F20: 0 | G20: =E20*F20 -> 0 | H20: 0 | I20: 0 | J20: =H20*I20 -> 0 | K20: =G20+J20 -> 0 | M20: =M19+K20-L20 -> 973846.8
A21: 18 | B21: 45795 | F21: 0 | G21: =E21*F21 -> 0 | H21: 0 | I21: 0 | J21: =H21*I21 -> 0 | K21: =G21+J21 -> 0 | M21: =M20+K21-L21 -> 973846.8
A22: 19 | B22: 45796 | F22: 0 | G22: =E22*F22 -> 0 | H22: 0 | I22: 0 | J22: =H22*I22 -> 0 | K22: =G22+J22 -> 0 | M22: =M21+K22-L22 -> 973846.8
A23: 20 | B23: 45797 | F23: 0 | G23: =E23*F23 -> 0 | H23: 0 | I23: 0 | J23: =H23*I23 -> 0 | K23: =G23+J23 -> 0 | M23: =M22+K23-L23 -> 973846.8
A24: 21 | B24: 45798 | F24: 0 | G24: =E24*F24 -> 0 | H24: 0 | I24: 0 | J24: =H24*I24 -> 0 | K24: =G24+J24 -> 0 | M24: =M23+K24-L24 -> 973846.8
... A28: 25 | B28: 45802 | F28: 0 | G28: =E28*F28 -> 0 | H28: 0 | I28: 0 | J28: =H28*I28 -> 0 | K28: =G28+J28 -> 0 | M28: =M27+K28-L28 -> 973846.8
A29: 26 | B29: 45803 | E29: 11.04 | F29: 91.15 | G29: =E29*F29 -> 1006.296 | H29: 0 | I29: 0 | J29: =H29*I29 -> 0 | K29: =G29+J29 -> 1006.296 | L29: 1006.3 | M29: =M28+K29-L29 -> 973846.8
A30: 27 | B30: 45804 | F30: 0 | G30: =E30*F30 -> 0 | H30: 0 | I30: 0 | J30: =H30*I30 -> 0 | K30: =G30+J30 -> 0 | M30: =M29+K30-L30 -> 973846.8
A31: 28 | B31: 45805 | F31: 0 | G31: =E31*F31 -> 0 | H31: 0 | I31: 0 | J31: =H31*I31 -> 0 | K31: =G31+J31 -> 0 | M31: =M30+K31-L31 -> 973846.8
A32: 29 | B32: 45806 | E32: 2000 | F32: 91.15 | G32: =E32*F32 -> 182300 | H32: 105 | I32: 104.27 | J32: =H32*I32 -> 10948.35 | K32: =G32+J32 -> 193248.35 | M32: =M31+K32-L32 -> 1167095.1
A33: 30 | B33: 45807 | F33: 0 | G33: =E33*F33 -> 0 | H33: 0 | I33: 0 | J33: =H33*I33 -> 0 | K33: =G33+J33 -> 0 | M33: =M32+K33-L33 -> 1167095.1
A34: 31 | B34: 45808 | F34: 0 | G34: =E34*F34 -> 0 | J34: =H34*I34 -> 0 | K34: =G34+J34 -> 0
E35: =SUM(E4:E34) -> 4011.04 | G35: =SUM(G4:G34) -> 365606.3 | H35: =SUM(H4:H34) -> 250 | J35: =SUM(J4:J34) -> 26067.5 | K35: =SUM(K4:K34) -> 391673.8 | L35: =SUM(L4:L31) -> 1006.3

Sheet Malebenur(KUWSDB)
A1: Sri Ramanjuneya Service Station
A2: S.No | B2: Date | C2: GRN No | D2: Ind No/Bill No | E2: Diesel (Lts) | F2: Price | G2: Amount | H2: Petrol (Lts) | I2: Price | J2: Amount | K2: Total amount | L2: Amount paid | M2: As on Date | N2: Remarks
A3: Opening Balance | K3: 0 | M3: 96655
A4: 1 | B4: 45778 | E4: 0 | F4: 0 | G4: =E4*F4 -> 0 | H4: 0 | J4: =H4*I4 -> 0 | K4: =G4+J4 -> 0 | L4: 0 | M4: =M3+K4-L4 -> 96655
A5: 2 | B5: 45779 | E5: 0 | F5: 0 | G5: =E5*F5 -> 0 | H5: 0 | J5: =H5*I5 -> 0 | K5: =G5+J5 -> 0 | L5: 0 | M5: =M4+K5-L5 -> 96655
A6: 3 | B6: 45780 | E6: 434.31 | F6: 92.1 | G6: =E6*F6 -> 39999.951 | H6: 0 | J6: =H6*I6 -> 0 | K6: =G6+J6 -> 39999.951 | L6: 39999.95 | M6: =M5+K6-L6 -> 96655.001
A7: 4 | B7: 45781 | E7: 0 | F7: 0 | G7: =E7*F7 -> 0 | H7: 0 | J7: =H7*I7 -> 0 | K7: =G7+J7 -> 0 | L7: 0 | M7: =M6+K7-L7 -> 96655.001
A8: 5 | B8: 45782 | E8: 0 | F8: 0 | G8: 0 | H8: 0 | I8: 0 | J8: =H8*I8 -> 0 | K8: =G8+J8 -> 0 | L8: 0 | M8: =M7+K8-L8 -> 96655.001
A9: 6 | B9: 45783 | E9: 0 | F9: 0 | G9: =E9*F9 -> 0 | H9: 0 | J9: =H9*I9 -> 0 | K9: =G9+J9 -> 0 | L9: 0 | M9: =M8+K9-L9 -> 96655.001
A10: 7 | B10: 45784 | E10: 460.53 | F10: 92.1 | G10: =E10*F10 -> 42414.813 | H10: 35 | I10: 103.86 | J10: =H10*I10 -> 3635.1 | K10: =G10+J10 -> 46049.913 | L10: 96656 | M10: =M9+K10-L10 -> 46048.914
A11: 8 | B11: 45785 | E11: 0 | F11: 0 | G11: =E11*F11 -> 0 | H11: 0 | J11: =H11*I11 -> 0 | K11: =G11+J11 -> 0 | L11: 0 | M11: =M10+K11-L11 -> 46048.914
A12: 9 | B12: 45786 | E12: 0 | F12: 0 | G12: =E12*F12 -> 0 | H12: 0 | J12: =H12*I12 -> 0 | K12: =G12+J12 -> 0 | L12: 0 | M12: =M11+K12-L12 -> 46048.914
A13: 10 | B13: 45787 | E13: 0 | F13: 0 | G13: =E13*F13 -> 0 | H13: 0 | J13: =H13*I13 -> 0 | K13: =G13+J13 -> 0 | L13: 0 | M13: =M12+K13-L13 -> 46048.914
A14: 11 | B14: 45788 | E14: 0 | F14: 0 | G14: =E14*F14 -> 0 | H14: 0 | J14: =H14*I14 -> 0 | K14: =G14+J14 -> 0 | L14: 0 | M14: =M13+K14-L14 -> 46048.914
A15: 12 | B15: 45789 | E15: 400 | F15: 92.1 | G15: =E15*F15 -> 36840 | H15: 35 | I15: 103.86 | J15: =H15*I15 -> 3635.1 | K15: =G15+J15 -> 40475.1 | L15: 0 | M15: =M14+K15-L15 -> 86524.014
A16: 13 | B16: 45790 | E16: 0 | F16: 0 | G16: =E16*F16 -> 0 | H16: 0 | J16: =H16*I16 -> 0 | K16: =G16+J16 -> 0 | L16: 0 | M16: =M15+K16-L16 -> 86524.014
A17: 14 | B17: 45791 | E17: 0 | F17: 0 | G17: =E17*F17 -> 0 | H17: 0 | J17: =H17*I17 -> 0 | K17: =G17+J17 -> 0 | L17: 0 | M17: =M16+K17-L17 -> 86524.014
A18: 15 | B18: 45792 | E18: 550 | F18: 92.1 | G18: =E18*F18 -> 50655 | H18: 20 | I18: 103.86 | J18: =H18*I18 -> 2077.2 | K18: =G18+J18 -> 52732.2 | L18: 0 | M18: =M17+K18-L18 -> 139256.21
A19: 16 | B19: 45793 | E19: 0 | F19: 0 | G19: =E19*F19 -> 0 | H19: 0 | J19: =H19*I19 -> 0 | K19: =G19+J19 -> 0 | L19: 0 | M19: =M18+K19-L19 -> 139256.21
A20: 17 | B20: 45794 | E20: 0 | F20: 0 | G20: =E20*F20 -> 0 | H20: 0 | J20: =H20*I20 -> 0 | K20: =G20+J20 -> 0 | L20: 0 | M20: =M19+K20-L20 -> 139256.21 | V20: =400*90.23 -> 36092
A21: 18 | B21: 45795 | E21: 0 | F21: 0 | G21: =E21*F21 -> 0 | H21: 0 | J21: =H21*I21 -> 0 | K21: =G21+J21 -> 0 | L21: 0 | M21: =M20+K21-L21 -> 139256.21 | V21: =35*104.14 -> 3644.9
A22: 19 | B22: 45796 | E22: 0 | F22: 0 | G22: =E22*F22 -> 0 | H22: 0 | J22: =H22*I22 -> 0 | K22: =G22+J22 -> 0 | L22: 0 | M22: =M21+K22-L22 -> 139256.21
A23: 20 | B23: 45797 | E23: 300 | F23: 92.1 | G23: =E23*F23 -> 27630 | H23: 20 | I23: 103.86 | J23: =H23*I23 -> 2077.2 | K23: =G23+J23 -> 29707.2 | L23: 29707.2 | M23: =M22+K23-L23 -> 139256.21
A24: 21 | B24: 45798 | E24: 300 | F24: 92.1 | G24: =E24*F24 -> 27630 | H24: 0 | J24: =H24*I24 -> 0 | K24: =G24+J24 -> 27630 | L24: 139500 | M24: =M23+K24-L24 -> 27386.214
A25: 22 | B25: 45799 | E25: 0 | F25: 0 | G25: =E25*F25 -> 0 | H25: 0 | J25: =H25*I25 -> 0 | K25: =G25+J25 -> 0 | L25: 0 | M25: =M24+K25-L25 -> 27386.214
A26: 23 | B26: 45800 | E26: 600 | F26: 92.1 | G26: =E26*F26 -> 55260 | H26: 35 | I26: 103.86 | J26: =H26*I26 -> 3635.1 | K26: =G26+J26 -> 58895.1 | L26: 0 | M26: =M25+K26-L26 -> 86281.314
A27: 24 | B27: 45801 | E27: 0 | F27: 0 | G27: =E27*F27 -> 0 | H27: 0 | J27: =H27*I27 -> 0 | K27: =G27+J27 -> 0 | L27: 0 | M27: =M26+K27-L27 -> 86281.314
A28: 25 | B28: 45802 | E28: 500 | F28: 92.1 | G28: =E28*F28 -> 46050 | H28: 0 | J28: =H28*I28 -> 0 | K28: =G28+J28 -> 46050 | L28: 0 | M28: =M27+K28-L28 -> 132331.31
A29: 26 | B29: 45803 | E29: 0 | F29: 0 | G29: =E29*F29 -> 0 | H29: 0 | J29: =H29*I29 -> 0 | K29: =G29+J29 -> 0 | L29: 0 | M29: =M28+K29-L29 -> 132331.31
A30: 27 | B30: 45804 | E30: 0 | F30: 0 | G30: =E30*F30 -> 0 | H30: 0 | J30: =H30*I30 -> 0 | K30: =G30+J30 -> 0 | L30: 27630 | M30: =M29+K30-L30 -> 104701.31
A31: 28 | B31: 45805 | E31: 0 | F31: 0 | G31: =E31*F31 -> 0 | H31: 0 | J31: =H31*I31 -> 0 | K31: =G31+J31 -> 0 | L31: 0 | M31: =M30+K31-L31 -> 104701.31
A32: 29 | B32: 45806 | E32: 0 | F32: 0 | G32: =E32*F32 -> 0 | H32: 0 | J32: =H32*I32 -> 0 | K32: =G32+J32 -> 0 | L32: 104700 | M32: =M31+K32-L32 -> 1.314
A33: 30 | B33: 45807 | E33: 375 | F33: 92.1 | G33: =E33*F33 -> 34537.5 | H33: 20 | I33: 103.86 | J33: =H33*I33 -> 2077.2 | K33: =G33+J33 -> 36614.7 | L33: 0 | M33: =M32+K33-L33 -> 36616.014
A34: 31 | B34: 0 | E34: 0 | F34: 0 | G34: =E34*F34 -> 0 | H34: 0 | I34: 0 | J34: =H34*I34 -> 0 | K34: =G34+J34 -> 0 | L34: 0 | M34: =M33+K34-L34 -> 36616.014
E35: 0 | F35: 0 | G35: =E35*F35 -> 0 | H35: 0 | J35: =H35*I35 -> 0 | K35: =G35+J35 -> 0 | L35: 0 | M35: =M34+K35-L35 -> 36616.014 | O35: 34539 | P35: =M35-O35 -> 2077.014
E36: =SUM(E4:E34) -> 3919.84 | G36: =SUM(G4:G34) -> 361017.26 | H36: =SUM(H4:H34) -> 165 | J36: =SUM(J4:J34) -> 17136.9 | K36: =SUM(K4:K34) -> 378154.16 | L36: =SUM(L4:L34) -> 438193.15
E37: 833 | G37: 76719 | H37: 28 | J37: 2908 | K37: =G37+J37 -> 79627 | L37: 79627
E38: =SUM(E36:E37) -> 4752.84 | F38: =SUM(F36:F37) -> 0 | G38: =SUM(G36:G37) -> 437736.26 | H38: =SUM(H36:H37) -> 193 | I38: =SUM(I36:I37) -> 0 | J38: =SUM(J36:J37) -> 20044.9 | K38: =SUM(K36:K37) -> 457781.16 | L38: =SUM(L36:L37) -> 517820.15
S42: 9052944708

Sheet Molakamuru(KUWSDB)
A1: Sreenithya Petroleum
A2: S.No | B2: Date | C2: GRN No | D2: Ind No/Bill No | E2: Diesel (Lts) | F2: Price | G2: Amount | H2: Petrol (Lts) | I2: Price | J2: Amount | K2: Total amount | L2: Date of payment | M2: Amount paid | N2: Remarks
A3: 1
A4: 2
A5: 3
A6: 4
A7: 5

Sheet Chellakere (KUWSDB)
A1: Sri Vishnu Baba Petroleum
A2: S.No | B2: Date | C2: GRN No | D2: Ind No/Bill No | E2: Diesel (Lts) | F2: Price | G2: Amount | H2: Petrol (Lts) | I2: Price | J2: Amount | K2: Total amount | L2: Amount paid | M2: As on Date | N2: Remarks
A3: Opening Balance | K3: 0 | L3: 0 | M3: =+K3 -> 0
A4: 1 | B4: 45778 | G4: =E4*F4 -> 0 | J4: =H4*I4 -> 0 | K4: =G4+J4 -> 0 | L4: =K4 -> 0 | M4: =M3+K4-L4 -> 0
A5: 2 | B5: 45779 | G5: =E5*F5 -> 0 | J5: =H5*I5 -> 0 | K5: =G5+J5 -> 0 | L5: =K5 -> 0 | M5: =M4+K5-L5 -> 0
A6: 3 | B6: 45780 | E6: 140 | F6: 92.09 | G6: =E6*F6 -> 12892.6 | J6: =H6*I6 -> 0 | K6: =G6+J6 -> 12892.6 | L6: =K6 -> 12892.6 | M6: =M5+K6-L6 -> 0
A7: 4 | B7: 45781 | G7: =E7*F7 -> 0 | J7: =H7*I7 -> 0 | K7: =G7+J7 -> 0 | L7: =K7 -> 0 | M7: =M6+K7-L7 -> 0
A8: 5 | B8: 45782 | E8: 280 | F8: 92.09 | G8: =E8*F8 -> 25785.2 | H8: 35 | I8: 103.86 | J8: =H8*I8 -> 3635.1 | K8: =G8+J8 -> 29420.3 | L8: =K8 -> 29420.3 | M8: =M7+K8-L8 -> 0
A9: 6 | B9: 45783 | G9: =E9*F9 -> 0 | J9: =H9*I9 -> 0 | K9: =G9+J9 -> 0 | L9: =K9 -> 0 | M9: =M8+K9-L9 -> 0
A10: 7 | B10: 45784 | E10: 325 | F10: 92.09 | G10: =E10*F10 -> 29929.25 | J10: =H10*I10 -> 0 | K10: =G10+J10 -> 29929.25 | L10: =K10 -> 29929.25 | M10: =M9+K10-L10 -> 0
A11: 8 | B11: 45785 | G11: =E11*F11 -> 0 | J11: =H11*I11 -> 0 | K11: =G11+J11 -> 0 | L11: =K11 -> 0 | M11: =M10+K11-L11 -> 0
A12: 9 | B12: 45786 | E12: 200 | F12: 92.09 | G12: =E12*F12 -> 18418 | H12: 15 | I12: 103.86 | J12: =H12*I12 -> 1557.9 | K12: =G12+J12 -> 19975.9 | L12: =K12 -> 19975.9 | M12: =M11+K12-L12 -> 0
A13: 10 | B13: 45787 | G13: =E13*F13 -> 0 | J13: =H13*I13 -> 0 | K13: =G13+J13 -> 0 | L13: =K13 -> 0 | M13: =M12+K13-L13 -> 0
A14: 11 | B14: 45788 | G14: =E14*F14 -> 0 | J14: =H14*I14 -> 0 | K14: =G14+J14 -> 0 | L14: =K14 -> 0 | M14: =M13+K14-L14 -> 0
A15: 12 | B15: 45789 | E15: 300 | F15: 92.09 | G15: =E15*F15 -> 27627 | H15: 20 | I15: 103.86 | J15: =H15*I15 -> 2077.2 | K15: =G15+J15 -> 29704.2 | L15: =K15 -> 29704.2 | M15: =M14+K15-L15 -> 0
A16: 13 | B16: 45790 | G16: =E16*F16 -> 0 | J16: =H16*I16 -> 0 | K16: =G16+J16 -> 0 | L16: =K16 -> 0 | M16: =M15+K16-L16 -> 0
A17: 14 | B17: 45791 | G17: =E17*F17 -> 0 | J17: =H17*I17 -> 0 | K17: =G17+J17 -> 0 | L17: =K17 -> 0 | M17: =M16+K17-L17 -> 0
A18: 15 | B18: 45792 | E18: 300 | F18: 92.09 | G18: =E18*F18 -> 27627 | H18: 20 | I18: 103.86 | J18: =H18*I18 -> 2077.2 | K18: =G18+J18 -> 29704.2 | L18: =K18 -> 29704.2 | M18: =M17+K18-L18 -> 0
A19: 16 | B19: 45793 | G19: =E19*F19 -> 0 | J19: =H19*I19 -> 0 | K19: =G19+J19 -> 0 | L19: =K19 -> 0 | M19: =M18+K19-L19 -> 0
A20: 17 | B20: 45794 | G20: =E20*F20 -> 0 | J20: =H20*I20 -> 0 | K20: =G20+J20 -> 0 | L20: =K20 -> 0 | M20: =M19+K20-L20 -> 0
A21: 18 | B21: 45795 | G21: =E21*F21 -> 0 | J21: =H21*I21 -> 0 | K21: =G21+J21 -> 0 | L21: =K21 -> 0 | M21: =M20+K21-L21 -> 0
A22: 19 | B22: 45796 | E22: 200 | F22: 92.09 | G22: =E22*F22 -> 18418 | H22: 15 | I22: 103.86 | J22: =H22*I22 -> 1557.9 | K22: =G22+J22 -> 19975.9 | L22: =K22 -> 19975.9 | M22: =M21+K22-L22 -> 0
A23: 20 | B23: 45797 | G23: =E23*F23 -> 0 | J23: =H23*I23 -> 0 | K23: =G23+J23 -> 0 | L23: =K23 -> 0 | M23: =M22+K23-L23 -> 0
A24: 21 | B24: 45798 | E24: 300 | F24: 92.09 | G24: =E24*F24 -> 27627 | H24: 20 | I24: 103.86 | J24: =H24*I24 -> 2077.2 | K24: =G24+J24 -> 29704.2 | L24: =K24 -> 29704.2 | M24: =M23+K24-L24 -> 0
A25: 22 | B25: 45799 | E25: 325 | F25: 92.09 | G25: =E25*F25 -> 29929.25 | J25: =H25*I25 -> 0 | K25: =G25+J25 -> 29929.25 | L25: =K25 -> 29929.25 | M25: =M24+K25-L25 -> 0
A26: 23 | B26: 45800 | G26: =E26*F26 -> 0 | J26: =H26*I26 -> 0 | K26: =G26+J26 -> 0 | L26: =K26 -> 0 | M26: =M25+K26-L26 -> 0
A27: 24 | B27: 45801 | G27: =E27*F27 -> 0 | J27: =H27*I27 -> 0 | K27: =G27+J27 -> 0 | L27: =K27 -> 0 | M27: =M26+K27-L27 -> 0
A28: 25 | B28: 45802 | G28: =E28*F28 -> 0 | J28: =H28*I28 -> 0 | K28: =G28+J28 -> 0 | L28: =K28 -> 0 | M28: 0
A29: 26 | B29: 45803 | G29: =E29*F29 -> 0 | J29: =H29*I29 -> 0 | K29: =G29+J29 -> 0 | L29: =K29 -> 0 | M29: 0
A30: 27 | B30: 45804 | E30: 300 | F30: 92.09 | G30: =E30*F30 -> 27627 | H30: 20 | I30: 103.86 | J30: =H30*I30 -> 2077.2 | K30: =G30+J30 -> 29704.2 | L30: =K30 -> 29704.2 | M30: 0
A31: 28 | B31: 45805 | E31: 300 | F31: 92.09 | G31: =E31*F31 -> 27627 | H31: 20 | I31: 103.86 | J31: =H31*I31 -> 2077.2 | K31: =G31+J31 -> 29704.2 | L31: =K31 -> 29704.2 | M31: 0
A32: 29 | B32: 45806 | G32: =E32*F32 -> 0 | J32: =H32*I32 -> 0 | K32: =G32+J32 -> 0 | L32: =K32 -> 0
A33: 30 | B33: 45807 | G33: =E33*F33 -> 0 | J33: =H33*I33 -> 0 | K33: =G33+J33 -> 0 | L33: =K33 -> 0
A34: 31 | B34: 45808
E35: =SUM(E4:E34) -> 2970 | G35: =SUM(G4:G34) -> 273507.3 | H35: =SUM(H4:H34) -> 165 | J35: =SUM(J4:J34) -> 17136.9 | K35: =SUM(K4:K34) -> 290644.2 | L35: =SUM(L4:L34) -> 290644.2

Sheet Jalgaon
A1: Sri Sai Petrol Pump
A2: S.No | B2: Date | C2: GRN No | D2: Ind No/Bill No | E2: Diesel (Lts) | F2: Price | G2: Amount | H2: Petrol (Lts) | I2: Price | J2: Amount | K2: Total amount | L2: Amount paid | M2: As on Date | N2: Remarks
A3: Opening Balance | K3: 4528.49 | M3: =+K3 -> 4528.49
A4: 1 | B4: 45778 | E4: 74.34 | F4: 91.47 | G4: =E4*F4 -> 6799.8798 | H4: 0 | I4: 0 | J4: =H4*I4 -> 0 | K4: =G4+J4 -> 6799.8798 | L4: 0 | M4: =M3+K4-L4 -> 11328.37
A5: 2 | B5: 45779 | E5: 86.36 | F5: 91.47 | G5: =E5*F5 -> 7899.3492 | H5: 0 | I5: 0 | J5: =H5*I5 -> 0 | K5: =G5+J5 -> 7899.3492 | L5: 0 | M5: =M4+K5-L5 -> 19227.719
A6: 3 | B6: 45780 | E6: 43.95 | F6: 91.08 | G6: =E6*F6 -> 4002.966 | H6: 0 | I6: 0 | J6: =H6*I6 -> 0 | K6: =G6+J6 -> 4002.966 | L6: =+K6 -> 4002.966 | M6: =M5+K6-L6 -> 19227.719
A7: 4 | B7: 45781 | E7: 38.93 | F7: 91.47 | G7: =E7*F7 -> 3560.9271 | H7: 0 | I7: 0 | J7: =H7*I7 -> 0 | K7: =G7+J7 -> 3560.9271 | L7: 0 | M7: =M6+K7-L7 -> 22788.646
A8: 5 | B8: 45782 | E8: 0 | F8: 0 | G8: =E8*F8 -> 0 | H8: 0 | I8: 0 | J8: =H8*I8 -> 0 | K8: =G8+J8 -> 0 | L8: =+K8 -> 0 | M8: =M7+K8-L8 -> 22788.646
A9: 6 | B9: 45783 | E9: 0 | F9: 0 | G9: =E9*F9 -> 0 | H9: 0 | I9: 0 | J9: =H9*I9 -> 0 | K9: =G9+J9 -> 0 | L9: =+K9 -> 0 | M9: =M8+K9-L9 -> 22788.646
A10: 7 | B10: 45784 | E10: 43.26 | F10: 93.39 | G10: =E10*F10 -> 4040.0514 | H10: 0 | I10: 0 | J10: =H10*I10 -> 0 | K10: =G10+J10 -> 4040.0514 | L10: =+K10 -> 4040.0514 | M10: =M9+K10-L10 -> 22788.646
A11: 8 | B11: 45785 | E11: 20 | F11: 91.47 | G11: =E11*F11 -> 1829.4 | H11: 0 | I11: 0 | J11: =H11*I11 -> 0 | K11: =G11+J11 -> 1829.4 | L11: 0 | M11: =M10+K11-L11 -> 24618.046
B12: 45785 | E12: 27.46 | F12: 92.03 | G12: =E12*F12 -> 2527.1438 | K12: =G12+J12 -> 2527.1438 | L12: 2527.14 | M12: =M11+K12-L12 -> 24618.05
B13: 45785 | E13: 21.79 | F13: 91.78 | G13: =E13*F13 -> 1999.8862 | K13: =G13+J13 -> 1999.8862 | L13: 2000 | M13: =M12+K13-L13 -> 24617.936
A14: 9 | B14: 45786 | E14: 0 | F14: 0 | G14: =E14*F14 -> 0 | H14: 0 | I14: 0 | J14: =H14*I14 -> 0 | K14: =G14+J14 -> 0 | L14: =+K14 -> 0 | M14: =M13+K14-L14 -> 24617.936
A15: 10 | B15: 45787 | E15: 0 | F15: 0 | G15: =E15*F15 -> 0 | H15: 0 | I15: 0 | J15: =H15*I15 -> 0 | K15: =G15+J15 -> 0 | L15: =+K15 -> 0 | M15: =M14+K15-L15 -> 24617.936
A16: 11 | B16: 45788 | E16: 0 | F16: 0 | G16: =E16*F16 -> 0 | H16: 0 | I16: 0 | J16: =H16*I16 -> 0 | K16: =G16+J16 -> 0 | L16: =+K16 -> 0 | M16: =M15+K16-L16 -> 24617.936
A17: 12 | B17: 45789 | E17: 48.11 | F17: 91.47 | G17: =E17*F17 -> 4400.6217 | H17: 1.14 | I17: 105.5 | J17: =H17*I17 -> 120.27 | K17: =G17+J17 -> 4520.8917 | L17: 0 | M17: =M16+K17-L17 -> 29138.828
A18: 13 | B18: 45790 | E18: 44.39 | F18: 91.47 | G18: =E18*F18 -> 4060.3533 | H18: 0 | I18: 0 | J18: =H18*I18 -> 0 | K18: =G18+J18 -> 4060.3533 | L18: =+K18 -> 4060.3533 | M18: =M17+K18-L18 -> 29138.828
A19: 14 | B19: 45791 | E19: 0 | F19: 0 | G19: =E19*F19 -> 0 | H19: 0 | I19: 0 | J19: =H19*I19 -> 0 | K19: =G19+J19 -> 0 | L19: 2000 | M19: =M18+K19-L19 -> 27138.828
A20: 15 | B20: 45792 | E20: 41.5 | F20: 91.56 | G20: =E20*F20 -> 3799.74 | H20: 0 | I20: 0 | J20: =H20*I20 -> 0 | K20: =G20+J20 -> 3799.74 | L20: 31300 | M20: =M19+K20-L20 -> -361.4322
A21: 16 | B21: 45793 | E21: 0 | F21: 0 | G21: =E21*F21 -> 0 | H21: 0 | I21: 0 | J21: =H21*I21 -> 0 | K21: =G21+J21 -> 0 | L21: =+K21 -> 0 | M21: =M20+K21-L21 -> -361.4322
A22: 17 | B22: 45794 | E22: 48.65 | F22: 91.47 | G22: =E22*F22 -> 4450.0155 | H22: 12.38 | I22: 104.94 | J22: =H22*I22 -> 1299.1572 | K22: =G22+J22 -> 5749.1727 | L22: 0 | M22: =M21+K22-L22 -> 5387.7405
A23: 18 | B23: 45795 | E23: 55.72 | F23: 91.47 | G23: =E23*F23 -> 5096.7084 | H23: 0 | I23: 0 | J23: =H23*I23 -> 0 | K23: =G23+J23 -> 5096.7084 | L23: 0 | M23: =M22+K23-L23 -> 10484.449
A24: 19 | B24: 45796 | E24: 0 | F24: 0 | G24: =E24*F24 -> 0 | H24: 0 | I24: 0 | J24: =H24*I24 -> 0 | K24: =G24+J24 -> 0 | L24: =+K24 -> 0 | M24: =M23+K24-L24 -> 10484.449
A25: 20 | B25: 45797 | E25: 35.43 | F25: 91.47 | G25: =E25*F25 -> 3240.7821 | H25: 0 | I25: 0 | J25: =H25*I25 -> 0 | K25: =G25+J25 -> 3240.7821 | L25: 0 | M25: =M24+K25-L25 -> 13725.231
B26: 45797 | E26: 42.19 | F26: 91.27 | G26: =E26*F26 -> 3850.6813 | H26: 0 | I26: 0 | J26: =H26*I26 -> 0 | K26: =G26+J26 -> 3850.6813 | L26: 3850 | M26: =M25+K26-L26 -> 13725.912
A27: 21 | B27: 45798 | E27: 74.61 | F27: 91.7 | G27: =E27*F27 -> 6841.737 | H27: 0 | I27: 0 | J27: =H27*I27 -> 0 | K27: =G27+J27 -> 6841.737 | L27: =+K27 -> 6841.737 | M27: =M26+K27-L27 -> 13725.912
A28: 22 | B28: 45799 | E28: 0 | F28: 0 | G28: =E28*F28 -> 0 | H28: 0 | I28: 0 | J28: =H28*I28 -> 0 | K28: =G28+J28 -> 0 | L28: =+K28 -> 0 | M28: =M27+K28-L28 -> 13725.912
A29: 23 | B29: 45800 | E29: 0 | F29: 0 | G29: =E29*F29 -> 0 | H29: 0 | I29: 0 | J29: =H29*I29 -> 0 | K29: =G29+J29 -> 0 | L29: =+K29 -> 0 | M29: =M28+K29-L29 -> 13725.912
A30: 24 | B30: 45801 | E30: 0 | F30: 0 | G30: =E30*F30 -> 0 | H30: 0 | I30: 0 | J30: =H30*I30 -> 0 | K30: =G30+J30 -> 0 | L30: =+K30 -> 0 | M30: =M29+K30-L30 -> 13725.912
A31: 25 | B31: 45802 | E31: 0 | F31: 0 | G31: =E31*F31 -> 0 | H31: 0 | I31: 0 | J31: =H31*I31 -> 0 | K31: =G31+J31 -> 0 | L31: =+K31 -> 0 | M31: =M30+K31-L31 -> 13725.912
A32: 26 | B32: 45803 | E32: 0 | F32: 0 | G32: =E32*F32 -> 0 | H32: 0 | I32: 0 | J32: =H32*I32 -> 0 | K32: =G32+J32 -> 0 | L32: =+K32 -> 0 | M32: =M31+K32-L32 -> 13725.912
A33: 27 | B33: 45804 | E33: 0 | F33: 0 | G33: =E33*F33 -> 0 | H33: 0 | I33: 0 | J33: =H33*I33 -> 0 | K33: =G33+J33 -> 0 | L33: =+K33 -> 0 | M33: =M32+K33-L33 -> 13725.912
A34: 28 | B34: 45805 | E34: 84.18 | F34: 91.96 | G34: =E34*F34 -> 7741.1928 | H34: 0 | I34: 0 | J34: =H34*I34 -> 0 | K34: =G34+J34 -> 7741.1928 | L34: =+K34 -> 7741.1928 | M34: =M33+K34-L34 -> 13725.912
A35: 29 | B35: 45806 | E35: 25.87 | F35: 91.96 | G35: =E35*F35 -> 2379.0052 | H35: 0 | I35: 0 | J35: =H35*I35 -> 0 | K35: =G35+J35 -> 2379.0052 | L35: =+K35 -> 2379.0052 | M35: =M34+K35-L35 -> 13725.912
A36: 30 | B36: 45807 | E36: 0 | F36: 0 | G36: =E36*F36 -> 0 | H36: 0 | I36: 0 | J36: =H36*I36 -> 0 | K36: =G36+J36 -> 0 | L36: =+K36 -> 0 | M36: =M35+K36-L36 -> 13725.912
A37: 31 | B37: 45808 | E37: 0 | F37: 0 | G37: =E37*F37 -> 0 | H37: 0 | I37: 0 | J37: =H37*I37 -> 0 | K37: =G37+J37 -> 0 | L37: =+K37 -> 0 | M37: =M36+K37-L37 -> 13725.912
A38: 32 | E38: 0 | F38: 0 | G38: =E38*F38 -> 0 | H38: 0 | I38: 0 | J38: =H38*I38 -> 0 | K38: =G38+J38 -> 0 | L38: =+K38 -> 0 | M38: =M37+K38-L38 -> 13725.912
E39: =SUM(E4:E38) -> 856.74 | G39: =SUM(G4:G38) -> 78520.441 | H39: =SUM(H4:H38) -> 13.52 | J39: =SUM(J4:J38) -> 1419.4272 | K39: =SUM(K4:K38) -> 79939.868 | L39: =SUM(L4:L38) -> 70742.446

Sheet MKBD
A1: Shree Sai Samarth Petroleum
A2: S.No | B2: Date | C2: GRN No | D2: Ind No/Bill No | E2: Diesel (Lts) | F2: Price | G2: Amount | H2: Petrol (Lts) | I2: Price | J2: Amount | K2: Total amount | L2: Amount paid | M2: As on Date | N2: Remarks
A3: Opening Balance | K3: 1670481.7 | M3: 1670481.7
A4: 1 | B4: 45778 | C4: 0 | E4: 0 | F4: 0 | G4: =E4*F4 -> 0 | H4: 0 | I4: 0 | J4: =H4*I4 -> 0 | K4: =G4+J4 -> 0 | M4: =M3+K4-L4 -> 1670481.7
A5: 2 | B5: 45779 | C5: 801 | E5: 3000 | F5: 91.14 | G5: =E5*F5 -> 273420 | H5: 0 | I5: 0 | J5: =H5*I5 -> 0 | K5: =G5+J5 -> 273420 | M5: =M4+K5-L5 -> 1943901.7
A6: 3 | B6: 45780 | C6: 0 | E6: 0 | F6: 0 | G6: =E6*F6 -> 0 | H6: 0 | I6: 0 | J6: =H6*I6 -> 0 | K6: =G6+J6 -> 0 | M6: =M5+K6-L6 -> 1943901.7
A7: 4 | B7: 45781 | C7: 0 | E7: 0 | F7: 0 | G7: =E7*F7 -> 0 | H7: 0 | I7: 0 | J7: =H7*I7 -> 0 | K7: =G7+J7 -> 0 | M7: =M6+K7-L7 -> 1943901.7
A8: 5 | B8: 45782 | C8: 0 | E8: 0 | F8: 0 | G8: =E8*F8 -> 0 | H8: 0 | I8: 0 | J8: =H8*I8 -> 0 | K8: =G8+J8 -> 0 | M8: =M7+K8-L8 -> 1943901.7
A9: 6 | B9: 45783 | C9: 805 | E9: 2000 | F9: 91.14 | G9: =E9*F9 -> 182280 | H9: 0 | I9: 0 | J9: =H9*I9 -> 0 | K9: =G9+J9 -> 182280 | M9: =M8+K9-L9 -> 2126181.7
A10: 7 | B10: 45784 | C10: 0 | E10: 3000 | F10: 91.14 | G10: =E10*F10 -> 273420 | H10: 0 | I10: 0 | J10: =H10*I10 -> 0 | K10: =G10+J10 -> 273420 | M10: =M9+K10-L10 -> 2399601.7
A11: 8 | B11: 45785 | C11: 0 | E11: 0 | F11: 0 | G11: =E11*F11 -> 0 | H11: 0 | J11: =H11*I11 -> 0 | K11: =G11+J11 -> 0 | M11: =M10+K11-L11 -> 2399601.7
A12: 9 | B12: 45786 | C12: 0 | E12: 0 | F12: 0 | G12: =E12*F12 -> 0 | H12: 20 | I12: 104.6 | J12: =H12*I12 -> 2092 | K12: =G12+J12 -> 2092 | M12: =M11+K12-L12 -> 2401693.7
A13: 10 | B13: 45787 | C13: 0 | E13: 0 | F13: 0 | G13: =E13*F13 -> 0 | H13: 0 | I13: 0 | J13: =H13*I13 -> 0 | K13: =G13+J13 -> 0 | M13: =M12+K13-L13 -> 2401693.7
A14: 11 | B14: 45788 | C14: 0 | E14: 4000 | F14: 91.14 | G14: =E14*F14 -> 364560 | H14: 0 | I14: 0 | J14: =H14*I14 -> 0 | K14: =G14+J14 -> 364560 | M14: =M13+K14-L14 -> 2766253.7
A15: 12 | B15: 45789 | C15: 0 | E15: 0 | F15: 0 | G15: =E15*F15 -> 0 | H15: 0 | I15: 0 | J15: =H15*I15 -> 0 | K15: =G15+J15 -> 0 | M15: =M14+K15-L15 -> 2766253.7
A16: 13 | B16: 45790 | C16: 0 | E16: 1750 | F16: 91.14 | G16: =E16*F16 -> 159495 | H16: 0 | I16: 0 | J16: =H16*I16 -> 0 | K16: =G16+J16 -> 159495 | M16: =M15+K16-L16 -> 2925748.7
A17: 14 | B17: 45791 | C17: 0 | E17: 3000 | F17: 91.14 | G17: =E17*F17 -> 273420 | H17: 0 | I17: 0 | J17: =H17*I17 -> 0 | K17: =G17+J17 -> 273420 | M17: =M16+K17-L17 -> 3199168.7
A18: 15 | B18: 45792 | C18: 0 | E18: 0 | F18: 0 | G18: =E18*F18 -> 0 | H18: 0 | I18: 0 | J18: =H18*I18 -> 0 | K18: =G18+J18 -> 0 | M18: =M17+K18-L18 -> 3199168.7
A19: 16 | B19: 45793 | C19: 0 | E19: 0 | F19: 0 | G19: =E19*F19 -> 0 | H19: 0 | I19: 0 | J19: =H19*I19 -> 0 | K19: =G19+J19 -> 0 | M19: =M18+K19-L19 -> 3199168.7
A20: 17 | B20: 45794 | C20: 0 | E20: 1000 | F20: 91.14 | G20: =E20*F20 -> 91140 | H20: 20 | I20: 104.6 | J20: =H20*I20 -> 2092 | K20: =G20+J20 -> 93232 | L20: 2000000 | M20: =M19+K20-L20 -> 1292400.7
A21: 18 | B21: 45795 | C21: 0 | E21: 2000 | F21: 91.14 | G21: =E21*F21 -> 182280 | H21: 35 | I21: 104.6 | J21: =H21*I21 -> 3661 | K21: =G21+J21 -> 185941 | M21: =M20+K21-L21 -> 1478341.7
A22: 19 | B22: 45796 | C22: 0 | E22: 1000 | F22: 91.14 | G22: =E22*F22 -> 91140 | H22: 0 | I22: 0 | J22: =H22*I22 -> 0 | K22: =G22+J22 -> 91140 | M22: =M21+K22-L22 -> 1569481.7
A23: 20 | B23: 45797 | C23: 0 | E23: 3000 | F23: 91.14 | G23: =E23*F23 -> 273420 | H23: 0 | I23: 0 | J23: =H23*I23 -> 0 | K23: =G23+J23 -> 273420 | M23: =M22+K23-L23 -> 1842901.7
A24: 21 | B24: 45798 | C24: 0 | E24: 1700 | F24: 91.14 | G24: =E24*F24 -> 154938 | H24: 0 | I24: 0 | J24: =H24*I24 -> 0 | K24: =G24+J24 -> 154938 | M24: =M23+K24-L24 -> 1997839.7
A25: 22 | B25: 45799 | C25: 0 | E25: 4000 | F25: 91.14 | G25: =E25*F25 -> 364560 | H25: 0 | I25: 0 | J25: =H25*I25 -> 0 | K25: =G25+J25 -> 364560 | M25: =M24+K25-L25 -> 2362399.7
A26: 23 | B26: 45800 | C26: 0 | E26: 0 | F26: 0 | G26: =E26*F26 -> 0 | H26: 0 | I26: 0 | J26: =H26*I26 -> 0 | K26: =G26+J26 -> 0 | M26: =M25+K26-L26 -> 2362399.7
A27: 24 | B27: 45801 | C27: 0 | E27: 0 | F27: 0 | G27: =E27*F27 -> 0 | H27: 0 | I27: 0 | J27: =H27*I27 -> 0 | K27: =G27+J27 -> 0 | M27: =M26+K27-L27 -> 2362399.7
A28: 25 | B28: 45802 | C28: 0 | E28: 0 | F28: 0 | G28: =E28*F28 -> 0 | H28: 0 | I28: 0 | J28: =H28*I28 -> 0 | K28: =G28+J28 -> 0 | M28: =M27+K28-L28 -> 2362399.7
A29: 26 | B29: 45803 | C29: 0 | E29: 0 | F29: 0 | G29: =E29*F29 -> 0 | H29: 0 | I29: 0 | J29: =H29*I29 -> 0 | K29: =G29+J29 -> 0 | M29: =M28+K29-L29 -> 2362399.7
A30: 27 | B30: 45804 | C30: 0 | E30: 0 | F30: 0 | G30: =E30*F30 -> 0 | H30: 0 | I30: 0 | J30: =H30*I30 -> 0 | K30: =G30+J30 -> 0 | M30: =M29+K30-L30 -> 2362399.7
A31: 28 | B31: 45805 | C31: 0 | E31: 3000 | F31: 91.14 | G31: =E31*F31 -> 273420 | H31: 0 | I31: 0 | J31: =H31*I31 -> 0 | K31: =G31+J31 -> 273420 | L31: 2360449 | M31: =M30+K31-L31 -> 275370.67
B32: 45805 | E32: 16.54 | F32: 90.68 | G32: =E32*F32 -> 1499.8472 | K32: =G32+J32 -> 1499.8472 | L32: 1499.85 | M32: =M31+K32-L32 -> 275370.67
A33: 29 | B33: 45806 | C33: 0 | E33: 1900 | F33: 91.14 | G33: =E33*F33 -> 173166 | H33: 20 | I33: 104.6 | J33: =H33*I33 -> 2092 | K33: =G33+J33 -> 175258 | M33: =M32+K33-L33 -> 450628.67
A34: 30 | B34: 45807 | C34: 0 | E34: 0 | F34: 0 | G34: =E34*F34 -> 0 | H34: 0 | I34: 0 | J34: =H34*I34 -> 0 | K34: =G34+J34 -> 0 | M34: =M33+K34-L34 -> 450628.67
A35: 31 | B35: 45808 | M35: =M34+K35-L35 -> 450628.67
E36: =SUM(E4:E35) -> 34366.54 | G36: =SUM(G4:G35) -> 3132158.8 | H36: =SUM(H4:H35) -> 95 | J36: =SUM(J4:J35) -> 9937 | K36: =SUM(K4:K35) -> 3142095.8 | L36: =SUM(L4:L35) -> 4361948.8

Sheet Haveri
A1: Shivalingeshwar Petroleum
A2: S.No | B2: Date | C2: GRN No | D2: Ind No/Bill No | E2: Diesel (Lts) | F2: Price | G2: Amount | H2: Petrol (Lts) | I2: Price | J2: Amount | K2: Total amount | L2: Amount paid | M2: As on Date | N2: Remarks
D3: Opening Balance | K3: 0 | L3: 0 | M3: 90058
A4: 1 | B4: 45778 | E4: 0 | F4: 91.47 | G4: =E4*F4 -> 0 | H4: 0 | I4: 103.43 | J4: =H4*I4 -> 0 | K4: =G4+J4 -> 0 | L4: 0 | M4: =M3+K4-L4 -> 90058
A5: 2 | B5: 45779 | E5: 217 | F5: 91.47 | G5: =E5*F5 -> 19848.99 | H5: 18 | I5: 103.43 | J5: =H5*I5 -> 1861.74 | K5: =G5+J5 -> 21710.73 | L5: 0 | M5: =M4+K5-L5 -> 111768.73
A6: 3 | B6: 45780 | E6: 0 | F6: 0 | G6: =E6*F6 -> 0 | H6: 0 | I6: 103.43 | J6: =H6*I6 -> 0 | K6: =G6+J6 -> 0 | L6: 0 | M6: =M5+K6-L6 -> 111768.73
A7: 4 | B7: 45781 | E7: 40 | F7: 91.47 | G7: =E7*F7 -> 3658.8 | H7: 0 | I7: 103.43 | J7: =H7*I7 -> 0 | K7: =G7+J7 -> 3658.8 | L7: 0 | M7: =M6+K7-L7 -> 115427.53
A8: 5 | B8: 45782 | E8: 0 | F8: 0 | G8: =E8*F8 -> 0 | H8: 0 | I8: 103.43 | J8: =H8*I8 -> 0 | K8: =G8+J8 -> 0 | L8: 0 | M8: =M7+K8-L8 -> 115427.53
A9: 6 | B9: 45783 | E9: 0 | F9: 0 | G9: =E9*F9 -> 0 | H9: 0 | I9: 103.43 | J9: =H9*I9 -> 0 | K9: =G9+J9 -> 0 | L9: 0 | M9: =M8+K9-L9 -> 115427.53
A10: 7 | B10: 45784 | E10: 0 | F10: 0 | G10: =E10*F10 -> 0 | H10: 0 | I10: 103.43 | J10: =H10*I10 -> 0 | K10: =G10+J10 -> 0 | L10: 0 | M10: =M9+K10-L10 -> 115427.53
A11: 8 | B11: 45785 | E11: 0 | F11: 0 | G11: =E11*F11 -> 0 | H11: 0 | I11: 103.43 | J11: =H11*I11 -> 0 | K11: =G11+J11 -> 0 | L11: 115444 | M11: =M10+K11-L11 -> -16.47
A12: 9 | B12: 45786 | E12: 40.01 | F12: 91.47 | G12: =E12*F12 -> 3659.7147 | H12: 6 | I12: 103.43 | J12: =H12*I12 -> 620.58 | K12: =G12+J12 -> 4280.2947 | L12: 0 | M12: =M11+K12-L12 -> 4263.8247 | O12: .
A13: 10 | B13: 45787 | E13: 49 | F13: 91.47 | G13: =E13*F13 -> 4482.03 | H13: 0 | I13: 0 | J13: =H13*I13 -> 0 | K13: =G13+J13 -> 4482.03 | L13: 0 | M13: =M12+K13-L13 -> 8745.8547
A14: 11 | B14: 45788 | E14: 35 | F14: 91.47 | G14: =E14*F14 -> 3201.45 | H14: 6 | I14: 103.43 | J14: =H14*I14 -> 620.58 | K14: =G14+J14 -> 3822.03 | L14: 0 | M14: =M13+K14-L14 -> 12567.885
A15: 12 | B15: 45789 | E15: 0 | F15: 0 | G15: =E15*F15 -> 0 | H15: 0 | I15: 0 | J15: =H15*I15 -> 0 | K15: =G15+J15 -> 0 | L15: 0 | M15: =M14+K15-L15 -> 12567.885
A16: 13 | B16: 45790 | E16: 150 | F16: 91.47 | G16: =E16*F16 -> 13720.5 | H16: 0 | I16: 0 | J16: =H16*I16 -> 0 | K16: =G16+J16 -> 13720.5 | L16: 0 | M16: =M15+K16-L16 -> 26288.385
A17: 14 | B17: 45791 | E17: 60 | F17: 91.47 | G17: =E17*F17 -> 5488.2 | H17: 10 | I17: 103.43 | J17: =H17*I17 -> 1034.3 | K17: =G17+J17 -> 6522.5 | L17: 0 | M17: =M16+K17-L17 -> 32810.885
A18: 15 | B18: 45792 | E18: 20 | F18: 91.47 | G18: =E18*F18 -> 1829.4 | H18: 5 | I18: 103.43 | J18: =H18*I18 -> 517.15 | K18: =G18+J18 -> 2346.55 | L18: 0 | M18: =M17+K18-L18 -> 35157.435
A19: 16 | B19: 45793 | E19: 200 | F19: 91.47 | G19: =E19*F19 -> 18294 | H19: 0 | I19: 0 | J19: =H19*I19 -> 0 | K19: =G19+J19 -> 18294 | L19: 0 | M19: =M18+K19-L19 -> 53451.435
A20: 17 | B20: 45794 | E20: 44.03 | F20: 91.47 | G20: =E20*F20 -> 4027.4241 | H20: 6 | I20: 103.43 | J20: =H20*I20 -> 620.58 | K20: =G20+J20 -> 4648.0041 | L20: 0 | M20: =M19+K20-L20 -> 58099.439
A21: 18 | B21: 45795 | E21: 49.41 | F21: 91.47 | G21: =E21*F21 -> 4519.5327 | H21: 0 | I21: 0 | J21: =H21*I21 -> 0 | K21: =G21+J21 -> 4519.5327 | L21: 0 | M21: =M20+K21-L21 -> 62618.971
A22: 19 | B22: 45796 | E22: 0 | F22: 0 | G22: =E22*F22 -> 0 | H22: 0 | I22: 0 | J22: =H22*I22 -> 0 | K22: =G22+J22 -> 0 | L22: 0 | M22: =M21+K22-L22 -> 62618.971
A23: 20 | B23: 45797 | E23: 0 | F23: 0 | G23: =E23*F23 -> 0 | H23: 0 | I23: 0 | J23: =H23*I23 -> 0 | K23: =G23+J23 -> 0 | L23: 0 | M23: =M22+K23-L23 -> 62618.971
A24: 21 | B24: 45798 | E24: 40.01 | F24: 91.47 | G24: =E24*F24 -> 3659.7147 | H24: 12.01 | I24: 103.43 | J24: =H24*I24 -> 1242.1943 | K24: =G24+J24 -> 4901.909 | L24: 0 | M24: =M23+K24-L24 -> 67520.88
... A32: 29 | B32: 45806 | E32: 87.67 | F32: 91.47 | G32: =E32*F32 -> 8019.1749 | H32: 0 | I32: 0 | J32: =H32*I32 -> 0 | K32: =G32+J32 -> 8019.1749 | L32: 0 | M32: =M31+K32-L32 -> 27337.525
A33: 30 | B33: 45807 | E33: 85 | F33: 91.47 | G33: =E33*F33 -> 7774.95 | H33: 0 | I33: 0 | J33: =H33*I33 -> 0 | K33: =G33+J33 -> 7774.95 | L33: 0 | M33: =M32+K33-L33 -> 35112.475 | Q33: =35000-8000 -> 27000
A34: 31 | B34: 45808 | E34: 0 | F34: 0 | G34: =E34*F34 -> 0 | H34: 11.67 | I34: 103.4 | J34: =H34*I34 -> 1206.678 | K34: =G34+J34 -> 1206.678 | L34: 0 | M34: =M33+K34-L34 -> 36319.153
E35: =SUM(E4:E34) -> 1327.13 | G35: =SUM(G4:G34) -> 121392.58 | H35: =SUM(H4:H34) -> 74.68 | J35: =SUM(J4:J34) -> 7723.8023 | K35: =SUM(K4:K34) -> 129116.38 | L35: =SUM(L4:L34) -> 182855.23
I38: =K24+L24 -> 4901.909

Sheet Guttal
A1: Taware filling station
A2: S.No | B2: Date | C2: GRN No | D2: Ind No/Bill No | E2: Diesel (Lts) | F2: Price | G2: Amount | H2: Petrol (Lts) | I2: Price | J2: Amount | K2: Total amount | L2: Amount paid | M2: As on Date | N2: Remarks
D3: Opening Balance | K3: 0 | L3: 0 | M3: =+K3 -> 0
A4: 1 | B4: 45778 | E4: 0 | F4: 0 | G4: =E4*F4 -> 0 | H4: 0 | I4: 0 | J4: =H4*I4 -> 0 | K4: =G4+J4 -> 0 | L4: 0 | M4: =M3+K4-L4 -> 0
A5: 2 | B5: 45779 | E5: 120 | F5: 91.8 | G5: =E5*F5 -> 11016 | H5: 0 | I5: 0 | J5: =H5*I5 -> 0 | K5: =G5+J5 -> 11016 | L5: 11016 | M5: =M4+K5-L5 -> 0
A6: 3 | B6: 45780 | E6: 100 | F6: 91.8 | G6: =E6*F6 -> 9180 | H6: 0 | I6: 0 | J6: =H6*I6 -> 0 | K6: =G6+J6 -> 9180 | L6: 9180 | M6: =M5+K6-L6 -> 0
A7: 4 | B7: 45781 | E7: 0 | F7: 0 | G7: =E7*F7 -> 0 | H7: 5 | I7: 103.76 | J7: =H7*I7 -> 518.8 | K7: =G7+J7 -> 518.8 | L7: 518.8 | M7: =M6+K7-L7 -> 0
A8: 5 | B8: 45782 | E8: 110 | F8: 91.8 | G8: =E8*F8 -> 10098 | H8: 0 | I8: 0 | J8: =H8*I8 -> 0 | K8: =G8+J8 -> 10098 | L8: 10098 | M8: =M7+K8-L8 -> 0
A9: 6 | B9: 45783 | E9: 0 | F9: 0 | G9: =E9*F9 -> 0 | H9: 0 | I9: 0 | J9: =H9*I9 -> 0 | K9: =G9+J9 -> 0 | L9: 0 | M9: =M8+K9-L9 -> 0
A10: 7 | B10: 45784 | E10: 0 | F10: 0 | G10: =E10*F10 -> 0 | H10: 0 | I10: 0 | J10: =H10*I10 -> 0 | K10: =G10+J10 -> 0 | L10: 0 | M10: =M9+K10-L10 -> 0
A11: 8 | B11: 45785 | E11: 90 | F11: 91.8 | G11: =E11*F11 -> 8262 | H11: 0 | I11: 0 | J11: =H11*I11 -> 0 | K11: =G11+J11 -> 8262 | L11: 8262 | M11: =M10+K11-L11 -> 0
A12: 9 | B12: 45786 | E12: 85 | F12: 91.8 | G12: =E12*F12 -> 7803 | H12: 15 | I12: 103.76 | J12: =H12*I12 -> 1556.4 | K12: =G12+J12 -> 9359.4 | L12: 9359.4 | M12: =M11+K12-L12 -> 0 | O12: .
A13: 10 | B13: 45787 | E13: 70 | F13: 91.8 | G13: =E13*F13 -> 6426 | H13: 0 | I13: 0 | J13: =H13*I13 -> 0 | K13: =G13+J13 -> 6426 | L13: 6426 | M13: =M12+K13-L13 -> 0
A14: 11 | B14: 45788 | E14: 0 | F14: 0 | G14: =E14*F14 -> 0 | H14: 0 | I14: 0 | J14: =H14*I14 -> 0 | K14: =G14+J14 -> 0 | L14: 0 | M14: =M13+K14-L14 -> 0
A15: 12 | B15: 45789 | E15: 80 | F15: 91.8 | G15: =E15*F15 -> 7344 | H15: 0 | I15: 0 | J15: =H15*I15 -> 0 | K15: =G15+J15 -> 7344 | L15: 7344 | M15: =M14+K15-L15 -> 0
A16: 13 | B16: 45790 | E16: 40 | F16: 91.8 | G16: =E16*F16 -> 3672 | H16: 5 | I16: 103.76 | J16: =H16*I16 -> 518.8 | K16: =G16+J16 -> 4190.8 | L16: 4190.8 | M16: =M15+K16-L16 -> 0
A17: 14 | B17: 45791 | E17: 30 | F17: 91.8 | G17: =E17*F17 -> 2754 | H17: 5 | I17: 103.76 | J17: =H17*I17 -> 518.8 | K17: =G17+J17 -> 3272.8 | L17: 3272.8 | M17: =M16+K17-L17 -> 0
A18: 15 | B18: 45792 | E18: 45 | F18: 91.8 | G18: =E18*F18 -> 4131 | H18: 0 | I18: 0 | J18: =H18*I18 -> 0 | K18: =G18+J18 -> 4131 | L18: 4131 | M18: =M17+K18-L18 -> 0
A19: 16 | B19: 45793 | E19: 70 | F19: 91.8 | G19: =E19*F19 -> 6426 | H19: 5 | I19: 103.76 | J19: =H19*I19 -> 518.8 | K19: =G19+J19 -> 6944.8 | L19: 6944.8 | M19: =M18+K19-L19 -> 0
A20: 17 | B20: 45794 | E20: 65.89 | F20: 91.8 | G20: =E20*F20 -> 6048.702 | H20: 5 | I20: 103.76 | J20: =H20*I20 -> 518.8 | K20: =G20+J20 -> 6567.502 | L20: 6567.5 | M20: =M19+K20-L20 -> 0.002
A21: 18 | B21: 45795 | E21: 0 | F21: 0 | G21: =E21*F21 -> 0 | H21: 0 | I21: 0 | J21: =H21*I21 -> 0 | K21: =G21+J21 -> 0 | L21: 0 | M21: =M20+K21-L21 -> 0.002
A22: 19 | B22: 45796 | E22: 0 | F22: 0 | G22: =E22*F22 -> 0 | H22: 0 | I22: 0 | J22: =H22*I22 -> 0 | K22: =G22+J22 -> 0 | L22: 0 | M22: =M21+K22-L22 -> 0.002
A23: 20 | B23: 45797 | E23: 30 | F23: 91.8 | G23: =E23*F23 -> 2754 | H23: 0 | I23: 0 | J23: =H23*I23 -> 0 | K23: =G23+J23 -> 2754 | L23: 2754 | M23: =M22+K23-L23 -> 0.002
A24: 21 | B24: 45798 | E24: 0 | F24: 0 | G24: =E24*F24 -> 0 | H24: 0 | I24: 0 | J24: =H24*I24 -> 0 | K24: =G24+J24 -> 0 | L24: 0 | M24: =M23+K24-L24 -> 0.002
... A28: 25 | B28: 45802 | E28: 0 | F28: 0 | G28: =E28*F28 -> 0 | H28: 0 | I28: 0 | J28: =H28*I28 -> 0 | K28: =G28+J28 -> 0 | L28: 0 | M28: =M27+K28-L28 -> 0.002
A29: 26 | B29: 45803 | E29: 30 | F29: 91.8 | G29: =E29*F29 -> 2754 | H29: 0 | I29: 0 | J29: =H29*I29 -> 0 | K29: =G29+J29 -> 2754 | L29: =H29+K29 -> 2754 | M29: =M28+K29-L29 -> 0.002
A30: 27 | B30: 45804 | E30: 10 | F30: 91.8 | G30: =E30*F30 -> 918 | H30: 5 | I30: 103.76 | J30: =H30*I30 -> 518.8 | K30: =G30+J30 -> 1436.8 | L30: 1436.8 | M30: =M29+K30-L30 -> 0.002
A31: 28 | B31: 45805 | E31: 74.9 | F31: 91.8 | G31: =E31*F31 -> 6875.82 | H31: 0 | I31: 0 | J31: =H31*I31 -> 0 | K31: =G31+J31 -> 6875.82 | L31: 6875.82 | M31: =M30+K31-L31 -> 0.002
A32: 29 | B32: 45806 | E32: 110 | F32: 91.8 | G32: =E32*F32 -> 10098 | H32: 4 | I32: 103.76 | J32: =H32*I32 -> 415.04 | K32: =G32+J32 -> 10513.04 | L32: 10513.04 | M32: =M31+K32-L32 -> 0.002
A33: 30 | B33: 45807 | E33: 0 | F33: 0 | G33: =E33*F33 -> 0 | H33: 0 | I33: 0 | J33: =H33*I33 -> 0 | K33: =G33+J33 -> 0 | L33: 0 | M33: =M32+K33-L33 -> 0.002
A34: 31 | B34: 45808 | E34: 85 | F34: 91.8 | G34: =E34*F34 -> 7803 | H34: 10 | I34: 103.76 | J34: =H34*I34 -> 1037.6 | K34: =G34+J34 -> 8840.6 | L34: =+K34 -> 8840.6
E35: =SUM(E4:E34) -> 1295.79 | G35: =SUM(G4:G34) -> 118953.52 | H35: =SUM(H4:H34) -> 67 | J35: =SUM(J4:J34) -> 6951.92 | K35: =SUM(K4:K34) -> 125905.44 | L35: =SUM(L4:L34) -> 125905.44
I38: =K24+L24 -> 0

Sheet Rattihali
A1: Shree Siri Gowari petroliam
A2: S.No | B2: Date | C2: GRN No | D2: Ind No/Bill No | E2: Diesel (Lts) | F2: Price | G2: Amount | H2: Petrol (Lts) | I2: Price | J2: Amount | K2: Total amount | L2: Amount paid | M2: As on Date | N2: Remarks
D3: Opening Balance | K3: 0 | L3: 0 | M3: =+K3 -> 0
A4: 1 | B4: 45778 | E4: 27.57 | F4: 92.04 | G4: =E4*F4 -> 2537.5428 | H4: 10 | I4: 104.02 | J4: =H4*I4 -> 1040.2 | K4: =G4+J4 -> 3577.7428 | L4: =+K4 -> 3577.7428 | M4: =M3+K4-L4 -> 0
A5: 2 | B5: 45779 | E5: 0 | F5: 0 | G5: =E5*F5 -> 0 | H5: 0 | I5: 0 | J5: =H5*I5 -> 0 | K5: =G5+J5 -> 0 | L5: =+K5 -> 0 | M5: =M4+K5-L5 -> 0
A6: 3 | B6: 45780 | E6: 0 | F6: 0 | G6: =E6*F6 -> 0 | H6: 0 | I6: 0 | J6: =H6*I6 -> 0 | K6: =G6+J6 -> 0 | L6: =+K6 -> 0 | M6: =M5+K6-L6 -> 0
A7: 4 | B7: 45781 | E7: 0 | F7: 0 | G7: =E7*F7 -> 0 | H7: 0 | I7: 0 | J7: =H7*I7 -> 0 | K7: =G7+J7 -> 0 | L7: =+K7 -> 0 | M7: =M6+K7-L7 -> 0
A8: 5 | B8: 45782 | E8: 0 | F8: 0 | G8: =E8*F8 -> 0 | H8: 0 | I8: 0 | J8: =H8*I8 -> 0 | K8: =G8+J8 -> 0 | L8: =+K8 -> 0 | M8: =M7+K8-L8 -> 0
A9: 6 | B9: 45783 | E9: 0 | F9: 0 | G9: =E9*F9 -> 0 | H9: 0 | I9: 0 | J9: =H9*I9 -> 0 | K9: =G9+J9 -> 0 | L9: =+K9 -> 0 | M9: =M8+K9-L9 -> 0
A10: 7 | B10: 45784 | E10: 60 | F10: 92.04 | G10: =E10*F10 -> 5522.4 | H10: 15 | I10: 104.02 | J10: =H10*I10 -> 1560.3 | K10: =G10+J10 -> 7082.7 | L10: =+K10 -> 7082.7 | M10: =M9+K10-L10 -> 0
A11: 8 | B11: 45785 | E11: 0 | F11: 0 | G11: =E11*F11 -> 0 | H11: 0 | I11: 0 | J11: =H11*I11 -> 0 | K11: =G11+J11 -> 0 | L11: =+K11 -> 0 | M11: =M10+K11-L11 -> 0
A12: 9 | B12: 45786 | E12: 70 | F12: 92.04 | G12: =E12*F12 -> 6442.8 | H12: 0 | I12: 0 | J12: =H12*I12 -> 0 | K12: =G12+J12 -> 6442.8 | L12: =+K12 -> 6442.8 | M12: =M11+K12-L12 -> 0 | O12: .
A13: 10 | B13: 45787 | E13: 0 | F13: 0 | G13: =E13*F13 -> 0 | H13: 0 | I13: 0 | J13: =H13*I13 -> 0 | K13: =G13+J13 -> 0 | L13: =+K13 -> 0 | M13: =M12+K13-L13 -> 0
A14: 11 | B14: 45788 | E14: 0 | F14: 92.04 | G14: =E14*F14 -> 0 | H14: 0 | I14: 0 | J14: =H14*I14 -> 0 | K14: =G14+J14 -> 0 | L14: =+K14 -> 0 | M14: =M13+K14-L14 -> 0
A15: 12 | B15: 45789 | E15: 100 | F15: 92.04 | G15: =E15*F15 -> 9204 | H15: 0 | I15: 0 | J15: =H15*I15 -> 0 | K15: =G15+J15 -> 9204 | L15: =+K15 -> 9204 | M15: =M14+K15-L15 -> 0
A16: 13 | B16: 45790 | E16: 100 | F16: 92.04 | G16: =E16*F16 -> 9204 | H16: 0 | I16: 0 | J16: =H16*I16 -> 0 | K16: =G16+J16 -> 9204 | L16: =+K16 -> 9204 | M16: =M15+K16-L16 -> 0
A17: 14 | B17: 45791 | E17: 170 | F17: 92.04 | G17: =E17*F17 -> 15646.8 | H17: 5 | I17: 104.02 | J17: =H17*I17 -> 520.1 | K17: =G17+J17 -> 16166.9 | L17: =+K17 -> 16166.9 | M17: =M16+K17-L17 -> 0
A18: 15 | B18: 45792 | E18: 145 | F18: 92.04 | G18: =E18*F18 -> 13345.8 | H18: 0 | I18: 0 | J18: =H18*I18 -> 0 | K18: =G18+J18 -> 13345.8 | L18: =+K18 -> 13345.8 | M18: =M17+K18-L18 -> 0
A19: 16 | B19: 45793 | E19: 75 | F19: 92.04 | G19: =E19*F19 -> 6903 | H19: 0 | I19: 0 | J19: =H19*I19 -> 0 | K19: =G19+J19 -> 6903 | L19: =+K19 -> 6903 | M19: =M18+K19-L19 -> 0
A20: 17 | B20: 45794 | E20: 75 | F20: 92.04 | G20: =E20*F20 -> 6903 | H20: 5 | I20: 104.02 | J20: =H20*I20 -> 520.1 | K20: =G20+J20 -> 7423.1 | L20: =+K20 -> 7423.1 | M20: =M19+K20-L20 -> 0
A21: 18 | B21: 45795 | E21: 0 | F21: 0 | G21: =E21*F21 -> 0 | H21: 0 | I21: 0 | J21: =H21*I21 -> 0 | K21: =G21+J21 -> 0 | L21: =+K21 -> 0 | M21: =M20+K21-L21 -> 0
A22: 19 | B22: 45796 | E22: 70 | F22: 92.04 | G22: =E22*F22 -> 6442.8 | H22: 10 | I22: 104.02 | J22: =H22*I22 -> 1040.2 | K22: =G22+J22 -> 7483 | L22: =+K22 -> 7483 | M22: =M21+K22-L22 -> 0
A23: 20 | B23: 45797 | E23: 105 | F23: 92.04 | G23: =E23*F23 -> 9664.2 | H23: 0 | I23: 0 | J23: =H23*I23 -> 0 | K23: =G23+J23 -> 9664.2 | L23: 0 | M23: =M22+K23-L23 -> 9664.2
A24: 21 | B24: 45798 | E24: 35 | F24: 92.04 | G24: =E24*F24 -> 3221.4 | H24: 0 | I24: 0 | J24: =H24*I24 -> 0 | K24: =G24+J24 -> 3221.4 | L24: 12885.6 | M24: =M23+K24-L24 -> 0
A25: 22 | B25: 45799 | E25: 70 | F25: 92.04 | G25: =E25*F25 -> 6442.8 | H25: 0 | I25: 0 | J25: =H25*I25 -> 0 | K25: =G25+J25 -> 6442.8 | L25: =+K25 -> 6442.8 | M25: =M24+K25-L25 -> 0
A26: 23 | B26: 45800 | E26: 70 | F26: 92.04 | G26: =E26*F26 -> 6442.8 | H26: 0 | I26: 0 | J26: =H26*I26 -> 0 | K26: =G26+J26 -> 6442.8 | L26: =+K26 -> 6442.8 | M26: =M25+K26-L26 -> 0
A27: 24 | B27: 45801 | E27: 0 | F27: 0 | G27: =E27*F27 -> 0 | H27: 0 | I27: 0 | J27: =H27*I27 -> 0 | K27: =G27+J27 -> 0 | L27: =+K27 -> 0 | M27: =M26+K27-L27 -> 0
A28: 25 | B28: 45802 | E28: 0 | F28: 0 | G28: =E28*F28 -> 0 | H28: 0 | I28: 0 | J28: =H28*I28 -> 0 | K28: =G28+J28 -> 0 | L28: =+K28 -> 0 | M28: =M27+K28-L28 -> 0
A29: 26 | B29: 45803 | E29: 68.85 | F29: 92.04 | G29: =E29*F29 -> 6336.954 | H29: 0 | I29: 0 | J29: =H29*I29 -> 0 | K29: =G29+J29 -> 6336.954 | L29: =+K29 -> 6336.954 | M29: =M28+K29-L29 -> 0
A30: 27 | B30: 45804 | E30: 70 | F30: 92.04 | G30: =E30*F30 -> 6442.8 | H30: 5 | I30: 104.2 | J30: =H30*I30 -> 521 | K30: =G30+J30 -> 6963.8 | L30: =+K30 -> 6963.8 | M30: =M29+K30-L30 -> 0
A31: 28 | B31: 45805 | E31: 35 | F31: 92.04 | G31: =E31*F31 -> 3221.4 | H31: 5 | I31: 104.2 | J31: =H31*I31 -> 521 | K31: =G31+J31 -> 3742.4 | L31: =+K31 -> 3742.4 | M31: =M30+K31-L31 -> 0
A32: 29 | B32: 45806 | E32: 36 | F32: 92.04 | G32: =E32*F32 -> 3313.44 | H32: 0 | I32: 0 | J32: =H32*I32 -> 0 | K32: =G32+J32 -> 3313.44 | L32: =+K32 -> 3313.44
A33: 30 | B33: 45807 | E33: 0 | F33: 0 | G33: =E33*F33 -> 0 | H33: 0 | I33: 0 | J33: =H33*I33 -> 0 | K33: =G33+J33 -> 0
A34: 31 | B34: 45808
E35: =SUM(E4:E34) -> 1382.42 | G35: =SUM(G4:G34) -> 127237.94 | H35: =SUM(H4:H34) -> 55 | J35: =SUM(J4:J34) -> 5722.9 | K35: =SUM(K4:K34) -> 132960.84 | L35: =SUM(L4:L34) -> 132960.84
I38: =K24+L24 -> 16107

Sheet Gajendragada
A1: Vanasri Petrol Pump
A2: S.No | B2: Date | C2: GRN No | D2: Ind no/Bill No | E2: Diesel (Lts) | F2: Price | G2: Amount | H2: Petrol (Lts) | I2: Price | J2: Amount | K2: Total amount | L2: Amount paid | M2: As on Date | N2: Remarks
A3: Opening Balance | K3: 0 | M3: 30323
A4: 1 | B4: 45778 | E4: 0 | F4: 0 | G4: =E4*F4 -> 0 | H4: 0 | I4: 0 | J4: =H4*I4 -> 0 | K4: =G4+J4 -> 0 | M4: =M3+K4-L4 -> 30323
A5: 2 | B5: 45779 | E5: 30 | F5: 91.83 | G5: =E5*F5 -> 2754.9 | H5: 10 | I5: 103.8 | J5: =H5*I5 -> 1038 | K5: =G5+J5 -> 3792.9 | M5: =M4+K5-L5 -> 34115.9
A6: 3 | B6: 45780 | E6: 0 | F6: 0 | G6: =E6*F6 -> 0 | H6: 0 | I6: 0 | J6: =H6*I6 -> 0 | K6: =G6+J6 -> 0 | M6: =M5+K6-L6 -> 34115.9
A7: 4 | B7: 45781 | E7: 0 | F7: 0 | G7: =E7*F7 -> 0 | H7: 0 | I7: 0 | J7: =H7*I7 -> 0 | K7: =G7+J7 -> 0 | M7: =M6+K7-L7 -> 34115.9
A8: 5 | B8: 45782 | E8: 30 | F8: 91.83 | G8: =E8*F8 -> 2754.9 | H8: 8 | I8: 103.8 | J8: =H8*I8 -> 830.4 | K8: =G8+J8 -> 3585.3 | M8: =M7+K8-L8 -> 37701.2 | O8: 8497892194 | P8: raja bhakshi
A9: 6 | B9: 45783 | E9: 0 | F9: 0 | G9: =E9*F9 -> 0 | H9: 0 | I9: 0 | J9: =H9*I9 -> 0 | K9: =G9+J9 -> 0 | M9: =M8+K9-L9 -> 37701.2
A10: 7 | B10: 45784 | E10: 0 | F10: 0 | G10: =E10*F10 -> 0 | H10: 0 | I10: 0 | J10: =H10*I10 -> 0 | K10: =G10+J10 -> 0 | M10: =M9+K10-L10 -> 37701.2
A11: 8 | B11: 45785 | E11: 0 | F11: 0 | G11: =E11*F11 -> 0 | H11: 0 | I11: 0 | J11: =H11*I11 -> 0 | K11: =G11+J11 -> 0 | M11: =M10+K11-L11 -> 37701.2
A12: 9 | B12: 45786 | E12: 0 | F12: 0 | G12: =E12*F12 -> 0 | H12: 0 | I12: 0 | J12: =H12*I12 -> 0 | K12: =G12+J12 -> 0 | M12: =M11+K12-L12 -> 37701.2
A13: 10 | B13: 45787 | E13: 0 | F13: 0 | G13: =E13*F13 -> 0 | H13: 0 | I13: 0 | J13: =H13*I13 -> 0 | K13: =G13+J13 -> 0 | M13: =M12+K13-L13 -> 37701.2
A14: 11 | B14: 45788 | E14: 0 | F14: 0 | G14: =E14*F14 -> 0 | H14: 0 | I14: 0 | J14: =H14*I14 -> 0 | K14: =G14+J14 -> 0 | M14: =M13+K14-L14 -> 37701.2
A15: 12 | B15: 45789 | E15: 0 | F15: 0 | G15: =E15*F15 -> 0 | H15: 0 | I15: 0 | J15: =H15*I15 -> 0 | K15: =G15+J15 -> 0 | M15: =M14+K15-L15 -> 37701.2
A16: 13 | B16: 45790 | E16: 0 | F16: 0 | G16: =E16*F16 -> 0 | H16: 0 | I16: 0 | J16: =H16*I16 -> 0 | K16: =G16+J16 -> 0 | M16: =M15+K16-L16 -> 37701.2
A17: 14 | B17: 45791 | E17: 0 | F17: 0 | G17: =E17*F17 -> 0 | H17: 0 | I17: 0 | J17: =H17*I17 -> 0 | K17: =G17+J17 -> 0 | M17: =M16+K17-L17 -> 37701.2
A18: 15 | B18: 45792 | E18: 0 | F18: 0 | G18: =E18*F18 -> 0 | H18: 0 | I18: 0 | J18: =H18*I18 -> 0 | K18: =G18+J18 -> 0 | M18: =M17+K18-L18 -> 37701.2
A19: 16 | B19: 45793 | E19: 0 | F19: 0 | G19: =E19*F19 -> 0 | H19: 0 | I19: 0 | J19: =H19*I19 -> 0 | K19: =G19+J19 -> 0 | M19: =M18+K19-L19 -> 37701.2
A20: 17 | B20: 45794 | E20: 0 | F20: 0 | G20: =E20*F20 -> 0 | H20: 0 | I20: 0 | J20: =H20*I20 -> 0 | K20: =G20+J20 -> 0 | M20: =M19+K20-L20 -> 37701.2
... A26: 23 | B26: 45800 | E26: 40 | F26: 91.83 | G26: =E26*F26 -> 3673.2 | H26: 0 | I26: 0 | J26: =H26*I26 -> 0 | K26: =G26+J26 -> 3673.2 | M26: =M25+K26-L26 -> 42931.4
A27: 24 | B27: 45801 | E27: 0 | F27: 0 | G27: =E27*F27 -> 0 | H27: 0 | I27: 0 | J27: =H27*I27 -> 0 | K27: =G27+J27 -> 0 | M27: =M26+K27-L27 -> 42931.4 | R27: 66742
A28: 25 | B28: 45802 | E28: 30 | F28: 91.83 | G28: =E28*F28 -> 2754.9 | H28: 0 | I28: 0 | J28: =H28*I28 -> 0 | K28: =G28+J28 -> 2754.9 | M28: =M27+K28-L28 -> 45686.3
A29: 26 | B29: 45803 | E29: 30 | F29: 91.83 | G29: =E29*F29 -> 2754.9 | H29: 0 | I29: 0 | J29: =H29*I29 -> 0 | K29: =G29+J29 -> 2754.9 | M29: =M28+K29-L29 -> 48441.2
A30: 27 | B30: 45804 | E30: 30 | F30: 91.83 | G30: =E30*F30 -> 2754.9 | H30: 0 | I30: 0 | J30: =H30*I30 -> 0 | K30: =G30+J30 -> 2754.9 | M30: =M29+K30-L30 -> 51196.1
A31: 28 | B31: 45805 | E31: 30 | F31: 91.83 | G31: =E31*F31 -> 2754.9 | H31: 0 | I31: 0 | J31: =H31*I31 -> 0 | K31: =G31+J31 -> 2754.9 | M31: =M30+K31-L31 -> 53951
A32: 29 | B32: 45806 | E32: 0 | F32: 0 | G32: =E32*F32 -> 0 | H32: 0 | I32: 0 | J32: =H32*I32 -> 0 | K32: =G32+J32 -> 0 | M32: =M31+K32-L32 -> 53951
A33: 30 | B33: 45807 | E33: 30 | F33: 91.83 | G33: =E33*F33 -> 2754.9 | H33: 0 | I33: 0 | K33: =G33+J33 -> 2754.9 | M33: =M32+K33-L33 -> 56705.9
A34: 31 | B34: 45808 | E34: 30 | F34: 91.83 | G34: =E34*F34 -> 2754.9 | K34: =G34+J34 -> 2754.9 | M34: =M33+K34-L34 -> 59460.8 | O34: 60720.56 | P34: 1280.1715
E35: =SUM(E4:E34) -> 280 | G35: =SUM(G4:G34) -> 25712.4 | H35: =SUM(H4:H34) -> 33 | J35: =SUM(J4:J34) -> 3425.4 | K35: =SUM(K4:K34) -> 29137.8 | L35: =SUM(L4:L34) -> 0

Sheet  Talikote
A1: Raykar Oil Agencies
A2: S.No | B2: Date | C2: GRN No | D2: Ind no/Bill No | E2: Diesel (Lts) | F2: Price | G2: Amount | H2: Petrol (Lts) | I2: Price | J2: Amount | K2: Total amount | L2: Amount paid | M2: As on Date | N2: Remarks
A3: Opening Balance | M3: 0
A4: 1 | B4: 02.05.2025 | E4: 0 | F4: 0 | G4: =E4*F4 -> 0 | H4: 4.83 | I4: 103.44 | J4: =H4*I4 -> 499.6152 | K4: =G4+J4 -> 499.6152 | L4: 499.62 | M4: =M3+K4-L4 -> -0.0048 | N4: IOCL Card
A5: 3 | B5: 03.05.2025 | E5: 81.48 | F5: 91.5 | G5: =E5*F5 -> 7455.42 | H5: 4.83 | I5: 103.44 | J5: =H5*I5 -> 499.6152 | K5: =G5+J5 -> 7955.0352 | L5: =+K5 -> 7955.0352 | M5: =M4+K5-L5 -> -0.0048 | N5: IOCL Card
A6: 4 | B6: 04.05.2025 | E6: 80 | F6: 91.5 | G6: =E6*F6 -> 7320 | H6: 1.93 | I6: 103.44 | J6: =H6*I6 -> 199.6392 | K6: =G6+J6 -> 7519.6392 | L6: =+K6 -> 7519.6392 | M6: =M5+K6-L6 -> -0.0048 | N6: IOCL Card
A7: 5 | B7: 05.05.2025 | E7: 30 | F7: 91.5 | G7: =E7*F7 -> 2745 | H7: 0 | I7: 0 | J7: =H7*I7 -> 0 | K7: =G7+J7 -> 2745 | L7: =+K7 -> 2745 | M7: =M6+K7-L7 -> -0.0048 | N7: IOCL Card
A8: 7 | B8: 07.05.2025 | E8: 94.38 | F8: 91.5 | G8: =E8*F8 -> 8635.77 | H8: 9.83 | I8: 103.44 | J8: =H8*I8 -> 1016.8152 | K8: =G8+J8 -> 9652.5852 | L8: =+K8 -> 9652.5852 | M8: =M7+K8-L8 -> -0.0048 | N8: IOCL Card
A9: 8 | B9: 09.05.2025 | E9: 0 | F9: 0 | G9: =E9*F9 -> 0 | H9: 4.83 | I9: 103.44 | J9: =H9*I9 -> 499.6152 | K9: =G9+J9 -> 499.6152 | L9: =+K9 -> 499.6152 | M9: =M8+K9-L9 -> -0.0048 | N9: IOCL Card
A10: 9 | B10: 10.05.2025 | E10: 104.92 | F10: 91.5 | G10: =E10*F10 -> 9600.18 | H10: 0 | I10: 0 | J10: =H10*I10 -> 0 | K10: =G10+J10 -> 9600.18 | L10: =+K10 -> 9600.18 | M10: =M9+K10-L10 -> -0.0048 | N10: IOCL Card
A11: 10 | B11: 12.05.2025 | E11: 50 | F11: 91.5 | G11: =E11*F11 -> 4575 | H11: 0 | I11: 0 | J11: =H11*I11 -> 0 | K11: =G11+J11 -> 4575 | L11: =+K11 -> 4575 | M11: =M10+K11-L11 -> -0.0048 | N11: IOCL Card
A12: 11 | B12: 14.05.2025 | E12: 42.19 | F12: 91.5 | G12: =E12*F12 -> 3860.385 | H12: 9.66 | I12: 103.44 | J12: =H12*I12 -> 999.2304 | K12: =G12+J12 -> 4859.6154 | L12: =+K12 -> 4859.6154 | M12: =M11+K12-L12 -> -0.0048 | N12: IOCL Card
A13: 12 | B13: 15.05.2025 | E13: 74.23 | F13: 91.5 | G13: =E13*F13 -> 6792.045 | H13: 4.83 | I13: 103.44 | J13: =H13*I13 -> 499.6152 | K13: =G13+J13 -> 7291.6602 | L13: =+K13 -> 7291.6602 | M13: =M12+K13-L13 -> -0.0048 | N13: IOCL Card
A14: 13 | B14: 17.05.2025 | E14: 40.53 | F14: 91.5 | G14: =E14*F14 -> 3708.495 | H14: 0 | I14: 0 | J14: =H14*I14 -> 0 | K14: =G14+J14 -> 3708.495 | L14: =+K14 -> 3708.495 | M14: =M13+K14-L14 -> -0.0048 | N14: IOCL Card
A15: 14 | B15: 20.05.2025 | E15: 0 | F15: 0 | G15: =E15*F15 -> 0 | H15: 0 | I15: 103.44 | J15: =H15*I15 -> 0 | K15: =G15+J15 -> 0 | L15: =+K15 -> 0 | M15: =M14+K15-L15 -> -0.0048 | N15: IOCL Card
A16: 15 | B16: 21.05.2025 | E16: 40.07 | F16: 91.5 | G16: =E16*F16 -> 3666.405 | H16: 21.25 | I16: 103.44 | J16: =H16*I16 -> 2198.1 | K16: =G16+J16 -> 5864.505 | L16: =+K16 -> 5864.505 | M16: =M15+K16-L16 -> -0.0048 | N16: IOCL Card
... A19: 18 | B19: 24.05.2025 | E19: 0 | F19: 0 | G19: =E19*F19 -> 0 | H19: 4.83 | I19: 103.44 | J19: =H19*I19 -> 499.6152 | K19: =G19+J19 -> 499.6152 | L19: =+K19 -> 499.6152 | M19: =M18+K19-L19 -> -0.0048 | N19: IOCL Card
A20: 19 | B20: 26.05.2025 | E20: 38.38 | F20: 91.45 | G20: =E20*F20 -> 3509.851 | H20: 0 | I20: 0 | J20: =H20*I20 -> 0 | K20: =G20+J20 -> 3509.851 | L20: 0 | M20: =M19+K20-L20 -> 3509.8462 | N20: IOCL Card
A21: 20 | B21: 27.05.2025 | E21: 43.24 | F21: 91.45 | G21: =E21*F21 -> 3954.298 | H21: 4.83 | I21: 103.44 | J21: =H21*I21 -> 499.6152 | K21: =G21+J21 -> 4453.9132 | L21: =+K21 -> 4453.9132 | M21: =M20+K21-L21 -> 3509.8462 | N21: IOCL Card
A22: 21 | B22: 29.05.2025 | E22: 41.81 | F22: 91.5 | G22: =E22*F22 -> 3825.615 | H22: 4.83 | I22: 103.44 | J22: =H22*I22 -> 499.6152 | K22: =G22+J22 -> 4325.2302 | L22: =+K22 -> 4325.2302 | M22: =M21+K22-L22 -> 3509.8462 | N22: IOCL Card
A23: 22 | B23: 30..05.2025 | E23: 63 | F23: 91.5 | G23: =E23*F23 -> 5764.5 | H23: 4.38 | I23: 103.44 | J23: =H23*I23 -> 453.0672 | K23: =G23+J23 -> 6217.5672 | L23: 9727.47 | M23: =M22+K23-L23 -> -0.0566 | N23: IOCL Card
A24: 23 | B24: 31.05.2025 | E24: 77.2 | F24: 91.5 | G24: =E24*F24 -> 7063.8 | H24: 0 | I24: 0 | J24: =H24*I24 -> 0 | K24: =G24+J24 -> 7063.8 | L24: 4575 | M24: =M23+K24-L24 -> 2488.7434 | N24: IOCL Card
A25: 24 | E25: 0 | F25: 0 | G25: =E25*F25 -> 0 | H25: 0 | I25: 0 | J25: =H25*I25 -> 0 | K25: =G25+J25 -> 0 | L25: =+K25 -> 0 | M25: =M24+K25-L25 -> 2488.7434 | N25: IOCL Card
A26: 25 | E26: 0 | F26: 0 | G26: =E26*F26 -> 0 | H26: 0 | I26: 0 | J26: =H26*I26 -> 0 | K26: =G26+J26 -> 0 | L26: =+K26 -> 0 | M26: =M25+K26-L26 -> 2488.7434 | N26: IOCL Card
A27: 26 | E27: 0 | F27: 0 | G27: =E27*F27 -> 0 | H27: 0 | I27: 0 | J27: =H27*I27 -> 0 | K27: =G27+J27 -> 0 | L27: =+K27 -> 0 | M27: =M26+K27-L27 -> 2488.7434 | N27: IOCL Card
A28: 27 | E28: 0 | F28: 0 | G28: =E28*F28 -> 0 | H28: 0 | I28: 0 | J28: =H28*I28 -> 0 | K28: =G28+J28 -> 0 | L28: =+K28 -> 0 | M28: =M27+K28-L28 -> 2488.7434 | N28: IOCL Card
A29: 28 | E29: 0 | F29: 0 | G29: =E29*F29 -> 0 | H29: 0 | I29: 0 | J29: =H29*I29 -> 0 | K29: =G29+J29 -> 0 | L29: =+K29 -> 0 | M29: =M28+K29-L29 -> 2488.7434 | N29: IOCL Card
A30: 29 | E30: 0 | F30: 0 | G30: =E30*F30 -> 0 | H30: 0 | I30: 0 | J30: =H30*I30 -> 0 | K30: =G30+J30 -> 0 | L30: =+K30 -> 0 | M30: 0 | N30: IOCL Card
A31: 30 | E31: 0 | F31: 0 | G31: =E31*F31 -> 0 | H31: 0 | I31: 0 | J31: =H31*I31 -> 0 | K31: =G31+J31 -> 0 | L31: =+K31 -> 0 | M31: 0 | N31: IOCL Card
A32: 31 | E32: 0 | F32: 0 | G32: =E32*F32 -> 0 | H32: 0 | I32: 0 | J32: =H32*I32 -> 0 | K32: =G32+J32 -> 0 | L32: =+K32 -> 0 | M32: 0 | N32: IOCL Card
A33: 32 | E33: 0 | F33: 0 | G33: =E33*F33 -> 0 | H33: 0 | I33: 0 | J33: =H33*I33 -> 0 | K33: =G33+J33 -> 0 | L33: =+K33 -> 0 | M33: 0 | N33: IOCL Card
A34: 33 | E34: 0 | F34: 0 | G34: =E34*F34 -> 0 | H34: 0 | I34: 0 | J34: =H34*I34 -> 0 | K34: =G34+J34 -> 0 | L34: =+K34 -> 0 | M34: 0 | N34: IOCL Card
A35: 34 | E35: 0 | F35: 0 | G35: =E35*F35 -> 0 | H35: 0 | I35: 0 | J35: =H35*I35 -> 0 | K35: =G35+J35 -> 0 | L35: =+K35 -> 0 | M35: 0 | N35: IOCL Card
A36: 35 | E36: 0 | F36: 0 | G36: =E36*F36 -> 0 | H36: 0 | I36: 0 | J36: =H36*I36 -> 0 | K36: =G36+J36 -> 0 | L36: =+K36 -> 0 | M36: 0 | N36: IOCL Card
A37: 36 | E37: 0 | F37: 0 | G37: =E37*F37 -> 0 | H37: 0 | I37: 0 | J37: =H37*I37 -> 0 | K37: =G37+J37 -> 0 | L37: =+K37 -> 0 | M37: 0 | N37: IOCL Card
A38: 37 | E38: 0 | F38: 0 | G38: =E38*F38 -> 0 | H38: 0 | I38: 0 | J38: =H38*I38 -> 0 | K38: =G38+J38 -> 0 | L38: =+K38 -> 0 | M38: 0 | N38: IOCL Card
A39: 38 | E39: 0 | F39: 0 | G39: =E39*F39 -> 0 | H39: 0 | I39: 0 | J39: =H39*I39 -> 0 | K39: =G39+J39 -> 0 | L39: =+K39 -> 0 | M39: 0 | N39: IOCL Card
A40: 39 | E40: 0 | F40: 0 | G40: =E40*F40 -> 0 | H40: 0 | I40: 0 | J40: =H40*I40 -> 0 | K40: =G40+J40 -> 0 | L40: =+K40 -> 0 | M40: 0 | N40: IOCL Card
A41: 40 | E41: 0 | F41: 0 | G41: =E41*F41 -> 0 | H41: 0 | I41: 0 | J41: =H41*I41 -> 0 | K41: =G41+J41 -> 0 | L41: =+K41 -> 0 | M41: 0 | N41: IOCL Card
... A43: 42 | E43: 0 | F43: 0 | G43: =E43*F43 -> 0 | H43: 0 | I43: 0 | J43: =H43*I43 -> 0 | K43: =G43+J43 -> 0 | L43: =+K43 -> 0 | M43: 0 | N43: IOCL Card
E44: =SUM(E4:E43) -> 1084.75 | G44: =SUM(G4:G43) -> 99250.544 | H44: =SUM(H4:H43) -> 90.52 | J44: =SUM(J4:J43) -> 9363.3888 | K44: =SUM(K4:K43) -> 108613.93 | L44: =SUM(L4:L43) -> 106125.19

Sheet Nalatwad
A1: Shri Pawad Basaweshwar Petroleums
A2: S.No | B2: Date | C2: GRN No | D2: Ind no/Bill No | E2: Diesel (Lts) | F2: Price | G2: Amount | H2: Petrol (Lts) | I2: Price | J2: Amount | K2: Total amount | L2: Amount paid | M2: As on Date | N2: Remarks
A3: Opening Balance | M3: 48315
A4: 1 | B4: 45778 | E4: 0 | F4: 0 | G4: =E4*F4 -> 0 | H4: 0 | I4: 0 | J4: =H4*I4 -> 0 | K4: =G4+J4 -> 0 | L4: =+K4 -> 0 | M4: =M3+K4-L4 -> 48315 | N4: IOCL Card
A5: 2 | B5: 45779 | E5: 0 | F5: 0 | G5: =E5*F5 -> 0 | H5: 0 | I5: 0 | J5: =H5*I5 -> 0 | K5: =G5+J5 -> 0 | L5: =+K5 -> 0 | M5: =M4+K5-L5 -> 48315 | N5: IOCL Card
A6: 3 | B6: 45780 | E6: 0 | F6: 0 | G6: =E6*F6 -> 0 | H6: 0 | I6: 0 | J6: =H6*I6 -> 0 | K6: =G6+J6 -> 0 | L6: =+K6 -> 0 | M6: =M5+K6-L6 -> 48315 | N6: IOCL Card
A7: 4 | B7: 45781 | E7: 0 | F7: 0 | G7: =E7*F7 -> 0 | H7: 0 | I7: 0 | J7: =H7*I7 -> 0 | K7: =G7+J7 -> 0 | L7: =+K7 -> 0 | M7: =M6+K7-L7 -> 48315 | N7: IOCL Card
A8: 5 | B8: 45782 | E8: 0 | F8: 0 | G8: =E8*F8 -> 0 | H8: 0 | I8: 0 | J8: =H8*I8 -> 0 | K8: =G8+J8 -> 0 | L8: =+K8 -> 0 | M8: =M7+K8-L8 -> 48315 | N8: IOCL Card
A9: 6 | B9: 45783 | E9: 36.1 | F9: 91.62 | G9: =E9*F9 -> 3307.482 | H9: 0 | I9: 0 | J9: =H9*I9 -> 0 | K9: =G9+J9 -> 3307.482 | L9: 0 | M9: =M8+K9-L9 -> 51622.482 | N9: IOCL Card
A10: 7 | B10: 45784 | E10: 50 | F10: 91.62 | G10: =E10*F10 -> 4581 | H10: 0 | I10: 0 | J10: =H10*I10 -> 0 | K10: =G10+J10 -> 4581 | L10: 0 | M10: =M9+K10-L10 -> 56203.482 | N10: IOCL Card
A11: 8 | B11: 45785 | E11: 100 | F11: 91.62 | G11: =E11*F11 -> 9162 | H11: 0 | I11: 0 | J11: =H11*I11 -> 0 | K11: =G11+J11 -> 9162 | L11: 0 | M11: =M10+K11-L11 -> 65365.482 | N11: IOCL Card
A12: 9 | B12: 45786 | E12: 3.91 | F12: 91.62 | G12: =E12*F12 -> 358.2342 | H12: 9.66 | I12: 103.57 | J12: =H12*I12 -> 1000.4862 | K12: =G12+J12 -> 1358.7204 | L12: 0 | M12: =M11+K12-L12 -> 66724.202 | N12: IOCL Card
A13: 10 | B13: 45787 | E13: 48.02 | F13: 91.62 | G13: =E13*F13 -> 4399.5924 | H13: 6.76 | I13: 103.57 | J13: =H13*I13 -> 700.1332 | K13: =G13+J13 -> 5099.7256 | L13: 0 | M13: =M12+K13-L13 -> 71823.928 | N13: IOCL Card
A14: 11 | B14: 45788 | E14: 0 | F14: 0 | G14: =E14*F14 -> 0 | H14: 0 | I14: 0 | J14: =H14*I14 -> 0 | K14: =G14+J14 -> 0 | L14: =+K14 -> 0 | M14: =M13+K14-L14 -> 71823.928 | N14: IOCL Card
A15: 12 | B15: 45789 | E15: 0 | F15: 0 | G15: =E15*F15 -> 0 | H15: 0 | I15: 0 | J15: =H15*I15 -> 0 | K15: =G15+J15 -> 0 | L15: 50000 | M15: =M14+K15-L15 -> 21823.928 | N15: IOCL Card
A16: 13 | B16: 45790 | E16: 10 | F16: 91.62 | G16: =E16*F16 -> 916.2 | H16: 0 | I16: 0 | J16: =H16*I16 -> 0 | K16: =G16+J16 -> 916.2 | L16: 0 | M16: =M15+K16-L16 -> 22740.128 | N16: IOCL Card
A17: 14 | B17: 45791 | E17: 93.89 | F17: 91.62 | G17: =E17*F17 -> 8602.2018 | H17: 0 | I17: 0 | J17: =H17*I17 -> 0 | K17: =G17+J17 -> 8602.2018 | L17: 0 | M17: =M16+K17-L17 -> 31342.33 | N17: IOCL Card
A18: 15 | B18: 45792 | E18: 0 | F18: 0 | G18: =E18*F18 -> 0 | H18: 0 | I18: 0 | J18: =H18*I18 -> 0 | K18: =G18+J18 -> 0 | L18: =+K18 -> 0 | M18: =M17+K18-L18 -> 31342.33 | N18: IOCL Card
A19: 16 | B19: 45793 | E19: 0 | F19: 0 | G19: =E19*F19 -> 0 | H19: 4.83 | I19: 103.57 | J19: =H19*I19 -> 500.2431 | K19: =G19+J19 -> 500.2431 | L19: 0 | M19: =M18+K19-L19 -> 31842.573 | N19: IOCL Card
A20: 17 | B20: 45794 | E20: 0 | F20: 0 | G20: =E20*F20 -> 0 | H20: 0 | I20: 0 | J20: =H20*I20 -> 0 | K20: =G20+J20 -> 0 | L20: =+K20 -> 0 | M20: =M19+K20-L20 -> 31842.573 | N20: IOCL Card
A21: 18 | B21: 45795 | E21: 0 | F21: 0 | G21: =E21*F21 -> 0 | H21: 0 | I21: 0 | J21: =H21*I21 -> 0 | K21: =G21+J21 -> 0 | L21: =+K21 -> 0 | M21: =M20+K21-L21 -> 31842.573 | N21: IOCL Card
A22: 19 | B22: 45796 | E22: 0 | F22: 0 | G22: =E22*F22 -> 0 | H22: 0 | I22: 0 | J22: =H22*I22 -> 0 | K22: =G22+J22 -> 0 | L22: =+K22 -> 0 | M22: =M21+K22-L22 -> 31842.573 | N22: IOCL Card
A23: 20 | B23: 45797 | E23: 94.97 | F23: 91.62 | G23: =E23*F23 -> 8701.1514 | H23: 0 | I23: 0 | J23: =H23*I23 -> 0 | K23: =G23+J23 -> 8701.1514 | L23: 0 | M23: =M22+K23-L23 -> 40543.724
A24: 21 | B24: 45798 | E24: 0 | F24: 0 | G24: =E24*F24 -> 0 | H24: 0 | I24: 0 | J24: =H24*I24 -> 0 | K24: =G24+J24 -> 0 | L24: 40535.84 | M24: =M23+K24-L24 -> 7.8843
A25: 22 | B25: 45799 | E25: 10 | F25: 91.62 | G25: =E25*F25 -> 916.2 | H25: 4.83 | I25: 103.57 | J25: =H25*I25 -> 500.2431 | K25: =G25+J25 -> 1416.4431 | L25: 0 | M25: =M24+K25-L25 -> 1424.3274
A26: 23 | B26: 45800 | E26: 10 | F26: 91.62 | G26: =E26*F26 -> 916.2 | H26: 0 | I26: 0 | J26: =H26*I26 -> 0 | K26: =G26+J26 -> 916.2 | L26: 0 | M26: =M25+K26-L26 -> 2340.5274
A27: 24 | B27: 45801 | E27: 0 | F27: 0 | G27: =E27*F27 -> 0 | H27: 0 | I27: 0 | J27: =H27*I27 -> 0 | K27: =G27+J27 -> 0 | L27: =+K27 -> 0 | M27: =M26+K27-L27 -> 2340.5274
A28: 25 | B28: 45802 | E28: 0 | F28: 0 | G28: =E28*F28 -> 0 | H28: 0 | I28: 0 | J28: =H28*I28 -> 0 | K28: =G28+J28 -> 0 | L28: =+K28 -> 0 | M28: =M27+K28-L28 -> 2340.5274
A29: 26 | B29: 45803 | E29: 97 | F29: 91.62 | G29: =E29*F29 -> 8887.14 | H29: 4.83 | I29: 103.57 | J29: =H29*I29 -> 500.2431 | K29: =G29+J29 -> 9387.3831 | L29: 0 | M29: =M28+K29-L29 -> 11727.911
A30: 27 | B30: 45804 | E30: 0 | F30: 0 | G30: =E30*F30 -> 0 | H30: 0 | I30: 0 | J30: =H30*I30 -> 0 | K30: =G30+J30 -> 0 | L30: =+K30 -> 0 | M30: =M29+K30-L30 -> 11727.911
A31: 28 | B31: 45805 | E31: 0 | F31: 0 | G31: =E31*F31 -> 0 | H31: 0 | I31: 0 | J31: =H31*I31 -> 0 | K31: =G31+J31 -> 0 | L31: =+K31 -> 0 | M31: =M30+K31-L31 -> 11727.911
A32: 29 | B32: 45806 | E32: 0 | F32: 0 | G32: =E32*F32 -> 0 | H32: 0 | I32: 0 | J32: =H32*I32 -> 0 | K32: =G32+J32 -> 0 | L32: =+K32 -> 0 | M32: =M31+K32-L32 -> 11727.911
A33: 30 | B33: 45807 | E33: 93 | F33: 91.62 | G33: =E33*F33 -> 8520.66 | H33: 0 | I33: 0 | J33: =H33*I33 -> 0 | K33: =G33+J33 -> 8520.66 | L33: 0 | M33: =M32+K33-L33 -> 20248.571
A34: 31 | B34: 45808 | E34: 0 | F34: 0 | G34: =E34*F34 -> 0 | H34: 0 | I34: 0 | J34: =H34*I34 -> 0 | K34: =G34+J34 -> 0 | L34: 0 | M34: =M33+K34-L34 -> 20248.571
A35: 35 | E35: 0 | F35: 0 | G35: =E35*F35 -> 0 | H35: 0 | I35: 0 | J35: =H35*I35 -> 0 | K35: =G35+J35 -> 0 | L35: =+K35 -> 0 | M35: =M34+K35-L35 -> 20248.571
A36: 36 | E36: 0 | F36: 0 | G36: =E36*F36 -> 0 | H36: 0 | I36: 0 | J36: =H36*I36 -> 0 | K36: =G36+J36 -> 0 | L36: =+K36 -> 0 | M36: =M35+K36-L36 -> 20248.571
A37: 37 | E37: 0 | F37: 0 | G37: =E37*F37 -> 0 | H37: 0 | I37: 0 | J37: =H37*I37 -> 0 | K37: =G37+J37 -> 0 | L37: =+K37 -> 0 | M37: =M36+K37-L37 -> 20248.571
A38: 38 | E38: 0 | F38: 0 | G38: =E38*F38 -> 0 | H38: 0 | I38: 0 | J38: =H38*I38 -> 0 | K38: =G38+J38 -> 0 | L38: =+K38 -> 0 | M38: =M37+K38-L38 -> 20248.571
A39: 39 | E39: 0 | F39: 0 | G39: =E39*F39 -> 0 | H39: 0 | I39: 0 | J39: =H39*I39 -> 0 | K39: =G39+J39 -> 0 | L39: =+K39 -> 0 | M39: =M38+K39-L39 -> 20248.571
A40: 40 | E40: 0 | F40: 0 | G40: =E40*F40 -> 0 | H40: 0 | I40: 0 | J40: =H40*I40 -> 0 | K40: =G40+J40 -> 0 | L40: =+K40 -> 0 | M40: 0
A41: 41 | E41: 0 | F41: 0 | G41: =E41*F41 -> 0 | H41: 0 | I41: 0 | J41: =H41*I41 -> 0 | K41: =G41+J41 -> 0 | L41: =+K41 -> 0 | M41: 0
A42: 42 | E42: 0 | F42: 0 | G42: =E42*F42 -> 0 | J42: =H42*I42 -> 0 | K42: =G42+J42 -> 0 | L42: =+K42 -> 0 | M42: 0
E43: =SUM(E4:E42) -> 646.89 | G43: =SUM(G4:G42) -> 59268.062 | H43: =SUM(H4:H42) -> 30.91 | J43: =SUM(J4:J42) -> 3201.3487 | K43: =SUM(K4:K42) -> 62469.41 | L43: =SUM(L4:L42) -> 90535.84

Sheet Muddebihal
A1: Bhosle Service Station
A2: S.No | B2: Date | C2: GRN No | D2: Ind no/Bill No | E2: Diesel (Lts) | F2: Price | G2: Amount | H2: Petrol (Lts) | I2: Price | J2: Amount | K2: Total amount | L2: Amount paid | M2: As on Date | N2: Remarks
A3: Opening Balance | M3: NA
A4: 1 | B4: 04.05.2025 | E4: 0 | F4: 0 | G4: =E4*F4 -> 0 | H4: 9.66 | I4: 103.39 | J4: =H4*I4 -> 998.7474 | K4: =G4+J4 -> 998.7474 | L4: =+K4 -> 998.7474 | M4: 0 | N4: IOCL Card
A5: 2 | B5: 10.05.2025 | E5: 98.41 | F5: 91.45 | G5: =E5*F5 -> 8999.5945 | H5: 9.66 | I5: 103.39 | J5: =H5*I5 -> 998.7474 | K5: =G5+J5 -> 9998.3419 | L5: =+K5 -> 9998.3419 | M5: 0 | N5: IOCL Card
A6: 3 | B6: 14.05.2025 | E6: 0 | F6: 0 | G6: =E6*F6 -> 0 | H6: 4.83 | I6: 103.39 | J6: =H6*I6 -> 499.3737 | K6: =G6+J6 -> 499.3737 | L6: =+K6 -> 499.3737 | M6: 0 | N6: IOCL Card
A7: 4 | B7: 15.05.2025 | E7: 0 | F7: 0 | G7: =E7*F7 -> 0 | H7: 4.83 | I7: 103.39 | J7: =H7*I7 -> 499.3737 | K7: =G7+J7 -> 499.3737 | L7: =+K7 -> 499.3737 | M7: 0 | N7: IOCL Card
A8: 5 | B8: 21.05.2025 | E8: 0 | F8: 0 | G8: =E8*F8 -> 0 | H8: 4.83 | I8: 103.39 | J8: =H8*I8 -> 499.3737 | K8: =G8+J8 -> 499.3737 | L8: =+K8 -> 499.3737 | M8: 0 | N8: IOCL Card
A9: 6 | B9: 25.05.2025 | E9: 48.3 | F9: 91.45 | G9: =E9*F9 -> 4417.035 | H9: 0 | I9: 0 | J9: =H9*I9 -> 0 | K9: =G9+J9 -> 4417.035 | L9: =+K9 -> 4417.035 | M9: 0 | N9: IOCL Card
A10: 7 | B10: 29.05.2025 | E10: 0 | F10: 0 | G10: =E10*F10 -> 0 | H10: 4.83 | I10: 103.39 | J10: =H10*I10 -> 499.3737 | K10: =G10+J10 -> 499.3737 | L10: =+K10 -> 499.3737 | M10: 0 | N10: IOCL Card
A11: 8 | E11: 0 | F11: 0 | G11: =E11*F11 -> 0 | H11: 0 | I11: 0 | J11: =H11*I11 -> 0 | K11: =G11+J11 -> 0 | L11: =+K11 -> 0 | M11: 0 | N11: IOCL Card
A12: 9 | E12: 0 | F12: 0 | G12: =E12*F12 -> 0 | H12: 0 | I12: 0 | J12: =H12*I12 -> 0 | K12: =G12+J12 -> 0 | L12: =+K12 -> 0 | M12: 0 | N12: IOCL Card
A13: 10 | E13: 0 | F13: 0 | G13: =E13*F13 -> 0 | H13: 0 | I13: 0 | J13: =H13*I13 -> 0 | K13: =G13+J13 -> 0 | L13: =+K13 -> 0 | M13: 0 | N13: IOCL Card
A14: 11 | E14: 0 | F14: 0 | G14: =E14*F14 -> 0 | H14: 0 | I14: 0 | J14: =H14*I14 -> 0 | K14: =G14+J14 -> 0 | L14: =+K14 -> 0 | M14: 0 | N14: IOCL Card
A15: 12 | E15: 0 | F15: 0 | G15: =E15*F15 -> 0 | H15: 0 | I15: 0 | J15: =H15*I15 -> 0 | K15: =G15+J15 -> 0 | L15: =+K15 -> 0 | M15: 0 | N15: IOCL Card
E16: 0 | F16: 0 | G16: =E16*F16 -> 0 | H16: 0 | I16: 0 | J16: =H16*I16 -> 0 | K16: =G16+J16 -> 0 | L16: =+K16 -> 0 | N16: IOCL Card
A17: 13 | E17: 0 | F17: 0 | G17: =E17*F17 -> 0 | H17: 0 | I17: 0 | J17: =H17*I17 -> 0 | K17: =G17+J17 -> 0 | L17: =+K17 -> 0 | M17: 0 | N17: IOCL Card
A18: 14 | E18: 0 | F18: 0 | G18: =E18*F18 -> 0 | H18: 0 | I18: 0 | J18: =H18*I18 -> 0 | K18: =G18+J18 -> 0 | L18: =+K18 -> 0 | M18: 0 | N18: IOCL Card
A19: 15 | E19: 0 | F19: 0 | G19: =E19*F19 -> 0 | H19: 0 | I19: 0 | J19: =H19*I19 -> 0 | K19: =G19+J19 -> 0 | L19: =+K19 -> 0 | M19: 0 | N19: IOCL Card
A20: 16 | E20: 0 | F20: 0 | G20: =E20*F20 -> 0 | H20: 0 | I20: 0 | J20: =H20*I20 -> 0 | K20: =G20+J20 -> 0 | L20: =+K20 -> 0 | M20: 0 | N20: IOCL Card
A21: 17 | E21: 0 | F21: 0 | G21: =E21*F21 -> 0 | H21: 0 | I21: 0 | J21: =H21*I21 -> 0 | K21: =G21+J21 -> 0 | L21: =+K21 -> 0 | M21: 0 | N21: IOCL Card
A22: 18 | E22: 0 | F22: 0 | G22: =E22*F22 -> 0 | H22: 0 | I22: 0 | J22: =H22*I22 -> 0 | K22: =G22+J22 -> 0 | L22: =+K22 -> 0 | M22: 0 | N22: IOCL Card
A23: 19 | E23: 0 | F23: 0 | G23: =E23*F23 -> 0 | H23: 0 | I23: 0 | J23: =H23*I23 -> 0 | K23: =G23+J23 -> 0 | L23: =+K23 -> 0 | M23: 0 | N23: IOCL Card
A24: 20 | E24: 0 | F24: 0 | G24: =E24*F24 -> 0 | H24: 0 | I24: 0 | J24: =H24*I24 -> 0 | K24: =G24+J24 -> 0 | L24: =+K24 -> 0 | M24: 0 | N24: IOCL Card
A25: 21 | E25: 0 | F25: 0 | G25: =E25*F25 -> 0 | H25: 0 | I25: 0 | J25: =H25*I25 -> 0 | K25: =G25+J25 -> 0 | L25: =+K25 -> 0 | M25: 0 | N25: IOCL Card
A26: 22 | E26: 0 | F26: 0 | G26: =E26*F26 -> 0 | H26: 0 | I26: 0 | J26: =H26*I26 -> 0 | K26: =G26+J26 -> 0 | L26: =+K26 -> 0 | M26: 0 | N26: IOCL Card
A27: 23 | E27: 0 | F27: 0 | G27: =E27*F27 -> 0 | H27: 0 | I27: 0 | J27: =H27*I27 -> 0 | K27: =G27+J27 -> 0 | L27: =+K27 -> 0 | M27: 0 | N27: IOCL Card
A28: 24 | E28: 0 | F28: 0 | G28: =E28*F28 -> 0 | H28: 0 | I28: 0 | J28: =H28*I28 -> 0 | K28: =G28+J28 -> 0 | L28: =+K28 -> 0 | M28: 0 | N28: IOCL Card
... A36: 31 | E36: 0 | F36: 0 | G36: =E36*F36 -> 0 | H36: 0 | I36: 0 | J36: =H36*I36 -> 0 | K36: =G36+J36 -> 0 | L36: =+K36 -> 0 | M36: 0 | N36: IOCL Card
A37: 34 | E37: 0 | F37: 0 | G37: =E37*F37 -> 0 | H37: 0 | I37: 0 | J37: =H37*I37 -> 0 | K37: =G37+J37 -> 0 | L37: =+K37 -> 0 | M37: 0
A38: 35 | E38: 0 | F38: 0 | G38: =E38*F38 -> 0 | H38: 0 | I38: 0 | J38: =H38*I38 -> 0 | K38: =G38+J38 -> 0 | L38: =+K38 -> 0 | M38: 0
A39: 36 | E39: 0 | F39: 0 | G39: =E39*F39 -> 0 | H39: 0 | I39: 0 | J39: =H39*I39 -> 0 | K39: =G39+J39 -> 0 | L39: =+K39 -> 0 | M39: 0
A40: 37 | E40: 0 | F40: 0 | G40: =E40*F40 -> 0 | H40: 0 | I40: 0 | J40: =H40*I40 -> 0 | K40: =G40+J40 -> 0 | L40: =+K40 -> 0 | M40: 0
A41: 38 | E41: 0 | F41: 0 | G41: =E41*F41 -> 0 | H41: 0 | I41: 0 | J41: =H41*I41 -> 0 | K41: =G41+J41 -> 0 | L41: =+K41 -> 0 | M41: 0
A42: 39 | E42: 0 | F42: 0 | G42: =E42*F42 -> 0 | H42: 0 | I42: 0 | J42: =H42*I42 -> 0 | K42: =G42+J42 -> 0 | L42: =+K42 -> 0 | M42: 0
A43: 40 | E43: 0 | F43: 0 | G43: =E43*F43 -> 0 | J43: =H43*I43 -> 0 | K43: =G43+J43 -> 0 | L43: =+K43 -> 0 | M43: 0
A44: 41 | E44: 0 | F44: 0 | G44: =E44*F44 -> 0 | J44: =H44*I44 -> 0 | K44: =G44+J44 -> 0 | L44: =+K44 -> 0 | M44: 0
A45: 42 | E45: 0 | F45: 0 | G45: =E45*F45 -> 0 | J45: =H45*I45 -> 0 | K45: =G45+J45 -> 0 | L45: =+K45 -> 0 | M45: 0
E46: =SUM(E4:E45) -> 146.71 | G46: =SUM(G4:G45) -> 13416.629 | H46: =SUM(H4:H45) -> 38.64 | J46: =SUM(J4:J45) -> 3994.9896 | K46: =SUM(K4:K45) -> 17411.619 | L46: =SUM(L4:L45) -> 17411.619

Sheet Chadchan
A1: Khavekar Petrolium
A2: S.No | B2: Date | C2: GRN No | D2: Ind no/Bill No | E2: Diesel (Lts) | F2: Price | G2: Amount | H2: Petrol (Lts) | I2: Price | J2: Amount | K2: Total amount | L2: Amount paid | M2: As on Date | N2: Remarks
B3: Opening Balance | K3: 192780 | M3: =+K3 -> 192780 | O3: 237866.59
A4: 1 | B4: 45778 | E4: 0 | F4: 0 | G4: 0 | H4: 5.1 | I4: 102.16 | J4: =H4*I4 -> 521.016 | K4: =G4+J4 -> 521.016 | M4: =M3+K4-L4 -> 193301.02
A5: 2 | B5: 45779 | E5: 0 | F5: 0 | G5: 0 | H5: 0 | I5: 0 | J5: =H5*I5 -> 0 | K5: =G5+J5 -> 0 | M5: =M4+K5-L5 -> 193301.02
A6: 3 | B6: 45780 | E6: 0 | F6: 0 | G6: 0 | H6: 0 | I6: 0 | J6: =H6*I6 -> 0 | K6: =G6+J6 -> 0 | M6: =M5+K6-L6 -> 193301.02
A7: 4 | B7: 45781 | E7: 0 | F7: 0 | G7: 0 | H7: 3.99 | I7: 102.16 | J7: =H7*I7 -> 407.6184 | K7: =G7+J7 -> 407.6184 | M7: =M6+K7-L7 -> 193708.63
A8: 5 | B8: 45782 | E8: 0 | F8: 0 | G8: 0 | H8: 0 | I8: 0 | J8: =H8*I8 -> 0 | K8: =G8+J8 -> 0 | M8: =M7+K8-L8 -> 193708.63 | Q8: 96.71
A9: 6 | B9: 45783 | E9: 0 | F9: 0 | G9: 0 | H9: 0 | I9: 0 | J9: =H9*I9 -> 0 | K9: =G9+J9 -> 0 | M9: =M8+K9-L9 -> 193708.63 | Q9: 102
A10: 7 | B10: 45784 | E10: 95.77 | F10: 90.23 | G10: =E10*F10 -> 8641.3271 | H10: 4.91 | I10: 102.16 | J10: =H10*I10 -> 501.6056 | K10: =G10+J10 -> 9142.9327 | M10: =M9+K10-L10 -> 202851.57 | Q10: 80.44
A11: 8 | B11: 45785 | E11: 180.72 | F11: 90.23 | G11: =E11*F11 -> 16306.366 | H11: 4.89 | I11: 102.16 | J11: =H11*I11 -> 499.5624 | K11: =G11+J11 -> 16805.928 | M11: =M10+K11-L11 -> 219657.5 | Q11: 100.02
A12: 9 | B12: 45786 | E12: 30 | F12: 90.23 | G12: =E12*F12 -> 2706.9 | H12: 0 | I12: 0 | J12: =H12*I12 -> 0 | K12: =G12+J12 -> 2706.9 | M12: =M11+K12-L12 -> 222364.4 | Q12: 43.57
A13: 10 | B13: 45787 | E13: 0 | F13: 0 | G13: =E13*F13 -> 0 | H13: 0 | I13: 0 | J13: =H13*I13 -> 0 | K13: =G13+J13 -> 0 | M13: =M12+K13-L13 -> 222364.4
A14: 11 | B14: 45788 | E14: 0 | F14: 0 | G14: =E14*F14 -> 0 | H14: 0 | I14: 0 | J14: =H14*I14 -> 0 | K14: =G14+J14 -> 0 | M14: =M13+K14-L14 -> 222364.4
A15: 12 | B15: 45789 | E15: 65 | F15: 90.23 | G15: =E15*F15 -> 5864.95 | H15: 1.95 | I15: 102.16 | J15: =H15*I15 -> 199.212 | K15: =G15+J15 -> 6064.162 | M15: =M14+K15-L15 -> 228428.56
A16: 13 | B16: 45790 | E16: 0 | F16: 0 | G16: =E16*F16 -> 0 | H16: 6.98 | I16: 102.16 | J16: =H16*I16 -> 713.0768 | K16: =G16+J16 -> 713.0768 | M16: =M15+K16-L16 -> 229141.63
A17: 14 | B17: 45791 | E17: 0 | F17: 0 | G17: =E17*F17 -> 0 | H17: 0 | I17: 0 | J17: =H17*I17 -> 0 | K17: =G17+J17 -> 0 | M17: =M16+K17-L17 -> 229141.63
A18: 15 | B18: 45792 | E18: 45 | F18: 90.23 | G18: =E18*F18 -> 4060.35 | H18: 5.68 | I18: 102.16 | J18: =H18*I18 -> 580.2688 | K18: =G18+J18 -> 4640.6188 | M18: =M17+K18-L18 -> 233782.25
A19: 16 | B19: 45793 | E19: 0 | F19: 90.23 | G19: =E19*F19 -> 0 | H19: 0 | I19: 0 | J19: =H19*I19 -> 0 | K19: =G19+J19 -> 0 | M19: =M18+K19-L19 -> 233782.25
A20: 17 | B20: 45794 | E20: 36.78 | F20: 90.23 | G20: =E20*F20 -> 3318.6594 | H20: 0 | I20: 0 | J20: =H20*I20 -> 0 | K20: =G20+J20 -> 3318.6594 | M20: =M19+K20-L20 -> 237100.91
A21: 18 | B21: 45795 | E21: 0 | F21: 0 | G21: =E21*F21 -> 0 | H21: 0 | I21: 0 | J21: =H21*I21 -> 0 | K21: =G21+J21 -> 0 | M21: =M20+K21-L21 -> 237100.91
A22: 19 | B22: 45796 | E22: 0 | F22: 0 | G22: =E22*F22 -> 0 | H22: 0 | I22: 0 | J22: =H22*I22 -> 0 | K22: =G22+J22 -> 0 | M22: =M21+K22-L22 -> 237100.91
A23: 20 | B23: 45797 | E23: 0 | F23: 0 | G23: =E23*F23 -> 0 | H23: 5.49 | I23: 102.16 | J23: =H23*I23 -> 560.8584 | K23: =G23+J23 -> 560.8584 | L23: 192780 | M23: =M22+K23-L23 -> 44881.771
A24: 21 | B24: 45798 | E24: 87.24 | F24: 90.23 | G24: =E24*F24 -> 7871.6652 | H24: 4.89 | I24: 102.16 | J24: =H24*I24 -> 499.5624 | K24: =G24+J24 -> 8371.2276 | M24: =M23+K24-L24 -> 53252.998
A25: 22 | B25: 45799 | E25: 0 | F25: 0 | G25: =E25*F25 -> 0 | H25: 0 | I25: 0 | J25: =H25*I25 -> 0 | K25: =G25+J25 -> 0 | M25: =M24+K25-L25 -> 53252.998
A26: 23 | B26: 45800 | E26: 20 | F26: 90.23 | G26: =E26*F26 -> 1804.6 | H26: 5.88 | I26: 102.16 | J26: =H26*I26 -> 600.7008 | K26: =G26+J26 -> 2405.3008 | M26: =M25+K26-L26 -> 55658.299
A27: 24 | B27: 45801 | E27: 0 | F27: 0 | G27: =E27*F27 -> 0 | H27: 0 | I27: 0 | J27: =H27*I27 -> 0 | K27: =G27+J27 -> 0 | M27: =M26+K27-L27 -> 55658.299
A28: 25 | B28: 45802 | E28: 0 | F28: 0 | G28: =E28*F28 -> 0 | H28: 0 | I28: 0 | J28: =H28*I28 -> 0 | K28: =G28+J28 -> 0 | M28: =M27+K28-L28 -> 55658.299
A29: 26 | B29: 45803 | E29: 37.88 | F29: 90.23 | G29: =E29*F29 -> 3417.9124 | H29: 0 | I29: 0 | J29: =H29*I29 -> 0 | K29: =G29+J29 -> 3417.9124 | M29: =M28+K29-L29 -> 59076.211
A30: 27 | B30: 45804 | E30: 0 | F30: 0 | G30: =E30*F30 -> 0 | H30: 0 | I30: 0 | J30: =H30*I30 -> 0 | K30: =G30+J30 -> 0 | M30: =M29+K30-L30 -> 59076.211
A31: 28 | B31: 45805 | E31: 100 | F31: 90.23 | G31: =E31*F31 -> 9023 | H31: 0 | I31: 0 | J31: =H31*I31 -> 0 | K31: =G31+J31 -> 9023 | M31: =M30+K31-L31 -> 68099.211
A32: 29 | B32: 45806 | E32: 0 | F32: 0 | G32: =E32*F32 -> 0 | H32: 10.6 | I32: 102.16 | J32: =H32*I32 -> 1082.896 | K32: =G32+J32 -> 1082.896 | M32: =M31+K32-L32 -> 69182.107
A33: 30 | B33: 45807 | E33: 33.52 | F33: 90.23 | G33: =E33*F33 -> 3024.5096 | H33: 0 | I33: 0 | J33: =H33*I33 -> 0 | K33: =G33+J33 -> 3024.5096 | M33: =M32+K33-L33 -> 72206.617
A34: 31 | B34: 45808 | E34: 64 | F34: 90.23 | G34: =E34*F34 -> 5774.72 | H34: 0 | I34: 0 | J34: =H34*I34 -> 0 | K34: =G34+J34 -> 5774.72 | M34: =M33+K34-L34 -> 77981.337
E35: =SUM(E4:E34) -> 795.91 | G35: =SUM(G4:G34) -> 71814.959 | H35: =SUM(H4:H34) -> 60.36 | J35: =SUM(J4:J34) -> 6166.3776 | K35: =SUM(K4:K34) -> 77981.337 | L35: =SUM(L4:L31) -> 192780

Sheet Sindagi
A1: G.P.PORWAL
A2: S.No | B2: Date | C2: GRN No | D2: Ind no/Bill No | E2: Diesel (Lts) | F2: Price | G2: Amount | H2: Petrol (Lts) | I2: Price | J2: Amount | K2: Total amount | L2: Amount paid | M2: As on Date | N2: Remarks
A3: Opening Balance | M3: NA
A4: 1 | B4: 45778 | E4: 33 | F4: 91.23 | G4: =E4*F4 -> 3010.59 | H4: 0 | I4: 0 | J4: =H4*I4 -> 0 | K4: =G4+J4 -> 3010.59 | L4: =+K4 -> 3010.59 | M4: 0
A5: 2 | B5: 45779 | E5: 0 | F5: 0 | G5: =E5*F5 -> 0 | H5: 0 | I5: 0 | J5: =H5*I5 -> 0 | K5: =G5+J5 -> 0 | L5: =+K5 -> 0 | M5: 0
A6: 3 | B6: 45780 | E6: 0 | F6: 0 | G6: =E6*F6 -> 0 | H6: 0 | I6: 0 | J6: =H6*I6 -> 0 | K6: =G6+J6 -> 0 | L6: =+K6 -> 0 | M6: 0
A7: 4 | B7: 45781 | E7: 0 | F7: 0 | G7: =E7*F7 -> 0 | H7: 0 | I7: 0 | J7: =H7*I7 -> 0 | K7: =G7+J7 -> 0 | L7: =+K7 -> 0 | M7: 0
A8: 5 | B8: 45782 | E8: 0 | F8: 0 | G8: =E8*F8 -> 0 | H8: 0 | I8: 0 | J8: =H8*I8 -> 0 | K8: =G8+J8 -> 0 | L8: =+K8 -> 0 | M8: 0
A9: 6 | B9: 45783 | E9: 0 | F9: 0 | G9: =E9*F9 -> 0 | H9: 0 | I9: 0 | J9: =H9*I9 -> 0 | K9: =G9+J9 -> 0 | L9: =+K9 -> 0 | M9: 0
A10: 7 | B10: 45784 | E10: 0 | F10: 0 | G10: =E10*F10 -> 0 | H10: 0 | I10: 0 | J10: =H10*I10 -> 0 | K10: =G10+J10 -> 0 | L10: =+K10 -> 0 | M10: 0
A11: 8 | B11: 45785 | E11: 0 | F11: 0 | G11: =E11*F11 -> 0 | H11: 0 | I11: 0 | J11: =H11*I11 -> 0 | K11: =G11+J11 -> 0 | L11: =+K11 -> 0 | M11: 0
A12: 9 | B12: 45786 | E12: 0 | F12: 0 | G12: =E12*F12 -> 0 | H12: 0 | I12: 0 | J12: =H12*I12 -> 0 | K12: =G12+J12 -> 0 | L12: =+K12 -> 0 | M12: 0
A13: 10 | B13: 45787 | E13: 0 | F13: 0 | G13: =E13*F13 -> 0 | H13: 0 | I13: 0 | J13: =H13*I13 -> 0 | K13: =G13+J13 -> 0 | L13: =+K13 -> 0 | M13: 0
A14: 11 | B14: 45788 | E14: 0 | F14: 0 | G14: =E14*F14 -> 0 | H14: 0 | I14: 0 | J14: =H14*I14 -> 0 | K14: =G14+J14 -> 0 | L14: =+K14 -> 0 | M14: 0
A15: 12 | B15: 45789 | E15: 0 | F15: 0 | G15: =E15*F15 -> 0 | H15: 0 | I15: 0 | J15: =H15*I15 -> 0 | K15: =G15+J15 -> 0 | L15: =+K15 -> 0 | M15: 0
... A33: 30 | B33: 45807 | E33: 0 | F33: 0 | G33: =E33*F33 -> 0 | H33: 0 | I33: 0 | J33: =H33*I33 -> 0 | K33: =G33+J33 -> 0 | L33: =+K33 -> 0 | M33: 0
A34: 31 | E34: 0 | F34: 0 | G34: =E34*F34 -> 0 | H34: 0 | I34: 0 | J34: =H34*I34 -> 0 | K34: =G34+J34 -> 0 | L34: =+K34 -> 0 | M34: 0
A35: 34 | E35: 0 | F35: 0 | G35: =E35*F35 -> 0 | H35: 0 | I35: 0 | J35: =H35*I35 -> 0 | K35: =G35+J35 -> 0 | L35: =+K35 -> 0 | M35: 0
A36: 35 | E36: 0 | F36: 0 | G36: =E36*F36 -> 0 | H36: 0 | I36: 0 | J36: =H36*I36 -> 0 | K36: =G36+J36 -> 0 | L36: =+K36 -> 0 | M36: 0
A37: 36 | E37: 0 | F37: 0 | G37: =E37*F37 -> 0 | H37: 0 | I37: 0 | J37: =H37*I37 -> 0 | K37: =G37+J37 -> 0 | L37: =+K37 -> 0 | M37: 0
A38: 37 | E38: 0 | F38: 0 | G38: =E38*F38 -> 0 | H38: 0 | I38: 0 | J38: =H38*I38 -> 0 | K38: =G38+J38 -> 0 | L38: =+K38 -> 0 | M38: 0
A39: 38 | E39: 0 | F39: 0 | G39: =E39*F39 -> 0 | H39: 0 | I39: 0 | J39: =H39*I39 -> 0 | K39: =G39+J39 -> 0 | L39: =+K39 -> 0 | M39: 0
A40: 39 | E40: 0 | F40: 0 | G40: =E40*F40 -> 0 | H40: 0 | I40: 0 | J40: =H40*I40 -> 0 | K40: =G40+J40 -> 0 | L40: =+K40 -> 0 | M40: 0
A41: 40 | E41: 0 | F41: 0 | G41: =E41*F41 -> 0 | H41: 0 | I41: 0 | J41: =H41*I41 -> 0 | K41: =G41+J41 -> 0 | L41: =+K41 -> 0 | M41: 0
A42: 41 | E42: 0 | F42: 0 | G42: =E42*F42 -> 0 | H42: 0 | I42: 0 | J42: =H42*I42 -> 0 | K42: =G42+J42 -> 0 | L42: =+K42 -> 0 | M42: 0
A43: 42 | E43: 0 | F43: 0 | G43: =E43*F43 -> 0 | H43: 0 | I43: 0 | J43: =H43*I43 -> 0 | K43: =G43+J43 -> 0 | L43: =+K43 -> 0 | M43: 0
E44: =SUM(E4:E43) -> 607.7 | G44: =SUM(G4:G43) -> 55440.471 | H44: =SUM(H4:H43) -> 0 | J44: =SUM(J4:J43) -> 0 | K44: =SUM(K4:K43) -> 55440.471 | L44: =SUM(L4:L43) -> 55440.471

Sheet Alemela
A1: Shiddeshwar Petroleums
A2: S.No | B2: Date | C2: GRN No | D2: Ind no/Bill No | E2: Diesel (Lts) | F2: Price | G2: Amount | H2: Petrol (Lts) | I2: Price | J2: Amount | K2: Total amount | L2: Amount paid | M2: As on Date | N2: Remarks
A3: Opening Balance | M3: 0
A4: 1 | B4: 02.05.2025 | E4: 5.47 | F4: 91.33 | G4: =E4*F4 -> 499.5751 | H4: 4.84 | I4: 103.26 | J4: =H4*I4 -> 499.7784 | K4: =G4+J4 -> 999.3535 | L4: =+K4 -> 999.3535 | M4: =M3+K4-L4 -> 0 | N4: IOCL Card
A5: 2 | B5: 05.05.2025 | E5: 0 | F5: 0 | G5: =E5*F5 -> 0 | H5: 2 | I5: 103.26 | J5: =H5*I5 -> 206.52 | K5: =G5+J5 -> 206.52 | L5: =+K5 -> 206.52 | M5: =M4+K5-L5 -> 0 | N5: IOCL Card
A6: 3 | B6: 11.05.2025 | E6: 0 | F6: 0 | G6: =E6*F6 -> 0 | H6: 4.84 | I6: 103.26 | J6: =H6*I6 -> 499.7784 | K6: =G6+J6 -> 499.7784 | L6: =+K6 -> 499.7784 | M6: =M5+K6-L6 -> 0 | N6: IOCL Card
A7: 4 | B7: 16.05.2025 | E7: 5.47 | F7: 91.33 | G7: =E7*F7 -> 499.5751 | H7: 5 | I7: 103.26 | J7: =H7*I7 -> 516.3 | K7: =G7+J7 -> 1015.8751 | L7: =+K7 -> 1015.8751 | M7: =M6+K7-L7 -> 0 | N7: IOCL Card
A8: 5 | B8: 17.05.2025 | E8: 0 | F8: 0 | G8: =E8*F8 -> 0 | H8: 6.4 | I8: 103.26 | J8: =H8*I8 -> 660.864 | K8: =G8+J8 -> 660.864 | L8: =+K8 -> 660.864 | M8: =M7+K8-L8 -> 0 | N8: IOCL Card
A9: 6 | B9: 20.05.2025 | E9: 24.09 | F9: 91.33 | G9: =E9*F9 -> 2200.1397 | H9: 4.84 | I9: 103.26 | J9: =H9*I9 -> 499.7784 | K9: =G9+J9 -> 2699.9181 | L9: =+K9 -> 2699.9181 | M9: =M8+K9-L9 -> 0 | N9: IOCL Card
A10: 7 | B10: 21.05.2025 | E10: 0 | F10: 0 | G10: =E10*F10 -> 0 | H10: 3 | I10: 103.26 | J10: =H10*I10 -> 309.78 | K10: =G10+J10 -> 309.78 | L10: =+K10 -> 309.78 | M10: =M9+K10-L10 -> 0 | N10: IOCL Card
A11: 8 | B11: 22.05.2025 | E11: 43.8 | F11: 91.33 | G11: =E11*F11 -> 4000.254 | H11: 5 | I11: 103.26 | J11: =H11*I11 -> 516.3 | K11: =G11+J11 -> 4516.554 | L11: =+K11 -> 4516.554 | M11: =M10+K11-L11 -> 0 | N11: IOCL Card
A12: 9 | B12: 24.05.2025 | E12: 0 | F12: 0 | G12: =E12*F12 -> 0 | H12: 2 | I12: 103.26 | J12: =H12*I12 -> 206.52 | K12: =G12+J12 -> 206.52 | L12: =+K12 -> 206.52 | M12: =M11+K12-L12 -> 0 | N12: IOCL Card
A13: 10 | B13: 26.05.2025 | E13: 10 | F13: 91.33 | G13: =E13*F13 -> 913.3 | H13: 0 | I13: 0 | J13: =H13*I13 -> 0 | K13: =G13+J13 -> 913.3 | L13: =+K13 -> 913.3 | M13: =M12+K13-L13 -> 0 | N13: IOCL Card
A14: 11 | B14: 28.05.2025 | E14: 101.39 | F14: 91.33 | G14: =E14*F14 -> 9259.9487 | H14: 8.32 | I14: 103.26 | J14: =H14*I14 -> 859.1232 | K14: =G14+J14 -> 10119.072 | L14: =+K14 -> 10119.072 | M14: =M13+K14-L14 -> 0 | N14: IOCL Card
A15: 12 | B15: 30.05.2025 | E15: 0 | F15: 0 | G15: =E15*F15 -> 0 | H15: 4.38 | I15: 103.26 | J15: =H15*I15 -> 452.2788 | K15: =G15+J15 -> 452.2788 | L15: =+K15 -> 452.2788 | M15: =M14+K15-L15 -> 0 | N15: IOCL Card
A16: 13 | B16: 31.05.2025 | E16: 105 | F16: 91.33 | G16: =E16*F16 -> 9589.65 | H16: 0 | I16: 0 | J16: =H16*I16 -> 0 | K16: =G16+J16 -> 9589.65 | L16: =+K16 -> 9589.65 | M16: =M15+K16-L16 -> 0 | N16: IOCL Card
A17: 14 | E17: 0 | F17: 0 | G17: =E17*F17 -> 0 | H17: 0 | I17: 0 | J17: =H17*I17 -> 0 | K17: =G17+J17 -> 0 | L17: =+K17 -> 0 | M17: =M16+K17-L17 -> 0 | N17: IOCL Card
A18: 15 | E18: 0 | F18: 0 | G18: =E18*F18 -> 0 | H18: 0 | I18: 0 | J18: =H18*I18 -> 0 | K18: =G18+J18 -> 0 | L18: =+K18 -> 0 | M18: =M17+K18-L18 -> 0 | N18: IOCL Card
A19: 16 | E19: 0 | F19: 0 | G19: =E19*F19 -> 0 | H19: 0 | I19: 0 | J19: =H19*I19 -> 0 | K19: =G19+J19 -> 0 | L19: =+K19 -> 0 | M19: =M18+K19-L19 -> 0 | N19: IOCL Card
A20: 17 | E20: 0 | F20: 0 | G20: =E20*F20 -> 0 | H20: 0 | I20: 0 | J20: =H20*I20 -> 0 | K20: =G20+J20 -> 0 | L20: =+K20 -> 0 | M20: =M19+K20-L20 -> 0 | N20: IOCL Card
A21: 18 | E21: 0 | F21: 0 | G21: =E21*F21 -> 0 | H21: 0 | I21: 0 | J21: =H21*I21 -> 0 | K21: =G21+J21 -> 0 | L21: =+K21 -> 0 | M21: =M20+K21-L21 -> 0 | N21: IOCL Card
A22: 19 | E22: 0 | F22: 0 | G22: =E22*F22 -> 0 | H22: 0 | I22: 0 | J22: =H22*I22 -> 0 | K22: =G22+J22 -> 0 | L22: =+K22 -> 0 | M22: =M21+K22-L22 -> 0 | N22: IOCL Card
A23: 20 | E23: 0 | F23: 0 | G23: =E23*F23 -> 0 | H23: 0 | I23: 0 | J23: =H23*I23 -> 0 | K23: =G23+J23 -> 0 | L23: =+K23 -> 0 | M23: =M22+K23-L23 -> 0
A24: 21 | E24: 0 | F24: 0 | G24: =E24*F24 -> 0 | H24: 0 | I24: 0 | J24: =H24*I24 -> 0 | K24: =G24+J24 -> 0 | L24: =+K24 -> 0 | M24: =M23+K24-L24 -> 0
A25: 22 | E25: 0 | F25: 0 | G25: =E25*F25 -> 0 | H25: 0 | I25: 0 | J25: =H25*I25 -> 0 | K25: =G25+J25 -> 0 | L25: =+K25 -> 0 | M25: =M24+K25-L25 -> 0
A26: 23 | E26: 0 | F26: 0 | G26: =E26*F26 -> 0 | H26: 0 | I26: 0 | J26: =H26*I26 -> 0 | K26: =G26+J26 -> 0 | L26: =+K26 -> 0 | M26: =M25+K26-L26 -> 0
A27: 24 | E27: 0 | F27: 0 | G27: =E27*F27 -> 0 | H27: 0 | I27: 0 | J27: =H27*I27 -> 0 | K27: =G27+J27 -> 0 | L27: =+K27 -> 0 | M27: =M26+K27-L27 -> 0
A28: 25 | E28: 0 | F28: 0 | G28: =E28*F28 -> 0 | H28: 0 | I28: 0 | J28: =H28*I28 -> 0 | K28: =G28+J28 -> 0 | L28: =+K28 -> 0 | M28: =M27+K28-L28 -> 0
A29: 26 | E29: 0 | F29: 0 | G29: =E29*F29 -> 0 | H29: 0 | I29: 0 | J29: =H29*I29 -> 0 | K29: =G29+J29 -> 0 | L29: =+K29 -> 0 | M29: =M28+K29-L29 -> 0
A30: 27 | E30: 0 | F30: 0 | G30: =E30*F30 -> 0 | H30: 0 | I30: 0 | J30: =H30*I30 -> 0 | K30: =G30+J30 -> 0 | L30: =+K30 -> 0 | M30: =M29+K30-L30 -> 0
A31: 28 | E31: 0 | F31: 0 | G31: =E31*F31 -> 0 | H31: 0 | I31: 0 | J31: =H31*I31 -> 0 | K31: =G31+J31 -> 0 | L31: =+K31 -> 0 | M31: =M30+K31-L31 -> 0
A32: 29 | E32: 0 | F32: 0 | G32: =E32*F32 -> 0 | H32: 0 | I32: 0 | J32: =H32*I32 -> 0 | K32: =G32+J32 -> 0 | L32: =+K32 -> 0 | M32: 0
A33: 30 | E33: 0 | F33: 0 | G33: =E33*F33 -> 0 | H33: 0 | I33: 0 | J33: =H33*I33 -> 0 | K33: =G33+J33 -> 0 | L33: =+K33 -> 0 | M33: 0
A34: 31 | E34: 0 | F34: 0 | G34: =E34*F34 -> 0 | H34: 0 | I34: 0 | J34: =H34*I34 -> 0 | K34: =G34+J34 -> 0 | L34: =+K34 -> 0 | M34: 0
A35: 35 | E35: 0 | F35: 0 | G35: =E35*F35 -> 0 | H35: 0 | I35: 0 | J35: =H35*I35 -> 0 | K35: =G35+J35 -> 0 | L35: =+K35 -> 0 | M35: 0
A36: 36 | E36: 0 | F36: 0 | G36: =E36*F36 -> 0 | H36: 0 | I36: 0 | J36: =H36*I36 -> 0 | K36: =G36+J36 -> 0 | L36: =+K36 -> 0 | M36: 0
A37: 37 | E37: 0 | F37: 0 | G37: =E37*F37 -> 0 | H37: 0 | I37: 0 | J37: =H37*I37 -> 0 | K37: =G37+J37 -> 0 | L37: =+K37 -> 0 | M37: 0
A38: 38 | E38: 0 | F38: 0 | G38: =E38*F38 -> 0 | H38: 0 | I38: 0 | J38: =H38*I38 -> 0 | K38: =G38+J38 -> 0 | L38: =+K38 -> 0 | M38: 0
A39: 39 | E39: 0 | F39: 0 | G39: =E39*F39 -> 0 | H39: 0 | I39: 0 | J39: =H39*I39 -> 0 | K39: =G39+J39 -> 0 | L39: =+K39 -> 0 | M39: 0
A40: 40 | E40: 0 | F40: 0 | G40: =E40*F40 -> 0 | H40: 0 | I40: 0 | J40: =H40*I40 -> 0 | K40: =G40+J40 -> 0 | L40: =+K40 -> 0 | M40: 0
A41: 41 | E41: 0 | F41: 0 | G41: =E41*F41 -> 0 | H41: 0 | I41: 0 | J41: =H41*I41 -> 0 | K41: =G41+J41 -> 0 | L41: =+K41 -> 0 | M41: 0
A42: 42 | E42: 0 | F42: 0 | G42: =E42*F42 -> 0 | J42: =H42*I42 -> 0 | K42: =G42+J42 -> 0 | L42: =+K42 -> 0 | M42: 0
E43: =SUM(E4:E42) -> 295.22 | G43: =SUM(G4:G42) -> 26962.443 | H43: =SUM(H4:H42) -> 50.62 | J43: =SUM(J4:J42) -> 5227.0212 | K43: =SUM(K4:K42) -> 32189.464 | L43: =SUM(L4:L42) -> 32189.464
L46: 41648.541
L47: =L43+L46 -> 73838.005

Sheet Munavalli(KUWSDB)
A1: Shahapur Petroleum
A2: S.No | B2: Date | C2: GRN No | D2: Ind No/Bill No | E2: Diesel (Lts) | F2: Price | G2: Amount | H2: Petrol (Lts) | I2: Price | J2: Amount | K2: Total amount | L2: Amount paid | M2: As on date | N2: Remarks
D3: Opening Balance | K3: 58857 | M3: =+K3 -> 58857
A4: 1 | B4: 45778 | E4: 0 | F4: 0 | G4: =E4*F4 -> 0 | H4: 0 | I4: 0 | J4: =H4*I4 -> 0 | K4: =G4+J4 -> 0 | L4: 0 | M4: =M3+K4-L4 -> 58857 | S4: 0
A5: 2 | B5: 45779 | E5: 857 | F5: 91.26 | G5: =E5*F5 -> 78209.82 | H5: 7 | I5: 103.18 | J5: =H5*I5 -> 722.26 | K5: =G5+J5 -> 78932.08 | L5: 0 | M5: =M4+K5-L5 -> 137789.08 | S5: 0
A6: 3 | B6: 45780 | E6: 435 | F6: 91.26 | G6: =E6*F6 -> 39698.1 | H6: 0 | I6: 0 | J6: =H6*I6 -> 0 | K6: =G6+J6 -> 39698.1 | L6: =+K6 -> 39698.1 | M6: =M5+K6-L6 -> 137789.08 | S6: 39698.1
A7: 4 | B7: 45780 | D7: IOCL | E7: 100 | F7: 91.18 | G7: =E7*F7 -> 9118 | H7: 0 | I7: 0 | J7: =H7*I7 -> 0 | K7: =G7+J7 -> 9118 | L7: =+K7 -> 9118 | M7: =M6+K7-L7 -> 137789.08 | S7: =+R7 -> 0
A8: 5 | B8: 45781 | D8: 540 | E8: 540 | F8: 91.26 | G8: =E8*F8 -> 49280.4 | H8: 5 | I8: 103.18 | J8: =H8*I8 -> 515.9 | K8: =G8+J8 -> 49796.3 | L8: 100000 | M8: =M7+K8-L8 -> 87585.38 | S8: 100000
A9: 6 | B9: 45782 | E9: 607 | F9: 91.26 | G9: =E9*F9 -> 55394.82 | H9: 10 | I9: 103.18 | J9: =H9*I9 -> 1031.8 | K9: =G9+J9 -> 56426.62 | L9: 0 | M9: =M8+K9-L9 -> 144012 | S9: 0
A10: 7 | B10: 45783 | E10: 650 | F10: 91.26 | G10: =E10*F10 -> 59319 | H10: 10 | I10: 103.18 | J10: =H10*I10 -> 1031.8 | K10: =G10+J10 -> 60350.8 | L10: 0 | M10: =M9+K10-L10 -> 204362.8 | S10: 0
A11: 8 | B11: 45784 | E11: 635 | F11: 91.26 | G11: =E11*F11 -> 57950.1 | H11: 0 | I11: 0 | J11: =H11*I11 -> 0 | K11: =G11+J11 -> 57950.1 | L11: 203331 | M11: =M10+K11-L11 -> 58981.9 | S11: 203331
A12: 9 | B12: 45785 | E12: 1046 | F12: 91.26 | G12: =E12*F12 -> 95457.96 | H12: 10 | I12: 103.18 | J12: =H12*I12 -> 1031.8 | K12: =G12+J12 -> 96489.76 | L12: 0 | M12: =M11+K12-L12 -> 155471.66 | Q12: 4019 | S12: 0
A13: 10 | B13: 45786 | E13: 1125 | F13: 91.26 | G13: =E13*F13 -> 102667.5 | H13: 0 | I13: 0 | J13: =H13*I13 -> 0 | K13: =G13+J13 -> 102667.5 | L13: 0 | M13: =M12+K13-L13 -> 258139.16 | Q13: 4208 | S13: 0
A14: 11 | B14: 45787 | E14: 640 | F14: 91.26 | G14: =E14*F14 -> 58406.4 | H14: 20 | I14: 103.18 | J14: =H14*I14 -> 2063.6 | K14: =G14+J14 -> 60470 | L14: 0 | M14: =M13+K14-L14 -> 318609.16 | Q14: =Q13-Q12 -> 189 | S14: 0
A15: 12 | B15: 45788 | E15: 825 | F15: 91.26 | G15: =E15*F15 -> 75289.5 | H15: 0 | I15: 0 | J15: =H15*I15 -> 0 | K15: =G15+J15 -> 75289.5 | L15: 0 | M15: =M14+K15-L15 -> 393898.66 | S15: 0
A16: 13 | B16: 45789 | E16: 1034 | F16: 91.26 | G16: =E16*F16 -> 94362.84 | H16: 0 | I16: 0 | J16: =H16*I16 -> 0 | K16: =G16+J16 -> 94362.84 | L16: 180000 | M16: =M15+K16-L16 -> 308261.5 | S16: 180000
A17: 14 | B17: 45790 | D17: IOCL | E17: 420 | F17: 91.19 | G17: =E17*F17 -> 38299.8 | H17: 0 | I17: 0 | J17: =H17*I17 -> 0 | K17: =G17+J17 -> 38299.8 | L17: =+K17 -> 38299.8 | M17: =M16+K17-L17 -> 308261.5 | S17: =+R17 -> 0
A18: 15 | B18: 45791 | D18: IOCL | E18: 700 | F18: 91.19 | G18: =E18*F18 -> 63833 | H18: 0 | I18: 0 | J18: =H18*I18 -> 0 | K18: =G18+J18 -> 63833 | L18: =+K18 -> 63833 | M18: =M17+K18-L18 -> 308261.5 | S18: =+R18 -> 0
A19: 16 | B19: 45792 | E19: 568.35 | F19: 91.26 | G19: =E19*F19 -> 51867.621 | H19: 15 | I19: 103.18 | J19: =H19*I19 -> 1547.7 | K19: =G19+J19 -> 53415.321 | L19: 300000 | M19: =M18+K19-L19 -> 61676.821 | S19: 300000
A20: 17 | B20: 45793 | E20: 800 | F20: 91.26 | G20: =E20*F20 -> 73008 | H20: 30 | I20: 103.18 | J20: =H20*I20 -> 3095.4 | K20: =G20+J20 -> 76103.4 | L20: 0 | M20: =M19+K20-L20 -> 137780.22 | S20: 0
A21: 18 | B21: 45794 | E21: 830 | F21: 91.26 | G21: =E21*F21 -> 75745.8 | H21: 0 | I21: 0 | J21: =H21*I21 -> 0 | K21: =G21+J21 -> 75745.8 | L21: 0 | M21: =M20+K21-L21 -> 213526.02 | S21: 0
A22: 19 | B22: 45795 | E22: 155 | F22: 91.26 | G22: =E22*F22 -> 14145.3 | H22: 5 | I22: 103.18 | J22: =H22*I22 -> 515.9 | K22: =G22+J22 -> 14661.2 | L22: 0 | M22: =M21+K22-L22 -> 228187.22 | S22: 0
A23: 20 | B23: 45796 | E23: 847 | F23: 91.26 | G23: =E23*F23 -> 77297.22 | H23: 0 | I23: 103.18 | J23: =H23*I23 -> 0 | K23: =G23+J23 -> 77297.22 | L23: 0 | M23: =M22+K23-L23 -> 305484.44 | S23: 0
A24: 21 | B24: 45797 | E24: 780 | F24: 91.26 | G24: =E24*F24 -> 71182.8 | H24: 10 | I24: 103.18 | J24: =H24*I24 -> 1031.8 | K24: =G24+J24 -> 72214.6 | L24: 0 | M24: =M23+K24-L24 -> 377699.04 | S24: 0
A25: 22 | B25: 45798 | E25: 689 | F25: 91.26 | G25: =E25*F25 -> 62878.14 | H25: 0 | I25: 0 | J25: =H25*I25 -> 0 | K25: =G25+J25 -> 62878.14 | L25: 200000 | M25: =M24+K25-L25 -> 240577.18 | S25: 200000
A26: 23 | B26: 45799 | E26: 315 | F26: 91.26 | G26: =E26*F26 -> 28746.9 | H26: 10 | I26: 103.18 | J26: =H26*I26 -> 1031.8 | K26: =G26+J26 -> 29778.7 | L26: 0 | M26: =M25+K26-L26 -> 270355.88 | S26: 0
A27: 24 | B27: 45800 | E27: 560 | F27: 91.26 | G27: =E27*F27 -> 51105.6 | H27: 5 | I27: 103.18 | J27: =H27*I27 -> 515.9 | K27: =G27+J27 -> 51621.5 | L27: 0 | M27: =M26+K27-L27 -> 321977.38 | S27: 0
A28: 25 | B28: 45801 | E28: 216.59 | F28: 91.26 | G28: =E28*F28 -> 19766.003 | H28: 5 | I28: 103.18 | J28: =H28*I28 -> 515.9 | K28: =G28+J28 -> 20281.903 | L28: 0 | M28: =M27+K28-L28 -> 342259.28 | S28: 0
A29: 26 | B29: 45802 | E29: 55 | F29: 91.26 | G29: =E29*F29 -> 5019.3 | H29: 0 | I29: 0 | J29: =H29*I29 -> 0 | K29: =G29+J29 -> 5019.3 | L29: 0 | M29: =M28+K29-L29 -> 347278.58 | S29: 0
A30: 27 | B30: 45803 | E30: 137 | F30: 91.26 | G30: =E30*F30 -> 12502.62 | H30: 11 | I30: 103.18 | J30: =H30*I30 -> 1134.98 | K30: =G30+J30 -> 13637.6 | L30: 0 | M30: =M29+K30-L30 -> 360916.18 | S30: 0
A31: 28 | B31: 45804 | D31: 305.63 | E31: 305.63 | F31: 91.26 | G31: =E31*F31 -> 27891.794 | H31: 7 | I31: 103.18 | J31: =H31*I31 -> 722.26 | K31: =G31+J31 -> 28614.054 | L31: 350000 | M31: =M30+K31-L31 -> 39530.238 | S31: 350000
A32: 29 | B32: 45805 | E32: 72 | F32: 91.26 | G32: =E32*F32 -> 6570.72 | H32: 5 | I32: 103.18 | J32: =H32*I32 -> 515.9 | K32: =G32+J32 -> 7086.62 | L32: 0 | M32: =M31+K32-L32 -> 46616.858 | S32: 0
A33: 30 | B33: 45806 | E33: 246 | F33: 91.26 | G33: =E33*F33 -> 22449.96 | H33: 11.32 | I33: 103.18 | J33: =H33*I33 -> 1167.9976 | K33: =G33+J33 -> 23617.958 | L33: 0 | M33: =M32+K33-L33 -> 70234.816 | S33: 0
A34: 31 | B34: 45807 | E34: 266.6 | F34: 91.26 | G34: =E34*F34 -> 24329.916 | H34: 0 | I34: 0 | J34: =H34*I34 -> 0 | K34: =G34+J34 -> 24329.916 | L34: 0 | M34: =M33+K34-L34 -> 94564.732 | S34: 0
A35: 32 | B35: 45808 | E35: 125 | F35: 91.26 | G35: =E35*F35 -> 11407.5 | H35: 10 | I35: 103.18 | J35: =H35*I35 -> 1031.8 | K35: =G35+J35 -> 12439.3 | L35: 0 | M35: =M34+K35-L35 -> 107004.03 | S35: 0
E36: 0 | F36: 91.26 | G36: =E36*F36 -> 0 | M36: =M35+K36-L36 -> 107004.03
E37: 0 | F37: 91.26 | G37: =E37*F37 -> 0 | M37: =M36+K37-L37 -> 107004.03
A38: 33 | E38: 0 | F38: 0 | G38: =E38*F38 -> 0 | H38: 0 | I38: 0 | J38: =H38*I38 -> 0 | K38: =G38+J38 -> 0 | L38: 0 | S38: 0
E39: =SUM(E4:E38) -> 16582.17 | G39: =SUM(G4:G38) -> 1513202.4 | H39: =SUM(H4:H35) -> 186.32 | J39: =SUM(J4:J38) -> 19224.498 | K39: =SUM(K4:K35) -> 1532426.9 | L39: =SUM(L4:L38) -> 1484279.9 | S39: =SUM(S4:S38) -> 1373029.1
L40: 1373029.1
E41: 1220 | L41: =L39-L40 -> 111250.8

Sheet  Shankeshwar
A1: S R PATIL
A2: S.No | B2: Date | C2: GRN No | D2: Ind no/Bill No | E2: Diesel (Lts) | F2: Price | G2: Amount | H2: Petrol (Lts) | I2: Price | J2: Amount | K2: Total amount | L2: Amount paid | M2: As on Date | N2: Remarks
A3: Opening Balance | M3: 0
A4: 1 | B4: 45778 | C4: 0 | D4: 0 | F4: 0 | G4: 0 | H4: =F4*G4 -> 0 | I4: 0 | J4: 0 | K4: =I4*J4 -> 0 | L4: =H4+K4 -> 0 | M4: 0 | N4: =N3+L4-M4 -> 0
A5: 2 | B5: 45779 | C5: 0 | D5: 0 | F5: 0 | G5: 0 | H5: =F5*G5 -> 0 | I5: 0 | J5: 0 | K5: =I5*J5 -> 0 | L5: =H5+K5 -> 0 | M5: 0 | N5: =N4+L5-M5 -> 0
A6: 3 | B6: 45780 | C6: 0 | D6: 0 | F6: 0 | G6: 0 | H6: =F6*G6 -> 0 | I6: 0 | J6: 0 | K6: =I6*J6 -> 0 | L6: =H6+K6 -> 0 | M6: 0 | N6: =N5+L6-M6 -> 0
A7: 4 | B7: 45781 | C7: 0 | D7: 0 | F7: 0 | G7: 0 | H7: =F7*G7 -> 0 | I7: 0 | J7: 0 | K7: =I7*J7 -> 0 | L7: =H7+K7 -> 0 | M7: 0 | N7: =N6+L7-M7 -> 0
A8: 5 | B8: 45782 | C8: 0 | D8: 0 | F8: 0 | G8: 0 | H8: =F8*G8 -> 0 | I8: 0 | J8: 0 | K8: =I8*J8 -> 0 | L8: =H8+K8 -> 0 | M8: 0 | N8: =N7+L8-M8 -> 0
A9: 6 | B9: 45783 | C9: 0 | D9: 0 | F9: 0 | G9: 0 | H9: =F9*G9 -> 0 | I9: 0 | J9: 0 | K9: =I9*J9 -> 0 | L9: =H9+K9 -> 0 | M9: 0 | N9: =N8+L9-M9 -> 0
A10: 7 | B10: 45784 | C10: 0 | D10: 0 | F10: 0 | G10: 0 | H10: =F10*G10 -> 0 | I10: 0 | J10: 0 | K10: =I10*J10 -> 0 | L10: =H10+K10 -> 0 | M10: 0 | N10: =N9+L10-M10 -> 0
A11: 8 | B11: 45785 | C11: 0 | D11: 0 | F11: 0 | G11: 0 | H11: =F11*G11 -> 0 | I11: 0 | J11: 0 | K11: =I11*J11 -> 0 | L11: =H11+K11 -> 0 | M11: 0 | N11: =N10+L11-M11 -> 0
A12: 9 | B12: 45786 | C12: 0 | D12: 0 | F12: 0 | G12: 0 | H12: =F12*G12 -> 0 | I12: 0 | J12: 0 | K12: =I12*J12 -> 0 | L12: =H12+K12 -> 0 | M12: 0 | N12: =N11+L12-M12 -> 0
A13: 10 | B13: 45787 | C13: 0 | D13: 0 | F13: 0 | G13: 0 | H13: =F13*G13 -> 0 | I13: 0 | J13: 0 | K13: =I13*J13 -> 0 | L13: =H13+K13 -> 0 | M13: 0 | N13: =N12+L13-M13 -> 0
A14: 11 | B14: 45788 | C14: 0 | D14: 0 | F14: 0 | G14: 0 | H14: =F14*G14 -> 0 | I14: 0 | J14: 0 | K14: =I14*J14 -> 0 | L14: =H14+K14 -> 0 | M14: 0 | N14: =N13+L14-M14 -> 0
A15: 12 | B15: 45789 | C15: 0 | D15: 0 | F15: 0 | G15: 0 | H15: =F15*G15 -> 0 | I15: 0 | J15: 0 | K15: =I15*J15 -> 0 | L15: =H15+K15 -> 0 | M15: 0 | N15: =N14+L15-M15 -> 0
A16: 13 | B16: 45790 | C16: 0 | D16: 0 | F16: 0 | G16: 0 | H16: =F16*G16 -> 0 | I16: 0 | J16: 0 | K16: =I16*J16 -> 0 | L16: =H16+K16 -> 0 | M16: 0 | N16: =N15+L16-M16 -> 0
A17: 14 | B17: 45791 | C17: 0 | D17: 0 | F17: 0 | G17: 0 | H17: =F17*G17 -> 0 | I17: 0 | J17: 0 | K17: =I17*J17 -> 0 | L17: =H17+K17 -> 0 | M17: 0 | N17: 0
A18: 15 | B18: 45792 | C18: 0 | D18: 0 | F18: 0 | G18: 0 | H18: =F18*G18 -> 0 | I18: 0 | J18: 0 | K18: =I18*J18 -> 0 | L18: =H18+K18 -> 0 | M18: 0 | N18: 0
A19: 16 | B19: 45793 | C19: 0 | D19: 0 | F19: 0 | G19: 0 | H19: =F19*G19 -> 0 | I19: 0 | J19: 0 | K19: =I19*J19 -> 0 | L19: =H19+K19 -> 0 | M19: 0 | N19: 0
A20: 17 | B20: 45794 | C20: 0 | D20: 0 | F20: 0 | G20: 0 | H20: =F20*G20 -> 0 | I20: 0 | J20: 0 | K20: =I20*J20 -> 0 | L20: =H20+K20 -> 0 | M20: 0 | N20: 0
A21: 18 | B21: 45795 | C21: 0 | D21: 0 | F21: 0 | G21: 0 | H21: =F21*G21 -> 0 | I21: 0 | J21: 0 | K21: =I21*J21 -> 0 | L21: =H21+K21 -> 0 | M21: 0 | N21: 0
A22: 19 | B22: 45796 | C22: 0 | D22: 0 | F22: 0 | G22: 0 | H22: =F22*G22 -> 0 | I22: 0 | J22: 0 | K22: =I22*J22 -> 0 | L22: =H22+K22 -> 0 | M22: 0 | N22: 0
A23: 20 | B23: 45797 | C23: 0 | D23: 0 | F23: 0 | G23: 0 | H23: =F23*G23 -> 0 | I23: 0 | J23: 0 | K23: =I23*J23 -> 0 | L23: =H23+K23 -> 0 | M23: 0 | N23: 0
A24: 21 | B24: 45798 | C24: 0 | D24: 0 | F24: 0 | G24: 0 | H24: =F24*G24 -> 0 | I24: 0 | J24: 0 | K24: =I24*J24 -> 0 | L24: =H24+K24 -> 0 | M24: 0 | N24: 0
A25: 22 | B25: 45799 | C25: 0 | D25: 0 | F25: 0 | G25: 0 | H25: =F25*G25 -> 0 | I25: 0 | J25: 0 | K25: =I25*J25 -> 0 | L25: =H25+K25 -> 0 | M25: 0 | N25: 0
A26: 23 | B26: 45800 | C26: 0 | D26: 0 | F26: 0 | G26: 0 | H26: =F26*G26 -> 0 | I26: 0 | J26: 0 | K26: =I26*J26 -> 0 | L26: =H26+K26 -> 0 | M26: 0 | N26: 0
A27: 24 | B27: 45801 | C27: 0 | D27: 0 | F27: 32 | G27: 91.3 | H27: =F27*G27 -> 2921.6 | I27: 0 | J27: 0 | K27: =I27*J27 -> 0 | L27: =H27+K27 -> 2921.6 | M27: 0
A28: 25 | B28: 45802 | C28: 0 | D28: 0 | F28: 0 | G28: 91.3 | H28: =F28*G28 -> 0 | I28: 0 | J28: 0 | K28: =I28*J28 -> 0 | L28: =H28+K28 -> 0 | M28: 0
A29: 26 | B29: 45803 | C29: 0 | D29: 0 | F29: 55 | G29: 91.3 | H29: =F29*G29 -> 5021.5 | I29: 0 | J29: 0 | K29: =I29*J29 -> 0 | L29: =H29+K29 -> 5021.5 | M29: 0
A30: 27 | B30: 45804 | C30: 0 | D30: 0 | F30: 0 | G30: 91.3 | H30: =F30*G30 -> 0 | I30: 0 | J30: 0 | K30: =I30*J30 -> 0 | L30: =H30+K30 -> 0 | M30: 0
A31: 28 | B31: 45805 | C31: 0 | D31: 0 | F31: 54.76 | G31: 91.3 | H31: =F31*G31 -> 4999.588 | I31: 0 | J31: 0 | K31: =I31*J31 -> 0 | L31: =H31+K31 -> 4999.588 | M31: 0
A32: 29 | B32: 45806 | C32: 0 | D32: 0 | F32: 54.76 | G32: 91.3 | H32: =F32*G32 -> 4999.588 | I32: 4.84 | J32: 103.22 | K32: =I32*J32 -> 499.5848 | L32: =H32+K32 -> 5499.1728 | M32: 0
A33: 30 | B33: 45807 | C33: 0 | D33: 0 | F33: 0 | G33: 0 | H33: =F33*G33 -> 0 | I33: 0 | J33: 0 | K33: =I33*J33 -> 0 | L33: =H33+K33 -> 0 | M33: 0
A34: 31 | B34: 45808 | C34: 0 | D34: 0 | F34: 120.48 | G34: 91.3 | H34: =F34*G34 -> 10999.824 | I34: 4.84 | J34: 103.22 | K34: =I34*J34 -> 499.5848 | L34: =H34+K34 -> 11499.409 | M34: 0
E35: =SUM(E4:E34) -> 0 | F35: =SUM(F4:F34) -> 317 | H35: =SUM(H4:H34) -> 28942.1 | I35: =SUM(I4:I34) -> 9.68 | K35: =SUM(K4:K34) -> 999.1696 | L35: =SUM(L4:L34) -> 29941.27

Sheet Ankalgi
A1: Nirwani Petroleums
A2: S.No | B2: Date | C2: GRN No | D2: Ind no/Bill No | E2: Diesel (Lts) | F2: Price | G2: Amount | H2: Petrol (Lts) | I2: Price | J2: Amount | K2: Total amount | L2: Amount paid | M2: As on Date | N2: Remarks
A3: Opening Balance | M3: 0
A4: 1 | B4: 45778 | C4: 0 | E4: 0 | F4: 0 | G4: =E4*F4 -> 0 | H4: 0 | I4: 0 | J4: =H4*I4 -> 0 | K4: =G4+J4 -> 0 | L4: 0 | M4: =M3+K4-L4 -> 0
A5: 2 | B5: 45779 | C5: 0 | E5: 0 | F5: 0 | G5: =E5*F5 -> 0 | H5: 0 | I5: 0 | J5: =H5*I5 -> 0 | K5: =G5+J5 -> 0 | L5: 0 | M5: =M4+K5-L5 -> 0
A6: 3 | B6: 45780 | C6: 0 | E6: 0 | F6: 0 | G6: =E6*F6 -> 0 | H6: 0 | I6: 0 | J6: =H6*I6 -> 0 | K6: =G6+J6 -> 0 | L6: 0 | M6: =M5+K6-L6 -> 0
A7: 4 | B7: 45781 | C7: 0 | E7: 0 | F7: 0 | G7: =E7*F7 -> 0 | H7: 0 | I7: 0 | J7: =H7*I7 -> 0 | K7: =G7+J7 -> 0 | L7: 0 | M7: =M6+K7-L7 -> 0
A8: 5 | B8: 45782 | C8: 0 | E8: 0 | F8: 0 | G8: =E8*F8 -> 0 | H8: 0 | I8: 0 | J8: =H8*I8 -> 0 | K8: =G8+J8 -> 0 | L8: 0 | M8: =M7+K8-L8 -> 0
A9: 6 | B9: 45783 | C9: 0 | E9: 0 | F9: 0 | G9: =E9*F9 -> 0 | H9: 0 | I9: 0 | J9: =H9*I9 -> 0 | K9: =G9+J9 -> 0 | L9: 0 | M9: =M8+K9-L9 -> 0
A10: 7 | B10: 45784 | C10: 0 | E10: 0 | F10: 0 | G10: =E10*F10 -> 0 | H10: 0 | I10: 0 | J10: =H10*I10 -> 0 | K10: =G10+J10 -> 0 | L10: 0 | M10: =M9+K10-L10 -> 0
A11: 8 | B11: 45785 | C11: 0 | E11: 0 | F11: 0 | G11: =E11*F11 -> 0 | H11: 0 | I11: 0 | J11: =H11*I11 -> 0 | K11: =G11+J11 -> 0 | L11: 0 | M11: =M10+K11-L11 -> 0
A12: 9 | B12: 45786 | C12: 0 | E12: 0 | F12: 0 | G12: =E12*F12 -> 0 | H12: 0 | I12: 0 | J12: =H12*I12 -> 0 | K12: =G12+J12 -> 0 | L12: 0 | M12: =M11+K12-L12 -> 0
A13: 10 | B13: 45787 | C13: 0 | E13: 112.92 | F13: 91.14 | G13: =E13*F13 -> 10291.529 | H13: 6 | I13: 103.05 | J13: =H13*I13 -> 618.3 | K13: =G13+J13 -> 10909.829 | L13: =+K13 -> 10909.829 | M13: =M12+K13-L13 -> 0
A14: 11 | B14: 45788 | C14: 0 | E14: 0 | F14: 0 | G14: =E14*F14 -> 0 | H14: 0 | I14: 0 | J14: =H14*I14 -> 0 | K14: =G14+J14 -> 0 | L14: =+K14 -> 0 | M14: =M13+K14-L14 -> 0
A15: 12 | B15: 45789 | C15: 0 | E15: 0 | F15: 0 | G15: =E15*F15 -> 0 | H15: 0 | I15: 0 | J15: =H15*I15 -> 0 | K15: =G15+J15 -> 0 | L15: =+K15 -> 0 | M15: =M14+K15-L15 -> 0
A16: 13 | B16: 45790 | C16: 0 | E16: 0 | F16: 0 | G16: =E16*F16 -> 0 | H16: 6 | I16: 103.05 | J16: =H16*I16 -> 618.3 | K16: =G16+J16 -> 618.3 | L16: =+K16 -> 618.3 | M16: =M15+K16-L16 -> 0
A17: 14 | B17: 45791 | C17: 0 | E17: 0 | F17: 0 | G17: =E17*F17 -> 0 | H17: 6 | I17: 103.5 | J17: =H17*I17 -> 621 | K17: =G17+J17 -> 621 | L17: =+K17 -> 621 | M17: 0
A18: 15 | B18: 45792 | C18: 0 | E18: 20 | F18: 91.14 | G18: =E18*F18 -> 1822.8 | H18: 0 | I18: 0 | J18: =H18*I18 -> 0 | K18: =G18+J18 -> 1822.8 | L18: =+K18 -> 1822.8 | M18: 0
A19: 16 | B19: 45793 | C19: 0 | E19: 0 | F19: 0 | G19: =E19*F19 -> 0 | H19: 0 | I19: 0 | J19: =H19*I19 -> 0 | K19: =G19+J19 -> 0 | L19: =+K19 -> 0 | M19: 0
A20: 17 | B20: 45794 | C20: 0 | E20: 0 | F20: 0 | G20: =E20*F20 -> 0 | H20: 0 | I20: 0 | J20: =H20*I20 -> 0 | K20: =G20+J20 -> 0 | L20: 0 | M20: 0
A21: 18 | B21: 45795 | C21: 0 | E21: 0 | F21: 0 | G21: =E21*F21 -> 0 | H21: 0 | I21: 0 | J21: =H21*I21 -> 0 | K21: =G21+J21 -> 0 | L21: 0 | M21: 0
A22: 19 | B22: 45796 | C22: 0 | E22: 0 | F22: 0 | G22: =E22*F22 -> 0 | H22: 0 | I22: 0 | J22: =H22*I22 -> 0 | K22: =G22+J22 -> 0 | L22: 0 | M22: 0
A23: 20 | B23: 45797 | C23: 0 | E23: 0 | F23: 0 | G23: =E23*F23 -> 0 | H23: 0 | I23: 0 | J23: =H23*I23 -> 0 | K23: =G23+J23 -> 0 | L23: 0 | M23: 0
A24: 21 | B24: 45798 | C24: 0 | E24: 0 | F24: 0 | G24: =E24*F24 -> 0 | H24: 0 | I24: 0 | J24: =H24*I24 -> 0 | K24: =G24+J24 -> 0 | L24: 0 | M24: 0
A25: 22 | B25: 45799 | C25: 0 | E25: 0 | F25: 0 | G25: =E25*F25 -> 0 | H25: 0 | I25: 0 | J25: =H25*I25 -> 0 | K25: =G25+J25 -> 0 | L25: 0 | M25: 0
A26: 23 | B26: 45800 | C26: 0 | E26: 0 | F26: 0 | G26: =E26*F26 -> 0 | H26: 0 | I26: 0 | J26: =H26*I26 -> 0 | K26: =G26+J26 -> 0 | L26: 0 | M26: 0
A27: 24 | B27: 45801 | C27: 0 | E27: 0 | F27: 0 | G27: =E27*F27 -> 0 | H27: 0 | I27: 0 | J27: =H27*I27 -> 0 | K27: =G27+J27 -> 0 | L27: 0
A28: 25 | B28: 45802 | C28: 0 | E28: 0 | F28: 0 | G28: =E28*F28 -> 0 | H28: 0 | I28: 0 | J28: =H28*I28 -> 0 | K28: =G28+J28 -> 0 | L28: 0
A29: 26 | B29: 45803 | C29: 0 | E29: 0 | F29: 0 | G29: =E29*F29 -> 0 | H29: 0 | I29: 0 | J29: =H29*I29 -> 0 | K29: =G29+J29 -> 0 | L29: 0
A30: 27 | B30: 45804 | C30: 0 | E30: 0 | F30: 0 | G30: =E30*F30 -> 0 | H30: 0 | I30: 0 | J30: =H30*I30 -> 0 | K30: =G30+J30 -> 0 | L30: 0
A31: 28 | B31: 45805 | C31: 0 | E31: 0 | F31: 0 | G31: =E31*F31 -> 0 | H31: 0 | I31: 0 | J31: =H31*I31 -> 0 | K31: =G31+J31 -> 0 | L31: 0
A32: 29 | B32: 45806 | C32: 0 | E32: 0 | F32: 0 | G32: =E32*F32 -> 0 | H32: 0 | I32: 0 | J32: =H32*I32 -> 0 | K32: =G32+J32 -> 0 | L32: 0
A33: 30 | B33: 45807 | C33: 0 | E33: 0 | F33: 0 | G33: =E33*F33 -> 0 | H33: 0 | I33: 0 | J33: =H33*I33 -> 0 | K33: =G33+J33 -> 0 | L33: 0
A34: 31 | B34: 45808 | C34: 0 | E34: 0 | F34: 0 | G34: =E34*F34 -> 0 | H34: 0 | I34: 0 | J34: =H34*I34 -> 0 | K34: =G34+J34 -> 0 | L34: =+K34 -> 0
E35: =SUM(E4:E34) -> 132.92 | G35: =SUM(G4:G34) -> 12114.329 | H35: =SUM(H4:H34) -> 18 | J35: =SUM(J4:J34) -> 1857.6 | K35: =SUM(K4:K34) -> 13971.929 | L35: =SUM(L4:L34) -> 13971.929
E36: 20 | G36: 1835.6 | H36: 19.28 | J36: 1999.9144 | K36: 3835.5144 | L36: 3835.5144
E37: =SUM(E35:E36) -> 152.92 | G37: =SUM(G35:G36) -> 13949.929 | H37: =SUM(H35:H36) -> 37.28 | J37: =SUM(J35:J36) -> 3857.5144 | K37: =SUM(K35:K36) -> 17807.443 | L37: =SUM(L35:L36) -> 17807.443

Sheet Ghattaprabha
A1: Vivek Petrol Pump
A2: S.No | B2: Date | C2: GRN No | D2: Ind No/Bill No | E2: Diesel (Lts) | F2: Price | G2: Amount | H2: Petrol (Lts) | I2: Price | J2: Amount | K2: Total amount | L2: Amount paid | M2: As on Date | N2: Remarks
D3: Opening Balance | K3: 1036347.3 | M3: =+K3 -> 1036347.3
