Workbook

Sheet Sheet1
A1: S.no | B1: Site Name | C1: Bunk Name | D1: Diesel(Liters) | E1: Diesel Amount | F1: Petrol(Liters) | G1: Petrol Amount | H1: Total Amount | I1: Opening Blance | J1: Amount Paid | K1: Closing Balances
A2: 1 | B2: Khammam-1 | C2: Sri Ramakotaiah Fuel Point | D2: 11984.26 | E2: 1146654 | F2: 130 | G2: 13969.8 | H2: =E2+G2 -> 1160623.8 | I2: 5140597 | J2: 2500000 | K2: =I2+H2-J2 -> 3801220.8
A3: 2 | B3: Khammam-2 | C3: Divya laxmi ganapathi | D3: 118512.26 | E3: 11339228 | F3: 535 | G3: 57491.1 | H3: =E3+G3 -> 11396719 | I3: 3730421 | J3: 1500000 | K3: =I3+H3-J3 -> 13627140
A4: 3 | B4: Khammam-3 | C4: Jayasai union bunk | D4: 33155.09 | E4: 3172942.1 | F4: 70 | G4: 7523.6 | H4: =E4+G4 -> 3180465.7 | I4: 8891075.4 | J4: 2000000 | K4: =I4+H4-J4 -> 10071541
A5: 4 | B5: Jadcherla-1 | C5: Sai Baba Fuel Station | D5: 6550.84 | E5: 631631.99 | F5: 305.75 | G5: 33091.323 | H5: =E5+G5 -> 664723.32 | I5: 1966837 | J5: 0 | K5: =I5+H5-J5 -> 2631560.3
A6: 5 | B6: Jadcherla-2 | C6: Uttara Enterprises | D6: 0 | E6: 0 | F6: 0 | G6: 0 | H6: =E6+G6 -> 0 | I6: 1832240.6 | J6: 0 | K6: =I6+H6-J6 -> 1832240.6
A7: 6 | B7: Jadcherla-3 | C7: Bhavani KSK Fuel Station-Nawabpet | D7: 4040 | E7: 389092.4 | F7: 0 | G7: 0 | H7: =E7+G7 -> 389092.4 | I7: 0 | J7: 0 | K7: =I7+H7-J7 -> 389092.4
A8: 7 | B8: Jadcherla-4 | C8: ADHOC FILLING STATION STATION | D8: 11600 | E8: 1118588 | F8: 0 | G8: 0 | H8: =E8+G8 -> 1118588 | I8: 0 | J8: 0 | K8: =I8+H8-J8 -> 1118588
A9: 8 | B9: Sangareddy-1 | C9: Shree lakshmi ganapathi F/S | D9: 4185.96 | E9: 403359.11 | F9: 62 | G9: 6706.54 | H9: =E9+G9 -> 410065.65 | I9: 1004532 | J9: 1414699.8 | K9: 0
A10: 9 | B10: Sangareddy-2 | C10: Sri Durgabhavani Filling Station | D10: 165 | E10: 15912 | F10: 16 | G10: 1732.96 | H10: =E10+G10 -> 17644.96 | I10: 0 | J10: 17644.96 | K10: =I10+H10-J10 -> 0
A11: 10 | B11: Sangareddy-3 | C11: Laxmi Narasimha Enterprises F/S | D11: 40 | E11: 3849 | F11: 0 | G11: 0 | H11: =E11+G11 -> 3849 | I11: 0 | J11: 3849 | K11: =I11+H11-J11 -> 0
A12: 11 | B12: Sangareddy-4 | C12: Sree Shiva Parvathi Filling Station | D12: 1459.79 | E12: 140476 | F12: 16 | G12: 1732.96 | H12: =E12+G12 -> 142208.96 | I12: 0 | J12: 142208.96 | K12: =I12+H12-J12 -> 0
A13: 12 | B13: YG Gudda | C13: Pallavi Petrolium | D13: 3800 | E13: 346940 | F13: 385 | G13: 39747.4 | H13: =E13+G13 -> 386687.4 | I13: 244365 | J13: 299920 | K13: =I13+H13-J13 -> 331132.4
A14: 13 | B14: Hosadurga-1 | C14: Merchant Petroliums | D14: 4500 | E14: 412380 | F14: 140 | G14: 14777 | H14: =E14+G14 -> 427157 | I14: 0 | J14: 150000 | K14: =I14+H14-J14 -> 277157
A15: 14 | B15: Hosadurga-2 | C15: Shree Veeraprathap Fuel | D15: 2000 | E15: 182780 | F15: 135 | G15: 13967.1 | H15: =E15+G15 -> 196747.1 | I15: 151569.4 | J15: 150000 | K15: =I15+H15-J15 -> 198316.5
A16: 15 | B16: Malebennuru(KUWSDB) | C16: Sri Ramanjuneya Service Station | D16: 3277.82 | E16: 301888 | F16: 138 | G16: 14332 | H16: =E16+G16 -> 316220 | I16: 96655 | J16: 385490 | K16: =I16+H16-J16 -> 27385
A17: 16 | B17: kadur | C17: Vishal Service Station | D17: 2000 | E17: 182300 | F17: 145 | G17: 15119.15 | H17: =E17+G17 -> 197419.15 | I17: 578097.65 | J17: 0 | K17: =I17+H17-J17 -> 775516.8
A18: 17 | B18: Hiriyur(VJNL) | C18: Sri Balaji Agencies | D18: 2400 | E18: 221040 | F18: 210 | G18: 21810.6 | H18: =E18+G18 -> 242850.6 | I18: 237520 | J18: 250000 | K18: =I18+H18-J18 -> 230370.6
A19: 18 | B19: Chellakere(KUWSDB) | C19: Sri Vishnu Baba Petroleum | D19: 2045 | E19: 188324.05 | F19: 125 | G19: 12982.5 | H19: =E19+G19 -> 201306.55 | I19: 0 | J19: 201306.55 | K19: =I19+H19-J19 -> 0
A20: 19 | B20: Khanapur(PKG-3) | C20: J K Makavi | D20: 169 | E20: 15411.11 | F20: 16.25 | G20: 1669.23 | H20: =E20+G20 -> 17080.34 | I20: 0 | J20: 17080.34 | K20: =I20+H20-J20 -> 0
A21: 20 | B21: Munavalli(PKG-3) | C21: Shahapur Petroleum | D21: 14283.35 | E21: 1303412.1 | F21: 127 | G21: 13103.86 | H21: =E21+G21 -> 1316516 | I21: 58857 | J21: 1134279.9 | K21: =I21+H21-J21 -> 241093.08
... A24: 23 | B24: Kabbur(PKG-3) | C24: Shri Jai Hanuman Petrolium | D24: 509.02 | E24: 46621.142 | F24: 11.56 | G24: 1196.8068 | H24: =E24+G24 -> 47817.949 | I24: 0 | J24: 47817.949 | K24: =I24+H24-J24 -> 0
A25: 24 | B25: Kumta (PKG-1) | C25: Krishma fuel station | D25: 760.33 | E25: 69889.534 | F25: 47.46 | G25: 4933.9416 | H25: =E25+G25 -> 74823.475 | J25: 74823.475 | K25: =I25+H25-J25 -> 0
A26: 25 | B26: Jalgaon | C26: Sri Sai Petrol Pump | D26: 597.14 | E26: 54712.182 | F26: 13.52 | G26: 1419.4272 | H26: =E26+G26 -> 56131.609 | I26: 4528.49 | J26: 49930.511 | K26: =I26+H26-J26 -> 10729.588
A27: 26 | B27: MKBD | C27: Shree Sai Samarth Petroleum | D27: 25450 | E27: 2319513 | F27: 75 | G27: 7845 | H27: =E27+G27 -> 2327358 | I27: 1668531 | J27: 2000000 | K27: =I27+H27-J27 -> 1995889
A28: 27 | B28: Haveri | C28: Shivalingeshwar Petroleum | D28: 944.46 | E28: 86389.756 | F28: 63.01 | G28: 6517.1243 | H28: =E28+G28 -> 92906.88 | I28: 90058 | J28: 115444 | K28: =I28+H28-J28 -> 67520.88
A29: 28 | B29: Guttal | C29: Taware filling station | D29: 935.89 | E29: 85914.702 | F29: 40 | G29: 4150.4 | H29: =E29+G29 -> 90065.102 | J29: 90065.102 | K29: =I29+H29-J29 -> 0
A30: 29 | B30: Rattihali | C30: Shree Siri Gowari petroliam | D30: 1032.57 | E30: 95037.743 | F30: 45 | G30: 4680.9 | H30: =E30+G30 -> 99718.643 | J30: 99718.643 | K30: =I30+H30-J30 -> 0
A31: 30 | B31: Gajendragada | C31: Vanasri Petrol Pump | D31: 60 | E31: 5509.8 | F31: 18 | G31: 1868.4 | H31: =E31+G31 -> 7378.2 | I31: 30323 | J31: 7378.2 | K31: =I31+H31-J31 -> 30323
A32: 31 | B32: Ghattaprabha(PKG-3) | C32: Vivek Petrol Pump | D32: 0 | E32: 0 | F32: 0 | G32: 0 | H32: =E32+G32 -> 0 | I32: 1036347.3 | J32: 400000 | K32: =I32+H32-J32 -> 636347.32
A33: 32 | B33: Gokak(PKG-3) | C33: AJ Petrolinks | D33: 11163.57 | E33: 1021243.4 | F33: 271 | G33: 28024.11 | H33: =E33+G33 -> 1049267.5 | I33: 473791 | J33: 300000 | K33: =I33+H33-J33 -> 1223058.5
A34: 33 | B34: Ghattaprabha-2(PKG-3) | C34: Manikeri Petroleums | D34: 0 | E34: 0 | F34: 4.82 | G34: 499.98 | H34: =E34+G34 -> 499.98 | I34: 0 | J34: 499.98 | K34: =I34+H34-J34 -> 0
A35: 34 | B35: Ankalgi(PKG-3) | C35: Nirwani Petroleums | D35: 152.92 | E35: 13949.929 | F35: 37.28 | G35: 3857.5144 | H35: =E35+G35 -> 17807.443 | I35: 0 | J35: 17807.443 | K35: =I35+H35-J35 -> 0
A36: 35 | B36: Talikote(PKG-1) | C36: Raykar Oil Agencies | D36: 637.8 | E36: 58358.7 | F36: 61.99 | G36: 5912.6304 | H36: =E36+G36 -> 64271.33 | I36: 0 | J36: 64271.33 | K36: =I36+H36-J36 -> 0
A37: 36 | B37: Chadchan(PKG-1) | C37: Khavekar Petrolium | D37: 577.29 | E37: 52088.877 | F37: 43.88 | G37: 4482.7808 | H37: =E37+G37 -> 56571.658 | I37: 192780 | J37: 192780 | K37: =I37+H37-J37 -> 56571.658
A38: 37 | B38: Sindagi | C38: G.P.PORWAL | D38: 138 | E38: 12589.74 | F38: 0 | G38: 0 | H38: =E38+G38 -> 12589.74 | I38: 0 | J38: 12589.74 | K38: =I38+H38-J38 -> 0
A39: 38 | B39: Muddebihal(PKG-1) | C39: Bhosle Service Station | D39: 98.41 | E39: 8999.5945 | F39: 33.81 | G39: 3495.6159 | H39: =E39+G39 -> 12495.21 | I39: 0 | J39: 12495.21 | K39: =I39+H39-J39 -> 0
A40: 39 | B40: Almela(PKG-1) | C40: Shiddeshwar Petroleums | D40: 35.03 | E40: 3199.2899 | F40: 30.92 | G40: 3192.7992 | H40: =E40+G40 -> 6392.0891 | I40: 0 | J40: 6392.0891 | K40: =I40+H40-J40 -> 0
A41: 40 | B41: Srirangapatna | C41: Sri Chakra Fuel Station | D41: 71.77 | E41: 6500.2089 | F41: 35.13 | G41: 3599.4198 | H41: =E41+G41 -> 10099.629 | I41: 0 | J41: 10099.629 | K41: =I41+H41-J41 -> 0
A42: 41 | B42: Nalatwad(PKG-1) | C42: Shri Pawad Basaweshwar Petroleums | D42: 436.89 | E42: 40027.862 | F42: 21.25 | G42: 2200.8625 | H42: =E42+G42 -> 42228.724 | I42: 48315 | J42: 90535.84 | K42: =I42+H42-J42 -> 7.8843
A43: Total | D43: =SUM(D2:D42) -> 272571.36 | E43: =SUM(E2:E42) -> 25754294 | F43: =SUM(F2:F42) -> 3563.63 | G43: =SUM(G2:G42) -> 373628.94 | H43: =SUM(H2:H42) -> 26127923 | I43: =SUM(I2:I42) -> 27985140 | J43: =SUM(J2:J42) -> 14320973 | K43: =SUM(K2:K42) -> 39792192
D49: =PROPER(C49)

Sheet June-25
A1: S.no | B1: Site Name | C1: Bunk Name | D1: Diesel(Liters) | E1: Diesel Amount | F1: Petrol(Liters) | G1: Petrol Amount | H1: Total Amount | I1: Opening Blance | J1: Amount Paid | K1: Closing Balances
A2: 1 | B2: Khammam-1 | C2: Sri Ramakotaiah Fuel Point | D2: =+'Khammam-1'!E36 -> 0 | E2: =+'Khammam-1'!G36 -> 0 | F2: =+'Khammam-1'!H36 -> 0 | G2: =+'Khammam-1'!J36 -> 0 | H2: =E2+G2 -> 0 | I2: =+'Khammam-1'!K3 -> 2301220.8 | J2: =+'Khammam-1'!L36 -> 2301220 | K2: =H2+I2-J2 -> 0.7968
A3: 2 | B3: Khammam-2 | C3: Divya laxmi ganapathi | D3: =+'Khammam-2'!E37 -> 148695.59 | E3: =+'Khammam-2'!G37 -> 14227153 | F3: =+'Khammam-2'!H37 -> 630 | G3: =+'Khammam-2'!J37 -> 67699.8 | H3: =E3+G3 -> 14294853 | I3: =+'Khammam-2'!K3 -> 9307338.8 | J3: =+'Khammam-2'!L37 -> 10036782 | K3: =H3+I3-J3 -> 13565410
A4: 3 | B4: Khammam-3 | C4: Jayasai union bunk | D4: =+'Khammam-3'!E35 -> 121466.14 | E4: =+'Khammam-3'!G35 -> 11624310 | F4: =+'Khammam-3'!H35 -> 502.98 | G4: =+'Khammam-3'!J35 -> 54060.29 | H4: =E4+G4 -> 11678370 | I4: =+'Khammam-3'!K3 -> 7457303.4 | J4: =+'Khammam-3'!L35 -> 8843736.1 | K4: =H4+I4-J4 -> 10291937
A5: 4 | B5: Jadcherla-1 | C5: Sai Baba Fuel Station | D5: =+'Jedcherla -1'!E36 -> 26513.87 | E5: =+'Jedcherla -1'!G36 -> 2556467.3 | F5: =+'Jedcherla -1'!H36 -> 479.35 | G5: =+'Jedcherla -1'!J36 -> 51880.05 | H5: =E5+G5 -> 2608347.4 | I5: =+'Jedcherla -1'!K3 -> 1149870.8 | J5: =+'Jedcherla -1'!L36 -> 1619072 | K5: =H5+I5-J5 -> 2139146.2 | M5: 2139146.9
A6: 5 | B6: Jadcherla-2 | C6: Uttara Enterprises | D6: 0 | E6: 0 | F6: 0 | G6: 0 | H6: =E6+G6 -> 0 | I6: =+'Jedcherla-2'!K3 -> 331699.53 | J6: =+'Jedcherla-2'!L35 -> 331700 | K6: =H6+I6-J6 -> -0.4737
A7: 6 | B7: Jadcherla-4 | C7: ADHOC FILLING STATION STATION | D7: =+'Jedcharla-3'!E35 -> 40895.59 | E7: =+'Jedcharla-3'!G35 -> 3943561.7 | F7: 0 | G7: 0 | H7: =E7+G7 -> 3943561.7 | I7: 0 | J7: =+'Jedcharla-3'!L35 -> 2733935 | K7: =H7+I7-J7 -> 1209626.7 | M7: =M5-K5 -> 0.7071
A8: 7 | B8: Sangareddy-1 | C8: Sree Shiva Parvathi Filling Station | D8: =+Sangareddy!E40 -> 8990 | E8: =+Sangareddy!G40 -> 865107.7 | F8: =+Sangareddy!H40 -> 120 | G8: =+Sangareddy!J40 -> 12967.6 | H8: =E8+G8 -> 878075.3 | I8: 0 | J8: =+Sangareddy!L40 -> 515538.5 | K8: =H8+I8-J8 -> 362536.8
A9: 8 | B9: Dindi | C9: Akarapu Balakistamma Fillling | D9: =+Dindi!E35 -> 175.7 | E9: =+Dindi!G35 -> 17013.031 | F9: =+Dindi!H35 -> 7.35 | G9: =+Dindi!J35 -> 798.651 | H9: =E9+G9 -> 17811.682 | J9: =+Dindi!L35 -> 17811.682 | K9: =H9+I9-J9 -> 0
A10: 9 | B10: Devarkhadra | C10: Kurumurthy Swami F/S | D10: =+Devarakhadra!E35 -> 1740.96 | E10: =+Devarakhadra!G35 -> 169047.22 | F10: =+Devarakhadra!H35 -> 0 | G10: =+Devarakhadra!J35 -> 0 | H10: =E10+G10 -> 169047.22 | I10: =+Devarakhadra!M3 -> 0 | J10: =+Devarakhadra!L35 -> 0 | K10: =H10+I10-J10 -> 169047.22
A11: 10 | B11: YG Gudda | C11: Pallavi Petrolium | D11: =+'YG Gudda '!E36 -> 8400 | E11: =+'YG Gudda '!G36 -> 766920 | F11: =+'YG Gudda '!H36 -> 595 | G11: =+'YG Gudda '!J36 -> 61427.8 | H11: =E11+G11 -> 828347.8 | I11: ='YG Gudda '!K3 -> 71933.179 | J11: =+'YG Gudda '!L36 -> 851800 | K11: =H11+I11-J11 -> 48480.979
A12: 11 | B12: Hosadurga-1 | C12: Merchant Petroliums | D12: =+Hosadurga!E35 -> 3100 | E12: =+Hosadurga!G35 -> 284084 | F12: =+Hosadurga!H35 -> 235 | G12: =+Hosadurga!J35 -> 24374.2 | H12: =E12+G12 -> 308458.2 | I12: =+Hosadurga!K3 -> 0 | J12: =+Hosadurga!L35 -> 308458.2 | K12: =H12+I12-J12 -> 0
A13: 12 | B13: Hosadurga-2 | C13: Shree Veeraprathap Fuel | D13: =+'Hosadurga -2'!E35 -> 4000 | E13: =+'Hosadurga -2'!G35 -> 365560 | F13: =+'Hosadurga -2'!H35 -> 140 | G13: =+'Hosadurga -2'!J35 -> 14484.4 | H13: =+'Hosadurga -2'!K35 -> 380044.4 | I13: =+'Hosadurga -2'!K3 -> 388266.5 | J13: =+'Hosadurga -2'!L35 -> 388266.5 | K13: =H13+I13-J13 -> 380044.4
A14: 13 | B14: Malebennuru(KUWSDB) | C14: Sri Ramanjuneya Service Station | D14: =+'Malebenur(KUWSDB)'!E38 -> 3700 | E14: =+'Malebenur(KUWSDB)'!G38 -> 340662 | F14: =+'Malebenur(KUWSDB)'!H38 -> 175 | G14: =+'Malebenur(KUWSDB)'!J38 -> 18175.5 | H14: =E14+G14 -> 358837.5 | I14: =+'Malebenur(KUWSDB)'!K3 -> 36616.014 | J14: =+'Malebenur(KUWSDB)'!L36 -> 296692.21 | K14: =H14+I14-J14 -> 98761.304
A15: 14 | B15: kadur | C15: Vishal Service Station | D15: =+Kadur!E35 -> 0 | E15: =+Kadur!G35 -> 0 | F15: =+Kadur!H35 -> 110 | G15: =+Kadur!J35 -> 11469.7 | H15: =E15+G15 -> 11469.7 | I15: =+Kadur!K3 -> 1167095.1 | J15: =+Kadur!L35 -> 968765.11 | K15: =H15+I15-J15 -> 209799.73
A16: 15 | B16: Hiriyur(VJNL) | C16: Sri Balaji Agencies | D16: =+'Hiriyur(VJNL)'!E35 -> 4000 | E16: =+'Hiriyur(VJNL)'!G35 -> 368400 | F16: =+'Hiriyur(VJNL)'!H35 -> 140 | G16: =+'Hiriyur(VJNL)'!J35 -> 14540.4 | H16: =E16+G16 -> 382940.4 | I16: =+'Hiriyur(VJNL)'!K3 -> 87640.8 | J16: =+'Hiriyur(VJNL)'!L35 -> 87640.8 | K16: =H16+I16-J16 -> 382940.4
A17: 16 | B17: Chellakere(KUWSDB) | C17: Sri Vishnu Baba Petroleum | D17: =+'Chellakere (KUWSDB)'!E35 -> 4564 | E17: =+'Chellakere (KUWSDB)'!G35 -> 416151.18 | F17: =+'Chellakere (KUWSDB)'!H35 -> 242 | G17: =+'Chellakere (KUWSDB)'!J35 -> 25134.12 | H17: =E17+G17 -> 441285.3 | I17: 0 | J17: =+'Chellakere (KUWSDB)'!L35 -> 441285.3 | K17: =H17+I17-J17 -> 0
A18: 17 | B18: Khanapur(PKG-3) | C18: J K Makavi | D18: =+Khanapur!E35 -> 454.02 | E18: =+Khanapur!G35 -> 41261.338 | F18: =+Khanapur!H35 -> 9.73 | G18: =+Khanapur!J35 -> 999.9521 | H18: =E18+G18 -> 42261.29 | I18: 0 | J18: =+Khanapur!M35 -> 42261.29 | K18: =H18+I18-J18 -> 0
A19: 18 | B19: Munavalli(PKG-3) | C19: Shahapur Petroleum | D19: =+'Munavalli(KUWSDB)'!E36 -> 8967.17 | E19: =+'Munavalli(KUWSDB)'!G36 -> 818343.93 | F19: =+'Munavalli(KUWSDB)'!H36 -> 259.38 | G19: =+'Munavalli(KUWSDB)'!J36 -> 26762.828 | H19: =E19+G19 -> 845106.76 | I19: =+'Munavalli(KUWSDB)'!K3 -> 107004.03 | J19: =+'Munavalli(KUWSDB)'!L36 -> 364300 | K19: =H19+I19-J19 -> 587810.79
A20: 19 | B20: Borgaon(PKG-3) | C20: Aadisagar Petrolium | D20: =+Borgaon!E35 -> 364.4 | E20: =+Borgaon!G35 -> 33440.988 | F20: =+Borgaon!H35 -> 36 | G20: =+Borgaon!J35 -> 3732.48 | H20: =E20+G20 -> 37173.468 | I20: =+Borgaon!K3 -> 22826.33 | J20: =+Borgaon!L35 -> 0 | K20: =H20+I20-J20 -> 59999.798
A21: 20 | B21: Ugar,Kudichi(PKG-3) | C21: Shiri Bhrhmanath Petrolium | D21: =+'Ugar,Khagwad,Kudichi'!E35 -> 2862.39 | E21: =+'Ugar,Khagwad,Kudichi'!G35 -> 263139.51 | F21: =+'Ugar,Khagwad,Kudichi'!H35 -> 190 | G21: =+'Ugar,Khagwad,Kudichi'!J35 -> 19739.1 | H21: =E21+G21 -> 282878.61 | I21: =+'Ugar,Khagwad,Kudichi'!K3 -> 241437.63 | J21: =+'Ugar,Khagwad,Kudichi'!L35 -> 287745 | K21: =H21+I21-J21 -> 236571.24
A22: 21 | B22: Kabbur(PKG-3) | C22: Shri Jai Hanuman Petrolium | D22: =+Kabbur!E35 -> 705 | E22: =+Kabbur!G35 -> 64570.95 | F22: =+Kabbur!H35 -> 32.51 | G22: =+Kabbur!J35 -> 3367.2309 | H22: =E22+G22 -> 67938.181 | I22: 0 | J22: =+Kabbur!L35 -> 67938.181 | K22: =H22+I22-J22 -> 0
A23: 22 | B23: Kumta (PKG-1) | C23: Krishna fuel station | D23: =+kumta!E35 -> 1235.75 | E23: =+kumta!G35 -> 113590.14 | F23: =+kumta!H35 -> 91.72 | G23: =+kumta!J35 -> 9532.9908 | H23: =E23+G23 -> 123123.13 | I23: 0 | J23: =+kumta!L35 -> 123123.13 | K23: =H23+I23-J23 -> 0
A24: 23 | B24: Jalgaon | C24: Sri Sai Petrol Pump | D24: =+Jalgaon!E40 -> 823.37 | E24: =+Jalgaon!G40 -> 75472.286 | F24: =+Jalgaon!H40 -> 14.64 | G24: =+Jalgaon!J40 -> 1539.9816 | H24: =E24+G24 -> 77012.267 | I24: =+Jalgaon!K3 -> 13725.912 | J24: =+Jalgaon!L40 -> 73672.3 | K24: =H24+I24-J24 -> 17065.88
A25: 24 | B25: MKBD | C25: Shree Sai Samarth Petroleum | D25: =+MKBD!E36 -> 17089.19 | E25: =+MKBD!G36 -> 1557508.8 | F25: =+MKBD!H36 -> 77 | G25: =+MKBD!J36 -> 8054.2 | H25: 1566762 | I25: =+MKBD!K3 -> 450628.67 | J25: =+MKBD!L36 -> 1005216 | K25: =H25+I25-J25 -> 1012174.7
A26: 25 | B26: Haveri | C26: Shivalingeshwar Petroleum | D26: =+Haveri!E35 -> 3219.58 | E26: =+Haveri!G35 -> 294494.98 | F26: =+Haveri!H35 -> 105.49 | G26: =+Haveri!J35 -> 10907.666 | H26: =E26+G26 -> 305402.65 | I26: =+Haveri!K3 -> 36319.153 | J26: =+Haveri!L35 -> 173800 | K26: =H26+I26-J26 -> 167921.8
A27: 26 | B27: Guttal | C27: Taware filling station | D27: =+Guttal!E35 -> 1316.9 | E27: =+Guttal!G35 -> 120891.42 | F27: =+Guttal!H35 -> 41 | G27: =+Guttal!J35 -> 4254.16 | H27: =E27+G27 -> 125145.58 | I27: 0 | J27: =+Guttal!L35 -> 125145.58 | K27: =H27+I27-J27 -> 0
A28: 27 | B28: Rattihali | C28: Shree Siri Gowari petroliam | D28: =+Rattihali!E35 -> 2658.06 | E28: =+Rattihali!G35 -> 244647.84 | F28: =+Rattihali!H35 -> 151.28 | G28: =+Rattihali!J35 -> 15736.146 | H28: =E28+G28 -> 260383.99 | I28: 0 | J28: =+Rattihali!L35 -> 105061.18 | K28: =H28+I28-J28 -> 155322.81
A29: 28 | B29: Gajendragada | C29: Vanasri Petrol Pump | D29: =+Gajendragada!E35 -> 1032.89 | E29: =+Gajendragada!G35 -> 94850.289 | F29: =+Gajendragada!H35 -> 75 | G29: =+Gajendragada!J35 -> 7785.75 | H29: =E29+G29 -> 102636.04 | I29: =+Gajendragada!K3 -> 59460.8 | J29: =+Gajendragada!L35 -> 88047.8 | K29: =H29+I29-J29 -> 74049.039
A30: 29 | B30: Ghattaprabha(PKG-3) | C30: Vivek Petrol Pump | D30: =+Ghattaprabha!E35 -> 3214.07 | E30: =+Ghattaprabha!G35 -> 294087.4 | F30: =+Ghattaprabha!H35 -> 143 | G30: =+Ghattaprabha!J35 -> 14789.06 | H30: =E30+G30 -> 308876.46 | I30: =+Ghattaprabha!K3 -> 0 | J30: =+Ghattaprabha!L35 -> 0 | K30: =H30+I30-J30 -> 308876.46
A31: 30 | B31: Gokak(PKG-3) | C31: AJ Petrolinks | D31: =+'Gokak Dharwad PKG 3'!E38 -> 10414.8 | E31: =+'Gokak Dharwad PKG 3'!G38 -> 952745.9 | F31: =+'Gokak Dharwad PKG 3'!H38 -> 362 | G31: =+'Gokak Dharwad PKG 3'!J38 -> 37480.98 | H31: =E31+G31 -> 990226.88 | I31: =+'Gokak Dharwad PKG 3'!K3 -> 1537989 | J31: =+'Gokak Dharwad PKG 3'!L38 -> 1621328 | K31: =H31+I31-J31 -> 906887.85
A32: 31 | B32: ShankeshWAR | C32: SR Patil | D32: =+' Shankeshwar'!E35 -> 571.44 | E32: =+' Shankeshwar'!G35 -> 52172.472 | F32: =+' Shankeshwar'!H35 -> 38 | G32: =+' Shankeshwar'!J35 -> 3922.36 | H32: =E32+G32 -> 56094.832 | J32: =+' Shankeshwar'!L35 -> 56094.832 | K32: =H32+I32-J32 -> 0
A33: 32 | B33: Talikote(PKG-1) | C33: Raykar Oil Agencies | D33: =+' Talikote'!E45 -> 1558.26 | E33: =+' Talikote'!G45 -> 142580.79 | F33: =+' Talikote'!H45 -> 72.68 | G33: =+' Talikote'!J45 -> 7518.0192 | H33: =E33+G33 -> 150098.81 | I33: =+' Talikote'!M3 -> 2488 | J33: =+' Talikote'!L45 -> 124004.62 | K33: =H33+I33-J33 -> 28582.189
A34: 33 | B34: Chadchan(PKG-1) | C34: Khavekar Petrolium | D34: =+Chadchan!E35 -> 1216.31 | E34: =+Chadchan!G35 -> 110512.23 | F34: =+Chadchan!H35 -> 71.09 | G34: =+Chadchan!J35 -> 7296.7344 | H34: =E34+G34 -> 117808.97 | I34: =+Chadchan!K3 -> 77981.337 | J34: =+Chadchan!L35 -> 102795 | K34: =H34+I34-J34 -> 92995.303
A35: 34 | B35: Sindagi | C35: G.P.PORWAL | D35: =+Sindagi!E44 -> 2214.03 | E35: =+Sindagi!G44 -> 201985.96 | F35: =+Sindagi!H44 -> 4.52 | G35: =+Sindagi!J44 -> 499.3244 | H35: =E35+G35 -> 202485.28 | I35: 0 | J35: =+Sindagi!L44 -> 192630.53 | K35: =H35+I35-J35 -> 9854.749
A36: 35 | B36: Muddebihal(PKG-1) | C36: Bhosle Service Station | D36: =+Muddebihal!E46 -> 394.94 | E36: =+Muddebihal!G46 -> 36117.263 | F36: =+Muddebihal!H46 -> 28.98 | G36: =+Muddebihal!J46 -> 2996.2422 | H36: =E36+G36 -> 39113.505 | I36: 0 | J36: =+Muddebihal!L46 -> 11599.495 | K36: =H36+I36-J36 -> 27514.01
A37: 36 | B37: Almela(PKG-1) | C37: Shiddeshwar Petroleums | D37: =+Alemela!E43 -> 1216.14 | E37: =+Alemela!G43 -> 111070.07 | F37: =+Alemela!H43 -> 38.84 | G37: =+Alemela!J43 -> 4010.6184 | H37: =E37+G37 -> 115080.68 | I37: 0 | J37: =+Alemela!L43 -> 40321.143 | K37: =H37+I37-J37 -> 74759.542
A38: 37 | B38: Nalatwad(PKG-1) | C38: Shri Pawad Basaweshwar Petroleums | D38: =+Nalatwad!E43 -> 761.83 | E38: =+Nalatwad!G43 -> 69798.865 | F38: =+Nalatwad!H43 -> 53.12 | G38: =+Nalatwad!J43 -> 5501.6384 | H38: =E38+G38 -> 75300.503 | I38: =+Nalatwad!M3 -> 20248.57 | J38: =+Nalatwad!L43 -> 58950.7 | K38: =H38+I38-J38 -> 36598.373
A39: 38 | B39: Srirangapatna | C39: Sri Chakra Fuel Station | D39: =+Srirangapatna!E35 -> 501.25 | E39: =+Srirangapatna!G35 -> 45398.213 | F39: =+Srirangapatna!H35 -> 74.01 | G39: =+Srirangapatna!J35 -> 7583.0646 | H39: =E39+G39 -> 52981.277 | I39: 0 | J39: =+Srirangapatna!L35 -> 52981.277 | K39: =H39+I39-J39 -> 0
A40: Total | D40: =SUM(D2:D39) -> 439033.64 | E40: =SUM(E2:E39) -> 41683118 | F40: =SUM(F2:F39) -> 5346.67 | G40: =SUM(G2:G39) -> 561023.04 | H40: =SUM(H2:H39) -> 42245340 | I40: =SUM(I2:I39) -> 24869094 | J40: =SUM(J2:J39) -> 34459719 | K40: =H40+I40-J40 -> 32654715

Sheet Khammam-1
A1: Sri Ramakotaiah Fuel Point
A2: S.No | B2: Date | C2: GRN No | D2: Ind No/Bill No | E2: Diesel (Lts) | F2: Price | G2: Amount | H2: Petrol (Lts) | I2: Price | J2: Amount | K2: Total amount | L2: Amount paid | M2: As 0n Date | N2: Remarks
A3: Opening Balance | K3: 2301220.8 | M3: =+K3 -> 2301220.8 | P3: 220299.06
A4: 1 | B4: 45809 | E4: 0 | F4: 0 | G4: =E4*F4 -> 0 | H4: 0 | I4: 0 | J4: =H4*I4 -> 0 | K4: =G4+J4 -> 0 | L4: 0 | M4: =M3+K4-L4 -> 2301220.8
A5: 2 | B5: 45810 | E5: 0 | F5: 0 | G5: =E5*F5 -> 0 | H5: 0 | I5: 0 | J5: =H5*I5 -> 0 | K5: =G5+J5 -> 0 | L5: 0 | M5: =M4+K5-L5 -> 2301220.8
A6: 3 | B6: 45811 | E6: 0 | F6: 0 | G6: =E6*F6 -> 0 | H6: 0 | I6: 0 | J6: =H6*I6 -> 0 | K6: =G6+J6 -> 0 | L6: 0 | M6: =M5+K6-L6 -> 2301220.8
A7: 4 | B7: 45812 | E7: 0 | F7: 0 | G7: =E7*F7 -> 0 | H7: 0 | I7: 0 | J7: =H7*I7 -> 0 | K7: =G7+J7 -> 0 | L7: 0 | M7: =M6+K7-L7 -> 2301220.8
A8: 5 | B8: 45813 | E8: 0 | F8: 0 | G8: =E8*F8 -> 0 | H8: 0 | I8: 0 | J8: =H8*I8 -> 0 | K8: =G8+J8 -> 0 | L8: 2301220 | M8: =M7+K8-L8 -> 0.7968
A9: 6 | B9: 45814 | E9: 0 | F9: 0 | G9: =E9*F9 -> 0 | H9: 0 | I9: 0 | J9: =H9*I9 -> 0 | K9: =G9+J9 -> 0 | L9: 0 | M9: =M8+K9-L9 -> 0.7968
A10: 7 | B10: 45815 | E10: 0 | F10: 0 | G10: =E10*F10 -> 0 | H10: 0 | I10: 0 | J10: =H10*I10 -> 0 | K10: =G10+J10 -> 0 | L10: 0 | M10: =M9+K10-L10 -> 0.7968
A11: 8 | B11: 45816 | E11: 0 | F11: 0 | G11: =E11*F11 -> 0 | H11: 0 | I11: 0 | J11: =H11*I11 -> 0 | K11: =G11+J11 -> 0 | L11: 0 | M11: =M10+K11-L11 -> 0.7968
A12: 9 | B12: 45817 | E12: 0 | F12: 0 | G12: =E12*F12 -> 0 | H12: 0 | I12: 0 | J12: =H12*I12 -> 0 | K12: =G12+J12 -> 0 | L12: 0 | M12: =M11+K12-L12 -> 0.7968
A13: 10 | B13: 45818 | E13: 0 | F13: 0 | G13: =E13*F13 -> 0 | H13: 0 | I13: 0 | J13: =H13*I13 -> 0 | K13: =G13+J13 -> 0 | L13: 0 | M13: =M12+K13-L13 -> 0.7968
A14: 11 | B14: 45819 | E14: 0 | F14: 0 | G14: =E14*F14 -> 0 | H14: 0 | I14: 0 | J14: =H14*I14 -> 0 | K14: =G14+J14 -> 0 | L14: 0 | M14: =M13+K14-L14 -> 0.7968
A15: 12 | B15: 45820 | E15: 0 | F15: 0 | G15: =E15*F15 -> 0 | H15: 0 | I15: 0 | J15: =H15*I15 -> 0 | K15: =G15+J15 -> 0 | L15: 0 | M15: =M14+K15-L15 -> 0.7968
... A18: 15 | B18: 45823 | E18: 0 | F18: 0 | G18: =E18*F18 -> 0 | H18: 0 | I18: 0 | J18: =H18*I18 -> 0 | K18: =G18+J18 -> 0 | L18: 0 | M18: =M17+K18-L18 -> 0.7968
A19: 16 | B19: 45824 | E19: 0 | F19: 0 | G19: =E19*F19 -> 0 | H19: 0 | I19: 0 | J19: =H19*I19 -> 0 | K19: =G19+J19 -> 0 | L19: 0 | M19: =M18+K19-L19 -> 0.7968 | O19: .
A20: 17 | B20: 45825 | E20: 0 | F20: 0 | G20: =E20*F20 -> 0 | H20: 0 | I20: 0 | J20: =H20*I20 -> 0 | K20: =G20+J20 -> 0 | L20: 0 | M20: =M19+K20-L20 -> 0.7968
A21: 18 | B21: 45826 | E21: 0 | F21: 0 | G21: =E21*F21 -> 0 | H21: 0 | I21: 0 | J21: =H21*I21 -> 0 | K21: =G21+J21 -> 0 | L21: 0 | M21: =M20+K21-L21 -> 0.7968
A22: 19 | B22: 45827 | E22: 0 | F22: 0 | G22: =E22*F22 -> 0 | H22: 0 | I22: 0 | J22: =H22*I22 -> 0 | K22: =G22+J22 -> 0 | L22: 0 | M22: =M21+K22-L22 -> 0.7968
A23: 20 | B23: 45828 | E23: 0 | F23: 0 | G23: =E23*F23 -> 0 | H23: 0 | I23: 0 | J23: =H23*I23 -> 0 | K23: =G23+J23 -> 0 | L23: 0 | M23: =M22+K23-L23 -> 0.7968
A24: 21 | B24: 45829 | E24: 0 | F24: 0 | G24: =E24*F24 -> 0 | H24: 0 | I24: 0 | J24: =H24*I24 -> 0 | K24: =G24+J24 -> 0 | L24: 0 | M24: =M23+K24-L24 -> 0.7968
A25: 22 | B25: 45830 | E25: 0 | F25: 0 | G25: =E25*F25 -> 0 | H25: 0 | I25: 0 | J25: =H25*I25 -> 0 | K25: =G25+J25 -> 0 | L25: 0 | M25: =M24+K25-L25 -> 0.7968
A26: 23 | B26: 45831 | E26: 0 | F26: 0 | G26: =E26*F26 -> 0 | H26: 0 | I26: 0 | J26: =H26*I26 -> 0 | K26: =G26+J26 -> 0 | L26: 0 | M26: =M25+K26-L26 -> 0.7968
A27: 24 | B27: 45832 | E27: 0 | F27: 0 | G27: =E27*F27 -> 0 | H27: 0 | I27: 0 | J27: =H27*I27 -> 0 | K27: =G27+J27 -> 0 | L27: 0 | M27: =M26+K27-L27 -> 0.7968
A28: 25 | B28: 45833 | E28: 0 | F28: 0 | G28: =E28*F28 -> 0 | H28: 0 | I28: 0 | J28: =H28*I28 -> 0 | K28: =G28+J28 -> 0 | L28: 0 | M28: =M27+K28-L28 -> 0.7968
A29: 26 | B29: 45834 | E29: 0 | F29: 0 | G29: =E29*F29 -> 0 | H29: 0 | I29: 0 | J29: =H29*I29 -> 0 | K29: =G29+J29 -> 0 | L29: 0 | M29: =M28+K29-L29 -> 0.7968
A30: 27 | B30: 45835 | E30: 0 | F30: 0 | G30: =E30*F30 -> 0 | H30: 0 | I30: 0 | J30: =H30*I30 -> 0 | K30: =G30+J30 -> 0 | L30: 0 | M30: =M29+K30-L30 -> 0.7968
A31: 28 | B31: 45836 | E31: 0 | F31: 0 | G31: =E31*F31 -> 0 | H31: 0 | I31: 0 | J31: =H31*I31 -> 0 | K31: =G31+J31 -> 0 | L31: 0 | M31: =M30+K31-L31 -> 0.7968
A32: 29 | B32: 45837 | E32: 0 | F32: 0 | G32: =E32*F32 -> 0 | H32: 0 | I32: 0 | J32: =H32*I32 -> 0 | K32: =G32+J32 -> 0 | L32: 0 | M32: =M31+K32-L32 -> 0.7968
A33: 30 | B33: 45838 | E33: 0 | F33: 0 | G33: =E33*F33 -> 0 | H33: 0 | I33: 0 | J33: =H33*I33 -> 0 | K33: =G33+J33 -> 0 | L33: 0 | M33: =M32+K33-L33 -> 0.7968 | R33: 2584221.7
A34: 31 | E34: 0 | F34: 0 | G34: =E34*F34 -> 0 | H34: 0 | I34: 0 | J34: =H34*I34 -> 0 | K34: =G34+J34 -> 0 | L34: 0 | M34: =M33+K34-L34 -> 0.7968
E35: 0 | F35: 0 | G35: =E35*F35 -> 0 | H35: 0 | I35: 0 | J35: =H35*I35 -> 0 | K35: =G35+J35 -> 0
E36: =SUM(E4:E35) -> 0 | G36: =SUM(G4:G35) -> 0 | H36: =SUM(H4:H35) -> 0 | J36: =SUM(J3:J35) -> 0 | K36: =SUM(K4:K35) -> 0 | L36: =SUM(L4:L35) -> 2301220
E41: =E36+H36 -> 0

Sheet Khammam-2
A1: Divya laxmi ganapathi
A2: S.No | B2: Date | C2: GRN No | D2: Ind No/Bill No | E2: Diesel (Lts) | F2: Price | G2: Amount | H2: Petrol (Lts) | I2: Price | J2: Amount | K2: Total amount | L2: Amount paid | M2: As 0n Date | N2: Remarks
A3: Opening Balance | K3: 9307338.8 | M3: =+K3 -> 9307338.8
A4: 1 | B4: 45809 | E4: 0 | F4: 0 | G4: =E4*F4 -> 0 | H4: 0 | I4: 0 | J4: =H4*I4 -> 0 | K4: =G4+J4 -> 0 | M4: =M3+K4-L4 -> 9307338.8
A5: 2 | B5: 45810 | C5: 2930 | D5: 1055/517 | E5: 2500 | F5: 95.68 | G5: =E5*F5 -> 239200 | H5: 70 | I5: 107.46 | J5: =H5*I5 -> 7522.2 | K5: =G5+J5 -> 246722.2 | M5: =M4+K5-L5 -> 9554061
A6: 3 | B6: 45811 | C6: 2942 | D6: 1091 | E6: 4999.46 | F6: 95.68 | G6: =E6*F6 -> 478348.33 | H6: 20 | I6: 107.46 | J6: =H6*I6 -> 2149.2 | K6: =G6+J6 -> 480497.53 | M6: =M5+K6-L6 -> 10034559
A7: 4 | B7: 45812 | C7: 2951 | D7: 1098 | E7: 2500 | F7: 95.68 | G7: =E7*F7 -> 239200 | H7: 35 | I7: 107.46 | J7: =H7*I7 -> 3761.1 | K7: =G7+J7 -> 242961.1 | M7: =M6+K7-L7 -> 10277520
A8: 5 | B8: 45813 | C8: 2962 | D8: 1119/1125/1129 | E8: 7500.08 | F8: 95.68 | G8: =E8*F8 -> 717607.65 | H8: 55 | I8: 107.46 | J8: =H8*I8 -> 5910.3 | K8: =G8+J8 -> 723517.95 | L8: 10036782 | M8: =M7+K8-L8 -> 964255.63
A9: 6 | B9: 45814 | C9: 2965 | D9: 1134/1139 | E9: 2800.25 | F9: 95.68 | G9: =E9*F9 -> 267927.92 | H9: 55 | I9: 107.46 | J9: =H9*I9 -> 5910.3 | K9: =G9+J9 -> 273838.22 | M9: =M8+K9-L9 -> 1238093.9
A10: 7 | B10: 45815 | C10: 2986 | D10: 1158/1161 | E10: 3716 | F10: 95.68 | G10: =E10*F10 -> 355546.88 | H10: 0 | I10: 107.46 | J10: =H10*I10 -> 0 | K10: =G10+J10 -> 355546.88 | M10: =M9+K10-L10 -> 1593640.7
A11: 8 | B11: 45816 | C11: 2989 | D11: 1172/1166 | E11: 5000.31 | F11: 95.68 | G11: =E11*F11 -> 478429.66 | H11: 20 | I11: 107.46 | J11: =H11*I11 -> 2149.2 | K11: =G11+J11 -> 480578.86 | M11: =M10+K11-L11 -> 2074219.6
A12: 9 | B12: 45817 | E12: 0 | F12: 0 | G12: =E12*F12 -> 0 | H12: 0 | I12: 0 | J12: =H12*I12 -> 0 | K12: =G12+J12 -> 0 | M12: =M11+K12-L12 -> 2074219.6
A13: 10 | B13: 45818 | C13: 3010 | D13: 1196/1192/1199/1197 | E13: 9310.15 | F13: 95.68 | G13: =E13*F13 -> 890795.15 | H13: 0 | I13: 0 | J13: =H13*I13 -> 0 | K13: =G13+J13 -> 890795.15 | M13: =M12+K13-L13 -> 2965014.7
A14: 11 | B14: 45819 | C14: 3017 | D14: 1221/1222/1226/1228 | E14: 9100 | F14: 95.68 | G14: =E14*F14 -> 870688 | H14: 55 | I14: 107.46 | J14: =H14*I14 -> 5910.3 | K14: =G14+J14 -> 876598.3 | M14: =M13+K14-L14 -> 3841613
A15: 12 | B15: 45820 | C15: 3019 | D15: 1216/1236/1244 | E15: 7500.11 | F15: 95.68 | G15: =E15*F15 -> 717610.52 | H15: 40 | I15: 107.46 | J15: =H15*I15 -> 4298.4 | K15: =G15+J15 -> 721908.92 | M15: =M14+K15-L15 -> 4563522
A16: 13 | B16: 45821 | C16: 3030 | D16: 1245/1246/1257/12591264/1263 | E16: 13500 | F16: 95.68 | G16: =E16*F16 -> 1291680 | H16: 40 | I16: 107.46 | J16: =H16*I16 -> 4298.4 | K16: =G16+J16 -> 1295978.4 | M16: =M15+K16-L16 -> 5859500.4
A17: 14 | B17: 45822 | C17: 3031 | D17: 1280/1278/1290/1291/1296 | E17: 10365.24 | F17: 95.68 | G17: =E17*F17 -> 991746.16 | H17: 40 | I17: 107.46 | J17: =H17*I17 -> 4298.4 | K17: =G17+J17 -> 996044.56 | M17: =M16+K17-L17 -> 6855544.9
A18: 15 | B18: 45823 | C18: 3045 | D18: 1300/1306/1320/1309 | E18: 8730.11 | F18: 95.68 | G18: =E18*F18 -> 835296.92 | H18: 20 | I18: 107.46 | J18: =H18*I18 -> 2149.2 | K18: =G18+J18 -> 837446.12 | M18: =M17+K18-L18 -> 7692991.1
A19: 16 | B19: 45824 | C19: 3065 | D19: 1329/1340/1334 | E19: 8600.07 | F19: 95.68 | G19: =E19*F19 -> 822854.7 | H19: 0 | I19: 0 | J19: =H19*I19 -> 0 | K19: =G19+J19 -> 822854.7 | M19: =M18+K19-L19 -> 8515845.8
A20: 17 | B20: 45825 | C20: 3074 | D20: 1333/1357/1346/1344 | E20: 6997.07 | F20: 95.68 | G20: =E20*F20 -> 669479.66 | H20: 60 | I20: 107.46 | J20: =H20*I20 -> 6447.6 | K20: =G20+J20 -> 675927.26 | M20: =M19+K20-L20 -> 9191773
A21: 18 | B21: 45826 | C21: 3085 | D21: 1351/1352/1374/1370 | E21: 9385 | F21: 95.68 | G21: =E21*F21 -> 897956.8 | H21: 40 | I21: 107.46 | J21: =H21*I21 -> 4298.4 | K21: =G21+J21 -> 902255.2 | M21: =M20+K21-L21 -> 10094028
A22: 19 | B22: 45827 | C22: 3104 | D22: 1380 | E22: 2800 | F22: 95.68 | G22: =E22*F22 -> 267904 | H22: 0 | I22: 0 | J22: =H22*I22 -> 0 | K22: =G22+J22 -> 267904 | M22: =M21+K22-L22 -> 10361932
A23: 20 | B23: 45828 | C23: 3120 | D23: 1399 | E23: 2942.85 | F23: 95.68 | G23: =E23*F23 -> 281571.89 | H23: 0 | I23: 0 | J23: =H23*I23 -> 0 | K23: =G23+J23 -> 281571.89 | M23: =M22+K23-L23 -> 10643504
A24: 21 | B24: 45829 | C24: 3122 | D24: 1412/1440 | E24: 7000.46 | F24: 95.68 | G24: =E24*F24 -> 669804.01 | H24: 40 | I24: 107.46 | J24: =H24*I24 -> 4298.4 | K24: =G24+J24 -> 674102.41 | M24: =M23+K24-L24 -> 11317607
A25: 22 | B25: 45830 | C25: 3153 | D25: 1473/1487/1504 | E25: 6452.43 | F25: 95.68 | G25: =E25*F25 -> 617368.5 | H25: 0 | I25: 0 | J25: =H25*I25 -> 0 | K25: =G25+J25 -> 617368.5 | M25: =M24+K25-L25 -> 11934975
A26: 23 | B26: 45831 | C26: 3154 | D26: 1500 | E26: 4112.71 | F26: 95.67 | G26: =E26*F26 -> 393462.97 | H26: 0 | I26: 0 | J26: =H26*I26 -> 0 | K26: =G26+J26 -> 393462.97 | M26: =M25+K26-L26 -> 12328438
A27: 24 | B27: 45832 | C27: 3171 | D27: 1528 | E27: 5676.03 | F27: 95.68 | G27: =E27*F27 -> 543082.55 | H27: 20 | I27: 107.46 | J27: =H27*I27 -> 2149.2 | K27: =G27+J27 -> 545231.75 | M27: =M26+K27-L27 -> 12873670
A28: 25 | B28: 45833 | E28: 0 | F28: 0 | G28: =E28*F28 -> 0 | H28: 0 | I28: 0 | J28: =H28*I28 -> 0 | K28: =G28+J28 -> 0 | M28: =M27+K28-L28 -> 12873670
A29: 26 | B29: 45834 | C29: 3172 | D29: 1567 | E29: 2478.11 | F29: 95.68 | G29: =E29*F29 -> 237105.56 | H29: 0 | I29: 0 | J29: =H29*I29 -> 0 | K29: =G29+J29 -> 237105.56 | M29: =M28+K29-L29 -> 13110775
A30: 27 | B30: 45835 | E30: 0 | F30: 0 | G30: =E30*F30 -> 0 | H30: 0 | I30: 0 | J30: =H30*I30 -> 0 | K30: =G30+J30 -> 0 | M30: =M29+K30-L30 -> 13110775
A31: 28 | B31: 45836 | C31: 3193 | D31: 1630 | E31: 2229.15 | F31: 95.68 | G31: =E31*F31 -> 213285.07 | H31: 0 | I31: 0 | J31: =H31*I31 -> 0 | K31: =G31+J31 -> 213285.07 | M31: =M30+K31-L31 -> 13324060
A32: 29 | B32: 45837 | D32: 1631 | E32: 2500 | F32: 95.68 | G32: =E32*F32 -> 239200 | H32: 20 | I32: 107.46 | J32: =H32*I32 -> 2149.2 | K32: =G32+J32 -> 241349.2 | M32: =M31+K32-L32 -> 13565410
A33: 30 | B33: 45838 | E33: 0 | F33: 0 | G33: =E33*F33 -> 0 | H33: 0 | I33: 0 | J33: =H33*I33 -> 0 | K33: =G33+J33 -> 0 | M33: =M32+K33-L33 -> 13565410
A34: 31 | E34: 0 | F34: 0 | G34: =E34*F34 -> 0 | H34: 0 | I34: 0 | J34: =H34*I34 -> 0 | K34: =G34+J34 -> 0 | M34: =M33+K34-L34 -> 13565410
A35: 32 | E35: 0 | F35: 0 | G35: =E35*F35 -> 0 | H35: 0 | I35: 0 | J35: =H35*I35 -> 0 | K35: =G35+J35 -> 0
A36: 33
E37: =SUM(E3:E36) -> 148695.59 | G37: =SUM(G3:G36) -> 14227153 | H37: =SUM(H3:H36) -> 630 | J37: =SUM(J3:J36) -> 67699.8 | K37: =SUM(K4:K36) -> 14294853 | L37: =SUM(L3:L36) -> 10036782

Sheet Khammam-3
A1: Jayasai union bunk
A2: S.No | B2: Date | C2: GRN No | D2: Ind No/Bill No | E2: Diesel (Lts) | F2: Price | G2: Amount | H2: Petrol (Lts) | I2: Price | J2: Amount | K2: Total amount | L2: Amount paid | M2: As 0n Date | N2: Remarks
A3: Opening Balance | K3: 7457303.4 | M3: =+K3 -> 7457303.4
A4: 1 | B4: 45809 | D4: 2924 | E4: =2500+1800 -> 4300 | F4: 95.7 | G4: =E4*F4 -> 411510 | H4: 0 | I4: 0 | J4: 0 | K4: =G4+J4 -> 411510 | M4: =M3+K4-L4 -> 7868813.4
A5: 2 | B5: 45810 | C5: 2924 | D5: 2932 | E5: 2384.25 | F5: 95.7 | G5: =E5*F5 -> 228172.73 | H5: 0 | I5: 0 | J5: 0 | K5: =G5+J5 -> 228172.73 | M5: =M4+K5-L5 -> 8096986.1
A6: 3 | B6: 45811 | C6: 2941 | D6: 2558/2557 | E6: 5299.96 | F6: 95.7 | G6: =E6*F6 -> 507206.17 | H6: 0 | I6: 0 | J6: 0 | K6: =G6+J6 -> 507206.17 | M6: =M5+K6-L6 -> 8604192.3
A7: 4 | B7: 45812 | C7: 2952 | D7: 2562 | E7: 2503.07 | F7: 95.7 | G7: =E7*F7 -> 239543.8 | H7: 0 | I7: 0 | J7: 0 | K7: =G7+J7 -> 239543.8 | M7: =M6+K7-L7 -> 8843736.1
A8: 5 | B8: 45813 | C8: 2963 | D8: 2579 | E8: 3024.9 | F8: 95.7 | G8: =E8*F8 -> 289482.93 | H8: 0 | I8: 0 | J8: 0 | K8: =G8+J8 -> 289482.93 | L8: 8843736.1 | M8: =M7+K8-L8 -> 289482.93
A9: 6 | B9: 45814 | C9: 2964 | D9: 2591/2590 | E9: 2700 | F9: 95.7 | G9: =E9*F9 -> 258390 | H9: 0 | I9: 0 | J9: 0 | K9: =G9+J9 -> 258390 | M9: =M8+K9-L9 -> 547872.93
A10: 7 | B10: 45815 | C10: 2987 | D10: 2601/2610 | E10: 2160.57 | F10: 95.7 | G10: =E10*F10 -> 206766.55 | H10: 37.98 | I10: 107.48 | J10: =H10*I10 -> 4082.0904 | K10: =G10+J10 -> 210848.64 | M10: =M9+K10-L10 -> 758721.57
A11: 8 | B11: 45816 | C11: 2990 | D11: 2617 | E11: 2321.49 | F11: 95.7 | G11: =E11*F11 -> 222166.59 | H11: 0 | I11: 0 | J11: =H11*I11 -> 0 | K11: =G11+J11 -> 222166.59 | M11: =M10+K11-L11 -> 980888.16
A12: 9 | B12: 45817 | C12: 3001 | D12: 2628/2630/2634/2636/2640 | E12: 10345.15 | F12: 95.7 | G12: =E12*F12 -> 990030.85 | H12: 95 | I12: 107.48 | J12: =H12*I12 -> 10210.6 | K12: =G12+J12 -> 1000241.5 | M12: =M11+K12-L12 -> 1981129.6
A13: 10 | B13: 45818 | E13: 0 | F13: 0 | G13: =E13*F13 -> 0 | H13: 0 | I13: 0 | J13: =H13*I13 -> 0 | K13: =G13+J13 -> 0 | M13: =M12+K13-L13 -> 1981129.6
A14: 11 | B14: 45819 | E14: 0 | F14: 0 | G14: =E14*F14 -> 0 | H14: 0 | I14: 0 | J14: =H14*I14 -> 0 | K14: =G14+J14 -> 0 | M14: =M13+K14-L14 -> 1981129.6
A15: 12 | B15: 45820 | E15: 0 | F15: 0 | G15: =E15*F15 -> 0 | H15: 0 | I15: 0 | J15: =H15*I15 -> 0 | K15: =G15+J15 -> 0 | M15: =M14+K15-L15 -> 1981129.6
A16: 13 | B16: 45821 | E16: 0 | F16: 0 | G16: =E16*F16 -> 0 | H16: 0 | I16: 0 | J16: =H16*I16 -> 0 | K16: =G16+J16 -> 0 | M16: =M15+K16-L16 -> 1981129.6
A17: 14 | B17: 45822 | E17: 0 | F17: 0 | G17: =E17*F17 -> 0 | H17: 0 | I17: 0 | J17: =H17*I17 -> 0 | K17: =G17+J17 -> 0 | M17: =M16+K17-L17 -> 1981129.6
A18: 15 | B18: 45823 | E18: 0 | F18: 0 | G18: =E18*F18 -> 0 | H18: 0 | I18: 0 | J18: =H18*I18 -> 0 | K18: =G18+J18 -> 0 | M18: =M17+K18-L18 -> 1981129.6
A19: 16 | B19: 45824 | E19: 0 | F19: 0 | G19: =E19*F19 -> 0 | H19: 0 | I19: 0 | J19: =H19*I19 -> 0 | K19: =G19+J19 -> 0 | M19: =M18+K19-L19 -> 1981129.6
A20: 17 | B20: 45825 | C20: 3073 | D20: 2657/2663/2664 | E20: 3029.76 | F20: 95.7 | G20: =E20*F20 -> 289948.03 | H20: 20 | I20: 107.48 | J20: =H20*I20 -> 2149.6 | K20: =G20+J20 -> 292097.63 | M20: =M19+K20-L20 -> 2273227.2
A21: 18 | B21: 45826 | C21: 3084 | D21: 2670/2674/2676/2679 | E21: 7800 | F21: 95.7 | G21: =E21*F21 -> 746460 | H21: 20 | I21: 107.48 | J21: =H21*I21 -> 2149.6 | K21: =G21+J21 -> 748609.6 | M21: =M20+K21-L21 -> 3021836.8
A22: 19 | B22: 45827 | C22: 3105 | D22: 2686/2689/2692/2695 | E22: 7500 | F22: 95.7 | G22: =E22*F22 -> 717750 | H22: 60 | I22: 107.48 | J22: =H22*I22 -> 6448.8 | K22: =G22+J22 -> 724198.8 | M22: =M21+K22-L22 -> 3746035.6
A23: 20 | B23: 45828 | C23: 3121 | D23: 2706/2710/2714/2716 | E23: 10300 | F23: 95.7 | G23: =E23*F23 -> 985710 | H23: 40 | I23: 107.48 | J23: =H23*I23 -> 4299.2 | K23: =G23+J23 -> 990009.2 | M23: =M22+K23-L23 -> 4736044.8 | O23: x
A24: 21 | B24: 45829 | E24: 0 | F24: 0 | G24: =E24*F24 -> 0 | H24: 0 | I24: 0 | J24: =H24*I24 -> 0 | K24: =G24+J24 -> 0 | M24: =M23+K24-L24 -> 4736044.8
A25: 22 | B25: 45830 | D25: 2731/2726/2739/2740 | E25: 10000 | F25: 95.7 | G25: =E25*F25 -> 957000 | H25: 20 | I25: 107.48 | J25: =H25*I25 -> 2149.6 | K25: =G25+J25 -> 959149.6 | M25: =M24+K25-L25 -> 5695194.4
A26: 23 | B26: 45831 | C26: 3152 | D26: 2755/2757/2763 | E26: 5300 | F26: 95.7 | G26: =E26*F26 -> 507210 | H26: 20 | I26: 107.48 | J26: =H26*I26 -> 2149.6 | K26: =G26+J26 -> 509359.6 | M26: =M25+K26-L26 -> 6204554
A27: 24 | B27: 45832 | C27: 3155 | D27: 2763/2770/2772/2774 | E27: 7800 | F27: 95.7 | G27: =E27*F27 -> 746460 | H27: 75 | I27: 107.48 | J27: =H27*I27 -> 8061 | K27: =G27+J27 -> 754521 | M27: =M26+K27-L27 -> 6959075
A28: 25 | B28: 45833 | C28: 3170 | D28: 2782/2787 | E28: 6200 | F28: 95.7 | G28: =E28*F28 -> 593340 | H28: 0 | I28: 0 | J28: =H28*I28 -> 0 | K28: =G28+J28 -> 593340 | M28: =M27+K28-L28 -> 7552415
A29: 26 | B29: 45834 | C29: 3173 | D29: 2791/2798/2802/2806 | E29: 9800 | F29: 95.7 | G29: =E29*F29 -> 937860 | H29: 20 | I29: 107.48 | J29: =H29*I29 -> 2149.6 | K29: =G29+J29 -> 940009.6 | M29: =M28+K29-L29 -> 8492424.6
A30: 27 | B30: 45835 | C30: 3190 | D30: 2808/2814/1816/1819 | E30: 8600 | F30: 95.7 | G30: =E30*F30 -> 823020 | H30: 75 | I30: 107.48 | J30: =H30*I30 -> 8061 | K30: =G30+J30 -> 831081 | M30: =M29+K30-L30 -> 9323505.6
A31: 28 | B31: 45836 | C31: 3194 | D31: 2822/2824/2827 | E31: 7300 | F31: 95.7 | G31: =E31*F31 -> 698610 | H31: 20 | I31: 107.48 | J31: =H31*I31 -> 2149.6 | K31: =G31+J31 -> 700759.6 | M31: =M30+K31-L31 -> 10024265
A32: 29 | B32: 45837 | C32: 3207 | D32: 2839 | E32: 696.99 | F32: 95.7 | G32: =E32*F32 -> 66701.943 | H32: 0 | I32: 0 | J32: =H32*I32 -> 0 | K32: =G32+J32 -> 66701.943 | M32: =M31+K32-L32 -> 10090967
A33: 30 | B33: 45838 | C33: 3208 | D33: 2852 | E33: 2100 | F33: 95.7 | G33: =E33*F33 -> 200970 | H33: 0 | I33: 0 | J33: =H33*I33 -> 0 | K33: =G33+J33 -> 200970 | M33: =M32+K33-L33 -> 10291937
A34: 31 | E34: 0 | F34: 0 | G34: =E34*F34 -> 0 | H34: 0 | I34: 0 | J34: =H34*I34 -> 0 | K34: =G34+J34 -> 0 | M34: =M33+K34-L34 -> 10291937
E35: =SUM(E4:E34) -> 121466.14 | G35: =SUM(G4:G34) -> 11624310 | H35: =SUM(H4:H34) -> 502.98 | J35: =SUM(J4:J34) -> 54060.29 | K35: =SUM(K4:K34) -> 11678370 | L35: =SUM(L4:L34) -> 8843736.1

Sheet Jedcherla -1
A1: Sai Baba Fuel Station
A2: S.No | B2: Date | C2: GRN No | D2: Ind No/Bill No | E2: Diesel (Lts) | F2: Price | G2: Amount | H2: Petrol (Lts) | I2: Price | J2: Amount | K2: Total amount | L2: Amount paid | M2: As on date | N2: Remarks
A3: Opening Balance | K3: 1149870.8 | M3: =+K3 -> 1149870.8
A4: 1 | B4: 45809 | E4: 0 | F4: 0 | G4: 0 | H4: 0 | I4: 0 | J4: =H4*I4 -> 0 | K4: =G4+J4 -> 0 | L4: 0 | M4: =M3+K4-L4 -> 1149870.8 | P4: 2259050
A5: 2 | B5: 45810 | E5: 2400 | F5: 96.42 | G5: =E5*F5 -> 231408 | H5: 19 | I5: 108.23 | J5: =H5*I5 -> 2056.37 | K5: =G5+J5 -> 233464.37 | L5: 0 | M5: =M4+K5-L5 -> 1383335.2
A6: 3 | B6: 45811 | E6: 0 | F6: 0 | G6: =E6*F6 -> 0 | H6: 35 | I6: 108.23 | J6: =H6*I6 -> 3788.05 | K6: =G6+J6 -> 3788.05 | L6: 0 | M6: =M5+K6-L6 -> 1387123.2
A7: 4 | B7: 45812 | E7: 2400 | F7: 96.42 | G7: =E7*F7 -> 231408 | H7: 5 | I7: 108.23 | J7: =H7*I7 -> 541.15 | K7: =G7+J7 -> 231949.15 | L7: 0 | M7: =M6+K7-L7 -> 1619072.4
A8: 5 | B8: 45813 | E8: 0 | F8: 0 | G8: =E8*F8 -> 0 | H8: 15 | I8: 108.23 | J8: =H8*I8 -> 1623.45 | K8: =G8+J8 -> 1623.45 | L8: 1619072 | M8: =M7+K8-L8 -> 1623.817 | P8: 23434
A9: 6 | B9: 45814 | E9: 2200 | F9: 96.42 | G9: =E9*F9 -> 212124 | H9: 20 | I9: 108.23 | J9: =H9*I9 -> 2164.6 | K9: =G9+J9 -> 214288.6 | L9: 0 | M9: =M8+K9-L9 -> 215912.42
A10: 7 | B10: 45815 | E10: 34.43 | F10: 96.42 | G10: =E10*F10 -> 3319.7406 | H10: 15 | I10: 108.23 | J10: =H10*I10 -> 1623.45 | K10: =G10+J10 -> 4943.1906 | L10: 0 | M10: =M9+K10-L10 -> 220855.61 | P10: =1619072*96.42 -> 1.5611092e+08
A11: 8 | B11: 45816 | E11: 1500 | F11: 96.42 | G11: =E11*F11 -> 144630 | H11: 29 | I11: 108.23 | J11: =H11*I11 -> 3138.67 | K11: =G11+J11 -> 147768.67 | L11: 0 | M11: =M10+K11-L11 -> 368624.28
A12: 9 | B12: 45817 | E12: 0 | F12: 0 | G12: =E12*F12 -> 0 | H12: 12 | I12: 108.23 | J12: =H12*I12 -> 1298.76 | K12: =G12+J12 -> 1298.76 | L12: 0 | M12: =M11+K12-L12 -> 369923.04
A13: 10 | B13: 45818 | C13: 1539.16 | D13: 0 | E13: 1539.16 | F13: 96.42 | G13: =E13*F13 -> 148405.81 | H13: 5 | I13: 108.23 | J13: =H13*I13 -> 541.15 | K13: =G13+J13 -> 148946.96 | L13: 0 | M13: =M12+K13-L13 -> 518869.99
A14: 11 | B14: 45819 | E14: 0 | F14: 0 | G14: =E14*F14 -> 0 | H14: 25 | I14: 108.23 | J14: =H14*I14 -> 2705.75 | K14: =G14+J14 -> 2705.75 | L14: 0 | M14: =M13+K14-L14 -> 521575.74 | S14: =1539-1490 -> 49
A15: 12 | B15: 45820 | E15: 1730.01 | F15: 96.42 | G15: =E15*F15 -> 166807.56 | H15: 10 | I15: 108.23 | J15: =H15*I15 -> 1082.3 | K15: =G15+J15 -> 167889.86 | L15: 0 | M15: =M14+K15-L15 -> 689465.61 | S15: =1730-1958 -> -228
A16: 13 | B16: 45821 | E16: 228 | F16: 96.42 | G16: =E16*F16 -> 21983.76 | H16: 20 | I16: 108.23 | J16: =H16*I16 -> 2164.6 | K16: =G16+J16 -> 24148.36 | L16: 0 | M16: =M15+K16-L16 -> 713613.97
A17: 14 | B17: 45822 | E17: 2032 | F17: 96.42 | G17: =E17*F17 -> 195925.44 | H17: 10 | I17: 108.23 | J17: =H17*I17 -> 1082.3 | K17: =G17+J17 -> 197007.74 | L17: 0 | M17: =M16+K17-L17 -> 910621.71
A18: 15 | B18: 45823 | D18: 2000 | E18: 0 | F18: 0 | G18: =E18*F18 -> 0 | H18: 15 | I18: 108.23 | J18: =H18*I18 -> 1623.45 | K18: =G18+J18 -> 1623.45 | L18: 0 | M18: =M17+K18-L18 -> 912245.16
A19: 16 | B19: 45824 | D19: 1000 | E19: 3000 | F19: 96.42 | G19: =E19*F19 -> 289260 | H19: 20 | I19: 108.23 | J19: =H19*I19 -> 2164.6 | K19: =G19+J19 -> 291424.6 | L19: 0 | M19: =M18+K19-L19 -> 1203669.8
A20: 17 | B20: 45825 | E20: 2053.97 | F20: 96.42 | G20: =E20*F20 -> 198043.79 | H20: 15 | I20: 108.23 | J20: =H20*I20 -> 1623.45 | K20: =G20+J20 -> 199667.24 | L20: 0 | M20: =M19+K20-L20 -> 1403337
A21: 18 | B21: 45826 | D21: 2200 | E21: 0 | F21: 96.42 | G21: =E21*F21 -> 0 | H21: 20 | I21: 108.23 | J21: =H21*I21 -> 2164.6 | K21: =G21+J21 -> 2164.6 | L21: 0 | M21: =M20+K21-L21 -> 1405501.6
A22: 19 | B22: 45827 | C22: 2500 | D22: 0 | E22: 2500 | F22: 96.42 | G22: =E22*F22 -> 241050 | H22: 20 | I22: 108.23 | J22: =H22*I22 -> 2164.6 | K22: =G22+J22 -> 243214.6 | L22: 0 | M22: =M21+K22-L22 -> 1648716.2 | P22: 2422641
A23: 20 | B23: 45828 | E23: 0 | F23: 0 | G23: =E23*F23 -> 0 | H23: 16.35 | I23: 108.23 | J23: =H23*I23 -> 1769.5605 | K23: =G23+J23 -> 1769.5605 | L23: 0 | M23: =M22+K23-L23 -> 1650485.8 | P23: 2419549
A24: 21 | B24: 45829 | E24: 2830 | F24: 96.42 | G24: =E24*F24 -> 272868.6 | H24: 20 | I24: 108.23 | J24: =H24*I24 -> 2164.6 | K24: =G24+J24 -> 275033.2 | L24: 0 | M24: =M23+K24-L24 -> 1925519 | P24: =P23-P22 -> -3092
A25: 22 | B25: 45830 | E25: 0 | F25: 0 | G25: =E25*F25 -> 0 | H25: 5 | I25: 108.23 | J25: =H25*I25 -> 541.15 | K25: =G25+J25 -> 541.15 | L25: 0 | M25: =M24+K25-L25 -> 1926060.1
A26: 23 | B26: 45831 | E26: 2030.8 | F26: 96.42 | G26: =E26*F26 -> 195809.74 | H26: 15 | I26: 108.23 | J26: =H26*I26 -> 1623.45 | K26: =G26+J26 -> 197433.19 | L26: 0 | M26: =M25+K26-L26 -> 2123493.3
A27: 24 | B27: 45832 | E27: 0 | F27: 0 | G27: =E27*F27 -> 0 | H27: 24 | I27: 108.23 | J27: =H27*I27 -> 2597.52 | K27: =G27+J27 -> 2597.52 | L27: 0 | M27: =M26+K27-L27 -> 2126090.8
A28: 25 | B28: 45833 | E28: 0 | F28: 0 | G28: =E28*F28 -> 0 | H28: 10 | I28: 108.23 | J28: =H28*I28 -> 1082.3 | K28: =G28+J28 -> 1082.3 | L28: 0 | M28: =M27+K28-L28 -> 2127173.1 | U28: =2139146-M35 -> -0.1929
A29: 26 | B29: 45834 | E29: 0 | F29: 0 | G29: =E29*F29 -> 0 | H29: 20 | I29: 108.23 | J29: =H29*I29 -> 2164.6 | K29: =G29+J29 -> 2164.6 | L29: 0 | M29: =M28+K29-L29 -> 2129337.7
A30: 27 | B30: 45835 | E30: 35.5 | F30: 96.42 | G30: =E30*F30 -> 3422.91 | H30: 20 | I30: 108.23 | J30: =H30*I30 -> 2164.6 | K30: =G30+J30 -> 5587.51 | L30: 0 | M30: =M29+K30-L30 -> 2134925.2
A31: 28 | B31: 45836 | E31: 0 | F31: 0 | G31: =E31*F31 -> 0 | H31: 15 | I31: 108.23 | J31: =H31*I31 -> 1623.45 | K31: =G31+J31 -> 1623.45 | L31: 0 | M31: =M30+K31-L31 -> 2136548.7
A32: 29 | B32: 45837 | E32: 0 | F32: 0 | G32: =E32*F32 -> 0 | H32: 15 | I32: 108.23 | J32: =H32*I32 -> 1623.45 | K32: =G32+J32 -> 1623.45 | L32: 0 | M32: =M31+K32-L32 -> 2138172.1
A33: 30 | B33: 45838 | E33: 0 | F33: 0 | G33: =E33*F33 -> 0 | H33: 9 | I33: 108.23 | J33: =H33*I33 -> 974.07 | K33: =G33+J33 -> 974.07 | L33: 0 | M33: =M32+K33-L33 -> 2139146.2
A34: 31 | E34: 0 | F34: 0 | G34: =E34*F34 -> 0 | H34: 0 | I34: 0 | J34: =H34*I34 -> 0 | K34: =G34+J34 -> 0 | L34: 0 | M34: =M33+K34-L34 -> 2139146.2
E35: 0 | F35: 0 | G35: =E35*F35 -> 0 | H35: 0 | I35: 0 | J35: =H35*I35 -> 0 | K35: =G35+J35 -> 0 | M35: =M34+K35-L35 -> 2139146.2
E36: =SUM(E4:E34) -> 26513.87 | G36: =SUM(G4:G34) -> 2556467.3 | H36: =SUM(H4:H34) -> 479.35 | J36: =SUM(J4:J34) -> 51880.05 | K36: =SUM(K4:K34) -> 2608347.4 | L36: =SUM(L4:L34) -> 1619072
E38: 26130
E39: =E36-E38 -> 383.87

Sheet Jedcherla-2
A1: Uttara Enterprises
A2: S.No | B2: Date | C2: GRN No | D2: Ind No/Bill No | E2: Diesel (Lts) | F2: Price | G2: Amount | H2: Petrol (Lts) | I2: Price | J2: Amount | K2: Total amount | L2: Amount paid | M2: As on Date | N2: Remarks
A3: Opening Balance | K3: 331699.53 | M3: =+K3 -> 331699.53
A4: 1 | B4: 45809 | G4: =E4*F4 -> 0 | J4: =H4*I4 -> 0 | K4: =G4+J4 -> 0 | M4: =M3+K4-L4 -> 331699.53
A5: 2 | B5: 45810 | E5: 0 | F5: 0 | G5: =E5*F5 -> 0 | J5: =H5*I5 -> 0 | K5: =G5+J5 -> 0 | M5: =M4+K5-L5 -> 331699.53
A6: 3 | B6: 45811 | E6: 0 | F6: 0 | G6: =E6*F6 -> 0 | J6: =H6*I6 -> 0 | K6: =G6+J6 -> 0 | M6: =M5+K6-L6 -> 331699.53 | R6: 541.08
A7: 4 | B7: 45812 | E7: 0 | F7: 0 | G7: =E7*F7 -> 0 | J7: =H7*I7 -> 0 | K7: =G7+J7 -> 0 | L7: 331700 | M7: =M6+K7-L7 -> -0.4737
A8: 5 | B8: 45813 | E8: 0 | F8: 0 | G8: =E8*F8 -> 0 | J8: =H8*I8 -> 0 | K8: =G8+J8 -> 0 | M8: =M7+K8-L8 -> -0.4737
A9: 6 | B9: 45814 | E9: 0 | F9: 0 | G9: =E9*F9 -> 0 | J9: =H9*I9 -> 0 | K9: =G9+J9 -> 0 | M9: =M8+K9-L9 -> -0.4737
A10: 7 | B10: 45815 | E10: 0 | F10: 0 | G10: =E10*F10 -> 0 | J10: =H10*I10 -> 0 | K10: =G10+J10 -> 0 | M10: =M9+K10-L10 -> -0.4737
A11: 8 | B11: 45816 | E11: 0 | F11: 0 | G11: =E11*F11 -> 0 | J11: =H11*I11 -> 0 | K11: =G11+J11 -> 0 | M11: =M10+K11-L11 -> -0.4737
A12: 9 | B12: 45817 | E12: 0 | F12: 0 | G12: =E12*F12 -> 0 | J12: =H12*I12 -> 0 | K12: =G12+J12 -> 0 | M12: =M11+K12-L12 -> -0.4737
A13: 10 | B13: 45818 | E13: 0 | F13: 0 | G13: =E13*F13 -> 0 | J13: =H13*I13 -> 0 | K13: =G13+J13 -> 0 | M13: =M12+K13-L13 -> -0.4737
A14: 11 | B14: 45819 | E14: 0 | F14: 0 | G14: =E14*F14 -> 0 | J14: =H14*I14 -> 0 | K14: =G14+J14 -> 0 | M14: =M13+K14-L14 -> -0.4737
A15: 12 | B15: 45820 | E15: 0 | F15: 0 | G15: =E15*F15 -> 0 | J15: =H15*I15 -> 0 | K15: =G15+J15 -> 0 | M15: =M14+K15-L15 -> -0.4737
A16: 13 | B16: 45821 | E16: 0 | F16: 0 | G16: =E16*F16 -> 0 | J16: =H16*I16 -> 0 | K16: =G16+J16 -> 0 | M16: =M15+K16-L16 -> -0.4737
A17: 14 | B17: 45822 | E17: 0 | F17: 0 | G17: =E17*F17 -> 0 | J17: =H17*I17 -> 0 | K17: =G17+J17 -> 0 | M17: =M16+K17-L17 -> -0.4737
A18: 15 | B18: 45823 | E18: 0 | F18: 0 | G18: =E18*F18 -> 0 | J18: =H18*I18 -> 0 | K18: =G18+J18 -> 0 | M18: =M17+K18-L18 -> -0.4737
A19: 16 | B19: 45824 | E19: 0 | F19: 0 | G19: =E19*F19 -> 0 | J19: =H19*I19 -> 0 | K19: =G19+J19 -> 0 | M19: =M18+K19-L19 -> -0.4737
... A29: 26 | B29: 45834 | E29: 0 | F29: 0 | G29: =E29*F29 -> 0 | J29: =H29*I29 -> 0 | K29: =G29+J29 -> 0 | M29: =M28+K29-L29 -> -0.4737
A30: 27 | B30: 45835 | E30: 0 | F30: 0 | G30: =E30*F30 -> 0 | J30: =H30*I30 -> 0 | K30: =G30+J30 -> 0 | M30: =M29+K30-L30 -> -0.4737 | P30: =2939612.08-2939070.93 -> 541.15
A31: 28 | B31: 45836 | E31: 0 | F31: 0 | G31: =E31*F31 -> 0 | J31: =H31*I31 -> 0 | K31: =G31+J31 -> 0 | M31: =M30+K31-L31 -> -0.4737
A32: 29 | B32: 45837 | E32: 0 | F32: 0 | G32: =E32*F32 -> 0 | J32: =H32*I32 -> 0 | K32: =G32+J32 -> 0
A33: 30 | B33: 45838 | E33: 0 | F33: 0 | G33: =E33*F33 -> 0 | J33: =H33*I33 -> 0 | K33: =G33+J33 -> 0
A34: 31 | E34: 0 | F34: 0 | G34: =E34*F34 -> 0 | J34: =H34*I34 -> 0 | K34: =G34+J34 -> 0
E35: =SUM(E4:E34) -> 0 | G35: =SUM(G4:G34) -> 0 | H35: =SUM(H4:H34) -> 0 | J35: =SUM(J4:J34) -> 0 | K35: =SUM(K4:K34) -> 0 | L35: =SUM(L4:L34) -> 331700

Sheet Jedcharla-3
A1: ADHOC FILLING STATION STATION
A2: S.No | B2: Date | C2: GRN No | D2: Ind No/Bill No | E2: Diesel (Lts) | F2: Price | G2: Amount | H2: Petrol (Lts) | I2: Price | J2: Amount | K2: Total amount | L2: Amount paid | M2: As on Date | N2: Remarks
A3: Opening Balance | K3: 0 | M3: =+K3 -> 0
A4: 1 | B4: 45809 | E4: 2400 | F4: 96.43 | G4: =E4*F4 -> 231432 | J4: =H4*I4 -> 0 | K4: =G4+J4 -> 231432 | M4: =M3+K4-L4 -> 231432
A5: 2 | B5: 45810 | G5: =E5*F5 -> 0 | J5: =H5*I5 -> 0 | K5: =G5+J5 -> 0 | M5: =M4+K5-L5 -> 231432
A6: 3 | B6: 45811 | E6: 2100 | F6: 96.43 | G6: =E6*F6 -> 202503 | J6: =H6*I6 -> 0 | K6: =G6+J6 -> 202503 | M6: =M5+K6-L6 -> 433935 | R6: 541.08
A7: 4 | B7: 45812 | G7: =E7*F7 -> 0 | J7: =H7*I7 -> 0 | K7: =G7+J7 -> 0 | M7: =M6+K7-L7 -> 433935
A8: 5 | B8: 45813 | E8: 2400 | F8: 96.43 | G8: =E8*F8 -> 231432 | J8: =H8*I8 -> 0 | K8: =G8+J8 -> 231432 | L8: 433935 | M8: =M7+K8-L8 -> 231432
A9: 6 | B9: 45814 | G9: =E9*F9 -> 0 | J9: =H9*I9 -> 0 | K9: =G9+J9 -> 0 | M9: =M8+K9-L9 -> 231432
A10: 7 | B10: 45815 | E10: 2460 | F10: 96.43 | G10: =E10*F10 -> 237217.8 | J10: =H10*I10 -> 0 | K10: =G10+J10 -> 237217.8 | M10: =M9+K10-L10 -> 468649.8
A11: 8 | B11: 45816 | G11: =E11*F11 -> 0 | J11: =H11*I11 -> 0 | K11: =G11+J11 -> 0 | M11: =M10+K11-L11 -> 468649.8
A12: 9 | B12: 45817 | E12: 1428 | F12: 96.43 | G12: =E12*F12 -> 137702.04 | J12: =H12*I12 -> 0 | K12: =G12+J12 -> 137702.04 | M12: =M11+K12-L12 -> 606351.84
A13: 10 | B13: 45818 | E13: 0 | G13: =E13*F13 -> 0 | J13: =H13*I13 -> 0 | K13: =G13+J13 -> 0 | M13: =M12+K13-L13 -> 606351.84
A14: 11 | B14: 45819 | E14: 1400 | F14: 96.43 | G14: =E14*F14 -> 135002 | J14: =H14*I14 -> 0 | K14: =G14+J14 -> 135002 | M14: =M13+K14-L14 -> 741353.84
A15: 12 | B15: 45820 | G15: =E15*F15 -> 0 | J15: =H15*I15 -> 0 | K15: =G15+J15 -> 0 | M15: =M14+K15-L15 -> 741353.84
A16: 13 | B16: 45821 | E16: 2000 | F16: 96.43 | G16: =E16*F16 -> 192860 | J16: =H16*I16 -> 0 | K16: =G16+J16 -> 192860 | M16: =M15+K16-L16 -> 934213.84
A17: 14 | B17: 45822 | G17: =E17*F17 -> 0 | J17: =H17*I17 -> 0 | K17: =G17+J17 -> 0 | M17: =M16+K17-L17 -> 934213.84
A18: 15 | B18: 45823 | E18: 1200 | F18: 96.43 | G18: =E18*F18 -> 115716 | J18: =H18*I18 -> 0 | K18: =G18+J18 -> 115716 | M18: =M17+K18-L18 -> 1049929.8
A19: 16 | B19: 45824 | G19: =E19*F19 -> 0 | J19: =H19*I19 -> 0 | K19: =G19+J19 -> 0 | M19: =M18+K19-L19 -> 1049929.8
A20: 17 | B20: 45825 | G20: =E20*F20 -> 0 | J20: =H20*I20 -> 0 | K20: =G20+J20 -> 0 | M20: =M19+K20-L20 -> 1049929.8
A21: 18 | B21: 45826 | E21: 2200 | F21: 96.43 | G21: =E21*F21 -> 212146 | J21: =H21*I21 -> 0 | K21: =G21+J21 -> 212146 | M21: =M20+K21-L21 -> 1262075.8 | P21: 2200 | Q21: =2200*96.43 -> 212146
A22: 19 | B22: 45827 | E22: 1500 | F22: 96.43 | G22: =E22*F22 -> 144645 | J22: =H22*I22 -> 0 | K22: =G22+J22 -> 144645 | M22: =M21+K22-L22 -> 1406720.8
A23: 20 | B23: 45828 | G23: =E23*F23 -> 0 | J23: =H23*I23 -> 0 | K23: =G23+J23 -> 0 | M23: =M22+K23-L23 -> 1406720.8
A24: 21 | B24: 45829 | G24: =E24*F24 -> 0 | J24: =H24*I24 -> 0 | K24: =G24+J24 -> 0 | M24: =M23+K24-L24 -> 1406720.8
A25: 22 | B25: 45830 | E25: 2000 | F25: 96.43 | G25: =E25*F25 -> 192860 | J25: =H25*I25 -> 0 | K25: =G25+J25 -> 192860 | M25: =M24+K25-L25 -> 1599580.8
A26: 23 | B26: 45831 | G26: =E26*F26 -> 0 | J26: =H26*I26 -> 0 | K26: =G26+J26 -> 0 | M26: =M25+K26-L26 -> 1599580.8
A27: 24 | B27: 45832 | E27: 3984.59 | F27: 96.43 | G27: =E27*F27 -> 384234.01 | J27: =H27*I27 -> 0 | K27: =G27+J27 -> 384234.01 | M27: =M26+K27-L27 -> 1983814.9
A28: 25 | B28: 45833 | E28: 4200 | F28: 96.43 | G28: =E28*F28 -> 405006 | J28: =H28*I28 -> 0 | K28: =G28+J28 -> 405006 | M28: =M27+K28-L28 -> 2388820.9
A29: 26 | B29: 45834 | E29: 1723 | F29: 96.43 | G29: =E29*F29 -> 166148.89 | J29: =H29*I29 -> 0 | K29: =G29+J29 -> 166148.89 | M29: =M28+K29-L29 -> 2554969.7 | P29: 4200
A30: 27 | B30: 45835 | E30: 2000 | F30: 96.43 | G30: =E30*F30 -> 192860 | J30: =H30*I30 -> 0 | K30: =G30+J30 -> 192860 | L30: 2300000 | M30: =M29+K30-L30 -> 447829.74
A31: 28 | B31: 45836 | E31: 2000 | F31: 96.43 | G31: =E31*F31 -> 192860 | J31: =H31*I31 -> 0 | K31: =G31+J31 -> 192860 | M31: =M30+K31-L31 -> 640689.74 | P31: =SUM(P21:P30) -> 6400 | Q31: =62008*6.43 -> 398711.44
A32: 29 | B32: 45837 | E32: 2400 | F32: 96.43 | G32: =E32*F32 -> 231432 | J32: =H32*I32 -> 0 | K32: =G32+J32 -> 231432 | M32: =M31+K32-L32 -> 872121.74
A33: 30 | B33: 45838 | E33: 3500 | F33: 96.43 | G33: =E33*F33 -> 337505 | J33: =H33*I33 -> 0 | K33: =G33+J33 -> 337505 | M33: =M32+K33-L33 -> 1209626.7
A34: 31 | G34: =E34*F34 -> 0 | J34: =H34*I34 -> 0 | K34: =G34+J34 -> 0 | M34: =M33+K34-L34 -> 1209626.7
E35: =SUM(E4:E34) -> 40895.59 | G35: =SUM(G4:G34) -> 3943561.7 | H35: =SUM(H4:H34) -> 0 | J35: =SUM(J4:J34) -> 0 | K35: =SUM(K4:K34) -> 3943561.7 | L35: =SUM(L4:L34) -> 2733935

Sheet Sangareddy
A1: Sree Shiva Parvathi Filling Station
A2: S.No | B2: Date | C2: GRN No | D2: Ind No/Bill No | E2: Diesel (Lts) | F2: Price | G2: Amount | H2: Petrol (Lts) | I2: Price | J2: Amount | K2: Total amount | L2: Amount paid | M2: As on Date | N2: Remarks
A3: Opening Balance | K3: 0 | M3: =+K3 -> 0
A4: 1 | B4: 45809 | E4: 0 | F4: 0 | G4: =E4*F4 -> 0 | H4: 0 | I4: 0 | J4: =H4*I4 -> 0 | K4: =G4+J4 -> 0 | M4: =M3+K4-L4 -> 0
A5: 2 | B5: 45810 | E5: 700 | F5: 96.23 | G5: =E5*F5 -> 67361 | H5: 0 | I5: 0 | J5: =H5*I5 -> 0 | K5: =G5+J5 -> 67361 | L5: =+K5 -> 67361 | M5: =M4+K5-L5 -> 0
A6: 3 | B6: 45811 | E6: 290 | F6: 96.23 | G6: =E6*F6 -> 27906.7 | H6: 0 | I6: 0 | J6: =H6*I6 -> 0 | K6: =G6+J6 -> 27906.7 | L6: =+K6 -> 27906.7 | M6: =M5+K6-L6 -> 0
B7: 45811 | E7: 400 | F7: 96.23 | G7: =E7*F7 -> 38492 | H7: 0 | I7: 0 | J7: =H7*I7 -> 0 | K7: =G7+J7 -> 38492 | M7: =M6+K7-L7 -> 38492
A8: 4 | B8: 45812 | E8: 100 | F8: 96.23 | G8: =E8*F8 -> 9623 | H8: 0 | I8: 0 | J8: =H8*I8 -> 0 | K8: =G8+J8 -> 9623 | L8: 48115 | M8: =M7+K8-L8 -> 0
A9: 5 | B9: 45813 | E9: 600 | F9: 96.23 | G9: =E9*F9 -> 57738 | H9: 0 | I9: 0 | J9: =H9*I9 -> 0 | K9: =G9+J9 -> 57738 | M9: =M8+K9-L9 -> 57738
A10: 6 | B10: 45814 | E10: 600 | F10: 96.23 | G10: =E10*F10 -> 57738 | H10: 0 | I10: 0 | J10: =H10*I10 -> 0 | K10: =G10+J10 -> 57738 | M10: =M9+K10-L10 -> 115476
A11: 7 | B11: 45815 | E11: 600 | F11: 96.23 | G11: =E11*F11 -> 57738 | H11: 20 | I11: 108.03 | J11: =H11*I11 -> 2160.6 | K11: =G11+J11 -> 59898.6 | M11: =M10+K11-L11 -> 175374.6
A12: 8 | B12: 45816 | E12: 0 | F12: 0 | G12: =E12*F12 -> 0 | H12: 0 | I12: 0 | J12: =H12*I12 -> 0 | K12: =G12+J12 -> 0 | M12: =M11+K12-L12 -> 175374.6
A13: 9 | B13: 45817 | E13: 0 | F13: 0 | G13: =E13*F13 -> 0 | H13: 0 | I13: 0 | J13: =H13*I13 -> 0 | K13: =G13+J13 -> 0 | M13: =M12+K13-L13 -> 175374.6
A14: 10 | B14: 45818 | E14: 0 | F14: 0 | G14: =E14*F14 -> 0 | H14: 0 | I14: 0 | J14: =H14*I14 -> 0 | K14: =G14+J14 -> 0 | M14: =M13+K14-L14 -> 175374.6
A15: 11 | B15: 45819 | E15: 600 | F15: 96.23 | G15: =E15*F15 -> 57738 | H15: 20 | I15: 108.03 | J15: =H15*I15 -> 2160.6 | K15: =G15+J15 -> 59898.6 | M15: =M14+K15-L15 -> 235273.2
A16: 12 | B16: 45820 | E16: 0 | F16: 0 | G16: =E16*F16 -> 0 | H16: 0 | I16: 0 | J16: =H16*I16 -> 0 | K16: =G16+J16 -> 0 | M16: =M15+K16-L16 -> 235273.2
A17: 13 | B17: 45821 | E17: 600 | F17: 96.23 | G17: =E17*F17 -> 57738 | H17: 0 | I17: 0 | J17: =H17*I17 -> 0 | K17: =G17+J17 -> 57738 | M17: =M16+K17-L17 -> 293011.2
A18: 14 | B18: 45822 | E18: 0 | F18: 0 | G18: =E18*F18 -> 0 | H18: 0 | I18: 0 | J18: =H18*I18 -> 0 | K18: =G18+J18 -> 0 | M18: =M17+K18-L18 -> 293011.2
A19: 15 | B19: 45823 | E19: 800 | F19: 96.23 | G19: =E19*F19 -> 76984 | H19: 20 | I19: 108.03 | J19: =H19*I19 -> 2160.6 | K19: =G19+J19 -> 79144.6 | M19: =M18+K19-L19 -> 372155.8
A20: 16 | B20: 45824 | E20: 0 | F20: 0 | G20: =E20*F20 -> 0 | H20: 0 | I20: 0 | J20: =H20*I20 -> 0 | K20: =G20+J20 -> 0 | M20: =M19+K20-L20 -> 372155.8
A21: 17 | B21: 45825 | E21: 0 | F21: 0 | G21: =E21*F21 -> 0 | H21: 0 | I21: 0 | J21: =H21*I21 -> 0 | K21: =G21+J21 -> 0 | M21: =M20+K21-L21 -> 372155.8
A22: 18 | B22: 45826 | E22: 800 | F22: 96.23 | G22: =E22*F22 -> 76984 | H22: 20 | I22: 108.03 | J22: =H22*I22 -> 2160.6 | K22: =G22+J22 -> 79144.6 | L22: 372155.8 | M22: =M21+K22-L22 -> 79144.6
A23: 19 | B23: 45827 | E23: 0 | F23: 0 | G23: =E23*F23 -> 0 | H23: 0 | I23: 0 | J23: =H23*I23 -> 0 | K23: =G23+J23 -> 0 | M23: =M22+K23-L23 -> 79144.6
A24: 20 | B24: 45828 | E24: 700 | F24: 96.23 | G24: =E24*F24 -> 67361 | H24: 20 | I24: 108.03 | J24: =H24*I24 -> 2160.6 | K24: =G24+J24 -> 69521.6 | M24: =M23+K24-L24 -> 148666.2
A25: 21 | B25: 45829 | E25: 0 | F25: 0 | G25: =E25*F25 -> 0 | H25: 0 | I25: 0 | J25: =H25*I25 -> 0 | K25: =G25+J25 -> 0 | M25: =M24+K25-L25 -> 148666.2
A26: 22 | B26: 45830 | E26: 600 | F26: 96.23 | G26: =E26*F26 -> 57738 | H26: 0 | I26: 0 | J26: =H26*I26 -> 0 | K26: =G26+J26 -> 57738 | M26: =M25+K26-L26 -> 206404.2
A27: 23 | B27: 45831 | E27: 0 | F27: 0 | G27: =E27*F27 -> 0 | H27: 0 | I27: 0 | J27: =H27*I27 -> 0 | K27: =G27+J27 -> 0 | M27: =M26+K27-L27 -> 206404.2
A28: 24 | B28: 45832 | E28: 800 | F28: 96.23 | G28: =E28*F28 -> 76984 | H28: 0 | I28: 0 | J28: =H28*I28 -> 0 | K28: =G28+J28 -> 76984 | M28: =M27+K28-L28 -> 283388.2
A29: 25 | B29: 45833 | E29: 0 | F29: 0 | G29: =E29*F29 -> 0 | H29: 0 | I29: 0 | J29: =H29*I29 -> 0 | K29: =G29+J29 -> 0 | M29: =M28+K29-L29 -> 283388.2
A30: 26 | B30: 45834 | E30: 0 | F30: 96.23 | G30: =E30*F30 -> 0 | H30: 0 | I30: 0 | J30: =H30*I30 -> 0 | K30: =G30+J30 -> 0 | M30: =M29+K30-L30 -> 283388.2
A31: 27 | B31: 45835 | E31: 0 | F31: 0 | G31: =E31*F31 -> 0 | H31: 0 | I31: 0 | J31: =H31*I31 -> 0 | K31: =G31+J31 -> 0 | M31: =M30+K31-L31 -> 283388.2
A32: 28 | B32: 45836 | E32: 800 | F32: 96.23 | G32: =E32*F32 -> 76984 | H32: 20 | I32: 108.23 | J32: =H32*I32 -> 2164.6 | K32: =G32+J32 -> 79148.6 | M32: =M31+K32-L32 -> 362536.8
A33: 29 | B33: 45837 | E33: 0 | F33: 0 | G33: =E33*F33 -> 0 | H33: 0 | I33: 0 | J33: =H33*I33 -> 0 | K33: =G33+J33 -> 0 | M33: =M32+K33-L33 -> 362536.8
A34: 30 | B34: 45838 | E34: 0 | F34: 0 | G34: =E34*F34 -> 0 | H34: 0 | I34: 0 | J34: =H34*I34 -> 0 | K34: =G34+J34 -> 0 | M34: =M33+K34-L34 -> 362536.8
... A39: 35 | B39: 45843 | E39: 0 | F39: 0 | G39: =E39*F39 -> 0 | H39: 0 | I39: 0 | J39: =H39*I39 -> 0 | K39: =G39+J39 -> 0 | M39: =M38+K39-L39 -> 362536.8
E40: =SUM(E4:E39) -> 8990 | G40: =SUM(G4:G39) -> 865107.7 | H40: =SUM(H4:H39) -> 120 | J40: =SUM(J4:J39) -> 12967.6 | K40: =SUM(K4:K39) -> 878075.3 | L40: =SUM(L4:L39) -> 515538.5

Sheet Dindi
A1: Akarapu Balakistamma Fillling
A2: S.No | B2: Date | C2: GRN No | D2: Ind no/Bill No | E2: Diesel (Lts) | F2: Price | G2: Amount | H2: Petrol (Lts) | I2: Price | J2: Amount | K2: Total amount | L2: Amount paid | M2: As on Date | N2: Remarks
A3: Opening Balance | M3: 0
A4: 1 | B4: 45809 | E4: 0 | F4: 0 | G4: =E4*F4 -> 0 | H4: 0 | I4: 0 | J4: =H4*I4 -> 0 | K4: =G4+J4 -> 0 | L4: =+K4 -> 0 | M4: 0
A5: 2 | B5: 45810 | E5: 0 | F5: 0 | G5: =E5*F5 -> 0 | H5: 0 | I5: 0 | J5: =H5*I5 -> 0 | K5: =G5+J5 -> 0 | L5: =+K5 -> 0 | M5: 0
A6: 3 | B6: 45811 | E6: 0 | F6: 0 | G6: =E6*F6 -> 0 | H6: 0 | I6: 0 | J6: =H6*I6 -> 0 | K6: =G6+J6 -> 0 | L6: =+K6 -> 0 | M6: 0
A7: 4 | B7: 45812 | E7: 51.64 | F7: 96.83 | G7: =E7*F7 -> 5000.3012 | H7: 0 | I7: 0 | J7: =H7*I7 -> 0 | K7: =G7+J7 -> 5000.3012 | L7: =+K7 -> 5000.3012 | M7: 0
A8: 5 | B8: 45813 | E8: 0 | F8: 0 | G8: =E8*F8 -> 0 | H8: 0 | I8: 0 | J8: =H8*I8 -> 0 | K8: =G8+J8 -> 0 | L8: =+K8 -> 0 | M8: 0
A9: 6 | B9: 45814 | E9: 0 | F9: 0 | G9: =E9*F9 -> 0 | H9: 0 | I9: 0 | J9: =H9*I9 -> 0 | K9: =G9+J9 -> 0 | L9: =+K9 -> 0 | M9: 0
A10: 7 | B10: 45815 | E10: 0 | F10: 0 | G10: =E10*F10 -> 0 | H10: 0 | I10: 0 | J10: =H10*I10 -> 0 | K10: =G10+J10 -> 0 | L10: =+K10 -> 0 | M10: 0
A11: 8 | B11: 45816 | E11: 0 | F11: 0 | G11: =E11*F11 -> 0 | H11: 0 | I11: 0 | J11: =H11*I11 -> 0 | K11: =G11+J11 -> 0 | L11: =+K11 -> 0 | M11: 0
A12: 9 | B12: 45817 | E12: 0 | F12: 0 | G12: =E12*F12 -> 0 | H12: 0 | I12: 0 | J12: =H12*I12 -> 0 | K12: =G12+J12 -> 0 | L12: =+K12 -> 0 | M12: 0
A13: 10 | B13: 45818 | E13: 0 | F13: 0 | G13: =E13*F13 -> 0 | H13: 0 | I13: 0 | J13: =H13*I13 -> 0 | K13: =G13+J13 -> 0 | L13: =+K13 -> 0 | M13: 0
A14: 11 | B14: 45819 | E14: 0 | F14: 0 | G14: =E14*F14 -> 0 | H14: 0 | I14: 0 | J14: =H14*I14 -> 0 | K14: =G14+J14 -> 0 | L14: =+K14 -> 0 | M14: 0
A15: 12 | B15: 45820 | E15: 124.06 | F15: 96.83 | G15: =E15*F15 -> 12012.73 | H15: 0 | I15: 0 | J15: =H15*I15 -> 0 | K15: =G15+J15 -> 12012.73 | L15: =+K15 -> 12012.73 | M15: 0
... A33: 30 | B33: 45838 | E33: 0 | F33: 0 | G33: =E33*F33 -> 0 | H33: 0 | I33: 0 | J33: =H33*I33 -> 0 | K33: =G33+J33 -> 0 | L33: =+K33 -> 0 | M33: 0
A34: 31 | E34: 0 | F34: 0 | G34: =E34*F34 -> 0 | H34: 0 | I34: 0 | J34: =H34*I34 -> 0 | K34: =G34+J34 -> 0 | L34: =+K34 -> 0 | M34: 0
E35: =SUM(E4:E34) -> 175.7 | G35: =SUM(G4:G34) -> 17013.031 | H35: =SUM(H4:H34) -> 7.35 | J35: =SUM(J4:J34) -> 798.651 | K35: =SUM(K4:K34) -> 17811.682 | L35: =SUM(L4:L34) -> 17811.682

Sheet Devarakhadra
A1: Kurumurthy Swami F/S
A2: S.No | B2: Date | C2: GRN No | D2: Ind no/Bill No | E2: Diesel (Lts) | F2: Price | G2: Amount | H2: Petrol (Lts) | I2: Price | J2: Amount | K2: Total amount | L2: Amount paid | M2: As on Date | N2: Remarks
A3: Opening Balance | M3: 0
A4: 1 | B4: 45809 | E4: 0 | F4: 0 | G4: =E4*F4 -> 0 | H4: 0 | I4: 0 | J4: =H4*I4 -> 0 | K4: =G4+J4 -> 0 | L4: =+K4 -> 0 | M4: =+M3+K4-L4 -> 0
A5: 2 | B5: 45810 | E5: 0 | F5: 0 | G5: =E5*F5 -> 0 | H5: 0 | I5: 0 | J5: =H5*I5 -> 0 | K5: =G5+J5 -> 0 | L5: =+K5 -> 0 | M5: =+M4+K5-L5 -> 0
A6: 3 | B6: 45811 | E6: 0 | F6: 0 | G6: =E6*F6 -> 0 | H6: 0 | I6: 0 | J6: =H6*I6 -> 0 | K6: =G6+J6 -> 0 | L6: =+K6 -> 0 | M6: =+M5+K6-L6 -> 0
A7: 4 | B7: 45812 | E7: 0 | F7: 0 | G7: =E7*F7 -> 0 | H7: 0 | I7: 0 | J7: =H7*I7 -> 0 | K7: =G7+J7 -> 0 | L7: =+K7 -> 0 | M7: =+M6+K7-L7 -> 0
A8: 5 | B8: 45813 | E8: 0 | F8: 0 | G8: =E8*F8 -> 0 | H8: 0 | I8: 0 | J8: =H8*I8 -> 0 | K8: =G8+J8 -> 0 | L8: =+K8 -> 0 | M8: =+M7+K8-L8 -> 0
A9: 6 | B9: 45814 | E9: 0 | F9: 0 | G9: =E9*F9 -> 0 | H9: 0 | I9: 0 | J9: =H9*I9 -> 0 | K9: =G9+J9 -> 0 | L9: =+K9 -> 0 | M9: =+M8+K9-L9 -> 0
A10: 7 | B10: 45815 | E10: 0 | F10: 0 | G10: =E10*F10 -> 0 | H10: 0 | I10: 0 | J10: =H10*I10 -> 0 | K10: =G10+J10 -> 0 | L10: =+K10 -> 0 | M10: =+M9+K10-L10 -> 0
A11: 8 | B11: 45816 | E11: 0 | F11: 0 | G11: =E11*F11 -> 0 | H11: 0 | I11: 0 | J11: =H11*I11 -> 0 | K11: =G11+J11 -> 0 | L11: =+K11 -> 0 | M11: =+M10+K11-L11 -> 0
A12: 9 | B12: 45817 | E12: 0 | F12: 0 | G12: =E12*F12 -> 0 | H12: 0 | I12: 0 | J12: =H12*I12 -> 0 | K12: =G12+J12 -> 0 | L12: =+K12 -> 0 | M12: =+M11+K12-L12 -> 0
A13: 10 | B13: 45818 | E13: 0 | F13: 0 | G13: =E13*F13 -> 0 | H13: 0 | I13: 0 | J13: =H13*I13 -> 0 | K13: =G13+J13 -> 0 | L13: =+K13 -> 0 | M13: =+M12+K13-L13 -> 0
A14: 11 | B14: 45819 | E14: 0 | F14: 0 | G14: =E14*F14 -> 0 | H14: 0 | I14: 0 | J14: =H14*I14 -> 0 | K14: =G14+J14 -> 0 | L14: =+K14 -> 0 | M14: =+M13+K14-L14 -> 0
A15: 12 | B15: 45820 | E15: 0 | F15: 0 | G15: =E15*F15 -> 0 | H15: 0 | I15: 0 | J15: =H15*I15 -> 0 | K15: =G15+J15 -> 0 | L15: =+K15 -> 0 | M15: =+M14+K15-L15 -> 0
... A18: 15 | B18: 45823 | E18: 0 | F18: 0 | G18: =E18*F18 -> 0 | H18: 0 | I18: 0 | J18: =H18*I18 -> 0 | K18: =G18+J18 -> 0 | L18: =+K18 -> 0 | M18: =+M17+K18-L18 -> 0
A19: 16 | B19: 45824 | E19: 230 | F19: 97.1 | G19: =E19*F19 -> 22333 | H19: 0 | I19: 0 | J19: =H19*I19 -> 0 | K19: =G19+J19 -> 22333 | L19: 0 | M19: =+M18+K19-L19 -> 22333 | N19: Fuel bills
A20: 17 | B20: 45825 | E20: 0 | F20: 0 | G20: =E20*F20 -> 0 | H20: 0 | I20: 0 | J20: =H20*I20 -> 0 | K20: =G20+J20 -> 0 | L20: =+K20 -> 0 | M20: =+M19+K20-L20 -> 22333
A21: 18 | B21: 45826 | E21: 230 | F21: 97.1 | G21: =E21*F21 -> 22333 | H21: 0 | I21: 0 | J21: =H21*I21 -> 0 | K21: =G21+J21 -> 22333 | L21: 0 | M21: =+M20+K21-L21 -> 44666
A22: 19 | B22: 45827 | E22: 10 | F22: 97.1 | G22: =E22*F22 -> 971 | H22: 0 | I22: 0 | J22: =H22*I22 -> 0 | K22: =G22+J22 -> 971 | M22: =+M21+K22-L22 -> 45637
A23: 20 | B23: 45828 | E23: 31.23 | F23: 97.1 | G23: =E23*F23 -> 3032.433 | H23: 0 | I23: 0 | J23: =H23*I23 -> 0 | K23: =G23+J23 -> 3032.433 | L23: 0 | M23: =+M22+K23-L23 -> 48669.433
A24: 21 | B24: 45829 | E24: 200 | F24: 97.1 | G24: =E24*F24 -> 19420 | H24: 0 | I24: 0 | J24: =H24*I24 -> 0 | K24: =G24+J24 -> 19420 | L24: 0 | M24: =+M23+K24-L24 -> 68089.433
A25: 22 | B25: 45830 | E25: 0 | F25: 0 | G25: =E25*F25 -> 0 | H25: 0 | I25: 0 | J25: =H25*I25 -> 0 | K25: =G25+J25 -> 0 | L25: =+K25 -> 0 | M25: =+M24+K25-L25 -> 68089.433
A26: 23 | B26: 45831 | E26: 200 | F26: 97.1 | G26: =E26*F26 -> 19420 | H26: 0 | I26: 0 | J26: =H26*I26 -> 0 | K26: =G26+J26 -> 19420 | L26: 0 | M26: =+M25+K26-L26 -> 87509.433
A27: 24 | B27: 45832 | E27: 190 | F27: 97.1 | G27: =E27*F27 -> 18449 | H27: 0 | I27: 0 | J27: =H27*I27 -> 0 | K27: =G27+J27 -> 18449 | L27: 0 | M27: =+M26+K27-L27 -> 105958.43
A28: 25 | B28: 45833 | E28: 200 | F28: 97.1 | G28: =E28*F28 -> 19420 | H28: 0 | I28: 0 | J28: =H28*I28 -> 0 | K28: =G28+J28 -> 19420 | L28: 0 | M28: =+M27+K28-L28 -> 125378.43
A29: 26 | B29: 45834 | E29: 0 | F29: 97.1 | G29: =E29*F29 -> 0 | H29: 0 | I29: 0 | J29: =H29*I29 -> 0 | K29: =G29+J29 -> 0 | L29: 0 | M29: =+M28+K29-L29 -> 125378.43
A30: 27 | B30: 45835 | E30: 200 | F30: 97.1 | G30: =E30*F30 -> 19420 | H30: 0 | I30: 0 | J30: =H30*I30 -> 0 | K30: =G30+J30 -> 19420 | L30: 0 | M30: =+M29+K30-L30 -> 144798.43
A31: 28 | B31: 45836 | E31: 49.73 | F31: 97.1 | G31: =E31*F31 -> 4828.783 | H31: 0 | I31: 0 | J31: =H31*I31 -> 0 | K31: =G31+J31 -> 4828.783 | L31: 0 | M31: =+M30+K31-L31 -> 149627.22
A32: 29 | B32: 45837 | E32: 0 | F32: 0 | G32: =E32*F32 -> 0 | H32: 0 | I32: 0 | J32: =H32*I32 -> 0 | K32: =G32+J32 -> 0 | L32: =+K32 -> 0 | M32: =+M31+K32-L32 -> 149627.22
A33: 30 | B33: 45838 | E33: 200 | F33: 97.1 | G33: =E33*F33 -> 19420 | H33: 0 | I33: 0 | J33: =H33*I33 -> 0 | K33: =G33+J33 -> 19420 | L33: 0 | M33: =+M32+K33-L33 -> 169047.22
A34: 31 | E34: 0 | F34: 0 | G34: =E34*F34 -> 0 | H34: 0 | I34: 0 | J34: =H34*I34 -> 0 | K34: =G34+J34 -> 0 | L34: =+K34 -> 0 | M34: =+M33+K34-L34 -> 169047.22
E35: =SUM(E4:E34) -> 1740.96 | G35: =SUM(G4:G34) -> 169047.22 | H35: =SUM(H4:H34) -> 0 | J35: =SUM(J4:J34) -> 0 | K35: =SUM(K4:K34) -> 169047.22 | L35: =SUM(L4:L34) -> 0

Sheet YG Gudda 
A1: Pallavi Petrolium
A2: S.No | B2: Date | C2: GRN No | D2: Ind No/Bill No | E2: Diesel (Lts) | F2: Price | G2: Amount | H2: Petrol (Lts) | I2: Price | J2: Amount | K2: Total amount | L2: Amount paid | M2: As on Date | N2: Remarks
A3: Opening Balance | K3: 71933.179 | M3: =+K3 -> 71933.179
A4: 1 | B4: 45809 | E4: 0 | G4: =E4*F4 -> 0 | H4: 0 | J4: =H4*I4 -> 0 | K4: =G4+J4 -> 0 | M4: =M3+K4-L4 -> 71933.179
A5: 2 | B5: 45810 | E5: 0 | G5: =E5*F5 -> 0 | H5: 0 | J5: =H5*I5 -> 0 | K5: =G5+J5 -> 0 | M5: =M4+K5-L5 -> 71933.179
A6: 3 | B6: 45811 | E6: 2400 | F6: 91.3 | G6: =E6*F6 -> 219120 | H6: 105 | I6: 103.24 | J6: =H6*I6 -> 10840.2 | K6: =G6+J6 -> 229960.2 | M6: =M5+K6-L6 -> 301893.38
A7: 4 | B7: 45812 | E7: 0 | G7: =E7*F7 -> 0 | H7: 0 | J7: =H7*I7 -> 0 | K7: =G7+J7 -> 0 | M7: =M6+K7-L7 -> 301893.38
A8: 5 | B8: 45813 | E8: 0 | G8: =E8*F8 -> 0 | H8: 0 | J8: =H8*I8 -> 0 | K8: =G8+J8 -> 0 | L8: 301800 | M8: =M7+K8-L8 -> 93.379414
A9: 6 | B9: 45814 | E9: 0 | G9: =E9*F9 -> 0 | H9: 105 | I9: 103.24 | J9: =H9*I9 -> 10840.2 | K9: =G9+J9 -> 10840.2 | M9: =M8+K9-L9 -> 10933.579
A10: 7 | B10: 45815 | E10: 0 | G10: =E10*F10 -> 0 | H10: 0 | J10: =H10*I10 -> 0 | K10: =G10+J10 -> 0 | M10: =M9+K10-L10 -> 10933.579
A11: 8 | B11: 45816 | E11: 0 | G11: =E11*F11 -> 0 | H11: 0 | J11: =H11*I11 -> 0 | K11: =G11+J11 -> 0 | M11: =M10+K11-L11 -> 10933.579
A12: 9 | B12: 45817 | E12: 200 | F12: 91.3 | G12: =E12*F12 -> 18260 | H12: 0 | J12: =H12*I12 -> 0 | K12: =G12+J12 -> 18260 | M12: =M11+K12-L12 -> 29193.579
A13: 10 | B13: 45818 | E13: 200 | F13: 91.3 | G13: =E13*F13 -> 18260 | H13: 0 | J13: =H13*I13 -> 0 | K13: =G13+J13 -> 18260 | M13: =M12+K13-L13 -> 47453.579
A14: 11 | B14: 45819 | E14: 0 | G14: =E14*F14 -> 0 | H14: 0 | J14: =H14*I14 -> 0 | K14: =G14+J14 -> 0 | M14: =M13+K14-L14 -> 47453.579
A15: 12 | B15: 45820 | E15: 2400 | F15: 91.3 | G15: =E15*F15 -> 219120 | H15: 105 | I15: 103.24 | J15: =H15*I15 -> 10840.2 | K15: =G15+J15 -> 229960.2 | M15: =M14+K15-L15 -> 277413.78
A16: 13 | B16: 45821 | E16: 0 | G16: =E16*F16 -> 0 | H16: 0 | J16: =H16*I16 -> 0 | K16: =G16+J16 -> 0 | M16: =M15+K16-L16 -> 277413.78
A17: 14 | B17: 45822 | E17: 0 | G17: =E17*F17 -> 0 | H17: 0 | J17: =H17*I17 -> 0 | K17: =G17+J17 -> 0 | M17: =M16+K17-L17 -> 277413.78
A18: 15 | B18: 45823 | E18: 0 | G18: =E18*F18 -> 0 | H18: 0 | J18: =H18*I18 -> 0 | K18: =G18+J18 -> 0 | M18: =M17+K18-L18 -> 277413.78
A19: 16 | B19: 45824 | E19: 0 | G19: =E19*F19 -> 0 | H19: 0 | J19: =H19*I19 -> 0 | K19: =G19+J19 -> 0 | M19: =M18+K19-L19 -> 277413.78
A20: 17 | B20: 45825 | E20: 0 | G20: =E20*F20 -> 0 | H20: 0 | J20: =H20*I20 -> 0 | K20: =G20+J20 -> 0 | M20: =M19+K20-L20 -> 277413.78
A21: 18 | B21: 45826 | E21: 0 | G21: =E21*F21 -> 0 | H21: 105 | I21: 103.24 | J21: =H21*I21 -> 10840.2 | K21: =G21+J21 -> 10840.2 | M21: =M20+K21-L21 -> 288253.98
A22: 19 | B22: 45827 | E22: 0 | G22: =E22*F22 -> 0 | H22: 0 | J22: =H22*I22 -> 0 | K22: =G22+J22 -> 0 | M22: =M21+K22-L22 -> 288253.98
A23: 20 | B23: 45828 | E23: 300 | F23: 91.3 | G23: =E23*F23 -> 27390 | H23: 0 | J23: =H23*I23 -> 0 | K23: =G23+J23 -> 27390 | M23: =M22+K23-L23 -> 315643.98
A24: 21 | B24: 45829 | E24: 1200 | F24: 91.3 | G24: =E24*F24 -> 109560 | H24: 0 | J24: =H24*I24 -> 0 | K24: =G24+J24 -> 109560 | M24: =M23+K24-L24 -> 425203.98
A25: 22 | B25: 45830 | E25: 0 | G25: =E25*F25 -> 0 | H25: 0 | J25: =H25*I25 -> 0 | K25: =G25+J25 -> 0 | M25: =M24+K25-L25 -> 425203.98
A26: 23 | B26: 45831 | E26: 0 | G26: =E26*F26 -> 0 | H26: 0 | J26: =H26*I26 -> 0 | K26: =G26+J26 -> 0 | M26: =M25+K26-L26 -> 425203.98
A27: 24 | B27: 45832 | E27: 0 | G27: =E27*F27 -> 0 | H27: 105 | I27: 103.24 | J27: =H27*I27 -> 10840.2 | K27: =G27+J27 -> 10840.2 | M27: =M26+K27-L27 -> 436044.18
A28: 25 | B28: 45833 | E28: 500 | F28: 91.3 | G28: =E28*F28 -> 45650 | H28: 0 | J28: =H28*I28 -> 0 | K28: =G28+J28 -> 45650 | L28: 100000 | M28: =M27+K28-L28 -> 381694.18
A29: 26 | B29: 45834 | E29: 1200 | F29: 91.3 | G29: =E29*F29 -> 109560 | H29: 0 | J29: =H29*I29 -> 0 | K29: =G29+J29 -> 109560 | M29: =M28+K29-L29 -> 491254.18
A30: 27 | B30: 45835 | E30: 0 | G30: =E30*F30 -> 0 | H30: 70 | I30: 103.24 | J30: =H30*I30 -> 7226.8 | K30: =G30+J30 -> 7226.8 | L30: 450000 | M30: =M29+K30-L30 -> 48480.979
A31: 28 | B31: 45836 | E31: 0 | G31: =E31*F31 -> 0 | H31: 0 | J31: =H31*I31 -> 0 | K31: =G31+J31 -> 0 | M31: =M30+K31-L31 -> 48480.979
A32: 29 | B32: 45837 | E32: 0 | G32: =E32*F32 -> 0 | H32: 0 | J32: =H32*I32 -> 0 | K32: =G32+J32 -> 0 | M32: =M31+K32-L32 -> 48480.979
A33: 30 | B33: 45838 | E33: 0 | G33: =E33*F33 -> 0 | H33: 0 | J33: =H33*I33 -> 0 | K33: =G33+J33 -> 0 | M33: =M32+K33-L33 -> 48480.979
A34: 31 | E34: 0 | G34: =E34*F34 -> 0 | H34: 0 | J34: =H34*I34 -> 0 | K34: =G34+J34 -> 0 | M34: =M33+K34-L34 -> 48480.979
A35: 32 | E35: 0 | G35: =E35*F35 -> 0 | H35: 0 | J35: =H35*I35 -> 0 | K35: =G35+J35 -> 0 | M35: =M34+K35-L35 -> 48480.979
E36: =SUM(E4:E35) -> 8400 | G36: =SUM(G4:G35) -> 766920 | H36: =SUM(H4:H35) -> 595 | J36: =SUM(J4:J35) -> 61427.8 | K36: =SUM(K4:K35) -> 828347.8 | L36: =SUM(L4:L35) -> 851800

Sheet Hosadurga
A1: Merchant Petroliums
A2: S.No | B2: Date | C2: GRN No | D2: Ind No/Bill No | E2: Diesel (Lts) | F2: Price | G2: Amount | H2: Petrol (Lts) | I2: Price | J2: Amount | K2: Total amount | L2: Amount paid | M2: As on Date | N2: Remarks
A3: Opening Balance | K3: 0 | M3: =+K3 -> 0
A4: 1 | B4: 45809 | C4: 1605/1606 | D4: F0827/JUN-852956,F0132 | E4: 1500 | F4: 91.64 | G4: =E4*F4 -> 137460 | H4: 35 | I4: 103.72 | J4: =H4*I4 -> 3630.2 | K4: =G4+J4 -> 141090.2 | L4: 0 | M4: =M3+K4-L4 -> 141090.2
A5: 2 | B5: 45810 | E5: 0 | F5: 0 | G5: =E5*F5 -> 0 | H5: 0 | I5: 0 | J5: =H5*I5 -> 0 | K5: =G5+J5 -> 0 | L5: 0 | M5: =M4+K5-L5 -> 141090.2
A6: 3 | B6: 45811 | E6: 0 | F6: 0 | G6: =E6*F6 -> 0 | H6: 0 | I6: 0 | J6: =H6*I6 -> 0 | K6: =G6+J6 -> 0 | L6: 0 | M6: =M5+K6-L6 -> 141090.2
A7: 4 | B7: 45812 | E7: 0 | F7: 0 | G7: =E7*F7 -> 0 | H7: 0 | I7: 0 | J7: =H7*I7 -> 0 | K7: =G7+J7 -> 0 | L7: 0 | M7: =M6+K7-L7 -> 141090.2
A8: 5 | B8: 45813 | E8: 0 | F8: 0 | G8: =E8*F8 -> 0 | H8: 0 | I8: 0 | J8: =H8*I8 -> 0 | K8: =G8+J8 -> 0 | L8: 141090.2 | M8: =M7+K8-L8 -> 0
A9: 6 | B9: 45814 | E9: 0 | F9: 0 | G9: =E9*F9 -> 0 | H9: 0 | I9: 0 | J9: =H9*I9 -> 0 | K9: =G9+J9 -> 0 | L9: 0 | M9: =M8+K9-L9 -> 0
A10: 7 | B10: 45815 | E10: 0 | F10: 0 | G10: =E10*F10 -> 0 | H10: 0 | I10: 0 | J10: =H10*I10 -> 0 | K10: =G10+J10 -> 0 | L10: 0 | M10: =M9+K10-L10 -> 0
A11: 8 | B11: 45816 | C11: 1610/1611 | D11: F4543/JUN853029,JUN-853028 | E11: 1600 | F11: 91.64 | G11: =E11*F11 -> 146624 | H11: 100 | I11: 103.72 | J11: =H11*I11 -> 10372 | K11: =G11+J11 -> 156996 | L11: 0 | M11: =M10+K11-L11 -> 156996
A12: 9 | B12: 45817 | E12: 0 | F12: 0 | G12: 0 | H12: 0 | I12: 0 | J12: =H12*I12 -> 0 | K12: =G12+J12 -> 0 | L12: 0 | M12: =M11+K12-L12 -> 156996
A13: 10 | B13: 45818 | E13: 0 | F13: 0 | G13: 0 | H13: 0 | I13: 0 | J13: =H13*I13 -> 0 | K13: =G13+J13 -> 0 | L13: 0 | M13: =M12+K13-L13 -> 156996
A14: 11 | B14: 45819 | E14: 0 | F14: 0 | G14: 0 | H14: 0 | I14: 0 | J14: =H14*I14 -> 0 | K14: =G14+J14 -> 0 | L14: 0 | M14: =M13+K14-L14 -> 156996
A15: 12 | B15: 45820 | E15: 0 | F15: 0 | G15: 0 | H15: 0 | I15: 0 | J15: =H15*I15 -> 0 | K15: =G15+J15 -> 0 | L15: 0 | M15: =M14+K15-L15 -> 156996
A16: 13 | B16: 45821 | E16: 0 | F16: 0 | G16: 0 | H16: 0 | I16: 0 | J16: =H16*I16 -> 0 | K16: =G16+J16 -> 0 | L16: 0 | M16: =M15+K16-L16 -> 156996 | X16: =100*104 -> 10400
A17: 14 | B17: 45822 | E17: 0 | F17: 0 | G17: 0 | H17: 0 | I17: 0 | J17: =H17*I17 -> 0 | K17: =G17+J17 -> 0 | L17: 0 | M17: =M16+K17-L17 -> 156996
A18: 15 | B18: 45823 | E18: 0 | F18: 0 | G18: 0 | H18: 0 | I18: 0 | J18: =H18*I18 -> 0 | K18: =G18+J18 -> 0 | L18: 0 | M18: =M17+K18-L18 -> 156996
A19: 16 | B19: 45824 | E19: 0 | F19: 0 | G19: 0 | H19: 0 | I19: 0 | J19: =H19*I19 -> 0 | K19: =G19+J19 -> 0 | L19: 0 | M19: =M18+K19-L19 -> 156996
A20: 17 | B20: 45825 | C20: 1614 | D20: F0295 | E20: 0 | F20: 0 | G20: 0 | H20: 100 | I20: 103.72 | J20: =H20*I20 -> 10372 | K20: =G20+J20 -> 10372 | L20: 0 | M20: =M19+K20-L20 -> 167368
A21: 18 | B21: 45826 | E21: 0 | F21: 0 | G21: 0 | H21: 0 | I21: 0 | J21: =H21*I21 -> 0 | K21: =G21+J21 -> 0 | L21: 0 | M21: =M20+K21-L21 -> 167368
A22: 19 | B22: 45827 | E22: 0 | F22: 0 | G22: 0 | H22: 0 | I22: 0 | J22: =H22*I22 -> 0 | K22: =G22+J22 -> 0 | L22: 0 | M22: =M21+K22-L22 -> 167368
A23: 20 | B23: 45828 | E23: 0 | F23: 0 | G23: 0 | H23: 0 | I23: 0 | J23: =H23*I23 -> 0 | K23: =G23+J23 -> 0 | L23: 0 | M23: =M22+K23-L23 -> 167368
A24: 21 | B24: 45829 | E24: 0 | F24: 0 | G24: 0 | H24: 0 | I24: 0 | J24: =H24*I24 -> 0 | K24: =G24+J24 -> 0 | L24: 0 | M24: =M23+K24-L24 -> 167368
A25: 22 | B25: 45830 | E25: 0 | F25: 0 | G25: 0 | H25: 0 | I25: 0 | J25: =H25*I25 -> 0 | K25: =G25+J25 -> 0 | L25: 0 | M25: =M24+K25-L25 -> 167368
A26: 23 | B26: 45831 | E26: 0 | F26: 0 | G26: 0 | H26: 0 | I26: 0 | J26: =H26*I26 -> 0 | K26: =G26+J26 -> 0 | L26: 0 | M26: =M25+K26-L26 -> 167368
A27: 24 | B27: 45832 | E27: 0 | F27: 0 | G27: 0 | H27: 0 | I27: 0 | J27: =H27*I27 -> 0 | K27: =G27+J27 -> 0 | L27: 0 | M27: =M26+K27-L27 -> 167368
A28: 25 | B28: 45833 | E28: 0 | F28: 0 | G28: 0 | H28: 0 | I28: 0 | J28: =H28*I28 -> 0 | K28: =G28+J28 -> 0 | L28: 0 | M28: =M27+K28-L28 -> 167368
A29: 26 | B29: 45834 | E29: 0 | F29: 0 | G29: 0 | H29: 0 | I29: 0 | J29: =H29*I29 -> 0 | K29: =G29+J29 -> 0 | L29: 0 | M29: =M28+K29-L29 -> 167368
A30: 27 | B30: 45835 | E30: 0 | F30: 0 | G30: 0 | H30: 0 | I30: 0 | J30: =H30*I30 -> 0 | K30: =G30+J30 -> 0 | L30: 0 | M30: =M29+K30-L30 -> 167368
A31: 28 | B31: 45836 | E31: 0 | F31: 0 | G31: 0 | H31: 0 | I31: 0 | J31: =H31*I31 -> 0 | K31: =G31+J31 -> 0 | L31: 167386 | M31: =M30+K31-L31 -> -18
A32: 29 | B32: 45837 | E32: 0 | F32: 0 | G32: 0 | H32: 0 | I32: 0 | J32: =H32*I32 -> 0 | K32: =G32+J32 -> 0 | L32: =-(18) -> -18 | M32: =M31+K32-L32 -> 0
A33: 30 | B33: 45838 | E33: 0 | F33: 0 | G33: 0 | H33: 0 | I33: 0 | J33: =H33*I33 -> 0 | K33: =G33+J33 -> 0 | L33: 0 | M33: =M32+K33-L33 -> 0
A34: 31 | E34: 0 | F34: 0 | G34: 0 | H34: 0 | I34: 0 | J34: =H34*I34 -> 0 | K34: =G34+J34 -> 0 | L34: 0 | M34: =M33+K34-L34 -> 0
E35: =SUM(E4:E34) -> 3100 | G35: =SUM(G4:G34) -> 284084 | H35: =SUM(H4:H34) -> 235 | J35: =SUM(J4:J34) -> 24374.2 | K35: =SUM(K4:K34) -> 308458.2 | L35: =SUM(L4:L34) -> 308458.2

Sheet Hosadurga -2
A1: Shree Veeraprathap Fuel
A2: S.No | B2: Date | C2: GRN No | D2: Ind No/Bill No | E2: Diesel (Lts) | F2: Price | G2: Amount | H2: Petrol (Lts) | I2: Price | J2: Amount | K2: Total amount | L2: Amount paid | M2: As on Date | N2: Remarks
A3: Opening Balance | K3: 388266.5 | M3: =+K3 -> 388266.5
A4: 1 | B4: 45809 | C4: 0 | E4: 0 | F4: 0 | G4: 0 | H4: 0 | I4: 0 | J4: =H4*I4 -> 0 | K4: =G4+J4 -> 0 | L4: 0 | M4: =M3+K4-L4 -> 388266.5
A5: 2 | B5: 45810 | C5: 0 | E5: 0 | F5: 0 | G5: 0 | H5: 0 | I5: 0 | J5: =H5*I5 -> 0 | K5: =G5+J5 -> 0 | L5: 0 | M5: =M4+K5-L5 -> 388266.5
A6: 3 | B6: 45811 | C6: 0 | E6: 0 | F6: 0 | G6: 0 | H6: 0 | I6: 0 | J6: =H6*I6 -> 0 | K6: =G6+J6 -> 0 | L6: 0 | M6: =M5+K6-L6 -> 388266.5
A7: 4 | B7: 45812 | C7: 0 | E7: 0 | F7: 0 | G7: 0 | H7: 0 | I7: 0 | J7: =H7*I7 -> 0 | K7: =G7+J7 -> 0 | L7: 0 | M7: =M6+K7-L7 -> 388266.5
A8: 5 | B8: 45813 | C8: 0 | E8: 0 | F8: 0 | G8: 0 | H8: 0 | I8: 0 | J8: =H8*I8 -> 0 | K8: =G8+J8 -> 0 | L8: 0 | M8: =M7+K8-L8 -> 388266.5
A9: 6 | B9: 45814 | C9: 0 | E9: 0 | F9: 0 | G9: 0 | H9: 0 | I9: 0 | J9: =H9*I9 -> 0 | K9: =G9+J9 -> 0 | L9: 0 | M9: =M8+K9-L9 -> 388266.5
A10: 7 | B10: 45815 | C10: 0 | E10: 0 | F10: 0 | G10: 0 | H10: 0 | I10: 0 | J10: =H10*I10 -> 0 | K10: =G10+J10 -> 0 | L10: 0 | M10: =M9+K10-L10 -> 388266.5
A11: 8 | B11: 45816 | C11: 0 | E11: 0 | F11: 0 | G11: 0 | H11: 0 | I11: 0 | J11: =H11*I11 -> 0 | K11: =G11+J11 -> 0 | L11: 0 | M11: =M10+K11-L11 -> 388266.5
A12: 9 | B12: 45817 | C12: 0 | E12: 0 | F12: 0 | G12: 0 | H12: 0 | I12: 0 | J12: =H12*I12 -> 0 | K12: =G12+J12 -> 0 | L12: 388266.5 | M12: =M11+K12-L12 -> 0.0019
A13: 10 | B13: 45818 | C13: 0 | E13: 0 | F13: 0 | G13: 0 | H13: 0 | I13: 0 | J13: =H13*I13 -> 0 | K13: =G13+J13 -> 0 | L13: 0 | M13: =M12+K13-L13 -> 0.0019
A14: 11 | B14: 45819 | C14: 0 | E14: 0 | F14: 0 | G14: 0 | H14: 0 | I14: 0 | J14: =H14*I14 -> 0 | K14: =G14+J14 -> 0 | L14: 0 | M14: =M13+K14-L14 -> 0.0019
A15: 12 | B15: 45820 | C15: 0 | E15: 0 | F15: 0 | G15: 0 | H15: 0 | I15: 0 | J15: =H15*I15 -> 0 | K15: =G15+J15 -> 0 | L15: 0 | M15: =M14+K15-L15 -> 0.0019
... A23: 20 | B23: 45828 | C23: 0 | E23: 0 | F23: 0 | G23: 0 | H23: 0 | I23: 0 | J23: =H23*I23 -> 0 | K23: =G23+J23 -> 0 | L23: 0 | M23: =M22+K23-L23 -> 0.0019
A24: 21 | B24: 45829 | C24: 0 | E24: 2000 | F24: 91.39 | G24: =E24*F24 -> 182780 | H24: 0 | I24: 0 | J24: =H24*I24 -> 0 | K24: =G24+J24 -> 182780 | L24: 0 | M24: =M23+K24-L24 -> 182780
A25: 22 | B25: 45830 | C25: 0 | E25: 0 | F25: 0 | G25: =E25*F25 -> 0 | H25: 0 | I25: 0 | J25: =H25*I25 -> 0 | K25: =G25+J25 -> 0 | L25: 0 | M25: =M24+K25-L25 -> 182780
A26: 23 | B26: 45831 | C26: 0 | E26: 0 | F26: 0 | G26: =E26*F26 -> 0 | H26: 0 | I26: 0 | J26: =H26*I26 -> 0 | K26: =G26+J26 -> 0 | L26: 0 | M26: =M25+K26-L26 -> 182780
A27: 24 | B27: 45832 | C27: 0 | E27: 0 | F27: 0 | G27: =E27*F27 -> 0 | H27: 70 | I27: 103.46 | J27: =H27*I27 -> 7242.2 | K27: =G27+J27 -> 7242.2 | L27: 0 | M27: =M26+K27-L27 -> 190022.2
A28: 25 | B28: 45833 | C28: 0 | E28: 0 | F28: 0 | G28: =E28*F28 -> 0 | H28: 0 | I28: 0 | J28: =H28*I28 -> 0 | K28: =G28+J28 -> 0 | L28: 0 | M28: =M27+K28-L28 -> 190022.2
A29: 26 | B29: 45834 | C29: 0 | E29: 0 | F29: 0 | G29: =E29*F29 -> 0 | H29: 0 | I29: 0 | J29: =H29*I29 -> 0 | K29: =G29+J29 -> 0 | L29: 0 | M29: =M28+K29-L29 -> 190022.2
A30: 27 | B30: 45835 | C30: 0 | E30: 0 | F30: 0 | G30: =E30*F30 -> 0 | H30: 0 | I30: 0 | J30: =H30*I30 -> 0 | K30: =G30+J30 -> 0 | L30: 0 | M30: =M29+K30-L30 -> 190022.2
A31: 28 | B31: 45836 | C31: 0 | E31: 2000 | F31: 91.39 | G31: =E31*F31 -> 182780 | H31: 70 | I31: 103.46 | J31: =H31*I31 -> 7242.2 | K31: =G31+J31 -> 190022.2 | L31: 0 | M31: =M30+K31-L31 -> 380044.4
A32: 29 | B32: 45837 | C32: 0 | E32: 0 | F32: 0 | G32: 0 | H32: 0 | I32: 0 | J32: =H32*I32 -> 0 | K32: =G32+J32 -> 0 | L32: 0
A33: 30 | B33: 45838 | C33: 0 | E33: 0 | F33: 0 | G33: 0 | H33: 0 | I33: 0 | J33: =H33*I33 -> 0 | K33: =G33+J33 -> 0 | L33: 0
A34: 31
E35: =SUM(E4:E34) -> 4000 | G35: =SUM(G4:G34) -> 365560 | H35: =SUM(H4:H34) -> 140 | J35: =SUM(J4:J34) -> 14484.4 | K35: =SUM(K4:K34) -> 380044.4 | L35: =SUM(L4:L34) -> 388266.5

Sheet Kadur
A1: Vishal Service Station
A2: S.No | B2: Date | C2: GRN No | D2: Ind No/Bill No | E2: Diesel (Lts) | F2: Price | G2: Amount | H2: Petrol (Lts) | I2: Price | J2: Amount | K2: Total amount | L2: Amount paid | M2: As on Date | N2: Remarks
A3: Opening Balance | K3: 1167095.1 | M3: =+K3 -> 1167095.1 | P3: 1142944.1
A4: 1 | B4: 45809 | F4: 0 | G4: =E4*F4 -> 0 | H4: 0 | I4: 0 | J4: =H4*I4 -> 0 | K4: =G4+J4 -> 0 | M4: =M3+K4-L4 -> 1167095.1
A5: 2 | B5: 45810 | F5: 0 | G5: =E5*F5 -> 0 | H5: 0 | I5: 0 | J5: =H5*I5 -> 0 | K5: =G5+J5 -> 0 | M5: =M4+K5-L5 -> 1167095.1
A6: 3 | B6: 45811 | F6: 0 | G6: =E6*F6 -> 0 | H6: 0 | I6: 0 | J6: =H6*I6 -> 0 | K6: =G6+J6 -> 0 | M6: =M5+K6-L6 -> 1167095.1
A7: 4 | B7: 45812 | F7: 0 | G7: =E7*F7 -> 0 | H7: 0 | I7: 0 | J7: =H7*I7 -> 0 | K7: =G7+J7 -> 0 | M7: =M6+K7-L7 -> 1167095.1
A8: 5 | B8: 45813 | F8: 0 | G8: =E8*F8 -> 0 | H8: 0 | I8: 0 | J8: =H8*I8 -> 0 | K8: =G8+J8 -> 0 | M8: =M7+K8-L8 -> 1167095.1
A9: 6 | B9: 45814 | F9: 0 | G9: =E9*F9 -> 0 | H9: 0 | I9: 0 | J9: =H9*I9 -> 0 | K9: =G9+J9 -> 0 | L9: 968765.11 | M9: =M8+K9-L9 -> 198330.03
A10: 7 | B10: 45815 | F10: 0 | G10: =E10*F10 -> 0 | H10: 0 | I10: 0 | J10: =H10*I10 -> 0 | K10: =G10+J10 -> 0 | M10: =M9+K10-L10 -> 198330.03
A11: 8 | B11: 45816 | F11: 0 | G11: =E11*F11 -> 0 | H11: 0 | I11: 0 | J11: =H11*I11 -> 0 | K11: =G11+J11 -> 0 | M11: =M10+K11-L11 -> 198330.03
A12: 9 | B12: 45817 | F12: 0 | G12: =E12*F12 -> 0 | H12: 0 | I12: 0 | J12: =H12*I12 -> 0 | K12: =G12+J12 -> 0 | M12: =M11+K12-L12 -> 198330.03
A13: 10 | B13: 45818 | F13: 0 | G13: =E13*F13 -> 0 | H13: 0 | I13: 0 | J13: =H13*I13 -> 0 | K13: =G13+J13 -> 0 | M13: =M12+K13-L13 -> 198330.03
A14: 11 | B14: 45819 | F14: 0 | G14: =E14*F14 -> 0 | H14: 0 | I14: 0 | J14: =H14*I14 -> 0 | K14: =G14+J14 -> 0 | M14: =M13+K14-L14 -> 198330.03
A15: 12 | B15: 45820 | F15: 0 | G15: =E15*F15 -> 0 | H15: 0 | I15: 0 | J15: =H15*I15 -> 0 | K15: =G15+J15 -> 0 | M15: =M14+K15-L15 -> 198330.03
A16: 13 | B16: 45821 | F16: 0 | G16: =E16*F16 -> 0 | H16: 0 | I16: 0 | J16: =H16*I16 -> 0 | K16: =G16+J16 -> 0 | M16: =M15+K16-L16 -> 198330.03
A17: 14 | B17: 45822 | F17: 0 | G17: =E17*F17 -> 0 | H17: 0 | I17: 0 | J17: =H17*I17 -> 0 | K17: =G17+J17 -> 0 | M17: =M16+K17-L17 -> 198330.03
A18: 15 | B18: 45823 | F18: 0 | G18: =E18*F18 -> 0 | H18: 0 | I18: 0 | J18: =H18*I18 -> 0 | K18: =G18+J18 -> 0 | M18: =M17+K18-L18 -> 198330.03
A19: 16 | B19: 45824 | F19: 0 | G19: =E19*F19 -> 0 | H19: 0 | I19: 0 | J19: =H19*I19 -> 0 | K19: =G19+J19 -> 0 | M19: =M18+K19-L19 -> 198330.03
A20: 17 | B20: 45825 | F20: 0 | G20: =E20*F20 -> 0 | H20: 0 | I20: 0 | J20: =H20*I20 -> 0 | K20: =G20+J20 -> 0 | M20: =M19+K20-L20 -> 198330.03
A21: 18 | B21: 45826 | F21: 0 | G21: =E21*F21 -> 0 | H21: 0 | I21: 0 | J21: =H21*I21 -> 0 | K21: =G21+J21 -> 0 | M21: =M20+K21-L21 -> 198330.03
... A33: 30 | B33: 45838 | F33: 0 | G33: =E33*F33 -> 0 | H33: 0 | I33: 0 | J33: =H33*I33 -> 0 | K33: =G33+J33 -> 0 | M33: =M32+K33-L33 -> 209799.73
A34: 31 | F34: 0 | G34: =E34*F34 -> 0 | J34: =H34*I34 -> 0 | K34: =G34+J34 -> 0
E35: =SUM(E4:E34) -> 0 | G35: =SUM(G4:G34) -> 0 | H35: =SUM(H4:H34) -> 110 | J35: =SUM(J4:J34) -> 11469.7 | K35: =SUM(K4:K34) -> 11469.7 | L35: =SUM(L4:L31) -> 968765.11

Sheet Hiriyur(VJNL)
A1: Sri Balaji Agencies
A2: S.No | B2: Date | C2: GRN No | D2: Ind No/Bill No | E2: Diesel (Lts) | F2: Price | G2: Amount | H2: Petrol (Lts) | I2: Price | J2: Amount | K2: Total amount | L2: Amount paid | M2: As on Date | N2: Remarks
A3: Opening Balance | K3: 87640.8 | M3: =+K3 -> 87640.8
A4: 1 | B4: 45809 | E4: 0 | G4: =E4*F4 -> 0 | H4: 0 | I4: 0 | J4: =H4*I4 -> 0 | K4: =G4+J4 -> 0 | M4: =M3+K4-L4 -> 87640.8
A5: 2 | B5: 45810 | E5: 0 | G5: =E5*F5 -> 0 | H5: 0 | I5: 0 | J5: =H5*I5 -> 0 | K5: =G5+J5 -> 0 | M5: =M4+K5-L5 -> 87640.8
A6: 3 | B6: 45811 | E6: 0 | G6: =E6*F6 -> 0 | H6: 0 | I6: 0 | J6: =H6*I6 -> 0 | K6: =G6+J6 -> 0 | M6: =M5+K6-L6 -> 87640.8
A7: 4 | B7: 45812 | E7: 0 | G7: =E7*F7 -> 0 | H7: 0 | I7: 0 | J7: =H7*I7 -> 0 | K7: =G7+J7 -> 0 | M7: =M6+K7-L7 -> 87640.8
A8: 5 | B8: 45813 | E8: 0 | G8: =E8*F8 -> 0 | H8: 0 | I8: 0 | J8: =H8*I8 -> 0 | K8: =G8+J8 -> 0 | L8: 87640.8 | M8: =M7+K8-L8 -> 0
A9: 6 | B9: 45814 | E9: 0 | G9: =E9*F9 -> 0 | H9: 0 | I9: 0 | J9: =H9*I9 -> 0 | K9: =G9+J9 -> 0 | M9: =M8+K9-L9 -> 0
A10: 7 | B10: 45815 | E10: 0 | G10: =E10*F10 -> 0 | H10: 0 | I10: 0 | J10: =H10*I10 -> 0 | K10: =G10+J10 -> 0 | M10: =M9+K10-L10 -> 0
A11: 8 | B11: 45816 | E11: 0 | G11: =E11*F11 -> 0 | H11: 0 | I11: 0 | J11: =H11*I11 -> 0 | K11: =G11+J11 -> 0 | M11: =M10+K11-L11 -> 0
A12: 9 | B12: 45817 | E12: 0 | G12: =E12*F12 -> 0 | H12: 0 | I12: 0 | J12: =H12*I12 -> 0 | K12: =G12+J12 -> 0 | M12: =M11+K12-L12 -> 0
A13: 10 | B13: 45818 | E13: 2000 | F13: 92.1 | G13: =E13*F13 -> 184200 | H13: 70 | I13: 103.86 | J13: =H13*I13 -> 7270.2 | K13: =G13+J13 -> 191470.2 | M13: =M12+K13-L13 -> 191470.2
A14: 11 | B14: 45819 | E14: 0 | G14: =E14*F14 -> 0 | H14: 0 | I14: 0 | J14: =H14*I14 -> 0 | K14: =G14+J14 -> 0 | M14: =M13+K14-L14 -> 191470.2
A15: 12 | B15: 45820 | E15: 0 | G15: =E15*F15 -> 0 | H15: 0 | I15: 0 | J15: =H15*I15 -> 0 | K15: =G15+J15 -> 0 | M15: =M14+K15-L15 -> 191470.2
A16: 13 | B16: 45821 | E16: 0 | G16: =E16*F16 -> 0 | H16: 0 | I16: 0 | J16: =H16*I16 -> 0 | K16: =G16+J16 -> 0 | M16: =M15+K16-L16 -> 191470.2
A17: 14 | B17: 45822 | E17: 0 | G17: =E17*F17 -> 0 | H17: 0 | I17: 0 | J17: =H17*I17 -> 0 | K17: =G17+J17 -> 0 | M17: =M16+K17-L17 -> 191470.2
A18: 15 | B18: 45823 | E18: 0 | G18: =E18*F18 -> 0 | H18: 0 | I18: 0 | J18: =H18*I18 -> 0 | K18: =G18+J18 -> 0 | M18: =M17+K18-L18 -> 191470.2
A19: 16 | B19: 45824 | E19: 0 | G19: =E19*F19 -> 0 | H19: 0 | I19: 0 | J19: =H19*I19 -> 0 | K19: =G19+J19 -> 0 | M19: =M18+K19-L19 -> 191470.2
A20: 17 | B20: 45825 | E20: 0 | G20: =E20*F20 -> 0 | H20: 0 | I20: 0 | J20: =H20*I20 -> 0 | K20: =G20+J20 -> 0 | M20: =M19+K20-L20 -> 191470.2
A21: 18 | B21: 45826 | E21: 0 | G21: =E21*F21 -> 0 | H21: 0 | I21: 0 | J21: =H21*I21 -> 0 | K21: =G21+J21 -> 0 | M21: =M20+K21-L21 -> 191470.2
A22: 19 | B22: 45827 | E22: 0 | G22: =E22*F22 -> 0 | H22: 0 | I22: 0 | J22: =H22*I22 -> 0 | K22: =G22+J22 -> 0 | M22: =M21+K22-L22 -> 191470.2
A23: 20 | B23: 45828 | E23: 0 | G23: =E23*F23 -> 0 | H23: 70 | I23: 103.86 | J23: =H23*I23 -> 7270.2 | K23: =G23+J23 -> 7270.2 | M23: =M22+K23-L23 -> 198740.4
A24: 21 | B24: 45829 | E24: 2000 | F24: 92.1 | G24: =E24*F24 -> 184200 | H24: 0 | I24: 0 | J24: =H24*I24 -> 0 | K24: =G24+J24 -> 184200 | M24: =M23+K24-L24 -> 382940.4
A25: 22 | B25: 45830 | E25: 0 | G25: =E25*F25 -> 0 | H25: 0 | I25: 0 | J25: =H25*I25 -> 0 | K25: =G25+J25 -> 0 | M25: =M24+K25-L25 -> 382940.4
A26: 23 | B26: 45831 | E26: 0 | G26: =E26*F26 -> 0 | H26: 0 | I26: 0 | J26: =H26*I26 -> 0 | K26: =G26+J26 -> 0 | M26: =M25+K26-L26 -> 382940.4
A27: 24 | B27: 45832 | E27: 0 | G27: =E27*F27 -> 0 | H27: 0 | I27: 0 | J27: =H27*I27 -> 0 | K27: =G27+J27 -> 0 | M27: =M26+K27-L27 -> 382940.4
A28: 25 | B28: 45833 | E28: 0 | G28: =E28*F28 -> 0 | H28: 0 | I28: 0 | J28: =H28*I28 -> 0 | K28: =G28+J28 -> 0 | M28: =M27+K28-L28 -> 382940.4
A29: 26 | B29: 45834 | E29: 0 | G29: =E29*F29 -> 0 | H29: 0 | I29: 0 | J29: =H29*I29 -> 0 | K29: =G29+J29 -> 0 | M29: =M28+K29-L29 -> 382940.4
A30: 27 | B30: 45835 | E30: 0 | G30: =E30*F30 -> 0 | H30: 0 | I30: 0 | J30: =H30*I30 -> 0 | K30: =G30+J30 -> 0 | M30: =M29+K30-L30 -> 382940.4
A31: 28 | B31: 45836 | E31: 0 | G31: =E31*F31 -> 0 | H31: 0 | I31: 0 | J31: =H31*I31 -> 0 | K31: =G31+J31 -> 0 | M31: =M30+K31-L31 -> 382940.4
A32: 29 | B32: 45837 | E32: 0 | G32: =E32*F32 -> 0 | H32: 0 | I32: 0 | J32: =H32*I32 -> 0 | K32: =G32+J32 -> 0 | M32: =M31+K32-L32 -> 382940.4
A33: 30 | B33: 45838 | E33: 0 | G33: =E33*F33 -> 0 | H33: 0 | I33: 0 | J33: =H33*I33 -> 0 | K33: =G33+J33 -> 0 | M33: =M32+K33-L33 -> 382940.4
A34: 31 | E34: 0 | G34: =E34*F34 -> 0 | H34: 0 | I34: 0 | J34: =H34*I34 -> 0 | K34: =G34+J34 -> 0 | M34: =M33+K34-L34 -> 382940.4
E35: =SUM(E4:E34) -> 4000 | G35: =SUM(G4:G34) -> 368400 | H35: =SUM(H4:H34) -> 140 | J35: =SUM(J4:J34) -> 14540.4 | K35: =SUM(K4:K34) -> 382940.4 | L35: =SUM(L4:L34) -> 87640.8

Sheet Chellakere (KUWSDB)
A1: Sri Vishnu Baba Petroleum
A2: S.No | B2: Date | C2: GRN No | D2: Ind No/Bill No | E2: Diesel (Lts) | F2: Price | G2: Amount | H2: Petrol (Lts) | I2: Price | J2: Amount | K2: Total amount | L2: Amount paid | M2: As on Date | N2: Remarks
A3: Opening Balance | K3: 0 | L3: 0 | M3: =+K3 -> 0
A4: 1 | B4: 45809 | G4: =E4*F4 -> 0 | J4: =H4*I4 -> 0 | K4: =G4+J4 -> 0 | L4: =K4 -> 0 | M4: =M3+K4-L4 -> 0
A5: 2 | B5: 45810 | E5: 300 | F5: 90.09 | G5: =E5*F5 -> 27027 | H5: 20 | I5: 103.86 | J5: =H5*I5 -> 2077.2 | K5: =G5+J5 -> 29104.2 | L5: =K5 -> 29104.2 | M5: =M4+K5-L5 -> 0
A6: 3 | B6: 45811 | E6: 215 | F6: 90.09 | G6: =E6*F6 -> 19369.35 | J6: =H6*I6 -> 0 | K6: =G6+J6 -> 19369.35 | L6: =K6 -> 19369.35 | M6: =M5+K6-L6 -> 0
A7: 4 | B7: 45812 | G7: =E7*F7 -> 0 | J7: =H7*I7 -> 0 | K7: =G7+J7 -> 0 | L7: =K7 -> 0 | M7: =M6+K7-L7 -> 0
A8: 5 | B8: 45813 | E8: 300 | F8: 90.09 | G8: =E8*F8 -> 27027 | H8: 20 | I8: 103.86 | J8: =H8*I8 -> 2077.2 | K8: =G8+J8 -> 29104.2 | L8: =K8 -> 29104.2 | M8: =M7+K8-L8 -> 0
A9: 6 | B9: 45814 | E9: 325 | F9: 90.09 | G9: =E9*F9 -> 29279.25 | J9: =H9*I9 -> 0 | K9: =G9+J9 -> 29279.25 | L9: =K9 -> 29279.25 | M9: =M8+K9-L9 -> 0
A10: 7 | B10: 45815 | E10: 320 | F10: 90.09 | G10: =E10*F10 -> 28828.8 | J10: =H10*I10 -> 0 | K10: =G10+J10 -> 28828.8 | L10: =K10 -> 28828.8 | M10: =M9+K10-L10 -> 0
A11: 8 | B11: 45816 | G11: =E11*F11 -> 0 | J11: =H11*I11 -> 0 | K11: =G11+J11 -> 0 | L11: =K11 -> 0 | M11: =M10+K11-L11 -> 0
A12: 9 | B12: 45817 | G12: =E12*F12 -> 0 | J12: =H12*I12 -> 0 | K12: =G12+J12 -> 0 | L12: =K12 -> 0 | M12: =M11+K12-L12 -> 0
A13: 10 | B13: 45818 | E13: 300 | F13: 90.09 | G13: =E13*F13 -> 27027 | H13: 22 | I13: 103.86 | J13: =H13*I13 -> 2284.92 | K13: =G13+J13 -> 29311.92 | L13: =K13 -> 29311.92 | M13: =M12+K13-L13 -> 0
A14: 11 | B14: 45819 | G14: =E14*F14 -> 0 | J14: =H14*I14 -> 0 | K14: =G14+J14 -> 0 | L14: =K14 -> 0 | M14: =M13+K14-L14 -> 0
A15: 12 | B15: 45820 | E15: 300 | F15: 90.09 | G15: =E15*F15 -> 27027 | H15: 20 | I15: 103.86 | J15: =H15*I15 -> 2077.2 | K15: =G15+J15 -> 29104.2 | L15: =K15 -> 29104.2 | M15: =M14+K15-L15 -> 0
A16: 13 | B16: 45821 | E16: 300 | F16: 92.09 | G16: =E16*F16 -> 27627 | H16: 20 | I16: 103.86 | J16: =H16*I16 -> 2077.2 | K16: =G16+J16 -> 29704.2 | L16: =K16 -> 29704.2 | M16: =M15+K16-L16 -> 0
A17: 14 | B17: 45822 | G17: =E17*F17 -> 0 | J17: =H17*I17 -> 0 | K17: =G17+J17 -> 0 | L17: =K17 -> 0 | M17: =M16+K17-L17 -> 0
A18: 15 | B18: 45823 | G18: =E18*F18 -> 0 | J18: =H18*I18 -> 0 | K18: =G18+J18 -> 0 | L18: =K18 -> 0 | M18: =M17+K18-L18 -> 0
A19: 16 | B19: 45824 | E19: 310 | F19: 92.09 | G19: =E19*F19 -> 28547.9 | H19: 10 | I19: 103.86 | J19: =H19*I19 -> 1038.6 | K19: =G19+J19 -> 29586.5 | L19: =K19 -> 29586.5 | M19: =M18+K19-L19 -> 0
A20: 17 | B20: 45825 | E20: 215 | F20: 92.09 | G20: =E20*F20 -> 19799.35 | J20: =H20*I20 -> 0 | K20: =G20+J20 -> 19799.35 | L20: =K20 -> 19799.35 | M20: =M19+K20-L20 -> 0
A21: 18 | B21: 45826 | F21: 92.09 | G21: =E21*F21 -> 0 | J21: =H21*I21 -> 0 | K21: =G21+J21 -> 0 | L21: =K21 -> 0 | M21: =M20+K21-L21 -> 0
A22: 19 | B22: 45827 | E22: 300 | F22: 92.09 | G22: =E22*F22 -> 27627 | H22: 20 | I22: 103.86 | J22: =H22*I22 -> 2077.2 | K22: =G22+J22 -> 29704.2 | L22: =K22 -> 29704.2 | M22: =M21+K22-L22 -> 0
A23: 20 | B23: 45828 | G23: =E23*F23 -> 0 | J23: =H23*I23 -> 0 | K23: =G23+J23 -> 0 | L23: =K23 -> 0 | M23: =M22+K23-L23 -> 0
A24: 21 | B24: 45829 | E24: 215 | F24: 92.07 | G24: =E24*F24 -> 19795.05 | J24: =H24*I24 -> 0 | K24: =G24+J24 -> 19795.05 | L24: =K24 -> 19795.05 | M24: =M23+K24-L24 -> 0
A25: 22 | B25: 45830 | G25: =E25*F25 -> 0 | J25: =H25*I25 -> 0 | K25: =G25+J25 -> 0 | L25: =K25 -> 0 | M25: =M24+K25-L25 -> 0
A26: 23 | B26: 45831 | E26: 215 | F26: 92.07 | G26: =E26*F26 -> 19795.05 | J26: =H26*I26 -> 0 | K26: =G26+J26 -> 19795.05 | L26: =K26 -> 19795.05 | M26: =M25+K26-L26 -> 0
A27: 24 | B27: 45832 | G27: =E27*F27 -> 0 | J27: =H27*I27 -> 0 | K27: =G27+J27 -> 0 | L27: =K27 -> 0 | M27: =M26+K27-L27 -> 0
A28: 25 | B28: 45833 | E28: 290 | F28: 92.07 | G28: =E28*F28 -> 26700.3 | H28: 30 | I28: 103.86 | J28: =H28*I28 -> 3115.8 | K28: =G28+J28 -> 29816.1 | L28: =K28 -> 29816.1 | M28: 0
A29: 26 | B29: 45834 | E29: 265 | F29: 92.07 | G29: =E29*F29 -> 24398.55 | H29: 50 | I29: 103.86 | J29: =H29*I29 -> 5193 | K29: =G29+J29 -> 29591.55 | L29: =K29 -> 29591.55 | M29: 0
A30: 27 | B30: 45835 | E30: 105 | F30: 92.07 | G30: =E30*F30 -> 9667.35 | J30: =H30*I30 -> 0 | K30: =G30+J30 -> 9667.35 | L30: =K30 -> 9667.35 | M30: 0
A31: 28 | B31: 45836 | E31: 289 | F31: 92.07 | G31: =E31*F31 -> 26608.23 | H31: 30 | I31: 103.86 | J31: =H31*I31 -> 3115.8 | K31: =G31+J31 -> 29724.03 | L31: =K31 -> 29724.03 | M31: 0
A32: 29 | B32: 45837 | G32: =E32*F32 -> 0 | J32: =H32*I32 -> 0 | K32: =G32+J32 -> 0 | L32: =K32 -> 0
A33: 30 | B33: 45838 | G33: =E33*F33 -> 0 | J33: =H33*I33 -> 0 | K33: =G33+J33 -> 0 | L33: =K33 -> 0
A34: 31
E35: =SUM(E4:E34) -> 4564 | G35: =SUM(G4:G34) -> 416151.18 | H35: =SUM(H4:H34) -> 242 | J35: =SUM(J4:J34) -> 25134.12 | K35: =SUM(K4:K34) -> 441285.3 | L35: =SUM(L4:L34) -> 441285.3

Sheet Malebenur(KUWSDB)
A1: Sri Ramanjuneya Service Station
A2: S.No | B2: Date | C2: GRN No | D2: Ind No/Bill No | E2: Diesel (Lts) | F2: Price | G2: Amount | H2: Petrol (Lts) | I2: Price | J2: Amount | K2: Total amount | L2: Amount paid | M2: As on Date | N2: Remarks
A3: Opening Balance | K3: 36616.014 | M3: =+K3 -> 36616.014
A4: 1 | B4: 45809 | E4: 0 | F4: 0 | G4: =E4*F4 -> 0 | H4: 0 | J4: =H4*I4 -> 0 | K4: =G4+J4 -> 0 | L4: 0 | M4: =M3+K4-L4 -> 36616.014
A5: 2 | B5: 45810 | E5: 500 | F5: 92.1 | G5: =E5*F5 -> 46050 | H5: 20 | I5: 103.86 | J5: =H5*I5 -> 2077.2 | K5: =G5+J5 -> 48127.2 | L5: 0 | M5: =M4+K5-L5 -> 84743.214
A6: 3 | B6: 45811 | E6: 0 | F6: 0 | G6: =E6*F6 -> 0 | H6: 0 | J6: =H6*I6 -> 0 | K6: =G6+J6 -> 0 | L6: 0 | M6: =M5+K6-L6 -> 84743.214
A7: 4 | B7: 45812 | E7: 0 | F7: 0 | G7: =E7*F7 -> 0 | H7: 0 | J7: =H7*I7 -> 0 | K7: =G7+J7 -> 0 | L7: 0 | M7: =M6+K7-L7 -> 84743.214
A8: 5 | B8: 45813 | E8: 0 | F8: 0 | G8: =E8*F8 -> 0 | H8: 0 | J8: =H8*I8 -> 0 | K8: =G8+J8 -> 0 | L8: 0 | M8: =M7+K8-L8 -> 84743.214
A9: 6 | B9: 45814 | E9: 0 | F9: 0 | G9: =E9*F9 -> 0 | H9: 0 | J9: =H9*I9 -> 0 | K9: =G9+J9 -> 0 | L9: 84743.21 | M9: =M8+K9-L9 -> 0.004
A10: 7 | B10: 45815 | E10: 0 | F10: 0 | G10: =E10*F10 -> 0 | H10: 0 | J10: =H10*I10 -> 0 | K10: =G10+J10 -> 0 | L10: 0 | M10: =M9+K10-L10 -> 0.004
A11: 8 | B11: 45816 | E11: 500 | F11: 92.1 | G11: =E11*F11 -> 46050 | H11: 0 | J11: =H11*I11 -> 0 | K11: =G11+J11 -> 46050 | L11: 0 | M11: =M10+K11-L11 -> 46050.004
A12: 9 | B12: 45817 | E12: 0 | F12: 0 | G12: =E12*F12 -> 0 | H12: 0 | J12: =H12*I12 -> 0 | K12: =G12+J12 -> 0 | L12: 0 | M12: =M11+K12-L12 -> 46050.004
A13: 10 | B13: 45818 | E13: 0 | F13: 0 | G13: =E13*F13 -> 0 | H13: 0 | J13: =H13*I13 -> 0 | K13: =G13+J13 -> 0 | L13: 0 | M13: =M12+K13-L13 -> 46050.004
A14: 11 | B14: 45819 | E14: 0 | F14: 0 | G14: =E14*F14 -> 0 | H14: 0 | J14: =H14*I14 -> 0 | K14: =G14+J14 -> 0 | L14: 0 | M14: =M13+K14-L14 -> 46050.004
A15: 12 | B15: 45820 | E15: 500 | F15: 92.1 | G15: =E15*F15 -> 46050 | H15: 35 | I15: 103.86 | J15: =H15*I15 -> 3635.1 | K15: =G15+J15 -> 49685.1 | L15: 0 | M15: =M14+K15-L15 -> 95735.104
A16: 13 | B16: 45821 | E16: 0 | F16: 0 | G16: =E16*F16 -> 0 | H16: 0 | J16: =H16*I16 -> 0 | K16: =G16+J16 -> 0 | L16: 0 | M16: =M15+K16-L16 -> 95735.104
A17: 14 | B17: 45822 | E17: 0 | F17: 0 | G17: =E17*F17 -> 0 | H17: 0 | J17: =H17*I17 -> 0 | K17: =G17+J17 -> 0 | L17: 0 | M17: =M16+K17-L17 -> 95735.104
A18: 15 | B18: 45823 | E18: 0 | F18: 0 | G18: =E18*F18 -> 0 | H18: 0 | J18: =H18*I18 -> 0 | K18: =G18+J18 -> 0 | L18: 0 | M18: =M17+K18-L18 -> 95735.104
A19: 16 | B19: 45824 | E19: 500 | F19: 92.1 | G19: =E19*F19 -> 46050 | H19: 20 | I19: 103.86 | J19: =H19*I19 -> 2077.2 | K19: =G19+J19 -> 48127.2 | L19: 0 | M19: =M18+K19-L19 -> 143862.3
A20: 17 | B20: 45825 | E20: 0 | F20: 0 | G20: =E20*F20 -> 0 | H20: 0 | J20: =H20*I20 -> 0 | K20: =G20+J20 -> 0 | L20: 0 | M20: =M19+K20-L20 -> 143862.3 | V20: =400*90.23 -> 36092
A21: 18 | B21: 45826 | E21: 0 | F21: 0 | G21: =E21*F21 -> 0 | H21: 0 | J21: =H21*I21 -> 0 | K21: =G21+J21 -> 0 | L21: 100000 | M21: =M20+K21-L21 -> 43862.304 | V21: =35*104.14 -> 3644.9
A22: 19 | B22: 45827 | E22: 500 | F22: 92.1 | G22: =E22*F22 -> 46050 | H22: 35 | I22: 103.86 | J22: =H22*I22 -> 3635.1 | K22: =G22+J22 -> 49685.1 | L22: 0 | M22: =M21+K22-L22 -> 93547.404
A23: 20 | B23: 45828 | E23: 0 | F23: 0 | G23: =E23*F23 -> 0 | H23: 0 | J23: =H23*I23 -> 0 | K23: =G23+J23 -> 0 | L23: 0 | M23: =M22+K23-L23 -> 93547.404
A24: 21 | B24: 45829 | E24: 0 | F24: 0 | G24: =E24*F24 -> 0 | H24: 0 | J24: =H24*I24 -> 0 | K24: =G24+J24 -> 0 | L24: 0 | M24: =M23+K24-L24 -> 93547.404
A25: 22 | B25: 45830 | E25: 0 | F25: 0 | G25: =E25*F25 -> 0 | H25: 0 | J25: =H25*I25 -> 0 | K25: =G25+J25 -> 0 | L25: 0 | M25: =M24+K25-L25 -> 93547.404
A26: 23 | B26: 45831 | E26: 200 | F26: 92.01 | G26: =E26*F26 -> 18402 | H26: 0 | J26: =H26*I26 -> 0 | K26: =G26+J26 -> 18402 | L26: 18402 | M26: =M25+K26-L26 -> 93547.404
A27: 24 | B27: 45832 | E27: 0 | F27: 0 | G27: =E27*F27 -> 0 | H27: 0 | J27: =H27*I27 -> 0 | K27: =G27+J27 -> 0 | L27: 0 | M27: =M26+K27-L27 -> 93547.404
A28: 25 | B28: 45833 | E28: 500 | F28: 92.01 | G28: =E28*F28 -> 46005 | H28: 35 | I28: 103.86 | J28: =H28*I28 -> 3635.1 | K28: =G28+J28 -> 49640.1 | L28: 93547 | M28: =M27+K28-L28 -> 49640.504
A29: 26 | B29: 45834 | E29: 0 | F29: 0 | G29: =E29*F29 -> 0 | H29: 0 | J29: =H29*I29 -> 0 | K29: =G29+J29 -> 0 | L29: 0 | M29: =M28+K29-L29 -> 49640.504
A30: 27 | B30: 45835 | E30: 0 | F30: 0 | G30: =E30*F30 -> 0 | H30: 0 | J30: =H30*I30 -> 0 | K30: =G30+J30 -> 0 | L30: 0 | M30: =M29+K30-L30 -> 49640.504
A31: 28 | B31: 45836 | E31: 500 | F31: 92.01 | G31: =E31*F31 -> 46005 | H31: 30 | I31: 103.86 | J31: =H31*I31 -> 3115.8 | K31: =G31+J31 -> 49120.8 | L31: 0 | M31: =M30+K31-L31 -> 98761.304
A32: 29 | B32: 45837 | E32: 0 | F32: 0 | G32: =E32*F32 -> 0 | H32: 0 | J32: =H32*I32 -> 0 | K32: =G32+J32 -> 0 | L32: 0 | M32: =M31+K32-L32 -> 98761.304
A33: 30 | B33: 45838 | E33: 0 | F33: 0 | G33: =E33*F33 -> 0 | H33: 0 | J33: =H33*I33 -> 0 | K33: =G33+J33 -> 0 | L33: 0 | M33: =M32+K33-L33 -> 98761.304
A34: 31 | E34: 0 | F34: 0 | G34: =E34*F34 -> 0 | H34: 0 | J34: =H34*I34 -> 0 | K34: =G34+J34 -> 0 | L34: 0 | M34: =M33+K34-L34 -> 98761.304
E35: 0 | F35: 0 | G35: =E35*F35 -> 0 | H35: 0 | J35: =H35*I35 -> 0 | K35: =G35+J35 -> 0 | L35: 0 | M35: =M34+K35-L35 -> 98761.304
E36: =SUM(E4:E34) -> 3700 | G36: =SUM(G4:G34) -> 340662 | H36: =SUM(H4:H34) -> 175 | J36: =SUM(J4:J34) -> 18175.5 | K36: =SUM(K4:K34) -> 358837.5 | L36: =SUM(L4:L34) -> 296692.21
E37: 0 | G37: 0 | H37: 0 | J37: 0 | K37: =G37+J37 -> 0 | L37: 0
E38: =SUM(E36:E37) -> 3700 | F38: =SUM(F36:F37) -> 0 | G38: =SUM(G36:G37) -> 340662 | H38: =SUM(H36:H37) -> 175 | I38: =SUM(I36:I37) -> 0 | J38: =SUM(J36:J37) -> 18175.5 | K38: =SUM(K36:K37) -> 358837.5 | L38: =SUM(L36:L37) -> 296692.21
S42: 9052944708

Sheet Haveri
A1: Shivalingeshwar Petroleum
A2: S.No | B2: Date | C2: GRN No | D2: Ind No/Bill No | E2: Diesel (Lts) | F2: Price | G2: Amount | H2: Petrol (Lts) | I2: Price | J2: Amount | K2: Total amount | L2: Amount paid | M2: As on Date | N2: Remarks
D3: Opening Balance | K3: 36319.153 | L3: 0 | M3: =+K3 -> 36319.153
A4: 1 | B4: 45809 | E4: 0 | F4: 0 | G4: =E4*F4 -> 0 | H4: 0 | I4: 0 | J4: =H4*I4 -> 0 | K4: =G4+J4 -> 0 | L4: 0 | M4: =M3+K4-L4 -> 36319.153
A5: 2 | B5: 45810 | E5: 0 | F5: 0 | G5: =E5*F5 -> 0 | H5: 0 | I5: 0 | J5: =H5*I5 -> 0 | K5: =G5+J5 -> 0 | L5: 0 | M5: =M4+K5-L5 -> 36319.153
A6: 3 | B6: 45811 | E6: 286.16 | F6: 91.47 | G6: =E6*F6 -> 26175.055 | H6: 0 | I6: 0 | J6: =H6*I6 -> 0 | K6: =G6+J6 -> 26175.055 | L6: 0 | M6: =M5+K6-L6 -> 62494.209
A7: 4 | B7: 45812 | E7: 32.4 | F7: 91.47 | G7: =E7*F7 -> 2963.628 | H7: 5 | I7: 103.4 | J7: =H7*I7 -> 517 | K7: =G7+J7 -> 3480.628 | L7: 0 | M7: =M6+K7-L7 -> 65974.837
A8: 5 | B8: 45813 | E8: 0 | F8: 0 | G8: =E8*F8 -> 0 | H8: 0 | I8: 0 | J8: =H8*I8 -> 0 | K8: =G8+J8 -> 0 | L8: 0 | M8: =M7+K8-L8 -> 65974.837
A9: 6 | B9: 45814 | E9: 478.97 | F9: 91.47 | G9: =E9*F9 -> 43811.386 | H9: 0 | I9: 0 | J9: =H9*I9 -> 0 | K9: =G9+J9 -> 43811.386 | L9: 65000 | M9: =M8+K9-L9 -> 44786.223
A10: 7 | B10: 45815 | E10: 30 | F10: 91.47 | G10: =E10*F10 -> 2744.1 | H10: 6 | I10: 103.4 | J10: =H10*I10 -> 620.4 | K10: =G10+J10 -> 3364.5 | L10: 0 | M10: =M9+K10-L10 -> 48150.723
A11: 8 | B11: 45816 | E11: 50.01 | F11: 91.47 | G11: =E11*F11 -> 4574.4147 | H11: 0 | I11: 0 | J11: =H11*I11 -> 0 | K11: =G11+J11 -> 4574.4147 | L11: 0 | M11: =M10+K11-L11 -> 52725.137
A12: 9 | B12: 45817 | E12: 0 | F12: 0 | G12: =E12*F12 -> 0 | H12: 0 | I12: 0 | J12: =H12*I12 -> 0 | K12: =G12+J12 -> 0 | L12: 0 | M12: =M11+K12-L12 -> 52725.137 | O12: .
A13: 10 | B13: 45818 | E13: 0 | F13: 0 | G13: =E13*F13 -> 0 | H13: 0 | I13: 0 | J13: =H13*I13 -> 0 | K13: =G13+J13 -> 0 | L13: 0 | M13: =M12+K13-L13 -> 52725.137
A14: 11 | B14: 45819 | E14: 38.08 | F14: 91.47 | G14: =E14*F14 -> 3483.1776 | H14: 0 | I14: 0 | J14: =H14*I14 -> 0 | K14: =G14+J14 -> 3483.1776 | L14: 0 | M14: =M13+K14-L14 -> 56208.315
A15: 12 | B15: 45820 | E15: 0 | F15: 0 | G15: =E15*F15 -> 0 | H15: 0 | I15: 0 | J15: =H15*I15 -> 0 | K15: =G15+J15 -> 0 | L15: 0 | M15: =M14+K15-L15 -> 56208.315
A16: 13 | B16: 45821 | E16: 89.02 | F16: 91.47 | G16: =E16*F16 -> 8142.6594 | H16: 0 | I16: 0 | J16: =H16*I16 -> 0 | K16: =G16+J16 -> 8142.6594 | L16: 0 | M16: =M15+K16-L16 -> 64350.974
A17: 14 | B17: 45822 | E17: 5 | F17: 91.47 | G17: =E17*F17 -> 457.35 | H17: 16.53 | I17: 103.4 | J17: =H17*I17 -> 1709.202 | K17: =G17+J17 -> 2166.552 | L17: 0 | M17: =M16+K17-L17 -> 66517.526
A18: 15 | B18: 45823 | E18: 157.69 | F18: 91.47 | G18: =E18*F18 -> 14423.904 | H18: 0 | I18: 0 | J18: =H18*I18 -> 0 | K18: =G18+J18 -> 14423.904 | L18: 0 | M18: =M17+K18-L18 -> 80941.431
A19: 16 | B19: 45824 | E19: 100 | F19: 91.47 | G19: =E19*F19 -> 9147 | H19: 0 | I19: 0 | J19: =H19*I19 -> 0 | K19: =G19+J19 -> 9147 | L19: 0 | M19: =M18+K19-L19 -> 90088.431
A20: 17 | B20: 45825 | E20: 205.38 | F20: 91.47 | G20: =E20*F20 -> 18786.109 | H20: 0 | I20: 0 | J20: =H20*I20 -> 0 | K20: =G20+J20 -> 18786.109 | L20: 0 | M20: =M19+K20-L20 -> 108874.54
A21: 18 | B21: 45826 | E21: 161.23 | F21: 91.47 | G21: =E21*F21 -> 14747.708 | H21: 20 | I21: 103.4 | J21: =H21*I21 -> 2068 | K21: =G21+J21 -> 16815.708 | L21: 108800 | M21: =M20+K21-L21 -> 16890.247
A22: 19 | B22: 45827 | E22: 22.32 | F22: 91.47 | G22: =E22*F22 -> 2041.6104 | H22: 6 | I22: 103.4 | J22: =H22*I22 -> 620.4 | K22: =G22+J22 -> 2662.0104 | L22: 0 | M22: =M21+K22-L22 -> 19552.258
A23: 20 | B23: 45828 | E23: 62.38 | F23: 91.47 | G23: =E23*F23 -> 5705.8986 | H23: 0 | I23: 0 | J23: =H23*I23 -> 0 | K23: =G23+J23 -> 5705.8986 | L23: 0 | M23: =M22+K23-L23 -> 25258.156
A24: 21 | B24: 45829 | E24: 381.06 | F24: 91.47 | G24: =E24*F24 -> 34855.558 | H24: 5 | I24: 103.4 | J24: =H24*I24 -> 517 | K24: =G24+J24 -> 35372.558 | L24: 0 | M24: =M23+K24-L24 -> 60630.714
... A32: 29 | B32: 45837 | E32: 0 | F32: 0 | G32: =E32*F32 -> 0 | H32: 0 | I32: 0 | J32: =H32*I32 -> 0 | K32: =G32+J32 -> 0 | L32: 0 | M32: =M31+K32-L32 -> 155271.11
A33: 30 | B33: 45838 | E33: 127 | F33: 91.47 | G33: =E33*F33 -> 11616.69 | H33: 10 | I33: 103.4 | J33: =H33*I33 -> 1034 | K33: =G33+J33 -> 12650.69 | L33: 0 | M33: =M32+K33-L33 -> 167921.8 | Q33: =35000-8000 -> 27000
A34: 31 | E34: 0 | F34: 0 | G34: =E34*F34 -> 0 | H34: 0 | I34: 0 | J34: =H34*I34 -> 0 | K34: =G34+J34 -> 0 | L34: 0 | M34: =M33+K34-L34 -> 167921.8
E35: =SUM(E4:E34) -> 3219.58 | G35: =SUM(G4:G34) -> 294494.98 | H35: =SUM(H4:H34) -> 105.49 | J35: =SUM(J4:J34) -> 10907.666 | K35: =SUM(K4:K34) -> 305402.65 | L35: =SUM(L4:L34) -> 173800
I38: =K24+L24 -> 35372.558

Sheet Guttal
A1: Taware filling station
A2: S.No | B2: Date | C2: GRN No | D2: Ind No/Bill No | E2: Diesel (Lts) | F2: Price | G2: Amount | H2: Petrol (Lts) | I2: Price | J2: Amount | K2: Total amount | L2: Amount paid | M2: As on Date | N2: Remarks
D3: Opening Balance | K3: 0 | L3: 0 | M3: =+K3 -> 0
A4: 1 | B4: 45809 | E4: 0 | F4: 0 | G4: =E4*F4 -> 0 | H4: 0 | I4: 0 | J4: =H4*I4 -> 0 | K4: =G4+J4 -> 0 | L4: 0 | M4: =M3+K4-L4 -> 0
A5: 2 | B5: 45810 | E5: 130 | F5: 91.8 | G5: =E5*F5 -> 11934 | H5: 0 | I5: 0 | J5: =H5*I5 -> 0 | K5: =G5+J5 -> 11934 | L5: =+K5 -> 11934 | M5: =M4+K5-L5 -> 0
A6: 3 | B6: 45811 | E6: 30 | F6: 91.8 | G6: =E6*F6 -> 2754 | H6: 0 | I6: 0 | J6: =H6*I6 -> 0 | K6: =G6+J6 -> 2754 | L6: =+K6 -> 2754 | M6: =M5+K6-L6 -> 0
A7: 4 | B7: 45812 | E7: 190.15 | F7: 91.8 | G7: =E7*F7 -> 17455.77 | H7: 0 | I7: 0 | J7: =H7*I7 -> 0 | K7: =G7+J7 -> 17455.77 | L7: =+K7 -> 17455.77 | M7: =M6+K7-L7 -> 0
A8: 5 | B8: 45813 | E8: 0 | F8: 0 | G8: =E8*F8 -> 0 | H8: 0 | I8: 0 | J8: =H8*I8 -> 0 | K8: =G8+J8 -> 0 | L8: =+K8 -> 0 | M8: =M7+K8-L8 -> 0
A9: 6 | B9: 45814 | E9: 0 | F9: 0 | G9: =E9*F9 -> 0 | H9: 0 | I9: 0 | J9: =H9*I9 -> 0 | K9: =G9+J9 -> 0 | L9: =+K9 -> 0 | M9: =M8+K9-L9 -> 0
A10: 7 | B10: 45815 | E10: 10 | F10: 91.8 | G10: =E10*F10 -> 918 | H10: 0 | I10: 0 | J10: =H10*I10 -> 0 | K10: =G10+J10 -> 918 | L10: =+K10 -> 918 | M10: =M9+K10-L10 -> 0
A11: 8 | B11: 45816 | E11: 0 | F11: 0 | G11: =E11*F11 -> 0 | H11: 0 | I11: 0 | J11: =H11*I11 -> 0 | K11: =G11+J11 -> 0 | L11: =+K11 -> 0 | M11: =M10+K11-L11 -> 0
A12: 9 | B12: 45817 | E12: 0 | F12: 0 | G12: =E12*F12 -> 0 | H12: 0 | I12: 0 | J12: =H12*I12 -> 0 | K12: =G12+J12 -> 0 | L12: =+K12 -> 0 | M12: =M11+K12-L12 -> 0 | O12: .
A13: 10 | B13: 45818 | E13: 71.95 | F13: 91.8 | G13: =E13*F13 -> 6605.01 | H13: 5 | I13: 103.76 | J13: =H13*I13 -> 518.8 | K13: =G13+J13 -> 7123.81 | L13: =+K13 -> 7123.81 | M13: =M12+K13-L13 -> 0
A14: 11 | B14: 45819 | E14: 0 | F14: 0 | G14: =E14*F14 -> 0 | H14: 11 | I14: 103.76 | J14: =H14*I14 -> 1141.36 | K14: =G14+J14 -> 1141.36 | L14: =+K14 -> 1141.36 | M14: =M13+K14-L14 -> 0
A15: 12 | B15: 45820 | E15: 0 | F15: 0 | G15: =E15*F15 -> 0 | H15: 0 | I15: 0 | J15: =H15*I15 -> 0 | K15: =G15+J15 -> 0 | L15: =+K15 -> 0 | M15: =M14+K15-L15 -> 0
A16: 13 | B16: 45821 | E16: 65 | F16: 91.8 | G16: =E16*F16 -> 5967 | H16: 0 | I16: 0 | J16: =H16*I16 -> 0 | K16: =G16+J16 -> 5967 | L16: =+K16 -> 5967 | M16: =M15+K16-L16 -> 0
A17: 14 | B17: 45822 | E17: 30 | F17: 91.8 | G17: =E17*F17 -> 2754 | H17: 0 | I17: 0 | J17: =H17*I17 -> 0 | K17: =G17+J17 -> 2754 | L17: =+K17 -> 2754 | M17: =M16+K17-L17 -> 0
A18: 15 | B18: 45823 | E18: 0 | F18: 0 | G18: =E18*F18 -> 0 | H18: 0 | I18: 0 | J18: =H18*I18 -> 0 | K18: =G18+J18 -> 0 | L18: =+K18 -> 0 | M18: =M17+K18-L18 -> 0
A19: 16 | B19: 45824 | E19: 0 | F19: 0 | G19: =E19*F19 -> 0 | H19: 0 | I19: 0 | J19: =H19*I19 -> 0 | K19: =G19+J19 -> 0 | L19: =+K19 -> 0 | M19: =M18+K19-L19 -> 0
A20: 17 | B20: 45825 | E20: 220 | F20: 91.8 | G20: =E20*F20 -> 20196 | H20: 0 | I20: 0 | J20: =H20*I20 -> 0 | K20: =G20+J20 -> 20196 | L20: =+K20 -> 20196 | M20: =M19+K20-L20 -> 0
A21: 18 | B21: 45826 | E21: 10 | F21: 91.8 | G21: =E21*F21 -> 918 | H21: 5 | I21: 103.76 | J21: =H21*I21 -> 518.8 | K21: =G21+J21 -> 1436.8 | L21: =+K21 -> 1436.8 | M21: =M20+K21-L21 -> 0
A22: 19 | B22: 45827 | E22: 120 | F22: 91.8 | G22: =E22*F22 -> 11016 | H22: 0 | I22: 0 | J22: =H22*I22 -> 0 | K22: =G22+J22 -> 11016 | L22: =+K22 -> 11016 | M22: =M21+K22-L22 -> 0
A23: 20 | B23: 45828 | E23: 165 | F23: 91.8 | G23: =E23*F23 -> 15147 | H23: 0 | I23: 0 | J23: =H23*I23 -> 0 | K23: =G23+J23 -> 15147 | L23: =+K23 -> 15147 | M23: =M22+K23-L23 -> 0
A24: 21 | B24: 45829 | E24: 135 | F24: 91.8 | G24: =E24*F24 -> 12393 | H24: 10 | I24: 103.76 | J24: =H24*I24 -> 1037.6 | K24: =G24+J24 -> 13430.6 | L24: =+K24 -> 13430.6 | M24: =M23+K24-L24 -> 0
... A33: 30 | B33: 45838 | E33: 90 | F33: 91.8 | G33: =E33*F33 -> 8262 | H33: 5 | I33: 103.76 | J33: =H33*I33 -> 518.8 | K33: =G33+J33 -> 8780.8 | L33: =+K33 -> 8780.8 | M33: =M32+K33-L33 -> 0
A34: 31 | E34: 0 | F34: 0 | G34: =E34*F34 -> 0 | H34: 0 | I34: 0 | J34: =H34*I34 -> 0 | K34: =G34+J34 -> 0 | L34: 0
E35: =SUM(E4:E34) -> 1316.9 | G35: =SUM(G4:G34) -> 120891.42 | H35: =SUM(H4:H34) -> 41 | J35: =SUM(J4:J34) -> 4254.16 | K35: =SUM(K4:K34) -> 125145.58 | L35: =SUM(L4:L34) -> 125145.58
I38: =K24+L24 -> 26861.2

Sheet Rattihali
A1: Shree Siri Gowari petroliam
A2: S.No | B2: Date | C2: GRN No | D2: Ind No/Bill No | E2: Diesel (Lts) | F2: Price | G2: Amount | H2: Petrol (Lts) | I2: Price | J2: Amount | K2: Total amount | L2: Amount paid | M2: As on Date | N2: Remarks
D3: Opening Balance | K3: 0 | L3: 0 | M3: =+K3 -> 0
A4: 1 | B4: 45809 | E4: 0 | F4: 0 | G4: =E4*F4 -> 0 | H4: 0 | I4: 0 | J4: =H4*I4 -> 0 | K4: =G4+J4 -> 0 | L4: =+K4 -> 0 | M4: =M3+K4-L4 -> 0
A5: 2 | B5: 45810 | E5: 180 | F5: 92.04 | G5: =E5*F5 -> 16567.2 | H5: 0 | I5: 0 | J5: =H5*I5 -> 0 | K5: =G5+J5 -> 16567.2 | L5: =+K5 -> 16567.2 | M5: =M4+K5-L5 -> 0
A6: 3 | B6: 45811 | E6: 0 | F6: 0 | G6: =E6*F6 -> 0 | H6: 0 | I6: 0 | J6: =H6*I6 -> 0 | K6: =G6+J6 -> 0 | L6: =+K6 -> 0 | M6: =M5+K6-L6 -> 0
A7: 4 | B7: 45812 | E7: 235 | F7: 92.04 | G7: =E7*F7 -> 21629.4 | H7: 0 | I7: 0 | J7: =H7*I7 -> 0 | K7: =G7+J7 -> 21629.4 | L7: =+K7 -> 21629.4 | M7: =M6+K7-L7 -> 0
A8: 5 | B8: 45813 | E8: 180 | F8: 92.04 | G8: =E8*F8 -> 16567.2 | H8: 15 | I8: 104.02 | J8: =H8*I8 -> 1560.3 | K8: =G8+J8 -> 18127.5 | L8: =+K8 -> 18127.5 | M8: =M7+K8-L8 -> 0
A9: 6 | B9: 45814 | E9: 200 | F9: 92.04 | G9: =E9*F9 -> 18408 | H9: 0 | I9: 0 | J9: =H9*I9 -> 0 | K9: =G9+J9 -> 18408 | L9: =+K9 -> 18408 | M9: =M8+K9-L9 -> 0
A10: 7 | B10: 45815 | E10: 0 | F10: 0 | G10: =E10*F10 -> 0 | H10: 0 | I10: 0 | J10: =H10*I10 -> 0 | K10: =G10+J10 -> 0 | L10: =+K10 -> 0 | M10: =M9+K10-L10 -> 0
A11: 8 | B11: 45816 | E11: 145 | F11: 92.04 | G11: =E11*F11 -> 13345.8 | H11: 0 | I11: 0 | J11: =H11*I11 -> 0 | K11: =G11+J11 -> 13345.8 | L11: =+K11 -> 13345.8 | M11: =M10+K11-L11 -> 0
A12: 9 | B12: 45817 | E12: 0 | F12: 0 | G12: =E12*F12 -> 0 | H12: 0 | I12: 0 | J12: =H12*I12 -> 0 | K12: =G12+J12 -> 0 | L12: =+K12 -> 0 | M12: =M11+K12-L12 -> 0 | O12: .
A13: 10 | B13: 45818 | E13: 180 | F13: 92.04 | G13: =E13*F13 -> 16567.2 | H13: 4 | I13: 104.02 | J13: =H13*I13 -> 416.08 | K13: =G13+J13 -> 16983.28 | L13: =+K13 -> 16983.28 | M13: =M12+K13-L13 -> 0
A14: 11 | B14: 45819 | E14: 0 | F14: 0 | G14: =E14*F14 -> 0 | H14: 0 | I14: 0 | J14: =H14*I14 -> 0 | K14: =G14+J14 -> 0 | L14: =+K14 -> 0 | M14: =M13+K14-L14 -> 0
A15: 12 | B15: 45820 | E15: 0 | F15: 0 | G15: =E15*F15 -> 0 | H15: 0 | I15: 0 | J15: =H15*I15 -> 0 | K15: =G15+J15 -> 0 | L15: =+K15 -> 0 | M15: =M14+K15-L15 -> 0
A16: 13 | B16: 45821 | E16: 0 | F16: 0 | G16: =E16*F16 -> 0 | H16: 0 | I16: 0 | J16: =H16*I16 -> 0 | K16: =G16+J16 -> 0 | L16: =+K16 -> 0 | M16: =M15+K16-L16 -> 0
A17: 14 | B17: 45822 | E17: 0 | F17: 0 | G17: =E17*F17 -> 0 | H17: 0 | I17: 0 | J17: =H17*I17 -> 0 | K17: =G17+J17 -> 0 | L17: =+K17 -> 0 | M17: =M16+K17-L17 -> 0
A18: 15 | B18: 45823 | E18: 0 | F18: 0 | G18: =E18*F18 -> 0 | H18: 0 | I18: 0 | J18: =H18*I18 -> 0 | K18: =G18+J18 -> 0 | L18: =+K18 -> 0 | M18: =M17+K18-L18 -> 0
A19: 16 | B19: 45824 | E19: 180 | F19: 92.04 | G19: =E19*F19 -> 16567.2 | H19: 20 | I19: 104.02 | J19: =H19*I19 -> 2080.4 | K19: =G19+J19 -> 18647.6 | L19: 0 | M19: =M18+K19-L19 -> 18647.6
A20: 17 | B20: 45825 | E20: 0 | F20: 0 | G20: =E20*F20 -> 0 | H20: 0 | I20: 0 | J20: =H20*I20 -> 0 | K20: =G20+J20 -> 0 | L20: =+K20 -> 0 | M20: =M19+K20-L20 -> 18647.6
A21: 18 | B21: 45826 | E21: 190 | F21: 92.04 | G21: =E21*F21 -> 17487.6 | H21: 0 | I21: 0 | J21: =H21*I21 -> 0 | K21: =G21+J21 -> 17487.6 | L21: 0 | M21: =M20+K21-L21 -> 36135.2
A22: 19 | B22: 45827 | E22: 0 | F22: 0 | G22: =E22*F22 -> 0 | H22: 0 | I22: 0 | J22: =H22*I22 -> 0 | K22: =G22+J22 -> 0 | L22: =+K22 -> 0 | M22: =M21+K22-L22 -> 36135.2
A23: 20 | B23: 45828 | E23: 0 | F23: 0 | G23: =E23*F23 -> 0 | H23: 0 | I23: 0 | J23: =H23*I23 -> 0 | K23: =G23+J23 -> 0 | L23: =+K23 -> 0 | M23: =M22+K23-L23 -> 36135.2
A24: 21 | B24: 45829 | E24: 145 | F24: 92.04 | G24: =E24*F24 -> 13345.8 | H24: 0 | I24: 0 | J24: =H24*I24 -> 0 | K24: =G24+J24 -> 13345.8 | L24: 0 | M24: =M23+K24-L24 -> 49481
A25: 22 | B25: 45830 | E25: 0 | F25: 0 | G25: =E25*F25 -> 0 | H25: 0 | I25: 0 | J25: =H25*I25 -> 0 | K25: =G25+J25 -> 0 | L25: =+K25 -> 0 | M25: =M24+K25-L25 -> 49481
A26: 23 | B26: 45831 | E26: 175 | F26: 92.04 | G26: =E26*F26 -> 16107 | H26: 34 | I26: 104.02 | J26: =H26*I26 -> 3536.68 | K26: =G26+J26 -> 19643.68 | L26: 0 | M26: =M25+K26-L26 -> 69124.68
A27: 24 | B27: 45832 | E27: 0 | F27: 0 | G27: =E27*F27 -> 0 | H27: 0 | I27: 0 | J27: =H27*I27 -> 0 | K27: =G27+J27 -> 0 | L27: =+K27 -> 0 | M27: =M26+K27-L27 -> 69124.68
A28: 25 | B28: 45833 | E28: 505 | F28: 92.04 | G28: =E28*F28 -> 46480.2 | H28: 65 | I28: 104.02 | J28: =H28*I28 -> 6761.3 | K28: =G28+J28 -> 53241.5 | L28: 0 | M28: =M27+K28-L28 -> 122366.18
A29: 26 | B29: 45834 | E29: 0 | F29: 0 | G29: =E29*F29 -> 0 | H29: 0 | I29: 0 | J29: =H29*I29 -> 0 | K29: =G29+J29 -> 0 | L29: =+K29 -> 0 | M29: =M28+K29-L29 -> 122366.18
A30: 27 | B30: 45835 | E30: 0 | F30: 0 | G30: =E30*F30 -> 0 | H30: 0 | I30: 0 | J30: =H30*I30 -> 0 | K30: =G30+J30 -> 0 | L30: =+K30 -> 0 | M30: =M29+K30-L30 -> 122366.18
A31: 28 | B31: 45836 | E31: 0 | F31: 0 | G31: =E31*F31 -> 0 | H31: 13.28 | I31: 104.02 | J31: =H31*I31 -> 1381.3856 | K31: =G31+J31 -> 1381.3856 | L31: 0 | M31: =M30+K31-L31 -> 123747.57
A32: 29 | B32: 45837 | E32: 0 | F32: 0 | G32: =E32*F32 -> 0 | H32: 0 | I32: 0 | J32: =H32*I32 -> 0 | K32: =G32+J32 -> 0 | L32: =+K32 -> 0 | M32: =M31+K32-L32 -> 123747.57
A33: 30 | B33: 45838 | E33: 343.06 | F33: 92.04 | G33: =E33*F33 -> 31575.242 | H33: 0 | I33: 0 | J33: =H33*I33 -> 0 | K33: =G33+J33 -> 31575.242 | L33: 0 | M33: =M32+K33-L33 -> 155322.81
A34: 31
E35: =SUM(E4:E34) -> 2658.06 | G35: =SUM(G4:G34) -> 244647.84 | H35: =SUM(H4:H34) -> 151.28 | J35: =SUM(J4:J34) -> 15736.146 | K35: =SUM(K4:K34) -> 260383.99 | L35: =SUM(L4:L34) -> 105061.18
I38: =K24+L24 -> 13345.8

Sheet Gajendragada
A1: Vanasri Petrol Pump
A2: S.No | B2: Date | C2: GRN No | D2: Ind no/Bill No | E2: Diesel (Lts) | F2: Price | G2: Amount | H2: Petrol (Lts) | I2: Price | J2: Amount | K2: Total amount | L2: Amount paid | M2: As on Date | N2: Remarks
A3: Opening Balance | K3: 59460.8 | M3: =+K3 -> 59460.8 | O3: 59460.8
A4: 1 | B4: 45809 | E4: 20 | F4: 91.83 | G4: =E4*F4 -> 1836.6 | H4: 5 | I4: 103.8 | J4: =H4*I4 -> 519 | K4: =G4+J4 -> 2355.6 | M4: =M3+K4-L4 -> 61816.4
A5: 2 | B5: 45810 | E5: 250 | F5: 91.83 | G5: =E5*F5 -> 22957.5 | H5: 5 | I5: 103.8 | J5: =H5*I5 -> 519 | K5: =G5+J5 -> 23476.5 | M5: =M4+K5-L5 -> 85292.9
A6: 3 | B6: 45811 | E6: 0 | F6: 0 | G6: =E6*F6 -> 0 | H6: 0 | I6: 0 | J6: =H6*I6 -> 0 | K6: =G6+J6 -> 0 | M6: =M5+K6-L6 -> 85292.9
A7: 4 | B7: 45812 | E7: 30 | F7: 91.83 | G7: =E7*F7 -> 2754.9 | H7: 0 | I7: 0 | J7: =H7*I7 -> 0 | K7: =G7+J7 -> 2754.9 | M7: =M6+K7-L7 -> 88047.8
A8: 5 | B8: 45813 | E8: 20 | F8: 91.83 | G8: =E8*F8 -> 1836.6 | H8: 5 | I8: 103.8 | J8: =H8*I8 -> 519 | K8: =G8+J8 -> 2355.6 | L8: 88047.8 | M8: =M7+K8-L8 -> 2355.6 | O8: 8497892194 | P8: raja bhakshi
A9: 6 | B9: 45814 | E9: 25 | F9: 91.83 | G9: =E9*F9 -> 2295.75 | H9: 0 | I9: 0 | J9: =H9*I9 -> 0 | K9: =G9+J9 -> 2295.75 | M9: =M8+K9-L9 -> 4651.35 | O9: 1280.1715
A10: 7 | B10: 45815 | E10: 0 | F10: 0 | G10: =E10*F10 -> 0 | H10: 0 | I10: 0 | J10: =H10*I10 -> 0 | K10: =G10+J10 -> 0 | M10: =M9+K10-L10 -> 4651.35
A11: 8 | B11: 45816 | E11: 20 | F11: 91.83 | G11: =E11*F11 -> 1836.6 | H11: 0 | I11: 0 | J11: =H11*I11 -> 0 | K11: =G11+J11 -> 1836.6 | M11: =M10+K11-L11 -> 6487.95
A12: 9 | B12: 45817 | E12: 25 | F12: 91.83 | G12: =E12*F12 -> 2295.75 | H12: 0 | I12: 0 | J12: =H12*I12 -> 0 | K12: =G12+J12 -> 2295.75 | M12: =M11+K12-L12 -> 8783.7
A13: 10 | B13: 45818 | E13: 25 | F13: 91.83 | G13: =E13*F13 -> 2295.75 | H13: 5 | I13: 103.8 | J13: =H13*I13 -> 519 | K13: =G13+J13 -> 2814.75 | M13: =M12+K13-L13 -> 11598.45
A14: 11 | B14: 45819 | F14: 91.83 | G14: =E14*F14 -> 0 | H14: 0 | I14: 0 | J14: =H14*I14 -> 0 | K14: =G14+J14 -> 0 | M14: =M13+K14-L14 -> 11598.45
A15: 12 | B15: 45820 | E15: 25 | F15: 91.83 | G15: =E15*F15 -> 2295.75 | H15: 0 | I15: 0 | J15: =H15*I15 -> 0 | K15: =G15+J15 -> 2295.75 | M15: =M14+K15-L15 -> 13894.2
A16: 13 | B16: 45821 | E16: 50 | F16: 91.83 | G16: =E16*F16 -> 4591.5 | H16: 5 | I16: 103.8 | J16: =H16*I16 -> 519 | K16: =G16+J16 -> 5110.5 | M16: =M15+K16-L16 -> 19004.7
A17: 14 | B17: 45822 | E17: 30 | F17: 91.83 | G17: =E17*F17 -> 2754.9 | H17: 5 | I17: 103.8 | J17: =H17*I17 -> 519 | K17: =G17+J17 -> 3273.9 | M17: =M16+K17-L17 -> 22278.6
A18: 15 | B18: 45823 | E18: 0 | F18: 0 | G18: =E18*F18 -> 0 | H18: 0 | I18: 0 | J18: =H18*I18 -> 0 | K18: =G18+J18 -> 0 | M18: =M17+K18-L18 -> 22278.6
A19: 16 | B19: 45824 | E19: 25 | F19: 91.83 | G19: =E19*F19 -> 2295.75 | H19: 10 | I19: 103.8 | J19: =H19*I19 -> 1038 | K19: =G19+J19 -> 3333.75 | M19: =M18+K19-L19 -> 25612.35
A20: 17 | B20: 45825 | E20: 29 | F20: 91.83 | G20: =E20*F20 -> 2663.07 | H20: 0 | I20: 0 | J20: =H20*I20 -> 0 | K20: =G20+J20 -> 2663.07 | M20: =M19+K20-L20 -> 28275.42
A21: 18 | B21: 45826 | E21: 25 | F21: 91.83 | G21: =E21*F21 -> 2295.75 | H21: 0 | I21: 0 | J21: =H21*I21 -> 0 | K21: =G21+J21 -> 2295.75 | M21: =M20+K21-L21 -> 30571.17
A22: 19 | B22: 45827 | E22: 30 | F22: 91.83 | G22: =E22*F22 -> 2754.9 | H22: 5 | I22: 103.8 | J22: =H22*I22 -> 519 | K22: =G22+J22 -> 3273.9 | M22: =M21+K22-L22 -> 33845.07
A23: 20 | B23: 45828 | E23: 207.89 | F23: 91.83 | G23: =E23*F23 -> 19090.539 | H23: 5 | I23: 103.8 | J23: =H23*I23 -> 519 | K23: =G23+J23 -> 19609.539 | M23: =M22+K23-L23 -> 53454.609
A24: 21 | B24: 45829 | E24: 92 | F24: 91.83 | G24: =E24*F24 -> 8448.36 | H24: 0 | I24: 0 | J24: =H24*I24 -> 0 | K24: =G24+J24 -> 8448.36 | M24: =M23+K24-L24 -> 61902.969
A25: 22 | B25: 45830 | E25: 0 | F25: 0 | G25: =E25*F25 -> 0 | H25: 5 | I25: 103.83 | J25: =H25*I25 -> 519.15 | K25: =G25+J25 -> 519.15 | M25: =M24+K25-L25 -> 62422.119
A26: 23 | B26: 45831 | E26: 25 | F26: 91.83 | G26: =E26*F26 -> 2295.75 | H26: 0 | I26: 0 | J26: =H26*I26 -> 0 | K26: =G26+J26 -> 2295.75 | M26: =M25+K26-L26 -> 64717.869
A27: 24 | B27: 45832 | E27: 0 | F27: 0 | G27: =E27*F27 -> 0 | H27: 0 | I27: 0 | J27: =H27*I27 -> 0 | K27: =G27+J27 -> 0 | M27: =M26+K27-L27 -> 64717.869 | R27: 66742
A28: 25 | B28: 45833 | E28: 0 | F28: 0 | G28: =E28*F28 -> 0 | H28: 0 | I28: 0 | J28: =H28*I28 -> 0 | K28: =G28+J28 -> 0 | M28: =M27+K28-L28 -> 64717.869
A29: 26 | B29: 45834 | E29: 0 | F29: 0 | G29: =E29*F29 -> 0 | H29: 10 | I29: 103.83 | J29: =H29*I29 -> 1038.3 | K29: =G29+J29 -> 1038.3 | M29: =M28+K29-L29 -> 65756.169
A30: 27 | B30: 45835 | E30: 20 | F30: 91.83 | G30: =E30*F30 -> 1836.6 | H30: 0 | I30: 0 | J30: =H30*I30 -> 0 | K30: =G30+J30 -> 1836.6 | M30: =M29+K30-L30 -> 67592.769
A31: 28 | B31: 45836 | E31: 29 | F31: 91.83 | G31: =E31*F31 -> 2663.07 | H31: 10 | I31: 103.83 | J31: =H31*I31 -> 1038.3 | K31: =G31+J31 -> 3701.37 | M31: =M30+K31-L31 -> 71294.139
A32: 29 | B32: 45837 | E32: 0 | F32: 0 | G32: =E32*F32 -> 0 | H32: 0 | I32: 0 | J32: =H32*I32 -> 0 | K32: =G32+J32 -> 0 | M32: =M31+K32-L32 -> 71294.139
A33: 30 | B33: 45838 | E33: 30 | F33: 91.83 | G33: =E33*F33 -> 2754.9 | H33: 0 | I33: 0 | J33: =H33*I33 -> 0 | K33: =G33+J33 -> 2754.9 | M33: =M32+K33-L33 -> 74049.039
A34: 31 | E34: 0 | F34: 0 | G34: =E34*F34 -> 0 | H34: 0 | I34: 0 | J34: =H34*I34 -> 0 | K34: =G34+J34 -> 0 | M34: =M33+K34-L34 -> 74049.039 | O34: 77593.59 | P34: =O34-M34 -> 3544.5513
E35: =SUM(E4:E34) -> 1032.89 | G35: =SUM(G4:G34) -> 94850.289 | H35: =SUM(H4:H34) -> 75 | J35: =SUM(J4:J34) -> 7785.75 | K35: =SUM(K4:K34) -> 102636.04 | L35: =SUM(L4:L34) -> 88047.8

Sheet  Talikote
A1: Talikote
A2: S.No | B2: Date | C2: GRN No | D2: Ind no/Bill No | E2: Diesel (Lts) | F2: Price | G2: Amount | H2: Petrol (Lts) | I2: Price | J2: Amount | K2: Total amount | L2: Amount paid | M2: As on Date | N2: Remarks
A3: Opening Balance | M3: 2488
A4: 1 | B4: 02.06.2025 | E4: 0 | F4: 0 | G4: =E4*F4 -> 0 | H4: 4.35 | I4: 103.44 | J4: =H4*I4 -> 449.964 | K4: =G4+J4 -> 449.964 | L4: 2937.96 | M4: =M3+K4-L4 -> 0.004 | N4: IOCL Card
A5: 3 | B5: 03.06.2025 | E5: 39.88 | F5: 91.5 | G5: =E5*F5 -> 3649.02 | H5: 9.66 | I5: 103.44 | J5: =H5*I5 -> 999.2304 | K5: =G5+J5 -> 4648.2504 | L5: 4648 | M5: =M4+K5-L5 -> 0.2544 | N5: IOCL Card
A6: 4 | B6: 04.06.2025 | E6: 120 | F6: 91.5 | G6: =E6*F6 -> 10980 | H6: 0 | I6: 0 | J6: =H6*I6 -> 0 | K6: =G6+J6 -> 10980 | L6: 10980 | M6: =M5+K6-L6 -> 0.2544 | N6: IOCL Card
A7: 5 | B7: 06.06.2025 | E7: 123.19 | F7: 91.5 | G7: =E7*F7 -> 11271.885 | H7: 6.67 | I7: 103.44 | J7: =H7*I7 -> 689.9448 | K7: =G7+J7 -> 11961.83 | L7: 3840 | M7: =M6+K7-L7 -> 8122.0842 | N7: IOCL Card
A8: 7 | B8: 07.06.2025 | E8: 0 | F8: 0 | G8: =E8*F8 -> 0 | H8: 0 | I8: 0 | J8: =H8*I8 -> 0 | K8: =G8+J8 -> 0 | L8: 8131 | M8: =M7+K8-L8 -> -8.9158 | N8: IOCL Card
A9: 8 | B9: 09.06.2025 | E9: 30 | F9: 91.5 | G9: =E9*F9 -> 2745 | H9: 0 | I9: 0 | J9: =H9*I9 -> 0 | K9: =G9+J9 -> 2745 | L9: 2745 | M9: =M8+K9-L9 -> -8.9158 | N9: IOCL Card
A10: 9 | B10: 10.06.2025 | E10: 71.27 | F10: 91.5 | G10: =E10*F10 -> 6521.205 | H10: 0 | I10: 0 | J10: =H10*I10 -> 0 | K10: =G10+J10 -> 6521.205 | L10: 6521.21 | M10: =M9+K10-L10 -> -8.9208 | N10: IOCL Card
A11: 10 | B11: 11.06.2025 | E11: 0 | F11: 0 | G11: =E11*F11 -> 0 | H11: 4.83 | I11: 103.44 | J11: =H11*I11 -> 499.6152 | K11: =G11+J11 -> 499.6152 | L11: 499.62 | M11: =M10+K11-L11 -> -8.9256 | N11: IOCL Card
A12: 11 | B12: 13.06.2025 | E12: 36.9 | F12: 91.5 | G12: =E12*F12 -> 3376.35 | H12: 0 | I12: 0 | J12: =H12*I12 -> 0 | K12: =G12+J12 -> 3376.35 | L12: 3376.35 | M12: =M11+K12-L12 -> -8.9256 | N12: IOCL Card
A13: 12 | B13: 14.06.2025 | E13: 31.6 | F13: 91.5 | G13: =E13*F13 -> 2891.4 | H13: 0 | I13: 0 | J13: =H13*I13 -> 0 | K13: =G13+J13 -> 2891.4 | L13: 2891.4 | M13: =M12+K13-L13 -> -8.9256 | N13: IOCL Card
A14: 13 | B14: 16.06.2025 | E14: 83.43 | F14: 91.5 | G14: =E14*F14 -> 7633.845 | H14: 6.86 | I14: 103.44 | J14: =H14*I14 -> 709.5984 | K14: =G14+J14 -> 8343.4434 | L14: 4647 | M14: =M13+K14-L14 -> 3687.5178 | N14: IOCL Card
A15: 14 | B15: 17.06.2025 | E15: 251.58 | F15: 91.5 | G15: =E15*F15 -> 23019.57 | H15: 0 | I15: 0 | J15: =H15*I15 -> 0 | K15: =G15+J15 -> 23019.57 | L15: 0 | M15: =M14+K15-L15 -> 26707.088 | N15: IOCL Card
... A21: 20 | B21: 24.06.2025 | E21: 40.44 | F21: 91.5 | G21: =E21*F21 -> 3700.26 | H21: 0 | I21: 103.44 | J21: =H21*I21 -> 0 | K21: =G21+J21 -> 3700.26 | L21: 38245.43 | M21: =M20+K21-L21 -> 6846.3434 | N21: IOCL Card
B22: 25.06.2025 | E22: 0 | F22: 0 | G22: 0 | H22: 9.66 | I22: 103.44 | J22: =H22*I22 -> 999.2304 | K22: =G22+J22 -> 999.2304 | L22: 999.23 | M22: =M21+K22-L22 -> 6846.3438 | N22: IOCL Card
A23: 21 | B23: 26.06.2025 | E23: 88.79 | F23: 91.5 | G23: =E23*F23 -> 8124.285 | H23: 4.83 | I23: 103.44 | J23: =H23*I23 -> 499.6152 | K23: =G23+J23 -> 8623.9002 | L23: 499.62 | M23: =M22+K23-L23 -> 14970.624 | N23: IOCL Card
A24: 22 | B24: 27.06.2025 | E24: 0 | F24: 0 | G24: =E24*F24 -> 0 | H24: 0 | I24: 0 | J24: =H24*I24 -> 0 | K24: =G24+J24 -> 0 | L24: 0 | M24: =M23+K24-L24 -> 14970.624 | N24: IOCL Card
A25: 23 | B25: 28.06.2025 | E25: 65.58 | F25: 91.5 | G25: =E25*F25 -> 6000.57 | H25: 4.83 | I25: 103.44 | J25: =H25*I25 -> 499.6152 | K25: =G25+J25 -> 6500.1852 | L25: 0 | M25: =M24+K25-L25 -> 21470.809 | N25: IOCL Card
A26: 24 | B26: 30.06.2025 | E26: 77.72 | F26: 91.5 | G26: =E26*F26 -> 7111.38 | H26: 0 | I26: 0 | J26: =H26*I26 -> 0 | K26: =G26+J26 -> 7111.38 | M26: =M25+K26-L26 -> 28582.189 | N26: IOCL Card
A27: 25 | E27: 0 | F27: 0 | G27: =E27*F27 -> 0 | H27: 0 | I27: 0 | J27: =H27*I27 -> 0 | K27: =G27+J27 -> 0 | L27: 0 | M27: =M26+K27-L27 -> 28582.189 | N27: IOCL Card
A28: 26 | E28: 0 | F28: 0 | G28: =E28*F28 -> 0 | H28: 0 | I28: 0 | J28: =H28*I28 -> 0 | K28: =G28+J28 -> 0 | L28: 0 | M28: =M27+K28-L28 -> 28582.189 | N28: IOCL Card
A29: 27 | E29: 0 | F29: 0 | G29: =E29*F29 -> 0 | H29: 0 | I29: 0 | J29: =H29*I29 -> 0 | K29: =G29+J29 -> 0 | L29: 0 | M29: =M28+K29-L29 -> 28582.189 | N29: IOCL Card
A30: 28 | E30: 0 | F30: 0 | G30: =E30*F30 -> 0 | H30: 0 | I30: 0 | J30: =H30*I30 -> 0 | K30: =G30+J30 -> 0 | L30: 0 | M30: =M29+K30-L30 -> 28582.189 | N30: IOCL Card
A31: 29 | E31: 0 | F31: 0 | G31: =E31*F31 -> 0 | H31: 0 | I31: 0 | J31: =H31*I31 -> 0 | K31: =G31+J31 -> 0 | L31: 0 | M31: =M30+K31-L31 -> 28582.189 | N31: IOCL Card
A32: 30 | E32: 0 | F32: 0 | G32: =E32*F32 -> 0 | H32: 0 | I32: 0 | J32: =H32*I32 -> 0 | K32: =G32+J32 -> 0 | L32: 0 | M32: 0 | N32: IOCL Card
A33: 31 | E33: 0 | F33: 0 | G33: =E33*F33 -> 0 | H33: 0 | I33: 0 | J33: =H33*I33 -> 0 | K33: =G33+J33 -> 0 | L33: 0 | M33: 0 | N33: IOCL Card
A34: 32 | E34: 0 | F34: 0 | G34: =E34*F34 -> 0 | H34: 0 | I34: 0 | J34: =H34*I34 -> 0 | K34: =G34+J34 -> 0 | L34: 0 | M34: 0 | N34: IOCL Card
A35: 33 | E35: 0 | F35: 0 | G35: =E35*F35 -> 0 | H35: 0 | I35: 0 | J35: =H35*I35 -> 0 | K35: =G35+J35 -> 0 | L35: 0 | M35: 0 | N35: IOCL Card
A36: 34 | E36: 0 | F36: 0 | G36: =E36*F36 -> 0 | H36: 0 | I36: 0 | J36: =H36*I36 -> 0 | K36: =G36+J36 -> 0 | L36: 0 | M36: 0 | N36: IOCL Card
A37: 35 | E37: 0 | F37: 0 | G37: =E37*F37 -> 0 | H37: 0 | I37: 0 | J37: =H37*I37 -> 0 | K37: =G37+J37 -> 0 | L37: 0 | M37: 0 | N37: IOCL Card
A38: 36 | E38: 0 | F38: 0 | G38: =E38*F38 -> 0 | H38: 0 | I38: 0 | J38: =H38*I38 -> 0 | K38: =G38+J38 -> 0 | L38: 0 | M38: 0 | N38: IOCL Card
A39: 37 | E39: 0 | F39: 0 | G39: =E39*F39 -> 0 | H39: 0 | I39: 0 | J39: =H39*I39 -> 0 | K39: =G39+J39 -> 0 | L39: 0 | M39: 0 | N39: IOCL Card
A40: 38 | E40: 0 | F40: 0 | G40: =E40*F40 -> 0 | H40: 0 | I40: 0 | J40: =H40*I40 -> 0 | K40: =G40+J40 -> 0 | L40: =+K40 -> 0 | M40: 0 | N40: IOCL Card
A41: 39 | E41: 0 | F41: 0 | G41: =E41*F41 -> 0 | H41: 0 | I41: 0 | J41: =H41*I41 -> 0 | K41: =G41+J41 -> 0 | L41: =+K41 -> 0 | M41: 0 | N41: IOCL Card
A42: 40 | E42: 0 | F42: 0 | G42: =E42*F42 -> 0 | H42: 0 | I42: 0 | J42: =H42*I42 -> 0 | K42: =G42+J42 -> 0 | L42: =+K42 -> 0 | M42: 0 | N42: IOCL Card
A43: 41 | E43: 0 | F43: 0 | G43: =E43*F43 -> 0 | H43: 0 | I43: 0 | J43: =H43*I43 -> 0 | K43: =G43+J43 -> 0 | L43: =+K43 -> 0 | M43: 0 | N43: IOCL Card
A44: 42 | E44: 0 | F44: 0 | G44: =E44*F44 -> 0 | H44: 0 | I44: 0 | J44: =H44*I44 -> 0 | K44: =G44+J44 -> 0 | L44: =+K44 -> 0 | M44: 0 | N44: IOCL Card
E45: =SUM(E4:E44) -> 1558.26 | G45: =SUM(G4:G44) -> 142580.79 | H45: =SUM(H4:H44) -> 72.68 | J45: =SUM(J4:J44) -> 7518.0192 | K45: =SUM(K4:K44) -> 150098.81 | L45: =SUM(L4:L44) -> 124004.62

Sheet Chadchan
A1: Khavekar Petrolium
A2: S.No | B2: Date | C2: GRN No | D2: Ind no/Bill No | E2: Diesel (Lts) | F2: Price | G2: Amount | H2: Petrol (Lts) | I2: Price | J2: Amount | K2: Total amount | L2: Amount paid | M2: As on Date | N2: Remarks
B3: Opening Balance | K3: 77981.337 | M3: =+K3 -> 77981.337 | O3: 237866.59
A4: 1 | B4: 45809 | E4: 72.07 | F4: 90.23 | G4: =E4*F4 -> 6502.8761 | H4: 1.19 | I4: 102.16 | J4: =H4*I4 -> 121.5704 | K4: =G4+J4 -> 6624.4465 | M4: =M3+K4-L4 -> 84605.783
A5: 2 | B5: 45810 | E5: 5 | F5: 90.23 | G5: =E5*F5 -> 451.15 | H5: 0 | I5: 0 | J5: =H5*I5 -> 0 | K5: =G5+J5 -> 451.15 | M5: =M4+K5-L5 -> 85056.933
A6: 3 | B6: 45811 | E6: 0 | F6: 0 | G6: =E6*F6 -> 0 | H6: 8.66 | I6: 102.16 | J6: =H6*I6 -> 884.7056 | K6: =G6+J6 -> 884.7056 | M6: =M5+K6-L6 -> 85941.639
A7: 4 | B7: 45812 | E7: 150 | F7: 90.23 | G7: =E7*F7 -> 13534.5 | H7: 0 | I7: 0 | J7: =H7*I7 -> 0 | K7: =G7+J7 -> 13534.5 | M7: =M6+K7-L7 -> 99476.139
A8: 5 | B8: 45813 | E8: 66.6 | F8: 90.23 | G8: =E8*F8 -> 6009.318 | H8: 2 | I8: 102.16 | J8: =H8*I8 -> 204.32 | K8: =G8+J8 -> 6213.638 | L8: 102795 | M8: =M7+K8-L8 -> 2894.777
A9: 6 | B9: 45814 | E9: 0 | F9: 0 | G9: =E9*F9 -> 0 | H9: 0 | I9: 0 | J9: =H9*I9 -> 0 | K9: =G9+J9 -> 0 | M9: =M8+K9-L9 -> 2894.777
A10: 7 | B10: 45815 | E10: 0 | F10: 0 | G10: =E10*F10 -> 0 | H10: 0 | I10: 0 | J10: =H10*I10 -> 0 | K10: =G10+J10 -> 0 | M10: =M9+K10-L10 -> 2894.777
A11: 8 | B11: 45816 | E11: 0 | F11: 0 | G11: =E11*F11 -> 0 | H11: 0 | I11: 0 | J11: =H11*I11 -> 0 | K11: =G11+J11 -> 0 | M11: =M10+K11-L11 -> 2894.777
A12: 9 | B12: 45817 | E12: 0 | F12: 0 | G12: =E12*F12 -> 0 | H12: 0 | I12: 0 | J12: =H12*I12 -> 0 | K12: =G12+J12 -> 0 | M12: =M11+K12-L12 -> 2894.777
A13: 10 | B13: 45818 | E13: 0 | F13: 0 | G13: =E13*F13 -> 0 | H13: 7.62 | I13: 102.16 | J13: =H13*I13 -> 778.4592 | K13: =G13+J13 -> 778.4592 | M13: =M12+K13-L13 -> 3673.2362
A14: 11 | B14: 45819 | E14: 34.06 | F14: 90.23 | G14: =E14*F14 -> 3073.2338 | H14: 0 | I14: 0 | J14: =H14*I14 -> 0 | K14: =G14+J14 -> 3073.2338 | M14: =M13+K14-L14 -> 6746.47
A15: 12 | B15: 45820 | E15: 44 | F15: 90.23 | G15: =E15*F15 -> 3970.12 | H15: 0 | I15: 0 | J15: =H15*I15 -> 0 | K15: =G15+J15 -> 3970.12 | M15: =M14+K15-L15 -> 10716.59
A16: 13 | B16: 45821 | E16: 80 | F16: 90.23 | G16: =E16*F16 -> 7218.4 | H16: 15.15 | I16: 102.16 | J16: =H16*I16 -> 1547.724 | K16: =G16+J16 -> 8766.124 | M16: =M15+K16-L16 -> 19482.714
A17: 14 | B17: 45822 | E17: 0 | F17: 0 | G17: =E17*F17 -> 0 | H17: 0 | I17: 0 | J17: =H17*I17 -> 0 | K17: =G17+J17 -> 0 | M17: =M16+K17-L17 -> 19482.714
A18: 15 | B18: 45823 | E18: 0 | F18: 0 | G18: =E18*F18 -> 0 | H18: 0 | I18: 0 | J18: =H18*I18 -> 0 | K18: =G18+J18 -> 0 | M18: =M17+K18-L18 -> 19482.714
A19: 16 | B19: 45824 | E19: 0 | F19: 0 | G19: =E19*F19 -> 0 | H19: 0 | I19: 0 | J19: =H19*I19 -> 0 | K19: =G19+J19 -> 0 | M19: =M18+K19-L19 -> 19482.714
A20: 17 | B20: 45825 | E20: 0 | F20: 0 | G20: =E20*F20 -> 0 | H20: 0 | I20: 0 | J20: =H20*I20 -> 0 | K20: =G20+J20 -> 0 | M20: =M19+K20-L20 -> 19482.714
... A33: 30 | B33: 45838 | E33: 42.7 | F33: 91.23 | G33: =E33*F33 -> 3895.521 | H33: 2 | I33: 103.16 | J33: =H33*I33 -> 206.32 | K33: =G33+J33 -> 4101.841 | M33: =M32+K33-L33 -> 92995.303
A34: 31 | E34: 0 | F34: 0 | G34: =E34*F34 -> 0 | H34: 0 | I34: 0 | J34: =H34*I34 -> 0 | K34: =G34+J34 -> 0 | M34: =M33+K34-L34 -> 92995.303
E35: =SUM(E4:E34) -> 1216.31 | G35: =SUM(G4:G34) -> 110512.23 | H35: =SUM(H4:H34) -> 71.09 | J35: =SUM(J4:J34) -> 7296.7344 | K35: =SUM(K4:K34) -> 117808.97 | L35: =SUM(L4:L31) -> 102795

Sheet Sindagi
A1: G.P.PORWAL
A2: S.No | B2: Date | C2: GRN No | D2: Ind no/Bill No | E2: Diesel (Lts) | F2: Price | G2: Amount | H2: Petrol (Lts) | I2: Price | J2: Amount | K2: Total amount | L2: Amount paid | M2: As on Date | N2: Remarks
A3: Opening Balance | M3: 0
A4: 1 | B4: 45809 | E4: 105 | F4: 91.23 | G4: =E4*F4 -> 9579.15 | H4: 0 | I4: 0 | J4: =H4*I4 -> 0 | K4: =G4+J4 -> 9579.15 | L4: =+K4 -> 9579.15 | M4: =M3+K4-L4 -> 0
A5: 2 | B5: 45810 | E5: 80 | F5: 91.23 | G5: =E5*F5 -> 7298.4 | H5: 0 | I5: 0 | J5: =H5*I5 -> 0 | K5: =G5+J5 -> 7298.4 | L5: =+K5 -> 7298.4 | M5: =M4+K5-L5 -> 0
A6: 3 | B6: 45811 | E6: 0 | F6: 0 | G6: =E6*F6 -> 0 | H6: 0 | I6: 0 | J6: =H6*I6 -> 0 | K6: =G6+J6 -> 0 | L6: =+K6 -> 0 | M6: =M5+K6-L6 -> 0
A7: 4 | B7: 45812 | E7: 199 | F7: 91.23 | G7: =E7*F7 -> 18154.77 | H7: 0 | I7: 0 | J7: =H7*I7 -> 0 | K7: =G7+J7 -> 18154.77 | L7: =+K7 -> 18154.77 | M7: =M6+K7-L7 -> 0
A8: 5 | B8: 45813 | E8: 0 | F8: 0 | G8: =E8*F8 -> 0 | H8: 0 | I8: 0 | J8: =H8*I8 -> 0 | K8: =G8+J8 -> 0 | L8: =+K8 -> 0 | M8: =M7+K8-L8 -> 0
A9: 6 | B9: 45814 | E9: 15 | F9: 91.23 | G9: =E9*F9 -> 1368.45 | H9: 0 | I9: 0 | J9: =H9*I9 -> 0 | K9: =G9+J9 -> 1368.45 | L9: =+K9 -> 1368.45 | M9: =M8+K9-L9 -> 0
A10: 7 | B10: 45815 | E10: 0 | F10: 91.23 | G10: =E10*F10 -> 0 | H10: 0 | I10: 0 | J10: =H10*I10 -> 0 | K10: =G10+J10 -> 0 | L10: =+K10 -> 0 | M10: =M9+K10-L10 -> 0
A11: 8 | B11: 45816 | E11: 0 | F11: 0 | G11: =E11*F11 -> 0 | H11: 0 | I11: 0 | J11: =H11*I11 -> 0 | K11: =G11+J11 -> 0 | L11: =+K11 -> 0 | M11: =M10+K11-L11 -> 0 | P11: =P10+N11-O11 -> 0
A12: 9 | B12: 45817 | E12: 264 | F12: 91.23 | G12: =E12*F12 -> 24084.72 | H12: 0 | I12: 0 | J12: =H12*I12 -> 0 | K12: =G12+J12 -> 24084.72 | L12: =+K12 -> 24084.72 | M12: =M11+K12-L12 -> 0
A13: 10 | B13: 45818 | E13: 96.01 | F13: 91.23 | G13: =E13*F13 -> 8758.9923 | H13: 0 | I13: 0 | J13: =H13*I13 -> 0 | K13: =G13+J13 -> 8758.9923 | L13: =+K13 -> 8758.9923 | M13: =M12+K13-L13 -> 0
A14: 11 | B14: 45819 | E14: 0 | F14: 0 | G14: =E14*F14 -> 0 | H14: 0 | I14: 0 | J14: =H14*I14 -> 0 | K14: =G14+J14 -> 0 | L14: =+K14 -> 0 | M14: =M13+K14-L14 -> 0
A15: 12 | B15: 45820 | E15: 0 | F15: 0 | G15: =E15*F15 -> 0 | H15: 0 | I15: 0 | J15: =H15*I15 -> 0 | K15: =G15+J15 -> 0 | L15: =+K15 -> 0 | M15: =M14+K15-L15 -> 0
A16: 13 | B16: 45821 | E16: 200 | F16: 91.23 | G16: =E16*F16 -> 18246 | H16: 0 | I16: 0 | J16: =H16*I16 -> 0 | K16: =G16+J16 -> 18246 | L16: =+K16 -> 18246 | M16: =M15+K16-L16 -> 0
A17: 14 | B17: 45822 | E17: 181.02 | F17: 91.23 | G17: =E17*F17 -> 16514.455 | H17: 0 | I17: 0 | J17: =H17*I17 -> 0 | K17: =G17+J17 -> 16514.455 | L17: 0 | M17: =M16+K17-L17 -> 16514.455
A18: 15 | B18: 45823 | E18: 0 | F18: 0 | G18: =E18*F18 -> 0 | H18: 0 | I18: 0 | J18: =H18*I18 -> 0 | K18: =G18+J18 -> 0 | L18: =+K18 -> 0 | M18: =M17+K18-L18 -> 16514.455
A19: 16 | B19: 45824 | E19: 15 | F19: 91.23 | G19: =E19*F19 -> 1368.45 | H19: 0 | I19: 0 | J19: =H19*I19 -> 0 | K19: =G19+J19 -> 1368.45 | L19: 0 | M19: =M18+K19-L19 -> 17882.905
A20: 17 | B20: 45825 | E20: 50 | F20: 91.23 | G20: =E20*F20 -> 4561.5 | H20: 0 | I20: 0 | J20: =H20*I20 -> 0 | K20: =G20+J20 -> 4561.5 | L20: 25455 | M20: =M19+K20-L20 -> -3010.5954 | Q20: =22444+3011 -> 25455
A21: 18 | B21: 45826 | E21: 173 | F21: 91.23 | G21: =E21*F21 -> 15782.79 | H21: 4.52 | I21: 110.47 | J21: =H21*I21 -> 499.3244 | K21: =G21+J21 -> 16282.114 | L21: 0 | M21: =M20+K21-L21 -> 13271.519
A22: 19 | B22: 45827 | E22: 100 | F22: 91.23 | G22: =E22*F22 -> 9123 | H22: 0 | I22: 0 | J22: =H22*I22 -> 0 | K22: =G22+J22 -> 9123 | L22: 0 | M22: =M21+K22-L22 -> 22394.519
A23: 20 | B23: 45828 | E23: 0 | F23: 0 | G23: =E23*F23 -> 0 | H23: 0 | I23: 0 | J23: =H23*I23 -> 0 | K23: =G23+J23 -> 0 | L23: =+K23 -> 0 | M23: =M22+K23-L23 -> 22394.519
A24: 21 | B24: 45829 | E24: 76 | F24: 91.23 | G24: =E24*F24 -> 6933.48 | H24: 0 | I24: 0 | J24: =H24*I24 -> 0 | K24: =G24+J24 -> 6933.48 | L24: 0 | M24: =M23+K24-L24 -> 29327.999
A25: 22 | B25: 45830 | E25: 0 | F25: 0 | G25: =E25*F25 -> 0 | H25: 0 | I25: 0 | J25: =H25*I25 -> 0 | K25: =G25+J25 -> 0 | L25: =+K25 -> 0 | M25: =M24+K25-L25 -> 29327.999
A26: 23 | B26: 45831 | E26: 210 | F26: 91.23 | G26: =E26*F26 -> 19158.3 | H26: 0 | I26: 0 | J26: =H26*I26 -> 0 | K26: =G26+J26 -> 19158.3 | L26: 0 | M26: =M25+K26-L26 -> 48486.299
A27: 24 | B27: 45832 | E27: 0 | F27: 0 | G27: =E27*F27 -> 0 | H27: 0 | I27: 0 | J27: =H27*I27 -> 0 | K27: =G27+J27 -> 0 | L27: =+K27 -> 0 | M27: =M26+K27-L27 -> 48486.299
A28: 25 | B28: 45833 | E28: 50 | F28: 91.23 | G28: =E28*F28 -> 4561.5 | H28: 0 | I28: 0 | J28: =H28*I28 -> 0 | K28: =G28+J28 -> 4561.5 | L28: 40000 | M28: =M27+K28-L28 -> 13047.799
A29: 26 | B29: 45834 | E29: 400 | F29: 91.23 | G29: =E29*F29 -> 36492 | H29: 0 | I29: 0 | J29: =H29*I29 -> 0 | K29: =G29+J29 -> 36492 | L29: 0 | M29: =M28+K29-L29 -> 49539.799
A30: 27 | B30: 45835 | E30: 0 | F30: 0 | G30: =E30*F30 -> 0 | H30: 0 | I30: 0 | J30: =H30*I30 -> 0 | K30: =G30+J30 -> 0 | L30: =+K30 -> 0 | M30: =M29+K30-L30 -> 49539.799
A31: 28 | B31: 45836 | E31: 0 | F31: 0 | G31: =E31*F31 -> 0 | H31: 0 | I31: 0 | J31: =H31*I31 -> 0 | K31: =G31+J31 -> 0 | L31: 39685.05 | M31: =M30+K31-L31 -> 9854.749
A32: 29 | B32: 45837 | E32: 0 | F32: 0 | G32: =E32*F32 -> 0 | H32: 0 | I32: 0 | J32: =H32*I32 -> 0 | K32: =G32+J32 -> 0 | L32: 0 | M32: =M31+K32-L32 -> 9854.749
A33: 30 | B33: 45838 | E33: 0 | F33: 0 | G33: =E33*F33 -> 0 | H33: 0 | I33: 0 | J33: =H33*I33 -> 0 | K33: =G33+J33 -> 0 | L33: =+K33 -> 0 | M33: =M32+K33-L33 -> 9854.749
A34: 31 | E34: 0 | F34: 0 | G34: =E34*F34 -> 0 | H34: 0 | I34: 0 | J34: =H34*I34 -> 0 | K34: =G34+J34 -> 0 | L34: =+K34 -> 0 | M34: =M33+K34-L34 -> 9854.749
A35: 34 | E35: 0 | F35: 0 | G35: =E35*F35 -> 0 | H35: 0 | I35: 0 | J35: =H35*I35 -> 0 | K35: =G35+J35 -> 0 | L35: =+K35 -> 0 | M35: =M34+K35-L35 -> 9854.749
A36: 35 | E36: 0 | F36: 0 | G36: =E36*F36 -> 0 | H36: 0 | I36: 0 | J36: =H36*I36 -> 0 | K36: =G36+J36 -> 0 | L36: =+K36 -> 0 | M36: =M35+K36-L36 -> 9854.749
A37: 36 | E37: 0 | F37: 0 | G37: =E37*F37 -> 0 | H37: 0 | I37: 0 | J37: =H37*I37 -> 0 | K37: =G37+J37 -> 0 | L37: =+K37 -> 0 | M37: =M36+K37-L37 -> 9854.749
A38: 37 | E38: 0 | F38: 0 | G38: =E38*F38 -> 0 | H38: 0 | I38: 0 | J38: =H38*I38 -> 0 | K38: =G38+J38 -> 0 | L38: =+K38 -> 0 | M38: =M37+K38-L38 -> 9854.749
A39: 38 | E39: 0 | F39: 0 | G39: =E39*F39 -> 0 | H39: 0 | I39: 0 | J39: =H39*I39 -> 0 | K39: =G39+J39 -> 0 | L39: =+K39 -> 0 | M39: =M38+K39-L39 -> 9854.749
A40: 39 | E40: 0 | F40: 0 | G40: =E40*F40 -> 0 | H40: 0 | I40: 0 | J40: =H40*I40 -> 0 | K40: =G40+J40 -> 0 | L40: =+K40 -> 0 | M40: =M39+K40-L40 -> 9854.749
A41: 40 | E41: 0 | F41: 0 | G41: =E41*F41 -> 0 | H41: 0 | I41: 0 | J41: =H41*I41 -> 0 | K41: =G41+J41 -> 0 | L41: =+K41 -> 0 | M41: =M40+K41-L41 -> 9854.749
A42: 41 | E42: 0 | F42: 0 | G42: =E42*F42 -> 0 | H42: 0 | I42: 0 | J42: =H42*I42 -> 0 | K42: =G42+J42 -> 0 | L42: =+K42 -> 0 | M42: =M41+K42-L42 -> 9854.749
A43: 42 | E43: 0 | F43: 0 | G43: =E43*F43 -> 0 | H43: 0 | I43: 0 | J43: =H43*I43 -> 0 | K43: =G43+J43 -> 0 | L43: =+K43 -> 0 | M43: =M42+K43-L43 -> 9854.749
E44: =SUM(E4:E43) -> 2214.03 | G44: =SUM(G4:G43) -> 201985.96 | H44: =SUM(H4:H43) -> 4.52 | J44: =SUM(J4:J43) -> 499.3244 | K44: =SUM(K4:K43) -> 202485.28 | L44: =SUM(L4:L43) -> 192630.53 | M44: =SUM(M4:M43) -> 501829.51

Sheet Muddebihal
A1: Bhosle Service Station
A2: S.No | B2: Date | C2: GRN No | D2: Ind no/Bill No | E2: Diesel (Lts) | F2: Price | G2: Amount | H2: Petrol (Lts) | I2: Price | J2: Amount | K2: Total amount | L2: Amount paid | M2: As on Date | N2: Remarks
A3: Opening Balance | M3: 0
A4: 1 | E4: 0 | F4: 0 | G4: =E4*F4 -> 0 | H4: 0 | I4: 0 | J4: =H4*I4 -> 0 | K4: =G4+J4 -> 0 | L4: =+K4 -> 0 | M4: =M3+K4-L4 -> 0 | N4: IOCL Card
A5: 2 | E5: 0 | F5: 0 | G5: =E5*F5 -> 0 | H5: 0 | I5: 0 | J5: =H5*I5 -> 0 | K5: =G5+J5 -> 0 | L5: =+K5 -> 0 | M5: =M4+K5-L5 -> 0 | N5: IOCL Card
A6: 3 | E6: 0 | F6: 0 | G6: =E6*F6 -> 0 | H6: 0 | I6: 0 | J6: =H6*I6 -> 0 | K6: =G6+J6 -> 0 | L6: =+K6 -> 0 | M6: =M5+K6-L6 -> 0 | N6: IOCL Card
A7: 4 | B7: 04.06.2025 | E7: 0 | F7: 0 | G7: =E7*F7 -> 0 | H7: 4.83 | I7: 103.39 | J7: =H7*I7 -> 499.3737 | K7: =G7+J7 -> 499.3737 | L7: =+K7 -> 499.3737 | M7: =M6+K7-L7 -> 0 | N7: IOCL Card
A8: 5 | B8: 07.06.2025 | E8: 0 | F8: 0 | G8: =E8*F8 -> 0 | H8: 4.83 | I8: 103.39 | J8: =H8*I8 -> 499.3737 | K8: =G8+J8 -> 499.3737 | L8: =+K8 -> 499.3737 | M8: =M7+K8-L8 -> 0 | N8: IOCL Card
A9: 6 | E9: 0 | F9: 0 | G9: =E9*F9 -> 0 | H9: 0 | I9: 0 | J9: =H9*I9 -> 0 | K9: =G9+J9 -> 0 | L9: =+K9 -> 0 | M9: =M8+K9-L9 -> 0 | N9: IOCL Card
A10: 7 | E10: 0 | F10: 0 | G10: =E10*F10 -> 0 | H10: 0 | I10: 0 | J10: =H10*I10 -> 0 | K10: =G10+J10 -> 0 | L10: =+K10 -> 0 | M10: =M9+K10-L10 -> 0 | N10: IOCL Card
A11: 8 | E11: 0 | F11: 0 | G11: =E11*F11 -> 0 | H11: 0 | I11: 0 | J11: =H11*I11 -> 0 | K11: =G11+J11 -> 0 | L11: =+K11 -> 0 | M11: =M10+K11-L11 -> 0 | N11: IOCL Card
A12: 9 | E12: 0 | F12: 0 | G12: =E12*F12 -> 0 | H12: 0 | I12: 0 | J12: =H12*I12 -> 0 | K12: =G12+J12 -> 0 | L12: =+K12 -> 0 | M12: =M11+K12-L12 -> 0 | N12: IOCL Card
A13: 10 | E13: 0 | F13: 0 | G13: =E13*F13 -> 0 | H13: 0 | I13: 0 | J13: =H13*I13 -> 0 | K13: =G13+J13 -> 0 | L13: =+K13 -> 0 | M13: =M12+K13-L13 -> 0 | N13: IOCL Card
A14: 11 | E14: 0 | F14: 0 | G14: =E14*F14 -> 0 | H14: 0 | I14: 0 | J14: =H14*I14 -> 0 | K14: =G14+J14 -> 0 | L14: =+K14 -> 0 | M14: =M13+K14-L14 -> 0 | N14: IOCL Card
A15: 12 | E15: 0 | F15: 0 | G15: =E15*F15 -> 0 | H15: 0 | I15: 0 | J15: =H15*I15 -> 0 | K15: =G15+J15 -> 0 | L15: =+K15 -> 0 | M15: =M14+K15-L15 -> 0 | N15: IOCL Card
A16: 13 | B16: 13.06.2025 | E16: 0 | F16: 0 | G16: =E16*F16 -> 0 | H16: 4.83 | I16: 103.39 | J16: =H16*I16 -> 499.3737 | K16: =G16+J16 -> 499.3737 | L16: =+K16 -> 499.3737 | M16: =M15+K16-L16 -> 0 | N16: IOCL Card
A17: 14 | B17: 18.06.2025 | E17: 0 | F17: 0 | G17: =E17*F17 -> 0 | H17: 4.83 | I17: 103.39 | J17: =H17*I17 -> 499.3737 | K17: =G17+J17 -> 499.3737 | L17: =+K17 -> 499.3737 | M17: =M16+K17-L17 -> 0 | N17: IOCL Card
A18: 15 | B18: 23.06.2025 | E18: 115 | F18: 91.45 | G18: =E18*F18 -> 10516.75 | H18: 0 | I18: 0 | J18: =H18*I18 -> 0 | K18: =G18+J18 -> 10516.75 | L18: 9602 | M18: =M17+K18-L18 -> 914.75 | N18: IOCL Card
A19: 16 | B19: 25.06.2025 | E19: 87.48 | F19: 91.45 | G19: =E19*F19 -> 8000.046 | H19: 4.83 | I19: 103.39 | J19: =H19*I19 -> 499.3737 | K19: =G19+J19 -> 8499.4197 | L19: 0 | M19: =M18+K19-L19 -> 9414.1697 | N19: IOCL Card
A20: 17 | B20: 28.06.2025 | E20: 0 | F20: 0 | G20: =E20*F20 -> 0 | H20: 4.83 | I20: 103.39 | J20: =H20*I20 -> 499.3737 | K20: =G20+J20 -> 499.3737 | L20: 0 | M20: =M19+K20-L20 -> 9913.5434 | N20: IOCL Card
A21: 18 | B21: 30.6.2025 | E21: 192.46 | F21: 91.45 | G21: =E21*F21 -> 17600.467 | H21: 0 | I21: 0 | J21: =H21*I21 -> 0 | K21: =G21+J21 -> 17600.467 | L21: 0 | M21: =M20+K21-L21 -> 27514.01 | N21: IOCL Card
A22: 19 | E22: 0 | F22: 0 | G22: =E22*F22 -> 0 | H22: 0 | I22: 0 | J22: =H22*I22 -> 0 | K22: =G22+J22 -> 0 | L22: =+K22 -> 0 | M22: =M21+K22-L22 -> 27514.01 | N22: IOCL Card
A23: 20 | E23: 0 | F23: 0 | G23: =E23*F23 -> 0 | H23: 0 | I23: 0 | J23: =H23*I23 -> 0 | K23: =G23+J23 -> 0 | L23: =+K23 -> 0 | M23: =M22+K23-L23 -> 27514.01 | N23: IOCL Card
A24: 21 | E24: 0 | F24: 0 | G24: =E24*F24 -> 0 | H24: 0 | I24: 0 | J24: =H24*I24 -> 0 | K24: =G24+J24 -> 0 | L24: =+K24 -> 0 | M24: =M23+K24-L24 -> 27514.01 | N24: IOCL Card
A25: 22 | E25: 0 | F25: 0 | G25: =E25*F25 -> 0 | H25: 0 | I25: 0 | J25: =H25*I25 -> 0 | K25: =G25+J25 -> 0 | L25: =+K25 -> 0 | M25: =M24+K25-L25 -> 27514.01 | N25: IOCL Card
A26: 23 | E26: 0 | F26: 0 | G26: =E26*F26 -> 0 | H26: 0 | I26: 0 | J26: =H26*I26 -> 0 | K26: =G26+J26 -> 0 | L26: =+K26 -> 0 | M26: =M25+K26-L26 -> 27514.01 | N26: IOCL Card
A27: 24 | E27: 0 | F27: 0 | G27: =E27*F27 -> 0 | H27: 0 | I27: 0 | J27: =H27*I27 -> 0 | K27: =G27+J27 -> 0 | L27: =+K27 -> 0 | M27: =M26+K27-L27 -> 27514.01 | N27: IOCL Card
A28: 25 | E28: 0 | F28: 0 | G28: =E28*F28 -> 0 | H28: 0 | I28: 0 | J28: =H28*I28 -> 0 | K28: =G28+J28 -> 0 | L28: =+K28 -> 0 | M28: =M27+K28-L28 -> 27514.01 | N28: IOCL Card
A29: 26 | E29: 0 | F29: 0 | G29: =E29*F29 -> 0 | H29: 0 | I29: 0 | J29: =H29*I29 -> 0 | K29: =G29+J29 -> 0 | L29: =+K29 -> 0 | M29: =M28+K29-L29 -> 27514.01 | N29: IOCL Card
A30: 27 | E30: 0 | F30: 0 | G30: =E30*F30 -> 0 | H30: 0 | I30: 0 | J30: =H30*I30 -> 0 | K30: =G30+J30 -> 0 | L30: =+K30 -> 0 | M30: =M29+K30-L30 -> 27514.01 | N30: IOCL Card
A31: 28 | E31: 0 | F31: 0 | G31: =E31*F31 -> 0 | H31: 0 | I31: 0 | J31: =H31*I31 -> 0 | K31: =G31+J31 -> 0 | L31: =+K31 -> 0 | M31: =M30+K31-L31 -> 27514.01 | N31: IOCL Card
A32: 29 | E32: 0 | F32: 0 | G32: =E32*F32 -> 0 | H32: 0 | I32: 0 | J32: =H32*I32 -> 0 | K32: =G32+J32 -> 0 | L32: =+K32 -> 0 | M32: =M31+K32-L32 -> 27514.01 | N32: IOCL Card
A33: 30 | E33: 0 | F33: 0 | G33: =E33*F33 -> 0 | H33: 0 | I33: 0 | J33: =H33*I33 -> 0 | K33: =G33+J33 -> 0 | L33: =+K33 -> 0 | M33: =M32+K33-L33 -> 27514.01 | N33: IOCL Card
... A36: 33 | E36: 0 | F36: 0 | G36: =E36*F36 -> 0 | H36: 0 | I36: 0 | J36: =H36*I36 -> 0 | K36: =G36+J36 -> 0 | L36: =+K36 -> 0 | M36: =M35+K36-L36 -> 27514.01 | N36: IOCL Card
A37: 34 | E37: 0 | F37: 0 | G37: =E37*F37 -> 0 | H37: 0 | I37: 0 | J37: =H37*I37 -> 0 | K37: =G37+J37 -> 0 | L37: =+K37 -> 0 | M37: =M36+K37-L37 -> 27514.01
A38: 35 | E38: 0 | F38: 0 | G38: =E38*F38 -> 0 | H38: 0 | I38: 0 | J38: =H38*I38 -> 0 | K38: =G38+J38 -> 0 | L38: =+K38 -> 0 | M38: =M37+K38-L38 -> 27514.01
A39: 36 | E39: 0 | F39: 0 | G39: =E39*F39 -> 0 | H39: 0 | I39: 0 | J39: =H39*I39 -> 0 | K39: =G39+J39 -> 0 | L39: =+K39 -> 0 | M39: =M38+K39-L39 -> 27514.01
A40: 37 | E40: 0 | F40: 0 | G40: =E40*F40 -> 0 | H40: 0 | I40: 0 | J40: =H40*I40 -> 0 | K40: =G40+J40 -> 0 | L40: =+K40 -> 0 | M40: =M39+K40-L40 -> 27514.01
A41: 38 | E41: 0 | F41: 0 | G41: =E41*F41 -> 0 | H41: 0 | I41: 0 | J41: =H41*I41 -> 0 | K41: =G41+J41 -> 0 | L41: =+K41 -> 0 | M41: =M40+K41-L41 -> 27514.01
A42: 39 | E42: 0 | F42: 0 | G42: =E42*F42 -> 0 | H42: 0 | I42: 0 | J42: =H42*I42 -> 0 | K42: =G42+J42 -> 0 | L42: =+K42 -> 0 | M42: =M41+K42-L42 -> 27514.01
A43: 40 | E43: 0 | F43: 0 | G43: =E43*F43 -> 0 | J43: =H43*I43 -> 0 | K43: =G43+J43 -> 0 | L43: =+K43 -> 0 | M43: =M42+K43-L43 -> 27514.01
A44: 41 | E44: 0 | F44: 0 | G44: =E44*F44 -> 0 | J44: =H44*I44 -> 0 | K44: =G44+J44 -> 0 | L44: =+K44 -> 0 | M44: =M43+K44-L44 -> 27514.01
A45: 42 | E45: 0 | F45: 0 | G45: =E45*F45 -> 0 | J45: =H45*I45 -> 0 | K45: =G45+J45 -> 0 | L45: =+K45 -> 0 | M45: =M44+K45-L45 -> 27514.01
E46: =SUM(E4:E45) -> 394.94 | G46: =SUM(G4:G45) -> 36117.263 | H46: =SUM(H4:H45) -> 28.98 | J46: =SUM(J4:J45) -> 2996.2422 | K46: =SUM(K4:K45) -> 39113.505 | L46: =SUM(L4:L45) -> 11599.495

Sheet Alemela
A1: Shiddeshwar Petroleums
A2: S.No | B2: Date | C2: GRN No | D2: Ind no/Bill No | E2: Diesel (Lts) | F2: Price | G2: Amount | H2: Petrol (Lts) | I2: Price | J2: Amount | K2: Total amount | L2: Amount paid | M2: As on Date | N2: Remarks
A3: Opening Balance | M3: 0
A4: 1 | B4: 02.06.2025 | E4: 5 | F4: 91.33 | G4: =E4*F4 -> 456.65 | H4: 0 | I4: 0 | J4: =H4*I4 -> 0 | K4: =G4+J4 -> 456.65 | L4: =+K4 -> 456.65 | M4: =M3+K4-L4 -> 0 | N4: IOCL Card
A5: 2 | B5: 04.06.2025 | E5: 219.71 | F5: 91.33 | G5: =E5*F5 -> 20066.114 | H5: 5 | I5: 103.26 | J5: =H5*I5 -> 516.3 | K5: =G5+J5 -> 20582.414 | L5: =+K5 -> 20582.414 | N5: IOCL Card
A6: 3 | B6: 08.06.2025 | E6: 0 | F6: 0 | G6: =E6*F6 -> 0 | H6: 5 | I6: 103.26 | J6: =H6*I6 -> 516.3 | K6: =G6+J6 -> 516.3 | L6: =+K6 -> 516.3 | M6: =M5+K6-L6 -> 0 | N6: IOCL Card
A7: 4 | B7: 09.06.2023 | E7: 200 | F7: 91.33 | G7: =E7*F7 -> 18266 | H7: 4.84 | I7: 103.26 | J7: =H7*I7 -> 499.7784 | K7: =G7+J7 -> 18765.778 | L7: =+K7 -> 18765.778 | M7: =M6+K7-L7 -> 0 | N7: IOCL Card
A8: 5 | B8: 12.06.2025 | E8: 0 | F8: 0 | G8: =E8*F8 -> 0 | H8: 6 | I8: 103.26 | J8: =H8*I8 -> 619.56 | K8: =G8+J8 -> 619.56 | M8: =M7+K8-L8 -> 619.56 | N8: IOCL Card
A9: 6 | B9: 15.06.2025 | E9: 44.87 | F9: 91.33 | G9: =E9*F9 -> 4097.9771 | H9: 0 | I9: 0 | J9: =H9*I9 -> 0 | K9: =G9+J9 -> 4097.9771 | M9: =M8+K9-L9 -> 4717.5371 | N9: IOCL Card
A10: 7 | B10: 19.06.2025 | E10: 70 | F10: 91.33 | G10: =E10*F10 -> 6393.1 | H10: 6 | I10: 103.26 | J10: =H10*I10 -> 619.56 | K10: =G10+J10 -> 7012.66 | L10: 0 | M10: =M9+K10-L10 -> 11730.197 | N10: IOCL Card
A11: 8 | B11: 20.06.2025 | E11: 50 | F11: 91.33 | G11: =E11*F11 -> 4566.5 | H11: 0 | I11: 0 | J11: =H11*I11 -> 0 | K11: =G11+J11 -> 4566.5 | L11: 0 | M11: =M10+K11-L11 -> 16296.697 | N11: IOCL Card
A12: 9 | B12: 25.06.2025 | E12: 127.19 | F12: 91.33 | G12: =E12*F12 -> 11616.263 | H12: 0 | I12: 0 | J12: =H12*I12 -> 0 | K12: =G12+J12 -> 11616.263 | L12: 0 | M12: =M11+K12-L12 -> 27912.96 | N12: IOCL Card
A13: 10 | B13: 26.06.2025 | E13: 170 | F13: 91.33 | G13: =E13*F13 -> 15526.1 | H13: 0 | I13: 0 | J13: =H13*I13 -> 0 | K13: =G13+J13 -> 15526.1 | L13: 0 | M13: =M12+K13-L13 -> 43439.06 | N13: IOCL Card
A14: 11 | B14: 27.06.2025 | E14: 0 | F14: 0 | G14: =E14*F14 -> 0 | H14: 6 | I14: 103.26 | J14: =H14*I14 -> 619.56 | K14: =G14+J14 -> 619.56 | L14: 0 | M14: =M13+K14-L14 -> 44058.62 | N14: IOCL Card
A15: 12 | B15: 28.06.2025 | E15: 144.37 | F15: 91.33 | G15: =E15*F15 -> 13185.312 | H15: 0 | I15: 0 | J15: =H15*I15 -> 0 | K15: =G15+J15 -> 13185.312 | L15: 0 | M15: =M14+K15-L15 -> 57243.932 | N15: IOCL Card
A16: 13 | B16: 29.06.2025 | E16: 100 | F16: 91.33 | G16: =E16*F16 -> 9133 | H16: 6 | I16: 103.26 | J16: =H16*I16 -> 619.56 | K16: =G16+J16 -> 9752.56 | L16: 0 | M16: =M15+K16-L16 -> 66996.492 | N16: IOCL Card
A17: 14 | B17: 30.06.2025 | E17: 85 | F17: 91.33 | G17: =E17*F17 -> 7763.05 | H17: 0 | I17: 0 | J17: =H17*I17 -> 0 | K17: =G17+J17 -> 7763.05 | L17: 0 | M17: =M16+K17-L17 -> 74759.542 | N17: IOCL Card
A18: 15 | E18: 0 | F18: 0 | G18: =E18*F18 -> 0 | H18: 0 | I18: 0 | J18: =H18*I18 -> 0 | K18: =G18+J18 -> 0 | L18: =+K18 -> 0 | M18: =M17+K18-L18 -> 74759.542 | N18: IOCL Card
A19: 16 | E19: 0 | F19: 0 | G19: =E19*F19 -> 0 | H19: 0 | I19: 0 | J19: =H19*I19 -> 0 | K19: =G19+J19 -> 0 | L19: =+K19 -> 0 | M19: =M18+K19-L19 -> 74759.542 | N19: IOCL Card
A20: 17 | E20: 0 | F20: 0 | G20: =E20*F20 -> 0 | H20: 0 | I20: 0 | J20: =H20*I20 -> 0 | K20: =G20+J20 -> 0 | L20: =+K20 -> 0 | M20: =M19+K20-L20 -> 74759.542 | N20: IOCL Card
A21: 18 | E21: 0 | F21: 0 | G21: =E21*F21 -> 0 | H21: 0 | I21: 0 | J21: =H21*I21 -> 0 | K21: =G21+J21 -> 0 | L21: =+K21 -> 0 | M21: =M20+K21-L21 -> 74759.542 | N21: IOCL Card
A22: 19 | E22: 0 | F22: 0 | G22: =E22*F22 -> 0 | H22: 0 | I22: 0 | J22: =H22*I22 -> 0 | K22: =G22+J22 -> 0 | L22: =+K22 -> 0 | M22: =M21+K22-L22 -> 74759.542 | N22: IOCL Card
A23: 20 | E23: 0 | F23: 0 | G23: =E23*F23 -> 0 | H23: 0 | I23: 0 | J23: =H23*I23 -> 0 | K23: =G23+J23 -> 0 | L23: =+K23 -> 0 | M23: =M22+K23-L23 -> 74759.542
A24: 21 | E24: 0 | F24: 0 | G24: =E24*F24 -> 0 | H24: 0 | I24: 0 | J24: =H24*I24 -> 0 | K24: =G24+J24 -> 0 | L24: =+K24 -> 0 | M24: =M23+K24-L24 -> 74759.542
A25: 22 | E25: 0 | F25: 0 | G25: =E25*F25 -> 0 | H25: 0 | I25: 0 | J25: =H25*I25 -> 0 | K25: =G25+J25 -> 0 | L25: =+K25 -> 0 | M25: =M24+K25-L25 -> 74759.542
A26: 23 | E26: 0 | F26: 0 | G26: =E26*F26 -> 0 | H26: 0 | I26: 0 | J26: =H26*I26 -> 0 | K26: =G26+J26 -> 0 | L26: =+K26 -> 0 | M26: =M25+K26-L26 -> 74759.542
A27: 24 | E27: 0 | F27: 0 | G27: =E27*F27 -> 0 | H27: 0 | I27: 0 | J27: =H27*I27 -> 0 | K27: =G27+J27 -> 0 | L27: =+K27 -> 0 | M27: =M26+K27-L27 -> 74759.542
A28: 25 | E28: 0 | F28: 0 | G28: =E28*F28 -> 0 | H28: 0 | I28: 0 | J28: =H28*I28 -> 0 | K28: =G28+J28 -> 0 | L28: =+K28 -> 0 | M28: =M27+K28-L28 -> 74759.542
A29: 26 | E29: 0 | F29: 0 | G29: =E29*F29 -> 0 | H29: 0 | I29: 0 | J29: =H29*I29 -> 0 | K29: =G29+J29 -> 0 | L29: =+K29 -> 0 | M29: =M28+K29-L29 -> 74759.542
A30: 27 | E30: 0 | F30: 0 | G30: =E30*F30 -> 0 | H30: 0 | I30: 0 | J30: =H30*I30 -> 0 | K30: =G30+J30 -> 0 | L30: =+K30 -> 0 | M30: =M29+K30-L30 -> 74759.542
A31: 28 | E31: 0 | F31: 0 | G31: =E31*F31 -> 0 | H31: 0 | I31: 0 | J31: =H31*I31 -> 0 | K31: =G31+J31 -> 0 | L31: =+K31 -> 0 | M31: =M30+K31-L31 -> 74759.542
A32: 29 | E32: 0 | F32: 0 | G32: =E32*F32 -> 0 | H32: 0 | I32: 0 | J32: =H32*I32 -> 0 | K32: =G32+J32 -> 0 | L32: =+K32 -> 0 | M32: =M31+K32-L32 -> 74759.542
A33: 30 | E33: 0 | F33: 0 | G33: =E33*F33 -> 0 | H33: 0 | I33: 0 | J33: =H33*I33 -> 0 | K33: =G33+J33 -> 0 | L33: =+K33 -> 0 | M33: =M32+K33-L33 -> 74759.542
A34: 31 | E34: 0 | F34: 0 | G34: =E34*F34 -> 0 | H34: 0 | I34: 0 | J34: =H34*I34 -> 0 | K34: =G34+J34 -> 0 | L34: =+K34 -> 0 | M34: =M33+K34-L34 -> 74759.542
... A41: 41 | E41: 0 | F41: 0 | G41: =E41*F41 -> 0 | H41: 0 | I41: 0 | J41: =H41*I41 -> 0 | K41: =G41+J41 -> 0 | L41: =+K41 -> 0 | M41: =M40+K41-L41 -> 74759.542
A42: 42 | E42: 0 | F42: 0 | G42: =E42*F42 -> 0 | J42: =H42*I42 -> 0 | K42: =G42+J42 -> 0 | L42: =+K42 -> 0 | M42: =M41+K42-L42 -> 74759.542
E43: =SUM(E4:E42) -> 1216.14 | G43: =SUM(G4:G42) -> 111070.07 | H43: =SUM(H4:H42) -> 38.84 | J43: =SUM(J4:J42) -> 4010.6184 | K43: =SUM(K4:K42) -> 115080.68 | L43: =SUM(L4:L42) -> 40321.143
L46: 41648.541
L47: =L43+L46 -> 81969.684

Sheet Nalatwad
A1: Shri Pawad Basaweshwar Petroleums
A2: S.No | B2: Date | C2: GRN No | D2: Ind no/Bill No | E2: Diesel (Lts) | F2: Price | G2: Amount | H2: Petrol (Lts) | I2: Price | J2: Amount | K2: Total amount | L2: Amount paid | M2: As on Date | N2: Remarks
A3: Opening Balance | M3: 20248.57
A4: 1 | B4: 45809 | E4: 0 | F4: 0 | G4: =E4*F4 -> 0 | H4: 0 | I4: 0 | J4: =H4*I4 -> 0 | K4: =G4+J4 -> 0 | L4: =+K4 -> 0 | M4: =M3+K4-L4 -> 20248.57 | N4: IOCL Card
A5: 2 | B5: 45810 | E5: 0 | F5: 0 | G5: =E5*F5 -> 0 | H5: 4.83 | I5: 103.57 | J5: =H5*I5 -> 500.2431 | K5: =G5+J5 -> 500.2431 | L5: 0 | M5: =M4+K5-L5 -> 20748.813 | N5: IOCL Card
A6: 3 | B6: 45811 | E6: 10 | F6: 91.62 | G6: =E6*F6 -> 916.2 | H6: 0 | I6: 0 | J6: =H6*I6 -> 0 | K6: =G6+J6 -> 916.2 | L6: 0 | M6: =M5+K6-L6 -> 21665.013 | N6: IOCL Card
A7: 4 | B7: 45812 | E7: 134.18 | F7: 91.62 | G7: =E7*F7 -> 12293.572 | H7: 0 | I7: 0 | J7: =H7*I7 -> 0 | K7: =G7+J7 -> 12293.572 | L7: 0 | M7: =M6+K7-L7 -> 33958.585 | N7: IOCL Card
A8: 5 | B8: 45813 | E8: 0 | F8: 0 | G8: =E8*F8 -> 0 | H8: 9.66 | I8: 103.57 | J8: =H8*I8 -> 1000.4862 | K8: =G8+J8 -> 1000.4862 | L8: 0 | M8: =M7+K8-L8 -> 34959.071 | N8: IOCL Card
A9: 6 | B9: 45814 | E9: 0 | F9: 0 | G9: =E9*F9 -> 0 | H9: 9.65 | I9: 103.57 | J9: =H9*I9 -> 999.4505 | K9: =G9+J9 -> 999.4505 | L9: 33950.7 | M9: =M8+K9-L9 -> 2007.8214 | N9: IOCL Card
A10: 7 | B10: 45815 | E10: 0 | F10: 0 | G10: =E10*F10 -> 0 | H10: 0 | I10: 0 | J10: =H10*I10 -> 0 | K10: =G10+J10 -> 0 | L10: =+K10 -> 0 | M10: =M9+K10-L10 -> 2007.8214 | N10: IOCL Card
A11: 8 | B11: 45816 | E11: 0 | F11: 0 | G11: =E11*F11 -> 0 | H11: 4.83 | I11: 103.57 | J11: =H11*I11 -> 500.2431 | K11: =G11+J11 -> 500.2431 | L11: 0 | M11: =M10+K11-L11 -> 2508.0645 | N11: IOCL Card
A12: 9 | B12: 45817 | E12: 100.55 | F12: 91.62 | G12: =E12*F12 -> 9212.391 | H12: 4.83 | I12: 103.57 | J12: =H12*I12 -> 500.2431 | K12: =G12+J12 -> 9712.6341 | L12: 0 | M12: =M11+K12-L12 -> 12220.699 | N12: IOCL Card
A13: 10 | B13: 45818 | E13: 0 | F13: 0 | G13: =E13*F13 -> 0 | H13: 0 | I13: 0 | J13: =H13*I13 -> 0 | K13: =G13+J13 -> 0 | L13: =+K13 -> 0 | M13: =M12+K13-L13 -> 12220.699 | N13: IOCL Card
A14: 11 | B14: 45819 | E14: 0 | F14: 0 | G14: =E14*F14 -> 0 | H14: 0 | I14: 0 | J14: =H14*I14 -> 0 | K14: =G14+J14 -> 0 | L14: =+K14 -> 0 | M14: =M13+K14-L14 -> 12220.699 | N14: IOCL Card
A15: 12 | B15: 45820 | E15: 120 | F15: 91.62 | G15: =E15*F15 -> 10994.4 | H15: 0 | I15: 0 | J15: =H15*I15 -> 0 | K15: =G15+J15 -> 10994.4 | L15: 0 | M15: =M14+K15-L15 -> 23215.099 | N15: IOCL Card
A16: 13 | B16: 45821 | E16: 100 | F16: 91.62 | G16: =E16*F16 -> 9162 | H16: 0 | I16: 0 | J16: =H16*I16 -> 0 | K16: =G16+J16 -> 9162 | L16: 0 | M16: =M15+K16-L16 -> 32377.099 | N16: IOCL Card
A17: 14 | B17: 45822 | E17: 0 | F17: 0 | G17: =E17*F17 -> 0 | H17: 0 | I17: 0 | J17: =H17*I17 -> 0 | K17: =G17+J17 -> 0 | L17: =+K17 -> 0 | M17: =M16+K17-L17 -> 32377.099 | N17: IOCL Card
A18: 15 | B18: 45823 | E18: 0 | F18: 0 | G18: =E18*F18 -> 0 | H18: 0 | I18: 0 | J18: =H18*I18 -> 0 | K18: =G18+J18 -> 0 | L18: =+K18 -> 0 | M18: =M17+K18-L18 -> 32377.099 | N18: IOCL Card
A19: 16 | B19: 45824 | E19: 0 | F19: 0 | G19: =E19*F19 -> 0 | H19: 4.83 | I19: 103.57 | J19: =H19*I19 -> 500.2431 | K19: =G19+J19 -> 500.2431 | L19: 0 | M19: =M18+K19-L19 -> 32877.342 | N19: IOCL Card
A20: 17 | B20: 45825 | E20: 92 | F20: 91.62 | G20: =E20*F20 -> 8429.04 | H20: 4.83 | I20: 103.57 | J20: =H20*I20 -> 500.2431 | K20: =G20+J20 -> 8929.2831 | L20: 0 | M20: =M19+K20-L20 -> 41806.625 | N20: IOCL Card
A21: 18 | B21: 45826 | E21: 41.29 | F21: 91.62 | G21: =E21*F21 -> 3782.9898 | H21: 0 | I21: 0 | J21: =H21*I21 -> 0 | K21: =G21+J21 -> 3782.9898 | L21: 0 | M21: =M20+K21-L21 -> 45589.615 | N21: IOCL Card
A22: 19 | B22: 45827 | E22: 0 | F22: 0 | G22: =E22*F22 -> 0 | H22: 0 | I22: 0 | J22: =H22*I22 -> 0 | K22: =G22+J22 -> 0 | L22: =+K22 -> 0 | M22: =M21+K22-L22 -> 45589.615 | N22: IOCL Card
A23: 20 | B23: 45828 | E23: 0 | F23: 0 | G23: =E23*F23 -> 0 | H23: 0 | I23: 0 | J23: =H23*I23 -> 0 | K23: =G23+J23 -> 0 | L23: =+K23 -> 0 | M23: =M22+K23-L23 -> 45589.615
A24: 21 | B24: 45829 | E24: 0 | F24: 0 | G24: =E24*F24 -> 0 | H24: 0 | I24: 0 | J24: =H24*I24 -> 0 | K24: =G24+J24 -> 0 | L24: =+K24 -> 0 | M24: =M23+K24-L24 -> 45589.615
A25: 22 | B25: 45830 | E25: 0 | F25: 0 | G25: =E25*F25 -> 0 | H25: 0 | I25: 0 | J25: =H25*I25 -> 0 | K25: =G25+J25 -> 0 | L25: =+K25 -> 0 | M25: =M24+K25-L25 -> 45589.615
A26: 23 | B26: 45831 | E26: 80 | F26: 91.62 | G26: =E26*F26 -> 7329.6 | H26: 0 | I26: 0 | J26: =H26*I26 -> 0 | K26: =G26+J26 -> 7329.6 | L26: 0 | M26: =M25+K26-L26 -> 52919.215
A27: 24 | B27: 45832 | E27: 0 | F27: 0 | G27: =E27*F27 -> 0 | H27: 0 | I27: 0 | J27: =H27*I27 -> 0 | K27: =G27+J27 -> 0 | L27: 25000 | M27: =M26+K27-L27 -> 27919.215
A28: 25 | B28: 45833 | E28: 42.81 | F28: 91.62 | G28: =E28*F28 -> 3922.2522 | H28: 0 | I28: 0 | J28: =H28*I28 -> 0 | K28: =G28+J28 -> 3922.2522 | L28: 0 | M28: =M27+K28-L28 -> 31841.467
A29: 26 | B29: 45834 | E29: 0 | F29: 0 | G29: =E29*F29 -> 0 | H29: 0 | I29: 0 | J29: =H29*I29 -> 0 | K29: =G29+J29 -> 0 | L29: =+K29 -> 0 | M29: =M28+K29-L29 -> 31841.467
A30: 27 | B30: 45835 | E30: 0 | F30: 0 | G30: =E30*F30 -> 0 | H30: 0 | I30: 0 | J30: =H30*I30 -> 0 | K30: =G30+J30 -> 0 | L30: =+K30 -> 0 | M30: =M29+K30-L30 -> 31841.467
A31: 28 | B31: 45836 | E31: 41 | F31: 91.62 | G31: =E31*F31 -> 3756.42 | H31: 4.83 | I31: 103.57 | J31: =H31*I31 -> 500.2431 | K31: =G31+J31 -> 4256.6631 | L31: 0 | M31: =M30+K31-L31 -> 36098.13
A32: 29 | B32: 45837 | E32: 0 | F32: 0 | G32: =E32*F32 -> 0 | H32: 0 | I32: 0 | J32: =H32*I32 -> 0 | K32: =G32+J32 -> 0 | L32: =+K32 -> 0 | M32: =M31+K32-L32 -> 36098.13
A33: 30 | B33: 45838 | E33: 0 | F33: 0 | G33: =E33*F33 -> 0 | H33: 4.83 | I33: 103.57 | J33: =H33*I33 -> 500.2431 | K33: =G33+J33 -> 500.2431 | L33: 0 | M33: =M32+K33-L33 -> 36598.373
A34: 31 | E34: 0 | F34: 0 | G34: =E34*F34 -> 0 | H34: 0 | I34: 0 | J34: =H34*I34 -> 0 | K34: =G34+J34 -> 0 | L34: 0 | M34: =M33+K34-L34 -> 36598.373
A35: 35 | E35: 0 | F35: 0 | G35: =E35*F35 -> 0 | H35: 0 | I35: 0 | J35: =H35*I35 -> 0 | K35: =G35+J35 -> 0 | L35: =+K35 -> 0 | M35: =M34+K35-L35 -> 36598.373
A36: 36 | E36: 0 | F36: 0 | G36: =E36*F36 -> 0 | H36: 0 | I36: 0 | J36: =H36*I36 -> 0 | K36: =G36+J36 -> 0 | L36: =+K36 -> 0 | M36: =M35+K36-L36 -> 36598.373
A37: 37 | E37: 0 | F37: 0 | G37: =E37*F37 -> 0 | H37: 0 | I37: 0 | J37: =H37*I37 -> 0 | K37: =G37+J37 -> 0 | L37: =+K37 -> 0 | M37: =M36+K37-L37 -> 36598.373
A38: 38 | E38: 0 | F38: 0 | G38: =E38*F38 -> 0 | H38: 0 | I38: 0 | J38: =H38*I38 -> 0 | K38: =G38+J38 -> 0 | L38: =+K38 -> 0 | M38: =M37+K38-L38 -> 36598.373
A39: 39 | E39: 0 | F39: 0 | G39: =E39*F39 -> 0 | H39: 0 | I39: 0 | J39: =H39*I39 -> 0 | K39: =G39+J39 -> 0 | L39: =+K39 -> 0 | M39: =M38+K39-L39 -> 36598.373
A40: 40 | E40: 0 | F40: 0 | G40: =E40*F40 -> 0 | H40: 0 | I40: 0 | J40: =H40*I40 -> 0 | K40: =G40+J40 -> 0 | L40: =+K40 -> 0 | M40: 0
A41: 41 | E41: 0 | F41: 0 | G41: =E41*F41 -> 0 | H41: 0 | I41: 0 | J41: =H41*I41 -> 0 | K41: =G41+J41 -> 0 | L41: =+K41 -> 0 | M41: 0
A42: 42 | E42: 0 | F42: 0 | G42: =E42*F42 -> 0 | J42: =H42*I42 -> 0 | K42: =G42+J42 -> 0 | L42: =+K42 -> 0 | M42: 0
E43: =SUM(E4:E42) -> 761.83 | G43: =SUM(G4:G42) -> 69798.865 | H43: =SUM(H4:H42) -> 53.12 | J43: =SUM(J4:J42) -> 5501.6384 | K43: =SUM(K4:K42) -> 75300.503 | L43: =SUM(L4:L42) -> 58950.7
Q47: 9542400867

Sheet Khanapur
A1: J K Makavi
A2: S.No | B2: Date | C2: GRN No | D2: Ind No/Bill No | E2: Diesel (Lts) | F2: Price | G2: Amount | H2: Petrol (Lts) | I2: Price | J2: Amount | K2: Total amount | L2: Date of payment | M2: Amount paid | N2: Remarks
D3: Opening Balance | K3: 0 | M3: =+K3 -> 0
A4: 1 | B4: 45809 | E4: 0 | F4: 0 | G4: =F4*E4 -> 0 | H4: 0 | I4: 0 | J4: =H4*I4 -> 0 | K4: =G4+J4 -> 0 | L4: =+K4 -> 0 | M4: =+L4 -> 0
A5: 2 | B5: 45810 | E5: 0 | F5: 0 | G5: =F5*E5 -> 0 | H5: 0 | I5: 0 | J5: =H5*I5 -> 0 | K5: =G5+J5 -> 0 | L5: =+K5 -> 0 | M5: =+L5 -> 0
A6: 3 | B6: 45811 | E6: 0 | F6: 0 | G6: =F6*E6 -> 0 | H6: 0 | I6: 0 | J6: =H6*I6 -> 0 | K6: =G6+J6 -> 0 | L6: =+K6 -> 0 | M6: 0
A7: 4 | B7: 45812 | E7: 0 | F7: 0 | G7: =F7*E7 -> 0 | H7: 0 | I7: 0 | J7: =H7*I7 -> 0 | K7: =G7+J7 -> 0 | L7: =+K7 -> 0 | M7: =+L7 -> 0
A8: 5 | B8: 45813 | E8: 0 | F8: 0 | G8: =F8*E8 -> 0 | H8: 0 | I8: 0 | J8: =H8*I8 -> 0 | K8: =G8+J8 -> 0 | L8: =+K8 -> 0 | M8: =+L8 -> 0
A9: 6 | B9: 45814 | E9: 20 | F9: 90.88 | G9: =F9*E9 -> 1817.6 | H9: 4.86 | I9: 102.77 | J9: =H9*I9 -> 499.4622 | K9: =G9+J9 -> 2317.0622 | L9: =+K9 -> 2317.0622 | M9: =+L9 -> 2317.0622
A10: 7 | B10: 45815 | E10: 20 | F10: 90.88 | G10: =F10*E10 -> 1817.6 | H10: 0 | I10: 0 | J10: =H10*I10 -> 0 | K10: =G10+J10 -> 1817.6 | L10: =+K10 -> 1817.6 | M10: =+L10 -> 1817.6
A11: 8 | B11: 45816 | E11: 20 | F11: 90.88 | G11: =F11*E11 -> 1817.6 | H11: 0 | I11: 0 | J11: =H11*I11 -> 0 | K11: =G11+J11 -> 1817.6 | L11: =+K11 -> 1817.6 | M11: =+L11 -> 1817.6
A12: 9 | B12: 45817 | E12: 40 | F12: 90.88 | G12: =F12*E12 -> 3635.2 | H12: 0 | I12: 0 | J12: =H12*I12 -> 0 | K12: =G12+J12 -> 3635.2 | L12: =+K12 -> 3635.2 | M12: =+L12 -> 3635.2 | P12: =4999.17+50339.51 -> 55338.68
A13: 10 | B13: 45818 | E13: 40 | F13: 90.88 | G13: =F13*E13 -> 3635.2 | H13: 0 | I13: 0 | J13: =H13*I13 -> 0 | K13: =G13+J13 -> 3635.2 | L13: =+K13 -> 3635.2 | M13: =+L13 -> 3635.2
A14: 11 | B14: 45819 | E14: 20 | F14: 90.88 | G14: =F14*E14 -> 1817.6 | H14: 0 | I14: 0 | J14: =H14*I14 -> 0 | K14: =G14+J14 -> 1817.6 | L14: =+K14 -> 1817.6 | M14: =+L14 -> 1817.6
A15: 12 | B15: 45820 | E15: 0 | F15: 0 | G15: =F15*E15 -> 0 | H15: 0 | I15: 0 | J15: =H15*I15 -> 0 | K15: =G15+J15 -> 0 | L15: =+K15 -> 0 | M15: =+L15 -> 0
A16: 13 | B16: 45821 | E16: 0 | F16: 0 | G16: =F16*E16 -> 0 | H16: 0 | I16: 0 | J16: =H16*I16 -> 0 | K16: =G16+J16 -> 0 | L16: =+K16 -> 0 | M16: =+L16 -> 0
A17: 14 | B17: 45822 | E17: 31 | F17: 90.88 | G17: =F17*E17 -> 2817.28 | H17: 0 | I17: 0 | J17: =H17*I17 -> 0 | K17: =G17+J17 -> 2817.28 | L17: =+K17 -> 2817.28 | M17: =+L17 -> 2817.28
A18: 15 | B18: 45823 | E18: 0 | F18: 0 | G18: =F18*E18 -> 0 | H18: 0 | I18: 0 | J18: =H18*I18 -> 0 | K18: =G18+J18 -> 0 | L18: =+K18 -> 0 | M18: =+L18 -> 0
A19: 16 | B19: 45824 | E19: 0 | F19: 0 | G19: =F19*E19 -> 0 | H19: 0 | I19: 0 | J19: =H19*I19 -> 0 | K19: =G19+J19 -> 0 | L19: =+K19 -> 0 | M19: =+L19 -> 0
A20: 17 | B20: 45825 | E20: 0 | F20: 0 | G20: =F20*E20 -> 0 | H20: 0 | I20: 0 | J20: =H20*I20 -> 0 | K20: =G20+J20 -> 0 | L20: =+K20 -> 0 | M20: =+L20 -> 0
A21: 18 | B21: 45826 | E21: 0 | F21: 0 | G21: =F21*E21 -> 0 | H21: 0 | I21: 0 | J21: =H21*I21 -> 0 | K21: =G21+J21 -> 0 | L21: =+K21 -> 0 | M21: =+L21 -> 0
A22: 19 | B22: 45827 | E22: 0 | F22: 0 | G22: =F22*E22 -> 0 | H22: 0 | I22: 0 | J22: =H22*I22 -> 0 | K22: =G22+J22 -> 0 | L22: =+K22 -> 0 | M22: =+L22 -> 0
A23: 20 | B23: 45828 | E23: 20 | F23: 90.88 | G23: =F23*E23 -> 1817.6 | H23: 0 | I23: 0 | J23: =H23*I23 -> 0 | K23: =G23+J23 -> 1817.6 | L23: =+K23 -> 1817.6 | M23: =+L23 -> 1817.6 | N23: 0
A24: 21 | B24: 45829 | E24: 100 | F24: 90.88 | G24: =F24*E24 -> 9088 | H24: 0 | I24: 0 | J24: =H24*I24 -> 0 | K24: =G24+J24 -> 9088 | L24: =+K24 -> 9088 | M24: =+L24 -> 9088
A25: 22 | B25: 45830 | E25: 0 | F25: 0 | G25: =F25*E25 -> 0 | H25: 0 | I25: 0 | J25: =H25*I25 -> 0 | K25: =G25+J25 -> 0 | L25: =+K25 -> 0 | M25: =+L25 -> 0
A26: 23 | B26: 45831 | E26: 38.51 | F26: 90.88 | G26: =F26*E26 -> 3499.7888 | H26: 0 | I26: 0 | J26: =H26*I26 -> 0 | K26: =G26+J26 -> 3499.7888 | L26: =+K26 -> 3499.7888 | M26: =+L26 -> 3499.7888
A27: 24 | B27: 45832 | E27: 0 | F27: 0 | G27: =F27*E27 -> 0 | H27: 0 | I27: 0 | J27: =H27*I27 -> 0 | K27: =G27+J27 -> 0 | L27: =+K27 -> 0 | M27: =+L27 -> 0
A28: 25 | B28: 45833 | E28: 0 | F28: 0 | G28: =F28*E28 -> 0 | H28: 4.87 | I28: 102.77 | J28: =H28*I28 -> 500.4899 | K28: =G28+J28 -> 500.4899 | L28: =+K28 -> 500.4899 | M28: =+L28 -> 500.4899
A29: 26 | B29: 45834 | E29: 0 | F29: 0 | G29: =F29*E29 -> 0 | H29: 0 | I29: 0 | J29: =H29*I29 -> 0 | K29: =G29+J29 -> 0 | L29: =+K29 -> 0 | M29: =+L29 -> 0
A30: 27 | B30: 45835 | E30: 74.51 | F30: 90.88 | G30: =F30*E30 -> 6771.4688 | H30: 0 | I30: 0 | J30: =H30*I30 -> 0 | K30: =G30+J30 -> 6771.4688 | L30: =+K30 -> 6771.4688 | M30: =+L30 -> 6771.4688
A31: 28 | B31: 45836 | E31: 0 | F31: 0 | G31: =F31*E31 -> 0 | H31: 0 | I31: 0 | J31: =H31*I31 -> 0 | K31: =G31+J31 -> 0 | L31: =+K31 -> 0 | M31: =+L31 -> 0
A32: 29 | B32: 45837 | E32: 0 | F32: 0 | G32: =F32*E32 -> 0 | H32: 0 | I32: 0 | J32: =H32*I32 -> 0 | K32: =G32+J32 -> 0 | L32: =+K32 -> 0 | M32: =+L32 -> 0
A33: 30 | B33: 45838 | E33: 30 | F33: 90.88 | G33: =F33*E33 -> 2726.4 | H33: 0 | I33: 0 | J33: =H33*I33 -> 0 | K33: =G33+J33 -> 2726.4 | L33: =+K33 -> 2726.4 | M33: =+L33 -> 2726.4
A34: 31
E35: =SUM(E4:E34) -> 454.02 | G35: =SUM(G4:G34) -> 41261.338 | H35: =SUM(H4:H34) -> 9.73 | J35: =SUM(J4:J34) -> 999.9521 | K35: =SUM(K4:K34) -> 42261.29 | M35: =SUM(M4:M34) -> 42261.29

Sheet Munavalli(KUWSDB)
A1: Shahapur Petroleum
A2: S.No | B2: Date | C2: GRN No | D2: Ind No/Bill No | E2: Diesel (Lts) | F2: Price | G2: Amount | H2: Petrol (Lts) | I2: Price | J2: Amount | K2: Total amount | L2: Amount paid | M2: As on date | N2: Remarks
D3: Opening Balance | K3: 107004.03 | M3: =+K3 -> 107004.03
A4: 1 | B4: 45809 | E4: 189.69 | F4: 91.26 | G4: =E4*F4 -> 17311.109 | H4: 0 | I4: 0 | J4: =H4*I4 -> 0 | K4: =G4+J4 -> 17311.109 | L4: 107000 | M4: =M3+K4-L4 -> 17315.141
A5: 2 | B5: 45810 | E5: 174.1 | F5: 91.26 | G5: =E5*F5 -> 15888.366 | H5: 10 | I5: 103.18 | J5: =H5*I5 -> 1031.8 | K5: =G5+J5 -> 16920.166 | L5: 0 | M5: =M4+K5-L5 -> 34235.307
A6: 3 | B6: 45811 | E6: 400 | F6: 91.26 | G6: =E6*F6 -> 36504 | H6: 16 | I6: 103.18 | J6: =H6*I6 -> 1650.88 | K6: =G6+J6 -> 38154.88 | L6: 0 | M6: =M5+K6-L6 -> 72390.187
A7: 4 | B7: 45812 | E7: 0 | F7: 91.26 | G7: =E7*F7 -> 0 | H7: 0 | I7: 103.18 | J7: =H7*I7 -> 0 | K7: =G7+J7 -> 0 | L7: 0 | M7: =M6+K7-L7 -> 72390.187
A8: 5 | B8: 45813 | E8: 287.95 | F8: 91.26 | G8: =E8*F8 -> 26278.317 | H8: 10 | I8: 103.18 | J8: =H8*I8 -> 1031.8 | K8: =G8+J8 -> 27310.117 | L8: 0 | M8: =M7+K8-L8 -> 99700.304
A9: 6 | B9: 45814 | E9: 104.66 | F9: 91.26 | G9: =E9*F9 -> 9551.2716 | H9: 0 | I9: 0 | J9: =H9*I9 -> 0 | K9: =G9+J9 -> 9551.2716 | L9: 97300 | M9: =M8+K9-L9 -> 11951.576
A10: 7 | B10: 45815 | E10: 219.16 | F10: 91.26 | G10: =E10*F10 -> 20000.542 | H10: 15 | I10: 103.18 | J10: =H10*I10 -> 1547.7 | K10: =G10+J10 -> 21548.242 | L10: 0 | M10: =M9+K10-L10 -> 33499.817
A11: 8 | B11: 45816 | E11: 134.81 | F11: 91.26 | G11: =E11*F11 -> 12302.761 | H11: 0 | I11: 0 | J11: =H11*I11 -> 0 | K11: =G11+J11 -> 12302.761 | L11: 0 | M11: =M10+K11-L11 -> 45802.578
A12: 9 | B12: 45817 | E12: 90 | F12: 91.26 | G12: =E12*F12 -> 8213.4 | H12: 5.23 | I12: 103.18 | J12: =H12*I12 -> 539.6314 | K12: =G12+J12 -> 8753.0314 | L12: 0 | M12: =M11+K12-L12 -> 54555.609
A13: 10 | B13: 45818 | E13: 612.17 | F13: 91.26 | G13: =E13*F13 -> 55866.634 | H13: 10 | I13: 103.18 | J13: =H13*I13 -> 1031.8 | K13: =G13+J13 -> 56898.434 | L13: 0 | M13: =M12+K13-L13 -> 111454.04
A14: 11 | B14: 45819 | E14: 548.9 | F14: 91.26 | G14: =E14*F14 -> 50092.614 | H14: 5 | I14: 103.18 | J14: =H14*I14 -> 515.9 | K14: =G14+J14 -> 50608.514 | L14: 0 | M14: =M13+K14-L14 -> 162062.56
A15: 12 | B15: 45820 | E15: 63.41 | F15: 91.26 | G15: =E15*F15 -> 5786.7966 | H15: 0 | I15: 0 | J15: =H15*I15 -> 0 | K15: =G15+J15 -> 5786.7966 | L15: 0 | M15: =M14+K15-L15 -> 167849.35
... A35: 32 | B35: 45840 | E35: 0 | F35: 0 | G35: =E35*F35 -> 0 | H35: 0 | I35: 0 | J35: =H35*I35 -> 0 | K35: =G35+J35 -> 0 | L35: 0 | M35: =M34+K35-L35 -> 587810.79
E36: =SUM(E4:E35) -> 8967.17 | G36: =SUM(G4:G35) -> 818343.93 | H36: =SUM(H4:H35) -> 259.38 | J36: =SUM(J4:J35) -> 26762.828 | K36: =SUM(K4:K35) -> 845106.76 | L36: =SUM(L4:L35) -> 364300

Sheet Ghattaprabha
A1: Vivek Petrol Pump
A2: S.No | B2: Date | C2: GRN No | D2: Ind No/Bill No | E2: Diesel (Lts) | F2: Price | G2: Amount | H2: Petrol (Lts) | I2: Price | J2: Amount | K2: Total amount | L2: Amount paid | M2: As on Date | N2: Remarks
D3: Opening Balance | K3: 0 | M3: =+K3 -> 0
A4: 1 | B4: 45809 | E4: 0 | F4: 0 | G4: =E4*F4 -> 0 | H4: 0 | I4: 0 | J4: =H4*I4 -> 0 | K4: =G4+J4 -> 0 | L4: 0 | M4: =M3+K4-L4 -> 0
A5: 2 | B5: 45810 | E5: 0 | F5: 0 | G5: =E5*F5 -> 0 | H5: 0 | I5: 0 | J5: =H5*I5 -> 0 | K5: =G5+J5 -> 0 | L5: 0 | M5: =M4+K5-L5 -> 0
A6: 3 | B6: 45811 | E6: 0 | F6: 0 | G6: =E6*F6 -> 0 | H6: 0 | I6: 0 | J6: =H6*I6 -> 0 | K6: =G6+J6 -> 0 | L6: 0 | M6: =M5+K6-L6 -> 0
A7: 4 | B7: 45812 | E7: 121.01 | F7: 91.5 | G7: =E7*F7 -> 11072.415 | H7: 17 | I7: 103.42 | J7: =H7*I7 -> 1758.14 | K7: =G7+J7 -> 12830.555 | L7: 0 | M7: =M6+K7-L7 -> 12830.555
A8: 5 | B8: 45813 | E8: 1008.38 | F8: 91.5 | G8: =E8*F8 -> 92266.77 | H8: 37 | I8: 103.42 | J8: =H8*I8 -> 3826.54 | K8: =G8+J8 -> 96093.31 | L8: 0 | M8: =M7+K8-L8 -> 108923.86
A9: 6 | B9: 45814 | E9: 93.3 | F9: 91.5 | G9: =E9*F9 -> 8536.95 | H9: 15 | I9: 103.42 | J9: =H9*I9 -> 1551.3 | K9: =G9+J9 -> 10088.25 | L9: 0 | M9: =M8+K9-L9 -> 119012.11
A10: 7 | B10: 45815 | E10: 172.55 | F10: 91.5 | G10: =E10*F10 -> 15788.325 | H10: 20 | I10: 103.42 | J10: =H10*I10 -> 2068.4 | K10: =G10+J10 -> 17856.725 | L10: 0 | M10: =M9+K10-L10 -> 136868.84
A11: 8 | B11: 45816 | E11: 650 | F11: 91.5 | G11: =E11*F11 -> 59475 | H11: 0 | I11: 0 | J11: =H11*I11 -> 0 | K11: =G11+J11 -> 59475 | L11: 0 | M11: =M10+K11-L11 -> 196343.84
A12: 9 | B12: 45817 | E12: 675.72 | F12: 91.5 | G12: =E12*F12 -> 61828.38 | H12: 12 | I12: 103.42 | J12: =H12*I12 -> 1241.04 | K12: =G12+J12 -> 63069.42 | L12: 0 | M12: =M11+K12-L12 -> 259413.26
A13: 10 | B13: 45818 | E13: 184.21 | F13: 91.5 | G13: =E13*F13 -> 16855.215 | H13: 15 | I13: 103.42 | J13: =H13*I13 -> 1551.3 | K13: =G13+J13 -> 18406.515 | L13: 0 | M13: =M12+K13-L13 -> 277819.78
A14: 11 | B14: 45819 | E14: 169.56 | F14: 91.5 | G14: =E14*F14 -> 15514.74 | H14: 16 | I14: 103.42 | J14: =H14*I14 -> 1654.72 | K14: =G14+J14 -> 17169.46 | L14: 0 | M14: =M13+K14-L14 -> 294989.24
A15: 12 | B15: 45820 | E15: 100 | F15: 91.5 | G15: =E15*F15 -> 9150 | H15: 0 | I15: 0 | J15: =H15*I15 -> 0 | K15: =G15+J15 -> 9150 | L15: 0 | M15: =M14+K15-L15 -> 304139.24
... A33: 30 | B33: 45838 | E33: 0 | F33: 0 | G33: =E33*F33 -> 0 | H33: 0 | I33: 0 | J33: =H33*I33 -> 0 | K33: =G33+J33 -> 0 | L33: 0 | M33: =M32+K33-L33 -> 308876.47
A34: 31 | E34: 0 | F34: 0 | G34: =E34*F34 -> 0 | H34: 0 | I34: 0 | J34: =H34*I34 -> 0 | K34: =G34+J34 -> 0 | L34: 0 | M34: =M33+K34-L34 -> 308876.47
E35: =SUM(E4:E33) -> 3214.07 | G35: =SUM(G4:G33) -> 294087.4 | H35: =SUM(H4:H33) -> 143 | J35: =SUM(J4:J33) -> 14789.06 | K35: =SUM(K4:K33) -> 308876.47 | L35: =SUM(L4:L33) -> 0
L47: 3010
L48: 4900
L49: 6953
L50: 7527

Sheet Gokak Dharwad PKG 3
A1: AJ Petrolinks
A2: S.No | B2: Date | C2: GRN No | D2: Ind No/Bill No | E2: Diesel (Lts) | F2: Price | G2: Amount | H2: Petrol (Lts) | I2: Price | J2: Amount | K2: Total amount | L2: Amount paid | M2: As on Date | N2: Remarks
D3: Opening Balance | K3: 1537989 | M3: =+K3 -> 1537989
A4: 1 | B4: 45809 | E4: 400 | F4: 91.48 | G4: =E4*F4 -> 36592 | H4: 5 | I4: 103.41 | J4: =H4*I4 -> 517.05 | K4: =G4+J4 -> 37109.05 | M4: =M3+K4-L4 -> 1575098
A5: 2 | B5: 45810 | E5: 337.65 | F5: 91.48 | G5: =E5*F5 -> 30888.222 | H5: 30 | I5: 103.41 | J5: =H5*I5 -> 3102.3 | K5: =G5+J5 -> 33990.522 | M5: =M4+K5-L5 -> 1609088.5
A6: 3 | B6: 45811 | E6: 123.1 | F6: 91.48 | G6: =E6*F6 -> 11261.188 | H6: 12 | I6: 103.41 | J6: =H6*I6 -> 1240.92 | K6: =G6+J6 -> 12502.108 | M6: =M5+K6-L6 -> 1621590.6
A7: 4 | B7: 45812 | E7: 120 | F7: 91.48 | G7: =E7*F7 -> 10977.6 | H7: 6 | I7: 103.41 | J7: =H7*I7 -> 620.46 | K7: =G7+J7 -> 11598.06 | M7: =M6+K7-L7 -> 1633188.7
A8: 5 | B8: 45813 | E8: 35.29 | F8: 91.48 | G8: =E8*F8 -> 3228.3292 | H8: 0 | I8: 0 | J8: =H8*I8 -> 0 | K8: =G8+J8 -> 3228.3292 | M8: =M7+K8-L8 -> 1636417
A9: 6 | B9: 45814 | E9: 0 | F9: 0 | G9: =E9*F9 -> 0 | H9: 0 | I9: 0 | J9: =H9*I9 -> 0 | K9: =G9+J9 -> 0 | L9: 1621328 | M9: =M8+K9-L9 -> 15089.033
A10: 7 | B10: 45815 | E10: 0 | F10: 0 | G10: =E10*F10 -> 0 | H10: 0 | I10: 0 | J10: =H10*I10 -> 0 | K10: =G10+J10 -> 0 | M10: =M9+K10-L10 -> 15089.033
A11: 8 | B11: 45816 | E11: 0 | F11: 0 | G11: =E11*F11 -> 0 | H11: 0 | I11: 0 | J11: =H11*I11 -> 0 | K11: =G11+J11 -> 0 | M11: =M10+K11-L11 -> 15089.033
A12: 9 | B12: 45817 | E12: 0 | F12: 0 | G12: =E12*F12 -> 0 | H12: 0 | I12: 0 | J12: =H12*I12 -> 0 | K12: =G12+J12 -> 0 | M12: =M11+K12-L12 -> 15089.033
A13: 10 | B13: 45818 | E13: 0 | F13: 0 | G13: =E13*F13 -> 0 | H13: 0 | I13: 0 | J13: =H13*I13 -> 0 | K13: =G13+J13 -> 0 | M13: =M12+K13-L13 -> 15089.033
A14: 11 | B14: 45819 | E14: 0 | F14: 0 | G14: =E14*F14 -> 0 | H14: 0 | I14: 0 | J14: =H14*I14 -> 0 | K14: =G14+J14 -> 0 | M14: =M13+K14-L14 -> 15089.033
A15: 12 | B15: 45820 | E15: 0 | F15: 0 | G15: =E15*F15 -> 0 | H15: 0 | I15: 0 | J15: =H15*I15 -> 0 | K15: =G15+J15 -> 0 | M15: =M14+K15-L15 -> 15089.033
A16: 13 | B16: 45821 | E16: 1046.14 | F16: 91.48 | G16: =E16*F16 -> 95700.887 | H16: 0 | I16: 0 | J16: =H16*I16 -> 0 | K16: =G16+J16 -> 95700.887 | M16: =M15+K16-L16 -> 110789.92
A17: 14 | B17: 45822 | E17: 79.31 | F17: 91.48 | G17: =E17*F17 -> 7255.2788 | H17: 22 | I17: 103.41 | J17: =H17*I17 -> 2275.02 | K17: =G17+J17 -> 9530.2988 | M17: =M16+K17-L17 -> 120320.22
B18: 45822 | E18: 0 | F18: 0 | G18: =E18*F18 -> 0 | H18: 6 | I18: 111.17 | J18: =H18*I18 -> 667.02 | K18: =G18+J18 -> 667.02 | M18: =M17+K18-L18 -> 120987.24
A19: 15 | B19: 45823 | E19: 451.27 | F19: 91.48 | G19: =E19*F19 -> 41282.18 | H19: 16 | I19: 103.41 | J19: =H19*I19 -> 1654.56 | K19: =G19+J19 -> 42936.74 | M19: =M18+K19-L19 -> 163923.98
A20: 16 | B20: 45824 | E20: 175.25 | F20: 91.48 | G20: =E20*F20 -> 16031.87 | H20: 16 | I20: 103.41 | J20: =H20*I20 -> 1654.56 | K20: =G20+J20 -> 17686.43 | M20: =M19+K20-L20 -> 181610.41
A21: 17 | B21: 45825 | E21: 1149.53 | F21: 91.48 | G21: =E21*F21 -> 105159 | H21: 24 | I21: 103.41 | J21: =H21*I21 -> 2481.84 | K21: =G21+J21 -> 107640.84 | M21: =M20+K21-L21 -> 289251.25
A22: 18 | B22: 45826 | E22: 950.75 | F22: 91.48 | G22: =E22*F22 -> 86974.61 | H22: 5 | I22: 103.41 | J22: =H22*I22 -> 517.05 | K22: =G22+J22 -> 87491.66 | M22: =M21+K22-L22 -> 376742.91
A23: 19 | B23: 45827 | E23: 864.96 | F23: 91.48 | G23: =E23*F23 -> 79126.541 | H23: 5 | I23: 103.41 | J23: =H23*I23 -> 517.05 | K23: =G23+J23 -> 79643.591 | M23: =M22+K23-L23 -> 456386.5
A24: 20 | B24: 45828 | E24: 116.2 | F24: 91.48 | G24: =E24*F24 -> 10629.976 | H24: 6 | I24: 103.41 | J24: =H24*I24 -> 620.46 | K24: =G24+J24 -> 11250.436 | M24: =M23+K24-L24 -> 467636.94
A25: 21 | B25: 45829 | E25: 141.68 | F25: 91.48 | G25: =E25*F25 -> 12960.886 | H25: 27 | I25: 103.41 | J25: =H25*I25 -> 2792.07 | K25: =G25+J25 -> 15752.956 | M25: =M24+K25-L25 -> 483389.9
A26: 22 | B26: 45830 | E26: 764.98 | F26: 91.48 | G26: =E26*F26 -> 69980.37 | H26: 15 | I26: 103.41 | J26: =H26*I26 -> 1551.15 | K26: =G26+J26 -> 71531.52 | M26: =M25+K26-L26 -> 554921.42
A27: 23 | B27: 45831 | E27: 947.41 | F27: 91.48 | G27: =E27*F27 -> 86669.067 | H27: 37 | I27: 103.41 | J27: =H27*I27 -> 3826.17 | K27: =G27+J27 -> 90495.237 | M27: =M26+K27-L27 -> 645416.65
A28: 24 | B28: 45832 | E28: 121.16 | F28: 91.48 | G28: =E28*F28 -> 11083.717 | H28: 16 | I28: 103.41 | J28: =H28*I28 -> 1654.56 | K28: =G28+J28 -> 12738.277 | M28: =M27+K28-L28 -> 658154.93
A29: 25 | B29: 45833 | E29: 578.15 | F29: 91.48 | G29: =E29*F29 -> 52889.162 | H29: 26 | I29: 103.41 | J29: =H29*I29 -> 2688.66 | K29: =G29+J29 -> 55577.822 | M29: =M28+K29-L29 -> 713732.75
A30: 26 | B30: 45834 | E30: 332.89 | F30: 91.48 | G30: =E30*F30 -> 30452.777 | H30: 21 | I30: 103.41 | J30: =H30*I30 -> 2171.61 | K30: =G30+J30 -> 32624.387 | M30: =M29+K30-L30 -> 746357.14
... A34: 30 | B34: 45838 | E34: 358.42 | F34: 91.48 | G34: =E34*F34 -> 32788.262 | H34: 35 | I34: 103.41 | J34: =H34*I34 -> 3619.35 | K34: =G34+J34 -> 36407.612 | M34: =M33+K34-L34 -> 906887.85
A35: 31 | E35: 0 | F35: 0 | G35: =E35*F35 -> 0 | H35: 0 | I35: 0 | J35: =H35*I35 -> 0 | K35: =G35+J35 -> 0 | M35: =M34+K35-L35 -> 906887.85
E36: 0 | F36: 0 | G36: =E36*F36 -> 0 | H36: 0 | I36: 0 | J36: =H36*I36 -> 0 | K36: =G36+J36 -> 0 | M36: =M35+K36-L36 -> 906887.85
E37: 0 | F37: 0 | G37: =E37*F37 -> 0 | H37: 0 | I37: 0 | J37: =H37*I37 -> 0 | K37: =G37+J37 -> 0 | M37: =M36+K37-L37 -> 906887.85
E38: =SUM(E4:E35) -> 10414.8 | G38: =SUM(G4:G35) -> 952745.9 | H38: =SUM(H4:H35) -> 362 | J38: =SUM(J4:J35) -> 37480.98 | K38: =SUM(K4:K35) -> 990226.88 | L38: =SUM(L4:L35) -> 1621328

Sheet  Shankeshwar
A1: S R PATIL
A2: S.No | B2: Date | C2: GRN No | D2: Ind no/Bill No | E2: Diesel (Lts) | F2: Price | G2: Amount | H2: Petrol (Lts) | I2: Price | J2: Amount | K2: Total amount | L2: Amount paid | M2: As on Date | N2: Remarks
A3: Opening Balance | M3: 0
A4: 1 | B4: 45809 | C4: 0 | E4: 65.72 | F4: 91.3 | G4: =E4*F4 -> 6000.236 | H4: 0 | I4: 0 | J4: =H4*I4 -> 0 | K4: =G4+J4 -> 6000.236 | L4: =+K4 -> 6000.236 | M4: =M3+K4-L4 -> 0
A5: 2 | B5: 45810 | C5: 0 | E5: 65.72 | F5: 91.3 | G5: =E5*F5 -> 6000.236 | H5: 0 | I5: 0 | J5: =H5*I5 -> 0 | K5: =G5+J5 -> 6000.236 | L5: =+K5 -> 6000.236 | M5: =M4+K5-L5 -> 0
A6: 3 | B6: 45811 | C6: 0 | E6: 100 | F6: 91.3 | G6: =E6*F6 -> 9130 | H6: 0 | I6: 0 | J6: =H6*I6 -> 0 | K6: =G6+J6 -> 9130 | L6: =+K6 -> 9130 | M6: =M5+K6-L6 -> 0
A7: 4 | B7: 45812 | C7: 0 | E7: 0 | F7: 0 | G7: =E7*F7 -> 0 | H7: 0 | I7: 0 | J7: =H7*I7 -> 0 | K7: =G7+J7 -> 0 | L7: 0 | M7: =M6+K7-L7 -> 0
A8: 5 | B8: 45813 | C8: 0 | E8: 0 | F8: 0 | G8: =E8*F8 -> 0 | H8: 0 | I8: 0 | J8: =H8*I8 -> 0 | K8: =G8+J8 -> 0 | L8: 0 | M8: =M7+K8-L8 -> 0
A9: 6 | B9: 45814 | C9: 0 | E9: 0 | F9: 0 | G9: =E9*F9 -> 0 | H9: 10 | I9: 103.22 | J9: =H9*I9 -> 1032.2 | K9: =G9+J9 -> 1032.2 | L9: 1032.2 | M9: =M8+K9-L9 -> 0
A10: 7 | B10: 45815 | C10: 0 | E10: 0 | F10: 0 | G10: =E10*F10 -> 0 | H10: 0 | I10: 0 | J10: =H10*I10 -> 0 | K10: =G10+J10 -> 0 | L10: 0 | M10: =M9+K10-L10 -> 0
A11: 8 | B11: 45816 | C11: 0 | E11: 0 | F11: 0 | G11: =E11*F11 -> 0 | H11: 0 | I11: 0 | J11: =H11*I11 -> 0 | K11: =G11+J11 -> 0 | L11: 0 | M11: =M10+K11-L11 -> 0
A12: 9 | B12: 45817 | C12: 0 | E12: 30 | F12: 91.3 | G12: =E12*F12 -> 2739 | H12: 0 | I12: 0 | J12: =H12*I12 -> 0 | K12: =G12+J12 -> 2739 | L12: 2739 | M12: =M11+K12-L12 -> 0
A13: 10 | B13: 45818 | C13: 0 | E13: 30 | F13: 91.3 | G13: =E13*F13 -> 2739 | H13: 0 | I13: 0 | J13: =H13*I13 -> 0 | K13: =G13+J13 -> 2739 | L13: 2739 | M13: =M12+K13-L13 -> 0
A14: 11 | B14: 45819 | C14: 0 | E14: 50 | F14: 91.3 | G14: =E14*F14 -> 4565 | H14: 0 | I14: 0 | J14: =H14*I14 -> 0 | K14: =G14+J14 -> 4565 | L14: 4565 | M14: =M13+K14-L14 -> 0
A15: 12 | B15: 45820 | C15: 0 | E15: 0 | F15: 0 | G15: =E15*F15 -> 0 | H15: 0 | I15: 0 | J15: =H15*I15 -> 0 | K15: =G15+J15 -> 0 | L15: 0 | M15: =M14+K15-L15 -> 0
A16: 13 | B16: 45821 | C16: 0 | E16: 0 | F16: 0 | G16: =E16*F16 -> 0 | H16: 0 | I16: 0 | J16: =H16*I16 -> 0 | K16: =G16+J16 -> 0 | L16: 0 | M16: =M15+K16-L16 -> 0
A17: 14 | B17: 45822 | C17: 0 | E17: 0 | F17: 0 | G17: =E17*F17 -> 0 | H17: 0 | I17: 0 | J17: =H17*I17 -> 0 | K17: =G17+J17 -> 0 | L17: 0 | M17: =M16+K17-L17 -> 0
A18: 15 | B18: 45823 | C18: 0 | E18: 30 | F18: 91.3 | G18: =E18*F18 -> 2739 | H18: 6 | I18: 103.22 | J18: =H18*I18 -> 619.32 | K18: =G18+J18 -> 3358.32 | L18: 3358 | M18: =M17+K18-L18 -> 0.32
... A33: 30 | B33: 45838 | C33: 0 | E33: 0 | F33: 0 | G33: =E33*F33 -> 0 | H33: 0 | I33: 0 | J33: =H33*I33 -> 0 | K33: =G33+J33 -> 0 | L33: 0 | M33: =M32+K33-L33 -> 0
A34: 31 | C34: 0 | E34: 0 | F34: 0 | G34: =E34*F34 -> 0 | H34: 0 | I34: 0 | J34: =H34*I34 -> 0 | K34: =G34+J34 -> 0 | L34: 0 | M34: =M33+K34-L34 -> 0
E35: =SUM(E4:E34) -> 571.44 | G35: =SUM(G4:G34) -> 52172.472 | H35: =SUM(H4:H34) -> 38 | J35: =SUM(J4:J34) -> 3922.36 | K35: =SUM(K4:K34) -> 56094.832 | L35: =SUM(L4:L34) -> 56094.832

Sheet kumta
A1: Krishma fuel station
A2: S.No | B2: Date | C2: GRN No | D2: Ind No/Bill No | E2: Diesel (Lts) | F2: Price | G2: Amount | H2: Petrol (Lts) | I2: Price | J2: Amount | K2: Total amount | L2: Amount paid | M2: As on Date | N2: Remarks
A3: Opening Balance | K3: 0 | M3: =+K3 -> 0
A4: 1 | B4: 45809 | E4: 78 | F4: 91.92 | G4: =E4*F4 -> 7169.76 | H4: 0 | I4: 0 | J4: =H4*I4 -> 0 | K4: =G4+J4 -> 7169.76 | L4: =+K4 -> 7169.76 | M4: =M3+K4-L4 -> 0 | N4: IOCL Card
A5: 2 | B5: 45810 | E5: 20 | F5: 91.92 | G5: =E5*F5 -> 1838.4 | H5: 0 | I5: 0 | J5: =H5*I5 -> 0 | K5: =G5+J5 -> 1838.4 | L5: =+K5 -> 1838.4 | M5: =M4+K5-L5 -> 0
A6: 3 | B6: 45811 | E6: 100 | F6: 91.92 | G6: =E6*F6 -> 9192 | H6: 0 | I6: 0 | J6: =H6*I6 -> 0 | K6: =G6+J6 -> 9192 | L6: =+K6 -> 9192 | M6: =M5+K6-L6 -> 0
A7: 4 | B7: 45812 | E7: 85 | F7: 91.92 | G7: =E7*F7 -> 7813.2 | H7: 0 | I7: 0 | J7: =H7*I7 -> 0 | K7: =G7+J7 -> 7813.2 | L7: =+K7 -> 7813.2 | M7: =M6+K7-L7 -> 0
A8: 5 | B8: 45813 | E8: 60 | F8: 91.92 | G8: =E8*F8 -> 5515.2 | H8: 0 | I8: 0 | J8: =H8*I8 -> 0 | K8: =G8+J8 -> 5515.2 | L8: =+K8 -> 5515.2 | M8: =M7+K8-L8 -> 0
A9: 6 | B9: 45814 | E9: 100 | F9: 91.92 | G9: =E9*F9 -> 9192 | H9: 0 | I9: 0 | J9: =H9*I9 -> 0 | K9: =G9+J9 -> 9192 | L9: =+K9 -> 9192 | M9: =M8+K9-L9 -> 0
A10: 7 | B10: 45815 | E10: 100 | F10: 91.92 | G10: =E10*F10 -> 9192 | H10: 0 | I10: 0 | J10: =H10*I10 -> 0 | K10: =G10+J10 -> 9192 | L10: =+K10 -> 9192 | M10: =M9+K10-L10 -> 0
A11: 8 | B11: 45816 | E11: 0 | F11: 0 | G11: =E11*F11 -> 0 | H11: 6.18 | I11: 103.89 | J11: =H11*I11 -> 642.0402 | K11: =G11+J11 -> 642.0402 | L11: =+K11 -> 642.0402 | M11: =M10+K11-L11 -> 0
A12: 9 | B12: 45817 | E12: 0 | F12: 0 | G12: =E12*F12 -> 0 | H12: 0 | I12: 0 | J12: =H12*I12 -> 0 | K12: =G12+J12 -> 0 | L12: =+K12 -> 0 | M12: =M11+K12-L12 -> 0
A13: 10 | B13: 45818 | E13: 90 | F13: 91.92 | G13: =E13*F13 -> 8272.8 | H13: 1.44 | I13: 103.89 | J13: =H13*I13 -> 149.6016 | K13: =G13+J13 -> 8422.4016 | L13: =+K13 -> 8422.4016 | M13: =M12+K13-L13 -> 0
A14: 11 | B14: 45819 | E14: 36.13 | F14: 91.92 | G14: =E14*F14 -> 3321.0696 | H14: 1.88 | I14: 103.89 | J14: =H14*I14 -> 195.3132 | K14: =G14+J14 -> 3516.3828 | L14: =+K14 -> 3516.3828 | M14: =M13+K14-L14 -> 0
A15: 12 | B15: 45820 | E15: 75 | F15: 91.92 | G15: =E15*F15 -> 6894 | H15: 0 | I15: 0 | J15: =H15*I15 -> 0 | K15: =G15+J15 -> 6894 | L15: =+K15 -> 6894 | M15: =M14+K15-L15 -> 0
A16: 13 | B16: 45821 | E16: 0 | F16: 0 | G16: =E16*F16 -> 0 | H16: 12.22 | I16: 103.89 | J16: =H16*I16 -> 1269.5358 | K16: =G16+J16 -> 1269.5358 | L16: =+K16 -> 1269.5358 | M16: =M15+K16-L16 -> 0
... A34: 31 | B34: 45839 | E34: 0 | F34: 0 | G34: =E34*F34 -> 0 | H34: 0 | I34: 0 | J34: =H34*I34 -> 0 | K34: =G34+J34 -> 0 | L34: =+K34 -> 0 | M34: =M33+K34-L34 -> 0
E35: =SUM(E4:E34) -> 1235.75 | G35: =SUM(G4:G34) -> 113590.14 | H35: =SUM(H4:H34) -> 91.72 | J35: =SUM(J4:J34) -> 9532.9908 | K35: =SUM(K4:K34) -> 123123.13 | L35: =SUM(L4:L34) -> 123123.13

Sheet Borgaon
A1: Aadisagar Petrolium
A2: S.No | B2: Date | C2: GRN No | D2: Ind no/Bill No | E2: Diesel (Lts) | F2: Price | G2: Amount | H2: Petrol (Lts) | I2: Price | J2: Amount | K2: Total amount | L2: Amount paid | M2: As on Date | N2: Remarks
A3: Opening Balance | K3: 22826.33 | M3: =+K3 -> 22826.33
A4: 1 | B4: 45809 | E4: 0 | F4: 0 | G4: =E4*F4 -> 0 | H4: 0 | I4: 0 | J4: =H4*I4 -> 0 | K4: =G4+J4 -> 0 | M4: =M3+K4-L4 -> 22826.33
A5: 2 | B5: 45810 | E5: 0 | F5: 0 | G5: =E5*F5 -> 0 | H5: 0 | I5: 0 | J5: =H5*I5 -> 0 | K5: =G5+J5 -> 0 | M5: =M4+K5-L5 -> 22826.33
A6: 3 | B6: 45811 | E6: 30 | F6: 91.77 | G6: =E6*F6 -> 2753.1 | H6: 10 | I6: 103.73 | J6: =H6*I6 -> 1037.3 | K6: =G6+J6 -> 3790.4 | M6: =M5+K6-L6 -> 26616.73
A7: 4 | B7: 45812 | E7: 32 | F7: 91.77 | G7: =E7*F7 -> 2936.64 | H7: 0 | I7: 0 | J7: =H7*I7 -> 0 | K7: =G7+J7 -> 2936.64 | M7: =M6+K7-L7 -> 29553.37
A8: 5 | B8: 45813 | E8: 0 | F8: 0 | G8: =E8*F8 -> 0 | H8: 0 | I8: 0 | J8: =H8*I8 -> 0 | K8: =G8+J8 -> 0 | M8: =M7+K8-L8 -> 29553.37
A9: 6 | B9: 45814 | E9: 0 | F9: 0 | G9: =E9*F9 -> 0 | H9: 0 | I9: 0 | J9: =H9*I9 -> 0 | K9: =G9+J9 -> 0 | M9: =M8+K9-L9 -> 29553.37
A10: 7 | B10: 45815 | E10: 30 | F10: 91.77 | G10: =E10*F10 -> 2753.1 | H10: 0 | I10: 103.53 | J10: =H10*I10 -> 0 | K10: =G10+J10 -> 2753.1 | M10: =M9+K10-L10 -> 32306.47
A11: 8 | B11: 45816 | E11: 0 | F11: 0 | G11: =E11*F11 -> 0 | H11: 4 | I11: 103.53 | J11: =H11*I11 -> 414.12 | K11: =G11+J11 -> 414.12 | M11: =M10+K11-L11 -> 32720.59
A12: 9 | B12: 45817 | E12: 20 | F12: 91.77 | G12: =E12*F12 -> 1835.4 | H12: 0 | I12: 0 | J12: =H12*I12 -> 0 | K12: =G12+J12 -> 1835.4 | M12: =M11+K12-L12 -> 34555.99
A13: 10 | B13: 45818 | F13: 91.77 | G13: =E13*F13 -> 0 | H13: 0 | I13: 0 | J13: =H13*I13 -> 0 | K13: =G13+J13 -> 0 | M13: =M12+K13-L13 -> 34555.99
A14: 11 | B14: 45819 | E14: 0 | F14: 0 | G14: =E14*F14 -> 0 | H14: 0 | I14: 0 | J14: =H14*I14 -> 0 | K14: =G14+J14 -> 0 | M14: =M13+K14-L14 -> 34555.99
A15: 12 | B15: 45820 | E15: 0 | F15: 0 | G15: =E15*F15 -> 0 | H15: 0 | I15: 0 | J15: =H15*I15 -> 0 | K15: =G15+J15 -> 0 | M15: =M14+K15-L15 -> 34555.99
A16: 13 | B16: 45821 | E16: 0 | F16: 0 | G16: =E16*F16 -> 0 | H16: 5 | I16: 103.53 | J16: =H16*I16 -> 517.65 | K16: =G16+J16 -> 517.65 | M16: =M15+K16-L16 -> 35073.64
A17: 14 | B17: 45822 | E17: 0 | F17: 0 | G17: =E17*F17 -> 0 | H17: 0 | I17: 0 | J17: =H17*I17 -> 0 | K17: =G17+J17 -> 0 | M17: =M16+K17-L17 -> 35073.64
A18: 15 | B18: 45823 | E18: 0 | F18: 0 | G18: =E18*F18 -> 0 | H18: 0 | I18: 0 | J18: =H18*I18 -> 0 | K18: =G18+J18 -> 0 | M18: =M17+K18-L18 -> 35073.64
A19: 16 | B19: 45824 | E19: 0 | F19: 0 | G19: =E19*F19 -> 0 | H19: 0 | I19: 0 | J19: =H19*I19 -> 0 | K19: =G19+J19 -> 0 | M19: =M18+K19-L19 -> 35073.64
A20: 17 | B20: 45825 | E20: 47.4 | F20: 91.77 | G20: =E20*F20 -> 4349.898 | H20: 0 | I20: 0 | J20: =H20*I20 -> 0 | K20: =G20+J20 -> 4349.898 | M20: =M19+K20-L20 -> 39423.538
A21: 18 | B21: 45826 | E21: 0 | F21: 0 | G21: =E21*F21 -> 0 | H21: 0 | I21: 0 | J21: =H21*I21 -> 0 | K21: =G21+J21 -> 0 | M21: =M20+K21-L21 -> 39423.538
A22: 19 | B22: 45827 | E22: 0 | F22: 0 | G22: =E22*F22 -> 0 | H22: 0 | I22: 0 | J22: =H22*I22 -> 0 | K22: =G22+J22 -> 0 | M22: =M21+K22-L22 -> 39423.538
A23: 20 | B23: 45828 | E23: 20 | F23: 91.77 | G23: =E23*F23 -> 1835.4 | H23: 0 | I23: 0 | J23: =H23*I23 -> 0 | K23: =G23+J23 -> 1835.4 | M23: =M22+K23-L23 -> 41258.938
A24: 21 | B24: 45829 | E24: 10 | F24: 91.77 | G24: =E24*F24 -> 917.7 | H24: 6 | I24: 103.73 | J24: =H24*I24 -> 622.38 | K24: =G24+J24 -> 1540.08 | M24: =M23+K24-L24 -> 42799.018
A25: 22 | B25: 45830 | E25: 30 | F25: 91.77 | G25: =E25*F25 -> 2753.1 | H25: 0 | I25: 0 | J25: =H25*I25 -> 0 | K25: =G25+J25 -> 2753.1 | M25: =M24+K25-L25 -> 45552.118
... A33: 30 | B33: 45838 | E33: 0 | F33: 0 | G33: =E33*F33 -> 0 | H33: 6 | I33: 103.73 | J33: =H33*I33 -> 622.38 | K33: =G33+J33 -> 622.38 | M33: =M32+K33-L33 -> 59999.798
A34: 31 | E34: 0 | F34: 0 | G34: =E34*F34 -> 0 | H34: 0 | I34: 0 | J34: =H34*I34 -> 0 | K34: =G34+J34 -> 0 | M34: =M33+K34-L34 -> 59999.798
E35: =SUM(E4:E34) -> 364.4 | G35: =SUM(G4:G34) -> 33440.988 | H35: =SUM(H4:H34) -> 36 | J35: =SUM(J4:J34) -> 3732.48 | K35: =SUM(K4:K34) -> 37173.468 | L35: =SUM(L4:L34) -> 0

Sheet Ugar,Khagwad,Kudichi
A1: Shiri Bhrhmanath Petrolium
A2: S.No | B2: Date | C2: GRN No | D2: Ind No/Bill No | E2: Diesel (Lts) | F2: Price | G2: Amount | H2: Petrol (Lts) | I2: Price | J2: Amount | K2: Total amount | L2: Amount paid | M2: As on Date | N2: Remarks
A3: Opening Balance | K3: 241437.63 | M3: =+K3 -> 241437.63
A4: 1 | B4: 45809 | E4: 270 | F4: 91.93 | G4: =E4*F4 -> 24821.1 | H4: 0 | I4: 0 | J4: =H4*I4 -> 0 | K4: =G4+J4 -> 24821.1 | L4: 0 | M4: =M3+K4-L4 -> 266258.73
A5: 2 | B5: 45810 | E5: 0 | F5: 0 | G5: =E5*F5 -> 0 | H5: 0 | I5: 0 | J5: =H5*I5 -> 0 | K5: =G5+J5 -> 0 | L5: 0 | M5: =M4+K5-L5 -> 266258.73
A6: 3 | B6: 45811 | E6: 230 | F6: 91.93 | G6: =E6*F6 -> 21143.9 | H6: 30 | I6: 103.89 | J6: =H6*I6 -> 3116.7 | K6: =G6+J6 -> 24260.6 | L6: 0 | M6: =M5+K6-L6 -> 290519.33
A7: 4 | B7: 45812 | E7: 0 | F7: 0 | G7: =E7*F7 -> 0 | H7: 0 | I7: 0 | J7: =H7*I7 -> 0 | K7: =G7+J7 -> 0 | L7: 0 | M7: =M6+K7-L7 -> 290519.33
A8: 5 | B8: 45813 | E8: 0 | F8: 0 | G8: =E8*F8 -> 0 | H8: 0 | I8: 0 | J8: =H8*I8 -> 0 | K8: =G8+J8 -> 0 | L8: 287745 | M8: =M7+K8-L8 -> 2774.328
A9: 6 | B9: 45814 | E9: 0 | F9: 0 | G9: =E9*F9 -> 0 | H9: 0 | I9: 0 | J9: =H9*I9 -> 0 | K9: =G9+J9 -> 0 | L9: 0 | M9: =M8+K9-L9 -> 2774.328
A10: 7 | B10: 45815 | E10: 200 | F10: 91.93 | G10: =E10*F10 -> 18386 | H10: 0 | I10: 0 | J10: =H10*I10 -> 0 | K10: =G10+J10 -> 18386 | L10: 0 | M10: =M9+K10-L10 -> 21160.328
A11: 8 | B11: 45816 | E11: 0 | F11: 0 | G11: =E11*F11 -> 0 | H11: 0 | I11: 0 | J11: =H11*I11 -> 0 | K11: =G11+J11 -> 0 | L11: 0 | M11: =M10+K11-L11 -> 21160.328
A12: 9 | B12: 45817 | E12: 0 | F12: 91.93 | G12: =E12*F12 -> 0 | H12: 30 | I12: 103.89 | J12: =H12*I12 -> 3116.7 | K12: =G12+J12 -> 3116.7 | L12: 0 | M12: =M11+K12-L12 -> 24277.028
A13: 10 | B13: 45818 | E13: 0 | F13: 0 | G13: =E13*F13 -> 0 | H13: 0 | I13: 0 | J13: =H13*I13 -> 0 | K13: =G13+J13 -> 0 | L13: 0 | M13: =M12+K13-L13 -> 24277.028
A14: 11 | B14: 45819 | E14: 0 | F14: 0 | G14: =E14*F14 -> 0 | H14: 0 | I14: 0 | J14: =H14*I14 -> 0 | K14: =G14+J14 -> 0 | L14: 0 | M14: =M13+K14-L14 -> 24277.028
A15: 12 | B15: 45820 | E15: 285 | F15: 91.93 | G15: =E15*F15 -> 26200.05 | H15: 10 | I15: 103.89 | J15: =H15*I15 -> 1038.9 | K15: =G15+J15 -> 27238.95 | L15: 0 | M15: =M14+K15-L15 -> 51515.978
... A33: 30 | B33: 45838 | E33: 0 | F33: 0 | G33: =E33*F33 -> 0 | H33: 0 | I33: 0 | J33: =H33*I33 -> 0 | K33: =G33+J33 -> 0 | L33: 0 | M33: =M32+K33-L33 -> 236571.24
A34: 31 | E34: 0 | F34: 0 | G34: =E34*F34 -> 0 | H34: 0 | I34: 0 | J34: =H34*I34 -> 0 | K34: =G34+J34 -> 0 | L34: 0 | M34: =M33+K34-L34 -> 236571.24
E35: =SUM(E4:E34) -> 2862.39 | G35: =SUM(G4:G34) -> 263139.51 | H35: =SUM(H4:H34) -> 190 | J35: =SUM(J4:J34) -> 19739.1 | K35: =SUM(K4:K34) -> 282878.61 | L35: =SUM(L4:L34) -> 287745

Sheet Kabbur
A1: Shri Jai Hanuman Petrolium
A2: S.No | B2: Date | C2: GRN No | D2: Ind no/Bill No | E2: Diesel (Lts) | F2: Price | G2: Amount | H2: Petrol (Lts) | I2: Price | J2: Amount | K2: Total amount | L2: Amount paid | M2: As on Date | N2: Remarks
A3: Opening Balance | K3: 0 | M3: =+K3 -> 0
A4: 1 | B4: 45809 | E4: 150 | F4: 91.59 | G4: =E4*F4 -> 13738.5 | K4: =G4+J4 -> 13738.5 | L4: =+K4 -> 13738.5
A5: 2 | B5: 45810 | E5: 0 | F5: 0 | G5: =E5*F5 -> 0 | K5: =G5+J5 -> 0 | L5: =+K5 -> 0
A6: 3 | B6: 45811 | E6: 110 | F6: 91.59 | G6: =E6*F6 -> 10074.9 | H6: 8 | I6: 103.53 | J6: =H6*I6 -> 828.24 | K6: =G6+J6 -> 10903.14 | L6: =+K6 -> 10903.14
A7: 4 | B7: 45812 | E7: 0 | F7: 0 | G7: =E7*F7 -> 0 | J7: =H7*I7 -> 0 | K7: =G7+J7 -> 0 | L7: =+K7 -> 0
A8: 5 | B8: 45813 | E8: 0 | F8: 0 | G8: =E8*F8 -> 0 | J8: =H8*I8 -> 0 | K8: =G8+J8 -> 0 | L8: =+K8 -> 0
A9: 6 | B9: 45814 | E9: 0 | F9: 0 | G9: =E9*F9 -> 0 | J9: =H9*I9 -> 0 | K9: =G9+J9 -> 0 | L9: =+K9 -> 0
A10: 7 | B10: 45815 | E10: 45 | F10: 91.59 | G10: =E10*F10 -> 4121.55 | H10: 8 | I10: 103.59 | J10: =H10*I10 -> 828.72 | K10: =G10+J10 -> 4950.27 | L10: =+K10 -> 4950.27
A11: 8 | B11: 45816 | E11: 0 | F11: 0 | G11: =E11*F11 -> 0 | J11: =H11*I11 -> 0 | K11: =G11+J11 -> 0 | L11: =+K11 -> 0
A12: 9 | B12: 45817 | E12: 0 | F12: 0 | G12: =E12*F12 -> 0 | J12: =H12*I12 -> 0 | K12: =G12+J12 -> 0 | L12: =+K12 -> 0
A13: 10 | B13: 45818 | E13: 0 | F13: 0 | G13: =E13*F13 -> 0 | J13: =H13*I13 -> 0 | K13: =G13+J13 -> 0 | L13: =+K13 -> 0
A14: 11 | B14: 45819 | E14: 0 | F14: 0 | G14: =E14*F14 -> 0 | J14: =H14*I14 -> 0 | K14: =G14+J14 -> 0 | L14: =+K14 -> 0
A15: 12 | B15: 45820 | E15: 20 | F15: 91.59 | G15: =E15*F15 -> 1831.8 | J15: =H15*I15 -> 0 | K15: =G15+J15 -> 1831.8 | L15: =+K15 -> 1831.8
A16: 13 | B16: 45821 | E16: 0 | F16: 0 | G16: =E16*F16 -> 0 | J16: =H16*I16 -> 0 | K16: =G16+J16 -> 0 | L16: =+K16 -> 0
A17: 14 | B17: 45822 | E17: 0 | F17: 0 | G17: =E17*F17 -> 0 | J17: =H17*I17 -> 0 | K17: =G17+J17 -> 0 | L17: =+K17 -> 0
A18: 15 | B18: 45823 | E18: 0 | F18: 0 | G18: =E18*F18 -> 0 | J18: =H18*I18 -> 0 | K18: =G18+J18 -> 0 | L18: =+K18 -> 0
A19: 16 | B19: 45824 | E19: 0 | F19: 0 | G19: =E19*F19 -> 0 | J19: =H19*I19 -> 0 | K19: =G19+J19 -> 0 | L19: =+K19 -> 0
A20: 17 | B20: 45825 | E20: 0 | F20: 0 | G20: =E20*F20 -> 0 | J20: =H20*I20 -> 0 | K20: =G20+J20 -> 0 | L20: =+K20 -> 0
A21: 18 | B21: 45826 | E21: 0 | F21: 0 | G21: =E21*F21 -> 0 | J21: =H21*I21 -> 0 | K21: =G21+J21 -> 0 | L21: =+K21 -> 0
A22: 19 | B22: 45827 | E22: 40 | F22: 91.59 | G22: =E22*F22 -> 3663.6 | H22: 6.51 | I22: 103.59 | J22: =H22*I22 -> 674.3709 | K22: =G22+J22 -> 4337.9709 | L22: =+K22 -> 4337.9709
A23: 20 | B23: 45828 | E23: 30 | F23: 91.59 | G23: =E23*F23 -> 2747.7 | J23: =H23*I23 -> 0 | K23: =G23+J23 -> 2747.7 | L23: =+K23 -> 2747.7
A24: 21 | B24: 45829 | E24: 150 | F24: 91.59 | G24: =E24*F24 -> 13738.5 | H24: 7 | I24: 103.59 | J24: =H24*I24 -> 725.13 | K24: =G24+J24 -> 14463.63 | L24: =+K24 -> 14463.63
A25: 22 | B25: 45830 | E25: 0 | F25: 0 | G25: =E25*F25 -> 0 | J25: =H25*I25 -> 0 | K25: =G25+J25 -> 0 | L25: =+K25 -> 0
A26: 23 | B26: 45831 | E26: 0 | F26: 0 | G26: =E26*F26 -> 0 | J26: =H26*I26 -> 0 | K26: =G26+J26 -> 0 | L26: =+K26 -> 0
A27: 24 | B27: 45832 | E27: 0 | F27: 0 | G27: =E27*F27 -> 0 | J27: =H27*I27 -> 0 | K27: =G27+J27 -> 0 | L27: =+K27 -> 0 | O27: 0
A28: 25 | B28: 45833 | E28: 100 | F28: 91.59 | G28: =E28*F28 -> 9159 | J28: =H28*I28 -> 0 | K28: =G28+J28 -> 9159 | L28: =+K28 -> 9159
A29: 26 | B29: 45834 | E29: 30 | F29: 91.59 | G29: =E29*F29 -> 2747.7 | H29: 3 | I29: 103.59 | J29: =H29*I29 -> 310.77 | K29: =G29+J29 -> 3058.47 | L29: =+K29 -> 3058.47
A30: 27 | B30: 45835 | E30: 0 | F30: 0 | G30: =E30*F30 -> 0 | K30: =G30+J30 -> 0 | L30: =+K30 -> 0
A31: 28 | B31: 45836 | E31: 0 | F31: 0 | G31: =E31*F31 -> 0 | K31: =G31+J31 -> 0 | L31: =+K31 -> 0
A32: 29 | B32: 45837 | E32: 30 | F32: 91.59 | G32: =E32*F32 -> 2747.7 | K32: =G32+J32 -> 2747.7 | L32: =+K32 -> 2747.7
A33: 30 | B33: 45838 | E33: 0 | F33: 0 | G33: =E33*F33 -> 0 | K33: =G33+J33 -> 0 | L33: =+K33 -> 0
A34: 31 | E34: 0 | F34: 0 | G34: =E34*F34 -> 0
E35: =SUM(E4:E34) -> 705 | G35: =SUM(G4:G34) -> 64570.95 | H35: =SUM(H4:H34) -> 32.51 | J35: =SUM(J4:J34) -> 3367.2309 | K35: =SUM(K4:K34) -> 67938.181 | L35: =SUM(L4:L34) -> 67938.181

Sheet Jalgaon
A1: Sri Sai Petrol Pump
A2: S.No | B2: Date | C2: GRN No | D2: Ind No/Bill No | E2: Diesel (Lts) | F2: Price | G2: Amount | H2: Petrol (Lts) | I2: Price | J2: Amount | K2: Total amount | L2: Amount paid | M2: As on Date | N2: Remarks
A3: Opening Balance | K3: 13725.912 | M3: =+K3 -> 13725.912
A4: 1 | B4: 45809 | E4: 0 | F4: 0 | G4: =E4*F4 -> 0 | H4: 0 | I4: 0 | J4: =H4*I4 -> 0 | K4: =G4+J4 -> 0 | L4: 0 | M4: =M3+K4-L4 -> 13725.912
A5: 2 | B5: 45810 | E5: 3.27 | F5: 91.81 | G5: =E5*F5 -> 300.2187 | H5: 0 | I5: 0 | J5: =H5*I5 -> 0 | K5: =G5+J5 -> 300.2187 | L5: 0 | M5: =M4+K5-L5 -> 14026.131
A6: 3 | B6: 45811 | E6: 49.07 | F6: 91.71 | G6: =E6*F6 -> 4500.2097 | H6: 0 | I6: 0 | J6: =H6*I6 -> 0 | K6: =G6+J6 -> 4500.2097 | L6: 4500.21 | M6: =M5+K6-L6 -> 14026.131
A7: 4 | B7: 45812 | E7: 0 | F7: 0 | G7: =E7*F7 -> 0 | H7: 0 | I7: 0 | J7: =H7*I7 -> 0 | K7: =G7+J7 -> 0 | L7: 0 | M7: =M6+K7-L7 -> 14026.131
A8: 5 | B8: 45813 | E8: 40.67 | F8: 91.47 | G8: =E8*F8 -> 3720.0849 | H8: 0 | I8: 0 | J8: =H8*I8 -> 0 | K8: =G8+J8 -> 3720.0849 | L8: 0 | M8: =M7+K8-L8 -> 17746.216
B9: 45813 | E9: 39.25 | F9: 91.71 | G9: =E9*F9 -> 3599.6175 | H9: 0 | I9: 0 | J9: =H9*I9 -> 0 | K9: =G9+J9 -> 3599.6175 | L9: 17500 | M9: =M8+K9-L9 -> 3845.8331
A10: 6 | B10: 45814 | E10: 25.08 | F10: 91.71 | G10: =E10*F10 -> 2300.0868 | H10: 0 | I10: 104.94 | J10: =H10*I10 -> 0 | K10: =G10+J10 -> 2300.0868 | L10: 2300 | M10: =M9+K10-L10 -> 3845.9199
A11: 7 | B11: 45815 | E11: 0 | F11: 0 | G11: =E11*F11 -> 0 | H11: 0 | I11: 0 | J11: =H11*I11 -> 0 | K11: =G11+J11 -> 0 | L11: 0 | M11: =M10+K11-L11 -> 3845.9199
A12: 8 | B12: 45816 | E12: 43.11 | F12: 91.71 | G12: =E12*F12 -> 3953.6181 | H12: 0 | I12: 0 | J12: =H12*I12 -> 0 | K12: =G12+J12 -> 3953.6181 | L12: 0 | M12: =M11+K12-L12 -> 7799.538
A13: 9 | B13: 45817 | E13: 38.33 | F13: 92.03 | G13: =E13*F13 -> 3527.5099 | H13: 0 | I13: 0 | J13: =H13*I13 -> 0 | K13: =G13+J13 -> 3527.5099 | L13: 3527.51 | M13: =M12+K13-L13 -> 7799.5379
A14: 10 | B14: 45818 | E14: 39.9 | F14: 91.71 | G14: =E14*F14 -> 3659.229 | H14: 0 | I14: 0 | J14: =H14*I14 -> 0 | K14: =G14+J14 -> 3659.229 | L14: 0 | M14: =M13+K14-L14 -> 11458.767
A15: 11 | B15: 45819 | E15: 46.41 | F15: 91.71 | G15: =E15*F15 -> 4256.2611 | H15: 0 | I15: 0 | J15: =H15*I15 -> 0 | K15: =G15+J15 -> 4256.2611 | L15: 4256.26 | M15: =M14+K15-L15 -> 11458.768
A16: 12 | B16: 45820 | E16: 34.04 | F16: 91.71 | G16: =E16*F16 -> 3121.8084 | H16: 0 | I16: 0 | J16: =H16*I16 -> 0 | K16: =G16+J16 -> 3121.8084 | L16: 14131.81 | M16: =M15+K16-L16 -> 448.7664
A17: 13 | B17: 45821 | E17: 0 | F17: 0 | G17: =E17*F17 -> 0 | H17: 0 | I17: 0 | J17: =H17*I17 -> 0 | K17: =G17+J17 -> 0 | L17: 0 | M17: =M16+K17-L17 -> 448.7664
A18: 14 | B18: 45822 | E18: 0 | F18: 0 | G18: =E18*F18 -> 0 | H18: 0 | I18: 0 | J18: =H18*I18 -> 0 | K18: =G18+J18 -> 0 | L18: 0 | M18: =M17+K18-L18 -> 448.7664
A19: 15 | B19: 45823 | E19: 0 | F19: 0 | G19: =E19*F19 -> 0 | H19: 0 | I19: 0 | J19: =H19*I19 -> 0 | K19: =G19+J19 -> 0 | L19: 0 | M19: =M18+K19-L19 -> 448.7664
A20: 16 | B20: 45824 | E20: 35.48 | F20: 92.03 | G20: =E20*F20 -> 3265.2244 | H20: 0 | I20: 0 | J20: =H20*I20 -> 0 | K20: =G20+J20 -> 3265.2244 | L20: 3265.22 | M20: =M19+K20-L20 -> 448.7708
A21: 17 | B21: 45825 | E21: 38.74 | F21: 90.35 | G21: =E21*F21 -> 3500.159 | H21: 0 | I21: 0 | J21: =H21*I21 -> 0 | K21: =G21+J21 -> 3500.159 | L21: 3500.16 | M21: =M20+K21-L21 -> 448.7698
... A34: 30 | B34: 45838 | E34: 14.61 | F34: 91.71 | G34: =E34*F34 -> 1339.8831 | H34: 0 | I34: 0 | J34: =H34*I34 -> 0 | K34: =G34+J34 -> 1339.8831 | L34: 0 | M34: =M33+K34-L34 -> 17065.88
A35: 31 | E35: 0 | F35: 0 | G35: =E35*F35 -> 0 | H35: 0 | I35: 0 | J35: =H35*I35 -> 0 | K35: =G35+J35 -> 0 | L35: 0 | M35: =M34+K35-L35 -> 17065.88
A36: 32 | E36: 0 | F36: 0 | G36: =E36*F36 -> 0 | H36: 0 | I36: 0 | J36: =H36*I36 -> 0 | K36: =G36+J36 -> 0 | L36: 0 | M36: =M35+K36-L36 -> 17065.88
A37: 33 | E37: 0 | F37: 0 | G37: =E37*F37 -> 0 | H37: 0 | I37: 0 | J37: =H37*I37 -> 0 | K37: =G37+J37 -> 0 | L37: 0 | M37: =M36+K37-L37 -> 17065.88
A38: 34 | E38: 0 | F38: 0 | G38: =E38*F38 -> 0 | H38: 0 | I38: 0 | J38: =H38*I38 -> 0 | K38: =G38+J38 -> 0 | L38: 0 | M38: =M37+K38-L38 -> 17065.88
E39: 0 | F39: 0 | G39: =E39*F39 -> 0 | H39: 0 | I39: 0 | J39: =H39*I39 -> 0 | K39: =G39+J39 -> 0 | L39: =+K39 -> 0 | M39: =M38+K39-L39 -> 17065.88
E40: =SUM(E4:E39) -> 823.37 | G40: =SUM(G4:G39) -> 75472.286 | H40: =SUM(H4:H39) -> 14.64 | J40: =SUM(J4:J39) -> 1539.9816 | K40: =SUM(K4:K39) -> 77012.267 | L40: =SUM(L4:L39) -> 73672.3

Sheet MKBD
A1: Shree Sai Samarth Petroleum
A2: S.No | B2: Date | C2: GRN No | D2: Ind No/Bill No | E2: Diesel (Lts) | F2: Price | G2: Amount | H2: Petrol (Lts) | I2: Price | J2: Amount | K2: Total amount | L2: Amount paid | M2: As on Date | N2: Remarks
A3: Opening Balance | K3: 450628.67 | M3: =+K3 -> 450628.67
A4: 1 | B4: 45809 | C4: 0 | E4: 0 | F4: 0 | G4: =E4*F4 -> 0 | H4: 0 | I4: 0 | J4: =H4*I4 -> 0 | K4: =G4+J4 -> 0 | M4: =M3+K4-L4 -> 450628.67
A5: 2 | B5: 45810 | C5: 801 | E5: 2589.19 | F5: 91.14 | G5: =E5*F5 -> 235978.78 | H5: 35 | I5: 104.6 | J5: =H5*I5 -> 3661 | K5: =G5+J5 -> 239639.78 | M5: =M4+K5-L5 -> 690268.44
A6: 3 | B6: 45811 | C6: 0 | E6: 0 | F6: 0 | G6: =E6*F6 -> 0 | H6: 0 | I6: 0 | J6: =H6*I6 -> 0 | K6: =G6+J6 -> 0 | M6: =M5+K6-L6 -> 690268.44
A7: 4 | B7: 45812 | C7: 0 | E7: 3500 | F7: 91.14 | G7: =E7*F7 -> 318990 | H7: 0 | I7: 0 | J7: =H7*I7 -> 0 | K7: =G7+J7 -> 318990 | M7: =M6+K7-L7 -> 1009258.4
A8: 5 | B8: 45813 | C8: 0 | E8: 0 | F8: 0 | G8: =E8*F8 -> 0 | H8: 0 | I8: 0 | J8: =H8*I8 -> 0 | K8: =G8+J8 -> 0 | M8: =M7+K8-L8 -> 1009258.4
A9: 6 | B9: 45814 | C9: 805 | E9: 0 | F9: 0 | G9: =E9*F9 -> 0 | H9: 0 | I9: 0 | J9: =H9*I9 -> 0 | K9: =G9+J9 -> 0 | L9: 1005216 | M9: =M8+K9-L9 -> 4042.4438
A10: 7 | B10: 45815 | C10: 0 | E10: 0 | F10: 0 | G10: =E10*F10 -> 0 | H10: 0 | I10: 0 | J10: =H10*I10 -> 0 | K10: =G10+J10 -> 0 | M10: =M9+K10-L10 -> 4042.4438
A11: 8 | B11: 45816 | C11: 0 | E11: 4000 | F11: 91.14 | G11: =E11*F11 -> 364560 | H11: 0 | I11: 0 | J11: =H11*I11 -> 0 | K11: =G11+J11 -> 364560 | M11: =M10+K11-L11 -> 368602.44
A12: 9 | B12: 45817 | C12: 0 | E12: 2000 | F12: 91.14 | G12: =E12*F12 -> 182280 | H12: 0 | I12: 0 | J12: =H12*I12 -> 0 | K12: =G12+J12 -> 182280 | M12: =M11+K12-L12 -> 550882.44
A13: 10 | B13: 45818 | C13: 0 | E13: 0 | F13: 0 | G13: =E13*F13 -> 0 | H13: 0 | I13: 0 | J13: =H13*I13 -> 0 | K13: =G13+J13 -> 0 | M13: =M12+K13-L13 -> 550882.44
A14: 11 | B14: 45819 | C14: 0 | E14: 0 | F14: 0 | G14: =E14*F14 -> 0 | H14: 0 | I14: 0 | J14: =H14*I14 -> 0 | K14: =G14+J14 -> 0 | M14: =M13+K14-L14 -> 550882.44
A15: 12 | B15: 45820 | C15: 0 | E15: 0 | F15: 0 | G15: =E15*F15 -> 0 | H15: 0 | I15: 0 | J15: =H15*I15 -> 0 | K15: =G15+J15 -> 0 | M15: =M14+K15-L15 -> 550882.44
A16: 13 | B16: 45821 | C16: 0 | E16: 0 | F16: 0 | G16: =E16*F16 -> 0 | H16: 20 | I16: 104.6 | J16: =H16*I16 -> 2092 | K16: =G16+J16 -> 2092 | M16: =M15+K16-L16 -> 552974.44
